{
  "type": "Feature",
  "properties": {
    "iso:country":"US",
    "sg:address":"1109 Ashwaubenon St",
    "sg:city":"Green Bay",
    "sg:classifiers":[
        {
            "category":"Building & Trades",
            "subcategory":"Cleaning & Sanitation",
            "type":"Services"
        }
    ],
    "sg:phone":"+1 920 339 1014",
    "sg:postcode":"54304",
    "sg:province":"WI",
    "sg:tags":[
        "janitor"
    ],
    "sg:website":"www.pro1janitorial.com",
    "wof:name":"Pro One Janitorial",
    "wof:placetype":"venue"
},
  "geometry": {"coordinates":[-88.093543,44.465683],"type":"Point"}
}