{
  "type": "Feature",
  "properties": {
    "iso:country":"US",
    "sg:address":"2902 E Washington Ave",
    "sg:city":"Madison",
    "sg:classifiers":[
        {
            "category":"Deli",
            "type":"Food & Drink"
        },
        {
            "category":"Restaurant",
            "type":"Food & Drink"
        },
        {
            "category":"Ice Cream",
            "type":"Food & Drink"
        }
    ],
    "sg:menulink":"http://www.allmenus.com/wi/madison/261179-ellas-deli/menu/",
    "sg:phone":"+1 608 241 5291",
    "sg:postcode":"53704",
    "sg:province":"WI",
    "sg:tags":[
        "deli",
        "american",
        "ice",
        "cream"
    ],
    "wof:name":"Ella's Deli",
    "wof:placetype":"venue"
},
  "geometry": {"coordinates":[-89.34446800000001,43.103574],"type":"Point"}
}