{
  "type": "Feature",
  "properties": {
    "addr:full":"1407 W Highland Ave Milwaukee WI 53233",
    "addr:housenumber":"1407",
    "addr:postcode":"53233",
    "addr:street":"W Highland Ave",
    "iso:country":"US",
    "sg:address":"1407 W Highland Ave",
    "sg:city":"Milwaukee",
    "sg:classifiers":[
        {
            "category":"Organizations",
            "subcategory":"Religious Organization",
            "type":"Services"
        }
    ],
    "sg:phone":"+1 414 342 4556",
    "sg:postcode":"53233",
    "sg:province":"WI",
    "sg:tags":[
        "clergy"
    ],
    "wof:name":"William Cochrane",
    "wof:placetype":"venue"
},
  "geometry": {"coordinates":[-87.931423,43.044252],"type":"Point"}
}