{
  "type": "Feature",
  "properties": {
    "iso:country":"US",
    "sg:address":"6514 Odana Rd",
    "sg:city":"Madison",
    "sg:classifiers":[
        {
            "category":"Travel",
            "subcategory":"Travel Agent",
            "type":"Entertainment"
        }
    ],
    "sg:phone":"+1 608 833 8400",
    "sg:postcode":"53719",
    "sg:province":"WI",
    "sg:tags":[
        "agency",
        "bureau"
    ],
    "wof:name":"Carlson Wagonlit Travel",
    "wof:placetype":"venue"
},
  "geometry": {"coordinates":[-89.49504,43.055752],"type":"Point"}
}