{
  "type": "Feature",
  "properties": {
    "iso:country":"US",
    "sg:address":"7683 County Line Rd",
    "sg:city":"Gleason",
    "sg:classifiers":[
        {
            "category":"Farming",
            "subcategory":"Dairy Farm",
            "type":"Manufacturing & Wholesale Goods"
        }
    ],
    "sg:phone":"+1 715 873 4786",
    "sg:postcode":"54435",
    "sg:province":"WI",
    "wof:name":"Lange Sugarbush",
    "wof:placetype":"venue"
},
  "geometry": {"coordinates":[-89.424651,45.293671],"type":"Point"}
}