{
  "type": "Feature",
  "properties": {
    "addr:full":"206 Roller Ave Beaver Dam WI 53916",
    "addr:housenumber":"206",
    "addr:postcode":"53916",
    "addr:street":"Roller Ave",
    "iso:country":"US",
    "sg:address":"206 Roller Ave",
    "sg:city":"Beaver Dam",
    "sg:classifiers":[
        {
            "category":"Manufacturing",
            "subcategory":"Paper Products",
            "type":"Manufacturing & Wholesale Goods"
        }
    ],
    "sg:phone":"+1 920 356 1231",
    "sg:postcode":"53916",
    "sg:province":"WI",
    "sg:tags":[
        "converted",
        "mfg"
    ],
    "wof:name":"Caught In Time",
    "wof:placetype":"venue"
},
  "geometry": {"coordinates":[-88.840953,43.445916],"type":"Point"}
}