{
  "type": "Feature",
  "properties": {
    "iso:country":"US",
    "sg:address":"876 W Waukau Ave",
    "sg:city":"Oshkosh",
    "sg:classifiers":[
        {
            "category":"Government",
            "subcategory":"Office",
            "type":"Public Place"
        }
    ],
    "sg:phone":"+1 920 233 9981",
    "sg:postcode":"54902",
    "sg:province":"WI",
    "sg:tags":[
        "federal"
    ],
    "wof:name":"Us Faa",
    "wof:placetype":"venue"
},
  "geometry": {"coordinates":[-88.550474,43.981226],"type":"Point"}
}