{
  "type": "Feature",
  "properties": {
    "iso:country":"US",
    "sg:address":"11112 N Buntrock Ave",
    "sg:city":"Thiensville",
    "sg:classifiers":[
        {
            "category":"Arts & Performance",
            "subcategory":"Theater",
            "type":"Entertainment"
        }
    ],
    "sg:phone":"+1 262 242 7867",
    "sg:postcode":"53092",
    "sg:province":"WI",
    "sg:tags":[
        "group"
    ],
    "wof:name":"Lakeshore Symphonic Band",
    "wof:placetype":"venue"
},
  "geometry": {"coordinates":[-87.989582,43.221122],"type":"Point"}
}