{
  "type": "Feature",
  "properties": {
    "iso:country":"US",
    "sg:address":"1016 16th Ave",
    "sg:city":"Monroe",
    "sg:classifiers":[
        {
            "category":"Government",
            "subcategory":"Office",
            "type":"Public Place"
        }
    ],
    "sg:phone":"+1 608 328 9460",
    "sg:postcode":"53566",
    "sg:province":"WI",
    "sg:tags":[
        "county",
        "resource"
    ],
    "sg:website":"www.greencounty.com",
    "wof:name":"Green County Child Support",
    "wof:placetype":"venue"
},
  "geometry": {"coordinates":[-89.639814,42.601962],"type":"Point"}
}