{
  "type": "Feature",
  "properties": {
    "iso:country":"US",
    "sg:address":"7156 S 46th St",
    "sg:city":"Franklin",
    "sg:classifiers":[
        {
            "category":"Building & Trades",
            "subcategory":"Cleaning & Sanitation",
            "type":"Services"
        }
    ],
    "sg:phone":"+1 414 761 2097",
    "sg:postcode":"53132",
    "sg:province":"WI",
    "sg:tags":[
        "janitor"
    ],
    "wof:name":"Next Generation Svc Inc",
    "wof:placetype":"venue"
},
  "geometry": {"coordinates":[-87.972469,42.911822],"type":"Point"}
}