{
  "type": "Feature",
  "properties": {
    "iso:country":"US",
    "sg:address":"459 River Rd",
    "sg:city":"Princeton",
    "sg:classifiers":[
        {
            "category":"Mining & Drilling",
            "type":"Manufacturing & Wholesale Goods"
        }
    ],
    "sg:phone":"+1 262 366 0529",
    "sg:postcode":"54968",
    "sg:province":"WI",
    "sg:tags":[
        "stone"
    ],
    "wof:name":"All Day Trucking & Excavating",
    "wof:placetype":"venue"
},
  "geometry": {"coordinates":[-89.130485,43.85563],"type":"Point"}
}