{
  "type": "Feature",
  "properties": {
    "addr:full":"2450 Plover Rd Plover WI 54467",
    "addr:housenumber":"2450",
    "addr:postcode":"54467",
    "addr:street":"Plover Rd",
    "iso:country":"US",
    "sg:address":"2450 Plover Rd",
    "sg:city":"Plover",
    "sg:classifiers":[
        {
            "category":"Building & Trades",
            "subcategory":"Construction",
            "type":"Services"
        }
    ],
    "sg:phone":"+1 715 423 8887",
    "sg:postcode":"54467",
    "sg:province":"WI",
    "sg:tags":[
        "house"
    ],
    "wof:name":"Heartland Custom Homes Inc",
    "wof:placetype":"venue"
},
  "geometry": {"coordinates":[-89.537437,44.453849],"type":"Point"}
}