{
  "type": "Feature",
  "properties": {
    "iso:country":"US",
    "sg:address":"6080 S Crosswinds Dr",
    "sg:city":"Cudahy",
    "sg:classifiers":[
        {
            "category":"Building & Trades",
            "subcategory":"Cleaning & Sanitation",
            "type":"Services"
        }
    ],
    "sg:phone":"+1 414 481 4885",
    "sg:postcode":"53110",
    "sg:province":"WI",
    "sg:tags":[
        "fireplace",
        "chimney"
    ],
    "wof:name":"Allstar Chimney",
    "wof:placetype":"venue"
},
  "geometry": {"coordinates":[-87.866077,42.936028],"type":"Point"}
}