{
  "type": "Feature",
  "properties": {
    "iso:country":"US",
    "sg:address":"525 N 17th St",
    "sg:city":"Milwaukee",
    "sg:classifiers":[
        {
            "category":"Government",
            "subcategory":"Office",
            "type":"Public Place"
        }
    ],
    "sg:phone":"+1 414 267 6101",
    "sg:postcode":"53233",
    "sg:province":"WI",
    "wof:name":"Women's Residential Ctr",
    "wof:placetype":"venue"
},
  "geometry": {"coordinates":[-87.934268,43.038361],"type":"Point"}
}