{
  "type": "Feature",
  "properties": {
    "iso:country":"US",
    "sg:address":"1572 Old Hwy 51",
    "sg:city":"Mosinee",
    "sg:classifiers":[
        {
            "category":"Retail",
            "subcategory":"Auto Repair",
            "type":"Services"
        }
    ],
    "sg:phone":"+1 715 692 6416",
    "sg:postcode":"54455",
    "sg:province":"WI",
    "sg:tags":[
        "automotive"
    ],
    "wof:name":"RAJ Enterprises",
    "wof:placetype":"venue"
},
  "geometry": {"coordinates":[-89.667067,44.824068],"type":"Point"}
}