{
  "type": "Feature",
  "properties": {
    "iso:country":"US",
    "sg:address":"4109 Capital Circle Dr",
    "sg:city":"Janesville",
    "sg:classifiers":[
        {
            "category":"Manufacturing",
            "subcategory":"Metals",
            "type":"Manufacturing & Wholesale Goods"
        }
    ],
    "sg:phone":"+1 608 752 1601",
    "sg:postcode":"53546",
    "sg:province":"WI",
    "sg:tags":[
        "equipment",
        "heating"
    ],
    "sg:website":"www.lanair.com",
    "wof:name":"Lanair Waste Oil Heaters",
    "wof:placetype":"venue"
},
  "geometry": {"coordinates":[-88.962594,42.676707],"type":"Point"}
}