{
  "type": "Feature",
  "properties": {
    "iso:country":"US",
    "sg:address":"2120 Hillcrest Ln",
    "sg:city":"Wautoma",
    "sg:classifiers":[
        {
            "category":"Building & Trades",
            "subcategory":"Construction",
            "type":"Services"
        }
    ],
    "sg:phone":"+1 920 787 5023",
    "sg:postcode":"54982",
    "sg:province":"WI",
    "sg:tags":[
        "house"
    ],
    "wof:name":"Heartland Builders",
    "wof:placetype":"venue"
},
  "geometry": {"coordinates":[-89.190354,44.056226],"type":"Point"}
}