{
  "type": "Feature",
  "properties": {
    "iso:country":"US",
    "sg:address":"832 E Geneva St",
    "sg:city":"Delavan",
    "sg:classifiers":[
        {
            "category":"Shopping",
            "subcategory":"Computers & Home Electronics",
            "type":"Retail Goods"
        }
    ],
    "sg:phone":"+1 262 728 3557",
    "sg:postcode":"53115",
    "sg:province":"WI",
    "sg:tags":[
        "television",
        "set",
        "appliance",
        "electric",
        "household"
    ],
    "wof:name":"Delavan Lakes TV and Appliance",
    "wof:placetype":"venue"
},
  "geometry": {"coordinates":[-88.635269,42.627449],"type":"Point"}
}