{
  "type": "Feature",
  "properties": {
    "iso:country":"US",
    "sg:address":"2500 N Mayfair Rd",
    "sg:city":"Milwaukee",
    "sg:classifiers":[
        {
            "category":"Shopping",
            "subcategory":"Clothing, Apparel, & Fashions",
            "type":"Retail Goods"
        }
    ],
    "sg:phone":"+1 414 774 5886",
    "sg:postcode":"53222",
    "sg:province":"WI",
    "sg:tags":[
        "accessory"
    ],
    "wof:name":"Claires",
    "wof:placetype":"venue"
},
  "geometry": {"coordinates":[-88.047678,43.063727],"type":"Point"}
}