{
  "type": "Feature",
  "properties": {
    "iso:country":"US",
    "sg:address":"3089 W Mason St",
    "sg:city":"Green Bay",
    "sg:classifiers":[
        {
            "category":"Government",
            "subcategory":"Office",
            "type":"Public Place"
        }
    ],
    "sg:phone":"+1 920 490 9771",
    "sg:postcode":"54313",
    "sg:province":"WI",
    "sg:tags":[
        "conservation"
    ],
    "wof:name":"Soaring Eagle Foundation Inc",
    "wof:placetype":"venue"
},
  "geometry": {"coordinates":[-88.126208,44.523733],"type":"Point"}
}