{
  "type": "Feature",
  "properties": {
    "iso:country":"US",
    "sg:address":"4938 Riverside Rd",
    "sg:city":"Waterford",
    "sg:classifiers":[
        {
            "category":"Social Services",
            "type":"Services"
        }
    ],
    "sg:phone":"+1 262 534 1984",
    "sg:postcode":"53185",
    "sg:province":"WI",
    "sg:tags":[
        "youth",
        "organization",
        "center"
    ],
    "wof:name":"Waterford Youth Baseball",
    "wof:placetype":"venue"
},
  "geometry": {"coordinates":[-88.219717,42.780176],"type":"Point"}
}