{
  "type": "Feature",
  "properties": {
    "iso:country":"US",
    "sg:address":"710 Larry Ct",
    "sg:city":"Waukesha",
    "sg:classifiers":[
        {
            "category":"Utilities",
            "subcategory":"Mobile Phone",
            "type":"Services"
        }
    ],
    "sg:phone":"+1 262 798 2900",
    "sg:postcode":"53186",
    "sg:province":"WI",
    "sg:tags":[
        "telephone",
        "cellular"
    ],
    "wof:name":"USA Mobility Inc",
    "wof:placetype":"venue"
},
  "geometry": {"coordinates":[-88.17534999999999,43.039297],"type":"Point"}
}