{
  "type": "Feature",
  "properties": {
    "iso:country":"US",
    "sg:address":"416 Powell St",
    "sg:city":"Dodgeville",
    "sg:classifiers":[
        {
            "category":"Retail",
            "subcategory":"Laundry & Dry Cleaning",
            "type":"Services"
        }
    ],
    "sg:phone":"+1 608 935 5848",
    "sg:postcode":"53533",
    "sg:province":"WI",
    "sg:tags":[
        "cleaners",
        "rug",
        "carpet"
    ],
    "wof:name":"Kevin & Jewell's Karpet Klean",
    "wof:placetype":"venue"
},
  "geometry": {"coordinates":[-90.142557,42.968149],"type":"Point"}
}