{
  "type": "Feature",
  "properties": {
    "iso:country":"US",
    "sg:address":"4648 State Hwy 78",
    "sg:city":"Black Earth",
    "sg:classifiers":[
        {
            "category":"Retail",
            "subcategory":"Repair Shop",
            "type":"Services"
        },
        {
            "category":"Building & Trades",
            "subcategory":"Construction",
            "type":"Services"
        }
    ],
    "sg:phone":"+1 608 767 2827",
    "sg:postcode":"53515",
    "sg:province":"WI",
    "sg:tags":[
        "ironwork",
        "contractor"
    ],
    "wof:name":"Walking Iron Erectors Inc",
    "wof:placetype":"venue"
},
  "geometry": {"coordinates":[-89.752091,43.108743],"type":"Point"}
}