{
  "type": "Feature",
  "properties": {
    "iso:country":"US",
    "sg:address":"44145 Dodd Dr",
    "sg:city":"Cable",
    "sg:classifiers":[
        {
            "category":"Travel",
            "subcategory":"Hotels & Motels",
            "type":"Entertainment"
        }
    ],
    "sg:phone":"+1 715 794 2137",
    "sg:postcode":"54821",
    "sg:province":"WI",
    "sg:tags":[
        "resort",
        "operation"
    ],
    "wof:name":"West Wind Resort",
    "wof:placetype":"venue"
},
  "geometry": {"coordinates":[-91.104826,46.212308],"type":"Point"}
}