{
  "type": "Feature",
  "properties": {
    "addr:full":"2407 W North Ave Milwaukee WI 53205",
    "addr:housenumber":"2407",
    "addr:postcode":"53205",
    "addr:street":"W North Ave",
    "iso:country":"US",
    "sg:address":"2407 W North Ave",
    "sg:city":"Milwaukee",
    "sg:classifiers":[
        {
            "category":"Education",
            "subcategory":"School",
            "type":"Public Place"
        }
    ],
    "sg:phone":"+1 414 345 0608",
    "sg:postcode":"53205",
    "sg:province":"WI",
    "wof:name":"Starms Monumental School",
    "wof:placetype":"venue"
},
  "geometry": {"coordinates":[-87.94367099999999,43.060479],"type":"Point"}
}