{
  "type": "Feature",
  "properties": {
    "iso:country":"US",
    "sg:address":"343 Main St",
    "sg:city":"Darlington",
    "sg:classifiers":[
        {
            "category":"Personal",
            "subcategory":"Beauty Salon",
            "type":"Services"
        }
    ],
    "sg:phone":"+1 608 776 8866",
    "sg:postcode":"53530",
    "sg:province":"WI",
    "sg:tags":[
        "shop"
    ],
    "wof:name":"Hair & Nail Connection",
    "wof:placetype":"venue"
},
  "geometry": {"coordinates":[-90.117696,42.679591],"type":"Point"}
}