{
  "type": "Feature",
  "properties": {
    "iso:country":"US",
    "sg:address":"2073 Cherokee St",
    "sg:city":"Grafton",
    "sg:classifiers":[
        {
            "category":"Insurance",
            "subcategory":"Insurance Agent",
            "type":"Services"
        }
    ],
    "sg:phone":"+1 414 355 5900",
    "sg:postcode":"53024",
    "sg:province":"WI",
    "wof:name":"Kolb & Assoc",
    "wof:placetype":"venue"
},
  "geometry": {"coordinates":[-87.93988899999999,43.31419],"type":"Point"}
}