{
  "type": "Feature",
  "properties": {
    "addr:full":"8081 State Hwy 57 Baileys Harbor WI 54202",
    "addr:housenumber":"8081",
    "addr:postcode":"54202",
    "addr:street":"State Hwy 57",
    "iso:country":"US",
    "sg:address":"8081 State Hwy 57",
    "sg:city":"Baileys Harbor",
    "sg:classifiers":[
        {
            "category":"Home & Garden",
            "subcategory":"Garden Supply",
            "type":"Retail Goods"
        }
    ],
    "sg:phone":"+1 920 839 9090",
    "sg:postcode":"54202",
    "sg:province":"WI",
    "sg:tags":[
        "ornament"
    ],
    "wof:name":"Nita's Garden Gate",
    "wof:placetype":"venue"
},
  "geometry": {"coordinates":[-87.12379199999999,45.063652],"type":"Point"}
}