{
  "type": "Feature",
  "properties": {
    "addr:full":"16100 W Greenfield Ave Brookfield WI 53005",
    "addr:housenumber":"16100",
    "addr:postcode":"53005",
    "addr:street":"W Greenfield Ave",
    "iso:country":"US",
    "sg:address":"16100 W Greenfield Ave",
    "sg:city":"Brookfield",
    "sg:classifiers":[
        {
            "category":"Building & Trades",
            "subcategory":"Landscaping Services",
            "type":"Services"
        }
    ],
    "sg:phone":"+1 262 785 2729",
    "sg:postcode":"53005",
    "sg:province":"WI",
    "sg:tags":[
        "landscape"
    ],
    "wof:name":"Neumann Landscape Specialists",
    "wof:placetype":"venue"
},
  "geometry": {"coordinates":[-88.11697100000001,43.016771],"type":"Point"}
}