{
  "type": "Feature",
  "properties": {
    "iso:country":"US",
    "sg:address":"7977 Territorial Rd",
    "sg:city":"Delavan",
    "sg:classifiers":[
        {
            "category":"Building & Trades",
            "subcategory":"Plumbing",
            "type":"Services"
        }
    ],
    "sg:phone":"+1 608 883 6885",
    "sg:postcode":"53115",
    "sg:province":"WI",
    "sg:tags":[
        "conditioning",
        "air",
        "system",
        "contractor"
    ],
    "wof:name":"Komfort Heating & Cooling Inc",
    "wof:placetype":"venue"
},
  "geometry": {"coordinates":[-88.681231,42.741081],"type":"Point"}
}