{
  "type": "Feature",
  "properties": {
    "iso:country":"US",
    "sg:address":"2185 S Koeller St",
    "sg:city":"Oshkosh",
    "sg:classifiers":[
        {
            "category":"Shopping",
            "type":"Retail Goods"
        },
        {
            "category":"Shopping",
            "subcategory":"Catalog Store",
            "type":"Retail Goods"
        }
    ],
    "sg:phone":"+1 920 231 1070",
    "sg:postcode":"54902",
    "sg:province":"WI",
    "sg:tags":[
        "factory",
        "outlet"
    ],
    "wof:name":"Miles Kimball Company",
    "wof:placetype":"venue"
},
  "geometry": {"coordinates":[-88.581915,44.001755],"type":"Point"}
}