{
  "type": "Feature",
  "properties": {
    "iso:country":"US",
    "sg:address":"2746 Heritage Dr",
    "sg:city":"Delafield",
    "sg:classifiers":[
        {
            "category":"Restaurant",
            "type":"Food & Drink"
        }
    ],
    "sg:phone":"+1 262 646 5406",
    "sg:postcode":"53018",
    "sg:province":"WI",
    "sg:tags":[
        "eating",
        "mfg"
    ],
    "wof:name":"Old World Bread Works",
    "wof:placetype":"venue"
},
  "geometry": {"coordinates":[-88.374772,43.049],"type":"Point"}
}