{
  "type": "Feature",
  "properties": {
    "iso:country":"US",
    "sg:address":"274 Park Ave",
    "sg:city":"Prairie Du Sac",
    "sg:classifiers":[
        {
            "category":"Building & Trades",
            "subcategory":"Construction",
            "type":"Services"
        }
    ],
    "sg:phone":"+1 608 643 5114",
    "sg:postcode":"53578",
    "sg:province":"WI",
    "sg:tags":[
        "maker",
        "cabinet"
    ],
    "wof:name":"Custom Installation",
    "wof:placetype":"venue"
},
  "geometry": {"coordinates":[-89.721873,43.286131],"type":"Point"}
}