{
  "type": "Feature",
  "properties": {
    "iso:country":"US",
    "sg:address":"5281 Irish Ridge Rd",
    "sg:city":"Viroqua",
    "sg:classifiers":[
        {
            "category":"Professional",
            "subcategory":"Business Services",
            "type":"Services"
        }
    ],
    "sg:phone":"+1 608 634 2233",
    "sg:postcode":"54665",
    "sg:province":"WI",
    "sg:tags":[
        "appraiser"
    ],
    "wof:name":"Miller & Assoc",
    "wof:placetype":"venue"
},
  "geometry": {"coordinates":[-91.021085,43.592861],"type":"Point"}
}