{
  "type": "Feature",
  "properties": {
    "addr:full":"7600 W North Ave Wauwatosa WI 53213",
    "addr:housenumber":"7600",
    "addr:postcode":"53213",
    "addr:street":"W North Ave",
    "iso:country":"US",
    "sg:address":"7600 W North Ave",
    "sg:city":"Wauwatosa",
    "sg:classifiers":[
        {
            "category":"Education",
            "subcategory":"School",
            "type":"Public Place"
        }
    ],
    "sg:phone":"+1 414 773 2400",
    "sg:postcode":"53213",
    "sg:province":"WI",
    "sg:website":"www.wauwatosa.k12.wi.us",
    "wof:name":"Longfellow Middle School",
    "wof:placetype":"venue"
},
  "geometry": {"coordinates":[-88.01247499999999,43.060672],"type":"Point"}
}