{
  "type": "Feature",
  "properties": {
    "iso:country":"US",
    "sg:address":"134 Tecumseh Rd",
    "sg:city":"New Holstein",
    "sg:classifiers":[
        {
            "category":"Social Services",
            "subcategory":"Job Training",
            "type":"Services"
        }
    ],
    "sg:phone":"+1 920 898 9224",
    "sg:postcode":"53061",
    "sg:province":"WI",
    "sg:tags":[
        "rehabilitation"
    ],
    "wof:name":"Resource Center For Farmers",
    "wof:placetype":"venue"
},
  "geometry": {"coordinates":[-88.04329799999999,43.964735],"type":"Point"}
}