{
  "type": "Feature",
  "properties": {
    "iso:country":"US",
    "sg:address":"1428 E Stratford Dr",
    "sg:city":"Beloit",
    "sg:classifiers":[
        {
            "category":"Building & Trades",
            "subcategory":"Landscaping Services",
            "type":"Services"
        }
    ],
    "sg:phone":"+1 608 365 8173",
    "sg:postcode":"53511",
    "sg:province":"WI",
    "sg:tags":[
        "lawn",
        "contractor",
        "landscape",
        "care"
    ],
    "wof:name":"J R's Yard & Garden",
    "wof:placetype":"venue"
},
  "geometry": {"coordinates":[-89.016937,42.559351],"type":"Point"}
}