{
  "type": "Feature",
  "properties": {
    "iso:country":"US",
    "sg:address":"5915 N 55th St",
    "sg:city":"Milwaukee",
    "sg:classifiers":[
        {
            "category":"Manufacturing",
            "subcategory":"Chemicals & Compounds",
            "type":"Manufacturing & Wholesale Goods"
        }
    ],
    "sg:phone":"+1 414 578 9433",
    "sg:postcode":"53218",
    "sg:province":"WI",
    "sg:tags":[
        "compounds",
        "powders",
        "resin",
        "materials-colorants",
        "plastics-raw",
        "liquids",
        "resins"
    ],
    "sg:website":"http://www.rosepolymer.com",
    "wof:name":"Rose Polymer Composites",
    "wof:placetype":"venue"
},
  "geometry": {"coordinates":[-87.980985,43.125915],"type":"Point"}
}