{
  "type": "Feature",
  "properties": {
    "iso:country":"US",
    "sg:address":"2595 N Downer Ave",
    "sg:city":"Milwaukee",
    "sg:classifiers":[
        {
            "category":"Wholesale",
            "subcategory":"Machinery & Supplies",
            "type":"Manufacturing & Wholesale Goods"
        }
    ],
    "sg:phone":"+1 414 961 6950",
    "sg:postcode":"53211",
    "sg:province":"WI",
    "sg:tags":[
        "dyer",
        "cleaners",
        "equipment"
    ],
    "wof:name":"Young's Cleaners",
    "wof:placetype":"venue"
},
  "geometry": {"coordinates":[-87.878172,43.065009],"type":"Point"}
}