{
  "type": "Feature",
  "properties": {
    "iso:country":"US",
    "sg:address":"1831 N Stevens St",
    "sg:city":"Rhinelander",
    "sg:classifiers":[
        {
            "category":"Taxi",
            "type":"Transportation"
        }
    ],
    "sg:phone":"+1 715 365 7433",
    "sg:postcode":"54501",
    "sg:province":"WI",
    "sg:tags":[
        "taxicab"
    ],
    "wof:name":"Rapid Cab Co Inc",
    "wof:placetype":"venue"
},
  "geometry": {"coordinates":[-89.393417,45.655348],"type":"Point"}
}