{
  "type": "Feature",
  "properties": {
    "iso:country":"US",
    "sg:address":"4752 N 36th St",
    "sg:city":"Milwaukee",
    "sg:classifiers":[
        {
            "category":"Social Services",
            "type":"Services"
        }
    ],
    "sg:phone":"+1 414 393 0936",
    "sg:postcode":"53209",
    "sg:province":"WI",
    "wof:name":"Latisha Smith Day Care",
    "wof:placetype":"venue"
},
  "geometry": {"coordinates":[-87.957901,43.103527],"type":"Point"}
}