{
  "type": "Feature",
  "properties": {
    "iso:country":"US",
    "sg:address":"7789 Raspberry Rd",
    "sg:city":"Wittenberg",
    "sg:classifiers":[
        {
            "category":"Building & Trades",
            "subcategory":"Construction",
            "type":"Services"
        }
    ],
    "sg:phone":"+1 715 253 2953",
    "sg:postcode":"54499",
    "sg:province":"WI",
    "sg:tags":[
        "industrial"
    ],
    "wof:name":"Raspberry Road Log Builders",
    "wof:placetype":"venue"
},
  "geometry": {"coordinates":[-89.12323499999999,44.873958],"type":"Point"}
}