{
  "type": "Feature",
  "properties": {
    "iso:country":"US",
    "sg:address":"650 75th St",
    "sg:city":"Amery",
    "sg:classifiers":[
        {
            "category":"Building & Trades",
            "subcategory":"Construction",
            "type":"Services"
        }
    ],
    "sg:phone":"+1 715 268 9764",
    "sg:postcode":"54001",
    "sg:province":"WI",
    "sg:tags":[
        "concrete",
        "contractor"
    ],
    "wof:name":"Western Concrete",
    "wof:placetype":"venue"
},
  "geometry": {"coordinates":[-92.31606600000001,45.30611],"type":"Point"}
}