{
  "type": "Feature",
  "properties": {
    "iso:country":"US",
    "sg:address":"37 E Follett St",
    "sg:city":"Fond Du Lac",
    "sg:classifiers":[
        {
            "category":"Restaurant",
            "type":"Food & Drink"
        }
    ],
    "sg:phone":"+1 920 921 5146",
    "sg:postcode":"54935",
    "sg:province":"WI",
    "wof:name":"Pats Hot Lunch",
    "wof:placetype":"venue"
},
  "geometry": {"coordinates":[-88.44635599999999,43.784956],"type":"Point"}
}