{
  "type": "Feature",
  "properties": {
    "iso:country":"US",
    "sg:address":"817 Main St",
    "sg:city":"Racine",
    "sg:classifiers":[
        {
            "category":"Insurance",
            "subcategory":"Insurance Agent",
            "type":"Services"
        }
    ],
    "sg:phone":"+1 262 637 4660",
    "sg:postcode":"53403",
    "sg:province":"WI",
    "wof:name":"Debra Brown Agency",
    "wof:placetype":"venue"
},
  "geometry": {"coordinates":[-87.782488,42.72323],"type":"Point"}
}