{
  "type": "Feature",
  "properties": {
    "iso:country":"US",
    "sg:address":"701 Park Ave",
    "sg:city":"Beaver Dam",
    "sg:classifiers":[
        {
            "category":"Autos & Motor Vehicles",
            "subcategory":"Automobile Sales",
            "type":"Retail Goods"
        }
    ],
    "sg:phone":"+1 920 887 1661",
    "sg:postcode":"53916",
    "sg:province":"WI",
    "sg:tags":[
        "new",
        "used"
    ],
    "sg:website":"www.lidtkemotors.com",
    "wof:name":"Lidtke Motors Inc",
    "wof:placetype":"venue"
},
  "geometry": {"coordinates":[-88.822703,43.456251],"type":"Point"}
}