{
  "type": "Feature",
  "properties": {
    "addr:full":"601 S Cedar Ave Marshfield WI 54449",
    "addr:housenumber":"601",
    "addr:postcode":"54449",
    "addr:street":"S Cedar Ave",
    "iso:country":"US",
    "sg:address":"601 S Cedar Ave",
    "sg:city":"Marshfield",
    "sg:classifiers":[
        {
            "category":"Real Estate",
            "subcategory":"Real Estate Operator",
            "type":"Services"
        }
    ],
    "sg:phone":"+1 715 389 2774",
    "sg:postcode":"54449",
    "sg:province":"WI",
    "sg:tags":[
        "property",
        "lessor"
    ],
    "wof:name":"Orville Hansen",
    "wof:placetype":"venue"
},
  "geometry": {"coordinates":[-90.173965,44.661312],"type":"Point"}
}