{
  "type": "Feature",
  "properties": {
    "addr:full":"1024 Geneva St Lake Geneva WI 53147",
    "addr:housenumber":"1024",
    "addr:postcode":"53147",
    "addr:street":"Geneva St",
    "iso:country":"US",
    "sg:address":"1024 Geneva St",
    "sg:city":"Lake Geneva",
    "sg:classifiers":[
        {
            "category":"Professional",
            "subcategory":"Business Services",
            "type":"Services"
        }
    ],
    "sg:phone":"+1 262 248 1782",
    "sg:postcode":"53147",
    "sg:province":"WI",
    "wof:name":"American Business Technologies",
    "wof:placetype":"venue"
},
  "geometry": {"coordinates":[-88.439865,42.592977],"type":"Point"}
}