{
  "type": "Feature",
  "properties": {
    "iso:country":"US",
    "sg:address":"3595 N Co Rd A",
    "sg:city":"Sheboygan Falls",
    "sg:classifiers":[
        {
            "category":"Organizations",
            "subcategory":"Religious Organization",
            "type":"Services"
        }
    ],
    "sg:phone":"+1 920 467 2709",
    "sg:postcode":"53073",
    "sg:province":"WI",
    "sg:tags":[
        "church"
    ],
    "wof:name":"Living Hope Bible Church",
    "wof:placetype":"venue"
},
  "geometry": {"coordinates":[-87.875868,43.833764],"type":"Point"}
}