{
  "type": "Feature",
  "properties": {
    "iso:country":"US",
    "sg:address":"925 Stewart St",
    "sg:city":"Madison",
    "sg:classifiers":[
        {
            "category":"Building & Trades",
            "subcategory":"Construction",
            "type":"Services"
        }
    ],
    "sg:phone":"+1 608 770 2885",
    "sg:postcode":"53713",
    "sg:province":"WI",
    "sg:tags":[
        "carpentry",
        "contractor"
    ],
    "wof:name":"Homeworks of Madison LLC",
    "wof:placetype":"venue"
},
  "geometry": {"coordinates":[-89.399001,43.029991],"type":"Point"}
}