{
  "type": "Feature",
  "properties": {
    "iso:country":"US",
    "sg:address":"166 N Main St",
    "sg:city":"Adams",
    "sg:classifiers":[
        {
            "category":"Organizations",
            "subcategory":"Religious Organization",
            "type":"Services"
        }
    ],
    "sg:phone":"+1 608 339 3485",
    "sg:postcode":"53910",
    "sg:province":"WI",
    "sg:tags":[
        "church"
    ],
    "wof:name":"St Joseph Catholic Church",
    "wof:placetype":"venue"
},
  "geometry": {"coordinates":[-89.81756900000001,43.958945],"type":"Point"}
}