{
  "type": "Feature",
  "properties": {
    "iso:country":"US",
    "sg:address":"200 Wisconsin Ave",
    "sg:city":"Stratford",
    "sg:classifiers":[
        {
            "category":"Wholesale",
            "subcategory":"Machinery & Supplies",
            "type":"Manufacturing & Wholesale Goods"
        }
    ],
    "sg:phone":"+1 715 845 3526",
    "sg:postcode":"54484",
    "sg:province":"WI",
    "wof:name":"Foxland Harvestore Inc",
    "wof:placetype":"venue"
},
  "geometry": {"coordinates":[-90.086598,44.799575],"type":"Point"}
}