{
  "type": "Feature",
  "properties": {
    "iso:country":"US",
    "sg:address":"1200 Bechaud Ave",
    "sg:city":"Fond Du Lac",
    "sg:classifiers":[
        {
            "category":"Organizations",
            "subcategory":"Non-profit Organization",
            "type":"Services"
        }
    ],
    "sg:phone":"+1 920 923 3036",
    "sg:postcode":"54937",
    "sg:province":"WI",
    "sg:tags":[
        "social"
    ],
    "wof:name":"ARC of Fond Du Lac Inc Gr",
    "wof:placetype":"venue"
},
  "geometry": {"coordinates":[-88.48485599999999,43.817145],"type":"Point"}
}