{
  "type": "Feature",
  "properties": {
    "iso:country":"US",
    "sg:address":"1323 W Main St",
    "sg:city":"Sun Prairie",
    "sg:classifiers":[
        {
            "category":"Shopping",
            "subcategory":"Gifts & Souvenirs",
            "type":"Retail Goods"
        }
    ],
    "sg:phone":"+1 608 825 3255",
    "sg:postcode":"53590",
    "sg:province":"WI",
    "wof:name":"Crafters Delight",
    "wof:placetype":"venue"
},
  "geometry": {"coordinates":[-89.234854,43.179631],"type":"Point"}
}