{
  "type": "Feature",
  "properties": {
    "iso:country":"US",
    "sg:address":"622 Ogden St",
    "sg:city":"Medford",
    "sg:classifiers":[
        {
            "category":"Building & Trades",
            "subcategory":"Landscaping Services",
            "type":"Services"
        }
    ],
    "sg:phone":"+1 715 748 5323",
    "sg:postcode":"54451",
    "sg:province":"WI",
    "sg:tags":[
        "landscape"
    ],
    "wof:name":"Underwood Landscaping",
    "wof:placetype":"venue"
},
  "geometry": {"coordinates":[-90.338611,45.137472],"type":"Point"}
}