{
  "type": "Feature",
  "properties": {
    "iso:country":"US",
    "sg:address":"16320 Cavern Ln",
    "sg:city":"Blue River",
    "sg:classifiers":[
        {
            "category":"Travel",
            "subcategory":"Campground",
            "type":"Entertainment"
        }
    ],
    "sg:phone":"+1 608 537 2988",
    "sg:postcode":"53518",
    "sg:province":"WI",
    "wof:name":"Eagle Cave Inc",
    "wof:placetype":"venue"
},
  "geometry": {"coordinates":[-90.540229,43.243386],"type":"Point"}
}