{
  "type": "Feature",
  "properties": {
    "iso:country":"US",
    "sg:address":"819 Florence",
    "sg:city":"Fort Atkinson",
    "sg:classifiers":[
        {
            "category":"Social Services",
            "type":"Services"
        }
    ],
    "sg:phone":"+1 920 563 7434",
    "sg:postcode":"53538",
    "sg:province":"WI",
    "sg:tags":[
        "organization",
        "welfare"
    ],
    "wof:name":"Soluciones De Segura",
    "wof:placetype":"venue"
},
  "geometry": {"coordinates":[-88.82334400000001,42.932531],"type":"Point"}
}