{
  "type": "Feature",
  "properties": {
    "iso:country":"US",
    "sg:address":"430 E Division St",
    "sg:city":"Fond Du Lac",
    "sg:classifiers":[
        {
            "category":"Health Services",
            "subcategory":"Medical Lab",
            "type":"Services"
        }
    ],
    "sg:phone":"+1 920 929 9300",
    "sg:postcode":"54935",
    "sg:province":"WI",
    "sg:tags":[
        "pathology"
    ],
    "wof:name":"Consultants Lab Wisconsin LLC",
    "wof:placetype":"venue"
},
  "geometry": {"coordinates":[-88.430481,43.77861],"type":"Point"}
}