{
  "type": "Feature",
  "properties": {
    "addr:full":"233 Watson St Ripon WI 54971",
    "addr:housenumber":"233",
    "addr:postcode":"54971",
    "addr:street":"Watson St",
    "iso:country":"US",
    "sg:address":"233 Watson St",
    "sg:city":"Ripon",
    "sg:classifiers":[
        {
            "category":"Recreation",
            "type":"Entertainment"
        }
    ],
    "sg:phone":"+1 920 748 3481",
    "sg:postcode":"54971",
    "sg:province":"WI",
    "wof:name":"Chos Black Belt Academy",
    "wof:placetype":"venue"
},
  "geometry": {"coordinates":[-88.83875,43.844925],"type":"Point"}
}