{
  "type": "Feature",
  "properties": {
    "iso:country":"US",
    "sg:address":"3515 Wildwood Dr",
    "sg:city":"Manitowoc",
    "sg:classifiers":[
        {
            "category":"Professional",
            "subcategory":"Management & Consulting",
            "type":"Services"
        }
    ],
    "sg:phone":"+1 920 684 4783",
    "sg:postcode":"54220",
    "sg:province":"WI",
    "wof:name":"Pharmacy Management Conslnt",
    "wof:placetype":"venue"
},
  "geometry": {"coordinates":[-87.694919,44.11252],"type":"Point"}
}