{
  "type": "Feature",
  "properties": {
    "iso:country":"US",
    "sg:address":"3511 N Duluth Ave",
    "sg:city":"Sturgeon Bay",
    "sg:classifiers":[
        {
            "category":"Manufacturing",
            "subcategory":"Glass & Minerals",
            "type":"Manufacturing & Wholesale Goods"
        }
    ],
    "sg:phone":"+1 920 743 2354",
    "sg:postcode":"54235",
    "sg:province":"WI",
    "sg:tags":[
        "concrete",
        "brick"
    ],
    "wof:name":"Cihlar Concrete Products Inc",
    "wof:placetype":"venue"
},
  "geometry": {"coordinates":[-87.39736000000001,44.832836],"type":"Point"}
}