{
  "type": "Feature",
  "properties": {
    "iso:country":"US",
    "sg:address":"6815 W Layton Ave",
    "sg:city":"Milwaukee",
    "sg:classifiers":[
        {
            "category":"Shopping",
            "subcategory":"Hobbies, Toys, & Games",
            "type":"Retail Goods"
        }
    ],
    "sg:phone":"+1 414 281 1800",
    "sg:postcode":"53220",
    "sg:province":"WI",
    "sg:tags":[
        "newspaper",
        "magazine",
        "model",
        "supply"
    ],
    "sg:website":"www.greenfieldhobby.com",
    "wof:name":"Greenfield News & Hobbyl",
    "wof:placetype":"venue"
},
  "geometry": {"coordinates":[-87.99993000000001,42.959228],"type":"Point"}
}