{
  "type": "Feature",
  "properties": {
    "iso:country":"US",
    "sg:address":"7408 Main St W",
    "sg:city":"Webster",
    "sg:classifiers":[
        {
            "category":"Bars & Pubs",
            "type":"Food & Drink"
        }
    ],
    "sg:phone":"+1 715 866 9950",
    "sg:postcode":"54893",
    "sg:province":"WI",
    "wof:name":"Tap",
    "wof:placetype":"venue"
},
  "geometry": {"coordinates":[-92.36516399999999,45.877452],"type":"Point"}
}