{
  "type": "Feature",
  "properties": {
    "addr:full":"3000 Emery Dr Wausau WI 54401",
    "addr:housenumber":"3000",
    "addr:postcode":"54401",
    "addr:street":"Emery Dr",
    "iso:country":"US",
    "sg:address":"3000 Emery Dr",
    "sg:city":"Wausau",
    "sg:classifiers":[
        {
            "category":"Health Services",
            "subcategory":"Health Practitioner",
            "type":"Services"
        }
    ],
    "sg:phone":"+1 715 675 6771",
    "sg:postcode":"54401",
    "sg:province":"WI",
    "sg:tags":[
        "acupuncture"
    ],
    "wof:name":"Acupuncture & Pain Treatment",
    "wof:placetype":"venue"
},
  "geometry": {"coordinates":[-89.674645,45.010032],"type":"Point"}
}