{
  "type": "Feature",
  "properties": {
    "iso:country":"US",
    "sg:address":"1224 N Prospect Ave",
    "sg:city":"Milwaukee",
    "sg:classifiers":[
        {
            "category":"Shopping",
            "subcategory":"Computers & Home Electronics",
            "type":"Retail Goods"
        }
    ],
    "sg:phone":"+1 414 421 1852",
    "sg:postcode":"53202",
    "sg:province":"WI",
    "sg:tags":[
        "software"
    ],
    "wof:name":"Xorbix Technologies Inc",
    "wof:placetype":"venue"
},
  "geometry": {"coordinates":[-87.897126,43.045999],"type":"Point"}
}