{
  "type": "Feature",
  "properties": {
    "iso:country":"US",
    "sg:address":"413 Court St",
    "sg:city":"Neillsville",
    "sg:classifiers":[
        {
            "category":"Social Services",
            "subcategory":"Child Care",
            "type":"Services"
        }
    ],
    "sg:phone":"+1 715 743 4490",
    "sg:postcode":"54456",
    "sg:province":"WI",
    "sg:tags":[
        "day"
    ],
    "wof:name":"Neillsville Nursery School",
    "wof:placetype":"venue"
},
  "geometry": {"coordinates":[-90.594715,44.55927],"type":"Point"}
}