{
  "type": "Feature",
  "properties": {
    "iso:country":"US",
    "sg:address":"410 W North St",
    "sg:city":"Dodgeville",
    "sg:classifiers":[
        {
            "category":"Real Estate",
            "subcategory":"Real Estate Agent",
            "type":"Services"
        }
    ],
    "sg:phone":"+1 608 935 3874",
    "sg:postcode":"53533",
    "sg:province":"WI",
    "wof:name":"Powell Realty",
    "wof:placetype":"venue"
},
  "geometry": {"coordinates":[-90.13628799999999,42.967339],"type":"Point"}
}