{
  "type": "Feature",
  "properties": {
    "addr:full":"6131 N Green Bay Ave Milwaukee WI 53209",
    "addr:housenumber":"6131",
    "addr:postcode":"53209",
    "addr:street":"N Green Bay Ave",
    "iso:country":"US",
    "sg:address":"6131 N Green Bay Ave",
    "sg:city":"Milwaukee",
    "sg:classifiers":[
        {
            "category":"Retail",
            "subcategory":"Animal Services",
            "type":"Services"
        }
    ],
    "sg:phone":"+1 414 352 0880",
    "sg:postcode":"53209",
    "sg:province":"WI",
    "sg:tags":[
        "merchandise"
    ],
    "sg:website":"www.trimtime.com",
    "wof:name":"Trim Time Inc",
    "wof:placetype":"venue"
},
  "geometry": {"coordinates":[-87.93287599999999,43.130018],"type":"Point"}
}