{
  "type": "Feature",
  "properties": {
    "addr:full":"4748 Shepard Lake Rd Rhinelander WI 54501",
    "addr:housenumber":"4748",
    "addr:postcode":"54501",
    "addr:street":"Shepard Lake Rd",
    "iso:country":"US",
    "sg:address":"4748 Shepard Lake Rd",
    "sg:city":"Rhinelander",
    "sg:classifiers":[
        {
            "category":"Wholesale",
            "subcategory":"Durable Goods & Equipment",
            "type":"Manufacturing & Wholesale Goods"
        }
    ],
    "sg:phone":"+1 715 362 7373",
    "sg:postcode":"54501",
    "sg:province":"WI",
    "sg:tags":[
        "fire",
        "extinguisher"
    ],
    "wof:name":"Silent Knight Security Systems",
    "wof:placetype":"venue"
},
  "geometry": {"coordinates":[-89.37135600000001,45.661958],"type":"Point"}
}