{
  "type": "Feature",
  "properties": {
    "addr:full":"4235 N 127th St Brookfield WI 53005",
    "addr:housenumber":"4235",
    "addr:postcode":"53005",
    "addr:street":"N 127Th St",
    "iso:country":"US",
    "sg:address":"4235 N 127th St",
    "sg:city":"Brookfield",
    "sg:classifiers":[
        {
            "category":"Manufacturing",
            "subcategory":"Textiles",
            "type":"Manufacturing & Wholesale Goods"
        },
        {
            "category":"Building & Trades",
            "subcategory":"Construction",
            "type":"Services"
        },
        {
            "category":"Home & Garden",
            "subcategory":"Carpets & Floor Coverings",
            "type":"Retail Goods"
        }
    ],
    "sg:phone":"+1 262 790 2170",
    "sg:postcode":"53005",
    "sg:province":"WI",
    "sg:tags":[
        "tile-wholesale",
        "material",
        "manufacturer",
        "tile-contractors"
    ],
    "sg:website":"http://www.tiletools.com",
    "wof:name":"Midwest Trade Tool Inc",
    "wof:placetype":"venue"
},
  "geometry": {"coordinates":[-88.069675,43.0943],"type":"Point"}
}