{
  "type": "Feature",
  "properties": {
    "iso:country":"US",
    "sg:address":"5258 N 57th St",
    "sg:city":"Milwaukee",
    "sg:classifiers":[
        {
            "category":"Social Services",
            "subcategory":"Child Care",
            "type":"Services"
        }
    ],
    "sg:phone":"+1 414 447 1037",
    "sg:postcode":"53218",
    "sg:province":"WI",
    "wof:name":"Baby Steps Family Daycare",
    "wof:placetype":"venue"
},
  "geometry": {"coordinates":[-87.983618,43.114606],"type":"Point"}
}