{
  "type": "Feature",
  "properties": {
    "iso:country":"US",
    "sg:address":"6247 W Riverside Dr",
    "sg:city":"Hurley",
    "sg:classifiers":[
        {
            "category":"Home & Garden",
            "subcategory":"Home Furnishings",
            "type":"Retail Goods"
        }
    ],
    "sg:phone":"+1 715 561 4402",
    "sg:postcode":"54534",
    "sg:province":"WI",
    "wof:name":"Mini Blinds & More",
    "wof:placetype":"venue"
},
  "geometry": {"coordinates":[-90.235313,46.500596],"type":"Point"}
}