{
  "type": "Feature",
  "properties": {
    "addr:full":"508 W Water St Princeton WI 54968",
    "addr:housenumber":"508",
    "addr:postcode":"54968",
    "addr:street":"W Water St",
    "iso:country":"US",
    "sg:address":"508 W Water St",
    "sg:city":"Princeton",
    "sg:classifiers":[
        {
            "category":"Bars & Pubs",
            "type":"Food & Drink"
        }
    ],
    "sg:phone":"+1 920 295 6861",
    "sg:postcode":"54968",
    "sg:province":"WI",
    "sg:tags":[
        "drinking"
    ],
    "wof:name":"Cruz' Inn",
    "wof:placetype":"venue"
},
  "geometry": {"coordinates":[-89.129242,43.849974],"type":"Point"}
}