{
  "type": "Feature",
  "properties": {
    "addr:full":"20496 Hematite Ave Tomah WI 54660",
    "addr:postcode":"20496;54660",
    "addr:street":"Hematite Ave",
    "iso:country":"US",
    "sg:address":"20496 Hematite Ave",
    "sg:city":"Tomah",
    "sg:phone":"+1 608 372 3611",
    "sg:postcode":"54660",
    "sg:province":"WI",
    "sg:tags":[
        "farm",
        "field",
        "crop"
    ],
    "wof:name":"Brian Rasmussen",
    "wof:placetype":"venue"
},
  "geometry": {"coordinates":[-90.582041,43.930071],"type":"Point"}
}