{
  "type": "Feature",
  "properties": {
    "iso:country":"US",
    "sg:address":"708 Superior Ave",
    "sg:city":"Sheboygan",
    "sg:classifiers":[
        {
            "category":"Wholesale",
            "subcategory":"Electrical",
            "type":"Manufacturing & Wholesale Goods"
        }
    ],
    "sg:phone":"+1 920 208 0353",
    "sg:postcode":"53081",
    "sg:province":"WI",
    "sg:tags":[
        "electronic"
    ],
    "wof:name":"Tube World Inc",
    "wof:placetype":"venue"
},
  "geometry": {"coordinates":[-87.711355,43.760787],"type":"Point"}
}