{
  "type": "Feature",
  "properties": {
    "addr:full":"7633 W Beloit Rd West Allis WI 53219",
    "addr:housenumber":"7633",
    "addr:postcode":"53219",
    "addr:street":"W Beloit Rd",
    "iso:country":"US",
    "sg:address":"7633 W Beloit Rd",
    "sg:city":"West Allis",
    "sg:classifiers":[
        {
            "category":"Home & Garden",
            "subcategory":"Home Furnishings",
            "type":"Retail Goods"
        }
    ],
    "sg:phone":"+1 414 454 0955",
    "sg:postcode":"53219",
    "sg:province":"WI",
    "sg:tags":[
        "quilting"
    ],
    "wof:name":"Homespun Creations",
    "wof:placetype":"venue"
},
  "geometry": {"coordinates":[-88.008188,42.996734],"type":"Point"}
}