{
  "type": "Feature",
  "properties": {
    "iso:country":"US",
    "sg:address":"3223 W Mc Kinley Blvd",
    "sg:city":"Milwaukee",
    "sg:classifiers":[
        {
            "category":"Wholesale",
            "subcategory":"Machinery & Supplies",
            "type":"Manufacturing & Wholesale Goods"
        }
    ],
    "sg:phone":"+1 414 344 3944",
    "sg:postcode":"53208",
    "sg:province":"WI",
    "sg:tags":[
        "dyer",
        "cleaners"
    ],
    "wof:name":"Ichiban Pilsung Inc",
    "wof:placetype":"venue"
},
  "geometry": {"coordinates":[-87.954926,43.0472],"type":"Point"}
}