{
  "type": "Feature",
  "properties": {
    "iso:country":"US",
    "sg:address":"1040 New Haven Cir",
    "sg:city":"Sun Prairie",
    "sg:classifiers":[
        {
            "category":"Real Estate",
            "subcategory":"Real Estate Operator",
            "type":"Services"
        }
    ],
    "sg:phone":"+1 608 825 0015",
    "sg:postcode":"53590",
    "sg:province":"WI",
    "sg:tags":[
        "building",
        "nonresidential"
    ],
    "wof:name":"Wiedmeyer Properties LLC",
    "wof:placetype":"venue"
},
  "geometry": {"coordinates":[-89.243248,43.194797],"type":"Point"}
}