{
  "type": "Feature",
  "properties": {
    "iso:country":"US",
    "sg:address":"1011 N Edge Trl",
    "sg:city":"Verona",
    "sg:classifiers":[
        {
            "category":"Restaurant",
            "type":"Food & Drink"
        }
    ],
    "sg:menulink":"http://www.allmenus.com/wi/verona/147354-milios-sandwiches/menu/",
    "sg:phone":"+1 608 848 7827",
    "sg:postcode":"53593",
    "sg:province":"WI",
    "sg:tags":[
        "wrap",
        "american",
        "sandwich"
    ],
    "wof:name":"Milio's Sandwiches",
    "wof:placetype":"venue"
},
  "geometry": {"coordinates":[-89.532241,43.001783],"type":"Point"}
}