{
  "type": "Feature",
  "properties": {
    "iso:country":"US",
    "sg:address":"1215 N 62nd St",
    "sg:city":"Milwaukee",
    "sg:classifiers":[
        {
            "category":"Manufacturing",
            "subcategory":"Tools & Machinery",
            "type":"Manufacturing & Wholesale Goods"
        }
    ],
    "sg:phone":"+1 414 771 7700",
    "sg:postcode":"53213",
    "sg:province":"WI",
    "sg:tags":[
        "a",
        "company",
        "m",
        "it",
        "through",
        "holding",
        "subsidiary"
    ],
    "wof:name":"Anafree Holdings Inc",
    "wof:placetype":"venue"
},
  "geometry": {"coordinates":[-87.990042,43.045516],"type":"Point"}
}