{
  "type": "Feature",
  "properties": {
    "iso:country":"US",
    "sg:address":"15 Preston Dr",
    "sg:city":"Platteville",
    "sg:classifiers":[
        {
            "category":"Shopping",
            "subcategory":"Clothing, Apparel, & Fashions",
            "type":"Retail Goods"
        }
    ],
    "sg:phone":"+1 608 348 5356",
    "sg:postcode":"53818",
    "sg:province":"WI",
    "sg:tags":[
        "furnishing"
    ],
    "wof:name":"Clothes For Him",
    "wof:placetype":"venue"
},
  "geometry": {"coordinates":[-90.48970199999999,42.735402],"type":"Point"}
}