{
  "type": "Feature",
  "properties": {
    "iso:country":"US",
    "sg:address":"3030 E College Ave",
    "sg:city":"Appleton",
    "sg:classifiers":[
        {
            "category":"Museum",
            "type":"Entertainment"
        }
    ],
    "sg:phone":"+1 920 766 3122",
    "sg:postcode":"54915",
    "sg:province":"WI",
    "sg:tags":[
        "gallery"
    ],
    "wof:name":"Charles A Grignon Mansion",
    "wof:placetype":"venue"
},
  "geometry": {"coordinates":[-88.359824,44.25858],"type":"Point"}
}