{
  "type": "Feature",
  "properties": {
    "iso:country":"US",
    "sg:address":"735 Madison Ave",
    "sg:city":"Fort Atkinson",
    "sg:classifiers":[
        {
            "category":"Banks & Credit Unions",
            "subcategory":"Bank",
            "type":"Services"
        }
    ],
    "sg:phone":"+1 920 568 8888",
    "sg:postcode":"53538",
    "sg:province":"WI",
    "sg:tags":[
        "loan",
        "institution",
        "business"
    ],
    "wof:name":"Fort Quick Cash",
    "wof:placetype":"venue"
},
  "geometry": {"coordinates":[-88.848564,42.934159],"type":"Point"}
}