{
  "type": "Feature",
  "properties": {
    "iso:country":"US",
    "sg:address":"4930 N 127th St",
    "sg:city":"Butler",
    "sg:classifiers":[
        {
            "category":"Building & Trades",
            "subcategory":"Construction",
            "type":"Services"
        }
    ],
    "sg:phone":"+1 262 781 8275",
    "sg:postcode":"53007",
    "sg:province":"WI",
    "sg:tags":[
        "contractor"
    ],
    "wof:name":"B & G Roofing Inc",
    "wof:placetype":"venue"
},
  "geometry": {"coordinates":[-88.06938,43.106236],"type":"Point"}
}