{
  "type": "Feature",
  "properties": {
    "iso:country":"US",
    "sg:address":"1847 Co Rd T",
    "sg:city":"New Richmond",
    "sg:classifiers":[
        {
            "category":"Restaurant",
            "type":"Food & Drink"
        },
        {
            "category":"Bars & Pubs",
            "type":"Food & Drink"
        }
    ],
    "sg:phone":"+1 715 246 4726",
    "sg:postcode":"54017",
    "sg:province":"WI",
    "sg:tags":[
        "bar"
    ],
    "wof:name":"Blue Moon Saloon",
    "wof:placetype":"venue"
},
  "geometry": {"coordinates":[-92.436116,45.135702],"type":"Point"}
}