{
  "type": "Feature",
  "properties": {
    "iso:country":"US",
    "sg:address":"765 Oak St",
    "sg:city":"Neenah",
    "sg:classifiers":[
        {
            "category":"Food & Beverages",
            "subcategory":"Specialty",
            "type":"Retail Goods"
        }
    ],
    "sg:phone":"+1 920 722 3933",
    "sg:postcode":"54956",
    "sg:province":"WI",
    "sg:tags":[
        "gourmet",
        "shop"
    ],
    "wof:name":"Colleen's Tough Times",
    "wof:placetype":"venue"
},
  "geometry": {"coordinates":[-88.459963,44.171165],"type":"Point"}
}