{
  "type": "Feature",
  "properties": {
    "iso:country":"US",
    "sg:address":"118 N Main St",
    "sg:city":"Oconomowoc",
    "sg:classifiers":[
        {
            "category":"Food & Beverages",
            "subcategory":"Specialty",
            "type":"Retail Goods"
        }
    ],
    "sg:phone":"+1 262 567 8320",
    "sg:postcode":"53066",
    "sg:province":"WI",
    "sg:tags":[
        "health",
        "diet"
    ],
    "wof:name":"Nature's Health Foods",
    "wof:placetype":"venue"
},
  "geometry": {"coordinates":[-88.499671,43.113744],"type":"Point"}
}