{
  "type": "Feature",
  "properties": {
    "iso:country":"US",
    "sg:address":"2100 Rapids Dr",
    "sg:city":"Racine",
    "sg:classifiers":[
        {
            "category":"Retail",
            "subcategory":"Auto Repair",
            "type":"Services"
        }
    ],
    "sg:phone":"+1 262 634 9645",
    "sg:postcode":"53404",
    "sg:province":"WI",
    "sg:tags":[
        "repairing",
        "automobile"
    ],
    "wof:name":"Jerry's Union 76",
    "wof:placetype":"venue"
},
  "geometry": {"coordinates":[-87.811078,42.748698],"type":"Point"}
}