{
  "type": "Feature",
  "properties": {
    "iso:country":"US",
    "sg:address":"5755 N 64th St",
    "sg:city":"Milwaukee",
    "sg:classifiers":[
        {
            "category":"Social Services",
            "subcategory":"Child Care",
            "type":"Services"
        }
    ],
    "sg:phone":"+1 414 535 9412",
    "sg:postcode":"53218",
    "sg:province":"WI",
    "wof:name":"Committed To Love & Care",
    "wof:placetype":"venue"
},
  "geometry": {"coordinates":[-87.991091,43.122054],"type":"Point"}
}