{
  "type": "Feature",
  "properties": {
    "iso:country":"US",
    "sg:address":"2712 Lmor Dr",
    "sg:city":"Sun Prairie",
    "sg:classifiers":[
        {
            "category":"Retail",
            "subcategory":"Animal Services",
            "type":"Services"
        }
    ],
    "sg:phone":"+1 608 837 7949",
    "sg:postcode":"53590",
    "sg:province":"WI",
    "wof:name":"Pets Paws",
    "wof:placetype":"venue"
},
  "geometry": {"coordinates":[-89.211308,43.213557],"type":"Point"}
}