{
  "type": "Feature",
  "properties": {
    "addr:full":"2030 Brookview Ct Neenah WI 54956",
    "addr:housenumber":"2030",
    "addr:postcode":"54956",
    "addr:street":"Brookview Ct",
    "iso:country":"US",
    "sg:address":"2030 Brookview Ct",
    "sg:city":"Neenah",
    "sg:classifiers":[
        {
            "category":"Restaurant",
            "type":"Food & Drink"
        }
    ],
    "sg:phone":"+1 920 729 9987",
    "sg:postcode":"54956",
    "sg:province":"WI",
    "sg:tags":[
        "eating"
    ],
    "wof:name":"Subway",
    "wof:placetype":"venue"
},
  "geometry": {"coordinates":[-88.48262800000001,44.229752],"type":"Point"}
}