{
  "type": "Feature",
  "properties": {
    "addr:full":"433 E Washington St Slinger WI 53086",
    "addr:housenumber":"433",
    "addr:postcode":"53086",
    "addr:street":"E Washington St",
    "iso:country":"US",
    "sg:address":"433 E Washington St",
    "sg:city":"Slinger",
    "sg:classifiers":[
        {
            "category":"Cinema",
            "subcategory":"Movie Rental",
            "type":"Entertainment"
        }
    ],
    "sg:phone":"+1 262 644 5454",
    "sg:postcode":"53086",
    "sg:province":"WI",
    "sg:tags":[
        "leasing",
        "video",
        "disc",
        "tape"
    ],
    "wof:name":"Video Plus",
    "wof:placetype":"venue"
},
  "geometry": {"coordinates":[-88.281637,43.331879],"type":"Point"}
}