{
  "type": "Feature",
  "properties": {
    "iso:country":"US",
    "sg:address":"3763 Risseeuw Rd",
    "sg:city":"Cedar Grove",
    "sg:classifiers":[
        {
            "category":"Restaurant",
            "type":"Food & Drink"
        }
    ],
    "sg:phone":"+1 920 668 6280",
    "sg:postcode":"53013",
    "sg:province":"WI",
    "sg:tags":[
        "eating"
    ],
    "wof:name":"Country Grove Restaurant",
    "wof:placetype":"venue"
},
  "geometry": {"coordinates":[-87.882413,43.601452],"type":"Point"}
}