{
  "type": "Feature",
  "properties": {
    "addr:full":"11217 W Becher St Milwaukee WI 53227",
    "addr:housenumber":"11217",
    "addr:postcode":"53227",
    "addr:street":"W Becher St",
    "iso:country":"US",
    "sg:address":"11217 W Becher St",
    "sg:city":"Milwaukee",
    "sg:classifiers":[
        {
            "category":"Professional",
            "subcategory":"Business Services",
            "type":"Services"
        },
        {
            "category":"Building & Trades",
            "subcategory":"Construction",
            "type":"Services"
        }
    ],
    "sg:phone":"+1 414 545 8500",
    "sg:postcode":"53227",
    "sg:province":"WI",
    "sg:tags":[
        "interior",
        "consultant",
        "design",
        "decorator",
        "contractor"
    ],
    "wof:name":"Creative Business Interiors",
    "wof:placetype":"venue"
},
  "geometry": {"coordinates":[-88.053043,43.006199],"type":"Point"}
}