{
  "type": "Feature",
  "properties": {
    "iso:country":"US",
    "sg:address":"110 E Chestnut St",
    "sg:city":"Chilton",
    "sg:classifiers":[
        {
            "category":"Banks & Credit Unions",
            "subcategory":"Bank",
            "type":"Services"
        }
    ],
    "sg:phone":"+1 920 849 1136",
    "sg:postcode":"53014",
    "sg:province":"WI",
    "sg:tags":[
        "loan",
        "real estate"
    ],
    "wof:name":"Value One Mortgage Bank",
    "wof:placetype":"venue"
},
  "geometry": {"coordinates":[-88.159626,44.024216],"type":"Point"}
}