{
  "type": "Feature",
  "properties": {
    "iso:country":"US",
    "sg:address":"8291 Tritt Rd",
    "sg:city":"Omro",
    "sg:classifiers":[
        {
            "category":"Real Estate",
            "subcategory":"Real Estate Agent",
            "type":"Services"
        }
    ],
    "sg:phone":"+1 920 685 6755",
    "sg:postcode":"54963",
    "sg:province":"WI",
    "sg:tags":[
        "inspection"
    ],
    "wof:name":"AFR Inspection Svc",
    "wof:placetype":"venue"
},
  "geometry": {"coordinates":[-88.812478,44.083575],"type":"Point"}
}