{
  "type": "Feature",
  "properties": {
    "iso:country":"US",
    "sg:address":"103 Co Rd A C",
    "sg:city":"Randolph",
    "sg:classifiers":[
        {
            "category":"Professional",
            "subcategory":"Management & Consulting",
            "type":"Services"
        }
    ],
    "sg:phone":"+1 920 296 0530",
    "sg:postcode":"53956",
    "sg:province":"WI",
    "sg:tags":[
        "business"
    ],
    "wof:name":"J W Dairy Consultants LLC",
    "wof:placetype":"venue"
},
  "geometry": {"coordinates":[-88.998029,43.531287],"type":"Point"}
}