{
  "type": "Feature",
  "properties": {
    "addr:full":"7530 W Becher St Milwaukee WI 53219",
    "addr:housenumber":"7530",
    "addr:postcode":"53219",
    "addr:street":"W Becher St",
    "iso:country":"US",
    "sg:address":"7530 W Becher St",
    "sg:city":"Milwaukee",
    "sg:classifiers":[
        {
            "category":"Building & Trades",
            "subcategory":"Cleaning & Sanitation",
            "type":"Services"
        }
    ],
    "sg:phone":"+1 414 543 0008",
    "sg:postcode":"53219",
    "sg:province":"WI",
    "sg:tags":[
        "janitor"
    ],
    "wof:name":"Dean's Cleaning Co",
    "wof:placetype":"venue"
},
  "geometry": {"coordinates":[-88.007069,43.006404],"type":"Point"}
}