{
  "type": "Feature",
  "properties": {
    "iso:country":"US",
    "sg:address":"2589 Altair St",
    "sg:city":"Green Bay",
    "sg:classifiers":[
        {
            "category":"Building & Trades",
            "subcategory":"Plumbing",
            "type":"Services"
        }
    ],
    "sg:phone":"+1 920 863 5575",
    "sg:postcode":"54311",
    "sg:province":"WI",
    "sg:tags":[
        "contractor"
    ],
    "wof:name":"Rainmaster Irrigation Inc",
    "wof:placetype":"venue"
},
  "geometry": {"coordinates":[-87.92644,44.453472],"type":"Point"}
}