{
  "type": "Feature",
  "properties": {
    "addr:full":"122 Fox River Dr Appleton WI 54913",
    "addr:housenumber":"122",
    "addr:postcode":"54913",
    "addr:street":"Fox River Dr",
    "iso:country":"US",
    "sg:address":"122 Fox River Dr",
    "sg:city":"Appleton",
    "sg:classifiers":[
        {
            "category":"Restaurant",
            "type":"Food & Drink"
        }
    ],
    "sg:menulink":"http://www.allmenus.com/wi/grand-chute/101261-cousins-subs/menu/",
    "sg:phone":"+1 920 830 9050",
    "sg:postcode":"54913",
    "sg:province":"WI",
    "sg:tags":[
        "wrap",
        "american",
        "sandwich"
    ],
    "wof:name":"Cousin's Subs",
    "wof:placetype":"venue"
},
  "geometry": {"coordinates":[-88.469285,44.262905],"type":"Point"}
}