{
  "type": "Feature",
  "properties": {
    "iso:country":"US",
    "sg:address":"13425 Watertown Plank Rd",
    "sg:city":"Elm Grove",
    "sg:classifiers":[
        {
            "category":"Shopping",
            "subcategory":"Gifts & Souvenirs",
            "type":"Retail Goods"
        }
    ],
    "sg:phone":"+1 262 784 5880",
    "sg:postcode":"53122",
    "sg:province":"WI",
    "sg:tags":[
        "shop"
    ],
    "wof:name":"Mystic Ireland",
    "wof:placetype":"venue"
},
  "geometry": {"coordinates":[-88.079124,43.042947],"type":"Point"}
}