{
  "type": "Feature",
  "properties": {
    "addr:full":"1316 N 14th St Superior WI 54880",
    "addr:housenumber":"1316",
    "addr:postcode":"54880",
    "addr:street":"N 14Th St",
    "iso:country":"US",
    "sg:address":"1316 N 14th St",
    "sg:city":"Superior",
    "sg:classifiers":[
        {
            "category":"Government",
            "subcategory":"Police Station",
            "type":"Public Place"
        }
    ],
    "sg:phone":"+1 715 395 1371",
    "sg:postcode":"54880",
    "sg:province":"WI",
    "sg:tags":[
        "protection",
        "sheriff"
    ],
    "wof:name":"Douglas County Sheriff's Dept",
    "wof:placetype":"venue"
},
  "geometry": {"coordinates":[-92.097708,46.721875],"type":"Point"}
}