{
  "type": "Feature",
  "properties": {
    "iso:country":"US",
    "sg:address":"810 Maritime Dr",
    "sg:city":"Port Washington",
    "sg:classifiers":[
        {
            "category":"Retail",
            "subcategory":"Auto Repair",
            "type":"Services"
        }
    ],
    "sg:phone":"+1 262 284 8889",
    "sg:postcode":"53074",
    "sg:province":"WI",
    "sg:tags":[
        "automobile",
        "restoration",
        "classic"
    ],
    "sg:website":"www.alohadreamcars.com",
    "wof:name":"Aloha Automotive Svc Inc",
    "wof:placetype":"venue"
},
  "geometry": {"coordinates":[-87.882862,43.370727],"type":"Point"}
}