{
  "type": "Feature",
  "properties": {
    "iso:country":"US",
    "sg:address":"12720 Co Rd K",
    "sg:city":"Reedsville",
    "sg:classifiers":[
        {
            "category":"Shopping",
            "subcategory":"Bicycles & Sporting Goods",
            "type":"Retail Goods"
        }
    ],
    "sg:phone":"+1 920 732 3533",
    "sg:postcode":"54230",
    "sg:province":"WI",
    "wof:name":"Mikes Gun and Ammo",
    "wof:placetype":"venue"
},
  "geometry": {"coordinates":[-87.840169,44.225423],"type":"Point"}
}