{
  "type": "Feature",
  "properties": {
    "iso:country":"US",
    "sg:address":"628 Dewey Ave",
    "sg:city":"Wild Rose",
    "sg:classifiers":[
        {
            "category":"Home & Garden",
            "subcategory":"Building Materials",
            "type":"Retail Goods"
        }
    ],
    "sg:phone":"+1 920 622 4153",
    "sg:postcode":"54984",
    "sg:province":"WI",
    "sg:tags":[
        "door"
    ],
    "wof:name":"Dan's Door Svc",
    "wof:placetype":"venue"
},
  "geometry": {"coordinates":[-89.246132,44.178438],"type":"Point"}
}