{
  "type": "Feature",
  "properties": {
    "iso:country":"US",
    "sg:address":"432 Morgan Ln",
    "sg:city":"Marathon",
    "sg:classifiers":[
        {
            "category":"Utilities",
            "type":"Services"
        }
    ],
    "sg:phone":"+1 715 443 3610",
    "sg:postcode":"54448",
    "sg:province":"WI",
    "sg:tags":[
        "sanitary"
    ],
    "wof:name":"Lemmer Snowplowing LLC",
    "wof:placetype":"venue"
},
  "geometry": {"coordinates":[-89.87497999999999,44.94452],"type":"Point"}
}