{
  "type": "Feature",
  "properties": {
    "iso:country":"US",
    "sg:address":"1652 Douglas Ave",
    "sg:city":"Racine",
    "sg:classifiers":[
        {
            "category":"Shopping",
            "subcategory":"Bicycles & Sporting Goods",
            "type":"Retail Goods"
        }
    ],
    "sg:phone":"+1 262 634 2121",
    "sg:postcode":"53404",
    "sg:province":"WI",
    "wof:name":"Devine's Sporting Goods Store",
    "wof:placetype":"venue"
},
  "geometry": {"coordinates":[-87.794134,42.7413],"type":"Point"}
}