{
  "type": "Feature",
  "properties": {
    "addr:full":"1115 W Ridge Rd Waukesha WI 53186",
    "addr:housenumber":"1115",
    "addr:postcode":"53186",
    "addr:street":"W Ridge Rd",
    "iso:country":"US",
    "sg:address":"1115 W Ridge Rd",
    "sg:city":"Waukesha",
    "sg:classifiers":[
        {
            "category":"Professional",
            "subcategory":"Accounting & Tax Preparation",
            "type":"Services"
        }
    ],
    "sg:phone":"+1 262 574 6912",
    "sg:postcode":"53186",
    "sg:province":"WI",
    "sg:tags":[
        "return"
    ],
    "wof:name":"Tax Resource Connection LLC",
    "wof:placetype":"venue"
},
  "geometry": {"coordinates":[-88.18812800000001,43.020132],"type":"Point"}
}