{
  "type": "Feature",
  "properties": {
    "iso:country":"US",
    "sg:address":"5430 W Forest Home Ave",
    "sg:city":"Milwaukee",
    "sg:classifiers":[
        {
            "category":"Personal",
            "subcategory":"Beauty Salon",
            "type":"Services"
        }
    ],
    "sg:phone":"+1 414 545 7151",
    "sg:postcode":"53220",
    "sg:province":"WI",
    "wof:name":"Studio 54 Hair By Sue",
    "wof:placetype":"venue"
},
  "geometry": {"coordinates":[-87.981888,42.980632],"type":"Point"}
}