{
  "type": "Feature",
  "properties": {
    "iso:country":"US",
    "sg:address":"3151 State Hwy 180",
    "sg:city":"Wausaukee",
    "sg:classifiers":[
        {
            "category":"Manufacturing",
            "subcategory":"Lumber",
            "type":"Manufacturing & Wholesale Goods"
        }
    ],
    "sg:phone":"+1 715 732 6409",
    "sg:postcode":"54177",
    "sg:province":"WI",
    "sg:tags":[
        "logging"
    ],
    "wof:name":"Robert Biernasz Logging",
    "wof:placetype":"venue"
},
  "geometry": {"coordinates":[-87.751105,45.327984],"type":"Point"}
}