{
  "type": "Feature",
  "properties": {
    "addr:full":"2660 N Packerland Dr Green Bay WI 54303",
    "addr:housenumber":"2660",
    "addr:postcode":"54303",
    "addr:street":"N Packerland Dr",
    "iso:country":"US",
    "sg:address":"2660 N Packerland Dr",
    "sg:city":"Green Bay",
    "sg:classifiers":[
        {
            "category":"Shopping",
            "subcategory":"Used Merchandise",
            "type":"Retail Goods"
        }
    ],
    "sg:phone":"+1 920 405 0533",
    "sg:postcode":"54303",
    "sg:province":"WI",
    "wof:name":"Frayed Not",
    "wof:placetype":"venue"
},
  "geometry": {"coordinates":[-88.091303,44.542037],"type":"Point"}
}