{
  "type": "Feature",
  "properties": {
    "iso:country":"US",
    "sg:address":"6443 Virginia St",
    "sg:city":"Vesper",
    "sg:classifiers":[
        {
            "category":"Education",
            "subcategory":"School",
            "type":"Public Place"
        }
    ],
    "sg:phone":"+1 715 569 4115",
    "sg:postcode":"54489",
    "sg:province":"WI",
    "sg:website":"www.wrps.org",
    "wof:name":"Vesper Elementary School",
    "wof:placetype":"venue"
},
  "geometry": {"coordinates":[-89.96977099999999,44.480544],"type":"Point"}
}