{
  "type": "Feature",
  "properties": {
    "iso:country":"US",
    "sg:address":"4035 Erie St",
    "sg:city":"Racine",
    "sg:classifiers":[
        {
            "category":"Social Services",
            "type":"Services"
        }
    ],
    "sg:phone":"+1 262 752 0944",
    "sg:postcode":"53402",
    "sg:province":"WI",
    "sg:tags":[
        "care",
        "center",
        "day"
    ],
    "wof:name":"Chi Chi's Daycare",
    "wof:placetype":"venue"
},
  "geometry": {"coordinates":[-87.786812,42.771566],"type":"Point"}
}