{
  "type": "Feature",
  "properties": {
    "iso:country":"US",
    "sg:address":"4207 Harding Rd",
    "sg:city":"Kenosha",
    "sg:classifiers":[
        {
            "category":"Organizations",
            "subcategory":"Membership Organization",
            "type":"Services"
        }
    ],
    "sg:phone":"+1 262 652 9641",
    "sg:postcode":"53142",
    "sg:province":"WI",
    "wof:name":"National Society Daughters",
    "wof:placetype":"venue"
},
  "geometry": {"coordinates":[-87.860322,42.578015],"type":"Point"}
}