{
  "type": "Feature",
  "properties": {
    "addr:full":"4229 Twenty Six Rd Loyal WI 54446",
    "addr:housenumber":"4229",
    "addr:postcode":"54446",
    "addr:street":"Twenty Six Rd",
    "iso:country":"US",
    "sg:address":"4229 Twenty Six Rd",
    "sg:city":"Loyal",
    "sg:classifiers":[
        {
            "category":"Farming",
            "subcategory":"Dairy Farm",
            "type":"Manufacturing & Wholesale Goods"
        }
    ],
    "sg:phone":"+1 715 255 8627",
    "sg:postcode":"54446",
    "sg:province":"WI",
    "wof:name":"Lawrence Esselman",
    "wof:placetype":"venue"
},
  "geometry": {"coordinates":[-90.530658,44.712365],"type":"Point"}
}