{
  "type": "Feature",
  "properties": {
    "iso:country":"US",
    "sg:address":"204 W Sumner St",
    "sg:city":"Hartford",
    "sg:classifiers":[
        {
            "category":"Restaurant",
            "type":"Food & Drink"
        }
    ],
    "sg:phone":"+1 262 670 6271",
    "sg:postcode":"53027",
    "sg:province":"WI",
    "sg:tags":[
        "eating"
    ],
    "wof:name":"Coffee Garden",
    "wof:placetype":"venue"
},
  "geometry": {"coordinates":[-88.380912,43.317728],"type":"Point"}
}