{
  "type": "Feature",
  "properties": {
    "iso:country":"US",
    "sg:address":"3 Veterans Rd",
    "sg:city":"Fort Atkinson",
    "sg:classifiers":[
        {
            "category":"Organizations",
            "subcategory":"Community Association",
            "type":"Services"
        }
    ],
    "sg:phone":"+1 920 563 5256",
    "sg:postcode":"53589",
    "sg:province":"WI",
    "wof:name":"V F W Post 1879",
    "wof:placetype":"venue"
},
  "geometry": {"coordinates":[-89.20064499999999,42.918583],"type":"Point"}
}