{
  "type": "Feature",
  "properties": {
    "iso:country":"US",
    "sg:address":"822 Summit St",
    "sg:city":"Manitowoc",
    "sg:classifiers":[
        {
            "category":"Real Estate",
            "subcategory":"Real Estate Services",
            "type":"Services"
        }
    ],
    "sg:phone":"+1 920 684 7693",
    "sg:postcode":"54220",
    "sg:province":"WI",
    "sg:tags":[
        "abstract",
        "title"
    ],
    "wof:name":"Maritime Title Services LLC",
    "wof:placetype":"venue"
},
  "geometry": {"coordinates":[-87.658818,44.072245],"type":"Point"}
}