{
  "type": "Feature",
  "properties": {
    "iso:country":"US",
    "sg:address":"9471 Fisher Ave",
    "sg:city":"Willard",
    "sg:classifiers":[
        {
            "category":"Real Estate",
            "subcategory":"Real Estate Operator",
            "type":"Services"
        }
    ],
    "sg:phone":"+1 715 267 7551",
    "sg:postcode":"54493",
    "sg:province":"WI",
    "sg:tags":[
        "property",
        "lessor"
    ],
    "wof:name":"Roger Gregorich",
    "wof:placetype":"venue"
},
  "geometry": {"coordinates":[-90.720063,44.764709],"type":"Point"}
}