{
  "type": "Feature",
  "properties": {
    "iso:country":"US",
    "sg:address":"1086 Park Rd",
    "sg:city":"Lancaster",
    "sg:classifiers":[
        {
            "category":"Freight",
            "type":"Transportation"
        }
    ],
    "sg:phone":"+1 608 723 4051",
    "sg:postcode":"53813",
    "sg:province":"WI",
    "sg:tags":[
        "general"
    ],
    "wof:name":"Zenz Storage LLC",
    "wof:placetype":"venue"
},
  "geometry": {"coordinates":[-90.722465,42.850468],"type":"Point"}
}