{
  "type": "Feature",
  "properties": {
    "iso:country":"US",
    "sg:address":"2660 8th St S",
    "sg:city":"Wisconsin Rapids",
    "sg:classifiers":[
        {
            "category":"Autos & Motor Vehicles",
            "subcategory":"Automobile Sales",
            "type":"Retail Goods"
        }
    ],
    "sg:phone":"+1 715 423 7020",
    "sg:postcode":"54494",
    "sg:province":"WI",
    "sg:tags":[
        "car",
        "used",
        "truck",
        "dealer",
        "new"
    ],
    "wof:name":"Brostrom-Kickert Chevrolet Inc",
    "wof:placetype":"venue"
},
  "geometry": {"coordinates":[-89.817025,44.370756],"type":"Point"}
}