{
  "type": "Feature",
  "properties": {
    "iso:country":"US",
    "sg:address":"33803 Co Hwy X",
    "sg:city":"Blue River",
    "sg:classifiers":[
        {
            "category":"Professional",
            "subcategory":"Business Services",
            "type":"Services"
        }
    ],
    "sg:phone":"+1 608 537 2901",
    "sg:postcode":"53518",
    "sg:province":"WI",
    "wof:name":"Cool Express of WI Inc",
    "wof:placetype":"venue"
},
  "geometry": {"coordinates":[-90.571747,43.207647],"type":"Point"}
}