{
  "type": "Feature",
  "properties": {
    "iso:country":"US",
    "sg:address":"2315 Co Rd Ab",
    "sg:city":"Mc Farland",
    "sg:classifiers":[
        {
            "category":"Banks & Credit Unions",
            "subcategory":"Investment Brokerage",
            "type":"Services"
        }
    ],
    "sg:phone":"+1 608 838 4099",
    "sg:postcode":"53558",
    "sg:province":"WI",
    "wof:name":"W I Investment Board",
    "wof:placetype":"venue"
},
  "geometry": {"coordinates":[-89.278489,42.975034],"type":"Point"}
}