{
  "type": "Feature",
  "properties": {
    "iso:country":"US",
    "sg:address":"7665 Bradley St",
    "sg:city":"Siren",
    "sg:classifiers":[
        {
            "category":"Travel",
            "subcategory":"Hotels & Motels",
            "type":"Entertainment"
        }
    ],
    "sg:phone":"+1 715 349 8180",
    "sg:postcode":"54872",
    "sg:province":"WI",
    "sg:tags":[
        "operation"
    ],
    "wof:name":"Lilac Village Bed & Breakfast",
    "wof:placetype":"venue"
},
  "geometry": {"coordinates":[-92.380702,45.785258],"type":"Point"}
}