{
  "type": "Feature",
  "properties": {
    "addr:full":"2011 E Park Pl Milwaukee WI 53211",
    "addr:housenumber":"2011",
    "addr:postcode":"53211",
    "addr:street":"E Park Pl",
    "iso:country":"US",
    "sg:address":"2011 E Park Pl",
    "sg:city":"Milwaukee",
    "sg:classifiers":[
        {
            "category":"Professional",
            "type":"Services"
        }
    ],
    "sg:phone":"+1 414 332 6142",
    "sg:postcode":"53211",
    "sg:province":"WI",
    "wof:name":"Red Circle Ltd",
    "wof:placetype":"venue"
},
  "geometry": {"coordinates":[-87.884356,43.0673],"type":"Point"}
}