{
  "type": "Feature",
  "properties": {
    "addr:full":"7811 Co Rd B Pittsville WI 54466",
    "addr:housenumber":"7811",
    "addr:postcode":"54466",
    "addr:street":"Co Rd",
    "iso:country":"US",
    "sg:address":"7811 Co Rd B",
    "sg:city":"Pittsville",
    "sg:classifiers":[
        {
            "category":"Retail",
            "subcategory":"Repair Shop",
            "type":"Services"
        }
    ],
    "sg:phone":"+1 715 676 3388",
    "sg:postcode":"54466",
    "sg:province":"WI",
    "wof:name":"Frigidweld",
    "wof:placetype":"venue"
},
  "geometry": {"coordinates":[-90.21838099999999,44.526617],"type":"Point"}
}