{
  "type": "Feature",
  "properties": {
    "iso:country":"US",
    "sg:address":"3257 Beryl Dr",
    "sg:city":"Watertown",
    "sg:classifiers":[
        {
            "category":"Building & Trades",
            "subcategory":"Construction",
            "type":"Services"
        }
    ],
    "sg:phone":"+1 920 262 9145",
    "sg:postcode":"53094",
    "sg:province":"WI",
    "sg:tags":[
        "general",
        "contractor"
    ],
    "wof:name":"G E Mallow Custom Building",
    "wof:placetype":"venue"
},
  "geometry": {"coordinates":[-88.692302,43.154911],"type":"Point"}
}