{
  "type": "Feature",
  "properties": {
    "iso:country":"US",
    "sg:address":"6875 Ridgeview Ln",
    "sg:city":"Platteville",
    "sg:classifiers":[
        {
            "category":"Building & Trades",
            "subcategory":"Construction",
            "type":"Services"
        }
    ],
    "sg:phone":"+1 608 348 3821",
    "sg:postcode":"53818",
    "sg:province":"WI",
    "sg:tags":[
        "nonresidential"
    ],
    "wof:name":"Ridgeview Development Inc",
    "wof:placetype":"venue"
},
  "geometry": {"coordinates":[-90.47966599999999,42.750893],"type":"Point"}
}