{
  "type": "Feature",
  "properties": {
    "iso:country":"US",
    "sg:address":"1363 N Prospect Ave",
    "sg:city":"Milwaukee",
    "sg:classifiers":[
        {
            "category":"Banks & Credit Unions",
            "subcategory":"Investment Brokerage",
            "type":"Services"
        }
    ],
    "sg:phone":"+1 414 276 4898",
    "sg:postcode":"53202",
    "sg:province":"WI",
    "sg:tags":[
        "advisory",
        "financial"
    ],
    "wof:name":"Voit Perlberg & Co",
    "wof:placetype":"venue"
},
  "geometry": {"coordinates":[-87.894422,43.049041],"type":"Point"}
}