{
  "type": "Feature",
  "properties": {
    "iso:country":"US",
    "sg:address":"733 N Meadow Dr",
    "sg:city":"Hudson",
    "sg:classifiers":[
        {
            "category":"Retail",
            "subcategory":"Animal Services",
            "type":"Services"
        }
    ],
    "sg:phone":"+1 715 386 9971",
    "sg:postcode":"54016",
    "sg:province":"WI",
    "wof:name":"Spots Prof Pet Grooming",
    "wof:placetype":"venue"
},
  "geometry": {"coordinates":[-92.64799,44.967553],"type":"Point"}
}