{
  "type": "Feature",
  "properties": {
    "iso:country":"US",
    "sg:address":"1901 E Capitol Dr",
    "sg:city":"Appleton",
    "sg:classifiers":[
        {
            "category":"Government",
            "subcategory":"Office",
            "type":"Public Place"
        }
    ],
    "sg:phone":"+1 920 738 5699",
    "sg:postcode":"54911",
    "sg:province":"WI",
    "sg:tags":[
        "taxation",
        "finance"
    ],
    "wof:name":"IRS",
    "wof:placetype":"venue"
},
  "geometry": {"coordinates":[-88.374935,44.294588],"type":"Point"}
}