{
  "type": "Feature",
  "properties": {
    "iso:country":"US",
    "sg:address":"101 S Jones St",
    "sg:city":"Barneveld",
    "sg:classifiers":[
        {
            "category":"Professional",
            "subcategory":"Accounting & Tax Preparation",
            "type":"Services"
        }
    ],
    "sg:phone":"+1 608 924 1706",
    "sg:postcode":"53507",
    "sg:province":"WI",
    "sg:tags":[
        "accountant"
    ],
    "wof:name":"Eno CPA LTD",
    "wof:placetype":"venue"
},
  "geometry": {"coordinates":[-89.895388,43.01497],"type":"Point"}
}