{
  "type": "Feature",
  "properties": {
    "addr:full":"11310 E Shore Rd Pearson WI 54462",
    "addr:housenumber":"11310",
    "addr:postcode":"54462",
    "addr:street":"E Shore Rd",
    "iso:country":"US",
    "sg:address":"11310 E Shore Rd",
    "sg:city":"Pearson",
    "sg:classifiers":[
        {
            "category":"Travel",
            "subcategory":"Hotels & Motels",
            "type":"Entertainment"
        }
    ],
    "sg:phone":"+1 715 484 2571",
    "sg:postcode":"54462",
    "sg:province":"WI",
    "sg:tags":[
        "resort"
    ],
    "wof:name":"East Shore",
    "wof:placetype":"venue"
},
  "geometry": {"coordinates":[-88.935822,45.438365],"type":"Point"}
}