{
  "type": "Feature",
  "properties": {
    "iso:country":"US",
    "sg:address":"2367 Kettering St",
    "sg:city":"Janesville",
    "sg:classifiers":[
        {
            "category":"Manufacturing",
            "subcategory":"Tools & Machinery",
            "type":"Manufacturing & Wholesale Goods"
        }
    ],
    "sg:phone":"+1 608 752 6148",
    "sg:postcode":"53546",
    "sg:province":"WI",
    "sg:tags":[
        "industry",
        "aerospace"
    ],
    "wof:name":"Alliant Techsystems",
    "wof:placetype":"venue"
},
  "geometry": {"coordinates":[-88.993994,42.731204],"type":"Point"}
}