{
  "type": "Feature",
  "properties": {
    "addr:full":"1806 Belknap St Superior WI 54880",
    "addr:housenumber":"1806",
    "addr:postcode":"54880",
    "addr:street":"Belknap St",
    "iso:country":"US",
    "sg:address":"1806 Belknap St",
    "sg:city":"Superior",
    "sg:classifiers":[
        {
            "category":"Organizations",
            "subcategory":"Religious Organization",
            "type":"Services"
        }
    ],
    "sg:phone":"+1 715 394 6265",
    "sg:postcode":"54880",
    "sg:province":"WI",
    "wof:name":"Presbytery Of Northern Waters",
    "wof:placetype":"venue"
},
  "geometry": {"coordinates":[-92.105401,46.720596],"type":"Point"}
}