{
  "type": "Feature",
  "properties": {
    "iso:country":"US",
    "sg:address":"805 Cattail Ct",
    "sg:city":"Plymouth",
    "sg:classifiers":[
        {
            "category":"Professional",
            "subcategory":"Accounting & Tax Preparation",
            "type":"Services"
        }
    ],
    "sg:phone":"+1 920 893 9527",
    "sg:postcode":"53073",
    "sg:province":"WI",
    "sg:tags":[
        "accountant"
    ],
    "wof:name":"Ledger Plus",
    "wof:placetype":"venue"
},
  "geometry": {"coordinates":[-87.958657,43.737824],"type":"Point"}
}