{
  "type": "Feature",
  "properties": {
    "iso:country":"US",
    "sg:address":"400 S Executive Dr",
    "sg:city":"Brookfield",
    "sg:classifiers":[
        {
            "category":"Building & Trades",
            "subcategory":"Construction",
            "type":"Services"
        }
    ],
    "sg:phone":"+1 262 797 2522",
    "sg:postcode":"53005",
    "sg:province":"WI",
    "sg:tags":[
        "house"
    ],
    "wof:name":"Reed Construction & Wstn Bldr",
    "wof:placetype":"venue"
},
  "geometry": {"coordinates":[-88.114356,43.028309],"type":"Point"}
}