{
  "type": "Feature",
  "properties": {
    "iso:country":"US",
    "sg:address":"2259 Progress Way",
    "sg:city":"Kaukauna",
    "sg:classifiers":[
        {
            "category":"Health Services",
            "subcategory":"Clinic",
            "type":"Services"
        }
    ],
    "sg:phone":"+1 920 759 4540",
    "sg:postcode":"54130",
    "sg:province":"WI",
    "sg:tags":[
        "kidney",
        "dialysis",
        "center"
    ],
    "wof:name":"FMC NA",
    "wof:placetype":"venue"
},
  "geometry": {"coordinates":[-88.264876,44.303294],"type":"Point"}
}