{
  "type": "Feature",
  "properties": {
    "iso:country":"US",
    "sg:address":"2308 6th Ave",
    "sg:city":"Monroe",
    "sg:classifiers":[
        {
            "category":"Bars & Pubs",
            "type":"Food & Drink"
        }
    ],
    "sg:phone":"+1 608 328 8135",
    "sg:postcode":"53566",
    "sg:province":"WI",
    "sg:website":"www.leisurelanes.2gobowl.com",
    "wof:name":"Spirits Bar & Grill",
    "wof:placetype":"venue"
},
  "geometry": {"coordinates":[-89.652202,42.590982],"type":"Point"}
}