{
  "type": "Feature",
  "properties": {
    "iso:country":"US",
    "sg:address":"212 W Cecil St",
    "sg:city":"Neenah",
    "sg:classifiers":[
        {
            "category":"Retail",
            "subcategory":"Auto Repair",
            "type":"Services"
        }
    ],
    "sg:phone":"+1 920 722 9435",
    "sg:postcode":"54956",
    "sg:province":"WI",
    "sg:tags":[
        "repairing",
        "automobile"
    ],
    "wof:name":"Jack's Foreign Car Repair",
    "wof:placetype":"venue"
},
  "geometry": {"coordinates":[-88.46896099999999,44.170969],"type":"Point"}
}