{
  "type": "Feature",
  "properties": {
    "iso:country":"US",
    "sg:address":"132 S Wisconsin St",
    "sg:city":"De Pere",
    "sg:classifiers":[
        {
            "category":"Shopping",
            "subcategory":"Jewelry",
            "type":"Retail Goods"
        }
    ],
    "sg:phone":"+1 920 336 8611",
    "sg:postcode":"54115",
    "sg:province":"WI",
    "sg:tags":[
        "jeweler"
    ],
    "wof:name":"William's Jewelers",
    "wof:placetype":"venue"
},
  "geometry": {"coordinates":[-88.059317,44.448137],"type":"Point"}
}