{
  "type": "Feature",
  "properties": {
    "addr:full":"428 Center St Prentice WI 54556",
    "addr:housenumber":"428",
    "addr:postcode":"54556",
    "addr:street":"Center St",
    "iso:country":"US",
    "sg:address":"428 Center St",
    "sg:city":"Prentice",
    "sg:classifiers":[
        {
            "category":"Government",
            "subcategory":"Post Office",
            "type":"Public Place"
        }
    ],
    "sg:phone":"+1 715 428 2310",
    "sg:postcode":"54556",
    "sg:province":"WI",
    "wof:name":"US Post Office",
    "wof:placetype":"venue"
},
  "geometry": {"coordinates":[-90.281851,45.545794],"type":"Point"}
}