{
  "type": "Feature",
  "properties": {
    "iso:country":"US",
    "sg:address":"1500 N 34th St",
    "sg:city":"Superior",
    "sg:classifiers":[
        {
            "category":"Social Services",
            "subcategory":"Adult Care",
            "type":"Services"
        }
    ],
    "sg:phone":"+1 715 398 7646",
    "sg:postcode":"54880",
    "sg:province":"WI",
    "sg:tags":[
        "residential"
    ],
    "wof:name":"Cbrs",
    "wof:placetype":"venue"
},
  "geometry": {"coordinates":[-92.102012,46.698767],"type":"Point"}
}