{
  "type": "Feature",
  "properties": {
    "iso:country":"US",
    "sg:address":"1422 W Stratton Rd",
    "sg:city":"Waupaca",
    "sg:classifiers":[
        {
            "category":"Social Services",
            "type":"Services"
        }
    ],
    "sg:phone":"+1 715 258 9422",
    "sg:postcode":"54981",
    "sg:province":"WI",
    "sg:tags":[
        "senior",
        "citizen"
    ],
    "wof:name":"Elder Link",
    "wof:placetype":"venue"
},
  "geometry": {"coordinates":[-89.184027,44.290638],"type":"Point"}
}