{
  "type": "Feature",
  "properties": {
    "addr:full":"450 S Main St Fontana WI 53125",
    "addr:housenumber":"450",
    "addr:postcode":"53125",
    "addr:street":"S Main St",
    "iso:country":"US",
    "sg:address":"450 S Main St",
    "sg:city":"Fontana",
    "sg:classifiers":[
        {
            "category":"Education",
            "subcategory":"School",
            "type":"Public Place"
        }
    ],
    "sg:phone":"+1 262 275 6881",
    "sg:postcode":"53125",
    "sg:province":"WI",
    "sg:tags":[
        "elementary"
    ],
    "wof:name":"Fontana Grade School",
    "wof:placetype":"venue"
},
  "geometry": {"coordinates":[-88.58483200000001,42.547511],"type":"Point"}
}