{
  "type": "Feature",
  "properties": {
    "iso:country":"US",
    "sg:address":"10923 W Lincoln Ave",
    "sg:city":"Milwaukee",
    "sg:classifiers":[
        {
            "category":"Insurance",
            "subcategory":"Insurance Agent",
            "type":"Services"
        },
        {
            "category":"Insurance",
            "subcategory":"Hazard Insurance",
            "type":"Services"
        },
        {
            "category":"Insurance",
            "subcategory":"Title Insurance",
            "type":"Services"
        }
    ],
    "sg:phone":"+1 414 321 9100",
    "sg:postcode":"53227",
    "sg:province":"WI",
    "sg:tags":[
        "business",
        "auto",
        "commercial",
        "homeowner",
        "boat",
        "property",
        "marine",
        "casualty"
    ],
    "sg:website":"http://www.gb4insurance.com",
    "wof:name":"Goetsch-Bucholtz Inc",
    "wof:placetype":"venue"
},
  "geometry": {"coordinates":[-88.048329,43.002514],"type":"Point"}
}