{
  "type": "Feature",
  "properties": {
    "addr:full":"15779 W Ryerson Rd New Berlin WI 53151",
    "addr:housenumber":"15779",
    "addr:postcode":"53151",
    "addr:street":"W Ryerson Rd",
    "iso:country":"US",
    "sg:address":"15779 W Ryerson Rd",
    "sg:city":"New Berlin",
    "sg:classifiers":[
        {
            "category":"Professional",
            "type":"Services"
        }
    ],
    "sg:phone":"+1 262 432 5366",
    "sg:postcode":"53151",
    "sg:province":"WI",
    "sg:tags":[
        "establishment"
    ],
    "wof:name":"Lens Best Corp",
    "wof:placetype":"venue"
},
  "geometry": {"coordinates":[-88.110603,42.990844],"type":"Point"}
}