{
  "type": "Feature",
  "properties": {
    "addr:full":"11120 Wynsong Dr Baraboo WI 53913",
    "addr:housenumber":"11120",
    "addr:postcode":"53913",
    "addr:street":"Wynsong Dr",
    "iso:country":"US",
    "sg:address":"11120 Wynsong Dr",
    "sg:city":"Baraboo",
    "sg:classifiers":[
        {
            "category":"Shopping",
            "subcategory":"Discount & Variety Stores",
            "type":"Retail Goods"
        }
    ],
    "sg:phone":"+1 608 356 2637",
    "sg:postcode":"53913",
    "sg:province":"WI",
    "wof:name":"Dollar Mart",
    "wof:placetype":"venue"
},
  "geometry": {"coordinates":[-89.76584200000001,43.490251],"type":"Point"}
}