{
  "type": "Feature",
  "properties": {
    "addr:full":"1841 S 14th St Milwaukee WI 53204",
    "addr:housenumber":"1841",
    "addr:postcode":"53204",
    "addr:street":"S 14Th St",
    "iso:country":"US",
    "sg:address":"1841 S 14th St",
    "sg:city":"Milwaukee",
    "sg:classifiers":[
        {
            "category":"Restaurant",
            "type":"Food & Drink"
        }
    ],
    "sg:menulink":"http://www.allmenus.com/wi/milwaukee/218330-burger-king/menu/",
    "sg:phone":"+1 414 384 4541",
    "sg:postcode":"53204",
    "sg:province":"WI",
    "sg:tags":[
        "american"
    ],
    "wof:name":"Burger King",
    "wof:placetype":"venue"
},
  "geometry": {"coordinates":[-87.929935,43.010604],"type":"Point"}
}