{
  "type": "Feature",
  "properties": {
    "iso:country":"US",
    "sg:address":"16825 W Observatory Rd",
    "sg:city":"New Berlin",
    "sg:classifiers":[
        {
            "category":"Personal",
            "subcategory":"Beauty Salon",
            "type":"Services"
        }
    ],
    "sg:phone":"+1 262 424 6245",
    "sg:postcode":"53151",
    "sg:province":"WI",
    "sg:tags":[
        "manicuring"
    ],
    "wof:name":"Nails By Roxanne",
    "wof:placetype":"venue"
},
  "geometry": {"coordinates":[-88.127443,42.969792],"type":"Point"}
}