{
  "type": "Feature",
  "properties": {
    "addr:full":"1107 Blake Ave South Milwaukee WI 53172",
    "addr:housenumber":"1107",
    "addr:postcode":"53172",
    "addr:street":"Blake Ave",
    "iso:country":"US",
    "sg:address":"1107 Blake Ave",
    "sg:city":"South Milwaukee",
    "sg:classifiers":[
        {
            "category":"Retail",
            "subcategory":"Repair Shop",
            "type":"Services"
        }
    ],
    "sg:phone":"+1 414 764 3322",
    "sg:postcode":"53172",
    "sg:province":"WI",
    "sg:tags":[
        "tractor"
    ],
    "wof:name":"Parker Power Equipment",
    "wof:placetype":"venue"
},
  "geometry": {"coordinates":[-87.865145,42.898817],"type":"Point"}
}