{
  "type": "Feature",
  "properties": {
    "addr:full":"3054 State Hwy 71 Elroy WI 53929",
    "addr:housenumber":"3054",
    "addr:postcode":"53929",
    "addr:street":"State Hwy 71",
    "iso:country":"US",
    "sg:address":"3054 State Hwy 71",
    "sg:city":"Elroy",
    "sg:classifiers":[
        {
            "category":"Building & Trades",
            "subcategory":"Plumbing",
            "type":"Services"
        }
    ],
    "sg:phone":"+1 608 462 4084",
    "sg:postcode":"53929",
    "sg:province":"WI",
    "sg:tags":[
        "conditioning",
        "air",
        "system",
        "contractor"
    ],
    "wof:name":"Elroy Aire",
    "wof:placetype":"venue"
},
  "geometry": {"coordinates":[-90.28861999999999,43.752121],"type":"Point"}
}