{
  "type": "Feature",
  "properties": {
    "iso:country":"US",
    "sg:address":"14290 Chestnut Grove Ct",
    "sg:city":"Brookfield",
    "sg:classifiers":[
        {
            "category":"Building & Trades",
            "subcategory":"Plumbing",
            "type":"Services"
        }
    ],
    "sg:phone":"+1 262 782 9246",
    "sg:postcode":"53005",
    "sg:province":"WI",
    "sg:tags":[
        "contractor"
    ],
    "wof:name":"AC Gaulke Inc",
    "wof:placetype":"venue"
},
  "geometry": {"coordinates":[-88.08981300000001,43.06084],"type":"Point"}
}