{
  "type": "Feature",
  "properties": {
    "iso:country":"US",
    "sg:address":"501 Hewett St",
    "sg:city":"Neillsville",
    "sg:classifiers":[
        {
            "category":"Professional",
            "subcategory":"Lawyer & Legal Services",
            "type":"Services"
        }
    ],
    "sg:phone":"+1 715 743 2799",
    "sg:postcode":"54456",
    "sg:province":"WI",
    "wof:name":"Olsher & Sherman Sherman",
    "wof:placetype":"venue"
},
  "geometry": {"coordinates":[-90.59625699999999,44.560336],"type":"Point"}
}