{
  "type": "Feature",
  "properties": {
    "iso:country":"US",
    "sg:address":"400 W Brentwood Ln",
    "sg:city":"Milwaukee",
    "sg:classifiers":[
        {
            "category":"Professional",
            "subcategory":"Business Services",
            "type":"Services"
        }
    ],
    "sg:phone":"+1 414 352 0779",
    "sg:postcode":"53217",
    "sg:province":"WI",
    "wof:name":"Family Mediation Services",
    "wof:placetype":"venue"
},
  "geometry": {"coordinates":[-87.91553399999999,43.13397],"type":"Point"}
}