{
  "type": "Feature",
  "properties": {
    "iso:country":"US",
    "sg:address":"2600 N Ballard Rd",
    "sg:city":"Appleton",
    "sg:classifiers":[
        {
            "category":"Manufacturing",
            "subcategory":"Printing",
            "type":"Manufacturing & Wholesale Goods"
        }
    ],
    "sg:phone":"+1 920 734 7500",
    "sg:postcode":"54911",
    "sg:province":"WI",
    "sg:tags":[
        "lithograph",
        "work",
        "commercial",
        "printer"
    ],
    "wof:name":"National Graphic Solutions LLC",
    "wof:placetype":"venue"
},
  "geometry": {"coordinates":[-88.37483400000001,44.285426],"type":"Point"}
}