{
  "type": "Feature",
  "properties": {
    "iso:country":"US",
    "sg:address":"4138 Fischer Rd",
    "sg:city":"Green Bay",
    "sg:classifiers":[
        {
            "category":"Building & Trades",
            "subcategory":"Construction",
            "type":"Services"
        }
    ],
    "sg:phone":"+1 920 866 9043",
    "sg:postcode":"54311",
    "sg:province":"WI",
    "sg:tags":[
        "contractor"
    ],
    "wof:name":"Seamless Gutters",
    "wof:placetype":"venue"
},
  "geometry": {"coordinates":[-87.875084,44.582038],"type":"Point"}
}