{
  "type": "Feature",
  "properties": {
    "addr:full":"10385 Paquette Rd Black River Fls WI 54615",
    "addr:housenumber":"10385",
    "addr:postcode":"54615",
    "addr:street":"Paquette Rd",
    "iso:country":"US",
    "sg:address":"10385 Paquette Rd",
    "sg:city":"Black River Fls",
    "sg:classifiers":[
        {
            "category":"Organizations",
            "subcategory":"Religious Organization",
            "type":"Services"
        }
    ],
    "sg:phone":"+1 715 284 7037",
    "sg:postcode":"54615",
    "sg:province":"WI",
    "sg:tags":[
        "church"
    ],
    "wof:name":"Pine Hill Church Of Christ",
    "wof:placetype":"venue"
},
  "geometry": {"coordinates":[-90.823661,44.202014],"type":"Point"}
}