{
  "type": "Feature",
  "properties": {
    "iso:country":"US",
    "sg:address":"6205 Davenport Dr",
    "sg:city":"Madison",
    "sg:classifiers":[
        {
            "category":"Professional",
            "subcategory":"Management & Consulting",
            "type":"Services"
        }
    ],
    "sg:phone":"+1 608 277 9518",
    "sg:postcode":"53711",
    "sg:province":"WI",
    "sg:tags":[
        "marketing",
        "strategic"
    ],
    "wof:name":"Mallet Jack",
    "wof:placetype":"venue"
},
  "geometry": {"coordinates":[-89.486773,43.043125],"type":"Point"}
}