{
  "type": "Feature",
  "properties": {
    "addr:full":"904 E State St Mauston WI 53948",
    "addr:housenumber":"904",
    "addr:postcode":"53948",
    "addr:street":"E State St",
    "iso:country":"US",
    "sg:address":"904 E State St",
    "sg:city":"Mauston",
    "sg:classifiers":[
        {
            "category":"Farming",
            "subcategory":"Farm & Veterinary Services",
            "type":"Manufacturing & Wholesale Goods"
        }
    ],
    "sg:phone":"+1 608 847 4453",
    "sg:postcode":"53948",
    "sg:province":"WI",
    "sg:tags":[
        "tax",
        "management",
        "return",
        "prep"
    ],
    "wof:name":"Lutz Tax & Accounting Inc",
    "wof:placetype":"venue"
},
  "geometry": {"coordinates":[-90.065789,43.793324],"type":"Point"}
}