{
  "type": "Feature",
  "properties": {
    "iso:country":"US",
    "sg:address":"201 Railroad St",
    "sg:city":"Eagle River",
    "sg:classifiers":[
        {
            "category":"Professional",
            "subcategory":"Lawyer & Legal Services",
            "type":"Services"
        }
    ],
    "sg:phone":"+1 715 479 3131",
    "sg:postcode":"54521",
    "sg:province":"WI",
    "sg:tags":[
        "attorney"
    ],
    "wof:name":"William J Joost Law Office",
    "wof:placetype":"venue"
},
  "geometry": {"coordinates":[-89.253333,45.918361],"type":"Point"}
}