{
  "type": "Feature",
  "properties": {
    "addr:full":"2206 W National Ave Milwaukee WI 53204",
    "addr:housenumber":"2206",
    "addr:postcode":"53204",
    "addr:street":"W National Ave",
    "iso:country":"US",
    "sg:address":"2206 W National Ave",
    "sg:city":"Milwaukee",
    "sg:classifiers":[
        {
            "category":"Home & Garden",
            "subcategory":"Home Furnishings",
            "type":"Retail Goods"
        }
    ],
    "sg:phone":"+1 414 383 4880",
    "sg:postcode":"53204",
    "sg:province":"WI",
    "sg:tags":[
        "candle"
    ],
    "wof:name":"El Angel",
    "wof:placetype":"venue"
},
  "geometry": {"coordinates":[-87.940896,43.022624],"type":"Point"}
}