{
  "type": "Feature",
  "properties": {
    "iso:country":"US",
    "sg:address":"19 Walker St",
    "sg:city":"Evansville",
    "sg:classifiers":[
        {
            "category":"Freight",
            "type":"Transportation"
        }
    ],
    "sg:phone":"+1 608 882 5249",
    "sg:postcode":"53536",
    "sg:province":"WI",
    "sg:tags":[
        "operator",
        "local",
        "trucking"
    ],
    "wof:name":"Willing Trucking Inc",
    "wof:placetype":"venue"
},
  "geometry": {"coordinates":[-89.298877,42.77292],"type":"Point"}
}