{
  "type": "Feature",
  "properties": {
    "iso:country":"US",
    "sg:address":"570 E Blackhawk Dr",
    "sg:city":"Fort Atkinson",
    "sg:classifiers":[
        {
            "category":"Professional",
            "type":"Services"
        }
    ],
    "sg:phone":"+1 920 568 8935",
    "sg:postcode":"53538",
    "sg:province":"WI",
    "wof:name":"T Hansen",
    "wof:placetype":"venue"
},
  "geometry": {"coordinates":[-88.828981,42.941993],"type":"Point"}
}