{
  "type": "Feature",
  "properties": {
    "iso:country":"US",
    "sg:address":"4699 Cloverland Rd",
    "sg:city":"Ladysmith",
    "sg:classifiers":[
        {
            "category":"Shopping",
            "subcategory":"Hobbies, Toys, & Games",
            "type":"Retail Goods"
        }
    ],
    "sg:phone":"+1 715 532 9247",
    "sg:postcode":"54848",
    "sg:province":"WI",
    "wof:name":"Rrails",
    "wof:placetype":"venue"
},
  "geometry": {"coordinates":[-91.028519,45.456911],"type":"Point"}
}