{
  "type": "Feature",
  "properties": {
    "iso:country":"US",
    "sg:address":"1300 S Main St",
    "sg:city":"Shawano",
    "sg:classifiers":[
        {
            "category":"Freight",
            "type":"Transportation"
        }
    ],
    "sg:phone":"+1 715 524 3704",
    "sg:postcode":"54166",
    "sg:province":"WI",
    "sg:tags":[
        "operator",
        "local",
        "trucking"
    ],
    "wof:name":"John C Pfister Trucking",
    "wof:placetype":"venue"
},
  "geometry": {"coordinates":[-88.608736,44.764513],"type":"Point"}
}