{
  "type": "Feature",
  "properties": {
    "addr:full":"230 Satterlee St Fond Du Lac WI 54935",
    "addr:housenumber":"230",
    "addr:postcode":"54935",
    "addr:street":"Satterlee St",
    "iso:country":"US",
    "sg:address":"230 Satterlee St",
    "sg:city":"Fond Du Lac",
    "sg:classifiers":[
        {
            "category":"Shopping",
            "subcategory":"Gifts & Souvenirs",
            "type":"Retail Goods"
        }
    ],
    "sg:phone":"+1 920 923 4224",
    "sg:postcode":"54935",
    "sg:province":"WI",
    "wof:name":"Country Curios",
    "wof:placetype":"venue"
},
  "geometry": {"coordinates":[-88.45802999999999,43.784883],"type":"Point"}
}