{
  "type": "Feature",
  "properties": {
    "iso:country":"US",
    "sg:address":"217 Van Deusen St",
    "sg:city":"Madison",
    "sg:classifiers":[
        {
            "category":"Real Estate",
            "subcategory":"Real Estate Operator",
            "type":"Services"
        }
    ],
    "sg:phone":"+1 608 280 0721",
    "sg:postcode":"53715",
    "sg:province":"WI",
    "sg:tags":[
        "building",
        "nonresidential"
    ],
    "wof:name":"Neumann & Kaye Properties LLC",
    "wof:placetype":"venue"
},
  "geometry": {"coordinates":[-89.38682,43.054206],"type":"Point"}
}