{
  "type": "Feature",
  "properties": {
    "iso:country":"US",
    "sg:address":"24530 State Rd 35 70",
    "sg:city":"Siren",
    "sg:classifiers":[
        {
            "category":"Shopping",
            "subcategory":"Used Merchandise",
            "type":"Retail Goods"
        }
    ],
    "sg:phone":"+1 715 349 7573",
    "sg:postcode":"54872",
    "sg:province":"WI",
    "sg:tags":[
        "antique"
    ],
    "wof:name":"Siren Now & Then",
    "wof:placetype":"venue"
},
  "geometry": {"coordinates":[-92.37508800000001,45.805089],"type":"Point"}
}