{
  "type": "Feature",
  "properties": {
    "addr:full":"117 N Wisconsin St Janesville WI 53545",
    "addr:housenumber":"117",
    "addr:postcode":"53545",
    "addr:street":"N Wisconsin St",
    "iso:country":"US",
    "sg:address":"117 N Wisconsin St",
    "sg:city":"Janesville",
    "sg:classifiers":[
        {
            "category":"Organizations",
            "subcategory":"Religious Organization",
            "type":"Services"
        }
    ],
    "sg:phone":"+1 608 756 0771",
    "sg:postcode":"53545",
    "sg:province":"WI",
    "wof:name":"Nativity of Mary",
    "wof:placetype":"venue"
},
  "geometry": {"coordinates":[-89.021252,42.685941],"type":"Point"}
}