{
  "type": "Feature",
  "properties": {
    "iso:country":"US",
    "sg:address":"11912 Lakeview Rd",
    "sg:city":"Ellison Bay",
    "sg:classifiers":[
        {
            "category":"Food & Beverages",
            "subcategory":"Specialty",
            "type":"Retail Goods"
        }
    ],
    "sg:phone":"+1 920 854 2286",
    "sg:postcode":"54210",
    "sg:province":"WI",
    "wof:name":"Daubner Shaklee Distributors",
    "wof:placetype":"venue"
},
  "geometry": {"coordinates":[-87.0715,45.252545],"type":"Point"}
}