{
  "type": "Feature",
  "properties": {
    "addr:full":"7137 540th St Menomonie WI 54751",
    "addr:housenumber":"7137",
    "addr:postcode":"54751",
    "addr:street":"540Th St",
    "iso:country":"US",
    "sg:address":"7137 540th St",
    "sg:city":"Menomonie",
    "sg:classifiers":[
        {
            "category":"Real Estate",
            "subcategory":"Real Estate Operator",
            "type":"Services"
        }
    ],
    "sg:phone":"+1 715 235 6030",
    "sg:postcode":"54751",
    "sg:province":"WI",
    "sg:tags":[
        "apartment"
    ],
    "wof:name":"O K Properties",
    "wof:placetype":"venue"
},
  "geometry": {"coordinates":[-91.888649,44.944283],"type":"Point"}
}