{
  "type": "Feature",
  "properties": {
    "iso:country":"US",
    "sg:address":"3007 80th St",
    "sg:city":"Kenosha",
    "sg:classifiers":[
        {
            "category":"Restaurant",
            "type":"Food & Drink"
        }
    ],
    "sg:menulink":"http://www.allmenus.com/wi/kenosha/218304-burger-king/menu/",
    "sg:phone":"+1 414 694 5082",
    "sg:postcode":"53142",
    "sg:province":"WI",
    "sg:tags":[
        "american"
    ],
    "wof:name":"Burger King",
    "wof:placetype":"venue"
},
  "geometry": {"coordinates":[-87.845659,42.558437],"type":"Point"}
}