{
  "type": "Feature",
  "properties": {
    "iso:country":"US",
    "sg:address":"107 Charles St",
    "sg:city":"Readstown",
    "sg:classifiers":[
        {
            "category":"Wholesale",
            "subcategory":"Machinery & Supplies",
            "type":"Manufacturing & Wholesale Goods"
        }
    ],
    "sg:phone":"+1 608 629 5405",
    "sg:postcode":"54652",
    "sg:province":"WI",
    "sg:tags":[
        "equipment",
        "dairy"
    ],
    "wof:name":"Kickapoo Dairy Svc Inc",
    "wof:placetype":"venue"
},
  "geometry": {"coordinates":[-90.760745,43.449205],"type":"Point"}
}