{
  "type": "Feature",
  "properties": {
    "iso:country":"US",
    "sg:address":"3311 48th St N",
    "sg:city":"Wisconsin Rapids",
    "sg:classifiers":[
        {
            "category":"Professional",
            "subcategory":"Business Services",
            "type":"Services"
        }
    ],
    "sg:phone":"+1 715 423 1292",
    "sg:postcode":"54494",
    "sg:province":"WI",
    "sg:tags":[
        "printing",
        "broker"
    ],
    "wof:name":"Lasting Impressions",
    "wof:placetype":"venue"
},
  "geometry": {"coordinates":[-89.766432,44.418175],"type":"Point"}
}