{
  "type": "Feature",
  "properties": {
    "iso:country":"US",
    "sg:address":"4526 Meadow Wood Cir",
    "sg:city":"De Forest",
    "sg:classifiers":[
        {
            "category":"Shopping",
            "type":"Retail Goods"
        }
    ],
    "sg:phone":"+1 608 846 9688",
    "sg:postcode":"53532",
    "sg:province":"WI",
    "sg:tags":[
        "merchandise",
        "business"
    ],
    "wof:name":"Kals Rsj LLC",
    "wof:placetype":"venue"
},
  "geometry": {"coordinates":[-89.346903,43.23908],"type":"Point"}
}