{
  "type": "Feature",
  "properties": {
    "iso:country":"US",
    "sg:address":"1333 E College Ave",
    "sg:city":"Oak Creek",
    "sg:classifiers":[
        {
            "category":"Health Services",
            "subcategory":"Health Practitioner",
            "type":"Services"
        }
    ],
    "sg:phone":"+1 414 571 9146",
    "sg:postcode":"53154",
    "sg:province":"WI",
    "sg:tags":[
        "therapist",
        "physical"
    ],
    "wof:name":"M & M Physical Therapy",
    "wof:placetype":"venue"
},
  "geometry": {"coordinates":[-87.89151200000001,42.929965],"type":"Point"}
}