{
  "type": "Feature",
  "properties": {
    "iso:country":"US",
    "sg:address":"718 US Hwy 141",
    "sg:city":"Coleman",
    "sg:classifiers":[
        {
            "category":"Government",
            "subcategory":"Office",
            "type":"Public Place"
        }
    ],
    "sg:phone":"+1 920 897 2191",
    "sg:postcode":"54112",
    "sg:province":"WI",
    "sg:tags":[
        "govt",
        "city"
    ],
    "wof:name":"Waste Water Treatment Plant",
    "wof:placetype":"venue"
},
  "geometry": {"coordinates":[-88.03344800000001,45.078133],"type":"Point"}
}