{
  "type": "Feature",
  "properties": {
    "iso:country":"US",
    "sg:address":"329 W 1st St",
    "sg:city":"Waldo",
    "sg:classifiers":[
        {
            "category":"Professional",
            "subcategory":"Secretarial Services",
            "type":"Services"
        }
    ],
    "sg:phone":"+1 920 528 7045",
    "sg:postcode":"53093",
    "sg:province":"WI",
    "sg:tags":[
        "reporting",
        "court"
    ],
    "wof:name":"Executive Business Svc",
    "wof:placetype":"venue"
},
  "geometry": {"coordinates":[-87.947904,43.674554],"type":"Point"}
}