{
  "type": "Feature",
  "properties": {
    "addr:full":"439 Hilton Dr Madison WI 53711",
    "addr:housenumber":"439",
    "addr:postcode":"53711",
    "addr:street":"Hilton Dr",
    "iso:country":"US",
    "sg:address":"439 Hilton Dr",
    "sg:city":"Madison",
    "sg:classifiers":[
        {
            "category":"Professional",
            "subcategory":"Engineering",
            "type":"Services"
        }
    ],
    "sg:phone":"+1 608 263 1678",
    "sg:postcode":"53711",
    "sg:province":"WI",
    "wof:name":"John H Perepezko",
    "wof:placetype":"venue"
},
  "geometry": {"coordinates":[-89.462864,43.05919],"type":"Point"}
}