{
  "type": "Feature",
  "properties": {
    "iso:country":"US",
    "sg:address":"5354 Co Rd D",
    "sg:city":"Leopolis",
    "sg:classifiers":[
        {
            "category":"Farming",
            "subcategory":"Dairy Farm",
            "type":"Manufacturing & Wholesale Goods"
        }
    ],
    "sg:phone":"+1 715 787 3348",
    "sg:postcode":"54948",
    "sg:province":"WI",
    "wof:name":"Hillside Farms",
    "wof:placetype":"venue"
},
  "geometry": {"coordinates":[-88.87630299999999,44.78892],"type":"Point"}
}