{
  "type": "Feature",
  "properties": {
    "addr:full":"200 E Wells St Milwaukee WI 53202",
    "addr:housenumber":"200",
    "addr:postcode":"53202",
    "addr:street":"E Wells St",
    "iso:country":"US",
    "sg:address":"200 E Wells St",
    "sg:city":"Milwaukee",
    "sg:classifiers":[
        {
            "category":"Government",
            "subcategory":"Office",
            "type":"Public Place"
        }
    ],
    "sg:phone":"+1 414 286 3747",
    "sg:postcode":"53202",
    "sg:province":"WI",
    "sg:tags":[
        "village"
    ],
    "wof:name":"Milwaukee Intergovernmental",
    "wof:placetype":"venue"
},
  "geometry": {"coordinates":[-87.90937599999999,43.041014],"type":"Point"}
}