{
  "type": "Feature",
  "properties": {
    "iso:country":"US",
    "sg:address":"6142 S 27th St",
    "sg:city":"Milwaukee",
    "sg:classifiers":[
        {
            "category":"Building & Trades",
            "subcategory":"Electrical",
            "type":"Services"
        }
    ],
    "sg:phone":"+1 414 282 0200",
    "sg:postcode":"53221",
    "sg:province":"WI",
    "sg:tags":[
        "communications",
        "specialization",
        "contractor"
    ],
    "wof:name":"Custom Mobile Installations",
    "wof:placetype":"venue"
},
  "geometry": {"coordinates":[-87.949252,42.933219],"type":"Point"}
}