{
  "type": "Feature",
  "properties": {
    "addr:full":"8720 Forest Lane Rd Ripon WI 54971",
    "addr:housenumber":"8720",
    "addr:postcode":"54971",
    "addr:street":"Forest Lane Rd",
    "iso:country":"US",
    "sg:address":"8720 Forest Lane Rd",
    "sg:city":"Ripon",
    "sg:phone":"+1 920 748 3647",
    "sg:postcode":"54971",
    "sg:province":"WI",
    "sg:tags":[
        "farm",
        "corn"
    ],
    "wof:name":"Lloyd Nitz",
    "wof:placetype":"venue"
},
  "geometry": {"coordinates":[-88.735407,43.86591],"type":"Point"}
}