{
  "type": "Feature",
  "properties": {
    "iso:country":"US",
    "sg:address":"216 Depot St",
    "sg:city":"Footville",
    "sg:classifiers":[
        {
            "category":"Bars & Pubs",
            "type":"Food & Drink"
        }
    ],
    "sg:phone":"+1 608 876 6521",
    "sg:postcode":"53537",
    "sg:province":"WI",
    "wof:name":"B'Ners Bar",
    "wof:placetype":"venue"
},
  "geometry": {"coordinates":[-89.211034,42.670194],"type":"Point"}
}