{
  "type": "Feature",
  "properties": {
    "iso:country":"US",
    "sg:address":"3712 Tower Ave",
    "sg:city":"Superior",
    "sg:classifiers":[
        {
            "category":"Shopping",
            "subcategory":"Clothing, Apparel, & Fashions",
            "type":"Retail Goods"
        }
    ],
    "sg:phone":"+1 715 394 7272",
    "sg:postcode":"54880",
    "sg:province":"WI",
    "sg:tags":[
        "woman"
    ],
    "wof:name":"Sara Bella Of Superior Inc",
    "wof:placetype":"venue"
},
  "geometry": {"coordinates":[-92.104049,46.69266],"type":"Point"}
}