{
  "type": "Feature",
  "properties": {
    "addr:full":"6263 Co Rd A Shiocton WI 54170",
    "addr:housenumber":"6263",
    "addr:postcode":"54170",
    "addr:street":"Co Rd A Shiocton",
    "iso:country":"US",
    "sg:address":"6263 Co Rd A",
    "sg:city":"Shiocton",
    "sg:classifiers":[
        {
            "category":"Farming",
            "subcategory":"Dairy Farm",
            "type":"Manufacturing & Wholesale Goods"
        }
    ],
    "sg:phone":"+1 920 984 3615",
    "sg:postcode":"54170",
    "sg:province":"WI",
    "wof:name":"Less Way Farms",
    "wof:placetype":"venue"
},
  "geometry": {"coordinates":[-88.506159,44.426647],"type":"Point"}
}