{
  "type": "Feature",
  "properties": {
    "iso:country":"US",
    "sg:address":"301 W Main St",
    "sg:city":"Marshall",
    "sg:classifiers":[
        {
            "category":"Professional",
            "subcategory":"Computer Services",
            "type":"Services"
        }
    ],
    "sg:phone":"+1 608 655 1500",
    "sg:postcode":"53559",
    "sg:province":"WI",
    "sg:tags":[
        "related"
    ],
    "wof:name":"Systems & Programming Sltns",
    "wof:placetype":"venue"
},
  "geometry": {"coordinates":[-89.067123,43.168935],"type":"Point"}
}