{
  "type": "Feature",
  "properties": {
    "iso:country":"US",
    "sg:address":"2421 Geneva St",
    "sg:city":"Racine",
    "sg:classifiers":[
        {
            "category":"Professional",
            "subcategory":"Management & Consulting",
            "type":"Services"
        }
    ],
    "sg:phone":"+1 262 752 1740",
    "sg:postcode":"53402",
    "sg:province":"WI",
    "sg:tags":[
        "party",
        "planning"
    ],
    "wof:name":"Whim Zee's",
    "wof:placetype":"venue"
},
  "geometry": {"coordinates":[-87.79432300000001,42.751159],"type":"Point"}
}