{
  "type": "Feature",
  "properties": {
    "iso:country":"US",
    "sg:address":"1751 Apple Dr",
    "sg:city":"Sun Prairie",
    "sg:classifiers":[
        {
            "category":"Building & Trades",
            "subcategory":"Construction",
            "type":"Services"
        }
    ],
    "sg:phone":"+1 608 825 3121",
    "sg:postcode":"53590",
    "sg:province":"WI",
    "sg:tags":[
        "home",
        "improvement"
    ],
    "wof:name":"Top Of The Line Seamless",
    "wof:placetype":"venue"
},
  "geometry": {"coordinates":[-89.243241,43.172627],"type":"Point"}
}