{
  "type": "Feature",
  "properties": {
    "addr:full":"1350 N Port Washington Rd #4919 Grafton WI 53024",
    "addr:housenumber":"1350",
    "addr:postcode":"53024",
    "addr:street":"N Port Washington Rd # 4919",
    "iso:country":"US",
    "sg:address":"1350 N Port Washington Rd #4919",
    "sg:city":"Grafton",
    "sg:classifiers":[
        {
            "category":"Home & Garden",
            "subcategory":"Hardware",
            "type":"Retail Goods"
        }
    ],
    "sg:phone":"+1 262 376 4908",
    "sg:postcode":"53024",
    "sg:province":"WI",
    "sg:tags":[
        "store"
    ],
    "sg:website":"www.homedepot.com",
    "wof:name":"Home Depot the",
    "wof:placetype":"venue"
},
  "geometry": {"coordinates":[-87.92522700000001,43.32424],"type":"Point"}
}