{
  "type": "Feature",
  "properties": {
    "iso:country":"US",
    "sg:address":"21400 W Greenfield Ave",
    "sg:city":"New Berlin",
    "sg:classifiers":[
        {
            "category":"Social Services",
            "subcategory":"Child Care",
            "type":"Services"
        }
    ],
    "sg:phone":"+1 262 544 4100",
    "sg:postcode":"53146",
    "sg:province":"WI",
    "sg:tags":[
        "day"
    ],
    "wof:name":"Kids Crnr Child Care Preschool",
    "wof:placetype":"venue"
},
  "geometry": {"coordinates":[-88.180864,43.013771],"type":"Point"}
}