{
  "type": "Feature",
  "properties": {
    "iso:country":"US",
    "sg:address":"1759 Thierer Rd",
    "sg:city":"Madison",
    "sg:classifiers":[
        {
            "category":"Shopping",
            "subcategory":"Department Store",
            "type":"Retail Goods"
        }
    ],
    "sg:phone":"+1 608 242 9265",
    "sg:postcode":"53704",
    "sg:province":"WI",
    "sg:tags":[
        "shop",
        "variety"
    ],
    "sg:website":"http://www.dollartree.com/",
    "wof:name":"Dollar Tree",
    "wof:placetype":"venue"
},
  "geometry": {"coordinates":[-89.313282,43.122871],"type":"Point"}
}