{
  "type": "Feature",
  "properties": {
    "iso:country":"US",
    "sg:address":"715 N Main St",
    "sg:city":"Lodi",
    "sg:classifiers":[
        {
            "category":"Local Transit",
            "type":"Transportation"
        }
    ],
    "sg:phone":"+1 608 592 7123",
    "sg:postcode":"53555",
    "sg:province":"WI",
    "sg:tags":[
        "ambulance"
    ],
    "wof:name":"Lodi Area EMS Svc",
    "wof:placetype":"venue"
},
  "geometry": {"coordinates":[-89.531803,43.318461],"type":"Point"}
}