{
  "type": "Feature",
  "properties": {
    "iso:country":"US",
    "sg:address":"3821 Evergreen Ave",
    "sg:city":"Wisconsin Rapids",
    "sg:classifiers":[
        {
            "category":"Personal",
            "subcategory":"Beauty Salon",
            "type":"Services"
        }
    ],
    "sg:phone":"+1 715 325 7022",
    "sg:postcode":"54494",
    "sg:province":"WI",
    "sg:tags":[
        "shop"
    ],
    "wof:name":"Kellerman Cuts LLC",
    "wof:placetype":"venue"
},
  "geometry": {"coordinates":[-89.779018,44.29194],"type":"Point"}
}