{
  "type": "Feature",
  "properties": {
    "iso:country":"US",
    "sg:address":"833 Chestnut St",
    "sg:city":"West Bend",
    "sg:classifiers":[
        {
            "category":"Social Services",
            "subcategory":"Child Care",
            "type":"Services"
        },
        {
            "category":"Education",
            "subcategory":"School",
            "type":"Public Place"
        }
    ],
    "sg:phone":"+1 262 335 6470",
    "sg:postcode":"53095",
    "sg:province":"WI",
    "sg:tags":[
        "day"
    ],
    "wof:name":"Children's World Learning Ctr",
    "wof:placetype":"venue"
},
  "geometry": {"coordinates":[-88.18709,43.419479],"type":"Point"}
}