{
  "type": "Feature",
  "properties": {
    "iso:country":"US",
    "sg:address":"225 Main St",
    "sg:city":"Elroy",
    "sg:classifiers":[
        {
            "category":"Utilities",
            "subcategory":"Water",
            "type":"Services"
        }
    ],
    "sg:phone":"+1 608 462 2418",
    "sg:postcode":"53929",
    "sg:province":"WI",
    "sg:tags":[
        "company",
        "sewage"
    ],
    "wof:name":"Elroy Water Dept",
    "wof:placetype":"venue"
},
  "geometry": {"coordinates":[-90.27137999999999,43.739849],"type":"Point"}
}