{
  "type": "Feature",
  "properties": {
    "iso:country":"US",
    "sg:address":"718 E Wells St",
    "sg:city":"Milwaukee",
    "sg:classifiers":[
        {
            "category":"Sports & Exercise",
            "subcategory":"Gym",
            "type":"Entertainment"
        }
    ],
    "sg:phone":"+1 414 271 4247",
    "sg:postcode":"53202",
    "sg:province":"WI",
    "sg:tags":[
        "shop",
        "fitness",
        "barber",
        "physical",
        "facility"
    ],
    "wof:name":"East Town Spa",
    "wof:placetype":"venue"
},
  "geometry": {"coordinates":[-87.90194099999999,43.041551],"type":"Point"}
}