{
  "type": "Feature",
  "properties": {
    "iso:country":"US",
    "sg:address":"2067 Douglas Ave",
    "sg:city":"Racine",
    "sg:classifiers":[
        {
            "category":"Manufacturing",
            "subcategory":"Glass & Minerals",
            "type":"Manufacturing & Wholesale Goods"
        }
    ],
    "sg:phone":"+1 262 638 0966",
    "sg:postcode":"53402",
    "sg:province":"WI",
    "sg:tags":[
        "structural"
    ],
    "wof:name":"Quick-Set Panels Corp",
    "wof:placetype":"venue"
},
  "geometry": {"coordinates":[-87.79785699999999,42.746376],"type":"Point"}
}