{
  "type": "Feature",
  "properties": {
    "iso:country":"US",
    "sg:address":"840 N 9th St",
    "sg:city":"De Pere",
    "sg:classifiers":[
        {
            "category":"Retail",
            "subcategory":"Auto Rental",
            "type":"Services"
        }
    ],
    "sg:phone":"+1 920 336 2843",
    "sg:postcode":"54115",
    "sg:province":"WI",
    "sg:tags":[
        "renting",
        "truck",
        "leasing"
    ],
    "wof:name":"U-Haul Co",
    "wof:placetype":"venue"
},
  "geometry": {"coordinates":[-88.07875300000001,44.457479],"type":"Point"}
}