{
  "type": "Feature",
  "properties": {
    "iso:country":"US",
    "sg:address":"2845 Deer Ln",
    "sg:city":"Cecil",
    "sg:classifiers":[
        {
            "category":"Farming",
            "subcategory":"Farm",
            "type":"Manufacturing & Wholesale Goods"
        }
    ],
    "sg:phone":"+1 715 745 2758",
    "sg:postcode":"54111",
    "sg:province":"WI",
    "sg:tags":[
        "crop",
        "general"
    ],
    "wof:name":"Mucks Leg Heights",
    "wof:placetype":"venue"
},
  "geometry": {"coordinates":[-88.38027099999999,44.808605],"type":"Point"}
}