{
  "type": "Feature",
  "properties": {
    "iso:country":"US",
    "sg:address":"9535 W Loomis Rd",
    "sg:city":"Franklin",
    "sg:classifiers":[
        {
            "category":"Social Services",
            "subcategory":"Adult Care",
            "type":"Services"
        }
    ],
    "sg:phone":"+1 414 448 0800",
    "sg:postcode":"53132",
    "sg:province":"WI",
    "sg:tags":[
        "home",
        "residential"
    ],
    "wof:name":"Harmony Of Brentwood Park",
    "wof:placetype":"venue"
},
  "geometry": {"coordinates":[-88.032991,42.893616],"type":"Point"}
}