{
  "type": "Feature",
  "properties": {
    "addr:full":"18345 Bolter Ln Brookfield WI 53045",
    "addr:housenumber":"18345",
    "addr:postcode":"53045",
    "addr:street":"Bolter Ln",
    "iso:country":"US",
    "sg:address":"18345 Bolter Ln",
    "sg:city":"Brookfield",
    "sg:classifiers":[
        {
            "category":"Building & Trades",
            "subcategory":"Construction",
            "type":"Services"
        }
    ],
    "sg:phone":"+1 262 523 1155",
    "sg:postcode":"53045",
    "sg:province":"WI",
    "sg:tags":[
        "house"
    ],
    "wof:name":"Shorebrock Inc",
    "wof:placetype":"venue"
},
  "geometry": {"coordinates":[-88.136814,43.068402],"type":"Point"}
}