{
  "type": "Feature",
  "properties": {
    "iso:country":"US",
    "sg:address":"852 Janesville St",
    "sg:city":"Oregon",
    "sg:classifiers":[
        {
            "category":"Food & Beverages",
            "subcategory":"Groceries & Convenience Stores",
            "type":"Retail Goods"
        },
        {
            "category":"Restaurant",
            "type":"Food & Drink"
        }
    ],
    "sg:phone":"+1 608 835 9829",
    "sg:postcode":"53575",
    "sg:province":"WI",
    "wof:name":"Sub Town Deli",
    "wof:placetype":"venue"
},
  "geometry": {"coordinates":[-89.374329,42.91828],"type":"Point"}
}