{
  "type": "Feature",
  "properties": {
    "iso:country":"US",
    "sg:address":"101 W 29th St",
    "sg:city":"Marshfield",
    "sg:classifiers":[
        {
            "category":"Organizations",
            "subcategory":"Non-profit Organization",
            "type":"Services"
        }
    ],
    "sg:phone":"+1 715 387 2748",
    "sg:postcode":"54449",
    "sg:province":"WI",
    "sg:tags":[
        "charitable",
        "institution"
    ],
    "wof:name":"Catholic Charities",
    "wof:placetype":"venue"
},
  "geometry": {"coordinates":[-90.18249900000001,44.641304],"type":"Point"}
}