{
  "type": "Feature",
  "properties": {
    "addr:full":"2221 Milton Ave Janesville WI 53545",
    "addr:housenumber":"2221",
    "addr:postcode":"53545",
    "addr:street":"Milton Ave",
    "iso:country":"US",
    "sg:address":"2221 Milton Ave",
    "sg:city":"Janesville",
    "sg:classifiers":[
        {
            "category":"Retail",
            "subcategory":"Auto Repair",
            "type":"Services"
        }
    ],
    "sg:phone":"+1 608 752 8166",
    "sg:postcode":"53545",
    "sg:province":"WI",
    "sg:tags":[
        "exhaust"
    ],
    "wof:name":"Midas Muffler",
    "wof:placetype":"venue"
},
  "geometry": {"coordinates":[-89.003666,42.708848],"type":"Point"}
}