{
  "type": "Feature",
  "properties": {
    "iso:country":"US",
    "sg:address":"1120 Center St",
    "sg:city":"Racine",
    "sg:classifiers":[
        {
            "category":"Real Estate",
            "subcategory":"Real Estate Services",
            "type":"Services"
        },
        {
            "category":"Real Estate",
            "subcategory":"Real Estate Operator",
            "type":"Services"
        }
    ],
    "sg:phone":"+1 262 632 6086",
    "sg:postcode":"53403",
    "sg:province":"WI",
    "sg:tags":[
        "vacancy",
        "apartment",
        "rental",
        "listing"
    ],
    "wof:name":"Saint Paul Gardens",
    "wof:placetype":"venue"
},
  "geometry": {"coordinates":[-87.789354,42.719318],"type":"Point"}
}