{
  "type": "Feature",
  "properties": {
    "iso:country":"US",
    "sg:address":"1022 Main St",
    "sg:city":"Oconto",
    "sg:classifiers":[
        {
            "category":"Food & Beverages",
            "subcategory":"Candy",
            "type":"Retail Goods"
        }
    ],
    "sg:phone":"+1 920 835 4923",
    "sg:postcode":"54153",
    "sg:province":"WI",
    "sg:tags":[
        "confectionery"
    ],
    "wof:name":"Grandma's Candy Cake & Cnfctns",
    "wof:placetype":"venue"
},
  "geometry": {"coordinates":[-87.868352,44.887837],"type":"Point"}
}