{
  "type": "Feature",
  "properties": {
    "iso:country":"US",
    "sg:address":"102 E 7th St",
    "sg:city":"Cochrane",
    "sg:classifiers":[
        {
            "category":"Home & Garden",
            "subcategory":"Building Materials",
            "type":"Retail Goods"
        }
    ],
    "sg:phone":"+1 608 248 2305",
    "sg:postcode":"54622",
    "sg:province":"WI",
    "sg:tags":[
        "lumber"
    ],
    "wof:name":"Cochrane Lumber",
    "wof:placetype":"venue"
},
  "geometry": {"coordinates":[-91.855832,44.228266],"type":"Point"}
}