{
  "type": "Feature",
  "properties": {
    "iso:country":"US",
    "sg:address":"4905 US Hwy 14",
    "sg:city":"Spring Green",
    "sg:classifiers":[
        {
            "category":"Autos & Motor Vehicles",
            "subcategory":"Fuel & Gas Station",
            "type":"Retail Goods"
        }
    ],
    "sg:phone":"+1 608 588 2465",
    "sg:postcode":"53588",
    "sg:province":"WI",
    "sg:tags":[
        "oil"
    ],
    "wof:name":"Riteway Plaza",
    "wof:placetype":"venue"
},
  "geometry": {"coordinates":[-90.073696,43.189621],"type":"Point"}
}