{
  "type": "Feature",
  "properties": {
    "iso:country":"US",
    "sg:address":"4695 W Greenfield Ave",
    "sg:city":"Milwaukee",
    "sg:classifiers":[
        {
            "category":"Professional",
            "subcategory":"Management & Consulting",
            "type":"Services"
        }
    ],
    "sg:phone":"+1 262 781 3817",
    "sg:postcode":"53214",
    "sg:province":"WI",
    "sg:tags":[
        "environmental"
    ],
    "wof:name":"Aaron L Hardt",
    "wof:placetype":"venue"
},
  "geometry": {"coordinates":[-87.97146,43.016755],"type":"Point"}
}