{
  "type": "Feature",
  "properties": {
    "addr:full":"800 S Washburn St Oshkosh WI 54904",
    "addr:housenumber":"800",
    "addr:postcode":"54904",
    "addr:street":"S Washburn St",
    "iso:country":"US",
    "sg:address":"800 S Washburn St",
    "sg:city":"Oshkosh",
    "sg:classifiers":[
        {
            "category":"Restaurant",
            "type":"Food & Drink"
        }
    ],
    "sg:menulink":"http://www.allmenus.com/wi/oshkosh/218343-burger-king/menu/",
    "sg:phone":"+1 414 235 2800",
    "sg:postcode":"54904",
    "sg:province":"WI",
    "sg:tags":[
        "american"
    ],
    "wof:name":"Burger King",
    "wof:placetype":"venue"
},
  "geometry": {"coordinates":[-88.584609,44.011726],"type":"Point"}
}