{
  "type": "Feature",
  "properties": {
    "iso:country":"US",
    "sg:address":"11228 S Union Rd",
    "sg:city":"Newton",
    "sg:classifiers":[
        {
            "category":"Farming",
            "subcategory":"Dairy Farm",
            "type":"Manufacturing & Wholesale Goods"
        }
    ],
    "sg:phone":"+1 920 726 4642",
    "sg:postcode":"53063",
    "sg:province":"WI",
    "wof:name":"K & K Jerseys",
    "wof:placetype":"venue"
},
  "geometry": {"coordinates":[-87.78190499999999,43.951658],"type":"Point"}
}