{
  "type": "Feature",
  "properties": {
    "addr:full":"14545 W Capitol Dr Brookfield WI 53005",
    "addr:housenumber":"14545",
    "addr:postcode":"53005",
    "addr:street":"W Capitol Dr",
    "iso:country":"US",
    "sg:address":"14545 W Capitol Dr",
    "sg:city":"Brookfield",
    "sg:classifiers":[
        {
            "category":"Shopping",
            "subcategory":"Jewelry",
            "type":"Retail Goods"
        },
        {
            "category":"Manufacturing",
            "subcategory":"Jewelry",
            "type":"Manufacturing & Wholesale Goods"
        }
    ],
    "sg:phone":"+1 262 373 0614",
    "sg:postcode":"53005",
    "sg:province":"WI",
    "sg:tags":[
        "repairing",
        "diamond",
        "jeweler"
    ],
    "wof:name":"Powers Goldsmith Shop LTD",
    "wof:placetype":"venue"
},
  "geometry": {"coordinates":[-88.094188,43.089515],"type":"Point"}
}