{
  "type": "Feature",
  "properties": {
    "iso:country":"US",
    "sg:address":"2029 Hegge Rd",
    "sg:city":"Westby",
    "sg:classifiers":[
        {
            "category":"Farming",
            "subcategory":"Dairy Farm",
            "type":"Manufacturing & Wholesale Goods"
        }
    ],
    "sg:phone":"+1 608 634 2630",
    "sg:postcode":"54667",
    "sg:province":"WI",
    "wof:name":"Roland Hoff",
    "wof:placetype":"venue"
},
  "geometry": {"coordinates":[-90.890022,43.65401],"type":"Point"}
}