{
  "type": "Feature",
  "properties": {
    "iso:country":"US",
    "sg:address":"520 Pleasant St",
    "sg:city":"Oshkosh",
    "sg:classifiers":[
        {
            "category":"Health Services",
            "subcategory":"Nursing And Care Facility",
            "type":"Services"
        }
    ],
    "sg:phone":"+1 920 233 4583",
    "sg:postcode":"54901",
    "sg:province":"WI",
    "sg:tags":[
        "personal"
    ],
    "wof:name":"Living Lghthuse Bayshore Manor",
    "wof:placetype":"venue"
},
  "geometry": {"coordinates":[-88.532954,44.021021],"type":"Point"}
}