{
  "type": "Feature",
  "properties": {
    "iso:country":"US",
    "sg:address":"3823 S 91st St",
    "sg:city":"Milwaukee",
    "sg:classifiers":[
        {
            "category":"Banks & Credit Unions",
            "subcategory":"Investment Brokerage",
            "type":"Services"
        }
    ],
    "sg:phone":"+1 414 321 8951",
    "sg:postcode":"53228",
    "sg:province":"WI",
    "sg:tags":[
        "advisory"
    ],
    "wof:name":"Oakmill Investments LLC",
    "wof:placetype":"venue"
},
  "geometry": {"coordinates":[-88.026495,42.97516],"type":"Point"}
}