{
  "type": "Feature",
  "properties": {
    "iso:country":"US",
    "sg:address":"2925 Washington Rd",
    "sg:city":"Kenosha",
    "sg:classifiers":[
        {
            "category":"Banks & Credit Unions",
            "subcategory":"Bank",
            "type":"Services"
        }
    ],
    "sg:phone":"+1 262 658 5300",
    "sg:postcode":"53140",
    "sg:province":"WI",
    "sg:tags":[
        "state"
    ],
    "wof:name":"Bank One",
    "wof:placetype":"venue"
},
  "geometry": {"coordinates":[-87.845444,42.602674],"type":"Point"}
}