{
  "type": "Feature",
  "properties": {
    "iso:country":"US",
    "sg:address":"1731 River Oaks Ct",
    "sg:city":"Mosinee",
    "sg:classifiers":[
        {
            "category":"Professional",
            "subcategory":"Business Services",
            "type":"Services"
        }
    ],
    "sg:phone":"+1 715 693 4160",
    "sg:postcode":"54455",
    "sg:province":"WI",
    "wof:name":"Intellihost Web Solutions",
    "wof:placetype":"venue"
},
  "geometry": {"coordinates":[-89.681543,44.830432],"type":"Point"}
}