{
  "type": "Feature",
  "properties": {
    "iso:country":"US",
    "sg:address":"9316 Klondike Dr",
    "sg:city":"Marshfield",
    "sg:classifiers":[
        {
            "category":"Wholesale",
            "subcategory":"Groceries",
            "type":"Manufacturing & Wholesale Goods"
        }
    ],
    "sg:phone":"+1 715 676 2110",
    "sg:postcode":"54449",
    "sg:province":"WI",
    "sg:tags":[
        "honey",
        "beekeeping",
        "syrup",
        "maple"
    ],
    "wof:name":"Honey Hauke Corp",
    "wof:placetype":"venue"
},
  "geometry": {"coordinates":[-90.170343,44.598123],"type":"Point"}
}