{
  "type": "Feature",
  "properties": {
    "addr:full":"104 South St Waunakee WI 53597",
    "addr:housenumber":"104",
    "addr:postcode":"53597",
    "addr:street":"South St",
    "iso:country":"US",
    "sg:address":"104 South St",
    "sg:city":"Waunakee",
    "sg:classifiers":[
        {
            "category":"Education",
            "subcategory":"Dance Studio",
            "type":"Public Place"
        }
    ],
    "sg:phone":"+1 608 273 9898",
    "sg:postcode":"53597",
    "sg:province":"WI",
    "sg:tags":[
        "instruction",
        "dancing"
    ],
    "wof:name":"Studio One Dance School",
    "wof:placetype":"venue"
},
  "geometry": {"coordinates":[-89.455181,43.190852],"type":"Point"}
}