{
  "type": "Feature",
  "properties": {
    "iso:country":"US",
    "sg:address":"716 S Ashland Ave",
    "sg:city":"Green Bay",
    "sg:classifiers":[
        {
            "category":"Banks & Credit Unions",
            "subcategory":"Investment Brokerage",
            "type":"Services"
        }
    ],
    "sg:phone":"+1 920 431 9005",
    "sg:postcode":"54304",
    "sg:province":"WI",
    "wof:name":"Prosperity Investment Experts",
    "wof:placetype":"venue"
},
  "geometry": {"coordinates":[-88.02991299999999,44.510864],"type":"Point"}
}