{
  "type": "Feature",
  "properties": {
    "iso:country":"US",
    "sg:address":"306 E Brooklyn St",
    "sg:city":"Chilton",
    "sg:classifiers":[
        {
            "category":"Retail",
            "subcategory":"Animal Services",
            "type":"Services"
        }
    ],
    "sg:phone":"+1 920 849 9834",
    "sg:postcode":"53014",
    "sg:province":"WI",
    "wof:name":"Pet Pals Professional Gro",
    "wof:placetype":"venue"
},
  "geometry": {"coordinates":[-88.154465,44.026089],"type":"Point"}
}