{
  "type": "Feature",
  "properties": {
    "iso:country":"US",
    "sg:address":"265 N Seymour St",
    "sg:city":"Fond Du Lac",
    "sg:classifiers":[
        {
            "category":"Personal",
            "subcategory":"Beauty Salon",
            "type":"Services"
        }
    ],
    "sg:phone":"+1 920 924 9050",
    "sg:postcode":"54935",
    "sg:province":"WI",
    "sg:tags":[
        "shop"
    ],
    "wof:name":"Odyssey Salon",
    "wof:placetype":"venue"
},
  "geometry": {"coordinates":[-88.46732900000001,43.7849],"type":"Point"}
}