{
  "type": "Feature",
  "properties": {
    "iso:country":"US",
    "sg:address":"2365 Woodland Park Dr",
    "sg:city":"Delafield",
    "sg:classifiers":[
        {
            "category":"Retail",
            "subcategory":"Portrait Studio",
            "type":"Services"
        }
    ],
    "sg:phone":"+1 262 646 2627",
    "sg:postcode":"53018",
    "sg:province":"WI",
    "sg:tags":[
        "photographer",
        "photo"
    ],
    "wof:name":"Gary Rupnow & Photography",
    "wof:placetype":"venue"
},
  "geometry": {"coordinates":[-88.397308,43.078366],"type":"Point"}
}