{
  "type": "Feature",
  "properties": {
    "addr:full":"6028 W Fond du Lac Ave Milwaukee WI 53218",
    "addr:housenumber":"6028",
    "addr:postcode":"53218",
    "addr:street":"W Fond Du Lac Ave",
    "iso:country":"US",
    "sg:address":"6028 W Fond du Lac Ave",
    "sg:city":"Milwaukee",
    "sg:classifiers":[
        {
            "category":"Autos & Motor Vehicles",
            "subcategory":"Fuel & Gas Station",
            "type":"Retail Goods"
        }
    ],
    "sg:phone":"+1 414 463 4020",
    "sg:postcode":"53218",
    "sg:province":"WI",
    "sg:tags":[
        "oil"
    ],
    "wof:name":"Northside Petroleum Inc",
    "wof:placetype":"venue"
},
  "geometry": {"coordinates":[-87.988905,43.099881],"type":"Point"}
}