{
  "type": "Feature",
  "properties": {
    "iso:country":"US",
    "sg:address":"826 Gohres St",
    "sg:city":"La Crosse",
    "sg:classifiers":[
        {
            "category":"Retail",
            "subcategory":"Auto Repair",
            "type":"Services"
        }
    ],
    "sg:phone":"+1 608 782 8755",
    "sg:postcode":"54603",
    "sg:province":"WI",
    "sg:tags":[
        "body"
    ],
    "wof:name":"Als Auto Body of La Crosse",
    "wof:placetype":"venue"
},
  "geometry": {"coordinates":[-91.24430599999999,43.849095],"type":"Point"}
}