{
  "type": "Feature",
  "properties": {
    "addr:full":"20803 State Hwy 60 Muscoda WI 53573",
    "addr:housenumber":"20803",
    "addr:postcode":"53573",
    "addr:street":"State Hwy 60",
    "iso:country":"US",
    "sg:address":"20803 State Hwy 60",
    "sg:city":"Muscoda",
    "sg:classifiers":[
        {
            "category":"Autos & Motor Vehicles",
            "subcategory":"Automobile Sales",
            "type":"Retail Goods"
        }
    ],
    "sg:phone":"+1 608 739 4242",
    "sg:postcode":"53573",
    "sg:province":"WI",
    "sg:tags":[
        "classic"
    ],
    "sg:website":"www.kensklassics.com",
    "wof:name":"Ken's Klassics",
    "wof:placetype":"venue"
},
  "geometry": {"coordinates":[-90.45557700000001,43.207159],"type":"Point"}
}