{
  "type": "Feature",
  "properties": {
    "iso:country":"US",
    "sg:address":"223 Kings Lynn Rd",
    "sg:city":"Stoughton",
    "sg:classifiers":[
        {
            "category":"Real Estate",
            "subcategory":"Real Estate Operator",
            "type":"Services"
        }
    ],
    "sg:phone":"+1 608 873 5197",
    "sg:postcode":"53589",
    "sg:province":"WI",
    "sg:tags":[
        "building",
        "apartment"
    ],
    "wof:name":"Olson Management",
    "wof:placetype":"venue"
},
  "geometry": {"coordinates":[-89.24056899999999,42.919379],"type":"Point"}
}