{
  "type": "Feature",
  "properties": {
    "iso:country":"US",
    "sg:address":"12091 W Line Rd",
    "sg:city":"Brownsville",
    "sg:classifiers":[
        {
            "category":"Farming",
            "subcategory":"Dairy Farm",
            "type":"Manufacturing & Wholesale Goods"
        }
    ],
    "sg:phone":"+1 920 583 3346",
    "sg:postcode":"53006",
    "sg:province":"WI",
    "wof:name":"Crestledge Farms LLC",
    "wof:placetype":"venue"
},
  "geometry": {"coordinates":[-88.521835,43.628009],"type":"Point"}
}