{
  "type": "Feature",
  "properties": {
    "iso:country":"US",
    "sg:address":"449 Van Horn St",
    "sg:city":"Berlin",
    "sg:classifiers":[
        {
            "category":"Wholesale",
            "subcategory":"Electrical",
            "type":"Manufacturing & Wholesale Goods"
        }
    ],
    "sg:phone":"+1 920 361 9985",
    "sg:postcode":"54923",
    "sg:province":"WI",
    "sg:tags":[
        "control",
        "security",
        "system"
    ],
    "wof:name":"TDS Security",
    "wof:placetype":"venue"
},
  "geometry": {"coordinates":[-88.959028,43.961238],"type":"Point"}
}