{
  "type": "Feature",
  "properties": {
    "iso:country":"US",
    "sg:address":"7840 N Faulkner Rd",
    "sg:city":"Milwaukee",
    "sg:classifiers":[
        {
            "category":"Building & Trades",
            "subcategory":"Equipment Rental",
            "type":"Services"
        }
    ],
    "sg:phone":"+1 414 354 2440",
    "sg:postcode":"53224",
    "sg:province":"WI",
    "sg:tags":[
        "leasing",
        "equipment-renting",
        "audio-visual"
    ],
    "wof:name":"American Audio Systems",
    "wof:placetype":"venue"
},
  "geometry": {"coordinates":[-88.020044,43.159653],"type":"Point"}
}