{
  "type": "Feature",
  "properties": {
    "iso:country":"US",
    "sg:address":"5960 Apache Rd",
    "sg:city":"Wild Rose",
    "sg:classifiers":[
        {
            "category":"Professional",
            "type":"Services"
        }
    ],
    "sg:phone":"+1 920 622 3212",
    "sg:postcode":"54984",
    "sg:province":"WI",
    "wof:name":"Steve Rodencal",
    "wof:placetype":"venue"
},
  "geometry": {"coordinates":[-89.18155,44.195537],"type":"Point"}
}