{
  "type": "Feature",
  "properties": {
    "iso:country":"US",
    "sg:address":"122 Arrowhead Dr",
    "sg:city":"Mukwonago",
    "sg:classifiers":[
        {
            "category":"Autos & Motor Vehicles",
            "subcategory":"Fuel & Gas Station",
            "type":"Retail Goods"
        }
    ],
    "sg:phone":"+1 262 363 2371",
    "sg:postcode":"53149",
    "sg:province":"WI",
    "sg:tags":[
        "oil"
    ],
    "wof:name":"Daybreak Too",
    "wof:placetype":"venue"
},
  "geometry": {"coordinates":[-88.322093,42.849198],"type":"Point"}
}