{
  "type": "Feature",
  "properties": {
    "iso:country":"US",
    "sg:address":"917 Chapin St",
    "sg:city":"Beloit",
    "sg:classifiers":[
        {
            "category":"Organizations",
            "subcategory":"Religious Organization",
            "type":"Services"
        }
    ],
    "sg:phone":"+1 608 365 0405",
    "sg:postcode":"53511",
    "sg:province":"IL",
    "sg:tags":[
        "church"
    ],
    "wof:name":"Latter-Day Saints",
    "wof:placetype":"venue"
},
  "geometry": {"coordinates":[-89.025628,42.503099],"type":"Point"}
}