{
  "type": "Feature",
  "properties": {
    "iso:country":"US",
    "sg:address":"1225 Whitewater Ave",
    "sg:city":"Fort Atkinson",
    "sg:classifiers":[
        {
            "category":"Autos & Motor Vehicles",
            "subcategory":"Automobile Sales",
            "type":"Retail Goods"
        }
    ],
    "sg:phone":"+1 920 568 1500",
    "sg:postcode":"53538",
    "sg:province":"WI",
    "sg:tags":[
        "car",
        "dealer"
    ],
    "wof:name":"J & L Motorsports",
    "wof:placetype":"venue"
},
  "geometry": {"coordinates":[-88.831902,42.913804],"type":"Point"}
}