{
  "type": "Feature",
  "properties": {
    "iso:country":"US",
    "sg:address":"909 E North Ave",
    "sg:city":"Milwaukee",
    "sg:classifiers":[
        {
            "category":"Social Services",
            "subcategory":"Child Care",
            "type":"Services"
        },
        {
            "category":"Community Center",
            "subcategory":"Youth",
            "type":"Public Place"
        },
        {
            "category":"Recreation",
            "type":"Entertainment"
        }
    ],
    "sg:phone":"+1 414 263 8383",
    "sg:postcode":"53212",
    "sg:province":"WI",
    "sg:tags":[
        "nursery",
        "day",
        "camps-recreational"
    ],
    "sg:website":"http://www.coa-yfc.org",
    "wof:name":"COA Youth & Family Centers",
    "wof:placetype":"venue"
},
  "geometry": {"coordinates":[-87.900361,43.060164],"type":"Point"}
}