{
  "type": "Feature",
  "properties": {
    "iso:country":"US",
    "sg:address":"11505 Co Rd V",
    "sg:city":"Lodi",
    "sg:classifiers":[
        {
            "category":"Food & Beverages",
            "subcategory":"Groceries & Convenience Stores",
            "type":"Retail Goods"
        },
        {
            "category":"Food & Beverages",
            "subcategory":"Liquor & Beverages",
            "type":"Retail Goods"
        }
    ],
    "sg:phone":"+1 608 592 4807",
    "sg:postcode":"53555",
    "sg:province":"WI",
    "sg:tags":[
        "alcoholic"
    ],
    "wof:name":"Mr Zip's Liquor & Grocery",
    "wof:placetype":"venue"
},
  "geometry": {"coordinates":[-89.572913,43.360092],"type":"Point"}
}