{
  "type": "Feature",
  "properties": {
    "addr:full":"2258 S Washington Rd Chilton WI 53014",
    "addr:housenumber":"2258",
    "addr:postcode":"53014",
    "addr:street":"S Washington Rd",
    "iso:country":"US",
    "sg:address":"2258 S Washington Rd",
    "sg:city":"Chilton",
    "sg:classifiers":[
        {
            "category":"Professional",
            "type":"Services"
        }
    ],
    "sg:phone":"+1 920 849 9571",
    "sg:postcode":"53014",
    "sg:province":"WI",
    "wof:name":"Didecisions LLC",
    "wof:placetype":"venue"
},
  "geometry": {"coordinates":[-88.170609,43.966558],"type":"Point"}
}