{
  "type": "Feature",
  "properties": {
    "addr:full":"1052 Claude St Menasha WI 54952",
    "addr:housenumber":"1052",
    "addr:postcode":"54952",
    "addr:street":"Claude St",
    "iso:country":"US",
    "sg:address":"1052 Claude St",
    "sg:city":"Menasha",
    "sg:classifiers":[
        {
            "category":"Building & Trades",
            "subcategory":"Electrical",
            "type":"Services"
        }
    ],
    "sg:phone":"+1 920 725 3823",
    "sg:postcode":"54952",
    "sg:province":"WI",
    "sg:tags":[
        "electric",
        "contractor"
    ],
    "wof:name":"Drath Electric Svc",
    "wof:placetype":"venue"
},
  "geometry": {"coordinates":[-88.432559,44.219127],"type":"Point"}
}