{
  "type": "Feature",
  "properties": {
    "iso:country":"US",
    "sg:address":"2684 S Madison Rd",
    "sg:city":"Beloit",
    "sg:classifiers":[
        {
            "category":"Building & Trades",
            "subcategory":"Cleaning & Sanitation",
            "type":"Services"
        }
    ],
    "sg:phone":"+1 608 362 7690",
    "sg:postcode":"53511",
    "sg:province":"WI",
    "sg:tags":[
        "maintenance"
    ],
    "wof:name":"Clear Vu Windows Inc",
    "wof:placetype":"venue"
},
  "geometry": {"coordinates":[-89.09536799999999,42.544223],"type":"Point"}
}