{
  "type": "Feature",
  "properties": {
    "iso:country":"US",
    "sg:address":"1104 Oak St",
    "sg:city":"Wisconsin Dells",
    "sg:classifiers":[
        {
            "category":"Food & Beverages",
            "subcategory":"Specialty",
            "type":"Retail Goods"
        }
    ],
    "sg:phone":"+1 608 254 7094",
    "sg:postcode":"53965",
    "sg:province":"WI",
    "wof:name":"Dell Vita Enterprise Inc",
    "wof:placetype":"venue"
},
  "geometry": {"coordinates":[-89.770673,43.633361],"type":"Point"}
}