{
  "type": "Feature",
  "properties": {
    "iso:country":"US",
    "sg:address":"7302 16th Ave",
    "sg:city":"Kenosha",
    "sg:classifiers":[
        {
            "category":"Building & Trades",
            "subcategory":"Cleaning & Sanitation",
            "type":"Services"
        }
    ],
    "sg:phone":"+1 262 657 4488",
    "sg:postcode":"53143",
    "sg:province":"WI",
    "sg:tags":[
        "maintenance"
    ],
    "wof:name":"Lisas Cleaning Service",
    "wof:placetype":"venue"
},
  "geometry": {"coordinates":[-87.82878700000001,42.56709],"type":"Point"}
}