{
  "type": "Feature",
  "properties": {
    "iso:country":"US",
    "sg:address":"1837 Park Ave",
    "sg:city":"Beloit",
    "sg:classifiers":[
        {
            "category":"Utilities",
            "subcategory":"Cable",
            "type":"Services"
        }
    ],
    "sg:phone":"+1 608 365 9555",
    "sg:postcode":"53511",
    "sg:province":"IL",
    "sg:tags":[
        "television",
        "station"
    ],
    "wof:name":"Time Warner",
    "wof:placetype":"venue"
},
  "geometry": {"coordinates":[-89.026698,42.524153],"type":"Point"}
}