{
  "type": "Feature",
  "properties": {
    "addr:full":"7340 W Greenfield Ave Milwaukee WI 53214",
    "addr:housenumber":"7340",
    "addr:postcode":"53214",
    "addr:street":"W Greenfield Ave",
    "iso:country":"US",
    "sg:address":"7340 W Greenfield Ave",
    "sg:city":"Milwaukee",
    "sg:classifiers":[
        {
            "category":"Professional",
            "subcategory":"Employment Agencies",
            "type":"Services"
        }
    ],
    "sg:phone":"+1 414 476 0270",
    "sg:postcode":"53214",
    "sg:province":"WI",
    "sg:tags":[
        "opportunity",
        "contractor"
    ],
    "sg:website":"http://www.ats-job.com",
    "wof:name":"American Technical Services Inc",
    "wof:placetype":"venue"
},
  "geometry": {"coordinates":[-88.004104,43.016682],"type":"Point"}
}