{
  "type": "Feature",
  "properties": {
    "addr:full":"310 E John St Rice Lake WI 54868",
    "addr:housenumber":"310",
    "addr:postcode":"54868",
    "addr:street":"E John St",
    "iso:country":"US",
    "sg:address":"310 E John St",
    "sg:city":"Rice Lake",
    "sg:classifiers":[
        {
            "category":"Retail",
            "subcategory":"Repair Shop",
            "type":"Services"
        }
    ],
    "sg:phone":"+1 715 234 1455",
    "sg:postcode":"54868",
    "sg:province":"WI",
    "wof:name":"Lake Area Satellite Antenna",
    "wof:placetype":"venue"
},
  "geometry": {"coordinates":[-91.729491,45.483691],"type":"Point"}
}