{
  "type": "Feature",
  "properties": {
    "iso:country":"US",
    "sg:address":"707 W Moreland Blvd",
    "sg:city":"Waukesha",
    "sg:classifiers":[
        {
            "category":"Health Services",
            "subcategory":"Doctor",
            "type":"Services"
        }
    ],
    "sg:phone":"+1 262 548 6022",
    "sg:postcode":"53188",
    "sg:province":"WI",
    "sg:tags":[
        "physician",
        "surgeon"
    ],
    "wof:name":"Metro Urology Group Sc",
    "wof:placetype":"venue"
},
  "geometry": {"coordinates":[-88.237858,43.024802],"type":"Point"}
}