{
  "type": "Feature",
  "properties": {
    "iso:country":"US",
    "sg:address":"2637 S Oneida St",
    "sg:city":"Appleton",
    "sg:classifiers":[
        {
            "category":"Personal",
            "type":"Services"
        }
    ],
    "sg:phone":"+1 920 830 8600",
    "sg:postcode":"54915",
    "sg:province":"WI",
    "sg:tags":[
        "consultant",
        "program",
        "health",
        "fitness"
    ],
    "wof:name":"Ultimate Fitness",
    "wof:placetype":"venue"
},
  "geometry": {"coordinates":[-88.40412000000001,44.238825],"type":"Point"}
}