{
  "type": "Feature",
  "properties": {
    "addr:full":"2062 Water Division Rd Green Bay WI 54311",
    "addr:housenumber":"2062",
    "addr:postcode":"54311",
    "addr:street":"Water Division Rd",
    "iso:country":"US",
    "sg:address":"2062 Water Division Rd",
    "sg:city":"Green Bay",
    "sg:classifiers":[
        {
            "category":"Freight",
            "type":"Transportation"
        }
    ],
    "sg:phone":"+1 920 863 5727",
    "sg:postcode":"54311",
    "sg:province":"WI",
    "sg:tags":[
        "operator",
        "trucking"
    ],
    "wof:name":"Nowak Trucking",
    "wof:placetype":"venue"
},
  "geometry": {"coordinates":[-87.81606499999999,44.464722],"type":"Point"}
}