{
  "type": "Feature",
  "properties": {
    "iso:country":"US",
    "sg:address":"10001 Co Rd F",
    "sg:city":"Milladore",
    "sg:classifiers":[
        {
            "category":"Retail",
            "subcategory":"Auto Repair",
            "type":"Services"
        }
    ],
    "sg:phone":"+1 715 652 2283",
    "sg:postcode":"54454",
    "sg:province":"WI",
    "sg:tags":[
        "general"
    ],
    "wof:name":"Eds Country Service LLC",
    "wof:placetype":"venue"
},
  "geometry": {"coordinates":[-89.91601799999999,44.612405],"type":"Point"}
}