{
  "type": "Feature",
  "properties": {
    "iso:country":"US",
    "sg:address":"3350 Hickey Rd",
    "sg:city":"Rhinelander",
    "sg:classifiers":[
        {
            "category":"Education",
            "subcategory":"School",
            "type":"Public Place"
        }
    ],
    "sg:phone":"+1 715 365 9160",
    "sg:postcode":"54501",
    "sg:province":"WI",
    "wof:name":"Pelican Elementary School",
    "wof:placetype":"venue"
},
  "geometry": {"coordinates":[-89.368211,45.624344],"type":"Point"}
}