{
  "type": "Feature",
  "properties": {
    "iso:country":"US",
    "sg:address":"1611 Janesville Ave",
    "sg:city":"Fort Atkinson",
    "sg:classifiers":[
        {
            "category":"Autos & Motor Vehicles",
            "subcategory":"Automobile Sales",
            "type":"Retail Goods"
        }
    ],
    "sg:phone":"+1 920 568 8161",
    "sg:postcode":"53538",
    "sg:province":"WI",
    "sg:tags":[
        "car",
        "dealer"
    ],
    "wof:name":"Mitchell Motors",
    "wof:placetype":"venue"
},
  "geometry": {"coordinates":[-88.853168,42.905129],"type":"Point"}
}