{
  "type": "Feature",
  "properties": {
    "iso:country":"US",
    "sg:address":"238 Westgate Mall",
    "sg:city":"Madison",
    "sg:classifiers":[
        {
            "category":"Recreation",
            "type":"Entertainment"
        }
    ],
    "sg:phone":"+1 608 273 4111",
    "sg:postcode":"53711",
    "sg:province":"WI",
    "wof:name":"Karate America",
    "wof:placetype":"venue"
},
  "geometry": {"coordinates":[-89.471979,43.051957],"type":"Point"}
}