{
  "type": "Feature",
  "properties": {
    "iso:country":"US",
    "sg:address":"3041 Summit Ave",
    "sg:city":"Waukesha",
    "sg:classifiers":[
        {
            "category":"Government",
            "subcategory":"Office",
            "type":"Public Place"
        }
    ],
    "sg:phone":"+1 262 524 3728",
    "sg:postcode":"53188",
    "sg:province":"WI",
    "sg:tags":[
        "village"
    ],
    "wof:name":"Waukesha Youth Sports Complex",
    "wof:placetype":"venue"
},
  "geometry": {"coordinates":[-88.270554,43.021169],"type":"Point"}
}