{
  "type": "Feature",
  "properties": {
    "iso:country":"US",
    "sg:address":"131 3rd St N",
    "sg:city":"Wisconsin Rapids",
    "sg:classifiers":[
        {
            "category":"Wholesale",
            "subcategory":"Auto Parts",
            "type":"Manufacturing & Wholesale Goods"
        }
    ],
    "sg:phone":"+1 715 423 2940",
    "sg:postcode":"54494",
    "sg:province":"WI",
    "sg:tags":[
        "automobile",
        "supply"
    ],
    "wof:name":"Auto Electric Co Inc",
    "wof:placetype":"venue"
},
  "geometry": {"coordinates":[-89.822565,44.391589],"type":"Point"}
}