{
  "type": "Feature",
  "properties": {
    "iso:country":"US",
    "sg:address":"7991 Robinson Rd",
    "sg:city":"Elroy",
    "sg:classifiers":[
        {
            "category":"Farming",
            "subcategory":"Dairy Farm",
            "type":"Manufacturing & Wholesale Goods"
        }
    ],
    "sg:phone":"+1 608 847 4144",
    "sg:postcode":"53929",
    "sg:province":"WI",
    "wof:name":"Golden Bluff Holsteins",
    "wof:placetype":"venue"
},
  "geometry": {"coordinates":[-90.167872,43.763901],"type":"Point"}
}