{
  "type": "Feature",
  "properties": {
    "iso:country":"US",
    "sg:address":"3940 N 63rd St",
    "sg:city":"Milwaukee",
    "sg:classifiers":[
        {
            "category":"Professional",
            "type":"Services"
        }
    ],
    "sg:phone":"+1 414 463 5094",
    "sg:postcode":"53216",
    "sg:province":"WI",
    "wof:name":"Earl C Ellis Crane Service",
    "wof:placetype":"venue"
},
  "geometry": {"coordinates":[-87.990728,43.0892],"type":"Point"}
}