{
  "type": "Feature",
  "properties": {
    "iso:country":"US",
    "sg:address":"8905 W Lincoln Ave",
    "sg:city":"Milwaukee",
    "sg:classifiers":[
        {
            "category":"Health Services",
            "subcategory":"Doctor",
            "type":"Services"
        }
    ],
    "sg:phone":"+1 414 329 5400",
    "sg:postcode":"53227",
    "sg:province":"WI",
    "sg:tags":[
        "gynecology",
        "physician",
        "surgeon",
        "surgeons",
        "obstetrics"
    ],
    "wof:name":"Leung Belinda MD",
    "wof:placetype":"venue"
},
  "geometry": {"coordinates":[-88.023507,43.002701],"type":"Point"}
}