{
  "type": "Feature",
  "properties": {
    "iso:country":"US",
    "sg:address":"6103 Morning View Ln",
    "sg:city":"Schofield",
    "sg:classifiers":[
        {
            "category":"Professional",
            "subcategory":"Detective & Security Services",
            "type":"Services"
        }
    ],
    "sg:phone":"+1 715 355 8930",
    "sg:postcode":"54476",
    "sg:province":"WI",
    "sg:tags":[
        "investigator"
    ],
    "wof:name":"Veenstra Inc",
    "wof:placetype":"venue"
},
  "geometry": {"coordinates":[-89.546767,44.913758],"type":"Point"}
}