{
  "type": "Feature",
  "properties": {
    "iso:country":"US",
    "sg:address":"5906 Christberg Rd",
    "sg:city":"Johnson Creek",
    "sg:classifiers":[
        {
            "category":"Farming",
            "subcategory":"Farm",
            "type":"Manufacturing & Wholesale Goods"
        }
    ],
    "sg:phone":"+1 920 699 2240",
    "sg:postcode":"53038",
    "sg:province":"WI",
    "sg:tags":[
        "crop",
        "general"
    ],
    "wof:name":"James J Linskens",
    "wof:placetype":"venue"
},
  "geometry": {"coordinates":[-88.747757,43.057212],"type":"Point"}
}