{
  "type": "Feature",
  "properties": {
    "iso:country":"US",
    "sg:address":"1111 Co Rd D",
    "sg:city":"Nekoosa",
    "sg:classifiers":[
        {
            "category":"Manufacturing",
            "subcategory":"Tools & Machinery",
            "type":"Manufacturing & Wholesale Goods"
        }
    ],
    "sg:phone":"+1 715 325 3343",
    "sg:postcode":"54457",
    "sg:province":"WI",
    "sg:tags":[
        "industrial",
        "mfg"
    ],
    "wof:name":"S & L Machine Corp",
    "wof:placetype":"venue"
},
  "geometry": {"coordinates":[-89.800012,44.220646],"type":"Point"}
}