{
  "type": "Feature",
  "properties": {
    "iso:country":"US",
    "sg:address":"12220 Lonzo Ln",
    "sg:city":"White Lake",
    "sg:classifiers":[
        {
            "category":"Retail",
            "subcategory":"Repair Shop",
            "type":"Services"
        }
    ],
    "sg:phone":"+1 715 276 9695",
    "sg:postcode":"54491",
    "sg:province":"WI",
    "wof:name":"Northland Services",
    "wof:placetype":"venue"
},
  "geometry": {"coordinates":[-88.617047,45.126715],"type":"Point"}
}