{
  "type": "Feature",
  "properties": {
    "iso:country":"US",
    "sg:address":"3034 270th Ave",
    "sg:city":"Maiden Rock",
    "sg:classifiers":[
        {
            "category":"Building & Trades",
            "subcategory":"Construction",
            "type":"Services"
        }
    ],
    "sg:phone":"+1 715 273 6062",
    "sg:postcode":"54750",
    "sg:province":"WI",
    "sg:tags":[
        "house"
    ],
    "wof:name":"Martin Tom Construction Inc",
    "wof:placetype":"venue"
},
  "geometry": {"coordinates":[-92.289716,44.635189],"type":"Point"}
}