{
  "type": "Feature",
  "properties": {
    "iso:country":"US",
    "sg:address":"1756 Berlin Rd",
    "sg:city":"Marshall",
    "sg:classifiers":[
        {
            "category":"Building & Trades",
            "subcategory":"Construction",
            "type":"Services"
        }
    ],
    "sg:phone":"+1 608 834 1954",
    "sg:postcode":"53559",
    "sg:province":"WI",
    "sg:tags":[
        "carpentry",
        "contractor"
    ],
    "wof:name":"Double D Country Woodworks",
    "wof:placetype":"venue"
},
  "geometry": {"coordinates":[-89.138092,43.188733],"type":"Point"}
}