{
  "type": "Feature",
  "properties": {
    "iso:country":"US",
    "sg:address":"1041 10th St S",
    "sg:city":"Wisconsin Rapids",
    "sg:classifiers":[
        {
            "category":"Organizations",
            "subcategory":"Religious Organization",
            "type":"Services"
        }
    ],
    "sg:phone":"+1 715 421 3137",
    "sg:postcode":"54494",
    "sg:province":"WI",
    "wof:name":"Christian Life Fellowship",
    "wof:placetype":"venue"
},
  "geometry": {"coordinates":[-89.81443400000001,44.382214],"type":"Point"}
}