{
  "type": "Feature",
  "properties": {
    "iso:country":"US",
    "sg:address":"5409 N Diversey Blvd",
    "sg:city":"Milwaukee",
    "sg:classifiers":[
        {
            "category":"Health Services",
            "subcategory":"Doctor",
            "type":"Services"
        }
    ],
    "sg:phone":"+1 414 332 3556",
    "sg:postcode":"53217",
    "sg:province":"WI",
    "wof:name":"I O Inc",
    "wof:placetype":"venue"
},
  "geometry": {"coordinates":[-87.904409,43.114444],"type":"Point"}
}