{
  "type": "Feature",
  "properties": {
    "iso:country":"US",
    "sg:address":"29856 279th St",
    "sg:city":"Holcombe",
    "sg:classifiers":[
        {
            "category":"Real Estate",
            "subcategory":"Real Estate Agent",
            "type":"Services"
        }
    ],
    "sg:phone":"+1 715 595 4030",
    "sg:postcode":"54745",
    "sg:province":"WI",
    "wof:name":"Lake Holcombe Commons",
    "wof:placetype":"venue"
},
  "geometry": {"coordinates":[-91.114918,45.279266],"type":"Point"}
}