{
  "type": "Feature",
  "properties": {
    "iso:country":"US",
    "sg:address":"6041 US Hwy 12",
    "sg:city":"Baraboo",
    "sg:classifiers":[
        {
            "category":"Freight",
            "type":"Transportation"
        }
    ],
    "sg:phone":"+1 608 355 9692",
    "sg:postcode":"53913",
    "sg:province":"WI",
    "sg:tags":[
        "trucking"
    ],
    "wof:name":"M & E Trucking",
    "wof:placetype":"venue"
},
  "geometry": {"coordinates":[-89.77306,43.427342],"type":"Point"}
}