{
  "type": "Feature",
  "properties": {
    "iso:country":"US",
    "sg:address":"3700 S Casper Dr",
    "sg:city":"New Berlin",
    "sg:classifiers":[
        {
            "category":"Education",
            "subcategory":"School",
            "type":"Public Place"
        }
    ],
    "sg:phone":"+1 262 786 2901",
    "sg:postcode":"53151",
    "sg:province":"WI",
    "sg:tags":[
        "organization",
        "religious",
        "secondary"
    ],
    "wof:name":"Star Bethlehem Lutheran School",
    "wof:placetype":"venue"
},
  "geometry": {"coordinates":[-88.117209,42.971985],"type":"Point"}
}