{
  "type": "Feature",
  "properties": {
    "iso:country":"US",
    "sg:address":"5585 Sugar Creek Rd",
    "sg:city":"Elkhorn",
    "sg:classifiers":[
        {
            "category":"Farming",
            "subcategory":"Farm",
            "type":"Manufacturing & Wholesale Goods"
        }
    ],
    "sg:phone":"+1 262 723 5365",
    "sg:postcode":"53121",
    "sg:province":"WI",
    "wof:name":"Mey-Villa Farm",
    "wof:placetype":"venue"
},
  "geometry": {"coordinates":[-88.57035500000001,42.698686],"type":"Point"}
}