{
  "type": "Feature",
  "properties": {
    "iso:country":"US",
    "sg:address":"7876 Hudson Rd",
    "sg:city":"Browntown",
    "sg:phone":"+1 608 325 2984",
    "sg:postcode":"53522",
    "sg:province":"WI",
    "sg:tags":[
        "farm",
        "corn",
        "soybean"
    ],
    "wof:name":"A Roland Emberson",
    "wof:placetype":"venue"
},
  "geometry": {"coordinates":[-89.748045,42.527236],"type":"Point"}
}