{
  "type": "Feature",
  "properties": {
    "iso:country":"US",
    "sg:address":"2209 S 109th St",
    "sg:city":"Milwaukee",
    "sg:classifiers":[
        {
            "category":"Wholesale",
            "subcategory":"Machinery & Supplies",
            "type":"Manufacturing & Wholesale Goods"
        }
    ],
    "sg:phone":"+1 414 327 2358",
    "sg:postcode":"53227",
    "sg:province":"WI",
    "sg:tags":[
        "equipment",
        "welding"
    ],
    "wof:name":"Tite-Spot Welders",
    "wof:placetype":"venue"
},
  "geometry": {"coordinates":[-88.048299,43.002741],"type":"Point"}
}