{
  "type": "Feature",
  "properties": {
    "iso:country":"US",
    "sg:address":"20865 Carrington Ct",
    "sg:city":"Brookfield",
    "sg:classifiers":[
        {
            "category":"Building & Trades",
            "subcategory":"Construction",
            "type":"Services"
        }
    ],
    "sg:phone":"+1 262 786 5528",
    "sg:postcode":"53045",
    "sg:province":"WI",
    "sg:tags":[
        "paving",
        "asphalt"
    ],
    "wof:name":"Cardinal Asphalt Paving",
    "wof:placetype":"venue"
},
  "geometry": {"coordinates":[-88.17266600000001,43.057717],"type":"Point"}
}