{
  "type": "Feature",
  "properties": {
    "addr:full":"3719 E Calumet St Appleton WI 54915",
    "addr:housenumber":"3719",
    "addr:postcode":"54915",
    "addr:street":"E Calumet St",
    "iso:country":"US",
    "sg:address":"3719 E Calumet St",
    "sg:city":"Appleton",
    "sg:classifiers":[
        {
            "category":"Restaurant",
            "type":"Food & Drink"
        }
    ],
    "sg:menulink":"http://www.allmenus.com/wi/appleton/215481-atlanta-bread-company/menu/",
    "sg:phone":"+1 920 882 3020",
    "sg:postcode":"54915",
    "sg:province":"WI",
    "sg:tags":[
        "american"
    ],
    "wof:name":"Atlanta Bread Company",
    "wof:placetype":"venue"
},
  "geometry": {"coordinates":[-88.366366,44.243871],"type":"Point"}
}