{
  "type": "Feature",
  "properties": {
    "iso:country":"US",
    "sg:address":"10453 McIntosh Rd",
    "sg:city":"Springbrook",
    "sg:classifiers":[
        {
            "category":"Home & Garden",
            "subcategory":"Garden Supply",
            "type":"Retail Goods"
        }
    ],
    "sg:phone":"+1 715 766 2028",
    "sg:postcode":"54875",
    "sg:province":"WI",
    "sg:tags":[
        "sprinkler",
        "machinery"
    ],
    "wof:name":"Rainmaker Irrigation Services",
    "wof:placetype":"venue"
},
  "geometry": {"coordinates":[-91.746215,46.003227],"type":"Point"}
}