{
  "type": "Feature",
  "properties": {
    "iso:country":"US",
    "sg:address":"110 E 3rd St N",
    "sg:city":"Ladysmith",
    "sg:classifiers":[
        {
            "category":"Real Estate",
            "subcategory":"Real Estate Services",
            "type":"Services"
        }
    ],
    "sg:phone":"+1 715 532 5404",
    "sg:postcode":"54848",
    "sg:province":"WI",
    "wof:name":"Rusk County Abstract Co",
    "wof:placetype":"venue"
},
  "geometry": {"coordinates":[-91.09813800000001,45.465183],"type":"Point"}
}