{
  "type": "Feature",
  "properties": {
    "addr:full":"1626 Elmira Ave Superior WI 54880",
    "addr:housenumber":"1626",
    "addr:postcode":"54880",
    "addr:street":"Elmira Ave",
    "iso:country":"US",
    "sg:address":"1626 Elmira Ave",
    "sg:city":"Superior",
    "sg:classifiers":[
        {
            "category":"Building & Trades",
            "subcategory":"Electrical",
            "type":"Services"
        }
    ],
    "sg:phone":"+1 715 395 5730",
    "sg:postcode":"54880",
    "sg:province":"WI",
    "sg:tags":[
        "electric",
        "contractor"
    ],
    "wof:name":"Billings Park Electric",
    "wof:placetype":"venue"
},
  "geometry": {"coordinates":[-92.114602,46.718522],"type":"Point"}
}