{
  "type": "Feature",
  "properties": {
    "addr:full":"333 1st St Menasha WI 54952",
    "addr:housenumber":"333",
    "addr:postcode":"54952",
    "addr:street":"1St St",
    "iso:country":"US",
    "sg:address":"333 1st St",
    "sg:city":"Menasha",
    "sg:classifiers":[
        {
            "category":"Professional",
            "subcategory":"Computer Services",
            "type":"Services"
        }
    ],
    "sg:phone":"+1 920 725 7726",
    "sg:postcode":"54952",
    "sg:province":"WI",
    "sg:tags":[
        "processing",
        "datum"
    ],
    "wof:name":"Medical AR Processing Inc",
    "wof:placetype":"venue"
},
  "geometry": {"coordinates":[-88.45010000000001,44.202885],"type":"Point"}
}