{
  "type": "Feature",
  "properties": {
    "iso:country":"US",
    "sg:address":"4125 N 124th St",
    "sg:city":"Brookfield",
    "sg:classifiers":[
        {
            "category":"Health Services",
            "subcategory":"Clinic",
            "type":"Services"
        },
        {
            "category":"Community Center",
            "type":"Public Place"
        },
        {
            "category":"Health Services",
            "subcategory":"Hospital",
            "type":"Services"
        }
    ],
    "sg:phone":"+1 262 790 4500",
    "sg:postcode":"53005",
    "sg:province":"WI",
    "sg:tags":[
        "medical",
        "sleep",
        "treatment",
        "disorders-information"
    ],
    "sg:website":"http://www.sleepmed.com",
    "wof:name":"Sleepmed Digitrace",
    "wof:placetype":"venue"
},
  "geometry": {"coordinates":[-88.066349,43.09057],"type":"Point"}
}