{
  "type": "Feature",
  "properties": {
    "iso:country":"US",
    "sg:address":"206 N Water St",
    "sg:city":"Albany",
    "sg:classifiers":[
        {
            "category":"Government",
            "subcategory":"Office",
            "type":"Public Place"
        }
    ],
    "sg:phone":"+1 608 862 3240",
    "sg:postcode":"53502",
    "sg:province":"WI",
    "sg:tags":[
        "village"
    ],
    "wof:name":"Albany Village Hall",
    "wof:placetype":"venue"
},
  "geometry": {"coordinates":[-89.440096,42.71112],"type":"Point"}
}