{
  "type": "Feature",
  "properties": {
    "iso:country":"US",
    "sg:address":"3980 Co Hwy H",
    "sg:city":"Fredonia",
    "sg:classifiers":[
        {
            "category":"Retail",
            "subcategory":"Auto Repair",
            "type":"Services"
        }
    ],
    "sg:phone":"+1 262 692 9660",
    "sg:postcode":"53021",
    "sg:province":"WI",
    "sg:tags":[
        "repairing",
        "automobile"
    ],
    "wof:name":"Fredonia Automotive",
    "wof:placetype":"venue"
},
  "geometry": {"coordinates":[-87.98412500000001,43.469678],"type":"Point"}
}