{
  "type": "Feature",
  "properties": {
    "iso:country":"US",
    "sg:address":"2266 N Prospect Ave",
    "sg:city":"Milwaukee",
    "sg:classifiers":[
        {
            "category":"Professional",
            "subcategory":"Lawyer & Legal Services",
            "type":"Services"
        }
    ],
    "sg:phone":"+1 414 224 8780",
    "sg:postcode":"53202",
    "sg:province":"WI",
    "sg:tags":[
        "attorney"
    ],
    "wof:name":"Atty Susan M Gramling",
    "wof:placetype":"venue"
},
  "geometry": {"coordinates":[-87.884048,43.059746],"type":"Point"}
}