{
  "type": "Feature",
  "properties": {
    "iso:country":"US",
    "sg:address":"3040 Bendamar Ln",
    "sg:city":"West Bend",
    "sg:classifiers":[
        {
            "category":"Freight",
            "type":"Transportation"
        }
    ],
    "sg:phone":"+1 262 338 8472",
    "sg:postcode":"53090",
    "sg:province":"WI",
    "sg:tags":[
        "operator",
        "local",
        "trucking"
    ],
    "wof:name":"Atlantis Trucking Inc",
    "wof:placetype":"venue"
},
  "geometry": {"coordinates":[-88.188515,43.460225],"type":"Point"}
}