{
  "type": "Feature",
  "properties": {
    "iso:country":"US",
    "sg:address":"215 W Pine St",
    "sg:city":"Platteville",
    "sg:classifiers":[
        {
            "category":"Organizations",
            "subcategory":"Religious Organization",
            "type":"Services"
        }
    ],
    "sg:phone":"+1 608 348 3022",
    "sg:postcode":"53818",
    "sg:province":"WI",
    "sg:website":"www.felc.org",
    "wof:name":"First English Lutheran Church",
    "wof:placetype":"venue"
},
  "geometry": {"coordinates":[-90.48145599999999,42.733567],"type":"Point"}
}