{
  "type": "Feature",
  "properties": {
    "iso:country":"US",
    "sg:address":"9925 Antioch Rd",
    "sg:city":"Salem",
    "sg:classifiers":[
        {
            "category":"Restaurant",
            "type":"Food & Drink"
        }
    ],
    "sg:phone":"+1 262 843 2169",
    "sg:postcode":"53168",
    "sg:province":"WI",
    "sg:tags":[
        "eating"
    ],
    "wof:name":"Ice Cream Man",
    "wof:placetype":"venue"
},
  "geometry": {"coordinates":[-88.100363,42.528001],"type":"Point"}
}