{
  "type": "Feature",
  "properties": {
    "iso:country":"US",
    "sg:address":"984 Main St",
    "sg:city":"Neenah",
    "sg:classifiers":[
        {
            "category":"Professional",
            "subcategory":"Credit Reporting & Collection",
            "type":"Services"
        }
    ],
    "sg:phone":"+1 920 721 5758",
    "sg:postcode":"54956",
    "sg:province":"WI",
    "wof:name":"Technical Services Credit Un",
    "wof:placetype":"venue"
},
  "geometry": {"coordinates":[-88.483054,44.189411],"type":"Point"}
}