{
  "type": "Feature",
  "properties": {
    "iso:country":"US",
    "sg:address":"9070 Spring Rd",
    "sg:city":"Fish Creek",
    "sg:classifiers":[
        {
            "category":"Professional",
            "subcategory":"Lawyer & Legal Services",
            "type":"Services"
        }
    ],
    "sg:phone":"+1 920 868 4130",
    "sg:postcode":"54212",
    "sg:province":"WI",
    "sg:tags":[
        "attorney"
    ],
    "wof:name":"Linda M Laarman Atty At Law",
    "wof:placetype":"venue"
},
  "geometry": {"coordinates":[-87.230013,45.112227],"type":"Point"}
}