{
  "type": "Feature",
  "properties": {
    "iso:country":"US",
    "sg:address":"350 Bus Park Dr",
    "sg:city":"Sun Prairie",
    "sg:classifiers":[
        {
            "category":"Professional",
            "subcategory":"Management & Consulting",
            "type":"Services"
        }
    ],
    "sg:phone":"+1 608 825 2171",
    "sg:postcode":"53590",
    "sg:province":"WI",
    "sg:tags":[
        "business"
    ],
    "wof:name":"A T C Associates",
    "wof:placetype":"venue"
},
  "geometry": {"coordinates":[-89.205336,43.201288],"type":"Point"}
}