{
  "type": "Feature",
  "properties": {
    "addr:full":"8082 Parnell Rd Cascade WI 53011",
    "addr:housenumber":"8082",
    "addr:postcode":"53011",
    "addr:street":"Parnell Rd",
    "iso:country":"US",
    "sg:address":"8082 Parnell Rd",
    "sg:city":"Cascade",
    "sg:classifiers":[
        {
            "category":"Professional",
            "type":"Services"
        }
    ],
    "sg:phone":"+1 920 528 7418",
    "sg:postcode":"53011",
    "sg:province":"WI",
    "wof:name":"Bs Embroidery LLC",
    "wof:placetype":"venue"
},
  "geometry": {"coordinates":[-88.07953999999999,43.659451],"type":"Point"}
}