{
  "type": "Feature",
  "properties": {
    "addr:full":"1124 22nd Dr S La Crosse WI 54601",
    "addr:housenumber":"1124",
    "addr:postcode":"54601",
    "addr:street":"22Nd Dr S",
    "iso:country":"US",
    "sg:address":"1124 22nd Dr S",
    "sg:city":"La Crosse",
    "sg:classifiers":[
        {
            "category":"Organizations",
            "subcategory":"Membership Organization",
            "type":"Services"
        }
    ],
    "sg:phone":"+1 608 787 0938",
    "sg:postcode":"54601",
    "sg:province":"WI",
    "wof:name":"National Assoc of Letter",
    "wof:placetype":"venue"
},
  "geometry": {"coordinates":[-91.222172,43.799699],"type":"Point"}
}