{
  "type": "Feature",
  "properties": {
    "iso:country":"US",
    "sg:address":"1124 17th Ave",
    "sg:city":"Monroe",
    "sg:classifiers":[
        {
            "category":"Professional",
            "subcategory":"Accounting & Tax Preparation",
            "type":"Services"
        }
    ],
    "sg:phone":"+1 608 328 8341",
    "sg:postcode":"53566",
    "sg:province":"WI",
    "sg:tags":[
        "accountant"
    ],
    "wof:name":"J T Mc Intosh Accounting",
    "wof:placetype":"venue"
},
  "geometry": {"coordinates":[-89.638489,42.600903],"type":"Point"}
}