{
  "type": "Feature",
  "properties": {
    "iso:country":"US",
    "sg:address":"129 W Brown Deer Rd",
    "sg:city":"Milwaukee",
    "sg:classifiers":[
        {
            "category":"Professional",
            "subcategory":"Business Services",
            "type":"Services"
        }
    ],
    "sg:phone":"+1 414 228 9877",
    "sg:postcode":"53217",
    "sg:province":"WI",
    "sg:tags":[
        "interior",
        "consultant",
        "design",
        "decorator"
    ],
    "wof:name":"Pam Kai Tollefson & Assoc",
    "wof:placetype":"venue"
},
  "geometry": {"coordinates":[-87.907969,43.176618],"type":"Point"}
}