{
  "type": "Feature",
  "properties": {
    "iso:country":"US",
    "sg:address":"3910 Lake Ave",
    "sg:city":"Wisconsin Rapids",
    "sg:classifiers":[
        {
            "category":"Professional",
            "subcategory":"Business Services",
            "type":"Services"
        }
    ],
    "sg:phone":"+1 715 423 8844",
    "sg:postcode":"54494",
    "sg:province":"WI",
    "sg:tags":[
        "water",
        "treatment"
    ],
    "wof:name":"Miller Water Conditioning Svc",
    "wof:placetype":"venue"
},
  "geometry": {"coordinates":[-89.778215,44.374952],"type":"Point"}
}