{
  "type": "Feature",
  "properties": {
    "iso:country":"US",
    "sg:address":"1510 David Ct",
    "sg:city":"Waukesha",
    "sg:classifiers":[
        {
            "category":"Professional",
            "type":"Services"
        }
    ],
    "sg:phone":"+1 262 513 8389",
    "sg:postcode":"53189",
    "sg:province":"WI",
    "wof:name":"Whuddleworld Inc",
    "wof:placetype":"venue"
},
  "geometry": {"coordinates":[-88.260349,42.986208],"type":"Point"}
}