{
  "type": "Feature",
  "properties": {
    "iso:country":"US",
    "sg:address":"1808 Co Rd U",
    "sg:city":"Plum City",
    "sg:classifiers":[
        {
            "category":"Building & Trades",
            "subcategory":"Construction",
            "type":"Services"
        }
    ],
    "sg:phone":"+1 715 647 3551",
    "sg:postcode":"54761",
    "sg:province":"WI",
    "sg:tags":[
        "excavating",
        "contractor"
    ],
    "wof:name":"Fleishauer Cat & Backhoe Svc",
    "wof:placetype":"venue"
},
  "geometry": {"coordinates":[-92.17456900000001,44.603167],"type":"Point"}
}