{
  "type": "Feature",
  "properties": {
    "iso:country":"US",
    "sg:address":"1700 Carl Becker Dr",
    "sg:city":"Racine",
    "sg:classifiers":[
        {
            "category":"Social Services",
            "subcategory":"Job Training",
            "type":"Services"
        }
    ],
    "sg:phone":"+1 262 635 3149",
    "sg:postcode":"53406",
    "sg:province":"WI",
    "sg:tags":[
        "rehabilitation"
    ],
    "wof:name":"Sun Dance Rehabilitation",
    "wof:placetype":"venue"
},
  "geometry": {"coordinates":[-87.84765,42.711225],"type":"Point"}
}