{
  "type": "Feature",
  "properties": {
    "iso:country":"US",
    "sg:address":"23577 State Rd 35",
    "sg:city":"Siren",
    "sg:classifiers":[
        {
            "category":"Building & Trades",
            "subcategory":"Construction",
            "type":"Services"
        }
    ],
    "sg:phone":"+1 715 349 7593",
    "sg:postcode":"54872",
    "sg:province":"WI",
    "sg:tags":[
        "masonry",
        "contractor"
    ],
    "wof:name":"Olson Concrete & Masonry",
    "wof:placetype":"venue"
},
  "geometry": {"coordinates":[-92.38085599999999,45.766865],"type":"Point"}
}