{
  "type": "Feature",
  "properties": {
    "addr:full":"717 S 26th St Manitowoc WI 54220",
    "addr:housenumber":"717",
    "addr:postcode":"54220",
    "addr:street":"S 26Th St",
    "iso:country":"US",
    "sg:address":"717 S 26th St",
    "sg:city":"Manitowoc",
    "sg:classifiers":[
        {
            "category":"Building & Trades",
            "subcategory":"Landscaping Services",
            "type":"Services"
        }
    ],
    "sg:phone":"+1 920 686 8299",
    "sg:postcode":"54220",
    "sg:province":"WI",
    "sg:tags":[
        "lawn",
        "maintenance",
        "grounds"
    ],
    "wof:name":"Wayne's World Of Lawn Care",
    "wof:placetype":"venue"
},
  "geometry": {"coordinates":[-87.680086,44.092703],"type":"Point"}
}