{
  "type": "Feature",
  "properties": {
    "iso:country":"US",
    "sg:address":"78 E Towne Mall",
    "sg:city":"Madison",
    "sg:classifiers":[
        {
            "category":"Recreation",
            "subcategory":"Arcade",
            "type":"Entertainment"
        }
    ],
    "sg:phone":"+1 608 246 0770",
    "sg:postcode":"53704",
    "sg:province":"WI",
    "sg:tags":[
        "device",
        "operator",
        "amusement"
    ],
    "wof:name":"Cyberstation",
    "wof:placetype":"venue"
},
  "geometry": {"coordinates":[-89.304429,43.128056],"type":"Point"}
}