{
  "type": "Feature",
  "properties": {
    "iso:country":"US",
    "sg:address":"1537 South St",
    "sg:city":"Racine",
    "sg:classifiers":[
        {
            "category":"Education",
            "subcategory":"Special Training",
            "type":"Public Place"
        }
    ],
    "sg:phone":"+1 262 752 9649",
    "sg:postcode":"53402",
    "sg:province":"WI",
    "sg:tags":[
        "for",
        "family",
        "child"
    ],
    "wof:name":"Sparkplug Education Program",
    "wof:placetype":"venue"
},
  "geometry": {"coordinates":[-87.801055,42.759043],"type":"Point"}
}