{
  "type": "Feature",
  "properties": {
    "iso:country":"US",
    "sg:address":"13378 Co Rd Z",
    "sg:city":"Darlington",
    "sg:classifiers":[
        {
            "category":"Farming",
            "subcategory":"Dairy Farm",
            "type":"Manufacturing & Wholesale Goods"
        }
    ],
    "sg:phone":"+1 608 776 2452",
    "sg:postcode":"53530",
    "sg:province":"WI",
    "wof:name":"Wayne Thompson",
    "wof:placetype":"venue"
},
  "geometry": {"coordinates":[-90.142809,42.686733],"type":"Point"}
}