{
  "type": "Feature",
  "properties": {
    "addr:full":"331 Cherrywood Ct Neenah WI 54956",
    "addr:housenumber":"331",
    "addr:postcode":"54956",
    "addr:street":"Cherrywood Ct",
    "iso:country":"US",
    "sg:address":"331 Cherrywood Ct",
    "sg:city":"Neenah",
    "sg:classifiers":[
        {
            "category":"Building & Trades",
            "subcategory":"Cleaning & Sanitation",
            "type":"Services"
        }
    ],
    "sg:phone":"+1 920 725 0258",
    "sg:postcode":"54956",
    "sg:province":"WI",
    "sg:tags":[
        "janitor"
    ],
    "wof:name":"In-Depth Cleaning Pros",
    "wof:placetype":"venue"
},
  "geometry": {"coordinates":[-88.471211,44.15471],"type":"Point"}
}