{
  "type": "Feature",
  "properties": {
    "iso:country":"US",
    "sg:address":"2600 N Mayfair Rd",
    "sg:city":"Milwaukee",
    "sg:classifiers":[
        {
            "category":"Professional",
            "subcategory":"Lawyer & Legal Services",
            "type":"Services"
        }
    ],
    "sg:phone":"+1 414 774 0750",
    "sg:postcode":"53222",
    "sg:province":"WI",
    "wof:name":"Adam C Essling",
    "wof:placetype":"venue"
},
  "geometry": {"coordinates":[-88.047627,43.061865],"type":"Point"}
}