{
  "type": "Feature",
  "properties": {
    "addr:full":"120 N Morrison St Appleton WI 54911",
    "addr:housenumber":"120",
    "addr:postcode":"54911",
    "addr:street":"N Morrison St",
    "iso:country":"US",
    "sg:address":"120 N Morrison St",
    "sg:city":"Appleton",
    "sg:classifiers":[
        {
            "category":"Organizations",
            "subcategory":"Membership Organization",
            "type":"Services"
        }
    ],
    "sg:phone":"+1 920 734 6233",
    "sg:postcode":"54911",
    "sg:province":"WI",
    "sg:tags":[
        "personal",
        "interest"
    ],
    "wof:name":"M A D D Upper Fox Valley",
    "wof:placetype":"venue"
},
  "geometry": {"coordinates":[-88.404251,44.26293],"type":"Point"}
}