{
  "type": "Feature",
  "properties": {
    "iso:country":"US",
    "sg:address":"2201 W Grant St",
    "sg:city":"Milwaukee",
    "sg:classifiers":[
        {
            "category":"Bars & Pubs",
            "type":"Food & Drink"
        }
    ],
    "sg:phone":"+1 414 672 7201",
    "sg:postcode":"53215",
    "sg:province":"WI",
    "sg:tags":[
        "drinking"
    ],
    "wof:name":"Club Vaquero",
    "wof:placetype":"venue"
},
  "geometry": {"coordinates":[-87.94162799999999,43.004844],"type":"Point"}
}