{
  "type": "Feature",
  "properties": {
    "iso:country":"US",
    "sg:address":"2044 N 25th St",
    "sg:city":"Milwaukee",
    "sg:classifiers":[
        {
            "category":"Social Services",
            "subcategory":"Child Care",
            "type":"Services"
        },
        {
            "category":"Social Services",
            "type":"Services"
        }
    ],
    "sg:phone":"+1 414 344 3488",
    "sg:postcode":"53205",
    "sg:province":"WI",
    "wof:name":"Dianna's Daycare",
    "wof:placetype":"venue"
},
  "geometry": {"coordinates":[-87.945005,43.05713],"type":"Point"}
}