{
  "type": "Feature",
  "properties": {
    "iso:country":"US",
    "sg:address":"15451 W Beloit Rd",
    "sg:city":"New Berlin",
    "sg:classifiers":[
        {
            "category":"Travel",
            "subcategory":"Hotels & Motels",
            "type":"Entertainment"
        }
    ],
    "sg:phone":"+1 262 787 0700",
    "sg:postcode":"53151",
    "sg:province":"WI",
    "wof:name":"Holiday Inn Express Milwaukee",
    "wof:placetype":"venue"
},
  "geometry": {"coordinates":[-88.105813,42.955759],"type":"Point"}
}