{
  "type": "Feature",
  "properties": {
    "iso:country":"US",
    "sg:address":"1035 Parker Dr",
    "sg:city":"Mauston",
    "sg:classifiers":[
        {
            "category":"Wholesale",
            "subcategory":"Jewelry",
            "type":"Manufacturing & Wholesale Goods"
        }
    ],
    "sg:phone":"+1 608 847 6443",
    "sg:postcode":"53948",
    "sg:province":"WI",
    "sg:tags":[
        "trophy"
    ],
    "wof:name":"Discount Trophy & Co",
    "wof:placetype":"venue"
},
  "geometry": {"coordinates":[-90.094889,43.804747],"type":"Point"}
}