{
  "type": "Feature",
  "properties": {
    "addr:full":"129 S Main St Lake Mills WI 53551",
    "addr:housenumber":"129",
    "addr:postcode":"53551",
    "addr:street":"S Main St",
    "iso:country":"US",
    "sg:address":"129 S Main St",
    "sg:city":"Lake Mills",
    "sg:classifiers":[
        {
            "category":"Organizations",
            "subcategory":"Community Association",
            "type":"Services"
        }
    ],
    "sg:phone":"+1 920 648 5115",
    "sg:postcode":"53551",
    "sg:province":"WI",
    "sg:tags":[
        "military"
    ],
    "wof:name":"American Legion",
    "wof:placetype":"venue"
},
  "geometry": {"coordinates":[-88.91306,43.078876],"type":"Point"}
}