{
  "type": "Feature",
  "properties": {
    "addr:full":"2583 S Superior St Milwaukee WI 53207",
    "addr:housenumber":"2583",
    "addr:postcode":"53207",
    "addr:street":"S Superior St",
    "iso:country":"US",
    "sg:address":"2583 S Superior St",
    "sg:city":"Milwaukee",
    "sg:classifiers":[
        {
            "category":"Professional",
            "subcategory":"Computer Services",
            "type":"Services"
        }
    ],
    "sg:phone":"+1 414 305 4364",
    "sg:postcode":"53207",
    "sg:province":"WI",
    "sg:tags":[
        "consultant",
        "designer",
        "system",
        "related"
    ],
    "wof:name":"Adamzit",
    "wof:placetype":"venue"
},
  "geometry": {"coordinates":[-87.887973,42.997745],"type":"Point"}
}