{
  "type": "Feature",
  "properties": {
    "iso:country":"US",
    "sg:address":"931 E Main St",
    "sg:city":"Madison",
    "sg:classifiers":[
        {
            "category":"Shopping",
            "type":"Retail Goods"
        }
    ],
    "sg:phone":"+1 608 257 2590",
    "sg:postcode":"53703",
    "sg:province":"WI",
    "sg:tags":[
        "craft",
        "gallery",
        "dealer"
    ],
    "sg:website":"www.guild.com",
    "wof:name":"GUILD.COM",
    "wof:placetype":"venue"
},
  "geometry": {"coordinates":[-89.370818,43.082268],"type":"Point"}
}