{
  "type": "Feature",
  "properties": {
    "addr:full":"1036 S Washington St Shawano WI 54166",
    "addr:housenumber":"1036",
    "addr:postcode":"54166",
    "addr:street":"S Washington St",
    "iso:country":"US",
    "sg:address":"1036 S Washington St",
    "sg:city":"Shawano",
    "sg:classifiers":[
        {
            "category":"Social Services",
            "subcategory":"Child Care",
            "type":"Services"
        }
    ],
    "sg:phone":"+1 715 526 2087",
    "sg:postcode":"54166",
    "sg:province":"WI",
    "sg:tags":[
        "day"
    ],
    "wof:name":"Sweet Peas Family Child Care",
    "wof:placetype":"venue"
},
  "geometry": {"coordinates":[-88.61009,44.767859],"type":"Point"}
}