{
  "type": "Feature",
  "properties": {
    "iso:country":"US",
    "sg:address":"5815 W Beloit Rd",
    "sg:city":"Milwaukee",
    "sg:classifiers":[
        {
            "category":"Restaurant",
            "type":"Food & Drink"
        }
    ],
    "sg:phone":"+1 414 541 5722",
    "sg:postcode":"53219",
    "sg:province":"WI",
    "sg:tags":[
        "eating"
    ],
    "wof:name":"Justforyou Catering",
    "wof:placetype":"venue"
},
  "geometry": {"coordinates":[-87.986032,43.009366],"type":"Point"}
}