{
  "type": "Feature",
  "properties": {
    "iso:country":"US",
    "sg:address":"9107 State Hwy 13",
    "sg:city":"South Range",
    "sg:classifiers":[
        {
            "category":"Building & Trades",
            "subcategory":"Construction",
            "type":"Services"
        }
    ],
    "sg:phone":"+1 715 364 2801",
    "sg:postcode":"54874",
    "sg:province":"WI",
    "sg:tags":[
        "residential"
    ],
    "wof:name":"Timber Construction",
    "wof:placetype":"venue"
},
  "geometry": {"coordinates":[-91.830722,46.64801],"type":"Point"}
}