{
  "type": "Feature",
  "properties": {
    "iso:country":"US",
    "sg:address":"648 130th St",
    "sg:city":"Amery",
    "sg:classifiers":[
        {
            "category":"Manufacturing",
            "subcategory":"Food",
            "type":"Manufacturing & Wholesale Goods"
        }
    ],
    "sg:phone":"+1 715 268 9496",
    "sg:postcode":"54001",
    "sg:province":"WI",
    "sg:tags":[
        "product",
        "mfg"
    ],
    "wof:name":"Bread Loafers Bakery",
    "wof:placetype":"venue"
},
  "geometry": {"coordinates":[-92.428784,45.302159],"type":"Point"}
}