{
  "type": "Feature",
  "properties": {
    "iso:country":"US",
    "sg:address":"400 Railroad St",
    "sg:city":"New Glarus",
    "sg:classifiers":[
        {
            "category":"Restaurant",
            "type":"Food & Drink"
        }
    ],
    "sg:phone":"+1 608 527 5322",
    "sg:postcode":"53574",
    "sg:province":"WI",
    "sg:tags":[
        "eating"
    ],
    "wof:name":"Whistle Stop Ice Cream Shop",
    "wof:placetype":"venue"
},
  "geometry": {"coordinates":[-89.632942,42.816303],"type":"Point"}
}