{
  "type": "Feature",
  "properties": {
    "iso:country":"US",
    "sg:address":"11807 Lax Chapel Rd",
    "sg:city":"Kiel",
    "sg:classifiers":[
        {
            "category":"Retail",
            "subcategory":"Auto Repair",
            "type":"Services"
        }
    ],
    "sg:phone":"+1 920 894 2134",
    "sg:postcode":"53042",
    "sg:province":"WI",
    "sg:tags":[
        "body",
        "automobile",
        "painting"
    ],
    "wof:name":"Joe's Auto Body",
    "wof:placetype":"venue"
},
  "geometry": {"coordinates":[-87.982507,43.963153],"type":"Point"}
}