{
  "type": "Feature",
  "properties": {
    "iso:country":"US",
    "sg:address":"1503 E Oklahoma Ave",
    "sg:city":"Milwaukee",
    "sg:classifiers":[
        {
            "category":"Bars & Pubs",
            "type":"Food & Drink"
        }
    ],
    "sg:phone":"+1 414 747 0644",
    "sg:postcode":"53207",
    "sg:province":"WI",
    "sg:tags":[
        "drinking"
    ],
    "wof:name":"Oklahoma Tap",
    "wof:placetype":"venue"
},
  "geometry": {"coordinates":[-87.88928799999999,42.988152],"type":"Point"}
}