{
  "type": "Feature",
  "properties": {
    "iso:country":"US",
    "sg:address":"2007 E Harmon Rd",
    "sg:city":"Lodi",
    "sg:classifiers":[
        {
            "category":"Farming",
            "subcategory":"Farm",
            "type":"Manufacturing & Wholesale Goods"
        }
    ],
    "sg:phone":"+1 608 592 5585",
    "sg:postcode":"53555",
    "sg:province":"WI",
    "sg:tags":[
        "crop",
        "general"
    ],
    "wof:name":"Schoepp Farms LLC",
    "wof:placetype":"venue"
},
  "geometry": {"coordinates":[-89.63066,43.341639],"type":"Point"}
}