{
  "type": "Feature",
  "properties": {
    "iso:country":"US",
    "sg:address":"5 Shefford Cir",
    "sg:city":"Madison",
    "sg:classifiers":[
        {
            "category":"Shopping",
            "subcategory":"Computers & Home Electronics",
            "type":"Retail Goods"
        }
    ],
    "sg:phone":"+1 608 277 7688",
    "sg:postcode":"53719",
    "sg:province":"WI",
    "sg:tags":[
        "software"
    ],
    "wof:name":"Affordable Computer Care",
    "wof:placetype":"venue"
},
  "geometry": {"coordinates":[-89.49989100000001,43.020964],"type":"Point"}
}