{
  "type": "Feature",
  "properties": {
    "iso:country":"US",
    "sg:address":"935 Cardinal Ln",
    "sg:city":"Green Bay",
    "sg:classifiers":[
        {
            "category":"Personal",
            "subcategory":"Beauty Salon",
            "type":"Services"
        }
    ],
    "sg:phone":"+1 920 434 0537",
    "sg:postcode":"54313",
    "sg:province":"WI",
    "wof:name":"Michael's Styling Ctr",
    "wof:placetype":"venue"
},
  "geometry": {"coordinates":[-88.084829,44.565699],"type":"Point"}
}