{
  "type": "Feature",
  "properties": {
    "addr:full":"2241 W Cortland Dr Appleton WI 54914",
    "addr:housenumber":"2241",
    "addr:postcode":"54914",
    "addr:street":"W Cortland Dr",
    "iso:country":"US",
    "sg:address":"2241 W Cortland Dr",
    "sg:city":"Appleton",
    "sg:classifiers":[
        {
            "category":"Professional",
            "subcategory":"Business Services",
            "type":"Services"
        }
    ],
    "sg:phone":"+1 920 954 1777",
    "sg:postcode":"54914",
    "sg:province":"WI",
    "wof:name":"D & W Enterprises",
    "wof:placetype":"venue"
},
  "geometry": {"coordinates":[-88.44153,44.279007],"type":"Point"}
}