{
  "type": "Feature",
  "properties": {
    "iso:country":"US",
    "sg:address":"11244 W National Ave",
    "sg:city":"Milwaukee",
    "sg:classifiers":[
        {
            "category":"Professional",
            "subcategory":"Business Services",
            "type":"Services"
        }
    ],
    "sg:phone":"+1 414 541 7057",
    "sg:postcode":"53227",
    "sg:province":"WI",
    "wof:name":"P M Escort Service",
    "wof:placetype":"venue"
},
  "geometry": {"coordinates":[-88.05415600000001,42.989809],"type":"Point"}
}