{
  "type": "Feature",
  "properties": {
    "iso:country":"US",
    "sg:address":"4640 S Howell Ave",
    "sg:city":"Milwaukee",
    "sg:classifiers":[
        {
            "category":"Shopping",
            "subcategory":"Bicycles & Sporting Goods",
            "type":"Retail Goods"
        }
    ],
    "sg:phone":"+1 414 481 2471",
    "sg:postcode":"53207",
    "sg:province":"WI",
    "wof:name":"Lakeshore Fisherman Sport",
    "wof:placetype":"venue"
},
  "geometry": {"coordinates":[-87.90958,42.960843],"type":"Point"}
}