{
  "type": "Feature",
  "properties": {
    "iso:country":"US",
    "sg:address":"12355 N Richardson Bay Rd",
    "sg:city":"Hayward",
    "sg:classifiers":[
        {
            "category":"Travel",
            "subcategory":"Hotels & Motels",
            "type":"Entertainment"
        }
    ],
    "sg:phone":"+1 715 462 3564",
    "sg:postcode":"54843",
    "sg:province":"WI",
    "sg:tags":[
        "resort"
    ],
    "wof:name":"Grand Pines Two Rounds Resort",
    "wof:placetype":"venue"
},
  "geometry": {"coordinates":[-91.31191699999999,45.99193],"type":"Point"}
}