{
  "type": "Feature",
  "properties": {
    "iso:country":"US",
    "sg:address":"710 260th St",
    "sg:city":"Woodville",
    "sg:classifiers":[
        {
            "category":"Building & Trades",
            "subcategory":"Landscaping Services",
            "type":"Services"
        }
    ],
    "sg:phone":"+1 715 698 2218",
    "sg:postcode":"54028",
    "sg:province":"WI",
    "wof:name":"Ron Anderson Building Co",
    "wof:placetype":"venue"
},
  "geometry": {"coordinates":[-92.277988,44.964357],"type":"Point"}
}