{
  "type": "Feature",
  "properties": {
    "iso:country":"US",
    "sg:address":"5676 Broad St",
    "sg:city":"Greendale",
    "sg:classifiers":[
        {
            "category":"Shopping",
            "subcategory":"Stationery & Office Supplies",
            "type":"Retail Goods"
        },
        {
            "category":"Wholesale",
            "subcategory":"Stationery",
            "type":"Manufacturing & Wholesale Goods"
        }
    ],
    "sg:phone":"+1 414 423 1782",
    "sg:postcode":"53129",
    "sg:province":"WI",
    "sg:tags":[
        "engravers-stationery",
        "announcement",
        "invitation"
    ],
    "wof:name":"Serendipity Design",
    "wof:placetype":"venue"
},
  "geometry": {"coordinates":[-87.99597799999999,42.940997],"type":"Point"}
}