{
  "type": "Feature",
  "properties": {
    "iso:country":"US",
    "sg:address":"3548 Lucia Crst",
    "sg:city":"Madison",
    "sg:classifiers":[
        {
            "category":"Manufacturing",
            "subcategory":"Chemicals & Compounds",
            "type":"Manufacturing & Wholesale Goods"
        }
    ],
    "sg:phone":"+1 608 218 1150",
    "sg:postcode":"53705",
    "sg:province":"WI",
    "sg:tags":[
        "soil",
        "making"
    ],
    "wof:name":"Soil Maker Enterprises",
    "wof:placetype":"venue"
},
  "geometry": {"coordinates":[-89.449725,43.073178],"type":"Point"}
}