{
  "type": "Feature",
  "properties": {
    "iso:country":"US",
    "sg:address":"321 12th Ave S",
    "sg:city":"Wisconsin Rapids",
    "sg:classifiers":[
        {
            "category":"Retail",
            "subcategory":"Veterinary Services",
            "type":"Services"
        }
    ],
    "sg:phone":"+1 715 421 2838",
    "sg:postcode":"54495",
    "sg:province":"WI",
    "sg:tags":[
        "hospital",
        "animal"
    ],
    "wof:name":"All Care Animal Hospital",
    "wof:placetype":"venue"
},
  "geometry": {"coordinates":[-89.838308,44.393279],"type":"Point"}
}