{
  "type": "Feature",
  "properties": {
    "iso:country":"US",
    "sg:address":"1140 Tullar Rd",
    "sg:city":"Neenah",
    "sg:classifiers":[
        {
            "category":"Organizations",
            "subcategory":"Religious Organization",
            "type":"Services"
        }
    ],
    "sg:phone":"+1 920 725 6822",
    "sg:postcode":"54956",
    "sg:province":"WI",
    "sg:tags":[
        "lutheran",
        "church"
    ],
    "sg:website":"www.gloriadeilc.org",
    "wof:name":"Gloria Dei Lutheran Church",
    "wof:placetype":"venue"
},
  "geometry": {"coordinates":[-88.495007,44.16509],"type":"Point"}
}