{
  "type": "Feature",
  "properties": {
    "iso:country":"US",
    "sg:address":"1612 Little Butternut Lake Ln",
    "sg:city":"Luck",
    "sg:classifiers":[
        {
            "category":"Building & Trades",
            "subcategory":"Construction",
            "type":"Services"
        }
    ],
    "sg:phone":"+1 715 472 2735",
    "sg:postcode":"54853",
    "sg:province":"WI",
    "sg:tags":[
        "excavating",
        "contractor"
    ],
    "wof:name":"Swerkstrom Excavating",
    "wof:placetype":"venue"
},
  "geometry": {"coordinates":[-92.489852,45.564449],"type":"Point"}
}