{
  "type": "Feature",
  "properties": {
    "addr:full":"1935 W Monroe St Milwaukee WI 53205",
    "addr:housenumber":"1935",
    "addr:postcode":"53205",
    "addr:street":"W Monroe St",
    "iso:country":"US",
    "sg:address":"1935 W Monroe St",
    "sg:city":"Milwaukee",
    "sg:classifiers":[
        {
            "category":"Personal",
            "subcategory":"Beauty Salon",
            "type":"Services"
        }
    ],
    "sg:phone":"+1 414 265 4428",
    "sg:postcode":"53205",
    "sg:province":"WI",
    "sg:tags":[
        "manicuring"
    ],
    "wof:name":"Joyce & Nails",
    "wof:placetype":"venue"
},
  "geometry": {"coordinates":[-87.937027,43.060309],"type":"Point"}
}