{
  "type": "Feature",
  "properties": {
    "addr:full":"6911 N Glen Shore Dr Milwaukee WI 53209",
    "addr:housenumber":"6911",
    "addr:postcode":"53209",
    "addr:street":"N Glen Shore Dr",
    "iso:country":"US",
    "sg:address":"6911 N Glen Shore Dr",
    "sg:city":"Milwaukee",
    "sg:classifiers":[
        {
            "category":"Professional",
            "type":"Services"
        }
    ],
    "sg:phone":"+1 414 351 0771",
    "sg:postcode":"53209",
    "sg:province":"WI",
    "wof:name":"Write Place Calligraphy",
    "wof:placetype":"venue"
},
  "geometry": {"coordinates":[-87.938108,43.141138],"type":"Point"}
}