{
  "type": "Feature",
  "properties": {
    "iso:country":"US",
    "sg:address":"12740 N River Rd",
    "sg:city":"Mequon",
    "sg:classifiers":[
        {
            "category":"Professional",
            "subcategory":"Management & Consulting",
            "type":"Services"
        }
    ],
    "sg:phone":"+1 262 512 9000",
    "sg:postcode":"53092",
    "sg:province":"WI",
    "sg:tags":[
        "marketing",
        "program"
    ],
    "wof:name":"Mosik",
    "wof:placetype":"venue"
},
  "geometry": {"coordinates":[-87.963803,43.248614],"type":"Point"}
}