{
  "type": "Feature",
  "properties": {
    "iso:country":"US",
    "sg:address":"19304 74th Ave",
    "sg:city":"Chippewa Falls",
    "sg:classifiers":[
        {
            "category":"Professional",
            "subcategory":"Management & Consulting",
            "type":"Services"
        }
    ],
    "sg:phone":"+1 715 720 2542",
    "sg:postcode":"54729",
    "sg:province":"WI",
    "sg:tags":[
        "marketing",
        "consultant"
    ],
    "wof:name":"American Solutions-Business",
    "wof:placetype":"venue"
},
  "geometry": {"coordinates":[-91.276917,44.946525],"type":"Point"}
}