{
  "type": "Feature",
  "properties": {
    "iso:country":"US",
    "sg:address":"111 N Jefferson St",
    "sg:city":"Green Bay",
    "sg:classifiers":[
        {
            "category":"Health Services",
            "subcategory":"Hospital",
            "type":"Services"
        }
    ],
    "sg:phone":"+1 920 448 4425",
    "sg:postcode":"54301",
    "sg:province":"WI",
    "sg:tags":[
        "mental"
    ],
    "wof:name":"Brown County Community Trtmnt",
    "wof:placetype":"venue"
},
  "geometry": {"coordinates":[-88.01274100000001,44.51421],"type":"Point"}
}