{
  "type": "Feature",
  "properties": {
    "iso:country":"US",
    "sg:address":"913 Hampshire Pl",
    "sg:city":"Madison",
    "sg:classifiers":[
        {
            "category":"Professional",
            "type":"Services"
        }
    ],
    "sg:phone":"+1 608 270 9634",
    "sg:postcode":"53711",
    "sg:province":"WI",
    "wof:name":"Rudolph Tod",
    "wof:placetype":"venue"
},
  "geometry": {"coordinates":[-89.481872,43.044932],"type":"Point"}
}