{
  "type": "Feature",
  "properties": {
    "iso:country":"US",
    "sg:address":"135 Stoney Brook Rd",
    "sg:city":"Appleton",
    "sg:classifiers":[
        {
            "category":"Food & Beverages",
            "subcategory":"Groceries & Convenience Stores",
            "type":"Retail Goods"
        }
    ],
    "sg:phone":"+1 920 997 0232",
    "sg:postcode":"54915",
    "sg:province":"WI",
    "sg:tags":[
        "grocer"
    ],
    "wof:name":"Pick'n Save",
    "wof:placetype":"venue"
},
  "geometry": {"coordinates":[-88.352105,44.25208],"type":"Point"}
}