{
  "type": "Feature",
  "properties": {
    "iso:country":"US",
    "sg:address":"410 N River St",
    "sg:city":"Spooner",
    "sg:classifiers":[
        {
            "category":"Professional",
            "subcategory":"Computer Services",
            "type":"Services"
        }
    ],
    "sg:phone":"+1 715 635 3971",
    "sg:postcode":"54801",
    "sg:province":"WI",
    "sg:tags":[
        "repair"
    ],
    "wof:name":"Spooner PC LLC",
    "wof:placetype":"venue"
},
  "geometry": {"coordinates":[-91.888511,45.826086],"type":"Point"}
}