{
  "type": "Feature",
  "properties": {
    "iso:country":"US",
    "sg:address":"6414 Brady Rd",
    "sg:city":"Bancroft",
    "sg:phone":"+1 715 366 2424",
    "sg:postcode":"54921",
    "sg:province":"WI",
    "sg:tags":[
        "farm",
        "irish",
        "potato"
    ],
    "wof:name":"Patrykus Farms Inc",
    "wof:placetype":"venue"
},
  "geometry": {"coordinates":[-89.457506,44.312973],"type":"Point"}
}