{
  "type": "Feature",
  "properties": {
    "iso:country":"US",
    "sg:address":"144 N 60th St",
    "sg:city":"Milwaukee",
    "sg:classifiers":[
        {
            "category":"Building & Trades",
            "subcategory":"Cleaning & Sanitation",
            "type":"Services"
        }
    ],
    "sg:phone":"+1 414 774 5353",
    "sg:postcode":"53213",
    "sg:province":"WI",
    "sg:tags":[
        "venetian",
        "blind"
    ],
    "wof:name":"White Glove Ultra-Sonic Blind",
    "wof:placetype":"venue"
},
  "geometry": {"coordinates":[-87.987425,43.032766],"type":"Point"}
}