{
  "type": "Feature",
  "properties": {
    "addr:full":"4928 Green Bay Rd Kenosha WI 53144",
    "addr:housenumber":"4928",
    "addr:postcode":"53144",
    "addr:street":"Green Bay Rd",
    "iso:country":"US",
    "sg:address":"4928 Green Bay Rd",
    "sg:city":"Kenosha",
    "sg:classifiers":[
        {
            "category":"Personal",
            "subcategory":"Beauty Salon",
            "type":"Services"
        }
    ],
    "sg:phone":"+1 262 654 4152",
    "sg:postcode":"53144",
    "sg:province":"WI",
    "sg:tags":[
        "electrolysis",
        "hairdresser"
    ],
    "wof:name":"Esthers Buty Slon Electrolysis",
    "wof:placetype":"venue"
},
  "geometry": {"coordinates":[-87.88240399999999,42.588818],"type":"Point"}
}