{
  "type": "Feature",
  "properties": {
    "iso:country":"US",
    "sg:address":"3189 Mortinson Ln",
    "sg:city":"Peshtigo",
    "sg:classifiers":[
        {
            "category":"Real Estate",
            "subcategory":"Real Estate Operator",
            "type":"Services"
        }
    ],
    "sg:phone":"+1 715 789 2262",
    "sg:postcode":"54157",
    "sg:province":"WI",
    "sg:tags":[
        "farm",
        "property",
        "dairy",
        "lessor"
    ],
    "wof:name":"Clarence Mortinson",
    "wof:placetype":"venue"
},
  "geometry": {"coordinates":[-87.820133,45.073304],"type":"Point"}
}