{
  "type": "Feature",
  "properties": {
    "iso:country":"US",
    "sg:address":"1412 Nixon Ave",
    "sg:city":"Eau Claire",
    "sg:classifiers":[
        {
            "category":"Professional",
            "subcategory":"Business Services",
            "type":"Services"
        }
    ],
    "sg:phone":"+1 715 839 0522",
    "sg:postcode":"54701",
    "sg:province":"WI",
    "wof:name":"Success Enterprises Inc",
    "wof:placetype":"venue"
},
  "geometry": {"coordinates":[-91.479644,44.787635],"type":"Point"}
}