{
  "type": "Feature",
  "properties": {
    "iso:country":"US",
    "sg:address":"14709 Roosevelt Dr",
    "sg:city":"Thorp",
    "sg:classifiers":[
        {
            "category":"Professional",
            "type":"Services"
        }
    ],
    "sg:phone":"+1 715 669 5250",
    "sg:postcode":"54771",
    "sg:province":"WI",
    "wof:name":"Jason Stuner",
    "wof:placetype":"venue"
},
  "geometry": {"coordinates":[-90.795101,45.053299],"type":"Point"}
}