{
  "type": "Feature",
  "properties": {
    "addr:full":"780 Pilgrim Pkwy Elm Grove WI 53122",
    "addr:housenumber":"780",
    "addr:postcode":"53122",
    "addr:street":"Pilgrim Pkwy;Grove",
    "iso:country":"US",
    "sg:address":"780 Pilgrim Pkwy",
    "sg:city":"Elm Grove",
    "sg:classifiers":[
        {
            "category":"Manufacturing",
            "subcategory":"Printing",
            "type":"Manufacturing & Wholesale Goods"
        }
    ],
    "sg:phone":"+1 262 786 0352",
    "sg:postcode":"53122",
    "sg:province":"WI",
    "sg:tags":[
        "lithographer"
    ],
    "wof:name":"Worzalla Publishing Co",
    "wof:placetype":"venue"
},
  "geometry": {"coordinates":[-88.10610800000001,43.041729],"type":"Point"}
}