{
  "type": "Feature",
  "properties": {
    "addr:full":"495 S Green Bay Rd Neenah WI 54956",
    "addr:housenumber":"495",
    "addr:postcode":"54956",
    "addr:street":"S Green Bay Rd",
    "iso:country":"US",
    "sg:address":"495 S Green Bay Rd",
    "sg:city":"Neenah",
    "sg:classifiers":[
        {
            "category":"Travel",
            "subcategory":"Hotels & Motels",
            "type":"Entertainment"
        }
    ],
    "sg:phone":"+1 920 720 9020",
    "sg:postcode":"54956",
    "sg:province":"WI",
    "sg:tags":[
        "operation"
    ],
    "wof:name":"Days Inn",
    "wof:placetype":"venue"
},
  "geometry": {"coordinates":[-88.48515399999999,44.179581],"type":"Point"}
}