{
  "type": "Feature",
  "properties": {
    "iso:country":"US",
    "sg:address":"7000 W Greenfield Ave",
    "sg:city":"Milwaukee",
    "sg:classifiers":[
        {
            "category":"Banks & Credit Unions",
            "subcategory":"Bank",
            "type":"Services"
        }
    ],
    "sg:phone":"+1 414 476 0900",
    "sg:postcode":"53214",
    "sg:province":"WI",
    "sg:tags":[
        "state",
        "commercial",
        "national"
    ],
    "wof:name":"M & I Marshall & Ilsley Bank",
    "wof:placetype":"venue"
},
  "geometry": {"coordinates":[-88.00131399999999,43.016667],"type":"Point"}
}