{
  "type": "Feature",
  "properties": {
    "iso:country":"US",
    "sg:address":"1431 US Hwy 51 N",
    "sg:city":"Woodruff",
    "sg:classifiers":[
        {
            "category":"Travel",
            "subcategory":"Hotels & Motels",
            "type":"Entertainment"
        }
    ],
    "sg:phone":"+1 715 356 3393",
    "sg:postcode":"54568",
    "sg:province":"WI",
    "wof:name":"Arbor Vitae Motel",
    "wof:placetype":"venue"
},
  "geometry": {"coordinates":[-89.69556799999999,45.921637],"type":"Point"}
}