{
  "type": "Feature",
  "properties": {
    "iso:country":"US",
    "sg:address":"5075 S 76th St",
    "sg:city":"Milwaukee",
    "sg:classifiers":[
        {
            "category":"Shopping",
            "subcategory":"Jewelry",
            "type":"Retail Goods"
        }
    ],
    "sg:phone":"+1 414 325 9800",
    "sg:postcode":"53220",
    "sg:province":"WI",
    "sg:tags":[
        "jeweler"
    ],
    "wof:name":"Kesslers Diamond Ctr",
    "wof:placetype":"venue"
},
  "geometry": {"coordinates":[-88.00847400000001,42.953378],"type":"Point"}
}