{
  "type": "Feature",
  "properties": {
    "iso:country":"US",
    "sg:address":"4204 Merrimac Way",
    "sg:city":"Oneida",
    "sg:classifiers":[
        {
            "category":"Building & Trades",
            "subcategory":"Construction",
            "type":"Services"
        }
    ],
    "sg:phone":"+1 920 499 8081",
    "sg:postcode":"54155",
    "sg:province":"WI",
    "sg:tags":[
        "house"
    ],
    "wof:name":"Urben Builder LLC",
    "wof:placetype":"venue"
},
  "geometry": {"coordinates":[-88.128467,44.542564],"type":"Point"}
}