{
  "type": "Feature",
  "properties": {
    "iso:country":"US",
    "sg:address":"2741 S Herman St",
    "sg:city":"Milwaukee",
    "sg:classifiers":[
        {
            "category":"Real Estate",
            "subcategory":"Real Estate Agent",
            "type":"Services"
        }
    ],
    "sg:phone":"+1 414 803 9213",
    "sg:postcode":"53207",
    "sg:province":"WI",
    "wof:name":"Molly",
    "wof:placetype":"venue"
},
  "geometry": {"coordinates":[-87.895611,42.994361],"type":"Point"}
}