{
  "type": "Feature",
  "properties": {
    "iso:country":"US",
    "sg:address":"605 E Bronson Rd",
    "sg:city":"Seymour",
    "sg:classifiers":[
        {
            "category":"Social Services",
            "subcategory":"Adult Care",
            "type":"Services"
        }
    ],
    "sg:phone":"+1 920 833 1566",
    "sg:postcode":"54165",
    "sg:province":"WI",
    "sg:tags":[
        "residential"
    ],
    "wof:name":"Meadow Wood Residential Care",
    "wof:placetype":"venue"
},
  "geometry": {"coordinates":[-88.32971,44.522426],"type":"Point"}
}