{
  "type": "Feature",
  "properties": {
    "iso:country":"US",
    "sg:address":"117 S Butler St",
    "sg:city":"Madison",
    "sg:classifiers":[
        {
            "category":"Bars & Pubs",
            "type":"Food & Drink"
        }
    ],
    "sg:phone":"+1 608 257 1176",
    "sg:postcode":"53703",
    "sg:province":"WI",
    "sg:tags":[
        "drinking"
    ],
    "wof:name":"Kenneth Burns",
    "wof:placetype":"venue"
},
  "geometry": {"coordinates":[-89.37855999999999,43.07487],"type":"Point"}
}