{
  "type": "Feature",
  "properties": {
    "iso:country":"US",
    "sg:address":"9534 Union Rd",
    "sg:city":"Platteville",
    "sg:classifiers":[
        {
            "category":"Farming",
            "subcategory":"Dairy Farm",
            "type":"Manufacturing & Wholesale Goods"
        }
    ],
    "sg:phone":"+1 608 348 3477",
    "sg:postcode":"53818",
    "sg:province":"WI",
    "wof:name":"David Danz",
    "wof:placetype":"venue"
},
  "geometry": {"coordinates":[-90.525122,42.85471],"type":"Point"}
}