{
  "type": "Feature",
  "properties": {
    "iso:country":"US",
    "sg:address":"2908 Gruenhagen Rd",
    "sg:city":"Birchwood",
    "sg:classifiers":[
        {
            "category":"Travel",
            "subcategory":"Hotels & Motels",
            "type":"Entertainment"
        }
    ],
    "sg:phone":"+1 715 354 3713",
    "sg:postcode":"54817",
    "sg:province":"WI",
    "sg:tags":[
        "resort"
    ],
    "wof:name":"Gruenhagen Bay Resort",
    "wof:placetype":"venue"
},
  "geometry": {"coordinates":[-91.678394,45.681984],"type":"Point"}
}