{
  "type": "Feature",
  "properties": {
    "iso:country":"US",
    "sg:address":"912 N Central Ave",
    "sg:city":"Marshfield",
    "sg:classifiers":[
        {
            "category":"Autos & Motor Vehicles",
            "subcategory":"Automobile Sales",
            "type":"Retail Goods"
        }
    ],
    "sg:phone":"+1 715 384 9858",
    "sg:postcode":"54449",
    "sg:province":"WI",
    "sg:tags":[
        "car",
        "used",
        "truck",
        "dealer"
    ],
    "wof:name":"Davis Auto Sales & Service",
    "wof:placetype":"venue"
},
  "geometry": {"coordinates":[-90.166466,44.677006],"type":"Point"}
}