{
  "type": "Feature",
  "properties": {
    "iso:country":"US",
    "sg:address":"1806 E North Ave",
    "sg:city":"Milwaukee",
    "sg:classifiers":[
        {
            "category":"Bars & Pubs",
            "type":"Food & Drink"
        }
    ],
    "sg:phone":"+1 414 271 2874",
    "sg:postcode":"53202",
    "sg:province":"WI",
    "sg:tags":[
        "bar"
    ],
    "wof:name":"Cush Lounge",
    "wof:placetype":"venue"
},
  "geometry": {"coordinates":[-87.887988,43.060194],"type":"Point"}
}