{
  "type": "Feature",
  "properties": {
    "iso:country":"US",
    "sg:address":"4200 Calumet Ave",
    "sg:city":"Manitowoc",
    "sg:classifiers":[
        {
            "category":"Health Services",
            "subcategory":"Nursing And Care Facility",
            "type":"Services"
        }
    ],
    "sg:phone":"+1 920 683 4100",
    "sg:postcode":"54220",
    "sg:province":"WI",
    "sg:tags":[
        "home",
        "convalescent"
    ],
    "wof:name":"Manitowoc Health Care Ctr",
    "wof:placetype":"venue"
},
  "geometry": {"coordinates":[-87.701187,44.075123],"type":"Point"}
}