{
  "type": "Feature",
  "properties": {
    "iso:country":"US",
    "sg:address":"5803 Haumschild Ln",
    "sg:city":"Johnson Creek",
    "sg:classifiers":[
        {
            "category":"Manufacturing",
            "subcategory":"Tools & Machinery",
            "type":"Manufacturing & Wholesale Goods"
        }
    ],
    "sg:phone":"+1 920 988 0175",
    "sg:postcode":"53038",
    "sg:province":"WI",
    "sg:tags":[
        "pattern",
        "industrial",
        "mfg"
    ],
    "wof:name":"Komo Pattern LLC",
    "wof:placetype":"venue"
},
  "geometry": {"coordinates":[-88.79715299999999,43.052217],"type":"Point"}
}