{
  "type": "Feature",
  "properties": {
    "iso:country":"US",
    "sg:address":"6085 Falcon Dr",
    "sg:city":"Wausau",
    "sg:classifiers":[
        {
            "category":"Retail",
            "subcategory":"Repair Shop",
            "type":"Services"
        }
    ],
    "sg:phone":"+1 715 675 4881",
    "sg:postcode":"54401",
    "sg:province":"WI",
    "wof:name":"B R Sales & Services",
    "wof:placetype":"venue"
},
  "geometry": {"coordinates":[-89.714066,45.016821],"type":"Point"}
}