{
  "type": "Feature",
  "properties": {
    "iso:country":"US",
    "sg:address":"1201 Beaudry Blvd",
    "sg:city":"Hudson",
    "sg:classifiers":[
        {
            "category":"Professional",
            "subcategory":"Art Services",
            "type":"Services"
        }
    ],
    "sg:phone":"+1 715 381 8260",
    "sg:postcode":"54016",
    "sg:province":"WI",
    "sg:tags":[
        "development",
        "package",
        "designing"
    ],
    "wof:name":"Flexoprint Inc",
    "wof:placetype":"venue"
},
  "geometry": {"coordinates":[-92.73826,44.957516],"type":"Point"}
}