{
  "type": "Feature",
  "properties": {
    "addr:full":"306 Bickford St New Lisbon WI 53950",
    "addr:housenumber":"306",
    "addr:postcode":"53950",
    "addr:street":"Bickford St",
    "iso:country":"US",
    "sg:address":"306 Bickford St",
    "sg:city":"New Lisbon",
    "sg:classifiers":[
        {
            "category":"Manufacturing",
            "subcategory":"Motor Vehicles & Parts",
            "type":"Manufacturing & Wholesale Goods"
        }
    ],
    "sg:phone":"+1 608 562 6072",
    "sg:postcode":"53950",
    "sg:province":"WI",
    "sg:tags":[
        "automotive",
        "reconditioning",
        "rebuilding"
    ],
    "wof:name":"Automotive Machine & Wldg LLC",
    "wof:placetype":"venue"
},
  "geometry": {"coordinates":[-90.14837799999999,43.88047],"type":"Point"}
}