{
  "type": "Feature",
  "properties": {
    "iso:country":"US",
    "sg:address":"1137 W Lorain St",
    "sg:city":"Appleton",
    "sg:classifiers":[
        {
            "category":"Building & Trades",
            "subcategory":"Cleaning & Sanitation",
            "type":"Services"
        }
    ],
    "sg:phone":"+1 920 738 0231",
    "sg:postcode":"54914",
    "sg:province":"WI",
    "sg:tags":[
        "maintenance"
    ],
    "wof:name":"Progrssive Maintenence Inc",
    "wof:placetype":"venue"
},
  "geometry": {"coordinates":[-88.425348,44.266616],"type":"Point"}
}