{
  "type": "Feature",
  "properties": {
    "iso:country":"US",
    "sg:address":"212 Miner Ave W",
    "sg:city":"Ladysmith",
    "sg:classifiers":[
        {
            "category":"Government",
            "subcategory":"Post Office",
            "type":"Public Place"
        }
    ],
    "sg:phone":"+1 715 532 3400",
    "sg:postcode":"54848",
    "sg:province":"WI",
    "sg:tags":[
        "postal",
        "us"
    ],
    "wof:name":"US Post Office",
    "wof:placetype":"venue"
},
  "geometry": {"coordinates":[-91.10327700000001,45.464137],"type":"Point"}
}