{
  "type": "Feature",
  "properties": {
    "addr:full":"1900 S 31st Rd Coleman WI 54112",
    "addr:housenumber":"1900",
    "addr:postcode":"54112",
    "addr:street":"S 31St Rd",
    "iso:country":"US",
    "sg:address":"1900 S 31st Rd",
    "sg:city":"Coleman",
    "sg:classifiers":[
        {
            "category":"Real Estate",
            "subcategory":"Real Estate Agent",
            "type":"Services"
        }
    ],
    "sg:phone":"+1 920 897 2910",
    "sg:postcode":"54112",
    "sg:province":"WI",
    "wof:name":"Dewitt Investments LLC",
    "wof:placetype":"venue"
},
  "geometry": {"coordinates":[-88.10637800000001,45.033623],"type":"Point"}
}