{
  "type": "Feature",
  "properties": {
    "iso:country":"US",
    "sg:address":"16751 Appleton Ave",
    "sg:city":"Menomonee Falls",
    "sg:classifiers":[
        {
            "category":"Professional",
            "type":"Services"
        }
    ],
    "sg:phone":"+1 262 251 4228",
    "sg:postcode":"53051",
    "sg:province":"WI",
    "wof:name":"Mark 1 Products Inc",
    "wof:placetype":"venue"
},
  "geometry": {"coordinates":[-88.118863,43.180267],"type":"Point"}
}