{
  "type": "Feature",
  "properties": {
    "iso:country":"US",
    "sg:address":"14274 Pine Ridge Lake Ln",
    "sg:city":"Lakewood",
    "sg:classifiers":[
        {
            "category":"Professional",
            "type":"Services"
        }
    ],
    "sg:phone":"+1 715 276 1396",
    "sg:postcode":"54138",
    "sg:province":"WI",
    "sg:tags":[
        "establishment"
    ],
    "wof:name":"Fluid System Components Inc",
    "wof:placetype":"venue"
},
  "geometry": {"coordinates":[-88.466477,45.321001],"type":"Point"}
}