{
  "type": "Feature",
  "properties": {
    "addr:full":"211 N Main St La Valle WI 53941",
    "addr:housenumber":"211",
    "addr:postcode":"53941",
    "addr:street":"N Main St",
    "iso:country":"US",
    "sg:address":"211 N Main St",
    "sg:city":"La Valle",
    "sg:classifiers":[
        {
            "category":"Shopping",
            "subcategory":"Used Merchandise",
            "type":"Retail Goods"
        }
    ],
    "sg:phone":"+1 608 985 7300",
    "sg:postcode":"53941",
    "sg:province":"WI",
    "sg:tags":[
        "antique"
    ],
    "wof:name":"Treasure Mill",
    "wof:placetype":"venue"
},
  "geometry": {"coordinates":[-90.15548699999999,43.468875],"type":"Point"}
}