{
  "type": "Feature",
  "properties": {
    "addr:full":"162 Elder St Hixton WI 54635",
    "addr:housenumber":"162",
    "addr:postcode":"54635",
    "addr:street":"Elder St",
    "iso:country":"US",
    "sg:address":"162 Elder St",
    "sg:city":"Hixton",
    "sg:classifiers":[
        {
            "category":"Shopping",
            "subcategory":"Used Merchandise",
            "type":"Retail Goods"
        }
    ],
    "sg:phone":"+1 715 963 3500",
    "sg:postcode":"54635",
    "sg:province":"WI",
    "wof:name":"Hixton Antique Mall",
    "wof:placetype":"venue"
},
  "geometry": {"coordinates":[-91.012146,44.388842],"type":"Point"}
}