{
  "type": "Feature",
  "properties": {
    "iso:country":"US",
    "sg:address":"316 Bridge St",
    "sg:city":"Burlington",
    "sg:classifiers":[
        {
            "category":"Personal",
            "subcategory":"Nail Salon",
            "type":"Services"
        }
    ],
    "sg:phone":"+1 262 767 1241",
    "sg:postcode":"53105",
    "sg:province":"WI",
    "wof:name":"Beauty Nails",
    "wof:placetype":"venue"
},
  "geometry": {"coordinates":[-88.27292,42.679659],"type":"Point"}
}