{
  "type": "Feature",
  "properties": {
    "iso:country":"US",
    "sg:address":"589 335th Ave",
    "sg:city":"Frederic",
    "sg:classifiers":[
        {
            "category":"Building & Trades",
            "subcategory":"Construction",
            "type":"Services"
        }
    ],
    "sg:phone":"+1 715 653 2542",
    "sg:postcode":"54837",
    "sg:province":"WI",
    "sg:tags":[
        "house"
    ],
    "wof:name":"Ej Construction",
    "wof:placetype":"venue"
},
  "geometry": {"coordinates":[-92.280556,45.690394],"type":"Point"}
}