{
  "type": "Feature",
  "properties": {
    "addr:full":"408 S Main St De Forest WI 53532",
    "addr:housenumber":"408",
    "addr:postcode":"53532",
    "addr:street":"S Main St",
    "iso:country":"US",
    "sg:address":"408 S Main St",
    "sg:city":"De Forest",
    "sg:classifiers":[
        {
            "category":"Real Estate",
            "subcategory":"Real Estate Agent",
            "type":"Services"
        }
    ],
    "sg:phone":"+1 608 846 7888",
    "sg:postcode":"53532",
    "sg:province":"WI",
    "wof:name":"Jeff J Lange",
    "wof:placetype":"venue"
},
  "geometry": {"coordinates":[-89.34384799999999,43.243629],"type":"Point"}
}