{
  "type": "Feature",
  "properties": {
    "iso:country":"US",
    "sg:address":"261 W Main St",
    "sg:city":"Stoughton",
    "sg:classifiers":[
        {
            "category":"Shopping",
            "type":"Retail Goods"
        }
    ],
    "sg:phone":"+1 608 877 1444",
    "sg:postcode":"53589",
    "sg:province":"WI",
    "sg:tags":[
        "cards",
        "sport",
        "baseball",
        "memorabilia"
    ],
    "wof:name":"Nelson Cards",
    "wof:placetype":"venue"
},
  "geometry": {"coordinates":[-89.222648,42.916713],"type":"Point"}
}