{
  "type": "Feature",
  "properties": {
    "iso:country":"US",
    "sg:address":"716 Kristy St",
    "sg:city":"Kaukauna",
    "sg:classifiers":[
        {
            "category":"Social Services",
            "subcategory":"Child Care",
            "type":"Services"
        }
    ],
    "sg:phone":"+1 920 766 7148",
    "sg:postcode":"54130",
    "sg:province":"WI",
    "sg:tags":[
        "day"
    ],
    "wof:name":"Marys Kiddie Korner",
    "wof:placetype":"venue"
},
  "geometry": {"coordinates":[-88.28833400000001,44.262086],"type":"Point"}
}