{
  "type": "Feature",
  "properties": {
    "iso:country":"US",
    "sg:address":"8572 Townhall Rd",
    "sg:city":"Platteville",
    "sg:classifiers":[
        {
            "category":"Building & Trades",
            "subcategory":"Construction",
            "type":"Services"
        }
    ],
    "sg:phone":"+1 608 348 4087",
    "sg:postcode":"53818",
    "sg:province":"WI",
    "sg:tags":[
        "house"
    ],
    "wof:name":"Austin Scott Builder LLC",
    "wof:placetype":"venue"
},
  "geometry": {"coordinates":[-90.516068,42.81364],"type":"Point"}
}