{
  "type": "Feature",
  "properties": {
    "iso:country":"US",
    "sg:address":"11224 S Cleveland Rd",
    "sg:city":"Cleveland",
    "sg:classifiers":[
        {
            "category":"Farming",
            "subcategory":"Farm",
            "type":"Manufacturing & Wholesale Goods"
        }
    ],
    "sg:phone":"+1 920 693 8020",
    "sg:postcode":"53015",
    "sg:province":"WI",
    "sg:tags":[
        "crop",
        "general"
    ],
    "wof:name":"Michael Kolb",
    "wof:placetype":"venue"
},
  "geometry": {"coordinates":[-87.817801,43.906429],"type":"Point"}
}