{
  "type": "Feature",
  "properties": {
    "addr:full":"2747 S 14th St Milwaukee WI 53215",
    "addr:housenumber":"2747",
    "addr:postcode":"53215",
    "addr:street":"S 14Th St",
    "iso:country":"US",
    "sg:address":"2747 S 14th St",
    "sg:city":"Milwaukee",
    "sg:classifiers":[
        {
            "category":"Real Estate",
            "subcategory":"Real Estate Operator",
            "type":"Services"
        }
    ],
    "sg:phone":"+1 414 389 0541",
    "sg:postcode":"53215",
    "sg:province":"WI",
    "sg:tags":[
        "building"
    ],
    "wof:name":"Cleveland Terrace",
    "wof:placetype":"venue"
},
  "geometry": {"coordinates":[-87.930086,42.994758],"type":"Point"}
}