{
  "type": "Feature",
  "properties": {
    "iso:country":"US",
    "sg:address":"2624 White Oaks Ct",
    "sg:city":"Beloit",
    "sg:classifiers":[
        {
            "category":"Building & Trades",
            "subcategory":"Construction",
            "type":"Services"
        }
    ],
    "sg:phone":"+1 608 362 8367",
    "sg:postcode":"53511",
    "sg:province":"IL",
    "sg:tags":[
        "drywall",
        "contractor"
    ],
    "wof:name":"Bel-Rock Drywall Service",
    "wof:placetype":"venue"
},
  "geometry": {"coordinates":[-88.99084,42.534101],"type":"Point"}
}