{
  "type": "Feature",
  "properties": {
    "addr:full":"2510 E Capitol Dr Milwaukee WI 53211",
    "addr:housenumber":"2510",
    "addr:postcode":"53211",
    "addr:street":"E Capitol Dr",
    "iso:country":"US",
    "sg:address":"2510 E Capitol Dr",
    "sg:city":"Milwaukee",
    "sg:classifiers":[
        {
            "category":"Real Estate",
            "subcategory":"Real Estate Agent",
            "type":"Services"
        }
    ],
    "sg:phone":"+1 414 964 9000",
    "sg:postcode":"53211",
    "sg:province":"WI",
    "sg:tags":[
        "broker"
    ],
    "sg:website":"www.coldwellbankeronline.com",
    "wof:name":"Coldwell Banker",
    "wof:placetype":"venue"
},
  "geometry": {"coordinates":[-87.87756400000001,43.089212],"type":"Point"}
}