{
  "type": "Feature",
  "properties": {
    "iso:country":"US",
    "sg:address":"850 Garden St",
    "sg:city":"Green Bay",
    "sg:classifiers":[
        {
            "category":"Retail",
            "subcategory":"Laundry & Dry Cleaning",
            "type":"Services"
        }
    ],
    "sg:phone":"+1 920 435 6877",
    "sg:postcode":"54303",
    "sg:province":"WI",
    "sg:tags":[
        "cleaners",
        "rug",
        "carpet"
    ],
    "wof:name":"Spranger's Steam Extraction",
    "wof:placetype":"venue"
},
  "geometry": {"coordinates":[-88.022827,44.529386],"type":"Point"}
}