{
  "type": "Feature",
  "properties": {
    "iso:country":"US",
    "sg:address":"7949 North St",
    "sg:city":"Pembine",
    "sg:classifiers":[
        {
            "category":"Freight",
            "type":"Transportation"
        }
    ],
    "sg:phone":"+1 715 324 5387",
    "sg:postcode":"54156",
    "sg:province":"WI",
    "sg:tags":[
        "commercial",
        "storage"
    ],
    "wof:name":"Pembine Mini Storage",
    "wof:placetype":"venue"
},
  "geometry": {"coordinates":[-87.988865,45.640753],"type":"Point"}
}