{
  "type": "Feature",
  "properties": {
    "iso:country":"US",
    "sg:address":"328 W Edgewater St",
    "sg:city":"Cambria",
    "sg:classifiers":[
        {
            "category":"Professional",
            "subcategory":"Management & Consulting",
            "type":"Services"
        }
    ],
    "sg:phone":"+1 920 348 6093",
    "sg:postcode":"53923",
    "sg:province":"WI",
    "wof:name":"Mwb Enterprises",
    "wof:placetype":"venue"
},
  "geometry": {"coordinates":[-89.110885,43.543123],"type":"Point"}
}