{
  "type": "Feature",
  "properties": {
    "iso:country":"US",
    "sg:address":"1920 50th Ave",
    "sg:city":"Baldwin",
    "sg:classifiers":[
        {
            "category":"Farming",
            "subcategory":"Livestock Farm",
            "type":"Manufacturing & Wholesale Goods"
        }
    ],
    "sg:phone":"+1 715 684 5941",
    "sg:postcode":"54002",
    "sg:province":"WI",
    "sg:tags":[
        "buffalo"
    ],
    "wof:name":"Rush River Bison",
    "wof:placetype":"venue"
},
  "geometry": {"coordinates":[-92.41307500000001,44.934515],"type":"Point"}
}