{
  "type": "Feature",
  "properties": {
    "iso:country":"US",
    "sg:address":"3130 Reiland Rd",
    "sg:city":"Appleton",
    "sg:classifiers":[
        {
            "category":"Retail",
            "subcategory":"Repair Shop",
            "type":"Services"
        }
    ],
    "sg:phone":"+1 920 731 6586",
    "sg:postcode":"54913",
    "sg:province":"WI",
    "wof:name":"Performance Upholstery",
    "wof:placetype":"venue"
},
  "geometry": {"coordinates":[-88.40757000000001,44.346652],"type":"Point"}
}