{
  "type": "Feature",
  "properties": {
    "iso:country":"US",
    "sg:address":"102 3rd Ave E",
    "sg:city":"Knapp",
    "sg:classifiers":[
        {
            "category":"Manufacturing",
            "subcategory":"Pet Food",
            "type":"Manufacturing & Wholesale Goods"
        }
    ],
    "sg:phone":"+1 715 665 2118",
    "sg:postcode":"54749",
    "sg:province":"WI",
    "sg:tags":[
        "feed",
        "equipment",
        "mfg",
        "prepared"
    ],
    "wof:name":"Vets Plus Inc",
    "wof:placetype":"venue"
},
  "geometry": {"coordinates":[-92.075664,44.955273],"type":"Point"}
}