{
  "type": "Feature",
  "properties": {
    "iso:country":"US",
    "sg:address":"2014 Hillside Dr",
    "sg:city":"Delafield",
    "sg:classifiers":[
        {
            "category":"Recreation",
            "type":"Entertainment"
        }
    ],
    "sg:phone":"+1 262 646 4975",
    "sg:postcode":"53018",
    "sg:province":"WI",
    "wof:name":"American Sddlbred Assn Wscnsin",
    "wof:placetype":"venue"
},
  "geometry": {"coordinates":[-88.377922,43.047724],"type":"Point"}
}