{
  "type": "Feature",
  "properties": {
    "iso:country":"US",
    "sg:address":"21727 Durand Ave",
    "sg:city":"Union Grove",
    "sg:classifiers":[
        {
            "category":"Freight",
            "type":"Transportation"
        }
    ],
    "sg:phone":"+1 262 878 4750",
    "sg:postcode":"53182",
    "sg:province":"WI",
    "sg:tags":[
        "hauling",
        "trucking"
    ],
    "wof:name":"Mark Szczerba Inc",
    "wof:placetype":"venue"
},
  "geometry": {"coordinates":[-88.078242,42.681643],"type":"Point"}
}