{
  "type": "Feature",
  "properties": {
    "iso:country":"US",
    "sg:address":"582 North Ave",
    "sg:city":"Hartland",
    "sg:classifiers":[
        {
            "category":"Building & Trades",
            "subcategory":"Construction",
            "type":"Services"
        }
    ],
    "sg:phone":"+1 262 369 9039",
    "sg:postcode":"53029",
    "sg:province":"WI",
    "sg:tags":[
        "contractor"
    ],
    "wof:name":"Rivers Rain Gutters",
    "wof:placetype":"venue"
},
  "geometry": {"coordinates":[-88.344233,43.112151],"type":"Point"}
}