{
  "type": "Feature",
  "properties": {
    "addr:full":"3200 Lake Shore Dr E Ashland WI 54806",
    "addr:housenumber":"3200",
    "addr:postcode":"54806",
    "addr:street":"Lake Shore Dr E",
    "iso:country":"US",
    "sg:address":"3200 Lake Shore Dr E",
    "sg:city":"Ashland",
    "sg:classifiers":[
        {
            "category":"Education",
            "subcategory":"Library",
            "type":"Public Place"
        }
    ],
    "sg:phone":"+1 715 682 2365",
    "sg:postcode":"54806",
    "sg:province":"WI",
    "sg:website":"www.nwls.lib.wi.us",
    "wof:name":"Northern Waters Library Svc",
    "wof:placetype":"venue"
},
  "geometry": {"coordinates":[-90.841149,46.611011],"type":"Point"}
}