{
  "type": "Feature",
  "properties": {
    "iso:country":"US",
    "sg:address":"1830 Co Rd C",
    "sg:city":"Arkdale",
    "sg:classifiers":[
        {
            "category":"Retail",
            "subcategory":"Repair Shop",
            "type":"Services"
        }
    ],
    "sg:phone":"+1 608 564 7104",
    "sg:postcode":"54613",
    "sg:province":"WI",
    "wof:name":"Rabuck Horseshoeing",
    "wof:placetype":"venue"
},
  "geometry": {"coordinates":[-89.92553700000001,44.111944],"type":"Point"}
}