{
  "type": "Feature",
  "properties": {
    "iso:country":"US",
    "sg:address":"6617 Old Sauk Rd",
    "sg:city":"Madison",
    "sg:classifiers":[
        {
            "category":"Travel",
            "subcategory":"Travel Agent",
            "type":"Entertainment"
        }
    ],
    "sg:phone":"+1 608 833 1619",
    "sg:postcode":"53705",
    "sg:province":"WI",
    "sg:tags":[
        "agency"
    ],
    "wof:name":"Renaissance Travel Inc",
    "wof:placetype":"venue"
},
  "geometry": {"coordinates":[-89.495445,43.07514],"type":"Point"}
}