{
  "type": "Feature",
  "properties": {
    "iso:country":"US",
    "sg:address":"414 Medbury St",
    "sg:city":"Kendall",
    "sg:classifiers":[
        {
            "category":"Organizations",
            "subcategory":"Community Association",
            "type":"Services"
        }
    ],
    "sg:phone":"+1 608 463 7459",
    "sg:postcode":"54638",
    "sg:province":"WI",
    "sg:tags":[
        "military"
    ],
    "wof:name":"Legion Hall",
    "wof:placetype":"venue"
},
  "geometry": {"coordinates":[-90.36877699999999,43.795592],"type":"Point"}
}