{
  "type": "Feature",
  "properties": {
    "iso:country":"US",
    "sg:address":"2525 S Oneida St",
    "sg:city":"Appleton",
    "sg:classifiers":[
        {
            "category":"Professional",
            "subcategory":"Management & Consulting",
            "type":"Services"
        },
        {
            "category":"Wholesale",
            "subcategory":"Non-durable Goods",
            "type":"Manufacturing & Wholesale Goods"
        }
    ],
    "sg:phone":"+1 920 731 1500",
    "sg:postcode":"54915",
    "sg:province":"WI",
    "sg:tags":[
        "public",
        "relations",
        "advertising"
    ],
    "wof:name":"Icon Apparel & Promotions LLC",
    "wof:placetype":"venue"
},
  "geometry": {"coordinates":[-88.404121,44.238911],"type":"Point"}
}