{
  "type": "Feature",
  "properties": {
    "iso:country":"US",
    "sg:address":"11900 State Hwy 52",
    "sg:city":"Wausau",
    "sg:classifiers":[
        {
            "category":"Farming",
            "subcategory":"Livestock Farm",
            "type":"Manufacturing & Wholesale Goods"
        }
    ],
    "sg:phone":"+1 715 845 6490",
    "sg:postcode":"54403",
    "sg:province":"WI",
    "sg:tags":[
        "animal",
        "general"
    ],
    "wof:name":"Triple L Whitetail LLC",
    "wof:placetype":"venue"
},
  "geometry": {"coordinates":[-89.472234,45.032255],"type":"Point"}
}