{
  "type": "Feature",
  "properties": {
    "addr:full":"555 W Estabrook Blvd Milwaukee WI 53212",
    "addr:housenumber":"555",
    "addr:postcode":"53212",
    "addr:street":"W Estabrook Blvd",
    "iso:country":"US",
    "sg:address":"555 W Estabrook Blvd",
    "sg:city":"Milwaukee",
    "sg:classifiers":[
        {
            "category":"Wholesale",
            "subcategory":"Furniture",
            "type":"Manufacturing & Wholesale Goods"
        }
    ],
    "sg:phone":"+1 414 906 3200",
    "sg:postcode":"53212",
    "sg:province":"WI",
    "sg:tags":[
        "sales"
    ],
    "sg:website":"www.forrersbi.com",
    "wof:name":"Forrer Business Interiors Inc",
    "wof:placetype":"venue"
},
  "geometry": {"coordinates":[-87.915982,43.096572],"type":"Point"}
}