{
  "type": "Feature",
  "properties": {
    "iso:country":"US",
    "sg:address":"225 W Blackhawk Ave",
    "sg:city":"Prairie Du Chien",
    "sg:classifiers":[
        {
            "category":"Restaurant",
            "type":"Food & Drink"
        }
    ],
    "sg:phone":"+1 608 326 6216",
    "sg:postcode":"53821",
    "sg:province":"WI",
    "sg:tags":[
        "tavern"
    ],
    "wof:name":"Kaber's Supper Club",
    "wof:placetype":"venue"
},
  "geometry": {"coordinates":[-91.148034,43.051527],"type":"Point"}
}