{
  "type": "Feature",
  "properties": {
    "iso:country":"US",
    "sg:address":"2836 Harrison St",
    "sg:city":"Oshkosh",
    "sg:classifiers":[
        {
            "category":"Shopping",
            "subcategory":"Used Merchandise",
            "type":"Retail Goods"
        }
    ],
    "sg:phone":"+1 920 237 2450",
    "sg:postcode":"54901",
    "sg:province":"WI",
    "sg:tags":[
        "shop",
        "thrift"
    ],
    "wof:name":"St Vincent De Paul Furniture",
    "wof:placetype":"venue"
},
  "geometry": {"coordinates":[-88.52875299999999,44.053331],"type":"Point"}
}