{
  "type": "Feature",
  "properties": {
    "iso:country":"US",
    "sg:address":"1733 Eagle Ln",
    "sg:city":"Eau Claire",
    "sg:classifiers":[
        {
            "category":"Professional",
            "subcategory":"Management & Consulting",
            "type":"Services"
        }
    ],
    "sg:phone":"+1 715 833 1930",
    "sg:postcode":"54703",
    "sg:province":"WI",
    "sg:tags":[
        "consultant",
        "automation",
        "electrical",
        "contractor"
    ],
    "wof:name":"Simply Automation Inc",
    "wof:placetype":"venue"
},
  "geometry": {"coordinates":[-91.579072,44.78495],"type":"Point"}
}