{
  "type": "Feature",
  "properties": {
    "iso:country":"US",
    "sg:address":"8348 Co Rd T",
    "sg:city":"Larsen",
    "sg:classifiers":[
        {
            "category":"Government",
            "subcategory":"Office",
            "type":"Public Place"
        }
    ],
    "sg:phone":"+1 920 836 2007",
    "sg:postcode":"54947",
    "sg:province":"WI",
    "sg:tags":[
        "city"
    ],
    "wof:name":"Clayton Town Hall",
    "wof:placetype":"venue"
},
  "geometry": {"coordinates":[-88.624719,44.195152],"type":"Point"}
}