{
  "type": "Feature",
  "properties": {
    "addr:full":"1515 W Mequon Rd Mequon WI 53092",
    "addr:housenumber":"1515",
    "addr:postcode":"53092",
    "addr:street":"W Mequon Rd",
    "iso:country":"US",
    "sg:address":"1515 W Mequon Rd",
    "sg:city":"Mequon",
    "sg:classifiers":[
        {
            "category":"Shopping",
            "subcategory":"Clothing, Apparel, & Fashions",
            "type":"Retail Goods"
        }
    ],
    "sg:phone":"+1 262 241 5864",
    "sg:postcode":"53092",
    "sg:province":"WI",
    "wof:name":"Bruce Paul Goodman-Fashionable",
    "wof:placetype":"venue"
},
  "geometry": {"coordinates":[-87.926372,43.221092],"type":"Point"}
}