{
  "type": "Feature",
  "properties": {
    "iso:country":"US",
    "sg:address":"2789 Co Rd B",
    "sg:city":"Hilbert",
    "sg:classifiers":[
        {
            "category":"Wholesale",
            "subcategory":"Farm Supplies",
            "type":"Manufacturing & Wholesale Goods"
        }
    ],
    "sg:phone":"+1 920 989 2050",
    "sg:postcode":"54129",
    "sg:province":"WI",
    "sg:tags":[
        "buyer",
        "livestock"
    ],
    "wof:name":"Tom Buchinger Livestock",
    "wof:placetype":"venue"
},
  "geometry": {"coordinates":[-88.176543,44.168921],"type":"Point"}
}