{
  "type": "Feature",
  "properties": {
    "iso:country":"US",
    "sg:address":"14967 W National Ave",
    "sg:city":"New Berlin",
    "sg:classifiers":[
        {
            "category":"Retail",
            "subcategory":"Car Wash",
            "type":"Services"
        }
    ],
    "sg:phone":"+1 262 797 7868",
    "sg:postcode":"53151",
    "sg:province":"WI",
    "sg:tags":[
        "carwash"
    ],
    "wof:name":"National Car Wash",
    "wof:placetype":"venue"
},
  "geometry": {"coordinates":[-88.099454,42.982647],"type":"Point"}
}