{
  "type": "Feature",
  "properties": {
    "iso:country":"US",
    "sg:address":"29251 Long Lake Rd",
    "sg:city":"Danbury",
    "sg:classifiers":[
        {
            "category":"Restaurant",
            "type":"Food & Drink"
        }
    ],
    "sg:phone":"+1 715 635 2386",
    "sg:postcode":"54830",
    "sg:province":"WI",
    "sg:tags":[
        "eating"
    ],
    "wof:name":"Jo Mamas A & H Cafe",
    "wof:placetype":"venue"
},
  "geometry": {"coordinates":[-92.136137,45.973617],"type":"Point"}
}