{
  "type": "Feature",
  "properties": {
    "iso:country":"US",
    "sg:address":"710 Cottage Grove Rd",
    "sg:city":"Madison",
    "sg:classifiers":[
        {
            "category":"Professional",
            "subcategory":"Employment Agencies",
            "type":"Services"
        }
    ],
    "sg:phone":"+1 608 223 0575",
    "sg:postcode":"53716",
    "sg:province":"WI",
    "sg:tags":[
        "opportunity"
    ],
    "wof:name":"Labor Ready Inc",
    "wof:placetype":"venue"
},
  "geometry": {"coordinates":[-89.31341500000001,43.083979],"type":"Point"}
}