{
  "type": "Feature",
  "properties": {
    "iso:country":"US",
    "sg:address":"2920 Superior Ave",
    "sg:city":"Sheboygan",
    "sg:classifiers":[
        {
            "category":"Health Services",
            "subcategory":"Doctor",
            "type":"Services"
        }
    ],
    "sg:phone":"+1 920 452 4911",
    "sg:postcode":"53081",
    "sg:province":"WI",
    "sg:tags":[
        "specializing",
        "physician",
        "surgery"
    ],
    "wof:name":"Lisberg Kenneth J MD",
    "wof:placetype":"venue"
},
  "geometry": {"coordinates":[-87.74570199999999,43.761207],"type":"Point"}
}