{
  "type": "Feature",
  "properties": {
    "iso:country":"US",
    "sg:address":"4873 Co Rd K",
    "sg:city":"Random Lake",
    "sg:classifiers":[
        {
            "category":"Professional",
            "type":"Services"
        }
    ],
    "sg:phone":"+1 920 994 2700",
    "sg:postcode":"53075",
    "sg:province":"WI",
    "sg:tags":[
        "establishment"
    ],
    "wof:name":"Featherlite-Southeast Wscnsn",
    "wof:placetype":"venue"
},
  "geometry": {"coordinates":[-87.93993,43.543192],"type":"Point"}
}