{
  "type": "Feature",
  "properties": {
    "addr:full":"5675 Loucks Rd Peshtigo WI 54157",
    "addr:housenumber":"5675",
    "addr:postcode":"54157",
    "addr:street":"Loucks Rd",
    "iso:country":"US",
    "sg:address":"5675 Loucks Rd",
    "sg:city":"Peshtigo",
    "sg:classifiers":[
        {
            "category":"Professional",
            "type":"Services"
        }
    ],
    "sg:phone":"+1 715 789 2601",
    "sg:postcode":"54157",
    "sg:province":"WI",
    "wof:name":"John Duescher",
    "wof:placetype":"venue"
},
  "geometry": {"coordinates":[-87.878787,45.084894],"type":"Point"}
}