{
  "type": "Feature",
  "properties": {
    "iso:country":"US",
    "sg:address":"2987 Yarmouth Greenway Dr",
    "sg:city":"Madison",
    "sg:classifiers":[
        {
            "category":"Communications",
            "subcategory":"Film & Video Production",
            "type":"Services"
        }
    ],
    "sg:phone":"+1 608 277 8900",
    "sg:postcode":"53711",
    "sg:province":"WI",
    "sg:tags":[
        "motion",
        "web",
        "e"
    ],
    "wof:name":"WEB COURSEWORKS",
    "wof:placetype":"venue"
},
  "geometry": {"coordinates":[-89.42709000000001,43.018904],"type":"Point"}
}