{
  "type": "Feature",
  "properties": {
    "iso:country":"US",
    "sg:address":"11109 Rogers Rd",
    "sg:city":"Black River Fls",
    "sg:classifiers":[
        {
            "category":"Insurance",
            "subcategory":"Insurance Agent",
            "type":"Services"
        }
    ],
    "sg:phone":"+1 715 284 9416",
    "sg:postcode":"54615",
    "sg:province":"WI",
    "wof:name":"Rural Insurance Claims Co",
    "wof:placetype":"venue"
},
  "geometry": {"coordinates":[-90.868039,44.286302],"type":"Point"}
}