{
  "type": "Feature",
  "properties": {
    "iso:country":"US",
    "sg:address":"411 Lincoln St",
    "sg:city":"Neenah",
    "sg:classifiers":[
        {
            "category":"Health Services",
            "subcategory":"Doctor",
            "type":"Services"
        }
    ],
    "sg:phone":"+1 920 727 4339",
    "sg:postcode":"54956",
    "sg:province":"WI",
    "sg:tags":[
        "medicine",
        "internal"
    ],
    "wof:name":"Lasalle Clientic",
    "wof:placetype":"venue"
},
  "geometry": {"coordinates":[-88.451014,44.18769],"type":"Point"}
}