{
  "type": "Feature",
  "properties": {
    "iso:country":"US",
    "sg:address":"200 S Washington St",
    "sg:city":"Green Bay",
    "sg:classifiers":[
        {
            "category":"Real Estate",
            "subcategory":"Real Estate Operator",
            "type":"Services"
        }
    ],
    "sg:phone":"+1 920 496 0993",
    "sg:postcode":"54301",
    "sg:province":"WI",
    "sg:tags":[
        "building",
        "nonresidential"
    ],
    "wof:name":"Nicolet RE & Investments",
    "wof:placetype":"venue"
},
  "geometry": {"coordinates":[-88.017693,44.512042],"type":"Point"}
}