{
  "type": "Feature",
  "properties": {
    "iso:country":"US",
    "sg:address":"7431 Co Rd Z",
    "sg:city":"Custer",
    "sg:classifiers":[
        {
            "category":"Bars & Pubs",
            "type":"Food & Drink"
        }
    ],
    "sg:phone":"+1 715 592 4233",
    "sg:postcode":"54423",
    "sg:province":"WI",
    "sg:tags":[
        "drinking"
    ],
    "wof:name":"Kezeske Sylvia Stre & Tavern",
    "wof:placetype":"venue"
},
  "geometry": {"coordinates":[-89.414267,44.569657],"type":"Point"}
}