{
  "type": "Feature",
  "properties": {
    "addr:full":"212 N Milwaukee St Milwaukee WI 53202",
    "addr:housenumber":"212",
    "addr:postcode":"53202",
    "addr:street":"N Milwaukee St",
    "iso:country":"US",
    "sg:address":"212 N Milwaukee St",
    "sg:city":"Milwaukee",
    "sg:classifiers":[
        {
            "category":"Parking",
            "type":"Transportation"
        }
    ],
    "sg:phone":"+1 414 347 1821",
    "sg:postcode":"53202",
    "sg:province":"WI",
    "sg:tags":[
        "garage"
    ],
    "wof:name":"Historic Third Ward Parking",
    "wof:placetype":"venue"
},
  "geometry": {"coordinates":[-87.905877,43.033777],"type":"Point"}
}