{
  "type": "Feature",
  "properties": {
    "iso:country":"US",
    "sg:address":"1160 Appleton Rd",
    "sg:city":"Menasha",
    "sg:classifiers":[
        {
            "category":"Retail",
            "subcategory":"Veterinary Services",
            "type":"Services"
        }
    ],
    "sg:phone":"+1 920 725 8307",
    "sg:postcode":"54952",
    "sg:province":"WI",
    "sg:tags":[
        "veterinarian"
    ],
    "wof:name":"Appanasha Pet Clinics SC",
    "wof:placetype":"venue"
},
  "geometry": {"coordinates":[-88.427779,44.222029],"type":"Point"}
}