{
  "type": "Feature",
  "properties": {
    "iso:country":"US",
    "sg:address":"N112w14545 Mequon Rd",
    "sg:city":"Germantown",
    "sg:classifiers":[
        {
            "category":"Professional",
            "subcategory":"Testing Lab",
            "type":"Services"
        },
        {
            "category":"Building & Trades",
            "subcategory":"Plumbing",
            "type":"Services"
        },
        {
            "category":"Utilities",
            "subcategory":"Sewage",
            "type":"Services"
        },
        {
            "category":"Building & Trades",
            "subcategory":"Cleaning & Sanitation",
            "type":"Services"
        }
    ],
    "sg:phone":"+1 262 251 1704",
    "sg:postcode":"53022",
    "sg:province":"WI",
    "sg:tags":[
        "systems-cleaning",
        "tank",
        "septic",
        "supply",
        "system",
        "tanks-treatment",
        "tank-testing",
        "inspection"
    ],
    "wof:name":"Kons Septic Service Inc",
    "wof:placetype":"venue"
},
  "geometry": {"coordinates":[-88.067093,43.221111],"type":"Point"}
}