{
  "type": "Feature",
  "properties": {
    "iso:country":"US",
    "sg:address":"5044 S 27th St",
    "sg:city":"Milwaukee",
    "sg:classifiers":[
        {
            "category":"Manufacturing",
            "subcategory":"Glass & Minerals",
            "type":"Manufacturing & Wholesale Goods"
        },
        {
            "category":"Retail",
            "subcategory":"Auto Repair",
            "type":"Services"
        }
    ],
    "sg:phone":"+1 414 282 8400",
    "sg:postcode":"53221",
    "sg:province":"WI",
    "sg:tags":[
        "plate",
        "window",
        "windshield",
        "glass-auto"
    ],
    "sg:website":"http://www.safelite.com",
    "wof:name":"Safelite AutoGlass",
    "wof:placetype":"venue"
},
  "geometry": {"coordinates":[-87.948635,42.972351],"type":"Point"}
}