{
  "type": "Feature",
  "properties": {
    "addr:full":"1910 University Ave Green Bay WI 54302",
    "addr:housenumber":"1910",
    "addr:postcode":"54302",
    "addr:street":"University Ave",
    "iso:country":"US",
    "sg:address":"1910 University Ave",
    "sg:city":"Green Bay",
    "sg:classifiers":[
        {
            "category":"Personal",
            "subcategory":"Beauty Salon",
            "type":"Services"
        }
    ],
    "sg:phone":"+1 920 433 9481",
    "sg:postcode":"54302",
    "sg:province":"WI",
    "wof:name":"Hair Loft",
    "wof:placetype":"venue"
},
  "geometry": {"coordinates":[-87.97631,44.512333],"type":"Point"}
}