{
  "type": "Feature",
  "properties": {
    "iso:country":"US",
    "sg:address":"5528 Co Rd K",
    "sg:city":"Amherst",
    "sg:phone":"+1 715 824 3451",
    "sg:postcode":"54406",
    "sg:province":"WI",
    "sg:tags":[
        "farm",
        "corn",
        "cash",
        "crop",
        "field",
        "grain"
    ],
    "wof:name":"Michael Zblewski",
    "wof:placetype":"venue"
},
  "geometry": {"coordinates":[-89.366388,44.402523],"type":"Point"}
}