{
  "type": "Feature",
  "properties": {
    "iso:country":"US",
    "sg:address":"15 S 2nd St",
    "sg:city":"Tomahawk",
    "sg:classifiers":[
        {
            "category":"Shopping",
            "subcategory":"Florist",
            "type":"Retail Goods"
        }
    ],
    "sg:phone":"+1 715 453 8222",
    "sg:postcode":"54487",
    "sg:province":"WI",
    "wof:name":"House of Flowers",
    "wof:placetype":"venue"
},
  "geometry": {"coordinates":[-89.732042,45.47086],"type":"Point"}
}