{
  "type": "Feature",
  "properties": {
    "iso:country":"US",
    "sg:address":"1137 N 25th St",
    "sg:city":"Milwaukee",
    "sg:classifiers":[
        {
            "category":"Social Services",
            "subcategory":"Child Care",
            "type":"Services"
        }
    ],
    "sg:phone":"+1 414 934 0578",
    "sg:postcode":"53233",
    "sg:province":"WI",
    "sg:tags":[
        "day"
    ],
    "wof:name":"Noels Early Childhood Center",
    "wof:placetype":"venue"
},
  "geometry": {"coordinates":[-87.944953,43.045308],"type":"Point"}
}