{
  "type": "Feature",
  "properties": {
    "iso:country":"US",
    "sg:address":"591 Silas Dr",
    "sg:city":"De Pere",
    "sg:classifiers":[
        {
            "category":"Building & Trades",
            "subcategory":"Construction",
            "type":"Services"
        }
    ],
    "sg:phone":"+1 920 337 6247",
    "sg:postcode":"54115",
    "sg:province":"WI",
    "sg:tags":[
        "house"
    ],
    "wof:name":"C A D Homes",
    "wof:placetype":"venue"
},
  "geometry": {"coordinates":[-88.166748,44.476688],"type":"Point"}
}