{
  "type": "Feature",
  "properties": {
    "iso:country":"US",
    "sg:address":"2705 E Richmond St",
    "sg:city":"Shawano",
    "sg:classifiers":[
        {
            "category":"Manufacturing",
            "subcategory":"Tools & Machinery",
            "type":"Manufacturing & Wholesale Goods"
        }
    ],
    "sg:phone":"+1 715 524 4681",
    "sg:postcode":"54166",
    "sg:province":"WI",
    "sg:tags":[
        "cutting"
    ],
    "wof:name":"Ross Carbide & Supply Co",
    "wof:placetype":"venue"
},
  "geometry": {"coordinates":[-88.581277,44.774775],"type":"Point"}
}