{
  "type": "Feature",
  "properties": {
    "iso:country":"US",
    "sg:address":"759 Co Rd I",
    "sg:city":"Oshkosh",
    "sg:classifiers":[
        {
            "category":"Farming",
            "subcategory":"Farm",
            "type":"Manufacturing & Wholesale Goods"
        }
    ],
    "sg:phone":"+1 920 688 5203",
    "sg:postcode":"54902",
    "sg:province":"WI",
    "sg:tags":[
        "crop",
        "general"
    ],
    "wof:name":"Warmbier Bernette",
    "wof:placetype":"venue"
},
  "geometry": {"coordinates":[-88.54403499999999,43.917423],"type":"Point"}
}