{
  "type": "Feature",
  "properties": {
    "iso:country":"US",
    "sg:address":"3160 S Prairie Ave",
    "sg:city":"Beloit",
    "sg:classifiers":[
        {
            "category":"Utilities",
            "subcategory":"Electric",
            "type":"Services"
        },
        {
            "category":"Manufacturing",
            "subcategory":"Electronics",
            "type":"Manufacturing & Wholesale Goods"
        }
    ],
    "sg:phone":"+1 608 365 3375",
    "sg:postcode":"53511",
    "sg:province":"WI",
    "sg:tags":[
        "equipment-testing"
    ],
    "wof:name":"Lappin Electric Co",
    "wof:placetype":"venue"
},
  "geometry": {"coordinates":[-89.011374,42.55895],"type":"Point"}
}