{
  "type": "Feature",
  "properties": {
    "iso:country":"US",
    "sg:address":"3374 Bay Settlement Rd",
    "sg:city":"Green Bay",
    "sg:classifiers":[
        {
            "category":"Food & Beverages",
            "subcategory":"Groceries & Convenience Stores",
            "type":"Retail Goods"
        }
    ],
    "sg:phone":"+1 920 468 1969",
    "sg:postcode":"54311",
    "sg:province":"WI",
    "sg:tags":[
        "grocer"
    ],
    "wof:name":"Craanen's Grocery",
    "wof:placetype":"venue"
},
  "geometry": {"coordinates":[-87.883786,44.564579],"type":"Point"}
}