{
  "type": "Feature",
  "properties": {
    "iso:country":"US",
    "sg:address":"215 S Clay St",
    "sg:city":"Green Bay",
    "sg:classifiers":[
        {
            "category":"Building & Trades",
            "subcategory":"Construction",
            "type":"Services"
        }
    ],
    "sg:phone":"+1 920 438 7006",
    "sg:postcode":"54301",
    "sg:province":"WI",
    "sg:tags":[
        "house"
    ],
    "wof:name":"Tupa Log Homes",
    "wof:placetype":"venue"
},
  "geometry": {"coordinates":[-88.00485500000001,44.507665],"type":"Point"}
}