{
  "type": "Feature",
  "properties": {
    "iso:country":"US",
    "sg:address":"7814 Stetson Ave",
    "sg:city":"Curtiss",
    "sg:classifiers":[
        {
            "category":"Freight",
            "type":"Transportation"
        }
    ],
    "sg:phone":"+1 715 678 2089",
    "sg:postcode":"54422",
    "sg:province":"WI",
    "sg:tags":[
        "hauling",
        "trucking"
    ],
    "wof:name":"Neitzel Farms Trucking Inc",
    "wof:placetype":"venue"
},
  "geometry": {"coordinates":[-90.444498,45.059983],"type":"Point"}
}