{
  "type": "Feature",
  "properties": {
    "iso:country":"US",
    "sg:address":"15655 W North Ave",
    "sg:city":"Brookfield",
    "sg:classifiers":[
        {
            "category":"Shopping",
            "subcategory":"Jewelry",
            "type":"Retail Goods"
        }
    ],
    "sg:phone":"+1 262 821 2802",
    "sg:postcode":"53005",
    "sg:province":"WI",
    "sg:tags":[
        "jeweler"
    ],
    "wof:name":"Krikis LTD Jewelers",
    "wof:placetype":"venue"
},
  "geometry": {"coordinates":[-88.106955,43.060381],"type":"Point"}
}