{
  "type": "Feature",
  "properties": {
    "iso:country":"US",
    "sg:address":"2280 Salscheider Ct",
    "sg:city":"Green Bay",
    "sg:classifiers":[
        {
            "category":"Professional",
            "type":"Services"
        }
    ],
    "sg:phone":"+1 920 437 2997",
    "sg:postcode":"54313",
    "sg:province":"WI",
    "wof:name":"Endeavor Environmental Svcs",
    "wof:placetype":"venue"
},
  "geometry": {"coordinates":[-88.07298400000001,44.575535],"type":"Point"}
}