{
  "type": "Feature",
  "properties": {
    "iso:country":"US",
    "sg:address":"749 Jaworski Rd",
    "sg:city":"Pulaski",
    "sg:classifiers":[
        {
            "category":"Professional",
            "subcategory":"Business Services",
            "type":"Services"
        }
    ],
    "sg:phone":"+1 920 822 1619",
    "sg:postcode":"54162",
    "sg:province":"WI",
    "wof:name":"Dreamraisers",
    "wof:placetype":"venue"
},
  "geometry": {"coordinates":[-88.201242,44.698561],"type":"Point"}
}