{
  "type": "Feature",
  "properties": {
    "addr:full":"9455 Main St Amherst Junction WI 54407",
    "addr:housenumber":"9455",
    "addr:postcode":"54407",
    "addr:street":"Main St",
    "iso:country":"US",
    "sg:address":"9455 Main St",
    "sg:city":"Amherst Junction",
    "sg:classifiers":[
        {
            "category":"Government",
            "subcategory":"Post Office",
            "type":"Public Place"
        }
    ],
    "sg:phone":"+1 715 000 1111",
    "sg:postcode":"54407",
    "sg:province":"WI",
    "wof:name":"US Post Office",
    "wof:placetype":"venue"
},
  "geometry": {"coordinates":[-89.311925,44.467672],"type":"Point"}
}