{
  "type": "Feature",
  "properties": {
    "iso:country":"US",
    "sg:address":"400 N Executive Dr",
    "sg:city":"Brookfield",
    "sg:classifiers":[
        {
            "category":"Professional",
            "subcategory":"Accounting & Tax Preparation",
            "type":"Services"
        }
    ],
    "sg:phone":"+1 262 789 0225",
    "sg:postcode":"53005",
    "sg:province":"WI",
    "wof:name":"H & R Block",
    "wof:placetype":"venue"
},
  "geometry": {"coordinates":[-88.114724,43.035749],"type":"Point"}
}