{
  "type": "Feature",
  "properties": {
    "iso:country":"US",
    "sg:address":"2109 Spring St",
    "sg:city":"Cross Plains",
    "sg:classifiers":[
        {
            "category":"Manufacturing",
            "subcategory":"Tools & Machinery",
            "type":"Manufacturing & Wholesale Goods"
        }
    ],
    "sg:phone":"+1 608 798 0050",
    "sg:postcode":"53528",
    "sg:province":"WI",
    "sg:tags":[
        "machine",
        "die",
        "maker",
        "shop"
    ],
    "wof:name":"Mg Ginnis Tool & Die",
    "wof:placetype":"venue"
},
  "geometry": {"coordinates":[-89.656462,43.115204],"type":"Point"}
}