{
  "type": "Feature",
  "properties": {
    "addr:full":"4902 Co Rd Hh Stevens Point WI 54481",
    "addr:housenumber":"4902",
    "addr:postcode":"54481",
    "addr:street":"Co Rd",
    "iso:country":"US",
    "sg:address":"4902 Co Rd Hh",
    "sg:city":"Stevens Point",
    "sg:classifiers":[
        {
            "category":"Organizations",
            "subcategory":"Religious Organization",
            "type":"Services"
        }
    ],
    "sg:phone":"+1 715 341 6612",
    "sg:postcode":"54481",
    "sg:province":"WI",
    "sg:tags":[
        "school",
        "church"
    ],
    "wof:name":"Greater Point Baptist Church",
    "wof:placetype":"venue"
},
  "geometry": {"coordinates":[-89.52843799999999,44.497229],"type":"Point"}
}