{
  "type": "Feature",
  "properties": {
    "iso:country":"US",
    "sg:address":"100 Wisconsin River Dr",
    "sg:city":"Port Edwards",
    "sg:classifiers":[
        {
            "category":"Building & Trades",
            "subcategory":"Electrical",
            "type":"Services"
        }
    ],
    "sg:phone":"+1 715 887 2969",
    "sg:postcode":"54469",
    "sg:province":"WI",
    "sg:tags":[
        "electric",
        "contractor"
    ],
    "wof:name":"Van Ert Electric",
    "wof:placetype":"venue"
},
  "geometry": {"coordinates":[-89.87047,44.336823],"type":"Point"}
}