{
  "type": "Feature",
  "properties": {
    "iso:country":"US",
    "sg:address":"104 E Division St",
    "sg:city":"Watertown",
    "sg:classifiers":[
        {
            "category":"Wholesale",
            "subcategory":"Meat",
            "type":"Manufacturing & Wholesale Goods"
        }
    ],
    "sg:phone":"+1 920 261 1053",
    "sg:postcode":"53098",
    "sg:province":"WI",
    "sg:tags":[
        "packer"
    ],
    "wof:name":"Johnsonville Foods",
    "wof:placetype":"venue"
},
  "geometry": {"coordinates":[-88.722828,43.197536],"type":"Point"}
}