{
  "type": "Feature",
  "properties": {
    "iso:country":"US",
    "sg:address":"10949 Tritz Rd",
    "sg:city":"Portage",
    "sg:classifiers":[
        {
            "category":"Retail",
            "subcategory":"Auto Repair",
            "type":"Services"
        }
    ],
    "sg:phone":"+1 608 742 3573",
    "sg:postcode":"53901",
    "sg:province":"WI",
    "sg:tags":[
        "general"
    ],
    "wof:name":"Daves Repair",
    "wof:placetype":"venue"
},
  "geometry": {"coordinates":[-89.54667,43.522124],"type":"Point"}
}