{
  "type": "Feature",
  "properties": {
    "iso:country":"US",
    "sg:address":"1831 N Central Ave",
    "sg:city":"Marshfield",
    "sg:classifiers":[
        {
            "category":"Shopping",
            "subcategory":"Discount & Variety Stores",
            "type":"Retail Goods"
        }
    ],
    "sg:phone":"+1 715 387 3409",
    "sg:postcode":"54449",
    "sg:province":"WI",
    "sg:website":"www.dollartree.com",
    "wof:name":"Dollar Tree",
    "wof:placetype":"venue"
},
  "geometry": {"coordinates":[-90.159778,44.686018],"type":"Point"}
}