{
  "type": "Feature",
  "properties": {
    "addr:full":"11290 Claywood Rd Gillett WI 54124",
    "addr:postcode":"11290;54124",
    "addr:street":"Claywood Rd",
    "iso:country":"US",
    "sg:address":"11290 Claywood Rd",
    "sg:city":"Gillett",
    "sg:classifiers":[
        {
            "category":"Farming",
            "subcategory":"Dairy Farm",
            "type":"Manufacturing & Wholesale Goods"
        }
    ],
    "sg:phone":"+1 920 842 2433",
    "sg:postcode":"54124",
    "sg:province":"WI",
    "wof:name":"Julius Ondik",
    "wof:placetype":"venue"
},
  "geometry": {"coordinates":[-88.3125,44.969254],"type":"Point"}
}