{
  "type": "Feature",
  "properties": {
    "iso:country":"US",
    "sg:address":"1945 W Snell Rd",
    "sg:city":"Oshkosh",
    "sg:classifiers":[
        {
            "category":"Manufacturing",
            "subcategory":"Metals",
            "type":"Manufacturing & Wholesale Goods"
        }
    ],
    "sg:phone":"+1 920 231 6060",
    "sg:postcode":"54901",
    "sg:province":"WI",
    "sg:tags":[
        "steel"
    ],
    "sg:website":"www.mathfab.com",
    "wof:name":"John Mathwig & Sons Inc",
    "wof:placetype":"venue"
},
  "geometry": {"coordinates":[-88.570251,44.064503],"type":"Point"}
}