{
  "type": "Feature",
  "properties": {
    "iso:country":"US",
    "sg:address":"5200 W Ashland Way",
    "sg:city":"Franklin",
    "sg:classifiers":[
        {
            "category":"Professional",
            "subcategory":"Research",
            "type":"Services"
        }
    ],
    "sg:phone":"+1 414 235 3767",
    "sg:postcode":"53132",
    "sg:province":"WI",
    "sg:tags":[
        "information",
        "medical"
    ],
    "wof:name":"Microbial Discovery Group",
    "wof:placetype":"venue"
},
  "geometry": {"coordinates":[-87.980881,42.870628],"type":"Point"}
}