{
  "type": "Feature",
  "properties": {
    "iso:country":"US",
    "sg:address":"125 Grand Ave E",
    "sg:city":"Rosholt",
    "sg:classifiers":[
        {
            "category":"Government",
            "subcategory":"Office",
            "type":"Public Place"
        }
    ],
    "sg:phone":"+1 715 677 4510",
    "sg:postcode":"54473",
    "sg:province":"WI",
    "sg:tags":[
        "village"
    ],
    "wof:name":"Rosholt Village Mntnc Shop",
    "wof:placetype":"venue"
},
  "geometry": {"coordinates":[-89.307681,44.627721],"type":"Point"}
}