{
  "type": "Feature",
  "properties": {
    "iso:country":"US",
    "sg:address":"2301 S 108th St",
    "sg:city":"Milwaukee",
    "sg:classifiers":[
        {
            "category":"Health Services",
            "subcategory":"Dentist",
            "type":"Services"
        }
    ],
    "sg:phone":"+1 414 321 6309",
    "sg:postcode":"53227",
    "sg:province":"WI",
    "sg:tags":[
        "product",
        "whitening",
        "teeth"
    ],
    "wof:name":"Art & Science Of Dentistry",
    "wof:placetype":"venue"
},
  "geometry": {"coordinates":[-88.047043,43.002491],"type":"Point"}
}