{
  "type": "Feature",
  "properties": {
    "iso:country":"US",
    "sg:address":"411 Amanda St",
    "sg:city":"Burlington",
    "sg:classifiers":[
        {
            "category":"Organizations",
            "subcategory":"Membership Organization",
            "type":"Services"
        }
    ],
    "sg:phone":"+1 262 763 2566",
    "sg:postcode":"53105",
    "sg:province":"WI",
    "wof:name":"Burlington Bowling Association",
    "wof:placetype":"venue"
},
  "geometry": {"coordinates":[-88.287826,42.680574],"type":"Point"}
}