{
  "type": "Feature",
  "properties": {
    "addr:full":"18609 Swenson Ln Ettrick WI 54627",
    "addr:housenumber":"18609",
    "addr:postcode":"54627",
    "addr:street":"Swenson Ln",
    "iso:country":"US",
    "sg:address":"18609 Swenson Ln",
    "sg:city":"Ettrick",
    "sg:phone":"+1 608 582 2322",
    "sg:postcode":"54627",
    "sg:province":"WI",
    "sg:tags":[
        "farm"
    ],
    "wof:name":"Paul Bibby",
    "wof:placetype":"venue"
},
  "geometry": {"coordinates":[-91.18207,44.108509],"type":"Point"}
}