{
  "type": "Feature",
  "properties": {
    "iso:country":"US",
    "sg:address":"9033 Worm Rd",
    "sg:city":"New London",
    "sg:classifiers":[
        {
            "category":"Retail",
            "subcategory":"Repair Shop",
            "type":"Services"
        }
    ],
    "sg:phone":"+1 920 982 6674",
    "sg:postcode":"54961",
    "sg:province":"WI",
    "wof:name":"New London Small Engine Svc",
    "wof:placetype":"venue"
},
  "geometry": {"coordinates":[-88.77152,44.438076],"type":"Point"}
}