{
  "type": "Feature",
  "properties": {
    "iso:country":"US",
    "sg:address":"601 E View Ct",
    "sg:city":"Verona",
    "sg:classifiers":[
        {
            "category":"Building & Trades",
            "subcategory":"Construction",
            "type":"Services"
        }
    ],
    "sg:phone":"+1 608 845 8629",
    "sg:postcode":"53593",
    "sg:province":"WI",
    "sg:tags":[
        "residential"
    ],
    "wof:name":"Rod Hanson Builders LLC",
    "wof:placetype":"venue"
},
  "geometry": {"coordinates":[-89.524174,42.981964],"type":"Point"}
}