{
  "type": "Feature",
  "properties": {
    "iso:country":"US",
    "sg:address":"6661 University Ave",
    "sg:city":"Middleton",
    "sg:classifiers":[
        {
            "category":"Professional",
            "subcategory":"Printing & Photocopies",
            "type":"Services"
        }
    ],
    "sg:phone":"+1 608 831 3322",
    "sg:postcode":"53562",
    "sg:province":"WI",
    "sg:tags":[
        "photocopying",
        "typesetting"
    ],
    "wof:name":"Econoprint",
    "wof:placetype":"venue"
},
  "geometry": {"coordinates":[-89.494251,43.095315],"type":"Point"}
}