{
  "type": "Feature",
  "properties": {
    "iso:country":"US",
    "sg:address":"10554 Prairie Rd",
    "sg:city":"Prairie Du Sac",
    "sg:classifiers":[
        {
            "category":"Farming",
            "subcategory":"Dairy Farm",
            "type":"Manufacturing & Wholesale Goods"
        }
    ],
    "sg:phone":"+1 608 643 8060",
    "sg:postcode":"53578",
    "sg:province":"WI",
    "wof:name":"Grandview Dairy Farm",
    "wof:placetype":"venue"
},
  "geometry": {"coordinates":[-89.808919,43.305991],"type":"Point"}
}