{
  "type": "Feature",
  "properties": {
    "addr:full":"13635 Cedar Lake Rd Kiel WI 53042",
    "addr:housenumber":"13635",
    "addr:postcode":"53042",
    "addr:street":"Cedar Lake Rd",
    "iso:country":"US",
    "sg:address":"13635 Cedar Lake Rd",
    "sg:city":"Kiel",
    "sg:classifiers":[
        {
            "category":"Building & Trades",
            "subcategory":"Cleaning & Sanitation",
            "type":"Services"
        }
    ],
    "sg:phone":"+1 920 894 3462",
    "sg:postcode":"53042",
    "sg:province":"WI",
    "sg:tags":[
        "maintenance"
    ],
    "wof:name":"Renu Air",
    "wof:placetype":"venue"
},
  "geometry": {"coordinates":[-87.942165,43.932324],"type":"Point"}
}