{
  "type": "Feature",
  "properties": {
    "iso:country":"US",
    "sg:address":"2121 S Kinnickinnic Ave Suite 7",
    "sg:city":"Milwaukee",
    "sg:classifiers":[
        {
            "category":"Insurance",
            "subcategory":"Hazard Insurance",
            "type":"Services"
        },
        {
            "category":"Insurance",
            "subcategory":"Insurance Agent",
            "type":"Services"
        },
        {
            "category":"Insurance",
            "subcategory":"Life Insurance",
            "type":"Services"
        }
    ],
    "sg:phone":"+1 414 483 3300",
    "sg:postcode":"53207",
    "sg:province":"WI",
    "sg:tags":[
        "auto"
    ],
    "sg:website":"http://statefarm.mqgroup.com/url.asp?usr=496345",
    "wof:name":"Aldrich, Sean T - State Farm Insurance Agent",
    "wof:placetype":"venue"
},
  "geometry": {"coordinates":[-87.906462,43.005673],"type":"Point"}
}