{
  "type": "Feature",
  "properties": {
    "iso:country":"US",
    "sg:address":"1001 US Hwy 14",
    "sg:city":"Janesville",
    "sg:classifiers":[
        {
            "category":"Freight",
            "type":"Transportation"
        }
    ],
    "sg:phone":"+1 608 868 1611",
    "sg:postcode":"53546",
    "sg:province":"WI",
    "sg:tags":[
        "commercial",
        "storage"
    ],
    "wof:name":"Eastside Storage Of Janesville",
    "wof:placetype":"venue"
},
  "geometry": {"coordinates":[-88.953789,42.694254],"type":"Point"}
}