{
  "type": "Feature",
  "properties": {
    "iso:country":"US",
    "sg:address":"210 S Main St",
    "sg:city":"Brillion",
    "sg:classifiers":[
        {
            "category":"Manufacturing",
            "subcategory":"Motor Vehicles & Parts",
            "type":"Manufacturing & Wholesale Goods"
        }
    ],
    "sg:phone":"+1 920 756 2720",
    "sg:postcode":"54110",
    "sg:province":"WI",
    "sg:tags":[
        "trim",
        "mfg"
    ],
    "wof:name":"Bullseye Screen Printing LLC",
    "wof:placetype":"venue"
},
  "geometry": {"coordinates":[-88.064148,44.175478],"type":"Point"}
}