{
  "type": "Feature",
  "properties": {
    "iso:country":"US",
    "sg:address":"310 W Lexington Blvd",
    "sg:city":"Milwaukee",
    "sg:classifiers":[
        {
            "category":"Professional",
            "subcategory":"Management & Consulting",
            "type":"Services"
        }
    ],
    "sg:phone":"+1 414 229 3949",
    "sg:postcode":"53217",
    "sg:province":"WI",
    "wof:name":"Jonathan Kahl",
    "wof:placetype":"venue"
},
  "geometry": {"coordinates":[-87.914061,43.113382],"type":"Point"}
}