{
  "type": "Feature",
  "properties": {
    "iso:country":"US",
    "sg:address":"206 Lake Dr",
    "sg:city":"Merrillan",
    "sg:classifiers":[
        {
            "category":"Building & Trades",
            "subcategory":"Construction",
            "type":"Services"
        }
    ],
    "sg:phone":"+1 715 333 2817",
    "sg:postcode":"54754",
    "sg:province":"WI",
    "sg:tags":[
        "house",
        "carpentry",
        "contractor"
    ],
    "wof:name":"JC Carpentry",
    "wof:placetype":"venue"
},
  "geometry": {"coordinates":[-90.827466,44.43768],"type":"Point"}
}