{
  "type": "Feature",
  "properties": {
    "iso:country":"US",
    "sg:address":"2613 N Dohs Rd",
    "sg:city":"Evansville",
    "sg:classifiers":[
        {
            "category":"Farming",
            "subcategory":"Farm",
            "type":"Manufacturing & Wholesale Goods"
        }
    ],
    "sg:phone":"+1 608 876 6587",
    "sg:postcode":"53536",
    "sg:province":"WI",
    "sg:tags":[
        "crop",
        "general"
    ],
    "wof:name":"David Rowley",
    "wof:placetype":"venue"
},
  "geometry": {"coordinates":[-89.230217,42.722779],"type":"Point"}
}