{
  "type": "Feature",
  "properties": {
    "iso:country":"US",
    "sg:address":"2241 Main St",
    "sg:city":"Green Bay",
    "sg:classifiers":[
        {
            "category":"Restaurant",
            "type":"Food & Drink"
        }
    ],
    "sg:phone":"+1 920 468 8833",
    "sg:postcode":"54302",
    "sg:province":"WI",
    "sg:tags":[
        "eating"
    ],
    "wof:name":"China Buffet",
    "wof:placetype":"venue"
},
  "geometry": {"coordinates":[-87.970794,44.484583],"type":"Point"}
}