{
  "type": "Feature",
  "properties": {
    "iso:country":"US",
    "sg:address":"13307 Watertown Plank Rd",
    "sg:city":"Elm Grove",
    "sg:classifiers":[
        {
            "category":"Professional",
            "type":"Services"
        }
    ],
    "sg:phone":"+1 262 783 6333",
    "sg:postcode":"53122",
    "sg:province":"WI",
    "wof:name":"Society of Tympanuchus Cupido",
    "wof:placetype":"venue"
},
  "geometry": {"coordinates":[-88.07849,43.043284],"type":"Point"}
}