{
  "type": "Feature",
  "properties": {
    "iso:country":"US",
    "sg:address":"6741 Odana Rd",
    "sg:city":"Madison",
    "sg:classifiers":[
        {
            "category":"Shopping",
            "subcategory":"Crafts & Fabrics",
            "type":"Retail Goods"
        }
    ],
    "sg:phone":"+1 608 826 4030",
    "sg:postcode":"53719",
    "sg:province":"WI",
    "sg:tags":[
        "shop"
    ],
    "sg:website":"www.joann.com",
    "wof:name":"Jo-Ann Fabrics & Crafts",
    "wof:placetype":"venue"
},
  "geometry": {"coordinates":[-89.500649,43.056529],"type":"Point"}
}