{
  "type": "Feature",
  "properties": {
    "iso:country":"US",
    "sg:address":"919 Schwartz St",
    "sg:city":"Green Bay",
    "sg:classifiers":[
        {
            "category":"Organizations",
            "subcategory":"Religious Organization",
            "type":"Services"
        }
    ],
    "sg:phone":"+1 920 593 8723",
    "sg:postcode":"54302",
    "sg:province":"WI",
    "sg:tags":[
        "church"
    ],
    "wof:name":"Confraternidad Metodista Unida",
    "wof:placetype":"venue"
},
  "geometry": {"coordinates":[-87.985564,44.489534],"type":"Point"}
}