{
  "type": "Feature",
  "properties": {
    "iso:country":"US",
    "sg:address":"12650 W National Ave",
    "sg:city":"New Berlin",
    "sg:classifiers":[
        {
            "category":"Wholesale",
            "subcategory":"Machinery & Supplies",
            "type":"Manufacturing & Wholesale Goods"
        }
    ],
    "sg:phone":"+1 262 786 1358",
    "sg:postcode":"53151",
    "sg:province":"WI",
    "sg:tags":[
        "truck"
    ],
    "wof:name":"Condiff Trucking Inc",
    "wof:placetype":"venue"
},
  "geometry": {"coordinates":[-88.072383,42.988294],"type":"Point"}
}