{
  "type": "Feature",
  "properties": {
    "addr:full":"309 Radtke St Schofield WI 54476",
    "addr:housenumber":"309",
    "addr:postcode":"54476",
    "addr:street":"Radtke St",
    "iso:country":"US",
    "sg:address":"309 Radtke St",
    "sg:city":"Schofield",
    "sg:classifiers":[
        {
            "category":"Wholesale",
            "subcategory":"Office Equipment",
            "type":"Manufacturing & Wholesale Goods"
        }
    ],
    "sg:phone":"+1 715 359 0347",
    "sg:postcode":"54476",
    "sg:province":"WI",
    "wof:name":"Office Equipment Leasing",
    "wof:placetype":"venue"
},
  "geometry": {"coordinates":[-89.61790999999999,44.919916],"type":"Point"}
}