{
  "type": "Feature",
  "properties": {
    "iso:country":"US",
    "sg:address":"4099 N Shore Dr",
    "sg:city":"Rhinelander",
    "sg:classifiers":[
        {
            "category":"Building & Trades",
            "subcategory":"Construction",
            "type":"Services"
        }
    ],
    "sg:phone":"+1 715 362 5338",
    "sg:postcode":"54501",
    "sg:province":"WI",
    "sg:tags":[
        "company"
    ],
    "wof:name":"Burns Construction",
    "wof:placetype":"venue"
},
  "geometry": {"coordinates":[-89.327272,45.636956],"type":"Point"}
}