{
  "type": "Feature",
  "properties": {
    "iso:country":"US",
    "sg:address":"6701 US Hwy 12",
    "sg:city":"Whitewater",
    "sg:classifiers":[
        {
            "category":"Professional",
            "subcategory":"Computer Services",
            "type":"Services"
        }
    ],
    "sg:phone":"+1 262 495 2972",
    "sg:postcode":"53190",
    "sg:province":"WI",
    "sg:tags":[
        "related"
    ],
    "wof:name":"L & BS Computer Services LLC",
    "wof:placetype":"venue"
},
  "geometry": {"coordinates":[-88.633575,42.796772],"type":"Point"}
}