{
  "type": "Feature",
  "properties": {
    "iso:country":"US",
    "sg:address":"5264 Meridian Ave",
    "sg:city":"Granton",
    "sg:classifiers":[
        {
            "category":"Farming",
            "subcategory":"Dairy Farm",
            "type":"Manufacturing & Wholesale Goods"
        }
    ],
    "sg:phone":"+1 715 238 7225",
    "sg:postcode":"54436",
    "sg:province":"WI",
    "wof:name":"James Sternitzky",
    "wof:placetype":"venue"
},
  "geometry": {"coordinates":[-90.436036,44.608978],"type":"Point"}
}