{
  "type": "Feature",
  "properties": {
    "iso:country":"US",
    "sg:address":"203 Lake St",
    "sg:city":"Pardeeville",
    "sg:classifiers":[
        {
            "category":"Recreation",
            "type":"Entertainment"
        }
    ],
    "sg:phone":"+1 608 429 2000",
    "sg:postcode":"53954",
    "sg:province":"WI",
    "sg:tags":[
        "club",
        "membership"
    ],
    "wof:name":"Pardeeville Curling Club",
    "wof:placetype":"venue"
},
  "geometry": {"coordinates":[-89.298387,43.537985],"type":"Point"}
}