{
  "type": "Feature",
  "properties": {
    "iso:country":"US",
    "sg:address":"135 W Stoney Ridge Way",
    "sg:city":"Saukville",
    "sg:classifiers":[
        {
            "category":"Professional",
            "subcategory":"Employment Agencies",
            "type":"Services"
        }
    ],
    "sg:phone":"+1 262 268 8060",
    "sg:postcode":"53080",
    "sg:province":"WI",
    "wof:name":"J M Eagle Partners Ltd",
    "wof:placetype":"venue"
},
  "geometry": {"coordinates":[-87.942519,43.38589],"type":"Point"}
}