{
  "type": "Feature",
  "properties": {
    "iso:country":"US",
    "sg:address":"1901 12th St",
    "sg:city":"Racine",
    "sg:classifiers":[
        {
            "category":"Education",
            "subcategory":"School",
            "type":"Public Place"
        }
    ],
    "sg:phone":"+1 262 619 4400",
    "sg:postcode":"53403",
    "sg:province":"WI",
    "wof:name":"Washington Park High School",
    "wof:placetype":"venue"
},
  "geometry": {"coordinates":[-87.805377,42.718747],"type":"Point"}
}