{
  "type": "Feature",
  "properties": {
    "addr:full":"30040 Mount Tom Rd Burlington WI 53105",
    "addr:housenumber":"30040",
    "addr:postcode":"53105",
    "addr:street":"Mount Tom Rd",
    "iso:country":"US",
    "sg:address":"30040 Mount Tom Rd",
    "sg:city":"Burlington",
    "sg:classifiers":[
        {
            "category":"Local Transit",
            "type":"Transportation"
        }
    ],
    "sg:phone":"+1 262 539 3470",
    "sg:postcode":"53105",
    "sg:province":"WI",
    "sg:tags":[
        "tanner"
    ],
    "wof:name":"Berndt's Hide Service",
    "wof:placetype":"venue"
},
  "geometry": {"coordinates":[-88.233126,42.666329],"type":"Point"}
}