{
  "type": "Feature",
  "properties": {
    "addr:full":"23 E Oak St Sturgeon Bay WI 54235",
    "addr:housenumber":"23",
    "addr:postcode":"54235",
    "addr:street":"E Oak St",
    "iso:country":"US",
    "sg:address":"23 E Oak St",
    "sg:city":"Sturgeon Bay",
    "sg:classifiers":[
        {
            "category":"Shopping",
            "subcategory":"Computers & Home Electronics",
            "type":"Retail Goods"
        }
    ],
    "sg:phone":"+1 920 743 0190",
    "sg:postcode":"54235",
    "sg:province":"WI",
    "sg:tags":[
        "communications",
        "radio",
        "navigation"
    ],
    "wof:name":"Bay Electronics Inc",
    "wof:placetype":"venue"
},
  "geometry": {"coordinates":[-87.384084,44.827852],"type":"Point"}
}