{
  "type": "Feature",
  "properties": {
    "iso:country":"US",
    "sg:address":"251 E Main St",
    "sg:city":"Reedsburg",
    "sg:classifiers":[
        {
            "category":"Manufacturing",
            "subcategory":"Retail Goods",
            "type":"Manufacturing & Wholesale Goods"
        }
    ],
    "sg:phone":"+1 608 524 3220",
    "sg:postcode":"53959",
    "sg:province":"WI",
    "sg:tags":[
        "screen",
        "printing",
        "mfg"
    ],
    "wof:name":"Club Doctor",
    "wof:placetype":"venue"
},
  "geometry": {"coordinates":[-90.007265,43.532575],"type":"Point"}
}