{
  "type": "Feature",
  "properties": {
    "iso:country":"US",
    "sg:address":"3861 Fairview Rd",
    "sg:city":"Edgar",
    "sg:classifiers":[
        {
            "category":"Farming",
            "subcategory":"Dairy Farm",
            "type":"Manufacturing & Wholesale Goods"
        }
    ],
    "sg:phone":"+1 715 687 2337",
    "sg:postcode":"54426",
    "sg:province":"WI",
    "wof:name":"Nick Cafarella",
    "wof:placetype":"venue"
},
  "geometry": {"coordinates":[-89.90078099999999,44.815391],"type":"Point"}
}