{
  "type": "Feature",
  "properties": {
    "iso:country":"US",
    "sg:address":"146 Briar Dr",
    "sg:city":"Neenah",
    "sg:classifiers":[
        {
            "category":"Insurance",
            "subcategory":"Insurance Agent",
            "type":"Services"
        }
    ],
    "sg:phone":"+1 920 727 9913",
    "sg:postcode":"54956",
    "sg:province":"WI",
    "wof:name":"Dubois Consulting",
    "wof:placetype":"venue"
},
  "geometry": {"coordinates":[-88.507174,44.166697],"type":"Point"}
}