{
  "type": "Feature",
  "properties": {
    "iso:country":"US",
    "sg:address":"1436 E North Ave",
    "sg:city":"Milwaukee",
    "sg:classifiers":[
        {
            "category":"Autos & Motor Vehicles",
            "subcategory":"Fuel & Gas Station",
            "type":"Retail Goods"
        }
    ],
    "sg:phone":"+1 414 225 9899",
    "sg:postcode":"53202",
    "sg:province":"WI",
    "sg:tags":[
        "oil"
    ],
    "wof:name":"Hometown Prince Auto",
    "wof:placetype":"venue"
},
  "geometry": {"coordinates":[-87.892568,43.060233],"type":"Point"}
}