{
  "type": "Feature",
  "properties": {
    "iso:country":"US",
    "sg:address":"8672 Gohr Rd",
    "sg:city":"Krakow",
    "sg:classifiers":[
        {
            "category":"Real Estate",
            "subcategory":"Real Estate Operator",
            "type":"Services"
        }
    ],
    "sg:phone":"+1 920 899 3883",
    "sg:postcode":"54137",
    "sg:province":"WI",
    "sg:tags":[
        "property",
        "lessor"
    ],
    "wof:name":"Mark Vandonsal",
    "wof:placetype":"venue"
},
  "geometry": {"coordinates":[-88.200096,44.752038],"type":"Point"}
}