{
  "type": "Feature",
  "properties": {
    "addr:full":"802 E 2nd Ave Brodhead WI 53520",
    "addr:housenumber":"802",
    "addr:postcode":"53520",
    "addr:street":"E 2Nd Ave",
    "iso:country":"US",
    "sg:address":"802 E 2nd Ave",
    "sg:city":"Brodhead",
    "sg:classifiers":[
        {
            "category":"Retail",
            "subcategory":"Auto Repair",
            "type":"Services"
        }
    ],
    "sg:phone":"+1 608 897 4374",
    "sg:postcode":"53520",
    "sg:province":"WI",
    "sg:tags":[
        "automotive"
    ],
    "wof:name":"Abbs Towing & Service",
    "wof:placetype":"venue"
},
  "geometry": {"coordinates":[-89.375522,42.622646],"type":"Point"}
}