{
  "type": "Feature",
  "properties": {
    "addr:full":"176 State Hwy 155 Sayner WI 54560",
    "addr:housenumber":"176",
    "addr:postcode":"54560",
    "addr:street":"State Hwy 155",
    "iso:country":"US",
    "sg:address":"176 State Hwy 155",
    "sg:city":"Sayner",
    "sg:classifiers":[
        {
            "category":"Utilities",
            "subcategory":"Natural Gas",
            "type":"Services"
        }
    ],
    "sg:phone":"+1 715 542 3292",
    "sg:postcode":"54560",
    "sg:province":"WI",
    "sg:tags":[
        "company"
    ],
    "wof:name":"Ace-Hi Bottled Gas Inc",
    "wof:placetype":"venue"
},
  "geometry": {"coordinates":[-89.52924299999999,45.983863],"type":"Point"}
}