{
  "type": "Feature",
  "properties": {
    "addr:full":"5030 N 91st St Milwaukee WI 53225",
    "addr:housenumber":"5030",
    "addr:postcode":"53225",
    "addr:street":"N 91St St",
    "iso:country":"US",
    "sg:address":"5030 N 91st St",
    "sg:city":"Milwaukee",
    "sg:classifiers":[
        {
            "category":"Building & Trades",
            "subcategory":"Landscaping Services",
            "type":"Services"
        }
    ],
    "sg:phone":"+1 414 527 1952",
    "sg:postcode":"53225",
    "sg:province":"WI",
    "sg:tags":[
        "lawn",
        "maintenance",
        "grounds"
    ],
    "wof:name":"Ken Swan Lawn Maintenance",
    "wof:placetype":"venue"
},
  "geometry": {"coordinates":[-88.02585999999999,43.111972],"type":"Point"}
}