{
  "type": "Feature",
  "properties": {
    "iso:country":"US",
    "sg:address":"2111 56th St",
    "sg:city":"Kenosha",
    "sg:classifiers":[
        {
            "category":"Autos & Motor Vehicles",
            "subcategory":"Automobile Sales",
            "type":"Retail Goods"
        }
    ],
    "sg:phone":"+1 262 656 0107",
    "sg:postcode":"53140",
    "sg:province":"WI",
    "sg:tags":[
        "car",
        "dealer"
    ],
    "wof:name":"Mike's Auto Wholesaling",
    "wof:placetype":"venue"
},
  "geometry": {"coordinates":[-87.834626,42.583509],"type":"Point"}
}