{
  "type": "Feature",
  "properties": {
    "addr:full":"4991 S US Hwy 45 Oshkosh WI 54902",
    "addr:housenumber":"4991",
    "addr:postcode":"54902",
    "addr:street":"S Us Hwy 45",
    "iso:country":"US",
    "sg:address":"4991 S US Hwy 45",
    "sg:city":"Oshkosh",
    "sg:classifiers":[
        {
            "category":"Education",
            "subcategory":"School",
            "type":"Public Place"
        }
    ],
    "sg:phone":"+1 920 424 0131",
    "sg:postcode":"54902",
    "sg:province":"WI",
    "sg:tags":[
        "elementary"
    ],
    "wof:name":"Lakeside Elementary School",
    "wof:placetype":"venue"
},
  "geometry": {"coordinates":[-88.510757,43.950103],"type":"Point"}
}