{
  "type": "Feature",
  "properties": {
    "addr:full":"725n Woodlake Rd Kohler WI 53044",
    "addr:housenumber":"725n",
    "addr:postcode":"53044",
    "addr:street":"Woodlake Rd",
    "iso:country":"US",
    "sg:address":"725n Woodlake Rd",
    "sg:city":"Kohler",
    "sg:classifiers":[
        {
            "category":"Restaurant",
            "type":"Food & Drink"
        }
    ],
    "sg:menulink":"http://www.allmenus.com/wi/kohler/139256-quiznos-sub/menu/",
    "sg:phone":"+1 920 453 9787",
    "sg:postcode":"53044",
    "sg:province":"WI",
    "sg:tags":[
        "wrap",
        "american",
        "sandwich"
    ],
    "wof:name":"Quiznos Sub",
    "wof:placetype":"venue"
},
  "geometry": {"coordinates":[-87.780889,43.748602],"type":"Point"}
}