{
  "type": "Feature",
  "properties": {
    "addr:full":"10474 S 92nd St Franklin WI 53132",
    "addr:housenumber":"10474",
    "addr:postcode":"53132",
    "addr:street":"S 92Nd St",
    "iso:country":"US",
    "sg:address":"10474 S 92nd St",
    "sg:city":"Franklin",
    "sg:classifiers":[
        {
            "category":"Professional",
            "type":"Services"
        }
    ],
    "sg:phone":"+1 414 425 4969",
    "sg:postcode":"53132",
    "sg:province":"WI",
    "sg:tags":[
        "writer"
    ],
    "wof:name":"Veracitech Inc",
    "wof:placetype":"venue"
},
  "geometry": {"coordinates":[-88.030399,42.846661],"type":"Point"}
}