{
  "type": "Feature",
  "properties": {
    "iso:country":"US",
    "sg:address":"2823 Lathrop Ave",
    "sg:city":"Racine",
    "sg:classifiers":[
        {
            "category":"Banks & Credit Unions",
            "subcategory":"Bank",
            "type":"Services"
        }
    ],
    "sg:phone":"+1 262 633 3505",
    "sg:postcode":"53405",
    "sg:province":"WI",
    "sg:tags":[
        "financing"
    ],
    "wof:name":"Motor Credit Corp",
    "wof:placetype":"venue"
},
  "geometry": {"coordinates":[-87.825859,42.697446],"type":"Point"}
}