{
  "type": "Feature",
  "properties": {
    "addr:full":"9404 State Hwy 16 Onalaska WI 54650",
    "addr:housenumber":"9404",
    "addr:postcode":"54650",
    "addr:street":"State Hwy 16",
    "iso:country":"US",
    "sg:address":"9404 State Hwy 16",
    "sg:city":"Onalaska",
    "sg:classifiers":[
        {
            "category":"Shopping",
            "subcategory":"Department Store",
            "type":"Retail Goods"
        }
    ],
    "sg:phone":"+1 608 783 3800",
    "sg:postcode":"54650",
    "sg:province":"WI",
    "sg:website":"www.kohls.com",
    "wof:name":"Kohl's",
    "wof:placetype":"venue"
},
  "geometry": {"coordinates":[-91.19486499999999,43.871332],"type":"Point"}
}