{
  "type": "Feature",
  "properties": {
    "iso:country":"US",
    "sg:address":"303 E Stanley St",
    "sg:city":"Thorp",
    "sg:classifiers":[
        {
            "category":"Autos & Motor Vehicles",
            "subcategory":"Automobile Sales",
            "type":"Retail Goods"
        }
    ],
    "sg:phone":"+1 715 669 3891",
    "sg:postcode":"54771",
    "sg:province":"WI",
    "sg:tags":[
        "automotive",
        "used"
    ],
    "wof:name":"S & K Enterprises",
    "wof:placetype":"venue"
},
  "geometry": {"coordinates":[-90.797388,44.959245],"type":"Point"}
}