{
  "type": "Feature",
  "properties": {
    "iso:country":"US",
    "sg:address":"2601 Finger Rd",
    "sg:city":"Green Bay",
    "sg:classifiers":[
        {
            "category":"Freight",
            "type":"Transportation"
        }
    ],
    "sg:phone":"+1 920 468 6869",
    "sg:postcode":"54302",
    "sg:province":"WI",
    "sg:tags":[
        "logistics",
        "arrangement"
    ],
    "wof:name":"Transportation Marketing Svcs",
    "wof:placetype":"venue"
},
  "geometry": {"coordinates":[-87.952634,44.488246],"type":"Point"}
}