{
  "type": "Feature",
  "properties": {
    "addr:full":"5960 W Brown Deer Rd Milwaukee WI 53223",
    "addr:housenumber":"5960",
    "addr:postcode":"53223",
    "addr:street":"W Brown Deer Rd",
    "iso:country":"US",
    "sg:address":"5960 W Brown Deer Rd",
    "sg:city":"Milwaukee",
    "sg:classifiers":[
        {
            "category":"Health Services",
            "subcategory":"Clinic",
            "type":"Services"
        }
    ],
    "sg:phone":"+1 414 354 2171",
    "sg:postcode":"53223",
    "sg:province":"WI",
    "sg:tags":[
        "banks",
        "blood",
        "center"
    ],
    "wof:name":"Blood Center",
    "wof:placetype":"venue"
},
  "geometry": {"coordinates":[-87.98073599999999,43.177747],"type":"Point"}
}