{
  "type": "Feature",
  "properties": {
    "iso:country":"US",
    "sg:address":"113 W Main St",
    "sg:city":"Twin Lakes",
    "sg:classifiers":[
        {
            "category":"Building & Trades",
            "subcategory":"Plumbing",
            "type":"Services"
        }
    ],
    "sg:phone":"+1 262 877 3100",
    "sg:postcode":"53181",
    "sg:province":"WI",
    "sg:tags":[
        "heating",
        "contractor"
    ],
    "wof:name":"Keith Magnuson",
    "wof:placetype":"venue"
},
  "geometry": {"coordinates":[-88.256377,42.530923],"type":"Point"}
}