{
  "type": "Feature",
  "properties": {
    "iso:country":"US",
    "sg:address":"1229 12th Ave",
    "sg:city":"Grafton",
    "sg:classifiers":[
        {
            "category":"Shopping",
            "subcategory":"Gifts & Souvenirs",
            "type":"Retail Goods"
        }
    ],
    "sg:phone":"+1 262 376 7710",
    "sg:postcode":"53024",
    "sg:province":"WI",
    "sg:tags":[
        "shop"
    ],
    "wof:name":"Inspiration Past & Present",
    "wof:placetype":"venue"
},
  "geometry": {"coordinates":[-87.95179,43.318921],"type":"Point"}
}