{
  "type": "Feature",
  "properties": {
    "iso:country":"US",
    "sg:address":"4655 W Oakwood Park Dr",
    "sg:city":"Franklin",
    "sg:classifiers":[
        {
            "category":"Shopping",
            "subcategory":"Crafts & Fabrics",
            "type":"Retail Goods"
        }
    ],
    "sg:phone":"+1 414 235 4299",
    "sg:postcode":"53132",
    "sg:province":"WI",
    "sg:tags":[
        "adhesive",
        "glue"
    ],
    "wof:name":"BC Adhesives",
    "wof:placetype":"venue"
},
  "geometry": {"coordinates":[-87.975121,42.860914],"type":"Point"}
}