{
  "type": "Feature",
  "properties": {
    "iso:country":"US",
    "sg:address":"1101 W Park Ave",
    "sg:city":"Kiel",
    "sg:classifiers":[
        {
            "category":"Manufacturing",
            "subcategory":"Metals",
            "type":"Manufacturing & Wholesale Goods"
        }
    ],
    "sg:phone":"+1 920 894 2232",
    "sg:postcode":"53042",
    "sg:province":"WI",
    "sg:tags":[
        "fabricator",
        "sheet"
    ],
    "wof:name":"Custom Fabricators Inc",
    "wof:placetype":"venue"
},
  "geometry": {"coordinates":[-88.046195,43.92102],"type":"Point"}
}