{
  "type": "Feature",
  "properties": {
    "iso:country":"US",
    "sg:address":"2565 Co Hwy M",
    "sg:city":"Spooner",
    "sg:classifiers":[
        {
            "category":"Building & Trades",
            "subcategory":"Construction",
            "type":"Services"
        }
    ],
    "sg:phone":"+1 715 635 6556",
    "sg:postcode":"54801",
    "sg:province":"WI",
    "sg:tags":[
        "contractor",
        "carpentry"
    ],
    "wof:name":"K C Woodworkers",
    "wof:placetype":"venue"
},
  "geometry": {"coordinates":[-91.680012,45.870076],"type":"Point"}
}