{
  "type": "Feature",
  "properties": {
    "iso:country":"US",
    "sg:address":"1856 Jackson St",
    "sg:city":"Oshkosh",
    "sg:classifiers":[
        {
            "category":"Personal",
            "type":"Services"
        }
    ],
    "sg:phone":"+1 920 233 0656",
    "sg:postcode":"54901",
    "sg:province":"WI",
    "sg:tags":[
        "wear",
        "formal"
    ],
    "wof:name":"Nedrebo's Formal Wear",
    "wof:placetype":"venue"
},
  "geometry": {"coordinates":[-88.542548,44.040217],"type":"Point"}
}