{
  "type": "Feature",
  "properties": {
    "iso:country":"US",
    "sg:address":"630 English St",
    "sg:city":"Racine",
    "sg:classifiers":[
        {
            "category":"Building & Trades",
            "subcategory":"Construction",
            "type":"Services"
        }
    ],
    "sg:phone":"+1 262 634 6344",
    "sg:postcode":"53402",
    "sg:province":"WI",
    "sg:tags":[
        "roofing",
        "contractor"
    ],
    "wof:name":"TNT Construction Co",
    "wof:placetype":"venue"
},
  "geometry": {"coordinates":[-87.788263,42.744808],"type":"Point"}
}