{
  "type": "Feature",
  "properties": {
    "iso:country":"US",
    "sg:address":"1 Laredo Ct",
    "sg:city":"Madison",
    "sg:classifiers":[
        {
            "category":"Professional",
            "subcategory":"Management & Consulting",
            "type":"Services"
        }
    ],
    "sg:phone":"+1 608 848 6688",
    "sg:postcode":"53719",
    "sg:province":"WI",
    "sg:tags":[
        "business"
    ],
    "sg:website":"www.collinscoaching.com",
    "wof:name":"Collins Coaching LLC",
    "wof:placetype":"venue"
},
  "geometry": {"coordinates":[-89.50762899999999,43.017545],"type":"Point"}
}