{
  "type": "Feature",
  "properties": {
    "addr:full":"2052 Gross St Green Bay WI 54304",
    "addr:housenumber":"2052",
    "addr:postcode":"54304",
    "addr:street":"Gross St",
    "iso:country":"US",
    "sg:address":"2052 Gross St",
    "sg:city":"Green Bay",
    "sg:classifiers":[
        {
            "category":"Restaurant",
            "type":"Food & Drink"
        }
    ],
    "sg:phone":"+1 920 494 9882",
    "sg:postcode":"54304",
    "sg:province":"WI",
    "sg:tags":[
        "eating"
    ],
    "wof:name":"Skips Place",
    "wof:placetype":"venue"
},
  "geometry": {"coordinates":[-88.055155,44.495791],"type":"Point"}
}