{
  "type": "Feature",
  "properties": {
    "addr:full":"300 3rd St Pepin WI 54759",
    "addr:housenumber":"300",
    "addr:postcode":"54759",
    "addr:street":"3Rd St",
    "iso:country":"US",
    "sg:address":"300 3rd St",
    "sg:city":"Pepin",
    "sg:classifiers":[
        {
            "category":"Autos & Motor Vehicles",
            "subcategory":"Fuel & Gas Station",
            "type":"Retail Goods"
        }
    ],
    "sg:phone":"+1 715 442 3033",
    "sg:postcode":"54759",
    "sg:province":"WI",
    "sg:tags":[
        "oil"
    ],
    "wof:name":"River Road Amoco",
    "wof:placetype":"venue"
},
  "geometry": {"coordinates":[-92.14619999999999,44.440732],"type":"Point"}
}