{
  "type": "Feature",
  "properties": {
    "iso:country":"US",
    "sg:address":"610 N Summit Ave",
    "sg:city":"Oconomowoc",
    "sg:classifiers":[
        {
            "category":"Shopping",
            "subcategory":"Optical Goods",
            "type":"Retail Goods"
        }
    ],
    "sg:phone":"+1 262 567 9700",
    "sg:postcode":"53066",
    "sg:province":"WI",
    "wof:name":"Boutique Optique",
    "wof:placetype":"venue"
},
  "geometry": {"coordinates":[-88.462261,43.029708],"type":"Point"}
}