{
  "type": "Feature",
  "properties": {
    "iso:country":"US",
    "sg:address":"109 N Wacouta Ave",
    "sg:city":"Prairie Du Chien",
    "sg:classifiers":[
        {
            "category":"Banks & Credit Unions",
            "subcategory":"Bank",
            "type":"Services"
        }
    ],
    "sg:phone":"+1 608 326 1715",
    "sg:postcode":"53821",
    "sg:province":"WI",
    "wof:name":"Wisconsin State Bank",
    "wof:placetype":"venue"
},
  "geometry": {"coordinates":[-91.145239,43.05382],"type":"Point"}
}