{
  "type": "Feature",
  "properties": {
    "iso:country":"US",
    "sg:address":"322 E Michigan St",
    "sg:city":"Milwaukee",
    "sg:classifiers":[
        {
            "category":"Banks & Credit Unions",
            "subcategory":"Financial Services",
            "type":"Services"
        }
    ],
    "sg:phone":"+1 414 273 4350",
    "sg:postcode":"53202",
    "sg:province":"WI",
    "sg:tags":[
        "manager",
        "investment",
        "real estate"
    ],
    "wof:name":"Market Street Investors Inc",
    "wof:placetype":"venue"
},
  "geometry": {"coordinates":[-87.906679,43.037565],"type":"Point"}
}