{
  "type": "Feature",
  "properties": {
    "iso:country":"US",
    "sg:address":"230 Park St",
    "sg:city":"Elkhorn",
    "sg:classifiers":[
        {
            "category":"Utilities",
            "subcategory":"Telephone",
            "type":"Services"
        }
    ],
    "sg:phone":"+1 262 723 4989",
    "sg:postcode":"53121",
    "sg:province":"WI",
    "sg:tags":[
        "communications",
        "computer",
        "related"
    ],
    "wof:name":"Wisenet LLC",
    "wof:placetype":"venue"
},
  "geometry": {"coordinates":[-88.558714,42.669795],"type":"Point"}
}