{
  "type": "Feature",
  "properties": {
    "addr:full":"432 Washington Dr West Bend WI 53095",
    "addr:housenumber":"432",
    "addr:postcode":"53095",
    "addr:street":"Washington Dr",
    "iso:country":"US",
    "sg:address":"432 Washington Dr",
    "sg:city":"West Bend",
    "sg:classifiers":[
        {
            "category":"Government",
            "subcategory":"Office",
            "type":"Public Place"
        }
    ],
    "sg:phone":"+1 262 335 4308",
    "sg:postcode":"53095",
    "sg:province":"WI",
    "sg:tags":[
        "county",
        "taxation"
    ],
    "sg:website":"www.co.washington.wi.us",
    "wof:name":"Washington County Finance Dept",
    "wof:placetype":"venue"
},
  "geometry": {"coordinates":[-88.04364700000001,43.374557],"type":"Point"}
}