{
  "type": "Feature",
  "properties": {
    "iso:country":"US",
    "sg:address":"855 Main St",
    "sg:city":"Baldwin",
    "sg:classifiers":[
        {
            "category":"Personal",
            "subcategory":"Barber",
            "type":"Services"
        }
    ],
    "sg:phone":"+1 715 684 2434",
    "sg:postcode":"54002",
    "sg:province":"WI",
    "wof:name":"Kenneth Van Someren Barber Shp",
    "wof:placetype":"venue"
},
  "geometry": {"coordinates":[-92.373375,44.966686],"type":"Point"}
}