{
  "type": "Feature",
  "properties": {
    "iso:country":"US",
    "sg:address":"1001 Milwaukee Ave",
    "sg:city":"South Milwaukee",
    "sg:classifiers":[
        {
            "category":"Shopping",
            "subcategory":"Florist",
            "type":"Retail Goods"
        }
    ],
    "sg:phone":"+1 414 762 0246",
    "sg:postcode":"53172",
    "sg:province":"WI",
    "sg:website":"www.parkwayfloral.com",
    "wof:name":"Parkway Floral Inc",
    "wof:placetype":"venue"
},
  "geometry": {"coordinates":[-87.86268699999999,42.91073],"type":"Point"}
}