{
  "type": "Feature",
  "properties": {
    "iso:country":"US",
    "sg:address":"7155 S 49th St",
    "sg:city":"Franklin",
    "sg:classifiers":[
        {
            "category":"Organizations",
            "subcategory":"Religious Organization",
            "type":"Services"
        }
    ],
    "sg:phone":"+1 414 421 2055",
    "sg:postcode":"53132",
    "sg:province":"WI",
    "wof:name":"Catholic War Veterans of",
    "wof:placetype":"venue"
},
  "geometry": {"coordinates":[-87.977215,42.913622],"type":"Point"}
}