{
  "type": "Feature",
  "properties": {
    "iso:country":"US",
    "sg:address":"1917 E 6th St",
    "sg:city":"Superior",
    "sg:classifiers":[
        {
            "category":"Professional",
            "type":"Services"
        }
    ],
    "sg:phone":"+1 715 395 0895",
    "sg:postcode":"54880",
    "sg:province":"WI",
    "wof:name":"Kathleen & Daniel Ziebel",
    "wof:placetype":"venue"
},
  "geometry": {"coordinates":[-92.054052,46.706426],"type":"Point"}
}