{
  "type": "Feature",
  "properties": {
    "addr:full":"1311 W Grand Ave Wisconsin Rapids WI 54495",
    "addr:housenumber":"1311",
    "addr:postcode":"54495",
    "addr:street":"W Grand Ave",
    "iso:country":"US",
    "sg:address":"1311 W Grand Ave",
    "sg:city":"Wisconsin Rapids",
    "sg:classifiers":[
        {
            "category":"Autos & Motor Vehicles",
            "subcategory":"Auto Supplies",
            "type":"Retail Goods"
        }
    ],
    "sg:phone":"+1 715 423 2010",
    "sg:postcode":"54495",
    "sg:province":"WI",
    "sg:tags":[
        "tire"
    ],
    "wof:name":"Matthews Tire Ctr Inc",
    "wof:placetype":"venue"
},
  "geometry": {"coordinates":[-89.84115799999999,44.395962],"type":"Point"}
}