{
  "type": "Feature",
  "properties": {
    "iso:country":"US",
    "sg:address":"1503 Big Rapids Rd",
    "sg:city":"Stratford",
    "sg:classifiers":[
        {
            "category":"Personal",
            "subcategory":"Beauty Salon",
            "type":"Services"
        }
    ],
    "sg:phone":"+1 715 687 8811",
    "sg:postcode":"54484",
    "sg:province":"WI",
    "sg:tags":[
        "shop"
    ],
    "wof:name":"Sandys Country Salon",
    "wof:placetype":"venue"
},
  "geometry": {"coordinates":[-90.032911,44.844507],"type":"Point"}
}