{
  "type": "Feature",
  "properties": {
    "iso:country":"US",
    "sg:address":"117 West Ave N",
    "sg:city":"Dresser",
    "sg:classifiers":[
        {
            "category":"Professional",
            "subcategory":"Computer Services",
            "type":"Services"
        }
    ],
    "sg:phone":"+1 715 755 2463",
    "sg:postcode":"54009",
    "sg:province":"WI",
    "sg:tags":[
        "datum"
    ],
    "wof:name":"Lonny Worman",
    "wof:placetype":"venue"
},
  "geometry": {"coordinates":[-92.63564,45.355918],"type":"Point"}
}