{
  "type": "Feature",
  "properties": {
    "iso:country":"US",
    "sg:address":"509 Superior Ave",
    "sg:city":"Sheboygan",
    "sg:classifiers":[
        {
            "category":"Shopping",
            "subcategory":"Pharmacy",
            "type":"Retail Goods"
        }
    ],
    "sg:phone":"+1 920 459 2637",
    "sg:postcode":"53081",
    "sg:province":"WI",
    "sg:website":"www.aurorahealthcare.org",
    "wof:name":"Aurora Pharmacy",
    "wof:placetype":"venue"
},
  "geometry": {"coordinates":[-87.709491,43.760632],"type":"Point"}
}