{
  "type": "Feature",
  "properties": {
    "iso:country":"US",
    "sg:address":"1113 Crestview Dr",
    "sg:city":"Watertown",
    "sg:classifiers":[
        {
            "category":"Banks & Credit Unions",
            "subcategory":"Financial Services",
            "type":"Services"
        }
    ],
    "sg:phone":"+1 920 206 0760",
    "sg:postcode":"53094",
    "sg:province":"WI",
    "sg:tags":[
        "investor"
    ],
    "wof:name":"Schemehorn Investments LLC",
    "wof:placetype":"venue"
},
  "geometry": {"coordinates":[-88.753831,43.187385],"type":"Point"}
}