{
  "type": "Feature",
  "properties": {
    "iso:country":"US",
    "sg:address":"301 Center St",
    "sg:city":"Wonewoc",
    "sg:classifiers":[
        {
            "category":"Retail",
            "subcategory":"Auto Repair",
            "type":"Services"
        }
    ],
    "sg:phone":"+1 608 464 7735",
    "sg:postcode":"53968",
    "sg:province":"WI",
    "sg:tags":[
        "repairing",
        "automobile"
    ],
    "wof:name":"Larry's Garage",
    "wof:placetype":"venue"
},
  "geometry": {"coordinates":[-90.223344,43.655531],"type":"Point"}
}