{
  "type": "Feature",
  "properties": {
    "iso:country":"US",
    "sg:address":"920 Schwartz St",
    "sg:city":"Green Bay",
    "sg:classifiers":[
        {
            "category":"Real Estate",
            "subcategory":"Real Estate Agent",
            "type":"Services"
        }
    ],
    "sg:phone":"+1 920 366 1009",
    "sg:postcode":"54302",
    "sg:province":"WI",
    "sg:tags":[
        "management"
    ],
    "wof:name":"Glab Maintenance Svc",
    "wof:placetype":"venue"
},
  "geometry": {"coordinates":[-87.98569000000001,44.489617],"type":"Point"}
}