{
  "type": "Feature",
  "properties": {
    "iso:country":"US",
    "sg:address":"4118 S Burrell St",
    "sg:city":"Milwaukee",
    "sg:classifiers":[
        {
            "category":"Restaurant",
            "type":"Food & Drink"
        }
    ],
    "sg:phone":"+1 414 481 3576",
    "sg:postcode":"53207",
    "sg:province":"WI",
    "sg:tags":[
        "eating"
    ],
    "wof:name":"Reum Restaurant Services Inc",
    "wof:placetype":"venue"
},
  "geometry": {"coordinates":[-87.908316,42.968609],"type":"Point"}
}