{
  "type": "Feature",
  "properties": {
    "iso:country":"US",
    "sg:address":"4117 Playbird Rd",
    "sg:city":"Sheboygan",
    "sg:classifiers":[
        {
            "category":"Freight",
            "type":"Transportation"
        }
    ],
    "sg:phone":"+1 920 565 4750",
    "sg:postcode":"53083",
    "sg:province":"WI",
    "sg:tags":[
        "trucking"
    ],
    "sg:website":"www.con-way.com",
    "wof:name":"Con-Way Central Express",
    "wof:placetype":"venue"
},
  "geometry": {"coordinates":[-87.765654,43.805128],"type":"Point"}
}