{
  "type": "Feature",
  "properties": {
    "addr:full":"9910 52nd St Kenosha WI 53144",
    "addr:housenumber":"9910",
    "addr:postcode":"53144",
    "addr:street":"52Nd St",
    "iso:country":"US",
    "sg:address":"9910 52nd St",
    "sg:city":"Kenosha",
    "sg:classifiers":[
        {
            "category":"Professional",
            "subcategory":"Engineering",
            "type":"Services"
        },
        {
            "category":"Retail",
            "subcategory":"Repair Shop",
            "type":"Services"
        }
    ],
    "sg:phone":"+1 262 658 0030",
    "sg:postcode":"53144",
    "sg:province":"WI",
    "sg:tags":[
        "rebuilding",
        "aircraft",
        "maintenance"
    ],
    "wof:name":"Kenosha Jet Center",
    "wof:placetype":"venue"
},
  "geometry": {"coordinates":[-87.927077,42.589358],"type":"Point"}
}