{
  "type": "Feature",
  "properties": {
    "addr:full":"314 Horicon St Mayville WI 53050",
    "addr:housenumber":"314",
    "addr:postcode":"53050",
    "addr:street":"Horicon St",
    "iso:country":"US",
    "sg:address":"314 Horicon St",
    "sg:city":"Mayville",
    "sg:classifiers":[
        {
            "category":"Insurance",
            "subcategory":"Health Insurance",
            "type":"Services"
        }
    ],
    "sg:phone":"+1 920 387 2814",
    "sg:postcode":"53050",
    "sg:province":"WI",
    "sg:tags":[
        "carrier"
    ],
    "wof:name":"M W Hoff and Associates Inc",
    "wof:placetype":"venue"
},
  "geometry": {"coordinates":[-88.5483,43.494013],"type":"Point"}
}