{
  "type": "Feature",
  "properties": {
    "iso:country":"US",
    "sg:address":"7679 State Hwy 85",
    "sg:city":"Mondovi",
    "sg:classifiers":[
        {
            "category":"Farming",
            "subcategory":"Farm",
            "type":"Manufacturing & Wholesale Goods"
        }
    ],
    "sg:phone":"+1 715 875 4947",
    "sg:postcode":"54755",
    "sg:province":"WI",
    "wof:name":"Chad Prissel Farms",
    "wof:placetype":"venue"
},
  "geometry": {"coordinates":[-91.776826,44.699495],"type":"Point"}
}