{
  "type": "Feature",
  "properties": {
    "iso:country":"US",
    "sg:address":"75 US Hwy 51",
    "sg:city":"Manitowish Wtrs",
    "sg:classifiers":[
        {
            "category":"Building & Trades",
            "subcategory":"Construction",
            "type":"Services"
        }
    ],
    "sg:phone":"+1 715 543 2707",
    "sg:postcode":"54545",
    "sg:province":"WI",
    "sg:tags":[
        "excavation",
        "excavating",
        "contractor"
    ],
    "wof:name":"Chuck's Excavating",
    "wof:placetype":"venue"
},
  "geometry": {"coordinates":[-89.868804,46.123439],"type":"Point"}
}