{
  "type": "Feature",
  "properties": {
    "iso:country":"US",
    "sg:address":"300 State St",
    "sg:city":"Holmen",
    "sg:classifiers":[
        {
            "category":"Shopping",
            "subcategory":"Clothing, Apparel, & Fashions",
            "type":"Retail Goods"
        }
    ],
    "sg:phone":"+1 608 526 1003",
    "sg:postcode":"54636",
    "sg:province":"WI",
    "sg:tags":[
        "bridal",
        "wear"
    ],
    "wof:name":"B R Bride Inc",
    "wof:placetype":"venue"
},
  "geometry": {"coordinates":[-91.25175900000001,43.963169],"type":"Point"}
}