{
  "type": "Feature",
  "properties": {
    "iso:country":"US",
    "sg:address":"2532 Glendale Ave",
    "sg:city":"Green Bay",
    "sg:classifiers":[
        {
            "category":"Restaurant",
            "type":"Food & Drink"
        },
        {
            "category":"Ice Cream",
            "type":"Food & Drink"
        }
    ],
    "sg:menulink":"http://www.allmenus.com/wi/howard/192650-dairy-queen/menu/",
    "sg:phone":"+1 920 434 4890",
    "sg:postcode":"54313",
    "sg:province":"WI",
    "sg:tags":[
        "burger",
        "american",
        "ice",
        "cream"
    ],
    "wof:name":"Dairy Queen",
    "wof:placetype":"venue"
},
  "geometry": {"coordinates":[-88.080237,44.563809],"type":"Point"}
}