{
  "type": "Feature",
  "properties": {
    "iso:country":"US",
    "sg:address":"2105 S 170th St",
    "sg:city":"New Berlin",
    "sg:classifiers":[
        {
            "category":"Professional",
            "type":"Services"
        }
    ],
    "sg:phone":"+1 262 953 2200",
    "sg:postcode":"53151",
    "sg:province":"WI",
    "sg:tags":[
        "establishment"
    ],
    "wof:name":"Exec-PC",
    "wof:placetype":"venue"
},
  "geometry": {"coordinates":[-88.12479999999999,43.004148],"type":"Point"}
}