{
  "type": "Feature",
  "properties": {
    "iso:country":"US",
    "sg:address":"3774 W Carpenter Ave",
    "sg:city":"Milwaukee",
    "sg:classifiers":[
        {
            "category":"Wholesale",
            "subcategory":"Durable Goods & Equipment",
            "type":"Manufacturing & Wholesale Goods"
        }
    ],
    "sg:phone":"+1 414 281 9330",
    "sg:postcode":"53221",
    "sg:province":"WI",
    "wof:name":"Dreamcatchers Supply",
    "wof:placetype":"venue"
},
  "geometry": {"coordinates":[-87.962978,42.955404],"type":"Point"}
}