{
  "type": "Feature",
  "properties": {
    "iso:country":"US",
    "sg:address":"8489 Kasten Ln",
    "sg:city":"Watertown",
    "sg:classifiers":[
        {
            "category":"Building & Trades",
            "subcategory":"Construction",
            "type":"Services"
        }
    ],
    "sg:phone":"+1 920 261 2328",
    "sg:postcode":"53094",
    "sg:province":"WI",
    "sg:tags":[
        "resurfacing",
        "laying",
        "refinishing",
        "floor"
    ],
    "wof:name":"Hometown Flooring",
    "wof:placetype":"venue"
},
  "geometry": {"coordinates":[-88.764284,43.158522],"type":"Point"}
}