{
  "type": "Feature",
  "properties": {
    "iso:country":"US",
    "sg:address":"1121 W Main Ave",
    "sg:city":"De Pere",
    "sg:classifiers":[
        {
            "category":"Autos & Motor Vehicles",
            "subcategory":"Automobile Sales",
            "type":"Retail Goods"
        }
    ],
    "sg:phone":"+1 920 336 7500",
    "sg:postcode":"54115",
    "sg:province":"WI",
    "sg:tags":[
        "building",
        "mini",
        "used",
        "residential",
        "car",
        "operator"
    ],
    "wof:name":"Fitzgerald Enterprises",
    "wof:placetype":"venue"
},
  "geometry": {"coordinates":[-88.100979,44.456437],"type":"Point"}
}