{
  "type": "Feature",
  "properties": {
    "iso:country":"US",
    "sg:address":"315 S Jefferson St",
    "sg:city":"Green Bay",
    "sg:classifiers":[
        {
            "category":"Social Services",
            "type":"Services"
        }
    ],
    "sg:phone":"+1 920 435 1188",
    "sg:postcode":"54301",
    "sg:province":"WI",
    "wof:name":"Bahler Kathleen & Assocations",
    "wof:placetype":"venue"
},
  "geometry": {"coordinates":[-88.015627,44.509869],"type":"Point"}
}