{
  "type": "Feature",
  "properties": {
    "iso:country":"US",
    "sg:address":"125 E 1st Ave",
    "sg:city":"Appleton",
    "sg:classifiers":[
        {
            "category":"Real Estate",
            "subcategory":"Real Estate Operator",
            "type":"Services"
        }
    ],
    "sg:phone":"+1 920 738 0077",
    "sg:postcode":"54911",
    "sg:province":"WI",
    "sg:tags":[
        "building",
        "apartment"
    ],
    "wof:name":"Capitins Cove Aprtments Partnr",
    "wof:placetype":"venue"
},
  "geometry": {"coordinates":[-88.404273,44.288417],"type":"Point"}
}