{
  "type": "Feature",
  "properties": {
    "iso:country":"US",
    "sg:address":"25215 Co Rd G",
    "sg:city":"Fairchild",
    "sg:classifiers":[
        {
            "category":"Government",
            "subcategory":"Office",
            "type":"Public Place"
        }
    ],
    "sg:phone":"+1 715 334 3315",
    "sg:postcode":"54726",
    "sg:province":"WI",
    "sg:tags":[
        "executive"
    ],
    "wof:name":"Fairchild Township Office",
    "wof:placetype":"venue"
},
  "geometry": {"coordinates":[-91.022006,44.828029],"type":"Point"}
}