{
  "type": "Feature",
  "properties": {
    "iso:country":"US",
    "sg:address":"2419 Menasha Ave",
    "sg:city":"Manitowoc",
    "sg:classifiers":[
        {
            "category":"Autos & Motor Vehicles",
            "subcategory":"Auto Supplies",
            "type":"Retail Goods"
        }
    ],
    "sg:phone":"+1 920 684 4439",
    "sg:postcode":"54220",
    "sg:province":"WI",
    "sg:tags":[
        "tire"
    ],
    "wof:name":"Pomp's Tire Svc",
    "wof:placetype":"venue"
},
  "geometry": {"coordinates":[-87.683126,44.116762],"type":"Point"}
}