{
  "type": "Feature",
  "properties": {
    "iso:country":"US",
    "sg:address":"936 9th St",
    "sg:city":"Menasha",
    "sg:classifiers":[
        {
            "category":"Local Transit",
            "type":"Transportation"
        }
    ],
    "sg:phone":"+1 920 725 4665",
    "sg:postcode":"54952",
    "sg:province":"WI",
    "sg:tags":[
        "passenger"
    ],
    "wof:name":"TNT Limousine Service",
    "wof:placetype":"venue"
},
  "geometry": {"coordinates":[-88.430975,44.215436],"type":"Point"}
}