{
  "type": "Feature",
  "properties": {
    "addr:full":"1924 Co Rd J Kewaunee WI 54216",
    "addr:housenumber":"1924",
    "addr:postcode":"54216",
    "addr:street":"Co Rd",
    "iso:country":"US",
    "sg:address":"1924 Co Rd J",
    "sg:city":"Kewaunee",
    "sg:classifiers":[
        {
            "category":"Farming",
            "subcategory":"Dairy Farm",
            "type":"Manufacturing & Wholesale Goods"
        }
    ],
    "sg:phone":"+1 920 388 2682",
    "sg:postcode":"54216",
    "sg:province":"WI",
    "wof:name":"Leonard Gruetzmacher",
    "wof:placetype":"venue"
},
  "geometry": {"coordinates":[-87.673305,44.400283],"type":"Point"}
}