{
  "type": "Feature",
  "properties": {
    "iso:country":"US",
    "sg:address":"333 N Main St",
    "sg:city":"Adams",
    "sg:classifiers":[
        {
            "category":"Professional",
            "subcategory":"Lawyer & Legal Services",
            "type":"Services"
        }
    ],
    "sg:phone":"+1 608 339 7777",
    "sg:postcode":"53910",
    "sg:province":"WI",
    "sg:tags":[
        "attorney"
    ],
    "wof:name":"Screnock Law Office",
    "wof:placetype":"venue"
},
  "geometry": {"coordinates":[-89.817818,43.962592],"type":"Point"}
}