{
  "type": "Feature",
  "properties": {
    "addr:full":"5495 State Rd 120 Elkhorn WI 53121",
    "addr:housenumber":"5495;120",
    "addr:postcode":"53121",
    "addr:street":"State Rd",
    "iso:country":"US",
    "sg:address":"5495 State Rd 120",
    "sg:city":"Elkhorn",
    "sg:classifiers":[
        {
            "category":"Retail",
            "subcategory":"Repair Shop",
            "type":"Services"
        }
    ],
    "sg:phone":"+1 262 248 0333",
    "sg:postcode":"53121",
    "sg:province":"WI",
    "sg:tags":[
        "building",
        "maintenance",
        "welding"
    ],
    "wof:name":"Redell Mechanical LLC",
    "wof:placetype":"venue"
},
  "geometry": {"coordinates":[-88.404766,42.691033],"type":"Point"}
}