{
  "type": "Feature",
  "properties": {
    "iso:country":"US",
    "sg:address":"4860 Co Rd K",
    "sg:city":"Oshkosh",
    "sg:classifiers":[
        {
            "category":"Manufacturing",
            "subcategory":"Metals",
            "type":"Manufacturing & Wholesale Goods"
        }
    ],
    "sg:phone":"+1 920 233 0784",
    "sg:postcode":"54904",
    "sg:province":"WI",
    "sg:tags":[
        "metalwork",
        "sheet",
        "mfg"
    ],
    "wof:name":"Glr Co",
    "wof:placetype":"venue"
},
  "geometry": {"coordinates":[-88.64379,43.996734],"type":"Point"}
}