{
  "type": "Feature",
  "properties": {
    "iso:country":"US",
    "sg:address":"2633 S Business Dr",
    "sg:city":"Sheboygan",
    "sg:classifiers":[
        {
            "category":"Shopping",
            "subcategory":"Shoes",
            "type":"Retail Goods"
        }
    ],
    "sg:phone":"+1 920 457 2301",
    "sg:postcode":"53081",
    "sg:province":"WI",
    "wof:name":"Meldisco K-M Sheyboygan Wisc",
    "wof:placetype":"venue"
},
  "geometry": {"coordinates":[-87.73535200000001,43.724287],"type":"Point"}
}