{
  "type": "Feature",
  "properties": {
    "iso:country":"US",
    "sg:address":"701 E High St",
    "sg:city":"Milton",
    "sg:classifiers":[
        {
            "category":"Banks & Credit Unions",
            "subcategory":"Investment Brokerage",
            "type":"Services"
        }
    ],
    "sg:phone":"+1 608 868 3201",
    "sg:postcode":"53563",
    "sg:province":"WI",
    "sg:tags":[
        "stock",
        "bond"
    ],
    "wof:name":"American Investors Group",
    "wof:placetype":"venue"
},
  "geometry": {"coordinates":[-88.939066,42.772805],"type":"Point"}
}