{
  "type": "Feature",
  "properties": {
    "addr:full":"2520 Greenway Vw Madison WI 53713",
    "addr:housenumber":"2520",
    "addr:postcode":"53713",
    "addr:street":"Greenway Vw",
    "iso:country":"US",
    "sg:address":"2520 Greenway Vw",
    "sg:city":"Madison",
    "sg:classifiers":[
        {
            "category":"Real Estate",
            "subcategory":"Real Estate Agent",
            "type":"Services"
        }
    ],
    "sg:phone":"+1 608 345 2801",
    "sg:postcode":"53713",
    "sg:province":"WI",
    "wof:name":"Erv Bendorf",
    "wof:placetype":"venue"
},
  "geometry": {"coordinates":[-89.423091,43.031737],"type":"Point"}
}