{
  "type": "Feature",
  "properties": {
    "addr:full":"7534 Schwaller Dr Plymouth WI 53073",
    "addr:housenumber":"7534",
    "addr:postcode":"53073",
    "addr:street":"Schwaller Dr",
    "iso:country":"US",
    "sg:address":"7534 Schwaller Dr",
    "sg:city":"Plymouth",
    "sg:classifiers":[
        {
            "category":"Home & Garden",
            "subcategory":"Building Materials",
            "type":"Retail Goods"
        }
    ],
    "sg:phone":"+1 920 893 8786",
    "sg:postcode":"53073",
    "sg:province":"WI",
    "wof:name":"Priced Right Exteriors",
    "wof:placetype":"venue"
},
  "geometry": {"coordinates":[-87.98277,43.811382],"type":"Point"}
}