{
  "type": "Feature",
  "properties": {
    "iso:country":"US",
    "sg:address":"6369 Hyslop Rd",
    "sg:city":"Waunakee",
    "sg:classifiers":[
        {
            "category":"Real Estate",
            "subcategory":"Real Estate Agent",
            "type":"Services"
        }
    ],
    "sg:phone":"+1 608 849 8867",
    "sg:postcode":"53597",
    "sg:province":"WI",
    "wof:name":"Rfd Corporation",
    "wof:placetype":"venue"
},
  "geometry": {"coordinates":[-89.506407,43.206657],"type":"Point"}
}