{
  "type": "Feature",
  "properties": {
    "iso:country":"US",
    "sg:address":"210 N Cascade St",
    "sg:city":"Osceola",
    "sg:classifiers":[
        {
            "category":"Retail",
            "subcategory":"Laundry & Dry Cleaning",
            "type":"Services"
        }
    ],
    "sg:phone":"+1 715 294 4276",
    "sg:postcode":"54020",
    "sg:province":"WI",
    "sg:tags":[
        "cleaners",
        "rug",
        "carpet"
    ],
    "wof:name":"Jay's Carpet Cleaning",
    "wof:placetype":"venue"
},
  "geometry": {"coordinates":[-92.705298,45.32158],"type":"Point"}
}