{
  "type": "Feature",
  "properties": {
    "iso:country":"US",
    "sg:address":"1129 Main St",
    "sg:city":"Union Grove",
    "sg:classifiers":[
        {
            "category":"Home & Garden",
            "subcategory":"Home Furnishings",
            "type":"Retail Goods"
        }
    ],
    "sg:phone":"+1 262 878 0300",
    "sg:postcode":"53182",
    "sg:province":"WI",
    "sg:tags":[
        "fireplace"
    ],
    "wof:name":"Heberlings Fireplace",
    "wof:placetype":"venue"
},
  "geometry": {"coordinates":[-88.051794,42.686136],"type":"Point"}
}