{
  "type": "Feature",
  "properties": {
    "iso:country":"US",
    "sg:address":"207 Britany Ct",
    "sg:city":"Pardeeville",
    "sg:classifiers":[
        {
            "category":"Travel",
            "subcategory":"Campground",
            "type":"Entertainment"
        }
    ],
    "sg:phone":"+1 608 429 3061",
    "sg:postcode":"53954",
    "sg:province":"WI",
    "wof:name":"Wisconsin Assoc Campground Onr",
    "wof:placetype":"venue"
},
  "geometry": {"coordinates":[-89.31462,43.534136],"type":"Point"}
}