{
  "type": "Feature",
  "properties": {
    "iso:country":"US",
    "sg:address":"113 S Pearl St",
    "sg:city":"Berlin",
    "sg:classifiers":[
        {
            "category":"Professional",
            "type":"Services"
        }
    ],
    "sg:phone":"+1 920 361 0171",
    "sg:postcode":"54923",
    "sg:province":"WI",
    "sg:tags":[
        "establishment"
    ],
    "wof:name":"Evans Pitle",
    "wof:placetype":"venue"
},
  "geometry": {"coordinates":[-88.948055,43.968002],"type":"Point"}
}