{
  "type": "Feature",
  "properties": {
    "addr:full":"4709 Co Hwy H Franksville WI 53126",
    "addr:housenumber":"4709",
    "addr:postcode":"53126",
    "addr:street":"Co Hwy H",
    "iso:country":"US",
    "sg:address":"4709 Co Hwy H",
    "sg:city":"Franksville",
    "sg:classifiers":[
        {
            "category":"Building & Trades",
            "subcategory":"Construction",
            "type":"Services"
        }
    ],
    "sg:phone":"+1 262 886 3740",
    "sg:postcode":"53126",
    "sg:province":"WI",
    "sg:tags":[
        "excavation",
        "demolition",
        "contractor"
    ],
    "wof:name":"Jaramillo Contractors Inc",
    "wof:placetype":"venue"
},
  "geometry": {"coordinates":[-87.91474599999999,42.781258],"type":"Point"}
}