{
  "type": "Feature",
  "properties": {
    "iso:country":"US",
    "sg:address":"2 E Mifflin St",
    "sg:city":"Madison",
    "sg:classifiers":[
        {
            "category":"Real Estate",
            "subcategory":"Real Estate Agent",
            "type":"Services"
        }
    ],
    "sg:phone":"+1 608 663 6390",
    "sg:postcode":"53703",
    "sg:province":"WI",
    "sg:tags":[
        "management"
    ],
    "wof:name":"Astar Capital Mgmt",
    "wof:placetype":"venue"
},
  "geometry": {"coordinates":[-89.384126,43.076195],"type":"Point"}
}