{
  "type": "Feature",
  "properties": {
    "iso:country":"US",
    "sg:address":"515 S Park St",
    "sg:city":"Madison",
    "sg:classifiers":[
        {
            "category":"Restaurant",
            "type":"Food & Drink"
        }
    ],
    "sg:phone":"+1 608 255 8227",
    "sg:postcode":"53715",
    "sg:province":"WI",
    "sg:tags":[
        "eating"
    ],
    "wof:name":"LA Hacienda Restaurant",
    "wof:placetype":"venue"
},
  "geometry": {"coordinates":[-89.400675,43.061654],"type":"Point"}
}