{
  "type": "Feature",
  "properties": {
    "iso:country":"US",
    "sg:address":"10427 N River Lake Dr",
    "sg:city":"Thiensville",
    "sg:classifiers":[
        {
            "category":"Professional",
            "subcategory":"Computer Services",
            "type":"Services"
        }
    ],
    "sg:phone":"+1 414 434 2300",
    "sg:postcode":"53092",
    "sg:province":"WI",
    "sg:tags":[
        "consulting",
        "internet"
    ],
    "wof:name":"Axel Lloyd & Assoc",
    "wof:placetype":"venue"
},
  "geometry": {"coordinates":[-87.965148,43.207365],"type":"Point"}
}