{
  "type": "Feature",
  "properties": {
    "iso:country":"US",
    "sg:address":"1420 Reckelberg Rd",
    "sg:city":"Kewaunee",
    "sg:classifiers":[
        {
            "category":"Farming",
            "subcategory":"Dairy Farm",
            "type":"Manufacturing & Wholesale Goods"
        }
    ],
    "sg:phone":"+1 920 845 2465",
    "sg:postcode":"54216",
    "sg:province":"WI",
    "wof:name":"Adolph Reckelberg",
    "wof:placetype":"venue"
},
  "geometry": {"coordinates":[-87.700525,44.436231],"type":"Point"}
}