{
  "type": "Feature",
  "properties": {
    "iso:country":"US",
    "sg:address":"550 US Hwy 141",
    "sg:city":"Coleman",
    "sg:classifiers":[
        {
            "category":"Social Services",
            "subcategory":"Child Care",
            "type":"Services"
        }
    ],
    "sg:phone":"+1 920 897 4646",
    "sg:postcode":"54112",
    "sg:province":"WI",
    "wof:name":"Kids 'n Kids Day Care Ctr",
    "wof:placetype":"venue"
},
  "geometry": {"coordinates":[-88.033506,45.075382],"type":"Point"}
}