{
  "type": "Feature",
  "properties": {
    "addr:full":"227 Broadway St Berlin WI 54923",
    "addr:housenumber":"227",
    "addr:postcode":"54923",
    "addr:street":"Broadway St",
    "iso:country":"US",
    "sg:address":"227 Broadway St",
    "sg:city":"Berlin",
    "sg:classifiers":[
        {
            "category":"Home & Garden",
            "subcategory":"Furniture",
            "type":"Retail Goods"
        }
    ],
    "sg:phone":"+1 920 361 2929",
    "sg:postcode":"54923",
    "sg:province":"WI",
    "wof:name":"Reruns Resale",
    "wof:placetype":"venue"
},
  "geometry": {"coordinates":[-88.952219,43.968424],"type":"Point"}
}