{
  "type": "Feature",
  "properties": {
    "iso:country":"US",
    "sg:address":"110 Corrina Blvd",
    "sg:city":"Waukesha",
    "sg:classifiers":[
        {
            "category":"Wholesale",
            "subcategory":"Non-durable Goods",
            "type":"Manufacturing & Wholesale Goods"
        }
    ],
    "sg:phone":"+1 262 524 8865",
    "sg:postcode":"53186",
    "sg:province":"WI",
    "wof:name":"Wisconsin Incorporation",
    "wof:placetype":"venue"
},
  "geometry": {"coordinates":[-88.22879500000001,43.013267],"type":"Point"}
}