{
  "type": "Feature",
  "properties": {
    "iso:country":"US",
    "sg:address":"701 E Vienna Ave",
    "sg:city":"Milwaukee",
    "sg:classifiers":[
        {
            "category":"Shopping",
            "subcategory":"Gifts & Souvenirs",
            "type":"Retail Goods"
        }
    ],
    "sg:phone":"+1 414 964 0010",
    "sg:postcode":"53212",
    "sg:province":"WI",
    "sg:tags":[
        "material",
        "wrapping"
    ],
    "wof:name":"Paper Caper",
    "wof:placetype":"venue"
},
  "geometry": {"coordinates":[-87.903658,43.08584],"type":"Point"}
}