{
  "type": "Feature",
  "properties": {
    "iso:country":"US",
    "sg:address":"1760 W 7th Ave",
    "sg:city":"Oshkosh",
    "sg:classifiers":[
        {
            "category":"Social Services",
            "subcategory":"Child Care",
            "type":"Services"
        }
    ],
    "sg:phone":"+1 920 235 3031",
    "sg:postcode":"54902",
    "sg:province":"WI",
    "sg:tags":[
        "day"
    ],
    "wof:name":"Pumpkin Patch Inc",
    "wof:placetype":"venue"
},
  "geometry": {"coordinates":[-88.57958000000001,44.011737],"type":"Point"}
}