{
  "type": "Feature",
  "properties": {
    "iso:country":"US",
    "sg:address":"453 E Park St",
    "sg:city":"Montello",
    "sg:classifiers":[
        {
            "category":"Retail",
            "subcategory":"Funeral Services",
            "type":"Services"
        }
    ],
    "sg:phone":"+1 608 297 2268",
    "sg:postcode":"53949",
    "sg:province":"WI",
    "sg:tags":[
        "director"
    ],
    "wof:name":"Steinhaus Leikness & Stahl",
    "wof:placetype":"venue"
},
  "geometry": {"coordinates":[-89.314998,43.795145],"type":"Point"}
}