{
  "type": "Feature",
  "properties": {
    "iso:country":"US",
    "sg:address":"8978 State Rd 11",
    "sg:city":"Delavan",
    "sg:classifiers":[
        {
            "category":"Building & Trades",
            "subcategory":"Construction",
            "type":"Services"
        }
    ],
    "sg:phone":"+1 262 724 5332",
    "sg:postcode":"53115",
    "sg:province":"WI",
    "sg:tags":[
        "insulating",
        "contractor"
    ],
    "wof:name":"Money Savers Insulation",
    "wof:placetype":"venue"
},
  "geometry": {"coordinates":[-88.73983800000001,42.651385],"type":"Point"}
}