{
  "type": "Feature",
  "properties": {
    "iso:country":"US",
    "sg:address":"450 C P Ave",
    "sg:city":"Lake Mills",
    "sg:classifiers":[
        {
            "category":"Freight",
            "type":"Transportation"
        },
        {
            "category":"Wholesale",
            "subcategory":"Dairy",
            "type":"Manufacturing & Wholesale Goods"
        }
    ],
    "sg:phone":"+1 920 648 3466",
    "sg:postcode":"53551",
    "sg:province":"WI",
    "sg:tags":[
        "product",
        "self",
        "storage",
        "grocery",
        "refrigerated",
        "warehouse"
    ],
    "wof:name":"Wisco Farm Co-Operative",
    "wof:placetype":"venue"
},
  "geometry": {"coordinates":[-88.898672,43.073583],"type":"Point"}
}