{
  "type": "Feature",
  "properties": {
    "iso:country":"US",
    "sg:address":"1068 W 5th Ave",
    "sg:city":"Oshkosh",
    "sg:classifiers":[
        {
            "category":"Arts & Performance",
            "subcategory":"Theater",
            "type":"Entertainment"
        }
    ],
    "sg:phone":"+1 920 426 5104",
    "sg:postcode":"54902",
    "sg:province":"WI",
    "sg:tags":[
        "live",
        "music"
    ],
    "wof:name":"D & D Disc Jockey Svc",
    "wof:placetype":"venue"
},
  "geometry": {"coordinates":[-88.563732,44.013471],"type":"Point"}
}