{
  "type": "Feature",
  "properties": {
    "iso:country":"US",
    "sg:address":"4801 Hayes Rd",
    "sg:city":"Madison",
    "sg:classifiers":[
        {
            "category":"Shopping",
            "type":"Retail Goods"
        }
    ],
    "sg:phone":"+1 608 242 1516",
    "sg:postcode":"53704",
    "sg:province":"WI",
    "sg:tags":[
        "sell",
        "apparatus",
        "supply",
        "medical",
        "rent",
        "app"
    ],
    "wof:name":"Home Care United Inc",
    "wof:placetype":"venue"
},
  "geometry": {"coordinates":[-89.299685,43.135579],"type":"Point"}
}