{
  "type": "Feature",
  "properties": {
    "iso:country":"US",
    "sg:address":"1526 Gohres St",
    "sg:city":"La Crosse",
    "sg:classifiers":[
        {
            "category":"Insurance",
            "subcategory":"Insurance Agent",
            "type":"Services"
        }
    ],
    "sg:phone":"+1 608 784 2600",
    "sg:postcode":"54603",
    "sg:province":"WI",
    "wof:name":"All American Insurance",
    "wof:placetype":"venue"
},
  "geometry": {"coordinates":[-91.23495,43.849158],"type":"Point"}
}