{
  "type": "Feature",
  "properties": {
    "addr:full":"1111 N Lynndale Dr Appleton WI 54914",
    "addr:housenumber":"1111",
    "addr:postcode":"54914",
    "addr:street":"N Lynndale Dr",
    "iso:country":"US",
    "sg:address":"1111 N Lynndale Dr",
    "sg:city":"Appleton",
    "sg:classifiers":[
        {
            "category":"Utilities",
            "subcategory":"Mobile Phone",
            "type":"Services"
        }
    ],
    "sg:phone":"+1 920 730 8418",
    "sg:postcode":"54914",
    "sg:province":"WI",
    "sg:tags":[
        "communication",
        "radiotelephone"
    ],
    "wof:name":"Dick Buss & Associates",
    "wof:placetype":"venue"
},
  "geometry": {"coordinates":[-88.446009,44.266282],"type":"Point"}
}