{
  "type": "Feature",
  "properties": {
    "iso:country":"US",
    "sg:address":"534 W Pine St",
    "sg:city":"Lancaster",
    "sg:phone":"+1 608 723 7462",
    "sg:postcode":"53813",
    "sg:province":"WI",
    "sg:tags":[
        "farm",
        "corn"
    ],
    "wof:name":"Thomas Friar",
    "wof:placetype":"venue"
},
  "geometry": {"coordinates":[-90.715154,42.850858],"type":"Point"}
}