{
  "type": "Feature",
  "properties": {
    "addr:full":"292 Burma Rd Mosinee WI 54455",
    "addr:housenumber":"292",
    "addr:postcode":"54455",
    "addr:street":"Burma Rd",
    "iso:country":"US",
    "sg:address":"292 Burma Rd",
    "sg:city":"Mosinee",
    "sg:classifiers":[
        {
            "category":"Home & Garden",
            "subcategory":"Hardware",
            "type":"Retail Goods"
        }
    ],
    "sg:phone":"+1 715 693 6641",
    "sg:postcode":"54455",
    "sg:province":"WI",
    "sg:tags":[
        "saw"
    ],
    "wof:name":"A S Saw Sales",
    "wof:placetype":"venue"
},
  "geometry": {"coordinates":[-89.702449,44.829445],"type":"Point"}
}