{
  "type": "Feature",
  "properties": {
    "iso:country":"US",
    "sg:address":"1930 W Morgan Ave",
    "sg:city":"Milwaukee",
    "sg:classifiers":[
        {
            "category":"Autos & Motor Vehicles",
            "subcategory":"Fuel & Gas Station",
            "type":"Retail Goods"
        },
        {
            "category":"Retail",
            "subcategory":"Auto Repair",
            "type":"Services"
        }
    ],
    "sg:phone":"+1 414 647 9458",
    "sg:postcode":"53221",
    "sg:province":"WI",
    "sg:tags":[
        "repairing",
        "automobile",
        "station",
        "gasoline"
    ],
    "wof:name":"Munro's Standard",
    "wof:placetype":"venue"
},
  "geometry": {"coordinates":[-87.938382,42.981214],"type":"Point"}
}