{
  "type": "Feature",
  "properties": {
    "iso:country":"US",
    "sg:address":"2405 Parview Rd",
    "sg:city":"Middleton",
    "sg:classifiers":[
        {
            "category":"Banks & Credit Unions",
            "subcategory":"Investment Brokerage",
            "type":"Services"
        }
    ],
    "sg:phone":"+1 608 831 4689",
    "sg:postcode":"53562",
    "sg:province":"WI",
    "sg:tags":[
        "advisory",
        "consulting",
        "management"
    ],
    "wof:name":"Hillside Investment Advisors",
    "wof:placetype":"venue"
},
  "geometry": {"coordinates":[-89.532061,43.09997],"type":"Point"}
}