{
  "type": "Feature",
  "properties": {
    "iso:country":"US",
    "sg:address":"2121 E Springs Dr",
    "sg:city":"Madison",
    "sg:classifiers":[
        {
            "category":"Shopping",
            "subcategory":"Bicycles & Sporting Goods",
            "type":"Retail Goods"
        }
    ],
    "sg:phone":"+1 608 244 7246",
    "sg:postcode":"53704",
    "sg:province":"WI",
    "wof:name":"Badger Bowl Pro Shop",
    "wof:placetype":"venue"
},
  "geometry": {"coordinates":[-89.296828,43.125756],"type":"Point"}
}