{
  "type": "Feature",
  "properties": {
    "iso:country":"US",
    "sg:address":"10 W Church St",
    "sg:city":"Evansville",
    "sg:classifiers":[
        {
            "category":"Government",
            "subcategory":"Fire Station",
            "type":"Public Place"
        }
    ],
    "sg:phone":"+1 608 882 9934",
    "sg:postcode":"53536",
    "sg:province":"WI",
    "sg:tags":[
        "protection"
    ],
    "wof:name":"Evansville Fire Protection Dst",
    "wof:placetype":"venue"
},
  "geometry": {"coordinates":[-89.301112,42.779119],"type":"Point"}
}