{
  "type": "Feature",
  "properties": {
    "iso:country":"US",
    "sg:address":"1375 Covered Bridge Rd",
    "sg:city":"Cedarburg",
    "sg:classifiers":[
        {
            "category":"Organizations",
            "subcategory":"Religious Organization",
            "type":"Services"
        }
    ],
    "sg:phone":"+1 262 377 1070",
    "sg:postcode":"53012",
    "sg:province":"WI",
    "sg:website":"www.saintfrancisborgia.org",
    "wof:name":"St Francis Borgia Church",
    "wof:placetype":"venue"
},
  "geometry": {"coordinates":[-88.0056,43.325699],"type":"Point"}
}