{
  "type": "Feature",
  "properties": {
    "iso:country":"US",
    "sg:address":"2309 Hansen Ave",
    "sg:city":"Racine",
    "sg:classifiers":[
        {
            "category":"Freight",
            "type":"Transportation"
        }
    ],
    "sg:phone":"+1 262 637 4906",
    "sg:postcode":"53405",
    "sg:province":"WI",
    "sg:tags":[
        "general"
    ],
    "wof:name":"D & M Paar LLC",
    "wof:placetype":"venue"
},
  "geometry": {"coordinates":[-87.812042,42.723369],"type":"Point"}
}