{
  "type": "Feature",
  "properties": {
    "iso:country":"US",
    "sg:address":"885 Willow Ridge Rd",
    "sg:city":"Hudson",
    "sg:classifiers":[
        {
            "category":"Professional",
            "subcategory":"Management & Consulting",
            "type":"Services"
        }
    ],
    "sg:phone":"+1 715 386 2879",
    "sg:postcode":"54016",
    "sg:province":"WI",
    "wof:name":"Mike & Pearl Doody",
    "wof:placetype":"venue"
},
  "geometry": {"coordinates":[-92.71974,44.990696],"type":"Point"}
}