{
  "type": "Feature",
  "properties": {
    "iso:country":"US",
    "sg:address":"1442 E Williams Dr",
    "sg:city":"Beloit",
    "sg:classifiers":[
        {
            "category":"Retail",
            "subcategory":"Repair Shop",
            "type":"Services"
        }
    ],
    "sg:phone":"+1 608 365 9390",
    "sg:postcode":"53511",
    "sg:province":"IL",
    "sg:tags":[
        "electrical",
        "contractor"
    ],
    "wof:name":"Foley Electric Inc",
    "wof:placetype":"venue"
},
  "geometry": {"coordinates":[-89.019715,42.560543],"type":"Point"}
}