{
  "type": "Feature",
  "properties": {
    "iso:country":"US",
    "sg:address":"11460 W Magellan St",
    "sg:city":"Franklin",
    "sg:classifiers":[
        {
            "category":"Real Estate",
            "subcategory":"Real Estate Agent",
            "type":"Services"
        }
    ],
    "sg:phone":"+1 414 425 8557",
    "sg:postcode":"53132",
    "sg:province":"WI",
    "wof:name":"Raven Realty Co",
    "wof:placetype":"venue"
},
  "geometry": {"coordinates":[-88.057225,42.907867],"type":"Point"}
}