{
  "type": "Feature",
  "properties": {
    "iso:country":"US",
    "sg:address":"3288 State Rd 20",
    "sg:city":"East Troy",
    "sg:phone":"+1 262 642 5957",
    "sg:postcode":"53120",
    "sg:province":"WI",
    "sg:tags":[
        "farm",
        "corn"
    ],
    "wof:name":"Dean Healey",
    "wof:placetype":"venue"
},
  "geometry": {"coordinates":[-88.46321500000001,42.792882],"type":"Point"}
}