{
  "type": "Feature",
  "properties": {
    "iso:country":"US",
    "sg:address":"417 Robins Run",
    "sg:city":"Burlington",
    "sg:classifiers":[
        {
            "category":"Building & Trades",
            "subcategory":"Landscaping Services",
            "type":"Services"
        }
    ],
    "sg:phone":"+1 262 206 1017",
    "sg:postcode":"53105",
    "sg:province":"WI",
    "sg:tags":[
        "lawn",
        "maintenance",
        "grounds"
    ],
    "wof:name":"Granite Rodge Lawn & Landscape",
    "wof:placetype":"venue"
},
  "geometry": {"coordinates":[-88.29478,42.682267],"type":"Point"}
}