{
  "type": "Feature",
  "properties": {
    "addr:full":"11 N Main St Janesville WI 53545",
    "addr:housenumber":"11",
    "addr:postcode":"53545",
    "addr:street":"N Main St",
    "iso:country":"US",
    "sg:address":"11 N Main St",
    "sg:city":"Janesville",
    "sg:classifiers":[
        {
            "category":"Bars & Pubs",
            "type":"Food & Drink"
        }
    ],
    "sg:phone":"+1 608 755 1551",
    "sg:postcode":"53545",
    "sg:province":"WI",
    "sg:tags":[
        "drinking"
    ],
    "wof:name":"Legends",
    "wof:placetype":"venue"
},
  "geometry": {"coordinates":[-89.02334,42.68355],"type":"Point"}
}