{
  "type": "Feature",
  "properties": {
    "iso:country":"US",
    "sg:address":"211 Estate Ct",
    "sg:city":"Elkhorn",
    "sg:classifiers":[
        {
            "category":"Professional",
            "subcategory":"Engineering",
            "type":"Services"
        }
    ],
    "sg:phone":"+1 262 723 2095",
    "sg:postcode":"53121",
    "sg:province":"WI",
    "sg:tags":[
        "firm",
        "mechanical"
    ],
    "wof:name":"Geneva Research",
    "wof:placetype":"venue"
},
  "geometry": {"coordinates":[-88.547727,42.683786],"type":"Point"}
}