{
  "type": "Feature",
  "properties": {
    "iso:country":"US",
    "sg:address":"505 Linda",
    "sg:city":"Mount Horeb",
    "sg:classifiers":[
        {
            "category":"Building & Trades",
            "subcategory":"Construction",
            "type":"Services"
        }
    ],
    "sg:phone":"+1 608 437 3742",
    "sg:postcode":"53572",
    "sg:province":"WI",
    "sg:tags":[
        "nonresidential"
    ],
    "wof:name":"Pete Keller Construction",
    "wof:placetype":"venue"
},
  "geometry": {"coordinates":[-89.721673,43.013628],"type":"Point"}
}