{
  "type": "Feature",
  "properties": {
    "addr:full":"201 Industrial Dr Beaver Dam WI 53916",
    "addr:housenumber":"201",
    "addr:postcode":"53916",
    "addr:street":"Industrial Dr",
    "iso:country":"US",
    "sg:address":"201 Industrial Dr",
    "sg:city":"Beaver Dam",
    "sg:classifiers":[
        {
            "category":"Manufacturing",
            "subcategory":"Chemicals & Compounds",
            "type":"Manufacturing & Wholesale Goods"
        }
    ],
    "sg:phone":"+1 920 887 7166",
    "sg:postcode":"53916",
    "sg:province":"WI",
    "sg:tags":[
        "metal"
    ],
    "sg:website":"www.burgessnorton.com",
    "wof:name":"Burgess-Norton Mfg Co",
    "wof:placetype":"venue"
},
  "geometry": {"coordinates":[-88.827478,43.477095],"type":"Point"}
}