{
  "type": "Feature",
  "properties": {
    "iso:country":"US",
    "sg:address":"164 E 1st St",
    "sg:city":"Fond Du Lac",
    "sg:classifiers":[
        {
            "category":"Bars & Pubs",
            "type":"Food & Drink"
        }
    ],
    "sg:phone":"+1 920 926 1877",
    "sg:postcode":"54935",
    "sg:province":"WI",
    "wof:name":"Affordable DJ Entertainment",
    "wof:placetype":"venue"
},
  "geometry": {"coordinates":[-88.439504,43.775912],"type":"Point"}
}