{
  "type": "Feature",
  "properties": {
    "addr:full":"237 Broad St Lake Geneva WI 53147",
    "addr:housenumber":"237",
    "addr:postcode":"53147",
    "addr:street":"Broad St",
    "iso:country":"US",
    "sg:address":"237 Broad St",
    "sg:city":"Lake Geneva",
    "sg:classifiers":[
        {
            "category":"Shopping",
            "type":"Retail Goods"
        }
    ],
    "sg:phone":"+1 262 248 9100",
    "sg:postcode":"53147",
    "sg:province":"WI",
    "sg:tags":[
        "art",
        "gallery",
        "dealer"
    ],
    "wof:name":"Waterfront Gallery",
    "wof:placetype":"venue"
},
  "geometry": {"coordinates":[-88.435256,42.591887],"type":"Point"}
}