{
  "type": "Feature",
  "properties": {
    "iso:country":"US",
    "sg:address":"1701 Washington St",
    "sg:city":"Manitowoc",
    "sg:classifiers":[
        {
            "category":"Banks & Credit Unions",
            "subcategory":"Bank",
            "type":"Services"
        }
    ],
    "sg:phone":"+1 920 686 0178",
    "sg:postcode":"54220",
    "sg:province":"WI",
    "wof:name":"Manitowoc County Empl Cu",
    "wof:placetype":"venue"
},
  "geometry": {"coordinates":[-87.671444,44.088935],"type":"Point"}
}