{
  "type": "Feature",
  "properties": {
    "iso:country":"US",
    "sg:address":"4625 Michaels Dr",
    "sg:city":"Appleton",
    "sg:classifiers":[
        {
            "category":"Shopping",
            "subcategory":"Clothing, Apparel, & Fashions",
            "type":"Retail Goods"
        }
    ],
    "sg:phone":"+1 920 738 6600",
    "sg:postcode":"54913",
    "sg:province":"WI",
    "sg:tags":[
        "shop",
        "bridal"
    ],
    "wof:name":"David's Bridal",
    "wof:placetype":"venue"
},
  "geometry": {"coordinates":[-88.476434,44.267542],"type":"Point"}
}