{
  "type": "Feature",
  "properties": {
    "iso:country":"US",
    "sg:address":"3245 Paradise Rd",
    "sg:city":"Chilton",
    "sg:classifiers":[
        {
            "category":"Farming",
            "subcategory":"Dairy Farm",
            "type":"Manufacturing & Wholesale Goods"
        }
    ],
    "sg:phone":"+1 920 849 4323",
    "sg:postcode":"53014",
    "sg:province":"WI",
    "sg:tags":[
        "field",
        "crop"
    ],
    "wof:name":"Jersey Creek Dairy",
    "wof:placetype":"venue"
},
  "geometry": {"coordinates":[-88.191712,43.97925],"type":"Point"}
}