{
  "type": "Feature",
  "properties": {
    "iso:country":"US",
    "sg:address":"5440 Wild Rose Ln",
    "sg:city":"Eau Claire",
    "sg:classifiers":[
        {
            "category":"Professional",
            "subcategory":"Computer Services",
            "type":"Services"
        }
    ],
    "sg:phone":"+1 715 833 7696",
    "sg:postcode":"54701",
    "sg:province":"WI",
    "sg:tags":[
        "programing",
        "custom"
    ],
    "wof:name":"Lowes Creek Consulting LLC",
    "wof:placetype":"venue"
},
  "geometry": {"coordinates":[-91.464221,44.75279],"type":"Point"}
}