{
  "type": "Feature",
  "properties": {
    "addr:full":"1824 N Farwell Ave Milwaukee WI 53202",
    "addr:housenumber":"1824",
    "addr:postcode":"53202",
    "addr:street":"N Farwell Ave",
    "iso:country":"US",
    "sg:address":"1824 N Farwell Ave",
    "sg:city":"Milwaukee",
    "sg:classifiers":[
        {
            "category":"Restaurant",
            "type":"Food & Drink"
        }
    ],
    "sg:menulink":"http://www.allmenus.com/wi/milwaukee/185034-ethiopian-cottage-restaurant/menu/",
    "sg:phone":"+1 414 224 5226",
    "sg:postcode":"53202",
    "sg:province":"WI",
    "sg:tags":[
        "ethiopian"
    ],
    "wof:name":"Ethiopian Cottage Restaurant",
    "wof:placetype":"venue"
},
  "geometry": {"coordinates":[-87.890778,43.054594],"type":"Point"}
}