{
  "type": "Feature",
  "properties": {
    "iso:country":"US",
    "sg:address":"912 W Nash St",
    "sg:city":"Milwaukee",
    "sg:classifiers":[
        {
            "category":"Building & Trades",
            "subcategory":"Construction",
            "type":"Services"
        }
    ],
    "sg:phone":"+1 414 264 6147",
    "sg:postcode":"53206",
    "sg:province":"WI",
    "sg:tags":[
        "house"
    ],
    "wof:name":"AG Home Improvement",
    "wof:placetype":"venue"
},
  "geometry": {"coordinates":[-87.92342499999999,43.084503],"type":"Point"}
}