{
  "type": "Feature",
  "properties": {
    "iso:country":"US",
    "sg:address":"2701 Packers Ave",
    "sg:city":"Madison",
    "sg:classifiers":[
        {
            "category":"Real Estate",
            "subcategory":"Real Estate Operator",
            "type":"Services"
        }
    ],
    "sg:phone":"+1 608 241 5838",
    "sg:postcode":"53704",
    "sg:province":"WI",
    "sg:tags":[
        "property",
        "commercial",
        "operates"
    ],
    "wof:name":"Vogel Properties Inc",
    "wof:placetype":"venue"
},
  "geometry": {"coordinates":[-89.355074,43.128542],"type":"Point"}
}