{
  "type": "Feature",
  "properties": {
    "addr:full":"14145 W Greenfield Ave New Berlin WI 53151",
    "addr:housenumber":"14145",
    "addr:postcode":"53151",
    "addr:street":"W Greenfield Ave",
    "iso:country":"US",
    "sg:address":"14145 W Greenfield Ave",
    "sg:city":"New Berlin",
    "sg:classifiers":[
        {
            "category":"Health Services",
            "subcategory":"Optometrist",
            "type":"Services"
        }
    ],
    "sg:phone":"+1 262 784 6446",
    "sg:postcode":"53151",
    "sg:province":"WI",
    "wof:name":"New Berlin Vision Care",
    "wof:placetype":"venue"
},
  "geometry": {"coordinates":[-88.088893,43.016488],"type":"Point"}
}