{
  "type": "Feature",
  "properties": {
    "iso:country":"US",
    "sg:address":"639 Mount Nemo Ave",
    "sg:city":"Eau Claire",
    "sg:classifiers":[
        {
            "category":"Manufacturing",
            "subcategory":"Tools & Machinery",
            "type":"Manufacturing & Wholesale Goods"
        }
    ],
    "sg:phone":"+1 715 271 1688",
    "sg:postcode":"54703",
    "sg:province":"WI",
    "sg:tags":[
        "electrical",
        "mfg"
    ],
    "wof:name":"Northtowne Electric Co LLC",
    "wof:placetype":"venue"
},
  "geometry": {"coordinates":[-91.472205,44.82269],"type":"Point"}
}