{
  "type": "Feature",
  "properties": {
    "iso:country":"US",
    "sg:address":"447 Brookwood Dr",
    "sg:city":"Hudson",
    "sg:classifiers":[
        {
            "category":"Arts & Performance",
            "subcategory":"Theater",
            "type":"Entertainment"
        }
    ],
    "sg:phone":"+1 715 386 5590",
    "sg:postcode":"54016",
    "sg:province":"WI",
    "sg:tags":[
        "group"
    ],
    "wof:name":"All American DJ",
    "wof:placetype":"venue"
},
  "geometry": {"coordinates":[-92.712433,44.997297],"type":"Point"}
}