{
  "type": "Feature",
  "properties": {
    "iso:country":"US",
    "sg:address":"1565 Greenwood Dr",
    "sg:city":"Mosinee",
    "sg:classifiers":[
        {
            "category":"Retail",
            "subcategory":"Repair Shop",
            "type":"Services"
        }
    ],
    "sg:phone":"+1 715 693 5701",
    "sg:postcode":"54455",
    "sg:province":"WI",
    "wof:name":"Professionals Choice",
    "wof:placetype":"venue"
},
  "geometry": {"coordinates":[-89.665519,44.824186],"type":"Point"}
}