{
  "type": "Feature",
  "properties": {
    "iso:country":"US",
    "sg:address":"4049 N Stowell Ave",
    "sg:city":"Milwaukee",
    "sg:classifiers":[
        {
            "category":"Shopping",
            "subcategory":"Stationery & Office Supplies",
            "type":"Retail Goods"
        },
        {
            "category":"Shopping",
            "subcategory":"Crafts & Fabrics",
            "type":"Retail Goods"
        }
    ],
    "sg:phone":"+1 414 332 2442",
    "sg:postcode":"53211",
    "sg:province":"WI",
    "sg:tags":[
        "stencil",
        "art"
    ],
    "wof:name":"Lynnier Concepts",
    "wof:placetype":"venue"
},
  "geometry": {"coordinates":[-87.87879700000001,43.090401],"type":"Point"}
}