{
  "type": "Feature",
  "properties": {
    "addr:full":"403 State Hwy 82 Mauston WI 53948",
    "addr:housenumber":"403",
    "addr:postcode":"53948",
    "addr:street":"State Hwy 82",
    "iso:country":"US",
    "sg:address":"403 State Hwy 82",
    "sg:city":"Mauston",
    "sg:classifiers":[
        {
            "category":"Restaurant",
            "type":"Food & Drink"
        }
    ],
    "sg:phone":"+1 608 847 4001",
    "sg:postcode":"53948",
    "sg:province":"WI",
    "wof:name":"A & W Family Restaurant",
    "wof:placetype":"venue"
},
  "geometry": {"coordinates":[-90.07704,43.793625],"type":"Point"}
}