{
  "type": "Feature",
  "properties": {
    "iso:country":"US",
    "sg:address":"2306 S 98th St",
    "sg:city":"Milwaukee",
    "sg:classifiers":[
        {
            "category":"Organizations",
            "subcategory":"Religious Organization",
            "type":"Services"
        }
    ],
    "sg:phone":"+1 414 321 8430",
    "sg:postcode":"53227",
    "sg:province":"WI",
    "sg:tags":[
        "church"
    ],
    "wof:name":"Emmanuel Lutheran Church-Deaf",
    "wof:placetype":"venue"
},
  "geometry": {"coordinates":[-88.034519,43.000856],"type":"Point"}
}