{
  "type": "Feature",
  "properties": {
    "iso:country":"US",
    "sg:address":"4008 S Howell Ave",
    "sg:city":"Milwaukee",
    "sg:classifiers":[
        {
            "category":"Insurance",
            "subcategory":"Insurance Agent",
            "type":"Services"
        }
    ],
    "sg:phone":"+1 414 431 0676",
    "sg:postcode":"53207",
    "sg:province":"WI",
    "wof:name":"Guardian Professional Billing",
    "wof:placetype":"venue"
},
  "geometry": {"coordinates":[-87.909478,42.970244],"type":"Point"}
}