{
  "type": "Feature",
  "properties": {
    "iso:country":"US",
    "sg:address":"7225 W River Rd",
    "sg:city":"Caledonia",
    "sg:classifiers":[
        {
            "category":"Professional",
            "subcategory":"Art Services",
            "type":"Services"
        }
    ],
    "sg:phone":"+1 262 752 6162",
    "sg:postcode":"53108",
    "sg:province":"WI",
    "sg:tags":[
        "commercial",
        "design"
    ],
    "wof:name":"Impact Design",
    "wof:placetype":"venue"
},
  "geometry": {"coordinates":[-87.878357,42.822561],"type":"Point"}
}