{
  "type": "Feature",
  "properties": {
    "addr:full":"1810 S Park St Madison WI 53715",
    "addr:housenumber":"1810",
    "addr:postcode":"53715",
    "addr:street":"S Park St",
    "iso:country":"US",
    "sg:address":"1810 S Park St",
    "sg:city":"Madison",
    "sg:classifiers":[
        {
            "category":"Cinema",
            "subcategory":"Movie Theater",
            "type":"Entertainment"
        }
    ],
    "sg:phone":"+1 608 255 0545",
    "sg:postcode":"53715",
    "sg:province":"WI",
    "wof:name":"CTM Madison Family Theater C",
    "wof:placetype":"venue"
},
  "geometry": {"coordinates":[-89.39412900000001,43.046624],"type":"Point"}
}