{
  "type": "Feature",
  "properties": {
    "iso:country":"US",
    "sg:address":"975 E Randy Rd",
    "sg:city":"Oak Creek",
    "sg:classifiers":[
        {
            "category":"Building & Trades",
            "subcategory":"Construction",
            "type":"Services"
        }
    ],
    "sg:phone":"+1 414 764 9220",
    "sg:postcode":"53154",
    "sg:province":"WI",
    "sg:tags":[
        "windows",
        "roofing",
        "siding",
        "door",
        "contractor"
    ],
    "wof:name":"We Fix It Inc",
    "wof:placetype":"venue"
},
  "geometry": {"coordinates":[-87.901994,42.84701],"type":"Point"}
}