{
  "type": "Feature",
  "properties": {
    "iso:country":"US",
    "sg:address":"6840 Wazeecha Ave",
    "sg:city":"Wisconsin Rapids",
    "sg:classifiers":[
        {
            "category":"Professional",
            "subcategory":"Business Services",
            "type":"Services"
        }
    ],
    "sg:phone":"+1 715 421 5534",
    "sg:postcode":"54494",
    "sg:province":"WI",
    "wof:name":"River City Process Servers",
    "wof:placetype":"venue"
},
  "geometry": {"coordinates":[-89.739101,44.366936],"type":"Point"}
}