{
  "type": "Feature",
  "properties": {
    "iso:country":"US",
    "sg:address":"5429 Prairie Dr",
    "sg:city":"Plover",
    "sg:classifiers":[
        {
            "category":"Home & Garden",
            "subcategory":"Mobile Homes",
            "type":"Retail Goods"
        }
    ],
    "sg:phone":"+1 715 341 0050",
    "sg:postcode":"54467",
    "sg:province":"WI",
    "wof:name":"Steenberg Homes Inc",
    "wof:placetype":"venue"
},
  "geometry": {"coordinates":[-89.51754699999999,44.424875],"type":"Point"}
}