{
  "type": "Feature",
  "properties": {
    "iso:country":"US",
    "sg:address":"1526 S 12th St",
    "sg:city":"Sheboygan",
    "sg:classifiers":[
        {
            "category":"Professional",
            "subcategory":"Lawyer & Legal Services",
            "type":"Services"
        }
    ],
    "sg:phone":"+1 920 457 7744",
    "sg:postcode":"53081",
    "sg:province":"WI",
    "sg:tags":[
        "attorney"
    ],
    "wof:name":"Fale Fale & Hemsing Law Office",
    "wof:placetype":"venue"
},
  "geometry": {"coordinates":[-87.71968,43.737602],"type":"Point"}
}