{
  "type": "Feature",
  "properties": {
    "addr:full":"2737 N 54th St Milwaukee WI 53210",
    "addr:housenumber":"2737",
    "addr:postcode":"53210",
    "addr:street":"N 54Th St",
    "iso:country":"US",
    "sg:address":"2737 N 54th St",
    "sg:city":"Milwaukee",
    "sg:classifiers":[
        {
            "category":"Social Services",
            "subcategory":"Child Care",
            "type":"Services"
        },
        {
            "category":"Social Services",
            "type":"Services"
        }
    ],
    "sg:phone":"+1 414 444 5288",
    "sg:postcode":"53210",
    "sg:province":"WI",
    "sg:tags":[
        "center",
        "day"
    ],
    "wof:name":"Shekias Dreamworld",
    "wof:placetype":"venue"
},
  "geometry": {"coordinates":[-87.981049,43.069144],"type":"Point"}
}