{
  "type": "Feature",
  "properties": {
    "iso:country":"US",
    "sg:address":"405 Haskell St",
    "sg:city":"Beaver Dam",
    "sg:classifiers":[
        {
            "category":"Shopping",
            "subcategory":"Stationery & Office Supplies",
            "type":"Retail Goods"
        }
    ],
    "sg:phone":"+1 920 887 7137",
    "sg:postcode":"53916",
    "sg:province":"WI",
    "wof:name":"A1 Laser & Ribbon",
    "wof:placetype":"venue"
},
  "geometry": {"coordinates":[-88.84914999999999,43.454915],"type":"Point"}
}