{
  "type": "Feature",
  "properties": {
    "iso:country":"US",
    "sg:address":"28541 Beach Dr",
    "sg:city":"Waterford",
    "sg:classifiers":[
        {
            "category":"Building & Trades",
            "subcategory":"Plumbing",
            "type":"Services"
        }
    ],
    "sg:phone":"+1 262 895 7170",
    "sg:postcode":"53185",
    "sg:province":"WI",
    "sg:tags":[
        "plumbing",
        "contractor"
    ],
    "wof:name":"Gorsline Plumbing and Contg",
    "wof:placetype":"venue"
},
  "geometry": {"coordinates":[-88.200666,42.809661],"type":"Point"}
}