{
  "type": "Feature",
  "properties": {
    "iso:country":"US",
    "sg:address":"1080 1st Ave",
    "sg:city":"Ridgeland",
    "sg:classifiers":[
        {
            "category":"Farming",
            "subcategory":"Dairy Farm",
            "type":"Manufacturing & Wholesale Goods"
        }
    ],
    "sg:phone":"+1 715 949 1657",
    "sg:postcode":"54763",
    "sg:province":"WI",
    "sg:tags":[
        "product"
    ],
    "wof:name":"Gary Kahl",
    "wof:placetype":"venue"
},
  "geometry": {"coordinates":[-91.93589,45.224364],"type":"Point"}
}