{
  "type": "Feature",
  "properties": {
    "iso:country":"US",
    "sg:address":"1335 N Dr Martin Luther King Dr",
    "sg:city":"Milwaukee",
    "sg:classifiers":[
        {
            "category":"Farming",
            "subcategory":"Fish & Marine Products",
            "type":"Manufacturing & Wholesale Goods"
        }
    ],
    "sg:phone":"+1 414 224 0486",
    "sg:postcode":"53212",
    "sg:province":"WI",
    "sg:tags":[
        "tropical"
    ],
    "wof:name":"Aqua Exhibits",
    "wof:placetype":"venue"
},
  "geometry": {"coordinates":[-87.914374,43.047537],"type":"Point"}
}