{
  "type": "Feature",
  "properties": {
    "addr:full":"308 Pierce Ave Little Chute WI 54140",
    "addr:housenumber":"308",
    "addr:postcode":"54140",
    "addr:street":"Pierce Ave",
    "iso:country":"US",
    "sg:address":"308 Pierce Ave",
    "sg:city":"Little Chute",
    "sg:classifiers":[
        {
            "category":"Personal",
            "subcategory":"Beauty Salon",
            "type":"Services"
        }
    ],
    "sg:phone":"+1 920 788 5019",
    "sg:postcode":"54140",
    "sg:province":"WI",
    "sg:tags":[
        "shop"
    ],
    "wof:name":"Girls Hair Fashion",
    "wof:placetype":"venue"
},
  "geometry": {"coordinates":[-88.32058000000001,44.283561],"type":"Point"}
}