{
  "type": "Feature",
  "properties": {
    "iso:country":"US",
    "sg:address":"1232 State Hwy 60",
    "sg:city":"Cedarburg",
    "sg:classifiers":[
        {
            "category":"Farming",
            "subcategory":"Dairy Farm",
            "type":"Manufacturing & Wholesale Goods"
        }
    ],
    "sg:phone":"+1 262 677 3137",
    "sg:postcode":"53012",
    "sg:province":"WI",
    "wof:name":"Ray Pecher",
    "wof:placetype":"venue"
},
  "geometry": {"coordinates":[-88.103391,43.323088],"type":"Point"}
}