{
  "type": "Feature",
  "properties": {
    "iso:country":"US",
    "sg:address":"1110 Wayne Rd",
    "sg:city":"West Bend",
    "sg:classifiers":[
        {
            "category":"Freight",
            "type":"Transportation"
        }
    ],
    "sg:phone":"+1 262 306 1155",
    "sg:postcode":"53090",
    "sg:province":"WI",
    "sg:tags":[
        "operator",
        "local",
        "trucking"
    ],
    "wof:name":"REB Trucking Corp",
    "wof:placetype":"venue"
},
  "geometry": {"coordinates":[-88.190833,43.437253],"type":"Point"}
}