{
  "type": "Feature",
  "properties": {
    "iso:country":"US",
    "sg:address":"29 Sherman Ave W",
    "sg:city":"Fort Atkinson",
    "sg:classifiers":[
        {
            "category":"Bars & Pubs",
            "type":"Food & Drink"
        }
    ],
    "sg:phone":"+1 920 563 4646",
    "sg:postcode":"53538",
    "sg:province":"WI",
    "sg:tags":[
        "drinking",
        "beverage",
        "alcoholic"
    ],
    "wof:name":"Belmont Casino",
    "wof:placetype":"venue"
},
  "geometry": {"coordinates":[-88.838173,42.929806],"type":"Point"}
}