{
  "type": "Feature",
  "properties": {
    "addr:full":"9478 Co Rd Bb Plainfield WI 54921",
    "addr:housenumber":"9478",
    "addr:postcode":"54921",
    "addr:street":"Co Rd",
    "iso:country":"US",
    "sg:address":"9478 Co Rd Bb",
    "sg:city":"Plainfield",
    "sg:classifiers":[
        {
            "category":"Real Estate",
            "subcategory":"Real Estate Operator",
            "type":"Services"
        }
    ],
    "sg:phone":"+1 715 366 7317",
    "sg:postcode":"54921",
    "sg:province":"WI",
    "sg:tags":[
        "property",
        "lessor"
    ],
    "wof:name":"Harvey Schmude",
    "wof:placetype":"venue"
},
  "geometry": {"coordinates":[-89.46273600000001,44.270056],"type":"Point"}
}