{
  "type": "Feature",
  "properties": {
    "addr:full":"7593 Dickinson Rd Greenleaf WI 54126",
    "addr:housenumber":"7593",
    "addr:postcode":"54126",
    "addr:street":"Dickinson Rd",
    "iso:country":"US",
    "sg:address":"7593 Dickinson Rd",
    "sg:city":"Greenleaf",
    "sg:classifiers":[
        {
            "category":"Government",
            "subcategory":"Office",
            "type":"Public Place"
        }
    ],
    "sg:phone":"+1 920 864 2480",
    "sg:postcode":"54126",
    "sg:province":"WI",
    "sg:tags":[
        "city"
    ],
    "wof:name":"Town Clerk",
    "wof:placetype":"venue"
},
  "geometry": {"coordinates":[-87.949018,44.274736],"type":"Point"}
}