{
  "type": "Feature",
  "properties": {
    "iso:country":"US",
    "sg:address":"33936 118th St",
    "sg:city":"Twin Lakes",
    "sg:classifiers":[
        {
            "category":"Professional",
            "subcategory":"Management & Consulting",
            "type":"Services"
        }
    ],
    "sg:phone":"+1 262 877 9940",
    "sg:postcode":"53181",
    "sg:province":"WI",
    "wof:name":"PAS Homes LLC",
    "wof:placetype":"venue"
},
  "geometry": {"coordinates":[-88.221073,42.507283],"type":"Point"}
}