{
  "type": "Feature",
  "properties": {
    "iso:country":"US",
    "sg:address":"2777 Allied St",
    "sg:city":"Green Bay",
    "sg:classifiers":[
        {
            "category":"Home & Garden",
            "subcategory":"Carpets & Floor Coverings",
            "type":"Retail Goods"
        }
    ],
    "sg:phone":"+1 920 494 6790",
    "sg:postcode":"54304",
    "sg:province":"WI",
    "sg:tags":[
        "dealer",
        "rug"
    ],
    "wof:name":"Carpet City",
    "wof:placetype":"venue"
},
  "geometry": {"coordinates":[-88.081107,44.475867],"type":"Point"}
}