{
  "type": "Feature",
  "properties": {
    "iso:country":"US",
    "sg:address":"919 Sauk Ave",
    "sg:city":"Baraboo",
    "sg:classifiers":[
        {
            "category":"Government",
            "subcategory":"Office",
            "type":"Public Place"
        }
    ],
    "sg:phone":"+1 608 356 4956",
    "sg:postcode":"53913",
    "sg:province":"WI",
    "sg:tags":[
        "village"
    ],
    "wof:name":"Sauk Ave Well-6",
    "wof:placetype":"venue"
},
  "geometry": {"coordinates":[-89.75849100000001,43.462148],"type":"Point"}
}