{
  "type": "Feature",
  "properties": {
    "iso:country":"US",
    "sg:address":"318 W Albert St",
    "sg:city":"Portage",
    "sg:classifiers":[
        {
            "category":"Professional",
            "subcategory":"Computer Services",
            "type":"Services"
        }
    ],
    "sg:phone":"+1 608 742 4157",
    "sg:postcode":"53901",
    "sg:province":"WI",
    "sg:tags":[
        "programing",
        "custom"
    ],
    "wof:name":"Dpe",
    "wof:placetype":"venue"
},
  "geometry": {"coordinates":[-89.470334,43.548683],"type":"Point"}
}