{
  "type": "Feature",
  "properties": {
    "iso:country":"US",
    "sg:address":"139 N Main St",
    "sg:city":"North Prairie",
    "sg:classifiers":[
        {
            "category":"Restaurant",
            "type":"Food & Drink"
        }
    ],
    "sg:phone":"+1 262 392 2201",
    "sg:postcode":"53153",
    "sg:province":"WI",
    "wof:name":"Ty's Tap",
    "wof:placetype":"venue"
},
  "geometry": {"coordinates":[-88.40552700000001,42.93434],"type":"Point"}
}