{
  "type": "Feature",
  "properties": {
    "iso:country":"US",
    "sg:address":"9071 N 95th St",
    "sg:city":"Milwaukee",
    "sg:classifiers":[
        {
            "category":"Retail",
            "subcategory":"Auto Repair",
            "type":"Services"
        }
    ],
    "sg:phone":"+1 414 362 0263",
    "sg:postcode":"53224",
    "sg:province":"WI",
    "sg:tags":[
        "repairing",
        "automobile"
    ],
    "wof:name":"Lewis Auto Repair",
    "wof:placetype":"venue"
},
  "geometry": {"coordinates":[-88.028793,43.180405],"type":"Point"}
}