{
  "type": "Feature",
  "properties": {
    "iso:country":"US",
    "sg:address":"7175 Rio Creek Rd",
    "sg:city":"Algoma",
    "sg:classifiers":[
        {
            "category":"Home & Garden",
            "subcategory":"Garden Supply",
            "type":"Retail Goods"
        }
    ],
    "sg:phone":"+1 920 837 2890",
    "sg:postcode":"54201",
    "sg:province":"WI",
    "sg:tags":[
        "bulb",
        "seed"
    ],
    "wof:name":"NK Seeds",
    "wof:placetype":"venue"
},
  "geometry": {"coordinates":[-87.541376,44.58508],"type":"Point"}
}