{
  "type": "Feature",
  "properties": {
    "addr:full":"200 2nd St Brokaw WI 54417",
    "addr:housenumber":"200",
    "addr:postcode":"54417",
    "addr:street":"2Nd St",
    "iso:country":"US",
    "sg:address":"200 2nd St",
    "sg:city":"Brokaw",
    "sg:classifiers":[
        {
            "category":"Government",
            "subcategory":"Office",
            "type":"Public Place"
        }
    ],
    "sg:phone":"+1 715 675 6002",
    "sg:postcode":"54417",
    "sg:province":"WI",
    "sg:tags":[
        "village"
    ],
    "wof:name":"Brokaw Village Hall",
    "wof:placetype":"venue"
},
  "geometry": {"coordinates":[-89.65293699999999,45.027999],"type":"Point"}
}