{
  "type": "Feature",
  "properties": {
    "iso:country":"US",
    "sg:address":"334 Richmond Dr",
    "sg:city":"Pewaukee",
    "sg:classifiers":[
        {
            "category":"Professional",
            "subcategory":"Art Services",
            "type":"Services"
        }
    ],
    "sg:phone":"+1 262 695 1150",
    "sg:postcode":"53072",
    "sg:province":"WI",
    "sg:tags":[
        "commercial",
        "design"
    ],
    "wof:name":"James Covert Design",
    "wof:placetype":"venue"
},
  "geometry": {"coordinates":[-88.25786600000001,43.078344],"type":"Point"}
}