{
  "type": "Feature",
  "properties": {
    "iso:country":"US",
    "sg:address":"1000 E Center St",
    "sg:city":"Milwaukee",
    "sg:classifiers":[
        {
            "category":"Personal",
            "type":"Services"
        }
    ],
    "sg:phone":"+1 414 374 8664",
    "sg:postcode":"53212",
    "sg:province":"WI",
    "sg:tags":[
        "dating"
    ],
    "wof:name":"Vibe Singles Connection",
    "wof:placetype":"venue"
},
  "geometry": {"coordinates":[-87.897847,43.067448],"type":"Point"}
}