{
  "type": "Feature",
  "properties": {
    "iso:country":"US",
    "sg:address":"2686 S 12th St",
    "sg:city":"Milwaukee",
    "sg:classifiers":[
        {
            "category":"Place Of Worship",
            "subcategory":"Church",
            "type":"Public Place"
        },
        {
            "category":"Place Of Worship",
            "type":"Public Place"
        }
    ],
    "sg:phone":"+1 414 645 7383",
    "sg:postcode":"53215",
    "sg:province":"WI",
    "sg:tags":[
        "churches-apostolic",
        "churches-pentecostal-apostolic"
    ],
    "wof:name":"Apostolic Missionary Church",
    "wof:placetype":"venue"
},
  "geometry": {"coordinates":[-87.927336,42.995765],"type":"Point"}
}