{
  "type": "Feature",
  "properties": {
    "iso:country":"US",
    "sg:address":"9280 Gopher Hill Rd",
    "sg:city":"Ixonia",
    "sg:classifiers":[
        {
            "category":"Building & Trades",
            "subcategory":"Construction",
            "type":"Services"
        }
    ],
    "sg:phone":"+1 414 315 3363",
    "sg:postcode":"53036",
    "sg:province":"WI",
    "sg:tags":[
        "masonry",
        "contractor"
    ],
    "wof:name":"Trukraft Concrete & Masonry",
    "wof:placetype":"venue"
},
  "geometry": {"coordinates":[-88.574626,43.17336],"type":"Point"}
}