{
  "type": "Feature",
  "properties": {
    "addr:full":"2814 35th Ave Elk Mound WI 54739",
    "addr:housenumber":"2814",
    "addr:postcode":"54739",
    "addr:street":"35Th Ave",
    "iso:country":"US",
    "sg:address":"2814 35th Ave",
    "sg:city":"Elk Mound",
    "sg:classifiers":[
        {
            "category":"Home & Garden",
            "subcategory":"Furniture",
            "type":"Retail Goods"
        }
    ],
    "sg:phone":"+1 715 874 6370",
    "sg:postcode":"54739",
    "sg:province":"WI",
    "sg:tags":[
        "cabinet"
    ],
    "wof:name":"Abby's Custom Woodworking",
    "wof:placetype":"venue"
},
  "geometry": {"coordinates":[-91.614363,44.893902],"type":"Point"}
}