{
  "type": "Feature",
  "properties": {
    "iso:country":"US",
    "sg:address":"116 Miner Ave E",
    "sg:city":"Ladysmith",
    "sg:classifiers":[
        {
            "category":"Cinema",
            "subcategory":"Movie Theater",
            "type":"Entertainment"
        }
    ],
    "sg:phone":"+1 715 532 7131",
    "sg:postcode":"54848",
    "sg:province":"WI",
    "sg:tags":[
        "motion",
        "picture"
    ],
    "wof:name":"Miner Theatre",
    "wof:placetype":"venue"
},
  "geometry": {"coordinates":[-91.10068,45.464159],"type":"Point"}
}