{
  "type": "Feature",
  "properties": {
    "iso:country":"US",
    "sg:address":"172 Country Club Dr",
    "sg:city":"Clintonville",
    "sg:classifiers":[
        {
            "category":"Insurance",
            "subcategory":"Insurance Agent",
            "type":"Services"
        }
    ],
    "sg:phone":"+1 715 823 6073",
    "sg:postcode":"54929",
    "sg:province":"WI",
    "wof:name":"AAL Insurance",
    "wof:placetype":"venue"
},
  "geometry": {"coordinates":[-88.77554000000001,44.634981],"type":"Point"}
}