{
  "type": "Feature",
  "properties": {
    "iso:country":"US",
    "sg:address":"2170 Co Hwy A",
    "sg:city":"Bloomer",
    "sg:classifiers":[
        {
            "category":"Bars & Pubs",
            "type":"Food & Drink"
        }
    ],
    "sg:phone":"+1 715 568 4858",
    "sg:postcode":"54724",
    "sg:province":"WI",
    "sg:tags":[
        "drinking"
    ],
    "wof:name":"Trout Creek Tavern",
    "wof:placetype":"venue"
},
  "geometry": {"coordinates":[-91.629124,45.087804],"type":"Point"}
}