{
  "type": "Feature",
  "properties": {
    "iso:country":"US",
    "sg:address":"576 Burr Oak Ln",
    "sg:city":"Hudson",
    "sg:classifiers":[
        {
            "category":"Building & Trades",
            "subcategory":"Construction",
            "type":"Services"
        }
    ],
    "sg:phone":"+1 715 549 6559",
    "sg:postcode":"54016",
    "sg:province":"WI",
    "sg:tags":[
        "contractor"
    ],
    "wof:name":"Lundgren Eldy Masonry",
    "wof:placetype":"venue"
},
  "geometry": {"coordinates":[-92.68555600000001,45.036835],"type":"Point"}
}