{
  "type": "Feature",
  "properties": {
    "iso:country":"US",
    "sg:address":"9166 Co Hwy M",
    "sg:city":"New Auburn",
    "sg:phone":"+1 715 237 2521",
    "sg:postcode":"54757",
    "sg:province":"WI",
    "sg:tags":[
        "farm",
        "corn"
    ],
    "wof:name":"Rego John",
    "wof:placetype":"venue"
},
  "geometry": {"coordinates":[-91.498085,45.22085],"type":"Point"}
}