{
  "type": "Feature",
  "properties": {
    "iso:country":"US",
    "sg:address":"9312 W National Ave",
    "sg:city":"Milwaukee",
    "sg:classifiers":[
        {
            "category":"Organizations",
            "subcategory":"Community Association",
            "type":"Services"
        }
    ],
    "sg:phone":"+1 414 541 7200",
    "sg:postcode":"53227",
    "sg:province":"WI",
    "wof:name":"Gmba",
    "wof:placetype":"venue"
},
  "geometry": {"coordinates":[-88.029555,43.003691],"type":"Point"}
}