{
  "type": "Feature",
  "properties": {
    "addr:full":"15400 W Mayflower Dr New Berlin WI 53151",
    "addr:housenumber":"15400",
    "addr:postcode":"53151",
    "addr:street":"W Mayflower Dr",
    "iso:country":"US",
    "sg:address":"15400 W Mayflower Dr",
    "sg:city":"New Berlin",
    "sg:classifiers":[
        {
            "category":"Restaurant",
            "type":"Food & Drink"
        }
    ],
    "sg:phone":"+1 262 784 6989",
    "sg:postcode":"53151",
    "sg:province":"WI",
    "sg:tags":[
        "eating"
    ],
    "wof:name":"Two Cousins",
    "wof:placetype":"venue"
},
  "geometry": {"coordinates":[-88.106847,42.966688],"type":"Point"}
}