{
  "type": "Feature",
  "properties": {
    "iso:country":"US",
    "sg:address":"200 Spring St",
    "sg:city":"Eau Claire",
    "sg:classifiers":[
        {
            "category":"Shopping",
            "subcategory":"Computers & Home Electronics",
            "type":"Retail Goods"
        }
    ],
    "sg:phone":"+1 715 833 5204",
    "sg:postcode":"54703",
    "sg:province":"WI",
    "wof:name":"Accounting Solutions",
    "wof:placetype":"venue"
},
  "geometry": {"coordinates":[-91.487044,44.816924],"type":"Point"}
}