{
  "type": "Feature",
  "properties": {
    "iso:country":"US",
    "sg:address":"7129 Co Rd C",
    "sg:city":"Plymouth",
    "sg:classifiers":[
        {
            "category":"Building & Trades",
            "subcategory":"Construction",
            "type":"Services"
        }
    ],
    "sg:phone":"+1 920 526 3862",
    "sg:postcode":"53073",
    "sg:province":"WI",
    "sg:tags":[
        "excavation",
        "contractor"
    ],
    "wof:name":"Baumann Excavating Inc",
    "wof:placetype":"venue"
},
  "geometry": {"coordinates":[-88.01503599999999,43.800763],"type":"Point"}
}