{
  "type": "Feature",
  "properties": {
    "addr:full":"3550 N Main St Oshkosh WI 54901",
    "addr:housenumber":"3550",
    "addr:postcode":"54901",
    "addr:street":"N Main St",
    "iso:country":"US",
    "sg:address":"3550 N Main St",
    "sg:city":"Oshkosh",
    "sg:classifiers":[
        {
            "category":"Manufacturing",
            "subcategory":"Rubber & Plastics",
            "type":"Manufacturing & Wholesale Goods"
        }
    ],
    "sg:phone":"+1 920 233 2020",
    "sg:postcode":"54901",
    "sg:province":"WI",
    "sg:tags":[
        "product"
    ],
    "wof:name":"Weldon",
    "wof:placetype":"venue"
},
  "geometry": {"coordinates":[-88.53796199999999,44.065158],"type":"Point"}
}