{
  "type": "Feature",
  "properties": {
    "iso:country":"US",
    "sg:address":"3624 17th Ave",
    "sg:city":"Kenosha",
    "sg:classifiers":[
        {
            "category":"Social Services",
            "type":"Services"
        }
    ],
    "sg:phone":"+1 262 605 0809",
    "sg:postcode":"53140",
    "sg:province":"WI",
    "wof:name":"Compassionate Care Counseling",
    "wof:placetype":"venue"
},
  "geometry": {"coordinates":[-87.829787,42.603623],"type":"Point"}
}