{
  "type": "Feature",
  "properties": {
    "iso:country":"US",
    "sg:address":"2220 Peterson Ave",
    "sg:city":"Eau Claire",
    "sg:classifiers":[
        {
            "category":"Building & Trades",
            "subcategory":"Plumbing",
            "type":"Services"
        }
    ],
    "sg:phone":"+1 715 835 1760",
    "sg:postcode":"54703",
    "sg:province":"WI",
    "sg:tags":[
        "repair",
        "electrical",
        "contractor"
    ],
    "wof:name":"Environmental Systems Htg & AC",
    "wof:placetype":"venue"
},
  "geometry": {"coordinates":[-91.437784,44.842525],"type":"Point"}
}