{
  "type": "Feature",
  "properties": {
    "addr:full":"4751 US Hwy 8 Bus Rhinelander WI 54501",
    "addr:housenumber":"4751",
    "addr:postcode":"54501",
    "addr:street":"Us Hwy 8 Bus",
    "iso:country":"US",
    "sg:address":"4751 US Hwy 8 Bus",
    "sg:city":"Rhinelander",
    "sg:classifiers":[
        {
            "category":"Building & Trades",
            "subcategory":"Construction",
            "type":"Services"
        }
    ],
    "sg:phone":"+1 715 362 3846",
    "sg:postcode":"54501",
    "sg:province":"WI",
    "sg:tags":[
        "masonry",
        "contractor"
    ],
    "wof:name":"Advanced Concrete & Masonry",
    "wof:placetype":"venue"
},
  "geometry": {"coordinates":[-89.372816,45.63034],"type":"Point"}
}