{
  "type": "Feature",
  "properties": {
    "addr:full":"300 E Main St Sun Prairie WI 53590",
    "addr:housenumber":"300",
    "addr:postcode":"53590",
    "addr:street":"E Main St",
    "iso:country":"US",
    "sg:address":"300 E Main St",
    "sg:city":"Sun Prairie",
    "sg:classifiers":[
        {
            "category":"Government",
            "subcategory":"Office",
            "type":"Public Place"
        }
    ],
    "sg:phone":"+1 608 825 1193",
    "sg:postcode":"53590",
    "sg:province":"WI",
    "sg:tags":[
        "executive"
    ],
    "wof:name":"City Administrators Office",
    "wof:placetype":"venue"
},
  "geometry": {"coordinates":[-89.211113,43.182995],"type":"Point"}
}