{
  "type": "Feature",
  "properties": {
    "iso:country":"US",
    "sg:address":"802 W Johnson St",
    "sg:city":"Fond Du Lac",
    "sg:classifiers":[
        {
            "category":"Restaurant",
            "type":"Food & Drink"
        }
    ],
    "sg:phone":"+1 920 929 8881",
    "sg:postcode":"54935",
    "sg:province":"WI",
    "sg:tags":[
        "eating"
    ],
    "wof:name":"Mandarin Garden",
    "wof:placetype":"venue"
},
  "geometry": {"coordinates":[-88.477419,43.784255],"type":"Point"}
}