{
  "type": "Feature",
  "properties": {
    "iso:country":"US",
    "sg:address":"805 5th Ave",
    "sg:city":"Antigo",
    "sg:classifiers":[
        {
            "category":"Wholesale",
            "subcategory":"Medical Equipment & Supplies",
            "type":"Manufacturing & Wholesale Goods"
        }
    ],
    "sg:phone":"+1 715 623 7272",
    "sg:postcode":"54409",
    "sg:province":"WI",
    "sg:tags":[
        "hospital"
    ],
    "wof:name":"Home Medical Products & Servic",
    "wof:placetype":"venue"
},
  "geometry": {"coordinates":[-89.156169,45.140497],"type":"Point"}
}