{
  "type": "Feature",
  "properties": {
    "iso:country":"US",
    "sg:address":"7358 Brunn Dr",
    "sg:city":"Franklin",
    "sg:classifiers":[
        {
            "category":"Professional",
            "subcategory":"Management & Consulting",
            "type":"Services"
        }
    ],
    "sg:phone":"+1 414 425 0106",
    "sg:postcode":"53132",
    "sg:province":"WI",
    "sg:tags":[
        "business"
    ],
    "wof:name":"Integrts Prfssnl Cnsltng & Stf",
    "wof:placetype":"venue"
},
  "geometry": {"coordinates":[-88.00486,42.910412],"type":"Point"}
}