{
  "type": "Feature",
  "properties": {
    "iso:country":"US",
    "sg:address":"2775 Co Rd J",
    "sg:city":"Fort Atkinson",
    "sg:classifiers":[
        {
            "category":"Building & Trades",
            "subcategory":"Construction",
            "type":"Services"
        }
    ],
    "sg:phone":"+1 920 563 2061",
    "sg:postcode":"53538",
    "sg:province":"WI",
    "sg:tags":[
        "housing",
        "family",
        "contractor"
    ],
    "sg:website":"www.bosdesignbuilders.com",
    "wof:name":"Bos Design Builders LLC",
    "wof:placetype":"venue"
},
  "geometry": {"coordinates":[-88.911394,42.93909],"type":"Point"}
}