{
  "type": "Feature",
  "properties": {
    "addr:full":"3962 Meadow Dr Fond Du Lac WI 54935",
    "addr:housenumber":"3962",
    "addr:postcode":"54935",
    "addr:street":"Meadow Dr",
    "iso:country":"US",
    "sg:address":"3962 Meadow Dr",
    "sg:city":"Fond Du Lac",
    "sg:phone":"+1 920 921 9462",
    "sg:postcode":"54935",
    "sg:province":"WI",
    "sg:tags":[
        "oil"
    ],
    "wof:name":"Mengel Oil Co",
    "wof:placetype":"venue"
},
  "geometry": {"coordinates":[-88.357857,43.835038],"type":"Point"}
}