{
  "type": "Feature",
  "properties": {
    "addr:full":"440 S Washington St Green Bay WI 54301",
    "addr:housenumber":"440",
    "addr:postcode":"54301",
    "addr:street":"S Washington St",
    "iso:country":"US",
    "sg:address":"440 S Washington St",
    "sg:city":"Green Bay",
    "sg:classifiers":[
        {
            "category":"Banks & Credit Unions",
            "subcategory":"Investment Brokerage",
            "type":"Services"
        }
    ],
    "sg:phone":"+1 920 437 4377",
    "sg:postcode":"54301",
    "sg:province":"WI",
    "sg:tags":[
        "consultant",
        "planning",
        "financial"
    ],
    "wof:name":"Robert W Baird & Co",
    "wof:placetype":"venue"
},
  "geometry": {"coordinates":[-88.018829,44.509782],"type":"Point"}
}