{
  "type": "Feature",
  "properties": {
    "addr:full":"818 E 1st St Merrill WI 54452",
    "addr:housenumber":"818",
    "addr:postcode":"54452",
    "addr:street":"E 1St St",
    "iso:country":"US",
    "sg:address":"818 E 1st St",
    "sg:city":"Merrill",
    "sg:classifiers":[
        {
            "category":"Food & Beverages",
            "subcategory":"Bakery",
            "type":"Retail Goods"
        }
    ],
    "sg:phone":"+1 715 536 5911",
    "sg:postcode":"54452",
    "sg:province":"WI",
    "sg:tags":[
        "baker"
    ],
    "wof:name":"J & J's Baking Co",
    "wof:placetype":"venue"
},
  "geometry": {"coordinates":[-89.68769899999999,45.180736],"type":"Point"}
}