{
  "type": "Feature",
  "properties": {
    "addr:full":"19 W Newton St Rice Lake WI 54868",
    "addr:housenumber":"19",
    "addr:postcode":"54868",
    "addr:street":"W Newton St",
    "iso:country":"US",
    "sg:address":"19 W Newton St",
    "sg:city":"Rice Lake",
    "sg:classifiers":[
        {
            "category":"Health Services",
            "subcategory":"Nursing And Care Facility",
            "type":"Services"
        }
    ],
    "sg:phone":"+1 715 234 2161",
    "sg:postcode":"54868",
    "sg:province":"WI",
    "sg:tags":[
        "home",
        "convalescent"
    ],
    "wof:name":"Heritage Manor",
    "wof:placetype":"venue"
},
  "geometry": {"coordinates":[-91.73380400000001,45.50264],"type":"Point"}
}