{
  "type": "Feature",
  "properties": {
    "iso:country":"US",
    "sg:address":"500 W Bender Rd",
    "sg:city":"Milwaukee",
    "sg:classifiers":[
        {
            "category":"Shopping",
            "type":"Retail Goods"
        }
    ],
    "sg:phone":"+1 414 964 2007",
    "sg:postcode":"53217",
    "sg:province":"WI",
    "sg:tags":[
        "merchandise"
    ],
    "wof:name":"Billys Backyard Collectibles",
    "wof:placetype":"venue"
},
  "geometry": {"coordinates":[-87.914736,43.129608],"type":"Point"}
}