{
  "type": "Feature",
  "properties": {
    "iso:country":"US",
    "sg:address":"2111 E Main St",
    "sg:city":"Merrill",
    "sg:classifiers":[
        {
            "category":"Building & Trades",
            "subcategory":"Landscaping Services",
            "type":"Services"
        }
    ],
    "sg:phone":"+1 715 536 7038",
    "sg:postcode":"54452",
    "sg:province":"WI",
    "wof:name":"4ever Green Lawncare",
    "wof:placetype":"venue"
},
  "geometry": {"coordinates":[-89.671294,45.180655],"type":"Point"}
}