{
  "type": "Feature",
  "properties": {
    "iso:country":"US",
    "sg:address":"8520 82nd St",
    "sg:city":"Pleasant Prairie",
    "sg:classifiers":[
        {
            "category":"Real Estate",
            "subcategory":"Real Estate Agent",
            "type":"Services"
        }
    ],
    "sg:phone":"+1 262 942 7162",
    "sg:postcode":"53158",
    "sg:province":"WI",
    "wof:name":"Hidden Oaks Estate",
    "wof:placetype":"venue"
},
  "geometry": {"coordinates":[-87.908593,42.556287],"type":"Point"}
}