{
  "type": "Feature",
  "properties": {
    "iso:country":"US",
    "sg:address":"1937 Pleasant Valley Rd",
    "sg:city":"Grafton",
    "sg:classifiers":[
        {
            "category":"Social Services",
            "subcategory":"Child Care",
            "type":"Services"
        }
    ],
    "sg:phone":"+1 262 377 6804",
    "sg:postcode":"53024",
    "sg:province":"WI",
    "sg:tags":[
        "day"
    ],
    "wof:name":"Evergreen Child Care L L C",
    "wof:placetype":"venue"
},
  "geometry": {"coordinates":[-87.96506,43.352279],"type":"Point"}
}