{
  "type": "Feature",
  "properties": {
    "iso:country":"US",
    "sg:address":"11041 N Range Line Rd",
    "sg:city":"Thiensville",
    "sg:classifiers":[
        {
            "category":"Professional",
            "subcategory":"Business Services",
            "type":"Services"
        }
    ],
    "sg:phone":"+1 262 242 3426",
    "sg:postcode":"53092",
    "sg:province":"WI",
    "sg:tags":[
        "interior",
        "design"
    ],
    "wof:name":"Bonita J Timarac Intr Design",
    "wof:placetype":"venue"
},
  "geometry": {"coordinates":[-87.94404299999999,43.220666],"type":"Point"}
}