{
  "type": "Feature",
  "properties": {
    "iso:country":"US",
    "sg:address":"9269 Isaar Rd",
    "sg:city":"Seymour",
    "sg:classifiers":[
        {
            "category":"Organizations",
            "subcategory":"Religious Organization",
            "type":"Services"
        }
    ],
    "sg:phone":"+1 920 833 2558",
    "sg:postcode":"54165",
    "sg:province":"WI",
    "sg:tags":[
        "church"
    ],
    "wof:name":"St Sebastian Catholic Church",
    "wof:placetype":"venue"
},
  "geometry": {"coordinates":[-88.284595,44.571299],"type":"Point"}
}