{
  "type": "Feature",
  "properties": {
    "iso:country":"US",
    "sg:address":"2142 Utica Rd",
    "sg:city":"Cambridge",
    "sg:classifiers":[
        {
            "category":"Professional",
            "subcategory":"Management & Consulting",
            "type":"Services"
        }
    ],
    "sg:phone":"+1 608 423 7091",
    "sg:postcode":"53523",
    "sg:province":"WI",
    "sg:tags":[
        "business"
    ],
    "wof:name":"Mark Cook Consulting",
    "wof:placetype":"venue"
},
  "geometry": {"coordinates":[-89.106944,42.964424],"type":"Point"}
}