{
  "type": "Feature",
  "properties": {
    "iso:country":"US",
    "sg:address":"3901 S Webster Ave",
    "sg:city":"Green Bay",
    "sg:classifiers":[
        {
            "category":"Personal",
            "subcategory":"Beauty Salon",
            "type":"Services"
        }
    ],
    "sg:phone":"+1 920 337 2922",
    "sg:postcode":"54301",
    "sg:province":"WI",
    "sg:tags":[
        "shop"
    ],
    "wof:name":"Tru Colors Salon",
    "wof:placetype":"venue"
},
  "geometry": {"coordinates":[-88.039852,44.45855],"type":"Point"}
}