{
  "type": "Feature",
  "properties": {
    "addr:full":"2369 Julianne St Oconomowoc WI 53066",
    "addr:housenumber":"2369",
    "addr:postcode":"53066",
    "addr:street":"Julianne St",
    "iso:country":"US",
    "sg:address":"2369 Julianne St",
    "sg:city":"Oconomowoc",
    "sg:classifiers":[
        {
            "category":"Professional",
            "subcategory":"Employment Agencies",
            "type":"Services"
        }
    ],
    "sg:phone":"+1 920 474 3333",
    "sg:postcode":"53066",
    "sg:province":"WI",
    "sg:tags":[
        "help",
        "supply"
    ],
    "wof:name":"MRM Services",
    "wof:placetype":"venue"
},
  "geometry": {"coordinates":[-88.513351,43.221357],"type":"Point"}
}