{
  "type": "Feature",
  "properties": {
    "addr:full":"430 N Maple St Ellsworth WI 54011",
    "addr:housenumber":"430",
    "addr:postcode":"54011",
    "addr:street":"N Maple St",
    "iso:country":"US",
    "sg:address":"430 N Maple St",
    "sg:city":"Ellsworth",
    "sg:classifiers":[
        {
            "category":"Real Estate",
            "subcategory":"Real Estate Agent",
            "type":"Services"
        }
    ],
    "sg:phone":"+1 715 273 3600",
    "sg:postcode":"54011",
    "sg:province":"WI",
    "wof:name":"Edina Realty Inc",
    "wof:placetype":"venue"
},
  "geometry": {"coordinates":[-92.486878,44.739096],"type":"Point"}
}