{
  "type": "Feature",
  "properties": {
    "iso:country":"US",
    "sg:address":"8085 State Rd 77",
    "sg:city":"Danbury",
    "sg:classifiers":[
        {
            "category":"Autos & Motor Vehicles",
            "subcategory":"Automobile Sales",
            "type":"Retail Goods"
        },
        {
            "category":"Autos & Motor Vehicles",
            "subcategory":"Motorcycle Sales",
            "type":"Retail Goods"
        }
    ],
    "sg:phone":"+1 715 656 3563",
    "sg:postcode":"54830",
    "sg:province":"WI",
    "sg:tags":[
        "all",
        "terrain",
        "accessory",
        "parts",
        "snowmobile",
        "lease"
    ],
    "wof:name":"Traxx Motorsports Inc",
    "wof:placetype":"venue"
},
  "geometry": {"coordinates":[-92.408432,46.012295],"type":"Point"}
}