{
  "type": "Feature",
  "properties": {
    "iso:country":"US",
    "sg:address":"115 E Arndt St",
    "sg:city":"Fond Du Lac",
    "sg:classifiers":[
        {
            "category":"Health Services",
            "subcategory":"Nursing And Care Facility",
            "type":"Services"
        }
    ],
    "sg:phone":"+1 920 923 7040",
    "sg:postcode":"54935",
    "sg:province":"WI",
    "sg:tags":[
        "home",
        "convalescent"
    ],
    "wof:name":"All About Life Rehabilitation",
    "wof:placetype":"venue"
},
  "geometry": {"coordinates":[-88.439862,43.786197],"type":"Point"}
}