{
  "type": "Feature",
  "properties": {
    "addr:full":"649 Gale Ave Wisconsin Dells WI 53965",
    "addr:housenumber":"649",
    "addr:postcode":"53965",
    "addr:street":"Gale Ave",
    "iso:country":"US",
    "sg:address":"649 Gale Ave",
    "sg:city":"Wisconsin Dells",
    "sg:classifiers":[
        {
            "category":"Wholesale",
            "subcategory":"Auto Parts",
            "type":"Manufacturing & Wholesale Goods"
        }
    ],
    "sg:phone":"+1 608 254 2235",
    "sg:postcode":"53965",
    "sg:province":"WI",
    "sg:tags":[
        "automobile",
        "rebuilt"
    ],
    "wof:name":"Avery Armature Svc",
    "wof:placetype":"venue"
},
  "geometry": {"coordinates":[-89.71468,43.730822],"type":"Point"}
}