{
  "type": "Feature",
  "properties": {
    "addr:full":"1925 Roosevelt Ave Racine WI 53406",
    "addr:housenumber":"1925",
    "addr:postcode":"53406",
    "addr:street":"Roosevelt Ave",
    "iso:country":"US",
    "sg:address":"1925 Roosevelt Ave",
    "sg:city":"Racine",
    "sg:classifiers":[
        {
            "category":"Wholesale",
            "subcategory":"Sporting Goods",
            "type":"Manufacturing & Wholesale Goods"
        }
    ],
    "sg:phone":"+1 262 554 0800",
    "sg:postcode":"53406",
    "sg:province":"WI",
    "sg:tags":[
        "extruded",
        "aluminum",
        "mfg"
    ],
    "sg:website":"www.kolararms.com",
    "wof:name":"Kolar Arms",
    "wof:placetype":"venue"
},
  "geometry": {"coordinates":[-87.840932,42.705646],"type":"Point"}
}