{
  "type": "Feature",
  "properties": {
    "addr:full":"4525 S Sovereign Dr New Berlin WI 53151",
    "addr:housenumber":"4525",
    "addr:postcode":"53151",
    "addr:street":"S Sovereign Dr",
    "iso:country":"US",
    "sg:address":"4525 S Sovereign Dr",
    "sg:city":"New Berlin",
    "sg:classifiers":[
        {
            "category":"Banks & Credit Unions",
            "subcategory":"Financial Services",
            "type":"Services"
        }
    ],
    "sg:phone":"+1 262 784 7570",
    "sg:postcode":"53151",
    "sg:province":"WI",
    "sg:tags":[
        "franchising"
    ],
    "wof:name":"Entrepreneur's Source",
    "wof:placetype":"venue"
},
  "geometry": {"coordinates":[-88.115284,42.962527],"type":"Point"}
}