{
  "type": "Feature",
  "properties": {
    "iso:country":"US",
    "sg:address":"6571 Patterson Rd",
    "sg:city":"Monroe",
    "sg:classifiers":[
        {
            "category":"Real Estate",
            "subcategory":"Real Estate Operator",
            "type":"Services"
        }
    ],
    "sg:phone":"+1 608 325 2675",
    "sg:postcode":"53566",
    "sg:province":"WI",
    "sg:tags":[
        "property",
        "lessor"
    ],
    "wof:name":"Ilene Patterson",
    "wof:placetype":"venue"
},
  "geometry": {"coordinates":[-89.689065,42.592232],"type":"Point"}
}