{
  "type": "Feature",
  "properties": {
    "iso:country":"US",
    "sg:address":"301 Water St",
    "sg:city":"Eau Claire",
    "sg:classifiers":[
        {
            "category":"Real Estate",
            "subcategory":"Real Estate Agent",
            "type":"Services"
        }
    ],
    "sg:phone":"+1 715 836 9660",
    "sg:postcode":"54703",
    "sg:province":"WI",
    "sg:tags":[
        "appraiser"
    ],
    "wof:name":"Lahn Appraisal",
    "wof:placetype":"venue"
},
  "geometry": {"coordinates":[-91.50770300000001,44.802165],"type":"Point"}
}