{
  "type": "Feature",
  "properties": {
    "iso:country":"US",
    "sg:address":"200 S Washington St",
    "sg:city":"Green Bay",
    "sg:classifiers":[
        {
            "category":"Professional",
            "subcategory":"Accounting & Tax Preparation",
            "type":"Services"
        }
    ],
    "sg:phone":"+1 920 435 4361",
    "sg:postcode":"54301",
    "sg:province":"WI",
    "wof:name":"Vernon J Bougie",
    "wof:placetype":"venue"
},
  "geometry": {"coordinates":[-88.017693,44.512042],"type":"Point"}
}