{
  "type": "Feature",
  "properties": {
    "iso:country":"US",
    "sg:address":"2116 W Bone Lake Dr",
    "sg:city":"Milltown",
    "sg:classifiers":[
        {
            "category":"Travel",
            "subcategory":"Hotels & Motels",
            "type":"Entertainment"
        }
    ],
    "sg:phone":"+1 715 857 5235",
    "sg:postcode":"54858",
    "sg:province":"WI",
    "sg:tags":[
        "resort"
    ],
    "wof:name":"Rest Point Resort",
    "wof:placetype":"venue"
},
  "geometry": {"coordinates":[-92.389754,45.5147],"type":"Point"}
}