{
  "type": "Feature",
  "properties": {
    "iso:country":"US",
    "sg:address":"317 Pine St",
    "sg:city":"Marathon",
    "sg:classifiers":[
        {
            "category":"Personal",
            "subcategory":"Beauty Salon",
            "type":"Services"
        }
    ],
    "sg:phone":"+1 715 443 3690",
    "sg:postcode":"54448",
    "sg:province":"WI",
    "wof:name":"Style N Tan N",
    "wof:placetype":"venue"
},
  "geometry": {"coordinates":[-89.843734,44.932043],"type":"Point"}
}