{
  "type": "Feature",
  "properties": {
    "iso:country":"US",
    "sg:address":"2021 Co Rd Pp",
    "sg:city":"De Pere",
    "sg:classifiers":[
        {
            "category":"Retail",
            "subcategory":"Veterinary Services",
            "type":"Services"
        }
    ],
    "sg:phone":"+1 920 336 7233",
    "sg:postcode":"54115",
    "sg:province":"WI",
    "wof:name":"Depere Veterinary Service SC",
    "wof:placetype":"venue"
},
  "geometry": {"coordinates":[-88.056822,44.416241],"type":"Point"}
}