{
  "type": "Feature",
  "properties": {
    "iso:country":"US",
    "sg:address":"381 Lake Shore Rd",
    "sg:city":"Grafton",
    "sg:classifiers":[
        {
            "category":"Professional",
            "type":"Services"
        }
    ],
    "sg:phone":"+1 262 377 0055",
    "sg:postcode":"53024",
    "sg:province":"WI",
    "wof:name":"Jim Wick",
    "wof:placetype":"venue"
},
  "geometry": {"coordinates":[-87.895416,43.302461],"type":"Point"}
}