{
  "type": "Feature",
  "properties": {
    "iso:country":"US",
    "sg:address":"413 Steele St",
    "sg:city":"Algoma",
    "sg:classifiers":[
        {
            "category":"Insurance",
            "subcategory":"Insurance Agent",
            "type":"Services"
        }
    ],
    "sg:phone":"+1 920 487 3553",
    "sg:postcode":"54201",
    "sg:province":"WI",
    "wof:name":"State Farm Insurance",
    "wof:placetype":"venue"
},
  "geometry": {"coordinates":[-87.439685,44.608771],"type":"Point"}
}