{
  "type": "Feature",
  "properties": {
    "iso:country":"US",
    "sg:address":"1525 S 71st St",
    "sg:city":"Milwaukee",
    "sg:classifiers":[
        {
            "category":"Organizations",
            "subcategory":"Religious Organization",
            "type":"Services"
        }
    ],
    "sg:phone":"+1 414 774 8783",
    "sg:postcode":"53214",
    "sg:province":"WI",
    "sg:tags":[
        "church"
    ],
    "wof:name":"Holy Assumption Congregation",
    "wof:placetype":"venue"
},
  "geometry": {"coordinates":[-88.00146100000001,43.013352],"type":"Point"}
}