{
  "type": "Feature",
  "properties": {
    "iso:country":"US",
    "sg:address":"30114 52nd St",
    "sg:city":"Salem",
    "sg:classifiers":[
        {
            "category":"Professional",
            "subcategory":"Management & Consulting",
            "type":"Services"
        }
    ],
    "sg:phone":"+1 262 537 3475",
    "sg:postcode":"53168",
    "sg:province":"WI",
    "wof:name":"Wellness Opportunities Group",
    "wof:placetype":"venue"
},
  "geometry": {"coordinates":[-88.175365,42.589836],"type":"Point"}
}