{
  "type": "Feature",
  "properties": {
    "addr:full":"220 W 10th St Merrill WI 54452",
    "addr:housenumber":"220",
    "addr:postcode":"54452",
    "addr:street":"W 10Th St",
    "iso:country":"US",
    "sg:address":"220 W 10th St",
    "sg:city":"Merrill",
    "sg:classifiers":[
        {
            "category":"Building & Trades",
            "subcategory":"Construction",
            "type":"Services"
        }
    ],
    "sg:phone":"+1 715 539 1649",
    "sg:postcode":"54452",
    "sg:province":"WI",
    "sg:tags":[
        "excavation",
        "contractor"
    ],
    "wof:name":"S & I Excavating & Cnstr",
    "wof:placetype":"venue"
},
  "geometry": {"coordinates":[-89.703391,45.18884],"type":"Point"}
}