{
  "type": "Feature",
  "properties": {
    "iso:country":"US",
    "sg:address":"3425 Vinland Center Rd",
    "sg:city":"Neenah",
    "sg:classifiers":[
        {
            "category":"Farming",
            "subcategory":"Dairy Farm",
            "type":"Manufacturing & Wholesale Goods"
        }
    ],
    "sg:phone":"+1 920 231 7790",
    "sg:postcode":"54956",
    "sg:province":"WI",
    "wof:name":"Kenneth Wiesner",
    "wof:placetype":"venue"
},
  "geometry": {"coordinates":[-88.569262,44.126204],"type":"Point"}
}