{
  "type": "Feature",
  "properties": {
    "iso:country":"US",
    "sg:address":"6213 N Teutonia Ave",
    "sg:city":"Milwaukee",
    "sg:classifiers":[
        {
            "category":"Personal",
            "subcategory":"Barber",
            "type":"Services"
        }
    ],
    "sg:phone":"+1 414 462 5297",
    "sg:postcode":"53209",
    "sg:province":"WI",
    "sg:tags":[
        "shop"
    ],
    "wof:name":"Jay S Barber Shop",
    "wof:placetype":"venue"
},
  "geometry": {"coordinates":[-87.952172,43.127174],"type":"Point"}
}