{
  "type": "Feature",
  "properties": {
    "iso:country":"US",
    "sg:address":"900 S Water St",
    "sg:city":"Milwaukee",
    "sg:classifiers":[
        {
            "category":"Wholesale",
            "subcategory":"Scrap",
            "type":"Manufacturing & Wholesale Goods"
        }
    ],
    "sg:phone":"+1 414 671 5990",
    "sg:postcode":"53204",
    "sg:province":"WI",
    "sg:tags":[
        "metal",
        "iron"
    ],
    "wof:name":"Miller Compressing Co",
    "wof:placetype":"venue"
},
  "geometry": {"coordinates":[-87.907921,43.020998],"type":"Point"}
}