{
  "type": "Feature",
  "properties": {
    "iso:country":"US",
    "sg:address":"2303 McIntosh St",
    "sg:city":"Wausau",
    "sg:classifiers":[
        {
            "category":"Manufacturing",
            "subcategory":"Furniture",
            "type":"Manufacturing & Wholesale Goods"
        }
    ],
    "sg:phone":"+1 715 842 8022",
    "sg:postcode":"54403",
    "sg:province":"WI",
    "sg:website":"www.conradmanufacturing.com",
    "wof:name":"Conrad Manufacturing",
    "wof:placetype":"venue"
},
  "geometry": {"coordinates":[-89.593762,44.952463],"type":"Point"}
}