{
  "type": "Feature",
  "properties": {
    "iso:country":"US",
    "sg:address":"3014 Co Rd C",
    "sg:city":"Mosinee",
    "sg:classifiers":[
        {
            "category":"Freight",
            "type":"Transportation"
        }
    ],
    "sg:phone":"+1 715 693 3412",
    "sg:postcode":"54455",
    "sg:province":"WI",
    "sg:tags":[
        "distance",
        "long",
        "trucking"
    ],
    "wof:name":"S & D Trucking Inc",
    "wof:placetype":"venue"
},
  "geometry": {"coordinates":[-89.84469199999999,44.726853],"type":"Point"}
}