{
  "type": "Feature",
  "properties": {
    "iso:country":"US",
    "sg:address":"739 Timber Ridge Ct",
    "sg:city":"Fontana",
    "sg:classifiers":[
        {
            "category":"Professional",
            "subcategory":"Business Services",
            "type":"Services"
        }
    ],
    "sg:phone":"+1 262 275 0030",
    "sg:postcode":"53125",
    "sg:province":"WI",
    "wof:name":"Great Prarie Ventures",
    "wof:placetype":"venue"
},
  "geometry": {"coordinates":[-88.559971,42.543879],"type":"Point"}
}