{
  "type": "Feature",
  "properties": {
    "iso:country":"US",
    "sg:address":"1593 Hill Rd",
    "sg:city":"Greenleaf",
    "sg:classifiers":[
        {
            "category":"Farming",
            "subcategory":"Livestock Farm",
            "type":"Manufacturing & Wholesale Goods"
        }
    ],
    "sg:phone":"+1 920 532 0174",
    "sg:postcode":"54126",
    "sg:province":"WI",
    "sg:tags":[
        "hog",
        "or",
        "feedlot"
    ],
    "wof:name":"Parkview Feeder Farms Inc",
    "wof:placetype":"venue"
},
  "geometry": {"coordinates":[-88.095392,44.270113],"type":"Point"}
}