{
  "type": "Feature",
  "properties": {
    "iso:country":"US",
    "sg:address":"5828 State Hwy 47 55",
    "sg:city":"Shawano",
    "sg:classifiers":[
        {
            "category":"Retail",
            "subcategory":"Repair Shop",
            "type":"Services"
        }
    ],
    "sg:phone":"+1 715 524 3660",
    "sg:postcode":"54166",
    "sg:province":"WI",
    "sg:tags":[
        "refrigerator",
        "freezer"
    ],
    "wof:name":"Arss Co",
    "wof:placetype":"venue"
},
  "geometry": {"coordinates":[-88.608671,44.799116],"type":"Point"}
}