{
  "type": "Feature",
  "properties": {
    "addr:full":"2327 Riverside Dr Beloit WI 53511",
    "addr:housenumber":"2327",
    "addr:postcode":"53511",
    "addr:street":"Riverside Dr",
    "iso:country":"US",
    "sg:address":"2327 Riverside Dr",
    "sg:city":"Beloit",
    "sg:classifiers":[
        {
            "category":"Social Services",
            "type":"Services"
        },
        {
            "category":"Professional",
            "subcategory":"Employment Agencies",
            "type":"Services"
        },
        {
            "category":"Organizations",
            "subcategory":"Membership Organization",
            "type":"Services"
        }
    ],
    "sg:phone":"+1 608 364 9000",
    "sg:postcode":"53511",
    "sg:province":"WI",
    "sg:tags":[
        "workers'",
        "club",
        "placement",
        "private",
        "volunteer"
    ],
    "wof:name":"Beloit Country Club",
    "wof:placetype":"venue"
},
  "geometry": {"coordinates":[-89.036179,42.53598],"type":"Point"}
}