{
  "type": "Feature",
  "properties": {
    "iso:country":"US",
    "sg:address":"1117 Liberty St",
    "sg:city":"Racine",
    "sg:classifiers":[
        {
            "category":"Social Services",
            "type":"Services"
        }
    ],
    "sg:phone":"+1 262 632 6731",
    "sg:postcode":"53404",
    "sg:province":"WI",
    "wof:name":"New Grove Daycare",
    "wof:placetype":"venue"
},
  "geometry": {"coordinates":[-87.794972,42.730293],"type":"Point"}
}