{
  "type": "Feature",
  "properties": {
    "iso:country":"US",
    "sg:address":"408 Pine St",
    "sg:city":"Sauk City",
    "sg:classifiers":[
        {
            "category":"Wholesale",
            "subcategory":"Chemicals & Plastics",
            "type":"Manufacturing & Wholesale Goods"
        }
    ],
    "sg:phone":"+1 608 643 4748",
    "sg:postcode":"53583",
    "sg:province":"WI",
    "wof:name":"Retrum John",
    "wof:placetype":"venue"
},
  "geometry": {"coordinates":[-89.737725,43.276525],"type":"Point"}
}