{
  "type": "Feature",
  "properties": {
    "iso:country":"US",
    "sg:address":"955 Challenger Dr",
    "sg:city":"Green Bay",
    "sg:classifiers":[
        {
            "category":"Food & Beverages",
            "subcategory":"Specialty",
            "type":"Retail Goods"
        }
    ],
    "sg:phone":"+1 920 406 6500",
    "sg:postcode":"54311",
    "sg:province":"WI",
    "sg:tags":[
        "vitamin"
    ],
    "sg:website":"www.europharmausa.com",
    "wof:name":"Europharma",
    "wof:placetype":"venue"
},
  "geometry": {"coordinates":[-87.932969,44.485095],"type":"Point"}
}