{
  "type": "Feature",
  "properties": {
    "iso:country":"US",
    "sg:address":"108 Lance Dr",
    "sg:city":"Twin Lakes",
    "sg:classifiers":[
        {
            "category":"Retail",
            "subcategory":"Repair Shop",
            "type":"Services"
        }
    ],
    "sg:phone":"+1 262 877 8229",
    "sg:postcode":"53181",
    "sg:province":"WI",
    "sg:tags":[
        "scooter",
        "motorcycle",
        "motor"
    ],
    "wof:name":"Twin Lakes V-Twin Motorcycle R",
    "wof:placetype":"venue"
},
  "geometry": {"coordinates":[-88.25491599999999,42.530659],"type":"Point"}
}