{
  "type": "Feature",
  "properties": {
    "iso:country":"US",
    "sg:address":"2321 State Hwy 25",
    "sg:city":"Menomonie",
    "sg:classifiers":[
        {
            "category":"Insurance",
            "subcategory":"Insurance Agent",
            "type":"Services"
        }
    ],
    "sg:phone":"+1 715 235 7055",
    "sg:postcode":"54751",
    "sg:province":"WI",
    "wof:name":"Westland Insurance Svc Inc",
    "wof:placetype":"venue"
},
  "geometry": {"coordinates":[-91.936168,44.766203],"type":"Point"}
}