{
  "type": "Feature",
  "properties": {
    "iso:country":"US",
    "sg:address":"207 E Buffalo St",
    "sg:city":"Milwaukee",
    "sg:classifiers":[
        {
            "category":"Professional",
            "subcategory":"Lawyer & Legal Services",
            "type":"Services"
        }
    ],
    "sg:phone":"+1 414 224 6084",
    "sg:postcode":"53202",
    "sg:province":"WI",
    "sg:tags":[
        "attorney"
    ],
    "wof:name":"Mitchell Law Office",
    "wof:placetype":"venue"
},
  "geometry": {"coordinates":[-87.90733400000001,43.033759],"type":"Point"}
}