{
  "type": "Feature",
  "properties": {
    "iso:country":"US",
    "sg:address":"311 S Main St",
    "sg:city":"Viroqua",
    "sg:classifiers":[
        {
            "category":"Professional",
            "type":"Services"
        }
    ],
    "sg:phone":"+1 608 637 9276",
    "sg:postcode":"54665",
    "sg:province":"WI",
    "wof:name":"Kindred Thread LLC Inc",
    "wof:placetype":"venue"
},
  "geometry": {"coordinates":[-90.889309,43.554074],"type":"Point"}
}