{
  "type": "Feature",
  "properties": {
    "addr:full":"3500 Meachem Rd Racine WI 53405",
    "addr:postcode":"3500;53405",
    "addr:street":"Meachem Rd",
    "iso:country":"US",
    "sg:address":"3500 Meachem Rd",
    "sg:city":"Racine",
    "sg:classifiers":[
        {
            "category":"Health Services",
            "subcategory":"Doctor",
            "type":"Services"
        }
    ],
    "sg:phone":"+1 262 598 9901",
    "sg:postcode":"53405",
    "sg:province":"WI",
    "sg:tags":[
        "dentist"
    ],
    "wof:name":"TMJ",
    "wof:placetype":"venue"
},
  "geometry": {"coordinates":[-87.83584500000001,42.690903],"type":"Point"}
}