{
  "type": "Feature",
  "properties": {
    "iso:country":"US",
    "sg:address":"2691 E Shore Dr",
    "sg:city":"Merrill",
    "sg:classifiers":[
        {
            "category":"Professional",
            "type":"Services"
        }
    ],
    "sg:phone":"+1 715 536 3944",
    "sg:postcode":"54452",
    "sg:province":"WI",
    "wof:name":"J & J Woodlands L L C",
    "wof:placetype":"venue"
},
  "geometry": {"coordinates":[-89.677019,45.208483],"type":"Point"}
}