{
  "type": "Feature",
  "properties": {
    "iso:country":"US",
    "sg:address":"4765 Hayes Rd",
    "sg:city":"Madison",
    "sg:classifiers":[
        {
            "category":"Travel",
            "subcategory":"Hotels & Motels",
            "type":"Entertainment"
        }
    ],
    "sg:phone":"+1 608 249 5300",
    "sg:postcode":"53704",
    "sg:province":"WI",
    "wof:name":"Super 8 Madison/East",
    "wof:placetype":"venue"
},
  "geometry": {"coordinates":[-89.300002,43.138298],"type":"Point"}
}