{
  "type": "Feature",
  "properties": {
    "iso:country":"US",
    "sg:address":"505 N 6th St",
    "sg:city":"Wausau",
    "sg:classifiers":[
        {
            "category":"Real Estate",
            "subcategory":"Real Estate Operator",
            "type":"Services"
        }
    ],
    "sg:phone":"+1 715 848 5788",
    "sg:postcode":"54403",
    "sg:province":"WI",
    "sg:tags":[
        "apartment"
    ],
    "wof:name":"Village Square Inc",
    "wof:placetype":"venue"
},
  "geometry": {"coordinates":[-89.623231,44.961176],"type":"Point"}
}