{
  "type": "Feature",
  "properties": {
    "iso:country":"US",
    "sg:address":"29 E Spruce St",
    "sg:city":"Chippewa Falls",
    "sg:classifiers":[
        {
            "category":"Professional",
            "subcategory":"Lawyer & Legal Services",
            "type":"Services"
        }
    ],
    "sg:phone":"+1 715 723 3046",
    "sg:postcode":"54729",
    "sg:province":"WI",
    "wof:name":"Cray Ardis A",
    "wof:placetype":"venue"
},
  "geometry": {"coordinates":[-91.395922,44.939932],"type":"Point"}
}