{
  "type": "Feature",
  "properties": {
    "addr:full":"11417 W Watertown Plank Rd Milwaukee WI 53226",
    "addr:housenumber":"11417",
    "addr:postcode":"53226",
    "addr:street":"W Watertown Plank Rd",
    "iso:country":"US",
    "sg:address":"11417 W Watertown Plank Rd",
    "sg:city":"Milwaukee",
    "sg:classifiers":[
        {
            "category":"Autos & Motor Vehicles",
            "subcategory":"Fuel & Gas Station",
            "type":"Retail Goods"
        }
    ],
    "sg:phone":"+1 414 607 0807",
    "sg:postcode":"53226",
    "sg:province":"WI",
    "sg:tags":[
        "oil"
    ],
    "wof:name":"H K Petro Inc",
    "wof:placetype":"venue"
},
  "geometry": {"coordinates":[-88.05695900000001,43.045429],"type":"Point"}
}