{
  "type": "Feature",
  "properties": {
    "addr:full":"307 S Broadway Green Bay WI 54303",
    "addr:housenumber":"307",
    "addr:postcode":"54303",
    "addr:street":"S Broadway",
    "iso:country":"US",
    "sg:address":"307 S Broadway",
    "sg:city":"Green Bay",
    "sg:classifiers":[
        {
            "category":"Retail",
            "subcategory":"Repair Shop",
            "type":"Services"
        }
    ],
    "sg:phone":"+1 920 437 0211",
    "sg:postcode":"54303",
    "sg:province":"WI",
    "sg:tags":[
        "cleaners",
        "parts",
        "vacuum"
    ],
    "wof:name":"Keith's Vacuum Ctr",
    "wof:placetype":"venue"
},
  "geometry": {"coordinates":[-88.023488,44.513665],"type":"Point"}
}