{
  "type": "Feature",
  "properties": {
    "iso:country":"US",
    "sg:address":"213 N 1st St",
    "sg:city":"Madison",
    "sg:classifiers":[
        {
            "category":"Building & Trades",
            "subcategory":"Construction",
            "type":"Services"
        }
    ],
    "sg:phone":"+1 608 266 4675",
    "sg:postcode":"53704",
    "sg:province":"WI",
    "sg:tags":[
        "house"
    ],
    "wof:name":"Madison Home Improvement",
    "wof:placetype":"venue"
},
  "geometry": {"coordinates":[-89.36203500000001,43.094189],"type":"Point"}
}