{
  "type": "Feature",
  "properties": {
    "addr:full":"5418 Joe Snow Rd Merrill WI 54452",
    "addr:housenumber":"5418",
    "addr:postcode":"54452",
    "addr:street":"Joe Snow Rd",
    "iso:country":"US",
    "sg:address":"5418 Joe Snow Rd",
    "sg:city":"Merrill",
    "sg:classifiers":[
        {
            "category":"Freight",
            "type":"Transportation"
        }
    ],
    "sg:phone":"+1 715 536 5955",
    "sg:postcode":"54452",
    "sg:province":"WI",
    "sg:tags":[
        "local",
        "mover",
        "storage",
        "trucking"
    ],
    "wof:name":"City Transfer Co",
    "wof:placetype":"venue"
},
  "geometry": {"coordinates":[-89.701904,45.163516],"type":"Point"}
}