{
  "type": "Feature",
  "properties": {
    "iso:country":"US",
    "sg:address":"926 S 35th St",
    "sg:city":"Manitowoc",
    "sg:classifiers":[
        {
            "category":"Recreation",
            "type":"Entertainment"
        }
    ],
    "sg:phone":"+1 920 686 0766",
    "sg:postcode":"54220",
    "sg:province":"WI",
    "sg:tags":[
        "martial",
        "arts",
        "instruction"
    ],
    "wof:name":"United Martial Arts",
    "wof:placetype":"venue"
},
  "geometry": {"coordinates":[-87.69104400000001,44.089847],"type":"Point"}
}