{
  "type": "Feature",
  "properties": {
    "iso:country":"US",
    "sg:address":"1140 S 30th St",
    "sg:city":"Manitowoc",
    "sg:classifiers":[
        {
            "category":"Shopping",
            "subcategory":"Department Store",
            "type":"Retail Goods"
        }
    ],
    "sg:phone":"+1 920 652 0991",
    "sg:postcode":"54220",
    "sg:province":"WI",
    "sg:tags":[
        "shop"
    ],
    "wof:name":"Family Dollar Store",
    "wof:placetype":"venue"
},
  "geometry": {"coordinates":[-87.685339,44.087596],"type":"Point"}
}