{
  "type": "Feature",
  "properties": {
    "addr:full":"3 Crestview Dr Hortonville WI 54944",
    "addr:housenumber":"3",
    "addr:postcode":"54944",
    "addr:street":"Crestview Dr",
    "iso:country":"US",
    "sg:address":"3 Crestview Dr",
    "sg:city":"Hortonville",
    "sg:classifiers":[
        {
            "category":"Manufacturing",
            "subcategory":"Food",
            "type":"Manufacturing & Wholesale Goods"
        }
    ],
    "sg:phone":"+1 920 779 6022",
    "sg:postcode":"54944",
    "sg:province":"WI",
    "sg:tags":[
        "desert",
        "ice",
        "mfg"
    ],
    "wof:name":"New Dillies Inc",
    "wof:placetype":"venue"
},
  "geometry": {"coordinates":[-88.62683,44.350719],"type":"Point"}
}