{
  "type": "Feature",
  "properties": {
    "addr:full":"718 Cottage Ct Madison WI 53716",
    "addr:housenumber":"718",
    "addr:postcode":"53716",
    "addr:street":"Cottage Ct",
    "iso:country":"US",
    "sg:address":"718 Cottage Ct",
    "sg:city":"Madison",
    "sg:classifiers":[
        {
            "category":"Insurance",
            "subcategory":"Insurance Agent",
            "type":"Services"
        }
    ],
    "sg:phone":"+1 608 241 8280",
    "sg:postcode":"53716",
    "sg:province":"WI",
    "wof:name":"American Family Insurance",
    "wof:placetype":"venue"
},
  "geometry": {"coordinates":[-89.313216,43.083963],"type":"Point"}
}