{
  "type": "Feature",
  "properties": {
    "addr:full":"7441 Middle Rd Sheboygan WI 53081",
    "addr:housenumber":"7441",
    "addr:postcode":"53081",
    "addr:street":"Middle Rd",
    "iso:country":"US",
    "sg:address":"7441 Middle Rd",
    "sg:city":"Sheboygan",
    "sg:classifiers":[
        {
            "category":"Freight",
            "type":"Transportation"
        }
    ],
    "sg:phone":"+1 920 457 0907",
    "sg:postcode":"53081",
    "sg:province":"WI",
    "sg:tags":[
        "commercial",
        "storage"
    ],
    "wof:name":"Vand-VELOPMENT LLC",
    "wof:placetype":"venue"
},
  "geometry": {"coordinates":[-87.760189,43.668078],"type":"Point"}
}