{
  "type": "Feature",
  "properties": {
    "iso:country":"US",
    "sg:address":"301 High St",
    "sg:city":"Embarrass",
    "sg:classifiers":[
        {
            "category":"Retail",
            "subcategory":"Repair Shop",
            "type":"Services"
        }
    ],
    "sg:phone":"+1 715 823 4085",
    "sg:postcode":"54933",
    "sg:province":"WI",
    "sg:tags":[
        "upholsterer"
    ],
    "wof:name":"Roehl's Upholstering",
    "wof:placetype":"venue"
},
  "geometry": {"coordinates":[-88.701994,44.664787],"type":"Point"}
}