{
  "type": "Feature",
  "properties": {
    "iso:country":"US",
    "sg:address":"26604 Roosevelt Ln",
    "sg:city":"Waterford",
    "sg:classifiers":[
        {
            "category":"Wholesale",
            "subcategory":"Metals & Minerals",
            "type":"Manufacturing & Wholesale Goods"
        }
    ],
    "sg:phone":"+1 262 895 2623",
    "sg:postcode":"53185",
    "sg:province":"WI",
    "sg:tags":[
        "preparation",
        "toilet",
        "center",
        "mfg"
    ],
    "wof:name":"Nail Tech",
    "wof:placetype":"venue"
},
  "geometry": {"coordinates":[-88.163541,42.819283],"type":"Point"}
}