{
  "type": "Feature",
  "properties": {
    "iso:country":"US",
    "sg:address":"327 Tower Ave",
    "sg:city":"Superior",
    "sg:classifiers":[
        {
            "category":"Autos & Motor Vehicles",
            "subcategory":"Automobile Sales",
            "type":"Retail Goods"
        }
    ],
    "sg:phone":"+1 715 394 7587",
    "sg:postcode":"54880",
    "sg:province":"WI",
    "sg:tags":[
        "car",
        "dealer"
    ],
    "wof:name":"Superior Auto Sales",
    "wof:placetype":"venue"
},
  "geometry": {"coordinates":[-92.103926,46.734276],"type":"Point"}
}