{
  "type": "Feature",
  "properties": {
    "addr:full":"3061 Allied St Green Bay WI 54304",
    "addr:housenumber":"3061",
    "addr:postcode":"54304",
    "addr:street":"Allied St",
    "iso:country":"US",
    "sg:address":"3061 Allied St",
    "sg:city":"Green Bay",
    "sg:classifiers":[
        {
            "category":"Retail",
            "subcategory":"Repair Shop",
            "type":"Services"
        }
    ],
    "sg:phone":"+1 920 336 4070",
    "sg:postcode":"54304",
    "sg:province":"WI",
    "sg:tags":[
        "electrical"
    ],
    "wof:name":"Spectrum Lighting Ltd",
    "wof:placetype":"venue"
},
  "geometry": {"coordinates":[-88.083845,44.46801],"type":"Point"}
}