{
  "type": "Feature",
  "properties": {
    "addr:full":"8797 Co Rd G Mt Horeb WI 53572",
    "addr:housenumber":"8797",
    "addr:postcode":"53572",
    "addr:street":"Co Rd",
    "iso:country":"US",
    "sg:address":"8797 Co Rd G",
    "sg:city":"Mt Horeb",
    "sg:classifiers":[
        {
            "category":"Professional",
            "subcategory":"Accounting & Tax Preparation",
            "type":"Services"
        }
    ],
    "sg:phone":"+1 608 832 6322",
    "sg:postcode":"53572",
    "sg:province":"WI",
    "sg:tags":[
        "accountant"
    ],
    "wof:name":"Verlyn G Adamson CPA",
    "wof:placetype":"venue"
},
  "geometry": {"coordinates":[-89.67712299999999,42.923978],"type":"Point"}
}