{
  "type": "Feature",
  "properties": {
    "addr:full":"962 Tower View Dr Greenville WI 54942",
    "addr:housenumber":"962",
    "addr:postcode":"54942",
    "addr:street":"Tower View Dr",
    "iso:country":"US",
    "sg:address":"962 Tower View Dr",
    "sg:city":"Greenville",
    "sg:classifiers":[
        {
            "category":"Manufacturing",
            "subcategory":"Paper Products",
            "type":"Manufacturing & Wholesale Goods"
        }
    ],
    "sg:phone":"+1 920 757 1357",
    "sg:postcode":"54942",
    "sg:province":"WI",
    "sg:tags":[
        "mill"
    ],
    "wof:name":"Dynamic Converting Industries",
    "wof:placetype":"venue"
},
  "geometry": {"coordinates":[-88.51073100000001,44.275075],"type":"Point"}
}