{
  "type": "Feature",
  "properties": {
    "iso:country":"US",
    "sg:address":"4916 Creek Haven Rd",
    "sg:city":"Cottage Grove",
    "sg:classifiers":[
        {
            "category":"Real Estate",
            "subcategory":"Real Estate Agent",
            "type":"Services"
        }
    ],
    "sg:phone":"+1 608 655 3676",
    "sg:postcode":"53527",
    "sg:province":"WI",
    "wof:name":"Capital Enterprises LLC",
    "wof:placetype":"venue"
},
  "geometry": {"coordinates":[-89.178579,43.117392],"type":"Point"}
}