{
  "type": "Feature",
  "properties": {
    "iso:country":"US",
    "sg:address":"414 W Moreland Blvd",
    "sg:city":"Waukesha",
    "sg:classifiers":[
        {
            "category":"Professional",
            "subcategory":"Lawyer & Legal Services",
            "type":"Services"
        }
    ],
    "sg:phone":"+1 262 542 9080",
    "sg:postcode":"53188",
    "sg:province":"WI",
    "sg:tags":[
        "attorney"
    ],
    "wof:name":"Grau Law Office",
    "wof:placetype":"venue"
},
  "geometry": {"coordinates":[-88.229564,43.024122],"type":"Point"}
}