{
  "type": "Feature",
  "properties": {
    "addr:full":"25 N Main St Rice Lake WI 54868",
    "addr:housenumber":"25",
    "addr:postcode":"54868",
    "addr:street":"N Main St",
    "iso:country":"US",
    "sg:address":"25 N Main St",
    "sg:city":"Rice Lake",
    "sg:classifiers":[
        {
            "category":"Manufacturing",
            "subcategory":"Jewelry",
            "type":"Manufacturing & Wholesale Goods"
        },
        {
            "category":"Shopping",
            "type":"Retail Goods"
        }
    ],
    "sg:phone":"+1 715 234 6228",
    "sg:postcode":"54868",
    "sg:province":"WI",
    "sg:tags":[
        "trophy",
        "ware",
        "medal",
        "award",
        "mfg"
    ],
    "wof:name":"Sports World Awards",
    "wof:placetype":"venue"
},
  "geometry": {"coordinates":[-91.733368,45.502353],"type":"Point"}
}