{
  "type": "Feature",
  "properties": {
    "iso:country":"US",
    "sg:address":"7318 Ireland Dr",
    "sg:city":"Hartford",
    "sg:classifiers":[
        {
            "category":"Building & Trades",
            "subcategory":"Construction",
            "type":"Services"
        }
    ],
    "sg:phone":"+1 262 670 6088",
    "sg:postcode":"53027",
    "sg:province":"WI",
    "sg:tags":[
        "water",
        "well",
        "drilling"
    ],
    "wof:name":"Anhalt Well Drilling & Pumps",
    "wof:placetype":"venue"
},
  "geometry": {"coordinates":[-88.402329,43.256514],"type":"Point"}
}