{
  "type": "Feature",
  "properties": {
    "iso:country":"US",
    "sg:address":"207 Dakota Ave",
    "sg:city":"Hayward",
    "sg:classifiers":[
        {
            "category":"Restaurant",
            "type":"Food & Drink"
        }
    ],
    "sg:phone":"+1 715 634 1337",
    "sg:postcode":"54843",
    "sg:province":"WI",
    "sg:tags":[
        "eating"
    ],
    "wof:name":"McDonalds",
    "wof:placetype":"venue"
},
  "geometry": {"coordinates":[-91.485636,46.013722],"type":"Point"}
}