{
  "type": "Feature",
  "properties": {
    "addr:full":"3450 N Main St Oshkosh WI 54901",
    "addr:housenumber":"3450",
    "addr:postcode":"54901",
    "addr:street":"N Main St",
    "iso:country":"US",
    "sg:address":"3450 N Main St",
    "sg:city":"Oshkosh",
    "sg:classifiers":[
        {
            "category":"Manufacturing",
            "subcategory":"Paper Products",
            "type":"Manufacturing & Wholesale Goods"
        }
    ],
    "sg:phone":"+1 920 426 2511",
    "sg:postcode":"54901",
    "sg:province":"WI",
    "sg:tags":[
        "packaging",
        "material"
    ],
    "sg:website":"www.bemis.com",
    "wof:name":"Bemistape",
    "wof:placetype":"venue"
},
  "geometry": {"coordinates":[-88.53793,44.062514],"type":"Point"}
}