{
  "type": "Feature",
  "properties": {
    "addr:full":"921 Cottage Rd Ellison Bay WI 54210",
    "addr:housenumber":"921",
    "addr:postcode":"54210",
    "addr:street":"Cottage Rd",
    "iso:country":"US",
    "sg:address":"921 Cottage Rd",
    "sg:city":"Ellison Bay",
    "sg:classifiers":[
        {
            "category":"Recreation",
            "type":"Entertainment"
        }
    ],
    "sg:phone":"+1 920 854 4614",
    "sg:postcode":"54210",
    "sg:province":"WI",
    "sg:tags":[
        "guide"
    ],
    "wof:name":"Captain Paul's Charter Fishing",
    "wof:placetype":"venue"
},
  "geometry": {"coordinates":[-87.02309700000001,45.286095],"type":"Point"}
}