{
  "type": "Feature",
  "properties": {
    "iso:country":"US",
    "sg:address":"800 Wisconsin St",
    "sg:city":"Eau Claire",
    "sg:classifiers":[
        {
            "category":"Organizations",
            "subcategory":"Non-profit Organization",
            "type":"Services"
        }
    ],
    "sg:phone":"+1 715 834 1108",
    "sg:postcode":"54703",
    "sg:province":"WI",
    "sg:tags":[
        "social"
    ],
    "wof:name":"American Heart Association",
    "wof:placetype":"venue"
},
  "geometry": {"coordinates":[-91.49755399999999,44.815965],"type":"Point"}
}