{
  "type": "Feature",
  "properties": {
    "iso:country":"US",
    "sg:address":"7649 Oboe Ave",
    "sg:city":"Cashton",
    "sg:classifiers":[
        {
            "category":"Farming",
            "subcategory":"Dairy Farm",
            "type":"Manufacturing & Wholesale Goods"
        }
    ],
    "sg:phone":"+1 608 654 7975",
    "sg:postcode":"54619",
    "sg:province":"WI",
    "wof:name":"Lucky Acres Dairy",
    "wof:placetype":"venue"
},
  "geometry": {"coordinates":[-90.823458,43.73616],"type":"Point"}
}