{
  "type": "Feature",
  "properties": {
    "iso:country":"US",
    "sg:address":"1987 State Hwy 59",
    "sg:city":"Palmyra",
    "sg:classifiers":[
        {
            "category":"Bus Charters",
            "type":"Transportation"
        }
    ],
    "sg:phone":"+1 262 495 2878",
    "sg:postcode":"53156",
    "sg:province":"WI",
    "sg:tags":[
        "rental"
    ],
    "wof:name":"Lakeland Coach Lines Inc",
    "wof:placetype":"venue"
},
  "geometry": {"coordinates":[-88.598787,42.878485],"type":"Point"}
}