{
  "type": "Feature",
  "properties": {
    "iso:country":"US",
    "sg:address":"820 N Plankinton Ave",
    "sg:city":"Milwaukee",
    "sg:classifiers":[
        {
            "category":"Professional",
            "subcategory":"Business Services",
            "type":"Services"
        }
    ],
    "sg:phone":"+1 414 273 1991",
    "sg:postcode":"53203",
    "sg:province":"WI",
    "sg:tags":[
        "consultant",
        "coach"
    ],
    "sg:website":"http://www.arcw.org",
    "wof:name":"Arcw",
    "wof:placetype":"venue"
},
  "geometry": {"coordinates":[-87.912657,43.040474],"type":"Point"}
}