{
  "type": "Feature",
  "properties": {
    "iso:country":"US",
    "sg:address":"218 E Walworth Ave",
    "sg:city":"Delavan",
    "sg:classifiers":[
        {
            "category":"Organizations",
            "subcategory":"Professional Association",
            "type":"Services"
        }
    ],
    "sg:phone":"+1 262 728 4277",
    "sg:postcode":"53115",
    "sg:province":"WI",
    "wof:name":"Geneva Landings Condo Assn",
    "wof:placetype":"venue"
},
  "geometry": {"coordinates":[-88.645356,42.633064],"type":"Point"}
}