{
  "type": "Feature",
  "properties": {
    "addr:full":"3993 Mill Rd Greenleaf WI 54126",
    "addr:housenumber":"3993",
    "addr:postcode":"54126",
    "addr:street":"Mill Rd",
    "iso:country":"US",
    "sg:address":"3993 Mill Rd",
    "sg:city":"Greenleaf",
    "sg:classifiers":[
        {
            "category":"Manufacturing",
            "subcategory":"Lumber",
            "type":"Manufacturing & Wholesale Goods"
        }
    ],
    "sg:phone":"+1 920 864 2286",
    "sg:postcode":"54126",
    "sg:province":"WI",
    "sg:tags":[
        "manufacture",
        "pallet"
    ],
    "wof:name":"Christensen Mills Inc",
    "wof:placetype":"venue"
},
  "geometry": {"coordinates":[-87.909533,44.298849],"type":"Point"}
}