{
  "type": "Feature",
  "properties": {
    "iso:country":"US",
    "sg:address":"123 Hospital Dr",
    "sg:city":"Watertown",
    "sg:classifiers":[
        {
            "category":"Health Services",
            "subcategory":"Doctor",
            "type":"Services"
        }
    ],
    "sg:phone":"+1 920 261 3333",
    "sg:postcode":"53098",
    "sg:province":"WI",
    "sg:tags":[
        "physician",
        "surgeon"
    ],
    "wof:name":"Moazam J Samdani Corp",
    "wof:placetype":"venue"
},
  "geometry": {"coordinates":[-88.698964,43.197535],"type":"Point"}
}