{
  "type": "Feature",
  "properties": {
    "iso:country":"US",
    "sg:address":"844 E College Ave",
    "sg:city":"Appleton",
    "sg:classifiers":[
        {
            "category":"Wholesale",
            "subcategory":"Home Furnishings",
            "type":"Manufacturing & Wholesale Goods"
        }
    ],
    "sg:phone":"+1 920 739 3906",
    "sg:postcode":"54911",
    "sg:province":"WI",
    "sg:tags":[
        "merchandise"
    ],
    "wof:name":"Artists Framing & Mtls Sup Co",
    "wof:placetype":"venue"
},
  "geometry": {"coordinates":[-88.393619,44.261893],"type":"Point"}
}