{
  "type": "Feature",
  "properties": {
    "iso:country":"US",
    "sg:address":"305 Elaine's Ct",
    "sg:city":"Dodgeville",
    "sg:classifiers":[
        {
            "category":"Health Services",
            "subcategory":"Optometrist",
            "type":"Services"
        }
    ],
    "sg:phone":"+1 608 930 4362",
    "sg:postcode":"53533",
    "sg:province":"WI",
    "wof:name":"Davis Duehr Dean-Dodgeville",
    "wof:placetype":"venue"
},
  "geometry": {"coordinates":[-90.13889899999999,42.973378],"type":"Point"}
}