{
  "type": "Feature",
  "properties": {
    "iso:country":"US",
    "sg:address":"314 S Division St",
    "sg:city":"Waupun",
    "sg:classifiers":[
        {
            "category":"Building & Trades",
            "subcategory":"Construction",
            "type":"Services"
        }
    ],
    "sg:phone":"+1 920 324 9566",
    "sg:postcode":"53963",
    "sg:province":"WI",
    "sg:tags":[
        "house"
    ],
    "wof:name":"Jmk Construction",
    "wof:placetype":"venue"
},
  "geometry": {"coordinates":[-88.738388,43.62927],"type":"Point"}
}