{
  "type": "Feature",
  "properties": {
    "addr:full":"6048 River Rd Eagle River WI 54521",
    "addr:housenumber":"6048",
    "addr:postcode":"54521",
    "addr:street":"River Rd",
    "iso:country":"US",
    "sg:address":"6048 River Rd",
    "sg:city":"Eagle River",
    "sg:classifiers":[
        {
            "category":"Professional",
            "type":"Services"
        }
    ],
    "sg:phone":"+1 715 479 4769",
    "sg:postcode":"54521",
    "sg:province":"WI",
    "wof:name":"Junkermann North",
    "wof:placetype":"venue"
},
  "geometry": {"coordinates":[-89.340982,45.906078],"type":"Point"}
}