{
  "type": "Feature",
  "properties": {
    "iso:country":"US",
    "sg:address":"124 Lake Shore Dr",
    "sg:city":"Lake Mills",
    "sg:classifiers":[
        {
            "category":"Building & Trades",
            "subcategory":"Construction",
            "type":"Services"
        }
    ],
    "sg:phone":"+1 262 521 1133",
    "sg:postcode":"53551",
    "sg:province":"WI",
    "sg:tags":[
        "excavating",
        "contractor"
    ],
    "wof:name":"DHR Grading & Excavating",
    "wof:placetype":"venue"
},
  "geometry": {"coordinates":[-88.920891,43.081133],"type":"Point"}
}