{
  "type": "Feature",
  "properties": {
    "iso:country":"US",
    "sg:address":"3187 Bark Lake Rd",
    "sg:city":"Hubertus",
    "sg:classifiers":[
        {
            "category":"Building & Trades",
            "subcategory":"Cleaning & Sanitation",
            "type":"Services"
        }
    ],
    "sg:phone":"+1 262 250 9585",
    "sg:postcode":"53033",
    "sg:province":"WI",
    "sg:tags":[
        "snow",
        "removal"
    ],
    "wof:name":"F & S Enterprises",
    "wof:placetype":"venue"
},
  "geometry": {"coordinates":[-88.196871,43.225346],"type":"Point"}
}