{
  "type": "Feature",
  "properties": {
    "iso:country":"US",
    "sg:address":"4967 117th St",
    "sg:city":"Chippewa Falls",
    "sg:classifiers":[
        {
            "category":"Autos & Motor Vehicles",
            "subcategory":"Automobile Sales",
            "type":"Retail Goods"
        }
    ],
    "sg:phone":"+1 715 723 8882",
    "sg:postcode":"54729",
    "sg:province":"WI",
    "sg:tags":[
        "car",
        "dealer"
    ],
    "wof:name":"Paul Oman West Side Auto",
    "wof:placetype":"venue"
},
  "geometry": {"coordinates":[-91.432997,44.914721],"type":"Point"}
}