{
  "type": "Feature",
  "properties": {
    "iso:country":"US",
    "sg:address":"155 State Hwy 138",
    "sg:city":"Stoughton",
    "sg:classifiers":[
        {
            "category":"Wholesale",
            "subcategory":"Farm Supplies",
            "type":"Manufacturing & Wholesale Goods"
        }
    ],
    "sg:phone":"+1 608 873 7063",
    "sg:postcode":"53589",
    "sg:province":"WI",
    "sg:tags":[
        "crop",
        "general"
    ],
    "wof:name":"Olsons Kent Feeds",
    "wof:placetype":"venue"
},
  "geometry": {"coordinates":[-89.240785,42.851752],"type":"Point"}
}