{
  "type": "Feature",
  "properties": {
    "iso:country":"US",
    "sg:address":"1840 Lime Kiln Rd",
    "sg:city":"Green Bay",
    "sg:classifiers":[
        {
            "category":"School Buses",
            "type":"Transportation"
        }
    ],
    "sg:phone":"+1 920 468 6515",
    "sg:postcode":"54311",
    "sg:province":"WI",
    "wof:name":"Jelco Wisconsin Inc 740",
    "wof:placetype":"venue"
},
  "geometry": {"coordinates":[-87.982499,44.469674],"type":"Point"}
}