{
  "type": "Feature",
  "properties": {
    "iso:country":"US",
    "sg:address":"5975 Pleasant Hill Rd",
    "sg:city":"Hartford",
    "sg:classifiers":[
        {
            "category":"Professional",
            "subcategory":"Business Services",
            "type":"Services"
        }
    ],
    "sg:phone":"+1 262 673 9236",
    "sg:postcode":"53027",
    "sg:province":"WI",
    "sg:tags":[
        "interior",
        "design"
    ],
    "wof:name":"Interiors By Corinne",
    "wof:placetype":"venue"
},
  "geometry": {"coordinates":[-88.326627,43.265503],"type":"Point"}
}