{
  "type": "Feature",
  "properties": {
    "iso:country":"US",
    "sg:address":"4604 Riverview Rd",
    "sg:city":"Marinette",
    "sg:phone":"+1 715 789 2764",
    "sg:postcode":"54143",
    "sg:province":"WI",
    "sg:tags":[
        "farm",
        "corn",
        "cash",
        "crop",
        "field",
        "grain",
        "dairy"
    ],
    "wof:name":"James Denowski",
    "wof:placetype":"venue"
},
  "geometry": {"coordinates":[-87.82633800000001,45.13575],"type":"Point"}
}