{
  "type": "Feature",
  "properties": {
    "addr:full":"7471 State Rd 67 Walworth WI 53184",
    "addr:housenumber":"7471;67",
    "addr:postcode":"53184",
    "addr:street":"State Rd",
    "iso:country":"US",
    "sg:address":"7471 State Rd 67",
    "sg:city":"Walworth",
    "sg:classifiers":[
        {
            "category":"Wholesale",
            "subcategory":"Farm Supplies",
            "type":"Manufacturing & Wholesale Goods"
        }
    ],
    "sg:phone":"+1 262 736 4500",
    "sg:postcode":"53184",
    "sg:province":"WI",
    "sg:tags":[
        "buyer",
        "livestock"
    ],
    "wof:name":"Ray Beetstra Dairy Farms",
    "wof:placetype":"venue"
},
  "geometry": {"coordinates":[-88.66689599999999,42.509061],"type":"Point"}
}