{
  "type": "Feature",
  "properties": {
    "iso:country":"US",
    "sg:address":"108 W Wells St",
    "sg:city":"Milwaukee",
    "sg:classifiers":[
        {
            "category":"Coffee & Tea",
            "type":"Food & Drink"
        }
    ],
    "sg:menulink":"http://www.allmenus.com/wi/milwaukee/8193-yaffa-restaurant/menu/",
    "sg:phone":"+1 414 223 0101",
    "sg:postcode":"53203",
    "sg:province":"WI",
    "sg:tags":[
        "pita",
        "american"
    ],
    "wof:name":"Yaffa Restaurant",
    "wof:placetype":"venue"
},
  "geometry": {"coordinates":[-87.91204,43.040287],"type":"Point"}
}