{
  "type": "Feature",
  "properties": {
    "addr:full":"200 S 18th Ave Wausau WI 54401",
    "addr:housenumber":"200",
    "addr:postcode":"54401",
    "addr:street":"S 18Th Ave",
    "iso:country":"US",
    "sg:address":"200 S 18th Ave",
    "sg:city":"Wausau",
    "sg:classifiers":[
        {
            "category":"Shopping",
            "subcategory":"Department Store",
            "type":"Retail Goods"
        }
    ],
    "sg:phone":"+1 715 842 7442",
    "sg:postcode":"54401",
    "sg:province":"WI",
    "sg:tags":[
        "discount",
        "optical",
        "center",
        "pharmacy"
    ],
    "sg:website":"www.shopko.com",
    "wof:name":"Shopko",
    "wof:placetype":"venue"
},
  "geometry": {"coordinates":[-89.65535199999999,44.961378],"type":"Point"}
}