{
  "type": "Feature",
  "properties": {
    "iso:country":"US",
    "sg:address":"903 N Grant Ave",
    "sg:city":"Exeland",
    "sg:classifiers":[
        {
            "category":"Banks & Credit Unions",
            "subcategory":"Bank",
            "type":"Services"
        }
    ],
    "sg:phone":"+1 715 943 2266",
    "sg:postcode":"54835",
    "sg:province":"WI",
    "wof:name":"Dairyland State Bank",
    "wof:placetype":"venue"
},
  "geometry": {"coordinates":[-91.242559,45.668533],"type":"Point"}
}