{
  "type": "Feature",
  "properties": {
    "addr:full":"1714 Golfview Cir Hudson WI 54016",
    "addr:housenumber":"1714",
    "addr:postcode":"54016",
    "addr:street":"Golfview Cir",
    "iso:country":"US",
    "sg:address":"1714 Golfview Cir",
    "sg:city":"Hudson",
    "sg:classifiers":[
        {
            "category":"Professional",
            "subcategory":"Management & Consulting",
            "type":"Services"
        }
    ],
    "sg:phone":"+1 715 381 3058",
    "sg:postcode":"54016",
    "sg:province":"WI",
    "sg:tags":[
        "promotion",
        "sales"
    ],
    "wof:name":"Promotional Systems Group Inc",
    "wof:placetype":"venue"
},
  "geometry": {"coordinates":[-92.733065,44.96952],"type":"Point"}
}