{
  "type": "Feature",
  "properties": {
    "iso:country":"US",
    "sg:address":"1860 8th St S",
    "sg:city":"Wisconsin Rapids",
    "sg:classifiers":[
        {
            "category":"Shopping",
            "type":"Retail Goods"
        }
    ],
    "sg:phone":"+1 715 422 4770",
    "sg:postcode":"54494",
    "sg:province":"WI",
    "sg:tags":[
        "spa",
        "hot",
        "tub"
    ],
    "wof:name":"Water Quality Store",
    "wof:placetype":"venue"
},
  "geometry": {"coordinates":[-89.817091,44.377806],"type":"Point"}
}