{
  "type": "Feature",
  "properties": {
    "addr:full":"1880 State Hwy 29 Elk Mound WI 54739",
    "addr:housenumber":"1880",
    "addr:postcode":"54739",
    "addr:street":"State Hwy 29 Elk",
    "iso:country":"US",
    "sg:address":"1880 State Hwy 29",
    "sg:city":"Elk Mound",
    "sg:classifiers":[
        {
            "category":"Building & Trades",
            "subcategory":"Construction",
            "type":"Services"
        }
    ],
    "sg:phone":"+1 715 829 1175",
    "sg:postcode":"54739",
    "sg:province":"WI",
    "sg:tags":[
        "siding",
        "contractor"
    ],
    "wof:name":"Gibson Home Improvements",
    "wof:placetype":"venue"
},
  "geometry": {"coordinates":[-91.63386,44.899916],"type":"Point"}
}