{
  "type": "Feature",
  "properties": {
    "iso:country":"US",
    "sg:address":"13154 Preston Rd",
    "sg:city":"Fennimore",
    "sg:classifiers":[
        {
            "category":"Farming",
            "subcategory":"Dairy Farm",
            "type":"Manufacturing & Wholesale Goods"
        }
    ],
    "sg:phone":"+1 608 943 8434",
    "sg:postcode":"53809",
    "sg:province":"WI",
    "wof:name":"Tom Gerlach",
    "wof:placetype":"venue"
},
  "geometry": {"coordinates":[-90.53731500000001,42.982157],"type":"Point"}
}