{
  "type": "Feature",
  "properties": {
    "iso:country":"US",
    "sg:address":"2109 Cattail Ct",
    "sg:city":"Pewaukee",
    "sg:classifiers":[
        {
            "category":"Professional",
            "type":"Services"
        }
    ],
    "sg:phone":"+1 262 695 0734",
    "sg:postcode":"53072",
    "sg:province":"WI",
    "wof:name":"Truog & Steffen",
    "wof:placetype":"venue"
},
  "geometry": {"coordinates":[-88.278076,43.059259],"type":"Point"}
}