{
  "type": "Feature",
  "properties": {
    "addr:full":"6954 30th Ave Barronett WI 54813",
    "addr:housenumber":"6954",
    "addr:postcode":"54813",
    "addr:street":"30Th Ave",
    "iso:country":"US",
    "sg:address":"6954 30th Ave",
    "sg:city":"Barronett",
    "sg:classifiers":[
        {
            "category":"Retail",
            "subcategory":"Repair Shop",
            "type":"Services"
        }
    ],
    "sg:phone":"+1 715 822 8141",
    "sg:postcode":"54813",
    "sg:province":"WI",
    "wof:name":"Bigfoote Taxidermy",
    "wof:placetype":"venue"
},
  "geometry": {"coordinates":[-91.917481,45.639042],"type":"Point"}
}