{
  "type": "Feature",
  "properties": {
    "iso:country":"US",
    "sg:address":"20350 Water Tower Blvd",
    "sg:city":"Brookfield",
    "sg:classifiers":[
        {
            "category":"Real Estate",
            "subcategory":"Real Estate Agent",
            "type":"Services"
        }
    ],
    "sg:phone":"+1 262 780 5500",
    "sg:postcode":"53045",
    "sg:province":"WI",
    "sg:website":"www.coldwellbankeronline.com",
    "wof:name":"Coldwell Banker",
    "wof:placetype":"venue"
},
  "geometry": {"coordinates":[-88.16543299999999,43.031016],"type":"Point"}
}