{
  "type": "Feature",
  "properties": {
    "iso:country":"US",
    "sg:address":"110 2nd St N",
    "sg:city":"Park Falls",
    "sg:classifiers":[
        {
            "category":"Banks & Credit Unions",
            "subcategory":"Financial Services",
            "type":"Services"
        }
    ],
    "sg:phone":"+1 715 762 2411",
    "sg:postcode":"54552",
    "sg:province":"WI",
    "sg:tags":[
        "company",
        "holding"
    ],
    "wof:name":"Park Falls Agency Inc",
    "wof:placetype":"venue"
},
  "geometry": {"coordinates":[-90.447829,45.937317],"type":"Point"}
}