{
  "type": "Feature",
  "properties": {
    "addr:full":"2325 Parklawn Dr Waukesha WI 53186",
    "addr:housenumber":"2325",
    "addr:postcode":"53186",
    "addr:street":"Parklawn Dr",
    "iso:country":"US",
    "sg:address":"2325 Parklawn Dr",
    "sg:city":"Waukesha",
    "sg:classifiers":[
        {
            "category":"Home & Garden",
            "subcategory":"Building Materials",
            "type":"Retail Goods"
        }
    ],
    "sg:phone":"+1 262 798 1212",
    "sg:postcode":"53186",
    "sg:province":"WI",
    "sg:tags":[
        "a",
        "windows",
        "window",
        "custom",
        "as",
        "operates",
        "replacement"
    ],
    "wof:name":"Window Concepts of Milwaukee",
    "wof:placetype":"venue"
},
  "geometry": {"coordinates":[-88.181698,43.031914],"type":"Point"}
}