{
  "type": "Feature",
  "properties": {
    "iso:country":"US",
    "sg:address":"808 Minnesota Ave",
    "sg:city":"Stevens Point",
    "sg:classifiers":[
        {
            "category":"Retail",
            "subcategory":"Laundry & Dry Cleaning",
            "type":"Services"
        }
    ],
    "sg:phone":"+1 715 344 1703",
    "sg:postcode":"54481",
    "sg:province":"WI",
    "wof:name":"Sabre-Clean Carpet Care",
    "wof:placetype":"venue"
},
  "geometry": {"coordinates":[-89.55960399999999,44.527915],"type":"Point"}
}