{
  "type": "Feature",
  "properties": {
    "iso:country":"US",
    "sg:address":"1098 Fond du Lac Ave",
    "sg:city":"Sheboygan Falls",
    "sg:classifiers":[
        {
            "category":"Food & Beverages",
            "subcategory":"Liquor & Beverages",
            "type":"Retail Goods"
        }
    ],
    "sg:phone":"+1 920 467 4158",
    "sg:postcode":"53085",
    "sg:province":"WI",
    "sg:tags":[
        "alcoholic"
    ],
    "wof:name":"Liquor Mart Inc",
    "wof:placetype":"venue"
},
  "geometry": {"coordinates":[-87.823854,43.733717],"type":"Point"}
}