{
  "type": "Feature",
  "properties": {
    "iso:country":"US",
    "sg:address":"7120 Winnebago Dr",
    "sg:city":"Fond Du Lac",
    "sg:classifiers":[
        {
            "category":"Shopping",
            "subcategory":"Used Merchandise",
            "type":"Retail Goods"
        }
    ],
    "sg:phone":"+1 920 923 9610",
    "sg:postcode":"54935",
    "sg:province":"WI",
    "sg:tags":[
        "antique"
    ],
    "wof:name":"Country Cupboards",
    "wof:placetype":"venue"
},
  "geometry": {"coordinates":[-88.420157,43.800869],"type":"Point"}
}