{
  "type": "Feature",
  "properties": {
    "iso:country":"US",
    "sg:address":"3068 Celestial Ln",
    "sg:city":"Green Bay",
    "sg:classifiers":[
        {
            "category":"Building & Trades",
            "subcategory":"Electrical",
            "type":"Services"
        }
    ],
    "sg:phone":"+1 920 434 0901",
    "sg:postcode":"54313",
    "sg:province":"WI",
    "sg:tags":[
        "electrical",
        "electric",
        "contractor"
    ],
    "wof:name":"De Main Electric",
    "wof:placetype":"venue"
},
  "geometry": {"coordinates":[-88.100032,44.596091],"type":"Point"}
}