{
  "type": "Feature",
  "properties": {
    "iso:country":"US",
    "sg:address":"1949 US Hwy 12",
    "sg:city":"Fort Atkinson",
    "sg:classifiers":[
        {
            "category":"Wholesale",
            "subcategory":"Electrical",
            "type":"Manufacturing & Wholesale Goods"
        }
    ],
    "sg:phone":"+1 920 568 9240",
    "sg:postcode":"53538",
    "sg:province":"WI",
    "sg:tags":[
        "electric",
        "motor"
    ],
    "wof:name":"G B Electric Motor Svc Inc",
    "wof:placetype":"venue"
},
  "geometry": {"coordinates":[-88.829595,42.908641],"type":"Point"}
}