{
  "type": "Feature",
  "properties": {
    "addr:full":"15 Wisconsin St Darien WI 53114",
    "addr:postcode":"53114",
    "addr:street":"15 Wisconsin St",
    "iso:country":"US",
    "sg:address":"15 Wisconsin St",
    "sg:city":"Darien",
    "sg:classifiers":[
        {
            "category":"Restaurant",
            "type":"Food & Drink"
        }
    ],
    "sg:phone":"+1 262 882 5342",
    "sg:postcode":"53114",
    "sg:province":"WI",
    "wof:name":"Farmers Inn",
    "wof:placetype":"venue"
},
  "geometry": {"coordinates":[-88.707728,42.60143],"type":"Point"}
}