{
  "type": "Feature",
  "properties": {
    "iso:country":"US",
    "sg:address":"4994 Co Rd C",
    "sg:city":"Ellsworth",
    "sg:classifiers":[
        {
            "category":"Building & Trades",
            "subcategory":"Construction",
            "type":"Services"
        }
    ],
    "sg:phone":"+1 715 792 5119",
    "sg:postcode":"54011",
    "sg:province":"WI",
    "sg:tags":[
        "general",
        "contractor"
    ],
    "wof:name":"Dodge Construction",
    "wof:placetype":"venue"
},
  "geometry": {"coordinates":[-92.45649,44.720826],"type":"Point"}
}