{
  "type": "Feature",
  "properties": {
    "iso:country":"US",
    "sg:address":"2224 Ledgeview Rd",
    "sg:city":"Green Lake",
    "sg:classifiers":[
        {
            "category":"Building & Trades",
            "subcategory":"Construction",
            "type":"Services"
        }
    ],
    "sg:phone":"+1 920 294 3561",
    "sg:postcode":"54941",
    "sg:province":"WI",
    "sg:tags":[
        "contractor"
    ],
    "wof:name":"Gordys Home Improvement Inc",
    "wof:placetype":"venue"
},
  "geometry": {"coordinates":[-88.99330999999999,43.835462],"type":"Point"}
}