{
  "type": "Feature",
  "properties": {
    "iso:country":"US",
    "sg:address":"311 Main St E",
    "sg:city":"Ashland",
    "sg:classifiers":[
        {
            "category":"Shopping",
            "subcategory":"Florist",
            "type":"Retail Goods"
        }
    ],
    "sg:phone":"+1 715 682 2646",
    "sg:postcode":"54806",
    "sg:province":"WI",
    "wof:name":"Marge's Floral Design",
    "wof:placetype":"venue"
},
  "geometry": {"coordinates":[-90.880197,46.592866],"type":"Point"}
}