{
  "type": "Feature",
  "properties": {
    "iso:country":"US",
    "sg:address":"106 State Hwy 54",
    "sg:city":"Seymour",
    "sg:classifiers":[
        {
            "category":"Banks & Credit Unions",
            "subcategory":"Bank",
            "type":"Services"
        }
    ],
    "sg:phone":"+1 920 833 2288",
    "sg:postcode":"54165",
    "sg:province":"WI",
    "wof:name":"Baylake Bank",
    "wof:placetype":"venue"
},
  "geometry": {"coordinates":[-88.190445,44.500548],"type":"Point"}
}