{
  "type": "Feature",
  "properties": {
    "iso:country":"US",
    "sg:address":"6806 28th Ave",
    "sg:city":"Kenosha",
    "sg:classifiers":[
        {
            "category":"Manufacturing",
            "subcategory":"Building Materials",
            "type":"Manufacturing & Wholesale Goods"
        }
    ],
    "sg:phone":"+1 262 654 7702",
    "sg:postcode":"53143",
    "sg:province":"WI",
    "wof:name":"Margetson Woodworking",
    "wof:placetype":"venue"
},
  "geometry": {"coordinates":[-87.842978,42.572117],"type":"Point"}
}