{
  "type": "Feature",
  "properties": {
    "iso:country":"US",
    "sg:address":"4681 Hillside Rd",
    "sg:city":"West Bend",
    "sg:classifiers":[
        {
            "category":"Freight",
            "type":"Transportation"
        }
    ],
    "sg:phone":"+1 262 644 4604",
    "sg:postcode":"53095",
    "sg:province":"WI",
    "sg:tags":[
        "operator",
        "trucking"
    ],
    "wof:name":"Mary Russell",
    "wof:placetype":"venue"
},
  "geometry": {"coordinates":[-88.241238,43.35777],"type":"Point"}
}