{
  "type": "Feature",
  "properties": {
    "iso:country":"US",
    "sg:address":"600 S Cecil St",
    "sg:city":"Bonduel",
    "sg:classifiers":[
        {
            "category":"Farming",
            "subcategory":"Dairy Farm",
            "type":"Manufacturing & Wholesale Goods"
        }
    ],
    "sg:phone":"+1 715 758 2272",
    "sg:postcode":"54107",
    "sg:province":"WI",
    "wof:name":"Dale Vangheem",
    "wof:placetype":"venue"
},
  "geometry": {"coordinates":[-88.445753,44.732019],"type":"Point"}
}