{
  "type": "Feature",
  "properties": {
    "iso:country":"US",
    "sg:address":"2112 Fred St",
    "sg:city":"Marinette",
    "sg:classifiers":[
        {
            "category":"Shopping",
            "type":"Retail Goods"
        }
    ],
    "sg:phone":"+1 715 732 2049",
    "sg:postcode":"54143",
    "sg:province":"WI",
    "sg:tags":[
        "merchandise"
    ],
    "wof:name":"Wood Shed",
    "wof:placetype":"venue"
},
  "geometry": {"coordinates":[-87.63495399999999,45.10127],"type":"Point"}
}