{
  "type": "Feature",
  "properties": {
    "iso:country":"US",
    "sg:address":"2875 Graf Rd",
    "sg:city":"Sturgeon Bay",
    "sg:classifiers":[
        {
            "category":"Farming",
            "subcategory":"Farm",
            "type":"Manufacturing & Wholesale Goods"
        }
    ],
    "sg:phone":"+1 920 743 8647",
    "sg:postcode":"54235",
    "sg:province":"WI",
    "wof:name":"Paul Graf Farms LLC",
    "wof:placetype":"venue"
},
  "geometry": {"coordinates":[-87.417814,44.806978],"type":"Point"}
}