{
  "type": "Feature",
  "properties": {
    "iso:country":"US",
    "sg:address":"135 S Hancock St",
    "sg:city":"Madison",
    "sg:classifiers":[
        {
            "category":"Professional",
            "subcategory":"Management & Consulting",
            "type":"Services"
        }
    ],
    "sg:phone":"+1 608 255 5591",
    "sg:postcode":"53703",
    "sg:province":"WI",
    "sg:tags":[
        "consultant",
        "business"
    ],
    "wof:name":"Gann Associates",
    "wof:placetype":"venue"
},
  "geometry": {"coordinates":[-89.377759,43.075505],"type":"Point"}
}