{
  "type": "Feature",
  "properties": {
    "iso:country":"US",
    "sg:address":"3633 Fairfax St",
    "sg:city":"Eau Claire",
    "sg:classifiers":[
        {
            "category":"Wholesale",
            "subcategory":"Vending Machines",
            "type":"Manufacturing & Wholesale Goods"
        }
    ],
    "sg:phone":"+1 715 215 0139",
    "sg:postcode":"54701",
    "sg:province":"WI",
    "wof:name":"WITT Vending & Steak Shop",
    "wof:placetype":"venue"
},
  "geometry": {"coordinates":[-91.468234,44.778354],"type":"Point"}
}