{
  "type": "Feature",
  "properties": {
    "iso:country":"US",
    "sg:address":"1937 W Hope Ave",
    "sg:city":"Milwaukee",
    "sg:classifiers":[
        {
            "category":"Social Services",
            "subcategory":"Child Care",
            "type":"Services"
        }
    ],
    "sg:phone":"+1 414 264 5028",
    "sg:postcode":"53209",
    "sg:province":"WI",
    "sg:tags":[
        "day"
    ],
    "wof:name":"All of US Childcare Inc",
    "wof:placetype":"venue"
},
  "geometry": {"coordinates":[-87.93485200000001,43.093136],"type":"Point"}
}