{
  "type": "Feature",
  "properties": {
    "iso:country":"US",
    "sg:address":"3301 Kinsman Blvd",
    "sg:city":"Madison",
    "sg:classifiers":[
        {
            "category":"Professional",
            "subcategory":"Research",
            "type":"Services"
        }
    ],
    "sg:phone":"+1 608 241 4471",
    "sg:postcode":"53704",
    "sg:province":"WI",
    "sg:tags":[
        "chemical",
        "biological",
        "laboratory"
    ],
    "sg:website":"www.covance.com",
    "wof:name":"Covance Laboratories Inc",
    "wof:placetype":"venue"
},
  "geometry": {"coordinates":[-89.33367800000001,43.125854],"type":"Point"}
}