{
  "type": "Feature",
  "properties": {
    "addr:full":"1515 Grandview Pkwy Sturtevant WI 53177",
    "addr:housenumber":"1515",
    "addr:postcode":"53177",
    "addr:street":"Grandview Pkwy",
    "iso:country":"US",
    "sg:address":"1515 Grandview Pkwy",
    "sg:city":"Sturtevant",
    "sg:classifiers":[
        {
            "category":"Professional",
            "subcategory":"Business Services",
            "type":"Services"
        }
    ],
    "sg:phone":"+1 262 884 9000",
    "sg:postcode":"53177",
    "sg:province":"WI",
    "wof:name":"Chuckerman Packaging",
    "wof:placetype":"venue"
},
  "geometry": {"coordinates":[-87.956801,42.718964],"type":"Point"}
}