{
  "type": "Feature",
  "properties": {
    "iso:country":"US",
    "sg:address":"602 W Clayton Ave",
    "sg:city":"Clayton",
    "sg:classifiers":[
        {
            "category":"Insurance",
            "subcategory":"Insurance Agent",
            "type":"Services"
        }
    ],
    "sg:phone":"+1 715 948 2100",
    "sg:postcode":"54004",
    "sg:province":"WI",
    "sg:tags":[
        "agency"
    ],
    "wof:name":"Clayton Cars",
    "wof:placetype":"venue"
},
  "geometry": {"coordinates":[-92.17547399999999,45.331323],"type":"Point"}
}