{
  "type": "Feature",
  "properties": {
    "iso:country":"US",
    "sg:address":"1874 670th St",
    "sg:city":"Bay City",
    "sg:classifiers":[
        {
            "category":"Travel",
            "subcategory":"Hotels & Motels",
            "type":"Entertainment"
        }
    ],
    "sg:phone":"+1 715 594 3844",
    "sg:postcode":"54723",
    "sg:province":"WI",
    "sg:tags":[
        "operation"
    ],
    "wof:name":"Land Of Oz Bed & Breakfast",
    "wof:placetype":"venue"
},
  "geometry": {"coordinates":[-92.463694,44.61128],"type":"Point"}
}