{
  "type": "Feature",
  "properties": {
    "iso:country":"US",
    "sg:address":"2151 Dixon St",
    "sg:city":"Stevens Point",
    "sg:classifiers":[
        {
            "category":"Retail",
            "subcategory":"Repair Shop",
            "type":"Services"
        }
    ],
    "sg:phone":"+1 715 341 1954",
    "sg:postcode":"54481",
    "sg:province":"WI",
    "wof:name":"Custom Leather & Repairs",
    "wof:placetype":"venue"
},
  "geometry": {"coordinates":[-89.568585,44.515674],"type":"Point"}
}