{
  "type": "Feature",
  "properties": {
    "iso:country":"US",
    "sg:address":"756 W Wisconsin Ave",
    "sg:city":"Pewaukee",
    "sg:classifiers":[
        {
            "category":"Recreation",
            "type":"Entertainment"
        }
    ],
    "sg:phone":"+1 262 695 4665",
    "sg:postcode":"53072",
    "sg:province":"WI",
    "sg:tags":[
        "guide"
    ],
    "wof:name":"Trophy Hunter Fishing Guide",
    "wof:placetype":"venue"
},
  "geometry": {"coordinates":[-88.278104,43.089509],"type":"Point"}
}