{
  "type": "Feature",
  "properties": {
    "iso:country":"US",
    "sg:address":"5011 51st St",
    "sg:city":"Mauston",
    "sg:classifiers":[
        {
            "category":"Wholesale",
            "subcategory":"Drugs",
            "type":"Manufacturing & Wholesale Goods"
        }
    ],
    "sg:phone":"+1 608 847 4775",
    "sg:postcode":"53948",
    "sg:province":"WI",
    "wof:name":"Ren Mountain Nutritionals",
    "wof:placetype":"venue"
},
  "geometry": {"coordinates":[-90.030265,43.803361],"type":"Point"}
}