{
  "type": "Feature",
  "properties": {
    "iso:country":"US",
    "sg:address":"318 N Franklin Ave",
    "sg:city":"Madison",
    "sg:classifiers":[
        {
            "category":"Education",
            "subcategory":"Special Training",
            "type":"Public Place"
        }
    ],
    "sg:phone":"+1 608 238 8789",
    "sg:postcode":"53705",
    "sg:province":"WI",
    "sg:tags":[
        "educational"
    ],
    "wof:name":"Learnitec",
    "wof:placetype":"venue"
},
  "geometry": {"coordinates":[-89.436329,43.071312],"type":"Point"}
}