{
  "type": "Feature",
  "properties": {
    "iso:country":"US",
    "sg:address":"8183 Kafka Rd",
    "sg:city":"Wausaukee",
    "sg:classifiers":[
        {
            "category":"Building & Trades",
            "subcategory":"Construction",
            "type":"Services"
        }
    ],
    "sg:phone":"+1 715 856 6213",
    "sg:postcode":"54177",
    "sg:province":"WI",
    "sg:tags":[
        "house"
    ],
    "wof:name":"Northeast Construction",
    "wof:placetype":"venue"
},
  "geometry": {"coordinates":[-88.005962,45.389052],"type":"Point"}
}