{
  "type": "Feature",
  "properties": {
    "iso:country":"US",
    "sg:address":"212 E Industrial Dr",
    "sg:city":"Beaver Dam",
    "sg:classifiers":[
        {
            "category":"Social Services",
            "subcategory":"Adult Care",
            "type":"Services"
        }
    ],
    "sg:phone":"+1 920 356 0032",
    "sg:postcode":"53916",
    "sg:province":"WI",
    "sg:tags":[
        "home",
        "residential"
    ],
    "wof:name":"Prairie Crest Assisted Living",
    "wof:placetype":"venue"
},
  "geometry": {"coordinates":[-88.818289,43.477079],"type":"Point"}
}