{
  "type": "Feature",
  "properties": {
    "iso:country":"US",
    "sg:address":"1802 E Eden Pl",
    "sg:city":"Milwaukee",
    "sg:classifiers":[
        {
            "category":"Building & Trades",
            "subcategory":"Cleaning & Sanitation",
            "type":"Services"
        }
    ],
    "sg:phone":"+1 414 482 0099",
    "sg:postcode":"53235",
    "sg:province":"WI",
    "sg:tags":[
        "butler",
        "maid"
    ],
    "wof:name":"Classy Maids",
    "wof:placetype":"venue"
},
  "geometry": {"coordinates":[-87.886345,42.980158],"type":"Point"}
}