{
  "type": "Feature",
  "properties": {
    "iso:country":"US",
    "sg:address":"14414 E Railway Ave",
    "sg:city":"Weyerhaeuser",
    "sg:classifiers":[
        {
            "category":"Bars & Pubs",
            "type":"Food & Drink"
        }
    ],
    "sg:phone":"+1 715 353 2437",
    "sg:postcode":"54895",
    "sg:province":"WI",
    "sg:tags":[
        "drinking"
    ],
    "wof:name":"Ditch Pickle Bar Grill",
    "wof:placetype":"venue"
},
  "geometry": {"coordinates":[-91.41530899999999,45.422209],"type":"Point"}
}