{
  "type": "Feature",
  "properties": {
    "addr:full":"1106 Jones Ave Racine WI 53402",
    "addr:housenumber":"1106",
    "addr:postcode":"53402",
    "addr:street":"Jones Ave",
    "iso:country":"US",
    "sg:address":"1106 Jones Ave",
    "sg:city":"Racine",
    "sg:classifiers":[
        {
            "category":"Building & Trades",
            "subcategory":"Construction",
            "type":"Services"
        }
    ],
    "sg:phone":"+1 262 634 2608",
    "sg:postcode":"53402",
    "sg:province":"WI",
    "sg:tags":[
        "gutter"
    ],
    "wof:name":"Storm Control Seamless Gutters",
    "wof:placetype":"venue"
},
  "geometry": {"coordinates":[-87.793442,42.74871],"type":"Point"}
}