{
  "type": "Feature",
  "properties": {
    "iso:country":"US",
    "sg:address":"1223 Belknap St",
    "sg:city":"Superior",
    "sg:classifiers":[
        {
            "category":"Retail",
            "subcategory":"Auto Repair",
            "type":"Services"
        }
    ],
    "sg:phone":"+1 715 394 6669",
    "sg:postcode":"54880",
    "sg:province":"WI",
    "sg:tags":[
        "general"
    ],
    "wof:name":"Exhaust Pros Of Superior",
    "wof:placetype":"venue"
},
  "geometry": {"coordinates":[-92.096152,46.720729],"type":"Point"}
}