{
  "type": "Feature",
  "properties": {
    "iso:country":"US",
    "sg:address":"850 Elm Grove Rd",
    "sg:city":"Elm Grove",
    "sg:classifiers":[
        {
            "category":"Health Services",
            "subcategory":"Health Practitioner",
            "type":"Services"
        }
    ],
    "sg:phone":"+1 262 784 1121",
    "sg:postcode":"53122",
    "sg:province":"WI",
    "wof:name":"Lifespan Psychological Svcs",
    "wof:placetype":"venue"
},
  "geometry": {"coordinates":[-88.079148,43.040053],"type":"Point"}
}