{
  "type": "Feature",
  "properties": {
    "iso:country":"US",
    "sg:address":"976 du Chateau Ave",
    "sg:city":"Green Bay",
    "sg:classifiers":[
        {
            "category":"Wholesale",
            "subcategory":"Groceries",
            "type":"Manufacturing & Wholesale Goods"
        }
    ],
    "sg:phone":"+1 920 494 4141",
    "sg:postcode":"54304",
    "sg:province":"WI",
    "sg:tags":[
        "confectionery"
    ],
    "wof:name":"Bereavement Care Baskets",
    "wof:placetype":"venue"
},
  "geometry": {"coordinates":[-88.064439,44.49566],"type":"Point"}
}