{
  "type": "Feature",
  "properties": {
    "iso:country":"US",
    "sg:address":"10998 State Hwy 60",
    "sg:city":"Columbus",
    "sg:classifiers":[
        {
            "category":"Retail",
            "subcategory":"Auto Repair",
            "type":"Services"
        }
    ],
    "sg:phone":"+1 920 623 3959",
    "sg:postcode":"53925",
    "sg:province":"WI",
    "sg:tags":[
        "repairing",
        "automobile"
    ],
    "wof:name":"Bittner Pump Svc",
    "wof:placetype":"venue"
},
  "geometry": {"coordinates":[-88.93615699999999,43.329526],"type":"Point"}
}