{
  "type": "Feature",
  "properties": {
    "addr:full":"159 E Court St Richland Center WI 53581",
    "addr:housenumber":"159",
    "addr:postcode":"53581",
    "addr:street":"E Court St",
    "iso:country":"US",
    "sg:address":"159 E Court St",
    "sg:city":"Richland Center",
    "sg:classifiers":[
        {
            "category":"Banks & Credit Unions",
            "subcategory":"Investment Brokerage",
            "type":"Services"
        }
    ],
    "sg:phone":"+1 608 647 3745",
    "sg:postcode":"53581",
    "sg:province":"WI",
    "wof:name":"Joel Rewald Investment Consltg",
    "wof:placetype":"venue"
},
  "geometry": {"coordinates":[-90.38486399999999,43.335422],"type":"Point"}
}