{
  "type": "Feature",
  "properties": {
    "addr:full":"2100 N Mayfair Rd Milwaukee WI 53226",
    "addr:housenumber":"2100",
    "addr:postcode":"53226",
    "addr:street":"N Mayfair Rd",
    "iso:country":"US",
    "sg:address":"2100 N Mayfair Rd",
    "sg:city":"Milwaukee",
    "sg:classifiers":[
        {
            "category":"Health Services",
            "subcategory":"Clinic",
            "type":"Services"
        },
        {
            "category":"Health Services",
            "subcategory":"Health Practitioner",
            "type":"Services"
        },
        {
            "category":"Health Services",
            "subcategory":"Chiropractor",
            "type":"Services"
        }
    ],
    "sg:phone":"+1 414 476 2225",
    "sg:postcode":"53226",
    "sg:province":"WI",
    "sg:tags":[
        "therapist",
        "therapy",
        "physical",
        "chiropractic"
    ],
    "wof:name":"Chiropractic Care Center of Wauwatosa",
    "wof:placetype":"venue"
},
  "geometry": {"coordinates":[-88.047501,43.05735],"type":"Point"}
}