{
  "type": "Feature",
  "properties": {
    "iso:country":"US",
    "sg:address":"2375 N Wahl Ave",
    "sg:city":"Milwaukee",
    "sg:classifiers":[
        {
            "category":"Professional",
            "subcategory":"Management & Consulting",
            "type":"Services"
        }
    ],
    "sg:phone":"+1 414 332 3857",
    "sg:postcode":"53211",
    "sg:province":"WI",
    "sg:tags":[
        "technical",
        "consultant",
        "business"
    ],
    "wof:name":"George Jacobi",
    "wof:placetype":"venue"
},
  "geometry": {"coordinates":[-87.87612900000001,43.061244],"type":"Point"}
}