{
  "type": "Feature",
  "properties": {
    "iso:country":"US",
    "sg:address":"9104 Abrams Ln",
    "sg:city":"Mount Hope",
    "sg:classifiers":[
        {
            "category":"Government",
            "subcategory":"Office",
            "type":"Public Place"
        }
    ],
    "sg:phone":"+1 608 988 4388",
    "sg:postcode":"53816",
    "sg:province":"WI",
    "sg:tags":[
        "township"
    ],
    "wof:name":"Mount Hope Township of",
    "wof:placetype":"venue"
},
  "geometry": {"coordinates":[-90.877116,42.972826],"type":"Point"}
}