{
  "type": "Feature",
  "properties": {
    "addr:full":"10 Marina Dr Superior WI 54880",
    "addr:housenumber":"10",
    "addr:postcode":"54880",
    "addr:street":"Marina Dr",
    "iso:country":"US",
    "sg:address":"10 Marina Dr",
    "sg:city":"Superior",
    "sg:classifiers":[
        {
            "category":"Restaurant",
            "type":"Food & Drink"
        }
    ],
    "sg:phone":"+1 715 394 2000",
    "sg:postcode":"54880",
    "sg:province":"WI",
    "wof:name":"Portside Cafe",
    "wof:placetype":"venue"
},
  "geometry": {"coordinates":[-92.066553,46.722268],"type":"Point"}
}