{
  "type": "Feature",
  "properties": {
    "iso:country":"US",
    "sg:address":"535 Main St",
    "sg:city":"Wild Rose",
    "sg:classifiers":[
        {
            "category":"Restaurant",
            "type":"Food & Drink"
        }
    ],
    "sg:phone":"+1 920 622 4400",
    "sg:postcode":"54984",
    "sg:province":"WI",
    "wof:name":"Vintage Garden Cafe",
    "wof:placetype":"venue"
},
  "geometry": {"coordinates":[-89.248586,44.17883],"type":"Point"}
}