{
  "type": "Feature",
  "properties": {
    "addr:full":"10416 N River Lake Dr Thiensville WI 53092",
    "addr:housenumber":"10416",
    "addr:postcode":"53092",
    "addr:street":"N River Lake Dr",
    "iso:country":"US",
    "sg:address":"10416 N River Lake Dr",
    "sg:city":"Thiensville",
    "sg:classifiers":[
        {
            "category":"Professional",
            "subcategory":"Management & Consulting",
            "type":"Services"
        }
    ],
    "sg:phone":"+1 262 242 5274",
    "sg:postcode":"53092",
    "sg:province":"WI",
    "wof:name":"Red Rock",
    "wof:placetype":"venue"
},
  "geometry": {"coordinates":[-87.96500399999999,43.207438],"type":"Point"}
}