{
  "type": "Feature",
  "properties": {
    "iso:country":"US",
    "sg:address":"8701 S Howell Ave",
    "sg:city":"Oak Creek",
    "sg:classifiers":[
        {
            "category":"Restaurant",
            "type":"Food & Drink"
        }
    ],
    "sg:phone":"+1 414 571 9059",
    "sg:postcode":"53154",
    "sg:province":"WI",
    "sg:tags":[
        "delicatessen"
    ],
    "wof:name":"Victorio's Italian Deli",
    "wof:placetype":"venue"
},
  "geometry": {"coordinates":[-87.912346,42.882961],"type":"Point"}
}