{
  "type": "Feature",
  "properties": {
    "iso:country":"US",
    "sg:address":"200 N Jefferson St",
    "sg:city":"Milwaukee",
    "sg:classifiers":[
        {
            "category":"Professional",
            "subcategory":"Engineering",
            "type":"Services"
        }
    ],
    "sg:phone":"+1 414 225 9817",
    "sg:postcode":"53202",
    "sg:province":"WI",
    "sg:tags":[
        "civil",
        "engineer"
    ],
    "sg:website":"www.daarengineering.com",
    "wof:name":"Daar Engineering Inc",
    "wof:placetype":"venue"
},
  "geometry": {"coordinates":[-87.90470500000001,43.033993],"type":"Point"}
}