{
  "type": "Feature",
  "properties": {
    "iso:country":"US",
    "sg:address":"1101 Chili Rd",
    "sg:city":"Chili",
    "sg:classifiers":[
        {
            "category":"Building & Trades",
            "subcategory":"Construction",
            "type":"Services"
        }
    ],
    "sg:phone":"+1 715 683 2490",
    "sg:postcode":"54420",
    "sg:province":"WI",
    "sg:tags":[
        "roofing",
        "material",
        "contractor"
    ],
    "wof:name":"Stichert Roofing & Lumber Co",
    "wof:placetype":"venue"
},
  "geometry": {"coordinates":[-90.365416,44.626642],"type":"Point"}
}