{
  "type": "Feature",
  "properties": {
    "addr:full":"415 Cedar Ave W Menomonie WI 54751",
    "addr:housenumber":"415",
    "addr:postcode":"54751",
    "addr:street":"Cedar Ave W",
    "iso:country":"US",
    "sg:address":"415 Cedar Ave W",
    "sg:city":"Menomonie",
    "sg:classifiers":[
        {
            "category":"Retail",
            "subcategory":"Auto Rental",
            "type":"Services"
        }
    ],
    "sg:phone":"+1 715 232 6356",
    "sg:postcode":"54751",
    "sg:province":"WI",
    "sg:tags":[
        "passenger",
        "car"
    ],
    "wof:name":"Ford Rental System",
    "wof:placetype":"venue"
},
  "geometry": {"coordinates":[-91.93622000000001,44.902222],"type":"Point"}
}