{
  "type": "Feature",
  "properties": {
    "addr:full":"8134 Aberdeen Ct Milwaukee WI 53213",
    "addr:housenumber":"8134",
    "addr:postcode":"53213",
    "addr:street":"Aberdeen Ct",
    "iso:country":"US",
    "sg:address":"8134 Aberdeen Ct",
    "sg:city":"Milwaukee",
    "sg:classifiers":[
        {
            "category":"Home & Garden",
            "subcategory":"Building Materials",
            "type":"Retail Goods"
        }
    ],
    "sg:phone":"+1 414 453 6924",
    "sg:postcode":"53213",
    "sg:province":"WI",
    "sg:tags":[
        "plumbing",
        "fixture",
        "supply"
    ],
    "wof:name":"Kitchen Solvers-Northern",
    "wof:placetype":"venue"
},
  "geometry": {"coordinates":[-88.015833,43.057141],"type":"Point"}
}