{
  "type": "Feature",
  "properties": {
    "iso:country":"US",
    "sg:address":"811 Keller Ave S",
    "sg:city":"Amery",
    "sg:classifiers":[
        {
            "category":"Utilities",
            "subcategory":"Natural Gas",
            "type":"Services"
        }
    ],
    "sg:phone":"+1 715 268 0703",
    "sg:postcode":"54001",
    "sg:province":"WI",
    "sg:tags":[
        "liquefied",
        "distribution",
        "petroleum"
    ],
    "wof:name":"Amery Office",
    "wof:placetype":"venue"
},
  "geometry": {"coordinates":[-92.366928,45.298072],"type":"Point"}
}