{
  "type": "Feature",
  "properties": {
    "iso:country":"US",
    "sg:address":"1405 Racine St",
    "sg:city":"Racine",
    "sg:classifiers":[
        {
            "category":"Retail",
            "subcategory":"Auto Repair",
            "type":"Services"
        }
    ],
    "sg:phone":"+1 262 633 2333",
    "sg:postcode":"53403",
    "sg:province":"WI",
    "sg:tags":[
        "automobile",
        "lubrication"
    ],
    "wof:name":"Mobil Express Lube",
    "wof:placetype":"venue"
},
  "geometry": {"coordinates":[-87.793699,42.715041],"type":"Point"}
}