{
  "type": "Feature",
  "properties": {
    "iso:country":"US",
    "sg:address":"4576 Blueberry Rd",
    "sg:city":"Fredonia",
    "sg:classifiers":[
        {
            "category":"Farming",
            "subcategory":"Dairy Farm",
            "type":"Manufacturing & Wholesale Goods"
        }
    ],
    "sg:phone":"+1 262 692 2871",
    "sg:postcode":"53021",
    "sg:province":"WI",
    "wof:name":"Sandy Loam Dairy Farms",
    "wof:placetype":"venue"
},
  "geometry": {"coordinates":[-87.96026500000001,43.455345],"type":"Point"}
}