{
  "type": "Feature",
  "properties": {
    "iso:country":"US",
    "sg:address":"1507 W Knapp St",
    "sg:city":"Rice Lake",
    "sg:classifiers":[
        {
            "category":"Health Services",
            "subcategory":"Hospital",
            "type":"Services"
        }
    ],
    "sg:phone":"+1 715 236 3610",
    "sg:postcode":"54868",
    "sg:province":"WI",
    "wof:name":"Rice Lake Physical Therapy",
    "wof:placetype":"venue"
},
  "geometry": {"coordinates":[-91.754453,45.509248],"type":"Point"}
}