{
  "type": "Feature",
  "properties": {
    "iso:country":"US",
    "sg:address":"2055 Allison Park Dr",
    "sg:city":"Richland Center",
    "sg:classifiers":[
        {
            "category":"Organizations",
            "subcategory":"Religious Organization",
            "type":"Services"
        }
    ],
    "sg:phone":"+1 608 647 6771",
    "sg:postcode":"53581",
    "sg:province":"WI",
    "sg:tags":[
        "church"
    ],
    "wof:name":"Richland Baptist Temple",
    "wof:placetype":"venue"
},
  "geometry": {"coordinates":[-90.388726,43.354221],"type":"Point"}
}