{
  "type": "Feature",
  "properties": {
    "iso:country":"US",
    "sg:address":"612 59th St",
    "sg:city":"Kenosha",
    "sg:classifiers":[
        {
            "category":"Retail",
            "subcategory":"Veterinary Services",
            "type":"Services"
        }
    ],
    "sg:phone":"+1 262 653 0067",
    "sg:postcode":"53140",
    "sg:province":"WI",
    "sg:tags":[
        "clinic",
        "veterinarian",
        "hospital"
    ],
    "wof:name":"Kenosha Lake Shore Veterinary Clinic",
    "wof:placetype":"venue"
},
  "geometry": {"coordinates":[-87.818405,42.582339],"type":"Point"}
}