{
  "type": "Feature",
  "properties": {
    "addr:full":"4765 85th St Kenosha WI 53142",
    "addr:housenumber":"4765",
    "addr:postcode":"53142",
    "addr:street":"85Th St",
    "iso:country":"US",
    "sg:address":"4765 85th St",
    "sg:city":"Kenosha",
    "sg:classifiers":[
        {
            "category":"Real Estate",
            "subcategory":"Architect",
            "type":"Services"
        }
    ],
    "sg:phone":"+1 262 694 6791",
    "sg:postcode":"53142",
    "sg:province":"WI",
    "sg:tags":[
        "architectural"
    ],
    "wof:name":"Robert R Hybert",
    "wof:placetype":"venue"
},
  "geometry": {"coordinates":[-87.86508600000001,42.551707],"type":"Point"}
}