{
  "type": "Feature",
  "properties": {
    "iso:country":"US",
    "sg:address":"10525 Co Rd C",
    "sg:city":"Clintonville",
    "sg:classifiers":[
        {
            "category":"Farming",
            "subcategory":"Dairy Farm",
            "type":"Manufacturing & Wholesale Goods"
        }
    ],
    "sg:phone":"+1 715 823 4708",
    "sg:postcode":"54929",
    "sg:province":"WI",
    "wof:name":"Willis & Sandra Eulrich",
    "wof:placetype":"venue"
},
  "geometry": {"coordinates":[-88.681614,44.659698],"type":"Point"}
}