{
  "type": "Feature",
  "properties": {
    "addr:full":"10100 S Windsor Dr Oak Creek WI 53154",
    "addr:housenumber":"10100",
    "addr:postcode":"53154",
    "addr:street":"S Windsor Dr",
    "iso:country":"US",
    "sg:address":"10100 S Windsor Dr",
    "sg:city":"Oak Creek",
    "sg:classifiers":[
        {
            "category":"Social Services",
            "subcategory":"Child Care",
            "type":"Services"
        }
    ],
    "sg:phone":"+1 414 764 4521",
    "sg:postcode":"53154",
    "sg:province":"WI",
    "sg:tags":[
        "day"
    ],
    "wof:name":"Christian Family Daycare Cente",
    "wof:placetype":"venue"
},
  "geometry": {"coordinates":[-87.93045600000001,42.861334],"type":"Point"}
}