{
  "type": "Feature",
  "properties": {
    "iso:country":"US",
    "sg:address":"1529 Mill Rd",
    "sg:city":"Menomonie",
    "sg:classifiers":[
        {
            "category":"Shopping",
            "subcategory":"Gifts & Souvenirs",
            "type":"Retail Goods"
        }
    ],
    "sg:phone":"+1 715 235 0818",
    "sg:postcode":"54751",
    "sg:province":"WI",
    "sg:tags":[
        "cards",
        "greeting"
    ],
    "wof:name":"Myrons Cards & Gifts 7",
    "wof:placetype":"venue"
},
  "geometry": {"coordinates":[-91.953475,44.871726],"type":"Point"}
}