{
  "type": "Feature",
  "properties": {
    "iso:country":"US",
    "sg:address":"201 N Main St",
    "sg:city":"Alma",
    "sg:classifiers":[
        {
            "category":"Travel",
            "subcategory":"Hotels & Motels",
            "type":"Entertainment"
        }
    ],
    "sg:phone":"+1 608 685 3380",
    "sg:postcode":"54756",
    "sg:province":"WI",
    "wof:name":"Alma Hotel",
    "wof:placetype":"venue"
},
  "geometry": {"coordinates":[-92.008981,44.421597],"type":"Point"}
}