{
  "type": "Feature",
  "properties": {
    "iso:country":"US",
    "sg:address":"109 South St",
    "sg:city":"Waunakee",
    "sg:classifiers":[
        {
            "category":"Professional",
            "subcategory":"Lawyer & Legal Services",
            "type":"Services"
        }
    ],
    "sg:phone":"+1 608 849 4325",
    "sg:postcode":"53597",
    "sg:province":"WI",
    "wof:name":"Cunningham Kimberly M Atty",
    "wof:placetype":"venue"
},
  "geometry": {"coordinates":[-89.45503100000001,43.190896],"type":"Point"}
}