{
  "type": "Feature",
  "properties": {
    "addr:full":"2335 W Mason St Green Bay WI 54303",
    "addr:housenumber":"2335",
    "addr:postcode":"54303",
    "addr:street":"W Mason St",
    "iso:country":"US",
    "sg:address":"2335 W Mason St",
    "sg:city":"Green Bay",
    "sg:classifiers":[
        {
            "category":"Restaurant",
            "type":"Food & Drink"
        }
    ],
    "sg:phone":"+1 920 494 4505",
    "sg:postcode":"54303",
    "sg:province":"WI",
    "sg:website":"www.losbanditoscantina.com",
    "wof:name":"Los Banditos",
    "wof:placetype":"venue"
},
  "geometry": {"coordinates":[-88.091482,44.524007],"type":"Point"}
}