{
  "type": "Feature",
  "properties": {
    "iso:country":"US",
    "sg:address":"18684 Co Rd G",
    "sg:city":"Muscoda",
    "sg:classifiers":[
        {
            "category":"Building & Trades",
            "subcategory":"Construction",
            "type":"Services"
        }
    ],
    "sg:phone":"+1 608 739 4091",
    "sg:postcode":"53573",
    "sg:province":"WI",
    "sg:tags":[
        "excavating",
        "contractor"
    ],
    "wof:name":"Dave Roh Logging & Excavating",
    "wof:placetype":"venue"
},
  "geometry": {"coordinates":[-90.45265499999999,43.181251],"type":"Point"}
}