{
  "type": "Feature",
  "properties": {
    "iso:country":"US",
    "sg:address":"9811 W Oklahoma Ave",
    "sg:city":"Milwaukee",
    "sg:classifiers":[
        {
            "category":"Retail",
            "subcategory":"Veterinary Services",
            "type":"Services"
        }
    ],
    "sg:phone":"+1 414 604 0320",
    "sg:postcode":"53227",
    "sg:province":"WI",
    "wof:name":"Cat Care Clinic Inc",
    "wof:placetype":"venue"
},
  "geometry": {"coordinates":[-88.03611600000001,42.98804],"type":"Point"}
}