{
  "type": "Feature",
  "properties": {
    "iso:country":"US",
    "sg:address":"3002 N Murray Ave",
    "sg:city":"Milwaukee",
    "sg:classifiers":[
        {
            "category":"Home & Garden",
            "subcategory":"Furniture",
            "type":"Retail Goods"
        }
    ],
    "sg:phone":"+1 414 962 9270",
    "sg:postcode":"53211",
    "sg:province":"WI",
    "sg:tags":[
        "house",
        "carpentry",
        "contractor"
    ],
    "wof:name":"Erickson Woodworking Inc",
    "wof:placetype":"venue"
},
  "geometry": {"coordinates":[-87.885302,43.074609],"type":"Point"}
}