{
  "type": "Feature",
  "properties": {
    "addr:full":"8875 Greenmeadow Ln Greendale WI 53129",
    "addr:housenumber":"8875",
    "addr:postcode":"53129",
    "addr:street":"Greenmeadow Ln",
    "iso:country":"US",
    "sg:address":"8875 Greenmeadow Ln",
    "sg:city":"Greendale",
    "sg:classifiers":[
        {
            "category":"Retail",
            "subcategory":"Repair Shop",
            "type":"Services"
        }
    ],
    "sg:phone":"+1 414 425 0280",
    "sg:postcode":"53129",
    "sg:province":"WI",
    "sg:tags":[
        "equipment"
    ],
    "wof:name":"Jeff M Bales",
    "wof:placetype":"venue"
},
  "geometry": {"coordinates":[-88.02512900000001,42.940358],"type":"Point"}
}