{
  "type": "Feature",
  "properties": {
    "iso:country":"US",
    "sg:address":"108 N Leonard St",
    "sg:city":"West Salem",
    "sg:classifiers":[
        {
            "category":"Manufacturing",
            "subcategory":"Printing",
            "type":"Manufacturing & Wholesale Goods"
        }
    ],
    "sg:phone":"+1 608 786 0515",
    "sg:postcode":"54669",
    "sg:province":"WI",
    "sg:tags":[
        "commercial",
        "lithographic"
    ],
    "wof:name":"E Z Print & Copy Inc",
    "wof:placetype":"venue"
},
  "geometry": {"coordinates":[-91.08137000000001,43.897908],"type":"Point"}
}