{
  "type": "Feature",
  "properties": {
    "iso:country":"US",
    "sg:address":"2918 S Mayfield Rd",
    "sg:city":"Jackson",
    "sg:classifiers":[
        {
            "category":"Professional",
            "subcategory":"Management & Consulting",
            "type":"Services"
        }
    ],
    "sg:phone":"+1 262 677 3428",
    "sg:postcode":"53037",
    "sg:province":"WI",
    "sg:tags":[
        "consultant"
    ],
    "wof:name":"Northland Consulting Svc",
    "wof:placetype":"venue"
},
  "geometry": {"coordinates":[-88.201308,43.295966],"type":"Point"}
}