{
  "type": "Feature",
  "properties": {
    "iso:country":"US",
    "sg:address":"944 Elmore Dr",
    "sg:city":"Campbellsport",
    "sg:classifiers":[
        {
            "category":"Building & Trades",
            "subcategory":"Construction",
            "type":"Services"
        },
        {
            "category":"Retail",
            "subcategory":"Auto Repair",
            "type":"Services"
        }
    ],
    "sg:phone":"+1 920 533 4425",
    "sg:postcode":"53010",
    "sg:province":"WI",
    "sg:tags":[
        "water",
        "automobile",
        "well",
        "drilling",
        "repairing"
    ],
    "wof:name":"Zieliekes Well Drilling Inc",
    "wof:placetype":"venue"
},
  "geometry": {"coordinates":[-88.300763,43.573527],"type":"Point"}
}