{
  "type": "Feature",
  "properties": {
    "iso:country":"US",
    "sg:address":"9447 State Hwy 13",
    "sg:city":"Phillips",
    "sg:classifiers":[
        {
            "category":"Shopping",
            "subcategory":"Bicycles & Sporting Goods",
            "type":"Retail Goods"
        }
    ],
    "sg:phone":"+1 715 339 3818",
    "sg:postcode":"54555",
    "sg:province":"WI",
    "wof:name":"Hwy 13 Bait & Tackle",
    "wof:placetype":"venue"
},
  "geometry": {"coordinates":[-90.422751,45.712623],"type":"Point"}
}