{
  "type": "Feature",
  "properties": {
    "iso:country":"US",
    "sg:address":"2370 Co Rd C",
    "sg:city":"Auburndale",
    "sg:classifiers":[
        {
            "category":"Farming",
            "subcategory":"Dairy Farm",
            "type":"Manufacturing & Wholesale Goods"
        }
    ],
    "sg:phone":"+1 715 384 8127",
    "sg:postcode":"54412",
    "sg:province":"WI",
    "wof:name":"Roger Andres",
    "wof:placetype":"venue"
},
  "geometry": {"coordinates":[-89.964134,44.743145],"type":"Point"}
}