{
  "type": "Feature",
  "properties": {
    "iso:country":"US",
    "sg:address":"219 N River St",
    "sg:city":"Spooner",
    "sg:classifiers":[
        {
            "category":"Banks & Credit Unions",
            "subcategory":"Bank",
            "type":"Services"
        }
    ],
    "sg:phone":"+1 715 635 7858",
    "sg:postcode":"54801",
    "sg:province":"WI",
    "sg:website":"www.shelllakestatebank.com",
    "wof:name":"Shell Lake State Bank",
    "wof:placetype":"venue"
},
  "geometry": {"coordinates":[-91.889715,45.82468],"type":"Point"}
}