{
  "type": "Feature",
  "properties": {
    "addr:full":"1511 E Lake Bluff Blvd Milwaukee WI 53211",
    "addr:housenumber":"1511",
    "addr:postcode":"53211",
    "addr:street":"E Lake Bluff Blvd",
    "iso:country":"US",
    "sg:address":"1511 E Lake Bluff Blvd",
    "sg:city":"Milwaukee",
    "sg:classifiers":[
        {
            "category":"Professional",
            "type":"Services"
        },
        {
            "category":"Arts & Performance",
            "subcategory":"Music",
            "type":"Entertainment"
        }
    ],
    "sg:phone":"+1 414 687 8551",
    "sg:postcode":"53211",
    "sg:province":"WI",
    "sg:tags":[
        "record",
        "producer",
        "label"
    ],
    "wof:name":"Suburban Entertainment",
    "wof:placetype":"venue"
},
  "geometry": {"coordinates":[-87.892245,43.095524],"type":"Point"}
}