{
  "type": "Feature",
  "properties": {
    "iso:country":"US",
    "sg:address":"105 Garfield Ave",
    "sg:city":"Eau Claire",
    "sg:classifiers":[
        {
            "category":"Communications",
            "subcategory":"Radio Station",
            "type":"Services"
        }
    ],
    "sg:phone":"+1 715 836 4170",
    "sg:postcode":"54701",
    "sg:province":"WI",
    "sg:tags":[
        "company",
        "broadcasting"
    ],
    "wof:name":"WUEC",
    "wof:placetype":"venue"
},
  "geometry": {"coordinates":[-91.49727,44.799058],"type":"Point"}
}