{
  "type": "Feature",
  "properties": {
    "iso:country":"US",
    "sg:address":"501 N Spring St",
    "sg:city":"Beaver Dam",
    "sg:classifiers":[
        {
            "category":"Retail",
            "subcategory":"Auto Repair",
            "type":"Services"
        }
    ],
    "sg:phone":"+1 920 885 6200",
    "sg:postcode":"53916",
    "sg:province":"WI",
    "sg:tags":[
        "repairing",
        "automobile"
    ],
    "wof:name":"R & S Auto Svc",
    "wof:placetype":"venue"
},
  "geometry": {"coordinates":[-88.83617599999999,43.461292],"type":"Point"}
}