{
  "type": "Feature",
  "properties": {
    "iso:country":"US",
    "sg:address":"1643 Greiner Rd",
    "sg:city":"Kaukauna",
    "sg:classifiers":[
        {
            "category":"Utilities",
            "subcategory":"Fuel Oil & Lpg",
            "type":"Services"
        }
    ],
    "sg:phone":"+1 920 766 9655",
    "sg:postcode":"54130",
    "sg:province":"WI",
    "sg:tags":[
        "dealer"
    ],
    "wof:name":"New Heritage LLC",
    "wof:placetype":"venue"
},
  "geometry": {"coordinates":[-88.265539,44.342829],"type":"Point"}
}