{
  "type": "Feature",
  "properties": {
    "iso:country":"US",
    "sg:address":"3908 Chicago Ave",
    "sg:city":"Conover",
    "sg:classifiers":[
        {
            "category":"Building & Trades",
            "subcategory":"Construction",
            "type":"Services"
        }
    ],
    "sg:phone":"+1 715 479 6996",
    "sg:postcode":"54519",
    "sg:province":"WI",
    "sg:tags":[
        "water",
        "well",
        "drilling"
    ],
    "wof:name":"Hedberg Well Drilling Inc",
    "wof:placetype":"venue"
},
  "geometry": {"coordinates":[-89.199282,46.004309],"type":"Point"}
}