{
  "type": "Feature",
  "properties": {
    "iso:country":"US",
    "sg:address":"772 7th St",
    "sg:city":"Clayton",
    "sg:classifiers":[
        {
            "category":"Farming",
            "subcategory":"Farm",
            "type":"Manufacturing & Wholesale Goods"
        }
    ],
    "sg:phone":"+1 715 357 3127",
    "sg:postcode":"54004",
    "sg:province":"WI",
    "sg:tags":[
        "crop",
        "general"
    ],
    "wof:name":"Nelson Julian Farm",
    "wof:placetype":"venue"
},
  "geometry": {"coordinates":[-92.01321,45.317635],"type":"Point"}
}