{
  "type": "Feature",
  "properties": {
    "iso:country":"US",
    "sg:address":"12720 Sheridan Rd",
    "sg:city":"Pleasant Prairie",
    "sg:classifiers":[
        {
            "category":"Autos & Motor Vehicles",
            "subcategory":"Fuel & Gas Station",
            "type":"Retail Goods"
        }
    ],
    "sg:phone":"+1 262 694 9120",
    "sg:postcode":"53158",
    "sg:province":"IL",
    "sg:tags":[
        "grocery",
        "station",
        "gasoline"
    ],
    "wof:name":"Citgo",
    "wof:placetype":"venue"
},
  "geometry": {"coordinates":[-87.82199,42.493233],"type":"Point"}
}