{
  "type": "Feature",
  "properties": {
    "iso:country":"US",
    "sg:address":"10025 W Greenfield Ave",
    "sg:city":"Milwaukee",
    "sg:classifiers":[
        {
            "category":"Wholesale",
            "subcategory":"Hardware",
            "type":"Manufacturing & Wholesale Goods"
        }
    ],
    "sg:phone":"+1 414 771 4822",
    "sg:postcode":"53214",
    "sg:province":"WI",
    "sg:tags":[
        "heating"
    ],
    "wof:name":"G & O Thermal Supply Co",
    "wof:placetype":"venue"
},
  "geometry": {"coordinates":[-88.038276,43.016518],"type":"Point"}
}