{
  "type": "Feature",
  "properties": {
    "iso:country":"US",
    "sg:address":"624 Albion Rd",
    "sg:city":"Edgerton",
    "sg:classifiers":[
        {
            "category":"Government",
            "subcategory":"Office",
            "type":"Public Place"
        }
    ],
    "sg:phone":"+1 608 884 8974",
    "sg:postcode":"53534",
    "sg:province":"WI",
    "sg:tags":[
        "city",
        "taxation"
    ],
    "wof:name":"Town Of Albion Clerk/Treasurer",
    "wof:placetype":"venue"
},
  "geometry": {"coordinates":[-89.068994,42.880478],"type":"Point"}
}