{
  "type": "Feature",
  "properties": {
    "iso:country":"US",
    "sg:address":"4491 Co Rd C",
    "sg:city":"Downsville",
    "sg:classifiers":[
        {
            "category":"Government",
            "subcategory":"Post Office",
            "type":"Public Place"
        }
    ],
    "sg:phone":"+1 715 664 8731",
    "sg:postcode":"54751",
    "sg:province":"WI",
    "sg:tags":[
        "postal",
        "us"
    ],
    "wof:name":"US Post Office",
    "wof:placetype":"venue"
},
  "geometry": {"coordinates":[-91.932535,44.774558],"type":"Point"}
}