{
  "type": "Feature",
  "properties": {
    "iso:country":"US",
    "sg:address":"102 Douglas St",
    "sg:city":"Chetek",
    "sg:classifiers":[
        {
            "category":"Organizations",
            "subcategory":"Community Association",
            "type":"Services"
        }
    ],
    "sg:phone":"+1 715 924 3962",
    "sg:postcode":"54728",
    "sg:province":"WI",
    "sg:tags":[
        "club"
    ],
    "wof:name":"Veterans Of Foreign Wars",
    "wof:placetype":"venue"
},
  "geometry": {"coordinates":[-91.651324,45.313624],"type":"Point"}
}