{
  "type": "Feature",
  "properties": {
    "addr:full":"225 Orin St Gays Mills WI 54631",
    "addr:housenumber":"225",
    "addr:postcode":"54631",
    "addr:street":"Orin St",
    "iso:country":"US",
    "sg:address":"225 Orin St",
    "sg:city":"Gays Mills",
    "sg:classifiers":[
        {
            "category":"Government",
            "subcategory":"Post Office",
            "type":"Public Place"
        }
    ],
    "sg:phone":"+1 608 735 4450",
    "sg:postcode":"54631",
    "sg:province":"WI",
    "wof:name":"US Post Office",
    "wof:placetype":"venue"
},
  "geometry": {"coordinates":[-90.84619000000001,43.316708],"type":"Point"}
}