{
  "type": "Feature",
  "properties": {
    "iso:country":"US",
    "sg:address":"116 S Main St",
    "sg:city":"Medford",
    "sg:classifiers":[
        {
            "category":"Bars & Pubs",
            "type":"Food & Drink"
        }
    ],
    "sg:phone":"+1 715 748 2283",
    "sg:postcode":"54451",
    "sg:province":"WI",
    "wof:name":"Mainstreet Bar & Grill",
    "wof:placetype":"venue"
},
  "geometry": {"coordinates":[-90.345489,45.138762],"type":"Point"}
}