{
  "type": "Feature",
  "properties": {
    "iso:country":"US",
    "sg:address":"110 N 3rd Ave",
    "sg:city":"Sturgeon Bay",
    "sg:classifiers":[
        {
            "category":"Restaurant",
            "type":"Food & Drink"
        }
    ],
    "sg:phone":"+1 920 743 4249",
    "sg:postcode":"54235",
    "sg:province":"WI",
    "sg:tags":[
        "eating"
    ],
    "wof:name":"Inn The",
    "wof:placetype":"venue"
},
  "geometry": {"coordinates":[-87.377735,44.835862],"type":"Point"}
}