{
  "type": "Feature",
  "properties": {
    "iso:country":"US",
    "sg:address":"1112 7th Ave",
    "sg:city":"Monroe",
    "sg:classifiers":[
        {
            "category":"Professional",
            "type":"Services"
        }
    ],
    "sg:phone":"+1 608 324 4450",
    "sg:postcode":"53566",
    "sg:province":"WI",
    "wof:name":"Madeleine Direct Inc",
    "wof:placetype":"venue"
},
  "geometry": {"coordinates":[-89.651751,42.599897],"type":"Point"}
}