{
  "type": "Feature",
  "properties": {
    "iso:country":"US",
    "sg:address":"841 Co Rd H",
    "sg:city":"Palmyra",
    "sg:classifiers":[
        {
            "category":"Shopping",
            "type":"Retail Goods"
        }
    ],
    "sg:phone":"+1 262 495 4010",
    "sg:postcode":"53156",
    "sg:province":"WI",
    "sg:tags":[
        "candle"
    ],
    "wof:name":"Babette's Candles",
    "wof:placetype":"venue"
},
  "geometry": {"coordinates":[-88.591825,42.872209],"type":"Point"}
}