{
  "type": "Feature",
  "properties": {
    "iso:country":"US",
    "sg:address":"1011 S Main St",
    "sg:city":"Rice Lake",
    "sg:classifiers":[
        {
            "category":"Education",
            "subcategory":"School",
            "type":"Public Place"
        }
    ],
    "sg:phone":"+1 715 234 4591",
    "sg:postcode":"54868",
    "sg:province":"WI",
    "wof:name":"Franklin Elementary School",
    "wof:placetype":"venue"
},
  "geometry": {"coordinates":[-91.733266,45.489976],"type":"Point"}
}