{
  "type": "Feature",
  "properties": {
    "iso:country":"US",
    "sg:address":"5497 Kristof Rd",
    "sg:city":"Hatley",
    "sg:classifiers":[
        {
            "category":"Mining & Drilling",
            "type":"Manufacturing & Wholesale Goods"
        }
    ],
    "sg:phone":"+1 715 446 3046",
    "sg:postcode":"54440",
    "sg:province":"WI",
    "sg:tags":[
        "gravel",
        "pit"
    ],
    "wof:name":"Edwin Siekierzynski",
    "wof:placetype":"venue"
},
  "geometry": {"coordinates":[-89.438582,44.793127],"type":"Point"}
}