{
  "type": "Feature",
  "properties": {
    "iso:country":"US",
    "sg:address":"5740 N Walworth Rd",
    "sg:city":"Walworth",
    "sg:classifiers":[
        {
            "category":"Farming",
            "subcategory":"Farm",
            "type":"Manufacturing & Wholesale Goods"
        }
    ],
    "sg:phone":"+1 262 275 3783",
    "sg:postcode":"53184",
    "sg:province":"WI",
    "sg:tags":[
        "general"
    ],
    "wof:name":"Robert A Pearce Farms Inc",
    "wof:placetype":"venue"
},
  "geometry": {"coordinates":[-88.61637399999999,42.574535],"type":"Point"}
}