{
  "type": "Feature",
  "properties": {
    "iso:country":"US",
    "sg:address":"11980 Co Rd C",
    "sg:city":"Clintonville",
    "sg:classifiers":[
        {
            "category":"Freight",
            "type":"Transportation"
        }
    ],
    "sg:phone":"+1 715 823 5426",
    "sg:postcode":"54929",
    "sg:province":"WI",
    "sg:tags":[
        "distance",
        "long",
        "trucking"
    ],
    "wof:name":"Badger Transport Inc",
    "wof:placetype":"venue"
},
  "geometry": {"coordinates":[-88.609982,44.670194],"type":"Point"}
}