{
  "type": "Feature",
  "properties": {
    "addr:full":"6201 Odana Rd Madison WI 53719",
    "addr:housenumber":"6201",
    "addr:postcode":"53719",
    "addr:street":"Odana Rd",
    "iso:country":"US",
    "sg:address":"6201 Odana Rd",
    "sg:city":"Madison",
    "sg:classifiers":[
        {
            "category":"Home & Garden",
            "subcategory":"Furniture",
            "type":"Retail Goods"
        }
    ],
    "sg:phone":"+1 608 271 9220",
    "sg:postcode":"53719",
    "sg:province":"WI",
    "sg:tags":[
        "household"
    ],
    "sg:website":"www.leathfurniture.com",
    "wof:name":"Leath Furniture LLC",
    "wof:placetype":"venue"
},
  "geometry": {"coordinates":[-89.488219,43.053537],"type":"Point"}
}