{
  "type": "Feature",
  "properties": {
    "iso:country":"US",
    "sg:address":"208 Cora St",
    "sg:city":"Johnson Creek",
    "sg:classifiers":[
        {
            "category":"Building & Trades",
            "subcategory":"Construction",
            "type":"Services"
        }
    ],
    "sg:phone":"+1 920 699 2273",
    "sg:postcode":"53038",
    "sg:province":"WI",
    "sg:tags":[
        "house"
    ],
    "wof:name":"Sabol Construction LLC",
    "wof:placetype":"venue"
},
  "geometry": {"coordinates":[-88.77315299999999,43.073729],"type":"Point"}
}