{
  "type": "Feature",
  "properties": {
    "addr:full":"12865 Co Rd C Black River Falls WI 54615",
    "addr:housenumber":"12865",
    "addr:postcode":"54615",
    "addr:street":"Co Rd C",
    "iso:country":"US",
    "sg:address":"12865 Co Rd C",
    "sg:city":"Black River Falls",
    "sg:classifiers":[
        {
            "category":"Freight",
            "type":"Transportation"
        }
    ],
    "sg:phone":"+1 715 284 9328",
    "sg:postcode":"54615",
    "sg:province":"WI",
    "sg:tags":[
        "operator",
        "local",
        "trucking"
    ],
    "wof:name":"Callihan Trucking",
    "wof:placetype":"venue"
},
  "geometry": {"coordinates":[-90.943786,44.273151],"type":"Point"}
}