{
  "type": "Feature",
  "properties": {
    "iso:country":"US",
    "sg:address":"2685 Wilderness Rd",
    "sg:city":"Sayner",
    "sg:classifiers":[
        {
            "category":"Freight",
            "type":"Transportation"
        }
    ],
    "sg:phone":"+1 715 542 3421",
    "sg:postcode":"54560",
    "sg:province":"WI",
    "sg:tags":[
        "hauling",
        "trucking"
    ],
    "wof:name":"Sun Dog Trucking",
    "wof:placetype":"venue"
},
  "geometry": {"coordinates":[-89.534936,45.980351],"type":"Point"}
}