{
  "type": "Feature",
  "properties": {
    "iso:country":"US",
    "sg:address":"747 N Broadway",
    "sg:city":"Milwaukee",
    "sg:classifiers":[
        {
            "category":"Restaurant",
            "type":"Food & Drink"
        }
    ],
    "sg:menulink":"http://www.allmenus.com/wi/milwaukee/8075-moceans/menu/",
    "sg:phone":"+1 414 272 7470",
    "sg:postcode":"53202",
    "sg:province":"WI",
    "sg:tags":[
        "seafood",
        "american"
    ],
    "wof:name":"Moceans",
    "wof:placetype":"venue"
},
  "geometry": {"coordinates":[-87.90797000000001,43.039894],"type":"Point"}
}