{
  "type": "Feature",
  "properties": {
    "iso:country":"US",
    "sg:address":"4405 W Loomis Rd",
    "sg:city":"Milwaukee",
    "sg:classifiers":[
        {
            "category":"Autos & Motor Vehicles",
            "subcategory":"Fuel & Gas Station",
            "type":"Retail Goods"
        }
    ],
    "sg:phone":"+1 414 281 9810",
    "sg:postcode":"53220",
    "sg:province":"WI",
    "sg:tags":[
        "wash"
    ],
    "wof:name":"Amoco",
    "wof:placetype":"venue"
},
  "geometry": {"coordinates":[-87.971408,42.956736],"type":"Point"}
}