{
  "type": "Feature",
  "properties": {
    "iso:country":"US",
    "sg:address":"2299 Hall Rd",
    "sg:city":"Hartford",
    "sg:classifiers":[
        {
            "category":"Professional",
            "subcategory":"Business Services",
            "type":"Services"
        }
    ],
    "sg:phone":"+1 262 673 2625",
    "sg:postcode":"53027",
    "sg:province":"WI",
    "sg:tags":[
        "int",
        "an",
        "as",
        "furnishing",
        "home",
        "operates",
        "furniture"
    ],
    "wof:name":"Shars Interiors",
    "wof:placetype":"venue"
},
  "geometry": {"coordinates":[-88.36057599999999,43.275462],"type":"Point"}
}