{
  "type": "Feature",
  "properties": {
    "iso:country":"US",
    "sg:address":"300 English St",
    "sg:city":"Racine",
    "sg:classifiers":[
        {
            "category":"Professional",
            "subcategory":"Computer Services",
            "type":"Services"
        }
    ],
    "sg:phone":"+1 262 635 0960",
    "sg:postcode":"53402",
    "sg:province":"WI",
    "sg:tags":[
        "prepackaged",
        "software"
    ],
    "wof:name":"Jane Planet",
    "wof:placetype":"venue"
},
  "geometry": {"coordinates":[-87.78487199999999,42.744749],"type":"Point"}
}