{
  "type": "Feature",
  "properties": {
    "iso:country":"US",
    "sg:address":"1283 Southfield Dr",
    "sg:city":"Menasha",
    "sg:classifiers":[
        {
            "category":"Organizations",
            "subcategory":"Professional Association",
            "type":"Services"
        }
    ],
    "sg:phone":"+1 920 830 2550",
    "sg:postcode":"54952",
    "sg:province":"WI",
    "sg:tags":[
        "business"
    ],
    "wof:name":"Business Growth Group LLC",
    "wof:placetype":"venue"
},
  "geometry": {"coordinates":[-88.397568,44.224734],"type":"Point"}
}