{
  "type": "Feature",
  "properties": {
    "iso:country":"US",
    "sg:address":"615 26th St",
    "sg:city":"Monroe",
    "sg:classifiers":[
        {
            "category":"Retail",
            "subcategory":"Veterinary Services",
            "type":"Services"
        }
    ],
    "sg:phone":"+1 608 329 4485",
    "sg:postcode":"53566",
    "sg:province":"WI",
    "wof:name":"Black River Veterinary Svcs",
    "wof:placetype":"venue"
},
  "geometry": {"coordinates":[-89.652104,42.588485],"type":"Point"}
}