{
  "type": "Feature",
  "properties": {
    "iso:country":"US",
    "sg:address":"8221 S 68th St",
    "sg:city":"Franklin",
    "sg:classifiers":[
        {
            "category":"Organizations",
            "subcategory":"Community Association",
            "type":"Services"
        }
    ],
    "sg:phone":"+1 414 425 7230",
    "sg:postcode":"53132",
    "sg:province":"WI",
    "sg:tags":[
        "club"
    ],
    "wof:name":"Tuckaway Country Club",
    "wof:placetype":"venue"
},
  "geometry": {"coordinates":[-87.999771,42.894864],"type":"Point"}
}