{
  "type": "Feature",
  "properties": {
    "iso:country":"US",
    "sg:address":"1610 Fairplay St",
    "sg:city":"Hazel Green",
    "sg:classifiers":[
        {
            "category":"Government",
            "subcategory":"Office",
            "type":"Public Place"
        }
    ],
    "sg:phone":"+1 608 854 2953",
    "sg:postcode":"53811",
    "sg:province":"WI",
    "sg:tags":[
        "village"
    ],
    "wof:name":"Hazel Green Light Dept",
    "wof:placetype":"venue"
},
  "geometry": {"coordinates":[-90.434988,42.532941],"type":"Point"}
}