{
  "type": "Feature",
  "properties": {
    "iso:country":"US",
    "sg:address":"4802 Sheboygan Ave",
    "sg:city":"Madison",
    "sg:classifiers":[
        {
            "category":"Communications",
            "type":"Services"
        }
    ],
    "sg:phone":"+1 608 231 9930",
    "sg:postcode":"53705",
    "sg:province":"WI",
    "wof:name":"R Ns Communications",
    "wof:placetype":"venue"
},
  "geometry": {"coordinates":[-89.464133,43.073002],"type":"Point"}
}