{
  "type": "Feature",
  "properties": {
    "iso:country":"US",
    "sg:address":"901 Fremont St",
    "sg:city":"Kiel",
    "sg:classifiers":[
        {
            "category":"Personal",
            "subcategory":"Tanning Parlor",
            "type":"Services"
        }
    ],
    "sg:phone":"+1 920 894 3311",
    "sg:postcode":"53042",
    "sg:province":"WI",
    "sg:tags":[
        "salon"
    ],
    "wof:name":"Shake It Up Day Spa",
    "wof:placetype":"venue"
},
  "geometry": {"coordinates":[-88.042872,43.912129],"type":"Point"}
}