{
  "type": "Feature",
  "properties": {
    "addr:full":"104 E Drexel Ave Oak Creek WI 53154",
    "addr:housenumber":"104",
    "addr:postcode":"53154",
    "addr:street":"E Drexel Ave",
    "iso:country":"US",
    "sg:address":"104 E Drexel Ave",
    "sg:city":"Oak Creek",
    "sg:classifiers":[
        {
            "category":"Health Services",
            "subcategory":"Chiropractor",
            "type":"Services"
        }
    ],
    "sg:phone":"+1 414 762 1060",
    "sg:postcode":"53154",
    "sg:province":"WI",
    "wof:name":"Gaveric Chiropractic",
    "wof:placetype":"venue"
},
  "geometry": {"coordinates":[-87.90838100000001,42.901146],"type":"Point"}
}