{
  "type": "Feature",
  "properties": {
    "iso:country":"US",
    "sg:address":"2011 S Lake Michigan Dr",
    "sg:city":"Sturgeon Bay",
    "sg:classifiers":[
        {
            "category":"Building & Trades",
            "subcategory":"Construction",
            "type":"Services"
        }
    ],
    "sg:phone":"+1 920 746 0703",
    "sg:postcode":"54235",
    "sg:province":"WI",
    "sg:tags":[
        "house",
        "contractor"
    ],
    "wof:name":"Alberts Randy Plst Door Cnty",
    "wof:placetype":"venue"
},
  "geometry": {"coordinates":[-87.32499300000001,44.763073],"type":"Point"}
}