{
  "type": "Feature",
  "properties": {
    "iso:country":"US",
    "sg:address":"1341 Avon St",
    "sg:city":"La Crosse",
    "sg:classifiers":[
        {
            "category":"Professional",
            "subcategory":"Accounting & Tax Preparation",
            "type":"Services"
        }
    ],
    "sg:phone":"+1 608 781 7375",
    "sg:postcode":"54603",
    "sg:province":"WI",
    "wof:name":"Quantum Accounting",
    "wof:placetype":"venue"
},
  "geometry": {"coordinates":[-91.24547,43.842382],"type":"Point"}
}