{
  "type": "Feature",
  "properties": {
    "iso:country":"US",
    "sg:address":"902 Milwaukee Ave",
    "sg:city":"South Milwaukee",
    "sg:classifiers":[
        {
            "category":"Health Services",
            "subcategory":"Health Practitioner",
            "type":"Services"
        }
    ],
    "sg:phone":"+1 414 771 9304",
    "sg:postcode":"53172",
    "sg:province":"WI",
    "sg:tags":[
        "psychologist"
    ],
    "wof:name":"Shore Counseling & Consltng",
    "wof:placetype":"venue"
},
  "geometry": {"coordinates":[-87.860679,42.910759],"type":"Point"}
}