{
  "type": "Feature",
  "properties": {
    "iso:country":"US",
    "sg:address":"315 Hall Ave",
    "sg:city":"Crivitz",
    "sg:classifiers":[
        {
            "category":"Restaurant",
            "type":"Food & Drink"
        }
    ],
    "sg:phone":"+1 715 854 7418",
    "sg:postcode":"54114",
    "sg:province":"WI",
    "wof:name":"R Family Restaurant",
    "wof:placetype":"venue"
},
  "geometry": {"coordinates":[-88.001297,45.229915],"type":"Point"}
}