{
  "type": "Feature",
  "properties": {
    "iso:country":"US",
    "sg:address":"11077 Co Rd X",
    "sg:city":"Stanley",
    "sg:classifiers":[
        {
            "category":"Retail",
            "subcategory":"Auto Repair",
            "type":"Services"
        }
    ],
    "sg:phone":"+1 715 644 5172",
    "sg:postcode":"54768",
    "sg:province":"WI",
    "sg:tags":[
        "body",
        "automobile"
    ],
    "wof:name":"Breezy Acres",
    "wof:placetype":"venue"
},
  "geometry": {"coordinates":[-90.870005,44.959083],"type":"Point"}
}