{
  "type": "Feature",
  "properties": {
    "iso:country":"US",
    "sg:address":"202 Church St",
    "sg:city":"Ontario",
    "sg:classifiers":[
        {
            "category":"Shopping",
            "subcategory":"Bicycles & Sporting Goods",
            "type":"Retail Goods"
        }
    ],
    "sg:phone":"+1 608 337 4735",
    "sg:postcode":"54651",
    "sg:province":"WI",
    "sg:tags":[
        "equipment",
        "archery",
        "supply"
    ],
    "wof:name":"Smith's Archery",
    "wof:placetype":"venue"
},
  "geometry": {"coordinates":[-90.59460799999999,43.724713],"type":"Point"}
}