{
  "type": "Feature",
  "properties": {
    "addr:full":"2721 US Hwy 51 N Woodruff WI 54568",
    "addr:housenumber":"2721",
    "addr:postcode":"54568",
    "addr:street":"Us Hwy 51 N",
    "iso:country":"US",
    "sg:address":"2721 US Hwy 51 N",
    "sg:city":"Woodruff",
    "sg:classifiers":[
        {
            "category":"Restaurant",
            "type":"Food & Drink"
        }
    ],
    "sg:phone":"+1 715 356 4335",
    "sg:postcode":"54568",
    "sg:province":"WI",
    "wof:name":"Marty's Place North",
    "wof:placetype":"venue"
},
  "geometry": {"coordinates":[-89.699045,45.978612],"type":"Point"}
}