{
  "type": "Feature",
  "properties": {
    "iso:country":"US",
    "sg:address":"320 Superior Ave",
    "sg:city":"Tomah",
    "sg:classifiers":[
        {
            "category":"Shopping",
            "subcategory":"Clothing, Apparel, & Fashions",
            "type":"Retail Goods"
        }
    ],
    "sg:phone":"+1 608 374 3883",
    "sg:postcode":"54660",
    "sg:province":"WI",
    "sg:tags":[
        "western"
    ],
    "wof:name":"Painted Pony",
    "wof:placetype":"venue"
},
  "geometry": {"coordinates":[-90.50462400000001,43.984304],"type":"Point"}
}