{
  "type": "Feature",
  "properties": {
    "iso:country":"US",
    "sg:address":"7905 W Appleton Ave",
    "sg:city":"Milwaukee",
    "sg:classifiers":[
        {
            "category":"Professional",
            "subcategory":"Management & Consulting",
            "type":"Services"
        }
    ],
    "sg:phone":"+1 414 438 9390",
    "sg:postcode":"53218",
    "sg:province":"WI",
    "sg:tags":[
        "consultant",
        "educational"
    ],
    "wof:name":"C Ross Education Ctr",
    "wof:placetype":"venue"
},
  "geometry": {"coordinates":[-88.01243100000001,43.100216],"type":"Point"}
}