{
  "type": "Feature",
  "properties": {
    "iso:country":"US",
    "sg:address":"4561 Stoney Ridge Rd",
    "sg:city":"Loganville",
    "sg:classifiers":[
        {
            "category":"Building & Trades",
            "subcategory":"Construction",
            "type":"Services"
        }
    ],
    "sg:phone":"+1 608 986 4645",
    "sg:postcode":"53959",
    "sg:province":"WI",
    "sg:tags":[
        "contractor"
    ],
    "wof:name":"Troyers Masonry",
    "wof:placetype":"venue"
},
  "geometry": {"coordinates":[-90.08259099999999,43.452842],"type":"Point"}
}