{
  "type": "Feature",
  "properties": {
    "iso:country":"US",
    "sg:address":"5952 River Rd",
    "sg:city":"Waunakee",
    "sg:classifiers":[
        {
            "category":"Wholesale",
            "subcategory":"Machinery & Supplies",
            "type":"Manufacturing & Wholesale Goods"
        }
    ],
    "sg:phone":"+1 608 849 9842",
    "sg:postcode":"53597",
    "sg:province":"WI",
    "sg:tags":[
        "equipment",
        "industrial"
    ],
    "wof:name":"Reinhart Foods",
    "wof:placetype":"venue"
},
  "geometry": {"coordinates":[-89.375479,43.183751],"type":"Point"}
}