{
  "type": "Feature",
  "properties": {
    "iso:country":"US",
    "sg:address":"251 Municipal Dr",
    "sg:city":"West Bend",
    "sg:classifiers":[
        {
            "category":"Building & Trades",
            "subcategory":"Construction",
            "type":"Services"
        }
    ],
    "sg:phone":"+1 262 335 5060",
    "sg:postcode":"53095",
    "sg:province":"WI",
    "sg:tags":[
        "marking",
        "maintenance",
        "parking"
    ],
    "wof:name":"West Bend Public Works",
    "wof:placetype":"venue"
},
  "geometry": {"coordinates":[-88.15034900000001,43.423453],"type":"Point"}
}