{
  "type": "Feature",
  "properties": {
    "iso:country":"US",
    "sg:address":"2211 Eagle Dr",
    "sg:city":"Middleton",
    "sg:classifiers":[
        {
            "category":"Building & Trades",
            "subcategory":"Landscaping Services",
            "type":"Services"
        }
    ],
    "sg:phone":"+1 608 824 0220",
    "sg:postcode":"53562",
    "sg:province":"WI",
    "wof:name":"Turf & Ornamental Spray System",
    "wof:placetype":"venue"
},
  "geometry": {"coordinates":[-89.527686,43.100666],"type":"Point"}
}