{
  "type": "Feature",
  "properties": {
    "iso:country":"US",
    "sg:address":"8579 State Hwy 164",
    "sg:city":"Hartland",
    "sg:classifiers":[
        {
            "category":"Manufacturing",
            "subcategory":"Lumber",
            "type":"Manufacturing & Wholesale Goods"
        }
    ],
    "sg:phone":"+1 262 246 3772",
    "sg:postcode":"53029",
    "sg:province":"WI",
    "sg:tags":[
        "timber",
        "contractor",
        "operation",
        "tract",
        "carpentry"
    ],
    "wof:name":"Carl E Trapp Enterprises",
    "wof:placetype":"venue"
},
  "geometry": {"coordinates":[-88.262462,43.173674],"type":"Point"}
}