{
  "type": "Feature",
  "properties": {
    "iso:country":"US",
    "sg:address":"1126 S 24th St",
    "sg:city":"Manitowoc",
    "sg:classifiers":[
        {
            "category":"Building & Trades",
            "subcategory":"Construction",
            "type":"Services"
        }
    ],
    "sg:phone":"+1 920 684 1295",
    "sg:postcode":"54220",
    "sg:province":"WI",
    "sg:tags":[
        "house"
    ],
    "wof:name":"Mrotek Builders",
    "wof:placetype":"venue"
},
  "geometry": {"coordinates":[-87.678145,44.086023],"type":"Point"}
}