{
  "type": "Feature",
  "properties": {
    "iso:country":"US",
    "sg:address":"2302 International Ln",
    "sg:city":"Madison",
    "sg:classifiers":[
        {
            "category":"Social Services",
            "type":"Services"
        }
    ],
    "sg:phone":"+1 608 233 2354",
    "sg:postcode":"53704",
    "sg:province":"WI",
    "sg:tags":[
        "organization",
        "welfare"
    ],
    "sg:website":"www.eyebankwis.com",
    "wof:name":"Eyebank Of Wisconsin",
    "wof:placetype":"venue"
},
  "geometry": {"coordinates":[-89.352914,43.122491],"type":"Point"}
}