{
  "type": "Feature",
  "properties": {
    "addr:full":"1216 Lynne Dr Waukesha WI 53186",
    "addr:housenumber":"1216",
    "addr:postcode":"53186",
    "addr:street":"Lynne Dr",
    "iso:country":"US",
    "sg:address":"1216 Lynne Dr",
    "sg:city":"Waukesha",
    "sg:classifiers":[
        {
            "category":"Real Estate",
            "subcategory":"Architect",
            "type":"Services"
        }
    ],
    "sg:phone":"+1 262 521 3288",
    "sg:postcode":"53186",
    "sg:province":"WI",
    "sg:tags":[
        "architectural"
    ],
    "wof:name":"Hunter Hargreaves Archite",
    "wof:placetype":"venue"
},
  "geometry": {"coordinates":[-88.211275,42.993257],"type":"Point"}
}