{
  "type": "Feature",
  "properties": {
    "iso:country":"US",
    "sg:address":"265 5th St",
    "sg:city":"Prairie Du Sac",
    "sg:classifiers":[
        {
            "category":"Retail",
            "subcategory":"Car Wash",
            "type":"Services"
        }
    ],
    "sg:phone":"+1 608 643 6066",
    "sg:postcode":"53578",
    "sg:province":"WI",
    "sg:tags":[
        "automobile",
        "detail",
        "clean"
    ],
    "wof:name":"Finish Line Auto & Cycle",
    "wof:placetype":"venue"
},
  "geometry": {"coordinates":[-89.725064,43.286179],"type":"Point"}
}