{
  "type": "Feature",
  "properties": {
    "addr:full":"2511 E Belleview Pl Milwaukee WI 53211",
    "addr:housenumber":"2511",
    "addr:postcode":"53211",
    "addr:street":"E Belleview Pl",
    "iso:country":"US",
    "sg:address":"2511 E Belleview Pl",
    "sg:city":"Milwaukee",
    "sg:classifiers":[
        {
            "category":"Education",
            "subcategory":"Special Training",
            "type":"Public Place"
        }
    ],
    "sg:phone":"+1 414 962 7457",
    "sg:postcode":"53211",
    "sg:province":"WI",
    "wof:name":"Mark Nerzloff",
    "wof:placetype":"venue"
},
  "geometry": {"coordinates":[-87.878174,43.065999],"type":"Point"}
}