{
  "type": "Feature",
  "properties": {
    "iso:country":"US",
    "sg:address":"2578 Roosevelt Rd",
    "sg:city":"Marinette",
    "sg:classifiers":[
        {
            "category":"Building & Trades",
            "subcategory":"Construction",
            "type":"Services"
        }
    ],
    "sg:phone":"+1 715 735 6844",
    "sg:postcode":"54143",
    "sg:province":"WI",
    "sg:tags":[
        "contractor"
    ],
    "wof:name":"Duane Erickson Plastering",
    "wof:placetype":"venue"
},
  "geometry": {"coordinates":[-87.658165,45.055411],"type":"Point"}
}