{
  "type": "Feature",
  "properties": {
    "iso:country":"US",
    "sg:address":"2571 Mountford Rd",
    "sg:city":"Poynette",
    "sg:classifiers":[
        {
            "category":"Farming",
            "subcategory":"Farm",
            "type":"Manufacturing & Wholesale Goods"
        }
    ],
    "sg:phone":"+1 608 635 4337",
    "sg:postcode":"53955",
    "sg:province":"WI",
    "sg:tags":[
        "crop",
        "general"
    ],
    "wof:name":"Roger Mountford",
    "wof:placetype":"venue"
},
  "geometry": {"coordinates":[-89.303496,43.374622],"type":"Point"}
}