{
  "type": "Feature",
  "properties": {
    "iso:country":"US",
    "sg:address":"8112 W Bluemound Rd",
    "sg:city":"Milwaukee",
    "sg:classifiers":[
        {
            "category":"Professional",
            "subcategory":"Management & Consulting",
            "type":"Services"
        }
    ],
    "sg:phone":"+1 414 259 1047",
    "sg:postcode":"53213",
    "sg:province":"WI",
    "sg:tags":[
        "department",
        "marketing"
    ],
    "wof:name":"One Call Concepts Inc",
    "wof:placetype":"venue"
},
  "geometry": {"coordinates":[-88.01593,43.036076],"type":"Point"}
}