{
  "type": "Feature",
  "properties": {
    "iso:country":"US",
    "sg:address":"491 Mc Cutcheon Rd",
    "sg:city":"Hudson",
    "sg:classifiers":[
        {
            "category":"Real Estate",
            "subcategory":"Real Estate Operator",
            "type":"Services"
        }
    ],
    "sg:phone":"+1 715 386 6583",
    "sg:postcode":"54016",
    "sg:province":"WI",
    "sg:tags":[
        "building",
        "apartment"
    ],
    "wof:name":"Thomas J Apts Inc",
    "wof:placetype":"venue"
},
  "geometry": {"coordinates":[-92.702146,45.003318],"type":"Point"}
}