{
  "type": "Feature",
  "properties": {
    "addr:full":"4891 Escarpement Ter Sherwood WI 54169",
    "addr:postcode":"4891;54169",
    "addr:street":"Escarpement Ter",
    "iso:country":"US",
    "sg:address":"4891 Escarpement Ter",
    "sg:city":"Sherwood",
    "sg:classifiers":[
        {
            "category":"Personal",
            "type":"Services"
        }
    ],
    "sg:phone":"+1 920 989 1389",
    "sg:postcode":"54169",
    "sg:province":"WI",
    "wof:name":"Amma LLC",
    "wof:placetype":"venue"
},
  "geometry": {"coordinates":[-88.28010999999999,44.171288],"type":"Point"}
}