{
  "type": "Feature",
  "properties": {
    "iso:country":"US",
    "sg:address":"2724 S Quincy Ave",
    "sg:city":"Milwaukee",
    "sg:classifiers":[
        {
            "category":"Professional",
            "subcategory":"Business Services",
            "type":"Services"
        }
    ],
    "sg:phone":"+1 414 481 3350",
    "sg:postcode":"53207",
    "sg:province":"WI",
    "sg:tags":[
        "holding"
    ],
    "wof:name":"Girard D&J Holdings",
    "wof:placetype":"venue"
},
  "geometry": {"coordinates":[-87.90156500000001,42.995173],"type":"Point"}
}