{
  "type": "Feature",
  "properties": {
    "iso:country":"US",
    "sg:address":"14702 W National Ave",
    "sg:city":"New Berlin",
    "sg:classifiers":[
        {
            "category":"Personal",
            "subcategory":"Beauty Salon",
            "type":"Services"
        }
    ],
    "sg:phone":"+1 262 797 8483",
    "sg:postcode":"53151",
    "sg:province":"WI",
    "wof:name":"Lori's Wave Review",
    "wof:placetype":"venue"
},
  "geometry": {"coordinates":[-88.097069,42.983503],"type":"Point"}
}