{
  "type": "Feature",
  "properties": {
    "iso:country":"US",
    "sg:address":"2155 Terrebonne Dr",
    "sg:city":"Mosinee",
    "sg:classifiers":[
        {
            "category":"Communications",
            "subcategory":"Film & Video Production",
            "type":"Services"
        }
    ],
    "sg:phone":"+1 715 241 7316",
    "sg:postcode":"54455",
    "sg:province":"WI",
    "sg:tags":[
        "taping"
    ],
    "sg:website":"www.rucinskireetz.com",
    "wof:name":"Rucinski & Reetz Communication",
    "wof:placetype":"venue"
},
  "geometry": {"coordinates":[-89.624343,44.845473],"type":"Point"}
}