{
  "type": "Feature",
  "properties": {
    "iso:country":"US",
    "sg:address":"4475 Dorothy Jane Ct",
    "sg:city":"Kaukauna",
    "sg:classifiers":[
        {
            "category":"Building & Trades",
            "subcategory":"Construction",
            "type":"Services"
        }
    ],
    "sg:phone":"+1 920 788 4023",
    "sg:postcode":"54130",
    "sg:province":"WI",
    "sg:tags":[
        "general",
        "contractor"
    ],
    "wof:name":"Mark Vosters Construction",
    "wof:placetype":"venue"
},
  "geometry": {"coordinates":[-88.28228900000001,44.400456],"type":"Point"}
}