{
  "type": "Feature",
  "properties": {
    "iso:country":"US",
    "sg:address":"730 Superior St",
    "sg:city":"Wisconsin Dells",
    "sg:classifiers":[
        {
            "category":"Professional",
            "type":"Services"
        }
    ],
    "sg:phone":"+1 608 253 9116",
    "sg:postcode":"53965",
    "sg:province":"WI",
    "sg:tags":[
        "establishment"
    ],
    "wof:name":"JVL Net",
    "wof:placetype":"venue"
},
  "geometry": {"coordinates":[-89.775154,43.627194],"type":"Point"}
}