{
  "type": "Feature",
  "properties": {
    "addr:full":"448 Falcon Ridge Dr Burlington WI 53105",
    "addr:housenumber":"448",
    "addr:postcode":"53105",
    "addr:street":"Falcon Ridge Dr",
    "iso:country":"US",
    "sg:address":"448 Falcon Ridge Dr",
    "sg:city":"Burlington",
    "sg:classifiers":[
        {
            "category":"Professional",
            "subcategory":"Business Services",
            "type":"Services"
        }
    ],
    "sg:phone":"+1 262 767 9695",
    "sg:postcode":"53105",
    "sg:province":"WI",
    "wof:name":"Safe At Home Inspections",
    "wof:placetype":"venue"
},
  "geometry": {"coordinates":[-88.27111499999999,42.694736],"type":"Point"}
}