{
  "type": "Feature",
  "properties": {
    "iso:country":"US",
    "sg:address":"3541 S 79th St",
    "sg:city":"Milwaukee",
    "sg:classifiers":[
        {
            "category":"Personal",
            "type":"Services"
        }
    ],
    "sg:phone":"+1 414 727 0666",
    "sg:postcode":"53220",
    "sg:province":"WI",
    "sg:tags":[
        "butlers'",
        "maids'"
    ],
    "wof:name":"Golden Maid",
    "wof:placetype":"venue"
},
  "geometry": {"coordinates":[-88.011589,42.980099],"type":"Point"}
}