{
  "type": "Feature",
  "properties": {
    "iso:country":"US",
    "sg:address":"515 Howard Rd",
    "sg:city":"Whitewater",
    "sg:classifiers":[
        {
            "category":"Retail",
            "subcategory":"Auto Repair",
            "type":"Services"
        }
    ],
    "sg:phone":"+1 262 473 3131",
    "sg:postcode":"53190",
    "sg:province":"WI",
    "sg:tags":[
        "diesel"
    ],
    "wof:name":"Mfj Services",
    "wof:placetype":"venue"
},
  "geometry": {"coordinates":[-88.698942,42.846689],"type":"Point"}
}