{
  "type": "Feature",
  "properties": {
    "addr:full":"3320 N Ballard Rd Appleton WI 54911",
    "addr:housenumber":"3320",
    "addr:postcode":"54911",
    "addr:street":"N Ballard Rd",
    "iso:country":"US",
    "sg:address":"3320 N Ballard Rd",
    "sg:city":"Appleton",
    "sg:classifiers":[
        {
            "category":"Restaurant",
            "type":"Food & Drink"
        }
    ],
    "sg:phone":"+1 920 832 9696",
    "sg:postcode":"54911",
    "sg:province":"WI",
    "wof:name":"Mc Donald's",
    "wof:placetype":"venue"
},
  "geometry": {"coordinates":[-88.374865,44.290995],"type":"Point"}
}