{
  "type": "Feature",
  "properties": {
    "iso:country":"US",
    "sg:address":"4933 Reiner Rd",
    "sg:city":"Madison",
    "sg:classifiers":[
        {
            "category":"Freight",
            "type":"Transportation"
        }
    ],
    "sg:phone":"+1 608 663 9852",
    "sg:postcode":"53718",
    "sg:province":"WI",
    "sg:tags":[
        "operator",
        "trucking"
    ],
    "wof:name":"Chad Wood Trucking",
    "wof:placetype":"venue"
},
  "geometry": {"coordinates":[-89.266514,43.119266],"type":"Point"}
}