{
  "type": "Feature",
  "properties": {
    "iso:country":"US",
    "sg:address":"1111 N 7th St",
    "sg:city":"Sheboygan",
    "sg:classifiers":[
        {
            "category":"Shopping",
            "type":"Retail Goods"
        }
    ],
    "sg:phone":"+1 920 458 9033",
    "sg:postcode":"53081",
    "sg:province":"WI",
    "sg:tags":[
        "art",
        "gallery",
        "dealer"
    ],
    "wof:name":"Roger Lahm Art & Design Glry",
    "wof:placetype":"venue"
},
  "geometry": {"coordinates":[-87.711196,43.757319],"type":"Point"}
}