{
  "type": "Feature",
  "properties": {
    "iso:country":"US",
    "sg:address":"982 S Pine St",
    "sg:city":"Grantsburg",
    "sg:classifiers":[
        {
            "category":"Building & Trades",
            "subcategory":"Construction",
            "type":"Services"
        }
    ],
    "sg:phone":"+1 715 463 5687",
    "sg:postcode":"54840",
    "sg:province":"WI",
    "sg:tags":[
        "whitewashing"
    ],
    "wof:name":"Goepfert Whitewashing",
    "wof:placetype":"venue"
},
  "geometry": {"coordinates":[-92.68218,45.772869],"type":"Point"}
}