{
  "type": "Feature",
  "properties": {
    "addr:full":"2306 Kinzie Ave Racine WI 53405",
    "addr:housenumber":"2306",
    "addr:postcode":"53405",
    "addr:street":"Kinzie Ave",
    "iso:country":"US",
    "sg:address":"2306 Kinzie Ave",
    "sg:city":"Racine",
    "sg:classifiers":[
        {
            "category":"Building & Trades",
            "subcategory":"Construction",
            "type":"Services"
        }
    ],
    "sg:phone":"+1 262 638 2674",
    "sg:postcode":"53405",
    "sg:province":"WI",
    "sg:tags":[
        "painter"
    ],
    "wof:name":"Lasting Impressions",
    "wof:placetype":"venue"
},
  "geometry": {"coordinates":[-87.812074,42.722665],"type":"Point"}
}