{
  "type": "Feature",
  "properties": {
    "iso:country":"US",
    "sg:address":"111 W College Ave",
    "sg:city":"Appleton",
    "sg:classifiers":[
        {
            "category":"Professional",
            "subcategory":"Advertising",
            "type":"Services"
        }
    ],
    "sg:phone":"+1 920 738 9676",
    "sg:postcode":"54911",
    "sg:province":"WI",
    "sg:tags":[
        "counselor"
    ],
    "wof:name":"Prime Design",
    "wof:placetype":"venue"
},
  "geometry": {"coordinates":[-88.406742,44.261741],"type":"Point"}
}