{
  "type": "Feature",
  "properties": {
    "iso:country":"US",
    "sg:address":"10106 Co Rd Y",
    "sg:city":"Mazomanie",
    "sg:classifiers":[
        {
            "category":"Communications",
            "type":"Services"
        }
    ],
    "sg:phone":"+1 608 795 4208",
    "sg:postcode":"53560",
    "sg:province":"WI",
    "sg:tags":[
        "communication"
    ],
    "wof:name":"Gary Engberg Outdoors",
    "wof:placetype":"venue"
},
  "geometry": {"coordinates":[-89.767764,43.237072],"type":"Point"}
}