{
  "type": "Feature",
  "properties": {
    "iso:country":"US",
    "sg:address":"823 11th Ave",
    "sg:city":"Union Grove",
    "sg:classifiers":[
        {
            "category":"Restaurant",
            "type":"Food & Drink"
        }
    ],
    "sg:phone":"+1 262 878 1950",
    "sg:postcode":"53182",
    "sg:province":"WI",
    "sg:tags":[
        "eating"
    ],
    "wof:name":"Thyme Savers LLC",
    "wof:placetype":"venue"
},
  "geometry": {"coordinates":[-88.049618,42.686388],"type":"Point"}
}