{
  "type": "Feature",
  "properties": {
    "iso:country":"US",
    "sg:address":"4723 Chadwick St",
    "sg:city":"Schofield",
    "sg:classifiers":[
        {
            "category":"Professional",
            "subcategory":"Engineering",
            "type":"Services"
        }
    ],
    "sg:phone":"+1 715 355 2300",
    "sg:postcode":"54476",
    "sg:province":"WI",
    "wof:name":"Richard P Lucht",
    "wof:placetype":"venue"
},
  "geometry": {"coordinates":[-89.555678,44.913834],"type":"Point"}
}