{
  "type": "Feature",
  "properties": {
    "iso:country":"US",
    "sg:address":"2008 W Rawson Ave",
    "sg:city":"Oak Creek",
    "sg:classifiers":[
        {
            "category":"Real Estate",
            "subcategory":"Real Estate Agent",
            "type":"Services"
        }
    ],
    "sg:phone":"+1 414 761 7636",
    "sg:postcode":"53154",
    "sg:province":"WI",
    "wof:name":"North 29th Street Quad",
    "wof:placetype":"venue"
},
  "geometry": {"coordinates":[-87.94198299999999,42.916419],"type":"Point"}
}