{
  "type": "Feature",
  "properties": {
    "iso:country":"US",
    "sg:address":"120 Scott St",
    "sg:city":"Ripon",
    "sg:classifiers":[
        {
            "category":"Bars & Pubs",
            "type":"Food & Drink"
        }
    ],
    "sg:phone":"+1 920 748 8222",
    "sg:postcode":"54971",
    "sg:province":"WI",
    "wof:name":"Pastimes Pub/Grille",
    "wof:placetype":"venue"
},
  "geometry": {"coordinates":[-88.83842,43.845419],"type":"Point"}
}