{
  "type": "Feature",
  "properties": {
    "iso:country":"US",
    "sg:address":"732 S Park Ave",
    "sg:city":"Medford",
    "sg:classifiers":[
        {
            "category":"Retail",
            "subcategory":"Repair Shop",
            "type":"Services"
        }
    ],
    "sg:phone":"+1 715 748 2849",
    "sg:postcode":"54451",
    "sg:province":"WI",
    "wof:name":"Lee Paul Upholstery",
    "wof:placetype":"venue"
},
  "geometry": {"coordinates":[-90.346491,45.13011],"type":"Point"}
}