{
  "type": "Feature",
  "properties": {
    "iso:country":"US",
    "sg:address":"1996 Ebenezer Rd",
    "sg:city":"Fennimore",
    "sg:classifiers":[
        {
            "category":"Farming",
            "subcategory":"Dairy Farm",
            "type":"Manufacturing & Wholesale Goods"
        }
    ],
    "sg:phone":"+1 608 943 8135",
    "sg:postcode":"53809",
    "sg:province":"WI",
    "wof:name":"Walter Dresen",
    "wof:placetype":"venue"
},
  "geometry": {"coordinates":[-90.521639,42.951933],"type":"Point"}
}