{
  "type": "Feature",
  "properties": {
    "iso:country":"US",
    "sg:address":"301 River Dr",
    "sg:city":"Wausau",
    "sg:classifiers":[
        {
            "category":"Retail",
            "subcategory":"Auto Repair",
            "type":"Services"
        }
    ],
    "sg:phone":"+1 715 842 9211",
    "sg:postcode":"54403",
    "sg:province":"WI",
    "sg:tags":[
        "automobile",
        "used",
        "general"
    ],
    "wof:name":"S & W Auto & Truck Repair",
    "wof:placetype":"venue"
},
  "geometry": {"coordinates":[-89.63149,44.957393],"type":"Point"}
}