{
  "type": "Feature",
  "properties": {
    "iso:country":"US",
    "sg:address":"9899 Anglers Ave",
    "sg:city":"Tomahawk",
    "sg:classifiers":[
        {
            "category":"Travel",
            "subcategory":"Hotels & Motels",
            "type":"Entertainment"
        },
        {
            "category":"Restaurant",
            "type":"Food & Drink"
        }
    ],
    "sg:phone":"+1 715 453 7515",
    "sg:postcode":"54487",
    "sg:province":"WI",
    "sg:tags":[
        "breakfast",
        "eating",
        "accommodation",
        "bed"
    ],
    "wof:name":"Eagles Rest Bed & Breakfast LL",
    "wof:placetype":"venue"
},
  "geometry": {"coordinates":[-89.62505,45.475203],"type":"Point"}
}