{
  "type": "Feature",
  "properties": {
    "iso:country":"US",
    "sg:address":"1770 530th Ave",
    "sg:city":"Menomonie",
    "sg:classifiers":[
        {
            "category":"Farming",
            "subcategory":"Dairy Farm",
            "type":"Manufacturing & Wholesale Goods"
        }
    ],
    "sg:phone":"+1 715 235 6184",
    "sg:postcode":"54751",
    "sg:province":"WI",
    "wof:name":"Kevin Rogers",
    "wof:placetype":"venue"
},
  "geometry": {"coordinates":[-92.062985,44.868652],"type":"Point"}
}