{
  "type": "Feature",
  "properties": {
    "iso:country":"US",
    "sg:address":"8942 Gray Lake Rd",
    "sg:city":"Gillett",
    "sg:classifiers":[
        {
            "category":"Home & Garden",
            "subcategory":"Furniture",
            "type":"Retail Goods"
        }
    ],
    "sg:phone":"+1 920 848 7978",
    "sg:postcode":"54124",
    "sg:province":"WI",
    "sg:tags":[
        "cabinet"
    ],
    "wof:name":"Northern Woods Cabinetry",
    "wof:placetype":"venue"
},
  "geometry": {"coordinates":[-88.204312,44.880848],"type":"Point"}
}