{
  "type": "Feature",
  "properties": {
    "iso:country":"US",
    "sg:address":"5502 170th Ave",
    "sg:city":"Bay City",
    "sg:classifiers":[
        {
            "category":"Building & Trades",
            "subcategory":"Construction",
            "type":"Services"
        }
    ],
    "sg:phone":"+1 715 594 3132",
    "sg:postcode":"54723",
    "sg:province":"WI",
    "sg:tags":[
        "builder",
        "operative"
    ],
    "wof:name":"Home Maintenance Company",
    "wof:placetype":"venue"
},
  "geometry": {"coordinates":[-92.402746,44.601788],"type":"Point"}
}