{
  "type": "Feature",
  "properties": {
    "iso:country":"US",
    "sg:address":"950 Queoff St",
    "sg:city":"Green Bay",
    "sg:classifiers":[
        {
            "category":"Professional",
            "subcategory":"Computer Services",
            "type":"Services"
        }
    ],
    "sg:phone":"+1 920 468 9299",
    "sg:postcode":"54311",
    "sg:province":"WI",
    "sg:tags":[
        "programing",
        "custom"
    ],
    "wof:name":"Digital Design Services Inc",
    "wof:placetype":"venue"
},
  "geometry": {"coordinates":[-87.940983,44.516208],"type":"Point"}
}