{
  "type": "Feature",
  "properties": {
    "iso:country":"US",
    "sg:address":"3445 Cottage Grove Rd",
    "sg:city":"Madison",
    "sg:classifiers":[
        {
            "category":"Manufacturing",
            "subcategory":"Signs",
            "type":"Manufacturing & Wholesale Goods"
        }
    ],
    "sg:phone":"+1 608 224 0105",
    "sg:postcode":"53718",
    "sg:province":"WI",
    "wof:name":"Sign Service Specialist",
    "wof:placetype":"venue"
},
  "geometry": {"coordinates":[-89.26679,43.084896],"type":"Point"}
}