{
  "type": "Feature",
  "properties": {
    "iso:country":"US",
    "sg:address":"939 N Carnot Rd",
    "sg:city":"Forestville",
    "sg:classifiers":[
        {
            "category":"Retail",
            "subcategory":"Auto Repair",
            "type":"Services"
        }
    ],
    "sg:phone":"+1 920 743 1371",
    "sg:postcode":"54213",
    "sg:province":"WI",
    "sg:tags":[
        "general"
    ],
    "wof:name":"Garys Auto Repair",
    "wof:placetype":"venue"
},
  "geometry": {"coordinates":[-87.418076,44.712891],"type":"Point"}
}