{
  "type": "Feature",
  "properties": {
    "iso:country":"US",
    "sg:address":"822 Rotering Ridge Rd",
    "sg:city":"Cochrane",
    "sg:classifiers":[
        {
            "category":"Farming",
            "subcategory":"Dairy Farm",
            "type":"Manufacturing & Wholesale Goods"
        }
    ],
    "sg:phone":"+1 608 626 3751",
    "sg:postcode":"54622",
    "sg:province":"WI",
    "wof:name":"Martin Ehrat",
    "wof:placetype":"venue"
},
  "geometry": {"coordinates":[-91.699442,44.290372],"type":"Point"}
}