{
  "type": "Feature",
  "properties": {
    "iso:country":"US",
    "sg:address":"5600 W Brown Deer Rd",
    "sg:city":"Milwaukee",
    "sg:phone":"+1 414 365 3003",
    "sg:postcode":"53223",
    "sg:province":"WI",
    "wof:name":"Art Of Wellness Chiroprac",
    "wof:placetype":"venue"
},
  "geometry": {"coordinates":[-87.98098400000001,43.177792],"type":"Point"}
}