{
  "type": "Feature",
  "properties": {
    "addr:full":"94 Stoddart St Beaver Dam WI 53916",
    "addr:housenumber":"94",
    "addr:postcode":"53916",
    "addr:street":"Stoddart St",
    "iso:country":"US",
    "sg:address":"94 Stoddart St",
    "sg:city":"Beaver Dam",
    "sg:classifiers":[
        {
            "category":"Insurance",
            "subcategory":"Insurance Agent",
            "type":"Services"
        }
    ],
    "sg:phone":"+1 920 887 3033",
    "sg:postcode":"53916",
    "sg:province":"WI",
    "wof:name":"American Family Insurance",
    "wof:placetype":"venue"
},
  "geometry": {"coordinates":[-88.82850999999999,43.469207],"type":"Point"}
}