{
  "type": "Feature",
  "properties": {
    "iso:country":"US",
    "sg:address":"309 Clyde Gallagher Ave",
    "sg:city":"Madison",
    "sg:classifiers":[
        {
            "category":"Real Estate",
            "subcategory":"Real Estate Operator",
            "type":"Services"
        }
    ],
    "sg:phone":"+1 608 244 7601",
    "sg:postcode":"53714",
    "sg:province":"WI",
    "sg:tags":[
        "building",
        "apartment"
    ],
    "wof:name":"Eastpointe Apartments",
    "wof:placetype":"venue"
},
  "geometry": {"coordinates":[-89.339969,43.102598],"type":"Point"}
}