{
  "type": "Feature",
  "properties": {
    "iso:country":"US",
    "sg:address":"209 N Main St",
    "sg:city":"Burlington",
    "sg:classifiers":[
        {
            "category":"Professional",
            "subcategory":"Employment Agencies",
            "type":"Services"
        }
    ],
    "sg:phone":"+1 262 767 2901",
    "sg:postcode":"53105",
    "sg:province":"WI",
    "wof:name":"Racine County Workforce Development Center",
    "wof:placetype":"venue"
},
  "geometry": {"coordinates":[-88.27040100000001,42.679798],"type":"Point"}
}