{
  "type": "Feature",
  "properties": {
    "iso:country":"US",
    "sg:address":"206 E Upham St",
    "sg:city":"Marshfield",
    "sg:classifiers":[
        {
            "category":"Health Services",
            "subcategory":"Doctor",
            "type":"Services"
        }
    ],
    "sg:phone":"+1 715 387 4818",
    "sg:postcode":"54449",
    "sg:province":"WI",
    "sg:tags":[
        "medicine",
        "injury",
        "sport"
    ],
    "wof:name":"Healthsouth Sports Medicine",
    "wof:placetype":"venue"
},
  "geometry": {"coordinates":[-90.162199,44.680356],"type":"Point"}
}