{
  "type": "Feature",
  "properties": {
    "iso:country":"US",
    "sg:address":"502 S Midvale Blvd",
    "sg:city":"Madison",
    "sg:classifiers":[
        {
            "category":"Building & Trades",
            "subcategory":"Plumbing",
            "type":"Services"
        }
    ],
    "sg:phone":"+1 608 238 7016",
    "sg:postcode":"53711",
    "sg:province":"WI",
    "sg:tags":[
        "conditioning",
        "air",
        "system",
        "contractor"
    ],
    "wof:name":"Arnies Heating & Air Condition",
    "wof:placetype":"venue"
},
  "geometry": {"coordinates":[-89.451193,43.05361],"type":"Point"}
}