{
  "type": "Feature",
  "properties": {
    "iso:country":"US",
    "sg:address":"2341 W Acacia Rd",
    "sg:city":"Milwaukee",
    "sg:classifiers":[
        {
            "category":"Professional",
            "subcategory":"Computer Services",
            "type":"Services"
        }
    ],
    "sg:phone":"+1 414 247 1919",
    "sg:postcode":"53209",
    "sg:province":"WI",
    "sg:tags":[
        "internet",
        "programing",
        "custom"
    ],
    "sg:website":"www.cornerstonecs.com",
    "wof:name":"Cornerstone Computer Solutions",
    "wof:placetype":"venue"
},
  "geometry": {"coordinates":[-87.942457,43.137953],"type":"Point"}
}