{
  "type": "Feature",
  "properties": {
    "iso:country":"US",
    "sg:address":"14775 W Beechwood Ave",
    "sg:city":"Brookfield",
    "sg:classifiers":[
        {
            "category":"Communications",
            "subcategory":"Film & Video Production",
            "type":"Services"
        }
    ],
    "sg:phone":"+1 262 786 0492",
    "sg:postcode":"53005",
    "sg:province":"WI",
    "sg:tags":[
        "motion",
        "picture"
    ],
    "wof:name":"Conference Plus",
    "wof:placetype":"venue"
},
  "geometry": {"coordinates":[-88.096335,43.027533],"type":"Point"}
}