{
  "type": "Feature",
  "properties": {
    "iso:country":"US",
    "sg:address":"5698 N Water Dr",
    "sg:city":"Manawa",
    "sg:classifiers":[
        {
            "category":"Real Estate",
            "subcategory":"Real Estate Agent",
            "type":"Services"
        }
    ],
    "sg:phone":"+1 920 596 3831",
    "sg:postcode":"54949",
    "sg:province":"WI",
    "wof:name":"Ann Filips Realty",
    "wof:placetype":"venue"
},
  "geometry": {"coordinates":[-88.942243,44.424655],"type":"Point"}
}