{
  "type": "Feature",
  "properties": {
    "iso:country":"US",
    "sg:address":"3405 Stewart Ave",
    "sg:city":"Wausau",
    "sg:classifiers":[
        {
            "category":"Autos & Motor Vehicles",
            "subcategory":"Automobile Sales",
            "type":"Retail Goods"
        }
    ],
    "sg:phone":"+1 715 842 2131",
    "sg:postcode":"54401",
    "sg:province":"WI",
    "sg:tags":[
        "car",
        "dealer"
    ],
    "wof:name":"O'Malley Oldsmobile Cadillac",
    "wof:placetype":"venue"
},
  "geometry": {"coordinates":[-89.680914,44.955258],"type":"Point"}
}