{
  "type": "Feature",
  "properties": {
    "iso:country":"US",
    "sg:address":"7860 State Rd 67",
    "sg:city":"Mayville",
    "sg:classifiers":[
        {
            "category":"Retail",
            "subcategory":"Veterinary Services",
            "type":"Services"
        }
    ],
    "sg:phone":"+1 920 387 4191",
    "sg:postcode":"53050",
    "sg:province":"WI",
    "sg:tags":[
        "veterinarian"
    ],
    "wof:name":"Mayville Animal Clinic",
    "wof:placetype":"venue"
},
  "geometry": {"coordinates":[-88.546026,43.474157],"type":"Point"}
}