{
  "type": "Feature",
  "properties": {
    "iso:country":"US",
    "sg:address":"4225 Main St",
    "sg:city":"Fish Creek",
    "sg:classifiers":[
        {
            "category":"Travel",
            "subcategory":"Hotels & Motels",
            "type":"Entertainment"
        }
    ],
    "sg:phone":"+1 920 868 3517",
    "sg:postcode":"54212",
    "sg:province":"WI",
    "sg:website":"www.whitegullinn.com",
    "wof:name":"White Gull Inn",
    "wof:placetype":"venue"
},
  "geometry": {"coordinates":[-87.25100500000001,45.128602],"type":"Point"}
}