{
  "type": "Feature",
  "properties": {
    "iso:country":"US",
    "sg:address":"202 Wood St",
    "sg:city":"Rothschild",
    "sg:classifiers":[
        {
            "category":"Real Estate",
            "subcategory":"Real Estate Agent",
            "type":"Services"
        }
    ],
    "sg:phone":"+1 715 581 4021",
    "sg:postcode":"54474",
    "sg:province":"WI",
    "wof:name":"Keystone Realestate",
    "wof:placetype":"venue"
},
  "geometry": {"coordinates":[-89.613831,44.889434],"type":"Point"}
}