{
  "type": "Feature",
  "properties": {
    "iso:country":"US",
    "sg:address":"3757 E Washington Ave",
    "sg:city":"Madison",
    "sg:classifiers":[
        {
            "category":"Retail",
            "subcategory":"Auto Repair",
            "type":"Services"
        }
    ],
    "sg:phone":"+1 608 241 3818",
    "sg:postcode":"53704",
    "sg:province":"WI",
    "sg:tags":[
        "exhaust"
    ],
    "wof:name":"Midas Muffler",
    "wof:placetype":"venue"
},
  "geometry": {"coordinates":[-89.325243,43.116363],"type":"Point"}
}