{
  "type": "Feature",
  "properties": {
    "iso:country":"US",
    "sg:address":"1111 Willow Ln",
    "sg:city":"Madison",
    "sg:classifiers":[
        {
            "category":"Social Services",
            "type":"Services"
        }
    ],
    "sg:phone":"+1 608 233 6979",
    "sg:postcode":"53705",
    "sg:province":"WI",
    "sg:tags":[
        "organization",
        "welfare"
    ],
    "wof:name":"Link Friendship House",
    "wof:placetype":"venue"
},
  "geometry": {"coordinates":[-89.489895,43.078818],"type":"Point"}
}