{
  "type": "Feature",
  "properties": {
    "iso:country":"US",
    "sg:address":"4358 Happy Hollow Ln",
    "sg:city":"Racine",
    "sg:classifiers":[
        {
            "category":"Manufacturing",
            "subcategory":"Rubber & Plastics",
            "type":"Manufacturing & Wholesale Goods"
        }
    ],
    "sg:phone":"+1 262 554 8178",
    "sg:postcode":"53403",
    "sg:province":"WI",
    "sg:tags":[
        "item",
        "gift",
        "mfg"
    ],
    "wof:name":"Carolcraft",
    "wof:placetype":"venue"
},
  "geometry": {"coordinates":[-87.849,42.68094],"type":"Point"}
}