{
  "type": "Feature",
  "properties": {
    "addr:full":"1135 Co Rd D Nekoosa WI 54457",
    "addr:housenumber":"1135",
    "addr:postcode":"54457",
    "addr:street":"Co Rd D",
    "iso:country":"US",
    "sg:address":"1135 Co Rd D",
    "sg:city":"Nekoosa",
    "sg:classifiers":[
        {
            "category":"Building & Trades",
            "subcategory":"Landscaping Services",
            "type":"Services"
        }
    ],
    "sg:phone":"+1 715 325 3915",
    "sg:postcode":"54457",
    "sg:province":"WI",
    "sg:tags":[
        "lawn",
        "maintenance",
        "grounds"
    ],
    "wof:name":"Green's Garden & Lawn Ctr",
    "wof:placetype":"venue"
},
  "geometry": {"coordinates":[-89.803517,44.220652],"type":"Point"}
}