{
  "type": "Feature",
  "properties": {
    "iso:country":"US",
    "sg:address":"2178 Goose Lake Rd",
    "sg:city":"New Richmond",
    "sg:classifiers":[
        {
            "category":"Professional",
            "subcategory":"Business Services",
            "type":"Services"
        }
    ],
    "sg:phone":"+1 715 248 4888",
    "sg:postcode":"54017",
    "sg:province":"WI",
    "sg:tags":[
        "embroidery"
    ],
    "wof:name":"Designer Logo Inc",
    "wof:placetype":"venue"
},
  "geometry": {"coordinates":[-92.585932,45.176604],"type":"Point"}
}