{
  "type": "Feature",
  "properties": {
    "iso:country":"US",
    "sg:address":"700 N Koeller St",
    "sg:city":"Oshkosh",
    "sg:classifiers":[
        {
            "category":"Restaurant",
            "type":"Food & Drink"
        }
    ],
    "sg:phone":"+1 920 233 2847",
    "sg:postcode":"54902",
    "sg:province":"WI",
    "wof:name":"Los Compadres",
    "wof:placetype":"venue"
},
  "geometry": {"coordinates":[-88.581408,44.026275],"type":"Point"}
}