{
  "type": "Feature",
  "properties": {
    "iso:country":"US",
    "sg:address":"75 2nd Ave",
    "sg:city":"Clear Lake",
    "sg:classifiers":[
        {
            "category":"Farming",
            "subcategory":"Farm",
            "type":"Manufacturing & Wholesale Goods"
        }
    ],
    "sg:phone":"+1 715 263 3458",
    "sg:postcode":"54005",
    "sg:province":"WI",
    "wof:name":"Streif Farms",
    "wof:placetype":"venue"
},
  "geometry": {"coordinates":[-92.147568,45.238345],"type":"Point"}
}