{
  "type": "Feature",
  "properties": {
    "iso:country":"US",
    "sg:address":"2162 S Ridge Rd",
    "sg:city":"Green Bay",
    "sg:classifiers":[
        {
            "category":"Retail",
            "subcategory":"Repair Shop",
            "type":"Services"
        }
    ],
    "sg:phone":"+1 920 429 1000",
    "sg:postcode":"54304",
    "sg:province":"WI",
    "sg:tags":[
        "picture",
        "framing"
    ],
    "wof:name":"Framemakers",
    "wof:placetype":"venue"
},
  "geometry": {"coordinates":[-88.06922400000001,44.495523],"type":"Point"}
}