{
  "type": "Feature",
  "properties": {
    "iso:country":"US",
    "sg:address":"324 E Michigan St",
    "sg:city":"Milwaukee",
    "sg:classifiers":[
        {
            "category":"Restaurant",
            "type":"Food & Drink"
        }
    ],
    "sg:phone":"+1 414 277 7687",
    "sg:postcode":"53202",
    "sg:province":"WI",
    "wof:name":"Soup House Inc",
    "wof:placetype":"venue"
},
  "geometry": {"coordinates":[-87.90669800000001,43.037563],"type":"Point"}
}