{
  "type": "Feature",
  "properties": {
    "iso:country":"US",
    "sg:address":"12580 W Rohr Ave",
    "sg:city":"Butler",
    "sg:classifiers":[
        {
            "category":"Wholesale",
            "subcategory":"Home Furnishings",
            "type":"Manufacturing & Wholesale Goods"
        }
    ],
    "sg:phone":"+1 262 781 5321",
    "sg:postcode":"53007",
    "sg:province":"WI",
    "sg:tags":[
        "mat",
        "matting"
    ],
    "wof:name":"Packerland Rent-A-Mat Inc",
    "wof:placetype":"venue"
},
  "geometry": {"coordinates":[-88.067057,43.113549],"type":"Point"}
}