{
  "type": "Feature",
  "properties": {
    "addr:full":"17 Park Pl Appleton WI 54914",
    "addr:housenumber":"17",
    "addr:postcode":"54914",
    "addr:street":"Park Pl",
    "iso:country":"US",
    "sg:address":"17 Park Pl",
    "sg:city":"Appleton",
    "sg:classifiers":[
        {
            "category":"Wholesale",
            "subcategory":"Non-durable Goods",
            "type":"Manufacturing & Wholesale Goods"
        }
    ],
    "sg:phone":"+1 920 731 8732",
    "sg:postcode":"54914",
    "sg:province":"WI",
    "sg:tags":[
        "advertising"
    ],
    "wof:name":"Real Estate Book",
    "wof:placetype":"venue"
},
  "geometry": {"coordinates":[-88.467935,44.256843],"type":"Point"}
}