{
  "type": "Feature",
  "properties": {
    "iso:country":"US",
    "sg:address":"440 14th St",
    "sg:city":"Dallas",
    "sg:classifiers":[
        {
            "category":"Freight",
            "type":"Transportation"
        }
    ],
    "sg:phone":"+1 715 837 1409",
    "sg:postcode":"54733",
    "sg:province":"WI",
    "sg:tags":[
        "consultant",
        "customs"
    ],
    "wof:name":"A B Seeds",
    "wof:placetype":"venue"
},
  "geometry": {"coordinates":[-91.870352,45.271392],"type":"Point"}
}