{
  "type": "Feature",
  "properties": {
    "iso:country":"US",
    "sg:address":"430 Kimberly Dr",
    "sg:city":"Waukesha",
    "sg:classifiers":[
        {
            "category":"Professional",
            "type":"Services"
        }
    ],
    "sg:phone":"+1 262 544 0490",
    "sg:postcode":"53188",
    "sg:province":"WI",
    "wof:name":"Information Works",
    "wof:placetype":"venue"
},
  "geometry": {"coordinates":[-88.248125,43.018883],"type":"Point"}
}