{
  "type": "Feature",
  "properties": {
    "addr:full":"2817 Fish Hatchery Rd Fitchburg WI 53713",
    "addr:housenumber":"2817",
    "addr:postcode":"53713",
    "addr:street":"Fish Hatchery Rd",
    "iso:country":"US",
    "sg:address":"2817 Fish Hatchery Rd",
    "sg:city":"Fitchburg",
    "sg:classifiers":[
        {
            "category":"Professional",
            "subcategory":"Lawyer & Legal Services",
            "type":"Services"
        }
    ],
    "sg:phone":"+1 608 288 7859",
    "sg:postcode":"53713",
    "sg:province":"WI",
    "sg:tags":[
        "attorney"
    ],
    "wof:name":"Scott E Mickelson",
    "wof:placetype":"venue"
},
  "geometry": {"coordinates":[-89.410372,43.029545],"type":"Point"}
}