{
  "type": "Feature",
  "properties": {
    "iso:country":"US",
    "sg:address":"5228 N Hopkins St",
    "sg:city":"Milwaukee",
    "sg:classifiers":[
        {
            "category":"Wholesale",
            "subcategory":"Chemicals & Plastics",
            "type":"Manufacturing & Wholesale Goods"
        }
    ],
    "sg:phone":"+1 414 461 4000",
    "sg:postcode":"53209",
    "sg:province":"WI",
    "sg:tags":[
        "product",
        "allied"
    ],
    "wof:name":"Hercules Inc",
    "wof:placetype":"venue"
},
  "geometry": {"coordinates":[-87.964159,43.114208],"type":"Point"}
}