{
  "type": "Feature",
  "properties": {
    "iso:country":"US",
    "sg:address":"1917 E Milwaukee St",
    "sg:city":"Janesville",
    "sg:classifiers":[
        {
            "category":"Health Services",
            "subcategory":"Doctor",
            "type":"Services"
        }
    ],
    "sg:phone":"+1 608 754 2554",
    "sg:postcode":"53545",
    "sg:province":"WI",
    "sg:tags":[
        "dentist"
    ],
    "wof:name":"James C Behm Inc",
    "wof:placetype":"venue"
},
  "geometry": {"coordinates":[-88.997214,42.692679],"type":"Point"}
}