{
  "type": "Feature",
  "properties": {
    "addr:full":"2957 Zoromski Rd Mosinee WI 54455",
    "addr:housenumber":"2957",
    "addr:postcode":"54455",
    "addr:street":"Zoromski Rd",
    "iso:country":"US",
    "sg:address":"2957 Zoromski Rd",
    "sg:city":"Mosinee",
    "sg:classifiers":[
        {
            "category":"Autos & Motor Vehicles",
            "subcategory":"Auto Supplies",
            "type":"Retail Goods"
        }
    ],
    "sg:phone":"+1 715 693 4282",
    "sg:postcode":"54455",
    "sg:province":"WI",
    "sg:tags":[
        "automobile"
    ],
    "wof:name":"Valhalla Engineering",
    "wof:placetype":"venue"
},
  "geometry": {"coordinates":[-89.572487,44.692796],"type":"Point"}
}