{
  "type": "Feature",
  "properties": {
    "addr:full":"8957 Pickeral Jay Rd East Troy WI 53120",
    "addr:housenumber":"8957",
    "addr:postcode":"53120",
    "addr:street":"Pickeral Jay Rd",
    "iso:country":"US",
    "sg:address":"8957 Pickeral Jay Rd",
    "sg:city":"East Troy",
    "sg:classifiers":[
        {
            "category":"Organizations",
            "subcategory":"Community Association",
            "type":"Services"
        }
    ],
    "sg:phone":"+1 262 642 7276",
    "sg:postcode":"53120",
    "sg:province":"WI",
    "sg:tags":[
        "environmental",
        "org"
    ],
    "wof:name":"Nature Conservancy",
    "wof:placetype":"venue"
},
  "geometry": {"coordinates":[-88.438029,42.818644],"type":"Point"}
}