{
  "type": "Feature",
  "properties": {
    "iso:country":"US",
    "sg:address":"977 Ashwaubenon St",
    "sg:city":"Green Bay",
    "sg:classifiers":[
        {
            "category":"Manufacturing",
            "subcategory":"Metals",
            "type":"Manufacturing & Wholesale Goods"
        }
    ],
    "sg:phone":"+1 920 336 5446",
    "sg:postcode":"54304",
    "sg:province":"WI",
    "sg:tags":[
        "assembly",
        "fabrication"
    ],
    "wof:name":"Fabrication Express LLC",
    "wof:placetype":"venue"
},
  "geometry": {"coordinates":[-88.090368,44.464287],"type":"Point"}
}