{
  "type": "Feature",
  "properties": {
    "iso:country":"US",
    "sg:address":"722 Pleasant Oak Dr",
    "sg:city":"Oregon",
    "sg:classifiers":[
        {
            "category":"Professional",
            "subcategory":"Management & Consulting",
            "type":"Services"
        }
    ],
    "sg:phone":"+1 608 835 3969",
    "sg:postcode":"53575",
    "sg:province":"WI",
    "sg:tags":[
        "business"
    ],
    "wof:name":"LLC Keller Mc Co",
    "wof:placetype":"venue"
},
  "geometry": {"coordinates":[-89.378485,42.911817],"type":"Point"}
}