{
  "type": "Feature",
  "properties": {
    "iso:country":"US",
    "sg:address":"315 S Elm St",
    "sg:city":"Oconomowoc",
    "sg:classifiers":[
        {
            "category":"Building & Trades",
            "subcategory":"Construction",
            "type":"Services"
        }
    ],
    "sg:phone":"+1 262 569 1245",
    "sg:postcode":"53066",
    "sg:province":"WI",
    "sg:tags":[
        "painter"
    ],
    "wof:name":"Mer Enterprises LTD",
    "wof:placetype":"venue"
},
  "geometry": {"coordinates":[-88.513352,43.108734],"type":"Point"}
}