{
  "type": "Feature",
  "properties": {
    "addr:full":"8053 State Hwy 33 Beaver Dam WI 53916",
    "addr:housenumber":"8053",
    "addr:postcode":"53916",
    "addr:street":"State Hwy 33",
    "iso:country":"US",
    "sg:address":"8053 State Hwy 33",
    "sg:city":"Beaver Dam",
    "sg:classifiers":[
        {
            "category":"Social Services",
            "type":"Services"
        }
    ],
    "sg:phone":"+1 920 885 4144",
    "sg:postcode":"53916",
    "sg:province":"WI",
    "sg:tags":[
        "care",
        "center",
        "day"
    ],
    "wof:name":"Golden Care Adult Day Center",
    "wof:placetype":"venue"
},
  "geometry": {"coordinates":[-88.80292799999999,43.452741],"type":"Point"}
}