{
  "type": "Feature",
  "properties": {
    "iso:country":"US",
    "sg:address":"2112 Rudolph Rd",
    "sg:city":"Eau Claire",
    "sg:classifiers":[
        {
            "category":"Organizations",
            "subcategory":"Religious Organization",
            "type":"Services"
        }
    ],
    "sg:phone":"+1 715 832 1011",
    "sg:postcode":"54701",
    "sg:province":"WI",
    "sg:tags":[
        "church"
    ],
    "wof:name":"First Presbyterian Church Inc",
    "wof:placetype":"venue"
},
  "geometry": {"coordinates":[-91.47852899999999,44.796516],"type":"Point"}
}