{
  "type": "Feature",
  "properties": {
    "iso:country":"US",
    "sg:address":"5309 38th Ave",
    "sg:city":"Kenosha",
    "sg:classifiers":[
        {
            "category":"Shopping",
            "subcategory":"Beauty & Cosmetics",
            "type":"Retail Goods"
        }
    ],
    "sg:phone":"+1 262 654 7928",
    "sg:postcode":"53144",
    "sg:province":"WI",
    "sg:tags":[
        "merchandise"
    ],
    "wof:name":"Sales Director Mary Kay Pdts",
    "wof:placetype":"venue"
},
  "geometry": {"coordinates":[-87.854512,42.585609],"type":"Point"}
}