{
  "type": "Feature",
  "properties": {
    "iso:country":"US",
    "sg:address":"1295 Ridgeway St",
    "sg:city":"Hammond",
    "sg:classifiers":[
        {
            "category":"Organizations",
            "subcategory":"Religious Organization",
            "type":"Services"
        }
    ],
    "sg:phone":"+1 715 796 2244",
    "sg:postcode":"54015",
    "sg:province":"WI",
    "sg:tags":[
        "church"
    ],
    "wof:name":"Immaculate Conception Parish",
    "wof:placetype":"venue"
},
  "geometry": {"coordinates":[-92.438347,44.973098],"type":"Point"}
}