{
  "type": "Feature",
  "properties": {
    "iso:country":"US",
    "sg:address":"1761 W Paulson Rd",
    "sg:city":"Green Bay",
    "sg:classifiers":[
        {
            "category":"Building & Trades",
            "subcategory":"Electrical",
            "type":"Services"
        }
    ],
    "sg:phone":"+1 920 490 0706",
    "sg:postcode":"54313",
    "sg:province":"WI",
    "sg:tags":[
        "installation"
    ],
    "wof:name":"Precision Installation",
    "wof:placetype":"venue"
},
  "geometry": {"coordinates":[-88.109736,44.488421],"type":"Point"}
}