{
  "type": "Feature",
  "properties": {
    "iso:country":"US",
    "sg:address":"512 Mary Knoll Ln",
    "sg:city":"Watertown",
    "sg:classifiers":[
        {
            "category":"Building & Trades",
            "subcategory":"Landscaping Services",
            "type":"Services"
        }
    ],
    "sg:phone":"+1 920 262 8319",
    "sg:postcode":"53098",
    "sg:province":"WI",
    "sg:tags":[
        "landscape"
    ],
    "wof:name":"DJS Landscape Contractor LLC",
    "wof:placetype":"venue"
},
  "geometry": {"coordinates":[-88.744954,43.201713],"type":"Point"}
}