{
  "type": "Feature",
  "properties": {
    "addr:full":"5509 W Center St Milwaukee WI 53210",
    "addr:housenumber":"5509",
    "addr:postcode":"53210",
    "addr:street":"W Center St",
    "iso:country":"US",
    "sg:address":"5509 W Center St",
    "sg:city":"Milwaukee",
    "sg:classifiers":[
        {
            "category":"Social Services",
            "subcategory":"Child Care",
            "type":"Services"
        }
    ],
    "sg:phone":"+1 414 444 6123",
    "sg:postcode":"53210",
    "sg:province":"WI",
    "wof:name":"Little Rascals Child Academy",
    "wof:placetype":"venue"
},
  "geometry": {"coordinates":[-87.98325,43.067933],"type":"Point"}
}