{
  "type": "Feature",
  "properties": {
    "iso:country":"US",
    "sg:address":"2520 Easlan Dr",
    "sg:city":"Plover",
    "sg:classifiers":[
        {
            "category":"Freight",
            "type":"Transportation"
        }
    ],
    "sg:phone":"+1 715 344 3594",
    "sg:postcode":"54467",
    "sg:province":"WI",
    "sg:tags":[
        "operator",
        "trucking"
    ],
    "wof:name":"B&K Transport",
    "wof:placetype":"venue"
},
  "geometry": {"coordinates":[-89.529583,44.460952],"type":"Point"}
}