{
  "type": "Feature",
  "properties": {
    "addr:full":"9672 Co Hwy U Elcho WI 54428",
    "addr:housenumber":"9672",
    "addr:postcode":"54428",
    "addr:street":"Co Hwy U Elcho",
    "iso:country":"US",
    "sg:address":"9672 Co Hwy U",
    "sg:city":"Elcho",
    "sg:classifiers":[
        {
            "category":"Building & Trades",
            "subcategory":"Construction",
            "type":"Services"
        }
    ],
    "sg:phone":"+1 715 275 3681",
    "sg:postcode":"54428",
    "sg:province":"WI",
    "sg:tags":[
        "dry wall",
        "contractor"
    ],
    "wof:name":"Shane's Dry Wall Co",
    "wof:placetype":"venue"
},
  "geometry": {"coordinates":[-89.123563,45.415819],"type":"Point"}
}