{
  "type": "Feature",
  "properties": {
    "iso:country":"US",
    "sg:address":"163 S Main St",
    "sg:city":"Amherst",
    "sg:classifiers":[
        {
            "category":"Real Estate",
            "subcategory":"Real Estate Agent",
            "type":"Services"
        }
    ],
    "sg:phone":"+1 715 824 3789",
    "sg:postcode":"54406",
    "sg:province":"WI",
    "wof:name":"O K Realty",
    "wof:placetype":"venue"
},
  "geometry": {"coordinates":[-89.285184,44.450267],"type":"Point"}
}