{
  "type": "Feature",
  "properties": {
    "iso:country":"US",
    "sg:address":"656 Moon Rd",
    "sg:city":"Mosinee",
    "sg:classifiers":[
        {
            "category":"Wholesale",
            "subcategory":"Construction Materials",
            "type":"Manufacturing & Wholesale Goods"
        },
        {
            "category":"Home & Garden",
            "subcategory":"Building Materials",
            "type":"Retail Goods"
        }
    ],
    "sg:phone":"+1 715 693 4070",
    "sg:postcode":"54455",
    "sg:province":"WI",
    "sg:tags":[
        "windows"
    ],
    "wof:name":"Sasse P A & Assoc Inc",
    "wof:placetype":"venue"
},
  "geometry": {"coordinates":[-89.733041,44.771681],"type":"Point"}
}