{
  "type": "Feature",
  "properties": {
    "iso:country":"US",
    "sg:address":"400 Lang Dr",
    "sg:city":"La Crosse",
    "sg:classifiers":[
        {
            "category":"Restaurant",
            "type":"Food & Drink"
        }
    ],
    "sg:phone":"+1 608 784 2242",
    "sg:postcode":"54603",
    "sg:province":"WI",
    "wof:name":"Ardies Lang Drive Restaurant",
    "wof:placetype":"venue"
},
  "geometry": {"coordinates":[-91.239442,43.832474],"type":"Point"}
}