{
  "type": "Feature",
  "properties": {
    "iso:country":"US",
    "sg:address":"905 7th Ave W",
    "sg:city":"Durand",
    "sg:classifiers":[
        {
            "category":"Health Services",
            "subcategory":"Doctor",
            "type":"Services"
        }
    ],
    "sg:phone":"+1 715 672 5981",
    "sg:postcode":"54736",
    "sg:province":"WI",
    "sg:tags":[
        "medical"
    ],
    "wof:name":"Castleberg Clinic",
    "wof:placetype":"venue"
},
  "geometry": {"coordinates":[-91.962155,44.621751],"type":"Point"}
}