{
  "type": "Feature",
  "properties": {
    "addr:full":"6250 Triple T Rd Mount Calvary WI 53057",
    "addr:housenumber":"6250",
    "addr:postcode":"53057",
    "addr:street":"Triple T Rd",
    "iso:country":"US",
    "sg:address":"6250 Triple T Rd",
    "sg:city":"Mount Calvary",
    "sg:classifiers":[
        {
            "category":"Farming",
            "subcategory":"Dairy Farm",
            "type":"Manufacturing & Wholesale Goods"
        }
    ],
    "sg:phone":"+1 920 922 8481",
    "sg:postcode":"53057",
    "sg:province":"WI",
    "wof:name":"Kramer Farm",
    "wof:placetype":"venue"
},
  "geometry": {"coordinates":[-88.241438,43.761394],"type":"Point"}
}