{
  "type": "Feature",
  "properties": {
    "iso:country":"US",
    "sg:address":"109 Gilbert St",
    "sg:city":"Blair",
    "sg:classifiers":[
        {
            "category":"Manufacturing",
            "subcategory":"Printing",
            "type":"Manufacturing & Wholesale Goods"
        }
    ],
    "sg:phone":"+1 608 989 2531",
    "sg:postcode":"54616",
    "sg:province":"WI",
    "sg:tags":[
        "newspaper"
    ],
    "wof:name":"Blair Press & Tri County Tab",
    "wof:placetype":"venue"
},
  "geometry": {"coordinates":[-91.232708,44.295398],"type":"Point"}
}