{
  "type": "Feature",
  "properties": {
    "iso:country":"US",
    "sg:address":"121 N 120th St",
    "sg:city":"Milwaukee",
    "sg:classifiers":[
        {
            "category":"Manufacturing",
            "subcategory":"Food",
            "type":"Manufacturing & Wholesale Goods"
        }
    ],
    "sg:phone":"+1 414 302 0606",
    "sg:postcode":"53226",
    "sg:province":"WI",
    "sg:tags":[
        "brewer"
    ],
    "wof:name":"Steep & Brew",
    "wof:placetype":"venue"
},
  "geometry": {"coordinates":[-88.061682,43.031959],"type":"Point"}
}