{
  "type": "Feature",
  "properties": {
    "iso:country":"US",
    "sg:address":"157 E Main St",
    "sg:city":"Ellsworth",
    "sg:classifiers":[
        {
            "category":"Professional",
            "type":"Services"
        }
    ],
    "sg:phone":"+1 715 273 5500",
    "sg:postcode":"54011",
    "sg:province":"WI",
    "sg:tags":[
        "caterer"
    ],
    "wof:name":"Hinck's Economart",
    "wof:placetype":"venue"
},
  "geometry": {"coordinates":[-92.476759,44.732075],"type":"Point"}
}