{
  "type": "Feature",
  "properties": {
    "iso:country":"US",
    "sg:address":"1902 Kropf Ave",
    "sg:city":"Madison",
    "sg:classifiers":[
        {
            "category":"Farming",
            "subcategory":"Fish & Marine Products",
            "type":"Manufacturing & Wholesale Goods"
        }
    ],
    "sg:phone":"+1 608 246 0243",
    "sg:postcode":"53704",
    "sg:province":"WI",
    "sg:tags":[
        "wildlife",
        "management"
    ],
    "wof:name":"American Wildlife Control",
    "wof:placetype":"venue"
},
  "geometry": {"coordinates":[-89.357658,43.116276],"type":"Point"}
}