{
  "type": "Feature",
  "properties": {
    "iso:country":"US",
    "sg:address":"6025 Ridge Rd",
    "sg:city":"Plymouth",
    "sg:classifiers":[
        {
            "category":"Wholesale",
            "subcategory":"Stationery",
            "type":"Manufacturing & Wholesale Goods"
        }
    ],
    "sg:phone":"+1 920 526 3232",
    "sg:postcode":"53073",
    "sg:province":"WI",
    "sg:tags":[
        "paper"
    ],
    "wof:name":"Coronet Paper Products",
    "wof:placetype":"venue"
},
  "geometry": {"coordinates":[-88.051322,43.770542],"type":"Point"}
}