{
  "type": "Feature",
  "properties": {
    "iso:country":"US",
    "sg:address":"920 Windsor St",
    "sg:city":"Sun Prairie",
    "sg:classifiers":[
        {
            "category":"Education",
            "subcategory":"Dance Studio",
            "type":"Public Place"
        }
    ],
    "sg:phone":"+1 608 221 4535",
    "sg:postcode":"53590",
    "sg:province":"WI",
    "sg:tags":[
        "instruction",
        "dancing"
    ],
    "wof:name":"Monona Academy Of Dance",
    "wof:placetype":"venue"
},
  "geometry": {"coordinates":[-89.228088,43.187561],"type":"Point"}
}