{
  "type": "Feature",
  "properties": {
    "addr:full":"111 W Howard Ave Milwaukee WI 53207",
    "addr:housenumber":"111",
    "addr:postcode":"53207",
    "addr:street":"W Howard Ave",
    "iso:country":"US",
    "sg:address":"111 W Howard Ave",
    "sg:city":"Milwaukee",
    "sg:classifiers":[
        {
            "category":"Bars & Pubs",
            "type":"Food & Drink"
        }
    ],
    "sg:phone":"+1 414 481 1441",
    "sg:postcode":"53207",
    "sg:province":"WI",
    "sg:tags":[
        "drinking"
    ],
    "wof:name":"Riccos",
    "wof:placetype":"venue"
},
  "geometry": {"coordinates":[-87.91041300000001,42.973687],"type":"Point"}
}