{
  "type": "Feature",
  "properties": {
    "iso:country":"US",
    "sg:address":"1508 Western Ave",
    "sg:city":"Green Bay",
    "sg:classifiers":[
        {
            "category":"Building & Trades",
            "subcategory":"Construction",
            "type":"Services"
        }
    ],
    "sg:phone":"+1 920 336 5150",
    "sg:postcode":"54303",
    "sg:province":"WI",
    "sg:tags":[
        "home",
        "improvement"
    ],
    "wof:name":"Professional Plastering",
    "wof:placetype":"venue"
},
  "geometry": {"coordinates":[-88.062123,44.526334],"type":"Point"}
}