{
  "type": "Feature",
  "properties": {
    "iso:country":"US",
    "sg:address":"1422 23rd St",
    "sg:city":"Cameron",
    "sg:classifiers":[
        {
            "category":"Farming",
            "subcategory":"Livestock Farm",
            "type":"Manufacturing & Wholesale Goods"
        }
    ],
    "sg:phone":"+1 715 458 2225",
    "sg:postcode":"54822",
    "sg:province":"WI",
    "sg:tags":[
        "beef",
        "feedlot",
        "cattle"
    ],
    "wof:name":"Prarie Lane",
    "wof:placetype":"venue"
},
  "geometry": {"coordinates":[-91.684301,45.410722],"type":"Point"}
}