{
  "type": "Feature",
  "properties": {
    "iso:country":"US",
    "sg:address":"10035 State Hwy 82",
    "sg:city":"Elroy",
    "sg:classifiers":[
        {
            "category":"Shopping",
            "subcategory":"Gifts & Souvenirs",
            "type":"Retail Goods"
        }
    ],
    "sg:phone":"+1 608 462 4075",
    "sg:postcode":"53929",
    "sg:province":"WI",
    "sg:tags":[
        "shop"
    ],
    "wof:name":"4 Seasons Crafts",
    "wof:placetype":"venue"
},
  "geometry": {"coordinates":[-90.267184,43.760337],"type":"Point"}
}