{
  "type": "Feature",
  "properties": {
    "iso:country":"US",
    "sg:address":"4053 Co Rd F",
    "sg:city":"Campbellsport",
    "sg:classifiers":[
        {
            "category":"Wholesale",
            "subcategory":"Durable Goods & Equipment",
            "type":"Manufacturing & Wholesale Goods"
        }
    ],
    "sg:phone":"+1 920 477 3912",
    "sg:postcode":"53010",
    "sg:province":"WI",
    "sg:tags":[
        "representative",
        "manufacturer"
    ],
    "wof:name":"South Eden Enterprises LLC",
    "wof:placetype":"venue"
},
  "geometry": {"coordinates":[-88.363589,43.660163],"type":"Point"}
}