{
  "type": "Feature",
  "properties": {
    "iso:country":"US",
    "sg:address":"527 N Main St",
    "sg:city":"Brillion",
    "sg:classifiers":[
        {
            "category":"Restaurant",
            "type":"Food & Drink"
        }
    ],
    "sg:phone":"+1 920 756 3721",
    "sg:postcode":"54110",
    "sg:province":"WI",
    "wof:name":"Mom's Place",
    "wof:placetype":"venue"
},
  "geometry": {"coordinates":[-88.064167,44.181589],"type":"Point"}
}