{
  "type": "Feature",
  "properties": {
    "addr:full":"4601 7th Ave Kenosha WI 53140",
    "addr:housenumber":"4601",
    "addr:postcode":"53140",
    "addr:street":"7Th Ave",
    "iso:country":"US",
    "sg:address":"4601 7th Ave",
    "sg:city":"Kenosha",
    "sg:classifiers":[
        {
            "category":"Bars & Pubs",
            "type":"Food & Drink"
        }
    ],
    "sg:phone":"+1 262 654 2646",
    "sg:postcode":"53140",
    "sg:province":"WI",
    "wof:name":"Cid's City Zoo Tavern",
    "wof:placetype":"venue"
},
  "geometry": {"coordinates":[-87.820515,42.593827],"type":"Point"}
}