{
  "type": "Feature",
  "properties": {
    "iso:country":"US",
    "sg:address":"1001 Host Dr",
    "sg:city":"Lake Geneva",
    "sg:classifiers":[
        {
            "category":"Professional",
            "subcategory":"Accounting & Tax Preparation",
            "type":"Services"
        }
    ],
    "sg:phone":"+1 262 248 0220",
    "sg:postcode":"53147",
    "sg:province":"WI",
    "sg:tags":[
        "accountant"
    ],
    "wof:name":"Patrick W Romenesko CPA",
    "wof:placetype":"venue"
},
  "geometry": {"coordinates":[-88.421123,42.579376],"type":"Point"}
}