{
  "type": "Feature",
  "properties": {
    "addr:full":"1362 W Main St Whitewater WI 53190",
    "addr:housenumber":"1362",
    "addr:postcode":"53190",
    "addr:street":"W Main St",
    "iso:country":"US",
    "sg:address":"1362 W Main St",
    "sg:city":"Whitewater",
    "sg:classifiers":[
        {
            "category":"Utilities",
            "subcategory":"Mobile Phone",
            "type":"Services"
        }
    ],
    "sg:phone":"+1 262 949 8288",
    "sg:postcode":"53190",
    "sg:province":"WI",
    "sg:tags":[
        "communication",
        "radiotelephone"
    ],
    "wof:name":"United States Cellular Corp",
    "wof:placetype":"venue"
},
  "geometry": {"coordinates":[-88.757548,42.834818],"type":"Point"}
}