{
  "type": "Feature",
  "properties": {
    "addr:full":"143 N Jackson St Milwaukee WI 53202",
    "addr:housenumber":"143",
    "addr:postcode":"53202",
    "addr:street":"N Jackson St",
    "iso:country":"US",
    "sg:address":"143 N Jackson St",
    "sg:city":"Milwaukee",
    "sg:classifiers":[
        {
            "category":"Personal",
            "type":"Services"
        }
    ],
    "sg:phone":"+1 414 727 8458",
    "sg:postcode":"53202",
    "sg:province":"WI",
    "wof:name":"Dash & Dazzle Tanning",
    "wof:placetype":"venue"
},
  "geometry": {"coordinates":[-87.90311,43.030463],"type":"Point"}
}