{
  "type": "Feature",
  "properties": {
    "iso:country":"US",
    "sg:address":"1301 Gohres St",
    "sg:city":"La Crosse",
    "sg:classifiers":[
        {
            "category":"Building & Trades",
            "subcategory":"Construction",
            "type":"Services"
        }
    ],
    "sg:phone":"+1 608 785 1069",
    "sg:postcode":"54603",
    "sg:province":"WI",
    "sg:tags":[
        "residential",
        "house"
    ],
    "wof:name":"S & H Construction Inc",
    "wof:placetype":"venue"
},
  "geometry": {"coordinates":[-91.236927,43.849226],"type":"Point"}
}