{
  "type": "Feature",
  "properties": {
    "iso:country":"US",
    "sg:address":"2736 S 60th St",
    "sg:city":"Milwaukee",
    "sg:classifiers":[
        {
            "category":"Organizations",
            "subcategory":"Religious Organization",
            "type":"Services"
        }
    ],
    "sg:phone":"+1 414 546 2727",
    "sg:postcode":"53219",
    "sg:province":"WI",
    "sg:tags":[
        "church"
    ],
    "wof:name":"Korean New Life Church",
    "wof:placetype":"venue"
},
  "geometry": {"coordinates":[-87.987581,42.994349],"type":"Point"}
}