{
  "type": "Feature",
  "properties": {
    "iso:country":"US",
    "sg:address":"151 N Main St",
    "sg:city":"Juneau",
    "sg:classifiers":[
        {
            "category":"Insurance",
            "subcategory":"Title Insurance",
            "type":"Services"
        },
        {
            "category":"Real Estate",
            "subcategory":"Real Estate Services",
            "type":"Services"
        }
    ],
    "sg:phone":"+1 920 386 2300",
    "sg:postcode":"53039",
    "sg:province":"WI",
    "sg:tags":[
        "company",
        "executive",
        "carrier"
    ],
    "sg:website":"www.titleservice.com",
    "wof:name":"Guaranty Title Services Inc",
    "wof:placetype":"venue"
},
  "geometry": {"coordinates":[-88.704549,43.405858],"type":"Point"}
}