{
  "type": "Feature",
  "properties": {
    "iso:country":"US",
    "sg:address":"3750 E Hammond Ave",
    "sg:city":"Cudahy",
    "sg:classifiers":[
        {
            "category":"Social Services",
            "subcategory":"Adult Care",
            "type":"Services"
        }
    ],
    "sg:phone":"+1 414 486 4120",
    "sg:postcode":"53110",
    "sg:province":"WI",
    "sg:tags":[
        "home",
        "residential"
    ],
    "wof:name":"Hammond House",
    "wof:placetype":"venue"
},
  "geometry": {"coordinates":[-87.85607299999999,42.949311],"type":"Point"}
}