{
  "type": "Feature",
  "properties": {
    "iso:country":"US",
    "sg:address":"6414 W Fond du Lac Ave",
    "sg:city":"Milwaukee",
    "sg:classifiers":[
        {
            "category":"Social Services",
            "type":"Services"
        }
    ],
    "sg:phone":"+1 414 463 8777",
    "sg:postcode":"53218",
    "sg:province":"WI",
    "sg:tags":[
        "organization",
        "welfare"
    ],
    "wof:name":"Bell Therapy Inc",
    "wof:placetype":"venue"
},
  "geometry": {"coordinates":[-87.993834,43.103889],"type":"Point"}
}