{
  "type": "Feature",
  "properties": {
    "iso:country":"US",
    "sg:address":"4199 Main St",
    "sg:city":"Fish Creek",
    "sg:classifiers":[
        {
            "category":"Shopping",
            "subcategory":"Gifts & Souvenirs",
            "type":"Retail Goods"
        }
    ],
    "sg:phone":"+1 920 868 1686",
    "sg:postcode":"54212",
    "sg:province":"WI",
    "sg:tags":[
        "shop"
    ],
    "wof:name":"Beach People",
    "wof:placetype":"venue"
},
  "geometry": {"coordinates":[-87.248651,45.128124],"type":"Point"}
}