{
  "type": "Feature",
  "properties": {
    "iso:country":"US",
    "sg:address":"1314 N 8th St",
    "sg:city":"Sheboygan",
    "sg:classifiers":[
        {
            "category":"Professional",
            "subcategory":"Credit Reporting & Collection",
            "type":"Services"
        }
    ],
    "sg:phone":"+1 920 458 5701",
    "sg:postcode":"53081",
    "sg:province":"WI",
    "sg:tags":[
        "agency"
    ],
    "wof:name":"Sheboygan Collection Svc Inc",
    "wof:placetype":"venue"
},
  "geometry": {"coordinates":[-87.713007,43.759471],"type":"Point"}
}