{
  "type": "Feature",
  "properties": {
    "iso:country":"US",
    "sg:address":"2744 S 9th Pl",
    "sg:city":"Milwaukee",
    "sg:classifiers":[
        {
            "category":"Retail",
            "subcategory":"Repair Shop",
            "type":"Services"
        }
    ],
    "sg:phone":"+1 414 671 4629",
    "sg:postcode":"53215",
    "sg:province":"WI",
    "sg:tags":[
        "related"
    ],
    "wof:name":"Jorge Auto Repair",
    "wof:placetype":"venue"
},
  "geometry": {"coordinates":[-87.923694,42.995454],"type":"Point"}
}