{
  "type": "Feature",
  "properties": {
    "iso:country":"US",
    "sg:address":"800 W Center St",
    "sg:city":"Adams",
    "sg:classifiers":[
        {
            "category":"Manufacturing",
            "subcategory":"Wood Products",
            "type":"Manufacturing & Wholesale Goods"
        }
    ],
    "sg:phone":"+1 608 339 7761",
    "sg:postcode":"53910",
    "sg:province":"WI",
    "sg:tags":[
        "business",
        "mfg"
    ],
    "wof:name":"Andrew Craft Services",
    "wof:placetype":"venue"
},
  "geometry": {"coordinates":[-89.827374,43.957907],"type":"Point"}
}