{
  "type": "Feature",
  "properties": {
    "iso:country":"US",
    "sg:address":"4192 Main St",
    "sg:city":"Fish Creek",
    "sg:classifiers":[
        {
            "category":"Travel",
            "subcategory":"Hotels & Motels",
            "type":"Entertainment"
        }
    ],
    "sg:phone":"+1 920 868 3442",
    "sg:postcode":"54212",
    "sg:province":"WI",
    "sg:website":"www.whistlingswan.com",
    "wof:name":"Whistling Swan",
    "wof:placetype":"venue"
},
  "geometry": {"coordinates":[-87.248934,45.128349],"type":"Point"}
}