{
  "type": "Feature",
  "properties": {
    "addr:full":"1409 6th St Algoma WI 54201",
    "addr:housenumber":"1409",
    "addr:postcode":"54201",
    "addr:street":"6Th St",
    "iso:country":"US",
    "sg:address":"1409 6th St",
    "sg:city":"Algoma",
    "sg:classifiers":[
        {
            "category":"Real Estate",
            "subcategory":"Real Estate Operator",
            "type":"Services"
        }
    ],
    "sg:phone":"+1 920 487 9935",
    "sg:postcode":"54201",
    "sg:province":"WI",
    "sg:tags":[
        "apartment"
    ],
    "wof:name":"Seagull Apartments",
    "wof:placetype":"venue"
},
  "geometry": {"coordinates":[-87.441551,44.600027],"type":"Point"}
}