{
  "type": "Feature",
  "properties": {
    "iso:country":"US",
    "sg:address":"2347 Co Rd A",
    "sg:city":"Markesan",
    "sg:classifiers":[
        {
            "category":"Freight",
            "type":"Transportation"
        },
        {
            "category":"Professional",
            "subcategory":"Advertising",
            "type":"Services"
        }
    ],
    "sg:phone":"+1 920 398 2975",
    "sg:postcode":"53946",
    "sg:province":"WI",
    "sg:tags":[
        "mailing",
        "shipping",
        "business",
        "general"
    ],
    "wof:name":"Fond Du Lac Warehousing Inc",
    "wof:placetype":"venue"
},
  "geometry": {"coordinates":[-88.936461,43.71915],"type":"Point"}
}