{
  "type": "Feature",
  "properties": {
    "iso:country":"US",
    "sg:address":"6991 W School St",
    "sg:city":"Three Lakes",
    "sg:classifiers":[
        {
            "category":"Shopping",
            "subcategory":"Bicycles & Sporting Goods",
            "type":"Retail Goods"
        }
    ],
    "sg:phone":"+1 715 546 2333",
    "sg:postcode":"54562",
    "sg:province":"WI",
    "wof:name":"Northland Marine Inc",
    "wof:placetype":"venue"
},
  "geometry": {"coordinates":[-89.169963,45.798449],"type":"Point"}
}