{
  "type": "Feature",
  "properties": {
    "addr:full":"3030 W College Ave Appleton WI 54914",
    "addr:housenumber":"3030",
    "addr:postcode":"54914",
    "addr:street":"W College Ave",
    "iso:country":"US",
    "sg:address":"3030 W College Ave",
    "sg:city":"Appleton",
    "sg:classifiers":[
        {
            "category":"Retail",
            "subcategory":"Auto Repair",
            "type":"Services"
        }
    ],
    "sg:phone":"+1 920 731 0901",
    "sg:postcode":"54914",
    "sg:province":"WI",
    "sg:tags":[
        "automobile",
        "lubrication"
    ],
    "wof:name":"Quick Lane At Les Stumpfs Ford",
    "wof:placetype":"venue"
},
  "geometry": {"coordinates":[-88.455656,44.261938],"type":"Point"}
}