{
  "type": "Feature",
  "properties": {
    "iso:country":"US",
    "sg:address":"2950 N Elco Rd",
    "sg:city":"Fall Creek",
    "sg:classifiers":[
        {
            "category":"Building & Trades",
            "subcategory":"Construction",
            "type":"Services"
        }
    ],
    "sg:phone":"+1 715 839 8626",
    "sg:postcode":"54742",
    "sg:province":"WI",
    "sg:tags":[
        "nonresidential"
    ],
    "wof:name":"Gordon Oler",
    "wof:placetype":"venue"
},
  "geometry": {"coordinates":[-91.37292,44.787984],"type":"Point"}
}