{
  "type": "Feature",
  "properties": {
    "iso:country":"US",
    "sg:address":"836 S 60th St",
    "sg:city":"Milwaukee",
    "sg:classifiers":[
        {
            "category":"Professional",
            "type":"Services"
        }
    ],
    "sg:phone":"+1 414 259 9909",
    "sg:postcode":"53214",
    "sg:province":"WI",
    "sg:tags":[
        "establishment"
    ],
    "wof:name":"A Mmta",
    "wof:placetype":"venue"
},
  "geometry": {"coordinates":[-87.987053,43.022991],"type":"Point"}
}