{
  "type": "Feature",
  "properties": {
    "addr:full":"3752 Co Rd Jj Spring Green WI 53588",
    "addr:housenumber":"3752",
    "addr:postcode":"53588",
    "addr:street":"Co Rd Jj Spring Green",
    "iso:country":"US",
    "sg:address":"3752 Co Rd Jj",
    "sg:city":"Spring Green",
    "sg:classifiers":[
        {
            "category":"Wholesale",
            "subcategory":"Poultry",
            "type":"Manufacturing & Wholesale Goods"
        }
    ],
    "sg:phone":"+1 608 588 2757",
    "sg:postcode":"53588",
    "sg:province":"WI",
    "sg:tags":[
        "eggs"
    ],
    "wof:name":"Peck's Fresh Eggs",
    "wof:placetype":"venue"
},
  "geometry": {"coordinates":[-90.118747,43.213649],"type":"Point"}
}