{
  "type": "Feature",
  "properties": {
    "iso:country":"US",
    "sg:address":"6215 Co Rd M",
    "sg:city":"Boulder Junction",
    "sg:classifiers":[
        {
            "category":"Bars & Pubs",
            "type":"Food & Drink"
        }
    ],
    "sg:phone":"+1 715 385 3242",
    "sg:postcode":"54512",
    "sg:province":"WI",
    "sg:tags":[
        "drinking",
        "eating"
    ],
    "wof:name":"Shrimps Legend",
    "wof:placetype":"venue"
},
  "geometry": {"coordinates":[-89.625124,46.151305],"type":"Point"}
}