{
  "type": "Feature",
  "properties": {
    "addr:full":"250 Edwards Blvd Lake Geneva WI 53147",
    "addr:housenumber":"250",
    "addr:postcode":"53147",
    "addr:street":"Edwards Blvd",
    "iso:country":"US",
    "sg:address":"250 Edwards Blvd",
    "sg:city":"Lake Geneva",
    "sg:classifiers":[
        {
            "category":"Retail",
            "subcategory":"Repair Shop",
            "type":"Services"
        }
    ],
    "sg:phone":"+1 262 749 4812",
    "sg:postcode":"53147",
    "sg:province":"WI",
    "sg:tags":[
        "related"
    ],
    "wof:name":"CEO Limousine Svc",
    "wof:placetype":"venue"
},
  "geometry": {"coordinates":[-88.41416099999999,42.590245],"type":"Point"}
}