{
  "type": "Feature",
  "properties": {
    "iso:country":"US",
    "sg:address":"755 S Bobolink Dr",
    "sg:city":"Brookfield",
    "sg:classifiers":[
        {
            "category":"Freight",
            "type":"Transportation"
        }
    ],
    "sg:phone":"+1 262 789 7149",
    "sg:postcode":"53005",
    "sg:province":"WI",
    "sg:tags":[
        "operator",
        "local",
        "trucking"
    ],
    "wof:name":"D Wang LLC",
    "wof:placetype":"venue"
},
  "geometry": {"coordinates":[-88.075884,43.022461],"type":"Point"}
}