{
  "type": "Feature",
  "properties": {
    "addr:full":"5158 Hoefs Rd Randolph WI 53956",
    "addr:housenumber":"5158",
    "addr:postcode":"53956",
    "addr:street":"Hoefs Rd",
    "iso:country":"US",
    "sg:address":"5158 Hoefs Rd",
    "sg:city":"Randolph",
    "sg:classifiers":[
        {
            "category":"Wholesale",
            "subcategory":"Farm Supplies",
            "type":"Manufacturing & Wholesale Goods"
        }
    ],
    "sg:phone":"+1 920 326 3916",
    "sg:postcode":"53956",
    "sg:province":"WI",
    "sg:tags":[
        "livestock"
    ],
    "wof:name":"Cbw Livestock",
    "wof:placetype":"venue"
},
  "geometry": {"coordinates":[-89.03618,43.475088],"type":"Point"}
}