{
  "type": "Feature",
  "properties": {
    "iso:country":"US",
    "sg:address":"7502 Castle Ave",
    "sg:city":"Sparta",
    "sg:classifiers":[
        {
            "category":"Retail",
            "subcategory":"Auto Repair",
            "type":"Services"
        }
    ],
    "sg:phone":"+1 608 272 3110",
    "sg:postcode":"54656",
    "sg:province":"WI",
    "sg:tags":[
        "body"
    ],
    "wof:name":"Cw Auto Body",
    "wof:placetype":"venue"
},
  "geometry": {"coordinates":[-90.836841,44.078391],"type":"Point"}
}