{
  "type": "Feature",
  "properties": {
    "iso:country":"US",
    "sg:address":"2 Southwick Cir",
    "sg:city":"Madison",
    "sg:classifiers":[
        {
            "category":"Professional",
            "subcategory":"Management & Consulting",
            "type":"Services"
        }
    ],
    "sg:phone":"+1 608 829 2137",
    "sg:postcode":"53717",
    "sg:province":"WI",
    "sg:tags":[
        "marketing"
    ],
    "wof:name":"Deltaquest LLC",
    "wof:placetype":"venue"
},
  "geometry": {"coordinates":[-89.506659,43.068373],"type":"Point"}
}