{
  "type": "Feature",
  "properties": {
    "addr:full":"2768 Lake Shore Dr Chilton WI 53014",
    "addr:housenumber":"2768",
    "addr:postcode":"53014",
    "addr:street":"Lake Shore Dr",
    "iso:country":"US",
    "sg:address":"2768 Lake Shore Dr",
    "sg:city":"Chilton",
    "sg:classifiers":[
        {
            "category":"Social Services",
            "subcategory":"Child Care",
            "type":"Services"
        }
    ],
    "sg:phone":"+1 920 849 2697",
    "sg:postcode":"53014",
    "sg:province":"WI",
    "sg:tags":[
        "day"
    ],
    "wof:name":"Sunshine Days Family Day Care",
    "wof:placetype":"venue"
},
  "geometry": {"coordinates":[-88.311718,43.990205],"type":"Point"}
}