{
  "type": "Feature",
  "properties": {
    "iso:country":"US",
    "sg:address":"2610 Seiferth Rd",
    "sg:city":"Madison",
    "sg:classifiers":[
        {
            "category":"Wholesale",
            "subcategory":"Groceries",
            "type":"Manufacturing & Wholesale Goods"
        }
    ],
    "sg:phone":"+1 608 222 7091",
    "sg:postcode":"53716",
    "sg:province":"WI",
    "sg:tags":[
        "coffee"
    ],
    "wof:name":"Gold Star Midwest LLC",
    "wof:placetype":"venue"
},
  "geometry": {"coordinates":[-89.30761,43.06208],"type":"Point"}
}