{
  "type": "Feature",
  "properties": {
    "iso:country":"US",
    "sg:address":"957 State Hwy 54",
    "sg:city":"Waupaca",
    "sg:classifiers":[
        {
            "category":"Shopping",
            "subcategory":"Gifts & Souvenirs",
            "type":"Retail Goods"
        }
    ],
    "sg:phone":"+1 715 256 0638",
    "sg:postcode":"54981",
    "sg:province":"WI",
    "wof:name":"Cottage Garden Farm",
    "wof:placetype":"venue"
},
  "geometry": {"coordinates":[-89.180458,44.352081],"type":"Point"}
}