{
  "type": "Feature",
  "properties": {
    "iso:country":"US",
    "sg:address":"1535 Mill Rd",
    "sg:city":"Menomonie",
    "sg:classifiers":[
        {
            "category":"Shopping",
            "subcategory":"Clothing, Apparel, & Fashions",
            "type":"Retail Goods"
        }
    ],
    "sg:phone":"+1 715 235 1788",
    "sg:postcode":"54751",
    "sg:province":"WI",
    "wof:name":"Christopher & Banks",
    "wof:placetype":"venue"
},
  "geometry": {"coordinates":[-91.953436,44.871727],"type":"Point"}
}