{
  "type": "Feature",
  "properties": {
    "iso:country":"US",
    "sg:address":"3980 Elm Rd",
    "sg:city":"Krakow",
    "sg:classifiers":[
        {
            "category":"Farming",
            "subcategory":"Farm",
            "type":"Manufacturing & Wholesale Goods"
        }
    ],
    "sg:phone":"+1 920 822 3653",
    "sg:postcode":"54137",
    "sg:province":"WI",
    "sg:tags":[
        "crop",
        "general"
    ],
    "wof:name":"Michael Zielinski",
    "wof:placetype":"venue"
},
  "geometry": {"coordinates":[-88.285929,44.720966],"type":"Point"}
}