{
  "type": "Feature",
  "properties": {
    "iso:country":"US",
    "sg:address":"1860 W Davenport St",
    "sg:city":"Rhinelander",
    "sg:classifiers":[
        {
            "category":"Shopping",
            "subcategory":"Musical Instruments",
            "type":"Retail Goods"
        }
    ],
    "sg:phone":"+1 715 369 4050",
    "sg:postcode":"54501",
    "sg:province":"WI",
    "wof:name":"Lakeland Music & Supply",
    "wof:placetype":"venue"
},
  "geometry": {"coordinates":[-89.43568999999999,45.635302],"type":"Point"}
}