{
  "type": "Feature",
  "properties": {
    "iso:country":"US",
    "sg:address":"835 Park Ave",
    "sg:city":"Beloit",
    "sg:classifiers":[
        {
            "category":"Restaurant",
            "type":"Food & Drink"
        }
    ],
    "sg:phone":"+1 608 364 0245",
    "sg:postcode":"53511",
    "sg:province":"IL",
    "sg:tags":[
        "eating"
    ],
    "wof:name":"Parkin Ice Cream Co",
    "wof:placetype":"venue"
},
  "geometry": {"coordinates":[-89.02673,42.505778],"type":"Point"}
}