{
  "type": "Feature",
  "properties": {
    "addr:full":"5617 381st Ave Burlington WI 53105",
    "addr:housenumber":"5617",
    "addr:postcode":"53105",
    "addr:street":"381St Ave",
    "iso:country":"US",
    "sg:address":"5617 381st Ave",
    "sg:city":"Burlington",
    "sg:classifiers":[
        {
            "category":"Building & Trades",
            "subcategory":"Plumbing",
            "type":"Services"
        }
    ],
    "sg:phone":"+1 262 537 4040",
    "sg:postcode":"53105",
    "sg:province":"WI",
    "sg:tags":[
        "contractor"
    ],
    "wof:name":"Podella Plumbing & Heating",
    "wof:placetype":"venue"
},
  "geometry": {"coordinates":[-88.27237,42.586692],"type":"Point"}
}