{
  "type": "Feature",
  "properties": {
    "iso:country":"US",
    "sg:address":"7735 W Howard Ave",
    "sg:city":"Milwaukee",
    "sg:classifiers":[
        {
            "category":"Organizations",
            "subcategory":"Religious Organization",
            "type":"Services"
        }
    ],
    "sg:phone":"+1 414 541 5580",
    "sg:postcode":"53220",
    "sg:province":"WI",
    "sg:tags":[
        "church"
    ],
    "wof:name":"Redeemer Evangelical Free Chr",
    "wof:placetype":"venue"
},
  "geometry": {"coordinates":[-88.009091,42.973679],"type":"Point"}
}