{
  "type": "Feature",
  "properties": {
    "iso:country":"US",
    "sg:address":"685 1st Ave",
    "sg:city":"Cumberland",
    "sg:classifiers":[
        {
            "category":"Social Services",
            "subcategory":"Child Care",
            "type":"Services"
        }
    ],
    "sg:phone":"+1 715 822 5955",
    "sg:postcode":"54829",
    "sg:province":"WI",
    "sg:tags":[
        "day"
    ],
    "wof:name":"Busy Beavers Day Care",
    "wof:placetype":"venue"
},
  "geometry": {"coordinates":[-92.01693,45.519243],"type":"Point"}
}