{
  "type": "Feature",
  "properties": {
    "iso:country":"US",
    "sg:address":"720 Industrial Dr",
    "sg:city":"Slinger",
    "sg:classifiers":[
        {
            "category":"Building & Trades",
            "subcategory":"Construction",
            "type":"Services"
        }
    ],
    "sg:phone":"+1 262 644 7298",
    "sg:postcode":"53086",
    "sg:province":"WI",
    "sg:tags":[
        "woodworker"
    ],
    "wof:name":"Town & Country Woodworks Inc",
    "wof:placetype":"venue"
},
  "geometry": {"coordinates":[-88.274722,43.322862],"type":"Point"}
}