{
  "type": "Feature",
  "properties": {
    "iso:country":"US",
    "sg:address":"6114 Pershing Blvd",
    "sg:city":"Kenosha",
    "sg:classifiers":[
        {
            "category":"Autos & Motor Vehicles",
            "subcategory":"Auto Supplies",
            "type":"Retail Goods"
        }
    ],
    "sg:phone":"+1 262 657 1180",
    "sg:postcode":"53142",
    "sg:province":"WI",
    "sg:tags":[
        "automobile",
        "part",
        "accessory"
    ],
    "wof:name":"Clicknsave Auto Parts",
    "wof:placetype":"venue"
},
  "geometry": {"coordinates":[-87.86290099999999,42.579263],"type":"Point"}
}