{
  "type": "Feature",
  "properties": {
    "iso:country":"US",
    "sg:address":"3095 Blue Goose Rd",
    "sg:city":"Saukville",
    "sg:classifiers":[
        {
            "category":"Education",
            "subcategory":"College",
            "type":"Public Place"
        }
    ],
    "sg:phone":"+1 262 675 6844",
    "sg:postcode":"53080",
    "sg:province":"WI",
    "sg:tags":[
        "academic",
        "school"
    ],
    "wof:name":"University Of Wisconsin",
    "wof:placetype":"venue"
},
  "geometry": {"coordinates":[-88.021509,43.388156],"type":"Point"}
}