{
  "type": "Feature",
  "properties": {
    "addr:full":"1023 US Hwy 18 Cobb WI 53526",
    "addr:housenumber":"1023",
    "addr:postcode":"53526",
    "addr:street":"Us Hwy 18",
    "iso:country":"US",
    "sg:address":"1023 US Hwy 18",
    "sg:city":"Cobb",
    "sg:classifiers":[
        {
            "category":"Freight",
            "type":"Transportation"
        }
    ],
    "sg:phone":"+1 608 623 2525",
    "sg:postcode":"53526",
    "sg:province":"WI",
    "wof:name":"Yelinek Livestock",
    "wof:placetype":"venue"
},
  "geometry": {"coordinates":[-90.369652,42.966865],"type":"Point"}
}