{
  "type": "Feature",
  "properties": {
    "addr:full":"1800 Harrison St Oshkosh WI 54901",
    "addr:housenumber":"1800",
    "addr:postcode":"54901",
    "addr:street":"Harrison St",
    "iso:country":"US",
    "sg:address":"1800 Harrison St",
    "sg:city":"Oshkosh",
    "sg:classifiers":[
        {
            "category":"Autos & Motor Vehicles",
            "subcategory":"Automobile Sales",
            "type":"Retail Goods"
        }
    ],
    "sg:phone":"+1 920 230 3344",
    "sg:postcode":"54901",
    "sg:province":"WI",
    "sg:tags":[
        "car",
        "dealer"
    ],
    "wof:name":"Friday's Auto Deals LLC",
    "wof:placetype":"venue"
},
  "geometry": {"coordinates":[-88.532662,44.041312],"type":"Point"}
}