{
  "type": "Feature",
  "properties": {
    "iso:country":"US",
    "sg:address":"2563 S 28th St",
    "sg:city":"Milwaukee",
    "sg:classifiers":[
        {
            "category":"Professional",
            "subcategory":"Business Services",
            "type":"Services"
        }
    ],
    "sg:phone":"+1 414 384 2842",
    "sg:postcode":"53215",
    "sg:province":"WI",
    "wof:name":"RTD Enterprise LLC",
    "wof:placetype":"venue"
},
  "geometry": {"coordinates":[-87.94943000000001,42.998855],"type":"Point"}
}