{
  "type": "Feature",
  "properties": {
    "iso:country":"US",
    "sg:address":"818 S Main St",
    "sg:city":"Shawano",
    "sg:classifiers":[
        {
            "category":"Government",
            "subcategory":"Office",
            "type":"Public Place"
        }
    ],
    "sg:phone":"+1 715 526 5656",
    "sg:postcode":"54166",
    "sg:province":"WI",
    "sg:tags":[
        "village"
    ],
    "wof:name":"Shawano Athletic Field Office",
    "wof:placetype":"venue"
},
  "geometry": {"coordinates":[-88.608956,44.771799],"type":"Point"}
}