{
  "type": "Feature",
  "properties": {
    "addr:full":"23463 State Rd 35 Siren WI 54872",
    "addr:housenumber":"23463;35",
    "addr:postcode":"54872",
    "addr:street":"State Rd",
    "iso:country":"US",
    "sg:address":"23463 State Rd 35",
    "sg:city":"Siren",
    "sg:classifiers":[
        {
            "category":"Building & Trades",
            "subcategory":"Landscaping Services",
            "type":"Services"
        }
    ],
    "sg:phone":"+1 715 349 2243",
    "sg:postcode":"54872",
    "sg:province":"WI",
    "wof:name":"Howard Kopecky",
    "wof:placetype":"venue"
},
  "geometry": {"coordinates":[-92.38164500000001,45.765186],"type":"Point"}
}