{
  "type": "Feature",
  "properties": {
    "iso:country":"US",
    "sg:address":"236 Westend Cir",
    "sg:city":"Sun Prairie",
    "sg:classifiers":[
        {
            "category":"Manufacturing",
            "subcategory":"Petroleum Products",
            "type":"Manufacturing & Wholesale Goods"
        },
        {
            "category":"Building & Trades",
            "subcategory":"Construction",
            "type":"Services"
        }
    ],
    "sg:phone":"+1 608 825 7176",
    "sg:postcode":"53590",
    "sg:province":"WI",
    "sg:tags":[
        "asphalt",
        "mfg"
    ],
    "wof:name":"Badger Black Top Sealing",
    "wof:placetype":"venue"
},
  "geometry": {"coordinates":[-89.194862,43.182561],"type":"Point"}
}