{
  "type": "Feature",
  "properties": {
    "addr:full":"5666 Broad St Greendale WI 53129",
    "addr:housenumber":"5666",
    "addr:postcode":"53129",
    "addr:street":"Broad St",
    "iso:country":"US",
    "sg:address":"5666 Broad St",
    "sg:city":"Greendale",
    "sg:classifiers":[
        {
            "category":"Home & Garden",
            "subcategory":"Building Materials",
            "type":"Retail Goods"
        }
    ],
    "sg:phone":"+1 414 423 6910",
    "sg:postcode":"53129",
    "sg:province":"WI",
    "sg:tags":[
        "glass",
        "gift"
    ],
    "wof:name":"Glassic Design",
    "wof:placetype":"venue"
},
  "geometry": {"coordinates":[-87.995923,42.941803],"type":"Point"}
}