{
  "type": "Feature",
  "properties": {
    "iso:country":"US",
    "sg:address":"109 N 28th St",
    "sg:city":"Superior",
    "sg:classifiers":[
        {
            "category":"Health Services",
            "subcategory":"Doctor",
            "type":"Services"
        }
    ],
    "sg:phone":"+1 715 395 3990",
    "sg:postcode":"54880",
    "sg:province":"WI",
    "sg:tags":[
        "physician",
        "surgeon"
    ],
    "wof:name":"St Luke's Outpatient Surgery",
    "wof:placetype":"venue"
},
  "geometry": {"coordinates":[-92.07872,46.706264],"type":"Point"}
}