{
  "type": "Feature",
  "properties": {
    "addr:full":"2527 State Hwy 35 Luck WI 54853",
    "addr:housenumber":"2527",
    "addr:postcode":"54853",
    "addr:street":"State Hwy 35",
    "iso:country":"US",
    "sg:address":"2527 State Hwy 35",
    "sg:city":"Luck",
    "sg:classifiers":[
        {
            "category":"Food & Beverages",
            "subcategory":"Groceries & Convenience Stores",
            "type":"Retail Goods"
        }
    ],
    "sg:phone":"+1 715 472 8393",
    "sg:postcode":"54853",
    "sg:province":"WI",
    "wof:name":"Kum & Go",
    "wof:placetype":"venue"
},
  "geometry": {"coordinates":[-92.48864500000001,45.569926],"type":"Point"}
}