{
  "type": "Feature",
  "properties": {
    "iso:country":"US",
    "sg:address":"745 Victoria St",
    "sg:city":"Green Bay",
    "sg:classifiers":[
        {
            "category":"Personal",
            "subcategory":"Beauty Salon",
            "type":"Services"
        }
    ],
    "sg:phone":"+1 920 468 3210",
    "sg:postcode":"54302",
    "sg:province":"WI",
    "sg:tags":[
        "shop"
    ],
    "wof:name":"Hats Off Hair Design Team",
    "wof:placetype":"venue"
},
  "geometry": {"coordinates":[-87.987094,44.492358],"type":"Point"}
}