{
  "type": "Feature",
  "properties": {
    "iso:country":"US",
    "sg:address":"2920 N 68th St",
    "sg:city":"Milwaukee",
    "sg:classifiers":[
        {
            "category":"Professional",
            "subcategory":"Advertising",
            "type":"Services"
        }
    ],
    "sg:phone":"+1 414 453 7214",
    "sg:postcode":"53210",
    "sg:province":"WI",
    "wof:name":"Spark Milwaukee",
    "wof:placetype":"venue"
},
  "geometry": {"coordinates":[-87.997266,43.072771],"type":"Point"}
}