{
  "type": "Feature",
  "properties": {
    "iso:country":"US",
    "sg:address":"7279 Bitney Rd",
    "sg:city":"Lodi",
    "sg:classifiers":[
        {
            "category":"Farming",
            "subcategory":"Dairy Farm",
            "type":"Manufacturing & Wholesale Goods"
        }
    ],
    "sg:phone":"+1 608 592 7405",
    "sg:postcode":"53555",
    "sg:province":"WI",
    "wof:name":"Neil Breunig Farm",
    "wof:placetype":"venue"
},
  "geometry": {"coordinates":[-89.590802,43.254471],"type":"Point"}
}