{
  "type": "Feature",
  "properties": {
    "addr:full":"219 W 10th St Buffalo City WI 54622",
    "addr:housenumber":"219",
    "addr:postcode":"54622",
    "addr:street":"W 10Th St",
    "iso:country":"US",
    "sg:address":"219 W 10th St",
    "sg:city":"Buffalo City",
    "sg:classifiers":[
        {
            "category":"Retail",
            "subcategory":"Portrait Studio",
            "type":"Services"
        }
    ],
    "sg:phone":"+1 608 248 2703",
    "sg:postcode":"54622",
    "sg:province":"WI",
    "sg:tags":[
        "photographer",
        "photo"
    ],
    "wof:name":"Gregs Photography",
    "wof:placetype":"venue"
},
  "geometry": {"coordinates":[-91.861412,44.230454],"type":"Point"}
}