{
  "type": "Feature",
  "properties": {
    "addr:full":"W6829 Industrial Blvd Onalaska WI 54650",
    "addr:housenumber":"w6829",
    "addr:postcode":"54650",
    "addr:street":"Industrial Blvd",
    "iso:country":"US",
    "sg:address":"W6829 Industrial Blvd",
    "sg:city":"Onalaska",
    "sg:classifiers":[
        {
            "category":"Retail",
            "subcategory":"Auto Repair",
            "type":"Services"
        }
    ],
    "sg:phone":"+1 608 781 1493",
    "sg:postcode":"54650",
    "sg:province":"WI",
    "sg:tags":[
        "body",
        "automobile",
        "painting",
        "repairing"
    ],
    "wof:name":"Roberts Repairs",
    "wof:placetype":"venue"
},
  "geometry": {"coordinates":[-91.245926,43.92152],"type":"Point"}
}