{
  "type": "Feature",
  "properties": {
    "iso:country":"US",
    "sg:address":"113 E Elm St",
    "sg:city":"River Falls",
    "sg:classifiers":[
        {
            "category":"Professional",
            "subcategory":"Lawyer & Legal Services",
            "type":"Services"
        }
    ],
    "sg:phone":"+1 715 425 0144",
    "sg:postcode":"54022",
    "sg:province":"WI",
    "sg:tags":[
        "attorney"
    ],
    "wof:name":"Gaylord Law Offices",
    "wof:placetype":"venue"
},
  "geometry": {"coordinates":[-92.62588,44.858565],"type":"Point"}
}