{
  "type": "Feature",
  "properties": {
    "iso:country":"US",
    "sg:address":"1725 State St",
    "sg:city":"La Crosse",
    "sg:classifiers":[
        {
            "category":"Education",
            "subcategory":"College",
            "type":"Public Place"
        }
    ],
    "sg:phone":"+1 608 785 8502",
    "sg:postcode":"54601",
    "sg:province":"WI",
    "wof:name":"Uw Lacrosse Economics Dept",
    "wof:placetype":"venue"
},
  "geometry": {"coordinates":[-91.22910299999999,43.812881],"type":"Point"}
}