{
  "type": "Feature",
  "properties": {
    "iso:country":"US",
    "sg:address":"2129 W North Ave",
    "sg:city":"Milwaukee",
    "sg:classifiers":[
        {
            "category":"Shopping",
            "subcategory":"Gifts & Souvenirs",
            "type":"Retail Goods"
        }
    ],
    "sg:phone":"+1 414 342 1300",
    "sg:postcode":"53205",
    "sg:province":"WI",
    "sg:tags":[
        "balloon",
        "artist"
    ],
    "wof:name":"Balloons Plus",
    "wof:placetype":"venue"
},
  "geometry": {"coordinates":[-87.939727,43.060435],"type":"Point"}
}