{
  "type": "Feature",
  "properties": {
    "iso:country":"US",
    "sg:address":"805 Uniek Dr",
    "sg:city":"Waunakee",
    "sg:classifiers":[
        {
            "category":"Manufacturing",
            "subcategory":"Printing",
            "type":"Manufacturing & Wholesale Goods"
        }
    ],
    "sg:phone":"+1 608 849 9999",
    "sg:postcode":"53597",
    "sg:province":"WI",
    "sg:tags":[
        "album",
        "photo",
        "frame",
        "craft",
        "mfg"
    ],
    "sg:website":"www.uniekinc.com",
    "wof:name":"Uniek Inc",
    "wof:placetype":"venue"
},
  "geometry": {"coordinates":[-89.438782,43.182251],"type":"Point"}
}