{
  "type": "Feature",
  "properties": {
    "iso:country":"US",
    "sg:address":"3064 Progress Rd",
    "sg:city":"Madison",
    "sg:classifiers":[
        {
            "category":"Autos & Motor Vehicles",
            "subcategory":"Auto Supplies",
            "type":"Retail Goods"
        },
        {
            "category":"Wholesale",
            "subcategory":"Electrical",
            "type":"Manufacturing & Wholesale Goods"
        }
    ],
    "sg:phone":"+1 920 485 0888",
    "sg:postcode":"53716",
    "sg:province":"WI",
    "sg:tags":[
        "battery"
    ],
    "wof:name":"Delta Equipment Company",
    "wof:placetype":"venue"
},
  "geometry": {"coordinates":[-89.303618,43.057838],"type":"Point"}
}