{
  "type": "Feature",
  "properties": {
    "addr:full":"2821 32nd St N Wisconsin Rapids WI 54494",
    "addr:housenumber":"2821",
    "addr:postcode":"54494",
    "addr:street":"32Nd St N",
    "iso:country":"US",
    "sg:address":"2821 32nd St N",
    "sg:city":"Wisconsin Rapids",
    "sg:classifiers":[
        {
            "category":"Retail",
            "subcategory":"Repair Shop",
            "type":"Services"
        }
    ],
    "sg:phone":"+1 715 424 5948",
    "sg:postcode":"54494",
    "sg:province":"WI",
    "wof:name":"Craftmaster Refinishing",
    "wof:placetype":"venue"
},
  "geometry": {"coordinates":[-89.78671900000001,44.413663],"type":"Point"}
}