{
  "type": "Feature",
  "properties": {
    "iso:country":"US",
    "sg:address":"5896 Center Rd",
    "sg:city":"Monticello",
    "sg:classifiers":[
        {
            "category":"Farming",
            "subcategory":"Dairy Farm",
            "type":"Manufacturing & Wholesale Goods"
        }
    ],
    "sg:phone":"+1 608 938 4395",
    "sg:postcode":"53570",
    "sg:province":"WI",
    "wof:name":"Larry Schmid",
    "wof:placetype":"venue"
},
  "geometry": {"coordinates":[-89.641902,42.710974],"type":"Point"}
}