{
  "type": "Feature",
  "properties": {
    "iso:country":"US",
    "sg:address":"1201 Hackett St",
    "sg:city":"Beloit",
    "sg:classifiers":[
        {
            "category":"Organizations",
            "subcategory":"Religious Organization",
            "type":"Services"
        }
    ],
    "sg:phone":"+1 608 363 8742",
    "sg:postcode":"53511",
    "sg:province":"WI",
    "wof:name":"Abundant Life Church of B",
    "wof:placetype":"venue"
},
  "geometry": {"coordinates":[-89.05151499999999,42.514399],"type":"Point"}
}