{
  "type": "Feature",
  "properties": {
    "iso:country":"US",
    "sg:address":"6801 21st Ave",
    "sg:city":"Kenosha",
    "sg:classifiers":[
        {
            "category":"Wholesale",
            "subcategory":"Construction Materials",
            "type":"Manufacturing & Wholesale Goods"
        }
    ],
    "sg:phone":"+1 262 564 0080",
    "sg:postcode":"53143",
    "sg:province":"WI",
    "sg:tags":[
        "fence"
    ],
    "wof:name":"Silt Fencing America",
    "wof:placetype":"venue"
},
  "geometry": {"coordinates":[-87.834284,42.572151],"type":"Point"}
}