{
  "type": "Feature",
  "properties": {
    "addr:full":"1897 S 1st St Cameron WI 54822",
    "addr:housenumber":"1897",
    "addr:postcode":"54822",
    "addr:street":"S 1St St",
    "iso:country":"US",
    "sg:address":"1897 S 1st St",
    "sg:city":"Cameron",
    "sg:classifiers":[
        {
            "category":"Retail",
            "subcategory":"Auto Repair",
            "type":"Services"
        }
    ],
    "sg:phone":"+1 715 458 2563",
    "sg:postcode":"54822",
    "sg:province":"WI",
    "sg:tags":[
        "engine"
    ],
    "wof:name":"Don's Repair",
    "wof:placetype":"venue"
},
  "geometry": {"coordinates":[-91.735539,45.400112],"type":"Point"}
}