{
  "type": "Feature",
  "properties": {
    "addr:full":"205 W Sadd St North Prairie WI 53153",
    "addr:housenumber":"205",
    "addr:postcode":"53153",
    "addr:street":"W Sadd St",
    "iso:country":"US",
    "sg:address":"205 W Sadd St",
    "sg:city":"North Prairie",
    "sg:classifiers":[
        {
            "category":"Health Services",
            "subcategory":"Doctor",
            "type":"Services"
        }
    ],
    "sg:phone":"+1 262 392 2244",
    "sg:postcode":"53153",
    "sg:province":"WI",
    "sg:tags":[
        "dentist"
    ],
    "wof:name":"North Prairie Dental Clinic",
    "wof:placetype":"venue"
},
  "geometry": {"coordinates":[-88.405683,42.93499],"type":"Point"}
}