{
  "type": "Feature",
  "properties": {
    "addr:full":"2304 18th St Kenosha WI 53140",
    "addr:housenumber":"2304",
    "addr:postcode":"53140",
    "addr:street":"18Th St",
    "iso:country":"US",
    "sg:address":"2304 18th St",
    "sg:city":"Kenosha",
    "sg:classifiers":[
        {
            "category":"Banks & Credit Unions",
            "subcategory":"Bank",
            "type":"Services"
        }
    ],
    "sg:phone":"+1 262 551 0263",
    "sg:postcode":"53140",
    "sg:province":"WI",
    "sg:tags":[
        "loan",
        "real estate"
    ],
    "wof:name":"American Home Mortgage",
    "wof:placetype":"venue"
},
  "geometry": {"coordinates":[-87.83742100000001,42.624346],"type":"Point"}
}