{
  "type": "Feature",
  "properties": {
    "iso:country":"US",
    "sg:address":"10368 Center Rd",
    "sg:city":"Thorp",
    "sg:classifiers":[
        {
            "category":"Organizations",
            "subcategory":"Membership Organization",
            "type":"Services"
        }
    ],
    "sg:phone":"+1 715 669 3442",
    "sg:postcode":"54771",
    "sg:province":"WI",
    "wof:name":"Womens International Bowl Assn",
    "wof:placetype":"venue"
},
  "geometry": {"coordinates":[-90.836297,44.988107],"type":"Point"}
}