{
  "type": "Feature",
  "properties": {
    "iso:country":"US",
    "sg:address":"545 W Dayton St",
    "sg:city":"Madison",
    "sg:classifiers":[
        {
            "category":"Professional",
            "type":"Services"
        }
    ],
    "sg:phone":"+1 608 266 6456",
    "sg:postcode":"53703",
    "sg:province":"WI",
    "sg:tags":[
        "establishment"
    ],
    "wof:name":"Teacher's Workshop",
    "wof:placetype":"venue"
},
  "geometry": {"coordinates":[-89.395905,43.070875],"type":"Point"}
}