{
  "type": "Feature",
  "properties": {
    "addr:full":"640 W Fulton St Waupaca WI 54981",
    "addr:housenumber":"640",
    "addr:postcode":"54981",
    "addr:street":"W Fulton St",
    "iso:country":"US",
    "sg:address":"640 W Fulton St",
    "sg:city":"Waupaca",
    "sg:classifiers":[
        {
            "category":"Restaurant",
            "type":"Food & Drink"
        }
    ],
    "sg:menulink":"http://www.allmenus.com/wi/waupaca/155254-hardees/menu/",
    "sg:phone":"+1 715 258 0220",
    "sg:postcode":"54981",
    "sg:province":"WI",
    "sg:tags":[
        "burger",
        "american"
    ],
    "wof:name":"Hardee's",
    "wof:placetype":"venue"
},
  "geometry": {"coordinates":[-89.096615,44.357982],"type":"Point"}
}