{
  "type": "Feature",
  "properties": {
    "addr:full":"50 N Main St Deerfield WI 53531",
    "addr:housenumber":"50",
    "addr:postcode":"53531",
    "addr:street":"N Main St",
    "iso:country":"US",
    "sg:address":"50 N Main St",
    "sg:city":"Deerfield",
    "sg:classifiers":[
        {
            "category":"Food & Beverages",
            "subcategory":"Liquor & Beverages",
            "type":"Retail Goods"
        }
    ],
    "sg:phone":"+1 608 764 1784",
    "sg:postcode":"53531",
    "sg:province":"WI",
    "wof:name":"Barley Pop Liquor Stop",
    "wof:placetype":"venue"
},
  "geometry": {"coordinates":[-89.075012,43.053404],"type":"Point"}
}