{
  "type": "Feature",
  "properties": {
    "addr:full":"406 Cherry St Evansville WI 53536",
    "addr:housenumber":"406",
    "addr:postcode":"53536",
    "addr:street":"Cherry St",
    "iso:country":"US",
    "sg:address":"406 Cherry St",
    "sg:city":"Evansville",
    "sg:classifiers":[
        {
            "category":"Shopping",
            "type":"Retail Goods"
        }
    ],
    "sg:phone":"+1 608 882 6156",
    "sg:postcode":"53536",
    "sg:province":"WI",
    "sg:tags":[
        "optical",
        "dispensing"
    ],
    "wof:name":"Katz-Eyez Inc",
    "wof:placetype":"venue"
},
  "geometry": {"coordinates":[-89.29608899999999,42.774858],"type":"Point"}
}