{
  "type": "Feature",
  "properties": {
    "iso:country":"US",
    "sg:address":"1401 E Mason St",
    "sg:city":"Green Bay",
    "sg:classifiers":[
        {
            "category":"Shopping",
            "subcategory":"Pharmacy",
            "type":"Retail Goods"
        }
    ],
    "sg:phone":"+1 920 435 7141",
    "sg:postcode":"54301",
    "sg:province":"WI",
    "wof:name":"Walgreens",
    "wof:placetype":"venue"
},
  "geometry": {"coordinates":[-87.99659800000001,44.499618],"type":"Point"}
}