{
  "type": "Feature",
  "properties": {
    "iso:country":"US",
    "sg:address":"11796 Weidner Rd",
    "sg:city":"Spring Green",
    "sg:classifiers":[
        {
            "category":"Farming",
            "subcategory":"Dairy Farm",
            "type":"Manufacturing & Wholesale Goods"
        }
    ],
    "sg:phone":"+1 608 588 2840",
    "sg:postcode":"53588",
    "sg:province":"WI",
    "sg:tags":[
        "field",
        "crop"
    ],
    "wof:name":"Thomas Feiner",
    "wof:placetype":"venue"
},
  "geometry": {"coordinates":[-90.028637,43.217108],"type":"Point"}
}