{
  "type": "Feature",
  "properties": {
    "iso:country":"US",
    "sg:address":"3054 S Chicago Ave",
    "sg:city":"Superior",
    "sg:classifiers":[
        {
            "category":"Arts & Performance",
            "subcategory":"Music",
            "type":"Entertainment"
        }
    ],
    "sg:phone":"+1 715 394 5343",
    "sg:postcode":"54880",
    "sg:province":"WI",
    "sg:tags":[
        "jockey",
        "disc"
    ],
    "wof:name":"Leif Productions Dj Service",
    "wof:placetype":"venue"
},
  "geometry": {"coordinates":[-92.197806,46.653269],"type":"Point"}
}