{
  "type": "Feature",
  "properties": {
    "iso:country":"US",
    "sg:address":"964 W Cecil St",
    "sg:city":"Neenah",
    "sg:classifiers":[
        {
            "category":"Social Services",
            "type":"Services"
        }
    ],
    "sg:phone":"+1 920 720 0085",
    "sg:postcode":"54956",
    "sg:province":"WI",
    "wof:name":"Kids Kart Club",
    "wof:placetype":"venue"
},
  "geometry": {"coordinates":[-88.486948,44.170953],"type":"Point"}
}