{
  "type": "Feature",
  "properties": {
    "iso:country":"US",
    "sg:address":"11762 Deer Lake Rd",
    "sg:city":"Tomahawk",
    "sg:classifiers":[
        {
            "category":"Building & Trades",
            "subcategory":"Construction",
            "type":"Services"
        }
    ],
    "sg:phone":"+1 715 453 5995",
    "sg:postcode":"54487",
    "sg:province":"WI",
    "sg:tags":[
        "housing",
        "commercial",
        "family",
        "contractor"
    ],
    "wof:name":"Whalen Construction Company",
    "wof:placetype":"venue"
},
  "geometry": {"coordinates":[-89.690292,45.540172],"type":"Point"}
}