{
  "type": "Feature",
  "properties": {
    "iso:country":"US",
    "sg:address":"6627 McKee Rd",
    "sg:city":"Madison",
    "sg:classifiers":[
        {
            "category":"Health Services",
            "subcategory":"Doctor",
            "type":"Services"
        }
    ],
    "sg:phone":"+1 608 848 5680",
    "sg:postcode":"53593",
    "sg:province":"WI",
    "sg:tags":[
        "dentist",
        "dental"
    ],
    "wof:name":"Maple Grove Dental SC",
    "wof:placetype":"venue"
},
  "geometry": {"coordinates":[-89.49212,43.015639],"type":"Point"}
}