{
  "type": "Feature",
  "properties": {
    "addr:full":"920 60th St Kenosha WI 53140",
    "addr:housenumber":"920",
    "addr:postcode":"53140",
    "addr:street":"60Th St",
    "iso:country":"US",
    "sg:address":"920 60th St",
    "sg:city":"Kenosha",
    "sg:classifiers":[
        {
            "category":"Social Services",
            "type":"Services"
        },
        {
            "category":"Personal",
            "type":"Services"
        }
    ],
    "sg:phone":"+1 262 654 5333",
    "sg:postcode":"53140",
    "sg:province":"WI",
    "sg:tags":[
        "family",
        "counselors-licensed",
        "individual",
        "marriage",
        "child",
        "professional",
        "counselor"
    ],
    "wof:name":"Heller Mary Kae Med",
    "wof:placetype":"venue"
},
  "geometry": {"coordinates":[-87.821794,42.580839],"type":"Point"}
}