{
  "type": "Feature",
  "properties": {
    "iso:country":"US",
    "sg:address":"111 Elm St",
    "sg:city":"Spooner",
    "sg:classifiers":[
        {
            "category":"Autos & Motor Vehicles",
            "subcategory":"Auto Supplies",
            "type":"Retail Goods"
        }
    ],
    "sg:phone":"+1 715 635 2165",
    "sg:postcode":"54801",
    "sg:province":"WI",
    "sg:tags":[
        "automobile",
        "parts"
    ],
    "wof:name":"Bumper To Bumper Auto Parts",
    "wof:placetype":"venue"
},
  "geometry": {"coordinates":[-91.88751,45.827538],"type":"Point"}
}