{
  "type": "Feature",
  "properties": {
    "addr:full":"8580 S Howell Ave Oak Creek WI 53154",
    "addr:housenumber":"8580",
    "addr:postcode":"53154",
    "addr:street":"S Howell Ave",
    "iso:country":"US",
    "sg:address":"8580 S Howell Ave",
    "sg:city":"Oak Creek",
    "sg:classifiers":[
        {
            "category":"Organizations",
            "subcategory":"Professional Association",
            "type":"Services"
        }
    ],
    "sg:phone":"+1 414 768 5844",
    "sg:postcode":"53154",
    "sg:province":"WI",
    "sg:tags":[
        "business"
    ],
    "wof:name":"Secub",
    "wof:placetype":"venue"
},
  "geometry": {"coordinates":[-87.912064,42.888021],"type":"Point"}
}