{
  "type": "Feature",
  "properties": {
    "iso:country":"US",
    "sg:address":"4419 Riverside Rd",
    "sg:city":"Waterford",
    "sg:classifiers":[
        {
            "category":"Freight",
            "type":"Transportation"
        }
    ],
    "sg:phone":"+1 262 534 4505",
    "sg:postcode":"53185",
    "sg:province":"WI",
    "sg:tags":[
        "broker",
        "trucking"
    ],
    "wof:name":"Cobra Delivery Inc",
    "wof:placetype":"venue"
},
  "geometry": {"coordinates":[-88.214868,42.775121],"type":"Point"}
}