{
  "type": "Feature",
  "properties": {
    "addr:full":"2800 E College Ave Appleton WI 54915",
    "addr:housenumber":"2800",
    "addr:postcode":"54915",
    "addr:street":"E College Ave",
    "iso:country":"US",
    "sg:address":"2800 E College Ave",
    "sg:city":"Appleton",
    "sg:classifiers":[
        {
            "category":"Communications",
            "subcategory":"Radio Station",
            "type":"Services"
        }
    ],
    "sg:phone":"+1 920 734 9226",
    "sg:postcode":"54915",
    "sg:province":"WI",
    "sg:tags":[
        "company",
        "broadcasting"
    ],
    "sg:website":"www.wapl.com",
    "wof:name":"WAPL",
    "wof:placetype":"venue"
},
  "geometry": {"coordinates":[-88.35718799999999,44.258489],"type":"Point"}
}