{
  "type": "Feature",
  "properties": {
    "addr:full":"675 N Brookfield Rd Brookfield WI 53045",
    "addr:housenumber":"675",
    "addr:postcode":"53045",
    "addr:street":"N Brookfield Rd",
    "iso:country":"US",
    "sg:address":"675 N Brookfield Rd",
    "sg:city":"Brookfield",
    "sg:classifiers":[
        {
            "category":"Insurance",
            "subcategory":"Insurance Agent",
            "type":"Services"
        }
    ],
    "sg:phone":"+1 262 786 0600",
    "sg:postcode":"53045",
    "sg:province":"WI",
    "wof:name":"Rural Insurance Co",
    "wof:placetype":"venue"
},
  "geometry": {"coordinates":[-88.146733,43.039563],"type":"Point"}
}