{
  "type": "Feature",
  "properties": {
    "iso:country":"US",
    "sg:address":"628 E Wisconsin St",
    "sg:city":"Hartford",
    "sg:classifiers":[
        {
            "category":"Building & Trades",
            "subcategory":"Construction",
            "type":"Services"
        }
    ],
    "sg:phone":"+1 262 673 2584",
    "sg:postcode":"53027",
    "sg:province":"WI",
    "sg:tags":[
        "painter"
    ],
    "wof:name":"Peters Painting Contractors",
    "wof:placetype":"venue"
},
  "geometry": {"coordinates":[-88.376593,43.320065],"type":"Point"}
}