{
  "type": "Feature",
  "properties": {
    "addr:full":"941 Ashwaubenon St Green Bay WI 54304",
    "addr:housenumber":"941",
    "addr:postcode":"54304",
    "addr:street":"Ashwaubenon St",
    "iso:country":"US",
    "sg:address":"941 Ashwaubenon St",
    "sg:city":"Green Bay",
    "sg:classifiers":[
        {
            "category":"Building & Trades",
            "subcategory":"Construction",
            "type":"Services"
        }
    ],
    "sg:phone":"+1 920 983 2334",
    "sg:postcode":"54304",
    "sg:province":"WI",
    "sg:tags":[
        "painter"
    ],
    "sg:website":"www.klein-dickert.com",
    "wof:name":"Klein-Dickert Paint Contr",
    "wof:placetype":"venue"
},
  "geometry": {"coordinates":[-88.08631099999999,44.462817],"type":"Point"}
}