{
  "type": "Feature",
  "properties": {
    "iso:country":"US",
    "sg:address":"9681 State Hwy 57",
    "sg:city":"Brussels",
    "sg:classifiers":[
        {
            "category":"Professional",
            "type":"Services"
        }
    ],
    "sg:phone":"+1 920 825 1424",
    "sg:postcode":"54204",
    "sg:province":"WI",
    "wof:name":"Brussels Service Ctr",
    "wof:placetype":"venue"
},
  "geometry": {"coordinates":[-87.619623,44.736498],"type":"Point"}
}