{
  "type": "Feature",
  "properties": {
    "iso:country":"US",
    "sg:address":"5705 Co Rd P",
    "sg:city":"Highland",
    "sg:classifiers":[
        {
            "category":"Farming",
            "subcategory":"Livestock Farm",
            "type":"Manufacturing & Wholesale Goods"
        }
    ],
    "sg:phone":"+1 608 929 7648",
    "sg:postcode":"53543",
    "sg:province":"WI",
    "sg:tags":[
        "feedlot",
        "hog",
        "or",
        "beef",
        "cattle"
    ],
    "wof:name":"Daniel Nankee",
    "wof:placetype":"venue"
},
  "geometry": {"coordinates":[-90.307874,43.092522],"type":"Point"}
}