{
  "type": "Feature",
  "properties": {
    "addr:full":"1250 Swan Rd De Pere WI 54115",
    "addr:housenumber":"1250",
    "addr:postcode":"54115",
    "addr:street":"Swan Rd",
    "iso:country":"US",
    "sg:address":"1250 Swan Rd",
    "sg:city":"De Pere",
    "sg:classifiers":[
        {
            "category":"Organizations",
            "subcategory":"Religious Organization",
            "type":"Services"
        }
    ],
    "sg:phone":"+1 920 336 7910",
    "sg:postcode":"54115",
    "sg:province":"WI",
    "sg:tags":[
        "church"
    ],
    "wof:name":"New Life Christian Fellowship",
    "wof:placetype":"venue"
},
  "geometry": {"coordinates":[-88.04199699999999,44.428757],"type":"Point"}
}