{
  "type": "Feature",
  "properties": {
    "iso:country":"US",
    "sg:address":"13731 Tannery Rd",
    "sg:city":"Mishicot",
    "sg:phone":"+1 920 755 4023",
    "sg:postcode":"54228",
    "sg:province":"WI",
    "sg:tags":[
        "farm",
        "soybean"
    ],
    "wof:name":"William Mohr",
    "wof:placetype":"venue"
},
  "geometry": {"coordinates":[-87.583468,44.267855],"type":"Point"}
}