{
  "type": "Feature",
  "properties": {
    "addr:full":"204 Dix St Columbus WI 53925",
    "addr:housenumber":"204",
    "addr:postcode":"53925",
    "addr:street":"Dix St",
    "iso:country":"US",
    "sg:address":"204 Dix St",
    "sg:city":"Columbus",
    "sg:classifiers":[
        {
            "category":"Food & Beverages",
            "subcategory":"Groceries & Convenience Stores",
            "type":"Retail Goods"
        }
    ],
    "sg:phone":"+1 920 623 2844",
    "sg:postcode":"53925",
    "sg:province":"WI",
    "sg:tags":[
        "station",
        "gas"
    ],
    "sg:website":"www.kwiktrip.com",
    "wof:name":"KWIK Trip",
    "wof:placetype":"venue"
},
  "geometry": {"coordinates":[-89.029143,43.343574],"type":"Point"}
}