{
  "type": "Feature",
  "properties": {
    "addr:full":"1709 Jefferson St Madison WI 53711",
    "addr:housenumber":"1709",
    "addr:postcode":"53711",
    "addr:street":"Jefferson St",
    "iso:country":"US",
    "sg:address":"1709 Jefferson St",
    "sg:city":"Madison",
    "sg:classifiers":[
        {
            "category":"Retail",
            "subcategory":"Animal Services",
            "type":"Services"
        }
    ],
    "sg:phone":"+1 608 251 0013",
    "sg:postcode":"53711",
    "sg:province":"WI",
    "wof:name":"Purrs and Paws Pet Sitting Svc",
    "wof:placetype":"venue"
},
  "geometry": {"coordinates":[-89.41463299999999,43.064154],"type":"Point"}
}