{
  "type": "Feature",
  "properties": {
    "iso:country":"US",
    "sg:address":"151 E Main St",
    "sg:city":"Stoughton",
    "sg:classifiers":[
        {
            "category":"Restaurant",
            "type":"Food & Drink"
        }
    ],
    "sg:phone":"+1 608 873 4422",
    "sg:postcode":"53589",
    "sg:province":"WI",
    "sg:tags":[
        "eating"
    ],
    "wof:name":"Sonnys",
    "wof:placetype":"venue"
},
  "geometry": {"coordinates":[-89.219674,42.916829],"type":"Point"}
}