{
  "type": "Feature",
  "properties": {
    "addr:full":"6917 Tottenham Rd Madison WI 53711",
    "addr:housenumber":"6917",
    "addr:postcode":"53711",
    "addr:street":"Tottenham Rd",
    "iso:country":"US",
    "sg:address":"6917 Tottenham Rd",
    "sg:city":"Madison",
    "sg:classifiers":[
        {
            "category":"Professional",
            "type":"Services"
        }
    ],
    "sg:phone":"+1 608 273 3867",
    "sg:postcode":"53711",
    "sg:province":"WI",
    "wof:name":"Lovepockets LLC",
    "wof:placetype":"venue"
},
  "geometry": {"coordinates":[-89.50194,43.030136],"type":"Point"}
}