{
  "type": "Feature",
  "properties": {
    "iso:country":"US",
    "sg:address":"4201 N Co Rd M",
    "sg:city":"Evansville",
    "sg:classifiers":[
        {
            "category":"Professional",
            "type":"Services"
        }
    ],
    "sg:phone":"+1 608 882 2523",
    "sg:postcode":"53536",
    "sg:province":"WI",
    "sg:tags":[
        "establishment"
    ],
    "wof:name":"Caxambas Associates",
    "wof:placetype":"venue"
},
  "geometry": {"coordinates":[-89.285605,42.73583],"type":"Point"}
}