{
  "type": "Feature",
  "properties": {
    "iso:country":"US",
    "sg:address":"140 Buffalo St",
    "sg:city":"Wisconsin Rapids",
    "sg:classifiers":[
        {
            "category":"Home & Garden",
            "subcategory":"Garden Supply",
            "type":"Retail Goods"
        }
    ],
    "sg:phone":"+1 715 421 0587",
    "sg:postcode":"54494",
    "sg:province":"WI",
    "sg:tags":[
        "nurseryman"
    ],
    "wof:name":"B & N Tauschek Nursery Company",
    "wof:placetype":"venue"
},
  "geometry": {"coordinates":[-89.780492,44.421517],"type":"Point"}
}