{
  "type": "Feature",
  "properties": {
    "iso:country":"US",
    "sg:address":"6338 906th St",
    "sg:city":"Elk Mound",
    "sg:classifiers":[
        {
            "category":"Building & Trades",
            "subcategory":"Construction",
            "type":"Services"
        }
    ],
    "sg:phone":"+1 715 879 5567",
    "sg:postcode":"54739",
    "sg:province":"WI",
    "sg:tags":[
        "house"
    ],
    "wof:name":"Wolf Cnstr of Chpwa Vlly",
    "wof:placetype":"venue"
},
  "geometry": {"coordinates":[-91.692072,44.90726],"type":"Point"}
}