{
  "type": "Feature",
  "properties": {
    "iso:country":"US",
    "sg:address":"400 Reid St",
    "sg:city":"De Pere",
    "sg:classifiers":[
        {
            "category":"Insurance",
            "subcategory":"Insurance Agent",
            "type":"Services"
        }
    ],
    "sg:phone":"+1 920 731 8700",
    "sg:postcode":"54115",
    "sg:province":"WI",
    "wof:name":"Tara Schultz Agency",
    "wof:placetype":"venue"
},
  "geometry": {"coordinates":[-88.073634,44.446799],"type":"Point"}
}