{
  "type": "Feature",
  "properties": {
    "iso:country":"US",
    "sg:address":"4901 Black Oak Dr",
    "sg:city":"Madison",
    "sg:classifiers":[
        {
            "category":"Communications",
            "type":"Services"
        }
    ],
    "sg:phone":"+1 608 277 0679",
    "sg:postcode":"53711",
    "sg:province":"WI",
    "wof:name":"Vectris Communications",
    "wof:placetype":"venue"
},
  "geometry": {"coordinates":[-89.462873,43.032776],"type":"Point"}
}