{
  "type": "Feature",
  "properties": {
    "iso:country":"US",
    "sg:address":"1337 70th Ave",
    "sg:city":"Roberts",
    "sg:classifiers":[
        {
            "category":"Building & Trades",
            "subcategory":"Construction",
            "type":"Services"
        }
    ],
    "sg:phone":"+1 715 749 3084",
    "sg:postcode":"54023",
    "sg:province":"WI",
    "sg:tags":[
        "contractor"
    ],
    "wof:name":"Rt Resurfacing Inc",
    "wof:placetype":"venue"
},
  "geometry": {"coordinates":[-92.524674,44.963611],"type":"Point"}
}