{
  "type": "Feature",
  "properties": {
    "iso:country":"US",
    "sg:address":"2201 Atwood Ave",
    "sg:city":"Madison",
    "sg:classifiers":[
        {
            "category":"Restaurant",
            "type":"Food & Drink"
        }
    ],
    "sg:phone":"+1 608 249 4333",
    "sg:postcode":"53704",
    "sg:province":"WI",
    "sg:tags":[
        "eating"
    ],
    "wof:name":"Harmony Bar & Grill",
    "wof:placetype":"venue"
},
  "geometry": {"coordinates":[-89.348525,43.093393],"type":"Point"}
}