{
  "type": "Feature",
  "properties": {
    "iso:country":"US",
    "sg:address":"6562 W Loon Lake Cir",
    "sg:city":"Shawano",
    "sg:classifiers":[
        {
            "category":"Building & Trades",
            "subcategory":"Landscaping Services",
            "type":"Services"
        }
    ],
    "sg:phone":"+1 715 526 5022",
    "sg:postcode":"54166",
    "sg:province":"WI",
    "sg:tags":[
        "tree"
    ],
    "wof:name":"Larsen Tree Trim & Lawn Svc",
    "wof:placetype":"venue"
},
  "geometry": {"coordinates":[-88.512217,44.827253],"type":"Point"}
}