{
  "type": "Feature",
  "properties": {
    "iso:country":"US",
    "sg:address":"609 Gilster St",
    "sg:city":"Onalaska",
    "sg:classifiers":[
        {
            "category":"Building & Trades",
            "subcategory":"Construction",
            "type":"Services"
        }
    ],
    "sg:phone":"+1 608 781 4155",
    "sg:postcode":"54650",
    "sg:province":"WI",
    "sg:tags":[
        "contractor"
    ],
    "wof:name":"Mark Miller Construction",
    "wof:placetype":"venue"
},
  "geometry": {"coordinates":[-91.20516000000001,43.871082],"type":"Point"}
}