{
  "type": "Feature",
  "properties": {
    "iso:country":"US",
    "sg:address":"5005 W Loomis Rd",
    "sg:city":"Greenfield",
    "sg:classifiers":[
        {
            "category":"Organizations",
            "subcategory":"Religious Organization",
            "type":"Services"
        }
    ],
    "sg:phone":"+1 414 817 9688",
    "sg:postcode":"53220",
    "sg:province":"WI",
    "sg:tags":[
        "church"
    ],
    "sg:website":"www.faithcc.us",
    "wof:name":"Faith Community Church",
    "wof:placetype":"venue"
},
  "geometry": {"coordinates":[-87.978595,42.951205],"type":"Point"}
}