{
  "type": "Feature",
  "properties": {
    "iso:country":"US",
    "sg:address":"763 N Milwaukee St",
    "sg:city":"Milwaukee",
    "sg:classifiers":[
        {
            "category":"Restaurant",
            "type":"Food & Drink"
        }
    ],
    "sg:phone":"+1 414 276 9646",
    "sg:postcode":"53202",
    "sg:province":"WI",
    "wof:name":"My Office",
    "wof:placetype":"venue"
},
  "geometry": {"coordinates":[-87.906826,43.040876],"type":"Point"}
}