{
  "type": "Feature",
  "properties": {
    "iso:country":"US",
    "sg:address":"3899 Park Rd",
    "sg:city":"Greenleaf",
    "sg:classifiers":[
        {
            "category":"Farming",
            "subcategory":"Livestock Farm",
            "type":"Manufacturing & Wholesale Goods"
        }
    ],
    "sg:phone":"+1 920 864 7562",
    "sg:postcode":"54126",
    "sg:province":"WI",
    "sg:tags":[
        "beef",
        "feedlot",
        "cattle"
    ],
    "wof:name":"Bruce Krahn",
    "wof:placetype":"venue"
},
  "geometry": {"coordinates":[-87.925422,44.284102],"type":"Point"}
}