{
  "type": "Feature",
  "properties": {
    "addr:full":"2137 W Greenfield Ave Milwaukee WI 53204",
    "addr:housenumber":"2137",
    "addr:postcode":"53204",
    "addr:street":"W Greenfield Ave",
    "iso:country":"US",
    "sg:address":"2137 W Greenfield Ave",
    "sg:city":"Milwaukee",
    "sg:classifiers":[
        {
            "category":"Social Services",
            "subcategory":"Job Training",
            "type":"Services"
        },
        {
            "category":"Social Services",
            "subcategory":"Child Care",
            "type":"Services"
        }
    ],
    "sg:phone":"+1 414 645 5350",
    "sg:postcode":"53204",
    "sg:province":"WI",
    "sg:tags":[
        "consultant",
        "nursery",
        "employment",
        "day"
    ],
    "wof:name":"Neighborhood Improvement Proje",
    "wof:placetype":"venue"
},
  "geometry": {"coordinates":[-87.93997400000001,43.017013],"type":"Point"}
}