{
  "type": "Feature",
  "properties": {
    "iso:country":"US",
    "sg:address":"8401 Murphy Dr",
    "sg:city":"Middleton",
    "sg:classifiers":[
        {
            "category":"Manufacturing",
            "subcategory":"Tools & Machinery",
            "type":"Manufacturing & Wholesale Goods"
        }
    ],
    "sg:phone":"+1 608 831 5773",
    "sg:postcode":"53562",
    "sg:province":"WI",
    "sg:tags":[
        "product",
        "electrical"
    ],
    "wof:name":"American Superconductor Corp",
    "wof:placetype":"venue"
},
  "geometry": {"coordinates":[-89.52625,43.098357],"type":"Point"}
}