{
  "type": "Feature",
  "properties": {
    "iso:country":"US",
    "sg:address":"905 Harrison St",
    "sg:city":"Green Bay",
    "sg:classifiers":[
        {
            "category":"Education",
            "subcategory":"School",
            "type":"Public Place"
        }
    ],
    "sg:phone":"+1 920 448 2106",
    "sg:postcode":"54303",
    "sg:province":"WI",
    "sg:tags":[
        "elementary"
    ],
    "wof:name":"Jefferson Elementary School",
    "wof:placetype":"venue"
},
  "geometry": {"coordinates":[-88.020212,44.528173],"type":"Point"}
}