{
  "type": "Feature",
  "properties": {
    "addr:full":"9421 W Pasanen Rd Exeland WI 54835",
    "addr:housenumber":"9421",
    "addr:postcode":"54835",
    "addr:street":"W Pasanen Rd",
    "iso:country":"US",
    "sg:address":"9421 W Pasanen Rd",
    "sg:city":"Exeland",
    "sg:classifiers":[
        {
            "category":"Farming",
            "subcategory":"Farm",
            "type":"Manufacturing & Wholesale Goods"
        }
    ],
    "sg:phone":"+1 715 943 2683",
    "sg:postcode":"54835",
    "sg:province":"WI",
    "wof:name":"Pasanen Farms",
    "wof:placetype":"venue"
},
  "geometry": {"coordinates":[-91.15853799999999,45.689723],"type":"Point"}
}