{
  "type": "Feature",
  "properties": {
    "iso:country":"US",
    "sg:address":"8501 W Lincoln Ave",
    "sg:city":"Milwaukee",
    "sg:classifiers":[
        {
            "category":"Shopping",
            "subcategory":"Computers & Home Electronics",
            "type":"Retail Goods"
        }
    ],
    "sg:phone":"+1 414 476 7091",
    "sg:postcode":"53227",
    "sg:province":"WI",
    "sg:tags":[
        "equipment",
        "dealer"
    ],
    "wof:name":"ASC Computer Wholesale",
    "wof:placetype":"venue"
},
  "geometry": {"coordinates":[-88.01983799999999,43.002728],"type":"Point"}
}