{
  "type": "Feature",
  "properties": {
    "addr:full":"10214 W Greenfield Ave Milwaukee WI 53214",
    "addr:housenumber":"10214",
    "addr:postcode":"53214",
    "addr:street":"W Greenfield Ave",
    "iso:country":"US",
    "sg:address":"10214 W Greenfield Ave",
    "sg:city":"Milwaukee",
    "sg:classifiers":[
        {
            "category":"Autos & Motor Vehicles",
            "subcategory":"Fuel & Gas Station",
            "type":"Retail Goods"
        },
        {
            "category":"Autos & Motor Vehicles",
            "subcategory":"Automobile Sales",
            "type":"Retail Goods"
        },
        {
            "category":"Autos & Motor Vehicles",
            "subcategory":"Auto Supplies",
            "type":"Retail Goods"
        },
        {
            "category":"Retail",
            "subcategory":"Auto Repair",
            "type":"Services"
        }
    ],
    "sg:phone":"+1 414 616 7209",
    "sg:postcode":"53214",
    "sg:province":"WI",
    "sg:tags":[
        "muffler",
        "brake",
        "sport",
        "system",
        "equipment",
        "lube",
        "electrical",
        "equipment-service",
        "performance",
        "racing",
        "wheel",
        "exhaust",
        "oil",
        "accessory",
        "servicing-automotive",
        "balancing",
        "axle",
        "wheels-aligning",
        "alignment-frame",
        "air conditioning",
        "car",
        "truck",
        "inspection"
    ],
    "sg:website":"http://www.tomtracker.com/redirect.cfm?bID=4837&hID=111353",
    "wof:name":"Meineke Car Care Center",
    "wof:placetype":"venue"
},
  "geometry": {"coordinates":[-88.03979699999999,43.01652],"type":"Point"}
}