{
  "type": "Feature",
  "properties": {
    "iso:country":"US",
    "sg:address":"7202 Co Rd D",
    "sg:city":"Albany",
    "sg:classifiers":[
        {
            "category":"Local Transit",
            "type":"Transportation"
        }
    ],
    "sg:phone":"+1 608 938 1300",
    "sg:postcode":"53502",
    "sg:province":"WI",
    "sg:tags":[
        "passenger",
        "limousine"
    ],
    "wof:name":"Abracadabra Limousine & Tuxedo",
    "wof:placetype":"venue"
},
  "geometry": {"coordinates":[-89.521345,42.766353],"type":"Point"}
}