{
  "type": "Feature",
  "properties": {
    "iso:country":"US",
    "sg:address":"1520 N Eugene St",
    "sg:city":"Appleton",
    "sg:classifiers":[
        {
            "category":"Real Estate",
            "subcategory":"Real Estate Agent",
            "type":"Services"
        }
    ],
    "sg:phone":"+1 920 731 7708",
    "sg:postcode":"54914",
    "sg:province":"WI",
    "wof:name":"Dove Real Estate Inv LLP",
    "wof:placetype":"venue"
},
  "geometry": {"coordinates":[-88.432394,44.277077],"type":"Point"}
}