{
  "type": "Feature",
  "properties": {
    "iso:country":"US",
    "sg:address":"1910 N 6th St",
    "sg:city":"Wausau",
    "sg:classifiers":[
        {
            "category":"Food & Beverages",
            "subcategory":"Meat & Fish",
            "type":"Retail Goods"
        }
    ],
    "sg:phone":"+1 715 845 5123",
    "sg:postcode":"54403",
    "sg:province":"WI",
    "wof:name":"Zillman Meat Market",
    "wof:placetype":"venue"
},
  "geometry": {"coordinates":[-89.623476,44.972713],"type":"Point"}
}