{
  "type": "Feature",
  "properties": {
    "iso:country":"US",
    "sg:address":"503 N Lake Ave",
    "sg:city":"Twin Lakes",
    "sg:classifiers":[
        {
            "category":"Insurance",
            "subcategory":"Insurance Agent",
            "type":"Services"
        }
    ],
    "sg:phone":"+1 262 279 3315",
    "sg:postcode":"53181",
    "sg:province":"WI",
    "wof:name":"Richard Mascolino Agency",
    "wof:placetype":"venue"
},
  "geometry": {"coordinates":[-88.246776,42.536097],"type":"Point"}
}