{
  "type": "Feature",
  "properties": {
    "iso:country":"US",
    "sg:address":"102 E Bell St",
    "sg:city":"Neenah",
    "sg:classifiers":[
        {
            "category":"Restaurant",
            "type":"Food & Drink"
        }
    ],
    "sg:phone":"+1 920 722 6666",
    "sg:postcode":"54956",
    "sg:province":"WI",
    "sg:tags":[
        "a",
        "as",
        "fast",
        "operates"
    ],
    "wof:name":"McDonalds",
    "wof:placetype":"venue"
},
  "geometry": {"coordinates":[-88.45957300000001,44.157031],"type":"Point"}
}