{
  "type": "Feature",
  "properties": {
    "iso:country":"US",
    "sg:address":"101 Canal St",
    "sg:city":"Little Chute",
    "sg:classifiers":[
        {
            "category":"Retail",
            "subcategory":"Funeral Services",
            "type":"Services"
        }
    ],
    "sg:phone":"+1 920 788 3321",
    "sg:postcode":"54140",
    "sg:province":"WI",
    "wof:name":"Verkuilen Funeral Home",
    "wof:placetype":"venue"
},
  "geometry": {"coordinates":[-88.31390399999999,44.277291],"type":"Point"}
}