{
  "type": "Feature",
  "properties": {
    "iso:country":"US",
    "sg:address":"15772 250th St",
    "sg:city":"Cadott",
    "sg:classifiers":[
        {
            "category":"Building & Trades",
            "subcategory":"Electrical",
            "type":"Services"
        }
    ],
    "sg:phone":"+1 715 289 3599",
    "sg:postcode":"54727",
    "sg:province":"WI",
    "sg:tags":[
        "electrical",
        "contractor"
    ],
    "wof:name":"Dennis Harm",
    "wof:placetype":"venue"
},
  "geometry": {"coordinates":[-91.166236,45.070699],"type":"Point"}
}