{
  "type": "Feature",
  "properties": {
    "iso:country":"US",
    "sg:address":"3713 Division St",
    "sg:city":"Manitowoc",
    "sg:classifiers":[
        {
            "category":"Professional",
            "type":"Services"
        }
    ],
    "sg:phone":"+1 920 683 3989",
    "sg:postcode":"54220",
    "sg:province":"WI",
    "sg:tags":[
        "establishment"
    ],
    "wof:name":"Secrets Tavrn",
    "wof:placetype":"venue"
},
  "geometry": {"coordinates":[-87.69570899999999,44.081067],"type":"Point"}
}