{
  "type": "Feature",
  "properties": {
    "iso:country":"US",
    "sg:address":"1521 Primrose Ln",
    "sg:city":"Janesville",
    "sg:classifiers":[
        {
            "category":"Personal",
            "subcategory":"Beauty Salon",
            "type":"Services"
        }
    ],
    "sg:phone":"+1 608 756 2772",
    "sg:postcode":"53545",
    "sg:province":"WI",
    "sg:tags":[
        "shop",
        "barber"
    ],
    "wof:name":"Galaxy Hair Designs",
    "wof:placetype":"venue"
},
  "geometry": {"coordinates":[-89.003199,42.713727],"type":"Point"}
}