{
  "type": "Feature",
  "properties": {
    "iso:country":"US",
    "sg:address":"3875 Pine Ridge Ct",
    "sg:city":"Green Bay",
    "sg:classifiers":[
        {
            "category":"Wholesale",
            "subcategory":"Durable Goods & Equipment",
            "type":"Manufacturing & Wholesale Goods"
        }
    ],
    "sg:phone":"+1 920 434 2746",
    "sg:postcode":"54313",
    "sg:province":"WI",
    "wof:name":"Pats Wholesale",
    "wof:placetype":"venue"
},
  "geometry": {"coordinates":[-88.132207,44.605991],"type":"Point"}
}