{
  "type": "Feature",
  "properties": {
    "iso:country":"US",
    "sg:address":"4109 Kinglet Cir",
    "sg:city":"Wausau",
    "sg:classifiers":[
        {
            "category":"Retail",
            "subcategory":"Repair Shop",
            "type":"Services"
        },
        {
            "category":"Building & Trades",
            "subcategory":"Construction",
            "type":"Services"
        }
    ],
    "sg:phone":"+1 715 359 2744",
    "sg:postcode":"54401",
    "sg:province":"WI",
    "sg:tags":[
        "windows"
    ],
    "wof:name":"Don's Window & Screen Repair",
    "wof:placetype":"venue"
},
  "geometry": {"coordinates":[-89.64133200000001,44.920257],"type":"Point"}
}