{
  "type": "Feature",
  "properties": {
    "addr:full":"2401 W Broadway Monona WI 53716",
    "addr:housenumber":"2401",
    "addr:postcode":"53716",
    "addr:street":"W Broadway",
    "iso:country":"US",
    "sg:address":"2401 W Broadway",
    "sg:city":"Monona",
    "sg:classifiers":[
        {
            "category":"Banks & Credit Unions",
            "subcategory":"Bank",
            "type":"Services"
        }
    ],
    "sg:phone":"+1 608 226 8800",
    "sg:postcode":"53716",
    "sg:province":"WI",
    "sg:tags":[
        "cashing",
        "check"
    ],
    "wof:name":"Cash Store",
    "wof:placetype":"venue"
},
  "geometry": {"coordinates":[-89.351296,43.047018],"type":"Point"}
}