{
  "type": "Feature",
  "properties": {
    "iso:country":"US",
    "sg:address":"8894 State Hwy 57",
    "sg:city":"Luxemburg",
    "sg:classifiers":[
        {
            "category":"Insurance",
            "subcategory":"Insurance Agent",
            "type":"Services"
        }
    ],
    "sg:phone":"+1 920 435 2320",
    "sg:postcode":"54217",
    "sg:province":"WI",
    "wof:name":"Leroy Mary A Insurance",
    "wof:placetype":"venue"
},
  "geometry": {"coordinates":[-87.757339,44.645781],"type":"Point"}
}