{
  "type": "Feature",
  "properties": {
    "iso:country":"US",
    "sg:address":"3155 State Hwy 73",
    "sg:city":"Columbus",
    "sg:classifiers":[
        {
            "category":"Home & Garden",
            "subcategory":"Garden Supply",
            "type":"Retail Goods"
        }
    ],
    "sg:phone":"+1 920 484 3834",
    "sg:postcode":"53925",
    "sg:province":"WI",
    "sg:tags":[
        "repair",
        "lawn",
        "provides",
        "mower"
    ],
    "wof:name":"Kirchberg Repair & Svc",
    "wof:placetype":"venue"
},
  "geometry": {"coordinates":[-89.004881,43.393851],"type":"Point"}
}