{
  "type": "Feature",
  "properties": {
    "iso:country":"US",
    "sg:address":"400 W Silver Spring Dr",
    "sg:city":"Milwaukee",
    "sg:classifiers":[
        {
            "category":"Personal",
            "type":"Services"
        },
        {
            "category":"Personal",
            "subcategory":"Beauty Salon",
            "type":"Services"
        }
    ],
    "sg:phone":"+1 414 962 7266",
    "sg:postcode":"53217",
    "sg:province":"WI",
    "sg:tags":[
        "shop",
        "electrolysis"
    ],
    "wof:name":"Salon Of Electrolysis",
    "wof:placetype":"venue"
},
  "geometry": {"coordinates":[-87.915477,43.118646],"type":"Point"}
}