{
  "type": "Feature",
  "properties": {
    "addr:full":"100 N Main St Hartford WI 53027",
    "addr:housenumber":"100",
    "addr:postcode":"53027",
    "addr:street":"N Main St",
    "iso:country":"US",
    "sg:address":"100 N Main St",
    "sg:city":"Hartford",
    "sg:classifiers":[
        {
            "category":"Shopping",
            "subcategory":"Gifts & Souvenirs",
            "type":"Retail Goods"
        }
    ],
    "sg:phone":"+1 262 670 1400",
    "sg:postcode":"53027",
    "sg:province":"WI",
    "wof:name":"Mole Hole of Hartford",
    "wof:placetype":"venue"
},
  "geometry": {"coordinates":[-88.378874,43.319569],"type":"Point"}
}