{
  "type": "Feature",
  "properties": {
    "iso:country":"US",
    "sg:address":"1236 Co Rd Ff",
    "sg:city":"Sheboygan",
    "sg:classifiers":[
        {
            "category":"Education",
            "subcategory":"School",
            "type":"Public Place"
        }
    ],
    "sg:phone":"+1 920 565 4457",
    "sg:postcode":"53083",
    "sg:province":"WI",
    "wof:name":"Northview Elementary",
    "wof:placetype":"venue"
},
  "geometry": {"coordinates":[-87.757452,43.84885],"type":"Point"}
}