{
  "type": "Feature",
  "properties": {
    "iso:country":"US",
    "sg:address":"9517 W Grantosa Dr",
    "sg:city":"Milwaukee",
    "sg:classifiers":[
        {
            "category":"Building & Trades",
            "subcategory":"Construction",
            "type":"Services"
        }
    ],
    "sg:phone":"+1 414 463 4510",
    "sg:postcode":"53222",
    "sg:province":"WI",
    "sg:tags":[
        "hanging",
        "contractor"
    ],
    "wof:name":"Schaefer Painting Co Inc",
    "wof:placetype":"venue"
},
  "geometry": {"coordinates":[-88.034702,43.094682],"type":"Point"}
}