{
  "type": "Feature",
  "properties": {
    "iso:country":"US",
    "sg:address":"7826 Mineral Point Rd",
    "sg:city":"Madison",
    "sg:classifiers":[
        {
            "category":"Retail",
            "subcategory":"Repair Shop",
            "type":"Services"
        }
    ],
    "sg:phone":"+1 608 233 7717",
    "sg:postcode":"53717",
    "sg:province":"WI",
    "sg:tags":[
        "picture",
        "framing"
    ],
    "wof:name":"D & R U-Frame-It Inc",
    "wof:placetype":"venue"
},
  "geometry": {"coordinates":[-89.519699,43.060578],"type":"Point"}
}