{
  "type": "Feature",
  "properties": {
    "addr:full":"114 Lake St Mukwonago WI 53149",
    "addr:housenumber":"114",
    "addr:postcode":"53149",
    "addr:street":"Lake St",
    "iso:country":"US",
    "sg:address":"114 Lake St",
    "sg:city":"Mukwonago",
    "sg:classifiers":[
        {
            "category":"Retail",
            "subcategory":"Portrait Studio",
            "type":"Services"
        }
    ],
    "sg:phone":"+1 262 363 4049",
    "sg:postcode":"53149",
    "sg:province":"WI",
    "sg:tags":[
        "photo"
    ],
    "wof:name":"You Nique Photography By Hitt",
    "wof:placetype":"venue"
},
  "geometry": {"coordinates":[-88.33324,42.864985],"type":"Point"}
}