{
  "type": "Feature",
  "properties": {
    "iso:country":"US",
    "sg:address":"704 Michigan St",
    "sg:city":"Sturgeon Bay",
    "sg:classifiers":[
        {
            "category":"Building & Trades",
            "subcategory":"Construction",
            "type":"Services"
        }
    ],
    "sg:phone":"+1 920 743 9071",
    "sg:postcode":"54235",
    "sg:province":"WI",
    "sg:tags":[
        "house"
    ],
    "wof:name":"Peninsula Builders",
    "wof:placetype":"venue"
},
  "geometry": {"coordinates":[-87.370892,44.835264],"type":"Point"}
}