{
  "type": "Feature",
  "properties": {
    "addr:full":"8319 Hwy 38 Caledonia WI 53108",
    "addr:housenumber":"8319",
    "addr:postcode":"53108",
    "addr:street":"Hwy 38",
    "iso:country":"US",
    "sg:address":"8319 Hwy 38",
    "sg:city":"Caledonia",
    "sg:classifiers":[
        {
            "category":"Sports & Exercise",
            "subcategory":"Stables",
            "type":"Entertainment"
        }
    ],
    "sg:postcode":"53108",
    "sg:province":"WI",
    "sg:tags":[
        "riding",
        "horseback"
    ],
    "wof:name":"Dreamcatcher Farm",
    "wof:placetype":"venue"
},
  "geometry": {"coordinates":[-87.88421200000001,42.814018],"type":"Point"}
}