{
  "type": "Feature",
  "properties": {
    "iso:country":"US",
    "sg:address":"1383 W Wisconsin Ave",
    "sg:city":"Oconomowoc",
    "sg:classifiers":[
        {
            "category":"Autos & Motor Vehicles",
            "subcategory":"Automobile Sales",
            "type":"Retail Goods"
        }
    ],
    "sg:phone":"+1 262 567 0050",
    "sg:postcode":"53066",
    "sg:province":"WI",
    "sg:tags":[
        "used"
    ],
    "wof:name":"U-Haul",
    "wof:placetype":"venue"
},
  "geometry": {"coordinates":[-88.522522,43.120846],"type":"Point"}
}