{
  "type": "Feature",
  "properties": {
    "iso:country":"US",
    "sg:address":"327 Birch Ln",
    "sg:city":"Reedsville",
    "sg:classifiers":[
        {
            "category":"Professional",
            "subcategory":"Business Services",
            "type":"Services"
        }
    ],
    "sg:phone":"+1 920 754 1185",
    "sg:postcode":"54230",
    "sg:province":"WI",
    "wof:name":"Heartland Promotions",
    "wof:placetype":"venue"
},
  "geometry": {"coordinates":[-87.953374,44.157073],"type":"Point"}
}