{
  "type": "Feature",
  "properties": {
    "iso:country":"US",
    "sg:address":"8525 Marsh Rd",
    "sg:city":"Waterford",
    "sg:phone":"+1 262 662 2324",
    "sg:postcode":"53185",
    "sg:province":"WI",
    "sg:tags":[
        "farm",
        "corn",
        "soybean"
    ],
    "wof:name":"Schrank Wilbert",
    "wof:placetype":"venue"
},
  "geometry": {"coordinates":[-88.247265,42.834395],"type":"Point"}
}