{
  "type": "Feature",
  "properties": {
    "iso:country":"US",
    "sg:address":"220 Hargrove Pl",
    "sg:city":"West Bend",
    "sg:classifiers":[
        {
            "category":"Professional",
            "subcategory":"Business Services",
            "type":"Services"
        }
    ],
    "sg:phone":"+1 262 335 2613",
    "sg:postcode":"53095",
    "sg:province":"WI",
    "wof:name":"Sutton Sales",
    "wof:placetype":"venue"
},
  "geometry": {"coordinates":[-88.170249,43.404478],"type":"Point"}
}