{
  "type": "Feature",
  "properties": {
    "iso:country":"US",
    "sg:address":"508 Front St",
    "sg:city":"Clinton",
    "sg:classifiers":[
        {
            "category":"Social Services",
            "type":"Services"
        }
    ],
    "sg:phone":"+1 608 676 4600",
    "sg:postcode":"53525",
    "sg:province":"WI",
    "sg:tags":[
        "organization",
        "welfare"
    ],
    "wof:name":"Senior Citizens Ctr",
    "wof:placetype":"venue"
},
  "geometry": {"coordinates":[-88.865094,42.55429],"type":"Point"}
}