{
  "type": "Feature",
  "properties": {
    "addr:full":"9725 S 54th St Franklin WI 53132",
    "addr:housenumber":"9725",
    "addr:postcode":"53132",
    "addr:street":"S 54Th St",
    "iso:country":"US",
    "sg:address":"9725 S 54th St",
    "sg:city":"Franklin",
    "sg:classifiers":[
        {
            "category":"Wholesale",
            "subcategory":"Fruits & Vegetables",
            "type":"Manufacturing & Wholesale Goods"
        }
    ],
    "sg:phone":"+1 414 421 5805",
    "sg:postcode":"53132",
    "sg:province":"WI",
    "sg:tags":[
        "veggie"
    ],
    "wof:name":"El Patron Fresh Produce Inc",
    "wof:placetype":"venue"
},
  "geometry": {"coordinates":[-87.984714,42.868332],"type":"Point"}
}