{
  "type": "Feature",
  "properties": {
    "iso:country":"US",
    "sg:address":"105 E Richmond St",
    "sg:city":"Shawano",
    "sg:classifiers":[
        {
            "category":"Social Services",
            "subcategory":"Adult Care",
            "type":"Services"
        }
    ],
    "sg:phone":"+1 715 524 5202",
    "sg:postcode":"54166",
    "sg:province":"WI",
    "sg:tags":[
        "house",
        "halfway"
    ],
    "wof:name":"New Era House",
    "wof:placetype":"venue"
},
  "geometry": {"coordinates":[-88.609066,44.774697],"type":"Point"}
}