{
  "type": "Feature",
  "properties": {
    "iso:country":"US",
    "sg:address":"2556 Hamburg Ridge Rd",
    "sg:city":"Stoddard",
    "sg:classifiers":[
        {
            "category":"Farming",
            "subcategory":"Dairy Farm",
            "type":"Manufacturing & Wholesale Goods"
        }
    ],
    "sg:phone":"+1 608 483 2298",
    "sg:postcode":"54658",
    "sg:province":"WI",
    "wof:name":"Hamburg Hills Farm",
    "wof:placetype":"venue"
},
  "geometry": {"coordinates":[-91.15004999999999,43.693514],"type":"Point"}
}