{
  "type": "Feature",
  "properties": {
    "iso:country":"US",
    "sg:address":"1250 Park Ave",
    "sg:city":"Columbus",
    "sg:classifiers":[
        {
            "category":"Autos & Motor Vehicles",
            "subcategory":"Fuel & Gas Station",
            "type":"Retail Goods"
        }
    ],
    "sg:phone":"+1 920 623 4355",
    "sg:postcode":"53925",
    "sg:province":"WI",
    "sg:tags":[
        "grocery"
    ],
    "wof:name":"Chestor Bandits Store Inc",
    "wof:placetype":"venue"
},
  "geometry": {"coordinates":[-89.025857,43.329886],"type":"Point"}
}