{
  "type": "Feature",
  "properties": {
    "iso:country":"US",
    "sg:address":"139 E Wisconsin Ave",
    "sg:city":"Oconomowoc",
    "sg:classifiers":[
        {
            "category":"Home & Garden",
            "subcategory":"Building Materials",
            "type":"Retail Goods"
        }
    ],
    "sg:phone":"+1 262 567 7210",
    "sg:postcode":"53066",
    "sg:province":"WI",
    "sg:tags":[
        "paint",
        "related",
        "supply"
    ],
    "wof:name":"Accent On Color",
    "wof:placetype":"venue"
},
  "geometry": {"coordinates":[-88.497886,43.110795],"type":"Point"}
}