{
  "type": "Feature",
  "properties": {
    "iso:country":"US",
    "sg:address":"1820 Layard Ave",
    "sg:city":"Racine",
    "sg:classifiers":[
        {
            "category":"Manufacturing",
            "subcategory":"Printing",
            "type":"Manufacturing & Wholesale Goods"
        }
    ],
    "sg:phone":"+1 262 634 6100",
    "sg:postcode":"53404",
    "sg:province":"WI",
    "sg:tags":[
        "printer"
    ],
    "wof:name":"TMS Inc",
    "wof:placetype":"venue"
},
  "geometry": {"coordinates":[-87.801378,42.750188],"type":"Point"}
}