{
  "type": "Feature",
  "properties": {
    "iso:country":"US",
    "sg:address":"233 Dodge St",
    "sg:city":"Kaukauna",
    "sg:classifiers":[
        {
            "category":"Real Estate",
            "subcategory":"Real Estate Agent",
            "type":"Services"
        }
    ],
    "sg:phone":"+1 920 766 5717",
    "sg:postcode":"54130",
    "sg:province":"WI",
    "wof:name":"Vanevenhoven Realty",
    "wof:placetype":"venue"
},
  "geometry": {"coordinates":[-88.27077800000001,44.276334],"type":"Point"}
}