{
  "type": "Feature",
  "properties": {
    "iso:country":"US",
    "sg:address":"3460 Levendoski Ln",
    "sg:city":"Chaseburg",
    "sg:classifiers":[
        {
            "category":"Professional",
            "subcategory":"Accounting & Tax Preparation",
            "type":"Services"
        }
    ],
    "sg:phone":"+1 608 483 2435",
    "sg:postcode":"54621",
    "sg:province":"WI",
    "wof:name":"ABC Accounting Service",
    "wof:placetype":"venue"
},
  "geometry": {"coordinates":[-91.134015,43.606015],"type":"Point"}
}