{
  "type": "Feature",
  "properties": {
    "iso:country":"US",
    "sg:address":"1670 S Main St",
    "sg:city":"West Bend",
    "sg:classifiers":[
        {
            "category":"Shopping",
            "subcategory":"Clothing, Apparel, & Fashions",
            "type":"Retail Goods"
        }
    ],
    "sg:phone":"+1 262 334 3310",
    "sg:postcode":"53095",
    "sg:province":"WI",
    "sg:website":"www.dressbarn.com",
    "wof:name":"Dress Barn",
    "wof:placetype":"venue"
},
  "geometry": {"coordinates":[-88.181136,43.40046],"type":"Point"}
}