{
  "type": "Feature",
  "properties": {
    "addr:full":"10514 7th St Sturtevant WI 53177",
    "addr:housenumber":"10514",
    "addr:postcode":"53177",
    "addr:street":"7Th St",
    "iso:country":"US",
    "sg:address":"10514 7th St",
    "sg:city":"Sturtevant",
    "sg:classifiers":[
        {
            "category":"Sports & Exercise",
            "subcategory":"Gym",
            "type":"Entertainment"
        }
    ],
    "sg:phone":"+1 262 859 2548",
    "sg:postcode":"53177",
    "sg:province":"WI",
    "sg:tags":[
        "fitness",
        "physical",
        "facility"
    ],
    "wof:name":"Palermo LLC",
    "wof:placetype":"venue"
},
  "geometry": {"coordinates":[-87.935678,42.65513],"type":"Point"}
}