{
  "type": "Feature",
  "properties": {
    "iso:country":"US",
    "sg:address":"7324 Lincoln Rd",
    "sg:city":"Van Dyne",
    "sg:classifiers":[
        {
            "category":"Farming",
            "subcategory":"Dairy Farm",
            "type":"Manufacturing & Wholesale Goods"
        }
    ],
    "sg:phone":"+1 920 688 5027",
    "sg:postcode":"54979",
    "sg:province":"WI",
    "wof:name":"Glory Farms",
    "wof:placetype":"venue"
},
  "geometry": {"coordinates":[-88.526529,43.879143],"type":"Point"}
}