{
  "type": "Feature",
  "properties": {
    "iso:country":"US",
    "sg:address":"445 River Dr",
    "sg:city":"Black River Falls",
    "sg:classifiers":[
        {
            "category":"Real Estate",
            "subcategory":"Real Estate Agent",
            "type":"Services"
        }
    ],
    "sg:phone":"+1 715 284 9800",
    "sg:postcode":"54615",
    "sg:province":"WI",
    "wof:name":"Heritage Real Estate",
    "wof:placetype":"venue"
},
  "geometry": {"coordinates":[-90.85218,44.285974],"type":"Point"}
}