{
  "type": "Feature",
  "properties": {
    "iso:country":"US",
    "sg:address":"307 W Washington St",
    "sg:city":"Valders",
    "sg:classifiers":[
        {
            "category":"Manufacturing",
            "subcategory":"Signs",
            "type":"Manufacturing & Wholesale Goods"
        }
    ],
    "sg:phone":"+1 920 775 9222",
    "sg:postcode":"54245",
    "sg:province":"WI",
    "wof:name":"Christel Sign",
    "wof:placetype":"venue"
},
  "geometry": {"coordinates":[-87.889548,44.066036],"type":"Point"}
}