{
  "type": "Feature",
  "properties": {
    "addr:full":"30626 Co Hwy F New Auburn WI 54757",
    "addr:housenumber":"30626",
    "addr:postcode":"54757",
    "addr:street":"Co Hwy F",
    "iso:country":"US",
    "sg:address":"30626 Co Hwy F",
    "sg:city":"New Auburn",
    "sg:classifiers":[
        {
            "category":"Manufacturing",
            "subcategory":"Wood Products",
            "type":"Manufacturing & Wholesale Goods"
        }
    ],
    "sg:phone":"+1 715 237 2990",
    "sg:postcode":"54757",
    "sg:province":"WI",
    "sg:tags":[
        "mfg"
    ],
    "wof:name":"Twin Lakes Builders",
    "wof:placetype":"venue"
},
  "geometry": {"coordinates":[-91.520186,45.287619],"type":"Point"}
}