{
  "type": "Feature",
  "properties": {
    "iso:country":"US",
    "sg:address":"207 Ellis St",
    "sg:city":"Kewaunee",
    "sg:classifiers":[
        {
            "category":"Bars & Pubs",
            "type":"Food & Drink"
        }
    ],
    "sg:phone":"+1 920 388 2162",
    "sg:postcode":"54216",
    "sg:province":"WI",
    "sg:tags":[
        "drinking"
    ],
    "wof:name":"Goose Nest The",
    "wof:placetype":"venue"
},
  "geometry": {"coordinates":[-87.50297,44.458364],"type":"Point"}
}