{
  "type": "Feature",
  "properties": {
    "addr:full":"2604 Aspen Ln Eagle River WI 54521",
    "addr:housenumber":"2604",
    "addr:postcode":"54521",
    "addr:street":"Aspen Ln",
    "iso:country":"US",
    "sg:address":"2604 Aspen Ln",
    "sg:city":"Eagle River",
    "sg:classifiers":[
        {
            "category":"Travel",
            "subcategory":"Hotels & Motels",
            "type":"Entertainment"
        }
    ],
    "sg:phone":"+1 715 479 1357",
    "sg:postcode":"54521",
    "sg:province":"WI",
    "sg:tags":[
        "cottage",
        "operation",
        "cabin"
    ],
    "wof:name":"Tamarack Timbers Cottages",
    "wof:placetype":"venue"
},
  "geometry": {"coordinates":[-89.384913,45.970675],"type":"Point"}
}