{
  "type": "Feature",
  "properties": {
    "iso:country":"US",
    "sg:address":"300 Miner Ave W",
    "sg:city":"Ladysmith",
    "sg:classifiers":[
        {
            "category":"Government",
            "subcategory":"Office",
            "type":"Public Place"
        }
    ],
    "sg:phone":"+1 715 532 7633",
    "sg:postcode":"54848",
    "sg:province":"WI",
    "sg:tags":[
        "general"
    ],
    "wof:name":"State of Wis",
    "wof:placetype":"venue"
},
  "geometry": {"coordinates":[-91.10467,45.464189],"type":"Point"}
}