{
  "type": "Feature",
  "properties": {
    "iso:country":"US",
    "sg:address":"115 S 3rd St E",
    "sg:city":"Fort Atkinson",
    "sg:classifiers":[
        {
            "category":"Professional",
            "subcategory":"Business Services",
            "type":"Services"
        }
    ],
    "sg:phone":"+1 920 563 3734",
    "sg:postcode":"53538",
    "sg:province":"WI",
    "wof:name":"Bodger Growth Enterprises LLC",
    "wof:placetype":"venue"
},
  "geometry": {"coordinates":[-88.835592,42.925962],"type":"Point"}
}