{
  "type": "Feature",
  "properties": {
    "addr:full":"109 S Main St Marion WI 54950",
    "addr:housenumber":"109",
    "addr:postcode":"54950",
    "addr:street":"S Main St",
    "iso:country":"US",
    "sg:address":"109 S Main St",
    "sg:city":"Marion",
    "sg:classifiers":[
        {
            "category":"Autos & Motor Vehicles",
            "subcategory":"Recreational Vehicle Sales",
            "type":"Retail Goods"
        }
    ],
    "sg:phone":"+1 715 754 4485",
    "sg:postcode":"54950",
    "sg:province":"WI",
    "wof:name":"Gold Star Motorsports",
    "wof:placetype":"venue"
},
  "geometry": {"coordinates":[-88.88931599999999,44.670866],"type":"Point"}
}