{
  "type": "Feature",
  "properties": {
    "iso:country":"US",
    "sg:address":"5201 Old Middleton Rd",
    "sg:city":"Madison",
    "sg:classifiers":[
        {
            "category":"Professional",
            "subcategory":"Advertising",
            "type":"Services"
        }
    ],
    "sg:phone":"+1 608 232 2300",
    "sg:postcode":"53705",
    "sg:province":"WI",
    "sg:tags":[
        "marketing",
        "public",
        "relations",
        "research"
    ],
    "sg:website":"www.knupp-watson.com",
    "wof:name":"Knupp & Watson Inc",
    "wof:placetype":"venue"
},
  "geometry": {"coordinates":[-89.470038,43.073901],"type":"Point"}
}