{
  "type": "Feature",
  "properties": {
    "iso:country":"US",
    "sg:address":"2290 N Green Bay Rd",
    "sg:city":"Grafton",
    "sg:classifiers":[
        {
            "category":"Retail",
            "subcategory":"Animal Services",
            "type":"Services"
        }
    ],
    "sg:phone":"+1 262 375 2919",
    "sg:postcode":"53024",
    "sg:province":"WI",
    "sg:tags":[
        "pet",
        "boarding",
        "sitting"
    ],
    "wof:name":"J D's Pet Care Svc",
    "wof:placetype":"venue"
},
  "geometry": {"coordinates":[-87.949463,43.336589],"type":"Point"}
}