{
  "type": "Feature",
  "properties": {
    "addr:full":"6201 N Teutonia Ave Milwaukee WI 53209",
    "addr:housenumber":"6201",
    "addr:postcode":"53209",
    "addr:street":"N Teutonia Ave",
    "iso:country":"US",
    "sg:address":"6201 N Teutonia Ave",
    "sg:city":"Milwaukee",
    "sg:classifiers":[
        {
            "category":"Food & Beverages",
            "subcategory":"Groceries & Convenience Stores",
            "type":"Retail Goods"
        }
    ],
    "sg:phone":"+1 414 462 1360",
    "sg:postcode":"53209",
    "sg:province":"WI",
    "sg:website":"http://www.save-a-lot.com/",
    "wof:name":"Save-A-Lot",
    "wof:placetype":"venue"
},
  "geometry": {"coordinates":[-87.952119,43.128316],"type":"Point"}
}