{
  "type": "Feature",
  "properties": {
    "iso:country":"US",
    "sg:address":"9246 Krakow Rd",
    "sg:city":"Krakow",
    "sg:classifiers":[
        {
            "category":"Farming",
            "subcategory":"Livestock Farm",
            "type":"Manufacturing & Wholesale Goods"
        }
    ],
    "sg:phone":"+1 920 899 3348",
    "sg:postcode":"54137",
    "sg:province":"WI",
    "sg:tags":[
        "beef",
        "feedlot",
        "cattle"
    ],
    "wof:name":"Jurecki Quin",
    "wof:placetype":"venue"
},
  "geometry": {"coordinates":[-88.232996,44.773534],"type":"Point"}
}