{
  "type": "Feature",
  "properties": {
    "iso:country":"US",
    "sg:address":"3015 N 87th St",
    "sg:city":"Milwaukee",
    "sg:classifiers":[
        {
            "category":"Food & Beverages",
            "subcategory":"Groceries & Convenience Stores",
            "type":"Retail Goods"
        }
    ],
    "sg:phone":"+1 414 875 8269",
    "sg:postcode":"53222",
    "sg:province":"WI",
    "wof:name":"Ad Gas Inc",
    "wof:placetype":"venue"
},
  "geometry": {"coordinates":[-88.02137399999999,43.074888],"type":"Point"}
}