{
  "type": "Feature",
  "properties": {
    "addr:full":"564 Water St Prairie Du Sac WI 53578",
    "addr:housenumber":"564",
    "addr:postcode":"53578",
    "addr:street":"Water St",
    "iso:country":"US",
    "sg:address":"564 Water St",
    "sg:city":"Prairie Du Sac",
    "sg:classifiers":[
        {
            "category":"Cinema",
            "subcategory":"Movie Theater",
            "type":"Entertainment"
        }
    ],
    "sg:phone":"+1 608 643 8504",
    "sg:postcode":"53578",
    "sg:province":"WI",
    "wof:name":"Bonham Theatre & Video",
    "wof:placetype":"venue"
},
  "geometry": {"coordinates":[-89.71865699999999,43.288108],"type":"Point"}
}