{
  "type": "Feature",
  "properties": {
    "addr:full":"1385 Co Rd T Marshall WI 53559",
    "addr:housenumber":"1385",
    "addr:postcode":"53559",
    "addr:street":"Co Rd",
    "iso:country":"US",
    "sg:address":"1385 Co Rd T",
    "sg:city":"Marshall",
    "sg:classifiers":[
        {
            "category":"Building & Trades",
            "subcategory":"Construction",
            "type":"Services"
        }
    ],
    "sg:phone":"+1 608 655 4118",
    "sg:postcode":"53559",
    "sg:province":"WI",
    "sg:tags":[
        "drywall",
        "dry wall",
        "contractor"
    ],
    "wof:name":"Munson Drywall Inc",
    "wof:placetype":"venue"
},
  "geometry": {"coordinates":[-89.117267,43.155347],"type":"Point"}
}