{
  "type": "Feature",
  "properties": {
    "iso:country":"US",
    "sg:address":"3982 Commercial St",
    "sg:city":"Stitzer",
    "sg:classifiers":[
        {
            "category":"Retail",
            "subcategory":"Auto Repair",
            "type":"Services"
        }
    ],
    "sg:phone":"+1 608 943 8043",
    "sg:postcode":"53825",
    "sg:province":"WI",
    "sg:tags":[
        "transmission"
    ],
    "wof:name":"Addison Transmission Svc",
    "wof:placetype":"venue"
},
  "geometry": {"coordinates":[-90.624631,42.925916],"type":"Point"}
}