{
  "type": "Feature",
  "properties": {
    "iso:country":"US",
    "sg:address":"8801 W Lisbon Ave",
    "sg:city":"Milwaukee",
    "sg:classifiers":[
        {
            "category":"Organizations",
            "subcategory":"Religious Organization",
            "type":"Services"
        }
    ],
    "sg:phone":"+1 414 462 2370",
    "sg:postcode":"53222",
    "sg:province":"WI",
    "wof:name":"Aldersgate Untd Methdst Church",
    "wof:placetype":"venue"
},
  "geometry": {"coordinates":[-88.023226,43.083241],"type":"Point"}
}