{
  "type": "Feature",
  "properties": {
    "addr:full":"1023 E Brady St Milwaukee WI 53202",
    "addr:housenumber":"1023",
    "addr:postcode":"53202",
    "addr:street":"E Brady St",
    "iso:country":"US",
    "sg:address":"1023 E Brady St",
    "sg:city":"Milwaukee",
    "sg:classifiers":[
        {
            "category":"Personal",
            "subcategory":"Psychics & Astrologers",
            "type":"Services"
        },
        {
            "category":"Recreation",
            "type":"Entertainment"
        }
    ],
    "sg:phone":"+1 888 585 8476",
    "sg:postcode":"53202",
    "sg:province":"WI",
    "sg:tags":[
        "medium",
        "entertainers-family",
        "business"
    ],
    "wof:name":"Psychic Tarot Spiritual Reading",
    "wof:placetype":"venue"
},
  "geometry": {"coordinates":[-87.898819,43.052989],"type":"Point"}
}