{
  "type": "Feature",
  "properties": {
    "iso:country":"US",
    "sg:address":"1804 89th St",
    "sg:city":"Kenosha",
    "sg:classifiers":[
        {
            "category":"Professional",
            "type":"Services"
        }
    ],
    "sg:phone":"+1 262 948 8170",
    "sg:postcode":"53143",
    "sg:province":"WI",
    "sg:tags":[
        "establishment"
    ],
    "wof:name":"Sunshine Limited",
    "wof:placetype":"venue"
},
  "geometry": {"coordinates":[-87.83208,42.544078],"type":"Point"}
}