{
  "type": "Feature",
  "properties": {
    "iso:country":"US",
    "sg:address":"15681 Dopp Rd",
    "sg:city":"Ettrick",
    "sg:classifiers":[
        {
            "category":"Building & Trades",
            "subcategory":"Construction",
            "type":"Services"
        }
    ],
    "sg:phone":"+1 608 525 7300",
    "sg:postcode":"54627",
    "sg:province":"WI",
    "sg:tags":[
        "house"
    ],
    "wof:name":"Buckwise Construction LLC",
    "wof:placetype":"venue"
},
  "geometry": {"coordinates":[-91.26754699999999,44.159703],"type":"Point"}
}