{
  "type": "Feature",
  "properties": {
    "iso:country":"US",
    "sg:address":"6265 Lake Poygan Rd",
    "sg:city":"Winneconne",
    "sg:classifiers":[
        {
            "category":"Shopping",
            "type":"Retail Goods"
        }
    ],
    "sg:phone":"+1 920 582 7659",
    "sg:postcode":"54986",
    "sg:province":"WI",
    "sg:tags":[
        "mural"
    ],
    "wof:name":"Sincere Harmony",
    "wof:placetype":"venue"
},
  "geometry": {"coordinates":[-88.84029099999999,44.117155],"type":"Point"}
}