{
  "type": "Feature",
  "properties": {
    "iso:country":"US",
    "sg:address":"400 E Juniper Ct",
    "sg:city":"Mequon",
    "sg:classifiers":[
        {
            "category":"Professional",
            "type":"Services"
        }
    ],
    "sg:phone":"+1 262 241 8345",
    "sg:postcode":"53092",
    "sg:province":"WI",
    "sg:tags":[
        "establishment"
    ],
    "wof:name":"Judy Guten Inc",
    "wof:placetype":"venue"
},
  "geometry": {"coordinates":[-87.902429,43.195715],"type":"Point"}
}