{
  "type": "Feature",
  "properties": {
    "addr:full":"2508 N Tarrant Rd Milton WI 53563",
    "addr:housenumber":"2508",
    "addr:postcode":"53563",
    "addr:street":"N Tarrant Rd",
    "iso:country":"US",
    "sg:address":"2508 N Tarrant Rd",
    "sg:city":"Milton",
    "sg:classifiers":[
        {
            "category":"Farming",
            "subcategory":"Livestock Farm",
            "type":"Manufacturing & Wholesale Goods"
        }
    ],
    "sg:phone":"+1 608 868 3909",
    "sg:postcode":"53563",
    "sg:province":"WI",
    "sg:tags":[
        "beef",
        "feedlot",
        "cattle"
    ],
    "wof:name":"Carol Pregont",
    "wof:placetype":"venue"
},
  "geometry": {"coordinates":[-88.895354,42.723896],"type":"Point"}
}