{
  "type": "Feature",
  "properties": {
    "iso:country":"US",
    "sg:address":"17910 W National Ave",
    "sg:city":"New Berlin",
    "sg:classifiers":[
        {
            "category":"Retail",
            "subcategory":"Repair Shop",
            "type":"Services"
        }
    ],
    "sg:phone":"+1 262 679 7117",
    "sg:postcode":"53146",
    "sg:province":"WI",
    "sg:tags":[
        "refrigeration"
    ],
    "wof:name":"Glacier Refrigeration Inc",
    "wof:placetype":"venue"
},
  "geometry": {"coordinates":[-88.12989399999999,42.963792],"type":"Point"}
}