{
  "type": "Feature",
  "properties": {
    "iso:country":"US",
    "sg:address":"828 S Lee St",
    "sg:city":"Appleton",
    "sg:classifiers":[
        {
            "category":"Banks & Credit Unions",
            "subcategory":"Financial Services",
            "type":"Services"
        }
    ],
    "sg:phone":"+1 920 832 8331",
    "sg:postcode":"54915",
    "sg:province":"WI",
    "sg:tags":[
        "investor"
    ],
    "wof:name":"Su Ko Investments Inc",
    "wof:placetype":"venue"
},
  "geometry": {"coordinates":[-88.37882399999999,44.258479],"type":"Point"}
}