{
  "type": "Feature",
  "properties": {
    "iso:country":"US",
    "sg:address":"107 N Main St",
    "sg:city":"Rosholt",
    "sg:classifiers":[
        {
            "category":"Bars & Pubs",
            "type":"Food & Drink"
        }
    ],
    "sg:phone":"+1 715 677 4740",
    "sg:postcode":"54473",
    "sg:province":"WI",
    "sg:tags":[
        "drinking"
    ],
    "wof:name":"Main Street Pub",
    "wof:placetype":"venue"
},
  "geometry": {"coordinates":[-89.309122,44.629393],"type":"Point"}
}