{
  "type": "Feature",
  "properties": {
    "iso:country":"US",
    "sg:address":"520 Race St",
    "sg:city":"Wisconsin Dells",
    "sg:classifiers":[
        {
            "category":"Education",
            "subcategory":"School",
            "type":"Public Place"
        }
    ],
    "sg:phone":"+1 608 253 1461",
    "sg:postcode":"53965",
    "sg:province":"WI",
    "wof:name":"Wisconsin Dells High School",
    "wof:placetype":"venue"
},
  "geometry": {"coordinates":[-89.763043,43.624324],"type":"Point"}
}