{
  "type": "Feature",
  "properties": {
    "iso:country":"US",
    "sg:address":"29741 Little Bear Dr",
    "sg:city":"Danbury",
    "sg:classifiers":[
        {
            "category":"Wholesale",
            "subcategory":"Machinery & Supplies",
            "type":"Manufacturing & Wholesale Goods"
        }
    ],
    "sg:phone":"+1 715 259 7854",
    "sg:postcode":"54830",
    "sg:province":"WI",
    "sg:tags":[
        "metalworking",
        "tool"
    ],
    "wof:name":"Johnson Dl Co",
    "wof:placetype":"venue"
},
  "geometry": {"coordinates":[-92.158456,45.99438],"type":"Point"}
}