{
  "type": "Feature",
  "properties": {
    "iso:country":"US",
    "sg:address":"4186 S Kinnickinnic Ave",
    "sg:city":"Milwaukee",
    "sg:classifiers":[
        {
            "category":"Local Transit",
            "type":"Transportation"
        }
    ],
    "sg:phone":"+1 414 483 0003",
    "sg:postcode":"53235",
    "sg:province":"WI",
    "sg:tags":[
        "passenger",
        "limousine"
    ],
    "sg:website":"www.corplimo.com",
    "wof:name":"Corporate Limousine Service",
    "wof:placetype":"venue"
},
  "geometry": {"coordinates":[-87.870457,42.967051],"type":"Point"}
}