{
  "type": "Feature",
  "properties": {
    "iso:country":"US",
    "sg:address":"606 N 13th St",
    "sg:city":"Milwaukee",
    "sg:classifiers":[
        {
            "category":"Education",
            "subcategory":"College",
            "type":"Public Place"
        }
    ],
    "sg:phone":"+1 414 288 7142",
    "sg:postcode":"53233",
    "sg:province":"WI",
    "sg:tags":[
        "academic",
        "school"
    ],
    "wof:name":"Marquette University",
    "wof:placetype":"venue"
},
  "geometry": {"coordinates":[-87.928188,43.035593],"type":"Point"}
}