{
  "type": "Feature",
  "properties": {
    "iso:country":"US",
    "sg:address":"1928 S 55th St",
    "sg:city":"Milwaukee",
    "sg:classifiers":[
        {
            "category":"Freight",
            "type":"Transportation"
        }
    ],
    "sg:phone":"+1 414 327 6002",
    "sg:postcode":"53219",
    "sg:province":"WI",
    "sg:tags":[
        "operator",
        "local",
        "trucking"
    ],
    "wof:name":"Sevedge Trucking",
    "wof:placetype":"venue"
},
  "geometry": {"coordinates":[-87.981439,43.008881],"type":"Point"}
}