{
  "type": "Feature",
  "properties": {
    "iso:country":"US",
    "sg:address":"953 N 27th St",
    "sg:city":"Milwaukee",
    "sg:classifiers":[
        {
            "category":"Building & Trades",
            "subcategory":"Cleaning & Sanitation",
            "type":"Services"
        }
    ],
    "sg:phone":"+1 414 934 8714",
    "sg:postcode":"53208",
    "sg:province":"WI",
    "sg:tags":[
        "property",
        "maintenance"
    ],
    "wof:name":"Safe Harbor Residential",
    "wof:placetype":"venue"
},
  "geometry": {"coordinates":[-87.94777000000001,43.043197],"type":"Point"}
}