{
  "type": "Feature",
  "properties": {
    "iso:country":"US",
    "sg:address":"2720 S 11th St",
    "sg:city":"Milwaukee",
    "sg:classifiers":[
        {
            "category":"Retail",
            "subcategory":"Repair Shop",
            "type":"Services"
        }
    ],
    "sg:phone":"+1 414 645 1244",
    "sg:postcode":"53215",
    "sg:province":"WI",
    "sg:tags":[
        "welding"
    ],
    "wof:name":"West Shore Welding",
    "wof:placetype":"venue"
},
  "geometry": {"coordinates":[-87.926143,42.994587],"type":"Point"}
}