{
  "type": "Feature",
  "properties": {
    "iso:country":"US",
    "sg:address":"3301 Belknap St",
    "sg:city":"Superior",
    "sg:classifiers":[
        {
            "category":"Restaurant",
            "type":"Food & Drink"
        }
    ],
    "sg:phone":"+1 715 392 3463",
    "sg:postcode":"54880",
    "sg:province":"WI",
    "sg:tags":[
        "style",
        "family"
    ],
    "wof:name":"Superior Dining Concepts",
    "wof:placetype":"venue"
},
  "geometry": {"coordinates":[-92.12584699999999,46.720749],"type":"Point"}
}