{
  "type": "Feature",
  "properties": {
    "iso:country":"US",
    "sg:address":"2250 Holmgren Way",
    "sg:city":"Green Bay",
    "sg:classifiers":[
        {
            "category":"Education",
            "subcategory":"Dance Studio",
            "type":"Public Place"
        }
    ],
    "sg:phone":"+1 920 499 6560",
    "sg:postcode":"54304",
    "sg:province":"WI",
    "sg:tags":[
        "instructor"
    ],
    "wof:name":"Barbs Centre For Dance",
    "wof:placetype":"venue"
},
  "geometry": {"coordinates":[-88.058793,44.490697],"type":"Point"}
}