{
  "type": "Feature",
  "properties": {
    "addr:full":"3437 Co Rd A Rosholt WI 54473",
    "addr:housenumber":"3437",
    "addr:postcode":"54473",
    "addr:street":"Co Rd A Rosholt",
    "iso:country":"US",
    "sg:address":"3437 Co Rd A",
    "sg:city":"Rosholt",
    "sg:classifiers":[
        {
            "category":"Retail",
            "subcategory":"Auto Repair",
            "type":"Services"
        }
    ],
    "sg:phone":"+1 715 677 4900",
    "sg:postcode":"54473",
    "sg:province":"WI",
    "sg:tags":[
        "body",
        "automobile",
        "painting"
    ],
    "wof:name":"R C's Kustom Paint",
    "wof:placetype":"venue"
},
  "geometry": {"coordinates":[-89.284543,44.639012],"type":"Point"}
}