{
  "type": "Feature",
  "properties": {
    "addr:full":"140 Broad St Lake Geneva WI 53147",
    "addr:housenumber":"140",
    "addr:postcode":"53147",
    "addr:street":"Broad St",
    "iso:country":"US",
    "sg:address":"140 Broad St",
    "sg:city":"Lake Geneva",
    "sg:classifiers":[
        {
            "category":"Shopping",
            "subcategory":"Clothing, Apparel, & Fashions",
            "type":"Retail Goods"
        }
    ],
    "sg:phone":"+1 262 249 8619",
    "sg:postcode":"53147",
    "sg:province":"WI",
    "sg:tags":[
        "t"
    ],
    "wof:name":"T Shirt Ctr Inc",
    "wof:placetype":"venue"
},
  "geometry": {"coordinates":[-88.435382,42.590549],"type":"Point"}
}