{
  "type": "Feature",
  "properties": {
    "iso:country":"US",
    "sg:address":"220 N Shore Dr",
    "sg:city":"Fountain City",
    "sg:classifiers":[
        {
            "category":"Retail",
            "subcategory":"Auto Repair",
            "type":"Services"
        }
    ],
    "sg:phone":"+1 608 687 9141",
    "sg:postcode":"54629",
    "sg:province":"WI",
    "sg:tags":[
        "automotive"
    ],
    "wof:name":"Custom Shop",
    "wof:placetype":"venue"
},
  "geometry": {"coordinates":[-91.731228,44.141608],"type":"Point"}
}