{
  "type": "Feature",
  "properties": {
    "iso:country":"US",
    "sg:address":"805 Seminole Ave",
    "sg:city":"Osceola",
    "sg:classifiers":[
        {
            "category":"Manufacturing",
            "subcategory":"Metals",
            "type":"Manufacturing & Wholesale Goods"
        }
    ],
    "sg:phone":"+1 715 294 3370",
    "sg:postcode":"54020",
    "sg:province":"WI",
    "sg:tags":[
        "plate",
        "mfg",
        "stamp",
        "fabricated",
        "repair",
        "welding"
    ],
    "sg:website":"www.polarisindustries.com",
    "wof:name":"Polaris Industries LP",
    "wof:placetype":"venue"
},
  "geometry": {"coordinates":[-92.70385899999999,45.318448],"type":"Point"}
}