{
  "type": "Feature",
  "properties": {
    "iso:country":"US",
    "sg:address":"900 Whispering Way",
    "sg:city":"Cottage Grove",
    "sg:classifiers":[
        {
            "category":"Professional",
            "type":"Services"
        }
    ],
    "sg:phone":"+1 608 246 2861",
    "sg:postcode":"53527",
    "sg:province":"WI",
    "wof:name":"Hauser Tree Service",
    "wof:placetype":"venue"
},
  "geometry": {"coordinates":[-89.201617,43.097404],"type":"Point"}
}