{
  "type": "Feature",
  "properties": {
    "iso:country":"US",
    "sg:address":"5525 W Beloit Rd",
    "sg:city":"Milwaukee",
    "sg:classifiers":[
        {
            "category":"Retail",
            "subcategory":"Auto Repair",
            "type":"Services"
        }
    ],
    "sg:phone":"+1 414 543 6504",
    "sg:postcode":"53214",
    "sg:province":"WI",
    "sg:tags":[
        "general"
    ],
    "wof:name":"R & R Service of West Allis",
    "wof:placetype":"venue"
},
  "geometry": {"coordinates":[-87.982494,43.011716],"type":"Point"}
}