{
  "type": "Feature",
  "properties": {
    "addr:full":"11801 W Silver Spring Dr Milwaukee WI 53225",
    "addr:housenumber":"11801",
    "addr:postcode":"53225",
    "addr:street":"W Silver Spring Dr",
    "iso:country":"US",
    "sg:address":"11801 W Silver Spring Dr",
    "sg:city":"Milwaukee",
    "sg:classifiers":[
        {
            "category":"Banks & Credit Unions",
            "subcategory":"Bank",
            "type":"Services"
        }
    ],
    "sg:phone":"+1 414 463 1180",
    "sg:postcode":"53225",
    "sg:province":"WI",
    "sg:tags":[
        "state"
    ],
    "wof:name":"Associated Bank",
    "wof:placetype":"venue"
},
  "geometry": {"coordinates":[-88.06095999999999,43.117029],"type":"Point"}
}