{
  "type": "Feature",
  "properties": {
    "iso:country":"US",
    "sg:address":"18130 Lamplighter Ln",
    "sg:city":"Brookfield",
    "sg:classifiers":[
        {
            "category":"Health Services",
            "subcategory":"Doctor",
            "type":"Services"
        }
    ],
    "sg:phone":"+1 262 782 0552",
    "sg:postcode":"53045",
    "sg:province":"WI",
    "wof:name":"David G Lloyd",
    "wof:placetype":"venue"
},
  "geometry": {"coordinates":[-88.135556,43.065867],"type":"Point"}
}