{
  "type": "Feature",
  "properties": {
    "addr:full":"2124 W 9th Ave Oshkosh WI 54904",
    "addr:housenumber":"2124",
    "addr:postcode":"54904",
    "addr:street":"W 9Th Ave",
    "iso:country":"US",
    "sg:address":"2124 W 9th Ave",
    "sg:city":"Oshkosh",
    "sg:classifiers":[
        {
            "category":"Food & Beverages",
            "subcategory":"Groceries & Convenience Stores",
            "type":"Retail Goods"
        }
    ],
    "sg:phone":"+1 920 426 2200",
    "sg:postcode":"54904",
    "sg:province":"WI",
    "wof:name":"Open Pantry Food Mart",
    "wof:placetype":"venue"
},
  "geometry": {"coordinates":[-88.587599,44.010933],"type":"Point"}
}