{
  "type": "Feature",
  "properties": {
    "iso:country":"US",
    "sg:address":"1232 Rose St",
    "sg:city":"La Crosse",
    "sg:classifiers":[
        {
            "category":"Banks & Credit Unions",
            "subcategory":"Bank",
            "type":"Services"
        }
    ],
    "sg:phone":"+1 608 784 8900",
    "sg:postcode":"54603",
    "sg:province":"WI",
    "wof:name":"River Bank",
    "wof:placetype":"venue"
},
  "geometry": {"coordinates":[-91.24805000000001,43.841002],"type":"Point"}
}