{
  "type": "Feature",
  "properties": {
    "iso:country":"US",
    "sg:address":"4795 State Hwy 73",
    "sg:city":"Neillsville",
    "sg:classifiers":[
        {
            "category":"Building & Trades",
            "subcategory":"Construction",
            "type":"Services"
        }
    ],
    "sg:phone":"+1 715 743 4952",
    "sg:postcode":"54456",
    "sg:province":"WI",
    "sg:tags":[
        "concrete",
        "contractor"
    ],
    "wof:name":"Brorson Construction Inc",
    "wof:placetype":"venue"
},
  "geometry": {"coordinates":[-90.57716000000001,44.590652],"type":"Point"}
}