{
  "type": "Feature",
  "properties": {
    "iso:country":"US",
    "sg:address":"12025 1010th St",
    "sg:city":"Bloomer",
    "sg:classifiers":[
        {
            "category":"Farming",
            "subcategory":"Nursery",
            "type":"Manufacturing & Wholesale Goods"
        }
    ],
    "sg:phone":"+1 715 568 1212",
    "sg:postcode":"54724",
    "sg:province":"WI",
    "sg:tags":[
        "ornamental"
    ],
    "wof:name":"Jubilee Nursery Inc",
    "wof:placetype":"venue"
},
  "geometry": {"coordinates":[-91.651483,45.114273],"type":"Point"}
}