{
  "type": "Feature",
  "properties": {
    "iso:country":"US",
    "sg:address":"29517 Bushnell Rd",
    "sg:city":"Burlington",
    "sg:classifiers":[
        {
            "category":"Manufacturing",
            "subcategory":"Metals",
            "type":"Manufacturing & Wholesale Goods"
        },
        {
            "category":"Manufacturing",
            "subcategory":"Tools & Machinery",
            "type":"Manufacturing & Wholesale Goods"
        }
    ],
    "sg:phone":"+1 262 539 2701",
    "sg:postcode":"53105",
    "sg:province":"WI",
    "sg:tags":[
        "works",
        "mfg",
        "die",
        "maker",
        "blast",
        "furnace"
    ],
    "wof:name":"Centerline Tools & Designs Inc",
    "wof:placetype":"venue"
},
  "geometry": {"coordinates":[-88.217955,42.653501],"type":"Point"}
}