{
  "type": "Feature",
  "properties": {
    "iso:country":"US",
    "sg:address":"752 Grand Ave",
    "sg:city":"Hartford",
    "sg:classifiers":[
        {
            "category":"Restaurant",
            "type":"Food & Drink"
        }
    ],
    "sg:phone":"+1 262 673 0777",
    "sg:postcode":"53027",
    "sg:province":"WI",
    "sg:tags":[
        "eating",
        "pizza"
    ],
    "wof:name":"Poad's Pizza",
    "wof:placetype":"venue"
},
  "geometry": {"coordinates":[-88.374092,43.308116],"type":"Point"}
}