{
  "type": "Feature",
  "properties": {
    "addr:full":"1592 E Mason St Green Bay WI 54302",
    "addr:housenumber":"1592",
    "addr:postcode":"54302",
    "addr:street":"E Mason St",
    "iso:country":"US",
    "sg:address":"1592 E Mason St",
    "sg:city":"Green Bay",
    "sg:classifiers":[
        {
            "category":"Autos & Motor Vehicles",
            "subcategory":"Automobile Sales",
            "type":"Retail Goods"
        }
    ],
    "sg:phone":"+1 920 391 1731",
    "sg:postcode":"54302",
    "sg:province":"WI",
    "sg:tags":[
        "car",
        "dealer"
    ],
    "wof:name":"Smitty's Used Cars",
    "wof:placetype":"venue"
},
  "geometry": {"coordinates":[-87.991705,44.497934],"type":"Point"}
}