{
  "type": "Feature",
  "properties": {
    "iso:country":"US",
    "sg:address":"3939 S 92nd St",
    "sg:city":"Milwaukee",
    "sg:classifiers":[
        {
            "category":"Professional",
            "type":"Services"
        }
    ],
    "sg:phone":"+1 414 321 1623",
    "sg:postcode":"53228",
    "sg:province":"WI",
    "wof:name":"M & M Svc Inc",
    "wof:placetype":"venue"
},
  "geometry": {"coordinates":[-88.027829,42.973406],"type":"Point"}
}