{
  "type": "Feature",
  "properties": {
    "iso:country":"US",
    "sg:address":"3401 W Layton Ave",
    "sg:city":"Milwaukee",
    "sg:classifiers":[
        {
            "category":"Health Services",
            "subcategory":"Doctor",
            "type":"Services"
        }
    ],
    "sg:phone":"+1 414 282 7577",
    "sg:postcode":"53221",
    "sg:province":"WI",
    "wof:name":"Gary R Major DDS",
    "wof:placetype":"venue"
},
  "geometry": {"coordinates":[-87.955935,42.959328],"type":"Point"}
}