{
  "type": "Feature",
  "properties": {
    "iso:country":"US",
    "sg:address":"1319 Menting Rd",
    "sg:city":"Mondovi",
    "sg:classifiers":[
        {
            "category":"Building & Trades",
            "subcategory":"Construction",
            "type":"Services"
        }
    ],
    "sg:phone":"+1 715 946 3702",
    "sg:postcode":"54755",
    "sg:province":"WI",
    "sg:tags":[
        "carpentry",
        "contractor"
    ],
    "wof:name":"Aron Building & Carpentry",
    "wof:placetype":"venue"
},
  "geometry": {"coordinates":[-91.796981,44.457148],"type":"Point"}
}