{
  "type": "Feature",
  "properties": {
    "iso:country":"US",
    "sg:address":"3717 W Howard Ave",
    "sg:city":"Milwaukee",
    "sg:classifiers":[
        {
            "category":"Sports & Exercise",
            "subcategory":"Golf",
            "type":"Entertainment"
        },
        {
            "category":"Government",
            "subcategory":"Office",
            "type":"Public Place"
        }
    ],
    "sg:phone":"+1 414 282 6610",
    "sg:postcode":"53221",
    "sg:province":"WI",
    "sg:tags":[
        "course",
        "conservation"
    ],
    "wof:name":"Parks-Zablocki Golf Course",
    "wof:placetype":"venue"
},
  "geometry": {"coordinates":[-87.961895,42.973837],"type":"Point"}
}