{
  "type": "Feature",
  "properties": {
    "iso:country":"US",
    "sg:address":"813 Fox Ln",
    "sg:city":"Waterford",
    "sg:classifiers":[
        {
            "category":"Banks & Credit Unions",
            "subcategory":"Bank",
            "type":"Services"
        }
    ],
    "sg:phone":"+1 262 534 5600",
    "sg:postcode":"53185",
    "sg:province":"WI",
    "sg:tags":[
        "loan",
        "real estate"
    ],
    "wof:name":"Ameristar Mortgage",
    "wof:placetype":"venue"
},
  "geometry": {"coordinates":[-88.200058,42.766392],"type":"Point"}
}