{
  "type": "Feature",
  "properties": {
    "iso:country":"US",
    "sg:address":"9364 N Waverly Dr",
    "sg:city":"Milwaukee",
    "sg:classifiers":[
        {
            "category":"Professional",
            "subcategory":"Business Services",
            "type":"Services"
        }
    ],
    "sg:phone":"+1 414 352 6272",
    "sg:postcode":"53217",
    "sg:province":"WI",
    "wof:name":"Slb Designs",
    "wof:placetype":"venue"
},
  "geometry": {"coordinates":[-87.91081699999999,43.187148],"type":"Point"}
}