{
  "type": "Feature",
  "properties": {
    "iso:country":"US",
    "sg:address":"735 Heatherstone Ridge",
    "sg:city":"Sun Prairie",
    "sg:classifiers":[
        {
            "category":"Building & Trades",
            "subcategory":"Construction",
            "type":"Services"
        }
    ],
    "sg:phone":"+1 608 834 8919",
    "sg:postcode":"53590",
    "sg:province":"WI",
    "sg:tags":[
        "residential"
    ],
    "wof:name":"Stevens Construction MGT",
    "wof:placetype":"venue"
},
  "geometry": {"coordinates":[-89.282536,43.189394],"type":"Point"}
}