{
  "type": "Feature",
  "properties": {
    "iso:country":"US",
    "sg:address":"10819 Stage Rd",
    "sg:city":"Brussels",
    "sg:classifiers":[
        {
            "category":"Building & Trades",
            "subcategory":"Plumbing",
            "type":"Services"
        }
    ],
    "sg:phone":"+1 920 825 7570",
    "sg:postcode":"54204",
    "sg:province":"WI",
    "sg:tags":[
        "heating",
        "contractor"
    ],
    "wof:name":"Central Heating & Shtmtl LLC",
    "wof:placetype":"venue"
},
  "geometry": {"coordinates":[-87.700349,44.712486],"type":"Point"}
}