{
  "type": "Feature",
  "properties": {
    "iso:country":"US",
    "sg:address":"5792 Lincoln Rd",
    "sg:city":"Vesper",
    "sg:classifiers":[
        {
            "category":"Retail",
            "subcategory":"Animal Services",
            "type":"Services"
        }
    ],
    "sg:phone":"+1 715 569 4771",
    "sg:postcode":"54489",
    "sg:province":"WI",
    "wof:name":"Grande Oaks Farm",
    "wof:placetype":"venue"
},
  "geometry": {"coordinates":[-90.007506,44.438428],"type":"Point"}
}