{
  "type": "Feature",
  "properties": {
    "iso:country":"US",
    "sg:address":"550 Hartbrook Dr",
    "sg:city":"Hartland",
    "sg:classifiers":[
        {
            "category":"Sports & Exercise",
            "subcategory":"Bowling",
            "type":"Entertainment"
        }
    ],
    "sg:phone":"+1 262 367 5166",
    "sg:postcode":"53029",
    "sg:province":"WI",
    "sg:tags":[
        "lounge",
        "alley",
        "cocktail"
    ],
    "wof:name":"Hartbrook Lanes",
    "wof:placetype":"venue"
},
  "geometry": {"coordinates":[-88.334625,43.110156],"type":"Point"}
}