{
  "type": "Feature",
  "properties": {
    "iso:country":"US",
    "sg:address":"2821 E Hamilton Ave",
    "sg:city":"Eau Claire",
    "sg:classifiers":[
        {
            "category":"Home & Garden",
            "subcategory":"Carpets & Floor Coverings",
            "type":"Retail Goods"
        }
    ],
    "sg:phone":"+1 715 839 8048",
    "sg:postcode":"54701",
    "sg:province":"WI",
    "wof:name":"Floors N More",
    "wof:placetype":"venue"
},
  "geometry": {"coordinates":[-91.462165,44.785739],"type":"Point"}
}