{
  "type": "Feature",
  "properties": {
    "iso:country":"US",
    "sg:address":"2588 Hallie Rd",
    "sg:city":"Chippewa Falls",
    "sg:classifiers":[
        {
            "category":"Restaurant",
            "type":"Food & Drink"
        }
    ],
    "sg:menulink":"http://www.allmenus.com/wi/chippewa-falls/293011-piffs-pizza/menu/",
    "sg:phone":"+1 715 720 0915",
    "sg:postcode":"54729",
    "sg:province":"WI",
    "sg:tags":[
        "pizza"
    ],
    "wof:name":"Piff's Pizza",
    "wof:placetype":"venue"
},
  "geometry": {"coordinates":[-91.428754,44.88105],"type":"Point"}
}