{
  "type": "Feature",
  "properties": {
    "iso:country":"US",
    "sg:address":"102 W Winnebago St",
    "sg:city":"Friesland",
    "sg:classifiers":[
        {
            "category":"Shopping",
            "subcategory":"Florist",
            "type":"Retail Goods"
        }
    ],
    "sg:phone":"+1 920 348 6080",
    "sg:postcode":"53923",
    "sg:province":"WI",
    "wof:name":"Floral Art & Gifts",
    "wof:placetype":"venue"
},
  "geometry": {"coordinates":[-89.067142,43.588536],"type":"Point"}
}