{
  "type": "Feature",
  "properties": {
    "addr:full":"1225 State Hwy 70 Tipler WI 54542",
    "addr:housenumber":"1225",
    "addr:postcode":"54542",
    "addr:street":"State Hwy 70",
    "iso:country":"US",
    "sg:address":"1225 State Hwy 70",
    "sg:city":"Tipler",
    "sg:classifiers":[
        {
            "category":"Health Services",
            "subcategory":"Nursing And Care Facility",
            "type":"Services"
        }
    ],
    "sg:phone":"+1 715 674 5318",
    "sg:postcode":"54542",
    "sg:province":"WI",
    "sg:tags":[
        "home",
        "convalescent"
    ],
    "wof:name":"Eileen's Foster Care Home",
    "wof:placetype":"venue"
},
  "geometry": {"coordinates":[-88.623869,45.925419],"type":"Point"}
}