{
  "type": "Feature",
  "properties": {
    "iso:country":"US",
    "sg:address":"231 Manitowoc Rd",
    "sg:city":"Reedsville",
    "sg:classifiers":[
        {
            "category":"Bars & Pubs",
            "type":"Food & Drink"
        }
    ],
    "sg:phone":"+1 920 754 4599",
    "sg:postcode":"54230",
    "sg:province":"WI",
    "sg:tags":[
        "drinking"
    ],
    "wof:name":"QS Place",
    "wof:placetype":"venue"
},
  "geometry": {"coordinates":[-87.950923,44.153385],"type":"Point"}
}