{
  "type": "Feature",
  "properties": {
    "iso:country":"US",
    "sg:address":"341 W Jefferson St",
    "sg:city":"West Salem",
    "sg:classifiers":[
        {
            "category":"Autos & Motor Vehicles",
            "subcategory":"Auto Supplies",
            "type":"Retail Goods"
        }
    ],
    "sg:phone":"+1 608 786 1119",
    "sg:postcode":"54669",
    "sg:province":"WI",
    "wof:name":"Farmers Insurance",
    "wof:placetype":"venue"
},
  "geometry": {"coordinates":[-91.084737,43.894247],"type":"Point"}
}