{
  "type": "Feature",
  "properties": {
    "iso:country":"US",
    "sg:address":"400 Kekoskee St",
    "sg:city":"Mayville",
    "sg:classifiers":[
        {
            "category":"Utilities",
            "subcategory":"Water",
            "type":"Services"
        }
    ],
    "sg:phone":"+1 920 387 7906",
    "sg:postcode":"53050",
    "sg:province":"WI",
    "sg:tags":[
        "company",
        "sewage"
    ],
    "wof:name":"Mayville Water & Wastewater",
    "wof:placetype":"venue"
},
  "geometry": {"coordinates":[-88.549038,43.503797],"type":"Point"}
}