{
  "type": "Feature",
  "properties": {
    "iso:country":"US",
    "sg:address":"1137 Field Rd",
    "sg:city":"Mosinee",
    "sg:classifiers":[
        {
            "category":"Retail",
            "subcategory":"Repair Shop",
            "type":"Services"
        }
    ],
    "sg:phone":"+1 715 693 6947",
    "sg:postcode":"54455",
    "sg:province":"WI",
    "sg:tags":[
        "trade",
        "welding",
        "contractor"
    ],
    "wof:name":"Studinskis Welding & Repair",
    "wof:placetype":"venue"
},
  "geometry": {"coordinates":[-89.670085,44.809035],"type":"Point"}
}