{
  "type": "Feature",
  "properties": {
    "iso:country":"US",
    "sg:address":"4800 W Burleigh St",
    "sg:city":"Milwaukee",
    "sg:classifiers":[
        {
            "category":"Restaurant",
            "type":"Food & Drink"
        }
    ],
    "sg:phone":"+1 414 444 0002",
    "sg:postcode":"53210",
    "sg:province":"WI",
    "sg:tags":[
        "shop",
        "coffee"
    ],
    "wof:name":"Zion Coffee Cafe LLC",
    "wof:placetype":"venue"
},
  "geometry": {"coordinates":[-87.97478599999999,43.075243],"type":"Point"}
}