{
  "type": "Feature",
  "properties": {
    "iso:country":"US",
    "sg:address":"311 W Mackie St",
    "sg:city":"Beaver Dam",
    "sg:classifiers":[
        {
            "category":"Organizations",
            "subcategory":"Religious Organization",
            "type":"Services"
        }
    ],
    "sg:phone":"+1 920 885 4497",
    "sg:postcode":"53916",
    "sg:province":"WI",
    "sg:website":"www.firstlutheranbeaverdam.org",
    "wof:name":"First Lutheran Church",
    "wof:placetype":"venue"
},
  "geometry": {"coordinates":[-88.84123099999999,43.460477],"type":"Point"}
}