{
  "type": "Feature",
  "properties": {
    "addr:full":"120 N Emery Ave Peshtigo WI 54157",
    "addr:housenumber":"120",
    "addr:postcode":"54157",
    "addr:street":"N Emery Ave",
    "iso:country":"US",
    "sg:address":"120 N Emery Ave",
    "sg:city":"Peshtigo",
    "sg:classifiers":[
        {
            "category":"Banks & Credit Unions",
            "subcategory":"Bank",
            "type":"Services"
        }
    ],
    "sg:phone":"+1 715 582 3723",
    "sg:postcode":"54157",
    "sg:province":"WI",
    "wof:name":"M & I Bank",
    "wof:placetype":"venue"
},
  "geometry": {"coordinates":[-87.75098800000001,45.05469],"type":"Point"}
}