{
  "type": "Feature",
  "properties": {
    "iso:country":"US",
    "sg:address":"1905 Co Rd J",
    "sg:city":"Baldwin",
    "sg:classifiers":[
        {
            "category":"Farming",
            "subcategory":"Farm",
            "type":"Manufacturing & Wholesale Goods"
        }
    ],
    "sg:phone":"+1 715 684 3674",
    "sg:postcode":"54002",
    "sg:province":"WI",
    "sg:tags":[
        "crop",
        "general"
    ],
    "wof:name":"Villageview Fram",
    "wof:placetype":"venue"
},
  "geometry": {"coordinates":[-92.411232,44.963425],"type":"Point"}
}