{
  "type": "Feature",
  "properties": {
    "iso:country":"US",
    "sg:address":"200 Preston Dr",
    "sg:city":"Platteville",
    "sg:classifiers":[
        {
            "category":"Real Estate",
            "subcategory":"Real Estate Operator",
            "type":"Services"
        }
    ],
    "sg:phone":"+1 608 348 7689",
    "sg:postcode":"53818",
    "sg:province":"WI",
    "sg:tags":[
        "mobile",
        "home",
        "community"
    ],
    "wof:name":"Woodland Terrace Mobile Hm Prk",
    "wof:placetype":"venue"
},
  "geometry": {"coordinates":[-90.48988300000001,42.73562],"type":"Point"}
}