{
  "type": "Feature",
  "properties": {
    "addr:full":"10027 E Waite Rd Clinton WI 53525",
    "addr:housenumber":"10027",
    "addr:postcode":"53525",
    "addr:street":"E Waite Rd",
    "iso:country":"US",
    "sg:address":"10027 E Waite Rd",
    "sg:city":"Clinton",
    "sg:classifiers":[
        {
            "category":"Real Estate",
            "subcategory":"Real Estate Operator",
            "type":"Services"
        }
    ],
    "sg:phone":"+1 608 676 4141",
    "sg:postcode":"53525",
    "sg:province":"WI",
    "sg:tags":[
        "apartment"
    ],
    "wof:name":"James A & Nellie Gilbank",
    "wof:placetype":"venue"
},
  "geometry": {"coordinates":[-88.844217,42.588807],"type":"Point"}
}