{
  "type": "Feature",
  "properties": {
    "addr:full":"5098 Horizon Ct West Bend WI 53095",
    "addr:housenumber":"5098",
    "addr:postcode":"53095",
    "addr:street":"Horizon Ct",
    "iso:country":"US",
    "sg:address":"5098 Horizon Ct",
    "sg:city":"West Bend",
    "sg:classifiers":[
        {
            "category":"Health Services",
            "subcategory":"Nursing And Care Facility",
            "type":"Services"
        }
    ],
    "sg:phone":"+1 262 334 9559",
    "sg:postcode":"53095",
    "sg:province":"WI",
    "sg:tags":[
        "hospice"
    ],
    "wof:name":"Kettle Moraine Support Svc",
    "wof:placetype":"venue"
},
  "geometry": {"coordinates":[-88.21554399999999,43.373806],"type":"Point"}
}