{
  "type": "Feature",
  "properties": {
    "iso:country":"US",
    "sg:address":"4630 Douglas Ave",
    "sg:city":"Racine",
    "sg:classifiers":[
        {
            "category":"Retail",
            "subcategory":"Veterinary Services",
            "type":"Services"
        }
    ],
    "sg:phone":"+1 262 639 7500",
    "sg:postcode":"53402",
    "sg:province":"WI",
    "sg:tags":[
        "veterinarian"
    ],
    "sg:website":"www.northshoreanimalhospital.com",
    "wof:name":"North Shore Animal Hospital",
    "wof:placetype":"venue"
},
  "geometry": {"coordinates":[-87.80695900000001,42.779929],"type":"Point"}
}