{
  "type": "Feature",
  "properties": {
    "iso:country":"US",
    "sg:address":"1267 Norman Rd",
    "sg:city":"Kewaunee",
    "sg:classifiers":[
        {
            "category":"Travel",
            "subcategory":"Campground",
            "type":"Entertainment"
        }
    ],
    "sg:phone":"+1 920 776 1588",
    "sg:postcode":"54216",
    "sg:province":"WI",
    "sg:tags":[
        "campsite",
        "trailer",
        "parks"
    ],
    "wof:name":"Mapleview Campsite",
    "wof:placetype":"venue"
},
  "geometry": {"coordinates":[-87.6032,44.360197],"type":"Point"}
}