{
  "type": "Feature",
  "properties": {
    "iso:country":"US",
    "sg:address":"312 E Race Ave",
    "sg:city":"Elmwood",
    "sg:classifiers":[
        {
            "category":"Autos & Motor Vehicles",
            "subcategory":"Fuel & Gas Station",
            "type":"Retail Goods"
        }
    ],
    "sg:phone":"+1 715 639 4701",
    "sg:postcode":"54740",
    "sg:province":"WI",
    "sg:tags":[
        "gasoline",
        "product",
        "station",
        "petroleum"
    ],
    "wof:name":"Thompson Oil Co",
    "wof:placetype":"venue"
},
  "geometry": {"coordinates":[-92.14244600000001,44.780872],"type":"Point"}
}