{
  "type": "Feature",
  "properties": {
    "iso:country":"US",
    "sg:address":"365 Krattley Ln",
    "sg:city":"Hudson",
    "sg:classifiers":[
        {
            "category":"Building & Trades",
            "subcategory":"Construction",
            "type":"Services"
        }
    ],
    "sg:phone":"+1 715 386 7630",
    "sg:postcode":"54016",
    "sg:province":"WI",
    "sg:tags":[
        "carpentry",
        "contractor"
    ],
    "wof:name":"Croix Valley Carpentry",
    "wof:placetype":"venue"
},
  "geometry": {"coordinates":[-92.728211,45.007833],"type":"Point"}
}