{
  "type": "Feature",
  "properties": {
    "iso:country":"US",
    "sg:address":"320 Superior Ave",
    "sg:city":"Washburn",
    "sg:classifiers":[
        {
            "category":"Health Services",
            "subcategory":"Doctor",
            "type":"Services"
        }
    ],
    "sg:phone":"+1 715 373 0128",
    "sg:postcode":"54891",
    "sg:province":"WI",
    "sg:tags":[
        "physician",
        "surgeon",
        "medical"
    ],
    "wof:name":"Kreuser Clinic",
    "wof:placetype":"venue"
},
  "geometry": {"coordinates":[-90.879116,46.680714],"type":"Point"}
}