{
  "type": "Feature",
  "properties": {
    "iso:country":"US",
    "sg:address":"2450 N 118th St",
    "sg:city":"Milwaukee",
    "sg:classifiers":[
        {
            "category":"Shopping",
            "subcategory":"Computers & Home Electronics",
            "type":"Retail Goods"
        }
    ],
    "sg:phone":"+1 414 607 1073",
    "sg:postcode":"53226",
    "sg:province":"WI",
    "sg:tags":[
        "software"
    ],
    "wof:name":"Badger Technology Tools",
    "wof:placetype":"venue"
},
  "geometry": {"coordinates":[-88.06068399999999,43.063135],"type":"Point"}
}