{
  "type": "Feature",
  "properties": {
    "addr:full":"1033 Emerald Ter Sun Prairie WI 53590",
    "addr:housenumber":"1033",
    "addr:postcode":"53590",
    "addr:street":"Emerald Ter",
    "iso:country":"US",
    "sg:address":"1033 Emerald Ter",
    "sg:city":"Sun Prairie",
    "sg:classifiers":[
        {
            "category":"Travel",
            "subcategory":"Hotels & Motels",
            "type":"Entertainment"
        }
    ],
    "sg:phone":"+1 608 837 8889",
    "sg:postcode":"53590",
    "sg:province":"WI",
    "sg:tags":[
        "operation"
    ],
    "wof:name":"Super 8 Motel",
    "wof:placetype":"venue"
},
  "geometry": {"coordinates":[-89.23195800000001,43.186102],"type":"Point"}
}