{
  "type": "Feature",
  "properties": {
    "iso:country":"US",
    "sg:address":"5198 Bluff Rd",
    "sg:city":"Eagle",
    "sg:classifiers":[
        {
            "category":"Building & Trades",
            "subcategory":"Construction",
            "type":"Services"
        }
    ],
    "sg:phone":"+1 262 495 4550",
    "sg:postcode":"53119",
    "sg:province":"WI",
    "sg:tags":[
        "painter"
    ],
    "wof:name":"Santi Painting Inc",
    "wof:placetype":"venue"
},
  "geometry": {"coordinates":[-88.557918,42.835549],"type":"Point"}
}