{
  "type": "Feature",
  "properties": {
    "iso:country":"US",
    "sg:address":"2422 Pennsylvania Ave",
    "sg:city":"Madison",
    "sg:classifiers":[
        {
            "category":"Building & Trades",
            "subcategory":"Construction",
            "type":"Services"
        }
    ],
    "sg:phone":"+1 608 241 3401",
    "sg:postcode":"53704",
    "sg:province":"WI",
    "sg:tags":[
        "woodworker"
    ],
    "wof:name":"Rylander Rex Wood Carving",
    "wof:placetype":"venue"
},
  "geometry": {"coordinates":[-89.357956,43.10651],"type":"Point"}
}