{
  "type": "Feature",
  "properties": {
    "iso:country":"US",
    "sg:address":"2636 N 24th St",
    "sg:city":"Milwaukee",
    "sg:classifiers":[
        {
            "category":"Social Services",
            "subcategory":"Child Care",
            "type":"Services"
        }
    ],
    "sg:phone":"+1 414 374 4955",
    "sg:postcode":"53206",
    "sg:province":"WI",
    "sg:tags":[
        "day"
    ],
    "wof:name":"Crtcr Learn",
    "wof:placetype":"venue"
},
  "geometry": {"coordinates":[-87.94239399999999,43.067182],"type":"Point"}
}