{
  "type": "Feature",
  "properties": {
    "iso:country":"US",
    "sg:address":"730 Briar Ridge Dr E",
    "sg:city":"Brookfield",
    "sg:classifiers":[
        {
            "category":"Insurance",
            "subcategory":"Insurance Agent",
            "type":"Services"
        }
    ],
    "sg:phone":"+1 262 827 1899",
    "sg:postcode":"53045",
    "sg:province":"WI",
    "wof:name":"Caldwell Life Investments",
    "wof:placetype":"venue"
},
  "geometry": {"coordinates":[-88.153615,43.041941],"type":"Point"}
}