{
  "type": "Feature",
  "properties": {
    "iso:country":"US",
    "sg:address":"100 Grant St., Ste. 1018",
    "sg:city":"De Pere",
    "sg:classifiers":[
        {
            "category":"Professional",
            "subcategory":"Computer Services",
            "type":"Services"
        }
    ],
    "sg:phone":"+1 414 301 3325",
    "sg:postcode":"54115",
    "sg:province":"WI",
    "sg:tags":[
        "auction",
        "online-auction",
        "real-estate",
        "wholesale-properties",
        "liquidation"
    ],
    "sg:website":"http://www.Real-Deal.us",
    "wof:name":"Real Deal US",
    "wof:placetype":"venue"
},
  "geometry": {"coordinates":[-88.070978,44.445533],"type":"Point"}
}