{
  "type": "Feature",
  "properties": {
    "addr:full":"1121 S 114th St Milwaukee WI 53214",
    "addr:housenumber":"1121",
    "addr:postcode":"53214",
    "addr:street":"S 114Th St",
    "iso:country":"US",
    "sg:address":"1121 S 114th St",
    "sg:city":"Milwaukee",
    "sg:classifiers":[
        {
            "category":"Professional",
            "subcategory":"Art Services",
            "type":"Services"
        }
    ],
    "sg:phone":"+1 414 312 8304",
    "sg:postcode":"53214",
    "sg:province":"WI",
    "sg:tags":[
        "designer",
        "display",
        "producer"
    ],
    "wof:name":"Gravelle Designs",
    "wof:placetype":"venue"
},
  "geometry": {"coordinates":[-88.05457699999999,43.019836],"type":"Point"}
}