{
  "type": "Feature",
  "properties": {
    "iso:country":"US",
    "sg:address":"5201 Co Rd B",
    "sg:city":"Rio",
    "sg:classifiers":[
        {
            "category":"Building & Trades",
            "subcategory":"Construction",
            "type":"Services"
        }
    ],
    "sg:phone":"+1 920 992 3166",
    "sg:postcode":"53960",
    "sg:province":"WI",
    "sg:tags":[
        "product",
        "asphalt"
    ],
    "wof:name":"Northeast Asphalt Inc",
    "wof:placetype":"venue"
},
  "geometry": {"coordinates":[-89.146323,43.470732],"type":"Point"}
}