{
  "type": "Feature",
  "properties": {
    "iso:country":"US",
    "sg:address":"8290 100th Ave",
    "sg:city":"Chippewa Falls",
    "sg:classifiers":[
        {
            "category":"Farming",
            "subcategory":"Dairy Farm",
            "type":"Manufacturing & Wholesale Goods"
        }
    ],
    "sg:phone":"+1 715 288 6441",
    "sg:postcode":"54729",
    "sg:province":"WI",
    "sg:tags":[
        "field",
        "corn",
        "crop"
    ],
    "wof:name":"Kenneth Bohl",
    "wof:placetype":"venue"
},
  "geometry": {"coordinates":[-91.503711,44.987864],"type":"Point"}
}