{
  "type": "Feature",
  "properties": {
    "iso:country":"US",
    "sg:address":"12540 Halweg Rd",
    "sg:city":"Merrimac",
    "sg:classifiers":[
        {
            "category":"Travel",
            "subcategory":"Campground",
            "type":"Entertainment"
        }
    ],
    "sg:phone":"+1 608 493 2367",
    "sg:postcode":"53561",
    "sg:province":"WI",
    "sg:tags":[
        "trailer"
    ],
    "wof:name":"Merry Macs Campn",
    "wof:placetype":"venue"
},
  "geometry": {"coordinates":[-89.711364,43.385862],"type":"Point"}
}