{
  "type": "Feature",
  "properties": {
    "addr:full":"1020 Mobile St Lake Geneva WI 53147",
    "addr:housenumber":"1020",
    "addr:postcode":"53147",
    "addr:street":"Mobile St",
    "iso:country":"US",
    "sg:address":"1020 Mobile St",
    "sg:city":"Lake Geneva",
    "sg:classifiers":[
        {
            "category":"Real Estate",
            "subcategory":"Real Estate Operator",
            "type":"Services"
        }
    ],
    "sg:phone":"+1 262 248 8239",
    "sg:postcode":"53147",
    "sg:province":"WI",
    "sg:tags":[
        "mobile",
        "home",
        "site"
    ],
    "wof:name":"Lake Geneva MB Home Park Inc",
    "wof:placetype":"venue"
},
  "geometry": {"coordinates":[-88.423801,42.579321],"type":"Point"}
}