{
  "type": "Feature",
  "properties": {
    "iso:country":"US",
    "sg:address":"2701 Northwestern Ave",
    "sg:city":"Wausau",
    "sg:classifiers":[
        {
            "category":"Travel",
            "subcategory":"Campground",
            "type":"Entertainment"
        }
    ],
    "sg:phone":"+1 715 849 2267",
    "sg:postcode":"54403",
    "sg:province":"WI",
    "sg:tags":[
        "camp"
    ],
    "wof:name":"Y M C A Camp Sturtevant",
    "wof:placetype":"venue"
},
  "geometry": {"coordinates":[-89.592288,44.929995],"type":"Point"}
}