{
  "type": "Feature",
  "properties": {
    "addr:full":"624 Lake Ave Racine WI 53403",
    "addr:housenumber":"624",
    "addr:postcode":"53403",
    "addr:street":"Lake Ave",
    "iso:country":"US",
    "sg:address":"624 Lake Ave",
    "sg:city":"Racine",
    "sg:classifiers":[
        {
            "category":"Real Estate",
            "subcategory":"Real Estate Agent",
            "type":"Services"
        }
    ],
    "sg:phone":"+1 262 632 9304",
    "sg:postcode":"53403",
    "sg:province":"WI",
    "sg:tags":[
        "management"
    ],
    "wof:name":"Meridian Group",
    "wof:placetype":"venue"
},
  "geometry": {"coordinates":[-87.781589,42.726768],"type":"Point"}
}