{
  "type": "Feature",
  "properties": {
    "addr:full":"1624 Hobbs Dr Delavan WI 53115",
    "addr:housenumber":"1624",
    "addr:postcode":"53115",
    "addr:street":"Hobbs Dr",
    "iso:country":"US",
    "sg:address":"1624 Hobbs Dr",
    "sg:city":"Delavan",
    "sg:classifiers":[
        {
            "category":"Professional",
            "subcategory":"Lawyer & Legal Services",
            "type":"Services"
        }
    ],
    "sg:phone":"+1 262 740 1971",
    "sg:postcode":"53115",
    "sg:province":"WI",
    "sg:tags":[
        "attorney"
    ],
    "sg:website":"www.tcclaw.com",
    "wof:name":"Thorpe Compton & Christian Sc",
    "wof:placetype":"venue"
},
  "geometry": {"coordinates":[-88.62353400000001,42.630859],"type":"Point"}
}