{
  "type": "Feature",
  "properties": {
    "addr:full":"7036 State Rd 50 Lake Geneva WI 53147",
    "addr:housenumber":"7036;50",
    "addr:postcode":"53147",
    "addr:street":"State Rd",
    "iso:country":"US",
    "sg:address":"7036 State Rd 50",
    "sg:city":"Lake Geneva",
    "sg:classifiers":[
        {
            "category":"Building & Trades",
            "subcategory":"Construction",
            "type":"Services"
        }
    ],
    "sg:phone":"+1 262 249 0375",
    "sg:postcode":"53147",
    "sg:province":"WI",
    "sg:tags":[
        "home",
        "builder"
    ],
    "wof:name":"Timberidge Home Owners Assoc",
    "wof:placetype":"venue"
},
  "geometry": {"coordinates":[-88.403339,42.595082],"type":"Point"}
}