{
  "type": "Feature",
  "properties": {
    "iso:country":"US",
    "sg:address":"5087 Hample Rd",
    "sg:city":"Black Creek",
    "sg:phone":"+1 920 984 3727",
    "sg:postcode":"54106",
    "sg:province":"WI",
    "sg:tags":[
        "farm",
        "field",
        "corn",
        "crop"
    ],
    "wof:name":"Ron Volkman",
    "wof:placetype":"venue"
},
  "geometry": {"coordinates":[-88.474233,44.425856],"type":"Point"}
}