{
  "type": "Feature",
  "properties": {
    "iso:country":"US",
    "sg:address":"6981 Timber Ridge Cir",
    "sg:city":"Eau Claire",
    "sg:classifiers":[
        {
            "category":"Restaurant",
            "type":"Food & Drink"
        }
    ],
    "sg:phone":"+1 715 831 1768",
    "sg:postcode":"54701",
    "sg:province":"WI",
    "sg:tags":[
        "eating"
    ],
    "wof:name":"Kitchen Solvers",
    "wof:placetype":"venue"
},
  "geometry": {"coordinates":[-91.520825,44.729243],"type":"Point"}
}