{
  "type": "Feature",
  "properties": {
    "iso:country":"US",
    "sg:address":"2297 US Hwy 45",
    "sg:city":"Antigo",
    "sg:classifiers":[
        {
            "category":"Autos & Motor Vehicles",
            "subcategory":"Automobile Sales",
            "type":"Retail Goods"
        }
    ],
    "sg:phone":"+1 715 623 3169",
    "sg:postcode":"54409",
    "sg:province":"WI",
    "sg:tags":[
        "truck"
    ],
    "wof:name":"Lisa's Truck Stop",
    "wof:placetype":"venue"
},
  "geometry": {"coordinates":[-89.148166,45.163289],"type":"Point"}
}