{
  "type": "Feature",
  "properties": {
    "iso:country":"US",
    "sg:address":"142 Maple Ln",
    "sg:city":"Coleman",
    "sg:classifiers":[
        {
            "category":"Professional",
            "type":"Services"
        }
    ],
    "sg:phone":"+1 920 897 4344",
    "sg:postcode":"54112",
    "sg:province":"WI",
    "wof:name":"Thomas A Lee",
    "wof:placetype":"venue"
},
  "geometry": {"coordinates":[-88.03270000000001,45.068245],"type":"Point"}
}