{
  "type": "Feature",
  "properties": {
    "iso:country":"US",
    "sg:address":"530 Lake Dr",
    "sg:city":"Mellen",
    "sg:classifiers":[
        {
            "category":"Bars & Pubs",
            "type":"Food & Drink"
        }
    ],
    "sg:phone":"+1 715 274 5022",
    "sg:postcode":"54546",
    "sg:province":"WI",
    "wof:name":"T & M's Last Call",
    "wof:placetype":"venue"
},
  "geometry": {"coordinates":[-90.65387800000001,46.321242],"type":"Point"}
}