{
  "type": "Feature",
  "properties": {
    "iso:country":"US",
    "sg:address":"112 E Blodgett St",
    "sg:city":"Marshfield",
    "sg:classifiers":[
        {
            "category":"Professional",
            "subcategory":"Advertising",
            "type":"Services"
        }
    ],
    "sg:phone":"+1 715 387 0842",
    "sg:postcode":"54449",
    "sg:province":"WI",
    "sg:tags":[
        "outdoor"
    ],
    "wof:name":"Mueller Outdoor Advg LLC",
    "wof:placetype":"venue"
},
  "geometry": {"coordinates":[-90.171498,44.669473],"type":"Point"}
}