{
  "type": "Feature",
  "properties": {
    "addr:full":"7794 State Hwy 80 New Lisbon WI 53950",
    "addr:housenumber":"7794",
    "addr:postcode":"53950",
    "addr:street":"State Hwy 80",
    "iso:country":"US",
    "sg:address":"7794 State Hwy 80",
    "sg:city":"New Lisbon",
    "sg:classifiers":[
        {
            "category":"Shopping",
            "subcategory":"Computers & Home Electronics",
            "type":"Retail Goods"
        }
    ],
    "sg:phone":"+1 608 562 5756",
    "sg:postcode":"53950",
    "sg:province":"WI",
    "sg:tags":[
        "repair"
    ],
    "wof:name":"Rips Computer & Repair",
    "wof:placetype":"venue"
},
  "geometry": {"coordinates":[-90.108678,43.927484],"type":"Point"}
}