{
  "type": "Feature",
  "properties": {
    "iso:country":"US",
    "sg:address":"100 S Main St",
    "sg:city":"Brillion",
    "sg:classifiers":[
        {
            "category":"Personal",
            "subcategory":"Barber",
            "type":"Services"
        }
    ],
    "sg:phone":"+1 920 756 2950",
    "sg:postcode":"54110",
    "sg:province":"WI",
    "wof:name":"Pete's Barber Shop",
    "wof:placetype":"venue"
},
  "geometry": {"coordinates":[-88.064224,44.176891],"type":"Point"}
}