{
  "type": "Feature",
  "properties": {
    "iso:country":"US",
    "sg:address":"1033 N Hawley Rd",
    "sg:city":"Milwaukee",
    "sg:classifiers":[
        {
            "category":"Wholesale",
            "subcategory":"Chemicals & Plastics",
            "type":"Manufacturing & Wholesale Goods"
        }
    ],
    "sg:phone":"+1 414 258 4235",
    "sg:postcode":"53208",
    "sg:province":"WI",
    "wof:name":"Ashland Inc",
    "wof:placetype":"venue"
},
  "geometry": {"coordinates":[-87.983366,43.043103],"type":"Point"}
}