{
  "type": "Feature",
  "properties": {
    "iso:country":"US",
    "sg:address":"3143 Molly Brown Ln",
    "sg:city":"Green Bay",
    "sg:classifiers":[
        {
            "category":"Organizations",
            "subcategory":"Religious Organization",
            "type":"Services"
        }
    ],
    "sg:phone":"+1 920 434 0282",
    "sg:postcode":"54313",
    "sg:province":"WI",
    "sg:tags":[
        "clergy"
    ],
    "wof:name":"Donald Behrendt",
    "wof:placetype":"venue"
},
  "geometry": {"coordinates":[-88.102649,44.563349],"type":"Point"}
}