{
  "type": "Feature",
  "properties": {
    "iso:country":"US",
    "sg:address":"1025 W Glen Oaks Ln",
    "sg:city":"Mequon",
    "sg:classifiers":[
        {
            "category":"Insurance",
            "subcategory":"Hazard Insurance",
            "type":"Services"
        },
        {
            "category":"Insurance",
            "subcategory":"Insurance Agent",
            "type":"Services"
        }
    ],
    "sg:phone":"+1 262 241 8488",
    "sg:postcode":"53092",
    "sg:province":"WI",
    "sg:tags":[
        "carrier"
    ],
    "wof:name":"Bonniwell Financial Service",
    "wof:placetype":"venue"
},
  "geometry": {"coordinates":[-87.921098,43.235765],"type":"Point"}
}