{
  "type": "Feature",
  "properties": {
    "iso:country":"US",
    "sg:address":"112 W Jackson St",
    "sg:city":"Ripon",
    "sg:classifiers":[
        {
            "category":"Professional",
            "subcategory":"Computer Services",
            "type":"Services"
        }
    ],
    "sg:phone":"+1 920 748 5660",
    "sg:postcode":"54971",
    "sg:province":"WI",
    "sg:tags":[
        "repair"
    ],
    "wof:name":"ACC Microcomputer Svc",
    "wof:placetype":"venue"
},
  "geometry": {"coordinates":[-88.83981,43.846321],"type":"Point"}
}