{
  "type": "Feature",
  "properties": {
    "iso:country":"US",
    "sg:address":"109 Curtis Ave",
    "sg:city":"Neenah",
    "sg:classifiers":[
        {
            "category":"Wholesale",
            "subcategory":"Hardware",
            "type":"Manufacturing & Wholesale Goods"
        }
    ],
    "sg:phone":"+1 920 969 1527",
    "sg:postcode":"54956",
    "sg:province":"WI",
    "sg:tags":[
        "fastener"
    ],
    "wof:name":"Fastenal Co",
    "wof:placetype":"venue"
},
  "geometry": {"coordinates":[-88.46791399999999,44.170238],"type":"Point"}
}