{
  "type": "Feature",
  "properties": {
    "iso:country":"US",
    "sg:address":"616 W Green Tree Rd",
    "sg:city":"Milwaukee",
    "sg:classifiers":[
        {
            "category":"Professional",
            "type":"Services"
        }
    ],
    "sg:phone":"+1 414 352 5996",
    "sg:postcode":"53217",
    "sg:province":"WI",
    "wof:name":"Brookside Cbrf Inc",
    "wof:placetype":"venue"
},
  "geometry": {"coordinates":[-87.91731799999999,43.144109],"type":"Point"}
}