{
  "type": "Feature",
  "properties": {
    "addr:full":"56 Golf Course Rd Madison WI 53704",
    "addr:housenumber":"56",
    "addr:postcode":"53704",
    "addr:street":"Golf Course Rd",
    "iso:country":"US",
    "sg:address":"56 Golf Course Rd",
    "sg:city":"Madison",
    "sg:classifiers":[
        {
            "category":"Manufacturing",
            "subcategory":"Printing",
            "type":"Manufacturing & Wholesale Goods"
        }
    ],
    "sg:phone":"+1 608 241 2292",
    "sg:postcode":"53704",
    "sg:province":"WI",
    "sg:tags":[
        "newspaper"
    ],
    "wof:name":"Drum Corps World",
    "wof:placetype":"venue"
},
  "geometry": {"coordinates":[-89.369868,43.150071],"type":"Point"}
}