{
  "type": "Feature",
  "properties": {
    "iso:country":"US",
    "sg:address":"865 Hunters Trl",
    "sg:city":"Sun Prairie",
    "sg:classifiers":[
        {
            "category":"Building & Trades",
            "subcategory":"Construction",
            "type":"Services"
        }
    ],
    "sg:phone":"+1 608 837 2145",
    "sg:postcode":"53590",
    "sg:province":"WI",
    "sg:tags":[
        "residential"
    ],
    "wof:name":"Royal Concepts",
    "wof:placetype":"venue"
},
  "geometry": {"coordinates":[-89.24564,43.171236],"type":"Point"}
}