{
  "type": "Feature",
  "properties": {
    "iso:country":"US",
    "sg:address":"154 Main St",
    "sg:city":"Seneca",
    "sg:classifiers":[
        {
            "category":"Wholesale",
            "subcategory":"Farm Supplies",
            "type":"Manufacturing & Wholesale Goods"
        }
    ],
    "sg:phone":"+1 608 734 3700",
    "sg:postcode":"54654",
    "sg:province":"WI",
    "sg:tags":[
        "feed"
    ],
    "wof:name":"Seneca Feed & Supply",
    "wof:placetype":"venue"
},
  "geometry": {"coordinates":[-90.959839,43.264095],"type":"Point"}
}