{
  "type": "Feature",
  "properties": {
    "iso:country":"US",
    "sg:address":"322 Birchwood Ln",
    "sg:city":"Sheboygan",
    "sg:classifiers":[
        {
            "category":"Wholesale",
            "subcategory":"Furniture",
            "type":"Manufacturing & Wholesale Goods"
        }
    ],
    "sg:phone":"+1 920 452 1815",
    "sg:postcode":"53081",
    "sg:province":"WI",
    "wof:name":"Birchwood Bus Machines",
    "wof:placetype":"venue"
},
  "geometry": {"coordinates":[-87.706684,43.700583],"type":"Point"}
}