{
  "type": "Feature",
  "properties": {
    "iso:country":"US",
    "sg:address":"5899 N Richmond St",
    "sg:city":"Appleton",
    "sg:classifiers":[
        {
            "category":"Building & Trades",
            "subcategory":"Construction",
            "type":"Services"
        }
    ],
    "sg:phone":"+1 920 749 1026",
    "sg:postcode":"54913",
    "sg:province":"WI",
    "sg:tags":[
        "concrete",
        "contractor"
    ],
    "wof:name":"Advance Concrete Contractors",
    "wof:placetype":"venue"
},
  "geometry": {"coordinates":[-88.41485900000001,44.31641],"type":"Point"}
}