{
  "type": "Feature",
  "properties": {
    "addr:full":"4609 Triangle St Mc Farland WI 53558",
    "addr:housenumber":"4609",
    "addr:postcode":"53558",
    "addr:street":"Triangle St Mc Farland",
    "iso:country":"US",
    "sg:address":"4609 Triangle St",
    "sg:city":"Mc Farland",
    "sg:classifiers":[
        {
            "category":"Wholesale",
            "subcategory":"Machinery & Supplies",
            "type":"Manufacturing & Wholesale Goods"
        }
    ],
    "sg:phone":"+1 608 838 2400",
    "sg:postcode":"53558",
    "sg:province":"WI",
    "sg:tags":[
        "abrasive",
        "blasting",
        "painting"
    ],
    "wof:name":"A-1 Surface Prep Inc",
    "wof:placetype":"venue"
},
  "geometry": {"coordinates":[-89.297031,43.025869],"type":"Point"}
}