{
  "type": "Feature",
  "properties": {
    "iso:country":"US",
    "sg:address":"5981 S 27th St",
    "sg:city":"Milwaukee",
    "sg:classifiers":[
        {
            "category":"Retail",
            "subcategory":"Veterinary Services",
            "type":"Services"
        }
    ],
    "sg:phone":"+1 414 282 5230",
    "sg:postcode":"53221",
    "sg:province":"WI",
    "sg:tags":[
        "clinic",
        "veterinarian",
        "hospital"
    ],
    "sg:website":"http://www.gfvet.com",
    "wof:name":"Greenfield Veterinary Clinic",
    "wof:placetype":"venue"
},
  "geometry": {"coordinates":[-87.948635,42.972351],"type":"Point"}
}