{
  "type": "Feature",
  "properties": {
    "addr:full":"2007 S Browns Lake Dr Burlington WI 53105",
    "addr:housenumber":"2007",
    "addr:postcode":"53105",
    "addr:street":"S Browns Lake Dr",
    "iso:country":"US",
    "sg:address":"2007 S Browns Lake Dr",
    "sg:city":"Burlington",
    "sg:classifiers":[
        {
            "category":"Retail",
            "subcategory":"Veterinary Services",
            "type":"Services"
        }
    ],
    "sg:phone":"+1 262 763 2254",
    "sg:postcode":"53105",
    "sg:province":"WI",
    "sg:tags":[
        "veterinarian"
    ],
    "wof:name":"Country Veterinary Service",
    "wof:placetype":"venue"
},
  "geometry": {"coordinates":[-88.245499,42.6964],"type":"Point"}
}