{
  "type": "Feature",
  "properties": {
    "iso:country":"US",
    "sg:address":"8641 N Regent Rd",
    "sg:city":"Milwaukee",
    "sg:classifiers":[
        {
            "category":"Real Estate",
            "subcategory":"Architect",
            "type":"Services"
        }
    ],
    "sg:phone":"+1 414 351 3335",
    "sg:postcode":"53217",
    "sg:province":"WI",
    "sg:tags":[
        "architectural"
    ],
    "wof:name":"Johnson Glen M Architect",
    "wof:placetype":"venue"
},
  "geometry": {"coordinates":[-87.90535300000001,43.175079],"type":"Point"}
}