{
  "type": "Feature",
  "properties": {
    "iso:country":"US",
    "sg:address":"810 Scherer Ave",
    "sg:city":"Oconto",
    "sg:classifiers":[
        {
            "category":"Education",
            "subcategory":"School",
            "type":"Public Place"
        }
    ],
    "sg:phone":"+1 920 834 7806",
    "sg:postcode":"54153",
    "sg:province":"WI",
    "wof:name":"Oconto Elementary School",
    "wof:placetype":"venue"
},
  "geometry": {"coordinates":[-87.869963,44.877951],"type":"Point"}
}