{
  "type": "Feature",
  "properties": {
    "iso:country":"US",
    "sg:address":"878 E Maes Ave",
    "sg:city":"Kimberly",
    "sg:classifiers":[
        {
            "category":"Banks & Credit Unions",
            "subcategory":"Bank",
            "type":"Services"
        }
    ],
    "sg:phone":"+1 920 788 9700",
    "sg:postcode":"54136",
    "sg:province":"WI",
    "sg:tags":[
        "personal",
        "institution"
    ],
    "wof:name":"Cash Store",
    "wof:placetype":"venue"
},
  "geometry": {"coordinates":[-88.324483,44.274108],"type":"Point"}
}