{
  "type": "Feature",
  "properties": {
    "iso:country":"US",
    "sg:address":"2606 Monroe St",
    "sg:city":"Madison",
    "sg:classifiers":[
        {
            "category":"Shopping",
            "subcategory":"Used Merchandise",
            "type":"Retail Goods"
        }
    ],
    "sg:phone":"+1 608 231 0998",
    "sg:postcode":"53711",
    "sg:province":"WI",
    "wof:name":"Monroe Street Antiques",
    "wof:placetype":"venue"
},
  "geometry": {"coordinates":[-89.428819,43.05733],"type":"Point"}
}