{
  "type": "Feature",
  "properties": {
    "iso:country":"US",
    "sg:address":"1221 21st St",
    "sg:city":"Racine",
    "sg:classifiers":[
        {
            "category":"Utilities",
            "subcategory":"Refuse",
            "type":"Services"
        }
    ],
    "sg:phone":"+1 262 638 1699",
    "sg:postcode":"53403",
    "sg:province":"WI",
    "sg:tags":[
        "system"
    ],
    "wof:name":"Ssi",
    "wof:placetype":"venue"
},
  "geometry": {"coordinates":[-87.794598,42.704224],"type":"Point"}
}