{
  "type": "Feature",
  "properties": {
    "iso:country":"US",
    "sg:address":"2548 Glendale Ave",
    "sg:city":"Green Bay",
    "sg:classifiers":[
        {
            "category":"Home & Garden",
            "subcategory":"Hardware",
            "type":"Retail Goods"
        }
    ],
    "sg:phone":"+1 920 434 1079",
    "sg:postcode":"54313",
    "sg:province":"WI",
    "wof:name":"Kimps Ace Hardware",
    "wof:placetype":"venue"
},
  "geometry": {"coordinates":[-88.08461,44.565539],"type":"Point"}
}