{
  "type": "Feature",
  "properties": {
    "iso:country":"US",
    "sg:address":"707 N Central Ave",
    "sg:city":"Marshfield",
    "sg:classifiers":[
        {
            "category":"Shopping",
            "subcategory":"Music",
            "type":"Retail Goods"
        }
    ],
    "sg:phone":"+1 715 486 0701",
    "sg:postcode":"54449",
    "sg:province":"WI",
    "wof:name":"Family Video",
    "wof:placetype":"venue"
},
  "geometry": {"coordinates":[-90.168386,44.674027],"type":"Point"}
}