{
  "type": "Feature",
  "properties": {
    "iso:country":"US",
    "sg:address":"4027 S Business Dr",
    "sg:city":"Sheboygan",
    "sg:classifiers":[
        {
            "category":"Health Services",
            "subcategory":"Health Practitioner",
            "type":"Services"
        }
    ],
    "sg:phone":"+1 920 459 9090",
    "sg:postcode":"53081",
    "sg:province":"WI",
    "wof:name":"Creekside Chiropractic",
    "wof:placetype":"venue"
},
  "geometry": {"coordinates":[-87.741688,43.710228],"type":"Point"}
}