{
  "type": "Feature",
  "properties": {
    "iso:country":"US",
    "sg:address":"333 W Brown Deer Rd",
    "sg:city":"Milwaukee",
    "sg:classifiers":[
        {
            "category":"Shopping",
            "subcategory":"Jewelry",
            "type":"Retail Goods"
        }
    ],
    "sg:phone":"+1 414 351 0333",
    "sg:postcode":"53217",
    "sg:province":"WI",
    "sg:tags":[
        "jeweler"
    ],
    "wof:name":"Atypic Gallery",
    "wof:placetype":"venue"
},
  "geometry": {"coordinates":[-87.910402,43.176644],"type":"Point"}
}