{
  "type": "Feature",
  "properties": {
    "iso:country":"US",
    "sg:address":"4570 S 27th St",
    "sg:city":"Milwaukee",
    "sg:classifiers":[
        {
            "category":"Community Center",
            "type":"Public Place"
        }
    ],
    "sg:phone":"+1 414 325 8720",
    "sg:postcode":"53221",
    "sg:province":"WI",
    "sg:tags":[
        "medical"
    ],
    "wof:name":"St Luke's Pain Management Ctr",
    "wof:placetype":"venue"
},
  "geometry": {"coordinates":[-87.94854599999999,42.960855],"type":"Point"}
}