{
  "type": "Feature",
  "properties": {
    "addr:full":"1114 Lake Shore Dr W Ashland WI 54806",
    "addr:housenumber":"1114",
    "addr:postcode":"54806",
    "addr:street":"Lake Shore Dr W",
    "iso:country":"US",
    "sg:address":"1114 Lake Shore Dr W",
    "sg:city":"Ashland",
    "sg:classifiers":[
        {
            "category":"Taxi",
            "type":"Transportation"
        }
    ],
    "sg:phone":"+1 715 682 4588",
    "sg:postcode":"54806",
    "sg:province":"WI",
    "sg:tags":[
        "taxicab"
    ],
    "wof:name":"Bay Area Transport LLC",
    "wof:placetype":"venue"
},
  "geometry": {"coordinates":[-90.89756,46.58643],"type":"Point"}
}