{
  "type": "Feature",
  "properties": {
    "iso:country":"US",
    "sg:address":"2701 30th Ave",
    "sg:city":"Kenosha",
    "sg:classifiers":[
        {
            "category":"Banks & Credit Unions",
            "subcategory":"Bank",
            "type":"Services"
        }
    ],
    "sg:phone":"+1 262 697 3700",
    "sg:postcode":"53144",
    "sg:province":"WI",
    "sg:website":"www.amccu.org",
    "wof:name":"A M Community Credit Union",
    "wof:placetype":"venue"
},
  "geometry": {"coordinates":[-87.845821,42.612717],"type":"Point"}
}