{
  "type": "Feature",
  "properties": {
    "iso:country":"US",
    "sg:address":"2648 Packerland Dr",
    "sg:city":"Green Bay",
    "sg:classifiers":[
        {
            "category":"Restaurant",
            "type":"Food & Drink"
        }
    ],
    "sg:phone":"+1 920 405 8000",
    "sg:postcode":"54313",
    "sg:province":"WI",
    "sg:tags":[
        "eating"
    ],
    "wof:name":"Fatzo's Sub & Pizza Shop",
    "wof:placetype":"venue"
},
  "geometry": {"coordinates":[-88.10802700000001,44.490612],"type":"Point"}
}