{
  "type": "Feature",
  "properties": {
    "addr:full":"4828 Cedar Hills Dr Slinger WI 53086",
    "addr:housenumber":"4828",
    "addr:postcode":"53086",
    "addr:street":"Cedar Hills Dr",
    "iso:country":"US",
    "sg:address":"4828 Cedar Hills Dr",
    "sg:city":"Slinger",
    "sg:classifiers":[
        {
            "category":"Home & Garden",
            "subcategory":"Building Materials",
            "type":"Retail Goods"
        },
        {
            "category":"Professional",
            "type":"Services"
        }
    ],
    "sg:phone":"+1 262 644 8382",
    "sg:postcode":"53086",
    "sg:province":"WI",
    "sg:tags":[
        "door"
    ],
    "wof:name":"Keith & Sons Overhead Door Inc",
    "wof:placetype":"venue"
},
  "geometry": {"coordinates":[-88.279455,43.360206],"type":"Point"}
}