{
  "type": "Feature",
  "properties": {
    "iso:country":"US",
    "sg:address":"540 W Olin Ave",
    "sg:city":"Madison",
    "sg:classifiers":[
        {
            "category":"Autos & Motor Vehicles",
            "subcategory":"Auto Supplies",
            "type":"Retail Goods"
        }
    ],
    "sg:phone":"+1 608 280 0506",
    "sg:postcode":"53715",
    "sg:province":"WI",
    "wof:name":"Nellie Hub Cap",
    "wof:placetype":"venue"
},
  "geometry": {"coordinates":[-89.39217,43.053987],"type":"Point"}
}