{
  "type": "Feature",
  "properties": {
    "addr:full":"2429 Butler Rd Iron Ridge WI 53035",
    "addr:housenumber":"2429",
    "addr:postcode":"53035",
    "addr:street":"Butler Rd",
    "iso:country":"US",
    "sg:address":"2429 Butler Rd",
    "sg:city":"Iron Ridge",
    "sg:classifiers":[
        {
            "category":"Shopping",
            "type":"Retail Goods"
        }
    ],
    "sg:phone":"+1 920 625 3233",
    "sg:postcode":"53035",
    "sg:province":"WI",
    "sg:tags":[
        "repair",
        "merchandise"
    ],
    "wof:name":"K & K Dairy Supply Inc",
    "wof:placetype":"venue"
},
  "geometry": {"coordinates":[-88.516864,43.351938],"type":"Point"}
}