{
  "type": "Feature",
  "properties": {
    "addr:full":"9123 N 85th St Milwaukee WI 53224",
    "addr:housenumber":"9123",
    "addr:postcode":"53224",
    "addr:street":"N 85Th St",
    "iso:country":"US",
    "sg:address":"9123 N 85th St",
    "sg:city":"Milwaukee",
    "sg:classifiers":[
        {
            "category":"Organizations",
            "subcategory":"Membership Organization",
            "type":"Services"
        }
    ],
    "sg:phone":"+1 262 242 3049",
    "sg:postcode":"53224",
    "sg:province":"WI",
    "wof:name":"Thoreson Family Foundatio",
    "wof:placetype":"venue"
},
  "geometry": {"coordinates":[-88.01566800000001,43.18315],"type":"Point"}
}