{
  "type": "Feature",
  "properties": {
    "addr:full":"535 Science Dr Madison WI 53711",
    "addr:housenumber":"535",
    "addr:postcode":"53711",
    "addr:street":"Science Dr",
    "iso:country":"US",
    "sg:address":"535 Science Dr",
    "sg:city":"Madison",
    "sg:classifiers":[
        {
            "category":"Communications",
            "subcategory":"Film & Video Production",
            "type":"Services"
        }
    ],
    "sg:phone":"+1 608 238 7575",
    "sg:postcode":"53711",
    "sg:province":"WI",
    "sg:tags":[
        "taping"
    ],
    "wof:name":"Token Creek Productions",
    "wof:placetype":"venue"
},
  "geometry": {"coordinates":[-89.46786400000001,43.056058],"type":"Point"}
}