{
  "type": "Feature",
  "properties": {
    "iso:country":"US",
    "sg:address":"2044 S 55th St",
    "sg:city":"Milwaukee",
    "sg:classifiers":[
        {
            "category":"Wholesale",
            "subcategory":"Machinery & Supplies",
            "type":"Manufacturing & Wholesale Goods"
        }
    ],
    "sg:phone":"+1 414 643 4453",
    "sg:postcode":"53219",
    "sg:province":"WI",
    "sg:tags":[
        "machine",
        "tool"
    ],
    "wof:name":"ERN Svc Inc",
    "wof:placetype":"venue"
},
  "geometry": {"coordinates":[-87.981465,43.006643],"type":"Point"}
}