{
  "type": "Feature",
  "properties": {
    "iso:country":"US",
    "sg:address":"345 Village Ct",
    "sg:city":"Green Bay",
    "sg:classifiers":[
        {
            "category":"Recreation",
            "type":"Entertainment"
        }
    ],
    "sg:phone":"+1 920 498 2797",
    "sg:postcode":"54303",
    "sg:province":"WI",
    "sg:tags":[
        "range",
        "practice",
        "golf",
        "driving"
    ],
    "wof:name":"Duck Creek Golf Center",
    "wof:placetype":"venue"
},
  "geometry": {"coordinates":[-88.069638,44.548375],"type":"Point"}
}