{
  "type": "Feature",
  "properties": {
    "iso:country":"US",
    "sg:address":"3609 Roosevelt Rd",
    "sg:city":"Kenosha",
    "sg:classifiers":[
        {
            "category":"Building & Trades",
            "subcategory":"Construction",
            "type":"Services"
        }
    ],
    "sg:phone":"+1 262 653 1583",
    "sg:postcode":"53142",
    "sg:province":"IL",
    "sg:tags":[
        "house"
    ],
    "wof:name":"Countryside Builders",
    "wof:placetype":"venue"
},
  "geometry": {"coordinates":[-87.852822,42.567645],"type":"Point"}
}