{
  "type": "Feature",
  "properties": {
    "addr:full":"8432 Fern Rd Oxford WI 53952",
    "addr:housenumber":"8432",
    "addr:postcode":"53952",
    "addr:street":"Fern Rd",
    "iso:country":"US",
    "sg:address":"8432 Fern Rd",
    "sg:city":"Oxford",
    "sg:phone":"+1 608 586 4128",
    "sg:postcode":"53952",
    "sg:province":"WI",
    "sg:tags":[
        "farm",
        "field",
        "corn",
        "soybean",
        "crop"
    ],
    "wof:name":"Wayne Walters",
    "wof:placetype":"venue"
},
  "geometry": {"coordinates":[-89.572675,43.792255],"type":"Point"}
}