{
  "type": "Feature",
  "properties": {
    "addr:full":"7015 State Rd 21 Wautoma WI 54982",
    "addr:housenumber":"7015;21",
    "addr:postcode":"54982",
    "addr:street":"State Rd",
    "iso:country":"US",
    "sg:address":"7015 State Rd 21",
    "sg:city":"Wautoma",
    "sg:classifiers":[
        {
            "category":"Travel",
            "subcategory":"Hotels & Motels",
            "type":"Entertainment"
        }
    ],
    "sg:phone":"+1 920 787 3367",
    "sg:postcode":"54982",
    "sg:province":"WI",
    "sg:website":"www.silvercryst.com",
    "wof:name":"Silvercryst Supper Club/Motel",
    "wof:placetype":"venue"
},
  "geometry": {"coordinates":[-89.231964,44.058545],"type":"Point"}
}