{
  "type": "Feature",
  "properties": {
    "iso:country":"US",
    "sg:address":"812 S Railroad St",
    "sg:city":"Kimberly",
    "sg:classifiers":[
        {
            "category":"Freight",
            "type":"Transportation"
        }
    ],
    "sg:phone":"+1 920 734 0890",
    "sg:postcode":"54136",
    "sg:province":"WI",
    "sg:tags":[
        "general"
    ],
    "wof:name":"Anchor Storage",
    "wof:placetype":"venue"
},
  "geometry": {"coordinates":[-88.339146,44.260571],"type":"Point"}
}