{
  "type": "Feature",
  "properties": {
    "addr:full":"401 4th St Marathon WI 54448",
    "addr:housenumber":"401",
    "addr:postcode":"54448",
    "addr:street":"4Th St",
    "iso:country":"US",
    "sg:address":"401 4th St",
    "sg:city":"Marathon",
    "sg:classifiers":[
        {
            "category":"Recreation",
            "type":"Entertainment"
        }
    ],
    "sg:phone":"+1 715 443 3772",
    "sg:postcode":"54448",
    "sg:province":"WI",
    "sg:tags":[
        "instruction",
        "swimming"
    ],
    "wof:name":"Marathon Area Swim Assn",
    "wof:placetype":"venue"
},
  "geometry": {"coordinates":[-89.839007,44.930465],"type":"Point"}
}