{
  "type": "Feature",
  "properties": {
    "addr:full":"7515 Rohlich Ct Middleton WI 53562",
    "addr:housenumber":"7515",
    "addr:postcode":"53562",
    "addr:street":"Rohlich Ct",
    "iso:country":"US",
    "sg:address":"7515 Rohlich Ct",
    "sg:city":"Middleton",
    "sg:classifiers":[
        {
            "category":"Real Estate",
            "subcategory":"Real Estate Operator",
            "type":"Services"
        }
    ],
    "sg:phone":"+1 608 831 7781",
    "sg:postcode":"53562",
    "sg:province":"WI",
    "sg:tags":[
        "building",
        "apartment"
    ],
    "wof:name":"Rohlich Court Apartments",
    "wof:placetype":"venue"
},
  "geometry": {"coordinates":[-89.512595,43.100082],"type":"Point"}
}