{
  "type": "Feature",
  "properties": {
    "iso:country":"US",
    "sg:address":"772 E Inman Pkwy",
    "sg:city":"Beloit",
    "sg:classifiers":[
        {
            "category":"Wholesale",
            "subcategory":"Machinery & Supplies",
            "type":"Manufacturing & Wholesale Goods"
        }
    ],
    "sg:phone":"+1 608 363 0531",
    "sg:postcode":"53511",
    "sg:province":"WI",
    "sg:tags":[
        "equipment",
        "material",
        "handling"
    ],
    "wof:name":"Joyce Dayton Corp",
    "wof:placetype":"venue"
},
  "geometry": {"coordinates":[-89.030834,42.554675],"type":"Point"}
}