{
  "type": "Feature",
  "properties": {
    "iso:country":"US",
    "sg:address":"300 York St",
    "sg:city":"Beaver Dam",
    "sg:classifiers":[
        {
            "category":"Professional",
            "subcategory":"Management & Consulting",
            "type":"Services"
        }
    ],
    "sg:phone":"+1 920 885 2392",
    "sg:postcode":"53916",
    "sg:province":"WI",
    "sg:tags":[
        "business"
    ],
    "wof:name":"Kiekhaefer Consulting LLC",
    "wof:placetype":"venue"
},
  "geometry": {"coordinates":[-88.836276,43.464867],"type":"Point"}
}