{
  "type": "Feature",
  "properties": {
    "iso:country":"US",
    "sg:address":"2289 S Thompson Dr",
    "sg:city":"Madison",
    "sg:classifiers":[
        {
            "category":"Building & Trades",
            "subcategory":"Construction",
            "type":"Services"
        }
    ],
    "sg:phone":"+1 608 279 9101",
    "sg:postcode":"53716",
    "sg:province":"WI",
    "sg:tags":[
        "general",
        "contractor"
    ],
    "wof:name":"Overson Construction Inc",
    "wof:placetype":"venue"
},
  "geometry": {"coordinates":[-89.28994299999999,43.067218],"type":"Point"}
}