{
  "type": "Feature",
  "properties": {
    "iso:country":"US",
    "sg:address":"1553 E Racine Ave",
    "sg:city":"Waukesha",
    "sg:classifiers":[
        {
            "category":"Building & Trades",
            "subcategory":"Construction",
            "type":"Services"
        }
    ],
    "sg:phone":"+1 262 542 6100",
    "sg:postcode":"53186",
    "sg:province":"WI",
    "sg:tags":[
        "house",
        "builder",
        "home"
    ],
    "sg:website":"www.halcyonhomesinc.com",
    "wof:name":"Halcyon Homes Inc",
    "wof:placetype":"venue"
},
  "geometry": {"coordinates":[-88.20401699999999,42.996981],"type":"Point"}
}