{
  "type": "Feature",
  "properties": {
    "iso:country":"US",
    "sg:address":"227 Dewey Ave",
    "sg:city":"Fontana",
    "sg:classifiers":[
        {
            "category":"Travel",
            "subcategory":"Hotels & Motels",
            "type":"Entertainment"
        }
    ],
    "sg:phone":"+1 262 275 6861",
    "sg:postcode":"53125",
    "sg:province":"WI",
    "sg:tags":[
        "operation"
    ],
    "wof:name":"Colony House",
    "wof:placetype":"venue"
},
  "geometry": {"coordinates":[-88.585896,42.545436],"type":"Point"}
}