{
  "type": "Feature",
  "properties": {
    "iso:country":"US",
    "sg:address":"1105 E Wisconsin Ave",
    "sg:city":"Appleton",
    "sg:classifiers":[
        {
            "category":"Professional",
            "subcategory":"Art Services",
            "type":"Services"
        }
    ],
    "sg:phone":"+1 920 733 8192",
    "sg:postcode":"54911",
    "sg:province":"WI",
    "sg:tags":[
        "photographer"
    ],
    "wof:name":"Gordon's Photography",
    "wof:placetype":"venue"
},
  "geometry": {"coordinates":[-88.387683,44.272944],"type":"Point"}
}