{
  "type": "Feature",
  "properties": {
    "addr:full":"11703 Waters Rd Fall River WI 53932",
    "addr:housenumber":"11703",
    "addr:postcode":"53932",
    "addr:street":"Waters Rd",
    "iso:country":"US",
    "sg:address":"11703 Waters Rd",
    "sg:city":"Fall River",
    "sg:classifiers":[
        {
            "category":"Farming",
            "subcategory":"Farm",
            "type":"Manufacturing & Wholesale Goods"
        }
    ],
    "sg:phone":"+1 920 484 3165",
    "sg:postcode":"53932",
    "sg:province":"WI",
    "sg:tags":[
        "crop",
        "general"
    ],
    "wof:name":"James Kopplin",
    "wof:placetype":"venue"
},
  "geometry": {"coordinates":[-88.994219,43.436875],"type":"Point"}
}