{
  "type": "Feature",
  "properties": {
    "iso:country":"US",
    "sg:address":"6830 W Villard Ave",
    "sg:city":"Milwaukee",
    "sg:classifiers":[
        {
            "category":"Government",
            "subcategory":"Office",
            "type":"Public Place"
        }
    ],
    "sg:phone":"+1 414 438 4869",
    "sg:postcode":"53218",
    "sg:province":"WI",
    "sg:tags":[
        "state",
        "resource"
    ],
    "wof:name":"Deaf & Hearing Impaired Svc",
    "wof:placetype":"venue"
},
  "geometry": {"coordinates":[-87.996982,43.112243],"type":"Point"}
}