{
  "type": "Feature",
  "properties": {
    "iso:country":"US",
    "sg:address":"2101 Sugar River Rd",
    "sg:city":"Verona",
    "sg:classifiers":[
        {
            "category":"Building & Trades",
            "subcategory":"Construction",
            "type":"Services"
        }
    ],
    "sg:phone":"+1 608 845 8611",
    "sg:postcode":"53593",
    "sg:province":"WI",
    "sg:tags":[
        "carpentry",
        "contractor"
    ],
    "wof:name":"Doug Wilson Carpentry",
    "wof:placetype":"venue"
},
  "geometry": {"coordinates":[-89.573246,42.97054],"type":"Point"}
}