{
  "type": "Feature",
  "properties": {
    "iso:country":"US",
    "sg:address":"1221 S Park St",
    "sg:city":"Port Washington",
    "sg:classifiers":[
        {
            "category":"Manufacturing",
            "subcategory":"Metals",
            "type":"Manufacturing & Wholesale Goods"
        }
    ],
    "sg:phone":"+1 262 284 3424",
    "sg:postcode":"53074",
    "sg:province":"WI",
    "sg:tags":[
        "stamping"
    ],
    "sg:website":"www.kmcstampings.com",
    "wof:name":"Kickhaefer Mfg CO-Kmc",
    "wof:placetype":"venue"
},
  "geometry": {"coordinates":[-87.883049,43.373986],"type":"Point"}
}