{
  "type": "Feature",
  "properties": {
    "iso:country":"US",
    "sg:address":"368 W Main St",
    "sg:city":"Ellsworth",
    "sg:classifiers":[
        {
            "category":"Shopping",
            "subcategory":"Gifts & Souvenirs",
            "type":"Retail Goods"
        }
    ],
    "sg:phone":"+1 715 273 4380",
    "sg:postcode":"54011",
    "sg:province":"WI",
    "wof:name":"Heartfelt Gifts",
    "wof:placetype":"venue"
},
  "geometry": {"coordinates":[-92.48366,44.732149],"type":"Point"}
}