{
  "type": "Feature",
  "properties": {
    "iso:country":"US",
    "sg:address":"1020 Superior Ave",
    "sg:city":"Tomah",
    "sg:classifiers":[
        {
            "category":"Retail",
            "subcategory":"Portrait Studio",
            "type":"Services"
        }
    ],
    "sg:phone":"+1 608 372 7666",
    "sg:postcode":"54660",
    "sg:province":"WI",
    "sg:tags":[
        "photographer"
    ],
    "wof:name":"Hininger Photography",
    "wof:placetype":"venue"
},
  "geometry": {"coordinates":[-90.5047,43.977487],"type":"Point"}
}