{
  "type": "Feature",
  "properties": {
    "iso:country":"US",
    "sg:address":"200 Industrial Ave",
    "sg:city":"Lyndon Station",
    "sg:classifiers":[
        {
            "category":"Manufacturing",
            "subcategory":"Metals",
            "type":"Manufacturing & Wholesale Goods"
        }
    ],
    "sg:phone":"+1 608 666 2080",
    "sg:postcode":"53944",
    "sg:province":"WI",
    "sg:tags":[
        "foundry"
    ],
    "wof:name":"Falcon Foundry Products & Svc",
    "wof:placetype":"venue"
},
  "geometry": {"coordinates":[-89.879166,43.706252],"type":"Point"}
}