{
  "type": "Feature",
  "properties": {
    "addr:full":"1712 19th St Eau Claire WI 54703",
    "addr:housenumber":"1712",
    "addr:postcode":"54703",
    "addr:street":"19Th St",
    "iso:country":"US",
    "sg:address":"1712 19th St",
    "sg:city":"Eau Claire",
    "sg:classifiers":[
        {
            "category":"Professional",
            "type":"Services"
        }
    ],
    "sg:phone":"+1 715 831 2133",
    "sg:postcode":"54703",
    "sg:province":"WI",
    "wof:name":"TW Assoc",
    "wof:placetype":"venue"
},
  "geometry": {"coordinates":[-91.535566,44.816854],"type":"Point"}
}