{
  "type": "Feature",
  "properties": {
    "iso:country":"US",
    "sg:address":"4601 E Towne Blvd",
    "sg:city":"Madison",
    "sg:classifiers":[
        {
            "category":"Autos & Motor Vehicles",
            "subcategory":"Auto Supplies",
            "type":"Retail Goods"
        }
    ],
    "sg:phone":"+1 608 249 5349",
    "sg:postcode":"53704",
    "sg:province":"WI",
    "wof:name":"Bridgestone/Firestone 29yp",
    "wof:placetype":"venue"
},
  "geometry": {"coordinates":[-89.306155,43.127928],"type":"Point"}
}