{
  "type": "Feature",
  "properties": {
    "iso:country":"US",
    "sg:address":"10309 W Wheeler Rd",
    "sg:city":"Evansville",
    "sg:classifiers":[
        {
            "category":"Building & Trades",
            "subcategory":"Construction",
            "type":"Services"
        }
    ],
    "sg:phone":"+1 608 882 9826",
    "sg:postcode":"53536",
    "sg:province":"WI",
    "sg:tags":[
        "house"
    ],
    "wof:name":"DH Const Co",
    "wof:placetype":"venue"
},
  "geometry": {"coordinates":[-89.201085,42.769686],"type":"Point"}
}