{
  "type": "Feature",
  "properties": {
    "iso:country":"US",
    "sg:address":"3115 Mathey Rd",
    "sg:city":"Sturgeon Bay",
    "sg:classifiers":[
        {
            "category":"Real Estate",
            "subcategory":"Real Estate Agent",
            "type":"Services"
        }
    ],
    "sg:phone":"+1 920 746 9051",
    "sg:postcode":"54235",
    "sg:province":"WI",
    "wof:name":"Sweet Dreams LLC",
    "wof:placetype":"venue"
},
  "geometry": {"coordinates":[-87.315533,44.820085],"type":"Point"}
}