{
  "type": "Feature",
  "properties": {
    "addr:full":"929 Williams St Lake Geneva WI 53147",
    "addr:housenumber":"929",
    "addr:postcode":"53147",
    "addr:street":"Williams St",
    "iso:country":"US",
    "sg:address":"929 Williams St",
    "sg:city":"Lake Geneva",
    "sg:classifiers":[
        {
            "category":"Health Services",
            "subcategory":"Health Practitioner",
            "type":"Services"
        }
    ],
    "sg:phone":"+1 262 248 2008",
    "sg:postcode":"53147",
    "sg:province":"WI",
    "sg:tags":[
        "therapist",
        "physical"
    ],
    "wof:name":"Tim Greene Physical Therapy",
    "wof:placetype":"venue"
},
  "geometry": {"coordinates":[-88.43574,42.600795],"type":"Point"}
}