{
  "type": "Feature",
  "properties": {
    "iso:country":"US",
    "sg:address":"503 E Ives St",
    "sg:city":"Marshfield",
    "sg:classifiers":[
        {
            "category":"Shopping",
            "subcategory":"Books",
            "type":"Retail Goods"
        }
    ],
    "sg:phone":"+1 715 387 4855",
    "sg:postcode":"54449",
    "sg:province":"WI",
    "sg:tags":[
        "religious",
        "dealer",
        "gift"
    ],
    "wof:name":"Christian Books and Gifts",
    "wof:placetype":"venue"
},
  "geometry": {"coordinates":[-90.16110500000001,44.677148],"type":"Point"}
}