{
  "type": "Feature",
  "properties": {
    "addr:full":"3921 Olive St Racine WI 53405",
    "addr:housenumber":"3921",
    "addr:postcode":"53405",
    "addr:street":"Olive St",
    "iso:country":"US",
    "sg:address":"3921 Olive St",
    "sg:city":"Racine",
    "sg:classifiers":[
        {
            "category":"Professional",
            "subcategory":"Employment Agencies",
            "type":"Services"
        }
    ],
    "sg:phone":"+1 262 554 1263",
    "sg:postcode":"53405",
    "sg:province":"WI",
    "sg:tags":[
        "help",
        "supply"
    ],
    "wof:name":"Manpower",
    "wof:placetype":"venue"
},
  "geometry": {"coordinates":[-87.827023,42.70246],"type":"Point"}
}