{
  "type": "Feature",
  "properties": {
    "iso:country":"US",
    "sg:address":"838 Co Rd J",
    "sg:city":"Hatley",
    "sg:classifiers":[
        {
            "category":"Freight",
            "type":"Transportation"
        }
    ],
    "sg:phone":"+1 715 446 3408",
    "sg:postcode":"54440",
    "sg:province":"WI",
    "sg:tags":[
        "special"
    ],
    "wof:name":"Highway J Storage",
    "wof:placetype":"venue"
},
  "geometry": {"coordinates":[-89.447661,44.799185],"type":"Point"}
}