{
  "type": "Feature",
  "properties": {
    "iso:country":"US",
    "sg:address":"698 S Whitney Way",
    "sg:city":"Madison",
    "sg:classifiers":[
        {
            "category":"Shopping",
            "subcategory":"Clothing, Apparel, & Fashions",
            "type":"Retail Goods"
        }
    ],
    "sg:phone":"+1 608 278 7509",
    "sg:postcode":"53711",
    "sg:province":"WI",
    "sg:tags":[
        "furnishing"
    ],
    "wof:name":"Casual Male Big & Tall",
    "wof:placetype":"venue"
},
  "geometry": {"coordinates":[-89.473494,43.051902],"type":"Point"}
}