{
  "type": "Feature",
  "properties": {
    "iso:country":"US",
    "sg:address":"5009 8th Ave",
    "sg:city":"Kenosha",
    "sg:classifiers":[
        {
            "category":"Professional",
            "type":"Services"
        }
    ],
    "sg:phone":"+1 262 657 9474",
    "sg:postcode":"53140",
    "sg:province":"WI",
    "sg:tags":[
        "establishment"
    ],
    "wof:name":"Phoenix Enterprises",
    "wof:placetype":"venue"
},
  "geometry": {"coordinates":[-87.82158099999999,42.590005],"type":"Point"}
}