{
  "type": "Feature",
  "properties": {
    "iso:country":"US",
    "sg:address":"101 Main St W",
    "sg:city":"Ashland",
    "sg:classifiers":[
        {
            "category":"Professional",
            "type":"Services"
        }
    ],
    "sg:phone":"+1 715 685 9320",
    "sg:postcode":"54806",
    "sg:province":"WI",
    "sg:tags":[
        "establishment"
    ],
    "wof:name":"Martinsen Co General Counsel",
    "wof:placetype":"venue"
},
  "geometry": {"coordinates":[-90.8832,46.59149],"type":"Point"}
}