{
  "type": "Feature",
  "properties": {
    "iso:country":"US",
    "sg:address":"3102 Woodland Dr",
    "sg:city":"Campbellsport",
    "sg:classifiers":[
        {
            "category":"Professional",
            "subcategory":"Business Services",
            "type":"Services"
        }
    ],
    "sg:phone":"+1 920 533 4180",
    "sg:postcode":"53010",
    "sg:province":"WI",
    "wof:name":"Darrens Automotive",
    "wof:placetype":"venue"
},
  "geometry": {"coordinates":[-88.23419199999999,43.644904],"type":"Point"}
}