{
  "type": "Feature",
  "properties": {
    "iso:country":"US",
    "sg:address":"960 Estes Dr",
    "sg:city":"De Pere",
    "sg:classifiers":[
        {
            "category":"Food & Beverages",
            "subcategory":"Specialty",
            "type":"Retail Goods"
        }
    ],
    "sg:phone":"+1 920 983 1912",
    "sg:postcode":"54115",
    "sg:province":"WI",
    "wof:name":"Bk Stiefel & Assoc",
    "wof:placetype":"venue"
},
  "geometry": {"coordinates":[-88.083378,44.441919],"type":"Point"}
}