{
  "type": "Feature",
  "properties": {
    "iso:country":"US",
    "sg:address":"501 Merritt Ave",
    "sg:city":"Oshkosh",
    "sg:classifiers":[
        {
            "category":"Social Services",
            "type":"Services"
        },
        {
            "category":"Health Services",
            "subcategory":"Clinic",
            "type":"Services"
        },
        {
            "category":"Sports & Exercise",
            "subcategory":"Gym",
            "type":"Entertainment"
        },
        {
            "category":"Professional",
            "subcategory":"Lawyer & Legal Services",
            "type":"Services"
        },
        {
            "category":"Personal",
            "type":"Services"
        },
        {
            "category":"Health Services",
            "subcategory":"Health Practitioner",
            "type":"Services"
        }
    ],
    "sg:phone":"+1 920 231 2858",
    "sg:postcode":"54901",
    "sg:province":"WI",
    "sg:tags":[
        "mental",
        "family",
        "individual",
        "counseling",
        "information",
        "holistic",
        "yoga",
        "divorce",
        "assistance",
        "counselors-licensed",
        "treatment",
        "alcoholism",
        "biofeedback",
        "psychiatric",
        "abuse",
        "child",
        "homeopathic",
        "instruction",
        "drug",
        "therapist",
        "marriage",
        "addiction",
        "counselor"
    ],
    "sg:website":"http://www.oshcc.com",
    "wof:name":"Oshkosh Counseling Wellness Center",
    "wof:placetype":"venue"
},
  "geometry": {"coordinates":[-88.53138,44.019642],"type":"Point"}
}