{
  "type": "Feature",
  "properties": {
    "iso:country":"US",
    "sg:address":"5765 Twin Lane Rd",
    "sg:city":"Marshall",
    "sg:classifiers":[
        {
            "category":"Building & Trades",
            "subcategory":"Construction",
            "type":"Services"
        }
    ],
    "sg:phone":"+1 608 837 0784",
    "sg:postcode":"53559",
    "sg:province":"WI",
    "sg:tags":[
        "concrete",
        "contractor"
    ],
    "wof:name":"Fehrman Construction Inc",
    "wof:placetype":"venue"
},
  "geometry": {"coordinates":[-89.147542,43.165676],"type":"Point"}
}