{
  "type": "Feature",
  "properties": {
    "iso:country":"US",
    "sg:address":"6111 W North Ave",
    "sg:city":"Milwaukee",
    "sg:classifiers":[
        {
            "category":"Shopping",
            "subcategory":"Books",
            "type":"Retail Goods"
        }
    ],
    "sg:phone":"+1 414 774 6111",
    "sg:postcode":"53213",
    "sg:province":"WI",
    "sg:tags":[
        "dealer"
    ],
    "wof:name":"Gospel City",
    "wof:placetype":"venue"
},
  "geometry": {"coordinates":[-87.989717,43.060635],"type":"Point"}
}