{
  "type": "Feature",
  "properties": {
    "addr:full":"117 W Lafayette St Cuba City WI 53807",
    "addr:housenumber":"117",
    "addr:postcode":"53807",
    "addr:street":"W Lafayette St",
    "iso:country":"US",
    "sg:address":"117 W Lafayette St",
    "sg:city":"Cuba City",
    "sg:classifiers":[
        {
            "category":"Freight",
            "type":"Transportation"
        }
    ],
    "sg:phone":"+1 608 744 2280",
    "sg:postcode":"53807",
    "sg:province":"WI",
    "sg:tags":[
        "operator",
        "local",
        "trucking"
    ],
    "wof:name":"Stacey Trucking",
    "wof:placetype":"venue"
},
  "geometry": {"coordinates":[-90.431822,42.608486],"type":"Point"}
}