{
  "type": "Feature",
  "properties": {
    "iso:country":"US",
    "sg:address":"3000 Poberezny Rd",
    "sg:city":"Oshkosh",
    "sg:classifiers":[
        {
            "category":"Restaurant",
            "type":"Food & Drink"
        }
    ],
    "sg:phone":"+1 920 233 3760",
    "sg:postcode":"54902",
    "sg:province":"WI",
    "sg:tags":[
        "eating"
    ],
    "wof:name":"Aces Cafeteria",
    "wof:placetype":"venue"
},
  "geometry": {"coordinates":[-88.58019,43.983188],"type":"Point"}
}