{
  "type": "Feature",
  "properties": {
    "iso:country":"US",
    "sg:address":"1376 Aldoro Dr",
    "sg:city":"Waukesha",
    "sg:classifiers":[
        {
            "category":"Restaurant",
            "type":"Food & Drink"
        }
    ],
    "sg:phone":"+1 262 896 9061",
    "sg:postcode":"53188",
    "sg:province":"WI",
    "sg:tags":[
        "eating"
    ],
    "wof:name":"T Rex Pizza Company",
    "wof:placetype":"venue"
},
  "geometry": {"coordinates":[-88.250302,43.030942],"type":"Point"}
}