{
  "type": "Feature",
  "properties": {
    "addr:full":"600 Wilshire Blvd Stevens Point WI 54481",
    "addr:housenumber":"600",
    "addr:postcode":"54481",
    "addr:street":"Wilshire Blvd",
    "iso:country":"US",
    "sg:address":"600 Wilshire Blvd",
    "sg:city":"Stevens Point",
    "sg:classifiers":[
        {
            "category":"Organizations",
            "subcategory":"Religious Organization",
            "type":"Services"
        }
    ],
    "sg:phone":"+1 715 344 3557",
    "sg:postcode":"54481",
    "sg:province":"WI",
    "sg:tags":[
        "church"
    ],
    "sg:website":"www.stevenspointumc.org",
    "wof:name":"St Paul's United Methodist Chr",
    "wof:placetype":"venue"
},
  "geometry": {"coordinates":[-89.55000699999999,44.529665],"type":"Point"}
}