{
  "type": "Feature",
  "properties": {
    "addr:full":"15 Park Pl Appleton WI 54914",
    "addr:housenumber":"15",
    "addr:postcode":"54914",
    "addr:street":"Park Pl",
    "iso:country":"US",
    "sg:address":"15 Park Pl",
    "sg:city":"Appleton",
    "sg:classifiers":[
        {
            "category":"Professional",
            "subcategory":"Computer Services",
            "type":"Services"
        }
    ],
    "sg:phone":"+1 920 832 9240",
    "sg:postcode":"54914",
    "sg:province":"WI",
    "sg:tags":[
        "prepackaged",
        "software"
    ],
    "wof:name":"ISE",
    "wof:placetype":"venue"
},
  "geometry": {"coordinates":[-88.467997,44.256855],"type":"Point"}
}