{
  "type": "Feature",
  "properties": {
    "iso:country":"US",
    "sg:address":"1759 250th Ave",
    "sg:city":"Luck",
    "sg:classifiers":[
        {
            "category":"Farming",
            "subcategory":"Farm",
            "type":"Manufacturing & Wholesale Goods"
        }
    ],
    "sg:phone":"+1 715 472 8380",
    "sg:postcode":"54853",
    "sg:province":"WI",
    "sg:tags":[
        "crop",
        "general"
    ],
    "wof:name":"Paul Hansen",
    "wof:placetype":"venue"
},
  "geometry": {"coordinates":[-92.518844,45.570118],"type":"Point"}
}