{
  "type": "Feature",
  "properties": {
    "iso:country":"US",
    "sg:address":"1660 N Prospect Ave",
    "sg:city":"Milwaukee",
    "sg:classifiers":[
        {
            "category":"Professional",
            "subcategory":"Art Services",
            "type":"Services"
        }
    ],
    "sg:phone":"+1 414 277 1208",
    "sg:postcode":"53202",
    "sg:province":"WI",
    "sg:tags":[
        "commercial",
        "design"
    ],
    "wof:name":"Vey Al Artsts",
    "wof:placetype":"venue"
},
  "geometry": {"coordinates":[-87.89041,43.053021],"type":"Point"}
}