{
  "type": "Feature",
  "properties": {
    "addr:full":"5834 W Villard Ave Milwaukee WI 53218",
    "addr:housenumber":"5834",
    "addr:postcode":"53218",
    "addr:street":"W Villard Ave",
    "iso:country":"US",
    "sg:address":"5834 W Villard Ave",
    "sg:city":"Milwaukee",
    "sg:classifiers":[
        {
            "category":"Building & Trades",
            "subcategory":"Locksmith",
            "type":"Services"
        }
    ],
    "sg:phone":"+1 414 203 2611",
    "sg:postcode":"53218",
    "sg:province":"WI",
    "sg:tags":[
        "lock"
    ],
    "wof:name":"Aaa Locksmith Of Milwaukee",
    "wof:placetype":"venue"
},
  "geometry": {"coordinates":[-87.98514900000001,43.112009],"type":"Point"}
}