{
  "type": "Feature",
  "properties": {
    "iso:country":"US",
    "sg:address":"2505 Country Creek Ln",
    "sg:city":"Schofield",
    "sg:classifiers":[
        {
            "category":"Professional",
            "type":"Services"
        }
    ],
    "sg:phone":"+1 715 355 8062",
    "sg:postcode":"54476",
    "sg:province":"WI",
    "wof:name":"Charity Choppers",
    "wof:placetype":"venue"
},
  "geometry": {"coordinates":[-89.588258,44.871375],"type":"Point"}
}