{
  "type": "Feature",
  "properties": {
    "addr:full":"318 9th Ave W Ashland WI 54806",
    "addr:housenumber":"318",
    "addr:postcode":"54806",
    "addr:street":"9Th Ave W",
    "iso:country":"US",
    "sg:address":"318 9th Ave W",
    "sg:city":"Ashland",
    "sg:classifiers":[
        {
            "category":"Freight",
            "type":"Transportation"
        }
    ],
    "sg:phone":"+1 715 682 3044",
    "sg:postcode":"54806",
    "sg:province":"WI",
    "sg:tags":[
        "mover"
    ],
    "wof:name":"Clark Transfer Lines",
    "wof:placetype":"venue"
},
  "geometry": {"coordinates":[-90.89211899999999,46.58624],"type":"Point"}
}