{
  "type": "Feature",
  "properties": {
    "iso:country":"US",
    "sg:address":"5301 N Ironwood Rd",
    "sg:city":"Milwaukee",
    "sg:classifiers":[
        {
            "category":"Professional",
            "subcategory":"Employment Agencies",
            "type":"Services"
        }
    ],
    "sg:phone":"+1 414 961 0156",
    "sg:postcode":"53217",
    "sg:province":"WI",
    "wof:name":"A B Data",
    "wof:placetype":"venue"
},
  "geometry": {"coordinates":[-87.918378,43.11273],"type":"Point"}
}