{
  "type": "Feature",
  "properties": {
    "addr:full":"2309 W Drexel Ave Oak Creek WI 53154",
    "addr:housenumber":"2309",
    "addr:postcode":"53154",
    "addr:street":"W Drexel Ave",
    "iso:country":"US",
    "sg:address":"2309 W Drexel Ave",
    "sg:city":"Oak Creek",
    "sg:classifiers":[
        {
            "category":"Retail",
            "subcategory":"Repair Shop",
            "type":"Services"
        }
    ],
    "sg:phone":"+1 414 761 2255",
    "sg:postcode":"53154",
    "sg:province":"WI",
    "sg:tags":[
        "cleaning"
    ],
    "wof:name":"Midwest Mechanical Maintenance",
    "wof:placetype":"venue"
},
  "geometry": {"coordinates":[-87.946935,42.901701],"type":"Point"}
}