{
  "type": "Feature",
  "properties": {
    "iso:country":"US",
    "sg:address":"123 Crescent St",
    "sg:city":"Rhinelander",
    "sg:classifiers":[
        {
            "category":"Professional",
            "subcategory":"Business Services",
            "type":"Services"
        }
    ],
    "sg:phone":"+1 715 362 2500",
    "sg:postcode":"54501",
    "sg:province":"WI",
    "wof:name":"Jr Services",
    "wof:placetype":"venue"
},
  "geometry": {"coordinates":[-89.43035,45.640494],"type":"Point"}
}