{
  "type": "Feature",
  "properties": {
    "iso:country":"US",
    "sg:address":"1315 17th St",
    "sg:city":"Monroe",
    "sg:classifiers":[
        {
            "category":"Bars & Pubs",
            "type":"Food & Drink"
        }
    ],
    "sg:phone":"+1 608 325 4380",
    "sg:postcode":"53566",
    "sg:province":"WI",
    "sg:tags":[
        "drinking",
        "eating"
    ],
    "wof:name":"Murphy's Depot Inc",
    "wof:placetype":"venue"
},
  "geometry": {"coordinates":[-89.643123,42.595827],"type":"Point"}
}