{
  "type": "Feature",
  "properties": {
    "iso:country":"US",
    "sg:address":"1759 38th St",
    "sg:city":"Somerset",
    "sg:classifiers":[
        {
            "category":"Farming",
            "subcategory":"Dairy Farm",
            "type":"Manufacturing & Wholesale Goods"
        }
    ],
    "sg:phone":"+1 715 247 5569",
    "sg:postcode":"54025",
    "sg:province":"WI",
    "wof:name":"Hildebrant Farm",
    "wof:placetype":"venue"
},
  "geometry": {"coordinates":[-92.727097,45.119233],"type":"Point"}
}