{
  "type": "Feature",
  "properties": {
    "addr:full":"29 E Towne Mall Madison WI 53704",
    "addr:housenumber":"29",
    "addr:postcode":"53704",
    "addr:street":"E Towne Mall",
    "iso:country":"US",
    "sg:address":"29 E Towne Mall",
    "sg:city":"Madison",
    "sg:classifiers":[
        {
            "category":"Shopping",
            "subcategory":"Shoes",
            "type":"Retail Goods"
        }
    ],
    "sg:phone":"+1 608 240 0212",
    "sg:postcode":"53704",
    "sg:province":"WI",
    "sg:tags":[
        "athletic",
        "footwear",
        "leisure"
    ],
    "sg:website":"www.finishline.com",
    "wof:name":"Finish Line",
    "wof:placetype":"venue"
},
  "geometry": {"coordinates":[-89.30428499999999,43.127965],"type":"Point"}
}