{
  "type": "Feature",
  "properties": {
    "iso:country":"US",
    "sg:address":"8893 Co Hwy A",
    "sg:city":"Long Lake",
    "sg:classifiers":[
        {
            "category":"Professional",
            "subcategory":"Accounting & Tax Preparation",
            "type":"Services"
        }
    ],
    "sg:phone":"+1 715 545 3084",
    "sg:postcode":"54542",
    "sg:province":"WI",
    "sg:tags":[
        "bookkeeping",
        "general"
    ],
    "wof:name":"Office Trax",
    "wof:placetype":"venue"
},
  "geometry": {"coordinates":[-88.880915,46.019439],"type":"Point"}
}