{
  "type": "Feature",
  "properties": {
    "addr:full":"3215 Dans Dr Stevens Point WI 54481",
    "addr:housenumber":"3215",
    "addr:postcode":"54481",
    "addr:street":"Dans Dr",
    "iso:country":"US",
    "sg:address":"3215 Dans Dr",
    "sg:city":"Stevens Point",
    "sg:classifiers":[
        {
            "category":"Manufacturing",
            "subcategory":"Tools & Machinery",
            "type":"Manufacturing & Wholesale Goods"
        }
    ],
    "sg:phone":"+1 715 341 8020",
    "sg:postcode":"54481",
    "sg:province":"WI",
    "sg:tags":[
        "control",
        "system",
        "temp"
    ],
    "wof:name":"C & D Control",
    "wof:placetype":"venue"
},
  "geometry": {"coordinates":[-89.551591,44.504155],"type":"Point"}
}