{
  "type": "Feature",
  "properties": {
    "iso:country":"US",
    "sg:address":"8800 US Hwy 61",
    "sg:city":"Lancaster",
    "sg:classifiers":[
        {
            "category":"Government",
            "subcategory":"Office",
            "type":"Public Place"
        }
    ],
    "sg:phone":"+1 608 723 2113",
    "sg:postcode":"53813",
    "sg:province":"WI",
    "sg:website":"www.omanor.com",
    "wof:name":"Grant County Orchard Manor",
    "wof:placetype":"venue"
},
  "geometry": {"coordinates":[-90.68705,42.824059],"type":"Point"}
}