{
  "type": "Feature",
  "properties": {
    "iso:country":"US",
    "sg:address":"7980 State Hwy 101",
    "sg:city":"Armstrong Creek",
    "sg:classifiers":[
        {
            "category":"Building & Trades",
            "subcategory":"Construction",
            "type":"Services"
        }
    ],
    "sg:phone":"+1 715 336 2567",
    "sg:postcode":"54103",
    "sg:province":"WI",
    "sg:tags":[
        "house"
    ],
    "wof:name":"Neumanns Construction Inc",
    "wof:placetype":"venue"
},
  "geometry": {"coordinates":[-88.446591,45.658343],"type":"Point"}
}