{
  "type": "Feature",
  "properties": {
    "iso:country":"US",
    "sg:address":"1026 Aralia Rd",
    "sg:city":"Genoa City",
    "sg:classifiers":[
        {
            "category":"Building & Trades",
            "subcategory":"Cleaning & Sanitation",
            "type":"Services"
        }
    ],
    "sg:phone":"+1 262 279 1162",
    "sg:postcode":"53128",
    "sg:province":"WI",
    "sg:tags":[
        "maintenance"
    ],
    "wof:name":"Garcia Cleaning Service",
    "wof:placetype":"venue"
},
  "geometry": {"coordinates":[-88.35006799999999,42.550107],"type":"Point"}
}