{
  "type": "Feature",
  "properties": {
    "iso:country":"US",
    "sg:address":"8237 State Rd 108",
    "sg:city":"Mindoro",
    "sg:classifiers":[
        {
            "category":"Building & Trades",
            "subcategory":"Construction",
            "type":"Services"
        }
    ],
    "sg:phone":"+1 608 386 6390",
    "sg:postcode":"54644",
    "sg:province":"WI",
    "sg:tags":[
        "concrete",
        "contractor"
    ],
    "wof:name":"Act Alternative Concrete Techs",
    "wof:placetype":"venue"
},
  "geometry": {"coordinates":[-91.084901,44.044151],"type":"Point"}
}