{
  "type": "Feature",
  "properties": {
    "addr:full":"9638 W Flagg Ave Milwaukee WI 53225",
    "addr:housenumber":"9638",
    "addr:postcode":"53225",
    "addr:street":"W Flagg Ave",
    "iso:country":"US",
    "sg:address":"9638 W Flagg Ave",
    "sg:city":"Milwaukee",
    "sg:classifiers":[
        {
            "category":"Manufacturing",
            "subcategory":"Glass & Minerals",
            "type":"Manufacturing & Wholesale Goods"
        }
    ],
    "sg:phone":"+1 414 461 0065",
    "sg:postcode":"53225",
    "sg:province":"WI",
    "sg:tags":[
        "whole",
        "sculpture",
        "ice"
    ],
    "wof:name":"Millennium Ice Sculpting",
    "wof:placetype":"venue"
},
  "geometry": {"coordinates":[-88.032793,43.12433],"type":"Point"}
}