{
  "type": "Feature",
  "properties": {
    "iso:country":"US",
    "sg:address":"6373 Bluff Rd",
    "sg:city":"Whitewater",
    "sg:classifiers":[
        {
            "category":"Building & Trades",
            "subcategory":"Construction",
            "type":"Services"
        }
    ],
    "sg:phone":"+1 262 495 8639",
    "sg:postcode":"53190",
    "sg:province":"WI",
    "sg:tags":[
        "house"
    ],
    "wof:name":"Vohs Construction LLC",
    "wof:placetype":"venue"
},
  "geometry": {"coordinates":[-88.617936,42.835469],"type":"Point"}
}