{
  "type": "Feature",
  "properties": {
    "iso:country":"US",
    "sg:address":"139 3rd St",
    "sg:city":"Baraboo",
    "sg:classifiers":[
        {
            "category":"Personal",
            "subcategory":"Beauty Salon",
            "type":"Services"
        }
    ],
    "sg:phone":"+1 608 356 3444",
    "sg:postcode":"53913",
    "sg:province":"WI",
    "sg:tags":[
        "shop"
    ],
    "wof:name":"Impressions Hair Designers",
    "wof:placetype":"venue"
},
  "geometry": {"coordinates":[-89.741832,43.469984],"type":"Point"}
}