{
  "type": "Feature",
  "properties": {
    "iso:country":"US",
    "sg:address":"1313 Milwaukee Ave",
    "sg:city":"South Milwaukee",
    "sg:classifiers":[
        {
            "category":"Health Services",
            "subcategory":"Nursing And Care Facility",
            "type":"Services"
        },
        {
            "category":"Social Services",
            "subcategory":"Adult Care",
            "type":"Services"
        }
    ],
    "sg:phone":"+1 414 762 8026",
    "sg:postcode":"53172",
    "sg:province":"WI",
    "sg:tags":[
        "residential",
        "skilled",
        "home"
    ],
    "wof:name":"St Mary's Manor",
    "wof:placetype":"venue"
},
  "geometry": {"coordinates":[-87.86904800000001,42.910797],"type":"Point"}
}