{
  "type": "Feature",
  "properties": {
    "iso:country":"US",
    "sg:address":"147 Lake Ave E",
    "sg:city":"Almena",
    "sg:classifiers":[
        {
            "category":"Professional",
            "subcategory":"Management & Consulting",
            "type":"Services"
        }
    ],
    "sg:phone":"+1 715 357 6282",
    "sg:postcode":"54848",
    "sg:province":"WI",
    "sg:tags":[
        "business"
    ],
    "wof:name":"Western Wisconsin Dev Corp",
    "wof:placetype":"venue"
},
  "geometry": {"coordinates":[-91.10083899999999,45.465189],"type":"Point"}
}