{
  "type": "Feature",
  "properties": {
    "addr:full":"1017 Wisconsin St Lake Geneva WI 53147",
    "addr:housenumber":"1017",
    "addr:postcode":"53147",
    "addr:street":"Wisconsin St",
    "iso:country":"US",
    "sg:address":"1017 Wisconsin St",
    "sg:city":"Lake Geneva",
    "sg:classifiers":[
        {
            "category":"Real Estate",
            "subcategory":"Real Estate Agent",
            "type":"Services"
        }
    ],
    "sg:phone":"+1 262 248 6557",
    "sg:postcode":"53147",
    "sg:province":"WI",
    "sg:tags":[
        "residential",
        "commercial",
        "sales"
    ],
    "wof:name":"Janie G Larson Realty",
    "wof:placetype":"venue"
},
  "geometry": {"coordinates":[-88.440022,42.594339],"type":"Point"}
}