{
  "type": "Feature",
  "properties": {
    "addr:full":"4070 State Hwy 91 Oshkosh WI 54904",
    "addr:housenumber":"4070",
    "addr:postcode":"54904",
    "addr:street":"State Hwy 91",
    "iso:country":"US",
    "sg:address":"4070 State Hwy 91",
    "sg:city":"Oshkosh",
    "sg:classifiers":[
        {
            "category":"Manufacturing",
            "subcategory":"Rubber & Plastics",
            "type":"Manufacturing & Wholesale Goods"
        }
    ],
    "sg:phone":"+1 920 233 7070",
    "sg:postcode":"54904",
    "sg:province":"WI",
    "sg:tags":[
        "belting",
        "supply"
    ],
    "sg:website":"www.fnsheppard.com",
    "wof:name":"F N Sheppard & Co",
    "wof:placetype":"venue"
},
  "geometry": {"coordinates":[-88.60023200000001,43.982952],"type":"Point"}
}