{
  "type": "Feature",
  "properties": {
    "iso:country":"US",
    "sg:address":"3217 Westfield Ridge",
    "sg:city":"Neenah",
    "sg:classifiers":[
        {
            "category":"Real Estate",
            "subcategory":"Real Estate Operator",
            "type":"Services"
        }
    ],
    "sg:phone":"+1 920 727 9794",
    "sg:postcode":"54956",
    "sg:province":"WI",
    "sg:tags":[
        "building",
        "nonresidential"
    ],
    "wof:name":"Livengood Midway Properties LL",
    "wof:placetype":"venue"
},
  "geometry": {"coordinates":[-88.55139200000001,44.191648],"type":"Point"}
}