{
  "type": "Feature",
  "properties": {
    "iso:country":"US",
    "sg:address":"1170 22nd Ave",
    "sg:city":"Kenosha",
    "sg:classifiers":[
        {
            "category":"Restaurant",
            "type":"Food & Drink"
        }
    ],
    "sg:phone":"+1 262 552 8241",
    "sg:postcode":"53140",
    "sg:province":"WI",
    "wof:name":"Briese's Brew & Gyros N Hero's",
    "wof:placetype":"venue"
},
  "geometry": {"coordinates":[-87.83605,42.640871],"type":"Point"}
}