{
  "type": "Feature",
  "properties": {
    "iso:country":"US",
    "sg:address":"100 S Washington St",
    "sg:city":"Elkhorn",
    "sg:classifiers":[
        {
            "category":"Health Services",
            "subcategory":"Doctor",
            "type":"Services"
        }
    ],
    "sg:phone":"+1 262 723 8882",
    "sg:postcode":"53121",
    "sg:province":"WI",
    "sg:tags":[
        "physician",
        "surgeon"
    ],
    "wof:name":"Wisconsin Center For Clinical",
    "wof:placetype":"venue"
},
  "geometry": {"coordinates":[-88.54226,42.670313],"type":"Point"}
}