{
  "type": "Feature",
  "properties": {
    "iso:country":"US",
    "sg:address":"2325 Parklawn Dr",
    "sg:city":"Waukesha",
    "sg:classifiers":[
        {
            "category":"Real Estate",
            "subcategory":"Surveying",
            "type":"Services"
        }
    ],
    "sg:phone":"+1 262 798 9404",
    "sg:postcode":"53186",
    "sg:province":"WI",
    "sg:tags":[
        "wisc",
        "power",
        "for",
        "underground",
        "line",
        "locating"
    ],
    "wof:name":"Central Locating Service Ltd",
    "wof:placetype":"venue"
},
  "geometry": {"coordinates":[-88.181698,43.031914],"type":"Point"}
}