{
  "type": "Feature",
  "properties": {
    "iso:country":"US",
    "sg:address":"7700 Portland Ave",
    "sg:city":"Milwaukee",
    "sg:classifiers":[
        {
            "category":"Banks & Credit Unions",
            "subcategory":"Bank",
            "type":"Services"
        }
    ],
    "sg:phone":"+1 414 258 6063",
    "sg:postcode":"53213",
    "sg:province":"WI",
    "sg:tags":[
        "state"
    ],
    "wof:name":"M & I Marshall & Ilsley Bank",
    "wof:placetype":"venue"
},
  "geometry": {"coordinates":[-88.008745,43.041423],"type":"Point"}
}