{
  "type": "Feature",
  "properties": {
    "iso:country":"US",
    "sg:address":"1587 Co Hwy I",
    "sg:city":"Grafton",
    "sg:classifiers":[
        {
            "category":"Travel",
            "subcategory":"Hotels & Motels",
            "type":"Entertainment"
        }
    ],
    "sg:phone":"+1 262 377 6054",
    "sg:postcode":"53024",
    "sg:province":"WI",
    "sg:tags":[
        "breakfast",
        "accommodation",
        "bed"
    ],
    "wof:name":"Behrens Wedding Chapel",
    "wof:placetype":"venue"
},
  "geometry": {"coordinates":[-87.985043,43.330203],"type":"Point"}
}