{
  "type": "Feature",
  "properties": {
    "addr:full":"1219 Rome Rd Rubicon WI 53078",
    "addr:housenumber":"1219",
    "addr:postcode":"53078",
    "addr:street":"Rome Rd",
    "iso:country":"US",
    "sg:address":"1219 Rome Rd",
    "sg:city":"Rubicon",
    "sg:classifiers":[
        {
            "category":"Government",
            "subcategory":"Post Office",
            "type":"Public Place"
        }
    ],
    "sg:phone":"+1 262 673 3058",
    "sg:postcode":"53078",
    "sg:province":"WI",
    "wof:name":"US Post Office",
    "wof:placetype":"venue"
},
  "geometry": {"coordinates":[-88.458012,43.339932],"type":"Point"}
}