{
  "type": "Feature",
  "properties": {
    "iso:country":"US",
    "sg:address":"1976 Old Lancaster Rd",
    "sg:city":"Platteville",
    "sg:classifiers":[
        {
            "category":"Professional",
            "type":"Services"
        }
    ],
    "sg:phone":"+1 608 348 9979",
    "sg:postcode":"53818",
    "sg:province":"WI",
    "wof:name":"Lighthouse",
    "wof:placetype":"venue"
},
  "geometry": {"coordinates":[-90.518396,42.758572],"type":"Point"}
}