{
  "type": "Feature",
  "properties": {
    "iso:country":"US",
    "sg:address":"4701 N 76th St",
    "sg:city":"Milwaukee",
    "sg:classifiers":[
        {
            "category":"Organizations",
            "subcategory":"Religious Organization",
            "type":"Services"
        }
    ],
    "sg:phone":"+1 414 463 2499",
    "sg:postcode":"53218",
    "sg:province":"WI",
    "sg:tags":[
        "church"
    ],
    "wof:name":"Church Of The First Born Intl",
    "wof:placetype":"venue"
},
  "geometry": {"coordinates":[-88.00649,43.104997],"type":"Point"}
}