{
  "type": "Feature",
  "properties": {
    "iso:country":"US",
    "sg:address":"2387 Municipal Dr",
    "sg:city":"Greenville",
    "sg:classifiers":[
        {
            "category":"Education",
            "subcategory":"School",
            "type":"Public Place"
        }
    ],
    "sg:phone":"+1 920 757 5516",
    "sg:postcode":"54942",
    "sg:province":"WI",
    "wof:name":"St Mary Elementary School",
    "wof:placetype":"venue"
},
  "geometry": {"coordinates":[-88.53675699999999,44.326997],"type":"Point"}
}