{
  "type": "Feature",
  "properties": {
    "iso:country":"US",
    "sg:address":"3591 Anderson St",
    "sg:city":"Madison",
    "sg:classifiers":[
        {
            "category":"Professional",
            "subcategory":"Research",
            "type":"Services"
        }
    ],
    "sg:phone":"+1 608 310 9550",
    "sg:postcode":"53704",
    "sg:province":"WI",
    "sg:tags":[
        "bio",
        "technology"
    ],
    "wof:name":"Tfx Bio Science",
    "wof:placetype":"venue"
},
  "geometry": {"coordinates":[-89.325695,43.120964],"type":"Point"}
}