{
  "type": "Feature",
  "properties": {
    "iso:country":"US",
    "sg:address":"6731 Mariner Dr",
    "sg:city":"Racine",
    "sg:classifiers":[
        {
            "category":"Retail",
            "subcategory":"Animal Services",
            "type":"Services"
        }
    ],
    "sg:phone":"+1 262 886 9662",
    "sg:postcode":"53406",
    "sg:province":"WI",
    "sg:tags":[
        "breeder",
        "horse"
    ],
    "wof:name":"Signature Arabians LTD",
    "wof:placetype":"venue"
},
  "geometry": {"coordinates":[-87.86758500000001,42.723694],"type":"Point"}
}