{
  "type": "Feature",
  "properties": {
    "addr:full":"113 W Wisconsin St Weyauwega WI 54983",
    "addr:housenumber":"113",
    "addr:postcode":"54983",
    "addr:street":"W Wisconsin St",
    "iso:country":"US",
    "sg:address":"113 W Wisconsin St",
    "sg:city":"Weyauwega",
    "sg:classifiers":[
        {
            "category":"Food & Beverages",
            "subcategory":"Dairy",
            "type":"Retail Goods"
        }
    ],
    "sg:phone":"+1 920 867 2870",
    "sg:postcode":"54983",
    "sg:province":"WI",
    "sg:tags":[
        "cheese"
    ],
    "wof:name":"Weyauwega Star Dairy Inc",
    "wof:placetype":"venue"
},
  "geometry": {"coordinates":[-88.934326,44.322192],"type":"Point"}
}