{
  "type": "Feature",
  "properties": {
    "iso:country":"US",
    "sg:address":"7617 Mineral Point Rd",
    "sg:city":"Madison",
    "sg:classifiers":[
        {
            "category":"Building & Trades",
            "subcategory":"Construction",
            "type":"Services"
        }
    ],
    "sg:phone":"+1 608 827 6001",
    "sg:postcode":"53705",
    "sg:province":"WI",
    "sg:tags":[
        "new",
        "general",
        "commercial",
        "renovated",
        "contractor"
    ],
    "sg:website":"www.corporate-construction.com",
    "wof:name":"Corporate Construction Ltd",
    "wof:placetype":"venue"
},
  "geometry": {"coordinates":[-89.513946,43.060505],"type":"Point"}
}