{
  "type": "Feature",
  "properties": {
    "iso:country":"US",
    "sg:address":"6056 Schulz Spur Dr",
    "sg:city":"Irma",
    "sg:classifiers":[
        {
            "category":"Manufacturing",
            "subcategory":"Lumber",
            "type":"Manufacturing & Wholesale Goods"
        }
    ],
    "sg:phone":"+1 715 536 6655",
    "sg:postcode":"54442",
    "sg:province":"WI",
    "sg:tags":[
        "forestry"
    ],
    "wof:name":"Aldo Pezzi",
    "wof:placetype":"venue"
},
  "geometry": {"coordinates":[-89.730622,45.278979],"type":"Point"}
}