{
  "type": "Feature",
  "properties": {
    "addr:full":"5582 Church Rd Fond Du Lac WI 54935",
    "addr:housenumber":"5582",
    "addr:postcode":"54935",
    "addr:street":"Church Rd",
    "iso:country":"US",
    "sg:address":"5582 Church Rd",
    "sg:city":"Fond Du Lac",
    "sg:classifiers":[
        {
            "category":"Farming",
            "subcategory":"Farm",
            "type":"Manufacturing & Wholesale Goods"
        }
    ],
    "sg:phone":"+1 920 922 2682",
    "sg:postcode":"54935",
    "sg:province":"WI",
    "sg:tags":[
        "crop",
        "general"
    ],
    "wof:name":"Steve Kelley",
    "wof:placetype":"venue"
},
  "geometry": {"coordinates":[-88.43801999999999,43.674891],"type":"Point"}
}