{
  "type": "Feature",
  "properties": {
    "addr:full":"10548 George Ave Auburndale WI 54412",
    "addr:housenumber":"10548",
    "addr:postcode":"54412",
    "addr:street":"George Ave",
    "iso:country":"US",
    "sg:address":"10548 George Ave",
    "sg:city":"Auburndale",
    "sg:classifiers":[
        {
            "category":"Government",
            "subcategory":"Post Office",
            "type":"Public Place"
        }
    ],
    "sg:phone":"+1 715 652 2217",
    "sg:postcode":"54412",
    "sg:province":"WI",
    "wof:name":"US Post Office",
    "wof:placetype":"venue"
},
  "geometry": {"coordinates":[-90.007851,44.627071],"type":"Point"}
}