{
  "type": "Feature",
  "properties": {
    "addr:full":"12201 W North Ave Milwaukee WI 53226",
    "addr:housenumber":"12201",
    "addr:postcode":"53226",
    "addr:street":"W North Ave",
    "iso:country":"US",
    "sg:address":"12201 W North Ave",
    "sg:city":"Milwaukee",
    "sg:classifiers":[
        {
            "category":"Shopping",
            "subcategory":"Clothing, Apparel, & Fashions",
            "type":"Retail Goods"
        },
        {
            "category":"Personal",
            "type":"Services"
        }
    ],
    "sg:phone":"+1 414 302 0170",
    "sg:postcode":"53226",
    "sg:province":"WI",
    "sg:tags":[
        "tailoring",
        "alterations-clothing",
        "alteration",
        "tailor",
        "wedding"
    ],
    "wof:name":"Raisa's Tailoring & Alterations",
    "wof:placetype":"venue"
},
  "geometry": {"coordinates":[-88.064796,43.059891],"type":"Point"}
}