{
  "type": "Feature",
  "properties": {
    "addr:full":"366 S Lake Ave Phillips WI 54555",
    "addr:housenumber":"366",
    "addr:postcode":"54555",
    "addr:street":"S Lake Ave",
    "iso:country":"US",
    "sg:address":"366 S Lake Ave",
    "sg:city":"Phillips",
    "sg:classifiers":[
        {
            "category":"Banks & Credit Unions",
            "subcategory":"Investment Brokerage",
            "type":"Services"
        }
    ],
    "sg:phone":"+1 715 339 6563",
    "sg:postcode":"54555",
    "sg:province":"WI",
    "sg:tags":[
        "security"
    ],
    "wof:name":"Investment Centers Of America",
    "wof:placetype":"venue"
},
  "geometry": {"coordinates":[-90.393158,45.686728],"type":"Point"}
}