{
  "type": "Feature",
  "properties": {
    "iso:country":"US",
    "sg:address":"1119 N 8th St",
    "sg:city":"Sheboygan",
    "sg:classifiers":[
        {
            "category":"Shopping",
            "subcategory":"Music",
            "type":"Retail Goods"
        }
    ],
    "sg:phone":"+1 920 458 0951",
    "sg:postcode":"53081",
    "sg:province":"WI",
    "sg:tags":[
        "compact",
        "record",
        "disc",
        "tape"
    ],
    "wof:name":"Music Boxx",
    "wof:placetype":"venue"
},
  "geometry": {"coordinates":[-87.71286600000001,43.757235],"type":"Point"}
}