{
  "type": "Feature",
  "properties": {
    "addr:full":"2936 Fish Hatchery Rd Madison WI 53713",
    "addr:housenumber":"2936",
    "addr:postcode":"53713",
    "addr:street":"Fish Hatchery Rd",
    "iso:country":"US",
    "sg:address":"2936 Fish Hatchery Rd",
    "sg:city":"Madison",
    "sg:classifiers":[
        {
            "category":"Restaurant",
            "type":"Food & Drink"
        }
    ],
    "sg:menulink":"http://www.allmenus.com/wi/fitchburg/284310-pizza-extreme/menu/",
    "sg:phone":"+1 608 278 1800",
    "sg:postcode":"53713",
    "sg:province":"WI",
    "sg:tags":[
        "american",
        "pizza"
    ],
    "wof:name":"Pizza Extreme",
    "wof:placetype":"venue"
},
  "geometry": {"coordinates":[-89.41176400000001,43.027868],"type":"Point"}
}