{
  "type": "Feature",
  "properties": {
    "addr:full":"1204 Rockvale Rd Ixonia WI 53036",
    "addr:housenumber":"1204",
    "addr:postcode":"53036",
    "addr:street":"Rockvale Rd",
    "iso:country":"US",
    "sg:address":"1204 Rockvale Rd",
    "sg:city":"Ixonia",
    "sg:classifiers":[
        {
            "category":"Organizations",
            "subcategory":"Religious Organization",
            "type":"Services"
        }
    ],
    "sg:phone":"+1 262 567 8131",
    "sg:postcode":"53036",
    "sg:province":"WI",
    "sg:tags":[
        "church"
    ],
    "wof:name":"St John Ev Lutheran Church",
    "wof:placetype":"venue"
},
  "geometry": {"coordinates":[-88.591576,43.122923],"type":"Point"}
}