{
  "type": "Feature",
  "properties": {
    "iso:country":"US",
    "sg:address":"3602 Co Rd B",
    "sg:city":"Shell Lake",
    "sg:classifiers":[
        {
            "category":"Building & Trades",
            "subcategory":"Electrical",
            "type":"Services"
        }
    ],
    "sg:phone":"+1 715 468 7738",
    "sg:postcode":"54871",
    "sg:province":"WI",
    "sg:tags":[
        "electrical",
        "contractor"
    ],
    "wof:name":"Jerry Sexton Electric",
    "wof:placetype":"venue"
},
  "geometry": {"coordinates":[-92.15908,45.754491],"type":"Point"}
}