{
  "type": "Feature",
  "properties": {
    "addr:full":"7064 Labansky Rd Reedsburg WI 53959",
    "addr:housenumber":"7064",
    "addr:postcode":"53959",
    "addr:street":"Labansky Rd",
    "iso:country":"US",
    "sg:address":"7064 Labansky Rd",
    "sg:city":"Reedsburg",
    "sg:classifiers":[
        {
            "category":"Professional",
            "subcategory":"Accounting & Tax Preparation",
            "type":"Services"
        }
    ],
    "sg:phone":"+1 608 524 3258",
    "sg:postcode":"53959",
    "sg:province":"WI",
    "wof:name":"Schroeder Accounting",
    "wof:placetype":"venue"
},
  "geometry": {"coordinates":[-89.966117,43.529688],"type":"Point"}
}