{
  "type": "Feature",
  "properties": {
    "iso:country":"US",
    "sg:address":"8672 Brunswick Rd",
    "sg:city":"Minocqua",
    "sg:classifiers":[
        {
            "category":"Professional",
            "subcategory":"Art Services",
            "type":"Services"
        }
    ],
    "sg:phone":"+1 715 356 3894",
    "sg:postcode":"54548",
    "sg:province":"WI",
    "sg:tags":[
        "commercial",
        "design",
        "business"
    ],
    "wof:name":"Dimensional Graphics",
    "wof:placetype":"venue"
},
  "geometry": {"coordinates":[-89.674953,45.882433],"type":"Point"}
}