{
  "type": "Feature",
  "properties": {
    "iso:country":"US",
    "sg:address":"30 Trowbridge Dr",
    "sg:city":"Fond Du Lac",
    "sg:classifiers":[
        {
            "category":"Home & Garden",
            "subcategory":"Building Materials",
            "type":"Retail Goods"
        }
    ],
    "sg:phone":"+1 920 923 2800",
    "sg:postcode":"54937",
    "sg:province":"WI",
    "sg:tags":[
        "stone"
    ],
    "wof:name":"Natural Stone Veneer Inc",
    "wof:placetype":"venue"
},
  "geometry": {"coordinates":[-88.471875,43.751747],"type":"Point"}
}