{
  "type": "Feature",
  "properties": {
    "iso:country":"US",
    "sg:address":"3138 US Hwy 51",
    "sg:city":"Janesville",
    "sg:classifiers":[
        {
            "category":"Shopping",
            "type":"Retail Goods"
        }
    ],
    "sg:phone":"+1 608 743 1907",
    "sg:postcode":"53546",
    "sg:province":"WI",
    "sg:tags":[
        "pet",
        "shop",
        "merchandise"
    ],
    "wof:name":"Kincaids Kritters",
    "wof:placetype":"venue"
},
  "geometry": {"coordinates":[-89.031212,42.634443],"type":"Point"}
}