{
  "type": "Feature",
  "properties": {
    "iso:country":"US",
    "sg:address":"1118 17th Ave",
    "sg:city":"Monroe",
    "sg:classifiers":[
        {
            "category":"Insurance",
            "subcategory":"Insurance Agent",
            "type":"Services"
        }
    ],
    "sg:phone":"+1 608 328 4235",
    "sg:postcode":"53566",
    "sg:province":"WI",
    "wof:name":"Massachusetts Mutual-Blue Chip",
    "wof:placetype":"venue"
},
  "geometry": {"coordinates":[-89.638492,42.600961],"type":"Point"}
}