{
  "type": "Feature",
  "properties": {
    "addr:full":"111 E Reindl Way Milwaukee WI 53212",
    "addr:housenumber":"111",
    "addr:postcode":"53212",
    "addr:street":"E Reindl Way",
    "iso:country":"US",
    "sg:address":"111 E Reindl Way",
    "sg:city":"Milwaukee",
    "sg:classifiers":[
        {
            "category":"Manufacturing",
            "subcategory":"Printing",
            "type":"Manufacturing & Wholesale Goods"
        }
    ],
    "sg:phone":"+1 414 906 1111",
    "sg:postcode":"53212",
    "sg:province":"WI",
    "sg:tags":[
        "book",
        "binding"
    ],
    "sg:website":"www.reindlbindery.com",
    "wof:name":"Reindl Bindery Co Inc",
    "wof:placetype":"venue"
},
  "geometry": {"coordinates":[-87.90872899999999,43.092739],"type":"Point"}
}