{
  "type": "Feature",
  "properties": {
    "iso:country":"US",
    "sg:address":"4933 Foxfire Trl",
    "sg:city":"Middleton",
    "sg:classifiers":[
        {
            "category":"Professional",
            "subcategory":"Art Services",
            "type":"Services"
        },
        {
            "category":"Professional",
            "subcategory":"Advertising",
            "type":"Services"
        }
    ],
    "sg:phone":"+1 608 831 7447",
    "sg:postcode":"53562",
    "sg:province":"WI",
    "sg:tags":[
        "commercial",
        "counselor",
        "design"
    ],
    "sg:website":"www.thilldesign.com",
    "wof:name":"Thill Phill Design Inc",
    "wof:placetype":"venue"
},
  "geometry": {"coordinates":[-89.508501,43.124522],"type":"Point"}
}