{
  "type": "Feature",
  "properties": {
    "iso:country":"US",
    "sg:address":"208 E Central Ave",
    "sg:city":"Oconto Falls",
    "sg:classifiers":[
        {
            "category":"Retail",
            "subcategory":"Portrait Studio",
            "type":"Services"
        }
    ],
    "sg:phone":"+1 920 846 3393",
    "sg:postcode":"54154",
    "sg:province":"WI",
    "sg:tags":[
        "photo"
    ],
    "sg:website":"www.mortellstudio.com",
    "wof:name":"Mortell Studio",
    "wof:placetype":"venue"
},
  "geometry": {"coordinates":[-88.140585,44.874914],"type":"Point"}
}