{
  "type": "Feature",
  "properties": {
    "addr:full":"223 Seagull Dr Mosinee WI 54455",
    "addr:housenumber":"223",
    "addr:postcode":"54455",
    "addr:street":"Seagull Dr",
    "iso:country":"US",
    "sg:address":"223 Seagull Dr",
    "sg:city":"Mosinee",
    "sg:classifiers":[
        {
            "category":"Banks & Credit Unions",
            "subcategory":"Investment Brokerage",
            "type":"Services"
        }
    ],
    "sg:phone":"+1 715 693 8700",
    "sg:postcode":"54455",
    "sg:province":"WI",
    "sg:tags":[
        "stock",
        "bond"
    ],
    "wof:name":"AFS Brokerage",
    "wof:placetype":"venue"
},
  "geometry": {"coordinates":[-89.699934,44.717667],"type":"Point"}
}