{
  "type": "Feature",
  "properties": {
    "iso:country":"US",
    "sg:address":"343 E Highland Dr",
    "sg:city":"Oconto Falls",
    "sg:classifiers":[
        {
            "category":"Restaurant",
            "type":"Food & Drink"
        }
    ],
    "sg:menulink":"http://www.allmenus.com/wi/oconto-falls/218338-burger-king/menu/",
    "sg:phone":"+1 920 846 0770",
    "sg:postcode":"54154",
    "sg:province":"WI",
    "sg:tags":[
        "american"
    ],
    "wof:name":"Burger King",
    "wof:placetype":"venue"
},
  "geometry": {"coordinates":[-88.144544,44.882759],"type":"Point"}
}