{
  "type": "Feature",
  "properties": {
    "addr:full":"414 W Wisconsin Ave Waukesha WI 53186",
    "addr:housenumber":"414",
    "addr:postcode":"53186",
    "addr:street":"W Wisconsin Ave",
    "iso:country":"US",
    "sg:address":"414 W Wisconsin Ave",
    "sg:city":"Waukesha",
    "sg:classifiers":[
        {
            "category":"Personal",
            "subcategory":"Beauty Salon",
            "type":"Services"
        }
    ],
    "sg:phone":"+1 262 896 0799",
    "sg:postcode":"53186",
    "sg:province":"WI",
    "wof:name":"Hair Esteem",
    "wof:placetype":"venue"
},
  "geometry": {"coordinates":[-88.23626899999999,43.009758],"type":"Point"}
}