{
  "type": "Feature",
  "properties": {
    "iso:country":"US",
    "sg:address":"6923 Zirbel Rd",
    "sg:city":"New London",
    "sg:classifiers":[
        {
            "category":"Wholesale",
            "subcategory":"Computers",
            "type":"Manufacturing & Wholesale Goods"
        }
    ],
    "sg:phone":"+1 920 596 1514",
    "sg:postcode":"54961",
    "sg:province":"WI",
    "wof:name":"Zero One Graphics",
    "wof:placetype":"venue"
},
  "geometry": {"coordinates":[-88.880637,44.40756],"type":"Point"}
}