{
  "type": "Feature",
  "properties": {
    "iso:country":"US",
    "sg:address":"2017 14th Ave",
    "sg:city":"Monroe",
    "sg:classifiers":[
        {
            "category":"Insurance",
            "subcategory":"Insurance Agent",
            "type":"Services"
        }
    ],
    "sg:phone":"+1 608 325 1501",
    "sg:postcode":"53566",
    "sg:province":"WI",
    "sg:tags":[
        "agency"
    ],
    "wof:name":"Primerica",
    "wof:placetype":"venue"
},
  "geometry": {"coordinates":[-89.6417,42.592895],"type":"Point"}
}