{
  "type": "Feature",
  "properties": {
    "addr:full":"12731 State Hwy 42 Ellison Bay WI 54210",
    "addr:housenumber":"12731",
    "addr:postcode":"54210",
    "addr:street":"State Hwy 42",
    "iso:country":"US",
    "sg:address":"12731 State Hwy 42",
    "sg:city":"Ellison Bay",
    "sg:classifiers":[
        {
            "category":"Ferry",
            "type":"Transportation"
        }
    ],
    "sg:phone":"+1 920 854 2972",
    "sg:postcode":"54210",
    "sg:province":"WI",
    "sg:tags":[
        "excursion",
        "boat"
    ],
    "wof:name":"Voights Marine Service Ltd",
    "wof:placetype":"venue"
},
  "geometry": {"coordinates":[-87.02165599999999,45.288394],"type":"Point"}
}