{
  "type": "Feature",
  "properties": {
    "iso:country":"US",
    "sg:address":"8585 N Port Washington Rd",
    "sg:city":"Milwaukee",
    "sg:classifiers":[
        {
            "category":"Personal",
            "subcategory":"Beauty Salon",
            "type":"Services"
        }
    ],
    "sg:phone":"+1 414 540 6685",
    "sg:postcode":"53217",
    "sg:province":"WI",
    "wof:name":"Ela's Esthetics",
    "wof:placetype":"venue"
},
  "geometry": {"coordinates":[-87.912487,43.172773],"type":"Point"}
}