{
  "type": "Feature",
  "properties": {
    "addr:full":"8340 W Bluemound Rd Wauwatosa WI 53213",
    "addr:housenumber":"8340",
    "addr:postcode":"53213",
    "addr:street":"W Bluemound Rd",
    "iso:country":"US",
    "sg:address":"8340 W Bluemound Rd",
    "sg:city":"Wauwatosa",
    "sg:classifiers":[
        {
            "category":"Food & Beverages",
            "subcategory":"Candy",
            "type":"Retail Goods"
        }
    ],
    "sg:phone":"+1 414 256 0800",
    "sg:postcode":"53213",
    "sg:province":"WI",
    "sg:tags":[
        "confectionery"
    ],
    "wof:name":"Candy Bouquet",
    "wof:placetype":"venue"
},
  "geometry": {"coordinates":[-88.016954,43.036079],"type":"Point"}
}