{
  "type": "Feature",
  "properties": {
    "iso:country":"US",
    "sg:address":"316 S Main St",
    "sg:city":"Janesville",
    "sg:classifiers":[
        {
            "category":"Communications",
            "subcategory":"Television Station",
            "type":"Services"
        }
    ],
    "sg:phone":"+1 608 758 6618",
    "sg:postcode":"53545",
    "sg:province":"WI",
    "sg:tags":[
        "broadcasting",
        "co"
    ],
    "wof:name":"JATV-12",
    "wof:placetype":"venue"
},
  "geometry": {"coordinates":[-89.01752,42.678378],"type":"Point"}
}