{
  "type": "Feature",
  "properties": {
    "iso:country":"US",
    "sg:address":"4336 Pralle Rd",
    "sg:city":"Onalaska",
    "sg:classifiers":[
        {
            "category":"Building & Trades",
            "subcategory":"Construction",
            "type":"Services"
        }
    ],
    "sg:phone":"+1 608 783 7516",
    "sg:postcode":"54650",
    "sg:province":"WI",
    "sg:tags":[
        "carpentry",
        "carpenter",
        "contractor"
    ],
    "wof:name":"Carlson Construction Co",
    "wof:placetype":"venue"
},
  "geometry": {"coordinates":[-91.202977,43.877198],"type":"Point"}
}