{
  "type": "Feature",
  "properties": {
    "iso:country":"US",
    "sg:address":"522 Springdale St",
    "sg:city":"Mount Horeb",
    "sg:classifiers":[
        {
            "category":"Retail",
            "subcategory":"Portrait Studio",
            "type":"Services"
        }
    ],
    "sg:phone":"+1 608 437 8988",
    "sg:postcode":"53572",
    "sg:province":"WI",
    "sg:tags":[
        "photo"
    ],
    "wof:name":"Flash Photography",
    "wof:placetype":"venue"
},
  "geometry": {"coordinates":[-89.73342100000001,43.008897],"type":"Point"}
}