{
  "type": "Feature",
  "properties": {
    "iso:country":"US",
    "sg:address":"3930 US Hwy 61 and 35",
    "sg:city":"Potosi",
    "sg:classifiers":[
        {
            "category":"Farming",
            "subcategory":"Farm",
            "type":"Manufacturing & Wholesale Goods"
        }
    ],
    "sg:phone":"+1 608 568 3361",
    "sg:postcode":"53820",
    "sg:province":"WI",
    "sg:tags":[
        "crop",
        "general"
    ],
    "wof:name":"Bode Kendle",
    "wof:placetype":"venue"
},
  "geometry": {"coordinates":[-90.613873,42.63651],"type":"Point"}
}