{
  "type": "Feature",
  "properties": {
    "addr:full":"5505 Pine Ave Oconto WI 54153",
    "addr:housenumber":"5505",
    "addr:postcode":"54153",
    "addr:street":"Pine Ave",
    "iso:country":"US",
    "sg:address":"5505 Pine Ave",
    "sg:city":"Oconto",
    "sg:classifiers":[
        {
            "category":"Food & Beverages",
            "subcategory":"Meat & Fish",
            "type":"Retail Goods"
        }
    ],
    "sg:phone":"+1 920 834 3138",
    "sg:postcode":"54153",
    "sg:province":"WI",
    "wof:name":"Painting & Fisheries",
    "wof:placetype":"venue"
},
  "geometry": {"coordinates":[-87.879912,44.876249],"type":"Point"}
}