{
  "type": "Feature",
  "properties": {
    "iso:country":"US",
    "sg:address":"1515 New Jersey Ave",
    "sg:city":"Sheboygan",
    "sg:classifiers":[
        {
            "category":"Sports & Exercise",
            "subcategory":"Bowling",
            "type":"Entertainment"
        },
        {
            "category":"Bars & Pubs",
            "type":"Food & Drink"
        }
    ],
    "sg:phone":"+1 920 458 5263",
    "sg:postcode":"53081",
    "sg:province":"WI",
    "sg:tags":[
        "drinking",
        "center"
    ],
    "wof:name":"Myers Westside Lanes",
    "wof:placetype":"venue"
},
  "geometry": {"coordinates":[-87.726111,43.746448],"type":"Point"}
}