{
  "type": "Feature",
  "properties": {
    "iso:country":"US",
    "sg:address":"906 Coulee Trl",
    "sg:city":"Hudson",
    "sg:classifiers":[
        {
            "category":"Building & Trades",
            "subcategory":"Construction",
            "type":"Services"
        }
    ],
    "sg:phone":"+1 715 425 6473",
    "sg:postcode":"54016",
    "sg:province":"WI",
    "sg:tags":[
        "general",
        "contractor"
    ],
    "wof:name":"Linehan Construction Co",
    "wof:placetype":"venue"
},
  "geometry": {"coordinates":[-92.61810199999999,44.927647],"type":"Point"}
}