{
  "type": "Feature",
  "properties": {
    "iso:country":"US",
    "sg:address":"900 Fond du Lac Ave",
    "sg:city":"Kewaskum",
    "sg:classifiers":[
        {
            "category":"Retail",
            "subcategory":"Auto Rental",
            "type":"Services"
        }
    ],
    "sg:phone":"+1 262 626 4528",
    "sg:postcode":"53040",
    "sg:province":"WI",
    "sg:tags":[
        "renting",
        "truck",
        "leasing"
    ],
    "wof:name":"U-Haul Co",
    "wof:placetype":"venue"
},
  "geometry": {"coordinates":[-88.221184,43.510674],"type":"Point"}
}