{
  "type": "Feature",
  "properties": {
    "iso:country":"US",
    "sg:address":"24906 81st St",
    "sg:city":"Salem",
    "sg:classifiers":[
        {
            "category":"Personal",
            "type":"Services"
        }
    ],
    "sg:phone":"+1 262 843 8049",
    "sg:postcode":"53168",
    "sg:province":"WI",
    "wof:name":"Handy Husband of Salem Inc",
    "wof:placetype":"venue"
},
  "geometry": {"coordinates":[-88.110811,42.559366],"type":"Point"}
}