{
  "type": "Feature",
  "properties": {
    "iso:country":"US",
    "sg:address":"12605 W Courtland",
    "sg:city":"Butler",
    "sg:classifiers":[
        {
            "category":"Social Services",
            "subcategory":"Adult Care",
            "type":"Services"
        }
    ],
    "sg:phone":"+1 262 373 0245",
    "sg:postcode":"53007",
    "sg:province":"WI",
    "sg:tags":[
        "home",
        "residential"
    ],
    "wof:name":"Community Living Arrangements",
    "wof:placetype":"venue"
},
  "geometry": {"coordinates":[-88.069505,43.102479],"type":"Point"}
}