{
  "type": "Feature",
  "properties": {
    "addr:full":"4772 610th St Menomonie WI 54751",
    "addr:housenumber":"4772",
    "addr:postcode":"54751",
    "addr:street":"610Th St",
    "iso:country":"US",
    "sg:address":"4772 610th St",
    "sg:city":"Menomonie",
    "sg:classifiers":[
        {
            "category":"Retail",
            "subcategory":"Auto Repair",
            "type":"Services"
        }
    ],
    "sg:phone":"+1 715 231 5388",
    "sg:postcode":"54751",
    "sg:province":"WI",
    "sg:tags":[
        "glass",
        "replacement"
    ],
    "wof:name":"Jet Auto Glass",
    "wof:placetype":"venue"
},
  "geometry": {"coordinates":[-91.85381,44.854768],"type":"Point"}
}