{
  "type": "Feature",
  "properties": {
    "iso:country":"US",
    "sg:address":"634 W Pierre Ln",
    "sg:city":"Port Washington",
    "sg:classifiers":[
        {
            "category":"Wholesale",
            "subcategory":"Medical Equipment & Supplies",
            "type":"Manufacturing & Wholesale Goods"
        }
    ],
    "sg:phone":"+1 262 268 1101",
    "sg:postcode":"53074",
    "sg:province":"WI",
    "sg:website":"www.phoenix-development.com",
    "wof:name":"Phoenix Development Inc",
    "wof:placetype":"venue"
},
  "geometry": {"coordinates":[-87.878948,43.39466],"type":"Point"}
}