{
  "type": "Feature",
  "properties": {
    "iso:country":"US",
    "sg:address":"4367 620th Ave",
    "sg:city":"Menomonie",
    "sg:classifiers":[
        {
            "category":"Farming",
            "subcategory":"Dairy Farm",
            "type":"Manufacturing & Wholesale Goods"
        }
    ],
    "sg:phone":"+1 715 235 5600",
    "sg:postcode":"54751",
    "sg:province":"WI",
    "wof:name":"Wilson Valley Farms",
    "wof:placetype":"venue"
},
  "geometry": {"coordinates":[-91.945035,44.90214],"type":"Point"}
}