{
  "type": "Feature",
  "properties": {
    "iso:country":"US",
    "sg:address":"954 3rd St SE",
    "sg:city":"Clear Lake",
    "sg:classifiers":[
        {
            "category":"Retail",
            "subcategory":"Repair Shop",
            "type":"Services"
        }
    ],
    "sg:phone":"+1 715 263 2119",
    "sg:postcode":"54005",
    "sg:province":"WI",
    "sg:tags":[
        "auto",
        "general"
    ],
    "wof:name":"Northland Charters",
    "wof:placetype":"venue"
},
  "geometry": {"coordinates":[-92.260229,45.241637],"type":"Point"}
}