{
  "type": "Feature",
  "properties": {
    "iso:country":"US",
    "sg:address":"800 E Taylor St",
    "sg:city":"Prairie Du Chien",
    "sg:classifiers":[
        {
            "category":"Insurance",
            "subcategory":"Insurance Agent",
            "type":"Services"
        }
    ],
    "sg:phone":"+1 608 326 0909",
    "sg:postcode":"53821",
    "sg:province":"WI",
    "wof:name":"Prairie Du Chien Memorial Hosp",
    "wof:placetype":"venue"
},
  "geometry": {"coordinates":[-91.136072,43.044067],"type":"Point"}
}