{
  "type": "Feature",
  "properties": {
    "iso:country":"US",
    "sg:address":"935 S 29th St",
    "sg:city":"Manitowoc",
    "sg:classifiers":[
        {
            "category":"Building & Trades",
            "subcategory":"Construction",
            "type":"Services"
        }
    ],
    "sg:phone":"+1 920 682 9663",
    "sg:postcode":"54220",
    "sg:province":"WI",
    "sg:tags":[
        "maker",
        "cabinet"
    ],
    "wof:name":"De Noyer's Woodworking",
    "wof:placetype":"venue"
},
  "geometry": {"coordinates":[-87.684203,44.089091],"type":"Point"}
}