{
  "type": "Feature",
  "properties": {
    "iso:country":"US",
    "sg:address":"1700 Strongs Ave",
    "sg:city":"Stevens Point",
    "sg:classifiers":[
        {
            "category":"Education",
            "subcategory":"Dance Studio",
            "type":"Public Place"
        }
    ],
    "sg:phone":"+1 715 341 8200",
    "sg:postcode":"54481",
    "sg:province":"WI",
    "wof:name":"Turning Point Dance Academy",
    "wof:placetype":"venue"
},
  "geometry": {"coordinates":[-89.579777,44.519211],"type":"Point"}
}