{
  "type": "Feature",
  "properties": {
    "addr:full":"901 S 12th St Watertown WI 53094",
    "addr:housenumber":"901",
    "addr:postcode":"53094",
    "addr:street":"S 12Th St",
    "iso:country":"US",
    "sg:address":"901 S 12th St",
    "sg:city":"Watertown",
    "sg:classifiers":[
        {
            "category":"Wholesale",
            "subcategory":"Electrical",
            "type":"Manufacturing & Wholesale Goods"
        }
    ],
    "sg:phone":"+1 920 261 4070",
    "sg:postcode":"53094",
    "sg:province":"WI",
    "sg:tags":[
        "equipment",
        "electric",
        "supply"
    ],
    "sg:website":"www.eaton.com",
    "wof:name":"Eaton Durant Controls",
    "wof:placetype":"venue"
},
  "geometry": {"coordinates":[-88.71368699999999,43.173794],"type":"Point"}
}