{
  "type": "Feature",
  "properties": {
    "addr:full":"4923 Tanglewood Ave Racine WI 53402",
    "addr:housenumber":"4923",
    "addr:postcode":"53402",
    "addr:street":"Tanglewood Ave",
    "iso:country":"US",
    "sg:address":"4923 Tanglewood Ave",
    "sg:city":"Racine",
    "sg:classifiers":[
        {
            "category":"Personal",
            "subcategory":"Beauty Salon",
            "type":"Services"
        }
    ],
    "sg:phone":"+1 262 752 1257",
    "sg:postcode":"53402",
    "sg:province":"WI",
    "wof:name":"Reflective Designs",
    "wof:placetype":"venue"
},
  "geometry": {"coordinates":[-87.797749,42.783247],"type":"Point"}
}