{
  "type": "Feature",
  "properties": {
    "iso:country":"US",
    "sg:address":"5513 Femrite Dr",
    "sg:city":"Madison",
    "sg:classifiers":[
        {
            "category":"Local Transit",
            "type":"Transportation"
        }
    ],
    "sg:phone":"+1 608 222 9883",
    "sg:postcode":"53718",
    "sg:province":"WI",
    "sg:tags":[
        "bus",
        "line"
    ],
    "wof:name":"Badger Bus Lines",
    "wof:placetype":"venue"
},
  "geometry": {"coordinates":[-89.282904,43.051656],"type":"Point"}
}