{
  "type": "Feature",
  "properties": {
    "iso:country":"US",
    "sg:address":"1419 Milwaukee St",
    "sg:city":"Delafield",
    "sg:classifiers":[
        {
            "category":"Building & Trades",
            "subcategory":"Plumbing",
            "type":"Services"
        }
    ],
    "sg:phone":"+1 262 646 2828",
    "sg:postcode":"53018",
    "sg:province":"WI",
    "sg:tags":[
        "product",
        "management",
        "energy",
        "system"
    ],
    "wof:name":"T Rex Energy Corp",
    "wof:placetype":"venue"
},
  "geometry": {"coordinates":[-88.38915900000001,43.061014],"type":"Point"}
}