{
  "type": "Feature",
  "properties": {
    "iso:country":"US",
    "sg:address":"85 S Court St",
    "sg:city":"Platteville",
    "sg:classifiers":[
        {
            "category":"Government",
            "subcategory":"Post Office",
            "type":"Public Place"
        }
    ],
    "sg:phone":"+1 608 348 2181",
    "sg:postcode":"53818",
    "sg:province":"WI",
    "sg:tags":[
        "postal",
        "us"
    ],
    "sg:website":"www.usps.com",
    "wof:name":"US Post Office",
    "wof:placetype":"venue"
},
  "geometry": {"coordinates":[-90.479609,42.733403],"type":"Point"}
}