{
  "type": "Feature",
  "properties": {
    "iso:country":"US",
    "sg:address":"915 Blake St",
    "sg:city":"Blanchardville",
    "sg:classifiers":[
        {
            "category":"Autos & Motor Vehicles",
            "subcategory":"Fuel & Gas Station",
            "type":"Retail Goods"
        }
    ],
    "sg:phone":"+1 608 523 1355",
    "sg:postcode":"53516",
    "sg:province":"WI",
    "sg:tags":[
        "oil"
    ],
    "wof:name":"Gas Pros",
    "wof:placetype":"venue"
},
  "geometry": {"coordinates":[-89.858137,42.804794],"type":"Point"}
}