{
  "type": "Feature",
  "properties": {
    "addr:full":"1530 S Commercial St Neenah WI 54956",
    "addr:housenumber":"1530",
    "addr:postcode":"54956",
    "addr:street":"S Commercial St",
    "iso:country":"US",
    "sg:address":"1530 S Commercial St",
    "sg:city":"Neenah",
    "sg:classifiers":[
        {
            "category":"Banks & Credit Unions",
            "subcategory":"Bank",
            "type":"Services"
        }
    ],
    "sg:phone":"+1 920 727 3500",
    "sg:postcode":"54956",
    "sg:province":"WI",
    "wof:name":"Associated Bank",
    "wof:placetype":"venue"
},
  "geometry": {"coordinates":[-88.463489,44.152827],"type":"Point"}
}