{
  "type": "Feature",
  "properties": {
    "iso:country":"US",
    "sg:address":"860 State Hwy 29",
    "sg:city":"Luxemburg",
    "sg:classifiers":[
        {
            "category":"Organizations",
            "subcategory":"Religious Organization",
            "type":"Services"
        }
    ],
    "sg:phone":"+1 920 845 2565",
    "sg:postcode":"54217",
    "sg:province":"WI",
    "sg:tags":[
        "clergy"
    ],
    "wof:name":"C T Lacombe",
    "wof:placetype":"venue"
},
  "geometry": {"coordinates":[-87.727046,44.443453],"type":"Point"}
}