{
  "type": "Feature",
  "properties": {
    "iso:country":"US",
    "sg:address":"14997 50th Ave",
    "sg:city":"Chippewa Falls",
    "sg:classifiers":[
        {
            "category":"Home & Garden",
            "subcategory":"Garden Supply",
            "type":"Retail Goods"
        },
        {
            "category":"Building & Trades",
            "subcategory":"Landscaping Services",
            "type":"Services"
        }
    ],
    "sg:phone":"+1 715 723 5131",
    "sg:postcode":"54729",
    "sg:province":"WI",
    "sg:tags":[
        "tree",
        "christmas"
    ],
    "wof:name":"Traditional Tree Farms",
    "wof:placetype":"venue"
},
  "geometry": {"coordinates":[-91.36932,44.915328],"type":"Point"}
}