{
  "type": "Feature",
  "properties": {
    "iso:country":"US",
    "sg:address":"6040 W Lisbon Ave",
    "sg:city":"Milwaukee",
    "sg:classifiers":[
        {
            "category":"Banks & Credit Unions",
            "subcategory":"Bank",
            "type":"Services"
        }
    ],
    "sg:phone":"+1 414 431 4504",
    "sg:postcode":"53210",
    "sg:province":"WI",
    "sg:tags":[
        "loan",
        "real estate"
    ],
    "wof:name":"A Fair Mortgage",
    "wof:placetype":"venue"
},
  "geometry": {"coordinates":[-87.988557,43.068703],"type":"Point"}
}