{
  "type": "Feature",
  "properties": {
    "iso:country":"US",
    "sg:address":"232 W Oak St",
    "sg:city":"Lancaster",
    "sg:classifiers":[
        {
            "category":"Wholesale",
            "subcategory":"Jewelry",
            "type":"Manufacturing & Wholesale Goods"
        }
    ],
    "sg:phone":"+1 608 249 1950",
    "sg:postcode":"53813",
    "sg:province":"WI",
    "sg:tags":[
        "stone"
    ],
    "wof:name":"Americoin & Jewelry",
    "wof:placetype":"venue"
},
  "geometry": {"coordinates":[-90.71220099999999,42.845064],"type":"Point"}
}