{
  "type": "Feature",
  "properties": {
    "iso:country":"US",
    "sg:address":"729 Juniper Ct",
    "sg:city":"West Bend",
    "sg:classifiers":[
        {
            "category":"Education",
            "subcategory":"Special Training",
            "type":"Public Place"
        }
    ],
    "sg:phone":"+1 262 334 9679",
    "sg:postcode":"53095",
    "sg:province":"WI",
    "wof:name":"Frey Music Studio",
    "wof:placetype":"venue"
},
  "geometry": {"coordinates":[-88.16492,43.414302],"type":"Point"}
}