{
  "type": "Feature",
  "properties": {
    "iso:country":"US",
    "sg:address":"1426 N Randall Ave",
    "sg:city":"Janesville",
    "sg:classifiers":[
        {
            "category":"Real Estate",
            "subcategory":"Real Estate Operator",
            "type":"Services"
        }
    ],
    "sg:phone":"+1 608 755 4691",
    "sg:postcode":"53545",
    "sg:province":"WI",
    "sg:tags":[
        "property",
        "lessor"
    ],
    "wof:name":"Earl Kersten",
    "wof:placetype":"venue"
},
  "geometry": {"coordinates":[-89.003167,42.702538],"type":"Point"}
}