{
  "type": "Feature",
  "properties": {
    "iso:country":"US",
    "sg:address":"9430 Muskrat Rd",
    "sg:city":"Portage",
    "sg:classifiers":[
        {
            "category":"Building & Trades",
            "subcategory":"Construction",
            "type":"Services"
        }
    ],
    "sg:phone":"+1 608 742 6174",
    "sg:postcode":"53901",
    "sg:province":"WI",
    "sg:tags":[
        "house"
    ],
    "wof:name":"Stanford Construction",
    "wof:placetype":"venue"
},
  "geometry": {"coordinates":[-89.528758,43.615179],"type":"Point"}
}