{
  "type": "Feature",
  "properties": {
    "iso:country":"US",
    "sg:address":"3144 Center Valley Rd",
    "sg:city":"Seymour",
    "sg:classifiers":[
        {
            "category":"Building & Trades",
            "subcategory":"Construction",
            "type":"Services"
        }
    ],
    "sg:phone":"+1 920 734 4343",
    "sg:postcode":"54165",
    "sg:province":"WI",
    "sg:tags":[
        "hanging",
        "contractor"
    ],
    "wof:name":"Bernetzke Painting",
    "wof:placetype":"venue"
},
  "geometry": {"coordinates":[-88.342789,44.40093],"type":"Point"}
}