{
  "type": "Feature",
  "properties": {
    "addr:full":"3705 Monroe Rd De Pere WI 54115",
    "addr:housenumber":"3705",
    "addr:postcode":"54115",
    "addr:street":"Monroe Rd De",
    "iso:country":"US",
    "sg:address":"3705 Monroe Rd",
    "sg:city":"De Pere",
    "sg:classifiers":[
        {
            "category":"Shopping",
            "subcategory":"Discount & Variety Stores",
            "type":"Retail Goods"
        }
    ],
    "sg:phone":"+1 920 336 6096",
    "sg:postcode":"54115",
    "sg:province":"WI",
    "sg:tags":[
        "merchandise",
        "general"
    ],
    "wof:name":"Shopko",
    "wof:placetype":"venue"
},
  "geometry": {"coordinates":[-88.015545,44.433971],"type":"Point"}
}