{
  "type": "Feature",
  "properties": {
    "addr:full":"976 E Johnson St Fond Du Lac WI 54935",
    "addr:housenumber":"976",
    "addr:postcode":"54935",
    "addr:street":"E Johnson St",
    "iso:country":"US",
    "sg:address":"976 E Johnson St",
    "sg:city":"Fond Du Lac",
    "sg:classifiers":[
        {
            "category":"Restaurant",
            "type":"Food & Drink"
        }
    ],
    "sg:menulink":"http://www.allmenus.com/wi/fond-du-lac/145470-subway/menu/",
    "sg:phone":"+1 920 923 6265",
    "sg:postcode":"54935",
    "sg:province":"WI",
    "sg:tags":[
        "american",
        "sandwich"
    ],
    "wof:name":"Subway",
    "wof:placetype":"venue"
},
  "geometry": {"coordinates":[-88.409318,43.783543],"type":"Point"}
}