{
  "type": "Feature",
  "properties": {
    "iso:country":"US",
    "sg:address":"1160 Thompson Ln",
    "sg:city":"Minocqua",
    "sg:classifiers":[
        {
            "category":"Professional",
            "subcategory":"Lawyer & Legal Services",
            "type":"Services"
        }
    ],
    "sg:phone":"+1 715 356 3908",
    "sg:postcode":"54548",
    "sg:province":"WI",
    "sg:tags":[
        "attorney"
    ],
    "wof:name":"Hoyt Law Office",
    "wof:placetype":"venue"
},
  "geometry": {"coordinates":[-89.845725,45.909681],"type":"Point"}
}