{
  "type": "Feature",
  "properties": {
    "iso:country":"US",
    "sg:address":"1097 Fairfield Ln",
    "sg:city":"West Bend",
    "sg:classifiers":[
        {
            "category":"Real Estate",
            "subcategory":"Real Estate Operator",
            "type":"Services"
        }
    ],
    "sg:phone":"+1 262 675 6761",
    "sg:postcode":"53090",
    "sg:province":"WI",
    "sg:tags":[
        "property",
        "lessor"
    ],
    "wof:name":"FCC Enterprises LLC",
    "wof:placetype":"venue"
},
  "geometry": {"coordinates":[-88.08831499999999,43.458273],"type":"Point"}
}