{
  "type": "Feature",
  "properties": {
    "iso:country":"US",
    "sg:address":"228 W Main St",
    "sg:city":"Dresser",
    "sg:classifiers":[
        {
            "category":"Manufacturing",
            "subcategory":"Rubber & Plastics",
            "type":"Manufacturing & Wholesale Goods"
        }
    ],
    "sg:phone":"+1 715 755 2811",
    "sg:postcode":"54009",
    "sg:province":"WI",
    "wof:name":"UFE Inc",
    "wof:placetype":"venue"
},
  "geometry": {"coordinates":[-92.636801,45.355602],"type":"Point"}
}