{
  "type": "Feature",
  "properties": {
    "addr:full":"8330 Hickory Ln Beaver Dam WI 53916",
    "addr:housenumber":"8330",
    "addr:postcode":"53916",
    "addr:street":"Hickory Ln",
    "iso:country":"US",
    "sg:address":"8330 Hickory Ln",
    "sg:city":"Beaver Dam",
    "sg:classifiers":[
        {
            "category":"Home & Garden",
            "subcategory":"Home Furnishings",
            "type":"Retail Goods"
        }
    ],
    "sg:phone":"+1 920 885 6847",
    "sg:postcode":"53916",
    "sg:province":"WI",
    "wof:name":"Wordens Upholstery",
    "wof:placetype":"venue"
},
  "geometry": {"coordinates":[-88.840593,43.498135],"type":"Point"}
}