{
  "type": "Feature",
  "properties": {
    "addr:full":"709 W Wisconsin St Hartford WI 53027",
    "addr:housenumber":"709",
    "addr:postcode":"53027",
    "addr:street":"W Wisconsin St",
    "iso:country":"US",
    "sg:address":"709 W Wisconsin St",
    "sg:city":"Hartford",
    "sg:classifiers":[
        {
            "category":"Manufacturing",
            "subcategory":"Tools & Machinery",
            "type":"Manufacturing & Wholesale Goods"
        }
    ],
    "sg:phone":"+1 262 673 5070",
    "sg:postcode":"53027",
    "sg:province":"WI",
    "sg:tags":[
        "repair",
        "industrial",
        "sheet",
        "mfg",
        "metal",
        "welding"
    ],
    "wof:name":"Weld-Fab Mfg",
    "wof:placetype":"venue"
},
  "geometry": {"coordinates":[-88.388443,43.320964],"type":"Point"}
}