{
  "type": "Feature",
  "properties": {
    "iso:country":"US",
    "sg:address":"1125 Mallard Ave",
    "sg:city":"Oshkosh",
    "sg:classifiers":[
        {
            "category":"Real Estate",
            "subcategory":"Real Estate Operator",
            "type":"Services"
        }
    ],
    "sg:phone":"+1 920 303 5754",
    "sg:postcode":"54901",
    "sg:province":"WI",
    "sg:tags":[
        "building",
        "nonresidential"
    ],
    "wof:name":"CK Properties",
    "wof:placetype":"venue"
},
  "geometry": {"coordinates":[-88.522904,44.043026],"type":"Point"}
}