{
  "type": "Feature",
  "properties": {
    "iso:country":"US",
    "sg:address":"2079 Lawrence Dr",
    "sg:city":"De Pere",
    "sg:classifiers":[
        {
            "category":"Professional",
            "subcategory":"Advertising",
            "type":"Services"
        }
    ],
    "sg:phone":"+1 920 338 9201",
    "sg:postcode":"54115",
    "sg:province":"WI",
    "sg:tags":[
        "counselor",
        "agency"
    ],
    "wof:name":"Country World Productions Inc",
    "wof:placetype":"venue"
},
  "geometry": {"coordinates":[-88.10677200000001,44.431091],"type":"Point"}
}