{
  "type": "Feature",
  "properties": {
    "iso:country":"US",
    "sg:address":"21750 Dobbs Dr",
    "sg:city":"Soldiers Grove",
    "sg:phone":"+1 608 538 3379",
    "sg:postcode":"54655",
    "sg:province":"WI",
    "sg:tags":[
        "farm",
        "field",
        "grain",
        "cash",
        "crop"
    ],
    "wof:name":"Bucks Poor Farm",
    "wof:placetype":"venue"
},
  "geometry": {"coordinates":[-90.647576,43.38652],"type":"Point"}
}