{
  "type": "Feature",
  "properties": {
    "addr:full":"508 58th St Kenosha WI 53140",
    "addr:housenumber":"508",
    "addr:postcode":"53140",
    "addr:street":"58Th St",
    "iso:country":"US",
    "sg:address":"508 58th St",
    "sg:city":"Kenosha",
    "sg:classifiers":[
        {
            "category":"Manufacturing",
            "subcategory":"Apparel",
            "type":"Manufacturing & Wholesale Goods"
        }
    ],
    "sg:phone":"+1 262 654 4059",
    "sg:postcode":"53140",
    "sg:province":"WI",
    "sg:tags":[
        "mfg"
    ],
    "wof:name":"Francines Fine Catering LLC",
    "wof:placetype":"venue"
},
  "geometry": {"coordinates":[-87.81815400000001,42.58336],"type":"Point"}
}