{
  "type": "Feature",
  "properties": {
    "iso:country":"US",
    "sg:address":"4411 N Lake Dr",
    "sg:city":"Milwaukee",
    "sg:classifiers":[
        {
            "category":"Building & Trades",
            "subcategory":"Construction",
            "type":"Services"
        }
    ],
    "sg:phone":"+1 414 963 4002",
    "sg:postcode":"53211",
    "sg:province":"WI",
    "sg:tags":[
        "home",
        "house",
        "commercial",
        "improvement"
    ],
    "wof:name":"North Shore Builders Inc",
    "wof:placetype":"venue"
},
  "geometry": {"coordinates":[-87.878837,43.098171],"type":"Point"}
}