{
  "type": "Feature",
  "properties": {
    "addr:full":"7792 State Hwy 70 E St Germain WI 54558",
    "addr:housenumber":"7792",
    "addr:postcode":"54558",
    "addr:street":"State Hwy 70 E",
    "iso:country":"US",
    "sg:address":"7792 State Hwy 70 E",
    "sg:city":"St Germain",
    "sg:classifiers":[
        {
            "category":"Manufacturing",
            "subcategory":"Tools & Machinery",
            "type":"Manufacturing & Wholesale Goods"
        }
    ],
    "sg:phone":"+1 715 479 7421",
    "sg:postcode":"54558",
    "sg:province":"WI",
    "sg:tags":[
        "die",
        "maker"
    ],
    "wof:name":"St Germain Pioneer Tool Inc",
    "wof:placetype":"venue"
},
  "geometry": {"coordinates":[-89.460078,45.898495],"type":"Point"}
}