{
  "type": "Feature",
  "properties": {
    "iso:country":"US",
    "sg:address":"10317 S Walker Rd",
    "sg:city":"Beloit",
    "sg:classifiers":[
        {
            "category":"Cinema",
            "subcategory":"Movie Rental",
            "type":"Entertainment"
        }
    ],
    "sg:phone":"+1 608 676 4325",
    "sg:postcode":"53511",
    "sg:province":"IL",
    "sg:tags":[
        "video",
        "reporting",
        "tape"
    ],
    "wof:name":"Cannaan Video Service",
    "wof:placetype":"venue"
},
  "geometry": {"coordinates":[-88.933789,42.528303],"type":"Point"}
}