{
  "type": "Feature",
  "properties": {
    "iso:country":"US",
    "sg:address":"214 N 25th St",
    "sg:city":"Milwaukee",
    "sg:classifiers":[
        {
            "category":"Manufacturing",
            "subcategory":"Tools & Machinery",
            "type":"Manufacturing & Wholesale Goods"
        }
    ],
    "sg:phone":"+1 414 344 4500",
    "sg:postcode":"53233",
    "sg:province":"WI",
    "sg:tags":[
        "equipment",
        "welding",
        "supply"
    ],
    "sg:website":"www.proweldinternational.net",
    "wof:name":"ASAP Fastening Systems Inc",
    "wof:placetype":"venue"
},
  "geometry": {"coordinates":[-87.944652,43.032776],"type":"Point"}
}