{
  "type": "Feature",
  "properties": {
    "iso:country":"US",
    "sg:address":"918 Evans St",
    "sg:city":"Oshkosh",
    "sg:classifiers":[
        {
            "category":"Building & Trades",
            "subcategory":"Construction",
            "type":"Services"
        }
    ],
    "sg:phone":"+1 920 426 5821",
    "sg:postcode":"54901",
    "sg:province":"WI",
    "sg:tags":[
        "residential"
    ],
    "wof:name":"Vandenboogaard Construction",
    "wof:placetype":"venue"
},
  "geometry": {"coordinates":[-88.526245,44.027887],"type":"Point"}
}