{
  "type": "Feature",
  "properties": {
    "addr:full":"3530 W Park Hill Ave Milwaukee WI 53208",
    "addr:housenumber":"3530",
    "addr:postcode":"53208",
    "addr:street":"W Park Hill Ave",
    "iso:country":"US",
    "sg:address":"3530 W Park Hill Ave",
    "sg:city":"Milwaukee",
    "sg:classifiers":[
        {
            "category":"Social Services",
            "subcategory":"Child Care",
            "type":"Services"
        }
    ],
    "sg:phone":"+1 414 934 8057",
    "sg:postcode":"53208",
    "sg:province":"WI",
    "wof:name":"Community Paths Child Care",
    "wof:placetype":"venue"
},
  "geometry": {"coordinates":[-87.95864400000001,43.032759],"type":"Point"}
}