{
  "type": "Feature",
  "properties": {
    "iso:country":"US",
    "sg:address":"10898 US Hwy 10",
    "sg:city":"Marshfield",
    "sg:classifiers":[
        {
            "category":"Farming",
            "subcategory":"Dairy Farm",
            "type":"Manufacturing & Wholesale Goods"
        }
    ],
    "sg:phone":"+1 715 676 2177",
    "sg:postcode":"54449",
    "sg:province":"WI",
    "wof:name":"Nasonville Dairy Inc",
    "wof:placetype":"venue"
},
  "geometry": {"coordinates":[-90.253816,44.598798],"type":"Point"}
}