{
  "type": "Feature",
  "properties": {
    "addr:full":"4811 Monona Dr Monona WI 53716",
    "addr:housenumber":"4811",
    "addr:postcode":"53716",
    "addr:street":"Monona Dr",
    "iso:country":"US",
    "sg:address":"4811 Monona Dr",
    "sg:city":"Monona",
    "sg:classifiers":[
        {
            "category":"Retail",
            "subcategory":"Laundry & Dry Cleaning",
            "type":"Services"
        },
        {
            "category":"Shopping",
            "subcategory":"Clothing, Apparel, & Fashions",
            "type":"Retail Goods"
        }
    ],
    "sg:phone":"+1 608 222 0110",
    "sg:postcode":"53716",
    "sg:province":"WI",
    "sg:tags":[
        "alteration"
    ],
    "wof:name":"Monona Alterations",
    "wof:placetype":"venue"
},
  "geometry": {"coordinates":[-89.326223,43.064791],"type":"Point"}
}