{
  "type": "Feature",
  "properties": {
    "iso:country":"US",
    "sg:address":"19555 W Bluemound Rd",
    "sg:city":"Brookfield",
    "sg:classifiers":[
        {
            "category":"Home & Garden",
            "subcategory":"Garden Supply",
            "type":"Retail Goods"
        }
    ],
    "sg:phone":"+1 262 789 8226",
    "sg:postcode":"53045",
    "sg:province":"WI",
    "sg:tags":[
        "house",
        "bird",
        "feeder"
    ],
    "sg:website":"www.wbu.com",
    "wof:name":"Wild Birds Unlimited",
    "wof:placetype":"venue"
},
  "geometry": {"coordinates":[-88.15216599999999,43.035916],"type":"Point"}
}