{
  "type": "Feature",
  "properties": {
    "iso:country":"US",
    "sg:address":"4487 Cherokee Trl",
    "sg:city":"Hubertus",
    "sg:classifiers":[
        {
            "category":"Wholesale",
            "subcategory":"Machinery & Supplies",
            "type":"Manufacturing & Wholesale Goods"
        }
    ],
    "sg:phone":"+1 262 628 4193",
    "sg:postcode":"53033",
    "sg:province":"WI",
    "sg:tags":[
        "equipment",
        "irrigation",
        "system"
    ],
    "wof:name":"Shoreline Irrigation LLC",
    "wof:placetype":"venue"
},
  "geometry": {"coordinates":[-88.260833,43.228432],"type":"Point"}
}