{
  "type": "Feature",
  "properties": {
    "addr:full":"610 E Longview Dr Appleton WI 54911",
    "addr:housenumber":"610",
    "addr:postcode":"54911",
    "addr:street":"E Longview Dr",
    "iso:country":"US",
    "sg:address":"610 E Longview Dr",
    "sg:city":"Appleton",
    "sg:classifiers":[
        {
            "category":"Social Services",
            "type":"Services"
        }
    ],
    "sg:phone":"+1 920 830 3900",
    "sg:postcode":"54911",
    "sg:province":"WI",
    "wof:name":"Alberts Richard & Assoc",
    "wof:placetype":"venue"
},
  "geometry": {"coordinates":[-88.39586799999999,44.28642],"type":"Point"}
}