{
  "type": "Feature",
  "properties": {
    "iso:country":"US",
    "sg:address":"1138 State St",
    "sg:city":"Green Bay",
    "sg:classifiers":[
        {
            "category":"Professional",
            "subcategory":"Business Services",
            "type":"Services"
        }
    ],
    "sg:phone":"+1 920 433 9442",
    "sg:postcode":"54304",
    "sg:province":"WI",
    "sg:tags":[
        "plant",
        "design",
        "maintenance"
    ],
    "wof:name":"Plant People",
    "wof:placetype":"venue"
},
  "geometry": {"coordinates":[-88.028379,44.504294],"type":"Point"}
}