{
  "type": "Feature",
  "properties": {
    "addr:full":"550 Elizabeth St Waukesha WI 53186",
    "addr:housenumber":"550",
    "addr:postcode":"53186",
    "addr:street":"Elizabeth St",
    "iso:country":"US",
    "sg:address":"550 Elizabeth St",
    "sg:city":"Waukesha",
    "sg:classifiers":[
        {
            "category":"Wholesale",
            "subcategory":"Stationery",
            "type":"Manufacturing & Wholesale Goods"
        }
    ],
    "sg:phone":"+1 262 524 2010",
    "sg:postcode":"53186",
    "sg:province":"WI",
    "sg:tags":[
        "business",
        "form",
        "system"
    ],
    "wof:name":"Garland Co",
    "wof:placetype":"venue"
},
  "geometry": {"coordinates":[-88.238373,43.004371],"type":"Point"}
}