{
  "type": "Feature",
  "properties": {
    "iso:country":"US",
    "sg:address":"9720 W Bluemound Rd",
    "sg:city":"Milwaukee",
    "sg:classifiers":[
        {
            "category":"Health Services",
            "subcategory":"Doctor",
            "type":"Services"
        }
    ],
    "sg:phone":"+1 414 774 1794",
    "sg:postcode":"53226",
    "sg:province":"WI",
    "sg:tags":[
        "clinic",
        "behavioral"
    ],
    "wof:name":"American Behavioral Clinics",
    "wof:placetype":"venue"
},
  "geometry": {"coordinates":[-88.035065,43.035166],"type":"Point"}
}