{
  "type": "Feature",
  "properties": {
    "iso:country":"US",
    "sg:address":"4640 Cottage Grove Rd",
    "sg:city":"Madison",
    "sg:classifiers":[
        {
            "category":"Retail",
            "subcategory":"Veterinary Services",
            "type":"Services"
        }
    ],
    "sg:phone":"+1 608 221 3509",
    "sg:postcode":"53716",
    "sg:province":"WI",
    "sg:tags":[
        "veterinarian",
        "animal"
    ],
    "wof:name":"Petcare Clinics Inc",
    "wof:placetype":"venue"
},
  "geometry": {"coordinates":[-89.29985499999999,43.084324],"type":"Point"}
}