{
  "type": "Feature",
  "properties": {
    "addr:full":"205 Chestnut St Silver Lake WI 53170",
    "addr:housenumber":"205",
    "addr:postcode":"53170",
    "addr:street":"Chestnut St",
    "iso:country":"US",
    "sg:address":"205 Chestnut St",
    "sg:city":"Silver Lake",
    "sg:classifiers":[
        {
            "category":"Building & Trades",
            "subcategory":"Plumbing",
            "type":"Services"
        }
    ],
    "sg:phone":"+1 262 889 4557",
    "sg:postcode":"53170",
    "sg:province":"WI",
    "sg:tags":[
        "plumbing"
    ],
    "wof:name":"Woodland Plumbing Inc",
    "wof:placetype":"venue"
},
  "geometry": {"coordinates":[-88.170833,42.546998],"type":"Point"}
}