{
  "type": "Feature",
  "properties": {
    "addr:full":"10265 Lumsden Rd Elroy WI 53929",
    "addr:housenumber":"10265",
    "addr:postcode":"53929",
    "addr:street":"Lumsden Rd",
    "iso:country":"US",
    "sg:address":"10265 Lumsden Rd",
    "sg:city":"Elroy",
    "sg:classifiers":[
        {
            "category":"Farming",
            "subcategory":"Dairy Farm",
            "type":"Manufacturing & Wholesale Goods"
        }
    ],
    "sg:phone":"+1 608 462 8523",
    "sg:postcode":"53929",
    "sg:province":"WI",
    "wof:name":"Peter Retzlaff",
    "wof:placetype":"venue"
},
  "geometry": {"coordinates":[-90.279038,43.720561],"type":"Point"}
}