{
  "type": "Feature",
  "properties": {
    "iso:country":"US",
    "sg:address":"3021 Macarthur Way",
    "sg:city":"Plover",
    "sg:classifiers":[
        {
            "category":"Retail",
            "subcategory":"Auto Repair",
            "type":"Services"
        }
    ],
    "sg:phone":"+1 715 343 0933",
    "sg:postcode":"54467",
    "sg:province":"WI",
    "sg:tags":[
        "body"
    ],
    "wof:name":"Carstar",
    "wof:placetype":"venue"
},
  "geometry": {"coordinates":[-89.548687,44.478564],"type":"Point"}
}