{
  "type": "Feature",
  "properties": {
    "iso:country":"US",
    "sg:address":"4114 Donald Dr",
    "sg:city":"Madison",
    "sg:classifiers":[
        {
            "category":"Education",
            "subcategory":"School",
            "type":"Public Place"
        }
    ],
    "sg:phone":"+1 608 204 7940",
    "sg:postcode":"53704",
    "sg:province":"WI",
    "wof:name":"Sandburg Elementary School",
    "wof:placetype":"venue"
},
  "geometry": {"coordinates":[-89.312684,43.135976],"type":"Point"}
}