{
  "type": "Feature",
  "properties": {
    "iso:country":"US",
    "sg:address":"4325 W Beltline Hwy",
    "sg:city":"Madison",
    "sg:classifiers":[
        {
            "category":"Shopping",
            "subcategory":"Computers & Home Electronics",
            "type":"Retail Goods"
        }
    ],
    "sg:phone":"+1 608 274 1007",
    "sg:postcode":"53711",
    "sg:province":"WI",
    "sg:website":"www.janssencomputers.com",
    "wof:name":"Janssen Computers",
    "wof:placetype":"venue"
},
  "geometry": {"coordinates":[-89.444867,43.034624],"type":"Point"}
}