{
  "type": "Feature",
  "properties": {
    "iso:country":"US",
    "sg:address":"2314 Keenan Rd",
    "sg:city":"Mc Farland",
    "sg:classifiers":[
        {
            "category":"Farming",
            "subcategory":"Dairy Farm",
            "type":"Manufacturing & Wholesale Goods"
        }
    ],
    "sg:phone":"+1 608 835 3077",
    "sg:postcode":"53558",
    "sg:province":"WI",
    "wof:name":"William Gausman",
    "wof:placetype":"venue"
},
  "geometry": {"coordinates":[-89.323041,42.970061],"type":"Point"}
}