{
  "type": "Feature",
  "properties": {
    "iso:country":"US",
    "sg:address":"3266 W Southwood Dr",
    "sg:city":"Franklin",
    "sg:classifiers":[
        {
            "category":"Building & Trades",
            "subcategory":"Construction",
            "type":"Services"
        }
    ],
    "sg:phone":"+1 414 761 8969",
    "sg:postcode":"53132",
    "sg:province":"WI",
    "sg:tags":[
        "concrete",
        "contractor"
    ],
    "wof:name":"Area Fence & Concrete",
    "wof:placetype":"venue"
},
  "geometry": {"coordinates":[-87.958192,42.87677],"type":"Point"}
}