{
  "type": "Feature",
  "properties": {
    "iso:country":"US",
    "sg:address":"910 20th St",
    "sg:city":"Two Rivers",
    "sg:classifiers":[
        {
            "category":"Manufacturing",
            "subcategory":"Textiles",
            "type":"Manufacturing & Wholesale Goods"
        }
    ],
    "sg:phone":"+1 920 794 1077",
    "sg:postcode":"54241",
    "sg:province":"WI",
    "sg:tags":[
        "mfg"
    ],
    "wof:name":"Cmd Enterprises",
    "wof:placetype":"venue"
},
  "geometry": {"coordinates":[-87.560294,44.151771],"type":"Point"}
}