{
  "type": "Feature",
  "properties": {
    "iso:country":"US",
    "sg:address":"830 Raymond St",
    "sg:city":"Green Bay",
    "sg:classifiers":[
        {
            "category":"Retail",
            "subcategory":"Auto Repair",
            "type":"Services"
        }
    ],
    "sg:phone":"+1 920 498 2746",
    "sg:postcode":"54304",
    "sg:province":"WI",
    "sg:tags":[
        "automotive"
    ],
    "wof:name":"Ds Enterprise",
    "wof:placetype":"venue"
},
  "geometry": {"coordinates":[-88.053443,44.515147],"type":"Point"}
}