{
  "type": "Feature",
  "properties": {
    "iso:country":"US",
    "sg:address":"120 N Madison St",
    "sg:city":"Evansville",
    "sg:classifiers":[
        {
            "category":"Retail",
            "subcategory":"Veterinary Services",
            "type":"Services"
        }
    ],
    "sg:phone":"+1 608 882 0177",
    "sg:postcode":"53536",
    "sg:province":"WI",
    "wof:name":"Visiting Vet LLC",
    "wof:placetype":"venue"
},
  "geometry": {"coordinates":[-89.299096,42.782848],"type":"Point"}
}