{
  "type": "Feature",
  "properties": {
    "iso:country":"US",
    "sg:address":"102 Kettle Moraine Dr S",
    "sg:city":"Slinger",
    "sg:classifiers":[
        {
            "category":"Professional",
            "subcategory":"Advertising",
            "type":"Services"
        }
    ],
    "sg:phone":"+1 262 644 5206",
    "sg:postcode":"53086",
    "sg:province":"WI",
    "sg:tags":[
        "mail"
    ],
    "wof:name":"Creative Marketing-America Inc",
    "wof:placetype":"venue"
},
  "geometry": {"coordinates":[-88.285085,43.33431],"type":"Point"}
}