{
  "type": "Feature",
  "properties": {
    "addr:full":"1810 N 16th St Superior WI 54880",
    "addr:housenumber":"1810",
    "addr:postcode":"54880",
    "addr:street":"N 16Th St",
    "iso:country":"US",
    "sg:address":"1810 N 16th St",
    "sg:city":"Superior",
    "sg:classifiers":[
        {
            "category":"Health Services",
            "subcategory":"Chiropractor",
            "type":"Services"
        }
    ],
    "sg:phone":"+1 715 394 5645",
    "sg:postcode":"54880",
    "sg:province":"WI",
    "wof:name":"Lange-Laughlin Chiropractic",
    "wof:placetype":"venue"
},
  "geometry": {"coordinates":[-92.10536399999999,46.719245],"type":"Point"}
}