{
  "type": "Feature",
  "properties": {
    "iso:country":"US",
    "sg:address":"4615 State Hwy 42",
    "sg:city":"Sturgeon Bay",
    "sg:classifiers":[
        {
            "category":"Recreation",
            "subcategory":"Marina",
            "type":"Entertainment"
        }
    ],
    "sg:phone":"+1 920 743 8838",
    "sg:postcode":"54235",
    "sg:province":"WI",
    "sg:tags":[
        "storage",
        "boat"
    ],
    "wof:name":"D C Storage & Shipshape",
    "wof:placetype":"venue"
},
  "geometry": {"coordinates":[-87.33690900000001,44.896583],"type":"Point"}
}