{
  "type": "Feature",
  "properties": {
    "iso:country":"US",
    "sg:address":"1242 6th St",
    "sg:city":"Beloit",
    "sg:classifiers":[
        {
            "category":"Retail",
            "subcategory":"Auto Repair",
            "type":"Services"
        }
    ],
    "sg:phone":"+1 608 362 8599",
    "sg:postcode":"53511",
    "sg:province":"IL",
    "sg:tags":[
        "repairing",
        "automobile",
        "general"
    ],
    "wof:name":"Anthony's Auto Repair",
    "wof:placetype":"venue"
},
  "geometry": {"coordinates":[-89.040515,42.513863],"type":"Point"}
}