{
  "type": "Feature",
  "properties": {
    "iso:country":"US",
    "sg:address":"116 E Main St",
    "sg:city":"Sun Prairie",
    "sg:classifiers":[
        {
            "category":"Bars & Pubs",
            "type":"Food & Drink"
        }
    ],
    "sg:phone":"+1 608 825 9977",
    "sg:postcode":"53590",
    "sg:province":"WI",
    "sg:tags":[
        "drinking"
    ],
    "wof:name":"Pitstop Pub LLC",
    "wof:placetype":"venue"
},
  "geometry": {"coordinates":[-89.213525,43.183376],"type":"Point"}
}