{
  "type": "Feature",
  "properties": {
    "iso:country":"US",
    "sg:address":"413 Main St",
    "sg:city":"Racine",
    "sg:classifiers":[
        {
            "category":"Organizations",
            "subcategory":"Non-profit Organization",
            "type":"Services"
        }
    ],
    "sg:phone":"+1 262 634 6002",
    "sg:postcode":"53403",
    "sg:province":"WI",
    "wof:name":"Downtown Racine Corp",
    "wof:placetype":"venue"
},
  "geometry": {"coordinates":[-87.782947,42.728206],"type":"Point"}
}