{
  "type": "Feature",
  "properties": {
    "iso:country":"US",
    "sg:address":"708 S 6th St",
    "sg:city":"Delavan",
    "sg:classifiers":[
        {
            "category":"Freight",
            "type":"Transportation"
        }
    ],
    "sg:phone":"+1 262 728 8169",
    "sg:postcode":"53115",
    "sg:province":"WI",
    "sg:tags":[
        "courier"
    ],
    "wof:name":"Redbone Express Inc",
    "wof:placetype":"venue"
},
  "geometry": {"coordinates":[-88.640651,42.623459],"type":"Point"}
}