{
  "type": "Feature",
  "properties": {
    "iso:country":"US",
    "sg:address":"13532 95th Ave",
    "sg:city":"Chippewa Falls",
    "sg:classifiers":[
        {
            "category":"Autos & Motor Vehicles",
            "subcategory":"Automobile Sales",
            "type":"Retail Goods"
        }
    ],
    "sg:phone":"+1 715 720 1957",
    "sg:postcode":"54729",
    "sg:province":"WI",
    "wof:name":"Steven Dresel Auto L L C",
    "wof:placetype":"venue"
},
  "geometry": {"coordinates":[-91.39317,44.980885],"type":"Point"}
}