{
  "type": "Feature",
  "properties": {
    "iso:country":"US",
    "sg:address":"925 W River St",
    "sg:city":"Chippewa Falls",
    "sg:classifiers":[
        {
            "category":"Freight",
            "type":"Transportation"
        }
    ],
    "sg:phone":"+1 715 723 1234",
    "sg:postcode":"54729",
    "sg:province":"WI",
    "sg:tags":[
        "commercial",
        "storage"
    ],
    "wof:name":"Chippewa River Business Park",
    "wof:placetype":"venue"
},
  "geometry": {"coordinates":[-91.41787600000001,44.92543],"type":"Point"}
}