{
  "type": "Feature",
  "properties": {
    "iso:country":"US",
    "sg:address":"4089 Co Rd Bb",
    "sg:city":"Menomonie",
    "sg:classifiers":[
        {
            "category":"Bus Charters",
            "type":"Transportation"
        }
    ],
    "sg:phone":"+1 715 235 5178",
    "sg:postcode":"54751",
    "sg:province":"WI",
    "sg:tags":[
        "rental"
    ],
    "wof:name":"Menomonie Coaches",
    "wof:placetype":"venue"
},
  "geometry": {"coordinates":[-91.965201,44.922517],"type":"Point"}
}