{
  "type": "Feature",
  "properties": {
    "iso:country":"US",
    "sg:address":"2150 Chestnut St",
    "sg:city":"West Bend",
    "sg:classifiers":[
        {
            "category":"Health Services",
            "subcategory":"Doctor",
            "type":"Services"
        }
    ],
    "sg:phone":"+1 262 334 5431",
    "sg:postcode":"53095",
    "sg:province":"WI",
    "wof:name":"Lutz Chiropractic",
    "wof:placetype":"venue"
},
  "geometry": {"coordinates":[-88.201453,43.419907],"type":"Point"}
}