{
  "type": "Feature",
  "properties": {
    "addr:full":"101 S Gibson St Medford WI 54451",
    "addr:housenumber":"101",
    "addr:postcode":"54451",
    "addr:street":"S Gibson St",
    "iso:country":"US",
    "sg:address":"101 S Gibson St",
    "sg:city":"Medford",
    "sg:classifiers":[
        {
            "category":"Health Services",
            "subcategory":"Optometrist",
            "type":"Services"
        }
    ],
    "sg:phone":"+1 715 748 5775",
    "sg:postcode":"54451",
    "sg:province":"WI",
    "sg:tags":[
        "medical"
    ],
    "wof:name":"Eye Clinic of Wausau S C",
    "wof:placetype":"venue"
},
  "geometry": {"coordinates":[-90.35393999999999,45.13671],"type":"Point"}
}