{
  "type": "Feature",
  "properties": {
    "addr:full":"830 Main St Union Grove WI 53182",
    "addr:housenumber":"830",
    "addr:postcode":"53182",
    "addr:street":"Main St",
    "iso:country":"US",
    "sg:address":"830 Main St",
    "sg:city":"Union Grove",
    "sg:classifiers":[
        {
            "category":"Government",
            "subcategory":"Post Office",
            "type":"Public Place"
        }
    ],
    "sg:phone":"+1 262 878 1100",
    "sg:postcode":"53182",
    "sg:province":"WI",
    "wof:name":"US Post Office",
    "wof:placetype":"venue"
},
  "geometry": {"coordinates":[-88.051967,42.689776],"type":"Point"}
}