{
  "type": "Feature",
  "properties": {
    "addr:full":"7400 W Rawson Ave Franklin WI 53132",
    "addr:housenumber":"7400",
    "addr:postcode":"53132",
    "addr:street":"W Rawson Ave",
    "iso:country":"US",
    "sg:address":"7400 W Rawson Ave",
    "sg:city":"Franklin",
    "sg:classifiers":[
        {
            "category":"Health Services",
            "subcategory":"Doctor",
            "type":"Services"
        }
    ],
    "sg:phone":"+1 414 529 2500",
    "sg:postcode":"53132",
    "sg:province":"WI",
    "sg:tags":[
        "physician",
        "surgeon"
    ],
    "wof:name":"Sports Medicine & Orthopedic",
    "wof:placetype":"venue"
},
  "geometry": {"coordinates":[-88.003174,42.916108],"type":"Point"}
}