{
  "type": "Feature",
  "properties": {
    "iso:country":"US",
    "sg:address":"24510 84th St",
    "sg:city":"Salem",
    "sg:classifiers":[
        {
            "category":"Professional",
            "subcategory":"Accounting & Tax Preparation",
            "type":"Services"
        }
    ],
    "sg:phone":"+1 262 843 2636",
    "sg:postcode":"53168",
    "sg:province":"WI",
    "sg:tags":[
        "accountant"
    ],
    "wof:name":"Wheeler Accounting Service",
    "wof:placetype":"venue"
},
  "geometry": {"coordinates":[-88.105103,42.555302],"type":"Point"}
}