{
  "type": "Feature",
  "properties": {
    "addr:full":"1954 Prospect St Racine WI 53404",
    "addr:housenumber":"1954",
    "addr:postcode":"53404",
    "addr:street":"Prospect St",
    "iso:country":"US",
    "sg:address":"1954 Prospect St",
    "sg:city":"Racine",
    "sg:classifiers":[
        {
            "category":"Personal",
            "subcategory":"Barber",
            "type":"Services"
        }
    ],
    "sg:phone":"+1 262 634 6335",
    "sg:postcode":"53404",
    "sg:province":"WI",
    "wof:name":"Marcus Barber Shop",
    "wof:placetype":"venue"
},
  "geometry": {"coordinates":[-87.805939,42.734143],"type":"Point"}
}