{
  "type": "Feature",
  "properties": {
    "iso:country":"US",
    "sg:address":"111 S Jefferson St",
    "sg:city":"Lancaster",
    "sg:classifiers":[
        {
            "category":"Government",
            "subcategory":"Office",
            "type":"Public Place"
        }
    ],
    "sg:phone":"+1 608 723 2604",
    "sg:postcode":"53813",
    "sg:province":"WI",
    "sg:tags":[
        "county",
        "taxation"
    ],
    "wof:name":"Grant County Treasurer",
    "wof:placetype":"venue"
},
  "geometry": {"coordinates":[-90.710907,42.847856],"type":"Point"}
}