{
  "type": "Feature",
  "properties": {
    "addr:full":"20114 Riveredge Dr Chippewa Falls WI 54729",
    "addr:postcode":"20114;54729",
    "addr:street":"Riveredge Dr",
    "iso:country":"US",
    "sg:address":"20114 Riveredge Dr",
    "sg:city":"Chippewa Falls",
    "sg:classifiers":[
        {
            "category":"Building & Trades",
            "subcategory":"Construction",
            "type":"Services"
        }
    ],
    "sg:phone":"+1 715 723 2500",
    "sg:postcode":"54729",
    "sg:province":"WI",
    "sg:tags":[
        "dry wall",
        "contractor"
    ],
    "wof:name":"Chippewa Valley Drywall Svc",
    "wof:placetype":"venue"
},
  "geometry": {"coordinates":[-91.262531,44.952663],"type":"Point"}
}