{
  "type": "Feature",
  "properties": {
    "iso:country":"US",
    "sg:address":"144 Po St",
    "sg:city":"West Bend",
    "sg:classifiers":[
        {
            "category":"Banks & Credit Unions",
            "subcategory":"Investment Brokerage",
            "type":"Services"
        }
    ],
    "sg:phone":"+1 262 306 6884",
    "sg:postcode":"53090",
    "sg:province":"WI",
    "sg:tags":[
        "security"
    ],
    "wof:name":"Robert W Baird & Co",
    "wof:placetype":"venue"
},
  "geometry": {"coordinates":[-88.17798,43.4308],"type":"Point"}
}