{
  "type": "Feature",
  "properties": {
    "iso:country":"US",
    "sg:address":"2205 Central Ave",
    "sg:city":"Superior",
    "sg:classifiers":[
        {
            "category":"Manufacturing",
            "subcategory":"Metals",
            "type":"Manufacturing & Wholesale Goods"
        }
    ],
    "sg:phone":"+1 715 392 4134",
    "sg:postcode":"54880",
    "sg:province":"WI",
    "sg:tags":[
        "steel",
        "plate",
        "sheet",
        "mfg",
        "work",
        "fabricated",
        "meta",
        "repair",
        "welding"
    ],
    "sg:website":"www.barkerswelding.com",
    "wof:name":"Barker's Welding Inc",
    "wof:placetype":"venue"
},
  "geometry": {"coordinates":[-92.109218,46.665888],"type":"Point"}
}