{
  "type": "Feature",
  "properties": {
    "iso:country":"US",
    "sg:address":"3328 Park Ridge Ave",
    "sg:city":"Appleton",
    "sg:classifiers":[
        {
            "category":"Professional",
            "subcategory":"Research",
            "type":"Services"
        }
    ],
    "sg:phone":"+1 920 830 3560",
    "sg:postcode":"54914",
    "sg:province":"WI",
    "sg:tags":[
        "nonphysical",
        "commercial"
    ],
    "wof:name":"Educational Services Inc",
    "wof:placetype":"venue"
},
  "geometry": {"coordinates":[-88.461007,44.293084],"type":"Point"}
}