{
  "type": "Feature",
  "properties": {
    "addr:full":"3103 52nd St Kenosha WI 53144",
    "addr:housenumber":"3103",
    "addr:postcode":"53144",
    "addr:street":"52Nd St",
    "iso:country":"US",
    "sg:address":"3103 52nd St",
    "sg:city":"Kenosha",
    "sg:classifiers":[
        {
            "category":"Banks & Credit Unions",
            "subcategory":"Bank",
            "type":"Services"
        }
    ],
    "sg:phone":"+1 262 652 2704",
    "sg:postcode":"53144",
    "sg:province":"WI",
    "sg:tags":[
        "loan",
        "real estate"
    ],
    "wof:name":"First Financial Mortgage",
    "wof:placetype":"venue"
},
  "geometry": {"coordinates":[-87.84815999999999,42.588107],"type":"Point"}
}