{
  "type": "Feature",
  "properties": {
    "iso:country":"US",
    "sg:address":"1010 Valley Rd",
    "sg:city":"Plymouth",
    "sg:classifiers":[
        {
            "category":"Manufacturing",
            "subcategory":"Rubber & Plastics",
            "type":"Manufacturing & Wholesale Goods"
        }
    ],
    "sg:phone":"+1 920 893 6281",
    "sg:postcode":"53073",
    "sg:province":"WI",
    "sg:tags":[
        "forming"
    ],
    "wof:name":"Shell Plastics LLC",
    "wof:placetype":"venue"
},
  "geometry": {"coordinates":[-87.96345,43.739885],"type":"Point"}
}