{
  "type": "Feature",
  "properties": {
    "iso:country":"US",
    "sg:address":"850 Armstrong St",
    "sg:city":"Portage",
    "sg:classifiers":[
        {
            "category":"Education",
            "subcategory":"School",
            "type":"Public Place"
        }
    ],
    "sg:phone":"+1 608 742 2387",
    "sg:postcode":"53901",
    "sg:province":"WI",
    "sg:tags":[
        "organization",
        "religious"
    ],
    "wof:name":"St Johns Lutheran School",
    "wof:placetype":"venue"
},
  "geometry": {"coordinates":[-89.471358,43.543532],"type":"Point"}
}