{
  "type": "Feature",
  "properties": {
    "iso:country":"US",
    "sg:address":"826 Summer St",
    "sg:city":"Hudson",
    "sg:classifiers":[
        {
            "category":"Real Estate",
            "subcategory":"Real Estate Agent",
            "type":"Services"
        }
    ],
    "sg:phone":"+1 715 377 0093",
    "sg:postcode":"54016",
    "sg:province":"WI",
    "wof:name":"G M Homes Summer Pines",
    "wof:placetype":"venue"
},
  "geometry": {"coordinates":[-92.747406,44.966807],"type":"Point"}
}