{
  "type": "Feature",
  "properties": {
    "iso:country":"US",
    "sg:address":"600 South St",
    "sg:city":"Green Lake",
    "sg:classifiers":[
        {
            "category":"Retail",
            "subcategory":"Self-service Laundry",
            "type":"Services"
        }
    ],
    "sg:phone":"+1 920 294 3664",
    "sg:postcode":"54941",
    "sg:province":"WI",
    "sg:tags":[
        "coin"
    ],
    "wof:name":"South St Coin Ldry & Dry Clg",
    "wof:placetype":"venue"
},
  "geometry": {"coordinates":[-88.952209,43.844136],"type":"Point"}
}