{
  "type": "Feature",
  "properties": {
    "addr:full":"6550 Haipek Rd Black River Fls WI 54615",
    "addr:housenumber":"6550",
    "addr:postcode":"54615",
    "addr:street":"Haipek Rd",
    "iso:country":"US",
    "sg:address":"6550 Haipek Rd",
    "sg:city":"Black River Fls",
    "sg:classifiers":[
        {
            "category":"Government",
            "subcategory":"Jail",
            "type":"Public Place"
        }
    ],
    "sg:phone":"+1 715 284 4550",
    "sg:postcode":"54615",
    "sg:province":"WI",
    "sg:tags":[
        "govt",
        "state",
        "institution"
    ],
    "wof:name":"Jackson Correctional Inst",
    "wof:placetype":"venue"
},
  "geometry": {"coordinates":[-90.79648,44.308771],"type":"Point"}
}