{
  "type": "Feature",
  "properties": {
    "iso:country":"US",
    "sg:address":"417 Jay St",
    "sg:city":"La Crosse",
    "sg:classifiers":[
        {
            "category":"Bars & Pubs",
            "type":"Food & Drink"
        }
    ],
    "sg:phone":"+1 608 782 5105",
    "sg:postcode":"54601",
    "sg:province":"WI",
    "sg:tags":[
        "drinking"
    ],
    "wof:name":"Rainbow's End",
    "wof:placetype":"venue"
},
  "geometry": {"coordinates":[-91.250333,43.811104],"type":"Point"}
}