{
  "type": "Feature",
  "properties": {
    "iso:country":"US",
    "sg:address":"1262 Arthur Dr",
    "sg:city":"Milton",
    "sg:classifiers":[
        {
            "category":"Autos & Motor Vehicles",
            "subcategory":"Fuel & Gas Station",
            "type":"Retail Goods"
        }
    ],
    "sg:phone":"+1 608 868 9000",
    "sg:postcode":"53563",
    "sg:province":"WI",
    "sg:tags":[
        "oil"
    ],
    "wof:name":"Milton Mobil Travel Ctr",
    "wof:placetype":"venue"
},
  "geometry": {"coordinates":[-88.939869,42.761874],"type":"Point"}
}