{
  "type": "Feature",
  "properties": {
    "addr:full":"2069 S 32nd St Milwaukee WI 53215",
    "addr:housenumber":"2069",
    "addr:postcode":"53215",
    "addr:street":"S 32Nd St",
    "iso:country":"US",
    "sg:address":"2069 S 32nd St",
    "sg:city":"Milwaukee",
    "sg:classifiers":[
        {
            "category":"Place Of Worship",
            "subcategory":"Church",
            "type":"Public Place"
        },
        {
            "category":"Place Of Worship",
            "type":"Public Place"
        },
        {
            "category":"Organizations",
            "subcategory":"Religious Organization",
            "type":"Services"
        }
    ],
    "sg:phone":"+1 414 645 5414",
    "sg:postcode":"53215",
    "sg:province":"WI",
    "sg:tags":[
        "churches-catholic-traditional",
        "churches-catholic"
    ],
    "wof:name":"St Rafael The Archangel & Congregation",
    "wof:placetype":"venue"
},
  "geometry": {"coordinates":[-87.954105,43.007229],"type":"Point"}
}