{
  "type": "Feature",
  "properties": {
    "iso:country":"US",
    "sg:address":"6302 Lacy Rd",
    "sg:city":"Fitchburg",
    "sg:classifiers":[
        {
            "category":"Building & Trades",
            "subcategory":"Construction",
            "type":"Services"
        }
    ],
    "sg:phone":"+1 608 437 8848",
    "sg:postcode":"53593",
    "sg:province":"WI",
    "sg:tags":[
        "concrete",
        "contractor"
    ],
    "wof:name":"Bomanite",
    "wof:placetype":"venue"
},
  "geometry": {"coordinates":[-89.484406,42.999478],"type":"Point"}
}