{
  "type": "Feature",
  "properties": {
    "iso:country":"US",
    "sg:address":"18895 W Bluemound Rd",
    "sg:city":"Brookfield",
    "sg:classifiers":[
        {
            "category":"Home & Garden",
            "subcategory":"Furniture",
            "type":"Retail Goods"
        }
    ],
    "sg:phone":"+1 262 782 5100",
    "sg:postcode":"53045",
    "sg:province":"WI",
    "wof:name":"Bellini Inc",
    "wof:placetype":"venue"
},
  "geometry": {"coordinates":[-88.15030299999999,43.035978],"type":"Point"}
}