{
  "type": "Feature",
  "properties": {
    "iso:country":"US",
    "sg:address":"2821 S Oneida St",
    "sg:city":"Green Bay",
    "sg:classifiers":[
        {
            "category":"Retail",
            "subcategory":"Auto Rental",
            "type":"Services"
        }
    ],
    "sg:phone":"+1 920 490 8333",
    "sg:postcode":"54304",
    "sg:province":"WI",
    "sg:tags":[
        "leasing"
    ],
    "sg:website":"www.enterprise.com",
    "wof:name":"Enterprise Rent-A-Car",
    "wof:placetype":"venue"
},
  "geometry": {"coordinates":[-88.074929,44.472929],"type":"Point"}
}