{
  "type": "Feature",
  "properties": {
    "iso:country":"US",
    "sg:address":"1201 N State St",
    "sg:city":"Merrill",
    "sg:classifiers":[
        {
            "category":"Education",
            "subcategory":"School",
            "type":"Public Place"
        }
    ],
    "sg:phone":"+1 715 536 4594",
    "sg:postcode":"54452",
    "sg:province":"WI",
    "wof:name":"Merrill High School",
    "wof:placetype":"venue"
},
  "geometry": {"coordinates":[-89.70873,45.191534],"type":"Point"}
}