{
  "type": "Feature",
  "properties": {
    "iso:country":"US",
    "sg:address":"4213 N Scharine Rd",
    "sg:city":"Whitewater",
    "sg:classifiers":[
        {
            "category":"Manufacturing",
            "subcategory":"Metals",
            "type":"Manufacturing & Wholesale Goods"
        }
    ],
    "sg:phone":"+1 608 883 2944",
    "sg:postcode":"53190",
    "sg:province":"WI",
    "sg:tags":[
        "structural",
        "metalwork",
        "sheet",
        "fabrication",
        "mfg"
    ],
    "wof:name":"Scharines Cstm Stl Fabrication",
    "wof:placetype":"venue"
},
  "geometry": {"coordinates":[-88.80776,42.731477],"type":"Point"}
}