{
  "type": "Feature",
  "properties": {
    "addr:full":"2526 E Oregon Trl Janesville WI 53546",
    "addr:housenumber":"2526",
    "addr:postcode":"53546",
    "addr:street":"E Oregon Trl",
    "iso:country":"US",
    "sg:address":"2526 E Oregon Trl",
    "sg:city":"Janesville",
    "sg:classifiers":[
        {
            "category":"Utilities",
            "subcategory":"Telephone",
            "type":"Services"
        },
        {
            "category":"Professional",
            "subcategory":"Business Services",
            "type":"Services"
        }
    ],
    "sg:phone":"+1 608 752 1449",
    "sg:postcode":"53546",
    "sg:province":"WI",
    "sg:tags":[
        "communications"
    ],
    "wof:name":"Chezs Telephone Connectors",
    "wof:placetype":"venue"
},
  "geometry": {"coordinates":[-88.98931399999999,42.627035],"type":"Point"}
}