{
  "type": "Feature",
  "properties": {
    "addr:full":"5810 W Oklahoma Ave Milwaukee WI 53219",
    "addr:housenumber":"5810",
    "addr:postcode":"53219",
    "addr:street":"W Oklahoma Ave",
    "iso:country":"US",
    "sg:address":"5810 W Oklahoma Ave",
    "sg:city":"Milwaukee",
    "sg:classifiers":[
        {
            "category":"Real Estate",
            "subcategory":"Real Estate Agent",
            "type":"Services"
        }
    ],
    "sg:phone":"+1 414 543 5508",
    "sg:postcode":"53219",
    "sg:province":"WI",
    "wof:name":"Fons Real Estate and Insur Co",
    "wof:placetype":"venue"
},
  "geometry": {"coordinates":[-87.98747299999999,42.988489],"type":"Point"}
}