{
  "type": "Feature",
  "properties": {
    "iso:country":"US",
    "sg:address":"708 E Day Ave",
    "sg:city":"Milwaukee",
    "sg:classifiers":[
        {
            "category":"Banks & Credit Unions",
            "subcategory":"Investment Brokerage",
            "type":"Services"
        }
    ],
    "sg:phone":"+1 414 332 5471",
    "sg:postcode":"53217",
    "sg:province":"WI",
    "sg:tags":[
        "trust"
    ],
    "wof:name":"Way Thompson Jr Trust",
    "wof:placetype":"venue"
},
  "geometry": {"coordinates":[-87.90167599999999,43.122277],"type":"Point"}
}