{
  "type": "Feature",
  "properties": {
    "iso:country":"US",
    "sg:address":"3108 Creekview Dr",
    "sg:city":"Middleton",
    "sg:classifiers":[
        {
            "category":"Travel",
            "subcategory":"Campground",
            "type":"Entertainment"
        }
    ],
    "sg:phone":"+1 608 836 7226",
    "sg:postcode":"53562",
    "sg:province":"WI",
    "sg:tags":[
        "camp"
    ],
    "wof:name":"Erringtns Portage Sprtsmns CLB",
    "wof:placetype":"venue"
},
  "geometry": {"coordinates":[-89.48168099999999,43.107162],"type":"Point"}
}