{
  "type": "Feature",
  "properties": {
    "iso:country":"US",
    "sg:address":"707 Co Hwy Bb",
    "sg:city":"Deerfield",
    "sg:classifiers":[
        {
            "category":"Farming",
            "subcategory":"Farm",
            "type":"Manufacturing & Wholesale Goods"
        }
    ],
    "sg:phone":"+1 608 764 5391",
    "sg:postcode":"53531",
    "sg:province":"WI",
    "sg:tags":[
        "crop",
        "general"
    ],
    "wof:name":"Erwin Borter",
    "wof:placetype":"venue"
},
  "geometry": {"coordinates":[-89.059106,43.084537],"type":"Point"}
}