{
  "type": "Feature",
  "properties": {
    "iso:country":"US",
    "sg:address":"3624 S Moorland Rd",
    "sg:city":"New Berlin",
    "sg:classifiers":[
        {
            "category":"Shopping",
            "subcategory":"Florist",
            "type":"Retail Goods"
        }
    ],
    "sg:phone":"+1 262 784 1751",
    "sg:postcode":"53151",
    "sg:province":"WI",
    "sg:tags":[
        "shop",
        "flower"
    ],
    "wof:name":"Seasons 4 Flowers & Gifts",
    "wof:placetype":"venue"
},
  "geometry": {"coordinates":[-88.108261,42.979142],"type":"Point"}
}