{
  "type": "Feature",
  "properties": {
    "iso:country":"US",
    "sg:address":"1810 S Calhoun Rd",
    "sg:city":"New Berlin",
    "sg:classifiers":[
        {
            "category":"Professional",
            "subcategory":"Employment Agencies",
            "type":"Services"
        }
    ],
    "sg:phone":"+1 262 821 3555",
    "sg:postcode":"53151",
    "sg:province":"WI",
    "wof:name":"Financial Headhunters Inc",
    "wof:placetype":"venue"
},
  "geometry": {"coordinates":[-88.127168,43.010067],"type":"Point"}
}