{
  "type": "Feature",
  "properties": {
    "addr:full":"508 Poplar St Hurley WI 54534",
    "addr:housenumber":"508",
    "addr:postcode":"54534",
    "addr:street":"Poplar St",
    "iso:country":"US",
    "sg:address":"508 Poplar St",
    "sg:city":"Hurley",
    "sg:classifiers":[
        {
            "category":"Retail",
            "subcategory":"Repair Shop",
            "type":"Services"
        }
    ],
    "sg:phone":"+1 715 561 3737",
    "sg:postcode":"54534",
    "sg:province":"WI",
    "sg:tags":[
        "electrical"
    ],
    "wof:name":"Electronics Tech",
    "wof:placetype":"venue"
},
  "geometry": {"coordinates":[-90.18764899999999,46.453076],"type":"Point"}
}