{
  "type": "Feature",
  "properties": {
    "iso:country":"US",
    "sg:address":"9221 Ripley Rd",
    "sg:city":"Cambridge",
    "sg:phone":"+1 608 423 3306",
    "sg:postcode":"53523",
    "sg:province":"WI",
    "sg:tags":[
        "farm",
        "corn",
        "soybean"
    ],
    "wof:name":"William Rohloff",
    "wof:placetype":"venue"
},
  "geometry": {"coordinates":[-88.98818199999999,43.005541],"type":"Point"}
}