{
  "type": "Feature",
  "properties": {
    "iso:country":"US",
    "sg:address":"5631 Kellner Rd",
    "sg:city":"Wisconsin Rapids",
    "sg:classifiers":[
        {
            "category":"Freight",
            "type":"Transportation"
        },
        {
            "category":"Building & Trades",
            "subcategory":"Construction",
            "type":"Services"
        }
    ],
    "sg:phone":"+1 715 423 2028",
    "sg:postcode":"54494",
    "sg:province":"WI",
    "sg:tags":[
        "excavating",
        "contractor",
        "local",
        "trucking"
    ],
    "wof:name":"Bohn Trucking & Excavating Inc",
    "wof:placetype":"venue"
},
  "geometry": {"coordinates":[-89.751954,44.37345],"type":"Point"}
}