{
  "type": "Feature",
  "properties": {
    "iso:country":"US",
    "sg:address":"5268 Wolfe Ln",
    "sg:city":"Durand",
    "sg:classifiers":[
        {
            "category":"Farming",
            "subcategory":"Farm",
            "type":"Manufacturing & Wholesale Goods"
        }
    ],
    "sg:phone":"+1 715 672 5150",
    "sg:postcode":"54736",
    "sg:province":"WI",
    "sg:tags":[
        "crop",
        "general"
    ],
    "wof:name":"Martha Wolfe",
    "wof:placetype":"venue"
},
  "geometry": {"coordinates":[-91.899112,44.601094],"type":"Point"}
}