{
  "type": "Feature",
  "properties": {
    "addr:full":"8100 144th Ave Bristol WI 53104",
    "addr:housenumber":"8100",
    "addr:postcode":"53104",
    "addr:street":"144Th Ave",
    "iso:country":"US",
    "sg:address":"8100 144th Ave",
    "sg:city":"Bristol",
    "sg:classifiers":[
        {
            "category":"Retail",
            "subcategory":"Auto Repair",
            "type":"Services"
        }
    ],
    "sg:phone":"+1 262 857 7078",
    "sg:postcode":"53104",
    "sg:province":"WI",
    "sg:tags":[
        "small",
        "engine",
        "machining"
    ],
    "wof:name":"NCM",
    "wof:placetype":"venue"
},
  "geometry": {"coordinates":[-87.98175500000001,42.559516],"type":"Point"}
}