{
  "type": "Feature",
  "properties": {
    "iso:country":"US",
    "sg:address":"701 W State St",
    "sg:city":"Fox Lake",
    "sg:classifiers":[
        {
            "category":"Restaurant",
            "type":"Food & Drink"
        }
    ],
    "sg:menulink":"http://www.allmenus.com/wi/fox-lake/145471-subway/menu/",
    "sg:phone":"+1 920 928 2700",
    "sg:postcode":"53933",
    "sg:province":"WI",
    "sg:tags":[
        "american",
        "sandwich"
    ],
    "wof:name":"Subway",
    "wof:placetype":"venue"
},
  "geometry": {"coordinates":[-88.915344,43.566439],"type":"Point"}
}