{
  "type": "Feature",
  "properties": {
    "addr:full":"2678 S Kinnickinnic Ave Milwaukee WI 53207",
    "addr:housenumber":"2678",
    "addr:postcode":"53207",
    "addr:street":"S Kinnickinnic Ave",
    "iso:country":"US",
    "sg:address":"2678 S Kinnickinnic Ave",
    "sg:city":"Milwaukee",
    "sg:classifiers":[
        {
            "category":"Restaurant",
            "type":"Food & Drink"
        }
    ],
    "sg:menulink":"http://www.allmenus.com/wi/milwaukee/184938-no-1-chinese-restaurant/menu/",
    "sg:phone":"+1 414 482 2218",
    "sg:postcode":"53207",
    "sg:province":"WI",
    "sg:tags":[
        "asian",
        "chinese"
    ],
    "wof:name":"No 1 Chinese Restaurant",
    "wof:placetype":"venue"
},
  "geometry": {"coordinates":[-87.897302,42.996297],"type":"Point"}
}