{
  "type": "Feature",
  "properties": {
    "iso:country":"US",
    "sg:address":"613 Cochrane St",
    "sg:city":"Waupun",
    "sg:classifiers":[
        {
            "category":"Building & Trades",
            "subcategory":"Construction",
            "type":"Services"
        }
    ],
    "sg:phone":"+1 920 324 8564",
    "sg:postcode":"53963",
    "sg:province":"WI",
    "sg:tags":[
        "house"
    ],
    "wof:name":"Marvs Construction",
    "wof:placetype":"venue"
},
  "geometry": {"coordinates":[-88.731174,43.624801],"type":"Point"}
}