{
  "type": "Feature",
  "properties": {
    "iso:country":"US",
    "sg:address":"2845 N Sherman Ave",
    "sg:city":"Madison",
    "sg:classifiers":[
        {
            "category":"Education",
            "subcategory":"Library",
            "type":"Public Place"
        }
    ],
    "sg:phone":"+1 608 246 4547",
    "sg:postcode":"53704",
    "sg:province":"WI",
    "wof:name":"Lakeview Branch Library",
    "wof:placetype":"venue"
},
  "geometry": {"coordinates":[-89.363426,43.130203],"type":"Point"}
}