{
  "type": "Feature",
  "properties": {
    "iso:country":"US",
    "sg:address":"4321 Lincoln Ave",
    "sg:city":"Stratford",
    "sg:classifiers":[
        {
            "category":"Manufacturing",
            "subcategory":"Building Materials",
            "type":"Manufacturing & Wholesale Goods"
        }
    ],
    "sg:phone":"+1 715 223 2778",
    "sg:postcode":"54484",
    "sg:province":"WI",
    "sg:tags":[
        "mfg",
        "wood",
        "kitchen",
        "cabinet"
    ],
    "wof:name":"Alan Jicinsky",
    "wof:placetype":"venue"
},
  "geometry": {"coordinates":[-90.19886200000001,44.827958],"type":"Point"}
}