{
  "type": "Feature",
  "properties": {
    "addr:full":"3185 Gateway Rd Brookfield WI 53045",
    "addr:housenumber":"3185",
    "addr:postcode":"53045",
    "addr:street":"Gateway Rd",
    "iso:country":"US",
    "sg:address":"3185 Gateway Rd",
    "sg:city":"Brookfield",
    "sg:classifiers":[
        {
            "category":"Building & Trades",
            "subcategory":"Plumbing",
            "type":"Services"
        }
    ],
    "sg:phone":"+1 262 783 3360",
    "sg:postcode":"53045",
    "sg:province":"WI",
    "sg:tags":[
        "contractor"
    ],
    "wof:name":"York International Corporation",
    "wof:placetype":"venue"
},
  "geometry": {"coordinates":[-88.18077599999999,43.077551],"type":"Point"}
}