{
  "type": "Feature",
  "properties": {
    "iso:country":"US",
    "sg:address":"445 2nd Ave N",
    "sg:city":"Onalaska",
    "sg:classifiers":[
        {
            "category":"Wholesale",
            "subcategory":"Machinery & Supplies",
            "type":"Manufacturing & Wholesale Goods"
        }
    ],
    "sg:phone":"+1 608 781 1751",
    "sg:postcode":"54650",
    "sg:province":"WI",
    "sg:tags":[
        "equipment",
        "industrial"
    ],
    "wof:name":"Superior Elevator Systems Inc",
    "wof:placetype":"venue"
},
  "geometry": {"coordinates":[-91.235489,43.885033],"type":"Point"}
}