{
  "type": "Feature",
  "properties": {
    "iso:country":"US",
    "sg:address":"2709 270th St",
    "sg:city":"Elmwood",
    "sg:classifiers":[
        {
            "category":"Freight",
            "type":"Transportation"
        },
        {
            "category":"Real Estate",
            "subcategory":"Real Estate Agent",
            "type":"Services"
        },
        {
            "category":"Professional",
            "subcategory":"Business Services",
            "type":"Services"
        }
    ],
    "sg:phone":"+1 715 664 8331",
    "sg:postcode":"54740",
    "sg:province":"WI",
    "sg:tags":[
        "fixed",
        "inspection",
        "motor",
        "facility"
    ],
    "wof:name":"A Plus Home Inspection",
    "wof:placetype":"venue"
},
  "geometry": {"coordinates":[-92.02464999999999,44.780443],"type":"Point"}
}