{
  "type": "Feature",
  "properties": {
    "addr:full":"860 2nd Ln Coloma WI 54930",
    "addr:housenumber":"860",
    "addr:postcode":"54930",
    "addr:street":"2Nd Ln",
    "iso:country":"US",
    "sg:address":"860 2nd Ln",
    "sg:city":"Coloma",
    "sg:classifiers":[
        {
            "category":"Professional",
            "subcategory":"Management & Consulting",
            "type":"Services"
        }
    ],
    "sg:phone":"+1 715 228 2330",
    "sg:postcode":"54930",
    "sg:province":"WI",
    "sg:tags":[
        "business"
    ],
    "wof:name":"Gmn Services",
    "wof:placetype":"venue"
},
  "geometry": {"coordinates":[-89.56748399999999,44.005618],"type":"Point"}
}