{
  "type": "Feature",
  "properties": {
    "addr:full":"3116 Preston Rd Eau Claire WI 54703",
    "addr:housenumber":"3116",
    "addr:postcode":"54703",
    "addr:street":"Preston Rd",
    "iso:country":"US",
    "sg:address":"3116 Preston Rd",
    "sg:city":"Eau Claire",
    "sg:classifiers":[
        {
            "category":"Freight",
            "type":"Transportation"
        }
    ],
    "sg:phone":"+1 715 835 5510",
    "sg:postcode":"54703",
    "sg:province":"WI",
    "sg:tags":[
        "special"
    ],
    "wof:name":"Whytes Warehouse & Storage",
    "wof:placetype":"venue"
},
  "geometry": {"coordinates":[-91.548832,44.831344],"type":"Point"}
}