{
  "type": "Feature",
  "properties": {
    "iso:country":"US",
    "sg:address":"1025 S Main St",
    "sg:city":"River Falls",
    "sg:classifiers":[
        {
            "category":"Restaurant",
            "type":"Food & Drink"
        }
    ],
    "sg:phone":"+1 715 426 0333",
    "sg:postcode":"54022",
    "sg:province":"WI",
    "wof:name":"China Moon",
    "wof:placetype":"venue"
},
  "geometry": {"coordinates":[-92.629417,44.847701],"type":"Point"}
}