{
  "type": "Feature",
  "properties": {
    "addr:full":"1917 S 60th St Milwaukee WI 53219",
    "addr:housenumber":"1917",
    "addr:postcode":"53219",
    "addr:street":"S 60Th St",
    "iso:country":"US",
    "sg:address":"1917 S 60th St",
    "sg:city":"Milwaukee",
    "sg:classifiers":[
        {
            "category":"Social Services",
            "subcategory":"Job Training",
            "type":"Services"
        },
        {
            "category":"Retail",
            "subcategory":"Repair Shop",
            "type":"Services"
        },
        {
            "category":"Wholesale",
            "subcategory":"Machinery & Supplies",
            "type":"Manufacturing & Wholesale Goods"
        },
        {
            "category":"Retail",
            "subcategory":"Laundry & Dry Cleaning",
            "type":"Services"
        },
        {
            "category":"Home & Garden",
            "subcategory":"Household Appliances",
            "type":"Retail Goods"
        }
    ],
    "sg:phone":"+1 414 321 3636",
    "sg:postcode":"53219",
    "sg:province":"WI",
    "sg:tags":[
        "coin",
        "commercial",
        "equipment",
        "dryer",
        "dryers-parts",
        "operated",
        "washer",
        "laundromat",
        "equipment-repairing"
    ],
    "sg:website":"http://www.badgerlaundrymachinery.com",
    "wof:name":"Badger Laundry Machinery",
    "wof:placetype":"venue"
},
  "geometry": {"coordinates":[-87.987399,43.009915],"type":"Point"}
}