{
  "type": "Feature",
  "properties": {
    "iso:country":"US",
    "sg:address":"3227 State Hwy 16",
    "sg:city":"La Crosse",
    "sg:classifiers":[
        {
            "category":"Insurance",
            "subcategory":"Insurance Agent",
            "type":"Services"
        }
    ],
    "sg:phone":"+1 608 782 1970",
    "sg:postcode":"54601",
    "sg:province":"WI",
    "sg:tags":[
        "advisory",
        "investment"
    ],
    "wof:name":"Mayer Financial Group",
    "wof:placetype":"venue"
},
  "geometry": {"coordinates":[-91.255989,43.807705],"type":"Point"}
}