{
  "type": "Feature",
  "properties": {
    "iso:country":"US",
    "sg:address":"3709 Homer Rd",
    "sg:city":"Boscobel",
    "sg:classifiers":[
        {
            "category":"Banks & Credit Unions",
            "subcategory":"Financial Services",
            "type":"Services"
        }
    ],
    "sg:phone":"+1 608 375 2205",
    "sg:postcode":"53805",
    "sg:province":"WI",
    "sg:tags":[
        "trust",
        "management"
    ],
    "wof:name":"Daniel Giles Swenson Trust",
    "wof:placetype":"venue"
},
  "geometry": {"coordinates":[-90.60884299999999,43.077827],"type":"Point"}
}