{
  "type": "Feature",
  "properties": {
    "iso:country":"US",
    "sg:address":"819 Park Ave",
    "sg:city":"Racine",
    "sg:classifiers":[
        {
            "category":"Organizations",
            "subcategory":"Religious Organization",
            "type":"Services"
        }
    ],
    "sg:phone":"+1 262 634 0884",
    "sg:postcode":"53403",
    "sg:province":"WI",
    "wof:name":"Racine Dominicans",
    "wof:placetype":"venue"
},
  "geometry": {"coordinates":[-87.785908,42.723248],"type":"Point"}
}