{
  "type": "Feature",
  "properties": {
    "iso:country":"US",
    "sg:address":"1800 N Swan Blvd",
    "sg:city":"Milwaukee",
    "sg:classifiers":[
        {
            "category":"Recreation",
            "type":"Entertainment"
        }
    ],
    "sg:phone":"+1 414 476 5199",
    "sg:postcode":"53226",
    "sg:province":"WI",
    "sg:tags":[
        "pool",
        "swimming"
    ],
    "wof:name":"Hoyt Outdoor Pool",
    "wof:placetype":"venue"
},
  "geometry": {"coordinates":[-88.033913,43.051693],"type":"Point"}
}