{
  "type": "Feature",
  "properties": {
    "iso:country":"US",
    "sg:address":"8631 Hetze Rd",
    "sg:city":"Milladore",
    "sg:classifiers":[
        {
            "category":"Farming",
            "subcategory":"Dairy Farm",
            "type":"Manufacturing & Wholesale Goods"
        }
    ],
    "sg:phone":"+1 715 457 6475",
    "sg:postcode":"54454",
    "sg:province":"WI",
    "wof:name":"E Hetze",
    "wof:placetype":"venue"
},
  "geometry": {"coordinates":[-89.864884,44.560131],"type":"Point"}
}