{
  "type": "Feature",
  "properties": {
    "addr:full":"2321 W Wisconsin Ave Appleton WI 54914",
    "addr:housenumber":"2321",
    "addr:postcode":"54914",
    "addr:street":"W Wisconsin Ave",
    "iso:country":"US",
    "sg:address":"2321 W Wisconsin Ave",
    "sg:city":"Appleton",
    "sg:classifiers":[
        {
            "category":"Retail",
            "subcategory":"Veterinary Services",
            "type":"Services"
        }
    ],
    "sg:phone":"+1 920 739 4122",
    "sg:postcode":"54914",
    "sg:province":"WI",
    "sg:tags":[
        "veterinarian"
    ],
    "wof:name":"All Creatures Animal Hospital",
    "wof:placetype":"venue"
},
  "geometry": {"coordinates":[-88.44321100000001,44.273166],"type":"Point"}
}