{
  "type": "Feature",
  "properties": {
    "iso:country":"US",
    "sg:address":"208 Benton St",
    "sg:city":"Cambridge",
    "sg:classifiers":[
        {
            "category":"Government",
            "subcategory":"Office",
            "type":"Public Place"
        }
    ],
    "sg:phone":"+1 608 423 7266",
    "sg:postcode":"53523",
    "sg:province":"WI",
    "sg:tags":[
        "village"
    ],
    "wof:name":"Rockdale Village Office",
    "wof:placetype":"venue"
},
  "geometry": {"coordinates":[-89.034876,42.973162],"type":"Point"}
}