{
  "type": "Feature",
  "properties": {
    "addr:full":"5510 Tri County Rd Whitewater WI 53190",
    "addr:housenumber":"5510",
    "addr:postcode":"53190",
    "addr:street":"Tri County Rd",
    "iso:country":"US",
    "sg:address":"5510 Tri County Rd",
    "sg:city":"Whitewater",
    "sg:classifiers":[
        {
            "category":"Real Estate",
            "subcategory":"Real Estate Operator",
            "type":"Services"
        }
    ],
    "sg:phone":"+1 262 473 6836",
    "sg:postcode":"53190",
    "sg:province":"WI",
    "sg:tags":[
        "property",
        "lessor"
    ],
    "wof:name":"Dewey Barrett",
    "wof:placetype":"venue"
},
  "geometry": {"coordinates":[-88.806922,42.843525],"type":"Point"}
}