{
  "type": "Feature",
  "properties": {
    "iso:country":"US",
    "sg:address":"820 N Main St",
    "sg:city":"Viroqua",
    "sg:classifiers":[
        {
            "category":"Health Services",
            "subcategory":"Chiropractor",
            "type":"Services"
        }
    ],
    "sg:phone":"+1 608 637 7177",
    "sg:postcode":"54665",
    "sg:province":"WI",
    "sg:tags":[
        "clinic"
    ],
    "wof:name":"Bjerke John A DC",
    "wof:placetype":"venue"
},
  "geometry": {"coordinates":[-90.888941,43.563533],"type":"Point"}
}