{
  "type": "Feature",
  "properties": {
    "iso:country":"US",
    "sg:address":"456 River Bluff Cir",
    "sg:city":"Oconomowoc",
    "sg:classifiers":[
        {
            "category":"Professional",
            "subcategory":"Accounting & Tax Preparation",
            "type":"Services"
        }
    ],
    "sg:phone":"+1 262 569 5917",
    "sg:postcode":"53066",
    "sg:province":"WI",
    "wof:name":"Ceridian",
    "wof:placetype":"venue"
},
  "geometry": {"coordinates":[-88.523203,43.109503],"type":"Point"}
}