{
  "type": "Feature",
  "properties": {
    "iso:country":"US",
    "sg:address":"3701 E Calumet St",
    "sg:city":"Appleton",
    "sg:classifiers":[
        {
            "category":"Banks & Credit Unions",
            "subcategory":"Bank",
            "type":"Services"
        }
    ],
    "sg:phone":"+1 920 731 2200",
    "sg:postcode":"54915",
    "sg:province":"WI",
    "wof:name":"American National Bank",
    "wof:placetype":"venue"
},
  "geometry": {"coordinates":[-88.35129999999999,44.243767],"type":"Point"}
}