{
  "type": "Feature",
  "properties": {
    "iso:country":"US",
    "sg:address":"1200 W Northland Ave",
    "sg:city":"Appleton",
    "sg:classifiers":[
        {
            "category":"Banks & Credit Unions",
            "subcategory":"Bank",
            "type":"Services"
        }
    ],
    "sg:phone":"+1 920 734 0110",
    "sg:postcode":"54914",
    "sg:province":"WI",
    "sg:tags":[
        "federal",
        "savings"
    ],
    "wof:name":"North Shore Bank F S B",
    "wof:placetype":"venue"
},
  "geometry": {"coordinates":[-88.424601,44.287493],"type":"Point"}
}