{
  "type": "Feature",
  "properties": {
    "iso:country":"US",
    "sg:address":"3394 Co Hwy Hh",
    "sg:city":"Dickeyville",
    "sg:classifiers":[
        {
            "category":"Farming",
            "subcategory":"Farm & Veterinary Services",
            "type":"Manufacturing & Wholesale Goods"
        }
    ],
    "sg:phone":"+1 608 568 3414",
    "sg:postcode":"53807",
    "sg:province":"WI",
    "sg:tags":[
        "aerial",
        "applicator"
    ],
    "wof:name":"Fransyl Equipment Co Inc",
    "wof:placetype":"venue"
},
  "geometry": {"coordinates":[-90.586058,42.615349],"type":"Point"}
}