{
  "type": "Feature",
  "properties": {
    "iso:country":"US",
    "sg:address":"5901 W Washington Blvd",
    "sg:city":"Milwaukee",
    "sg:classifiers":[
        {
            "category":"Building & Trades",
            "subcategory":"Construction",
            "type":"Services"
        }
    ],
    "sg:phone":"+1 414 453 6610",
    "sg:postcode":"53208",
    "sg:province":"WI",
    "sg:tags":[
        "nonresidential"
    ],
    "wof:name":"Landtek of Wisconsin LLC",
    "wof:placetype":"venue"
},
  "geometry": {"coordinates":[-87.987564,43.052966],"type":"Point"}
}