{
  "type": "Feature",
  "properties": {
    "iso:country":"US",
    "sg:address":"1019 Superior St",
    "sg:city":"Sturgeon Bay",
    "sg:classifiers":[
        {
            "category":"Home & Garden",
            "subcategory":"Home Furnishings",
            "type":"Retail Goods"
        }
    ],
    "sg:phone":"+1 920 743 3498",
    "sg:postcode":"54235",
    "sg:province":"WI",
    "sg:tags":[
        "curtain",
        "made",
        "drapery"
    ],
    "wof:name":"Windows & Beyond",
    "wof:placetype":"venue"
},
  "geometry": {"coordinates":[-87.36657700000001,44.830079],"type":"Point"}
}