{
  "type": "Feature",
  "properties": {
    "addr:full":"324 N Waterville Rd Oconomowoc WI 53066",
    "addr:housenumber":"324",
    "addr:postcode":"53066",
    "addr:street":"N Waterville Rd",
    "iso:country":"US",
    "sg:address":"324 N Waterville Rd",
    "sg:city":"Oconomowoc",
    "sg:classifiers":[
        {
            "category":"Building & Trades",
            "subcategory":"Construction",
            "type":"Services"
        }
    ],
    "sg:phone":"+1 414 531 9709",
    "sg:postcode":"53066",
    "sg:province":"WI",
    "sg:tags":[
        "layer",
        "carpet"
    ],
    "wof:name":"Jason M Krause Carpet Svc",
    "wof:placetype":"venue"
},
  "geometry": {"coordinates":[-88.43194099999999,43.036492],"type":"Point"}
}