{
  "type": "Feature",
  "properties": {
    "iso:country":"US",
    "sg:address":"2326 Illinois St",
    "sg:city":"Racine",
    "sg:classifiers":[
        {
            "category":"Retail",
            "subcategory":"Animal Services",
            "type":"Services"
        }
    ],
    "sg:phone":"+1 262 554 1237",
    "sg:postcode":"53405",
    "sg:province":"WI",
    "sg:tags":[
        "pet",
        "grooming",
        "washing"
    ],
    "wof:name":"A-1 Grooming By Barbie",
    "wof:placetype":"venue"
},
  "geometry": {"coordinates":[-87.83341299999999,42.700787],"type":"Point"}
}