{
  "type": "Feature",
  "properties": {
    "iso:country":"US",
    "sg:address":"4221 Gunderson Rd",
    "sg:city":"Waterford",
    "sg:classifiers":[
        {
            "category":"Shopping",
            "subcategory":"Computers & Home Electronics",
            "type":"Retail Goods"
        }
    ],
    "sg:phone":"+1 262 534 9824",
    "sg:postcode":"53185",
    "sg:province":"WI",
    "wof:name":"De Systems",
    "wof:placetype":"venue"
},
  "geometry": {"coordinates":[-88.150092,42.778529],"type":"Point"}
}