{
  "type": "Feature",
  "properties": {
    "iso:country":"US",
    "sg:address":"4260 S 76th St",
    "sg:city":"Milwaukee",
    "sg:classifiers":[
        {
            "category":"Real Estate",
            "subcategory":"Real Estate Agent",
            "type":"Services"
        }
    ],
    "sg:phone":"+1 414 545 3717",
    "sg:postcode":"53220",
    "sg:province":"WI",
    "wof:name":"Haritage Property Invstmnt",
    "wof:placetype":"venue"
},
  "geometry": {"coordinates":[-88.008015,42.969332],"type":"Point"}
}