{
  "type": "Feature",
  "properties": {
    "addr:full":"1376 Fern Dr Wisconsin Dells WI 53965",
    "addr:housenumber":"1376",
    "addr:postcode":"53965",
    "addr:street":"Fern Dr",
    "iso:country":"US",
    "sg:address":"1376 Fern Dr",
    "sg:city":"Wisconsin Dells",
    "sg:classifiers":[
        {
            "category":"Professional",
            "subcategory":"Business Services",
            "type":"Services"
        }
    ],
    "sg:phone":"+1 608 253 5610",
    "sg:postcode":"53965",
    "sg:province":"WI",
    "wof:name":"Recovery Specialists",
    "wof:placetype":"venue"
},
  "geometry": {"coordinates":[-89.830367,43.795546],"type":"Point"}
}