{
  "type": "Feature",
  "properties": {
    "iso:country":"US",
    "sg:address":"6436 Riverdale Ln",
    "sg:city":"Greendale",
    "sg:classifiers":[
        {
            "category":"Education",
            "subcategory":"Special Training",
            "type":"Public Place"
        }
    ],
    "sg:phone":"+1 414 423 0074",
    "sg:postcode":"53129",
    "sg:province":"WI",
    "sg:tags":[
        "educational"
    ],
    "wof:name":"Beyond Words Inc",
    "wof:placetype":"venue"
},
  "geometry": {"coordinates":[-87.990707,42.929688],"type":"Point"}
}