{
  "type": "Feature",
  "properties": {
    "iso:country":"US",
    "sg:address":"9324 W Allyn St",
    "sg:city":"Milwaukee",
    "sg:classifiers":[
        {
            "category":"Manufacturing",
            "subcategory":"Electronics",
            "type":"Manufacturing & Wholesale Goods"
        }
    ],
    "sg:phone":"+1 414 365 8528",
    "sg:postcode":"53224",
    "sg:province":"WI",
    "sg:tags":[
        "electronic",
        "component",
        "mfg"
    ],
    "wof:name":"E Troniks",
    "wof:placetype":"venue"
},
  "geometry": {"coordinates":[-88.025595,43.182801],"type":"Point"}
}