{
  "type": "Feature",
  "properties": {
    "iso:country":"US",
    "sg:address":"15987 Hudson Rd",
    "sg:city":"Camp Douglas",
    "sg:classifiers":[
        {
            "category":"Shopping",
            "subcategory":"Used Merchandise",
            "type":"Retail Goods"
        }
    ],
    "sg:phone":"+1 608 427 6728",
    "sg:postcode":"54618",
    "sg:province":"WI",
    "wof:name":"Mill Bluff Antiques",
    "wof:placetype":"venue"
},
  "geometry": {"coordinates":[-90.33723999999999,43.936711],"type":"Point"}
}