{
  "type": "Feature",
  "properties": {
    "iso:country":"US",
    "sg:address":"2263 Maple Dr",
    "sg:city":"St Croix Falls",
    "sg:classifiers":[
        {
            "category":"Travel",
            "subcategory":"Hotels & Motels",
            "type":"Entertainment"
        }
    ],
    "sg:phone":"+1 715 483 3986",
    "sg:postcode":"54024",
    "sg:province":"WI",
    "sg:tags":[
        "breakfast",
        "operation",
        "bed",
        "accommodation"
    ],
    "wof:name":"Wissahickon Farms Country Inn",
    "wof:placetype":"venue"
},
  "geometry": {"coordinates":[-92.62079199999999,45.40541],"type":"Point"}
}