{
  "type": "Feature",
  "properties": {
    "iso:country":"US",
    "sg:address":"6538 W Fond du Lac Ave",
    "sg:city":"Milwaukee",
    "sg:classifiers":[
        {
            "category":"Personal",
            "subcategory":"Beauty Salon",
            "type":"Services"
        }
    ],
    "sg:phone":"+1 414 462 5622",
    "sg:postcode":"53218",
    "sg:province":"WI",
    "wof:name":"Unique Stylez",
    "wof:placetype":"venue"
},
  "geometry": {"coordinates":[-87.99255,43.102624],"type":"Point"}
}