{
  "type": "Feature",
  "properties": {
    "iso:country":"US",
    "sg:address":"15040 Shemak Rd",
    "sg:city":"Muscoda",
    "sg:classifiers":[
        {
            "category":"Bars & Pubs",
            "type":"Food & Drink"
        }
    ],
    "sg:phone":"+1 608 943 8525",
    "sg:postcode":"53573",
    "sg:province":"WI",
    "sg:tags":[
        "drinking"
    ],
    "wof:name":"Castle Rock Inn",
    "wof:placetype":"venue"
},
  "geometry": {"coordinates":[-90.49931,43.056628],"type":"Point"}
}