{
  "type": "Feature",
  "properties": {
    "iso:country":"US",
    "sg:address":"304 8th Ave E",
    "sg:city":"Osceola",
    "sg:classifiers":[
        {
            "category":"Health Services",
            "subcategory":"Nursing And Care Facility",
            "type":"Services"
        }
    ],
    "sg:phone":"+1 715 294 1600",
    "sg:postcode":"54020",
    "sg:province":"WI",
    "wof:name":"Royal Oaks Inc",
    "wof:placetype":"venue"
},
  "geometry": {"coordinates":[-92.69748,45.325208],"type":"Point"}
}