{
  "type": "Feature",
  "properties": {
    "iso:country":"US",
    "sg:address":"9215 Ripley Rd",
    "sg:city":"Cambridge",
    "sg:classifiers":[
        {
            "category":"Professional",
            "type":"Services"
        }
    ],
    "sg:phone":"+1 608 423 3973",
    "sg:postcode":"53523",
    "sg:province":"WI",
    "sg:tags":[
        "establishment"
    ],
    "wof:name":"Iskra Ae",
    "wof:placetype":"venue"
},
  "geometry": {"coordinates":[-88.988249,43.005593],"type":"Point"}
}