{
  "type": "Feature",
  "properties": {
    "iso:country":"US",
    "sg:address":"1701 S 41st St",
    "sg:city":"Manitowoc",
    "sg:classifiers":[
        {
            "category":"Retail",
            "subcategory":"Auto Rental",
            "type":"Services"
        }
    ],
    "sg:phone":"+1 920 683 3079",
    "sg:postcode":"54220",
    "sg:province":"WI",
    "sg:tags":[
        "trailer"
    ],
    "wof:name":"Ryder",
    "wof:placetype":"venue"
},
  "geometry": {"coordinates":[-87.699258,44.080355],"type":"Point"}
}