{
  "type": "Feature",
  "properties": {
    "addr:full":"3058 S 13th St Milwaukee WI 53215",
    "addr:housenumber":"3058",
    "addr:postcode":"53215",
    "addr:street":"S 13Th St",
    "iso:country":"US",
    "sg:address":"3058 S 13th St",
    "sg:city":"Milwaukee",
    "sg:classifiers":[
        {
            "category":"Shopping",
            "type":"Retail Goods"
        }
    ],
    "sg:phone":"+1 414 643 5775",
    "sg:postcode":"53215",
    "sg:province":"WI",
    "sg:tags":[
        "merchandise"
    ],
    "wof:name":"Bobs OK Coins",
    "wof:placetype":"venue"
},
  "geometry": {"coordinates":[-87.928701,42.989362],"type":"Point"}
}