{
  "type": "Feature",
  "properties": {
    "iso:country":"US",
    "sg:address":"1225 Sundt Ln",
    "sg:city":"Stoughton",
    "sg:classifiers":[
        {
            "category":"Banks & Credit Unions",
            "subcategory":"Financial Services",
            "type":"Services"
        }
    ],
    "sg:phone":"+1 608 873 3788",
    "sg:postcode":"53589",
    "sg:province":"WI",
    "sg:tags":[
        "investor"
    ],
    "wof:name":"Sleyter Investments LLC",
    "wof:placetype":"venue"
},
  "geometry": {"coordinates":[-89.23836,42.928187],"type":"Point"}
}