{
  "type": "Feature",
  "properties": {
    "iso:country":"US",
    "sg:address":"6199 Belgium Ridge Rd",
    "sg:city":"Viroqua",
    "sg:classifiers":[
        {
            "category":"Farming",
            "subcategory":"Farm",
            "type":"Manufacturing & Wholesale Goods"
        }
    ],
    "sg:phone":"+1 608 637 3079",
    "sg:postcode":"54665",
    "sg:province":"WI",
    "sg:tags":[
        "crop",
        "general"
    ],
    "wof:name":"Twin Valley Farms LLC",
    "wof:placetype":"venue"
},
  "geometry": {"coordinates":[-90.952119,43.531611],"type":"Point"}
}