{
  "type": "Feature",
  "properties": {
    "iso:country":"US",
    "sg:address":"4771 17th Dr",
    "sg:city":"Wautoma",
    "sg:classifiers":[
        {
            "category":"Building & Trades",
            "subcategory":"Construction",
            "type":"Services"
        }
    ],
    "sg:phone":"+1 920 787 4040",
    "sg:postcode":"54982",
    "sg:province":"WI",
    "sg:tags":[
        "contractor"
    ],
    "wof:name":"Donald Mancl Construction",
    "wof:placetype":"venue"
},
  "geometry": {"coordinates":[-89.277359,44.149007],"type":"Point"}
}