{
  "type": "Feature",
  "properties": {
    "iso:country":"US",
    "sg:address":"1500 Wisconsin Dells Pkwy N",
    "sg:city":"Wisconsin Dells",
    "sg:classifiers":[
        {
            "category":"Recreation",
            "type":"Entertainment"
        }
    ],
    "sg:phone":"+1 608 254 5540",
    "sg:postcode":"53965",
    "sg:province":"WI",
    "sg:tags":[
        "parks"
    ],
    "wof:name":"Tim Bavati Wild Life Park",
    "wof:placetype":"venue"
},
  "geometry": {"coordinates":[-89.79140700000001,43.606495],"type":"Point"}
}