{
  "type": "Feature",
  "properties": {
    "addr:full":"8535 S Whitney Dr Oak Creek WI 53154",
    "addr:housenumber":"8535",
    "addr:postcode":"53154",
    "addr:street":"S Whitney Dr",
    "iso:country":"US",
    "sg:address":"8535 S Whitney Dr",
    "sg:city":"Oak Creek",
    "sg:classifiers":[
        {
            "category":"Professional",
            "type":"Services"
        }
    ],
    "sg:phone":"+1 414 761 9866",
    "sg:postcode":"53154",
    "sg:province":"WI",
    "wof:name":"Muse Inc",
    "wof:placetype":"venue"
},
  "geometry": {"coordinates":[-87.942333,42.890208],"type":"Point"}
}