{
  "type": "Feature",
  "properties": {
    "iso:country":"US",
    "sg:address":"1713 Oak Leaf Dr",
    "sg:city":"Green Bay",
    "sg:classifiers":[
        {
            "category":"Shopping",
            "subcategory":"Clothing, Apparel, & Fashions",
            "type":"Retail Goods"
        }
    ],
    "sg:phone":"+1 920 499 5260",
    "sg:postcode":"54304",
    "sg:province":"WI",
    "sg:tags":[
        "shop",
        "bridal"
    ],
    "wof:name":"Bridal Classics",
    "wof:placetype":"venue"
},
  "geometry": {"coordinates":[-88.088007,44.513223],"type":"Point"}
}