{
  "type": "Feature",
  "properties": {
    "addr:full":"813 Ela Ave Waterford WI 53185",
    "addr:housenumber":"813",
    "addr:postcode":"53185",
    "addr:street":"Ela Ave",
    "iso:country":"US",
    "sg:address":"813 Ela Ave",
    "sg:city":"Waterford",
    "sg:classifiers":[
        {
            "category":"Manufacturing",
            "subcategory":"Tools & Machinery",
            "type":"Manufacturing & Wholesale Goods"
        }
    ],
    "sg:phone":"+1 262 534 2787",
    "sg:postcode":"53185",
    "sg:province":"WI",
    "sg:tags":[
        "physician",
        "surgeon"
    ],
    "wof:name":"CML Inc",
    "wof:placetype":"venue"
},
  "geometry": {"coordinates":[-88.228168,42.751392],"type":"Point"}
}