{
  "type": "Feature",
  "properties": {
    "iso:country":"US",
    "sg:address":"2611 12th St S",
    "sg:city":"Wisconsin Rapids",
    "sg:classifiers":[
        {
            "category":"Government",
            "subcategory":"Office",
            "type":"Public Place"
        }
    ],
    "sg:phone":"+1 715 384 5555",
    "sg:postcode":"54494",
    "sg:province":"WI",
    "wof:name":"Crisis Intervention & Referral",
    "wof:placetype":"venue"
},
  "geometry": {"coordinates":[-89.811809,44.371223],"type":"Point"}
}