{
  "type": "Feature",
  "properties": {
    "iso:country":"US",
    "sg:address":"480 Broadway St",
    "sg:city":"Prairie Du Sac",
    "sg:classifiers":[
        {
            "category":"Health Services",
            "subcategory":"Doctor",
            "type":"Services"
        }
    ],
    "sg:phone":"+1 608 643 7924",
    "sg:postcode":"53578",
    "sg:province":"WI",
    "sg:tags":[
        "physician",
        "surgeon"
    ],
    "wof:name":"Matthew P Grade MD",
    "wof:placetype":"venue"
},
  "geometry": {"coordinates":[-89.724364,43.28958],"type":"Point"}
}