{
  "type": "Feature",
  "properties": {
    "iso:country":"US",
    "sg:address":"7604 Forest Ave",
    "sg:city":"Fond Du Lac",
    "sg:classifiers":[
        {
            "category":"Manufacturing",
            "subcategory":"Retail Goods",
            "type":"Manufacturing & Wholesale Goods"
        }
    ],
    "sg:phone":"+1 920 921 6456",
    "sg:postcode":"54937",
    "sg:province":"WI",
    "sg:tags":[
        "floral",
        "mfg",
        "arrangement"
    ],
    "wof:name":"Craft & Floral",
    "wof:placetype":"venue"
},
  "geometry": {"coordinates":[-88.539801,43.777302],"type":"Point"}
}