{
  "type": "Feature",
  "properties": {
    "iso:country":"US",
    "sg:address":"501 S Nicolet Rd",
    "sg:city":"Appleton",
    "sg:classifiers":[
        {
            "category":"Wholesale",
            "subcategory":"Stationery",
            "type":"Manufacturing & Wholesale Goods"
        }
    ],
    "sg:phone":"+1 920 993 1630",
    "sg:postcode":"54914",
    "sg:province":"WI",
    "sg:tags":[
        "folder",
        "file",
        "custom"
    ],
    "wof:name":"Office Mates 5",
    "wof:placetype":"venue"
},
  "geometry": {"coordinates":[-88.469146,44.257923],"type":"Point"}
}