{
  "type": "Feature",
  "properties": {
    "iso:country":"US",
    "sg:address":"739 S 108th St",
    "sg:city":"Milwaukee",
    "sg:classifiers":[
        {
            "category":"Education",
            "subcategory":"Special Training",
            "type":"Public Place"
        }
    ],
    "sg:phone":"+1 414 302 5050",
    "sg:postcode":"53214",
    "sg:province":"WI",
    "wof:name":"Bartending School Wisconsin",
    "wof:placetype":"venue"
},
  "geometry": {"coordinates":[-88.04719900000001,43.022243],"type":"Point"}
}