{
  "type": "Feature",
  "properties": {
    "iso:country":"US",
    "sg:address":"11902 560th Ave",
    "sg:city":"Prescott",
    "sg:classifiers":[
        {
            "category":"Professional",
            "subcategory":"Advertising",
            "type":"Services"
        }
    ],
    "sg:phone":"+1 715 262 4291",
    "sg:postcode":"54021",
    "sg:province":"WI",
    "sg:tags":[
        "distribution"
    ],
    "wof:name":"Big Bull's Boomland",
    "wof:placetype":"venue"
},
  "geometry": {"coordinates":[-92.731967,44.743393],"type":"Point"}
}