{
  "type": "Feature",
  "properties": {
    "iso:country":"US",
    "sg:address":"7493 Ferdon Rd",
    "sg:city":"New Lisbon",
    "sg:classifiers":[
        {
            "category":"Airport",
            "type":"Transportation"
        }
    ],
    "sg:phone":"+1 608 562 9961",
    "sg:postcode":"53950",
    "sg:province":"WI",
    "wof:name":"Mauston New Lisbon Union Arprt",
    "wof:placetype":"venue"
},
  "geometry": {"coordinates":[-90.142285,43.843912],"type":"Point"}
}