{
  "type": "Feature",
  "properties": {
    "addr:full":"7595 Otten Ln Kewaskum WI 53040",
    "addr:housenumber":"7595",
    "addr:postcode":"53040",
    "addr:street":"Otten Ln",
    "iso:country":"US",
    "sg:address":"7595 Otten Ln",
    "sg:city":"Kewaskum",
    "sg:classifiers":[
        {
            "category":"Wholesale",
            "subcategory":"Scrap",
            "type":"Manufacturing & Wholesale Goods"
        }
    ],
    "sg:phone":"+1 262 338 3352",
    "sg:postcode":"53040",
    "sg:province":"WI",
    "sg:tags":[
        "recycling",
        "center"
    ],
    "wof:name":"Green Man Technologies-Wi Inc",
    "wof:placetype":"venue"
},
  "geometry": {"coordinates":[-88.21017000000001,43.465993],"type":"Point"}
}