{
  "type": "Feature",
  "properties": {
    "iso:country":"US",
    "sg:address":"21 N Brown St",
    "sg:city":"Rhinelander",
    "sg:classifiers":[
        {
            "category":"Real Estate",
            "subcategory":"Real Estate Services",
            "type":"Services"
        }
    ],
    "sg:phone":"+1 715 369 3934",
    "sg:postcode":"54501",
    "sg:province":"WI",
    "sg:tags":[
        "company",
        "abstract",
        "title"
    ],
    "wof:name":"Shoreline Title Services Inc",
    "wof:placetype":"venue"
},
  "geometry": {"coordinates":[-89.412834,45.63875],"type":"Point"}
}