{
  "type": "Feature",
  "properties": {
    "iso:country":"US",
    "sg:address":"546 4th St N",
    "sg:city":"Hudson",
    "sg:classifiers":[
        {
            "category":"Education",
            "subcategory":"Special Training",
            "type":"Public Place"
        }
    ],
    "sg:phone":"+1 715 386 2105",
    "sg:postcode":"54016",
    "sg:province":"WI",
    "wof:name":"Kindermusik",
    "wof:placetype":"venue"
},
  "geometry": {"coordinates":[-92.7588,44.995682],"type":"Point"}
}