{
  "type": "Feature",
  "properties": {
    "iso:country":"US",
    "sg:address":"3662 N 7th St",
    "sg:city":"Milwaukee",
    "sg:classifiers":[
        {
            "category":"Real Estate",
            "subcategory":"Real Estate Agent",
            "type":"Services"
        }
    ],
    "sg:phone":"+1 414 372 1105",
    "sg:postcode":"53212",
    "sg:province":"WI",
    "wof:name":"Ss Bedrell Inc",
    "wof:placetype":"venue"
},
  "geometry": {"coordinates":[-87.91965500000001,43.085324],"type":"Point"}
}