{
  "type": "Feature",
  "properties": {
    "iso:country":"US",
    "sg:address":"7672 178th St",
    "sg:city":"Chippewa Falls",
    "sg:classifiers":[
        {
            "category":"Professional",
            "subcategory":"Management & Consulting",
            "type":"Services"
        }
    ],
    "sg:phone":"+1 715 723 8917",
    "sg:postcode":"54729",
    "sg:province":"WI",
    "wof:name":"Paula K Kleintjes",
    "wof:placetype":"venue"
},
  "geometry": {"coordinates":[-91.310231,44.954941],"type":"Point"}
}