{
  "type": "Feature",
  "properties": {
    "addr:full":"4871 Co Rd II Highland WI 53543",
    "addr:housenumber":"4871",
    "addr:postcode":"53543",
    "addr:street":"Co Rd Ii",
    "iso:country":"US",
    "sg:address":"4871 Co Rd II",
    "sg:city":"Highland",
    "sg:classifiers":[
        {
            "category":"Manufacturing",
            "subcategory":"Buildings",
            "type":"Manufacturing & Wholesale Goods"
        }
    ],
    "sg:phone":"+1 608 935 3939",
    "sg:postcode":"53543",
    "sg:province":"WI",
    "sg:tags":[
        "prefabricated",
        "wood",
        "mfg"
    ],
    "wof:name":"Butteris Homes & Construction",
    "wof:placetype":"venue"
},
  "geometry": {"coordinates":[-90.25814699999999,43.048129],"type":"Point"}
}