{
  "type": "Feature",
  "properties": {
    "iso:country":"US",
    "sg:address":"9992 Old Ln",
    "sg:city":"Lancaster",
    "sg:phone":"+1 608 723 2216",
    "sg:postcode":"53813",
    "sg:province":"WI",
    "sg:tags":[
        "farm",
        "corn",
        "beef",
        "feedlot",
        "cattle"
    ],
    "wof:name":"Robert Alcorn",
    "wof:placetype":"venue"
},
  "geometry": {"coordinates":[-90.71620799999999,42.867847],"type":"Point"}
}