{
  "type": "Feature",
  "properties": {
    "iso:country":"US",
    "sg:address":"548 Janick Cir W",
    "sg:city":"Stevens Point",
    "sg:classifiers":[
        {
            "category":"Social Services",
            "subcategory":"Child Care",
            "type":"Services"
        }
    ],
    "sg:phone":"+1 715 341 7724",
    "sg:postcode":"54481",
    "sg:province":"WI",
    "sg:tags":[
        "day"
    ],
    "wof:name":"Caring Corner",
    "wof:placetype":"venue"
},
  "geometry": {"coordinates":[-89.540473,44.530029],"type":"Point"}
}