{
  "type": "Feature",
  "properties": {
    "addr:full":"2639 170th Ave Glenwood City WI 54013",
    "addr:housenumber":"2639",
    "addr:postcode":"54013",
    "addr:street":"170Th Ave",
    "iso:country":"US",
    "sg:address":"2639 170th Ave",
    "sg:city":"Glenwood City",
    "sg:phone":"+1 715 265 7462",
    "sg:postcode":"54013",
    "sg:province":"WI",
    "sg:tags":[
        "beef",
        "farm",
        "cash",
        "grain",
        "cattle",
        "feedlot"
    ],
    "wof:name":"Lonny Djoseland",
    "wof:placetype":"venue"
},
  "geometry": {"coordinates":[-92.270792,45.104881],"type":"Point"}
}