{
  "type": "Feature",
  "properties": {
    "iso:country":"US",
    "sg:address":"112 S Main St",
    "sg:city":"Mayville",
    "sg:classifiers":[
        {
            "category":"Personal",
            "subcategory":"Barber",
            "type":"Services"
        }
    ],
    "sg:phone":"+1 920 387 5540",
    "sg:postcode":"53050",
    "sg:province":"WI",
    "wof:name":"His & Her Hair Care Ctr",
    "wof:placetype":"venue"
},
  "geometry": {"coordinates":[-88.54403000000001,43.494158],"type":"Point"}
}