{
  "type": "Feature",
  "properties": {
    "addr:full":"6773 Hillside Ct Cecil WI 54166",
    "addr:housenumber":"6773",
    "addr:postcode":"54166",
    "addr:street":"Hillside Ct",
    "iso:country":"US",
    "sg:address":"6773 Hillside Ct",
    "sg:city":"Cecil",
    "sg:classifiers":[
        {
            "category":"Social Services",
            "subcategory":"Adult Care",
            "type":"Services"
        }
    ],
    "sg:phone":"+1 715 745 2780",
    "sg:postcode":"54166",
    "sg:province":"WI",
    "sg:tags":[
        "home",
        "residential"
    ],
    "wof:name":"Jenny's Assisted Living",
    "wof:placetype":"venue"
},
  "geometry": {"coordinates":[-88.49101899999999,44.833156],"type":"Point"}
}