{
  "type": "Feature",
  "properties": {
    "iso:country":"US",
    "sg:address":"636 State Hwy 25",
    "sg:city":"Eau Galle",
    "sg:classifiers":[
        {
            "category":"Farming",
            "subcategory":"Dairy Farm",
            "type":"Manufacturing & Wholesale Goods"
        }
    ],
    "sg:phone":"+1 715 283 4917",
    "sg:postcode":"54737",
    "sg:province":"WI",
    "wof:name":"Erik Reuter",
    "wof:placetype":"venue"
},
  "geometry": {"coordinates":[-91.94863,44.697056],"type":"Point"}
}