{
  "type": "Feature",
  "properties": {
    "iso:country":"US",
    "sg:address":"12735 W Capitol Dr",
    "sg:city":"Brookfield",
    "sg:classifiers":[
        {
            "category":"Restaurant",
            "type":"Food & Drink"
        }
    ],
    "sg:phone":"+1 262 783 5227",
    "sg:postcode":"53005",
    "sg:province":"WI",
    "wof:name":"Dairy Queen",
    "wof:placetype":"venue"
},
  "geometry": {"coordinates":[-88.07023599999999,43.08891],"type":"Point"}
}