{
  "type": "Feature",
  "properties": {
    "addr:full":"136 E Towne Mall Madison WI 53704",
    "addr:housenumber":"136",
    "addr:postcode":"53704",
    "addr:street":"E Towne Mall",
    "iso:country":"US",
    "sg:address":"136 E Towne Mall",
    "sg:city":"Madison",
    "sg:classifiers":[
        {
            "category":"Shopping",
            "subcategory":"Gifts & Souvenirs",
            "type":"Retail Goods"
        }
    ],
    "sg:phone":"+1 608 242 9578",
    "sg:postcode":"53704",
    "sg:province":"WI",
    "sg:tags":[
        "novelty"
    ],
    "wof:name":"A Dollar",
    "wof:placetype":"venue"
},
  "geometry": {"coordinates":[-89.304405,43.128164],"type":"Point"}
}