{
  "type": "Feature",
  "properties": {
    "iso:country":"US",
    "sg:address":"2221 Douglas Ave",
    "sg:city":"Racine",
    "sg:classifiers":[
        {
            "category":"Government",
            "subcategory":"Office",
            "type":"Public Place"
        }
    ],
    "sg:phone":"+1 262 636 9454",
    "sg:postcode":"53402",
    "sg:province":"WI",
    "sg:tags":[
        "village"
    ],
    "wof:name":"Racine Douglas Park Comm Ctr",
    "wof:placetype":"venue"
},
  "geometry": {"coordinates":[-87.798373,42.749138],"type":"Point"}
}