{
  "type": "Feature",
  "properties": {
    "iso:country":"US",
    "sg:address":"5001 W Mill Rd",
    "sg:city":"Milwaukee",
    "sg:classifiers":[
        {
            "category":"Recreation",
            "subcategory":"Barbecue",
            "type":"Entertainment"
        }
    ],
    "sg:phone":"+1 414 353 8300",
    "sg:postcode":"53218",
    "sg:province":"WI",
    "sg:tags":[
        "grill",
        "supply"
    ],
    "wof:name":"Keg Products Inc",
    "wof:placetype":"venue"
},
  "geometry": {"coordinates":[-87.97429700000001,43.133888],"type":"Point"}
}