{
  "type": "Feature",
  "properties": {
    "iso:country":"US",
    "sg:address":"1105 Butts Ave",
    "sg:city":"Tomah",
    "sg:classifiers":[
        {
            "category":"Organizations",
            "subcategory":"Religious Organization",
            "type":"Services"
        }
    ],
    "sg:phone":"+1 608 372 4543",
    "sg:postcode":"54660",
    "sg:province":"WI",
    "wof:name":"First United Methodist Church",
    "wof:placetype":"venue"
},
  "geometry": {"coordinates":[-90.514921,43.97721],"type":"Point"}
}