{
  "type": "Feature",
  "properties": {
    "iso:country":"US",
    "sg:address":"6117 Monona Dr",
    "sg:city":"Monona",
    "sg:classifiers":[
        {
            "category":"Manufacturing",
            "subcategory":"Printing",
            "type":"Manufacturing & Wholesale Goods"
        }
    ],
    "sg:phone":"+1 608 221 8899",
    "sg:postcode":"53716",
    "sg:province":"WI",
    "sg:tags":[
        "newspaper"
    ],
    "wof:name":"Nursing Productions Of America",
    "wof:placetype":"venue"
},
  "geometry": {"coordinates":[-89.325416,43.054035],"type":"Point"}
}