{
  "type": "Feature",
  "properties": {
    "iso:country":"US",
    "sg:address":"3161 Golf Rd",
    "sg:city":"Delafield",
    "sg:classifiers":[
        {
            "category":"Personal",
            "subcategory":"Beauty Salon",
            "type":"Services"
        }
    ],
    "sg:phone":"+1 262 646 7334",
    "sg:postcode":"53018",
    "sg:province":"WI",
    "sg:tags":[
        "shop"
    ],
    "wof:name":"Cost Cutters",
    "wof:placetype":"venue"
},
  "geometry": {"coordinates":[-88.366317,43.052144],"type":"Point"}
}