{
  "type": "Feature",
  "properties": {
    "iso:country":"US",
    "sg:address":"6250 Co Rd K",
    "sg:city":"Fond Du Lac",
    "sg:classifiers":[
        {
            "category":"Shopping",
            "type":"Retail Goods"
        }
    ],
    "sg:phone":"+1 920 922 8059",
    "sg:postcode":"54935",
    "sg:province":"WI",
    "sg:tags":[
        "mausoleum"
    ],
    "wof:name":"Ledgeview Memorial Park",
    "wof:placetype":"venue"
},
  "geometry": {"coordinates":[-88.390133,43.767564],"type":"Point"}
}