{
  "type": "Feature",
  "properties": {
    "iso:country":"US",
    "sg:address":"8488 US Hwy 141",
    "sg:city":"Crivitz",
    "sg:classifiers":[
        {
            "category":"Real Estate",
            "subcategory":"Real Estate Operator",
            "type":"Services"
        }
    ],
    "sg:phone":"+1 715 854 7802",
    "sg:postcode":"54114",
    "sg:province":"WI",
    "sg:tags":[
        "property",
        "lessor"
    ],
    "wof:name":"Diktanas Farms",
    "wof:placetype":"venue"
},
  "geometry": {"coordinates":[-87.990442,45.262206],"type":"Point"}
}