{
  "type": "Feature",
  "properties": {
    "addr:full":"530 E Clay St Whitewater WI 53190",
    "addr:housenumber":"530",
    "addr:postcode":"53190",
    "addr:street":"E Clay St",
    "iso:country":"US",
    "sg:address":"530 E Clay St",
    "sg:city":"Whitewater",
    "sg:classifiers":[
        {
            "category":"Retail",
            "subcategory":"Repair Shop",
            "type":"Services"
        }
    ],
    "sg:phone":"+1 262 473 6706",
    "sg:postcode":"53190",
    "sg:province":"WI",
    "sg:tags":[
        "welding"
    ],
    "wof:name":"Meske Welding",
    "wof:placetype":"venue"
},
  "geometry": {"coordinates":[-88.722238,42.831115],"type":"Point"}
}