{
  "type": "Feature",
  "properties": {
    "iso:country":"US",
    "sg:address":"840 Park Dr",
    "sg:city":"Balsam Lake",
    "sg:classifiers":[
        {
            "category":"Professional",
            "subcategory":"Lawyer & Legal Services",
            "type":"Services"
        }
    ],
    "sg:phone":"+1 715 405 1001",
    "sg:postcode":"54810",
    "sg:province":"WI",
    "sg:tags":[
        "attorney"
    ],
    "wof:name":"Mark D Biller Trial Lawyer",
    "wof:placetype":"venue"
},
  "geometry": {"coordinates":[-92.439769,45.457868],"type":"Point"}
}