{
  "type": "Feature",
  "properties": {
    "iso:country":"US",
    "sg:address":"1601 10th St",
    "sg:city":"Monroe",
    "sg:classifiers":[
        {
            "category":"Real Estate",
            "subcategory":"Real Estate Agent",
            "type":"Services"
        }
    ],
    "sg:phone":"+1 608 325 7977",
    "sg:postcode":"53566",
    "sg:province":"WI",
    "wof:name":"Towne Square Realty Inc",
    "wof:placetype":"venue"
},
  "geometry": {"coordinates":[-89.638581,42.602112],"type":"Point"}
}