{
  "type": "Feature",
  "properties": {
    "addr:full":"4745 Meadow Rd Cecil WI 54107",
    "addr:housenumber":"4745",
    "addr:postcode":"54107",
    "addr:street":"Meadow Rd",
    "iso:country":"US",
    "sg:address":"4745 Meadow Rd",
    "sg:city":"Cecil",
    "sg:classifiers":[
        {
            "category":"Wholesale",
            "subcategory":"Scrap",
            "type":"Manufacturing & Wholesale Goods"
        }
    ],
    "sg:phone":"+1 715 745 4155",
    "sg:postcode":"54107",
    "sg:province":"WI",
    "sg:tags":[
        "recycling",
        "center"
    ],
    "wof:name":"Lakeview Recycling",
    "wof:placetype":"venue"
},
  "geometry": {"coordinates":[-88.480012,44.798622],"type":"Point"}
}