{
  "type": "Feature",
  "properties": {
    "addr:full":"10406 Co Rd Z Pound WI 54161",
    "addr:housenumber":"10406",
    "addr:postcode":"54161",
    "addr:street":"Co Rd",
    "iso:country":"US",
    "sg:address":"10406 Co Rd Z",
    "sg:city":"Pound",
    "sg:classifiers":[
        {
            "category":"Professional",
            "type":"Services"
        }
    ],
    "sg:phone":"+1 920 842 4097",
    "sg:postcode":"54161",
    "sg:province":"WI",
    "wof:name":"Marvs Service",
    "wof:placetype":"venue"
},
  "geometry": {"coordinates":[-88.275156,45.068212],"type":"Point"}
}