{
  "type": "Feature",
  "properties": {
    "iso:country":"US",
    "sg:address":"318 N Lake Rd",
    "sg:city":"Oconomowoc",
    "sg:classifiers":[
        {
            "category":"Building & Trades",
            "subcategory":"Construction",
            "type":"Services"
        }
    ],
    "sg:phone":"+1 262 569 1516",
    "sg:postcode":"53066",
    "sg:province":"WI",
    "sg:tags":[
        "residential",
        "real estate"
    ],
    "wof:name":"Condo Developement Inc",
    "wof:placetype":"venue"
},
  "geometry": {"coordinates":[-88.499577,43.112085],"type":"Point"}
}