{
  "type": "Feature",
  "properties": {
    "iso:country":"US",
    "sg:address":"1177 Lyndon Rd",
    "sg:city":"Wisconsin Dells",
    "sg:classifiers":[
        {
            "category":"Wholesale",
            "subcategory":"Chemicals & Plastics",
            "type":"Manufacturing & Wholesale Goods"
        }
    ],
    "sg:phone":"+1 608 253 7350",
    "sg:postcode":"53965",
    "sg:province":"WI",
    "wof:name":"Sarco Plastics Inc",
    "wof:placetype":"venue"
},
  "geometry": {"coordinates":[-89.84750699999999,43.599365],"type":"Point"}
}