{
  "type": "Feature",
  "properties": {
    "iso:country":"US",
    "sg:address":"7465 Oak Circle Dr",
    "sg:city":"Middleton",
    "sg:classifiers":[
        {
            "category":"Real Estate",
            "subcategory":"Real Estate Operator",
            "type":"Services"
        }
    ],
    "sg:phone":"+1 608 831 1059",
    "sg:postcode":"53562",
    "sg:province":"WI",
    "sg:tags":[
        "building",
        "nonresidential"
    ],
    "wof:name":"Garron Properties",
    "wof:placetype":"venue"
},
  "geometry": {"coordinates":[-89.565488,43.14387],"type":"Point"}
}