{
  "type": "Feature",
  "properties": {
    "addr:full":"200 Industrial Dr Horicon WI 53032",
    "addr:housenumber":"200",
    "addr:postcode":"53032",
    "addr:street":"Industrial Dr",
    "iso:country":"US",
    "sg:address":"200 Industrial Dr",
    "sg:city":"Horicon",
    "sg:classifiers":[
        {
            "category":"Manufacturing",
            "subcategory":"Rubber & Plastics",
            "type":"Manufacturing & Wholesale Goods"
        }
    ],
    "sg:phone":"+1 920 485 4761",
    "sg:postcode":"53032",
    "sg:province":"WI",
    "sg:tags":[
        "product",
        "mfg"
    ],
    "wof:name":"Wisconsin Div of Centro",
    "wof:placetype":"venue"
},
  "geometry": {"coordinates":[-88.653972,43.456151],"type":"Point"}
}