{
  "type": "Feature",
  "properties": {
    "addr:full":"1806 E 12th St Merrill WI 54452",
    "addr:housenumber":"1806",
    "addr:postcode":"54452",
    "addr:street":"E 12Th St",
    "iso:country":"US",
    "sg:address":"1806 E 12th St",
    "sg:city":"Merrill",
    "sg:classifiers":[
        {
            "category":"Local Transit",
            "type":"Transportation"
        }
    ],
    "sg:phone":"+1 715 536 8218",
    "sg:postcode":"54452",
    "sg:province":"WI",
    "sg:tags":[
        "passenger"
    ],
    "wof:name":"Wisconsin Professional Livery",
    "wof:placetype":"venue"
},
  "geometry": {"coordinates":[-89.673585,45.18998],"type":"Point"}
}