{
  "type": "Feature",
  "properties": {
    "iso:country":"US",
    "sg:address":"17925 W Lincoln Ave",
    "sg:city":"New Berlin",
    "sg:classifiers":[
        {
            "category":"Manufacturing",
            "subcategory":"Tools & Machinery",
            "type":"Manufacturing & Wholesale Goods"
        }
    ],
    "sg:phone":"+1 262 782 3737",
    "sg:postcode":"53146",
    "sg:province":"WI",
    "sg:tags":[
        "equipment",
        "system",
        "automation"
    ],
    "sg:website":"www.automationtechnology.cc",
    "wof:name":"Automation Technology",
    "wof:placetype":"venue"
},
  "geometry": {"coordinates":[-88.141998,43.002371],"type":"Point"}
}