{
  "type": "Feature",
  "properties": {
    "iso:country":"US",
    "sg:address":"511 Germain St",
    "sg:city":"Somerset",
    "sg:classifiers":[
        {
            "category":"Professional",
            "subcategory":"Business Services",
            "type":"Services"
        }
    ],
    "sg:phone":"+1 715 247 2867",
    "sg:postcode":"54025",
    "sg:province":"WI",
    "sg:tags":[
        "literary",
        "agent"
    ],
    "wof:name":"Pederson Literacy",
    "wof:placetype":"venue"
},
  "geometry": {"coordinates":[-92.68192500000001,45.125657],"type":"Point"}
}