{
  "type": "Feature",
  "properties": {
    "iso:country":"US",
    "sg:address":"1101 1st St",
    "sg:city":"Stevens Point",
    "sg:classifiers":[
        {
            "category":"Airline",
            "type":"Transportation"
        }
    ],
    "sg:phone":"+1 715 341 4740",
    "sg:postcode":"54481",
    "sg:province":"WI",
    "sg:tags":[
        "bus",
        "line",
        "courier",
        "air"
    ],
    "wof:name":"Jeff Thompson Agency",
    "wof:placetype":"venue"
},
  "geometry": {"coordinates":[-89.586623,44.525418],"type":"Point"}
}