{
  "type": "Feature",
  "properties": {
    "iso:country":"US",
    "sg:address":"4015 Van Ostrand Rd",
    "sg:city":"White Lake",
    "sg:classifiers":[
        {
            "category":"Personal",
            "subcategory":"Beauty Salon",
            "type":"Services"
        }
    ],
    "sg:phone":"+1 715 882 5313",
    "sg:postcode":"54491",
    "sg:province":"WI",
    "sg:tags":[
        "shop"
    ],
    "wof:name":"Country Beauty Shop",
    "wof:placetype":"venue"
},
  "geometry": {"coordinates":[-88.74886100000001,45.168228],"type":"Point"}
}