{
  "type": "Feature",
  "properties": {
    "iso:country":"US",
    "sg:address":"22 E Pine St",
    "sg:city":"Sturgeon Bay",
    "sg:classifiers":[
        {
            "category":"Shopping",
            "type":"Retail Goods"
        }
    ],
    "sg:phone":"+1 920 746 0848",
    "sg:postcode":"54235",
    "sg:province":"WI",
    "sg:tags":[
        "product",
        "wood"
    ],
    "wof:name":"Door County Design & Woodwork",
    "wof:placetype":"venue"
},
  "geometry": {"coordinates":[-87.382448,44.826959],"type":"Point"}
}