{
  "type": "Feature",
  "properties": {
    "addr:full":"1141 W Grand Ave Wisconsin Rapids WI 54495",
    "addr:housenumber":"1141",
    "addr:postcode":"54495",
    "addr:street":"W Grand Ave",
    "iso:country":"US",
    "sg:address":"1141 W Grand Ave",
    "sg:city":"Wisconsin Rapids",
    "sg:classifiers":[
        {
            "category":"Retail",
            "subcategory":"Photofinishing",
            "type":"Services"
        }
    ],
    "sg:phone":"+1 715 424 4462",
    "sg:postcode":"54495",
    "sg:province":"WI",
    "sg:tags":[
        "laboratory",
        "portrait",
        "studio",
        "photo"
    ],
    "wof:name":"Goochs Photography",
    "wof:placetype":"venue"
},
  "geometry": {"coordinates":[-89.837942,44.395778],"type":"Point"}
}