{
  "type": "Feature",
  "properties": {
    "iso:country":"US",
    "sg:address":"238 S Bristol St",
    "sg:city":"Sun Prairie",
    "sg:classifiers":[
        {
            "category":"Wholesale",
            "subcategory":"Auto Parts",
            "type":"Manufacturing & Wholesale Goods"
        }
    ],
    "sg:phone":"+1 608 825 6235",
    "sg:postcode":"53590",
    "sg:province":"WI",
    "sg:tags":[
        "supply"
    ],
    "wof:name":"Springtime Service Spring",
    "wof:placetype":"venue"
},
  "geometry": {"coordinates":[-89.214028,43.179613],"type":"Point"}
}