{
  "type": "Feature",
  "properties": {
    "iso:country":"US",
    "sg:address":"3000 W Howard Ave",
    "sg:city":"Milwaukee",
    "sg:classifiers":[
        {
            "category":"Real Estate",
            "subcategory":"Real Estate Services",
            "type":"Services"
        }
    ],
    "sg:phone":"+1 414 282 6192",
    "sg:postcode":"53221",
    "sg:province":"WI",
    "sg:tags":[
        "apartment",
        "management",
        "rental",
        "finder"
    ],
    "sg:website":"http://www.forrent.com/apartment-community-profile/1010890.php?cmp=CAC-CSearchProfile",
    "wof:name":"Southgate Apartments",
    "wof:placetype":"venue"
},
  "geometry": {"coordinates":[-87.95247000000001,42.973961],"type":"Point"}
}