{
  "type": "Feature",
  "properties": {
    "iso:country":"US",
    "sg:address":"1361 S 108th St",
    "sg:city":"West Allis",
    "sg:classifiers":[
        {
            "category":"Banks & Credit Unions",
            "subcategory":"Bank",
            "type":"Services"
        }
    ],
    "sg:phone":"+1 414 302 0000",
    "sg:postcode":"53214",
    "sg:province":"WI",
    "sg:tags":[
        "loan"
    ],
    "sg:website":"www.plsfinancial.com",
    "wof:name":"Payday Loan Store Wi Inc",
    "wof:placetype":"venue"
},
  "geometry": {"coordinates":[-88.047117,43.017775],"type":"Point"}
}