{
  "type": "Feature",
  "properties": {
    "iso:country":"US",
    "sg:address":"333 Pine Ridge Blvd",
    "sg:city":"Wausau",
    "sg:classifiers":[
        {
            "category":"Education",
            "subcategory":"Library",
            "type":"Public Place"
        }
    ],
    "sg:phone":"+1 715 847 2184",
    "sg:postcode":"54401",
    "sg:province":"WI",
    "sg:tags":[
        "special",
        "interest"
    ],
    "wof:name":"Dr Joseph F Smith Medical Libr",
    "wof:placetype":"venue"
},
  "geometry": {"coordinates":[-89.669909,44.967399],"type":"Point"}
}