{
  "type": "Feature",
  "properties": {
    "iso:country":"US",
    "sg:address":"2513 S Jackson St",
    "sg:city":"Appleton",
    "sg:classifiers":[
        {
            "category":"Building & Trades",
            "subcategory":"Construction",
            "type":"Services"
        }
    ],
    "sg:phone":"+1 920 830 1596",
    "sg:postcode":"54915",
    "sg:province":"WI",
    "sg:tags":[
        "house"
    ],
    "wof:name":"Home Repair",
    "wof:placetype":"venue"
},
  "geometry": {"coordinates":[-88.398051,44.238711],"type":"Point"}
}