{
  "type": "Feature",
  "properties": {
    "iso:country":"US",
    "sg:address":"9235 Co Hwy B",
    "sg:city":"Clinton",
    "sg:classifiers":[
        {
            "category":"Retail",
            "subcategory":"Repair Shop",
            "type":"Services"
        }
    ],
    "sg:phone":"+1 262 736 4248",
    "sg:postcode":"53525",
    "sg:province":"WI",
    "sg:tags":[
        "tank",
        "cleaning",
        "septic"
    ],
    "wof:name":"Collins Sanitary LLC",
    "wof:placetype":"venue"
},
  "geometry": {"coordinates":[-88.753652,42.53538],"type":"Point"}
}