{
  "type": "Feature",
  "properties": {
    "iso:country":"US",
    "sg:address":"1122 17th St",
    "sg:city":"Racine",
    "sg:classifiers":[
        {
            "category":"Shopping",
            "subcategory":"Clothing, Apparel, & Fashions",
            "type":"Retail Goods"
        }
    ],
    "sg:phone":"+1 262 638 0923",
    "sg:postcode":"53403",
    "sg:province":"WI",
    "sg:tags":[
        "alteration"
    ],
    "wof:name":"Maria's Alterations & Repairs",
    "wof:placetype":"venue"
},
  "geometry": {"coordinates":[-87.79354499999999,42.710899],"type":"Point"}
}