{
  "type": "Feature",
  "properties": {
    "addr:full":"1126 Whitewater Ave Fort Atkinson WI 53538",
    "addr:housenumber":"1126",
    "addr:postcode":"53538",
    "addr:street":"Whitewater Ave",
    "iso:country":"US",
    "sg:address":"1126 Whitewater Ave",
    "sg:city":"Fort Atkinson",
    "sg:classifiers":[
        {
            "category":"Professional",
            "subcategory":"Accounting & Tax Preparation",
            "type":"Services"
        }
    ],
    "sg:phone":"+1 920 563 3794",
    "sg:postcode":"53538",
    "sg:province":"WI",
    "sg:tags":[
        "accountant"
    ],
    "wof:name":"AGK Accounting",
    "wof:placetype":"venue"
},
  "geometry": {"coordinates":[-88.832026,42.914125],"type":"Point"}
}