{
  "type": "Feature",
  "properties": {
    "iso:country":"US",
    "sg:address":"231 E Buffalo St",
    "sg:city":"Milwaukee",
    "sg:classifiers":[
        {
            "category":"Shopping",
            "subcategory":"Computers & Home Electronics",
            "type":"Retail Goods"
        }
    ],
    "sg:phone":"+1 414 224 1209",
    "sg:postcode":"53202",
    "sg:province":"WI",
    "sg:tags":[
        "equipment",
        "dealer",
        "software"
    ],
    "wof:name":"Corporate PC Source Inc",
    "wof:placetype":"venue"
},
  "geometry": {"coordinates":[-87.90774999999999,43.033732],"type":"Point"}
}