{
  "type": "Feature",
  "properties": {
    "addr:full":"203 Lincoln Ave Sheboygan WI 53081",
    "addr:housenumber":"203",
    "addr:postcode":"53081",
    "addr:street":"Lincoln Ave",
    "iso:country":"US",
    "sg:address":"203 Lincoln Ave",
    "sg:city":"Sheboygan",
    "sg:classifiers":[
        {
            "category":"Shopping",
            "subcategory":"Bicycles & Sporting Goods",
            "type":"Retail Goods"
        }
    ],
    "sg:phone":"+1 920 208 0208",
    "sg:postcode":"53081",
    "sg:province":"WI",
    "wof:name":"Icpt Discs & Stuff",
    "wof:placetype":"venue"
},
  "geometry": {"coordinates":[-87.70452,43.764608],"type":"Point"}
}