{
  "type": "Feature",
  "properties": {
    "iso:country":"US",
    "sg:address":"3303 Racine Ave",
    "sg:city":"Land O Lakes",
    "sg:classifiers":[
        {
            "category":"Building & Trades",
            "subcategory":"Construction",
            "type":"Services"
        }
    ],
    "sg:phone":"+1 715 547 6107",
    "sg:postcode":"54540",
    "sg:province":"WI",
    "sg:tags":[
        "carpentry",
        "contractor"
    ],
    "wof:name":"Becker Carpentry",
    "wof:placetype":"venue"
},
  "geometry": {"coordinates":[-89.154409,46.140183],"type":"Point"}
}