{
  "type": "Feature",
  "properties": {
    "addr:full":"8405 S 27th St Franklin WI 53132",
    "addr:housenumber":"8405",
    "addr:postcode":"53132",
    "addr:street":"S 27Th St",
    "iso:country":"US",
    "sg:address":"8405 S 27th St",
    "sg:city":"Franklin",
    "sg:classifiers":[
        {
            "category":"Restaurant",
            "type":"Food & Drink"
        }
    ],
    "sg:menulink":"http://www.allmenus.com/wi/franklin/291173-toscana-italian-ristorante/menu/",
    "sg:phone":"+1 414 304 1333",
    "sg:postcode":"53132",
    "sg:province":"WI",
    "sg:tags":[
        "italian"
    ],
    "wof:name":"Toscana Italian Ristorante",
    "wof:placetype":"venue"
},
  "geometry": {"coordinates":[-87.950836,42.892656],"type":"Point"}
}