{
  "type": "Feature",
  "properties": {
    "addr:full":"4511 N Oakland Ave Milwaukee WI 53211",
    "addr:housenumber":"4511",
    "addr:postcode":"53211",
    "addr:street":"N Oakland Ave",
    "iso:country":"US",
    "sg:address":"4511 N Oakland Ave",
    "sg:city":"Milwaukee",
    "sg:classifiers":[
        {
            "category":"Restaurant",
            "type":"Food & Drink"
        }
    ],
    "sg:menulink":"http://www.allmenus.com/wi/shorewood/18227-china-palace-restaurant/menu/",
    "sg:phone":"+1 414 332 2024",
    "sg:postcode":"53211",
    "sg:province":"WI",
    "sg:tags":[
        "asian",
        "chinese"
    ],
    "wof:name":"China Palace Restaurant",
    "wof:placetype":"venue"
},
  "geometry": {"coordinates":[-87.8878,43.098698],"type":"Point"}
}