{
  "type": "Feature",
  "properties": {
    "addr:full":"5722 Co Rd C Rosendale WI 54974",
    "addr:housenumber":"5722",
    "addr:postcode":"54974",
    "addr:street":"Co Rd",
    "iso:country":"US",
    "sg:address":"5722 Co Rd C",
    "sg:city":"Rosendale",
    "sg:classifiers":[
        {
            "category":"Wholesale",
            "subcategory":"Dairy",
            "type":"Manufacturing & Wholesale Goods"
        }
    ],
    "sg:phone":"+1 920 922 5200",
    "sg:postcode":"54974",
    "sg:province":"WI",
    "sg:tags":[
        "cheese",
        "sausage"
    ],
    "sg:website":"www.stardairy.com",
    "wof:name":"Knaus Cheese Inc",
    "wof:placetype":"venue"
},
  "geometry": {"coordinates":[-88.633921,43.751726],"type":"Point"}
}