{
  "type": "Feature",
  "properties": {
    "iso:country":"US",
    "sg:address":"3240 E Van Norman Ave",
    "sg:city":"Cudahy",
    "sg:classifiers":[
        {
            "category":"Wholesale",
            "subcategory":"Machinery & Supplies",
            "type":"Manufacturing & Wholesale Goods"
        }
    ],
    "sg:phone":"+1 414 294 3000",
    "sg:postcode":"53110",
    "sg:province":"WI",
    "sg:tags":[
        "valve"
    ],
    "wof:name":"Nog, Inc.",
    "wof:placetype":"venue"
},
  "geometry": {"coordinates":[-87.868938,42.962738],"type":"Point"}
}