{
  "type": "Feature",
  "properties": {
    "addr:full":"924 Rowe Rd Sheboygan WI 53083",
    "addr:housenumber":"924",
    "addr:postcode":"53083",
    "addr:street":"Rowe Rd",
    "iso:country":"US",
    "sg:address":"924 Rowe Rd",
    "sg:city":"Sheboygan",
    "sg:classifiers":[
        {
            "category":"Personal",
            "type":"Services"
        }
    ],
    "sg:phone":"+1 920 918 0419",
    "sg:postcode":"53083",
    "sg:province":"WI",
    "sg:tags":[
        "therapist",
        "massage"
    ],
    "wof:name":"Haven Hands",
    "wof:placetype":"venue"
},
  "geometry": {"coordinates":[-87.74472900000001,43.834612],"type":"Point"}
}