{
  "type": "Feature",
  "properties": {
    "iso:country":"US",
    "sg:address":"8020 Sheridan Rd",
    "sg:city":"Kenosha",
    "sg:classifiers":[
        {
            "category":"Health Services",
            "subcategory":"Doctor",
            "type":"Services"
        }
    ],
    "sg:phone":"+1 262 605 0600",
    "sg:postcode":"53143",
    "sg:province":"WI",
    "sg:tags":[
        "physician",
        "surgeon"
    ],
    "wof:name":"Wisconsin Retina Sc",
    "wof:placetype":"venue"
},
  "geometry": {"coordinates":[-87.825419,42.556994],"type":"Point"}
}