{
  "type": "Feature",
  "properties": {
    "iso:country":"US",
    "sg:address":"11311 W Locust St",
    "sg:city":"Milwaukee",
    "sg:classifiers":[
        {
            "category":"Building & Trades",
            "subcategory":"Construction",
            "type":"Services"
        }
    ],
    "sg:phone":"+1 414 476 6688",
    "sg:postcode":"53222",
    "sg:province":"WI",
    "sg:tags":[
        "residential",
        "industrial"
    ],
    "wof:name":"Brodd Property Management",
    "wof:placetype":"venue"
},
  "geometry": {"coordinates":[-88.054141,43.071238],"type":"Point"}
}