{
  "type": "Feature",
  "properties": {
    "iso:country":"US",
    "sg:address":"141 N Pine St",
    "sg:city":"Burlington",
    "sg:classifiers":[
        {
            "category":"Restaurant",
            "type":"Food & Drink"
        }
    ],
    "sg:phone":"+1 262 763 5252",
    "sg:postcode":"53105",
    "sg:province":"WI",
    "sg:tags":[
        "eating"
    ],
    "wof:name":"Foxville Family Restaurant",
    "wof:placetype":"venue"
},
  "geometry": {"coordinates":[-88.27480300000001,42.677299],"type":"Point"}
}