{
  "type": "Feature",
  "properties": {
    "iso:country":"US",
    "sg:address":"6075 Leprechaun Ln",
    "sg:city":"Hartford",
    "sg:classifiers":[
        {
            "category":"Retail",
            "subcategory":"Repair Shop",
            "type":"Services"
        }
    ],
    "sg:phone":"+1 262 966 7423",
    "sg:postcode":"53027",
    "sg:province":"WI",
    "wof:name":"Medtronic",
    "wof:placetype":"venue"
},
  "geometry": {"coordinates":[-88.339705,43.216255],"type":"Point"}
}