{
  "type": "Feature",
  "properties": {
    "iso:country":"US",
    "sg:address":"1119 W Mason St",
    "sg:city":"Green Bay",
    "sg:classifiers":[
        {
            "category":"Shopping",
            "subcategory":"Pharmacy",
            "type":"Retail Goods"
        }
    ],
    "sg:phone":"+1 920 499 6772",
    "sg:postcode":"54303",
    "sg:province":"WI",
    "sg:website":"www.krider.com",
    "wof:name":"Krider Pharmacy",
    "wof:placetype":"venue"
},
  "geometry": {"coordinates":[-88.044663,44.516811],"type":"Point"}
}