{
  "type": "Feature",
  "properties": {
    "addr:full":"101 Broad St Lake Geneva WI 53147",
    "addr:housenumber":"101",
    "addr:postcode":"53147",
    "addr:street":"Broad St",
    "iso:country":"US",
    "sg:address":"101 Broad St",
    "sg:city":"Lake Geneva",
    "sg:classifiers":[
        {
            "category":"Wholesale",
            "subcategory":"Sporting Goods",
            "type":"Manufacturing & Wholesale Goods"
        }
    ],
    "sg:phone":"+1 262 249 0100",
    "sg:postcode":"53147",
    "sg:province":"WI",
    "wof:name":"Snowbird and Son",
    "wof:placetype":"venue"
},
  "geometry": {"coordinates":[-88.435339,42.591091],"type":"Point"}
}