{
  "type": "Feature",
  "properties": {
    "iso:country":"US",
    "sg:address":"3438 Birchwood Rd",
    "sg:city":"Saukville",
    "sg:classifiers":[
        {
            "category":"Manufacturing",
            "subcategory":"Rubber & Plastics",
            "type":"Manufacturing & Wholesale Goods"
        }
    ],
    "sg:phone":"+1 262 334 5002",
    "sg:postcode":"53080",
    "sg:province":"WI",
    "sg:tags":[
        "product",
        "mfg"
    ],
    "wof:name":"Creative Plastic & Mfg",
    "wof:placetype":"venue"
},
  "geometry": {"coordinates":[-88.010505,43.40257],"type":"Point"}
}