{
  "type": "Feature",
  "properties": {
    "iso:country":"US",
    "sg:address":"109 S Main St",
    "sg:city":"Fond Du Lac",
    "sg:classifiers":[
        {
            "category":"Bars & Pubs",
            "type":"Food & Drink"
        }
    ],
    "sg:phone":"+1 920 906 4933",
    "sg:postcode":"54935",
    "sg:province":"WI",
    "wof:name":"Visions Of Fond Du Lac Inc",
    "wof:placetype":"venue"
},
  "geometry": {"coordinates":[-88.446921,43.775522],"type":"Point"}
}