{
  "type": "Feature",
  "properties": {
    "iso:country":"US",
    "sg:address":"110 Meadowood Dr",
    "sg:city":"Randolph",
    "sg:classifiers":[
        {
            "category":"Education",
            "subcategory":"Special Training",
            "type":"Public Place"
        }
    ],
    "sg:phone":"+1 920 326 2425",
    "sg:postcode":"53956",
    "sg:province":"WI",
    "wof:name":"Future Farmers of America",
    "wof:placetype":"venue"
},
  "geometry": {"coordinates":[-88.999752,43.543236],"type":"Point"}
}