{
  "type": "Feature",
  "properties": {
    "iso:country":"US",
    "sg:address":"4830 52nd Ave",
    "sg:city":"Kenosha",
    "sg:classifiers":[
        {
            "category":"Manufacturing",
            "subcategory":"Tools & Machinery",
            "type":"Manufacturing & Wholesale Goods"
        }
    ],
    "sg:phone":"+1 262 658 3590",
    "sg:postcode":"53144",
    "sg:province":"WI",
    "sg:tags":[
        "industry",
        "aerospace"
    ],
    "wof:name":"Patco Industries Inc",
    "wof:placetype":"venue"
},
  "geometry": {"coordinates":[-87.870774,42.595341],"type":"Point"}
}