{
  "type": "Feature",
  "properties": {
    "iso:country":"US",
    "sg:address":"124 N Ludington St",
    "sg:city":"Columbus",
    "sg:classifiers":[
        {
            "category":"Personal",
            "subcategory":"Beauty Salon",
            "type":"Services"
        }
    ],
    "sg:phone":"+1 920 623 4550",
    "sg:postcode":"53925",
    "sg:province":"WI",
    "sg:tags":[
        "shop"
    ],
    "wof:name":"Central Beauty Shoppe",
    "wof:placetype":"venue"
},
  "geometry": {"coordinates":[-89.01366899999999,43.33891],"type":"Point"}
}