{
  "type": "Feature",
  "properties": {
    "addr:full":"104 S Eyder Ave Phillips WI 54555",
    "addr:housenumber":"104",
    "addr:postcode":"54555",
    "addr:street":"S Eyder Ave",
    "iso:country":"US",
    "sg:address":"104 S Eyder Ave",
    "sg:city":"Phillips",
    "sg:classifiers":[
        {
            "category":"Government",
            "subcategory":"Office",
            "type":"Public Place"
        }
    ],
    "sg:phone":"+1 715 339 3002",
    "sg:postcode":"54555",
    "sg:province":"WI",
    "wof:name":"Conservation Warden",
    "wof:placetype":"venue"
},
  "geometry": {"coordinates":[-90.398962,45.686574],"type":"Point"}
}