{
  "type": "Feature",
  "properties": {
    "iso:country":"US",
    "sg:address":"615 Hall Ave",
    "sg:city":"Oconto",
    "sg:classifiers":[
        {
            "category":"Retail",
            "subcategory":"Funeral Services",
            "type":"Services"
        }
    ],
    "sg:phone":"+1 920 834 3091",
    "sg:postcode":"54153",
    "sg:province":"WI",
    "sg:tags":[
        "director"
    ],
    "wof:name":"Richard J Pinkart",
    "wof:placetype":"venue"
},
  "geometry": {"coordinates":[-87.859514,44.891939],"type":"Point"}
}