{
  "type": "Feature",
  "properties": {
    "iso:country":"US",
    "sg:address":"6853 State Hwy 91",
    "sg:city":"Pickett",
    "sg:classifiers":[
        {
            "category":"Farming",
            "subcategory":"Dairy Farm",
            "type":"Manufacturing & Wholesale Goods"
        }
    ],
    "sg:phone":"+1 920 685 5743",
    "sg:postcode":"54964",
    "sg:province":"WI",
    "wof:name":"Thomas Davis",
    "wof:placetype":"venue"
},
  "geometry": {"coordinates":[-88.744362,43.9822],"type":"Point"}
}