{
  "type": "Feature",
  "properties": {
    "iso:country":"US",
    "sg:address":"309 Barstow St",
    "sg:city":"Horicon",
    "sg:classifiers":[
        {
            "category":"Restaurant",
            "type":"Food & Drink"
        }
    ],
    "sg:menulink":"http://www.allmenus.com/wi/horicon/145523-subway/menu/",
    "sg:phone":"+1 920 485 6767",
    "sg:postcode":"53032",
    "sg:province":"WI",
    "sg:tags":[
        "american",
        "sandwich"
    ],
    "wof:name":"Subway",
    "wof:placetype":"venue"
},
  "geometry": {"coordinates":[-88.635745,43.44824],"type":"Point"}
}