{
  "type": "Feature",
  "properties": {
    "addr:full":"1815 Revere Trl De Pere WI 54115",
    "addr:housenumber":"1815",
    "addr:postcode":"54115",
    "addr:street":"Revere Trl",
    "iso:country":"US",
    "sg:address":"1815 Revere Trl",
    "sg:city":"De Pere",
    "sg:classifiers":[
        {
            "category":"Insurance",
            "subcategory":"Insurance Agent",
            "type":"Services"
        }
    ],
    "sg:phone":"+1 920 337 6103",
    "sg:postcode":"54115",
    "sg:province":"WI",
    "wof:name":"Dave Bernarde",
    "wof:placetype":"venue"
},
  "geometry": {"coordinates":[-88.082583,44.427044],"type":"Point"}
}