{
  "type": "Feature",
  "properties": {
    "iso:country":"US",
    "sg:address":"1613 Holiday Dr",
    "sg:city":"Janesville",
    "sg:classifiers":[
        {
            "category":"Personal",
            "type":"Services"
        }
    ],
    "sg:phone":"+1 608 752 1424",
    "sg:postcode":"53545",
    "sg:province":"WI",
    "sg:tags":[
        "wear",
        "formal"
    ],
    "wof:name":"Top Hat N' Tails",
    "wof:placetype":"venue"
},
  "geometry": {"coordinates":[-89.00269299999999,42.714456],"type":"Point"}
}