{
  "type": "Feature",
  "properties": {
    "iso:country":"US",
    "sg:address":"140 W. Chestnut Street Suite 3",
    "sg:city":"Burlington",
    "sg:classifiers":[
        {
            "category":"Personal",
            "subcategory":"Beauty Salon",
            "type":"Services"
        },
        {
            "category":"Personal",
            "subcategory":"Nail Salon",
            "type":"Services"
        }
    ],
    "sg:phone":"+1 262 417 1485",
    "sg:postcode":"53105",
    "sg:province":"WI",
    "sg:tags":[
        "hair"
    ],
    "sg:website":"salonraw.com/",
    "wof:name":"Raw Salon",
    "wof:placetype":"venue"
},
  "geometry": {"coordinates":[-88.27709299999999,42.679967],"type":"Point"}
}