{
  "type": "Feature",
  "properties": {
    "iso:country":"US",
    "sg:address":"2318 Co Rd A",
    "sg:city":"Stoughton",
    "sg:classifiers":[
        {
            "category":"Farming",
            "subcategory":"Farm",
            "type":"Manufacturing & Wholesale Goods"
        }
    ],
    "sg:phone":"+1 608 873 7868",
    "sg:postcode":"53589",
    "sg:province":"WI",
    "wof:name":"Hagen Farms",
    "wof:placetype":"venue"
},
  "geometry": {"coordinates":[-89.186914,42.90787],"type":"Point"}
}