{
  "type": "Feature",
  "properties": {
    "iso:country":"US",
    "sg:address":"7690 Mayer Rd",
    "sg:city":"Wonewoc",
    "sg:classifiers":[
        {
            "category":"Professional",
            "type":"Services"
        }
    ],
    "sg:phone":"+1 608 464 3933",
    "sg:postcode":"53968",
    "sg:province":"WI",
    "wof:name":"Ron A Breunig",
    "wof:placetype":"venue"
},
  "geometry": {"coordinates":[-90.15992,43.670981],"type":"Point"}
}