{
  "type": "Feature",
  "properties": {
    "iso:country":"US",
    "sg:address":"1414 S Maple Ave",
    "sg:city":"Marshfield",
    "sg:classifiers":[
        {
            "category":"Retail",
            "subcategory":"Self-service Laundry",
            "type":"Services"
        }
    ],
    "sg:phone":"+1 715 387 0920",
    "sg:postcode":"54449",
    "sg:province":"WI",
    "sg:tags":[
        "dry",
        "self",
        "laundromat",
        "commercial",
        "cleaning"
    ],
    "wof:name":"Five Corners Laundry & Dry Clg",
    "wof:placetype":"venue"
},
  "geometry": {"coordinates":[-90.179951,44.655519],"type":"Point"}
}