{
  "type": "Feature",
  "properties": {
    "iso:country":"US",
    "sg:address":"4415 County Line Rd",
    "sg:city":"Luxemburg",
    "sg:classifiers":[
        {
            "category":"Freight",
            "type":"Transportation"
        }
    ],
    "sg:phone":"+1 920 866 2568",
    "sg:postcode":"54217",
    "sg:province":"WI",
    "sg:tags":[
        "operator",
        "hauling",
        "local",
        "livestock",
        "trucking"
    ],
    "wof:name":"Ducat's Trucking Inc",
    "wof:placetype":"venue"
},
  "geometry": {"coordinates":[-87.763975,44.600272],"type":"Point"}
}