{
  "type": "Feature",
  "properties": {
    "iso:country":"US",
    "sg:address":"1006 Jefferson St",
    "sg:city":"Merrill",
    "sg:classifiers":[
        {
            "category":"Retail",
            "subcategory":"Portrait Studio",
            "type":"Services"
        }
    ],
    "sg:phone":"+1 715 536 7771",
    "sg:postcode":"54452",
    "sg:province":"WI",
    "sg:tags":[
        "photo"
    ],
    "wof:name":"Day & Night Photography",
    "wof:placetype":"venue"
},
  "geometry": {"coordinates":[-89.703692,45.190567],"type":"Point"}
}