{
  "type": "Feature",
  "properties": {
    "iso:country":"US",
    "sg:address":"4848 Switzke Rd",
    "sg:city":"Jefferson",
    "sg:classifiers":[
        {
            "category":"Retail",
            "subcategory":"Repair Shop",
            "type":"Services"
        }
    ],
    "sg:phone":"+1 920 674 3192",
    "sg:postcode":"53549",
    "sg:province":"WI",
    "wof:name":"System Resources LLC",
    "wof:placetype":"venue"
},
  "geometry": {"coordinates":[-88.739188,43.018804],"type":"Point"}
}