{
  "type": "Feature",
  "properties": {
    "iso:country":"US",
    "sg:address":"3349 N 9th St",
    "sg:city":"Milwaukee",
    "sg:classifiers":[
        {
            "category":"Retail",
            "subcategory":"Repair Shop",
            "type":"Services"
        }
    ],
    "sg:phone":"+1 414 374 1373",
    "sg:postcode":"53206",
    "sg:province":"WI",
    "sg:tags":[
        "appliance"
    ],
    "wof:name":"Watkin's Appliance Repair",
    "wof:placetype":"venue"
},
  "geometry": {"coordinates":[-87.922467,43.080979],"type":"Point"}
}