{
  "type": "Feature",
  "properties": {
    "addr:full":"1132 Madison St Beaver Dam WI 53916",
    "addr:housenumber":"1132",
    "addr:postcode":"53916",
    "addr:street":"Madison St",
    "iso:country":"US",
    "sg:address":"1132 Madison St",
    "sg:city":"Beaver Dam",
    "sg:classifiers":[
        {
            "category":"Building & Trades",
            "subcategory":"Plumbing",
            "type":"Services"
        }
    ],
    "sg:phone":"+1 920 887 1334",
    "sg:postcode":"53916",
    "sg:province":"WI",
    "sg:tags":[
        "septic"
    ],
    "wof:name":"Bagley Septic Pumping Svc",
    "wof:placetype":"venue"
},
  "geometry": {"coordinates":[-88.854634,43.443411],"type":"Point"}
}