{
  "type": "Feature",
  "properties": {
    "iso:country":"US",
    "sg:address":"721 Cardinal Ln",
    "sg:city":"Green Bay",
    "sg:classifiers":[
        {
            "category":"Insurance",
            "subcategory":"Insurance Agent",
            "type":"Services"
        }
    ],
    "sg:phone":"+1 920 662 9636",
    "sg:postcode":"54313",
    "sg:province":"WI",
    "wof:name":"New York Life Insurance Co",
    "wof:placetype":"venue"
},
  "geometry": {"coordinates":[-88.084834,44.560296],"type":"Point"}
}