{
  "type": "Feature",
  "properties": {
    "iso:country":"US",
    "sg:address":"6747 W Lincoln Ave",
    "sg:city":"Milwaukee",
    "sg:classifiers":[
        {
            "category":"Autos & Motor Vehicles",
            "subcategory":"Automobile Sales",
            "type":"Retail Goods"
        }
    ],
    "sg:phone":"+1 414 541 7926",
    "sg:postcode":"53219",
    "sg:province":"WI",
    "sg:tags":[
        "car",
        "dealer"
    ],
    "wof:name":"Ryan Motors Inc",
    "wof:placetype":"venue"
},
  "geometry": {"coordinates":[-87.99717800000001,43.002802],"type":"Point"}
}