{
  "type": "Feature",
  "properties": {
    "iso:country":"US",
    "sg:address":"27458 Patricia Ln",
    "sg:city":"Pewaukee",
    "sg:classifiers":[
        {
            "category":"Real Estate",
            "subcategory":"Real Estate Operator",
            "type":"Services"
        }
    ],
    "sg:phone":"+1 262 691 0732",
    "sg:postcode":"53072",
    "sg:province":"WI",
    "sg:tags":[
        "building",
        "nonresidential"
    ],
    "wof:name":"Don Properties LLC",
    "wof:placetype":"venue"
},
  "geometry": {"coordinates":[-88.29370299999999,43.092966],"type":"Point"}
}