{
  "type": "Feature",
  "properties": {
    "iso:country":"US",
    "sg:address":"1102 Mill Rd",
    "sg:city":"Nelson",
    "sg:classifiers":[
        {
            "category":"Manufacturing",
            "subcategory":"Lumber",
            "type":"Manufacturing & Wholesale Goods"
        }
    ],
    "sg:phone":"+1 715 673 4343",
    "sg:postcode":"54756",
    "sg:province":"WI",
    "sg:tags":[
        "sawmill"
    ],
    "wof:name":"Brunkow Hardwood Corp",
    "wof:placetype":"venue"
},
  "geometry": {"coordinates":[-92.01424299999999,44.438968],"type":"Point"}
}