{
  "type": "Feature",
  "properties": {
    "iso:country":"US",
    "sg:address":"1264 Satinwood Ln",
    "sg:city":"Whitewater",
    "sg:classifiers":[
        {
            "category":"Organizations",
            "subcategory":"Membership Organization",
            "type":"Services"
        }
    ],
    "sg:phone":"+1 262 473 2444",
    "sg:postcode":"53190",
    "sg:province":"WI",
    "wof:name":"Family Motor Coach Association",
    "wof:placetype":"venue"
},
  "geometry": {"coordinates":[-88.755717,42.831663],"type":"Point"}
}