{
  "type": "Feature",
  "properties": {
    "iso:country":"US",
    "sg:address":"645 State St",
    "sg:city":"Madison",
    "sg:classifiers":[
        {
            "category":"Shopping",
            "type":"Retail Goods"
        },
        {
            "category":"Manufacturing",
            "subcategory":"Printing",
            "type":"Manufacturing & Wholesale Goods"
        }
    ],
    "sg:phone":"+1 608 256 4156",
    "sg:postcode":"53703",
    "sg:province":"WI",
    "sg:tags":[
        "poster",
        "merchandise"
    ],
    "wof:name":"Fine Posters and Prints",
    "wof:placetype":"venue"
},
  "geometry": {"coordinates":[-89.397302,43.074825],"type":"Point"}
}