{
  "type": "Feature",
  "properties": {
    "addr:full":"4544 Bonnie Ave Madison WI 53718",
    "addr:housenumber":"4544",
    "addr:postcode":"53718",
    "addr:street":"Bonnie Ave",
    "iso:country":"US",
    "sg:address":"4544 Bonnie Ave",
    "sg:city":"Madison",
    "sg:classifiers":[
        {
            "category":"Shopping",
            "subcategory":"Bicycles & Sporting Goods",
            "type":"Retail Goods"
        }
    ],
    "sg:phone":"+1 608 256 3729",
    "sg:postcode":"53718",
    "sg:province":"WI",
    "sg:tags":[
        "equipment",
        "archery",
        "supply"
    ],
    "wof:name":"Rangers",
    "wof:placetype":"venue"
},
  "geometry": {"coordinates":[-89.235846,43.09594],"type":"Point"}
}