{
  "type": "Feature",
  "properties": {
    "addr:full":"1481 State Hwy 57 Random Lake WI 53075",
    "addr:housenumber":"1481",
    "addr:postcode":"53075",
    "addr:street":"State Hwy 57",
    "iso:country":"US",
    "sg:address":"1481 State Hwy 57",
    "sg:city":"Random Lake",
    "sg:classifiers":[
        {
            "category":"Personal",
            "type":"Services"
        },
        {
            "category":"Restaurant",
            "type":"Food & Drink"
        }
    ],
    "sg:phone":"+1 920 994 9696",
    "sg:postcode":"53075",
    "sg:province":"WI",
    "wof:name":"Greens Hideaway",
    "wof:placetype":"venue"
},
  "geometry": {"coordinates":[-87.94086,43.59352],"type":"Point"}
}