{
  "type": "Feature",
  "properties": {
    "iso:country":"US",
    "sg:address":"3815 N Brookfield Rd",
    "sg:city":"Brookfield",
    "sg:classifiers":[
        {
            "category":"Shopping",
            "subcategory":"Computers & Home Electronics",
            "type":"Retail Goods"
        },
        {
            "category":"Professional",
            "subcategory":"Computer Services",
            "type":"Services"
        }
    ],
    "sg:phone":"+1 262 567 6990",
    "sg:postcode":"53045",
    "sg:province":"WI",
    "sg:tags":[
        "support",
        "sales",
        "software"
    ],
    "wof:name":"Small Business Computer Svcs",
    "wof:placetype":"venue"
},
  "geometry": {"coordinates":[-88.146058,43.086968],"type":"Point"}
}