{
  "type": "Feature",
  "properties": {
    "addr:full":"1744 18th Ave Barron WI 54812",
    "addr:housenumber":"1744",
    "addr:postcode":"54812",
    "addr:street":"18Th Ave",
    "iso:country":"US",
    "sg:address":"1744 18th Ave",
    "sg:city":"Barron",
    "sg:classifiers":[
        {
            "category":"Wholesale",
            "subcategory":"Non-durable Goods",
            "type":"Manufacturing & Wholesale Goods"
        },
        {
            "category":"Home & Garden",
            "subcategory":"Garden Supply",
            "type":"Retail Goods"
        }
    ],
    "sg:phone":"+1 715 234 2534",
    "sg:postcode":"54812",
    "sg:province":"WI",
    "sg:tags":[
        "tree",
        "christmas"
    ],
    "wof:name":"Pine Crest Tree Farms",
    "wof:placetype":"venue"
},
  "geometry": {"coordinates":[-91.796475,45.466453],"type":"Point"}
}