{
  "type": "Feature",
  "properties": {
    "addr:full":"741 Bordeaux Rue Green Bay WI 54301",
    "addr:housenumber":"741",
    "addr:postcode":"54301",
    "addr:street":"Rue Green",
    "iso:country":"US",
    "sg:address":"741 Bordeaux Rue",
    "sg:city":"Green Bay",
    "sg:classifiers":[
        {
            "category":"Wholesale",
            "subcategory":"Machinery & Supplies",
            "type":"Manufacturing & Wholesale Goods"
        }
    ],
    "sg:phone":"+1 920 336 9999",
    "sg:postcode":"54301",
    "sg:province":"WI",
    "sg:tags":[
        "system",
        "conveyor"
    ],
    "wof:name":"Conveyor Integration Inc",
    "wof:placetype":"venue"
},
  "geometry": {"coordinates":[-88.020515,44.461455],"type":"Point"}
}