{
  "type": "Feature",
  "properties": {
    "iso:country":"US",
    "sg:address":"3328 9th Ave",
    "sg:city":"Racine",
    "sg:classifiers":[
        {
            "category":"Retail",
            "subcategory":"Repair Shop",
            "type":"Services"
        }
    ],
    "sg:phone":"+1 262 639 0161",
    "sg:postcode":"53402",
    "sg:province":"WI",
    "sg:tags":[
        "plumbing",
        "drain",
        "cleaning",
        "sewer"
    ],
    "wof:name":"Northern Sanitation Sewer Svc",
    "wof:placetype":"venue"
},
  "geometry": {"coordinates":[-87.79924800000001,42.760419],"type":"Point"}
}