{
  "type": "Feature",
  "properties": {
    "iso:country":"US",
    "sg:address":"5796 State Rd 22",
    "sg:city":"Wild Rose",
    "sg:classifiers":[
        {
            "category":"Freight",
            "type":"Transportation"
        }
    ],
    "sg:phone":"+1 920 622 3484",
    "sg:postcode":"54984",
    "sg:province":"WI",
    "sg:tags":[
        "distance",
        "carrier",
        "long",
        "contract"
    ],
    "wof:name":"Ross Caves & Son Inc",
    "wof:placetype":"venue"
},
  "geometry": {"coordinates":[-89.247077,44.188204],"type":"Point"}
}