{
  "type": "Feature",
  "properties": {
    "iso:country":"US",
    "sg:address":"4717 S Pearl Lake Rd",
    "sg:city":"Redgranite",
    "sg:classifiers":[
        {
            "category":"Professional",
            "type":"Services"
        }
    ],
    "sg:phone":"+1 920 566 4689",
    "sg:postcode":"54970",
    "sg:province":"WI",
    "sg:tags":[
        "establishment"
    ],
    "wof:name":"Rach & Rach",
    "wof:placetype":"venue"
},
  "geometry": {"coordinates":[-89.11288,44.083907],"type":"Point"}
}