{
  "type": "Feature",
  "properties": {
    "addr:full":"1518 N Little Rd Janesville WI 53548",
    "addr:housenumber":"1518",
    "addr:postcode":"53548",
    "addr:street":"N Little Rd",
    "iso:country":"US",
    "sg:address":"1518 N Little Rd",
    "sg:city":"Janesville",
    "sg:classifiers":[
        {
            "category":"Health Services",
            "subcategory":"Nursing And Care Facility",
            "type":"Services"
        }
    ],
    "sg:phone":"+1 608 754 7512",
    "sg:postcode":"53548",
    "sg:province":"WI",
    "sg:tags":[
        "home",
        "skilled",
        "convalescent"
    ],
    "wof:name":"Shirley's Place",
    "wof:placetype":"venue"
},
  "geometry": {"coordinates":[-89.101491,42.697812],"type":"Point"}
}