{
  "type": "Feature",
  "properties": {
    "addr:full":"1303 Cass St La Crosse WI 54601",
    "addr:housenumber":"1303",
    "addr:postcode":"54601",
    "addr:street":"Cass St",
    "iso:country":"US",
    "sg:address":"1303 Cass St",
    "sg:city":"La Crosse",
    "sg:classifiers":[
        {
            "category":"Organizations",
            "subcategory":"Professional Association",
            "type":"Services"
        }
    ],
    "sg:phone":"+1 608 782 4760",
    "sg:postcode":"54601",
    "sg:province":"WI",
    "wof:name":"Citizen Advocacy",
    "wof:placetype":"venue"
},
  "geometry": {"coordinates":[-91.235907,43.808778],"type":"Point"}
}