{
  "type": "Feature",
  "properties": {
    "iso:country":"US",
    "sg:address":"835 Elm St",
    "sg:city":"De Pere",
    "sg:classifiers":[
        {
            "category":"Building & Trades",
            "subcategory":"Construction",
            "type":"Services"
        }
    ],
    "sg:phone":"+1 920 336 3368",
    "sg:postcode":"54115",
    "sg:province":"WI",
    "sg:tags":[
        "floor",
        "laying",
        "contractor"
    ],
    "wof:name":"Rasmussen Industrial Flooring",
    "wof:placetype":"venue"
},
  "geometry": {"coordinates":[-88.080667,44.453289],"type":"Point"}
}