{
  "type": "Feature",
  "properties": {
    "addr:full":"5238 State Hwy 42 Sturgeon Bay WI 54235",
    "addr:housenumber":"5238",
    "addr:postcode":"54235",
    "addr:street":"State Hwy 42",
    "iso:country":"US",
    "sg:address":"5238 State Hwy 42",
    "sg:city":"Sturgeon Bay",
    "sg:classifiers":[
        {
            "category":"Farming",
            "subcategory":"Dairy Farm",
            "type":"Manufacturing & Wholesale Goods"
        }
    ],
    "sg:phone":"+1 920 743 4974",
    "sg:postcode":"54235",
    "sg:province":"WI",
    "wof:name":"Sunny View Farm",
    "wof:placetype":"venue"
},
  "geometry": {"coordinates":[-87.337135,44.927321],"type":"Point"}
}