{
  "type": "Feature",
  "properties": {
    "iso:country":"US",
    "sg:address":"2870 S River Rd",
    "sg:city":"Rhinelander",
    "sg:classifiers":[
        {
            "category":"Professional",
            "subcategory":"Business Services",
            "type":"Services"
        },
        {
            "category":"Building & Trades",
            "subcategory":"Landscaping Services",
            "type":"Services"
        }
    ],
    "sg:phone":"+1 715 362 9669",
    "sg:postcode":"54501",
    "sg:province":"WI",
    "sg:tags":[
        "landscape",
        "contractor"
    ],
    "wof:name":"Patio's Plus Inc",
    "wof:placetype":"venue"
},
  "geometry": {"coordinates":[-89.462385,45.600233],"type":"Point"}
}