{
  "type": "Feature",
  "properties": {
    "iso:country":"US",
    "sg:address":"9060 N Deerbrook Trl",
    "sg:city":"Milwaukee",
    "sg:classifiers":[
        {
            "category":"Home & Garden",
            "subcategory":"Home Furnishings",
            "type":"Retail Goods"
        }
    ],
    "sg:phone":"+1 414 355 9010",
    "sg:postcode":"53223",
    "sg:province":"WI",
    "sg:tags":[
        "linen"
    ],
    "wof:name":"Bbj Linen",
    "wof:placetype":"venue"
},
  "geometry": {"coordinates":[-87.966497,43.180493],"type":"Point"}
}