{
  "type": "Feature",
  "properties": {
    "iso:country":"US",
    "sg:address":"3725 N 126th St",
    "sg:city":"Brookfield",
    "sg:classifiers":[
        {
            "category":"Retail",
            "subcategory":"Repair Shop",
            "type":"Services"
        }
    ],
    "sg:phone":"+1 262 781 1609",
    "sg:postcode":"53005",
    "sg:province":"WI",
    "sg:tags":[
        "equipment",
        "conditioning",
        "air"
    ],
    "sg:website":"www.carrier.com",
    "wof:name":"Carrier Corp Building Systems",
    "wof:placetype":"venue"
},
  "geometry": {"coordinates":[-88.069034,43.085104],"type":"Point"}
}