{
  "type": "Feature",
  "properties": {
    "iso:country":"US",
    "sg:address":"11722 Columbia Ave",
    "sg:city":"Greenwood",
    "sg:classifiers":[
        {
            "category":"Organizations",
            "subcategory":"Membership Organization",
            "type":"Services"
        }
    ],
    "sg:phone":"+1 715 267 6817",
    "sg:postcode":"54437",
    "sg:province":"WI",
    "wof:name":"Kirkhill Guardianship Inc",
    "wof:placetype":"venue"
},
  "geometry": {"coordinates":[-90.709379,44.844332],"type":"Point"}
}