{
  "type": "Feature",
  "properties": {
    "iso:country":"US",
    "sg:address":"5602 W Vliet St",
    "sg:city":"Milwaukee",
    "sg:classifiers":[
        {
            "category":"Autos & Motor Vehicles",
            "subcategory":"Fuel & Gas Station",
            "type":"Retail Goods"
        }
    ],
    "sg:phone":"+1 414 774 1530",
    "sg:postcode":"53208",
    "sg:province":"WI",
    "sg:tags":[
        "oil"
    ],
    "wof:name":"Hawley Road Mobil",
    "wof:placetype":"venue"
},
  "geometry": {"coordinates":[-87.984162,43.049716],"type":"Point"}
}