{
  "type": "Feature",
  "properties": {
    "iso:country":"US",
    "sg:address":"4309 Rolla Ln",
    "sg:city":"Madison",
    "sg:classifiers":[
        {
            "category":"Professional",
            "subcategory":"Lawyer & Legal Services",
            "type":"Services"
        }
    ],
    "sg:phone":"+1 608 232 0150",
    "sg:postcode":"53711",
    "sg:province":"WI",
    "wof:name":"Jlo Enterprises of Madison SC",
    "wof:placetype":"venue"
},
  "geometry": {"coordinates":[-89.449186,43.049514],"type":"Point"}
}