{
  "type": "Feature",
  "properties": {
    "iso:country":"US",
    "sg:address":"816 State Rd 23",
    "sg:city":"Princeton",
    "sg:classifiers":[
        {
            "category":"Restaurant",
            "type":"Food & Drink"
        }
    ],
    "sg:phone":"+1 920 295 4767",
    "sg:postcode":"54968",
    "sg:province":"WI",
    "wof:name":"Aunt Judy's Cafe",
    "wof:placetype":"venue"
},
  "geometry": {"coordinates":[-89.227396,43.83128],"type":"Point"}
}