{
  "type": "Feature",
  "properties": {
    "addr:full":"7395 Co Hwy H Stanley WI 54768",
    "addr:housenumber":"7395",
    "addr:postcode":"54768",
    "addr:street":"Co Hwy H",
    "iso:country":"US",
    "sg:address":"7395 Co Hwy H",
    "sg:city":"Stanley",
    "sg:classifiers":[
        {
            "category":"Retail",
            "subcategory":"Auto Repair",
            "type":"Services"
        }
    ],
    "sg:phone":"+1 715 644 3317",
    "sg:postcode":"54768",
    "sg:province":"WI",
    "sg:tags":[
        "general"
    ],
    "wof:name":"Integrity Automotive",
    "wof:placetype":"venue"
},
  "geometry": {"coordinates":[-90.93782400000001,44.947044],"type":"Point"}
}