{
  "type": "Feature",
  "properties": {
    "iso:country":"US",
    "sg:address":"915 Columbus St",
    "sg:city":"Manitowoc",
    "sg:classifiers":[
        {
            "category":"Real Estate",
            "subcategory":"Real Estate Agent",
            "type":"Services"
        }
    ],
    "sg:phone":"+1 920 684 7438",
    "sg:postcode":"54220",
    "sg:province":"WI",
    "wof:name":"Freedom Enterprises",
    "wof:placetype":"venue"
},
  "geometry": {"coordinates":[-87.660488,44.081973],"type":"Point"}
}