{
  "type": "Feature",
  "properties": {
    "iso:country":"US",
    "sg:address":"2527 S Business Dr",
    "sg:city":"Sheboygan",
    "sg:classifiers":[
        {
            "category":"Shopping",
            "subcategory":"Tobacco",
            "type":"Retail Goods"
        }
    ],
    "sg:phone":"+1 920 453 4294",
    "sg:postcode":"53081",
    "sg:province":"WI",
    "sg:tags":[
        "product"
    ],
    "wof:name":"Smokers Club",
    "wof:placetype":"venue"
},
  "geometry": {"coordinates":[-87.73195200000001,43.729359],"type":"Point"}
}