{
  "type": "Feature",
  "properties": {
    "iso:country":"US",
    "sg:address":"9961 Co Hwy H",
    "sg:city":"Marshfield",
    "sg:classifiers":[
        {
            "category":"Real Estate",
            "subcategory":"Real Estate Operator",
            "type":"Services"
        }
    ],
    "sg:phone":"+1 715 384 4111",
    "sg:postcode":"54449",
    "sg:province":"WI",
    "sg:tags":[
        "property",
        "lessor"
    ],
    "wof:name":"Joseph Weber",
    "wof:placetype":"venue"
},
  "geometry": {"coordinates":[-90.212171,44.655732],"type":"Point"}
}