{
  "type": "Feature",
  "properties": {
    "iso:country":"US",
    "sg:address":"1605 W Oklahoma Ave",
    "sg:city":"Milwaukee",
    "sg:classifiers":[
        {
            "category":"Retail",
            "subcategory":"Auto Repair",
            "type":"Services"
        }
    ],
    "sg:phone":"+1 414 647 1151",
    "sg:postcode":"53215",
    "sg:province":"WI",
    "sg:tags":[
        "general"
    ],
    "wof:name":"Kens Auto Services",
    "wof:placetype":"venue"
},
  "geometry": {"coordinates":[-87.934887,42.988271],"type":"Point"}
}