{
  "type": "Feature",
  "properties": {
    "iso:country":"US",
    "sg:address":"4131 Main Rd",
    "sg:city":"Plymouth",
    "sg:classifiers":[
        {
            "category":"Retail",
            "subcategory":"Auto Repair",
            "type":"Services"
        }
    ],
    "sg:phone":"+1 920 565 3738",
    "sg:postcode":"53073",
    "sg:province":"WI",
    "sg:tags":[
        "repairing",
        "automobile"
    ],
    "wof:name":"Jim's Auto Svc",
    "wof:placetype":"venue"
},
  "geometry": {"coordinates":[-87.898305,43.833761],"type":"Point"}
}