{
  "type": "Feature",
  "properties": {
    "iso:country":"US",
    "sg:address":"6534 Penny Ln",
    "sg:city":"Glenbeulah",
    "sg:classifiers":[
        {
            "category":"Building & Trades",
            "subcategory":"Landscaping Services",
            "type":"Services"
        }
    ],
    "sg:phone":"+1 920 526 3278",
    "sg:postcode":"53023",
    "sg:province":"WI",
    "wof:name":"Quality Stump & Tree Removal",
    "wof:placetype":"venue"
},
  "geometry": {"coordinates":[-88.09054500000001,43.77595],"type":"Point"}
}