{
  "type": "Feature",
  "properties": {
    "iso:country":"US",
    "sg:address":"5511 Co Rd Ee",
    "sg:city":"Bay City",
    "sg:classifiers":[
        {
            "category":"Farming",
            "subcategory":"Dairy Farm",
            "type":"Manufacturing & Wholesale Goods"
        }
    ],
    "sg:phone":"+1 715 594 3740",
    "sg:postcode":"54723",
    "sg:province":"WI",
    "wof:name":"Bob Furlon",
    "wof:placetype":"venue"
},
  "geometry": {"coordinates":[-92.41240000000001,44.616297],"type":"Point"}
}