{
  "type": "Feature",
  "properties": {
    "iso:country":"US",
    "sg:address":"1737 Park St",
    "sg:city":"Middleton",
    "sg:classifiers":[
        {
            "category":"Professional",
            "subcategory":"Business Services",
            "type":"Services"
        }
    ],
    "sg:phone":"+1 608 831 4544",
    "sg:postcode":"53562",
    "sg:province":"WI",
    "wof:name":"Sandra A A S I D Lewis",
    "wof:placetype":"venue"
},
  "geometry": {"coordinates":[-89.501729,43.094558],"type":"Point"}
}