{
  "type": "Feature",
  "properties": {
    "iso:country":"US",
    "sg:address":"7501 Parkview Rd",
    "sg:city":"Greendale",
    "sg:classifiers":[
        {
            "category":"Professional",
            "type":"Services"
        }
    ],
    "sg:phone":"+1 414 423 0157",
    "sg:postcode":"53129",
    "sg:province":"WI",
    "wof:name":"Calikay",
    "wof:placetype":"venue"
},
  "geometry": {"coordinates":[-88.00866499999999,42.938092],"type":"Point"}
}