{
  "type": "Feature",
  "properties": {
    "iso:country":"US",
    "sg:address":"1112 Powers St",
    "sg:city":"Oshkosh",
    "sg:classifiers":[
        {
            "category":"Banks & Credit Unions",
            "subcategory":"Bank",
            "type":"Services"
        }
    ],
    "sg:phone":"+1 920 230 4650",
    "sg:postcode":"54901",
    "sg:province":"WI",
    "sg:tags":[
        "loan",
        "real estate"
    ],
    "wof:name":"Home Mortgage Consultants",
    "wof:placetype":"venue"
},
  "geometry": {"coordinates":[-88.529391,44.03116],"type":"Point"}
}