{
  "type": "Feature",
  "properties": {
    "iso:country":"US",
    "sg:address":"16689 Co Hwy S N",
    "sg:city":"Boyd",
    "sg:phone":"+1 715 667 5380",
    "sg:postcode":"54726",
    "sg:province":"WI",
    "sg:tags":[
        "farm",
        "grain",
        "cash"
    ],
    "wof:name":"Peter Telisak",
    "wof:placetype":"venue"
},
  "geometry": {"coordinates":[-91.00421299999999,45.083549],"type":"Point"}
}