{
  "type": "Feature",
  "properties": {
    "addr:full":"13299 Carl Berg Rd Grantsburg WI 54840",
    "addr:housenumber":"13299",
    "addr:postcode":"54840",
    "addr:street":"Carl Berg Rd",
    "iso:country":"US",
    "sg:address":"13299 Carl Berg Rd",
    "sg:city":"Grantsburg",
    "sg:classifiers":[
        {
            "category":"Manufacturing",
            "subcategory":"Tools & Machinery",
            "type":"Manufacturing & Wholesale Goods"
        }
    ],
    "sg:phone":"+1 715 488 2365",
    "sg:postcode":"54840",
    "sg:province":"WI",
    "sg:tags":[
        "mfg"
    ],
    "wof:name":"Crex Tool & Mold Inc",
    "wof:placetype":"venue"
},
  "geometry": {"coordinates":[-92.66495500000001,45.671956],"type":"Point"}
}