{
  "type": "Feature",
  "properties": {
    "iso:country":"US",
    "sg:address":"1420 S Calhoun Rd",
    "sg:city":"New Berlin",
    "sg:classifiers":[
        {
            "category":"Retail",
            "subcategory":"Laundry & Dry Cleaning",
            "type":"Services"
        }
    ],
    "sg:phone":"+1 262 784 8432",
    "sg:postcode":"53151",
    "sg:province":"WI",
    "sg:tags":[
        "professional",
        "cleaners"
    ],
    "wof:name":"One Hour Martinizing",
    "wof:placetype":"venue"
},
  "geometry": {"coordinates":[-88.126926,43.01574],"type":"Point"}
}