{
  "type": "Feature",
  "properties": {
    "addr:full":"1803 Stonepine Bay Hudson WI 54016",
    "addr:housenumber":"1803",
    "addr:postcode":"54016",
    "addr:street":"Stonepine Bay",
    "iso:country":"US",
    "sg:address":"1803 Stonepine Bay",
    "sg:city":"Hudson",
    "sg:classifiers":[
        {
            "category":"Building & Trades",
            "subcategory":"Landscaping Services",
            "type":"Services"
        }
    ],
    "sg:phone":"+1 715 381 2919",
    "sg:postcode":"54016",
    "sg:province":"WI",
    "sg:tags":[
        "landscape"
    ],
    "wof:name":"Plantscapes",
    "wof:placetype":"venue"
},
  "geometry": {"coordinates":[-92.733137,44.971437],"type":"Point"}
}