{
  "type": "Feature",
  "properties": {
    "iso:country":"US",
    "sg:address":"1200 Industrial St",
    "sg:city":"Reedsburg",
    "sg:classifiers":[
        {
            "category":"Manufacturing",
            "subcategory":"Rubber & Plastics",
            "type":"Manufacturing & Wholesale Goods"
        }
    ],
    "sg:phone":"+1 608 524 2316",
    "sg:postcode":"53959",
    "sg:province":"WI",
    "sg:tags":[
        "product",
        "specialty",
        "mfg"
    ],
    "wof:name":"Cellox LLC",
    "wof:placetype":"venue"
},
  "geometry": {"coordinates":[-89.992441,43.524209],"type":"Point"}
}