{
  "type": "Feature",
  "properties": {
    "iso:country":"US",
    "sg:address":"1230 E Green Bay St",
    "sg:city":"Shawano",
    "sg:classifiers":[
        {
            "category":"Restaurant",
            "type":"Food & Drink"
        }
    ],
    "sg:menulink":"http://www.allmenus.com/wi/shawano/145744-subway/menu/",
    "sg:phone":"+1 715 524 3344",
    "sg:postcode":"54166",
    "sg:province":"WI",
    "sg:tags":[
        "american",
        "sandwich"
    ],
    "wof:name":"Subway",
    "wof:placetype":"venue"
},
  "geometry": {"coordinates":[-88.58859699999999,44.782183],"type":"Point"}
}