{
  "type": "Feature",
  "properties": {
    "iso:country":"US",
    "sg:address":"1320 S West Ave",
    "sg:city":"Waukesha",
    "sg:classifiers":[
        {
            "category":"Building & Trades",
            "subcategory":"Equipment Rental",
            "type":"Services"
        }
    ],
    "sg:phone":"+1 262 547 6201",
    "sg:postcode":"53186",
    "sg:province":"WI",
    "sg:tags":[
        "tool"
    ],
    "wof:name":"Budget Rental Center",
    "wof:placetype":"venue"
},
  "geometry": {"coordinates":[-88.237182,42.990764],"type":"Point"}
}