{
  "type": "Feature",
  "properties": {
    "iso:country":"US",
    "sg:address":"8701 Co Rd Ee",
    "sg:city":"Portage",
    "sg:classifiers":[
        {
            "category":"Building & Trades",
            "subcategory":"Construction",
            "type":"Services"
        }
    ],
    "sg:phone":"+1 608 742 2677",
    "sg:postcode":"53901",
    "sg:province":"WI",
    "sg:tags":[
        "excavation",
        "contractor"
    ],
    "wof:name":"Curtis Excavating Inc",
    "wof:placetype":"venue"
},
  "geometry": {"coordinates":[-89.36486600000001,43.591922],"type":"Point"}
}