{
  "type": "Feature",
  "properties": {
    "iso:country":"US",
    "sg:address":"16935 W Wisconsin Ave",
    "sg:city":"Brookfield",
    "sg:classifiers":[
        {
            "category":"Insurance",
            "subcategory":"Insurance Agent",
            "type":"Services"
        }
    ],
    "sg:phone":"+1 262 827 0600",
    "sg:postcode":"53005",
    "sg:province":"WI",
    "wof:name":"J P & Associates Inc",
    "wof:placetype":"venue"
},
  "geometry": {"coordinates":[-88.124146,43.039766],"type":"Point"}
}