{
  "type": "Feature",
  "properties": {
    "iso:country":"US",
    "sg:address":"1380 105th Ave",
    "sg:city":"Amery",
    "sg:classifiers":[
        {
            "category":"Building & Trades",
            "subcategory":"Landscaping Services",
            "type":"Services"
        }
    ],
    "sg:phone":"+1 715 268 5168",
    "sg:postcode":"54001",
    "sg:province":"WI",
    "sg:tags":[
        "landscape"
    ],
    "wof:name":"Gardens By Design",
    "wof:placetype":"venue"
},
  "geometry": {"coordinates":[-92.44148800000001,45.360851],"type":"Point"}
}