{
  "type": "Feature",
  "properties": {
    "iso:country":"US",
    "sg:address":"9976 Birch Circle Rd",
    "sg:city":"Ladysmith",
    "sg:classifiers":[
        {
            "category":"Professional",
            "type":"Services"
        }
    ],
    "sg:phone":"+1 715 532 3434",
    "sg:postcode":"54848",
    "sg:province":"WI",
    "sg:tags":[
        "establishment"
    ],
    "wof:name":"Parker Doug & Rhonda Memories",
    "wof:placetype":"venue"
},
  "geometry": {"coordinates":[-91.187349,45.412195],"type":"Point"}
}