{
  "type": "Feature",
  "properties": {
    "addr:full":"2300 Opportunity Ln Plover WI 54467",
    "addr:housenumber":"2300",
    "addr:postcode":"54467",
    "addr:street":"Opportunity Ln",
    "iso:country":"US",
    "sg:address":"2300 Opportunity Ln",
    "sg:city":"Plover",
    "sg:classifiers":[
        {
            "category":"Building & Trades",
            "subcategory":"Equipment Rental",
            "type":"Services"
        }
    ],
    "sg:phone":"+1 715 343 1382",
    "sg:postcode":"54467",
    "sg:province":"WI",
    "wof:name":"Brr Rentals LLC",
    "wof:placetype":"venue"
},
  "geometry": {"coordinates":[-89.53434799999999,44.462652],"type":"Point"}
}