{
  "type": "Feature",
  "properties": {
    "iso:country":"US",
    "sg:address":"9964 Irish Ridge Rd",
    "sg:city":"Cassville",
    "sg:classifiers":[
        {
            "category":"Farming",
            "subcategory":"Dairy Farm",
            "type":"Manufacturing & Wholesale Goods"
        }
    ],
    "sg:phone":"+1 608 725 5866",
    "sg:postcode":"53806",
    "sg:province":"WI",
    "wof:name":"Uppena Farm",
    "wof:placetype":"venue"
},
  "geometry": {"coordinates":[-90.90024,42.704047],"type":"Point"}
}