{
  "type": "Feature",
  "properties": {
    "iso:country":"US",
    "sg:address":"3310 N 82nd St",
    "sg:city":"Milwaukee",
    "sg:classifiers":[
        {
            "category":"Marine",
            "type":"Transportation"
        }
    ],
    "sg:phone":"+1 414 276 0793",
    "sg:postcode":"53222",
    "sg:province":"WI",
    "sg:tags":[
        "water",
        "station",
        "gasoline",
        "transport"
    ],
    "wof:name":"Admirals Wharf Inc",
    "wof:placetype":"venue"
},
  "geometry": {"coordinates":[-88.01469,43.080124],"type":"Point"}
}