{
  "type": "Feature",
  "properties": {
    "addr:full":"6709 Watts Rd Madison WI 53719",
    "addr:housenumber":"6709",
    "addr:postcode":"53719",
    "addr:street":"Watts Rd",
    "iso:country":"US",
    "sg:address":"6709 Watts Rd",
    "sg:city":"Madison",
    "sg:classifiers":[
        {
            "category":"Wholesale",
            "subcategory":"Hardware",
            "type":"Manufacturing & Wholesale Goods"
        },
        {
            "category":"Home & Garden",
            "subcategory":"Home Furnishings",
            "type":"Retail Goods"
        }
    ],
    "sg:phone":"+1 608 276 6010",
    "sg:postcode":"53719",
    "sg:province":"WI",
    "sg:tags":[
        "stove",
        "wood",
        "fireplace",
        "burning"
    ],
    "sg:website":"www.firesideusa.com",
    "wof:name":"Fireside Hearth & Home",
    "wof:placetype":"venue"
},
  "geometry": {"coordinates":[-89.50132600000001,43.050118],"type":"Point"}
}