{
  "type": "Feature",
  "properties": {
    "iso:country":"US",
    "sg:address":"1024 Thomas St",
    "sg:city":"Ripon",
    "sg:classifiers":[
        {
            "category":"Manufacturing",
            "subcategory":"Retail Goods",
            "type":"Manufacturing & Wholesale Goods"
        }
    ],
    "sg:phone":"+1 920 748 5506",
    "sg:postcode":"54971",
    "sg:province":"WI",
    "sg:tags":[
        "product",
        "mfg"
    ],
    "wof:name":"Geisler Industries LLC",
    "wof:placetype":"venue"
},
  "geometry": {"coordinates":[-88.845058,43.836016],"type":"Point"}
}