{
  "type": "Feature",
  "properties": {
    "iso:country":"US",
    "sg:address":"305 Blue View Dr",
    "sg:city":"Mount Horeb",
    "sg:classifiers":[
        {
            "category":"Building & Trades",
            "subcategory":"Plumbing",
            "type":"Services"
        }
    ],
    "sg:phone":"+1 608 437 5734",
    "sg:postcode":"53572",
    "sg:province":"WI",
    "sg:tags":[
        "plumbing",
        "contractor"
    ],
    "wof:name":"Landen Plumbing Service & Repr",
    "wof:placetype":"venue"
},
  "geometry": {"coordinates":[-89.733074,43.017134],"type":"Point"}
}