{
  "type": "Feature",
  "properties": {
    "addr:full":"806 N Sandy Ln Elkhorn WI 53121",
    "addr:housenumber":"806",
    "addr:postcode":"53121",
    "addr:street":"N Sandy Ln",
    "iso:country":"US",
    "sg:address":"806 N Sandy Ln",
    "sg:city":"Elkhorn",
    "sg:classifiers":[
        {
            "category":"Home & Garden",
            "subcategory":"Building Materials",
            "type":"Retail Goods"
        }
    ],
    "sg:phone":"+1 262 723 5114",
    "sg:postcode":"53121",
    "sg:province":"WI",
    "wof:name":"Kohler Overhead Door",
    "wof:placetype":"venue"
},
  "geometry": {"coordinates":[-88.53907100000001,42.685019],"type":"Point"}
}