{
  "type": "Feature",
  "properties": {
    "iso:country":"US",
    "sg:address":"1243 Elmwood Ave",
    "sg:city":"Ixonia",
    "sg:classifiers":[
        {
            "category":"Wholesale",
            "subcategory":"Construction Materials",
            "type":"Manufacturing & Wholesale Goods"
        },
        {
            "category":"Building & Trades",
            "subcategory":"Construction",
            "type":"Services"
        }
    ],
    "sg:phone":"+1 920 206 6284",
    "sg:postcode":"53036",
    "sg:province":"WI",
    "sg:tags":[
        "granite",
        "merchandise",
        "contractor"
    ],
    "wof:name":"Designs In Marble LLC",
    "wof:placetype":"venue"
},
  "geometry": {"coordinates":[-88.593647,43.140421],"type":"Point"}
}