{
  "type": "Feature",
  "properties": {
    "iso:country":"US",
    "sg:address":"1020 Westfield Ln",
    "sg:city":"Neenah",
    "sg:classifiers":[
        {
            "category":"Insurance",
            "subcategory":"Insurance Agent",
            "type":"Services"
        }
    ],
    "sg:phone":"+1 920 722 9194",
    "sg:postcode":"54956",
    "sg:province":"WI",
    "wof:name":"Knights Of Columbus Insurance",
    "wof:placetype":"venue"
},
  "geometry": {"coordinates":[-88.484225,44.21713],"type":"Point"}
}