{
  "type": "Feature",
  "properties": {
    "iso:country":"US",
    "sg:address":"17 N 2nd St",
    "sg:city":"Barron",
    "sg:classifiers":[
        {
            "category":"Organizations",
            "subcategory":"Religious Organization",
            "type":"Services"
        }
    ],
    "sg:phone":"+1 715 637 3299",
    "sg:postcode":"54812",
    "sg:province":"WI",
    "wof:name":"Dicks Lawn Care Service",
    "wof:placetype":"venue"
},
  "geometry": {"coordinates":[-91.85537,45.402221],"type":"Point"}
}