{
  "type": "Feature",
  "properties": {
    "iso:country":"US",
    "sg:address":"6205 E Wickstrom St",
    "sg:city":"South Range",
    "sg:classifiers":[
        {
            "category":"Government",
            "subcategory":"Post Office",
            "type":"Public Place"
        }
    ],
    "sg:phone":"+1 715 398 7107",
    "sg:postcode":"54874",
    "sg:province":"WI",
    "wof:name":"US Post Office",
    "wof:placetype":"venue"
},
  "geometry": {"coordinates":[-91.982491,46.608669],"type":"Point"}
}