{
  "type": "Feature",
  "properties": {
    "iso:country":"US",
    "sg:address":"8500 W Capitol Dr",
    "sg:city":"Milwaukee",
    "sg:classifiers":[
        {
            "category":"Insurance",
            "subcategory":"Insurance Agent",
            "type":"Services"
        }
    ],
    "sg:phone":"+1 414 527 4288",
    "sg:postcode":"53222",
    "sg:province":"WI",
    "wof:name":"State Farm Insurance",
    "wof:placetype":"venue"
},
  "geometry": {"coordinates":[-88.020152,43.089795],"type":"Point"}
}