{
  "type": "Feature",
  "properties": {
    "iso:country":"US",
    "sg:address":"43255 Co Hwy D",
    "sg:city":"Cable",
    "sg:classifiers":[
        {
            "category":"Travel",
            "subcategory":"Hotels & Motels",
            "type":"Entertainment"
        }
    ],
    "sg:phone":"+1 715 794 2127",
    "sg:postcode":"54821",
    "sg:province":"WI",
    "sg:tags":[
        "operation",
        "drinking"
    ],
    "wof:name":"Namakagon Chief Resort",
    "wof:placetype":"venue"
},
  "geometry": {"coordinates":[-91.074201,46.200647],"type":"Point"}
}