{
  "type": "Feature",
  "properties": {
    "iso:country":"US",
    "sg:address":"1002 E 5th St",
    "sg:city":"Shawano",
    "sg:classifiers":[
        {
            "category":"Insurance",
            "subcategory":"Insurance Agent",
            "type":"Services"
        }
    ],
    "sg:phone":"+1 715 526 7788",
    "sg:postcode":"54166",
    "sg:province":"WI",
    "wof:name":"Asenbrenner Insurance Inc",
    "wof:placetype":"venue"
},
  "geometry": {"coordinates":[-88.592298,44.782965],"type":"Point"}
}