{
  "type": "Feature",
  "properties": {
    "addr:full":"200 Prospect Pl De Pere WI 54115",
    "addr:housenumber":"200",
    "addr:postcode":"54115",
    "addr:street":"Prospect Pl",
    "iso:country":"US",
    "sg:address":"200 Prospect Pl",
    "sg:city":"De Pere",
    "sg:classifiers":[
        {
            "category":"Organizations",
            "subcategory":"Membership Organization",
            "type":"Services"
        }
    ],
    "sg:phone":"+1 920 336 0383",
    "sg:postcode":"54115",
    "sg:province":"WI",
    "wof:name":"Aa",
    "wof:placetype":"venue"
},
  "geometry": {"coordinates":[-88.07412600000001,44.434961],"type":"Point"}
}