{
  "type": "Feature",
  "properties": {
    "iso:country":"US",
    "sg:address":"555 N Pioneer Rd",
    "sg:city":"Fond Du Lac",
    "sg:classifiers":[
        {
            "category":"Freight",
            "type":"Transportation"
        }
    ],
    "sg:phone":"+1 920 922 9855",
    "sg:postcode":"54937",
    "sg:province":"WI",
    "sg:tags":[
        "trucking"
    ],
    "wof:name":"Kingsway Express LLC",
    "wof:placetype":"venue"
},
  "geometry": {"coordinates":[-88.483038,43.794853],"type":"Point"}
}