{
  "type": "Feature",
  "properties": {
    "iso:country":"US",
    "sg:address":"15383 Northway Dr",
    "sg:city":"Menomonee Falls",
    "sg:classifiers":[
        {
            "category":"Professional",
            "type":"Services"
        }
    ],
    "sg:phone":"+1 262 781 6082",
    "sg:postcode":"53051",
    "sg:province":"WI",
    "wof:name":"Jeffery Johnson",
    "wof:placetype":"venue"
},
  "geometry": {"coordinates":[-88.10330999999999,43.117315],"type":"Point"}
}