{
  "type": "Feature",
  "properties": {
    "addr:full":"9219 Lyons Rd New London WI 54961",
    "addr:housenumber":"9219",
    "addr:postcode":"54961",
    "addr:street":"Lyons Rd",
    "iso:country":"US",
    "sg:address":"9219 Lyons Rd",
    "sg:city":"New London",
    "sg:classifiers":[
        {
            "category":"Banks & Credit Unions",
            "subcategory":"Investment Brokerage",
            "type":"Services"
        }
    ],
    "sg:phone":"+1 920 982 2584",
    "sg:postcode":"54961",
    "sg:province":"WI",
    "sg:tags":[
        "advisory",
        "financial"
    ],
    "wof:name":"Larson Financial Svc",
    "wof:placetype":"venue"
},
  "geometry": {"coordinates":[-88.76252599999999,44.364137],"type":"Point"}
}