{
  "type": "Feature",
  "properties": {
    "iso:country":"US",
    "sg:address":"1797 Co Rd J",
    "sg:city":"Wisconsin Dells",
    "sg:classifiers":[
        {
            "category":"Government",
            "subcategory":"Office",
            "type":"Public Place"
        }
    ],
    "sg:phone":"+1 608 254 7491",
    "sg:postcode":"53965",
    "sg:province":"WI",
    "sg:tags":[
        "city"
    ],
    "wof:name":"Town Hall",
    "wof:placetype":"venue"
},
  "geometry": {"coordinates":[-89.868266,43.648354],"type":"Point"}
}