{
  "type": "Feature",
  "properties": {
    "iso:country":"US",
    "sg:address":"10005 N Raven Rd",
    "sg:city":"Hayward",
    "sg:classifiers":[
        {
            "category":"Personal",
            "subcategory":"Beauty Salon",
            "type":"Services"
        }
    ],
    "sg:phone":"+1 715 634 8234",
    "sg:postcode":"54843",
    "sg:province":"WI",
    "sg:tags":[
        "shop"
    ],
    "wof:name":"Town & Country Beauty Salon",
    "wof:placetype":"venue"
},
  "geometry": {"coordinates":[-91.497007,45.996285],"type":"Point"}
}