{
  "type": "Feature",
  "properties": {
    "iso:country":"US",
    "sg:address":"133 S Michigan St",
    "sg:city":"Prairie Du Chien",
    "sg:classifiers":[
        {
            "category":"Education",
            "subcategory":"College",
            "type":"Public Place"
        }
    ],
    "sg:phone":"+1 608 326 4292",
    "sg:postcode":"53821",
    "sg:province":"WI",
    "wof:name":"Upper Iowa University",
    "wof:placetype":"venue"
},
  "geometry": {"coordinates":[-91.14379700000001,43.05133],"type":"Point"}
}