{
  "type": "Feature",
  "properties": {
    "addr:full":"3226 Kingsley Way Madison WI 53713",
    "addr:housenumber":"3226",
    "addr:postcode":"53713",
    "addr:street":"Kingsley Way",
    "iso:country":"US",
    "sg:address":"3226 Kingsley Way",
    "sg:city":"Madison",
    "sg:classifiers":[
        {
            "category":"Professional",
            "subcategory":"Business Services",
            "type":"Services"
        }
    ],
    "sg:phone":"+1 608 274 6400",
    "sg:postcode":"53713",
    "sg:province":"WI",
    "sg:tags":[
        "water",
        "treatment"
    ],
    "wof:name":"Rain Soft-Dane County",
    "wof:placetype":"venue"
},
  "geometry": {"coordinates":[-89.401577,43.029129],"type":"Point"}
}