{
  "type": "Feature",
  "properties": {
    "iso:country":"US",
    "sg:address":"5111 Wright Ave",
    "sg:city":"Racine",
    "sg:classifiers":[
        {
            "category":"Social Services",
            "subcategory":"Adult Care",
            "type":"Services"
        }
    ],
    "sg:phone":"+1 262 638 2600",
    "sg:postcode":"53406",
    "sg:province":"WI",
    "sg:tags":[
        "home",
        "for",
        "elderly"
    ],
    "wof:name":"Danish-American",
    "wof:placetype":"venue"
},
  "geometry": {"coordinates":[-87.840729,42.715035],"type":"Point"}
}