{
  "type": "Feature",
  "properties": {
    "iso:country":"US",
    "sg:address":"3805 S Casper Dr",
    "sg:city":"New Berlin",
    "sg:classifiers":[
        {
            "category":"Recreation",
            "type":"Entertainment"
        }
    ],
    "sg:phone":"+1 262 797 2443",
    "sg:postcode":"53151",
    "sg:province":"WI",
    "sg:tags":[
        "parks"
    ],
    "wof:name":"New Berlin Parks & Recreation",
    "wof:placetype":"venue"
},
  "geometry": {"coordinates":[-88.11846,42.97335],"type":"Point"}
}