{
  "type": "Feature",
  "properties": {
    "addr:full":"1760 Dublin Trl Neenah WI 54956",
    "addr:housenumber":"1760",
    "addr:postcode":"54956",
    "addr:street":"Dublin Trl",
    "iso:country":"US",
    "sg:address":"1760 Dublin Trl",
    "sg:city":"Neenah",
    "sg:classifiers":[
        {
            "category":"Real Estate",
            "subcategory":"Real Estate Agent",
            "type":"Services"
        }
    ],
    "sg:phone":"+1 920 969 9140",
    "sg:postcode":"54956",
    "sg:province":"WI",
    "wof:name":"Premier Real Estate",
    "wof:placetype":"venue"
},
  "geometry": {"coordinates":[-88.50782100000001,44.224543],"type":"Point"}
}