{
  "type": "Feature",
  "properties": {
    "iso:country":"US",
    "sg:address":"6970 Rock Ridge Ct",
    "sg:city":"Verona",
    "sg:classifiers":[
        {
            "category":"Building & Trades",
            "subcategory":"Construction",
            "type":"Services"
        }
    ],
    "sg:phone":"+1 608 845 7131",
    "sg:postcode":"53593",
    "sg:province":"WI",
    "sg:tags":[
        "residential"
    ],
    "wof:name":"Pulver Construction",
    "wof:placetype":"venue"
},
  "geometry": {"coordinates":[-89.529831,43.011936],"type":"Point"}
}