{
  "type": "Feature",
  "properties": {
    "iso:country":"US",
    "sg:address":"1037 Riders Club Rd",
    "sg:city":"Onalaska",
    "sg:classifiers":[
        {
            "category":"Professional",
            "subcategory":"Business Services",
            "type":"Services"
        }
    ],
    "sg:phone":"+1 608 779 2227",
    "sg:postcode":"54650",
    "sg:province":"WI",
    "sg:tags":[
        "computer",
        "design",
        "system"
    ],
    "wof:name":"Rivercrest Technologies Inc",
    "wof:placetype":"venue"
},
  "geometry": {"coordinates":[-91.22261,43.905601],"type":"Point"}
}