{
  "type": "Feature",
  "properties": {
    "iso:country":"US",
    "sg:address":"915 Duchess Ct",
    "sg:city":"Oconomowoc",
    "sg:classifiers":[
        {
            "category":"Professional",
            "type":"Services"
        }
    ],
    "sg:phone":"+1 262 569 9628",
    "sg:postcode":"53066",
    "sg:province":"WI",
    "wof:name":"Stencel Military Art",
    "wof:placetype":"venue"
},
  "geometry": {"coordinates":[-88.52237,43.101463],"type":"Point"}
}