{
  "type": "Feature",
  "properties": {
    "iso:country":"US",
    "sg:address":"27625 Gables Rd",
    "sg:city":"Webster",
    "sg:classifiers":[
        {
            "category":"Travel",
            "subcategory":"Campground",
            "type":"Entertainment"
        }
    ],
    "sg:phone":"+1 715 866 7268",
    "sg:postcode":"54893",
    "sg:province":"WI",
    "sg:tags":[
        "drinking",
        "trailer"
    ],
    "wof:name":"Devils Lake Park Resort",
    "wof:placetype":"venue"
},
  "geometry": {"coordinates":[-92.344805,45.916154],"type":"Point"}
}