{
  "type": "Feature",
  "properties": {
    "iso:country":"US",
    "sg:address":"304 Urquhart Rd",
    "sg:city":"Stanley",
    "sg:classifiers":[
        {
            "category":"Building & Trades",
            "subcategory":"Plumbing",
            "type":"Services"
        }
    ],
    "sg:phone":"+1 715 644 2482",
    "sg:postcode":"54768",
    "sg:province":"WI",
    "sg:tags":[
        "air",
        "heating",
        "conditioning",
        "contractor"
    ],
    "wof:name":"Classic Heating & Air",
    "wof:placetype":"venue"
},
  "geometry": {"coordinates":[-90.953157,44.955064],"type":"Point"}
}