{
  "type": "Feature",
  "properties": {
    "iso:country":"US",
    "sg:address":"4175 N 35th St",
    "sg:city":"Milwaukee",
    "sg:classifiers":[
        {
            "category":"Professional",
            "type":"Services"
        }
    ],
    "sg:phone":"+1 414 483 9742",
    "sg:postcode":"53216",
    "sg:province":"WI",
    "wof:name":"National Chapter of Heavy",
    "wof:placetype":"venue"
},
  "geometry": {"coordinates":[-87.957072,43.092104],"type":"Point"}
}