{
  "type": "Feature",
  "properties": {
    "iso:country":"US",
    "sg:address":"225 Main St",
    "sg:city":"Elroy",
    "sg:classifiers":[
        {
            "category":"Government",
            "subcategory":"Office",
            "type":"Public Place"
        }
    ],
    "sg:phone":"+1 608 462 2429",
    "sg:postcode":"53929",
    "sg:province":"WI",
    "sg:tags":[
        "village"
    ],
    "wof:name":"Elroy City Garage",
    "wof:placetype":"venue"
},
  "geometry": {"coordinates":[-90.27137999999999,43.739849],"type":"Point"}
}