{
  "type": "Feature",
  "properties": {
    "iso:country":"US",
    "sg:address":"775 Co Rd D",
    "sg:city":"Mineral Point",
    "sg:phone":"+1 608 987 2027",
    "sg:postcode":"53565",
    "sg:province":"WI",
    "sg:tags":[
        "farm",
        "corn",
        "soybean"
    ],
    "wof:name":"Timothy Wiesbrook",
    "wof:placetype":"venue"
},
  "geometry": {"coordinates":[-90.07315,42.8564],"type":"Point"}
}