{
  "type": "Feature",
  "properties": {
    "iso:country":"US",
    "sg:address":"440 Fredonia Ave",
    "sg:city":"Fredonia",
    "sg:classifiers":[
        {
            "category":"Shopping",
            "type":"Retail Goods"
        }
    ],
    "sg:phone":"+1 262 692 6006",
    "sg:postcode":"53021",
    "sg:province":"WI",
    "sg:tags":[
        "product",
        "wood"
    ],
    "wof:name":"Sandberg Manufacturing",
    "wof:placetype":"venue"
},
  "geometry": {"coordinates":[-87.95200800000001,43.470138],"type":"Point"}
}