{
  "type": "Feature",
  "properties": {
    "iso:country":"US",
    "sg:address":"2659 N 22nd St",
    "sg:city":"Milwaukee",
    "sg:classifiers":[
        {
            "category":"Organizations",
            "subcategory":"Religious Organization",
            "type":"Services"
        }
    ],
    "sg:phone":"+1 414 372 5030",
    "sg:postcode":"53206",
    "sg:province":"WI",
    "sg:tags":[
        "church"
    ],
    "wof:name":"First Bible Missionary Baptist",
    "wof:placetype":"venue"
},
  "geometry": {"coordinates":[-87.940069,43.066746],"type":"Point"}
}