{
  "type": "Feature",
  "properties": {
    "iso:country":"US",
    "sg:address":"429 Redman Dr",
    "sg:city":"Ripon",
    "sg:classifiers":[
        {
            "category":"Professional",
            "subcategory":"Engineering",
            "type":"Services"
        }
    ],
    "sg:phone":"+1 920 748 1220",
    "sg:postcode":"54971",
    "sg:province":"WI",
    "wof:name":"Steffen Engineering Inc",
    "wof:placetype":"venue"
},
  "geometry": {"coordinates":[-88.848129,43.851237],"type":"Point"}
}