{
  "type": "Feature",
  "properties": {
    "addr:full":"18615 W Bluemound Rd Brookfield WI 53045",
    "addr:housenumber":"18615",
    "addr:postcode":"53045",
    "addr:street":"W Bluemound Rd",
    "iso:country":"US",
    "sg:address":"18615 W Bluemound Rd",
    "sg:city":"Brookfield",
    "sg:classifiers":[
        {
            "category":"Home & Garden",
            "subcategory":"Furniture",
            "type":"Retail Goods"
        }
    ],
    "sg:phone":"+1 262 827 8898",
    "sg:postcode":"53045",
    "sg:province":"WI",
    "wof:name":"Boston Store Furniture Gallery",
    "wof:placetype":"venue"
},
  "geometry": {"coordinates":[-88.143675,43.036259],"type":"Point"}
}