{
  "type": "Feature",
  "properties": {
    "iso:country":"US",
    "sg:address":"2070 Wisconsin Ave",
    "sg:city":"Grafton",
    "sg:classifiers":[
        {
            "category":"Professional",
            "subcategory":"Lawyer & Legal Services",
            "type":"Services"
        }
    ],
    "sg:phone":"+1 262 387 0706",
    "sg:postcode":"53024",
    "sg:province":"WI",
    "wof:name":"Kitzke & Associates Sc",
    "wof:placetype":"venue"
},
  "geometry": {"coordinates":[-87.960161,43.305232],"type":"Point"}
}