{
  "type": "Feature",
  "properties": {
    "iso:country":"US",
    "sg:address":"1409 W Zedler Ln",
    "sg:city":"Thiensville",
    "sg:classifiers":[
        {
            "category":"Professional",
            "type":"Services"
        }
    ],
    "sg:phone":"+1 262 241 3776",
    "sg:postcode":"53092",
    "sg:province":"WI",
    "wof:name":"Kc Service",
    "wof:placetype":"venue"
},
  "geometry": {"coordinates":[-87.929258,43.199456],"type":"Point"}
}