{
  "type": "Feature",
  "properties": {
    "iso:country":"US",
    "sg:address":"115 W 4th St",
    "sg:city":"Blair",
    "sg:classifiers":[
        {
            "category":"Shopping",
            "type":"Retail Goods"
        }
    ],
    "sg:phone":"+1 608 989 2383",
    "sg:postcode":"54616",
    "sg:province":"WI",
    "sg:tags":[
        "monument"
    ],
    "wof:name":"Jack Funeral Homes",
    "wof:placetype":"venue"
},
  "geometry": {"coordinates":[-91.231927,44.290881],"type":"Point"}
}