{
  "type": "Feature",
  "properties": {
    "iso:country":"US",
    "sg:address":"825 Ela Ave",
    "sg:city":"Waterford",
    "sg:classifiers":[
        {
            "category":"Local Transit",
            "type":"Transportation"
        }
    ],
    "sg:phone":"+1 262 534 4780",
    "sg:postcode":"53185",
    "sg:province":"WI",
    "sg:tags":[
        "bus",
        "line"
    ],
    "wof:name":"S & J Svc Inc",
    "wof:placetype":"venue"
},
  "geometry": {"coordinates":[-88.227769,42.751398],"type":"Point"}
}