{
  "type": "Feature",
  "properties": {
    "iso:country":"US",
    "sg:address":"303 E College Ave",
    "sg:city":"Appleton",
    "sg:classifiers":[
        {
            "category":"Retail",
            "subcategory":"Laundry & Dry Cleaning",
            "type":"Services"
        }
    ],
    "sg:phone":"+1 920 731 1116",
    "sg:postcode":"54911",
    "sg:province":"WI",
    "sg:tags":[
        "repairing",
        "garment",
        "fur"
    ],
    "wof:name":"Ave Fur Vault",
    "wof:placetype":"venue"
},
  "geometry": {"coordinates":[-88.40100200000001,44.26174],"type":"Point"}
}