{
  "type": "Feature",
  "properties": {
    "iso:country":"US",
    "sg:address":"5714 W North Ave",
    "sg:city":"Milwaukee",
    "sg:classifiers":[
        {
            "category":"Retail",
            "subcategory":"Auto Repair",
            "type":"Services"
        }
    ],
    "sg:phone":"+1 414 442 8500",
    "sg:postcode":"53208",
    "sg:province":"WI",
    "sg:tags":[
        "automotive"
    ],
    "wof:name":"North Avenue Automotive",
    "wof:placetype":"venue"
},
  "geometry": {"coordinates":[-87.985178,43.060767],"type":"Point"}
}