{
  "type": "Feature",
  "properties": {
    "iso:country":"US",
    "sg:address":"3510 W Tomahawk Trl",
    "sg:city":"Montello",
    "sg:classifiers":[
        {
            "category":"Travel",
            "subcategory":"Campground",
            "type":"Entertainment"
        }
    ],
    "sg:phone":"+1 920 295 3389",
    "sg:postcode":"53949",
    "sg:province":"WI",
    "wof:name":"Lakeside Campground",
    "wof:placetype":"venue"
},
  "geometry": {"coordinates":[-89.18461499999999,43.767453],"type":"Point"}
}