{
  "type": "Feature",
  "properties": {
    "iso:country":"US",
    "sg:address":"3540 N 126th St",
    "sg:city":"Brookfield",
    "sg:classifiers":[
        {
            "category":"Manufacturing",
            "subcategory":"Printing",
            "type":"Manufacturing & Wholesale Goods"
        }
    ],
    "sg:phone":"+1 262 790 5210",
    "sg:postcode":"53005",
    "sg:province":"WI",
    "sg:tags":[
        "publisher"
    ],
    "sg:website":"www.musick8.com",
    "wof:name":"Plank Road Publishing",
    "wof:placetype":"venue"
},
  "geometry": {"coordinates":[-88.068979,43.083819],"type":"Point"}
}