{
  "type": "Feature",
  "properties": {
    "addr:full":"3352 Quincy Ave Madison WI 53704",
    "addr:housenumber":"3352",
    "addr:postcode":"53704",
    "addr:street":"Quincy Ave",
    "iso:country":"US",
    "sg:address":"3352 Quincy Ave",
    "sg:city":"Madison",
    "sg:classifiers":[
        {
            "category":"Shopping",
            "subcategory":"Hobbies, Toys, & Games",
            "type":"Retail Goods"
        }
    ],
    "sg:phone":"+1 608 244 0503",
    "sg:postcode":"53704",
    "sg:province":"WI",
    "wof:name":"Eyetooth Diversions",
    "wof:placetype":"venue"
},
  "geometry": {"coordinates":[-89.33555,43.111953],"type":"Point"}
}