{
  "type": "Feature",
  "properties": {
    "addr:full":"5986 Peak Hill Rd Loganville WI 53943",
    "addr:housenumber":"5986",
    "addr:postcode":"53943",
    "addr:street":"Peak Hill Rd",
    "iso:country":"US",
    "sg:address":"5986 Peak Hill Rd",
    "sg:city":"Loganville",
    "sg:classifiers":[
        {
            "category":"Farming",
            "subcategory":"Livestock Farm",
            "type":"Manufacturing & Wholesale Goods"
        }
    ],
    "sg:phone":"+1 608 727 2067",
    "sg:postcode":"53943",
    "sg:province":"WI",
    "sg:tags":[
        "beef",
        "feedlot",
        "cattle"
    ],
    "wof:name":"Jim Phillippi",
    "wof:placetype":"venue"
},
  "geometry": {"coordinates":[-90.027489,43.429623],"type":"Point"}
}