{
  "type": "Feature",
  "properties": {
    "iso:country":"US",
    "sg:address":"8947 Hudson Rd",
    "sg:city":"Clintonville",
    "sg:classifiers":[
        {
            "category":"Organizations",
            "subcategory":"Community Association",
            "type":"Services"
        }
    ],
    "sg:phone":"+1 715 823 5353",
    "sg:postcode":"54929",
    "sg:province":"WI",
    "wof:name":"International Assoc of LI",
    "wof:placetype":"venue"
},
  "geometry": {"coordinates":[-88.776303,44.628695],"type":"Point"}
}