{
  "type": "Feature",
  "properties": {
    "iso:country":"US",
    "sg:address":"703 Amron Ave",
    "sg:city":"Antigo",
    "sg:classifiers":[
        {
            "category":"Manufacturing",
            "subcategory":"Retail Goods",
            "type":"Manufacturing & Wholesale Goods"
        }
    ],
    "sg:phone":"+1 715 627 5500",
    "sg:postcode":"54409",
    "sg:province":"WI",
    "sg:tags":[
        "product",
        "mfg"
    ],
    "wof:name":"Sweeney Mfg",
    "wof:placetype":"venue"
},
  "geometry": {"coordinates":[-89.153581,45.166243],"type":"Point"}
}