{
  "type": "Feature",
  "properties": {
    "iso:country":"US",
    "sg:address":"1136 W Mason St",
    "sg:city":"Green Bay",
    "sg:classifiers":[
        {
            "category":"Building & Trades",
            "subcategory":"Cleaning & Sanitation",
            "type":"Services"
        },
        {
            "category":"Retail",
            "subcategory":"Repair Shop",
            "type":"Services"
        }
    ],
    "sg:phone":"+1 920 499 8287",
    "sg:postcode":"54303",
    "sg:province":"WI",
    "sg:tags":[
        "polishing",
        "waxing",
        "floor"
    ],
    "wof:name":"Neat 'n Clean",
    "wof:placetype":"venue"
},
  "geometry": {"coordinates":[-88.045979,44.517431],"type":"Point"}
}