{
  "type": "Feature",
  "properties": {
    "iso:country":"US",
    "sg:address":"8101 Schofield Ave",
    "sg:city":"Schofield",
    "sg:classifiers":[
        {
            "category":"Bars & Pubs",
            "type":"Food & Drink"
        }
    ],
    "sg:phone":"+1 715 241 0592",
    "sg:postcode":"54476",
    "sg:province":"WI",
    "sg:tags":[
        "drinking"
    ],
    "wof:name":"C J's Sports Bar & Grill",
    "wof:placetype":"venue"
},
  "geometry": {"coordinates":[-89.516061,44.899183],"type":"Point"}
}