{
  "type": "Feature",
  "properties": {
    "iso:country":"US",
    "sg:address":"113 Jonathon Dr",
    "sg:city":"Janesville",
    "sg:classifiers":[
        {
            "category":"Building & Trades",
            "subcategory":"Construction",
            "type":"Services"
        }
    ],
    "sg:phone":"+1 608 755 1120",
    "sg:postcode":"53548",
    "sg:province":"WI",
    "sg:tags":[
        "house"
    ],
    "wof:name":"Fairbert Builders",
    "wof:placetype":"venue"
},
  "geometry": {"coordinates":[-89.06584,42.679791],"type":"Point"}
}