{
  "type": "Feature",
  "properties": {
    "iso:country":"US",
    "sg:address":"2221 S Hastings Way",
    "sg:city":"Eau Claire",
    "sg:classifiers":[
        {
            "category":"Shopping",
            "subcategory":"Used Merchandise",
            "type":"Retail Goods"
        }
    ],
    "sg:phone":"+1 715 831 9000",
    "sg:postcode":"54701",
    "sg:province":"WI",
    "sg:tags":[
        "pawnbroker"
    ],
    "wof:name":"Pawn Doctors",
    "wof:placetype":"venue"
},
  "geometry": {"coordinates":[-91.46174999999999,44.795306],"type":"Point"}
}