{
  "type": "Feature",
  "properties": {
    "iso:country":"US",
    "sg:address":"9301 Newell Rd",
    "sg:city":"Dalton",
    "sg:classifiers":[
        {
            "category":"Professional",
            "subcategory":"Business Services",
            "type":"Services"
        }
    ],
    "sg:phone":"+1 608 429 9931",
    "sg:postcode":"53926",
    "sg:province":"WI",
    "sg:tags":[
        "beef",
        "feedlot",
        "cattle"
    ],
    "wof:name":"Ronald Brusveen",
    "wof:placetype":"venue"
},
  "geometry": {"coordinates":[-89.207646,43.615068],"type":"Point"}
}