{
  "type": "Feature",
  "properties": {
    "iso:country":"US",
    "sg:address":"1590 E Main St",
    "sg:city":"Reedsburg",
    "sg:classifiers":[
        {
            "category":"Retail",
            "subcategory":"Self-service Laundry",
            "type":"Services"
        }
    ],
    "sg:phone":"+1 608 524 4459",
    "sg:postcode":"53959",
    "sg:province":"WI",
    "wof:name":"Viking Village Laundromat",
    "wof:placetype":"venue"
},
  "geometry": {"coordinates":[-89.984864,43.532389],"type":"Point"}
}