{
  "type": "Feature",
  "properties": {
    "addr:full":"934 S Holt Cir Madison WI 53719",
    "addr:housenumber":"934",
    "addr:postcode":"53719",
    "addr:street":"S Holt Cir",
    "iso:country":"US",
    "sg:address":"934 S Holt Cir",
    "sg:city":"Madison",
    "sg:classifiers":[
        {
            "category":"Building & Trades",
            "subcategory":"Cleaning & Sanitation",
            "type":"Services"
        }
    ],
    "sg:phone":"+1 608 273 0643",
    "sg:postcode":"53719",
    "sg:province":"WI",
    "sg:tags":[
        "maintenance"
    ],
    "wof:name":"Pope Properties 4 LLC",
    "wof:placetype":"venue"
},
  "geometry": {"coordinates":[-89.50458,43.044741],"type":"Point"}
}