{
  "type": "Feature",
  "properties": {
    "iso:country":"US",
    "sg:address":"1501 Villa St",
    "sg:city":"Racine",
    "sg:classifiers":[
        {
            "category":"Social Services",
            "type":"Services"
        }
    ],
    "sg:phone":"+1 262 637 7515",
    "sg:postcode":"53403",
    "sg:province":"WI",
    "sg:tags":[
        "senior",
        "citizen"
    ],
    "wof:name":"Skillbank-Racine County",
    "wof:placetype":"venue"
},
  "geometry": {"coordinates":[-87.787005,42.712544],"type":"Point"}
}