{
  "type": "Feature",
  "properties": {
    "iso:country":"US",
    "sg:address":"2 Beloit Mall St",
    "sg:city":"Beloit",
    "sg:classifiers":[
        {
            "category":"Professional",
            "subcategory":"Business Services",
            "type":"Services"
        }
    ],
    "sg:phone":"+1 608 364 3022",
    "sg:postcode":"53511",
    "sg:province":"WI",
    "wof:name":"Ueda of Beloit",
    "wof:placetype":"venue"
},
  "geometry": {"coordinates":[-89.03418499999999,42.52222],"type":"Point"}
}