{
  "type": "Feature",
  "properties": {
    "iso:country":"US",
    "sg:address":"2410 S Main St",
    "sg:city":"West Bend",
    "sg:classifiers":[
        {
            "category":"Professional",
            "subcategory":"Accounting & Tax Preparation",
            "type":"Services"
        }
    ],
    "sg:phone":"+1 262 338 6621",
    "sg:postcode":"53095",
    "sg:province":"WI",
    "sg:tags":[
        "accountant"
    ],
    "wof:name":"Stephen M Kjer CPA",
    "wof:placetype":"venue"
},
  "geometry": {"coordinates":[-88.180914,43.392842],"type":"Point"}
}