{
  "type": "Feature",
  "properties": {
    "addr:full":"6051 W Brown Deer Rd Milwaukee WI 53223",
    "addr:housenumber":"6051",
    "addr:postcode":"53223",
    "addr:street":"W Brown Deer Rd",
    "iso:country":"US",
    "sg:address":"6051 W Brown Deer Rd",
    "sg:city":"Milwaukee",
    "sg:phone":"+1 414 354 3003",
    "sg:postcode":"53223",
    "sg:province":"WI",
    "wof:name":"Bischoff Monica DDS PC",
    "wof:placetype":"venue"
},
  "geometry": {"coordinates":[-87.984753,43.177301],"type":"Point"}
}