{
  "type": "Feature",
  "properties": {
    "addr:full":"429 S Montana Ave New Richmond WI 54017",
    "addr:housenumber":"429",
    "addr:postcode":"54017",
    "addr:street":"S Montana Ave",
    "iso:country":"US",
    "sg:address":"429 S Montana Ave",
    "sg:city":"New Richmond",
    "sg:classifiers":[
        {
            "category":"Retail",
            "subcategory":"Repair Shop",
            "type":"Services"
        },
        {
            "category":"Shopping",
            "subcategory":"Bicycles & Sporting Goods",
            "type":"Retail Goods"
        }
    ],
    "sg:phone":"+1 715 246 6664",
    "sg:postcode":"54017",
    "sg:province":"WI",
    "sg:tags":[
        "gun",
        "gunsmith"
    ],
    "wof:name":"Saint Croix Gunsmithing",
    "wof:placetype":"venue"
},
  "geometry": {"coordinates":[-92.54237000000001,45.118483],"type":"Point"}
}