{
  "type": "Feature",
  "properties": {
    "iso:country":"US",
    "sg:address":"31194 Co Hwy M",
    "sg:city":"Holcombe",
    "sg:classifiers":[
        {
            "category":"Building & Trades",
            "subcategory":"Construction",
            "type":"Services"
        }
    ],
    "sg:phone":"+1 715 595 6366",
    "sg:postcode":"54745",
    "sg:province":"WI",
    "sg:tags":[
        "house"
    ],
    "wof:name":"Geist Construction Inc",
    "wof:placetype":"venue"
},
  "geometry": {"coordinates":[-91.036396,45.248887],"type":"Point"}
}