{
  "type": "Feature",
  "properties": {
    "iso:country":"US",
    "sg:address":"5028 State Hwy 42",
    "sg:city":"Manitowoc",
    "sg:classifiers":[
        {
            "category":"Manufacturing",
            "subcategory":"Tools & Machinery",
            "type":"Manufacturing & Wholesale Goods"
        }
    ],
    "sg:phone":"+1 920 758 2491",
    "sg:postcode":"54220",
    "sg:province":"WI",
    "sg:tags":[
        "stamping",
        "mfg",
        "metal",
        "equipment",
        "agricultural",
        "fabrication"
    ],
    "wof:name":"Schuette Mfg & Stl Sls Inc",
    "wof:placetype":"venue"
},
  "geometry": {"coordinates":[-87.767841,44.040379],"type":"Point"}
}