{
  "type": "Feature",
  "properties": {
    "iso:country":"US",
    "sg:address":"2450 E Washington Ave",
    "sg:city":"Madison",
    "sg:classifiers":[
        {
            "category":"Retail",
            "subcategory":"Auto Repair",
            "type":"Services"
        }
    ],
    "sg:phone":"+1 608 241 1551",
    "sg:postcode":"53704",
    "sg:province":"WI",
    "sg:tags":[
        "muffler",
        "shop",
        "brake"
    ],
    "wof:name":"Speedy Auto Service",
    "wof:placetype":"venue"
},
  "geometry": {"coordinates":[-89.350402,43.099006],"type":"Point"}
}