{
  "type": "Feature",
  "properties": {
    "addr:full":"1915 22nd St Kenosha WI 53140",
    "addr:housenumber":"1915",
    "addr:postcode":"53140",
    "addr:street":"22Nd St",
    "iso:country":"US",
    "sg:address":"1915 22nd St",
    "sg:city":"Kenosha",
    "sg:classifiers":[
        {
            "category":"Wholesale",
            "subcategory":"Motor Vehicles",
            "type":"Manufacturing & Wholesale Goods"
        }
    ],
    "sg:phone":"+1 414 405 1000",
    "sg:postcode":"53140",
    "sg:province":"WI",
    "wof:name":"Eagle Auto Brokers",
    "wof:placetype":"venue"
},
  "geometry": {"coordinates":[-87.83574299999999,42.617412],"type":"Point"}
}