{
  "type": "Feature",
  "properties": {
    "iso:country":"US",
    "sg:address":"3270 S 3rd St",
    "sg:city":"Milwaukee",
    "sg:classifiers":[
        {
            "category":"Building & Trades",
            "subcategory":"Construction",
            "type":"Services"
        }
    ],
    "sg:phone":"+1 414 489 9710",
    "sg:postcode":"53207",
    "sg:province":"WI",
    "sg:tags":[
        "finisher",
        "plating",
        "metal"
    ],
    "wof:name":"Elite Finishing",
    "wof:placetype":"venue"
},
  "geometry": {"coordinates":[-87.914357,42.984119],"type":"Point"}
}