{
  "type": "Feature",
  "properties": {
    "addr:full":"5310 W North Ave Milwaukee WI 53208",
    "addr:housenumber":"5310",
    "addr:postcode":"53208",
    "addr:street":"W North Ave",
    "iso:country":"US",
    "sg:address":"5310 W North Ave",
    "sg:city":"Milwaukee",
    "sg:classifiers":[
        {
            "category":"Place Of Worship",
            "subcategory":"Church",
            "type":"Public Place"
        },
        {
            "category":"Place Of Worship",
            "type":"Public Place"
        }
    ],
    "sg:phone":"+1 414 571 2334",
    "sg:postcode":"53208",
    "sg:province":"WI",
    "sg:tags":[
        "churches-catholic-traditional",
        "churches-catholic"
    ],
    "wof:name":"Old Roman Catholic Brotherhood Of Divine Compassion, Ltd",
    "wof:placetype":"venue"
},
  "geometry": {"coordinates":[-87.98000500000001,43.060682],"type":"Point"}
}