{
  "type": "Feature",
  "properties": {
    "iso:country":"US",
    "sg:address":"260 High View Ln",
    "sg:city":"Oconomowoc",
    "sg:classifiers":[
        {
            "category":"Wholesale",
            "subcategory":"Electrical",
            "type":"Manufacturing & Wholesale Goods"
        }
    ],
    "sg:phone":"+1 262 549 6041",
    "sg:postcode":"53066",
    "sg:province":"WI",
    "sg:tags":[
        "equipment"
    ],
    "wof:name":"Comsonics",
    "wof:placetype":"venue"
},
  "geometry": {"coordinates":[-88.499694,43.092725],"type":"Point"}
}