{
  "type": "Feature",
  "properties": {
    "iso:country":"US",
    "sg:address":"3145 N Menomonee River Pkwy",
    "sg:city":"Milwaukee",
    "sg:classifiers":[
        {
            "category":"Organizations",
            "subcategory":"Religious Organization",
            "type":"Services"
        }
    ],
    "sg:phone":"+1 414 258 1889",
    "sg:postcode":"53222",
    "sg:province":"WI",
    "sg:tags":[
        "clergy"
    ],
    "wof:name":"Carl Lund",
    "wof:placetype":"venue"
},
  "geometry": {"coordinates":[-88.039804,43.076459],"type":"Point"}
}