{
  "type": "Feature",
  "properties": {
    "iso:country":"US",
    "sg:address":"633 W Wisconsin Ave",
    "sg:city":"Milwaukee",
    "sg:classifiers":[
        {
            "category":"Health Services",
            "subcategory":"Nursing And Care Facility",
            "type":"Services"
        },
        {
            "category":"Health Services",
            "subcategory":"Health Practitioner",
            "type":"Services"
        }
    ],
    "sg:phone":"+1 414 431 0500",
    "sg:postcode":"53203",
    "sg:province":"WI",
    "sg:tags":[
        "home",
        "eldercare-home"
    ],
    "wof:name":"Senior Helpers",
    "wof:placetype":"venue"
},
  "geometry": {"coordinates":[-87.919483,43.038806],"type":"Point"}
}