{
  "type": "Feature",
  "properties": {
    "iso:country":"US",
    "sg:address":"2109 Manor Green Dr",
    "sg:city":"Madison",
    "sg:classifiers":[
        {
            "category":"Professional",
            "subcategory":"Art Services",
            "type":"Services"
        },
        {
            "category":"Professional",
            "subcategory":"Computer Services",
            "type":"Services"
        }
    ],
    "sg:phone":"+1 608 288 9627",
    "sg:postcode":"53711",
    "sg:province":"WI",
    "sg:tags":[
        "graphic",
        "designer",
        "related"
    ],
    "wof:name":"Cleveland Publishing Services",
    "wof:placetype":"venue"
},
  "geometry": {"coordinates":[-89.47394300000001,43.027781],"type":"Point"}
}