{
  "type": "Feature",
  "properties": {
    "addr:full":"8285 Adams Ln Cassville WI 53806",
    "addr:housenumber":"8285",
    "addr:postcode":"53806",
    "addr:street":"Adams Ln",
    "iso:country":"US",
    "sg:address":"8285 Adams Ln",
    "sg:city":"Cassville",
    "sg:classifiers":[
        {
            "category":"Health Services",
            "subcategory":"Clinic",
            "type":"Services"
        }
    ],
    "sg:phone":"+1 608 725 5190",
    "sg:postcode":"53806",
    "sg:province":"WI",
    "sg:tags":[
        "home",
        "care"
    ],
    "wof:name":"Home Care Select",
    "wof:placetype":"venue"
},
  "geometry": {"coordinates":[-90.841454,42.688755],"type":"Point"}
}