{
  "type": "Feature",
  "properties": {
    "iso:country":"US",
    "sg:address":"223 N Livingston St",
    "sg:city":"Madison",
    "sg:classifiers":[
        {
            "category":"Arts & Performance",
            "subcategory":"Theater",
            "type":"Entertainment"
        }
    ],
    "sg:phone":"+1 608 335 6834",
    "sg:postcode":"53703",
    "sg:province":"WI",
    "sg:tags":[
        "live",
        "music"
    ],
    "wof:name":"Sonic Sound",
    "wof:placetype":"venue"
},
  "geometry": {"coordinates":[-89.377774,43.083112],"type":"Point"}
}