{
  "type": "Feature",
  "properties": {
    "iso:country":"US",
    "sg:address":"6001 Maple Rd",
    "sg:city":"Neillsville",
    "sg:classifiers":[
        {
            "category":"Building & Trades",
            "subcategory":"Construction",
            "type":"Services"
        }
    ],
    "sg:phone":"+1 715 743 2251",
    "sg:postcode":"54456",
    "sg:province":"WI",
    "sg:tags":[
        "general",
        "contractor"
    ],
    "wof:name":"Wood Wright Construction",
    "wof:placetype":"venue"
},
  "geometry": {"coordinates":[-90.605327,44.538154],"type":"Point"}
}