{
  "type": "Feature",
  "properties": {
    "iso:country":"US",
    "sg:address":"240 Nelson St",
    "sg:city":"Sharon",
    "sg:classifiers":[
        {
            "category":"Building & Trades",
            "subcategory":"Construction",
            "type":"Services"
        }
    ],
    "sg:phone":"+1 262 736 3000",
    "sg:postcode":"53585",
    "sg:province":"WI",
    "sg:tags":[
        "contractor"
    ],
    "wof:name":"Aatron Contractors",
    "wof:placetype":"venue"
},
  "geometry": {"coordinates":[-88.733608,42.504246],"type":"Point"}
}