{
  "type": "Feature",
  "properties": {
    "iso:country":"US",
    "sg:address":"215 Forest Ave",
    "sg:city":"Kewaskum",
    "sg:classifiers":[
        {
            "category":"Retail",
            "subcategory":"Funeral Services",
            "type":"Services"
        }
    ],
    "sg:phone":"+1 262 626 2185",
    "sg:postcode":"53040",
    "sg:province":"WI",
    "sg:tags":[
        "director"
    ],
    "wof:name":"Miller's Funeral Home",
    "wof:placetype":"venue"
},
  "geometry": {"coordinates":[-88.231192,43.521194],"type":"Point"}
}