{
  "type": "Feature",
  "properties": {
    "addr:full":"6161 S 118th St Hales Corners WI 53130",
    "addr:housenumber":"6161",
    "addr:postcode":"53130",
    "addr:street":"S 118Th St",
    "iso:country":"US",
    "sg:address":"6161 S 118th St",
    "sg:city":"Hales Corners",
    "sg:classifiers":[
        {
            "category":"Building & Trades",
            "subcategory":"Construction",
            "type":"Services"
        }
    ],
    "sg:phone":"+1 414 427 9770",
    "sg:postcode":"53130",
    "sg:province":"WI",
    "sg:tags":[
        "house"
    ],
    "wof:name":"Projects Complete Inc",
    "wof:placetype":"venue"
},
  "geometry": {"coordinates":[-88.06057699999999,42.93145],"type":"Point"}
}