{
  "type": "Feature",
  "properties": {
    "iso:country":"US",
    "sg:address":"302 S Main St",
    "sg:city":"West Bend",
    "sg:classifiers":[
        {
            "category":"Bars & Pubs",
            "type":"Food & Drink"
        }
    ],
    "sg:phone":"+1 262 334 7877",
    "sg:postcode":"53095",
    "sg:province":"WI",
    "sg:tags":[
        "drinking"
    ],
    "wof:name":"Three Old Guys",
    "wof:placetype":"venue"
},
  "geometry": {"coordinates":[-88.181157,43.420766],"type":"Point"}
}