{
  "type": "Feature",
  "properties": {
    "iso:country":"US",
    "sg:address":"10403 Co Rd F",
    "sg:city":"Danbury",
    "sg:classifiers":[
        {
            "category":"Insurance",
            "subcategory":"Insurance Agent",
            "type":"Services"
        }
    ],
    "sg:phone":"+1 715 656 3971",
    "sg:postcode":"54830",
    "sg:province":"WI",
    "wof:name":"Mollenhoff Milt Insurance",
    "wof:placetype":"venue"
},
  "geometry": {"coordinates":[-92.522329,45.941284],"type":"Point"}
}