{
  "type": "Feature",
  "properties": {
    "iso:country":"US",
    "sg:address":"14360 Co Rd Ww",
    "sg:city":"Eleva",
    "sg:classifiers":[
        {
            "category":"Building & Trades",
            "subcategory":"Construction",
            "type":"Services"
        }
    ],
    "sg:phone":"+1 715 287 3359",
    "sg:postcode":"54738",
    "sg:province":"WI",
    "sg:tags":[
        "excavating",
        "contractor"
    ],
    "wof:name":"Dirtworks Excavating",
    "wof:placetype":"venue"
},
  "geometry": {"coordinates":[-91.536911,44.620092],"type":"Point"}
}