{
  "type": "Feature",
  "properties": {
    "addr:full":"3235 Parkside Dr Brookfield WI 53005",
    "addr:housenumber":"3235",
    "addr:postcode":"53005",
    "addr:street":"Parkside Dr",
    "iso:country":"US",
    "sg:address":"3235 Parkside Dr",
    "sg:city":"Brookfield",
    "sg:classifiers":[
        {
            "category":"Home & Garden",
            "subcategory":"Hardware",
            "type":"Retail Goods"
        }
    ],
    "sg:phone":"+1 262 781 6174",
    "sg:postcode":"53005",
    "sg:province":"WI",
    "wof:name":"Rasmussen Industrial Supply Co",
    "wof:placetype":"venue"
},
  "geometry": {"coordinates":[-88.080911,43.076961],"type":"Point"}
}