{
  "type": "Feature",
  "properties": {
    "iso:country":"US",
    "sg:address":"8645 Co Rd C",
    "sg:city":"New Lisbon",
    "sg:phone":"+1 608 427 3407",
    "sg:postcode":"53950",
    "sg:province":"WI",
    "sg:tags":[
        "farm",
        "soybean"
    ],
    "wof:name":"Ray Anderson",
    "wof:placetype":"venue"
},
  "geometry": {"coordinates":[-90.197661,43.92328],"type":"Point"}
}