{
  "type": "Feature",
  "properties": {
    "iso:country":"US",
    "sg:address":"5109 Merrill Rd",
    "sg:city":"Rosendale",
    "sg:classifiers":[
        {
            "category":"Building & Trades",
            "subcategory":"Construction",
            "type":"Services"
        }
    ],
    "sg:phone":"+1 920 923 1553",
    "sg:postcode":"54974",
    "sg:province":"WI",
    "sg:tags":[
        "house"
    ],
    "wof:name":"Dmb Construction",
    "wof:placetype":"venue"
},
  "geometry": {"coordinates":[-88.623714,43.724884],"type":"Point"}
}