{
  "type": "Feature",
  "properties": {
    "iso:country":"US",
    "sg:address":"525 Memory Ln",
    "sg:city":"Antigo",
    "sg:classifiers":[
        {
            "category":"Travel",
            "subcategory":"Hotels & Motels",
            "type":"Entertainment"
        }
    ],
    "sg:phone":"+1 715 623 0506",
    "sg:postcode":"54409",
    "sg:province":"WI",
    "wof:name":"Northwoods Birch Inn",
    "wof:placetype":"venue"
},
  "geometry": {"coordinates":[-89.14928,45.168752],"type":"Point"}
}