{
  "type": "Feature",
  "properties": {
    "addr:full":"11822 Co Rd M Auburndale WI 54412",
    "addr:housenumber":"11822",
    "addr:postcode":"54412",
    "addr:street":"Co Rd M",
    "iso:country":"US",
    "sg:address":"11822 Co Rd M",
    "sg:city":"Auburndale",
    "sg:phone":"+1 715 652 2801",
    "sg:postcode":"54412",
    "sg:province":"WI",
    "sg:tags":[
        "farm",
        "field",
        "corn",
        "crop"
    ],
    "wof:name":"Harvey OHM",
    "wof:placetype":"venue"
},
  "geometry": {"coordinates":[-90.024738,44.672938],"type":"Point"}
}