{
  "type": "Feature",
  "properties": {
    "iso:country":"US",
    "sg:address":"100 Eagle Dr",
    "sg:city":"Balsam Lake",
    "sg:classifiers":[
        {
            "category":"Food & Beverages",
            "subcategory":"Groceries & Convenience Stores",
            "type":"Retail Goods"
        }
    ],
    "sg:phone":"+1 715 485 3154",
    "sg:postcode":"54810",
    "sg:province":"WI",
    "wof:name":"Hills Super Valu",
    "wof:placetype":"venue"
},
  "geometry": {"coordinates":[-92.48366300000001,45.449026],"type":"Point"}
}