{
  "type": "Feature",
  "properties": {
    "iso:country":"US",
    "sg:address":"3745 State Rd 85",
    "sg:city":"Eau Claire",
    "sg:classifiers":[
        {
            "category":"Building & Trades",
            "subcategory":"Construction",
            "type":"Services"
        }
    ],
    "sg:phone":"+1 715 456 2504",
    "sg:postcode":"54701",
    "sg:province":"WI",
    "sg:tags":[
        "roofing",
        "contractor"
    ],
    "wof:name":"A-1 Roofing Siding & Constr",
    "wof:placetype":"venue"
},
  "geometry": {"coordinates":[-91.566648,44.763746],"type":"Point"}
}