{
  "type": "Feature",
  "properties": {
    "addr:full":"4229 N 25th St Milwaukee WI 53209",
    "addr:housenumber":"4229",
    "addr:postcode":"53209",
    "addr:street":"N 25Th St",
    "iso:country":"US",
    "sg:address":"4229 N 25th St",
    "sg:city":"Milwaukee",
    "sg:classifiers":[
        {
            "category":"Professional",
            "type":"Services"
        }
    ],
    "sg:phone":"+1 414 444 7323",
    "sg:postcode":"53209",
    "sg:province":"WI",
    "wof:name":"Iuvent Technical Svc Co LLC",
    "wof:placetype":"venue"
},
  "geometry": {"coordinates":[-87.944683,43.094447],"type":"Point"}
}