{
  "type": "Feature",
  "properties": {
    "iso:country":"US",
    "sg:address":"520 E Newhall Ave",
    "sg:city":"Waukesha",
    "sg:classifiers":[
        {
            "category":"Education",
            "subcategory":"School",
            "type":"Public Place"
        }
    ],
    "sg:phone":"+1 262 896 2932",
    "sg:postcode":"53186",
    "sg:province":"WI",
    "sg:website":"www.wcssonline.org",
    "wof:name":"St Mary's Catholic School",
    "wof:placetype":"venue"
},
  "geometry": {"coordinates":[-88.221378,42.999444],"type":"Point"}
}