{
  "type": "Feature",
  "properties": {
    "iso:country":"US",
    "sg:address":"9324 Concord Dr",
    "sg:city":"Mequon",
    "sg:classifiers":[
        {
            "category":"Professional",
            "type":"Services"
        }
    ],
    "sg:phone":"+1 262 242 2823",
    "sg:postcode":"53097",
    "sg:province":"WI",
    "wof:name":"R&H Fab Tech Llc",
    "wof:placetype":"venue"
},
  "geometry": {"coordinates":[-88.026163,43.205673],"type":"Point"}
}