{
  "type": "Feature",
  "properties": {
    "addr:full":"607 Colle St Luxemburg WI 54217",
    "addr:housenumber":"607",
    "addr:postcode":"54217",
    "addr:street":"Colle St",
    "iso:country":"US",
    "sg:address":"607 Colle St",
    "sg:city":"Luxemburg",
    "sg:classifiers":[
        {
            "category":"Building & Trades",
            "subcategory":"Plumbing",
            "type":"Services"
        }
    ],
    "sg:phone":"+1 920 845 2444",
    "sg:postcode":"54217",
    "sg:province":"WI",
    "sg:tags":[
        "plumbing",
        "contractor"
    ],
    "wof:name":"Jim's Plumbing & Heating Svc",
    "wof:placetype":"venue"
},
  "geometry": {"coordinates":[-87.702287,44.540175],"type":"Point"}
}