{
  "type": "Feature",
  "properties": {
    "iso:country":"US",
    "sg:address":"2360 N 53rd St",
    "sg:city":"Milwaukee",
    "sg:classifiers":[
        {
            "category":"Social Services",
            "subcategory":"Child Care",
            "type":"Services"
        }
    ],
    "sg:phone":"+1 414 444 3796",
    "sg:postcode":"53210",
    "sg:province":"WI",
    "wof:name":"Gwendolyn's Child Care",
    "wof:placetype":"venue"
},
  "geometry": {"coordinates":[-87.979842,43.06136],"type":"Point"}
}