{
  "type": "Feature",
  "properties": {
    "iso:country":"US",
    "sg:address":"320 Pine St",
    "sg:city":"Sheboygan Falls",
    "sg:classifiers":[
        {
            "category":"Retail",
            "subcategory":"Laundry & Dry Cleaning",
            "type":"Services"
        }
    ],
    "sg:phone":"+1 920 467 4644",
    "sg:postcode":"53085",
    "sg:province":"WI",
    "sg:tags":[
        "cleaners"
    ],
    "wof:name":"Troy Cleaners & Launderers",
    "wof:placetype":"venue"
},
  "geometry": {"coordinates":[-87.814155,43.727045],"type":"Point"}
}