{
  "type": "Feature",
  "properties": {
    "iso:country":"US",
    "sg:address":"1787 State Rd 49",
    "sg:city":"Berlin",
    "sg:classifiers":[
        {
            "category":"Manufacturing",
            "subcategory":"Furniture",
            "type":"Manufacturing & Wholesale Goods"
        }
    ],
    "sg:phone":"+1 920 361 2276",
    "sg:postcode":"54923",
    "sg:province":"WI",
    "sg:tags":[
        "upholstered",
        "wood",
        "household",
        "kit",
        "mfg"
    ],
    "wof:name":"Red Barn Woodcrafts Inc",
    "wof:placetype":"venue"
},
  "geometry": {"coordinates":[-88.991673,44.049262],"type":"Point"}
}