{
  "type": "Feature",
  "properties": {
    "iso:country":"US",
    "sg:address":"155 Johnston Dr",
    "sg:city":"Dousman",
    "sg:classifiers":[
        {
            "category":"Freight",
            "type":"Transportation"
        }
    ],
    "sg:phone":"+1 262 965 4457",
    "sg:postcode":"53118",
    "sg:province":"WI",
    "sg:tags":[
        "operator",
        "trucking"
    ],
    "wof:name":"Jjs Four Season Services LLC",
    "wof:placetype":"venue"
},
  "geometry": {"coordinates":[-88.47704400000001,43.016998],"type":"Point"}
}