{
  "type": "Feature",
  "properties": {
    "iso:country":"US",
    "sg:address":"4400 21st St",
    "sg:city":"Racine",
    "sg:classifiers":[
        {
            "category":"Professional",
            "subcategory":"Business Services",
            "type":"Services"
        }
    ],
    "sg:phone":"+1 262 598 9504",
    "sg:postcode":"53405",
    "sg:province":"WI",
    "wof:name":"Charon Technologies Inc",
    "wof:placetype":"venue"
},
  "geometry": {"coordinates":[-87.83564,42.70415],"type":"Point"}
}