{
  "type": "Feature",
  "properties": {
    "iso:country":"US",
    "sg:address":"1207 N Parkview St",
    "sg:city":"Cottage Grove",
    "sg:classifiers":[
        {
            "category":"Professional",
            "subcategory":"Management & Consulting",
            "type":"Services"
        }
    ],
    "sg:phone":"+1 608 839 1817",
    "sg:postcode":"53527",
    "sg:province":"WI",
    "wof:name":"Eaglespire Coaching LLC",
    "wof:placetype":"venue"
},
  "geometry": {"coordinates":[-89.20874,43.100628],"type":"Point"}
}