{
  "type": "Feature",
  "properties": {
    "iso:country":"US",
    "sg:address":"2815 E Hamilton Ave",
    "sg:city":"Eau Claire",
    "sg:classifiers":[
        {
            "category":"Wholesale",
            "subcategory":"Machinery & Supplies",
            "type":"Manufacturing & Wholesale Goods"
        }
    ],
    "sg:phone":"+1 715 831 1667",
    "sg:postcode":"54701",
    "sg:province":"WI",
    "sg:tags":[
        "salon",
        "beauty"
    ],
    "wof:name":"Aerial Co",
    "wof:placetype":"venue"
},
  "geometry": {"coordinates":[-91.462121,44.785739],"type":"Point"}
}