{
  "type": "Feature",
  "properties": {
    "iso:country":"US",
    "sg:address":"7120 N Crossway Rd",
    "sg:city":"Milwaukee",
    "sg:classifiers":[
        {
            "category":"Building & Trades",
            "subcategory":"Pest Control",
            "type":"Services"
        }
    ],
    "sg:phone":"+1 414 630 3869",
    "sg:postcode":"53217",
    "sg:province":"WI",
    "wof:name":"Up North Svc Inc",
    "wof:placetype":"venue"
},
  "geometry": {"coordinates":[-87.907273,43.147057],"type":"Point"}
}