{
  "type": "Feature",
  "properties": {
    "iso:country":"US",
    "sg:address":"602 Peace Pipe Rd",
    "sg:city":"Lac Du Flambeau",
    "sg:classifiers":[
        {
            "category":"Travel",
            "subcategory":"Travel Agent",
            "type":"Entertainment"
        }
    ],
    "sg:phone":"+1 715 588 9052",
    "sg:postcode":"54538",
    "sg:province":"WI",
    "sg:tags":[
        "information",
        "tourist"
    ],
    "wof:name":"Heritage Tourism Info",
    "wof:placetype":"venue"
},
  "geometry": {"coordinates":[-89.89191700000001,45.970706],"type":"Point"}
}