{
  "type": "Feature",
  "properties": {
    "addr:full":"2001 Shawano Ave Green Bay WI 54303",
    "addr:housenumber":"2001",
    "addr:postcode":"54303",
    "addr:street":"Shawano Ave",
    "iso:country":"US",
    "sg:address":"2001 Shawano Ave",
    "sg:city":"Green Bay",
    "sg:classifiers":[
        {
            "category":"Retail",
            "subcategory":"Auto Repair",
            "type":"Services"
        }
    ],
    "sg:phone":"+1 920 499 2944",
    "sg:postcode":"54303",
    "sg:province":"WI",
    "sg:tags":[
        "body"
    ],
    "wof:name":"Cobora Auto Body",
    "wof:placetype":"venue"
},
  "geometry": {"coordinates":[-88.075238,44.534971],"type":"Point"}
}