{
  "type": "Feature",
  "properties": {
    "iso:country":"US",
    "sg:address":"500 W Main St",
    "sg:city":"Balsam Lake",
    "sg:classifiers":[
        {
            "category":"Professional",
            "type":"Services"
        }
    ],
    "sg:phone":"+1 715 485 9427",
    "sg:postcode":"54810",
    "sg:province":"WI",
    "sg:tags":[
        "establishment"
    ],
    "wof:name":"Up At The Lake",
    "wof:placetype":"venue"
},
  "geometry": {"coordinates":[-92.461516,45.453428],"type":"Point"}
}