{
  "type": "Feature",
  "properties": {
    "iso:country":"US",
    "sg:address":"8959 State Hwy 39",
    "sg:city":"Blanchardville",
    "sg:classifiers":[
        {
            "category":"Health Services",
            "subcategory":"Medical Lab",
            "type":"Services"
        }
    ],
    "sg:phone":"+1 608 523 1903",
    "sg:postcode":"53516",
    "sg:province":"WI",
    "sg:tags":[
        "custom"
    ],
    "sg:website":"www.panigen.com",
    "wof:name":"Panigen Inc",
    "wof:placetype":"venue"
},
  "geometry": {"coordinates":[-89.79553,42.847018],"type":"Point"}
}