{
  "type": "Feature",
  "properties": {
    "iso:country":"US",
    "sg:address":"8634 W Brown Deer Rd",
    "sg:city":"Milwaukee",
    "sg:classifiers":[
        {
            "category":"Banks & Credit Unions",
            "subcategory":"Bank",
            "type":"Services"
        }
    ],
    "sg:phone":"+1 414 357 8661",
    "sg:postcode":"53224",
    "sg:province":"WI",
    "sg:tags":[
        "loan",
        "real estate"
    ],
    "wof:name":"M & E Mortgage",
    "wof:placetype":"venue"
},
  "geometry": {"coordinates":[-88.022481,43.177804],"type":"Point"}
}