{
  "type": "Feature",
  "properties": {
    "addr:full":"2309 Indiana Ave Stevens Point WI 54481",
    "addr:housenumber":"2309",
    "addr:postcode":"54481",
    "addr:street":"Indiana Ave",
    "iso:country":"US",
    "sg:address":"2309 Indiana Ave",
    "sg:city":"Stevens Point",
    "sg:classifiers":[
        {
            "category":"Retail",
            "subcategory":"Auto Rental",
            "type":"Services"
        }
    ],
    "sg:phone":"+1 715 345 0150",
    "sg:postcode":"54481",
    "sg:province":"WI",
    "sg:tags":[
        "truck"
    ],
    "wof:name":"Valley Truck Leasing Inc",
    "wof:placetype":"venue"
},
  "geometry": {"coordinates":[-89.554581,44.514825],"type":"Point"}
}