{
  "type": "Feature",
  "properties": {
    "iso:country":"US",
    "sg:address":"3737 Evergreen Ct",
    "sg:city":"Malone",
    "sg:classifiers":[
        {
            "category":"Building & Trades",
            "subcategory":"Construction",
            "type":"Services"
        }
    ],
    "sg:phone":"+1 920 922 1418",
    "sg:postcode":"53049",
    "sg:province":"WI",
    "sg:tags":[
        "contractor"
    ],
    "wof:name":"Rosenthal Masonry",
    "wof:placetype":"venue"
},
  "geometry": {"coordinates":[-88.344287,43.840455],"type":"Point"}
}