{
  "type": "Feature",
  "properties": {
    "iso:country":"US",
    "sg:address":"1506 Lamers Clancy Rd",
    "sg:city":"Greenleaf",
    "sg:classifiers":[
        {
            "category":"Wholesale",
            "subcategory":"Construction Materials",
            "type":"Manufacturing & Wholesale Goods"
        },
        {
            "category":"Manufacturing",
            "subcategory":"Wood Products",
            "type":"Manufacturing & Wholesale Goods"
        }
    ],
    "sg:phone":"+1 920 532 4152",
    "sg:postcode":"54126",
    "sg:province":"WI",
    "sg:tags":[
        "pallet",
        "skid",
        "mfg"
    ],
    "wof:name":"Wrightstown Wood Products Inc",
    "wof:placetype":"venue"
},
  "geometry": {"coordinates":[-88.10521900000001,44.28453],"type":"Point"}
}