{
  "type": "Feature",
  "properties": {
    "iso:country":"US",
    "sg:address":"1021 Proctor Dr",
    "sg:city":"Elkhorn",
    "sg:classifiers":[
        {
            "category":"Wholesale",
            "subcategory":"Computers",
            "type":"Manufacturing & Wholesale Goods"
        }
    ],
    "sg:phone":"+1 262 723 5726",
    "sg:postcode":"53121",
    "sg:province":"WI",
    "wof:name":"Systems Plus Inc",
    "wof:placetype":"venue"
},
  "geometry": {"coordinates":[-88.524485,42.658145],"type":"Point"}
}