{
  "type": "Feature",
  "properties": {
    "iso:country":"US",
    "sg:address":"605 W Fountain St",
    "sg:city":"Dodgeville",
    "sg:classifiers":[
        {
            "category":"Retail",
            "subcategory":"Laundry & Dry Cleaning",
            "type":"Services"
        }
    ],
    "sg:phone":"+1 608 935 2731",
    "sg:postcode":"53533",
    "sg:province":"WI",
    "sg:tags":[
        "drycleaning",
        "plant"
    ],
    "wof:name":"Curt Prideaux Ea Inc",
    "wof:placetype":"venue"
},
  "geometry": {"coordinates":[-90.140705,42.958765],"type":"Point"}
}