{
  "type": "Feature",
  "properties": {
    "iso:country":"US",
    "sg:address":"701 W Water St",
    "sg:city":"Cambridge",
    "sg:classifiers":[
        {
            "category":"Organizations",
            "subcategory":"Religious Organization",
            "type":"Services"
        }
    ],
    "sg:phone":"+1 608 423 3015",
    "sg:postcode":"53523",
    "sg:province":"WI",
    "sg:tags":[
        "church"
    ],
    "wof:name":"Saint Pius X Catholic Church",
    "wof:placetype":"venue"
},
  "geometry": {"coordinates":[-89.025954,43.000712],"type":"Point"}
}