{
  "type": "Feature",
  "properties": {
    "addr:full":"174 E Wisconsin Ave Oconomowoc WI 53066",
    "addr:housenumber":"174",
    "addr:postcode":"53066",
    "addr:street":"E Wisconsin Ave",
    "iso:country":"US",
    "sg:address":"174 E Wisconsin Ave",
    "sg:city":"Oconomowoc",
    "sg:classifiers":[
        {
            "category":"Government",
            "subcategory":"Office",
            "type":"Public Place"
        }
    ],
    "sg:phone":"+1 262 569 2190",
    "sg:postcode":"53066",
    "sg:province":"WI",
    "sg:tags":[
        "civil",
        "defense",
        "agency"
    ],
    "wof:name":"Oconomowoc Civil Defense Adm",
    "wof:placetype":"venue"
},
  "geometry": {"coordinates":[-88.49857299999999,43.111339],"type":"Point"}
}