{
  "type": "Feature",
  "properties": {
    "iso:country":"US",
    "sg:address":"2321 Stout Rd",
    "sg:city":"Menomonie",
    "sg:classifiers":[
        {
            "category":"Health Services",
            "subcategory":"Doctor",
            "type":"Services"
        }
    ],
    "sg:phone":"+1 715 235 4144",
    "sg:postcode":"54751",
    "sg:province":"WI",
    "sg:tags":[
        "medical"
    ],
    "wof:name":"David B Ketroser MD",
    "wof:placetype":"venue"
},
  "geometry": {"coordinates":[-91.901578,44.882048],"type":"Point"}
}