{
  "type": "Feature",
  "properties": {
    "iso:country":"US",
    "sg:address":"3986 Ledge Rd",
    "sg:city":"Malone",
    "sg:classifiers":[
        {
            "category":"Wholesale",
            "subcategory":"Auto Parts",
            "type":"Manufacturing & Wholesale Goods"
        }
    ],
    "sg:phone":"+1 920 921 8157",
    "sg:postcode":"53049",
    "sg:province":"WI",
    "sg:tags":[
        "automobile",
        "rebuilt"
    ],
    "wof:name":"George's Auto & Truck Salvage",
    "wof:placetype":"venue"
},
  "geometry": {"coordinates":[-88.35725,43.814918],"type":"Point"}
}