{
  "type": "Feature",
  "properties": {
    "iso:country":"US",
    "sg:address":"3930 W Cherry St",
    "sg:city":"Milwaukee",
    "sg:classifiers":[
        {
            "category":"Wholesale",
            "subcategory":"Groceries",
            "type":"Manufacturing & Wholesale Goods"
        }
    ],
    "sg:phone":"+1 414 931 0028",
    "sg:postcode":"53208",
    "sg:province":"WI",
    "wof:name":"Vanessa Gassama Enterprises",
    "wof:placetype":"venue"
},
  "geometry": {"coordinates":[-87.963202,43.05022],"type":"Point"}
}