{
  "type": "Feature",
  "properties": {
    "iso:country":"US",
    "sg:address":"188 US Hwy 45",
    "sg:city":"Kewaskum",
    "sg:classifiers":[
        {
            "category":"Personal",
            "subcategory":"Barber",
            "type":"Services"
        }
    ],
    "sg:phone":"+1 262 626 4734",
    "sg:postcode":"53040",
    "sg:province":"WI",
    "wof:name":"Richard's KUT & Style Shop",
    "wof:placetype":"venue"
},
  "geometry": {"coordinates":[-88.237486,43.543977],"type":"Point"}
}