{
  "type": "Feature",
  "properties": {
    "addr:full":"1720 Riverwood Ln Wisconsin Rapids WI 54494",
    "addr:housenumber":"1720",
    "addr:postcode":"54494",
    "addr:street":"Riverwood Ln",
    "iso:country":"US",
    "sg:address":"1720 Riverwood Ln",
    "sg:city":"Wisconsin Rapids",
    "sg:classifiers":[
        {
            "category":"Shopping",
            "subcategory":"Gifts & Souvenirs",
            "type":"Retail Goods"
        }
    ],
    "sg:phone":"+1 715 424 0510",
    "sg:postcode":"54494",
    "sg:province":"WI",
    "wof:name":"Odyssey Fine Arts",
    "wof:placetype":"venue"
},
  "geometry": {"coordinates":[-89.83599700000001,44.379642],"type":"Point"}
}