{
  "type": "Feature",
  "properties": {
    "addr:full":"692 Stonegate Pass Colgate WI 53017",
    "addr:housenumber":"692",
    "addr:postcode":"53017",
    "addr:street":"Stonegate Pass Colgate",
    "iso:country":"US",
    "sg:address":"692 Stonegate Pass",
    "sg:city":"Colgate",
    "sg:classifiers":[
        {
            "category":"Banks & Credit Unions",
            "subcategory":"Investment Brokerage",
            "type":"Services"
        }
    ],
    "sg:phone":"+1 262 628 3395",
    "sg:postcode":"53017",
    "sg:province":"WI",
    "sg:tags":[
        "advisory"
    ],
    "wof:name":"Richardson Financial",
    "wof:placetype":"venue"
},
  "geometry": {"coordinates":[-88.19419499999999,43.213394],"type":"Point"}
}