{
  "type": "Feature",
  "properties": {
    "iso:country":"US",
    "sg:address":"3031 W Mill Rd",
    "sg:city":"Milwaukee",
    "sg:classifiers":[
        {
            "category":"Social Services",
            "type":"Services"
        }
    ],
    "sg:phone":"+1 414 228 8496",
    "sg:postcode":"53209",
    "sg:province":"WI",
    "sg:tags":[
        "organization",
        "welfare"
    ],
    "wof:name":"Salvation Army Fema",
    "wof:placetype":"venue"
},
  "geometry": {"coordinates":[-87.94955400000001,43.133723],"type":"Point"}
}