{
  "type": "Feature",
  "properties": {
    "iso:country":"US",
    "sg:address":"6208 75th St",
    "sg:city":"Kenosha",
    "sg:classifiers":[
        {
            "category":"Restaurant",
            "type":"Food & Drink"
        },
        {
            "category":"Bakery",
            "type":"Food & Drink"
        }
    ],
    "sg:menulink":"http://www.allmenus.com/wi/kenosha/100329-golden-corral/menu/",
    "sg:phone":"+1 262 942 9396",
    "sg:postcode":"53142",
    "sg:province":"WI",
    "sg:tags":[
        "american",
        "bakery",
        "pastry"
    ],
    "wof:name":"Golden Corral",
    "wof:placetype":"venue"
},
  "geometry": {"coordinates":[-87.88295100000001,42.566736],"type":"Point"}
}