{
  "type": "Feature",
  "properties": {
    "addr:full":"4629 N Port Washington Rd Milwaukee WI 53212",
    "addr:housenumber":"4629",
    "addr:postcode":"53212",
    "addr:street":"N Port Washington Rd",
    "iso:country":"US",
    "sg:address":"4629 N Port Washington Rd",
    "sg:city":"Milwaukee",
    "sg:classifiers":[
        {
            "category":"Social Services",
            "type":"Services"
        }
    ],
    "sg:phone":"+1 414 906 8500",
    "sg:postcode":"53212",
    "sg:province":"WI",
    "sg:tags":[
        "instruction",
        "health",
        "care"
    ],
    "wof:name":"Helping Give Quality Health",
    "wof:placetype":"venue"
},
  "geometry": {"coordinates":[-87.916961,43.102844],"type":"Point"}
}