{
  "type": "Feature",
  "properties": {
    "iso:country":"US",
    "sg:address":"1735 Sal St",
    "sg:city":"Green Bay",
    "sg:classifiers":[
        {
            "category":"Manufacturing",
            "subcategory":"Wood Products",
            "type":"Manufacturing & Wholesale Goods"
        }
    ],
    "sg:phone":"+1 920 465 6764",
    "sg:postcode":"54302",
    "sg:province":"WI",
    "sg:website":"www.deleersmillwork.com",
    "wof:name":"De Leers Millwork Inc",
    "wof:placetype":"venue"
},
  "geometry": {"coordinates":[-87.996437,44.487612],"type":"Point"}
}