{
  "type": "Feature",
  "properties": {
    "addr:full":"5297 Hillcrest Dr Loganville WI 53943",
    "addr:housenumber":"5297",
    "addr:postcode":"53943",
    "addr:street":"Hillcrest Dr",
    "iso:country":"US",
    "sg:address":"5297 Hillcrest Dr",
    "sg:city":"Loganville",
    "sg:phone":"+1 608 727 2356",
    "sg:postcode":"53943",
    "sg:province":"WI",
    "sg:tags":[
        "farm",
        "field",
        "corn",
        "crop"
    ],
    "wof:name":"Donald Meyer",
    "wof:placetype":"venue"
},
  "geometry": {"coordinates":[-90.053647,43.419977],"type":"Point"}
}