{
  "type": "Feature",
  "properties": {
    "iso:country":"US",
    "sg:address":"300 S Main St",
    "sg:city":"Luck",
    "sg:classifiers":[
        {
            "category":"Personal",
            "subcategory":"Beauty Salon",
            "type":"Services"
        }
    ],
    "sg:phone":"+1 715 472 8202",
    "sg:postcode":"54853",
    "sg:province":"WI",
    "sg:tags":[
        "shop"
    ],
    "wof:name":"Hair Affair Inc",
    "wof:placetype":"venue"
},
  "geometry": {"coordinates":[-92.482384,45.573785],"type":"Point"}
}