{
  "type": "Feature",
  "properties": {
    "iso:country":"US",
    "sg:address":"2240 S Ridge Rd",
    "sg:city":"Green Bay",
    "sg:classifiers":[
        {
            "category":"Restaurant",
            "type":"Food & Drink"
        },
        {
            "category":"Ice Cream",
            "type":"Food & Drink"
        }
    ],
    "sg:menulink":"http://www.allmenus.com/wi/ashwaubenon/192633-dairy-queen/menu/",
    "sg:phone":"+1 920 499 7700",
    "sg:postcode":"54304",
    "sg:province":"WI",
    "sg:tags":[
        "burger",
        "american",
        "ice",
        "cream"
    ],
    "wof:name":"Dairy Queen",
    "wof:placetype":"venue"
},
  "geometry": {"coordinates":[-88.070358,44.493489],"type":"Point"}
}