{
  "type": "Feature",
  "properties": {
    "addr:full":"2779 Star Crest Trl Sun Prairie WI 53590",
    "addr:housenumber":"2779",
    "addr:postcode":"53590",
    "addr:street":"Star Crest Trl",
    "iso:country":"US",
    "sg:address":"2779 Star Crest Trl",
    "sg:city":"Sun Prairie",
    "sg:classifiers":[
        {
            "category":"Home & Garden",
            "subcategory":"Garden Supply",
            "type":"Retail Goods"
        }
    ],
    "sg:phone":"+1 608 837 5349",
    "sg:postcode":"53590",
    "sg:province":"WI",
    "sg:tags":[
        "installs",
        "tree"
    ],
    "wof:name":"S R BS Trees",
    "wof:placetype":"venue"
},
  "geometry": {"coordinates":[-89.213803,43.222212],"type":"Point"}
}