{
  "type": "Feature",
  "properties": {
    "iso:country":"US",
    "sg:address":"11413 N Flat Rock Ln",
    "sg:city":"Gillett",
    "sg:classifiers":[
        {
            "category":"Freight",
            "type":"Transportation"
        }
    ],
    "sg:phone":"+1 920 855 2902",
    "sg:postcode":"54124",
    "sg:province":"WI",
    "sg:tags":[
        "over",
        "trucking"
    ],
    "wof:name":"J & T Transit Inc",
    "wof:placetype":"venue"
},
  "geometry": {"coordinates":[-88.33801,44.861308],"type":"Point"}
}