{
  "type": "Feature",
  "properties": {
    "iso:country":"US",
    "sg:address":"339 E Louisa St",
    "sg:city":"Darlington",
    "sg:classifiers":[
        {
            "category":"Social Services",
            "subcategory":"Child Care",
            "type":"Services"
        }
    ],
    "sg:phone":"+1 608 776 2300",
    "sg:postcode":"53530",
    "sg:province":"WI",
    "sg:tags":[
        "kindergarten",
        "academic",
        "school"
    ],
    "wof:name":"Humpty Dumpty Preschool Inc",
    "wof:placetype":"venue"
},
  "geometry": {"coordinates":[-90.1153,42.680121],"type":"Point"}
}