{
  "type": "Feature",
  "properties": {
    "iso:country":"US",
    "sg:address":"424 Hazel St",
    "sg:city":"Oshkosh",
    "sg:classifiers":[
        {
            "category":"Professional",
            "subcategory":"Business Services",
            "type":"Services"
        }
    ],
    "sg:phone":"+1 920 232 9882",
    "sg:postcode":"54901",
    "sg:province":"WI",
    "wof:name":"Mann and Associates",
    "wof:placetype":"venue"
},
  "geometry": {"coordinates":[-88.522368,44.019198],"type":"Point"}
}