{
  "type": "Feature",
  "properties": {
    "iso:country":"US",
    "sg:address":"2310 Custer Rd",
    "sg:city":"Custer",
    "sg:classifiers":[
        {
            "category":"Bars & Pubs",
            "type":"Food & Drink"
        }
    ],
    "sg:phone":"+1 715 592 4238",
    "sg:postcode":"54423",
    "sg:province":"WI",
    "wof:name":"Custer's Pit Stop",
    "wof:placetype":"venue"
},
  "geometry": {"coordinates":[-89.426231,44.511503],"type":"Point"}
}