{
  "type": "Feature",
  "properties": {
    "iso:country":"US",
    "sg:address":"3045 S 67th St",
    "sg:city":"Milwaukee",
    "sg:classifiers":[
        {
            "category":"Autos & Motor Vehicles",
            "subcategory":"Auto Supplies",
            "type":"Retail Goods"
        }
    ],
    "sg:phone":"+1 414 327 4854",
    "sg:postcode":"53219",
    "sg:province":"WI",
    "wof:name":"Firestone",
    "wof:placetype":"venue"
},
  "geometry": {"coordinates":[-87.996605,42.988737],"type":"Point"}
}