{
  "type": "Feature",
  "properties": {
    "iso:country":"US",
    "sg:address":"7649 Tower Rd",
    "sg:city":"Siren",
    "sg:classifiers":[
        {
            "category":"Manufacturing",
            "subcategory":"Retail Goods",
            "type":"Manufacturing & Wholesale Goods"
        }
    ],
    "sg:phone":"+1 715 349 5724",
    "sg:postcode":"54872",
    "sg:province":"WI",
    "sg:tags":[
        "assembly",
        "fabricating"
    ],
    "wof:name":"Diversified Services Ctr",
    "wof:placetype":"venue"
},
  "geometry": {"coordinates":[-92.378377,45.777213],"type":"Point"}
}