{
  "type": "Feature",
  "properties": {
    "iso:country":"US",
    "sg:address":"1256 S Lake Shore Dr",
    "sg:city":"Genoa City",
    "sg:classifiers":[
        {
            "category":"Organizations",
            "subcategory":"Religious Organization",
            "type":"Services"
        }
    ],
    "sg:phone":"+1 262 279 6295",
    "sg:postcode":"53128",
    "sg:province":"WI",
    "sg:tags":[
        "church"
    ],
    "wof:name":"St Mary's Catholic Church",
    "wof:placetype":"venue"
},
  "geometry": {"coordinates":[-88.35363099999999,42.539266],"type":"Point"}
}