{
  "type": "Feature",
  "properties": {
    "iso:country":"US",
    "sg:address":"555 E Wells St",
    "sg:city":"Milwaukee",
    "sg:classifiers":[
        {
            "category":"Organizations",
            "subcategory":"Professional Association",
            "type":"Services"
        }
    ],
    "sg:phone":"+1 414 276 5338",
    "sg:postcode":"53202",
    "sg:province":"WI",
    "wof:name":"Council For Accreditation",
    "wof:placetype":"venue"
},
  "geometry": {"coordinates":[-87.904837,43.041222],"type":"Point"}
}