{
  "type": "Feature",
  "properties": {
    "iso:country":"US",
    "sg:address":"123 W 2nd St",
    "sg:city":"New Richmond",
    "sg:classifiers":[
        {
            "category":"Retail",
            "subcategory":"Laundry & Dry Cleaning",
            "type":"Services"
        },
        {
            "category":"Personal",
            "subcategory":"Barber",
            "type":"Services"
        }
    ],
    "sg:phone":"+1 715 246 4467",
    "sg:postcode":"54017",
    "sg:province":"WI",
    "sg:tags":[
        "power"
    ],
    "wof:name":"Karl's Barber Shop",
    "wof:placetype":"venue"
},
  "geometry": {"coordinates":[-92.53880700000001,45.121721],"type":"Point"}
}