{
  "type": "Feature",
  "properties": {
    "iso:country":"US",
    "sg:address":"1956 Plover St",
    "sg:city":"Stevens Point",
    "sg:classifiers":[
        {
            "category":"Professional",
            "type":"Services"
        }
    ],
    "sg:phone":"+1 715 341 9190",
    "sg:postcode":"54481",
    "sg:province":"WI",
    "wof:name":"Bryant Browne",
    "wof:placetype":"venue"
},
  "geometry": {"coordinates":[-89.575623,44.517068],"type":"Point"}
}