{
  "type": "Feature",
  "properties": {
    "iso:country":"US",
    "sg:address":"6811 Wandawega Cir",
    "sg:city":"Mequon",
    "sg:classifiers":[
        {
            "category":"Organizations",
            "subcategory":"Non-profit Organization",
            "type":"Services"
        }
    ],
    "sg:phone":"+1 262 242 2015",
    "sg:postcode":"53092",
    "sg:province":"WI",
    "sg:tags":[
        "medical",
        "management"
    ],
    "wof:name":"Web MD Medical Management",
    "wof:placetype":"venue"
},
  "geometry": {"coordinates":[-87.99526400000001,43.219331],"type":"Point"}
}