{
  "type": "Feature",
  "properties": {
    "addr:full":"2210 W Good Hope Rd Milwaukee WI 53209",
    "addr:housenumber":"2210",
    "addr:postcode":"53209",
    "addr:street":"W Good Hope Rd",
    "iso:country":"US",
    "sg:address":"2210 W Good Hope Rd",
    "sg:city":"Milwaukee",
    "sg:classifiers":[
        {
            "category":"Insurance",
            "subcategory":"Insurance Agent",
            "type":"Services"
        }
    ],
    "sg:phone":"+1 414 351 1010",
    "sg:postcode":"53209",
    "sg:province":"WI",
    "wof:name":"Inusrance Consulting Services",
    "wof:placetype":"venue"
},
  "geometry": {"coordinates":[-87.944441,43.148411],"type":"Point"}
}