{
  "type": "Feature",
  "properties": {
    "addr:full":"107 Shoo St Brooklyn WI 53521",
    "addr:housenumber":"107",
    "addr:postcode":"53521",
    "addr:street":"Shoo St",
    "iso:country":"US",
    "sg:address":"107 Shoo St",
    "sg:city":"Brooklyn",
    "sg:classifiers":[
        {
            "category":"Retail",
            "subcategory":"Repair Shop",
            "type":"Services"
        }
    ],
    "sg:phone":"+1 608 576 7703",
    "sg:postcode":"53521",
    "sg:province":"WI",
    "sg:tags":[
        "welding"
    ],
    "wof:name":"Owen Welding",
    "wof:placetype":"venue"
},
  "geometry": {"coordinates":[-89.36666099999999,42.855258],"type":"Point"}
}