{
  "type": "Feature",
  "properties": {
    "iso:country":"US",
    "sg:address":"2911 72nd Ave",
    "sg:city":"Wilson",
    "sg:classifiers":[
        {
            "category":"Manufacturing",
            "subcategory":"Metals",
            "type":"Manufacturing & Wholesale Goods"
        }
    ],
    "sg:phone":"+1 715 772 3238",
    "sg:postcode":"54027",
    "sg:province":"WI",
    "sg:tags":[
        "production",
        "grinding"
    ],
    "wof:name":"Briskie Grinding",
    "wof:placetype":"venue"
},
  "geometry": {"coordinates":[-92.213656,44.962811],"type":"Point"}
}