{
  "type": "Feature",
  "properties": {
    "iso:country":"US",
    "sg:address":"116 E James St",
    "sg:city":"Columbus",
    "sg:classifiers":[
        {
            "category":"Shopping",
            "subcategory":"Gifts & Souvenirs",
            "type":"Retail Goods"
        }
    ],
    "sg:phone":"+1 920 623 2513",
    "sg:postcode":"53925",
    "sg:province":"WI",
    "wof:name":"West James",
    "wof:placetype":"venue"
},
  "geometry": {"coordinates":[-89.014524,43.338135],"type":"Point"}
}