{
  "type": "Feature",
  "properties": {
    "iso:country":"US",
    "sg:address":"2929 S Chase Ave",
    "sg:city":"Milwaukee",
    "sg:classifiers":[
        {
            "category":"Manufacturing",
            "subcategory":"Buildings",
            "type":"Manufacturing & Wholesale Goods"
        },
        {
            "category":"Building & Trades",
            "subcategory":"Construction",
            "type":"Services"
        }
    ],
    "sg:phone":"+1 414 744 8580",
    "sg:postcode":"53207",
    "sg:province":"WI",
    "sg:tags":[
        "asphalt",
        "builder",
        "contractor",
        "sealcoating",
        "home",
        "paving"
    ],
    "wof:name":"McDowell Construction",
    "wof:placetype":"venue"
},
  "geometry": {"coordinates":[-87.909418,42.990835],"type":"Point"}
}