{
  "type": "Feature",
  "properties": {
    "addr:full":"686 Progress Way Sun Prairie WI 53590",
    "addr:housenumber":"686",
    "addr:postcode":"53590",
    "addr:street":"Progress Way",
    "iso:country":"US",
    "sg:address":"686 Progress Way",
    "sg:city":"Sun Prairie",
    "sg:classifiers":[
        {
            "category":"Organizations",
            "subcategory":"Religious Organization",
            "type":"Services"
        }
    ],
    "sg:phone":"+1 608 834 8288",
    "sg:postcode":"53590",
    "sg:province":"WI",
    "sg:tags":[
        "church"
    ],
    "wof:name":"New Crossing Church",
    "wof:placetype":"venue"
},
  "geometry": {"coordinates":[-89.19703800000001,43.204633],"type":"Point"}
}