{
  "type": "Feature",
  "properties": {
    "iso:country":"US",
    "sg:address":"2797 Prairie Ave",
    "sg:city":"Beloit",
    "sg:classifiers":[
        {
            "category":"Professional",
            "subcategory":"Employment Agencies",
            "type":"Services"
        }
    ],
    "sg:phone":"+1 608 362 1330",
    "sg:postcode":"53511",
    "sg:province":"WI",
    "sg:tags":[
        "help",
        "contractor"
    ],
    "wof:name":"Manpower Temporary Svc",
    "wof:placetype":"venue"
},
  "geometry": {"coordinates":[-89.011577,42.543915],"type":"Point"}
}