{
  "type": "Feature",
  "properties": {
    "iso:country":"US",
    "sg:address":"708 Illinois St",
    "sg:city":"Racine",
    "sg:classifiers":[
        {
            "category":"Professional",
            "subcategory":"Business Services",
            "type":"Services"
        }
    ],
    "sg:phone":"+1 262 898 8395",
    "sg:postcode":"53405",
    "sg:province":"WI",
    "wof:name":"Anco Group Inc",
    "wof:placetype":"venue"
},
  "geometry": {"coordinates":[-87.833671,42.722635],"type":"Point"}
}