{
  "type": "Feature",
  "properties": {
    "addr:full":"10697 Lax Chapel Rd Kiel WI 53042",
    "addr:housenumber":"10697",
    "addr:postcode":"53042",
    "addr:street":"Lax Chapel Rd",
    "iso:country":"US",
    "sg:address":"10697 Lax Chapel Rd",
    "sg:city":"Kiel",
    "sg:classifiers":[
        {
            "category":"Banks & Credit Unions",
            "subcategory":"Financial Services",
            "type":"Services"
        }
    ],
    "sg:phone":"+1 920 894 3308",
    "sg:postcode":"53042",
    "sg:province":"WI",
    "sg:tags":[
        "investor"
    ],
    "wof:name":"Behnke Investments",
    "wof:placetype":"venue"
},
  "geometry": {"coordinates":[-87.982435,43.970855],"type":"Point"}
}