{
  "type": "Feature",
  "properties": {
    "iso:country":"US",
    "sg:address":"20621 Co Rd H",
    "sg:city":"Strum",
    "sg:classifiers":[
        {
            "category":"Farming",
            "subcategory":"Dairy Farm",
            "type":"Manufacturing & Wholesale Goods"
        }
    ],
    "sg:phone":"+1 715 695 3528",
    "sg:postcode":"54770",
    "sg:province":"WI",
    "sg:tags":[
        "field",
        "corn",
        "crop"
    ],
    "wof:name":"Wade & Todd",
    "wof:placetype":"venue"
},
  "geometry": {"coordinates":[-91.359619,44.545837],"type":"Point"}
}