{
  "type": "Feature",
  "properties": {
    "iso:country":"US",
    "sg:address":"2408 Johnson Rd",
    "sg:city":"Kenosha",
    "sg:classifiers":[
        {
            "category":"Professional",
            "subcategory":"Computer Services",
            "type":"Services"
        }
    ],
    "sg:phone":"+1 262 652 6979",
    "sg:postcode":"53143",
    "sg:province":"WI",
    "sg:tags":[
        "consulting",
        "datum",
        "business"
    ],
    "wof:name":"Diversified Computer",
    "wof:placetype":"venue"
},
  "geometry": {"coordinates":[-87.838202,42.561237],"type":"Point"}
}