{
  "type": "Feature",
  "properties": {
    "iso:country":"US",
    "sg:address":"651 North Ave",
    "sg:city":"Hartland",
    "sg:classifiers":[
        {
            "category":"Building & Trades",
            "subcategory":"Construction",
            "type":"Services"
        }
    ],
    "sg:phone":"+1 262 367 9590",
    "sg:postcode":"53029",
    "sg:province":"WI",
    "sg:tags":[
        "planning",
        "remodeling",
        "kitchen"
    ],
    "wof:name":"Monica Baas Design",
    "wof:placetype":"venue"
},
  "geometry": {"coordinates":[-88.343141,43.114222],"type":"Point"}
}