{
  "type": "Feature",
  "properties": {
    "iso:country":"US",
    "sg:address":"200 Oak St",
    "sg:city":"Mauston",
    "sg:classifiers":[
        {
            "category":"Government",
            "subcategory":"Office",
            "type":"Public Place"
        }
    ],
    "sg:phone":"+1 608 847 9346",
    "sg:postcode":"53948",
    "sg:province":"WI",
    "wof:name":"Register In Probate",
    "wof:placetype":"venue"
},
  "geometry": {"coordinates":[-90.07611,43.796186],"type":"Point"}
}