{
  "type": "Feature",
  "properties": {
    "iso:country":"US",
    "sg:address":"1065 Koshkonong Rd",
    "sg:city":"Cambridge",
    "sg:classifiers":[
        {
            "category":"Freight",
            "type":"Transportation"
        }
    ],
    "sg:phone":"+1 608 577 9312",
    "sg:postcode":"53523",
    "sg:province":"WI",
    "sg:tags":[
        "operator",
        "local",
        "trucking"
    ],
    "wof:name":"Vargason Trucking",
    "wof:placetype":"venue"
},
  "geometry": {"coordinates":[-89.083547,42.977704],"type":"Point"}
}