{
  "type": "Feature",
  "properties": {
    "addr:full":"8372 N Steven Rd Milwaukee WI 53223",
    "addr:housenumber":"8372",
    "addr:postcode":"53223",
    "addr:street":"N Steven Rd",
    "iso:country":"US",
    "sg:address":"8372 N Steven Rd",
    "sg:city":"Milwaukee",
    "sg:classifiers":[
        {
            "category":"Wholesale",
            "subcategory":"Durable Goods & Equipment",
            "type":"Manufacturing & Wholesale Goods"
        }
    ],
    "sg:phone":"+1 414 362 9677",
    "sg:postcode":"53223",
    "sg:province":"WI",
    "sg:tags":[
        "representative",
        "manufacturer"
    ],
    "wof:name":"Multi Pack",
    "wof:placetype":"venue"
},
  "geometry": {"coordinates":[-88.000345,43.16992],"type":"Point"}
}