{
  "type": "Feature",
  "properties": {
    "iso:country":"US",
    "sg:address":"1406 E 7th St",
    "sg:city":"Merrill",
    "sg:classifiers":[
        {
            "category":"Real Estate",
            "subcategory":"Surveying",
            "type":"Services"
        }
    ],
    "sg:phone":"+1 715 536 3113",
    "sg:postcode":"54452",
    "sg:province":"WI",
    "wof:name":"Lincoln Land Survey",
    "wof:placetype":"venue"
},
  "geometry": {"coordinates":[-89.679557,45.18605],"type":"Point"}
}