{
  "type": "Feature",
  "properties": {
    "addr:full":"3244 E Lake Virginia Rd Reedsburg WI 53959",
    "addr:housenumber":"3244",
    "addr:postcode":"53959",
    "addr:street":"E Lake Virginia Rd",
    "iso:country":"US",
    "sg:address":"3244 E Lake Virginia Rd",
    "sg:city":"Reedsburg",
    "sg:classifiers":[
        {
            "category":"Freight",
            "type":"Transportation"
        }
    ],
    "sg:phone":"+1 608 524 3050",
    "sg:postcode":"53959",
    "sg:province":"WI",
    "sg:tags":[
        "operator",
        "local",
        "trucking"
    ],
    "wof:name":"Steve Whitney Trucking LLC",
    "wof:placetype":"venue"
},
  "geometry": {"coordinates":[-89.937714,43.529981],"type":"Point"}
}