{
  "type": "Feature",
  "properties": {
    "iso:country":"US",
    "sg:address":"24691 State Rd 35 70",
    "sg:city":"Siren",
    "sg:classifiers":[
        {
            "category":"Manufacturing",
            "subcategory":"Printing",
            "type":"Manufacturing & Wholesale Goods"
        }
    ],
    "sg:phone":"+1 715 349 2040",
    "sg:postcode":"54872",
    "sg:province":"WI",
    "sg:tags":[
        "printer"
    ],
    "wof:name":"Lakeland Press",
    "wof:placetype":"venue"
},
  "geometry": {"coordinates":[-92.369204,45.811912],"type":"Point"}
}