{
  "type": "Feature",
  "properties": {
    "iso:country":"US",
    "sg:address":"156 Co Hwy G",
    "sg:city":"Wonewoc",
    "sg:classifiers":[
        {
            "category":"Farming",
            "subcategory":"Livestock Farm",
            "type":"Manufacturing & Wholesale Goods"
        }
    ],
    "sg:phone":"+1 608 489 3104",
    "sg:postcode":"53968",
    "sg:province":"WI",
    "sg:tags":[
        "beef",
        "feedlot",
        "cattle"
    ],
    "wof:name":"Francis Goodman",
    "wof:placetype":"venue"
},
  "geometry": {"coordinates":[-90.221714,43.649842],"type":"Point"}
}