{
  "type": "Feature",
  "properties": {
    "iso:country":"US",
    "sg:address":"19109 Ucker Point Creek Rd",
    "sg:city":"Kiel",
    "sg:classifiers":[
        {
            "category":"Freight",
            "type":"Transportation"
        }
    ],
    "sg:phone":"+1 920 894 2502",
    "sg:postcode":"53042",
    "sg:province":"WI",
    "sg:tags":[
        "operator",
        "local",
        "trucking"
    ],
    "wof:name":"Jungles Trucking",
    "wof:placetype":"venue"
},
  "geometry": {"coordinates":[-88.00721,43.964049],"type":"Point"}
}