{
  "type": "Feature",
  "properties": {
    "iso:country":"US",
    "sg:address":"1511 Eastern Ave",
    "sg:city":"Plymouth",
    "sg:classifiers":[
        {
            "category":"Restaurant",
            "type":"Food & Drink"
        }
    ],
    "sg:menulink":"http://www.allmenus.com/wi/plymouth/145707-subway/menu/",
    "sg:phone":"+1 920 892 6159",
    "sg:postcode":"53073",
    "sg:province":"WI",
    "sg:tags":[
        "american",
        "sandwich"
    ],
    "wof:name":"Subway",
    "wof:placetype":"venue"
},
  "geometry": {"coordinates":[-87.962754,43.747048],"type":"Point"}
}