{
  "type": "Feature",
  "properties": {
    "addr:full":"4919 Gills Coulee Rd West Salem WI 54669",
    "addr:housenumber":"4919",
    "addr:postcode":"54669",
    "addr:street":"Gills Coulee Rd",
    "iso:country":"US",
    "sg:address":"4919 Gills Coulee Rd",
    "sg:city":"West Salem",
    "sg:classifiers":[
        {
            "category":"Retail",
            "subcategory":"Repair Shop",
            "type":"Services"
        }
    ],
    "sg:phone":"+1 608 786 1397",
    "sg:postcode":"54669",
    "sg:province":"WI",
    "sg:tags":[
        "taxidermist"
    ],
    "wof:name":"Thunder Valley Taxidermy",
    "wof:placetype":"venue"
},
  "geometry": {"coordinates":[-91.146714,43.918384],"type":"Point"}
}