{
  "type": "Feature",
  "properties": {
    "iso:country":"US",
    "sg:address":"2831 Grandview Blvd",
    "sg:city":"Pewaukee",
    "sg:classifiers":[
        {
            "category":"Banks & Credit Unions",
            "subcategory":"Investment Brokerage",
            "type":"Services"
        }
    ],
    "sg:phone":"+1 262 544 6330",
    "sg:postcode":"53072",
    "sg:province":"WI",
    "sg:tags":[
        "security"
    ],
    "wof:name":"C J W & Assoc",
    "wof:placetype":"venue"
},
  "geometry": {"coordinates":[-88.252231,43.070417],"type":"Point"}
}