{
  "type": "Feature",
  "properties": {
    "addr:full":"101 E Milwaukee St Janesville WI 53545",
    "addr:housenumber":"101",
    "addr:postcode":"53545",
    "addr:street":"E Milwaukee St",
    "iso:country":"US",
    "sg:address":"101 E Milwaukee St",
    "sg:city":"Janesville",
    "sg:classifiers":[
        {
            "category":"Government",
            "subcategory":"Office",
            "type":"Public Place"
        }
    ],
    "sg:phone":"+1 608 758 6190",
    "sg:postcode":"53545",
    "sg:province":"WI",
    "sg:tags":[
        "state",
        "taxation"
    ],
    "wof:name":"Revenue Dept Income",
    "wof:placetype":"venue"
},
  "geometry": {"coordinates":[-89.021507,42.683464],"type":"Point"}
}