{
  "type": "Feature",
  "properties": {
    "iso:country":"US",
    "sg:address":"2425 Stone Rd",
    "sg:city":"Manitowoc",
    "sg:classifiers":[
        {
            "category":"Building & Trades",
            "subcategory":"Construction",
            "type":"Services"
        }
    ],
    "sg:phone":"+1 920 684 0624",
    "sg:postcode":"54220",
    "sg:province":"WI",
    "sg:tags":[
        "house"
    ],
    "wof:name":"Dworak Builders",
    "wof:placetype":"venue"
},
  "geometry": {"coordinates":[-87.740898,44.124382],"type":"Point"}
}