{
  "type": "Feature",
  "properties": {
    "addr:full":"3893 Terrace Cir De Forest WI 53532",
    "addr:housenumber":"3893",
    "addr:postcode":"53532",
    "addr:street":"Terrace Cir",
    "iso:country":"US",
    "sg:address":"3893 Terrace Cir",
    "sg:city":"De Forest",
    "sg:classifiers":[
        {
            "category":"Arts & Performance",
            "subcategory":"Theater",
            "type":"Entertainment"
        }
    ],
    "sg:phone":"+1 608 240 4770",
    "sg:postcode":"53532",
    "sg:province":"WI",
    "sg:tags":[
        "television",
        "program",
        "producer"
    ],
    "wof:name":"Toeken Creek Mobile TV",
    "wof:placetype":"venue"
},
  "geometry": {"coordinates":[-89.300012,43.213146],"type":"Point"}
}