{
  "type": "Feature",
  "properties": {
    "iso:country":"US",
    "sg:address":"4238 Acker Rd",
    "sg:city":"Madison",
    "sg:classifiers":[
        {
            "category":"Shopping",
            "type":"Retail Goods"
        }
    ],
    "sg:phone":"+1 608 249 8178",
    "sg:postcode":"53704",
    "sg:province":"WI",
    "sg:tags":[
        "custom",
        "monument"
    ],
    "wof:name":"Pechmann Memorials Inc",
    "wof:placetype":"venue"
},
  "geometry": {"coordinates":[-89.32611,43.167065],"type":"Point"}
}