{
  "type": "Feature",
  "properties": {
    "iso:country":"US",
    "sg:address":"1613 Randy Ln",
    "sg:city":"Madison",
    "sg:classifiers":[
        {
            "category":"Arts & Performance",
            "subcategory":"Theater",
            "type":"Entertainment"
        }
    ],
    "sg:phone":"+1 608 249 9014",
    "sg:postcode":"53704",
    "sg:province":"WI",
    "sg:tags":[
        "musician"
    ],
    "wof:name":"Shirley G Storkson",
    "wof:placetype":"venue"
},
  "geometry": {"coordinates":[-89.367369,43.134865],"type":"Point"}
}