{
  "type": "Feature",
  "properties": {
    "iso:country":"US",
    "sg:address":"5123 W Villard Ave",
    "sg:city":"Milwaukee",
    "sg:classifiers":[
        {
            "category":"Food & Beverages",
            "subcategory":"Groceries & Convenience Stores",
            "type":"Retail Goods"
        }
    ],
    "sg:phone":"+1 414 464 7270",
    "sg:postcode":"53218",
    "sg:province":"WI",
    "sg:tags":[
        "grocer",
        "beer"
    ],
    "wof:name":"Villard Shop Rite",
    "wof:placetype":"venue"
},
  "geometry": {"coordinates":[-87.97729200000001,43.11192],"type":"Point"}
}