{
  "type": "Feature",
  "properties": {
    "iso:country":"US",
    "sg:address":"2066 S 37th St",
    "sg:city":"Milwaukee",
    "sg:classifiers":[
        {
            "category":"Bars & Pubs",
            "type":"Food & Drink"
        }
    ],
    "sg:phone":"+1 414 643 8052",
    "sg:postcode":"53215",
    "sg:province":"WI",
    "sg:tags":[
        "drinking"
    ],
    "wof:name":"Working Class Heros",
    "wof:placetype":"venue"
},
  "geometry": {"coordinates":[-87.960403,43.007832],"type":"Point"}
}