{
  "type": "Feature",
  "properties": {
    "iso:country":"US",
    "sg:address":"3730 W Holmes Ave",
    "sg:city":"Milwaukee",
    "sg:classifiers":[
        {
            "category":"Building & Trades",
            "subcategory":"Construction",
            "type":"Services"
        }
    ],
    "sg:phone":"+1 414 241 7956",
    "sg:postcode":"53221",
    "sg:province":"WI",
    "wof:name":"Mulqueen Bros LLC",
    "wof:placetype":"venue"
},
  "geometry": {"coordinates":[-87.963268,42.954393],"type":"Point"}
}