{
  "type": "Feature",
  "properties": {
    "iso:country":"US",
    "sg:address":"1524 60th Ave",
    "sg:city":"Roberts",
    "sg:classifiers":[
        {
            "category":"Retail",
            "subcategory":"Auto Repair",
            "type":"Services"
        }
    ],
    "sg:phone":"+1 715 796 5547",
    "sg:postcode":"54023",
    "sg:province":"WI",
    "sg:tags":[
        "automotive"
    ],
    "wof:name":"Mrb Radiator Repair",
    "wof:placetype":"venue"
},
  "geometry": {"coordinates":[-92.500547,44.949283],"type":"Point"}
}