{
  "type": "Feature",
  "properties": {
    "iso:country":"US",
    "sg:address":"1800 Stewart Ave",
    "sg:city":"Wausau",
    "sg:classifiers":[
        {
            "category":"Restaurant",
            "type":"Food & Drink"
        }
    ],
    "sg:menulink":"http://www.allmenus.com/wi/wausau/89038-figaros-pizza/menu/",
    "sg:phone":"+1 715 849 9292",
    "sg:postcode":"54401",
    "sg:province":"WI",
    "sg:tags":[
        "american",
        "italian",
        "pizza"
    ],
    "wof:name":"Figaro's Pizza",
    "wof:placetype":"venue"
},
  "geometry": {"coordinates":[-89.65769299999999,44.95918],"type":"Point"}
}