{
  "type": "Feature",
  "properties": {
    "addr:full":"1701 Lands End Ln Reedsburg WI 53959",
    "addr:housenumber":"1701",
    "addr:postcode":"53959",
    "addr:street":"Lands End Ln",
    "iso:country":"US",
    "sg:address":"1701 Lands End Ln",
    "sg:city":"Reedsburg",
    "sg:classifiers":[
        {
            "category":"Shopping",
            "subcategory":"Catalog Store",
            "type":"Retail Goods"
        }
    ],
    "sg:phone":"+1 608 524 7000",
    "sg:postcode":"53959",
    "sg:province":"WI",
    "sg:tags":[
        "house",
        "mail"
    ],
    "wof:name":"Lands End",
    "wof:placetype":"venue"
},
  "geometry": {"coordinates":[-89.98266599999999,43.543333],"type":"Point"}
}