{
  "type": "Feature",
  "properties": {
    "iso:country":"US",
    "sg:address":"4265 N 30th St",
    "sg:city":"Milwaukee",
    "sg:classifiers":[
        {
            "category":"Manufacturing",
            "subcategory":"Tools & Machinery",
            "type":"Manufacturing & Wholesale Goods"
        }
    ],
    "sg:phone":"+1 414 875 2900",
    "sg:postcode":"53209",
    "sg:province":"WI",
    "sg:tags":[
        "control",
        "industrial",
        "relay"
    ],
    "sg:website":"www.drs-pct.com",
    "wof:name":"DRS Power & Control Tech Inc",
    "wof:placetype":"venue"
},
  "geometry": {"coordinates":[-87.950604,43.094323],"type":"Point"}
}