{
  "type": "Feature",
  "properties": {
    "addr:full":"5270 Williamsburg Way Fitchburg WI 53719",
    "addr:housenumber":"5270",
    "addr:postcode":"53719",
    "addr:street":"Williamsburg Way",
    "iso:country":"US",
    "sg:address":"5270 Williamsburg Way",
    "sg:city":"Fitchburg",
    "sg:classifiers":[
        {
            "category":"Personal",
            "subcategory":"Beauty Salon",
            "type":"Services"
        },
        {
            "category":"Personal",
            "subcategory":"Barber",
            "type":"Services"
        }
    ],
    "sg:phone":"+1 608 274 6869",
    "sg:postcode":"53719",
    "sg:province":"WI",
    "sg:website":"http://www.touchofclasshairstyling.com",
    "wof:name":"Touch Of Class Hairstyling, Inc",
    "wof:placetype":"venue"
},
  "geometry": {"coordinates":[-89.469976,43.024281],"type":"Point"}
}