{
  "type": "Feature",
  "properties": {
    "iso:country":"US",
    "sg:address":"5786 Seminole Ridge Cir",
    "sg:city":"Madison",
    "sg:classifiers":[
        {
            "category":"Professional",
            "subcategory":"Art Services",
            "type":"Services"
        }
    ],
    "sg:phone":"+1 608 288 9459",
    "sg:postcode":"53711",
    "sg:province":"WI",
    "sg:tags":[
        "commercial",
        "design"
    ],
    "wof:name":"A Line Design",
    "wof:placetype":"venue"
},
  "geometry": {"coordinates":[-89.444914,43.008935],"type":"Point"}
}