{
  "type": "Feature",
  "properties": {
    "iso:country":"US",
    "sg:address":"1331 Packerland Dr",
    "sg:city":"Green Bay",
    "sg:classifiers":[
        {
            "category":"Education",
            "subcategory":"Special Training",
            "type":"Public Place"
        }
    ],
    "sg:phone":"+1 920 492 2678",
    "sg:postcode":"54304",
    "sg:province":"WI",
    "sg:tags":[
        "educational",
        "provides"
    ],
    "wof:name":"Interactive Learning Services",
    "wof:placetype":"venue"
},
  "geometry": {"coordinates":[-88.09932499999999,44.518618],"type":"Point"}
}