{
  "type": "Feature",
  "properties": {
    "iso:country":"US",
    "sg:address":"6155 W Fond du Lac Ave",
    "sg:city":"Milwaukee",
    "sg:classifiers":[
        {
            "category":"Retail",
            "subcategory":"Auto Repair",
            "type":"Services"
        }
    ],
    "sg:phone":"+1 414 527 3131",
    "sg:postcode":"53218",
    "sg:province":"WI",
    "sg:tags":[
        "repairing",
        "automobile"
    ],
    "wof:name":"Auto Werkes Import Ctr",
    "wof:placetype":"venue"
},
  "geometry": {"coordinates":[-87.98774,43.098517],"type":"Point"}
}