{
  "type": "Feature",
  "properties": {
    "iso:country":"US",
    "sg:address":"413 E Washington St",
    "sg:city":"Slinger",
    "sg:classifiers":[
        {
            "category":"Real Estate",
            "subcategory":"Surveying",
            "type":"Services"
        }
    ],
    "sg:phone":"+1 262 644 0395",
    "sg:postcode":"53086",
    "sg:province":"WI",
    "sg:tags":[
        "surveyor"
    ],
    "wof:name":"Baudhuin Inc",
    "wof:placetype":"venue"
},
  "geometry": {"coordinates":[-88.28149500000001,43.331792],"type":"Point"}
}