{
  "type": "Feature",
  "properties": {
    "iso:country":"US",
    "sg:address":"3158 State Hwy 149",
    "sg:city":"Malone",
    "sg:classifiers":[
        {
            "category":"Farming",
            "subcategory":"Dairy Farm",
            "type":"Manufacturing & Wholesale Goods"
        }
    ],
    "sg:phone":"+1 920 795 4708",
    "sg:postcode":"53049",
    "sg:province":"WI",
    "sg:tags":[
        "field",
        "corn",
        "wheat",
        "crop"
    ],
    "wof:name":"Raymond Wagner",
    "wof:placetype":"venue"
},
  "geometry": {"coordinates":[-88.317435,43.833652],"type":"Point"}
}