{
  "type": "Feature",
  "properties": {
    "addr:full":"1976 Verlin Rd Green Bay WI 54311",
    "addr:housenumber":"1976",
    "addr:postcode":"54311",
    "addr:street":"Verlin Rd",
    "iso:country":"US",
    "sg:address":"1976 Verlin Rd",
    "sg:city":"Green Bay",
    "sg:classifiers":[
        {
            "category":"Manufacturing",
            "subcategory":"Building Materials",
            "type":"Manufacturing & Wholesale Goods"
        }
    ],
    "sg:phone":"+1 920 468 0163",
    "sg:postcode":"54311",
    "sg:province":"WI",
    "sg:tags":[
        "bathroom",
        "mfg",
        "wooden",
        "cabinet",
        "kitchen",
        "vanity"
    ],
    "wof:name":"Kitchen Kraft Inc",
    "wof:placetype":"venue"
},
  "geometry": {"coordinates":[-87.984223,44.474308],"type":"Point"}
}