{
  "type": "Feature",
  "properties": {
    "iso:country":"US",
    "sg:address":"14273 Waters Way",
    "sg:city":"New Berlin",
    "sg:classifiers":[
        {
            "category":"Professional",
            "subcategory":"Computer Services",
            "type":"Services"
        }
    ],
    "sg:phone":"+1 414 736 1139",
    "sg:postcode":"53151",
    "sg:province":"WI",
    "sg:tags":[
        "internet"
    ],
    "wof:name":"Lee & Lee Innovations",
    "wof:placetype":"venue"
},
  "geometry": {"coordinates":[-88.09163100000001,42.987331],"type":"Point"}
}