{
  "type": "Feature",
  "properties": {
    "addr:full":"527 S Janesville St Whitewater WI 53190",
    "addr:housenumber":"527",
    "addr:postcode":"53190",
    "addr:street":"S Janesville St",
    "iso:country":"US",
    "sg:address":"527 S Janesville St",
    "sg:city":"Whitewater",
    "sg:classifiers":[
        {
            "category":"Retail",
            "subcategory":"Veterinary Services",
            "type":"Services"
        }
    ],
    "sg:phone":"+1 262 473 2930",
    "sg:postcode":"53190",
    "sg:province":"WI",
    "sg:tags":[
        "veterinarian"
    ],
    "sg:website":"http://www.whitewatervethospital.com",
    "wof:name":"Whitewater Veterinary Hospital SC",
    "wof:placetype":"venue"
},
  "geometry": {"coordinates":[-88.74269700000001,42.827444],"type":"Point"}
}