{
  "type": "Feature",
  "properties": {
    "iso:country":"US",
    "sg:address":"10744 Owen Ave",
    "sg:city":"Greenwood",
    "sg:classifiers":[
        {
            "category":"Farming",
            "subcategory":"Dairy Farm",
            "type":"Manufacturing & Wholesale Goods"
        }
    ],
    "sg:phone":"+1 715 267 6336",
    "sg:postcode":"54437",
    "sg:province":"WI",
    "wof:name":"Lloyd Engelberth",
    "wof:placetype":"venue"
},
  "geometry": {"coordinates":[-90.557327,44.804838],"type":"Point"}
}