{
  "type": "Feature",
  "properties": {
    "iso:country":"US",
    "sg:address":"1110 S Oneida St",
    "sg:city":"Appleton",
    "sg:classifiers":[
        {
            "category":"Freight",
            "type":"Transportation"
        }
    ],
    "sg:phone":"+1 920 739 3101",
    "sg:postcode":"54915",
    "sg:province":"WI",
    "sg:tags":[
        "general"
    ],
    "wof:name":"Pack Rat Mini Storage",
    "wof:placetype":"venue"
},
  "geometry": {"coordinates":[-88.404577,44.252433],"type":"Point"}
}