{
  "type": "Feature",
  "properties": {
    "iso:country":"US",
    "sg:address":"8519 Wicks Rd",
    "sg:city":"Gratiot",
    "sg:classifiers":[
        {
            "category":"Wholesale",
            "subcategory":"Farm Supplies",
            "type":"Manufacturing & Wholesale Goods"
        }
    ],
    "sg:phone":"+1 608 922 3397",
    "sg:postcode":"53541",
    "sg:province":"WI",
    "wof:name":"Komproods Feed Service",
    "wof:placetype":"venue"
},
  "geometry": {"coordinates":[-89.985527,42.572766],"type":"Point"}
}