{
  "type": "Feature",
  "properties": {
    "addr:full":"7112 Co Rd P Watertown WI 53094",
    "addr:housenumber":"7112",
    "addr:postcode":"53094",
    "addr:street":"Co Rd",
    "iso:country":"US",
    "sg:address":"7112 Co Rd P",
    "sg:city":"Watertown",
    "sg:classifiers":[
        {
            "category":"Farming",
            "subcategory":"Livestock Farm",
            "type":"Manufacturing & Wholesale Goods"
        }
    ],
    "sg:phone":"+1 920 262 1915",
    "sg:postcode":"53094",
    "sg:province":"WI",
    "sg:tags":[
        "general"
    ],
    "wof:name":"Strese Farmington Acres",
    "wof:placetype":"venue"
},
  "geometry": {"coordinates":[-88.656918,43.103673],"type":"Point"}
}