{
  "type": "Feature",
  "properties": {
    "addr:full":"5302 Co Hwy P Delavan WI 53115",
    "addr:housenumber":"5302",
    "addr:postcode":"53115",
    "addr:street":"Co Hwy P Delavan",
    "iso:country":"US",
    "sg:address":"5302 Co Hwy P",
    "sg:city":"Delavan",
    "sg:classifiers":[
        {
            "category":"Building & Trades",
            "subcategory":"Construction",
            "type":"Services"
        }
    ],
    "sg:phone":"+1 262 728 5054",
    "sg:postcode":"53115",
    "sg:province":"WI",
    "sg:tags":[
        "excavating",
        "contractor"
    ],
    "wof:name":"Haban Septic & Excavating",
    "wof:placetype":"venue"
},
  "geometry": {"coordinates":[-88.660121,42.697975],"type":"Point"}
}