{
  "type": "Feature",
  "properties": {
    "addr:full":"2992 Beechwood Industrial Ct Hubertus WI 53033",
    "addr:housenumber":"2992",
    "addr:postcode":"53033",
    "addr:street":"Beechwood Industrial Ct",
    "iso:country":"US",
    "sg:address":"2992 Beechwood Industrial Ct",
    "sg:city":"Hubertus",
    "sg:classifiers":[
        {
            "category":"Cinema",
            "subcategory":"Movie Rental",
            "type":"Entertainment"
        }
    ],
    "sg:phone":"+1 262 628 4444",
    "sg:postcode":"53033",
    "sg:province":"WI",
    "sg:tags":[
        "video",
        "tape"
    ],
    "wof:name":"Hollywood Video",
    "wof:placetype":"venue"
},
  "geometry": {"coordinates":[-88.188123,43.233655],"type":"Point"}
}