{
  "type": "Feature",
  "properties": {
    "iso:country":"US",
    "sg:address":"2527 Main St",
    "sg:city":"Cross Plains",
    "sg:classifiers":[
        {
            "category":"Insurance",
            "subcategory":"Insurance Agent",
            "type":"Services"
        }
    ],
    "sg:phone":"+1 608 798 3511",
    "sg:postcode":"53528",
    "sg:province":"WI",
    "wof:name":"Mike Grzenia Insurance",
    "wof:placetype":"venue"
},
  "geometry": {"coordinates":[-89.643085,43.110597],"type":"Point"}
}