{
  "type": "Feature",
  "properties": {
    "iso:country":"US",
    "sg:address":"1570 Elizabeth St",
    "sg:city":"Green Bay",
    "sg:classifiers":[
        {
            "category":"Organizations",
            "subcategory":"Labor Organization",
            "type":"Services"
        }
    ],
    "sg:phone":"+1 920 432 1128",
    "sg:postcode":"54302",
    "sg:province":"WI",
    "wof:name":"Local 158",
    "wof:placetype":"venue"
},
  "geometry": {"coordinates":[-87.98268299999999,44.520545],"type":"Point"}
}