{
  "type": "Feature",
  "properties": {
    "iso:country":"US",
    "sg:address":"3223 Tower Ave",
    "sg:city":"Superior",
    "sg:classifiers":[
        {
            "category":"Bars & Pubs",
            "type":"Food & Drink"
        },
        {
            "category":"Restaurant",
            "type":"Food & Drink"
        }
    ],
    "sg:phone":"+1 715 392 7141",
    "sg:postcode":"54880",
    "sg:province":"WI",
    "sg:tags":[
        "drinking",
        "eating"
    ],
    "wof:name":"Joes Pagoda Chinese Restaurant",
    "wof:placetype":"venue"
},
  "geometry": {"coordinates":[-92.104136,46.700612],"type":"Point"}
}