{
  "type": "Feature",
  "properties": {
    "iso:country":"US",
    "sg:address":"3460 Creekview Rd",
    "sg:city":"De Pere",
    "sg:classifiers":[
        {
            "category":"Building & Trades",
            "subcategory":"Construction",
            "type":"Services"
        }
    ],
    "sg:phone":"+1 920 336 5469",
    "sg:postcode":"54115",
    "sg:province":"WI",
    "sg:tags":[
        "concrete",
        "contractor"
    ],
    "wof:name":"B & B Construction Co",
    "wof:placetype":"venue"
},
  "geometry": {"coordinates":[-87.958381,44.400887],"type":"Point"}
}