{
  "type": "Feature",
  "properties": {
    "addr:full":"6791 Co Rd Oj Plymouth WI 53073",
    "addr:housenumber":"6791",
    "addr:postcode":"53073",
    "addr:street":"Co Rd",
    "iso:country":"US",
    "sg:address":"6791 Co Rd Oj",
    "sg:city":"Plymouth",
    "sg:classifiers":[
        {
            "category":"Arts & Performance",
            "subcategory":"Theater",
            "type":"Entertainment"
        }
    ],
    "sg:phone":"+1 920 893 8934",
    "sg:postcode":"53073",
    "sg:province":"WI",
    "sg:tags":[
        "live",
        "music"
    ],
    "wof:name":"R J Productions",
    "wof:placetype":"venue"
},
  "geometry": {"coordinates":[-87.97160100000001,43.786705],"type":"Point"}
}