{
  "type": "Feature",
  "properties": {
    "iso:country":"US",
    "sg:address":"15850 W Bluemound Rd",
    "sg:city":"Brookfield",
    "sg:classifiers":[
        {
            "category":"Real Estate",
            "subcategory":"Real Estate Operator",
            "type":"Services"
        }
    ],
    "sg:phone":"+1 262 785 9803",
    "sg:postcode":"53005",
    "sg:province":"WI",
    "sg:tags":[
        "condominium"
    ],
    "wof:name":"Condo Emporium",
    "wof:placetype":"venue"
},
  "geometry": {"coordinates":[-88.10817,43.036225],"type":"Point"}
}