{
  "type": "Feature",
  "properties": {
    "iso:country":"US",
    "sg:address":"2047 N Cambridge Ave",
    "sg:city":"Milwaukee",
    "sg:classifiers":[
        {
            "category":"Real Estate",
            "subcategory":"Real Estate Agent",
            "type":"Services"
        }
    ],
    "sg:phone":"+1 414 291 5104",
    "sg:postcode":"53202",
    "sg:province":"WI",
    "sg:tags":[
        "management"
    ],
    "wof:name":"Bell Property Management",
    "wof:placetype":"venue"
},
  "geometry": {"coordinates":[-87.892029,43.05831],"type":"Point"}
}