{
  "type": "Feature",
  "properties": {
    "iso:country":"US",
    "sg:address":"6401 116th St",
    "sg:city":"Pleasant Prairie",
    "sg:classifiers":[
        {
            "category":"Building & Trades",
            "subcategory":"Construction",
            "type":"Services"
        }
    ],
    "sg:phone":"+1 262 694 1550",
    "sg:postcode":"53158",
    "sg:province":"WI",
    "sg:tags":[
        "excavation",
        "contractor"
    ],
    "wof:name":"Ingrams Excavtg",
    "wof:placetype":"venue"
},
  "geometry": {"coordinates":[-87.883329,42.508199],"type":"Point"}
}