{
  "type": "Feature",
  "properties": {
    "iso:country":"US",
    "sg:address":"1215 Co Rd L",
    "sg:city":"East Troy",
    "sg:classifiers":[
        {
            "category":"Autos & Motor Vehicles",
            "subcategory":"Auto Supplies",
            "type":"Retail Goods"
        }
    ],
    "sg:phone":"+1 262 642 4223",
    "sg:postcode":"53120",
    "sg:province":"WI",
    "wof:name":"Gleason Equipment",
    "wof:placetype":"venue"
},
  "geometry": {"coordinates":[-88.360553,42.806131],"type":"Point"}
}