{
  "type": "Feature",
  "properties": {
    "addr:full":"658 13th St Hillsdale WI 54733",
    "addr:housenumber":"658",
    "addr:postcode":"54733",
    "addr:street":"13Th St",
    "iso:country":"US",
    "sg:address":"658 13th St",
    "sg:city":"Hillsdale",
    "sg:classifiers":[
        {
            "category":"Farming",
            "subcategory":"Farm",
            "type":"Manufacturing & Wholesale Goods"
        }
    ],
    "sg:phone":"+1 715 837 1514",
    "sg:postcode":"54733",
    "sg:province":"WI",
    "wof:name":"Raising Acres",
    "wof:placetype":"venue"
},
  "geometry": {"coordinates":[-91.89031300000001,45.308483],"type":"Point"}
}