{
  "type": "Feature",
  "properties": {
    "addr:full":"3715 S O Riley Rd Darien WI 53114",
    "addr:housenumber":"3715;o",
    "addr:postcode":"53114",
    "addr:street":"S;Riley Rd",
    "iso:country":"US",
    "sg:address":"3715 S O Riley Rd",
    "sg:city":"Darien",
    "sg:classifiers":[
        {
            "category":"Building & Trades",
            "subcategory":"Construction",
            "type":"Services"
        }
    ],
    "sg:phone":"+1 262 724 5625",
    "sg:postcode":"53114",
    "sg:province":"WI",
    "sg:tags":[
        "concrete",
        "contractor"
    ],
    "wof:name":"Paschke Concrete",
    "wof:placetype":"venue"
},
  "geometry": {"coordinates":[-88.78594699999999,42.621814],"type":"Point"}
}