{
  "type": "Feature",
  "properties": {
    "iso:country":"US",
    "sg:address":"16950 W Lincoln Ave",
    "sg:city":"New Berlin",
    "sg:classifiers":[
        {
            "category":"Wholesale",
            "subcategory":"Stationery",
            "type":"Manufacturing & Wholesale Goods"
        }
    ],
    "sg:phone":"+1 262 797 7180",
    "sg:postcode":"53151",
    "sg:province":"WI",
    "sg:tags":[
        "mill",
        "paper",
        "broker",
        "representative"
    ],
    "sg:website":"www.rjschinner.com",
    "wof:name":"R J Schinner Co Inc",
    "wof:placetype":"venue"
},
  "geometry": {"coordinates":[-88.123624,43.002584],"type":"Point"}
}