{
  "type": "Feature",
  "properties": {
    "iso:country":"US",
    "sg:address":"5900 N Port Washington Rd",
    "sg:city":"Milwaukee",
    "sg:classifiers":[
        {
            "category":"Shopping",
            "subcategory":"Clothing, Apparel, & Fashions",
            "type":"Retail Goods"
        }
    ],
    "sg:phone":"+1 414 964 6865",
    "sg:postcode":"53217",
    "sg:province":"WI",
    "sg:tags":[
        "item",
        "boutique"
    ],
    "wof:name":"Claire's Boutique",
    "wof:placetype":"venue"
},
  "geometry": {"coordinates":[-87.91653100000001,43.118908],"type":"Point"}
}