{
  "type": "Feature",
  "properties": {
    "iso:country":"US",
    "sg:address":"1250 Femrite Dr",
    "sg:city":"Monona",
    "sg:classifiers":[
        {
            "category":"Professional",
            "type":"Services"
        }
    ],
    "sg:phone":"+1 608 839 8843",
    "sg:postcode":"53716",
    "sg:province":"WI",
    "sg:tags":[
        "establishment"
    ],
    "wof:name":"Paul Davis Systems",
    "wof:placetype":"venue"
},
  "geometry": {"coordinates":[-89.31159599999999,43.05052],"type":"Point"}
}