{
  "type": "Feature",
  "properties": {
    "iso:country":"US",
    "sg:address":"5679 Dutch Hollow Rd",
    "sg:city":"Potosi",
    "sg:classifiers":[
        {
            "category":"Farming",
            "subcategory":"Livestock Farm",
            "type":"Manufacturing & Wholesale Goods"
        }
    ],
    "sg:phone":"+1 608 763 2474",
    "sg:postcode":"53820",
    "sg:province":"WI",
    "sg:tags":[
        "corn",
        "beef",
        "feedlot",
        "cattle"
    ],
    "wof:name":"Gene Reynolds",
    "wof:placetype":"venue"
},
  "geometry": {"coordinates":[-90.78456300000001,42.704903],"type":"Point"}
}