{
  "type": "Feature",
  "properties": {
    "iso:country":"US",
    "sg:address":"1601 Cedar Point Dr",
    "sg:city":"Delavan",
    "sg:classifiers":[
        {
            "category":"Manufacturing",
            "subcategory":"Chemicals & Compounds",
            "type":"Manufacturing & Wholesale Goods"
        }
    ],
    "sg:phone":"+1 262 728 4205",
    "sg:postcode":"53115",
    "sg:province":"WI",
    "sg:tags":[
        "preparation",
        "pharmaceutical",
        "mfg"
    ],
    "wof:name":"Health LLC",
    "wof:placetype":"venue"
},
  "geometry": {"coordinates":[-88.60731699999999,42.607316],"type":"Point"}
}