{
  "type": "Feature",
  "properties": {
    "iso:country":"US",
    "sg:address":"281 S Victory St",
    "sg:city":"Fall Creek",
    "sg:classifiers":[
        {
            "category":"Building & Trades",
            "subcategory":"Construction",
            "type":"Services"
        }
    ],
    "sg:phone":"+1 715 877 3725",
    "sg:postcode":"54742",
    "sg:province":"WI",
    "sg:tags":[
        "masonry",
        "contractor"
    ],
    "wof:name":"D & M Masonry Inc",
    "wof:placetype":"venue"
},
  "geometry": {"coordinates":[-91.28002,44.761132],"type":"Point"}
}