{
  "type": "Feature",
  "properties": {
    "iso:country":"US",
    "sg:address":"253 Tower Heights Ct",
    "sg:city":"Prescott",
    "sg:classifiers":[
        {
            "category":"Building & Trades",
            "subcategory":"Construction",
            "type":"Services"
        }
    ],
    "sg:phone":"+1 715 262 5109",
    "sg:postcode":"54021",
    "sg:province":"WI",
    "sg:tags":[
        "agricultural",
        "general",
        "contractor"
    ],
    "wof:name":"Croix Construction Co Inc",
    "wof:placetype":"venue"
},
  "geometry": {"coordinates":[-92.78433,44.75076],"type":"Point"}
}