{
  "type": "Feature",
  "properties": {
    "iso:country":"US",
    "sg:address":"4820 Co Rd B",
    "sg:city":"La Crosse",
    "sg:classifiers":[
        {
            "category":"Professional",
            "subcategory":"Business Services",
            "type":"Services"
        },
        {
            "category":"Building & Trades",
            "subcategory":"Construction",
            "type":"Services"
        }
    ],
    "sg:phone":"+1 608 785 3001",
    "sg:postcode":"54601",
    "sg:province":"WI",
    "sg:tags":[
        "restoration",
        "cleaning",
        "patio",
        "deck"
    ],
    "wof:name":"Premier Pressure Washing",
    "wof:placetype":"venue"
},
  "geometry": {"coordinates":[-91.186081,43.858514],"type":"Point"}
}