{
  "type": "Feature",
  "properties": {
    "iso:country":"US",
    "sg:address":"515 S Knowles Ave",
    "sg:city":"New Richmond",
    "sg:classifiers":[
        {
            "category":"Personal",
            "subcategory":"Barber",
            "type":"Services"
        }
    ],
    "sg:phone":"+1 715 246 4966",
    "sg:postcode":"54017",
    "sg:province":"WI",
    "wof:name":"Hair Unlimited",
    "wof:placetype":"venue"
},
  "geometry": {"coordinates":[-92.537588,45.118095],"type":"Point"}
}