{
  "type": "Feature",
  "properties": {
    "iso:country":"US",
    "sg:address":"3372 Co Rd S",
    "sg:city":"Marathon",
    "sg:classifiers":[
        {
            "category":"Organizations",
            "subcategory":"Religious Organization",
            "type":"Services"
        }
    ],
    "sg:phone":"+1 715 443 3675",
    "sg:postcode":"54448",
    "sg:province":"WI",
    "sg:tags":[
        "church"
    ],
    "wof:name":"Sacred Heart Church",
    "wof:placetype":"venue"
},
  "geometry": {"coordinates":[-89.668425,45.00223],"type":"Point"}
}