{
  "type": "Feature",
  "properties": {
    "iso:country":"US",
    "sg:address":"193 Grove St",
    "sg:city":"Merrimac",
    "sg:classifiers":[
        {
            "category":"Manufacturing",
            "subcategory":"Metals",
            "type":"Manufacturing & Wholesale Goods"
        }
    ],
    "sg:phone":"+1 608 493 9960",
    "sg:postcode":"53561",
    "sg:province":"WI",
    "sg:tags":[
        "ornamental",
        "work"
    ],
    "wof:name":"Badger Village Blacksmithing",
    "wof:placetype":"venue"
},
  "geometry": {"coordinates":[-89.621882,43.371797],"type":"Point"}
}