{
  "type": "Feature",
  "properties": {
    "iso:country":"US",
    "sg:address":"556 W 5th Ave",
    "sg:city":"Oshkosh",
    "sg:classifiers":[
        {
            "category":"Restaurant",
            "type":"Food & Drink"
        }
    ],
    "sg:phone":"+1 920 303 1400",
    "sg:postcode":"54902",
    "sg:province":"WI",
    "sg:tags":[
        "eating"
    ],
    "wof:name":"Players Pizza & Pub LLP",
    "wof:placetype":"venue"
},
  "geometry": {"coordinates":[-88.551478,44.013307],"type":"Point"}
}