{
  "type": "Feature",
  "properties": {
    "iso:country":"US",
    "sg:address":"6411 Kenyon Rd",
    "sg:city":"Black River Falls",
    "sg:classifiers":[
        {
            "category":"Farming",
            "subcategory":"Dairy Farm",
            "type":"Manufacturing & Wholesale Goods"
        }
    ],
    "sg:phone":"+1 715 284 5589",
    "sg:postcode":"54615",
    "sg:province":"WI",
    "wof:name":"Douglas Mason",
    "wof:placetype":"venue"
},
  "geometry": {"coordinates":[-90.902502,44.298773],"type":"Point"}
}