{
  "type": "Feature",
  "properties": {
    "iso:country":"US",
    "sg:address":"409 High St",
    "sg:city":"Racine",
    "sg:classifiers":[
        {
            "category":"Professional",
            "type":"Services"
        }
    ],
    "sg:phone":"+1 262 619 0296",
    "sg:postcode":"53402",
    "sg:province":"WI",
    "wof:name":"Hamilton Arquincy",
    "wof:placetype":"venue"
},
  "geometry": {"coordinates":[-87.785902,42.742273],"type":"Point"}
}