{
  "type": "Feature",
  "properties": {
    "iso:country":"US",
    "sg:address":"8461 Germantown Rd",
    "sg:city":"Crivitz",
    "sg:classifiers":[
        {
            "category":"Building & Trades",
            "subcategory":"Construction",
            "type":"Services"
        }
    ],
    "sg:phone":"+1 715 854 2880",
    "sg:postcode":"54114",
    "sg:province":"WI",
    "sg:tags":[
        "equipment",
        "hanging",
        "contractor"
    ],
    "wof:name":"Spectrum Home Maintenance",
    "wof:placetype":"venue"
},
  "geometry": {"coordinates":[-88.023501,45.2317],"type":"Point"}
}