{
  "type": "Feature",
  "properties": {
    "iso:country":"US",
    "sg:address":"306 de Witt St",
    "sg:city":"Portage",
    "sg:classifiers":[
        {
            "category":"Professional",
            "type":"Services"
        }
    ],
    "sg:phone":"+1 608 846 0352",
    "sg:postcode":"53901",
    "sg:province":"WI",
    "wof:name":"Geared For Sports",
    "wof:placetype":"venue"
},
  "geometry": {"coordinates":[-89.460242,43.540565],"type":"Point"}
}