{
  "type": "Feature",
  "properties": {
    "iso:country":"US",
    "sg:address":"210 Pine St",
    "sg:city":"Waupaca",
    "sg:classifiers":[
        {
            "category":"Wholesale",
            "subcategory":"Farm Supplies",
            "type":"Manufacturing & Wholesale Goods"
        }
    ],
    "sg:phone":"+1 715 256 9313",
    "sg:postcode":"54981",
    "sg:province":"WI",
    "sg:tags":[
        "bulb",
        "seed"
    ],
    "wof:name":"Legacy Seeds Inc",
    "wof:placetype":"venue"
},
  "geometry": {"coordinates":[-89.078383,44.360608],"type":"Point"}
}