{
  "type": "Feature",
  "properties": {
    "iso:country":"US",
    "sg:address":"1302 Droster Rd",
    "sg:city":"Madison",
    "sg:classifiers":[
        {
            "category":"Building & Trades",
            "subcategory":"Construction",
            "type":"Services"
        }
    ],
    "sg:phone":"+1 608 226 9970",
    "sg:postcode":"53716",
    "sg:province":"WI",
    "sg:tags":[
        "roofing",
        "contractor"
    ],
    "wof:name":"Best Way Svc Inc",
    "wof:placetype":"venue"
},
  "geometry": {"coordinates":[-89.28672400000001,43.079333],"type":"Point"}
}