{
  "type": "Feature",
  "properties": {
    "iso:country":"US",
    "sg:address":"416 Ventura Ln",
    "sg:city":"Whitewater",
    "sg:classifiers":[
        {
            "category":"Social Services",
            "type":"Services"
        }
    ],
    "sg:phone":"+1 262 472 9166",
    "sg:postcode":"53190",
    "sg:province":"WI",
    "wof:name":"Pastoral & Family Therapy",
    "wof:placetype":"venue"
},
  "geometry": {"coordinates":[-88.763599,42.828049],"type":"Point"}
}