{
  "type": "Feature",
  "properties": {
    "addr:full":"1600 W Prospect Ave Appleton WI 54914",
    "addr:housenumber":"1600",
    "addr:postcode":"54914",
    "addr:street":"W Prospect Ave",
    "iso:country":"US",
    "sg:address":"1600 W Prospect Ave",
    "sg:city":"Appleton",
    "sg:classifiers":[
        {
            "category":"Education",
            "subcategory":"School",
            "type":"Public Place"
        }
    ],
    "sg:phone":"+1 920 733 6632",
    "sg:postcode":"54914",
    "sg:province":"WI",
    "sg:website":"www.xavier.k12.wi.us",
    "wof:name":"Xavier High School",
    "wof:placetype":"venue"
},
  "geometry": {"coordinates":[-88.436077,44.248359],"type":"Point"}
}