{
  "type": "Feature",
  "properties": {
    "iso:country":"US",
    "sg:address":"5871 S 108th St",
    "sg:city":"Hales Corners",
    "sg:classifiers":[
        {
            "category":"Restaurant",
            "type":"Food & Drink"
        }
    ],
    "sg:phone":"+1 414 427 1400",
    "sg:postcode":"53130",
    "sg:province":"WI",
    "wof:name":"Bosch",
    "wof:placetype":"venue"
},
  "geometry": {"coordinates":[-88.048409,42.938686],"type":"Point"}
}