{
  "type": "Feature",
  "properties": {
    "addr:full":"1485 Wexford Ln Green Bay WI 54313",
    "addr:housenumber":"1485",
    "addr:postcode":"54313",
    "addr:street":"Wexford Ln",
    "iso:country":"US",
    "sg:address":"1485 Wexford Ln",
    "sg:city":"Green Bay",
    "sg:classifiers":[
        {
            "category":"Real Estate",
            "subcategory":"Real Estate Agent",
            "type":"Services"
        }
    ],
    "sg:phone":"+1 920 494 5999",
    "sg:postcode":"54313",
    "sg:province":"WI",
    "wof:name":"Paige Realty",
    "wof:placetype":"venue"
},
  "geometry": {"coordinates":[-88.099698,44.480433],"type":"Point"}
}