{
  "type": "Feature",
  "properties": {
    "iso:country":"US",
    "sg:address":"610 Division St",
    "sg:city":"Neenah",
    "sg:classifiers":[
        {
            "category":"Education",
            "subcategory":"School",
            "type":"Public Place"
        }
    ],
    "sg:phone":"+1 920 729 4565",
    "sg:postcode":"54956",
    "sg:province":"WI",
    "wof:name":"St Margaret-Mary's School",
    "wof:placetype":"venue"
},
  "geometry": {"coordinates":[-88.45507499999999,44.178421],"type":"Point"}
}