{
  "type": "Feature",
  "properties": {
    "iso:country":"US",
    "sg:address":"609 S Taylor Dr",
    "sg:city":"Sheboygan",
    "sg:classifiers":[
        {
            "category":"Shopping",
            "subcategory":"Optical Goods",
            "type":"Retail Goods"
        }
    ],
    "sg:phone":"+1 920 459 8814",
    "sg:postcode":"53081",
    "sg:province":"WI",
    "wof:name":"Walmart Vision Center",
    "wof:placetype":"venue"
},
  "geometry": {"coordinates":[-87.74848299999999,43.750241],"type":"Point"}
}