{
  "type": "Feature",
  "properties": {
    "iso:country":"US",
    "sg:address":"204 W Brodhead St",
    "sg:city":"Orfordville",
    "sg:classifiers":[
        {
            "category":"Food & Beverages",
            "subcategory":"Groceries & Convenience Stores",
            "type":"Retail Goods"
        }
    ],
    "sg:phone":"+1 608 879 9074",
    "sg:postcode":"53576",
    "sg:province":"WI",
    "wof:name":"Donna's Gas & Grocery",
    "wof:placetype":"venue"
},
  "geometry": {"coordinates":[-89.258401,42.629056],"type":"Point"}
}