{
  "type": "Feature",
  "properties": {
    "iso:country":"US",
    "sg:address":"1028 E Juneau Ave",
    "sg:city":"Milwaukee",
    "sg:classifiers":[
        {
            "category":"Restaurant",
            "type":"Food & Drink"
        }
    ],
    "sg:menulink":"http://www.allmenus.com/wi/milwaukee/8091-osteria-del-mondo/menu/",
    "sg:phone":"+1 414 291 3770",
    "sg:postcode":"53202",
    "sg:province":"WI",
    "sg:tags":[
        "italian"
    ],
    "wof:name":"Osteria Del Mondo",
    "wof:placetype":"venue"
},
  "geometry": {"coordinates":[-87.89876,43.045702],"type":"Point"}
}