{
  "type": "Feature",
  "properties": {
    "iso:country":"US",
    "sg:address":"420 N Iowa St",
    "sg:city":"Dodgeville",
    "sg:classifiers":[
        {
            "category":"Food & Beverages",
            "subcategory":"Groceries & Convenience Stores",
            "type":"Retail Goods"
        }
    ],
    "sg:phone":"+1 608 935 1661",
    "sg:postcode":"53533",
    "sg:province":"WI",
    "wof:name":"Phillips 66 Dodgeville",
    "wof:placetype":"venue"
},
  "geometry": {"coordinates":[-90.130821,42.963795],"type":"Point"}
}