{
  "type": "Feature",
  "properties": {
    "iso:country":"US",
    "sg:address":"3199 Hall Dr",
    "sg:city":"Medford",
    "sg:classifiers":[
        {
            "category":"Freight",
            "type":"Transportation"
        }
    ],
    "sg:phone":"+1 715 748 3980",
    "sg:postcode":"54451",
    "sg:province":"WI",
    "sg:tags":[
        "operator",
        "local",
        "trucking"
    ],
    "wof:name":"Rock Thums Trucking",
    "wof:placetype":"venue"
},
  "geometry": {"coordinates":[-90.249464,45.144886],"type":"Point"}
}