{
  "type": "Feature",
  "properties": {
    "iso:country":"US",
    "sg:address":"801 Russett St",
    "sg:city":"Racine",
    "sg:classifiers":[
        {
            "category":"Travel",
            "subcategory":"Campground",
            "type":"Entertainment"
        }
    ],
    "sg:phone":"+1 262 634 2589",
    "sg:postcode":"53405",
    "sg:province":"WI",
    "sg:tags":[
        "camp"
    ],
    "wof:name":"Great Lakes Basketball Camp",
    "wof:placetype":"venue"
},
  "geometry": {"coordinates":[-87.827341,42.723764],"type":"Point"}
}