{
  "type": "Feature",
  "properties": {
    "iso:country":"US",
    "sg:address":"1324 Vernon St",
    "sg:city":"Stoughton",
    "sg:classifiers":[
        {
            "category":"Building & Trades",
            "subcategory":"Construction",
            "type":"Services"
        }
    ],
    "sg:phone":"+1 608 873 8037",
    "sg:postcode":"53589",
    "sg:province":"WI",
    "sg:tags":[
        "house"
    ],
    "wof:name":"David Mack Construction",
    "wof:placetype":"venue"
},
  "geometry": {"coordinates":[-89.205837,42.916807],"type":"Point"}
}