{
  "type": "Feature",
  "properties": {
    "iso:country":"US",
    "sg:address":"1444 Welsh Rd",
    "sg:city":"Watertown",
    "sg:classifiers":[
        {
            "category":"Building & Trades",
            "subcategory":"Construction",
            "type":"Services"
        }
    ],
    "sg:phone":"+1 920 261 5310",
    "sg:postcode":"53098",
    "sg:province":"WI",
    "sg:tags":[
        "concrete",
        "contractor"
    ],
    "wof:name":"Henze Concrete",
    "wof:placetype":"venue"
},
  "geometry": {"coordinates":[-88.764134,43.25267],"type":"Point"}
}