{
  "type": "Feature",
  "properties": {
    "addr:full":"2820 Plank Rd Appleton WI 54915",
    "addr:housenumber":"2820",
    "addr:postcode":"54915",
    "addr:street":"Plank Rd",
    "iso:country":"US",
    "sg:address":"2820 Plank Rd",
    "sg:city":"Appleton",
    "sg:classifiers":[
        {
            "category":"Autos & Motor Vehicles",
            "subcategory":"Auto Supplies",
            "type":"Retail Goods"
        }
    ],
    "sg:phone":"+1 920 831 9950",
    "sg:postcode":"54915",
    "sg:province":"WI",
    "sg:tags":[
        "tire"
    ],
    "wof:name":"Pomps Tire Service Inc",
    "wof:placetype":"venue"
},
  "geometry": {"coordinates":[-88.36410100000001,44.235271],"type":"Point"}
}