{
  "type": "Feature",
  "properties": {
    "iso:country":"US",
    "sg:address":"220 W Lake St",
    "sg:city":"Horicon",
    "sg:classifiers":[
        {
            "category":"Professional",
            "type":"Services"
        }
    ],
    "sg:phone":"+1 920 485 2958",
    "sg:postcode":"53032",
    "sg:province":"WI",
    "wof:name":"Brunner Kirchoff",
    "wof:placetype":"venue"
},
  "geometry": {"coordinates":[-88.637899,43.451383],"type":"Point"}
}