{
  "type": "Feature",
  "properties": {
    "addr:full":"1181 N Main St West Bend WI 53090",
    "addr:housenumber":"1181",
    "addr:postcode":"53090",
    "addr:street":"N Main St",
    "iso:country":"US",
    "sg:address":"1181 N Main St",
    "sg:city":"West Bend",
    "sg:classifiers":[
        {
            "category":"Professional",
            "subcategory":"Business Services",
            "type":"Services"
        }
    ],
    "sg:phone":"+1 262 335 0585",
    "sg:postcode":"53090",
    "sg:province":"WI",
    "wof:name":"Coupon Wear LLC",
    "wof:placetype":"venue"
},
  "geometry": {"coordinates":[-88.185143,43.434379],"type":"Point"}
}