{
  "type": "Feature",
  "properties": {
    "iso:country":"US",
    "sg:address":"32 W Hosmer St",
    "sg:city":"Marinette",
    "sg:classifiers":[
        {
            "category":"Bars & Pubs",
            "type":"Food & Drink"
        }
    ],
    "sg:phone":"+1 715 735 9804",
    "sg:postcode":"54143",
    "sg:province":"WI",
    "sg:tags":[
        "drinking"
    ],
    "wof:name":"Mike & Jean's Bar & Grill",
    "wof:placetype":"venue"
},
  "geometry": {"coordinates":[-87.599109,45.090626],"type":"Point"}
}