{
  "type": "Feature",
  "properties": {
    "iso:country":"US",
    "sg:address":"1438 Northport Dr",
    "sg:city":"Madison",
    "sg:classifiers":[
        {
            "category":"Banks & Credit Unions",
            "subcategory":"Bank",
            "type":"Services"
        }
    ],
    "sg:phone":"+1 608 282 6151",
    "sg:postcode":"53704",
    "sg:province":"WI",
    "sg:tags":[
        "federal",
        "savings",
        "institution"
    ],
    "wof:name":"Home Savings At Madison",
    "wof:placetype":"venue"
},
  "geometry": {"coordinates":[-89.376785,43.136111],"type":"Point"}
}