{
  "type": "Feature",
  "properties": {
    "addr:full":"13500 Watertown Plank Rd Elm Grove WI 53122",
    "addr:housenumber":"13500",
    "addr:postcode":"53122",
    "addr:street":"Watertown Plank Rd",
    "iso:country":"US",
    "sg:address":"13500 Watertown Plank Rd",
    "sg:city":"Elm Grove",
    "sg:classifiers":[
        {
            "category":"Professional",
            "subcategory":"Management & Consulting",
            "type":"Services"
        }
    ],
    "sg:phone":"+1 262 754 4770",
    "sg:postcode":"53122",
    "sg:province":"WI",
    "sg:tags":[
        "consultant"
    ],
    "wof:name":"Boyd Consulting Group Inc",
    "wof:placetype":"venue"
},
  "geometry": {"coordinates":[-88.080733,43.042261],"type":"Point"}
}