{
  "type": "Feature",
  "properties": {
    "iso:country":"US",
    "sg:address":"7421 540th St",
    "sg:city":"Menomonie",
    "sg:classifiers":[
        {
            "category":"Building & Trades",
            "subcategory":"Construction",
            "type":"Services"
        }
    ],
    "sg:phone":"+1 715 235 5135",
    "sg:postcode":"54751",
    "sg:province":"WI",
    "sg:tags":[
        "roofing",
        "contractor"
    ],
    "wof:name":"Red Cedar Siding & Roofing",
    "wof:placetype":"venue"
},
  "geometry": {"coordinates":[-91.887349,44.94853],"type":"Point"}
}