{
  "type": "Feature",
  "properties": {
    "addr:full":"3705 S 43rd St Milwaukee WI 53220",
    "addr:housenumber":"3705",
    "addr:postcode":"53220",
    "addr:street":"S 43Rd St",
    "iso:country":"US",
    "sg:address":"3705 S 43rd St",
    "sg:city":"Milwaukee",
    "sg:classifiers":[
        {
            "category":"Building & Trades",
            "subcategory":"Construction",
            "type":"Services"
        }
    ],
    "sg:phone":"+1 414 321 3197",
    "sg:postcode":"53220",
    "sg:province":"WI",
    "sg:tags":[
        "concrete",
        "contractor"
    ],
    "wof:name":"D Gary Dgc Co",
    "wof:placetype":"venue"
},
  "geometry": {"coordinates":[-87.968208,42.977377],"type":"Point"}
}