{
  "type": "Feature",
  "properties": {
    "addr:full":"7351 N 76th St Milwaukee WI 53223",
    "addr:housenumber":"7351",
    "addr:postcode":"53223",
    "addr:street":"N 76Th St",
    "iso:country":"US",
    "sg:address":"7351 N 76th St",
    "sg:city":"Milwaukee",
    "sg:classifiers":[
        {
            "category":"Shopping",
            "type":"Retail Goods"
        }
    ],
    "sg:phone":"+1 414 353 6980",
    "sg:postcode":"53223",
    "sg:province":"WI",
    "sg:tags":[
        "spa",
        "pool",
        "swimming"
    ],
    "wof:name":"Allied Pools and Spas",
    "wof:placetype":"venue"
},
  "geometry": {"coordinates":[-88.005448,43.148883],"type":"Point"}
}