{
  "type": "Feature",
  "properties": {
    "iso:country":"US",
    "sg:address":"428 N Superior St",
    "sg:city":"De Pere",
    "sg:classifiers":[
        {
            "category":"Manufacturing",
            "subcategory":"Tools & Machinery",
            "type":"Manufacturing & Wholesale Goods"
        }
    ],
    "sg:phone":"+1 920 983 1492",
    "sg:postcode":"54115",
    "sg:province":"WI",
    "sg:tags":[
        "built",
        "industrial",
        "designed",
        "mfg"
    ],
    "wof:name":"Automated Systems & Engineerin",
    "wof:placetype":"venue"
},
  "geometry": {"coordinates":[-88.056537,44.451514],"type":"Point"}
}