{
  "type": "Feature",
  "properties": {
    "iso:country":"US",
    "sg:address":"220 N Beaumont Rd",
    "sg:city":"Prairie Du Chien",
    "sg:classifiers":[
        {
            "category":"Government",
            "subcategory":"Office",
            "type":"Public Place"
        }
    ],
    "sg:phone":"+1 608 326 0200",
    "sg:postcode":"53821",
    "sg:province":"WI",
    "sg:tags":[
        "executive"
    ],
    "wof:name":"County of Crawford",
    "wof:placetype":"venue"
},
  "geometry": {"coordinates":[-91.14647600000001,43.05439],"type":"Point"}
}