{
  "type": "Feature",
  "properties": {
    "iso:country":"US",
    "sg:address":"1353 Williamson St",
    "sg:city":"Madison",
    "sg:classifiers":[
        {
            "category":"Restaurant",
            "type":"Food & Drink"
        }
    ],
    "sg:menulink":"http://www.allmenus.com/wi/madison/261175-babs-french-quarter-kitchen/menu/",
    "sg:phone":"+1 608 251 1222",
    "sg:postcode":"53703",
    "sg:province":"WI",
    "sg:tags":[
        "french"
    ],
    "wof:name":"Babs French Quarter Kitchen",
    "wof:placetype":"venue"
},
  "geometry": {"coordinates":[-89.36147,43.085045],"type":"Point"}
}