{
  "type": "Feature",
  "properties": {
    "iso:country":"US",
    "sg:address":"979 Kellogg St",
    "sg:city":"Green Bay",
    "sg:classifiers":[
        {
            "category":"Organizations",
            "subcategory":"Religious Organization",
            "type":"Services"
        }
    ],
    "sg:phone":"+1 920 499 2195",
    "sg:postcode":"54303",
    "sg:province":"WI",
    "wof:name":"Weycker For Assembly",
    "wof:placetype":"venue"
},
  "geometry": {"coordinates":[-88.031659,44.525299],"type":"Point"}
}