{
  "type": "Feature",
  "properties": {
    "iso:country":"US",
    "sg:address":"24459 State Hwy 58",
    "sg:city":"Richland Center",
    "sg:classifiers":[
        {
            "category":"Professional",
            "type":"Services"
        }
    ],
    "sg:phone":"+1 608 585 2040",
    "sg:postcode":"53581",
    "sg:province":"WI",
    "wof:name":"Christina A Willis",
    "wof:placetype":"venue"
},
  "geometry": {"coordinates":[-90.281721,43.344251],"type":"Point"}
}