{
  "type": "Feature",
  "properties": {
    "addr:full":"2812 S 108th St Milwaukee WI 53227",
    "addr:housenumber":"2812",
    "addr:postcode":"53227",
    "addr:street":"S 108Th St",
    "iso:country":"US",
    "sg:address":"2812 S 108th St",
    "sg:city":"Milwaukee",
    "sg:classifiers":[
        {
            "category":"Banks & Credit Unions",
            "subcategory":"Bank",
            "type":"Services"
        }
    ],
    "sg:phone":"+1 414 449 2929",
    "sg:postcode":"53227",
    "sg:province":"WI",
    "sg:tags":[
        "cashing",
        "check"
    ],
    "wof:name":"Community Financial Svc Ctr",
    "wof:placetype":"venue"
},
  "geometry": {"coordinates":[-88.04698999999999,42.991425],"type":"Point"}
}