{
  "type": "Feature",
  "properties": {
    "iso:country":"US",
    "sg:address":"34 S Main St",
    "sg:city":"Mayville",
    "sg:classifiers":[
        {
            "category":"Insurance",
            "subcategory":"Insurance Agent",
            "type":"Services"
        }
    ],
    "sg:phone":"+1 920 387 2140",
    "sg:postcode":"53050",
    "sg:province":"WI",
    "wof:name":"Mayville Insurance",
    "wof:placetype":"venue"
},
  "geometry": {"coordinates":[-88.544008,43.495292],"type":"Point"}
}