{
  "type": "Feature",
  "properties": {
    "addr:full":"212 N Lynndale Dr Appleton WI 54914",
    "addr:housenumber":"212",
    "addr:postcode":"54914",
    "addr:street":"N Lynndale Dr",
    "iso:country":"US",
    "sg:address":"212 N Lynndale Dr",
    "sg:city":"Appleton",
    "sg:classifiers":[
        {
            "category":"Retail",
            "subcategory":"Auto Repair",
            "type":"Services"
        }
    ],
    "sg:phone":"+1 920 733 5556",
    "sg:postcode":"54914",
    "sg:province":"WI",
    "sg:tags":[
        "automotive"
    ],
    "wof:name":"Ziebart",
    "wof:placetype":"venue"
},
  "geometry": {"coordinates":[-88.445829,44.263598],"type":"Point"}
}