{
  "type": "Feature",
  "properties": {
    "iso:country":"US",
    "sg:address":"111 E Kilbourn Ave",
    "sg:city":"Milwaukee",
    "sg:classifiers":[
        {
            "category":"Wholesale",
            "subcategory":"Home Furnishings",
            "type":"Manufacturing & Wholesale Goods"
        }
    ],
    "sg:phone":"+1 414 765 1300",
    "sg:postcode":"53202",
    "sg:province":"WI",
    "sg:tags":[
        "rug",
        "carpet"
    ],
    "sg:website":"www.floorsandwindows.com",
    "wof:name":"Nationwide Floorcovering Inc",
    "wof:placetype":"venue"
},
  "geometry": {"coordinates":[-87.911993,43.041761],"type":"Point"}
}