{
  "type": "Feature",
  "properties": {
    "iso:country":"US",
    "sg:address":"2971 Shefield Ct",
    "sg:city":"Green Bay",
    "sg:classifiers":[
        {
            "category":"Wholesale",
            "subcategory":"Machinery & Supplies",
            "type":"Manufacturing & Wholesale Goods"
        }
    ],
    "sg:phone":"+1 920 406 0087",
    "sg:postcode":"54311",
    "sg:province":"WI",
    "sg:tags":[
        "filter"
    ],
    "wof:name":"Filtration Services LLC",
    "wof:placetype":"venue"
},
  "geometry": {"coordinates":[-87.934341,44.46188],"type":"Point"}
}