{
  "type": "Feature",
  "properties": {
    "addr:full":"515 Manitowoc Rd Reedsville WI 54230",
    "addr:housenumber":"515",
    "addr:postcode":"54230",
    "addr:street":"Manitowoc Rd",
    "iso:country":"US",
    "sg:address":"515 Manitowoc Rd",
    "sg:city":"Reedsville",
    "sg:classifiers":[
        {
            "category":"Retail",
            "subcategory":"Auto Repair",
            "type":"Services"
        }
    ],
    "sg:phone":"+1 920 754 4611",
    "sg:postcode":"54230",
    "sg:province":"WI",
    "sg:tags":[
        "body",
        "automobile",
        "painting"
    ],
    "wof:name":"A-C A R Restorations",
    "wof:placetype":"venue"
},
  "geometry": {"coordinates":[-87.95945,44.153324],"type":"Point"}
}