{
  "type": "Feature",
  "properties": {
    "iso:country":"US",
    "sg:address":"3008 Soda Creek Rd",
    "sg:city":"Marathon",
    "sg:classifiers":[
        {
            "category":"Farming",
            "subcategory":"Dairy Farm",
            "type":"Manufacturing & Wholesale Goods"
        }
    ],
    "sg:phone":"+1 715 443 2795",
    "sg:postcode":"54448",
    "sg:province":"WI",
    "wof:name":"I Knoeck",
    "wof:placetype":"venue"
},
  "geometry": {"coordinates":[-89.853471,44.916208],"type":"Point"}
}