{
  "type": "Feature",
  "properties": {
    "iso:country":"US",
    "sg:address":"1802 Co Rd A",
    "sg:city":"Green Lake",
    "sg:classifiers":[
        {
            "category":"Sports & Exercise",
            "subcategory":"Bowling",
            "type":"Entertainment"
        }
    ],
    "sg:phone":"+1 920 294 3314",
    "sg:postcode":"54941",
    "sg:province":"WI",
    "sg:tags":[
        "center"
    ],
    "wof:name":"Howie's Green Meadows Lanes",
    "wof:placetype":"venue"
},
  "geometry": {"coordinates":[-88.982305,43.873473],"type":"Point"}
}