{
  "type": "Feature",
  "properties": {
    "iso:country":"US",
    "sg:address":"123 S Main St",
    "sg:city":"Fond Du Lac",
    "sg:classifiers":[
        {
            "category":"Banks & Credit Unions",
            "subcategory":"Bank",
            "type":"Services"
        }
    ],
    "sg:phone":"+1 920 921 9804",
    "sg:postcode":"54935",
    "sg:province":"WI",
    "sg:tags":[
        "loan",
        "real estate"
    ],
    "wof:name":"Countrywide Home Loans",
    "wof:placetype":"venue"
},
  "geometry": {"coordinates":[-88.446896,43.775932],"type":"Point"}
}