{
  "type": "Feature",
  "properties": {
    "iso:country":"US",
    "sg:address":"3881 19th Ct",
    "sg:city":"Montello",
    "sg:classifiers":[
        {
            "category":"Freight",
            "type":"Transportation"
        }
    ],
    "sg:phone":"+1 608 297 2910",
    "sg:postcode":"53949",
    "sg:province":"WI",
    "sg:tags":[
        "distance",
        "long",
        "trucking"
    ],
    "wof:name":"Fitzgerald John Trucking",
    "wof:placetype":"venue"
},
  "geometry": {"coordinates":[-89.242591,43.780598],"type":"Point"}
}