{
  "type": "Feature",
  "properties": {
    "addr:full":"2227 Eagle Dr Middleton WI 53562",
    "addr:housenumber":"2227",
    "addr:postcode":"53562",
    "addr:street":"Eagle Dr",
    "iso:country":"US",
    "sg:address":"2227 Eagle Dr",
    "sg:city":"Middleton",
    "sg:classifiers":[
        {
            "category":"Home & Garden",
            "subcategory":"Building Materials",
            "type":"Retail Goods"
        }
    ],
    "sg:phone":"+1 608 251 9517",
    "sg:postcode":"53562",
    "sg:province":"WI",
    "sg:tags":[
        "glass",
        "window",
        "plate"
    ],
    "wof:name":"P S Auto Glass",
    "wof:placetype":"venue"
},
  "geometry": {"coordinates":[-89.527683,43.100542],"type":"Point"}
}