{
  "type": "Feature",
  "properties": {
    "iso:country":"US",
    "sg:address":"1775 Linnerud Dr",
    "sg:city":"Sun Prairie",
    "sg:classifiers":[
        {
            "category":"Real Estate",
            "subcategory":"Real Estate Operator",
            "type":"Services"
        }
    ],
    "sg:phone":"+1 608 837 3478",
    "sg:postcode":"53590",
    "sg:province":"WI",
    "sg:tags":[
        "apartment"
    ],
    "wof:name":"Hunter's Ridge Apartment Home",
    "wof:placetype":"venue"
},
  "geometry": {"coordinates":[-89.244091,43.174132],"type":"Point"}
}