{
  "type": "Feature",
  "properties": {
    "addr:full":"1000 E Grand Ave Chippewa Falls WI 54729",
    "addr:housenumber":"1000",
    "addr:postcode":"54729",
    "addr:street":"E Grand Ave",
    "iso:country":"US",
    "sg:address":"1000 E Grand Ave",
    "sg:city":"Chippewa Falls",
    "sg:classifiers":[
        {
            "category":"Social Services",
            "type":"Services"
        }
    ],
    "sg:phone":"+1 715 720 1666",
    "sg:postcode":"54729",
    "sg:province":"WI",
    "sg:tags":[
        "senior",
        "citizen"
    ],
    "wof:name":"Chippewa Falls Area Senior Ctr",
    "wof:placetype":"venue"
},
  "geometry": {"coordinates":[-91.380753,44.94453],"type":"Point"}
}