{
  "type": "Feature",
  "properties": {
    "iso:country":"US",
    "sg:address":"600 New York Ave",
    "sg:city":"Manitowoc",
    "sg:classifiers":[
        {
            "category":"Shopping",
            "subcategory":"Pharmacy",
            "type":"Retail Goods"
        }
    ],
    "sg:phone":"+1 920 683 5265",
    "sg:postcode":"54220",
    "sg:province":"WI",
    "wof:name":"Manitowoc Pharmacies Inc",
    "wof:placetype":"venue"
},
  "geometry": {"coordinates":[-87.656173,44.104811],"type":"Point"}
}