{
  "type": "Feature",
  "properties": {
    "iso:country":"US",
    "sg:address":"4215 Co Rd Oo",
    "sg:city":"Hager City",
    "sg:classifiers":[
        {
            "category":"Farming",
            "subcategory":"Livestock Farm",
            "type":"Manufacturing & Wholesale Goods"
        }
    ],
    "sg:phone":"+1 715 792 2257",
    "sg:postcode":"54014",
    "sg:province":"WI",
    "sg:tags":[
        "corn",
        "beef",
        "feedlot",
        "cattle"
    ],
    "wof:name":"Rodney Kinneman",
    "wof:placetype":"venue"
},
  "geometry": {"coordinates":[-92.609058,44.691669],"type":"Point"}
}