{
  "type": "Feature",
  "properties": {
    "iso:country":"US",
    "sg:address":"5401 Dennis Dr",
    "sg:city":"Mc Farland",
    "sg:classifiers":[
        {
            "category":"Shopping",
            "subcategory":"Gifts & Souvenirs",
            "type":"Retail Goods"
        }
    ],
    "sg:phone":"+1 608 838 8324",
    "sg:postcode":"53558",
    "sg:province":"WI",
    "wof:name":"Pin It On ME Gifts",
    "wof:placetype":"venue"
},
  "geometry": {"coordinates":[-89.28998799999999,43.009018],"type":"Point"}
}