{
  "type": "Feature",
  "properties": {
    "iso:country":"US",
    "sg:address":"331 Cedar St",
    "sg:city":"Luxemburg",
    "sg:classifiers":[
        {
            "category":"Real Estate",
            "subcategory":"Real Estate Agent",
            "type":"Services"
        }
    ],
    "sg:phone":"+1 920 845 2331",
    "sg:postcode":"54217",
    "sg:province":"WI",
    "sg:tags":[
        "cooperative"
    ],
    "wof:name":"Kewaunee Cooperative Luxemburg",
    "wof:placetype":"venue"
},
  "geometry": {"coordinates":[-87.705928,44.537855],"type":"Point"}
}