{
  "type": "Feature",
  "properties": {
    "iso:country":"US",
    "sg:address":"2949 N Sherman Blvd",
    "sg:city":"Milwaukee",
    "sg:classifiers":[
        {
            "category":"Banks & Credit Unions",
            "subcategory":"Investment Brokerage",
            "type":"Services"
        }
    ],
    "sg:phone":"+1 414 873 2489",
    "sg:postcode":"53210",
    "sg:province":"WI",
    "wof:name":"D & C Investments",
    "wof:placetype":"venue"
},
  "geometry": {"coordinates":[-87.967487,43.072484],"type":"Point"}
}