{
  "type": "Feature",
  "properties": {
    "iso:country":"US",
    "sg:address":"11780 N Martin Dr",
    "sg:city":"Strum",
    "sg:phone":"+1 715 878 4755",
    "sg:postcode":"54770",
    "sg:province":"WI",
    "sg:tags":[
        "farm",
        "corn",
        "soybean"
    ],
    "wof:name":"Peetz Eldon",
    "wof:placetype":"venue"
},
  "geometry": {"coordinates":[-91.387377,44.653206],"type":"Point"}
}