{
  "type": "Feature",
  "properties": {
    "iso:country":"US",
    "sg:address":"11330 W Lincoln Ave",
    "sg:city":"Milwaukee",
    "sg:classifiers":[
        {
            "category":"Professional",
            "subcategory":"Advertising",
            "type":"Services"
        }
    ],
    "sg:phone":"+1 414 224 2121",
    "sg:postcode":"53227",
    "sg:province":"WI",
    "wof:name":"Milwaukee Journal Sentinel",
    "wof:placetype":"venue"
},
  "geometry": {"coordinates":[-88.05203899999999,43.002701],"type":"Point"}
}