{
  "type": "Feature",
  "properties": {
    "iso:country":"US",
    "sg:address":"364 Wakely Rd",
    "sg:city":"Nekoosa",
    "sg:classifiers":[
        {
            "category":"Museum",
            "type":"Entertainment"
        }
    ],
    "sg:phone":"+1 715 886 4202",
    "sg:postcode":"54457",
    "sg:province":"WI",
    "sg:tags":[
        "gallery"
    ],
    "wof:name":"Historic Point Basse Inc",
    "wof:placetype":"venue"
},
  "geometry": {"coordinates":[-89.885667,44.300098],"type":"Point"}
}