{
  "type": "Feature",
  "properties": {
    "iso:country":"US",
    "sg:address":"7149 State Rd 175",
    "sg:city":"Oshkosh",
    "sg:classifiers":[
        {
            "category":"Building & Trades",
            "subcategory":"Construction",
            "type":"Services"
        }
    ],
    "sg:phone":"+1 920 688 5191",
    "sg:postcode":"54902",
    "sg:province":"WI",
    "sg:tags":[
        "hanging",
        "contractor"
    ],
    "wof:name":"M & M Painting",
    "wof:placetype":"venue"
},
  "geometry": {"coordinates":[-88.503775,43.907394],"type":"Point"}
}