{
  "type": "Feature",
  "properties": {
    "addr:full":"6221 Yarwood Rd Gillett WI 54124",
    "addr:housenumber":"6221",
    "addr:postcode":"54124",
    "addr:street":"Yarwood Rd",
    "iso:country":"US",
    "sg:address":"6221 Yarwood Rd",
    "sg:city":"Gillett",
    "sg:classifiers":[
        {
            "category":"Building & Trades",
            "subcategory":"Construction",
            "type":"Services"
        }
    ],
    "sg:phone":"+1 920 855 2848",
    "sg:postcode":"54124",
    "sg:province":"WI",
    "sg:tags":[
        "contractor"
    ],
    "wof:name":"Jeff Hertwig Drywall & Plaster",
    "wof:placetype":"venue"
},
  "geometry": {"coordinates":[-88.296898,44.899535],"type":"Point"}
}