{
  "type": "Feature",
  "properties": {
    "addr:full":"144 Gwynn St Green Bay WI 54301",
    "addr:housenumber":"144",
    "addr:postcode":"54301",
    "addr:street":"Gwynn St",
    "iso:country":"US",
    "sg:address":"144 Gwynn St",
    "sg:city":"Green Bay",
    "sg:classifiers":[
        {
            "category":"Freight",
            "type":"Transportation"
        }
    ],
    "sg:phone":"+1 920 336 0843",
    "sg:postcode":"54301",
    "sg:province":"WI",
    "sg:tags":[
        "operator",
        "local",
        "trucking"
    ],
    "wof:name":"Marco Rincon Trucking",
    "wof:placetype":"venue"
},
  "geometry": {"coordinates":[-88.037623,44.454342],"type":"Point"}
}