{
  "type": "Feature",
  "properties": {
    "addr:full":"203 W 5th Ave Minong WI 54859",
    "addr:housenumber":"203",
    "addr:postcode":"54859",
    "addr:street":"W 5Th Ave",
    "iso:country":"US",
    "sg:address":"203 W 5th Ave",
    "sg:city":"Minong",
    "sg:classifiers":[
        {
            "category":"Bars & Pubs",
            "type":"Food & Drink"
        }
    ],
    "sg:phone":"+1 715 466 4318",
    "sg:postcode":"54859",
    "sg:province":"WI",
    "wof:name":"Mc Nad Enterprises Inc",
    "wof:placetype":"venue"
},
  "geometry": {"coordinates":[-91.821619,46.100216],"type":"Point"}
}