{
  "type": "Feature",
  "properties": {
    "iso:country":"US",
    "sg:address":"5068 Ashland Way",
    "sg:city":"Franklin",
    "sg:classifiers":[
        {
            "category":"Professional",
            "subcategory":"Management & Consulting",
            "type":"Services"
        }
    ],
    "sg:phone":"+1 414 433 0800",
    "sg:postcode":"53132",
    "sg:province":"WI",
    "sg:tags":[
        "public",
        "relations"
    ],
    "wof:name":"Zund America",
    "wof:placetype":"venue"
},
  "geometry": {"coordinates":[-87.979276,42.870727],"type":"Point"}
}