{
  "type": "Feature",
  "properties": {
    "iso:country":"US",
    "sg:address":"1210 Main St",
    "sg:city":"Oconto",
    "sg:classifiers":[
        {
            "category":"Government",
            "subcategory":"Office",
            "type":"Public Place"
        }
    ],
    "sg:phone":"+1 920 834 7711",
    "sg:postcode":"54153",
    "sg:province":"WI",
    "sg:tags":[
        "city"
    ],
    "wof:name":"Oconto City Clerk",
    "wof:placetype":"venue"
},
  "geometry": {"coordinates":[-87.865982,44.887188],"type":"Point"}
}