{
  "type": "Feature",
  "properties": {
    "iso:country":"US",
    "sg:address":"8668 Hill Lake Dr",
    "sg:city":"Minocqua",
    "sg:classifiers":[
        {
            "category":"Wholesale",
            "subcategory":"Farm Supplies",
            "type":"Manufacturing & Wholesale Goods"
        },
        {
            "category":"Home & Garden",
            "subcategory":"Garden Supply",
            "type":"Retail Goods"
        }
    ],
    "sg:phone":"+1 715 358 6858",
    "sg:postcode":"54548",
    "sg:province":"WI",
    "sg:tags":[
        "center"
    ],
    "wof:name":"Northern Pines Greenery Inc",
    "wof:placetype":"venue"
},
  "geometry": {"coordinates":[-89.750046,45.886305],"type":"Point"}
}