{
  "type": "Feature",
  "properties": {
    "iso:country":"US",
    "sg:address":"2710 Packerland Dr",
    "sg:city":"Green Bay",
    "sg:classifiers":[
        {
            "category":"Shopping",
            "subcategory":"Gifts & Souvenirs",
            "type":"Retail Goods"
        }
    ],
    "sg:phone":"+1 920 498 8801",
    "sg:postcode":"54313",
    "sg:province":"WI",
    "wof:name":"Flower Mill",
    "wof:placetype":"venue"
},
  "geometry": {"coordinates":[-88.109477,44.487267],"type":"Point"}
}