{
  "type": "Feature",
  "properties": {
    "iso:country":"US",
    "sg:address":"14252 109th Ave",
    "sg:city":"Chippewa Falls",
    "sg:classifiers":[
        {
            "category":"Building & Trades",
            "subcategory":"Construction",
            "type":"Services"
        }
    ],
    "sg:phone":"+1 715 288 6333",
    "sg:postcode":"54729",
    "sg:province":"WI",
    "sg:tags":[
        "house"
    ],
    "wof:name":"Pro Mar Construction Inc",
    "wof:placetype":"venue"
},
  "geometry": {"coordinates":[-91.38228700000001,45.001441],"type":"Point"}
}