{
  "type": "Feature",
  "properties": {
    "iso:country":"US",
    "sg:address":"165 S Pine Ct",
    "sg:city":"Appleton",
    "sg:classifiers":[
        {
            "category":"Shopping",
            "subcategory":"Gifts & Souvenirs",
            "type":"Retail Goods"
        }
    ],
    "sg:phone":"+1 920 832 9550",
    "sg:postcode":"54914",
    "sg:province":"WI",
    "sg:tags":[
        "specializing",
        "house",
        "item",
        "mail"
    ],
    "wof:name":"Successories",
    "wof:placetype":"venue"
},
  "geometry": {"coordinates":[-88.473516,44.250294],"type":"Point"}
}