{
  "type": "Feature",
  "properties": {
    "iso:country":"US",
    "sg:address":"5298 US Hwy 45",
    "sg:city":"Fond Du Lac",
    "sg:classifiers":[
        {
            "category":"Professional",
            "subcategory":"Management & Consulting",
            "type":"Services"
        }
    ],
    "sg:phone":"+1 920 923 2200",
    "sg:postcode":"54935",
    "sg:province":"WI",
    "sg:tags":[
        "construction"
    ],
    "wof:name":"H Tod Culver Inc",
    "wof:placetype":"venue"
},
  "geometry": {"coordinates":[-88.388666,43.728253],"type":"Point"}
}