{
  "type": "Feature",
  "properties": {
    "iso:country":"US",
    "sg:address":"5205 Brown Valley Ln",
    "sg:city":"Middleton",
    "sg:classifiers":[
        {
            "category":"Professional",
            "subcategory":"Art Services",
            "type":"Services"
        }
    ],
    "sg:phone":"+1 608 233 1944",
    "sg:postcode":"53562",
    "sg:province":"WI",
    "sg:tags":[
        "photo",
        "photography",
        "commercial",
        "studio",
        "portrait"
    ],
    "wof:name":"Designer Portraits By Shannon",
    "wof:placetype":"venue"
},
  "geometry": {"coordinates":[-89.470068,43.110879],"type":"Point"}
}