{
  "type": "Feature",
  "properties": {
    "iso:country":"US",
    "sg:address":"309 State St",
    "sg:city":"Beloit",
    "sg:classifiers":[
        {
            "category":"Personal",
            "subcategory":"Beauty Salon",
            "type":"Services"
        }
    ],
    "sg:phone":"+1 608 365 2919",
    "sg:postcode":"53511",
    "sg:province":"IL",
    "wof:name":"Tip To Toe Nails",
    "wof:placetype":"venue"
},
  "geometry": {"coordinates":[-89.035522,42.49959],"type":"Point"}
}