{
  "type": "Feature",
  "properties": {
    "iso:country":"US",
    "sg:address":"1603 Highview St",
    "sg:city":"De Pere",
    "sg:classifiers":[
        {
            "category":"Building & Trades",
            "subcategory":"Construction",
            "type":"Services"
        }
    ],
    "sg:phone":"+1 920 336 6364",
    "sg:postcode":"54115",
    "sg:province":"WI",
    "sg:tags":[
        "excavation",
        "contractor"
    ],
    "wof:name":"Van Vonderen Steve Excavating",
    "wof:placetype":"venue"
},
  "geometry": {"coordinates":[-88.049682,44.438636],"type":"Point"}
}