{
  "type": "Feature",
  "properties": {
    "iso:country":"US",
    "sg:address":"1001 Noridge Trl",
    "sg:city":"Port Washington",
    "sg:classifiers":[
        {
            "category":"Organizations",
            "subcategory":"Non-profit Organization",
            "type":"Services"
        }
    ],
    "sg:phone":"+1 262 268 6859",
    "sg:postcode":"53074",
    "sg:province":"WI",
    "sg:tags":[
        "fund",
        "counselor",
        "raising"
    ],
    "wof:name":"Mcs Consulting",
    "wof:placetype":"venue"
},
  "geometry": {"coordinates":[-87.860483,43.401087],"type":"Point"}
}