{
  "type": "Feature",
  "properties": {
    "iso:country":"US",
    "sg:address":"3625 N 126th St",
    "sg:city":"Brookfield",
    "sg:classifiers":[
        {
            "category":"Wholesale",
            "subcategory":"Machinery & Supplies",
            "type":"Manufacturing & Wholesale Goods"
        }
    ],
    "sg:phone":"+1 262 781 2830",
    "sg:postcode":"53005",
    "sg:province":"WI",
    "sg:tags":[
        "pump"
    ],
    "wof:name":"ASC Pumping Equipment",
    "wof:placetype":"venue"
},
  "geometry": {"coordinates":[-88.06908,43.083146],"type":"Point"}
}