{
  "type": "Feature",
  "properties": {
    "addr:full":"6358 County Line Rd Luxemburg WI 54217",
    "addr:housenumber":"6358",
    "addr:postcode":"54217",
    "addr:street":"County Line Rd",
    "iso:country":"US",
    "sg:address":"6358 County Line Rd",
    "sg:city":"Luxemburg",
    "sg:classifiers":[
        {
            "category":"Professional",
            "type":"Services"
        }
    ],
    "sg:phone":"+1 920 845 5660",
    "sg:postcode":"54217",
    "sg:province":"WI",
    "wof:name":"Patrick C Zellner",
    "wof:placetype":"venue"
},
  "geometry": {"coordinates":[-87.76452999999999,44.559939],"type":"Point"}
}