{
  "type": "Feature",
  "properties": {
    "iso:country":"US",
    "sg:address":"829 Foxfield Rd",
    "sg:city":"Oregon",
    "sg:classifiers":[
        {
            "category":"Home & Garden",
            "subcategory":"Home Furnishings",
            "type":"Retail Goods"
        }
    ],
    "sg:phone":"+1 608 835 3256",
    "sg:postcode":"53575",
    "sg:province":"WI",
    "sg:tags":[
        "utensil",
        "cooking"
    ],
    "wof:name":"Pinnacle Concepts",
    "wof:placetype":"venue"
},
  "geometry": {"coordinates":[-89.382732,42.908894],"type":"Point"}
}