{
  "type": "Feature",
  "properties": {
    "iso:country":"US",
    "sg:address":"240 Maple St",
    "sg:city":"Woodruff",
    "sg:classifiers":[
        {
            "category":"Social Services",
            "subcategory":"Adult Care",
            "type":"Services"
        }
    ],
    "sg:phone":"+1 715 356 8805",
    "sg:postcode":"54568",
    "sg:province":"WI",
    "sg:tags":[
        "organization",
        "senior",
        "citizen"
    ],
    "wof:name":"Dr Kate Lakeland Hospice",
    "wof:placetype":"venue"
},
  "geometry": {"coordinates":[-89.701383,45.895121],"type":"Point"}
}