{
  "type": "Feature",
  "properties": {
    "iso:country":"US",
    "sg:address":"1201 S Oak Ave",
    "sg:city":"Marshfield",
    "sg:classifiers":[
        {
            "category":"Building & Trades",
            "subcategory":"Equipment Rental",
            "type":"Services"
        }
    ],
    "sg:phone":"+1 715 387 8417",
    "sg:postcode":"54449",
    "sg:province":"WI",
    "sg:tags":[
        "yard"
    ],
    "sg:website":"www.unitedrentals.com",
    "wof:name":"United Rentals",
    "wof:placetype":"venue"
},
  "geometry": {"coordinates":[-90.185205,44.65802],"type":"Point"}
}