{
  "type": "Feature",
  "properties": {
    "addr:full":"10909 W Morgan Ave Milwaukee WI 53228",
    "addr:housenumber":"10909",
    "addr:postcode":"53228",
    "addr:street":"W Morgan Ave",
    "iso:country":"US",
    "sg:address":"10909 W Morgan Ave",
    "sg:city":"Milwaukee",
    "sg:classifiers":[
        {
            "category":"Shopping",
            "subcategory":"Books",
            "type":"Retail Goods"
        }
    ],
    "sg:phone":"+1 414 321 8302",
    "sg:postcode":"53228",
    "sg:province":"WI",
    "wof:name":"Bread & Books Inc",
    "wof:placetype":"venue"
},
  "geometry": {"coordinates":[-88.048783,42.980753],"type":"Point"}
}