{
  "type": "Feature",
  "properties": {
    "addr:full":"203 W 7th St Neillsville WI 54456",
    "addr:housenumber":"203",
    "addr:postcode":"54456",
    "addr:street":"W 7Th St",
    "iso:country":"US",
    "sg:address":"203 W 7th St",
    "sg:city":"Neillsville",
    "sg:classifiers":[
        {
            "category":"Bars & Pubs",
            "type":"Food & Drink"
        }
    ],
    "sg:phone":"+1 715 743 6808",
    "sg:postcode":"54456",
    "sg:province":"WI",
    "sg:tags":[
        "drinking"
    ],
    "wof:name":"Brickyard",
    "wof:placetype":"venue"
},
  "geometry": {"coordinates":[-90.598322,44.561433],"type":"Point"}
}