{
  "type": "Feature",
  "properties": {
    "addr:full":"1816 Franklin St Little Chute WI 54140",
    "addr:housenumber":"1816",
    "addr:postcode":"54140",
    "addr:street":"Franklin St",
    "iso:country":"US",
    "sg:address":"1816 Franklin St",
    "sg:city":"Little Chute",
    "sg:classifiers":[
        {
            "category":"Organizations",
            "subcategory":"Community Association",
            "type":"Services"
        }
    ],
    "sg:phone":"+1 920 788 2462",
    "sg:postcode":"54140",
    "sg:province":"WI",
    "wof:name":"Kiwanis International Inc",
    "wof:placetype":"venue"
},
  "geometry": {"coordinates":[-88.306652,44.291915],"type":"Point"}
}