{
  "type": "Feature",
  "properties": {
    "iso:country":"US",
    "sg:address":"174 N Hickory St",
    "sg:city":"Fond Du Lac",
    "sg:classifiers":[
        {
            "category":"Real Estate",
            "subcategory":"Real Estate Agent",
            "type":"Services"
        }
    ],
    "sg:phone":"+1 920 923 3900",
    "sg:postcode":"54935",
    "sg:province":"WI",
    "wof:name":"Century 21",
    "wof:placetype":"venue"
},
  "geometry": {"coordinates":[-88.462576,43.783506],"type":"Point"}
}