{
  "type": "Feature",
  "properties": {
    "iso:country":"US",
    "sg:address":"549 Douglas Dr",
    "sg:city":"Colgate",
    "sg:classifiers":[
        {
            "category":"Building & Trades",
            "subcategory":"Construction",
            "type":"Services"
        }
    ],
    "sg:phone":"+1 262 628 7146",
    "sg:postcode":"53017",
    "sg:province":"WI",
    "sg:tags":[
        "general",
        "contractor"
    ],
    "wof:name":"Laufer Builders",
    "wof:placetype":"venue"
},
  "geometry": {"coordinates":[-88.195861,43.208634],"type":"Point"}
}