{
  "type": "Feature",
  "properties": {
    "iso:country":"US",
    "sg:address":"5335 State Hwy 29",
    "sg:city":"Denmark",
    "sg:classifiers":[
        {
            "category":"Food & Beverages",
            "subcategory":"Dairy",
            "type":"Retail Goods"
        }
    ],
    "sg:phone":"+1 920 863 8613",
    "sg:postcode":"54208",
    "sg:province":"WI",
    "sg:tags":[
        "cheese"
    ],
    "wof:name":"Saputo Cheese USA Inc",
    "wof:placetype":"venue"
},
  "geometry": {"coordinates":[-87.819761,44.443866],"type":"Point"}
}