{
  "type": "Feature",
  "properties": {
    "iso:country":"US",
    "sg:address":"313 Herman St",
    "sg:city":"Iron Ridge",
    "sg:classifiers":[
        {
            "category":"Professional",
            "type":"Services"
        }
    ],
    "sg:phone":"+1 920 387 3848",
    "sg:postcode":"53035",
    "sg:province":"WI",
    "wof:name":"Heath H Buchholz",
    "wof:placetype":"venue"
},
  "geometry": {"coordinates":[-88.52868100000001,43.396769],"type":"Point"}
}