{
  "type": "Feature",
  "properties": {
    "iso:country":"US",
    "sg:address":"5485 Klatt Rd",
    "sg:city":"Gillett",
    "sg:classifiers":[
        {
            "category":"Building & Trades",
            "subcategory":"Plumbing",
            "type":"Services"
        }
    ],
    "sg:phone":"+1 920 855 2275",
    "sg:postcode":"54124",
    "sg:province":"WI",
    "sg:tags":[
        "air",
        "heating",
        "contractor",
        "system",
        "conditioning"
    ],
    "wof:name":"Lisowe Heating & Cooling LLC",
    "wof:placetype":"venue"
},
  "geometry": {"coordinates":[-88.409975,44.872744],"type":"Point"}
}