{
  "type": "Feature",
  "properties": {
    "addr:full":"785 Summit Ave Oconomowoc WI 53066",
    "addr:housenumber":"785",
    "addr:postcode":"53066",
    "addr:street":"Summit Ave",
    "iso:country":"US",
    "sg:address":"785 Summit Ave",
    "sg:city":"Oconomowoc",
    "sg:classifiers":[
        {
            "category":"Health Services",
            "subcategory":"Doctor",
            "type":"Services"
        }
    ],
    "sg:phone":"+1 262 569 8488",
    "sg:postcode":"53066",
    "sg:province":"WI",
    "sg:tags":[
        "clinic",
        "medical"
    ],
    "wof:name":"Lake Country Women's Care",
    "wof:placetype":"venue"
},
  "geometry": {"coordinates":[-88.48669099999999,43.101865],"type":"Point"}
}