{
  "type": "Feature",
  "properties": {
    "iso:country":"US",
    "sg:address":"7215 Co Rd V",
    "sg:city":"Ellsworth",
    "sg:phone":"+1 715 594 3603",
    "sg:postcode":"54011",
    "sg:province":"WI",
    "sg:tags":[
        "farm",
        "corn"
    ],
    "wof:name":"Gail Johnson",
    "wof:placetype":"venue"
},
  "geometry": {"coordinates":[-92.492897,44.673655],"type":"Point"}
}