{
  "type": "Feature",
  "properties": {
    "iso:country":"US",
    "sg:address":"8501 Meuleman Rd",
    "sg:city":"Black Creek",
    "sg:classifiers":[
        {
            "category":"Bars & Pubs",
            "type":"Food & Drink"
        }
    ],
    "sg:phone":"+1 920 525 2413",
    "sg:postcode":"54106",
    "sg:province":"WI",
    "sg:tags":[
        "drinking"
    ],
    "wof:name":"Bear's Corner Bar",
    "wof:placetype":"venue"
},
  "geometry": {"coordinates":[-88.458613,44.546681],"type":"Point"}
}