{
  "type": "Feature",
  "properties": {
    "iso:country":"US",
    "sg:address":"400 S Western Ave",
    "sg:city":"Waupaca",
    "sg:classifiers":[
        {
            "category":"Wholesale",
            "subcategory":"Machinery & Supplies",
            "type":"Manufacturing & Wholesale Goods"
        }
    ],
    "sg:phone":"+1 715 256 1381",
    "sg:postcode":"54981",
    "sg:province":"WI",
    "sg:tags":[
        "equipment",
        "industrial"
    ],
    "wof:name":"Wapaca",
    "wof:placetype":"venue"
},
  "geometry": {"coordinates":[-89.103163,44.355841],"type":"Point"}
}