{
  "type": "Feature",
  "properties": {
    "iso:country":"US",
    "sg:address":"223 3rd Ave",
    "sg:city":"Baraboo",
    "sg:classifiers":[
        {
            "category":"Home & Garden",
            "subcategory":"Building Materials",
            "type":"Retail Goods"
        },
        {
            "category":"Building & Trades",
            "subcategory":"Construction",
            "type":"Services"
        }
    ],
    "sg:phone":"+1 608 356 2550",
    "sg:postcode":"53913",
    "sg:province":"WI",
    "sg:tags":[
        "plate",
        "glazing",
        "residential",
        "commercial",
        "glass",
        "window",
        "automotive"
    ],
    "wof:name":"Pete's Glass Inc",
    "wof:placetype":"venue"
},
  "geometry": {"coordinates":[-89.74571,43.469869],"type":"Point"}
}