{
  "type": "Feature",
  "properties": {
    "addr:full":"1711 Wisconsin Ave Superior WI 54880",
    "addr:housenumber":"1711",
    "addr:postcode":"54880",
    "addr:street":"Wisconsin Ave",
    "iso:country":"US",
    "sg:address":"1711 Wisconsin Ave",
    "sg:city":"Superior",
    "sg:classifiers":[
        {
            "category":"Social Services",
            "subcategory":"Job Training",
            "type":"Services"
        }
    ],
    "sg:phone":"+1 715 394 5071",
    "sg:postcode":"54880",
    "sg:province":"WI",
    "sg:tags":[
        "medical",
        "expert"
    ],
    "wof:name":"Julianne E Koski MD",
    "wof:placetype":"venue"
},
  "geometry": {"coordinates":[-92.131101,46.718209],"type":"Point"}
}