{
  "type": "Feature",
  "properties": {
    "iso:country":"US",
    "sg:address":"5996 Co Rd de",
    "sg:city":"Bangor",
    "sg:classifiers":[
        {
            "category":"Farming",
            "subcategory":"Dairy Farm",
            "type":"Manufacturing & Wholesale Goods"
        }
    ],
    "sg:phone":"+1 608 486 4279",
    "sg:postcode":"54614",
    "sg:province":"WI",
    "wof:name":"Dairy Farm",
    "wof:placetype":"venue"
},
  "geometry": {"coordinates":[-91.009972,43.942339],"type":"Point"}
}