{
  "type": "Feature",
  "properties": {
    "iso:country":"US",
    "sg:address":"4725 N Green Bay Rd",
    "sg:city":"Racine",
    "sg:classifiers":[
        {
            "category":"Building & Trades",
            "subcategory":"Construction",
            "type":"Services"
        }
    ],
    "sg:phone":"+1 262 639 6998",
    "sg:postcode":"53404",
    "sg:province":"WI",
    "sg:tags":[
        "concrete",
        "contractor"
    ],
    "wof:name":"KRC Concrete Construction",
    "wof:placetype":"venue"
},
  "geometry": {"coordinates":[-87.81887,42.783594],"type":"Point"}
}