{
  "type": "Feature",
  "properties": {
    "iso:country":"US",
    "sg:address":"837 Maple St",
    "sg:city":"Neenah",
    "sg:classifiers":[
        {
            "category":"Arts & Performance",
            "subcategory":"Theater",
            "type":"Entertainment"
        }
    ],
    "sg:phone":"+1 920 729 4982",
    "sg:postcode":"54956",
    "sg:province":"WI",
    "sg:tags":[
        "theatrical"
    ],
    "wof:name":"Bob Abendschein",
    "wof:placetype":"venue"
},
  "geometry": {"coordinates":[-88.463765,44.172395],"type":"Point"}
}