{
  "type": "Feature",
  "properties": {
    "iso:country":"US",
    "sg:address":"1305 W Wright St",
    "sg:city":"Milwaukee",
    "sg:classifiers":[
        {
            "category":"Retail",
            "subcategory":"Car Wash",
            "type":"Services"
        }
    ],
    "sg:phone":"+1 414 372 4042",
    "sg:postcode":"53206",
    "sg:province":"WI",
    "sg:tags":[
        "automobile",
        "detail",
        "clean"
    ],
    "wof:name":"Campbell's Detailing",
    "wof:placetype":"venue"
},
  "geometry": {"coordinates":[-87.92871599999999,43.06394],"type":"Point"}
}