{
  "type": "Feature",
  "properties": {
    "iso:country":"US",
    "sg:address":"508 S Lake Ave",
    "sg:city":"Phillips",
    "sg:classifiers":[
        {
            "category":"Organizations",
            "subcategory":"Non-profit Organization",
            "type":"Services"
        }
    ],
    "sg:phone":"+1 715 339 2155",
    "sg:postcode":"54555",
    "sg:province":"WI",
    "sg:website":"www.price-electric.com",
    "wof:name":"Price Electric Co-Op Inc",
    "wof:placetype":"venue"
},
  "geometry": {"coordinates":[-90.391025,45.684454],"type":"Point"}
}