{
  "type": "Feature",
  "properties": {
    "iso:country":"US",
    "sg:address":"4315 Co Rd K",
    "sg:city":"Fond Du Lac",
    "sg:phone":"+1 920 477 5082",
    "sg:postcode":"54935",
    "sg:province":"WI",
    "sg:tags":[
        "farm",
        "field",
        "crop"
    ],
    "wof:name":"Carl Emery Luger",
    "wof:placetype":"venue"
},
  "geometry": {"coordinates":[-88.401543,43.693253],"type":"Point"}
}