{
  "type": "Feature",
  "properties": {
    "iso:country":"US",
    "sg:address":"1728 Tower Ave",
    "sg:city":"Superior",
    "sg:classifiers":[
        {
            "category":"Cinema",
            "subcategory":"Movie Rental",
            "type":"Entertainment"
        }
    ],
    "sg:phone":"+1 715 394 4454",
    "sg:postcode":"54880",
    "sg:province":"WI",
    "sg:tags":[
        "video",
        "tape"
    ],
    "wof:name":"Video Box Office",
    "wof:placetype":"venue"
},
  "geometry": {"coordinates":[-92.103868,46.717349],"type":"Point"}
}