{
  "type": "Feature",
  "properties": {
    "iso:country":"US",
    "sg:address":"2531 N 44th St",
    "sg:city":"Milwaukee",
    "sg:classifiers":[
        {
            "category":"Arts & Performance",
            "subcategory":"Theater",
            "type":"Entertainment"
        }
    ],
    "sg:phone":"+1 414 444 9313",
    "sg:postcode":"53210",
    "sg:province":"WI",
    "wof:name":"Wisconsin Actors Ensemble",
    "wof:placetype":"venue"
},
  "geometry": {"coordinates":[-87.968885,43.065525],"type":"Point"}
}