{
  "type": "Feature",
  "properties": {
    "iso:country":"US",
    "sg:address":"714 S Clinton St",
    "sg:city":"Cuba City",
    "sg:classifiers":[
        {
            "category":"Real Estate",
            "subcategory":"Real Estate Operator",
            "type":"Services"
        }
    ],
    "sg:phone":"+1 608 744 3229",
    "sg:postcode":"53807",
    "sg:province":"WI",
    "sg:tags":[
        "building",
        "apartment"
    ],
    "wof:name":"Maplewood Glen Senior Living",
    "wof:placetype":"venue"
},
  "geometry": {"coordinates":[-90.427547,42.600644],"type":"Point"}
}