{
  "type": "Feature",
  "properties": {
    "iso:country":"US",
    "sg:address":"1001 E North Ave",
    "sg:city":"Milwaukee",
    "sg:classifiers":[
        {
            "category":"Home & Garden",
            "subcategory":"Home Furnishings",
            "type":"Retail Goods"
        }
    ],
    "sg:phone":"+1 414 372 0530",
    "sg:postcode":"53212",
    "sg:province":"WI",
    "sg:tags":[
        "basket"
    ],
    "wof:name":"Humphrey-Stephens Fiber Arts",
    "wof:placetype":"venue"
},
  "geometry": {"coordinates":[-87.897931,43.060203],"type":"Point"}
}