{
  "type": "Feature",
  "properties": {
    "iso:country":"US",
    "sg:address":"147 W Maple St",
    "sg:city":"Lancaster",
    "sg:classifiers":[
        {
            "category":"Professional",
            "subcategory":"Lawyer & Legal Services",
            "type":"Services"
        }
    ],
    "sg:phone":"+1 608 723 7866",
    "sg:postcode":"53813",
    "sg:province":"WI",
    "sg:tags":[
        "attorney"
    ],
    "wof:name":"Thomas T Schrader",
    "wof:placetype":"venue"
},
  "geometry": {"coordinates":[-90.710361,42.848035],"type":"Point"}
}