{
  "type": "Feature",
  "properties": {
    "addr:full":"822 N 14th St Sheboygan WI 53081",
    "addr:housenumber":"822",
    "addr:postcode":"53081",
    "addr:street":"N 14Th St",
    "iso:country":"US",
    "sg:address":"822 N 14th St",
    "sg:city":"Sheboygan",
    "sg:classifiers":[
        {
            "category":"Home & Garden",
            "subcategory":"Furniture",
            "type":"Retail Goods"
        }
    ],
    "sg:phone":"+1 920 457 3656",
    "sg:postcode":"53081",
    "sg:province":"WI",
    "wof:name":"Richardson Industries Inc",
    "wof:placetype":"venue"
},
  "geometry": {"coordinates":[-87.72303100000001,43.754076],"type":"Point"}
}