{
  "type": "Feature",
  "properties": {
    "iso:country":"US",
    "sg:address":"458 N Washington St",
    "sg:city":"Berlin",
    "sg:classifiers":[
        {
            "category":"Shopping",
            "subcategory":"Hobbies, Toys, & Games",
            "type":"Retail Goods"
        },
        {
            "category":"Retail",
            "subcategory":"Auto Repair",
            "type":"Services"
        }
    ],
    "sg:phone":"+1 920 361 4130",
    "sg:postcode":"54923",
    "sg:province":"WI",
    "sg:tags":[
        "body",
        "automobile",
        "painting"
    ],
    "wof:name":"Auto Body Specialists",
    "wof:placetype":"venue"
},
  "geometry": {"coordinates":[-88.956766,43.981142],"type":"Point"}
}