{
  "type": "Feature",
  "properties": {
    "iso:country":"US",
    "sg:address":"143 S Main St",
    "sg:city":"Amherst",
    "sg:classifiers":[
        {
            "category":"Home & Garden",
            "subcategory":"Hardware",
            "type":"Retail Goods"
        }
    ],
    "sg:phone":"+1 715 824 5614",
    "sg:postcode":"54406",
    "sg:province":"WI",
    "wof:name":"O K Hardware & Rentals",
    "wof:placetype":"venue"
},
  "geometry": {"coordinates":[-89.285115,44.450462],"type":"Point"}
}