{
  "type": "Feature",
  "properties": {
    "iso:country":"US",
    "sg:address":"2323 W Everett St",
    "sg:city":"Appleton",
    "sg:classifiers":[
        {
            "category":"Professional",
            "subcategory":"Printing & Photocopies",
            "type":"Services"
        }
    ],
    "sg:phone":"+1 920 955 3720",
    "sg:postcode":"54914",
    "sg:province":"WI",
    "sg:tags":[
        "services-commercial",
        "form",
        "printers-business"
    ],
    "wof:name":"United Tag & Printing Solutions",
    "wof:placetype":"venue"
},
  "geometry": {"coordinates":[-88.44289999999999,44.2523],"type":"Point"}
}