{
  "type": "Feature",
  "properties": {
    "iso:country":"US",
    "sg:address":"232 Horicon St",
    "sg:city":"Mayville",
    "sg:classifiers":[
        {
            "category":"Building & Trades",
            "subcategory":"Construction",
            "type":"Services"
        }
    ],
    "sg:phone":"+1 920 387 9445",
    "sg:postcode":"53050",
    "sg:province":"WI",
    "sg:tags":[
        "concrete",
        "contractor"
    ],
    "wof:name":"American Concrete Leveling",
    "wof:placetype":"venue"
},
  "geometry": {"coordinates":[-88.545425,43.493916],"type":"Point"}
}