{
  "type": "Feature",
  "properties": {
    "iso:country":"US",
    "sg:address":"1610 Ruskin St",
    "sg:city":"Madison",
    "sg:classifiers":[
        {
            "category":"Education",
            "subcategory":"School",
            "type":"Public Place"
        }
    ],
    "sg:phone":"+1 608 204 2100",
    "sg:postcode":"53704",
    "sg:province":"WI",
    "wof:name":"Sherman Middle School",
    "wof:placetype":"venue"
},
  "geometry": {"coordinates":[-89.361761,43.117839],"type":"Point"}
}