{
  "type": "Feature",
  "properties": {
    "iso:country":"US",
    "sg:address":"10001 W Lisbon Ave",
    "sg:city":"Milwaukee",
    "sg:classifiers":[
        {
            "category":"Manufacturing",
            "subcategory":"Printing",
            "type":"Manufacturing & Wholesale Goods"
        }
    ],
    "sg:phone":"+1 414 466 3933",
    "sg:postcode":"53222",
    "sg:province":"WI",
    "sg:tags":[
        "printer"
    ],
    "wof:name":"Hometown Graphics",
    "wof:placetype":"venue"
},
  "geometry": {"coordinates":[-88.038493,43.089302],"type":"Point"}
}