{
  "type": "Feature",
  "properties": {
    "iso:country":"US",
    "sg:address":"2112 S 111th St",
    "sg:city":"Milwaukee",
    "sg:classifiers":[
        {
            "category":"Professional",
            "subcategory":"Management & Consulting",
            "type":"Services"
        }
    ],
    "sg:phone":"+1 414 329 7786",
    "sg:postcode":"53227",
    "sg:province":"WI",
    "wof:name":"Geo C Mueller PHD",
    "wof:placetype":"venue"
},
  "geometry": {"coordinates":[-88.05046900000001,43.004662],"type":"Point"}
}