{
  "type": "Feature",
  "properties": {
    "iso:country":"US",
    "sg:address":"10016 Exchange Rd",
    "sg:city":"Prairie Du Sac",
    "sg:classifiers":[
        {
            "category":"Professional",
            "subcategory":"Business Services",
            "type":"Services"
        }
    ],
    "sg:phone":"+1 608 544 3882",
    "sg:postcode":"53578",
    "sg:province":"WI",
    "sg:tags":[
        "construction"
    ],
    "wof:name":"Everts Sales & Construction",
    "wof:placetype":"venue"
},
  "geometry": {"coordinates":[-89.828597,43.289653],"type":"Point"}
}