{
  "type": "Feature",
  "properties": {
    "iso:country":"US",
    "sg:address":"1630 Linden Dr",
    "sg:city":"Madison",
    "sg:classifiers":[
        {
            "category":"Farming",
            "subcategory":"Farm",
            "type":"Manufacturing & Wholesale Goods"
        }
    ],
    "sg:phone":"+1 608 271 7427",
    "sg:postcode":"53706",
    "sg:province":"WI",
    "sg:tags":[
        "crop",
        "general"
    ],
    "wof:name":"Dean Arny",
    "wof:placetype":"venue"
},
  "geometry": {"coordinates":[-89.413849,43.075226],"type":"Point"}
}