{
  "type": "Feature",
  "properties": {
    "iso:country":"US",
    "sg:address":"9302 39th Ave",
    "sg:city":"Pleasant Prairie",
    "sg:classifiers":[
        {
            "category":"Organizations",
            "subcategory":"Non-profit Organization",
            "type":"Services"
        }
    ],
    "sg:phone":"+1 262 697 1510",
    "sg:postcode":"53158",
    "sg:province":"WI",
    "sg:tags":[
        "alternative",
        "abortion"
    ],
    "wof:name":"Genesis House Of Southeast Wi",
    "wof:placetype":"venue"
},
  "geometry": {"coordinates":[-87.85415399999999,42.531214],"type":"Point"}
}