{
  "type": "Feature",
  "properties": {
    "addr:full":"10319 Co Rd I Burnett WI 53922",
    "addr:housenumber":"10319",
    "addr:postcode":"53922",
    "addr:street":"Co Rd I",
    "iso:country":"US",
    "sg:address":"10319 Co Rd I",
    "sg:city":"Burnett",
    "sg:classifiers":[
        {
            "category":"Farming",
            "subcategory":"Dairy Farm",
            "type":"Manufacturing & Wholesale Goods"
        }
    ],
    "sg:phone":"+1 920 324 3269",
    "sg:postcode":"53922",
    "sg:province":"WI",
    "sg:tags":[
        "corn",
        "grain",
        "cash"
    ],
    "wof:name":"Ed-Bon Holstins",
    "wof:placetype":"venue"
},
  "geometry": {"coordinates":[-88.723977,43.570439],"type":"Point"}
}