{
  "type": "Feature",
  "properties": {
    "addr:full":"325 N Bagley Ave Bagley WI 53801",
    "addr:housenumber":"325",
    "addr:postcode":"53801",
    "addr:street":"N Bagley Ave",
    "iso:country":"US",
    "sg:address":"325 N Bagley Ave",
    "sg:city":"Bagley",
    "sg:classifiers":[
        {
            "category":"Real Estate",
            "subcategory":"Real Estate Operator",
            "type":"Services"
        }
    ],
    "sg:phone":"+1 608 996 2373",
    "sg:postcode":"53801",
    "sg:province":"WI",
    "sg:tags":[
        "building",
        "apartment"
    ],
    "wof:name":"Valley Apartments",
    "wof:placetype":"venue"
},
  "geometry": {"coordinates":[-91.102934,42.907034],"type":"Point"}
}