{
  "type": "Feature",
  "properties": {
    "iso:country":"US",
    "sg:address":"33805 Jaquish North Rd",
    "sg:city":"Hillpoint",
    "sg:classifiers":[
        {
            "category":"Professional",
            "type":"Services"
        }
    ],
    "sg:phone":"+1 608 585 2177",
    "sg:postcode":"53937",
    "sg:province":"WI",
    "wof:name":"Joseph Kaul",
    "wof:placetype":"venue"
},
  "geometry": {"coordinates":[-90.199977,43.372659],"type":"Point"}
}