{
  "type": "Feature",
  "properties": {
    "addr:full":"1602 E Milwaukee St Janesville WI 53545",
    "addr:housenumber":"1602",
    "addr:postcode":"53545",
    "addr:street":"E Milwaukee St",
    "iso:country":"US",
    "sg:address":"1602 E Milwaukee St",
    "sg:city":"Janesville",
    "sg:classifiers":[
        {
            "category":"Building & Trades",
            "subcategory":"Construction",
            "type":"Services"
        }
    ],
    "sg:phone":"+1 608 752 5207",
    "sg:postcode":"53545",
    "sg:province":"WI",
    "sg:tags":[
        "painter"
    ],
    "wof:name":"Jim Rook Painting",
    "wof:placetype":"venue"
},
  "geometry": {"coordinates":[-89.00194,42.691075],"type":"Point"}
}