{
  "type": "Feature",
  "properties": {
    "iso:country":"US",
    "sg:address":"822 Walsh Rd",
    "sg:city":"Madison",
    "sg:classifiers":[
        {
            "category":"Home & Garden",
            "subcategory":"Carpets & Floor Coverings",
            "type":"Retail Goods"
        }
    ],
    "sg:phone":"+1 608 240 0040",
    "sg:postcode":"53714",
    "sg:province":"WI",
    "wof:name":"Blake Stevens Wood Flooring",
    "wof:placetype":"venue"
},
  "geometry": {"coordinates":[-89.309994,43.108051],"type":"Point"}
}