{
  "type": "Feature",
  "properties": {
    "iso:country":"US",
    "sg:address":"20011 Jupiter Rd",
    "sg:city":"Tomah",
    "sg:classifiers":[
        {
            "category":"Farming",
            "subcategory":"Dairy Farm",
            "type":"Manufacturing & Wholesale Goods"
        }
    ],
    "sg:phone":"+1 608 427 6721",
    "sg:postcode":"54660",
    "sg:province":"WI",
    "wof:name":"Dairy Farmer",
    "wof:placetype":"venue"
},
  "geometry": {"coordinates":[-90.398088,43.891442],"type":"Point"}
}