{
  "type": "Feature",
  "properties": {
    "iso:country":"US",
    "sg:address":"118 S Main St",
    "sg:city":"Fountain City",
    "sg:classifiers":[
        {
            "category":"Food & Beverages",
            "subcategory":"Specialty",
            "type":"Retail Goods"
        },
        {
            "category":"Manufacturing",
            "subcategory":"Pet Food",
            "type":"Manufacturing & Wholesale Goods"
        }
    ],
    "sg:phone":"+1 608 687 9580",
    "sg:postcode":"54629",
    "sg:province":"WI",
    "sg:tags":[
        "mill",
        "health",
        "diet",
        "mfg"
    ],
    "wof:name":"Great River Organic Milling Co",
    "wof:placetype":"venue"
},
  "geometry": {"coordinates":[-91.715945,44.129743],"type":"Point"}
}