{
  "type": "Feature",
  "properties": {
    "iso:country":"US",
    "sg:address":"2190 Riplinger Rd",
    "sg:city":"Spencer",
    "sg:classifiers":[
        {
            "category":"Farming",
            "subcategory":"Dairy Farm",
            "type":"Manufacturing & Wholesale Goods"
        }
    ],
    "sg:phone":"+1 715 255 9012",
    "sg:postcode":"54479",
    "sg:province":"WI",
    "wof:name":"Michael Gaetz",
    "wof:placetype":"venue"
},
  "geometry": {"coordinates":[-90.420947,44.821186],"type":"Point"}
}