{
  "type": "Feature",
  "properties": {
    "iso:country":"US",
    "sg:address":"2211 Lang Dr",
    "sg:city":"Lodi",
    "sg:classifiers":[
        {
            "category":"Building & Trades",
            "subcategory":"Construction",
            "type":"Services"
        }
    ],
    "sg:phone":"+1 608 592 5908",
    "sg:postcode":"53555",
    "sg:province":"WI",
    "sg:tags":[
        "concrete",
        "cutting",
        "breaking",
        "sawing"
    ],
    "wof:name":"Curb Cuts",
    "wof:placetype":"venue"
},
  "geometry": {"coordinates":[-89.522543,43.356318],"type":"Point"}
}