{
  "type": "Feature",
  "properties": {
    "iso:country":"US",
    "sg:address":"1272 Traprock Dr",
    "sg:city":"St Croix Falls",
    "sg:classifiers":[
        {
            "category":"Building & Trades",
            "subcategory":"Construction",
            "type":"Services"
        }
    ],
    "sg:phone":"+1 715 483 9979",
    "sg:postcode":"54024",
    "sg:province":"WI",
    "sg:tags":[
        "house",
        "general",
        "contractor"
    ],
    "wof:name":"Cross Construction",
    "wof:placetype":"venue"
},
  "geometry": {"coordinates":[-92.627299,45.382836],"type":"Point"}
}