{
  "type": "Feature",
  "properties": {
    "iso:country":"US",
    "sg:address":"418 N Main St",
    "sg:city":"Amherst",
    "sg:classifiers":[
        {
            "category":"Professional",
            "type":"Services"
        }
    ],
    "sg:phone":"+1 715 824 4476",
    "sg:postcode":"54406",
    "sg:province":"WI",
    "wof:name":"Just Plain Mahogany LLC",
    "wof:placetype":"venue"
},
  "geometry": {"coordinates":[-89.284288,44.455375],"type":"Point"}
}