{
  "type": "Feature",
  "properties": {
    "addr:full":"2120 W Clybourn St Milwaukee WI 53233",
    "addr:housenumber":"2120",
    "addr:postcode":"53233",
    "addr:street":"W Clybourn St",
    "iso:country":"US",
    "sg:address":"2120 W Clybourn St",
    "sg:city":"Milwaukee",
    "sg:phone":"+1 414 933 7355",
    "sg:postcode":"53233",
    "sg:province":"WI",
    "sg:website":"http://www.chinesekungfucenter.com",
    "wof:name":"Chinese Kung Fu Center",
    "wof:placetype":"venue"
},
  "geometry": {"coordinates":[-87.939566,43.036105],"type":"Point"}
}