{
  "type": "Feature",
  "properties": {
    "iso:country":"US",
    "sg:address":"2433 S Green Bay Rd",
    "sg:city":"Racine",
    "sg:classifiers":[
        {
            "category":"Shopping",
            "subcategory":"Hobbies, Toys, & Games",
            "type":"Retail Goods"
        }
    ],
    "sg:phone":"+1 262 637 8697",
    "sg:postcode":"53406",
    "sg:province":"WI",
    "wof:name":"Toys R Us",
    "wof:placetype":"venue"
},
  "geometry": {"coordinates":[-87.852373,42.703104],"type":"Point"}
}