{
  "type": "Feature",
  "properties": {
    "addr:full":"20 N 1st St Black River Fls WI 54615",
    "addr:housenumber":"20",
    "addr:postcode":"54615",
    "addr:street":"N 1St St",
    "iso:country":"US",
    "sg:address":"20 N 1st St",
    "sg:city":"Black River Fls",
    "sg:classifiers":[
        {
            "category":"Home & Garden",
            "subcategory":"Carpets & Floor Coverings",
            "type":"Retail Goods"
        }
    ],
    "sg:phone":"+1 715 284 2922",
    "sg:postcode":"54615",
    "sg:province":"WI",
    "sg:tags":[
        "dealer",
        "rug"
    ],
    "wof:name":"Prochaska Carpet Svc",
    "wof:placetype":"venue"
},
  "geometry": {"coordinates":[-90.848735,44.295955],"type":"Point"}
}