{
  "type": "Feature",
  "properties": {
    "iso:country":"US",
    "sg:address":"7459 State Hwy 42",
    "sg:city":"Sheboygan",
    "sg:classifiers":[
        {
            "category":"Retail",
            "subcategory":"Auto Repair",
            "type":"Services"
        }
    ],
    "sg:phone":"+1 920 565 3324",
    "sg:postcode":"53083",
    "sg:province":"WI",
    "sg:tags":[
        "body",
        "automobile",
        "painting"
    ],
    "wof:name":"SRJJ Enterprises",
    "wof:placetype":"venue"
},
  "geometry": {"coordinates":[-87.785971,43.810457],"type":"Point"}
}