{
  "type": "Feature",
  "properties": {
    "addr:full":"740 N Water St Milwaukee WI 53202",
    "addr:housenumber":"740",
    "addr:postcode":"53202",
    "addr:street":"N Water St",
    "iso:country":"US",
    "sg:address":"740 N Water St",
    "sg:city":"Milwaukee",
    "sg:classifiers":[
        {
            "category":"Utilities",
            "subcategory":"Mobile Phone",
            "type":"Services"
        },
        {
            "category":"Shopping",
            "subcategory":"Mobile Phones",
            "type":"Retail Goods"
        }
    ],
    "sg:postcode":"53202",
    "sg:province":"WI",
    "sg:tags":[
        "supply",
        "communication",
        "telephone",
        "wireless",
        "equipment",
        "cellular"
    ],
    "sg:website":"http://clickserve.dartsearch.net/link/click?lid=43000000329024651",
    "wof:name":"U.S. Cellular",
    "wof:placetype":"venue"
},
  "geometry": {"coordinates":[-87.909218,43.039633],"type":"Point"}
}