{
  "type": "Feature",
  "properties": {
    "iso:country":"US",
    "sg:address":"1661 N Farwell Ave",
    "sg:city":"Milwaukee",
    "sg:classifiers":[
        {
            "category":"Professional",
            "subcategory":"Business Services",
            "type":"Services"
        }
    ],
    "sg:phone":"+1 414 271 1144",
    "sg:postcode":"53202",
    "sg:province":"WI",
    "sg:tags":[
        "translator",
        "interpreter"
    ],
    "sg:website":"www.iversonlang.com",
    "wof:name":"Iverson Language Assoc Inc",
    "wof:placetype":"venue"
},
  "geometry": {"coordinates":[-87.89394900000001,43.050924],"type":"Point"}
}