{
  "type": "Feature",
  "properties": {
    "addr:full":"1302 Saint Thomas Dr Eau Claire WI 54703",
    "addr:housenumber":"1302",
    "addr:postcode":"54703",
    "addr:street":"Saint Thomas Dr",
    "iso:country":"US",
    "sg:address":"1302 Saint Thomas Dr",
    "sg:city":"Eau Claire",
    "sg:classifiers":[
        {
            "category":"Personal",
            "subcategory":"Beauty Salon",
            "type":"Services"
        }
    ],
    "sg:phone":"+1 715 836 9123",
    "sg:postcode":"54703",
    "sg:province":"WI",
    "sg:tags":[
        "shop"
    ],
    "wof:name":"Stylistics",
    "wof:placetype":"venue"
},
  "geometry": {"coordinates":[-91.56658,44.812962],"type":"Point"}
}