{
  "type": "Feature",
  "properties": {
    "addr:full":"300 Broad St Menasha WI 54952",
    "addr:housenumber":"300",
    "addr:postcode":"54952",
    "addr:street":"Broad St",
    "iso:country":"US",
    "sg:address":"300 Broad St",
    "sg:city":"Menasha",
    "sg:classifiers":[
        {
            "category":"Education",
            "subcategory":"School",
            "type":"Public Place"
        }
    ],
    "sg:phone":"+1 920 725 1715",
    "sg:postcode":"54952",
    "sg:province":"WI",
    "sg:tags":[
        "organization",
        "religious"
    ],
    "wof:name":"Trinity Lutheran School",
    "wof:placetype":"venue"
},
  "geometry": {"coordinates":[-88.449169,44.202031],"type":"Point"}
}