{
  "type": "Feature",
  "properties": {
    "iso:country":"US",
    "sg:address":"7010 W Sandpiper Ct",
    "sg:city":"Milwaukee",
    "sg:classifiers":[
        {
            "category":"Organizations",
            "subcategory":"Religious Organization",
            "type":"Services"
        }
    ],
    "sg:phone":"+1 414 351 3334",
    "sg:postcode":"53223",
    "sg:province":"WI",
    "sg:tags":[
        "church"
    ],
    "wof:name":"St John's Community Church",
    "wof:placetype":"venue"
},
  "geometry": {"coordinates":[-87.997703,43.174121],"type":"Point"}
}