{
  "type": "Feature",
  "properties": {
    "iso:country":"US",
    "sg:address":"420 Washington St",
    "sg:city":"Eau Claire",
    "sg:classifiers":[
        {
            "category":"Shopping",
            "type":"Retail Goods"
        }
    ],
    "sg:phone":"+1 715 833 9975",
    "sg:postcode":"54701",
    "sg:province":"WI",
    "sg:tags":[
        "miscellaneous",
        "store"
    ],
    "wof:name":"Digital Edge",
    "wof:placetype":"venue"
},
  "geometry": {"coordinates":[-91.491203,44.805053],"type":"Point"}
}