{
  "type": "Feature",
  "properties": {
    "iso:country":"US",
    "sg:address":"730 Wisconsin Ave",
    "sg:city":"Racine",
    "sg:classifiers":[
        {
            "category":"Government",
            "subcategory":"Office",
            "type":"Public Place"
        }
    ],
    "sg:phone":"+1 262 636 3201",
    "sg:postcode":"53403",
    "sg:province":"WI",
    "wof:name":"Racine County Human Resources",
    "wof:placetype":"venue"
},
  "geometry": {"coordinates":[-87.783818,42.724926],"type":"Point"}
}