{
  "type": "Feature",
  "properties": {
    "addr:full":"728 Highview Ln Kimberly WI 54136",
    "addr:housenumber":"728",
    "addr:postcode":"54136",
    "addr:street":"Highview Ln",
    "iso:country":"US",
    "sg:address":"728 Highview Ln",
    "sg:city":"Kimberly",
    "sg:classifiers":[
        {
            "category":"Building & Trades",
            "subcategory":"Construction",
            "type":"Services"
        }
    ],
    "sg:phone":"+1 920 788 5603",
    "sg:postcode":"54136",
    "sg:province":"WI",
    "sg:tags":[
        "contractor"
    ],
    "wof:name":"Lee Menting Builders",
    "wof:placetype":"venue"
},
  "geometry": {"coordinates":[-88.332487,44.261934],"type":"Point"}
}