{
  "type": "Feature",
  "properties": {
    "iso:country":"US",
    "sg:address":"1214 Co Rd Kb",
    "sg:city":"Denmark",
    "sg:classifiers":[
        {
            "category":"Building & Trades",
            "subcategory":"Plumbing",
            "type":"Services"
        }
    ],
    "sg:phone":"+1 920 863 6931",
    "sg:postcode":"54208",
    "sg:province":"WI",
    "sg:tags":[
        "contractor"
    ],
    "wof:name":"Hermans Heating & AC",
    "wof:placetype":"venue"
},
  "geometry": {"coordinates":[-87.707785,44.356057],"type":"Point"}
}