{
  "type": "Feature",
  "properties": {
    "iso:country":"US",
    "sg:address":"310 Elm St",
    "sg:city":"New London",
    "sg:classifiers":[
        {
            "category":"Building & Trades",
            "subcategory":"Construction",
            "type":"Services"
        }
    ],
    "sg:phone":"+1 920 359 8888",
    "sg:postcode":"54961",
    "sg:province":"WI",
    "sg:tags":[
        "paving",
        "asphalt",
        "contractor"
    ],
    "wof:name":"New London Asphalt",
    "wof:placetype":"venue"
},
  "geometry": {"coordinates":[-88.751053,44.395093],"type":"Point"}
}