{
  "type": "Feature",
  "properties": {
    "iso:country":"US",
    "sg:address":"2418 N Sherman Ave",
    "sg:city":"Madison",
    "sg:classifiers":[
        {
            "category":"Retail",
            "subcategory":"Funeral Services",
            "type":"Services"
        }
    ],
    "sg:phone":"+1 608 249 8257",
    "sg:postcode":"53704",
    "sg:province":"WI",
    "sg:tags":[
        "home"
    ],
    "wof:name":"Madison Cremation Service",
    "wof:placetype":"venue"
},
  "geometry": {"coordinates":[-89.363657,43.126067],"type":"Point"}
}