{
  "type": "Feature",
  "properties": {
    "iso:country":"US",
    "sg:address":"805 Witzel Ave",
    "sg:city":"Oshkosh",
    "sg:classifiers":[
        {
            "category":"Manufacturing",
            "subcategory":"Lumber",
            "type":"Manufacturing & Wholesale Goods"
        }
    ],
    "sg:phone":"+1 920 232 5314",
    "sg:postcode":"54902",
    "sg:province":"WI",
    "sg:tags":[
        "government"
    ],
    "wof:name":"Oshkosh Forestry Div Workshop",
    "wof:placetype":"venue"
},
  "geometry": {"coordinates":[-88.56168,44.017782],"type":"Point"}
}