{
  "type": "Feature",
  "properties": {
    "iso:country":"US",
    "sg:address":"2390 W Nordale Dr",
    "sg:city":"Appleton",
    "sg:classifiers":[
        {
            "category":"Building & Trades",
            "subcategory":"Electrical",
            "type":"Services"
        }
    ],
    "sg:phone":"+1 920 731 2388",
    "sg:postcode":"54914",
    "sg:province":"WI",
    "sg:tags":[
        "electrical",
        "electric",
        "contractor"
    ],
    "wof:name":"Bissing Electric Inc",
    "wof:placetype":"venue"
},
  "geometry": {"coordinates":[-88.44294,44.286514],"type":"Point"}
}