{
  "type": "Feature",
  "properties": {
    "iso:country":"US",
    "sg:address":"1643 Niles Ln",
    "sg:city":"Centuria",
    "sg:classifiers":[
        {
            "category":"Travel",
            "subcategory":"Travel Agent",
            "type":"Entertainment"
        }
    ],
    "sg:phone":"+1 715 646 2605",
    "sg:postcode":"54824",
    "sg:province":"WI",
    "sg:tags":[
        "agency"
    ],
    "wof:name":"Apex Travel",
    "wof:placetype":"venue"
},
  "geometry": {"coordinates":[-92.50099299999999,45.445983],"type":"Point"}
}