{
  "type": "Feature",
  "properties": {
    "iso:country":"US",
    "sg:address":"600 Cashman Dr",
    "sg:city":"Chippewa Falls",
    "sg:classifiers":[
        {
            "category":"Professional",
            "subcategory":"Business Services",
            "type":"Services"
        }
    ],
    "sg:phone":"+1 715 720 8093",
    "sg:postcode":"54729",
    "sg:province":"WI",
    "sg:tags":[
        "metal",
        "fabrication"
    ],
    "wof:name":"A L M",
    "wof:placetype":"venue"
},
  "geometry": {"coordinates":[-91.353955,44.938391],"type":"Point"}
}