{
  "type": "Feature",
  "properties": {
    "iso:country":"US",
    "sg:address":"160 S 2nd St",
    "sg:city":"Milwaukee",
    "sg:classifiers":[
        {
            "category":"Manufacturing",
            "subcategory":"Printing",
            "type":"Manufacturing & Wholesale Goods"
        }
    ],
    "sg:phone":"+1 414 276 6676",
    "sg:postcode":"53204",
    "sg:province":"WI",
    "sg:tags":[
        "offset"
    ],
    "wof:name":"Badger-Becker Inc",
    "wof:placetype":"venue"
},
  "geometry": {"coordinates":[-87.912418,43.032331],"type":"Point"}
}