{
  "type": "Feature",
  "properties": {
    "iso:country":"US",
    "sg:address":"1028 S 9th St",
    "sg:city":"Manitowoc",
    "sg:classifiers":[
        {
            "category":"Professional",
            "subcategory":"Lawyer & Legal Services",
            "type":"Services"
        }
    ],
    "sg:phone":"+1 920 683 3500",
    "sg:postcode":"54220",
    "sg:province":"WI",
    "sg:tags":[
        "attorney"
    ],
    "wof:name":"Whyte Hirschboeck & Dudek",
    "wof:placetype":"venue"
},
  "geometry": {"coordinates":[-87.65926399999999,44.087246],"type":"Point"}
}