{
  "type": "Feature",
  "properties": {
    "iso:country":"US",
    "sg:address":"2891 Waubesa Ave",
    "sg:city":"Madison",
    "sg:classifiers":[
        {
            "category":"Manufacturing",
            "subcategory":"Signs",
            "type":"Manufacturing & Wholesale Goods"
        }
    ],
    "sg:phone":"+1 608 221 3929",
    "sg:postcode":"53711",
    "sg:province":"WI",
    "sg:tags":[
        "specialty",
        "mfg"
    ],
    "wof:name":"Creative Signs",
    "wof:placetype":"venue"
},
  "geometry": {"coordinates":[-89.33836599999999,43.004616],"type":"Point"}
}