{
  "type": "Feature",
  "properties": {
    "addr:full":"50 Prairie Ave Prairie Du Sac WI 53578",
    "addr:housenumber":"50",
    "addr:postcode":"53578",
    "addr:street":"Prairie Ave",
    "iso:country":"US",
    "sg:address":"50 Prairie Ave",
    "sg:city":"Prairie Du Sac",
    "sg:classifiers":[
        {
            "category":"Health Services",
            "subcategory":"Clinic",
            "type":"Services"
        }
    ],
    "sg:phone":"+1 608 588 2620",
    "sg:postcode":"53578",
    "sg:province":"WI",
    "sg:tags":[
        "specialty",
        "outpatient"
    ],
    "wof:name":"Pathways",
    "wof:placetype":"venue"
},
  "geometry": {"coordinates":[-89.719397,43.28348],"type":"Point"}
}