{
  "type": "Feature",
  "properties": {
    "addr:full":"206 Carver St Winslow WI 61089",
    "addr:housenumber":"206",
    "addr:postcode":"61089",
    "addr:street":"Carver St",
    "iso:country":"US",
    "sg:address":"206 Carver St",
    "sg:city":"Winslow",
    "sg:classifiers":[
        {
            "category":"Insurance",
            "subcategory":"Insurance Agent",
            "type":"Services"
        }
    ],
    "sg:phone":"+1 815 367 2622",
    "sg:postcode":"61089",
    "sg:province":"WI",
    "wof:name":"Meyer Insurance",
    "wof:placetype":"venue"
},
  "geometry": {"coordinates":[-89.795344,42.496368],"type":"Point"}
}