{
  "type": "Feature",
  "properties": {
    "addr:full":"212 Talcott Ave Fort Atkinson WI 53538",
    "addr:housenumber":"212",
    "addr:postcode":"53538",
    "addr:street":"Talcott Ave",
    "iso:country":"US",
    "sg:address":"212 Talcott Ave",
    "sg:city":"Fort Atkinson",
    "sg:classifiers":[
        {
            "category":"Organizations",
            "subcategory":"Religious Organization",
            "type":"Services"
        }
    ],
    "sg:phone":"+1 920 563 4467",
    "sg:postcode":"53538",
    "sg:province":"WI",
    "sg:tags":[
        "church"
    ],
    "wof:name":"Fort Christian Assembly",
    "wof:placetype":"venue"
},
  "geometry": {"coordinates":[-88.840856,42.914609],"type":"Point"}
}