{
  "type": "Feature",
  "properties": {
    "iso:country":"US",
    "sg:address":"101 Western Ave",
    "sg:city":"Watertown",
    "sg:classifiers":[
        {
            "category":"Wholesale",
            "subcategory":"Groceries",
            "type":"Manufacturing & Wholesale Goods"
        }
    ],
    "sg:phone":"+1 920 261 6158",
    "sg:postcode":"53094",
    "sg:province":"WI",
    "sg:tags":[
        "retail"
    ],
    "wof:name":"Berres Bros Coffee Roasters",
    "wof:placetype":"venue"
},
  "geometry": {"coordinates":[-88.725278,43.189015],"type":"Point"}
}