{
  "type": "Feature",
  "properties": {
    "iso:country":"US",
    "sg:address":"3351 W Lynndale Ave",
    "sg:city":"Milwaukee",
    "sg:classifiers":[
        {
            "category":"Professional",
            "subcategory":"Business Services",
            "type":"Services"
        }
    ],
    "sg:phone":"+1 414 281 8090",
    "sg:postcode":"53221",
    "sg:province":"WI",
    "wof:name":"Monitoring & Reminder Services",
    "wof:placetype":"venue"
},
  "geometry": {"coordinates":[-87.95743899999999,42.975158],"type":"Point"}
}