{
  "type": "Feature",
  "properties": {
    "iso:country":"US",
    "sg:address":"5005 Co Rd U",
    "sg:city":"Newton",
    "sg:classifiers":[
        {
            "category":"Farming",
            "subcategory":"Dairy Farm",
            "type":"Manufacturing & Wholesale Goods"
        }
    ],
    "sg:phone":"+1 920 726 4730",
    "sg:postcode":"53063",
    "sg:province":"WI",
    "wof:name":"Ralph Lutze",
    "wof:placetype":"venue"
},
  "geometry": {"coordinates":[-87.709278,43.993985],"type":"Point"}
}