{
  "type": "Feature",
  "properties": {
    "iso:country":"US",
    "sg:address":"527 Hillside Rd",
    "sg:city":"Edgerton",
    "sg:classifiers":[
        {
            "category":"Building & Trades",
            "subcategory":"Landscaping Services",
            "type":"Services"
        }
    ],
    "sg:phone":"+1 608 884 8291",
    "sg:postcode":"53534",
    "sg:province":"WI",
    "sg:tags":[
        "landscape",
        "contractor"
    ],
    "wof:name":"Hillside Landscape Co",
    "wof:placetype":"venue"
},
  "geometry": {"coordinates":[-89.038078,42.875131],"type":"Point"}
}