{
  "type": "Feature",
  "properties": {
    "iso:country":"US",
    "sg:address":"4030 S Katherine Dr",
    "sg:city":"New Berlin",
    "sg:classifiers":[
        {
            "category":"Arts & Performance",
            "subcategory":"Theater",
            "type":"Entertainment"
        }
    ],
    "sg:phone":"+1 262 797 0050",
    "sg:postcode":"53151",
    "sg:province":"WI",
    "sg:tags":[
        "group"
    ],
    "wof:name":"Soundwaves",
    "wof:placetype":"venue"
},
  "geometry": {"coordinates":[-88.110726,42.971613],"type":"Point"}
}