{
  "type": "Feature",
  "properties": {
    "iso:country":"US",
    "sg:address":"5772 Leland Rd",
    "sg:city":"Loganville",
    "sg:classifiers":[
        {
            "category":"Farming",
            "subcategory":"Farm",
            "type":"Manufacturing & Wholesale Goods"
        }
    ],
    "sg:phone":"+1 608 546 2606",
    "sg:postcode":"53943",
    "sg:province":"WI",
    "sg:tags":[
        "crop",
        "general"
    ],
    "wof:name":"Yanke Hillside Farms Inc",
    "wof:placetype":"venue"
},
  "geometry": {"coordinates":[-90.035989,43.31954],"type":"Point"}
}