{
  "type": "Feature",
  "properties": {
    "iso:country":"US",
    "sg:address":"2502 E Greenquist Lake Ln",
    "sg:city":"Cumberland",
    "sg:classifiers":[
        {
            "category":"Organizations",
            "subcategory":"Religious Organization",
            "type":"Services"
        }
    ],
    "sg:phone":"+1 715 822 3001",
    "sg:postcode":"54829",
    "sg:province":"WI",
    "wof:name":"Trinity Lthran Church McKinley",
    "wof:placetype":"venue"
},
  "geometry": {"coordinates":[-92.179096,45.568058],"type":"Point"}
}