{
  "type": "Feature",
  "properties": {
    "iso:country":"US",
    "sg:address":"726 E Center St",
    "sg:city":"Milwaukee",
    "sg:classifiers":[
        {
            "category":"Retail",
            "subcategory":"Funeral Services",
            "type":"Services"
        }
    ],
    "sg:phone":"+1 414 562 6539",
    "sg:postcode":"53212",
    "sg:province":"WI",
    "sg:tags":[
        "director"
    ],
    "wof:name":"Ritter-Larsen Brothers Funeral",
    "wof:placetype":"venue"
},
  "geometry": {"coordinates":[-87.901865,43.067546],"type":"Point"}
}