{
  "type": "Feature",
  "properties": {
    "iso:country":"US",
    "sg:address":"2400 Springbrook Ct",
    "sg:city":"Beloit",
    "sg:classifiers":[
        {
            "category":"Retail",
            "subcategory":"Auto Repair",
            "type":"Services"
        }
    ],
    "sg:phone":"+1 608 361 0459",
    "sg:postcode":"53511",
    "sg:province":"WI",
    "sg:tags":[
        "transmission"
    ],
    "wof:name":"American Transmission Corp",
    "wof:placetype":"venue"
},
  "geometry": {"coordinates":[-88.99872499999999,42.510156],"type":"Point"}
}