{
  "type": "Feature",
  "properties": {
    "iso:country":"US",
    "sg:address":"1476 N Blue Spring Lake Dr",
    "sg:city":"Palmyra",
    "sg:classifiers":[
        {
            "category":"Education",
            "subcategory":"School",
            "type":"Public Place"
        }
    ],
    "sg:phone":"+1 262 495 7104",
    "sg:postcode":"53156",
    "sg:province":"WI",
    "wof:name":"Battle Creek School",
    "wof:placetype":"venue"
},
  "geometry": {"coordinates":[-88.607277,42.859374],"type":"Point"}
}