{
  "type": "Feature",
  "properties": {
    "iso:country":"US",
    "sg:address":"167 Westhill Dr",
    "sg:city":"Rhinelander",
    "sg:classifiers":[
        {
            "category":"Shopping",
            "subcategory":"Catalog Store",
            "type":"Retail Goods"
        }
    ],
    "sg:phone":"+1 715 369 0774",
    "sg:postcode":"54501",
    "sg:province":"WI",
    "sg:tags":[
        "mail",
        "house"
    ],
    "wof:name":"Rappleys Northwoods Books",
    "wof:placetype":"venue"
},
  "geometry": {"coordinates":[-89.435845,45.637925],"type":"Point"}
}