{
  "type": "Feature",
  "properties": {
    "iso:country":"US",
    "sg:address":"1313 Belknap St",
    "sg:city":"Superior",
    "sg:classifiers":[
        {
            "category":"Government",
            "subcategory":"Office",
            "type":"Public Place"
        }
    ],
    "sg:phone":"+1 715 395 1380",
    "sg:postcode":"54880",
    "sg:province":"WI",
    "sg:tags":[
        "county",
        "planning",
        "dev"
    ],
    "wof:name":"Douglas County Zoning Admin",
    "wof:placetype":"venue"
},
  "geometry": {"coordinates":[-92.09777,46.720738],"type":"Point"}
}