{
  "type": "Feature",
  "properties": {
    "iso:country":"US",
    "sg:address":"1726 Barrett St",
    "sg:city":"Sheboygan",
    "sg:classifiers":[
        {
            "category":"Building & Trades",
            "subcategory":"Construction",
            "type":"Services"
        }
    ],
    "sg:phone":"+1 920 452 4503",
    "sg:postcode":"53081",
    "sg:province":"WI",
    "sg:tags":[
        "home",
        "family",
        "contractor"
    ],
    "wof:name":"Andrew Hopp General Contractor",
    "wof:placetype":"venue"
},
  "geometry": {"coordinates":[-87.700051,43.76339],"type":"Point"}
}