{
  "type": "Feature",
  "properties": {
    "iso:country":"US",
    "sg:address":"3600 Swoboda Rd",
    "sg:city":"Verona",
    "sg:classifiers":[
        {
            "category":"Professional",
            "subcategory":"Management & Consulting",
            "type":"Services"
        }
    ],
    "sg:phone":"+1 608 829 0222",
    "sg:postcode":"53593",
    "sg:province":"WI",
    "sg:tags":[
        "business"
    ],
    "wof:name":"Imerge Consulting",
    "wof:placetype":"venue"
},
  "geometry": {"coordinates":[-89.592141,43.050439],"type":"Point"}
}