{
  "type": "Feature",
  "properties": {
    "iso:country":"US",
    "sg:address":"2711 Branwood Dr",
    "sg:city":"Wisconsin Rapids",
    "sg:classifiers":[
        {
            "category":"Organizations",
            "subcategory":"Political Organization",
            "type":"Services"
        }
    ],
    "sg:phone":"+1 715 421 3940",
    "sg:postcode":"54494",
    "sg:province":"WI",
    "wof:name":"Republican Party Wood County",
    "wof:placetype":"venue"
},
  "geometry": {"coordinates":[-89.791147,44.349434],"type":"Point"}
}