{
  "type": "Feature",
  "properties": {
    "iso:country":"US",
    "sg:address":"100 W 9th St",
    "sg:city":"Fond Du Lac",
    "sg:classifiers":[
        {
            "category":"Recreation",
            "type":"Entertainment"
        }
    ],
    "sg:phone":"+1 920 929 3536",
    "sg:postcode":"54935",
    "sg:province":"WI",
    "sg:tags":[
        "fitness",
        "physical",
        "facility"
    ],
    "wof:name":"Aquatic Center",
    "wof:placetype":"venue"
},
  "geometry": {"coordinates":[-88.453507,43.769435],"type":"Point"}
}