{
  "type": "Feature",
  "properties": {
    "iso:country":"US",
    "sg:address":"2055 Wisconsin Ave",
    "sg:city":"Grafton",
    "sg:classifiers":[
        {
            "category":"Retail",
            "subcategory":"Auto Repair",
            "type":"Services"
        }
    ],
    "sg:phone":"+1 262 377 8229",
    "sg:postcode":"53024",
    "sg:province":"WI",
    "sg:tags":[
        "muffler",
        "exhaust",
        "system"
    ],
    "wof:name":"Midas Auto Svc Experts",
    "wof:placetype":"venue"
},
  "geometry": {"coordinates":[-87.959954,43.305768],"type":"Point"}
}