{
  "type": "Feature",
  "properties": {
    "addr:full":"289 Shenandoah Ct Burlington WI 53105",
    "addr:housenumber":"289",
    "addr:postcode":"53105",
    "addr:street":"Shenandoah Ct",
    "iso:country":"US",
    "sg:address":"289 Shenandoah Ct",
    "sg:city":"Burlington",
    "sg:classifiers":[
        {
            "category":"Building & Trades",
            "subcategory":"Construction",
            "type":"Services"
        }
    ],
    "sg:phone":"+1 262 767 9398",
    "sg:postcode":"53105",
    "sg:province":"WI",
    "sg:tags":[
        "house"
    ],
    "wof:name":"Bauer Construction",
    "wof:placetype":"venue"
},
  "geometry": {"coordinates":[-88.300982,42.677959],"type":"Point"}
}