{
  "type": "Feature",
  "properties": {
    "iso:country":"US",
    "sg:address":"117 87th Pl",
    "sg:city":"Pleasant Prairie",
    "sg:classifiers":[
        {
            "category":"Building & Trades",
            "subcategory":"Construction",
            "type":"Services"
        }
    ],
    "sg:phone":"+1 262 697 0140",
    "sg:postcode":"53158",
    "sg:province":"WI",
    "sg:tags":[
        "painter"
    ],
    "wof:name":"Complete Painting Svc",
    "wof:placetype":"venue"
},
  "geometry": {"coordinates":[-87.815133,42.546718],"type":"Point"}
}