{
  "type": "Feature",
  "properties": {
    "addr:full":"2890 Kennedy Dr Beloit WI 53511",
    "addr:housenumber":"2890",
    "addr:postcode":"53511",
    "addr:street":"Kennedy Dr",
    "iso:country":"US",
    "sg:address":"2890 Kennedy Dr",
    "sg:city":"Beloit",
    "sg:classifiers":[
        {
            "category":"Manufacturing",
            "subcategory":"Tools & Machinery",
            "type":"Manufacturing & Wholesale Goods"
        }
    ],
    "sg:phone":"+1 608 365 3621",
    "sg:postcode":"53511",
    "sg:province":"WI",
    "sg:tags":[
        "machine",
        "die",
        "shop",
        "mfg"
    ],
    "wof:name":"Versa Tl Die Machining & Engrg",
    "wof:placetype":"venue"
},
  "geometry": {"coordinates":[-88.979741,42.521295],"type":"Point"}
}