{
  "type": "Feature",
  "properties": {
    "addr:full":"12714 W Hampton Ave Butler WI 53007",
    "addr:housenumber":"12714",
    "addr:postcode":"53007",
    "addr:street":"W Hampton Ave",
    "iso:country":"US",
    "sg:address":"12714 W Hampton Ave",
    "sg:city":"Butler",
    "sg:classifiers":[
        {
            "category":"Professional",
            "subcategory":"Advertising",
            "type":"Services"
        },
        {
            "category":"Communications",
            "subcategory":"Newspaper",
            "type":"Services"
        },
        {
            "category":"Wholesale",
            "subcategory":"Books, Periodicals, & Newspapers",
            "type":"Manufacturing & Wholesale Goods"
        }
    ],
    "sg:phone":"+1 262 781 4672",
    "sg:postcode":"53007",
    "sg:province":"WI",
    "sg:tags":[
        "dealers-wholesale",
        "print",
        "news"
    ],
    "sg:website":"http://www.coffeenewsusa.com",
    "wof:name":"Coffee News",
    "wof:placetype":"venue"
},
  "geometry": {"coordinates":[-88.069644,43.104778],"type":"Point"}
}