{
  "type": "Feature",
  "properties": {
    "iso:country":"US",
    "sg:address":"9418 W Schlinger Ave",
    "sg:city":"West Allis",
    "sg:classifiers":[
        {
            "category":"Building & Trades",
            "subcategory":"Electrical",
            "type":"Services"
        }
    ],
    "sg:phone":"+1 414 771 1344",
    "sg:postcode":"53214",
    "sg:province":"WI",
    "sg:tags":[
        "electric",
        "contractor"
    ],
    "wof:name":"Action Electrical Svc",
    "wof:placetype":"venue"
},
  "geometry": {"coordinates":[-88.03092100000001,43.023851],"type":"Point"}
}