{
  "type": "Feature",
  "properties": {
    "iso:country":"US",
    "sg:address":"245 Horizon Dr",
    "sg:city":"Verona",
    "sg:classifiers":[
        {
            "category":"Professional",
            "subcategory":"Management & Consulting",
            "type":"Services"
        }
    ],
    "sg:phone":"+1 608 848 2995",
    "sg:postcode":"53593",
    "sg:province":"WI",
    "sg:tags":[
        "consultant",
        "business"
    ],
    "wof:name":"Great Lakes Management Group",
    "wof:placetype":"venue"
},
  "geometry": {"coordinates":[-89.525648,42.99552],"type":"Point"}
}