{
  "type": "Feature",
  "properties": {
    "iso:country":"US",
    "sg:address":"412 Mill Rd",
    "sg:city":"Kiel",
    "sg:classifiers":[
        {
            "category":"Retail",
            "subcategory":"Laundry & Dry Cleaning",
            "type":"Services"
        },
        {
            "category":"Building & Trades",
            "subcategory":"Construction",
            "type":"Services"
        }
    ],
    "sg:phone":"+1 920 894 2173",
    "sg:postcode":"53042",
    "sg:province":"WI",
    "sg:tags":[
        "upholstery",
        "painter",
        "carpet"
    ],
    "wof:name":"Crown Services Inc",
    "wof:placetype":"venue"
},
  "geometry": {"coordinates":[-88.027523,43.910685],"type":"Point"}
}