{
  "type": "Feature",
  "properties": {
    "iso:country":"US",
    "sg:address":"2487 Morgan Ln",
    "sg:city":"Green Bay",
    "sg:classifiers":[
        {
            "category":"Professional",
            "subcategory":"Business Services",
            "type":"Services"
        }
    ],
    "sg:phone":"+1 920 468 4469",
    "sg:postcode":"54311",
    "sg:province":"WI",
    "wof:name":"Tag A Long",
    "wof:placetype":"venue"
},
  "geometry": {"coordinates":[-87.961114,44.478213],"type":"Point"}
}