{
  "type": "Feature",
  "properties": {
    "iso:country":"US",
    "sg:address":"1875 Hollyhock Ln",
    "sg:city":"Elm Grove",
    "sg:classifiers":[
        {
            "category":"Shopping",
            "subcategory":"Gifts & Souvenirs",
            "type":"Retail Goods"
        }
    ],
    "sg:phone":"+1 262 786 3338",
    "sg:postcode":"53122",
    "sg:province":"WI",
    "sg:tags":[
        "party",
        "supply"
    ],
    "wof:name":"Milwaukee Christmas Parade",
    "wof:placetype":"venue"
},
  "geometry": {"coordinates":[-88.081576,43.055944],"type":"Point"}
}