{
  "type": "Feature",
  "properties": {
    "iso:country":"US",
    "sg:address":"11715 Kraut Rd",
    "sg:city":"Franksville",
    "sg:classifiers":[
        {
            "category":"Manufacturing",
            "subcategory":"Apparel",
            "type":"Manufacturing & Wholesale Goods"
        }
    ],
    "sg:phone":"+1 262 884 2080",
    "sg:postcode":"53126",
    "sg:province":"WI",
    "sg:tags":[
        "flag",
        "banner"
    ],
    "wof:name":"Beardsley Flag Pole Co",
    "wof:placetype":"venue"
},
  "geometry": {"coordinates":[-87.924216,42.751777],"type":"Point"}
}