{
  "type": "Feature",
  "properties": {
    "iso:country":"US",
    "sg:address":"405 Collins St",
    "sg:city":"Plymouth",
    "sg:classifiers":[
        {
            "category":"Shopping",
            "subcategory":"Gifts & Souvenirs",
            "type":"Retail Goods"
        }
    ],
    "sg:phone":"+1 920 892 6228",
    "sg:postcode":"53073",
    "sg:province":"WI",
    "wof:name":"Mullet River Mercantile LLC",
    "wof:placetype":"venue"
},
  "geometry": {"coordinates":[-87.976344,43.745673],"type":"Point"}
}