{
  "type": "Feature",
  "properties": {
    "addr:full":"1124 W Cecil St Neenah WI 54956",
    "addr:housenumber":"1124",
    "addr:postcode":"54956",
    "addr:street":"W Cecil St",
    "iso:country":"US",
    "sg:address":"1124 W Cecil St",
    "sg:city":"Neenah",
    "sg:classifiers":[
        {
            "category":"Building & Trades",
            "subcategory":"Construction",
            "type":"Services"
        }
    ],
    "sg:phone":"+1 920 722 5832",
    "sg:postcode":"54956",
    "sg:province":"WI",
    "sg:tags":[
        "painter"
    ],
    "wof:name":"Doug's Painting",
    "wof:placetype":"venue"
},
  "geometry": {"coordinates":[-88.49512900000001,44.170882],"type":"Point"}
}