{
  "type": "Feature",
  "properties": {
    "iso:country":"US",
    "sg:address":"1006 N University Ave",
    "sg:city":"Beaver Dam",
    "sg:classifiers":[
        {
            "category":"Personal",
            "subcategory":"Beauty Salon",
            "type":"Services"
        }
    ],
    "sg:phone":"+1 920 885 3556",
    "sg:postcode":"53916",
    "sg:province":"WI",
    "wof:name":"Sweetman's Barber & Beauty",
    "wof:placetype":"venue"
},
  "geometry": {"coordinates":[-88.829651,43.46699],"type":"Point"}
}