{
  "type": "Feature",
  "properties": {
    "iso:country":"US",
    "sg:address":"310 Tiffany Valley Rd",
    "sg:city":"Nelson",
    "sg:classifiers":[
        {
            "category":"Freight",
            "type":"Transportation"
        }
    ],
    "sg:phone":"+1 715 672 8674",
    "sg:postcode":"54756",
    "sg:province":"WI",
    "sg:tags":[
        "operator",
        "local",
        "trucking"
    ],
    "wof:name":"Poeschel Trucking LLC",
    "wof:placetype":"venue"
},
  "geometry": {"coordinates":[-91.840908,44.551683],"type":"Point"}
}