{
  "type": "Feature",
  "properties": {
    "iso:country":"US",
    "sg:address":"2458 Pennsylvania Ave",
    "sg:city":"Madison",
    "sg:classifiers":[
        {
            "category":"Local Transit",
            "type":"Transportation"
        }
    ],
    "sg:phone":"+1 608 242 2000",
    "sg:postcode":"53704",
    "sg:province":"WI",
    "sg:tags":[
        "airport"
    ],
    "sg:website":"www.unioncab.com",
    "wof:name":"Union Cab Of Madison Co-Op",
    "wof:placetype":"venue"
},
  "geometry": {"coordinates":[-89.358108,43.105946],"type":"Point"}
}