{
  "type": "Feature",
  "properties": {
    "addr:full":"942 E Dayton St Madison WI 53703",
    "addr:housenumber":"942",
    "addr:postcode":"53703",
    "addr:street":"E Dayton St",
    "iso:country":"US",
    "sg:address":"942 E Dayton St",
    "sg:city":"Madison",
    "sg:classifiers":[
        {
            "category":"Banks & Credit Unions",
            "subcategory":"Financial Services",
            "type":"Services"
        }
    ],
    "sg:phone":"+1 608 255 7902",
    "sg:postcode":"53703",
    "sg:province":"WI",
    "sg:tags":[
        "investor"
    ],
    "wof:name":"Adventure Investments Company",
    "wof:placetype":"venue"
},
  "geometry": {"coordinates":[-89.374267,43.084571],"type":"Point"}
}