{
  "type": "Feature",
  "properties": {
    "iso:country":"US",
    "sg:address":"410 W Verona Ave",
    "sg:city":"Verona",
    "sg:classifiers":[
        {
            "category":"Bars & Pubs",
            "type":"Food & Drink"
        }
    ],
    "sg:phone":"+1 608 845 6471",
    "sg:postcode":"53593",
    "sg:province":"WI",
    "sg:tags":[
        "drinking",
        "eating"
    ],
    "wof:name":"Cozee Inn",
    "wof:placetype":"venue"
},
  "geometry": {"coordinates":[-89.54019,42.989318],"type":"Point"}
}