{
  "type": "Feature",
  "properties": {
    "iso:country":"US",
    "sg:address":"777 S Military Rd",
    "sg:city":"Fond Du Lac",
    "sg:classifiers":[
        {
            "category":"Retail",
            "subcategory":"Auto Repair",
            "type":"Services"
        }
    ],
    "sg:phone":"+1 920 926 1444",
    "sg:postcode":"54935",
    "sg:province":"WI",
    "sg:tags":[
        "repairing",
        "automobile",
        "general"
    ],
    "wof:name":"Best Deal Automotive Truck",
    "wof:placetype":"venue"
},
  "geometry": {"coordinates":[-88.47023,43.761498],"type":"Point"}
}