{
  "type": "Feature",
  "properties": {
    "iso:country":"US",
    "sg:address":"8292 Co Rd Pf",
    "sg:city":"Sauk City",
    "sg:classifiers":[
        {
            "category":"Farming",
            "subcategory":"Dairy Farm",
            "type":"Manufacturing & Wholesale Goods"
        }
    ],
    "sg:phone":"+1 608 544 3152",
    "sg:postcode":"53583",
    "sg:province":"WI",
    "wof:name":"Enge Farms Inc",
    "wof:placetype":"venue"
},
  "geometry": {"coordinates":[-89.96899,43.351317],"type":"Point"}
}