{
  "type": "Feature",
  "properties": {
    "iso:country":"US",
    "sg:address":"310 N Olk St",
    "sg:city":"Hortonville",
    "sg:classifiers":[
        {
            "category":"Insurance",
            "subcategory":"Insurance Agent",
            "type":"Services"
        }
    ],
    "sg:phone":"+1 920 779 4515",
    "sg:postcode":"54944",
    "sg:province":"WI",
    "wof:name":"Ellington Mutual Insurance Co",
    "wof:placetype":"venue"
},
  "geometry": {"coordinates":[-88.635462,44.339262],"type":"Point"}
}