{
  "type": "Feature",
  "properties": {
    "iso:country":"US",
    "sg:address":"115 E Webster St",
    "sg:city":"Cuba City",
    "sg:classifiers":[
        {
            "category":"Social Services",
            "subcategory":"Job Training",
            "type":"Services"
        }
    ],
    "sg:phone":"+1 608 744 7355",
    "sg:postcode":"53807",
    "sg:province":"WI",
    "wof:name":"Mazzuchelli Citizens Inc",
    "wof:placetype":"venue"
},
  "geometry": {"coordinates":[-90.43069800000001,42.60551],"type":"Point"}
}