{
  "type": "Feature",
  "properties": {
    "addr:full":"115 E Webster St Cuba City WI 53807",
    "addr:housenumber":"115",
    "addr:postcode":"53807",
    "addr:street":"E Webster St",
    "iso:country":"US",
    "sg:address":"115 E Webster St",
    "sg:city":"Cuba City",
    "sg:classifiers":[
        {
            "category":"Social Services",
            "subcategory":"Job Training",
            "type":"Services"
        }
    ],
    "sg:phone":"+1 608 744 7355",
    "sg:postcode":"53807",
    "sg:province":"WI",
    "wof:name":"Mazzuchelli Citizens Inc",
    "wof:placetype":"venue"
},
  "geometry": {"coordinates":[-90.43069800000001,42.60551],"type":"Point"}
}