{
  "type": "Feature",
  "properties": {
    "addr:full":"329 S Judge Dr Saukville WI 53080",
    "addr:housenumber":"329",
    "addr:postcode":"53080",
    "addr:street":"S Judge Dr",
    "iso:country":"US",
    "sg:address":"329 S Judge Dr",
    "sg:city":"Saukville",
    "sg:classifiers":[
        {
            "category":"Professional",
            "subcategory":"Art Services",
            "type":"Services"
        }
    ],
    "sg:phone":"+1 262 284 5540",
    "sg:postcode":"53080",
    "sg:province":"WI",
    "sg:tags":[
        "graphic",
        "design"
    ],
    "wof:name":"Md2 Marketing Design",
    "wof:placetype":"venue"
},
  "geometry": {"coordinates":[-87.953594,43.377079],"type":"Point"}
}