{
  "type": "Feature",
  "properties": {
    "iso:country":"US",
    "sg:address":"510 E Arnold St",
    "sg:city":"Marshfield",
    "sg:classifiers":[
        {
            "category":"Building & Trades",
            "subcategory":"Construction",
            "type":"Services"
        }
    ],
    "sg:phone":"+1 715 384 3979",
    "sg:postcode":"54449",
    "sg:province":"WI",
    "sg:tags":[
        "excavating",
        "rental",
        "contractor"
    ],
    "wof:name":"Able Construction",
    "wof:placetype":"venue"
},
  "geometry": {"coordinates":[-90.166759,44.666652],"type":"Point"}
}