{
  "type": "Feature",
  "properties": {
    "iso:country":"US",
    "sg:address":"2985 Triverton Pike Dr",
    "sg:city":"Fitchburg",
    "sg:classifiers":[
        {
            "category":"Building & Trades",
            "subcategory":"Construction",
            "type":"Services"
        }
    ],
    "sg:phone":"+1 608 276 5228",
    "sg:postcode":"53711",
    "sg:province":"WI",
    "sg:tags":[
        "house",
        "contractor",
        "residential"
    ],
    "wof:name":"Village Homes LLC",
    "wof:placetype":"venue"
},
  "geometry": {"coordinates":[-89.429852,43.017741],"type":"Point"}
}