{
  "type": "Feature",
  "properties": {
    "iso:country":"US",
    "sg:address":"501 Nathan Ln",
    "sg:city":"Elkhorn",
    "sg:phone":"+1 262 723 5900",
    "sg:postcode":"53121",
    "sg:province":"WI",
    "sg:tags":[
        "equipment",
        "commercial",
        "supply"
    ],
    "wof:name":"Stafford-Smith Inc",
    "wof:placetype":"venue"
},
  "geometry": {"coordinates":[-88.54541999999999,42.661193],"type":"Point"}
}