{
  "type": "Feature",
  "properties": {
    "iso:country":"US",
    "sg:address":"8578 N Deerfoot Rd",
    "sg:city":"Hayward",
    "sg:classifiers":[
        {
            "category":"Autos & Motor Vehicles",
            "subcategory":"Boat Sales",
            "type":"Retail Goods"
        }
    ],
    "sg:phone":"+1 715 462 3086",
    "sg:postcode":"54843",
    "sg:province":"WI",
    "sg:tags":[
        "outboard"
    ],
    "wof:name":"All Mechanical Svc",
    "wof:placetype":"venue"
},
  "geometry": {"coordinates":[-91.149075,45.945657],"type":"Point"}
}