{
  "type": "Feature",
  "properties": {
    "iso:country":"US",
    "sg:address":"2727 S 27th St",
    "sg:city":"Milwaukee",
    "sg:classifiers":[
        {
            "category":"Retail",
            "subcategory":"Auto Repair",
            "type":"Services"
        }
    ],
    "sg:phone":"+1 414 645 7000",
    "sg:postcode":"53215",
    "sg:province":"WI",
    "sg:tags":[
        "transmission"
    ],
    "sg:website":"www.enginetrans.com",
    "wof:name":"Engine & Transmission Exchange",
    "wof:placetype":"venue"
},
  "geometry": {"coordinates":[-87.948332,42.994342],"type":"Point"}
}