{
  "type": "Feature",
  "properties": {
    "iso:country":"US",
    "sg:address":"300 Wrigley Dr",
    "sg:city":"Lake Geneva",
    "sg:classifiers":[
        {
            "category":"Travel",
            "subcategory":"Hotels & Motels",
            "type":"Entertainment"
        }
    ],
    "sg:phone":"+1 262 248 9182",
    "sg:postcode":"53147",
    "sg:province":"WI",
    "sg:tags":[
        "operation",
        "eating"
    ],
    "sg:website":"www.bestwestern.com",
    "wof:name":"Best Western Inn",
    "wof:placetype":"venue"
},
  "geometry": {"coordinates":[-88.43350700000001,42.588739],"type":"Point"}
}