{
  "type": "Feature",
  "properties": {
    "iso:country":"US",
    "sg:address":"1270 State Hwy 86",
    "sg:city":"Brantwood",
    "sg:classifiers":[
        {
            "category":"Government",
            "subcategory":"Office",
            "type":"Public Place"
        }
    ],
    "sg:phone":"+1 715 564 3240",
    "sg:postcode":"54513",
    "sg:province":"WI",
    "sg:tags":[
        "legislative",
        "body"
    ],
    "wof:name":"Spirit Town Hall",
    "wof:placetype":"venue"
},
  "geometry": {"coordinates":[-90.101849,45.454086],"type":"Point"}
}