{
  "type": "Feature",
  "properties": {
    "iso:country":"US",
    "sg:address":"1053 Co Rd A",
    "sg:city":"Dorchester",
    "sg:classifiers":[
        {
            "category":"Farming",
            "subcategory":"Dairy Farm",
            "type":"Manufacturing & Wholesale Goods"
        }
    ],
    "sg:phone":"+1 715 654 5385",
    "sg:postcode":"54425",
    "sg:province":"WI",
    "sg:tags":[
        "field",
        "corn",
        "grain",
        "cash",
        "crop"
    ],
    "wof:name":"Tom Peissig",
    "wof:placetype":"venue"
},
  "geometry": {"coordinates":[-90.362798,45.002848],"type":"Point"}
}