{
  "type": "Feature",
  "properties": {
    "iso:country":"US",
    "sg:address":"947 Burnwyck Dr",
    "sg:city":"Janesville",
    "sg:classifiers":[
        {
            "category":"Manufacturing",
            "subcategory":"Signs",
            "type":"Manufacturing & Wholesale Goods"
        },
        {
            "category":"Professional",
            "subcategory":"Advertising",
            "type":"Services"
        }
    ],
    "sg:phone":"+1 608 754 1317",
    "sg:postcode":"53546",
    "sg:province":"WI",
    "sg:tags":[
        "yard",
        "specialty",
        "mfg"
    ],
    "wof:name":"Special Moments Inc",
    "wof:placetype":"venue"
},
  "geometry": {"coordinates":[-88.957641,42.694637],"type":"Point"}
}