{
  "type": "Feature",
  "properties": {
    "addr:full":"5833 Koelpin Rd Oshkosh WI 54902",
    "addr:housenumber":"5833",
    "addr:postcode":"54902",
    "addr:street":"Koelpin Rd",
    "iso:country":"US",
    "sg:address":"5833 Koelpin Rd",
    "sg:city":"Oshkosh",
    "sg:classifiers":[
        {
            "category":"Building & Trades",
            "subcategory":"Construction",
            "type":"Services"
        }
    ],
    "sg:phone":"+1 920 426 9562",
    "sg:postcode":"54902",
    "sg:province":"WI",
    "sg:tags":[
        "home",
        "contractor",
        "improvement",
        "construct",
        "house"
    ],
    "wof:name":"Inside Out Construction L",
    "wof:placetype":"venue"
},
  "geometry": {"coordinates":[-88.493475,43.930453],"type":"Point"}
}