{
  "type": "Feature",
  "properties": {
    "iso:country":"US",
    "sg:address":"316 Steele St",
    "sg:city":"Algoma",
    "sg:classifiers":[
        {
            "category":"Organizations",
            "subcategory":"Religious Organization",
            "type":"Services"
        }
    ],
    "sg:phone":"+1 920 487 3906",
    "sg:postcode":"54201",
    "sg:province":"WI",
    "wof:name":"Lakeside Community Church",
    "wof:placetype":"venue"
},
  "geometry": {"coordinates":[-87.438409,44.608645],"type":"Point"}
}