{
  "type": "Feature",
  "properties": {
    "iso:country":"US",
    "sg:address":"305 S Lake Ave",
    "sg:city":"Phillips",
    "sg:classifiers":[
        {
            "category":"Organizations",
            "subcategory":"Professional Association",
            "type":"Services"
        }
    ],
    "sg:phone":"+1 715 339 4100",
    "sg:postcode":"54555",
    "sg:province":"WI",
    "sg:tags":[
        "chambers",
        "business",
        "commerce"
    ],
    "sg:website":"www.phillipswisconsin.org",
    "wof:name":"Phillips Area Chamber Commerce",
    "wof:placetype":"venue"
},
  "geometry": {"coordinates":[-90.391889,45.68577],"type":"Point"}
}