{
  "type": "Feature",
  "properties": {
    "iso:country":"US",
    "sg:address":"4770 Co Rd Z",
    "sg:city":"Dodgeville",
    "sg:classifiers":[
        {
            "category":"Retail",
            "subcategory":"Auto Repair",
            "type":"Services"
        }
    ],
    "sg:phone":"+1 608 935 0898",
    "sg:postcode":"53533",
    "sg:province":"WI",
    "sg:tags":[
        "body"
    ],
    "wof:name":"Greenwood Auto Body",
    "wof:placetype":"venue"
},
  "geometry": {"coordinates":[-90.073132,43.052318],"type":"Point"}
}