{
  "type": "Feature",
  "properties": {
    "iso:country":"US",
    "sg:address":"723 N Lake Rd",
    "sg:city":"Oconomowoc",
    "sg:classifiers":[
        {
            "category":"Wholesale",
            "subcategory":"Machinery & Supplies",
            "type":"Manufacturing & Wholesale Goods"
        }
    ],
    "sg:phone":"+1 262 567 4787",
    "sg:postcode":"53066",
    "sg:province":"WI",
    "sg:tags":[
        "equipment",
        "industrial"
    ],
    "wof:name":"Lakeside Recycling Systems",
    "wof:placetype":"venue"
},
  "geometry": {"coordinates":[-88.499737,43.119564],"type":"Point"}
}