{
  "type": "Feature",
  "properties": {
    "iso:country":"US",
    "sg:address":"13784 Lund Ln",
    "sg:city":"Mountain",
    "sg:classifiers":[
        {
            "category":"Bars & Pubs",
            "type":"Food & Drink"
        }
    ],
    "sg:phone":"+1 715 276 7852",
    "sg:postcode":"54149",
    "sg:province":"WI",
    "sg:tags":[
        "drinking"
    ],
    "wof:name":"J TS 20/20",
    "wof:placetype":"venue"
},
  "geometry": {"coordinates":[-88.45083,45.181401],"type":"Point"}
}