{
  "type": "Feature",
  "properties": {
    "iso:country":"US",
    "sg:address":"1605 N Wisconsin St",
    "sg:city":"Port Washington",
    "sg:classifiers":[
        {
            "category":"Autos & Motor Vehicles",
            "subcategory":"Fuel & Gas Station",
            "type":"Retail Goods"
        }
    ],
    "sg:phone":"+1 262 284 2122",
    "sg:postcode":"53074",
    "sg:province":"WI",
    "sg:tags":[
        "station",
        "gasoline"
    ],
    "wof:name":"Quik Stop Shoppe",
    "wof:placetype":"venue"
},
  "geometry": {"coordinates":[-87.871799,43.406972],"type":"Point"}
}