{
  "type": "Feature",
  "properties": {
    "iso:country":"US",
    "sg:address":"5919 US Hwy 45",
    "sg:city":"Deerbrook",
    "sg:classifiers":[
        {
            "category":"Freight",
            "type":"Transportation"
        }
    ],
    "sg:phone":"+1 715 627 2713",
    "sg:postcode":"54424",
    "sg:province":"WI",
    "sg:tags":[
        "distance",
        "long",
        "trucking"
    ],
    "wof:name":"Leiterman Enterprises",
    "wof:placetype":"venue"
},
  "geometry": {"coordinates":[-89.150572,45.242438],"type":"Point"}
}