{
  "type": "Feature",
  "properties": {
    "iso:country":"US",
    "sg:address":"9352 State Hwy 16",
    "sg:city":"Onalaska",
    "sg:classifiers":[
        {
            "category":"Autos & Motor Vehicles",
            "subcategory":"Auto Supplies",
            "type":"Retail Goods"
        }
    ],
    "sg:phone":"+1 608 781 2244",
    "sg:postcode":"54650",
    "sg:province":"WI",
    "sg:tags":[
        "tire"
    ],
    "sg:website":"www.goodyear.com",
    "wof:name":"Goodyear Auto Svc Ctr",
    "wof:placetype":"venue"
},
  "geometry": {"coordinates":[-91.200254,43.868691],"type":"Point"}
}