{
  "type": "Feature",
  "properties": {
    "iso:country":"US",
    "sg:address":"4219 State Rd 175",
    "sg:city":"Slinger",
    "sg:classifiers":[
        {
            "category":"Building & Trades",
            "subcategory":"Cleaning & Sanitation",
            "type":"Services"
        }
    ],
    "sg:phone":"+1 262 644 8856",
    "sg:postcode":"53086",
    "sg:province":"WI",
    "sg:tags":[
        "maintenance"
    ],
    "wof:name":"A1 Chimney Service Wisconsin",
    "wof:placetype":"venue"
},
  "geometry": {"coordinates":[-88.300392,43.342626],"type":"Point"}
}