{
  "type": "Feature",
  "properties": {
    "addr:full":"5005 Odana Rd Madison WI 53711",
    "addr:housenumber":"5005",
    "addr:postcode":"53711",
    "addr:street":"Odana Rd",
    "iso:country":"US",
    "sg:address":"5005 Odana Rd",
    "sg:city":"Madison",
    "sg:classifiers":[
        {
            "category":"Organizations",
            "subcategory":"Community Association",
            "type":"Services"
        }
    ],
    "sg:phone":"+1 608 278 9573",
    "sg:postcode":"53711",
    "sg:province":"WI",
    "wof:name":"Pta Inc",
    "wof:placetype":"venue"
},
  "geometry": {"coordinates":[-89.46718,43.04995],"type":"Point"}
}