{
  "type": "Feature",
  "properties": {
    "addr:full":"500 Gebhardt Rd Black River Falls WI 54615",
    "addr:housenumber":"500",
    "addr:postcode":"54615",
    "addr:street":"Gebhardt Rd",
    "iso:country":"US",
    "sg:address":"500 Gebhardt Rd",
    "sg:city":"Black River Falls",
    "sg:classifiers":[
        {
            "category":"Freight",
            "type":"Transportation"
        }
    ],
    "sg:phone":"+1 715 284 5074",
    "sg:postcode":"54615",
    "sg:province":"WI",
    "sg:tags":[
        "operator",
        "local",
        "trucking"
    ],
    "wof:name":"T&L Trucking LLC",
    "wof:placetype":"venue"
},
  "geometry": {"coordinates":[-90.84218300000001,44.280181],"type":"Point"}
}