{
  "type": "Feature",
  "properties": {
    "iso:country":"US",
    "sg:address":"7621 Marshview Rd",
    "sg:city":"Verona",
    "sg:classifiers":[
        {
            "category":"Real Estate",
            "subcategory":"Developer",
            "type":"Services"
        }
    ],
    "sg:phone":"+1 608 845 8845",
    "sg:postcode":"53593",
    "sg:province":"WI",
    "wof:name":"River Land Aaj LLC",
    "wof:placetype":"venue"
},
  "geometry": {"coordinates":[-89.584868,42.981858],"type":"Point"}
}