{
  "type": "Feature",
  "properties": {
    "iso:country":"US",
    "sg:address":"605 Random Lake Rd",
    "sg:city":"Random Lake",
    "sg:classifiers":[
        {
            "category":"Education",
            "subcategory":"School",
            "type":"Public Place"
        }
    ],
    "sg:phone":"+1 920 994 9193",
    "sg:postcode":"53075",
    "sg:province":"WI",
    "sg:website":"www.randomlake.k12.wi.us",
    "wof:name":"Random Lake High School",
    "wof:placetype":"venue"
},
  "geometry": {"coordinates":[-87.970833,43.554301],"type":"Point"}
}