{
  "type": "Feature",
  "properties": {
    "iso:country":"US",
    "sg:address":"13018 Centerville Rd",
    "sg:city":"Cleveland",
    "sg:classifiers":[
        {
            "category":"Health Services",
            "subcategory":"Doctor",
            "type":"Services"
        }
    ],
    "sg:phone":"+1 920 693 3224",
    "sg:postcode":"53015",
    "sg:province":"WI",
    "sg:tags":[
        "medical"
    ],
    "wof:name":"James Pawlak Dr",
    "wof:placetype":"venue"
},
  "geometry": {"coordinates":[-87.731585,43.940426],"type":"Point"}
}