{
  "type": "Feature",
  "properties": {
    "addr:full":"31841 Squire Ct Waukesha WI 53189",
    "addr:housenumber":"31841",
    "addr:postcode":"53189",
    "addr:street":"Squire Ct",
    "iso:country":"US",
    "sg:address":"31841 Squire Ct",
    "sg:city":"Waukesha",
    "sg:classifiers":[
        {
            "category":"Real Estate",
            "subcategory":"Real Estate Operator",
            "type":"Services"
        }
    ],
    "sg:phone":"+1 262 968 5906",
    "sg:postcode":"53189",
    "sg:province":"WI",
    "sg:tags":[
        "building",
        "nonresidential"
    ],
    "wof:name":"Asl Properties",
    "wof:placetype":"venue"
},
  "geometry": {"coordinates":[-88.381322,42.986331],"type":"Point"}
}