{
  "type": "Feature",
  "properties": {
    "iso:country":"US",
    "sg:address":"735 Water St",
    "sg:city":"Sauk City",
    "sg:classifiers":[
        {
            "category":"Retail",
            "subcategory":"Laundry & Dry Cleaning",
            "type":"Services"
        }
    ],
    "sg:phone":"+1 608 643 6122",
    "sg:postcode":"53583",
    "sg:province":"WI",
    "sg:tags":[
        "drycleaning",
        "plant"
    ],
    "wof:name":"Twin City Cleaners",
    "wof:placetype":"venue"
},
  "geometry": {"coordinates":[-89.718092,43.283547],"type":"Point"}
}