{
  "type": "Feature",
  "properties": {
    "addr:full":"3341 N 9th St Milwaukee WI 53206",
    "addr:housenumber":"3341",
    "addr:postcode":"53206",
    "addr:street":"N 9Th St",
    "iso:country":"US",
    "sg:address":"3341 N 9th St",
    "sg:city":"Milwaukee",
    "sg:classifiers":[
        {
            "category":"Social Services",
            "subcategory":"Child Care",
            "type":"Services"
        }
    ],
    "sg:phone":"+1 414 431 1594",
    "sg:postcode":"53206",
    "sg:province":"WI",
    "wof:name":"A Present Help Family Child",
    "wof:placetype":"venue"
},
  "geometry": {"coordinates":[-87.922465,43.08109],"type":"Point"}
}