{
  "type": "Feature",
  "properties": {
    "iso:country":"US",
    "sg:address":"2300 S Galvin Ave",
    "sg:city":"Marshfield",
    "sg:classifiers":[
        {
            "category":"Government",
            "subcategory":"Office",
            "type":"Public Place"
        }
    ],
    "sg:phone":"+1 715 384 3444",
    "sg:postcode":"54449",
    "sg:province":"WI",
    "wof:name":"Wood County Highway Garage",
    "wof:placetype":"venue"
},
  "geometry": {"coordinates":[-90.14024499999999,44.641172],"type":"Point"}
}