{
  "type": "Feature",
  "properties": {
    "iso:country":"US",
    "sg:address":"151 S University Dr",
    "sg:city":"West Bend",
    "sg:classifiers":[
        {
            "category":"Manufacturing",
            "subcategory":"Retail Goods",
            "type":"Manufacturing & Wholesale Goods"
        }
    ],
    "sg:phone":"+1 262 334 5615",
    "sg:postcode":"53095",
    "sg:province":"WI",
    "sg:tags":[
        "notion",
        "mfg"
    ],
    "wof:name":"Turn Key Products Inc",
    "wof:placetype":"venue"
},
  "geometry": {"coordinates":[-88.211011,43.421962],"type":"Point"}
}