{
  "type": "Feature",
  "properties": {
    "addr:full":"551 Ramsey Rd Arlington WI 53911",
    "addr:housenumber":"551",
    "addr:postcode":"53911",
    "addr:street":"Ramsey Rd",
    "iso:country":"US",
    "sg:address":"551 Ramsey Rd",
    "sg:city":"Arlington",
    "sg:classifiers":[
        {
            "category":"Food & Beverages",
            "subcategory":"Bakery",
            "type":"Retail Goods"
        }
    ],
    "sg:phone":"+1 608 846 5186",
    "sg:postcode":"53911",
    "sg:province":"WI",
    "sg:tags":[
        "baker"
    ],
    "wof:name":"I Do Cakes By Betty",
    "wof:placetype":"venue"
},
  "geometry": {"coordinates":[-89.363232,43.294214],"type":"Point"}
}