{
  "type": "Feature",
  "properties": {
    "iso:country":"US",
    "sg:address":"45 N Crestway Ct",
    "sg:city":"Appleton",
    "sg:classifiers":[
        {
            "category":"Shopping",
            "subcategory":"Clothing, Apparel, & Fashions",
            "type":"Retail Goods"
        }
    ],
    "sg:phone":"+1 920 733 1896",
    "sg:postcode":"54913",
    "sg:province":"WI",
    "wof:name":"Fashion Image Consultants LLC",
    "wof:placetype":"venue"
},
  "geometry": {"coordinates":[-88.38666000000001,44.32251],"type":"Point"}
}