{
  "type": "Feature",
  "properties": {
    "iso:country":"US",
    "sg:address":"2056 190th Ave",
    "sg:city":"Centuria",
    "sg:classifiers":[
        {
            "category":"Farming",
            "subcategory":"Dairy Farm",
            "type":"Manufacturing & Wholesale Goods"
        }
    ],
    "sg:phone":"+1 715 646 2504",
    "sg:postcode":"54824",
    "sg:province":"WI",
    "wof:name":"Brian Matson",
    "wof:placetype":"venue"
},
  "geometry": {"coordinates":[-92.58797199999999,45.483348],"type":"Point"}
}