{
  "type": "Feature",
  "properties": {
    "iso:country":"US",
    "sg:address":"4495 State Hwy 55",
    "sg:city":"White Lake",
    "sg:classifiers":[
        {
            "category":"Food & Beverages",
            "subcategory":"Groceries & Convenience Stores",
            "type":"Retail Goods"
        },
        {
            "category":"Restaurant",
            "type":"Food & Drink"
        }
    ],
    "sg:phone":"+1 715 882 8304",
    "sg:postcode":"54491",
    "sg:province":"WI",
    "sg:tags":[
        "shop",
        "beauty"
    ],
    "wof:name":"Bob & Joni's",
    "wof:placetype":"venue"
},
  "geometry": {"coordinates":[-88.732016,45.188651],"type":"Point"}
}