{
  "type": "Feature",
  "properties": {
    "iso:country":"US",
    "sg:address":"3304 Bay Settlement Rd",
    "sg:city":"Green Bay",
    "sg:classifiers":[
        {
            "category":"Building & Trades",
            "subcategory":"Construction",
            "type":"Services"
        }
    ],
    "sg:phone":"+1 920 468 6095",
    "sg:postcode":"54311",
    "sg:province":"WI",
    "sg:tags":[
        "hanging",
        "contractor"
    ],
    "wof:name":"Pablos Painting & Associates",
    "wof:placetype":"venue"
},
  "geometry": {"coordinates":[-87.88163900000001,44.566793],"type":"Point"}
}