{
  "type": "Feature",
  "properties": {
    "iso:country":"US",
    "sg:address":"18259 Co Rd G",
    "sg:city":"Muscoda",
    "sg:classifiers":[
        {
            "category":"Farming",
            "subcategory":"Farm",
            "type":"Manufacturing & Wholesale Goods"
        }
    ],
    "sg:phone":"+1 608 739 4086",
    "sg:postcode":"53573",
    "sg:province":"WI",
    "sg:tags":[
        "crop",
        "general"
    ],
    "wof:name":"Elton Zimmerman",
    "wof:placetype":"venue"
},
  "geometry": {"coordinates":[-90.484201,43.163016],"type":"Point"}
}