{
  "type": "Feature",
  "properties": {
    "addr:full":"150 N Sunnyslope Rd Brookfield WI 53005",
    "addr:housenumber":"150",
    "addr:postcode":"53005",
    "addr:street":"N Sunnyslope Rd",
    "iso:country":"US",
    "sg:address":"150 N Sunnyslope Rd",
    "sg:city":"Brookfield",
    "sg:classifiers":[
        {
            "category":"Health Services",
            "subcategory":"Health Practitioner",
            "type":"Services"
        }
    ],
    "sg:phone":"+1 262 432 5660",
    "sg:postcode":"53005",
    "sg:province":"WI",
    "sg:website":"www.wiautism.com",
    "wof:name":"Wisconsin Early Autism Project",
    "wof:placetype":"venue"
},
  "geometry": {"coordinates":[-88.086781,43.035053],"type":"Point"}
}