{
  "type": "Feature",
  "properties": {
    "iso:country":"US",
    "sg:address":"3705 W Drexel Ave",
    "sg:city":"Franklin",
    "sg:classifiers":[
        {
            "category":"Retail",
            "subcategory":"Laundry & Dry Cleaning",
            "type":"Services"
        },
        {
            "category":"Building & Trades",
            "subcategory":"Construction",
            "type":"Services"
        }
    ],
    "sg:phone":"+1 414 397 4071",
    "sg:postcode":"53132",
    "sg:province":"WI",
    "sg:tags":[
        "cleaners",
        "silt",
        "install",
        "fence"
    ],
    "wof:name":"Environcom",
    "wof:placetype":"venue"
},
  "geometry": {"coordinates":[-87.964129,42.901619],"type":"Point"}
}