{
  "type": "Feature",
  "properties": {
    "iso:country":"US",
    "sg:address":"604 W Riverside Ave",
    "sg:city":"Merrill",
    "sg:classifiers":[
        {
            "category":"Banks & Credit Unions",
            "subcategory":"Financial Services",
            "type":"Services"
        }
    ],
    "sg:phone":"+1 715 536 1385",
    "sg:postcode":"54452",
    "sg:province":"WI",
    "sg:tags":[
        "investor"
    ],
    "wof:name":"Timberlakes Investments LLC",
    "wof:placetype":"venue"
},
  "geometry": {"coordinates":[-89.708398,45.173158],"type":"Point"}
}