{
  "type": "Feature",
  "properties": {
    "addr:full":"500 N Chestnut St Green Bay WI 54303",
    "addr:housenumber":"500",
    "addr:postcode":"54303",
    "addr:street":"N Chestnut St",
    "iso:country":"US",
    "sg:address":"500 N Chestnut St",
    "sg:city":"Green Bay",
    "sg:classifiers":[
        {
            "category":"Professional",
            "subcategory":"Accounting & Tax Preparation",
            "type":"Services"
        }
    ],
    "sg:phone":"+1 920 432 8667",
    "sg:postcode":"54303",
    "sg:province":"WI",
    "sg:tags":[
        "return",
        "filing"
    ],
    "wof:name":"Schley Tax Svc",
    "wof:placetype":"venue"
},
  "geometry": {"coordinates":[-88.018463,44.523454],"type":"Point"}
}