{
  "type": "Feature",
  "properties": {
    "iso:country":"US",
    "sg:address":"2488 Woodland Rd",
    "sg:city":"Woodland",
    "sg:classifiers":[
        {
            "category":"Building & Trades",
            "subcategory":"Construction",
            "type":"Services"
        }
    ],
    "sg:phone":"+1 920 625 3122",
    "sg:postcode":"53085",
    "sg:province":"WI",
    "sg:tags":[
        "resurfacing",
        "laying",
        "refinishing",
        "floor"
    ],
    "wof:name":"B & B Wood Floor Refinishing",
    "wof:placetype":"venue"
},
  "geometry": {"coordinates":[-87.819643,43.776244],"type":"Point"}
}