{
  "type": "Feature",
  "properties": {
    "iso:country":"US",
    "sg:address":"338 Main St",
    "sg:city":"Racine",
    "sg:classifiers":[
        {
            "category":"Professional",
            "subcategory":"Art Services",
            "type":"Services"
        }
    ],
    "sg:phone":"+1 262 637 2233",
    "sg:postcode":"53403",
    "sg:province":"WI",
    "sg:tags":[
        "graphic",
        "design"
    ],
    "sg:website":"www.design-partners.com",
    "wof:name":"Design Partners Inc",
    "wof:placetype":"venue"
},
  "geometry": {"coordinates":[-87.783415,42.729831],"type":"Point"}
}