{
  "type": "Feature",
  "properties": {
    "iso:country":"US",
    "sg:address":"1439 Regent St",
    "sg:city":"Madison",
    "sg:classifiers":[
        {
            "category":"Restaurant",
            "type":"Food & Drink"
        }
    ],
    "sg:phone":"+1 608 255 1313",
    "sg:postcode":"53711",
    "sg:province":"WI",
    "sg:website":"www.foodspot.com/sukhothai",
    "wof:name":"Sukhothai Restaurant",
    "wof:placetype":"venue"
},
  "geometry": {"coordinates":[-89.40975400000001,43.067687],"type":"Point"}
}