{
  "type": "Feature",
  "properties": {
    "iso:country":"US",
    "sg:address":"3933 Czech Dr",
    "sg:city":"Redgranite",
    "sg:classifiers":[
        {
            "category":"Building & Trades",
            "subcategory":"Construction",
            "type":"Services"
        }
    ],
    "sg:phone":"+1 920 361 2946",
    "sg:postcode":"54970",
    "sg:province":"WI",
    "sg:tags":[
        "carpentry",
        "contractor"
    ],
    "wof:name":"Sergo Construction LLC",
    "wof:placetype":"venue"
},
  "geometry": {"coordinates":[-89.072636,43.990316],"type":"Point"}
}