{
  "type": "Feature",
  "properties": {
    "iso:country":"US",
    "sg:address":"1339 Spaight St",
    "sg:city":"Madison",
    "sg:classifiers":[
        {
            "category":"Professional",
            "subcategory":"Management & Consulting",
            "type":"Services"
        }
    ],
    "sg:phone":"+1 608 255 6680",
    "sg:postcode":"53703",
    "sg:province":"WI",
    "sg:tags":[
        "energy",
        "consultation"
    ],
    "wof:name":"Cain Consulting and Services",
    "wof:placetype":"venue"
},
  "geometry": {"coordinates":[-89.359657,43.083917],"type":"Point"}
}