{
  "type": "Feature",
  "properties": {
    "iso:country":"US",
    "sg:address":"6411 Mineral Point Rd",
    "sg:city":"Madison",
    "sg:classifiers":[
        {
            "category":"Real Estate",
            "subcategory":"Architect",
            "type":"Services"
        }
    ],
    "sg:phone":"+1 608 276 9200",
    "sg:postcode":"53705",
    "sg:province":"WI",
    "sg:tags":[
        "design"
    ],
    "sg:website":"www.strang-inc.com",
    "wof:name":"Strang Inc",
    "wof:placetype":"venue"
},
  "geometry": {"coordinates":[-89.48942,43.060734],"type":"Point"}
}