{
  "type": "Feature",
  "properties": {
    "iso:country":"US",
    "sg:address":"105 N Water St",
    "sg:city":"Milwaukee",
    "sg:classifiers":[
        {
            "category":"Professional",
            "subcategory":"Engineering",
            "type":"Services"
        }
    ],
    "sg:phone":"+1 414 615 2300",
    "sg:postcode":"53202",
    "sg:province":"WI",
    "sg:tags":[
        "engineer"
    ],
    "wof:name":"Michael A Corrigan PE",
    "wof:placetype":"venue"
},
  "geometry": {"coordinates":[-87.909577,43.031781],"type":"Point"}
}