{
  "type": "Feature",
  "properties": {
    "iso:country":"US",
    "sg:address":"158 Fontana Blvd",
    "sg:city":"Fontana",
    "sg:classifiers":[
        {
            "category":"Restaurant",
            "type":"Food & Drink"
        }
    ],
    "sg:phone":"+1 262 275 6330",
    "sg:postcode":"53125",
    "sg:province":"WI",
    "sg:tags":[
        "eating"
    ],
    "wof:name":"Concert Master Chef Services",
    "wof:placetype":"venue"
},
  "geometry": {"coordinates":[-88.577592,42.549139],"type":"Point"}
}