{
  "type": "Feature",
  "properties": {
    "addr:full":"1214 Joliet St Janesville WI 53546",
    "addr:housenumber":"1214",
    "addr:postcode":"53546",
    "addr:street":"Joliet St",
    "iso:country":"US",
    "sg:address":"1214 Joliet St",
    "sg:city":"Janesville",
    "sg:classifiers":[
        {
            "category":"Organizations",
            "subcategory":"Religious Organization",
            "type":"Services"
        }
    ],
    "sg:phone":"+1 608 755 0434",
    "sg:postcode":"53546",
    "sg:province":"WI",
    "sg:tags":[
        "church"
    ],
    "wof:name":"Faith Bible Church",
    "wof:placetype":"venue"
},
  "geometry": {"coordinates":[-89.03536200000001,42.657148],"type":"Point"}
}