{
  "type": "Feature",
  "properties": {
    "iso:country":"US",
    "sg:address":"3360 N 49th St",
    "sg:city":"Milwaukee",
    "sg:classifiers":[
        {
            "category":"Retail",
            "subcategory":"Auto Repair",
            "type":"Services"
        }
    ],
    "sg:phone":"+1 414 445 2096",
    "sg:postcode":"53216",
    "sg:province":"WI",
    "sg:tags":[
        "transmission"
    ],
    "wof:name":"Ortiz Trans Svc",
    "wof:placetype":"venue"
},
  "geometry": {"coordinates":[-87.974716,43.079955],"type":"Point"}
}