{
  "type": "Feature",
  "properties": {
    "addr:full":"8909 Danish Settlement Rd Phillips WI 54555",
    "addr:postcode":"8909;54555",
    "addr:street":"Danish Settlement Rd",
    "iso:country":"US",
    "sg:address":"8909 Danish Settlement Rd",
    "sg:city":"Phillips",
    "sg:classifiers":[
        {
            "category":"Farming",
            "subcategory":"Dairy Farm",
            "type":"Manufacturing & Wholesale Goods"
        }
    ],
    "sg:phone":"+1 715 332 5518",
    "sg:postcode":"54555",
    "sg:province":"WI",
    "sg:tags":[
        "field",
        "crop"
    ],
    "wof:name":"Wilderness Springs",
    "wof:placetype":"venue"
},
  "geometry": {"coordinates":[-90.51943199999999,45.659854],"type":"Point"}
}