{
  "type": "Feature",
  "properties": {
    "addr:full":"8894 Snake Rd Elkhart Lake WI 53020",
    "addr:housenumber":"8894",
    "addr:postcode":"53020",
    "addr:street":"Snake Rd",
    "iso:country":"US",
    "sg:address":"8894 Snake Rd",
    "sg:city":"Elkhart Lake",
    "sg:classifiers":[
        {
            "category":"Farming",
            "subcategory":"Dairy Farm",
            "type":"Manufacturing & Wholesale Goods"
        }
    ],
    "sg:phone":"+1 920 876 3184",
    "sg:postcode":"53020",
    "sg:province":"WI",
    "wof:name":"Kuhn Farm",
    "wof:placetype":"venue"
},
  "geometry": {"coordinates":[-88.001992,43.861179],"type":"Point"}
}