{
  "type": "Feature",
  "properties": {
    "addr:full":"555 S Industrial Dr Hartland WI 53029",
    "addr:housenumber":"555",
    "addr:postcode":"53029",
    "addr:street":"S Industrial Dr",
    "iso:country":"US",
    "sg:address":"555 S Industrial Dr",
    "sg:city":"Hartland",
    "sg:classifiers":[
        {
            "category":"Utilities",
            "subcategory":"Natural Gas",
            "type":"Services"
        }
    ],
    "sg:phone":"+1 262 369 2750",
    "sg:postcode":"53029",
    "sg:province":"WI",
    "sg:tags":[
        "marketer"
    ],
    "wof:name":"Enron North America Corp",
    "wof:placetype":"venue"
},
  "geometry": {"coordinates":[-88.360084,43.096111],"type":"Point"}
}