{
  "type": "Feature",
  "properties": {
    "addr:full":"5076 Valley Rd Luxemburg WI 54217",
    "addr:housenumber":"5076",
    "addr:postcode":"54217",
    "addr:street":"Valley Rd",
    "iso:country":"US",
    "sg:address":"5076 Valley Rd",
    "sg:city":"Luxemburg",
    "sg:classifiers":[
        {
            "category":"Building & Trades",
            "subcategory":"Construction",
            "type":"Services"
        }
    ],
    "sg:phone":"+1 920 845 9409",
    "sg:postcode":"54217",
    "sg:province":"WI",
    "sg:tags":[
        "concrete",
        "contractor"
    ],
    "wof:name":"Badgerland Concrete",
    "wof:placetype":"venue"
},
  "geometry": {"coordinates":[-87.68385000000001,44.50992],"type":"Point"}
}