{
  "type": "Feature",
  "properties": {
    "iso:country":"US",
    "sg:address":"120 Evergreen Dr",
    "sg:city":"Delavan",
    "sg:classifiers":[
        {
            "category":"Professional",
            "subcategory":"Business Services",
            "type":"Services"
        }
    ],
    "sg:phone":"+1 262 728 2346",
    "sg:postcode":"53115",
    "sg:province":"WI",
    "wof:name":"Kmg Technologies",
    "wof:placetype":"venue"
},
  "geometry": {"coordinates":[-88.66700299999999,42.632475],"type":"Point"}
}