{
  "type": "Feature",
  "properties": {
    "iso:country":"US",
    "sg:address":"107 Louis St",
    "sg:city":"Prairie Du Chien",
    "sg:classifiers":[
        {
            "category":"Social Services",
            "type":"Services"
        }
    ],
    "sg:phone":"+1 608 326 2997",
    "sg:postcode":"53821",
    "sg:province":"WI",
    "wof:name":"Pratte Counseling Services",
    "wof:placetype":"venue"
},
  "geometry": {"coordinates":[-91.14656600000001,43.053094],"type":"Point"}
}