{
  "type": "Feature",
  "properties": {
    "iso:country":"US",
    "sg:address":"2193 Colladay Point Dr",
    "sg:city":"Stoughton",
    "sg:classifiers":[
        {
            "category":"Shopping",
            "type":"Retail Goods"
        }
    ],
    "sg:phone":"+1 608 873 8877",
    "sg:postcode":"53589",
    "sg:province":"WI",
    "sg:tags":[
        "mural"
    ],
    "wof:name":"Artful Lee",
    "wof:placetype":"venue"
},
  "geometry": {"coordinates":[-89.27746,42.964348],"type":"Point"}
}