{
  "type": "Feature",
  "properties": {
    "addr:full":"3918 S 18th St Sheboygan WI 53081",
    "addr:housenumber":"3918",
    "addr:postcode":"53081",
    "addr:street":"S 18Th St",
    "iso:country":"US",
    "sg:address":"3918 S 18th St",
    "sg:city":"Sheboygan",
    "sg:classifiers":[
        {
            "category":"Manufacturing",
            "subcategory":"Jewelry",
            "type":"Manufacturing & Wholesale Goods"
        }
    ],
    "sg:phone":"+1 262 723 6605",
    "sg:postcode":"53081",
    "sg:province":"WI",
    "sg:tags":[
        "costume",
        "mfg"
    ],
    "wof:name":"Gunyon Company Inc",
    "wof:placetype":"venue"
},
  "geometry": {"coordinates":[-87.729691,43.715049],"type":"Point"}
}