{
  "type": "Feature",
  "properties": {
    "addr:full":"5922 N 76th St Milwaukee WI 53218",
    "addr:housenumber":"5922",
    "addr:postcode":"53218",
    "addr:street":"N 76Th St",
    "iso:country":"US",
    "sg:address":"5922 N 76th St",
    "sg:city":"Milwaukee",
    "sg:classifiers":[
        {
            "category":"Personal",
            "subcategory":"Beauty Salon",
            "type":"Services"
        }
    ],
    "sg:phone":"+1 414 462 9899",
    "sg:postcode":"53218",
    "sg:province":"WI",
    "wof:name":"Mamas African Hair Braiding",
    "wof:placetype":"venue"
},
  "geometry": {"coordinates":[-88.005886,43.125563],"type":"Point"}
}