{
  "type": "Feature",
  "properties": {
    "iso:country":"US",
    "sg:address":"50 N Union Rd",
    "sg:city":"Evansville",
    "sg:classifiers":[
        {
            "category":"Restaurant",
            "type":"Food & Drink"
        }
    ],
    "sg:phone":"+1 608 882 2158",
    "sg:postcode":"53536",
    "sg:province":"WI",
    "wof:name":"Bubs Drive In",
    "wof:placetype":"venue"
},
  "geometry": {"coordinates":[-89.297458,42.784229],"type":"Point"}
}