{
  "type": "Feature",
  "properties": {
    "iso:country":"US",
    "sg:address":"200 W 6th St",
    "sg:city":"Necedah",
    "sg:classifiers":[
        {
            "category":"Government",
            "subcategory":"Office",
            "type":"Public Place"
        }
    ],
    "sg:phone":"+1 608 565 2391",
    "sg:postcode":"54646",
    "sg:province":"WI",
    "sg:tags":[
        "home",
        "golf",
        "site",
        "developer"
    ],
    "wof:name":"Oak Grove Golf Community",
    "wof:placetype":"venue"
},
  "geometry": {"coordinates":[-90.07005599999999,44.02014],"type":"Point"}
}