{
  "type": "Feature",
  "properties": {
    "iso:country":"US",
    "sg:address":"16945 Co Hwy Oo",
    "sg:city":"Chippewa Falls",
    "sg:classifiers":[
        {
            "category":"Building & Trades",
            "subcategory":"Construction",
            "type":"Services"
        }
    ],
    "sg:phone":"+1 715 828 6287",
    "sg:postcode":"54729",
    "sg:province":"WI",
    "sg:tags":[
        "general"
    ],
    "wof:name":"Adams Construction",
    "wof:placetype":"venue"
},
  "geometry": {"coordinates":[-91.329433,44.886211],"type":"Point"}
}