{
  "type": "Feature",
  "properties": {
    "iso:country":"US",
    "sg:address":"1234 S Tomahawk Ave",
    "sg:city":"Tomahawk",
    "sg:classifiers":[
        {
            "category":"Travel",
            "subcategory":"Hotels & Motels",
            "type":"Entertainment"
        }
    ],
    "sg:phone":"+1 715 453 6547",
    "sg:postcode":"54487",
    "sg:province":"WI",
    "sg:tags":[
        "operation"
    ],
    "wof:name":"Lake Mohawkson Cabin",
    "wof:placetype":"venue"
},
  "geometry": {"coordinates":[-89.733334,45.457201],"type":"Point"}
}