{
  "type": "Feature",
  "properties": {
    "iso:country":"US",
    "sg:address":"417 Henry St",
    "sg:city":"Mukwonago",
    "sg:classifiers":[
        {
            "category":"Health Services",
            "subcategory":"Clinic",
            "type":"Services"
        }
    ],
    "sg:phone":"+1 262 363 2423",
    "sg:postcode":"53149",
    "sg:province":"WI",
    "sg:tags":[
        "home",
        "care"
    ],
    "wof:name":"Home Advantage LLC",
    "wof:placetype":"venue"
},
  "geometry": {"coordinates":[-88.334447,42.861588],"type":"Point"}
}