{
  "type": "Feature",
  "properties": {
    "iso:country":"US",
    "sg:address":"451 Lisa Ct",
    "sg:city":"Oregon",
    "sg:classifiers":[
        {
            "category":"Professional",
            "subcategory":"Secretarial Services",
            "type":"Services"
        }
    ],
    "sg:phone":"+1 608 835 6568",
    "sg:postcode":"53575",
    "sg:province":"WI",
    "sg:tags":[
        "transcription",
        "medical"
    ],
    "wof:name":"Speed Scribe",
    "wof:placetype":"venue"
},
  "geometry": {"coordinates":[-89.391524,42.919292],"type":"Point"}
}