{
  "type": "Feature",
  "properties": {
    "iso:country":"US",
    "sg:address":"120 E Lake St",
    "sg:city":"Lake Mills",
    "sg:classifiers":[
        {
            "category":"Restaurant",
            "type":"Food & Drink"
        }
    ],
    "sg:phone":"+1 920 648 7874",
    "sg:postcode":"53551",
    "sg:province":"WI",
    "sg:tags":[
        "shop",
        "coffee"
    ],
    "wof:name":"Sweet Blessings LLC",
    "wof:placetype":"venue"
},
  "geometry": {"coordinates":[-88.912262,43.079666],"type":"Point"}
}