{
  "type": "Feature",
  "properties": {
    "addr:full":"1208 S Watertown St Waupun WI 53963",
    "addr:housenumber":"1208",
    "addr:postcode":"53963",
    "addr:street":"S Watertown St",
    "iso:country":"US",
    "sg:address":"1208 S Watertown St",
    "sg:city":"Waupun",
    "sg:classifiers":[
        {
            "category":"Health Services",
            "subcategory":"Health Practitioner",
            "type":"Services"
        }
    ],
    "sg:phone":"+1 920 324 4358",
    "sg:postcode":"53963",
    "sg:province":"WI",
    "sg:tags":[
        "psychologist"
    ],
    "wof:name":"Community Psychological Svc",
    "wof:placetype":"venue"
},
  "geometry": {"coordinates":[-88.72477000000001,43.616245],"type":"Point"}
}