{
  "type": "Feature",
  "properties": {
    "iso:country":"US",
    "sg:address":"5707 W Carlsville Rd",
    "sg:city":"Sturgeon Bay",
    "sg:classifiers":[
        {
            "category":"Building & Trades",
            "subcategory":"Construction",
            "type":"Services"
        }
    ],
    "sg:phone":"+1 920 746 0191",
    "sg:postcode":"54235",
    "sg:province":"WI",
    "sg:tags":[
        "contractor"
    ],
    "wof:name":"Schleicher Roofing & Cnstr",
    "wof:placetype":"venue"
},
  "geometry": {"coordinates":[-87.351856,44.951424],"type":"Point"}
}