{
  "type": "Feature",
  "properties": {
    "addr:full":"5885 White Clay Lake Dr Cecil WI 54111",
    "addr:housenumber":"5885",
    "addr:postcode":"54111",
    "addr:street":"White Clay Lake Dr",
    "iso:country":"US",
    "sg:address":"5885 White Clay Lake Dr",
    "sg:city":"Cecil",
    "sg:classifiers":[
        {
            "category":"Farming",
            "subcategory":"Dairy Farm",
            "type":"Manufacturing & Wholesale Goods"
        }
    ],
    "sg:phone":"+1 715 745 2842",
    "sg:postcode":"54111",
    "sg:province":"WI",
    "wof:name":"Wayne Manthei",
    "wof:placetype":"venue"
},
  "geometry": {"coordinates":[-88.386819,44.797759],"type":"Point"}
}