{
  "type": "Feature",
  "properties": {
    "iso:country":"US",
    "sg:address":"3988 Elaines Way",
    "sg:city":"Slinger",
    "sg:classifiers":[
        {
            "category":"Professional",
            "type":"Services"
        }
    ],
    "sg:phone":"+1 262 644 6708",
    "sg:postcode":"53086",
    "sg:province":"WI",
    "wof:name":"Sgro & Sons",
    "wof:placetype":"venue"
},
  "geometry": {"coordinates":[-88.30829300000001,43.334334],"type":"Point"}
}