{
  "type": "Feature",
  "properties": {
    "iso:country":"US",
    "sg:address":"720 Blackhawk Dr",
    "sg:city":"Fort Atkinson",
    "sg:classifiers":[
        {
            "category":"Professional",
            "subcategory":"Accounting & Tax Preparation",
            "type":"Services"
        }
    ],
    "sg:phone":"+1 920 568 0935",
    "sg:postcode":"53538",
    "sg:province":"WI",
    "wof:name":"John D Hershman",
    "wof:placetype":"venue"
},
  "geometry": {"coordinates":[-88.845839,42.942878],"type":"Point"}
}