{
  "type": "Feature",
  "properties": {
    "addr:full":"9130 W Loomis Rd Franklin WI 53132",
    "addr:housenumber":"9130",
    "addr:postcode":"53132",
    "addr:street":"W Loomis Rd",
    "iso:country":"US",
    "sg:address":"9130 W Loomis Rd",
    "sg:city":"Franklin",
    "sg:classifiers":[
        {
            "category":"Professional",
            "subcategory":"Printing & Photocopies",
            "type":"Services"
        },
        {
            "category":"Professional",
            "subcategory":"Credit Reporting & Collection",
            "type":"Services"
        }
    ],
    "sg:phone":"+1 414 427 5050",
    "sg:postcode":"53132",
    "sg:province":"WI",
    "sg:tags":[
        "plaque",
        "medal",
        "award",
        "trophies"
    ],
    "wof:name":"Logarakis Group Inc",
    "wof:placetype":"venue"
},
  "geometry": {"coordinates":[-88.029093,42.900724],"type":"Point"}
}