{
  "type": "Feature",
  "properties": {
    "addr:full":"6018 203rd Ave Bristol WI 53104",
    "addr:housenumber":"6018",
    "addr:postcode":"53104",
    "addr:street":"203Rd Ave",
    "iso:country":"US",
    "sg:address":"6018 203rd Ave",
    "sg:city":"Bristol",
    "sg:classifiers":[
        {
            "category":"Professional",
            "subcategory":"Business Services",
            "type":"Services"
        }
    ],
    "sg:phone":"+1 262 857 2422",
    "sg:postcode":"53104",
    "sg:province":"WI",
    "wof:name":"Wedgwood Interiors",
    "wof:placetype":"venue"
},
  "geometry": {"coordinates":[-88.053985,42.580815],"type":"Point"}
}