{
  "type": "Feature",
  "properties": {
    "iso:country":"US",
    "sg:address":"10555 N Port Washington Rd",
    "sg:city":"Thiensville",
    "sg:classifiers":[
        {
            "category":"Education",
            "subcategory":"Special Training",
            "type":"Public Place"
        }
    ],
    "sg:phone":"+1 262 240 2295",
    "sg:postcode":"53092",
    "sg:province":"WI",
    "sg:tags":[
        "organization",
        "school",
        "going",
        "m",
        "into"
    ],
    "wof:name":"Creative Sharp Prsentation Inc",
    "wof:placetype":"venue"
},
  "geometry": {"coordinates":[-87.924355,43.207178],"type":"Point"}
}