{
  "type": "Feature",
  "properties": {
    "addr:full":"534 Redbird Cir De Pere WI 54115",
    "addr:housenumber":"534",
    "addr:postcode":"54115",
    "addr:street":"Redbird Cir",
    "iso:country":"US",
    "sg:address":"534 Redbird Cir",
    "sg:city":"De Pere",
    "sg:classifiers":[
        {
            "category":"Health Services",
            "subcategory":"Doctor",
            "type":"Services"
        }
    ],
    "sg:phone":"+1 920 336 4002",
    "sg:postcode":"54115",
    "sg:province":"WI",
    "sg:tags":[
        "dentist"
    ],
    "wof:name":"Children's Dental Clnc-Grn By",
    "wof:placetype":"venue"
},
  "geometry": {"coordinates":[-88.03810900000001,44.438514],"type":"Point"}
}