{
  "type": "Feature",
  "properties": {
    "iso:country":"US",
    "sg:address":"1111 E Brown Deer Rd",
    "sg:city":"Milwaukee",
    "sg:classifiers":[
        {
            "category":"Arts & Performance",
            "subcategory":"Arts Center",
            "type":"Entertainment"
        }
    ],
    "sg:phone":"+1 414 352 2880",
    "sg:postcode":"53217",
    "sg:province":"WI",
    "sg:tags":[
        "nature"
    ],
    "sg:website":"http://www.schlitzauduboncenter.com",
    "wof:name":"Schlitz Audubon Nature Center",
    "wof:placetype":"venue"
},
  "geometry": {"coordinates":[-87.895196,43.176526],"type":"Point"}
}