{
  "type": "Feature",
  "properties": {
    "iso:country":"US",
    "sg:address":"2930 Co Rd F",
    "sg:city":"Blue Mounds",
    "sg:classifiers":[
        {
            "category":"Wholesale",
            "subcategory":"Machinery & Supplies",
            "type":"Manufacturing & Wholesale Goods"
        }
    ],
    "sg:phone":"+1 608 437 4463",
    "sg:postcode":"53517",
    "sg:province":"WI",
    "sg:tags":[
        "vacuum",
        "system",
        "cleaning"
    ],
    "wof:name":"Dirt Devil Central Vacuum",
    "wof:placetype":"venue"
},
  "geometry": {"coordinates":[-89.85392400000001,42.950436],"type":"Point"}
}