{
  "type": "Feature",
  "properties": {
    "iso:country":"US",
    "sg:address":"101 Raymond St",
    "sg:city":"Friendship",
    "sg:classifiers":[
        {
            "category":"Building & Trades",
            "subcategory":"Plumbing",
            "type":"Services"
        }
    ],
    "sg:phone":"+1 608 339 8135",
    "sg:postcode":"53934",
    "sg:province":"WI",
    "sg:tags":[
        "air",
        "heating",
        "contractor",
        "system",
        "conditioning"
    ],
    "wof:name":"A F Heating & Air Conditioning",
    "wof:placetype":"venue"
},
  "geometry": {"coordinates":[-89.819395,43.973946],"type":"Point"}
}