{
  "type": "Feature",
  "properties": {
    "addr:full":"12896 37th Ave Chippewa Falls WI 54729",
    "addr:housenumber":"12896",
    "addr:postcode":"54729",
    "addr:street":"37Th Ave",
    "iso:country":"US",
    "sg:address":"12896 37th Ave",
    "sg:city":"Chippewa Falls",
    "sg:classifiers":[
        {
            "category":"Freight",
            "type":"Transportation"
        }
    ],
    "sg:phone":"+1 715 720 6160",
    "sg:postcode":"54729",
    "sg:province":"WI",
    "sg:tags":[
        "hauling",
        "trucking"
    ],
    "wof:name":"Midwest Motors LLC",
    "wof:placetype":"venue"
},
  "geometry": {"coordinates":[-91.415502,44.896438],"type":"Point"}
}