{
  "type": "Feature",
  "properties": {
    "iso:country":"US",
    "sg:address":"2207 Dahlk Cir",
    "sg:city":"Verona",
    "sg:classifiers":[
        {
            "category":"Real Estate",
            "subcategory":"Real Estate Operator",
            "type":"Services"
        }
    ],
    "sg:phone":"+1 608 845 6161",
    "sg:postcode":"53593",
    "sg:province":"WI",
    "sg:tags":[
        "building",
        "apartment"
    ],
    "wof:name":"Perkins Apts LLC",
    "wof:placetype":"venue"
},
  "geometry": {"coordinates":[-89.61259099999999,42.971153],"type":"Point"}
}