{
  "type": "Feature",
  "properties": {
    "iso:country":"US",
    "sg:address":"6734 370th St",
    "sg:city":"Menomonie",
    "sg:classifiers":[
        {
            "category":"Building & Trades",
            "subcategory":"Plumbing",
            "type":"Services"
        }
    ],
    "sg:phone":"+1 715 235 1239",
    "sg:postcode":"54751",
    "sg:province":"WI",
    "sg:tags":[
        "contractor"
    ],
    "wof:name":"Jims Repair Service",
    "wof:placetype":"venue"
},
  "geometry": {"coordinates":[-91.97547900000001,44.936096],"type":"Point"}
}