{
  "type": "Feature",
  "properties": {
    "iso:country":"US",
    "sg:address":"4514 Fetke Lake Dr",
    "sg:city":"Rhinelander",
    "sg:classifiers":[
        {
            "category":"Wholesale",
            "subcategory":"Toys & Hobbies",
            "type":"Manufacturing & Wholesale Goods"
        }
    ],
    "sg:phone":"+1 715 369 1155",
    "sg:postcode":"54501",
    "sg:province":"WI",
    "sg:tags":[
        "stuffed",
        "animal"
    ],
    "wof:name":"Hodag Inc",
    "wof:placetype":"venue"
},
  "geometry": {"coordinates":[-89.46810499999999,45.686722],"type":"Point"}
}