{
  "type": "Feature",
  "properties": {
    "iso:country":"US",
    "sg:address":"1583 Marsha Ln",
    "sg:city":"Woodruff",
    "sg:classifiers":[
        {
            "category":"Recreation",
            "type":"Entertainment"
        }
    ],
    "sg:phone":"+1 715 356 5009",
    "sg:postcode":"54568",
    "sg:province":"WI",
    "wof:name":"Good Gallery",
    "wof:placetype":"venue"
},
  "geometry": {"coordinates":[-89.702487,45.927493],"type":"Point"}
}