{
  "type": "Feature",
  "properties": {
    "iso:country":"US",
    "sg:address":"698 Town Hall Dr",
    "sg:city":"Pulaski",
    "sg:classifiers":[
        {
            "category":"Building & Trades",
            "subcategory":"Construction",
            "type":"Services"
        }
    ],
    "sg:phone":"+1 920 822 2317",
    "sg:postcode":"54162",
    "sg:province":"WI",
    "sg:tags":[
        "house"
    ],
    "wof:name":"Willies Masonry & Home Imprvs",
    "wof:placetype":"venue"
},
  "geometry": {"coordinates":[-88.27665,44.702052],"type":"Point"}
}