{
  "type": "Feature",
  "properties": {
    "iso:country":"US",
    "sg:address":"636 30th St",
    "sg:city":"Monroe",
    "sg:classifiers":[
        {
            "category":"Restaurant",
            "type":"Food & Drink"
        }
    ],
    "sg:phone":"+1 608 329 7964",
    "sg:postcode":"53566",
    "sg:province":"WI",
    "sg:tags":[
        "style",
        "family"
    ],
    "wof:name":"Townedge Family Restuarant",
    "wof:placetype":"venue"
},
  "geometry": {"coordinates":[-89.652691,42.584801],"type":"Point"}
}