{
  "type": "Feature",
  "properties": {
    "addr:full":"3538 Park Dr Sturgeon Bay WI 54235",
    "addr:housenumber":"3538",
    "addr:postcode":"54235",
    "addr:street":"Park Dr",
    "iso:country":"US",
    "sg:address":"3538 Park Dr",
    "sg:city":"Sturgeon Bay",
    "sg:classifiers":[
        {
            "category":"Building & Trades",
            "subcategory":"Equipment Rental",
            "type":"Services"
        }
    ],
    "sg:phone":"+1 920 743 6952",
    "sg:postcode":"54235",
    "sg:province":"WI",
    "sg:tags":[
        "aircraft",
        "leasing",
        "charter"
    ],
    "sg:website":"www.orionflightservices.com",
    "wof:name":"Orion Flight Svc Inc",
    "wof:placetype":"venue"
},
  "geometry": {"coordinates":[-87.427527,44.850102],"type":"Point"}
}