{
  "type": "Feature",
  "properties": {
    "iso:country":"US",
    "sg:address":"2716 N 19th St",
    "sg:city":"Milwaukee",
    "sg:classifiers":[
        {
            "category":"Shopping",
            "subcategory":"Discount & Variety Stores",
            "type":"Retail Goods"
        }
    ],
    "sg:phone":"+1 414 264 6991",
    "sg:postcode":"53206",
    "sg:province":"WI",
    "sg:tags":[
        "auto",
        "used",
        "parts",
        "merchandise",
        "general"
    ],
    "wof:name":"Townsend Salvage",
    "wof:placetype":"venue"
},
  "geometry": {"coordinates":[-87.936742,43.069306],"type":"Point"}
}