{
  "type": "Feature",
  "properties": {
    "iso:country":"US",
    "sg:address":"2326 65th Ave",
    "sg:city":"Colfax",
    "sg:classifiers":[
        {
            "category":"Farming",
            "subcategory":"Farm & Veterinary Services",
            "type":"Manufacturing & Wholesale Goods"
        }
    ],
    "sg:phone":"+1 715 874 5270",
    "sg:postcode":"54739",
    "sg:province":"WI",
    "sg:tags":[
        "labor",
        "contractor"
    ],
    "wof:name":"Echo Brook Freight",
    "wof:placetype":"venue"
},
  "geometry": {"coordinates":[-91.62052,44.936404],"type":"Point"}
}