{
  "type": "Feature",
  "properties": {
    "iso:country":"US",
    "sg:address":"560 270th St",
    "sg:city":"Woodville",
    "sg:classifiers":[
        {
            "category":"Farming",
            "subcategory":"Farm",
            "type":"Manufacturing & Wholesale Goods"
        }
    ],
    "sg:phone":"+1 715 698 2748",
    "sg:postcode":"54028",
    "sg:province":"WI",
    "sg:tags":[
        "crop",
        "general"
    ],
    "wof:name":"Bruce Achterhof",
    "wof:placetype":"venue"
},
  "geometry": {"coordinates":[-92.257558,44.941799],"type":"Point"}
}