{
  "type": "Feature",
  "properties": {
    "iso:country":"US",
    "sg:address":"725 Fremont St",
    "sg:city":"Kiel",
    "sg:classifiers":[
        {
            "category":"Manufacturing",
            "subcategory":"Tools & Machinery",
            "type":"Manufacturing & Wholesale Goods"
        }
    ],
    "sg:phone":"+1 920 894 2221",
    "sg:postcode":"53042",
    "sg:province":"WI",
    "sg:tags":[
        "equipment",
        "conveyor",
        "conveying"
    ],
    "sg:website":"www.hgweber.com",
    "wof:name":"H G Weber & Co",
    "wof:placetype":"venue"
},
  "geometry": {"coordinates":[-88.041146,43.912589],"type":"Point"}
}