{
  "type": "Feature",
  "properties": {
    "iso:country":"US",
    "sg:address":"503 S Mill St",
    "sg:city":"Dalton",
    "sg:classifiers":[
        {
            "category":"Freight",
            "type":"Transportation"
        }
    ],
    "sg:phone":"+1 920 394 3090",
    "sg:postcode":"53939",
    "sg:province":"WI",
    "sg:tags":[
        "farm",
        "crop",
        "trucking",
        "food",
        "operator",
        "covered"
    ],
    "wof:name":"Broken Stirrup Enterprises",
    "wof:placetype":"venue"
},
  "geometry": {"coordinates":[-89.13428,43.688532],"type":"Point"}
}