{
  "type": "Feature",
  "properties": {
    "iso:country":"US",
    "sg:address":"1205 E Irving Ave",
    "sg:city":"Oshkosh",
    "sg:classifiers":[
        {
            "category":"Professional",
            "type":"Services"
        }
    ],
    "sg:phone":"+1 920 232 0039",
    "sg:postcode":"54901",
    "sg:province":"WI",
    "wof:name":"Becman Company",
    "wof:placetype":"venue"
},
  "geometry": {"coordinates":[-88.520906,44.024885],"type":"Point"}
}