{
  "type": "Feature",
  "properties": {
    "iso:country":"US",
    "sg:address":"1801 Pewaukee Rd",
    "sg:city":"Waukesha",
    "sg:classifiers":[
        {
            "category":"Professional",
            "subcategory":"Business Services",
            "type":"Services"
        }
    ],
    "sg:phone":"+1 262 547 1862",
    "sg:postcode":"53188",
    "sg:province":"WI",
    "sg:tags":[
        "water",
        "treatment"
    ],
    "sg:website":"www.culligan.com",
    "wof:name":"Bruner By Culligan",
    "wof:placetype":"venue"
},
  "geometry": {"coordinates":[-88.225335,43.057075],"type":"Point"}
}