{
  "type": "Feature",
  "properties": {
    "iso:country":"US",
    "sg:address":"835 W Wisconsin St",
    "sg:city":"Sparta",
    "sg:classifiers":[
        {
            "category":"Home & Garden",
            "subcategory":"Building Materials",
            "type":"Retail Goods"
        }
    ],
    "sg:phone":"+1 608 269 6766",
    "sg:postcode":"54656",
    "sg:province":"WI",
    "sg:tags":[
        "lumber"
    ],
    "wof:name":"Sparta Home & Building Ctr",
    "wof:placetype":"venue"
},
  "geometry": {"coordinates":[-90.821068,43.939064],"type":"Point"}
}