{
  "type": "Feature",
  "properties": {
    "iso:country":"US",
    "sg:address":"315 N Falls St",
    "sg:city":"River Falls",
    "sg:classifiers":[
        {
            "category":"Restaurant",
            "type":"Food & Drink"
        }
    ],
    "sg:phone":"+1 715 425 9820",
    "sg:postcode":"54022",
    "sg:province":"WI",
    "sg:tags":[
        "eating"
    ],
    "wof:name":"Blues Dogs",
    "wof:placetype":"venue"
},
  "geometry": {"coordinates":[-92.63361,44.861544],"type":"Point"}
}