{
  "type": "Feature",
  "properties": {
    "iso:country":"US",
    "sg:address":"1303 Memorial Dr",
    "sg:city":"Watertown",
    "sg:classifiers":[
        {
            "category":"Restaurant",
            "type":"Food & Drink"
        }
    ],
    "sg:menulink":"http://www.allmenus.com/wi/watertown/145796-subway/menu/",
    "sg:phone":"+1 920 206 8760",
    "sg:postcode":"53098",
    "sg:province":"WI",
    "sg:tags":[
        "american",
        "sandwich"
    ],
    "wof:name":"Subway",
    "wof:placetype":"venue"
},
  "geometry": {"coordinates":[-88.701605,43.201006],"type":"Point"}
}