{
  "type": "Feature",
  "properties": {
    "iso:country":"US",
    "sg:address":"2040 Hillside Ln",
    "sg:city":"Green Bay",
    "sg:classifiers":[
        {
            "category":"Organizations",
            "subcategory":"Religious Organization",
            "type":"Services"
        }
    ],
    "sg:phone":"+1 920 468 4811",
    "sg:postcode":"54302",
    "sg:province":"WI",
    "sg:website":"www.communitynews.org",
    "wof:name":"St Bernard Parish",
    "wof:placetype":"venue"
},
  "geometry": {"coordinates":[-87.97160700000001,44.494474],"type":"Point"}
}