{
  "type": "Feature",
  "properties": {
    "iso:country":"US",
    "sg:address":"10267 Co Rd Y",
    "sg:city":"Mazomanie",
    "sg:classifiers":[
        {
            "category":"Freight",
            "type":"Transportation"
        }
    ],
    "sg:phone":"+1 608 795 4505",
    "sg:postcode":"53560",
    "sg:province":"WI",
    "sg:tags":[
        "operator",
        "local",
        "trucking"
    ],
    "wof:name":"Everson Trucking LLC",
    "wof:placetype":"venue"
},
  "geometry": {"coordinates":[-89.77793200000001,43.234067],"type":"Point"}
}