{
  "type": "Feature",
  "properties": {
    "addr:full":"26412 Schads Dr Waterford WI 53185",
    "addr:postcode":"26412;53185",
    "addr:street":"Schads Dr",
    "iso:country":"US",
    "sg:address":"26412 Schads Dr",
    "sg:city":"Waterford",
    "sg:classifiers":[
        {
            "category":"Shopping",
            "subcategory":"Computers & Home Electronics",
            "type":"Retail Goods"
        }
    ],
    "sg:phone":"+1 262 895 2124",
    "sg:postcode":"53185",
    "sg:province":"WI",
    "sg:tags":[
        "repair"
    ],
    "wof:name":"Windlake TV",
    "wof:placetype":"venue"
},
  "geometry": {"coordinates":[-88.160201,42.822866],"type":"Point"}
}