{
  "type": "Feature",
  "properties": {
    "addr:full":"214 4th Ave N Park Falls WI 54552",
    "addr:housenumber":"214",
    "addr:postcode":"54552",
    "addr:street":"4Th Ave N",
    "iso:country":"US",
    "sg:address":"214 4th Ave N",
    "sg:city":"Park Falls",
    "sg:classifiers":[
        {
            "category":"Building & Trades",
            "subcategory":"Construction",
            "type":"Services"
        }
    ],
    "sg:phone":"+1 715 762 3876",
    "sg:postcode":"54552",
    "sg:province":"WI",
    "sg:tags":[
        "general",
        "contractor"
    ],
    "wof:name":"H & M Construction & Insulatng",
    "wof:placetype":"venue"
},
  "geometry": {"coordinates":[-90.451657,45.936291],"type":"Point"}
}