{
  "type": "Feature",
  "properties": {
    "iso:country":"US",
    "sg:address":"2150 W Nordale Dr",
    "sg:city":"Appleton",
    "sg:classifiers":[
        {
            "category":"Retail",
            "subcategory":"Auto Repair",
            "type":"Services"
        }
    ],
    "sg:phone":"+1 920 735 0442",
    "sg:postcode":"54914",
    "sg:province":"WI",
    "sg:tags":[
        "body",
        "truck",
        "general"
    ],
    "wof:name":"Quality Truck Care Center",
    "wof:placetype":"venue"
},
  "geometry": {"coordinates":[-88.439853,44.28647],"type":"Point"}
}