{
  "type": "Feature",
  "properties": {
    "iso:country":"US",
    "sg:address":"3929 Co Hwy A",
    "sg:city":"Elkhorn",
    "sg:classifiers":[
        {
            "category":"Social Services",
            "type":"Services"
        }
    ],
    "sg:phone":"+1 262 723 7881",
    "sg:postcode":"53121",
    "sg:province":"WI",
    "wof:name":"Healthy Families Walworth",
    "wof:placetype":"venue"
},
  "geometry": {"coordinates":[-88.496288,42.762576],"type":"Point"}
}