{
  "type": "Feature",
  "properties": {
    "iso:country":"US",
    "sg:address":"2933 105th St",
    "sg:city":"Sturtevant",
    "sg:classifiers":[
        {
            "category":"Freight",
            "type":"Transportation"
        }
    ],
    "sg:phone":"+1 262 884 6468",
    "sg:postcode":"53177",
    "sg:province":"WI",
    "sg:tags":[
        "operator",
        "local",
        "storage",
        "trucking"
    ],
    "wof:name":"Executive Moving & Storage",
    "wof:placetype":"venue"
},
  "geometry": {"coordinates":[-87.914537,42.699442],"type":"Point"}
}