{
  "type": "Feature",
  "properties": {
    "iso:country":"US",
    "sg:address":"1603 Harding Ave",
    "sg:city":"Eau Claire",
    "sg:classifiers":[
        {
            "category":"Real Estate",
            "subcategory":"Real Estate Agent",
            "type":"Services"
        }
    ],
    "sg:phone":"+1 715 834 1501",
    "sg:postcode":"54701",
    "sg:province":"WI",
    "sg:website":"www.klevenrealtors.com",
    "wof:name":"Kleven Real Estate Inc",
    "wof:placetype":"venue"
},
  "geometry": {"coordinates":[-91.479788,44.801835],"type":"Point"}
}