{
  "type": "Feature",
  "properties": {
    "addr:full":"126 W Holum St De Forest WI 53532",
    "addr:housenumber":"126",
    "addr:postcode":"53532",
    "addr:street":"W Holum St",
    "iso:country":"US",
    "sg:address":"126 W Holum St",
    "sg:city":"De Forest",
    "sg:classifiers":[
        {
            "category":"Professional",
            "subcategory":"Management & Consulting",
            "type":"Services"
        }
    ],
    "sg:phone":"+1 608 850 5904",
    "sg:postcode":"53532",
    "sg:province":"WI",
    "wof:name":"Webuytimesharecom",
    "wof:placetype":"venue"
},
  "geometry": {"coordinates":[-89.34530700000001,43.247396],"type":"Point"}
}