{
  "type": "Feature",
  "properties": {
    "iso:country":"US",
    "sg:address":"3867 E Townline Rd",
    "sg:city":"Luxemburg",
    "sg:classifiers":[
        {
            "category":"Building & Trades",
            "subcategory":"Construction",
            "type":"Services"
        }
    ],
    "sg:phone":"+1 920 845 2955",
    "sg:postcode":"54217",
    "sg:province":"WI",
    "sg:tags":[
        "operator",
        "contractor",
        "local",
        "trucking"
    ],
    "wof:name":"Riemer Masonry",
    "wof:placetype":"venue"
},
  "geometry": {"coordinates":[-87.643805,44.468826],"type":"Point"}
}