{
  "type": "Feature",
  "properties": {
    "iso:country":"US",
    "sg:address":"4346 Bear Lake Rd",
    "sg:city":"Aniwa",
    "sg:classifiers":[
        {
            "category":"Retail",
            "subcategory":"Auto Repair",
            "type":"Services"
        }
    ],
    "sg:phone":"+1 715 449 2263",
    "sg:postcode":"54408",
    "sg:province":"WI",
    "sg:tags":[
        "body",
        "automobile",
        "painting"
    ],
    "wof:name":"Krueger's Top Notch Auto Body",
    "wof:placetype":"venue"
},
  "geometry": {"coordinates":[-89.27895599999999,45.058633],"type":"Point"}
}