{
  "type": "Feature",
  "properties": {
    "addr:full":"1503 E Milwaukee St Janesville WI 53545",
    "addr:housenumber":"1503",
    "addr:postcode":"53545",
    "addr:street":"E Milwaukee St",
    "iso:country":"US",
    "sg:address":"1503 E Milwaukee St",
    "sg:city":"Janesville",
    "sg:classifiers":[
        {
            "category":"Social Services",
            "subcategory":"Child Care",
            "type":"Services"
        }
    ],
    "sg:phone":"+1 608 373 7090",
    "sg:postcode":"53545",
    "sg:province":"WI",
    "wof:name":"Big Fun Family Day Care Ctr",
    "wof:placetype":"venue"
},
  "geometry": {"coordinates":[-89.003047,42.690893],"type":"Point"}
}