{
  "type": "Feature",
  "properties": {
    "iso:country":"US",
    "sg:address":"1553 Apple Tree Ln",
    "sg:city":"Waupaca",
    "sg:classifiers":[
        {
            "category":"Professional",
            "subcategory":"Business Services",
            "type":"Services"
        }
    ],
    "sg:phone":"+1 715 256 4134",
    "sg:postcode":"54981",
    "sg:province":"WI",
    "wof:name":"Isaac Vanier",
    "wof:placetype":"venue"
},
  "geometry": {"coordinates":[-89.065769,44.338947],"type":"Point"}
}