{
  "type": "Feature",
  "properties": {
    "iso:country":"US",
    "sg:address":"1201 W Vliet St",
    "sg:city":"Milwaukee",
    "sg:classifiers":[
        {
            "category":"Home & Garden",
            "subcategory":"Furniture",
            "type":"Retail Goods"
        }
    ],
    "sg:phone":"+1 414 933 1312",
    "sg:postcode":"53205",
    "sg:province":"WI",
    "wof:name":"Furniture Liquidation Center",
    "wof:placetype":"venue"
},
  "geometry": {"coordinates":[-87.92783799999999,43.048542],"type":"Point"}
}