{
  "type": "Feature",
  "properties": {
    "iso:country":"US",
    "sg:address":"1449 Green Bay Rd",
    "sg:city":"Sturgeon Bay",
    "sg:classifiers":[
        {
            "category":"Restaurant",
            "type":"Food & Drink"
        }
    ],
    "sg:phone":"+1 920 746 7739",
    "sg:postcode":"54235",
    "sg:province":"WI",
    "wof:name":"Cousin's Subs",
    "wof:placetype":"venue"
},
  "geometry": {"coordinates":[-87.399779,44.820792],"type":"Point"}
}