{
  "type": "Feature",
  "properties": {
    "iso:country":"US",
    "sg:address":"1353 Excalibur Dr",
    "sg:city":"Janesville",
    "sg:classifiers":[
        {
            "category":"Personal",
            "subcategory":"Beauty Salon",
            "type":"Services"
        }
    ],
    "sg:phone":"+1 608 756 9300",
    "sg:postcode":"53546",
    "sg:province":"WI",
    "wof:name":"Hair America Intl",
    "wof:placetype":"venue"
},
  "geometry": {"coordinates":[-88.97493900000001,42.701896],"type":"Point"}
}