{
  "type": "Feature",
  "properties": {
    "iso:country":"US",
    "sg:address":"2722 Henry St",
    "sg:city":"Sheboygan",
    "sg:classifiers":[
        {
            "category":"Education",
            "subcategory":"School",
            "type":"Public Place"
        }
    ],
    "sg:phone":"+1 920 459 2660",
    "sg:postcode":"53081",
    "sg:province":"WI",
    "sg:website":"www.christchildacademy.com",
    "wof:name":"Christ Child Academy",
    "wof:placetype":"venue"
},
  "geometry": {"coordinates":[-87.72233300000001,43.723307],"type":"Point"}
}