{
  "type": "Feature",
  "properties": {
    "addr:full":"7102 Harvest Hill Rd Madison WI 53717",
    "addr:housenumber":"7102",
    "addr:postcode":"53717",
    "addr:street":"Harvest Hill Rd",
    "iso:country":"US",
    "sg:address":"7102 Harvest Hill Rd",
    "sg:city":"Madison",
    "sg:classifiers":[
        {
            "category":"Building & Trades",
            "subcategory":"Landscaping Services",
            "type":"Services"
        }
    ],
    "sg:phone":"+1 608 836 8880",
    "sg:postcode":"53717",
    "sg:province":"WI",
    "wof:name":"Dille Lawn Care",
    "wof:placetype":"venue"
},
  "geometry": {"coordinates":[-89.504688,43.078719],"type":"Point"}
}