{
  "type": "Feature",
  "properties": {
    "iso:country":"US",
    "sg:address":"3713 State Hwy 42",
    "sg:city":"Fish Creek",
    "sg:classifiers":[
        {
            "category":"Restaurant",
            "type":"Food & Drink"
        }
    ],
    "sg:phone":"+1 920 868 3076",
    "sg:postcode":"54212",
    "sg:province":"WI",
    "sg:website":"www.theenglishinn.com",
    "wof:name":"English Inn",
    "wof:placetype":"venue"
},
  "geometry": {"coordinates":[-87.216543,45.131386],"type":"Point"}
}