{
  "type": "Feature",
  "properties": {
    "iso:country":"US",
    "sg:address":"113 Balsam Rd",
    "sg:city":"Sheboygan Falls",
    "sg:classifiers":[
        {
            "category":"Building & Trades",
            "subcategory":"Construction",
            "type":"Services"
        }
    ],
    "sg:phone":"+1 920 467 6285",
    "sg:postcode":"53085",
    "sg:province":"WI",
    "sg:tags":[
        "painter"
    ],
    "wof:name":"Willie Hagemeier Decorating",
    "wof:placetype":"venue"
},
  "geometry": {"coordinates":[-87.811363,43.741647],"type":"Point"}
}