{
  "type": "Feature",
  "properties": {
    "iso:country":"US",
    "sg:address":"801 Main St",
    "sg:city":"Marinette",
    "sg:classifiers":[
        {
            "category":"Bars & Pubs",
            "type":"Food & Drink"
        }
    ],
    "sg:phone":"+1 715 735 5256",
    "sg:postcode":"54143",
    "sg:province":"WI",
    "sg:tags":[
        "drinking"
    ],
    "wof:name":"Red Brick Tavern",
    "wof:placetype":"venue"
},
  "geometry": {"coordinates":[-87.614893,45.092417],"type":"Point"}
}