{
  "type": "Feature",
  "properties": {
    "iso:country":"US",
    "sg:address":"101 S Main St",
    "sg:city":"De Forest",
    "sg:classifiers":[
        {
            "category":"Food & Beverages",
            "subcategory":"Bakery",
            "type":"Retail Goods"
        }
    ],
    "sg:phone":"+1 608 846 3052",
    "sg:postcode":"53532",
    "sg:province":"WI",
    "sg:tags":[
        "baker"
    ],
    "wof:name":"De Forest Donut Shop & Bakery",
    "wof:placetype":"venue"
},
  "geometry": {"coordinates":[-89.34383699999999,43.247541],"type":"Point"}
}