{
  "type": "Feature",
  "properties": {
    "iso:country":"US",
    "sg:address":"707 Water St",
    "sg:city":"Sauk City",
    "sg:classifiers":[
        {
            "category":"Real Estate",
            "subcategory":"Real Estate Agent",
            "type":"Services"
        }
    ],
    "sg:phone":"+1 608 643 2494",
    "sg:postcode":"53583",
    "sg:province":"WI",
    "sg:tags":[
        "management"
    ],
    "wof:name":"Kris Kohlman Property Mgmt LLC",
    "wof:placetype":"venue"
},
  "geometry": {"coordinates":[-89.71809,43.283647],"type":"Point"}
}