{
  "type": "Feature",
  "properties": {
    "iso:country":"US",
    "sg:address":"4405 Scanleton Rd",
    "sg:city":"Black River Fls",
    "sg:classifiers":[
        {
            "category":"Building & Trades",
            "subcategory":"Landscaping Services",
            "type":"Services"
        }
    ],
    "sg:phone":"+1 715 284 5281",
    "sg:postcode":"54615",
    "sg:province":"WI",
    "sg:tags":[
        "landscape",
        "contractor"
    ],
    "wof:name":"Hawk Island Excavating & Lands",
    "wof:placetype":"venue"
},
  "geometry": {"coordinates":[-90.868267,44.23223],"type":"Point"}
}