{
  "type": "Feature",
  "properties": {
    "iso:country":"US",
    "sg:address":"2840 Hill Rd",
    "sg:city":"Granton",
    "sg:classifiers":[
        {
            "category":"Organizations",
            "subcategory":"Religious Organization",
            "type":"Services"
        }
    ],
    "sg:phone":"+1 715 238 7269",
    "sg:postcode":"54436",
    "sg:province":"WI",
    "wof:name":"Zion American Lutheran Church",
    "wof:placetype":"venue"
},
  "geometry": {"coordinates":[-90.452979,44.567515],"type":"Point"}
}