{
  "type": "Feature",
  "properties": {
    "iso:country":"US",
    "sg:address":"6441 W Howard Ave",
    "sg:city":"Milwaukee",
    "sg:classifiers":[
        {
            "category":"Autos & Motor Vehicles",
            "subcategory":"Fuel & Gas Station",
            "type":"Retail Goods"
        },
        {
            "category":"Retail",
            "subcategory":"Auto Repair",
            "type":"Services"
        }
    ],
    "sg:phone":"+1 414 321 7740",
    "sg:postcode":"53220",
    "sg:province":"WI",
    "sg:tags":[
        "repairing",
        "automobile",
        "station",
        "gasoline"
    ],
    "wof:name":"A & D Svc Inc",
    "wof:placetype":"venue"
},
  "geometry": {"coordinates":[-87.993466,42.973777],"type":"Point"}
}