{
  "type": "Feature",
  "properties": {
    "addr:full":"585 N Main St Cottage Grove WI 53527",
    "addr:housenumber":"585",
    "addr:postcode":"53527",
    "addr:street":"N Main St",
    "iso:country":"US",
    "sg:address":"585 N Main St",
    "sg:city":"Cottage Grove",
    "sg:classifiers":[
        {
            "category":"Personal",
            "subcategory":"Beauty Salon",
            "type":"Services"
        }
    ],
    "sg:phone":"+1 608 839 5161",
    "sg:postcode":"53527",
    "sg:province":"WI",
    "wof:name":"Village Hair Cutters",
    "wof:placetype":"venue"
},
  "geometry": {"coordinates":[-89.199646,43.085428],"type":"Point"}
}