{
  "type": "Feature",
  "properties": {
    "addr:full":"25 W Canal St Chippewa Falls WI 54729",
    "addr:housenumber":"25",
    "addr:postcode":"54729",
    "addr:street":"W Canal St",
    "iso:country":"US",
    "sg:address":"25 W Canal St",
    "sg:city":"Chippewa Falls",
    "sg:classifiers":[
        {
            "category":"Recreation",
            "type":"Entertainment"
        }
    ],
    "sg:phone":"+1 715 723 3777",
    "sg:postcode":"54729",
    "sg:province":"WI",
    "sg:tags":[
        "club",
        "membership"
    ],
    "wof:name":"Falls Hunt Club",
    "wof:placetype":"venue"
},
  "geometry": {"coordinates":[-91.39337999999999,44.927986],"type":"Point"}
}