{
  "type": "Feature",
  "properties": {
    "iso:country":"US",
    "sg:address":"2805 University Ave",
    "sg:city":"Madison",
    "sg:classifiers":[
        {
            "category":"Retail",
            "subcategory":"Laundry & Dry Cleaning",
            "type":"Services"
        }
    ],
    "sg:phone":"+1 608 233 2939",
    "sg:postcode":"53705",
    "sg:province":"WI",
    "wof:name":"Mais Alteration & Gifts",
    "wof:placetype":"venue"
},
  "geometry": {"coordinates":[-89.438723,43.074721],"type":"Point"}
}