{
  "type": "Feature",
  "properties": {
    "iso:country":"US",
    "sg:address":"4260 N Teutonia Ave",
    "sg:city":"Milwaukee",
    "sg:classifiers":[
        {
            "category":"Organizations",
            "subcategory":"Religious Organization",
            "type":"Services"
        }
    ],
    "sg:phone":"+1 414 445 2189",
    "sg:postcode":"53209",
    "sg:province":"WI",
    "sg:tags":[
        "church"
    ],
    "wof:name":"Allen Chapel African Methodist",
    "wof:placetype":"venue"
},
  "geometry": {"coordinates":[-87.94118400000001,43.093915],"type":"Point"}
}