{
  "type": "Feature",
  "properties": {
    "iso:country":"US",
    "sg:address":"325 State Rd 149",
    "sg:city":"Kiel",
    "sg:classifiers":[
        {
            "category":"Building & Trades",
            "subcategory":"Construction",
            "type":"Services"
        }
    ],
    "sg:phone":"+1 920 894 3842",
    "sg:postcode":"53042",
    "sg:province":"WI",
    "sg:tags":[
        "roofing",
        "contractor"
    ],
    "wof:name":"Wincon Services Inc",
    "wof:placetype":"venue"
},
  "geometry": {"coordinates":[-88.058807,43.906536],"type":"Point"}
}