{
  "type": "Feature",
  "properties": {
    "iso:country":"US",
    "sg:address":"4220 S Beaumont Ave",
    "sg:city":"Kansasville",
    "sg:classifiers":[
        {
            "category":"Personal",
            "subcategory":"Barber",
            "type":"Services"
        }
    ],
    "sg:phone":"+1 262 878 1940",
    "sg:postcode":"53139",
    "sg:province":"WI",
    "sg:tags":[
        "shop"
    ],
    "wof:name":"Beechers Barber Shop",
    "wof:placetype":"venue"
},
  "geometry": {"coordinates":[-88.11059,42.685065],"type":"Point"}
}