{
  "type": "Feature",
  "properties": {
    "iso:country":"US",
    "sg:address":"7833 W Capitol Dr",
    "sg:city":"Milwaukee",
    "sg:classifiers":[
        {
            "category":"Social Services",
            "subcategory":"Child Care",
            "type":"Services"
        }
    ],
    "sg:phone":"+1 414 616 5000",
    "sg:postcode":"53222",
    "sg:province":"WI",
    "sg:tags":[
        "day"
    ],
    "wof:name":"SDC Head Start 78th Street",
    "wof:placetype":"venue"
},
  "geometry": {"coordinates":[-88.0106,43.089817],"type":"Point"}
}