{
  "type": "Feature",
  "properties": {
    "addr:full":"9875 Image Ave Sparta WI 54656",
    "addr:housenumber":"9875",
    "addr:postcode":"54656",
    "addr:street":"Image Ave",
    "iso:country":"US",
    "sg:address":"9875 Image Ave",
    "sg:city":"Sparta",
    "sg:classifiers":[
        {
            "category":"Real Estate",
            "subcategory":"Real Estate Operator",
            "type":"Services"
        }
    ],
    "sg:phone":"+1 608 269 0153",
    "sg:postcode":"54656",
    "sg:province":"WI",
    "sg:tags":[
        "building",
        "apartment"
    ],
    "wof:name":"Northtown Apts LLC",
    "wof:placetype":"venue"
},
  "geometry": {"coordinates":[-90.79481800000001,43.919874],"type":"Point"}
}