{
  "type": "Feature",
  "properties": {
    "iso:country":"US",
    "sg:address":"705 N Mill St",
    "sg:city":"Weyauwega",
    "sg:classifiers":[
        {
            "category":"Home & Garden",
            "subcategory":"Carpets & Floor Coverings",
            "type":"Retail Goods"
        }
    ],
    "sg:phone":"+1 920 867 3146",
    "sg:postcode":"54983",
    "sg:province":"WI",
    "sg:tags":[
        "dealer",
        "rug"
    ],
    "wof:name":"Real Estate Builders Inc",
    "wof:placetype":"venue"
},
  "geometry": {"coordinates":[-88.933899,44.329426],"type":"Point"}
}