{
  "type": "Feature",
  "properties": {
    "addr:full":"400 N Broadway Milwaukee WI 53202",
    "addr:housenumber":"400",
    "addr:postcode":"53202",
    "addr:street":"N Broadway",
    "iso:country":"US",
    "sg:address":"400 N Broadway",
    "sg:city":"Milwaukee",
    "sg:classifiers":[
        {
            "category":"Real Estate",
            "subcategory":"Real Estate Services",
            "type":"Services"
        },
        {
            "category":"Banks & Credit Unions",
            "subcategory":"Financial Services",
            "type":"Services"
        }
    ],
    "sg:phone":"+1 414 276 1393",
    "sg:postcode":"53202",
    "sg:province":"WI",
    "sg:tags":[
        "loan",
        "mortgage"
    ],
    "wof:name":"Affiliated Funding Usa",
    "wof:placetype":"venue"
},
  "geometry": {"coordinates":[-87.90735599999999,43.035069],"type":"Point"}
}