{
  "type": "Feature",
  "properties": {
    "iso:country":"US",
    "sg:address":"125 E School St",
    "sg:city":"Columbus",
    "sg:classifiers":[
        {
            "category":"Wholesale",
            "subcategory":"Medical Equipment & Supplies",
            "type":"Manufacturing & Wholesale Goods"
        }
    ],
    "sg:phone":"+1 920 623 0578",
    "sg:postcode":"53925",
    "sg:province":"WI",
    "sg:tags":[
        "dental",
        "sales"
    ],
    "wof:name":"Highspeed Repair",
    "wof:placetype":"venue"
},
  "geometry": {"coordinates":[-89.017124,43.335931],"type":"Point"}
}