{
  "type": "Feature",
  "properties": {
    "iso:country":"US",
    "sg:address":"1910 E Trowbridge St",
    "sg:city":"Milwaukee",
    "sg:classifiers":[
        {
            "category":"Professional",
            "subcategory":"Management & Consulting",
            "type":"Services"
        }
    ],
    "sg:phone":"+1 414 482 2287",
    "sg:postcode":"53207",
    "sg:province":"WI",
    "sg:tags":[
        "consultant"
    ],
    "wof:name":"J Wautier Consulting",
    "wof:placetype":"venue"
},
  "geometry": {"coordinates":[-87.88624,42.991802],"type":"Point"}
}