{
  "type": "Feature",
  "properties": {
    "iso:country":"US",
    "sg:address":"111 S Main St",
    "sg:city":"Oconomowoc",
    "sg:classifiers":[
        {
            "category":"Building & Trades",
            "subcategory":"Plumbing",
            "type":"Services"
        }
    ],
    "sg:phone":"+1 262 567 4243",
    "sg:postcode":"53066",
    "sg:province":"WI",
    "sg:tags":[
        "co",
        "duct",
        "work",
        "system",
        "air",
        "heating",
        "refrigeration",
        "conditioning",
        "contractor"
    ],
    "wof:name":"Aasen Heating and Cooling",
    "wof:placetype":"venue"
},
  "geometry": {"coordinates":[-88.49930500000001,43.110231],"type":"Point"}
}