{
  "type": "Feature",
  "properties": {
    "iso:country":"US",
    "sg:address":"207 Wells St",
    "sg:city":"Darlington",
    "sg:classifiers":[
        {
            "category":"Banks & Credit Unions",
            "subcategory":"Bank",
            "type":"Services"
        }
    ],
    "sg:phone":"+1 608 776 4598",
    "sg:postcode":"53530",
    "sg:province":"WI",
    "sg:tags":[
        "state",
        "commercial"
    ],
    "wof:name":"F & M Bank-Wisconsin",
    "wof:placetype":"venue"
},
  "geometry": {"coordinates":[-90.1165,42.678699],"type":"Point"}
}