{
  "type": "Feature",
  "properties": {
    "iso:country":"US",
    "sg:address":"17076 State Rd 194",
    "sg:city":"Sheldon",
    "sg:classifiers":[
        {
            "category":"Farming",
            "subcategory":"Dairy Farm",
            "type":"Manufacturing & Wholesale Goods"
        }
    ],
    "sg:phone":"+1 715 452 5756",
    "sg:postcode":"54766",
    "sg:province":"WI",
    "wof:name":"Frank Novotny",
    "wof:placetype":"venue"
},
  "geometry": {"coordinates":[-90.918663,45.324589],"type":"Point"}
}