{
  "type": "Feature",
  "properties": {
    "iso:country":"US",
    "sg:address":"709 W Beckert Rd",
    "sg:city":"New London",
    "sg:classifiers":[
        {
            "category":"Organizations",
            "subcategory":"Religious Organization",
            "type":"Services"
        }
    ],
    "sg:phone":"+1 920 982 5833",
    "sg:postcode":"54961",
    "sg:province":"WI",
    "wof:name":"Trinity Lutheran Church",
    "wof:placetype":"venue"
},
  "geometry": {"coordinates":[-88.747619,44.373821],"type":"Point"}
}