{
  "type": "Feature",
  "properties": {
    "iso:country":"US",
    "sg:address":"1340 Scott St",
    "sg:city":"Kewaunee",
    "sg:classifiers":[
        {
            "category":"Retail",
            "subcategory":"Auto Repair",
            "type":"Services"
        }
    ],
    "sg:phone":"+1 920 388 4980",
    "sg:postcode":"54216",
    "sg:province":"WI",
    "sg:tags":[
        "automobile",
        "lubrication"
    ],
    "wof:name":"Road Runner Oil Express",
    "wof:placetype":"venue"
},
  "geometry": {"coordinates":[-87.51743500000001,44.448949],"type":"Point"}
}