{
  "type": "Feature",
  "properties": {
    "addr:full":"2500 N Mayfair Rd Milwaukee WI 53222",
    "addr:housenumber":"2500",
    "addr:postcode":"53222",
    "addr:street":"N Mayfair Rd",
    "iso:country":"US",
    "sg:address":"2500 N Mayfair Rd",
    "sg:city":"Milwaukee",
    "sg:classifiers":[
        {
            "category":"Shopping",
            "subcategory":"Music",
            "type":"Retail Goods"
        }
    ],
    "sg:phone":"+1 414 258 3663",
    "sg:postcode":"53222",
    "sg:province":"WI",
    "sg:tags":[
        "product",
        "prerecorded",
        "tape",
        "blank",
        "small",
        "video",
        "audio"
    ],
    "wof:name":"Musicland Group Inc",
    "wof:placetype":"venue"
},
  "geometry": {"coordinates":[-88.047678,43.063727],"type":"Point"}
}