{
  "type": "Feature",
  "properties": {
    "iso:country":"US",
    "sg:address":"15 Park Pl",
    "sg:city":"Appleton",
    "sg:classifiers":[
        {
            "category":"Banks & Credit Unions",
            "subcategory":"Investment Brokerage",
            "type":"Services"
        },
        {
            "category":"Banks & Credit Unions",
            "subcategory":"Bank",
            "type":"Services"
        }
    ],
    "sg:phone":"+1 920 882 3008",
    "sg:postcode":"54914",
    "sg:province":"WI",
    "sg:tags":[
        "loan",
        "security",
        "real estate"
    ],
    "wof:name":"Freedom Home Mortgage LLC",
    "wof:placetype":"venue"
},
  "geometry": {"coordinates":[-88.467997,44.256855],"type":"Point"}
}