{
  "type": "Feature",
  "properties": {
    "iso:country":"US",
    "sg:address":"1913 Melvin Ave",
    "sg:city":"Racine",
    "sg:classifiers":[
        {
            "category":"Government",
            "subcategory":"Office",
            "type":"Public Place"
        }
    ],
    "sg:phone":"+1 262 637 8163",
    "sg:postcode":"53404",
    "sg:province":"WI",
    "sg:tags":[
        "test",
        "station"
    ],
    "wof:name":"Test Station",
    "wof:placetype":"venue"
},
  "geometry": {"coordinates":[-87.804508,42.755373],"type":"Point"}
}