{
  "type": "Feature",
  "properties": {
    "iso:country":"US",
    "sg:address":"12070 Firestation Rd",
    "sg:city":"Tripoli",
    "sg:classifiers":[
        {
            "category":"Government",
            "subcategory":"Fire Station",
            "type":"Public Place"
        }
    ],
    "sg:phone":"+1 715 564 2650",
    "sg:postcode":"54564",
    "sg:province":"WI",
    "sg:tags":[
        "department",
        "protection"
    ],
    "wof:name":"Tripoli Volunteer Fire Dept",
    "wof:placetype":"venue"
},
  "geometry": {"coordinates":[-89.994989,45.554217],"type":"Point"}
}