{
  "type": "Feature",
  "properties": {
    "addr:full":"2564 Telluride Trl Green Bay WI 54313",
    "addr:housenumber":"2564",
    "addr:postcode":"54313",
    "addr:street":"Telluride Trl",
    "iso:country":"US",
    "sg:address":"2564 Telluride Trl",
    "sg:city":"Green Bay",
    "sg:classifiers":[
        {
            "category":"Professional",
            "subcategory":"Management & Consulting",
            "type":"Services"
        }
    ],
    "sg:phone":"+1 920 662 1931",
    "sg:postcode":"54313",
    "sg:province":"WI",
    "sg:tags":[
        "consultant",
        "business"
    ],
    "wof:name":"UNI Svc Performance Mgmt Inc",
    "wof:placetype":"venue"
},
  "geometry": {"coordinates":[-88.082858,44.579983],"type":"Point"}
}