{
  "type": "Feature",
  "properties": {
    "iso:country":"US",
    "sg:address":"2195 Gilson Ct",
    "sg:city":"Green Bay",
    "sg:classifiers":[
        {
            "category":"Professional",
            "type":"Services"
        }
    ],
    "sg:phone":"+1 920 494 0634",
    "sg:postcode":"54304",
    "sg:province":"WI",
    "wof:name":"S&R Services LLC",
    "wof:placetype":"venue"
},
  "geometry": {"coordinates":[-88.079364,44.499424],"type":"Point"}
}