{
  "type": "Feature",
  "properties": {
    "addr:full":"1310 Emerald Ter Sun Prairie WI 53590",
    "addr:housenumber":"1310",
    "addr:postcode":"53590",
    "addr:street":"Emerald Ter",
    "iso:country":"US",
    "sg:address":"1310 Emerald Ter",
    "sg:city":"Sun Prairie",
    "sg:classifiers":[
        {
            "category":"Retail",
            "subcategory":"Funeral Services",
            "type":"Services"
        }
    ],
    "sg:phone":"+1 608 837 9054",
    "sg:postcode":"53590",
    "sg:province":"WI",
    "wof:name":"Cress Funeral & Cremation Svc",
    "wof:placetype":"venue"
},
  "geometry": {"coordinates":[-89.230706,43.186723],"type":"Point"}
}