{
  "type": "Feature",
  "properties": {
    "addr:full":"9098 590th St Colfax WI 54730",
    "addr:housenumber":"9098",
    "addr:postcode":"54730",
    "addr:street":"590Th St",
    "iso:country":"US",
    "sg:address":"9098 590th St",
    "sg:city":"Colfax",
    "sg:classifiers":[
        {
            "category":"Shopping",
            "subcategory":"Discount & Variety Stores",
            "type":"Retail Goods"
        }
    ],
    "sg:phone":"+1 715 632 2267",
    "sg:postcode":"54730",
    "sg:province":"WI",
    "sg:tags":[
        "merchandise",
        "general"
    ],
    "wof:name":"Bucks Corner Store",
    "wof:placetype":"venue"
},
  "geometry": {"coordinates":[-91.86497199999999,44.994765],"type":"Point"}
}