{
  "type": "Feature",
  "properties": {
    "iso:country":"US",
    "sg:address":"6653 N 53rd St",
    "sg:city":"Milwaukee",
    "sg:classifiers":[
        {
            "category":"Place Of Worship",
            "subcategory":"Church",
            "type":"Public Place"
        }
    ],
    "sg:phone":"+1 414 358 0764",
    "sg:postcode":"53223",
    "sg:province":"WI",
    "sg:tags":[
        "churches-salvation",
        "army"
    ],
    "wof:name":"Sisters of The Sorrowful Mother",
    "wof:placetype":"venue"
},
  "geometry": {"coordinates":[-87.978156,43.138599],"type":"Point"}
}