{
  "type": "Feature",
  "properties": {
    "iso:country":"US",
    "sg:address":"2600 Tulip Ln",
    "sg:city":"Green Bay",
    "sg:classifiers":[
        {
            "category":"Building & Trades",
            "subcategory":"Construction",
            "type":"Services"
        }
    ],
    "sg:phone":"+1 920 434 0758",
    "sg:postcode":"54313",
    "sg:province":"WI",
    "sg:tags":[
        "home",
        "general",
        "family",
        "contractor"
    ],
    "wof:name":"Kaster Builders Inc",
    "wof:placetype":"venue"
},
  "geometry": {"coordinates":[-88.0876,44.566613],"type":"Point"}
}