{
  "type": "Feature",
  "properties": {
    "addr:full":"5205 42nd St Kenosha WI 53144",
    "addr:housenumber":"5205",
    "addr:postcode":"53144",
    "addr:street":"42Nd St",
    "iso:country":"US",
    "sg:address":"5205 42nd St",
    "sg:city":"Kenosha",
    "sg:classifiers":[
        {
            "category":"Professional",
            "subcategory":"Engineering",
            "type":"Services"
        }
    ],
    "sg:phone":"+1 262 652 6351",
    "sg:postcode":"53144",
    "sg:province":"WI",
    "sg:tags":[
        "consulting",
        "engineer"
    ],
    "wof:name":"Kencon",
    "wof:placetype":"venue"
},
  "geometry": {"coordinates":[-87.871223,42.5988],"type":"Point"}
}