{
  "type": "Feature",
  "properties": {
    "addr:full":"402 Main St Friendship WI 53934",
    "addr:housenumber":"402",
    "addr:postcode":"53934",
    "addr:street":"Main St",
    "iso:country":"US",
    "sg:address":"402 Main St",
    "sg:city":"Friendship",
    "sg:classifiers":[
        {
            "category":"Government",
            "subcategory":"Office",
            "type":"Public Place"
        }
    ],
    "sg:phone":"+1 608 339 4267",
    "sg:postcode":"53934",
    "sg:province":"WI",
    "wof:name":"Adams County Corp Counsel",
    "wof:placetype":"venue"
},
  "geometry": {"coordinates":[-89.816109,43.97172],"type":"Point"}
}