{
  "type": "Feature",
  "properties": {
    "iso:country":"US",
    "sg:address":"7138 State Hwy 144",
    "sg:city":"West Bend",
    "sg:classifiers":[
        {
            "category":"Bars & Pubs",
            "type":"Food & Drink"
        }
    ],
    "sg:phone":"+1 262 338 6258",
    "sg:postcode":"53090",
    "sg:province":"WI",
    "wof:name":"Pier 144",
    "wof:placetype":"venue"
},
  "geometry": {"coordinates":[-88.165587,43.451627],"type":"Point"}
}