{
  "type": "Feature",
  "properties": {
    "addr:full":"2325 W Kimberly Ave Milwaukee WI 53221",
    "addr:housenumber":"2325",
    "addr:postcode":"53221",
    "addr:street":"W Kimberly Ave",
    "iso:country":"US",
    "sg:address":"2325 W Kimberly Ave",
    "sg:city":"Milwaukee",
    "sg:classifiers":[
        {
            "category":"Building & Trades",
            "subcategory":"Construction",
            "type":"Services"
        }
    ],
    "sg:phone":"+1 414 282 0909",
    "sg:postcode":"53221",
    "sg:province":"WI",
    "sg:tags":[
        "house"
    ],
    "wof:name":"Golden Century Builders",
    "wof:placetype":"venue"
},
  "geometry": {"coordinates":[-87.94910400000001,42.933872],"type":"Point"}
}