{
  "type": "Feature",
  "properties": {
    "iso:country":"US",
    "sg:address":"221 Broad St",
    "sg:city":"Prescott",
    "sg:classifiers":[
        {
            "category":"Real Estate",
            "subcategory":"Real Estate Agent",
            "type":"Services"
        }
    ],
    "sg:phone":"+1 715 262 3214",
    "sg:postcode":"54021",
    "sg:province":"WI",
    "sg:website":"www.stcroixrealty.com",
    "wof:name":"Saint Croix Realty",
    "wof:placetype":"venue"
},
  "geometry": {"coordinates":[-92.801808,44.748649],"type":"Point"}
}