{
  "type": "Feature",
  "properties": {
    "iso:country":"US",
    "sg:address":"208 Wisconsin Ave N",
    "sg:city":"Frederic",
    "sg:classifiers":[
        {
            "category":"Organizations",
            "subcategory":"Religious Organization",
            "type":"Services"
        }
    ],
    "sg:phone":"+1 715 327 4436",
    "sg:postcode":"54837",
    "sg:province":"WI",
    "sg:tags":[
        "church"
    ],
    "wof:name":"St Lukes United Methodist Chr",
    "wof:placetype":"venue"
},
  "geometry": {"coordinates":[-92.466103,45.661435],"type":"Point"}
}