{
  "type": "Feature",
  "properties": {
    "addr:full":"1404 7th Ave W Brodhead WI 53520",
    "addr:housenumber":"1404",
    "addr:postcode":"53520",
    "addr:street":"7Th Ave W",
    "iso:country":"US",
    "sg:address":"1404 7th Ave W",
    "sg:city":"Brodhead",
    "sg:classifiers":[
        {
            "category":"Farming",
            "subcategory":"Dairy Farm",
            "type":"Manufacturing & Wholesale Goods"
        }
    ],
    "sg:phone":"+1 608 897 4210",
    "sg:postcode":"53520",
    "sg:province":"WI",
    "wof:name":"Brodhead All Star Dairy",
    "wof:placetype":"venue"
},
  "geometry": {"coordinates":[-89.384101,42.61627],"type":"Point"}
}