{
  "type": "Feature",
  "properties": {
    "iso:country":"US",
    "sg:address":"5273 Leonard Point Rd",
    "sg:city":"Omro",
    "sg:classifiers":[
        {
            "category":"Retail",
            "subcategory":"Auto Repair",
            "type":"Services"
        }
    ],
    "sg:phone":"+1 920 426 2710",
    "sg:postcode":"54963",
    "sg:province":"WI",
    "sg:tags":[
        "general"
    ],
    "wof:name":"On Spot Auto Service LLC",
    "wof:placetype":"venue"
},
  "geometry": {"coordinates":[-88.655975,44.047735],"type":"Point"}
}