{
  "type": "Feature",
  "properties": {
    "iso:country":"US",
    "sg:address":"1915 Broadway Ave",
    "sg:city":"Sheboygan",
    "sg:classifiers":[
        {
            "category":"Professional",
            "type":"Services"
        }
    ],
    "sg:phone":"+1 920 458 7284",
    "sg:postcode":"53081",
    "sg:province":"WI",
    "sg:tags":[
        "establishment"
    ],
    "wof:name":"Gildner & Gildner",
    "wof:placetype":"venue"
},
  "geometry": {"coordinates":[-87.73204200000001,43.735652],"type":"Point"}
}