{
  "type": "Feature",
  "properties": {
    "iso:country":"US",
    "sg:address":"1900 E North St",
    "sg:city":"Waukesha",
    "sg:classifiers":[
        {
            "category":"Manufacturing",
            "subcategory":"Tools & Machinery",
            "type":"Manufacturing & Wholesale Goods"
        }
    ],
    "sg:phone":"+1 262 547 1251",
    "sg:postcode":"53188",
    "sg:province":"WI",
    "sg:tags":[
        "copper",
        "transformer",
        "power",
        "mfg"
    ],
    "sg:website":"www.cooperpower.com",
    "wof:name":"Cooper Power Systems Inc",
    "wof:placetype":"venue"
},
  "geometry": {"coordinates":[-88.221062,43.025593],"type":"Point"}
}