{
  "type": "Feature",
  "properties": {
    "iso:country":"US",
    "sg:address":"2920 Wick Rd",
    "sg:city":"Markesan",
    "sg:classifiers":[
        {
            "category":"Professional",
            "type":"Services"
        }
    ],
    "sg:phone":"+1 920 398 2767",
    "sg:postcode":"53946",
    "sg:province":"WI",
    "wof:name":"Donald Ahonen",
    "wof:placetype":"venue"
},
  "geometry": {"coordinates":[-89.028183,43.784216],"type":"Point"}
}