{
  "type": "Feature",
  "properties": {
    "addr:full":"11716 Co Rd Vv Cassville WI 53806",
    "addr:housenumber":"11716",
    "addr:postcode":"53806",
    "addr:street":"Co Rd",
    "iso:country":"US",
    "sg:address":"11716 Co Rd Vv",
    "sg:city":"Cassville",
    "sg:classifiers":[
        {
            "category":"Bus Charters",
            "type":"Transportation"
        },
        {
            "category":"School Buses",
            "type":"Transportation"
        }
    ],
    "sg:phone":"+1 608 725 5440",
    "sg:postcode":"53806",
    "sg:province":"WI",
    "sg:tags":[
        "rental"
    ],
    "wof:name":"Russ Stratton Buses Inc",
    "wof:placetype":"venue"
},
  "geometry": {"coordinates":[-91.001491,42.722914],"type":"Point"}
}