{
  "type": "Feature",
  "properties": {
    "iso:country":"US",
    "sg:address":"2531 Branwood Dr",
    "sg:city":"Wisconsin Rapids",
    "sg:classifiers":[
        {
            "category":"Building & Trades",
            "subcategory":"Construction",
            "type":"Services"
        }
    ],
    "sg:phone":"+1 715 424 3490",
    "sg:postcode":"54494",
    "sg:province":"WI",
    "sg:tags":[
        "general",
        "contractor"
    ],
    "wof:name":"Lee Building & Remodeling",
    "wof:placetype":"venue"
},
  "geometry": {"coordinates":[-89.79346200000001,44.349546],"type":"Point"}
}