{
  "type": "Feature",
  "properties": {
    "addr:full":"920 US Hwy 12 Baraboo WI 53965",
    "addr:housenumber":"920",
    "addr:postcode":"53965",
    "addr:street":"Us Hwy 12",
    "iso:country":"US",
    "sg:address":"920 US Hwy 12",
    "sg:city":"Baraboo",
    "sg:classifiers":[
        {
            "category":"Personal",
            "subcategory":"Beauty Salon",
            "type":"Services"
        }
    ],
    "sg:phone":"+1 608 356 2366",
    "sg:postcode":"53965",
    "sg:province":"WI",
    "wof:name":"Cost Cutters Family Hair Care",
    "wof:placetype":"venue"
},
  "geometry": {"coordinates":[-89.78403900000001,43.586625],"type":"Point"}
}