{
  "type": "Feature",
  "properties": {
    "addr:full":"122 N Grand Ave Waukesha WI 53186",
    "addr:housenumber":"122",
    "addr:postcode":"53186",
    "addr:street":"N Grand Ave",
    "iso:country":"US",
    "sg:address":"122 N Grand Ave",
    "sg:city":"Waukesha",
    "sg:classifiers":[
        {
            "category":"Professional",
            "type":"Services"
        },
        {
            "category":"Restaurant",
            "type":"Food & Drink"
        }
    ],
    "sg:phone":"+1 262 513 8705",
    "sg:postcode":"53186",
    "sg:province":"WI",
    "wof:name":"Angel's Dog House",
    "wof:placetype":"venue"
},
  "geometry": {"coordinates":[-88.231949,43.003441],"type":"Point"}
}