{
  "type": "Feature",
  "properties": {
    "addr:full":"133 Walnut St Spooner WI 54801",
    "addr:housenumber":"133",
    "addr:postcode":"54801",
    "addr:street":"Walnut St",
    "iso:country":"US",
    "sg:address":"133 Walnut St",
    "sg:city":"Spooner",
    "sg:classifiers":[
        {
            "category":"Food & Beverages",
            "subcategory":"Specialty",
            "type":"Retail Goods"
        },
        {
            "category":"Wholesale",
            "subcategory":"Groceries",
            "type":"Manufacturing & Wholesale Goods"
        }
    ],
    "sg:phone":"+1 715 635 9791",
    "sg:postcode":"54801",
    "sg:province":"WI",
    "sg:tags":[
        "herbal",
        "remedy",
        "health",
        "encapsulated",
        "diet"
    ],
    "wof:name":"Vitamin Source Inc",
    "wof:placetype":"venue"
},
  "geometry": {"coordinates":[-91.887968,45.826505],"type":"Point"}
}