{
  "type": "Feature",
  "properties": {
    "iso:country":"US",
    "sg:address":"5577 Twin Lane Rd",
    "sg:city":"Marshall",
    "sg:classifiers":[
        {
            "category":"Sports & Exercise",
            "subcategory":"Race Track",
            "type":"Entertainment"
        }
    ],
    "sg:phone":"+1 608 834 1439",
    "sg:postcode":"53559",
    "sg:province":"WI",
    "sg:tags":[
        "operation",
        "racing",
        "or"
    ],
    "wof:name":"Rec Auto of Wisconsin Inc",
    "wof:placetype":"venue"
},
  "geometry": {"coordinates":[-89.147811,43.155298],"type":"Point"}
}