{
  "type": "Feature",
  "properties": {
    "iso:country":"US",
    "sg:address":"711 Fairfax St",
    "sg:city":"Altoona",
    "sg:classifiers":[
        {
            "category":"Retail",
            "subcategory":"Car Wash",
            "type":"Services"
        }
    ],
    "sg:phone":"+1 715 835 3887",
    "sg:postcode":"54720",
    "sg:province":"WI",
    "sg:tags":[
        "polishing",
        "washing"
    ],
    "wof:name":"Mike's Car Wash",
    "wof:placetype":"venue"
},
  "geometry": {"coordinates":[-91.46829,44.802086],"type":"Point"}
}