{
  "type": "Feature",
  "properties": {
    "iso:country":"US",
    "sg:address":"1116 Fox River Dr",
    "sg:city":"De Pere",
    "sg:classifiers":[
        {
            "category":"Professional",
            "subcategory":"Business Services",
            "type":"Services"
        }
    ],
    "sg:phone":"+1 920 336 1059",
    "sg:postcode":"54115",
    "sg:province":"WI",
    "wof:name":"Conlon Enterprises",
    "wof:placetype":"venue"
},
  "geometry": {"coordinates":[-88.064527,44.439887],"type":"Point"}
}