{
  "type": "Feature",
  "properties": {
    "iso:country":"US",
    "sg:address":"2101 Royal Ave",
    "sg:city":"Madison",
    "sg:classifiers":[
        {
            "category":"Shopping",
            "subcategory":"Pharmacy",
            "type":"Retail Goods"
        }
    ],
    "sg:phone":"+1 608 221 9015",
    "sg:postcode":"53713",
    "sg:province":"WI",
    "wof:name":"Kmart",
    "wof:placetype":"venue"
},
  "geometry": {"coordinates":[-89.35957500000001,43.043378],"type":"Point"}
}