{
  "type": "Feature",
  "properties": {
    "addr:full":"10464 S Leisure Dr Hazelhurst WI 54531",
    "addr:housenumber":"10464",
    "addr:postcode":"54531",
    "addr:street":"S Leisure Dr",
    "iso:country":"US",
    "sg:address":"10464 S Leisure Dr",
    "sg:city":"Hazelhurst",
    "sg:classifiers":[
        {
            "category":"Utilities",
            "subcategory":"Telephone",
            "type":"Services"
        }
    ],
    "sg:phone":"+1 715 356 2398",
    "sg:postcode":"54531",
    "sg:province":"WI",
    "sg:tags":[
        "telecommunication"
    ],
    "wof:name":"Orius Telecommunication",
    "wof:placetype":"venue"
},
  "geometry": {"coordinates":[-89.767186,45.736721],"type":"Point"}
}