{
  "type": "Feature",
  "properties": {
    "iso:country":"US",
    "sg:address":"10310 Diamond Rd",
    "sg:city":"Whitelaw",
    "sg:classifiers":[
        {
            "category":"Professional",
            "type":"Services"
        }
    ],
    "sg:phone":"+1 920 682 1486",
    "sg:postcode":"54247",
    "sg:province":"WI",
    "wof:name":"Ethel Porubcansky",
    "wof:placetype":"venue"
},
  "geometry": {"coordinates":[-87.731653,44.227411],"type":"Point"}
}