{
  "type": "Feature",
  "properties": {
    "addr:full":"922 S 70th St Milwaukee WI 53214",
    "addr:housenumber":"922",
    "addr:postcode":"53214",
    "addr:street":"S 70Th St",
    "iso:country":"US",
    "sg:address":"922 S 70th St",
    "sg:city":"Milwaukee",
    "sg:classifiers":[
        {
            "category":"Manufacturing",
            "subcategory":"Signs",
            "type":"Manufacturing & Wholesale Goods"
        }
    ],
    "sg:phone":"+1 414 453 4010",
    "sg:postcode":"53214",
    "sg:province":"WI",
    "sg:website":"www.poblocki.com",
    "wof:name":"Poblocki & Sons LLC",
    "wof:placetype":"venue"
},
  "geometry": {"coordinates":[-87.999892,43.022215],"type":"Point"}
}