{
  "type": "Feature",
  "properties": {
    "iso:country":"US",
    "sg:address":"1945 N 30th St",
    "sg:city":"Milwaukee",
    "sg:classifiers":[
        {
            "category":"Building & Trades",
            "subcategory":"Construction",
            "type":"Services"
        }
    ],
    "sg:phone":"+1 414 342 4220",
    "sg:postcode":"53208",
    "sg:province":"WI",
    "sg:tags":[
        "paint",
        "varnish",
        "contractor",
        "removal"
    ],
    "wof:name":"Adams Industries Inc",
    "wof:placetype":"venue"
},
  "geometry": {"coordinates":[-87.951091,43.055744],"type":"Point"}
}