{
  "type": "Feature",
  "properties": {
    "iso:country":"US",
    "sg:address":"2265 Powder Hill Rd",
    "sg:city":"Hartford",
    "sg:classifiers":[
        {
            "category":"Farming",
            "subcategory":"Livestock Farm",
            "type":"Manufacturing & Wholesale Goods"
        }
    ],
    "sg:phone":"+1 262 644 6564",
    "sg:postcode":"53027",
    "sg:province":"WI",
    "sg:tags":[
        "feedlot",
        "grain",
        "cash",
        "beef",
        "cattle"
    ],
    "wof:name":"Ehmke Farms",
    "wof:placetype":"venue"
},
  "geometry": {"coordinates":[-88.30475800000001,43.273047],"type":"Point"}
}