{
  "type": "Feature",
  "properties": {
    "iso:country":"US",
    "sg:address":"3120 Kennedy Rd",
    "sg:city":"Janesville",
    "sg:classifiers":[
        {
            "category":"Organizations",
            "subcategory":"Professional Association",
            "type":"Services"
        }
    ],
    "sg:phone":"+1 608 752 5055",
    "sg:postcode":"53545",
    "sg:province":"WI",
    "sg:website":"www.seventhdaybaptist.org",
    "wof:name":"Seventh Day Baptist Ctr",
    "wof:placetype":"venue"
},
  "geometry": {"coordinates":[-89.00592,42.720093],"type":"Point"}
}