{
  "type": "Feature",
  "properties": {
    "iso:country":"US",
    "sg:address":"1117 W Mason St",
    "sg:city":"Green Bay",
    "sg:classifiers":[
        {
            "category":"Food & Beverages",
            "subcategory":"Bakery",
            "type":"Retail Goods"
        }
    ],
    "sg:phone":"+1 920 499 6711",
    "sg:postcode":"54303",
    "sg:province":"WI",
    "wof:name":"Marquette Bakery",
    "wof:placetype":"venue"
},
  "geometry": {"coordinates":[-88.044726,44.516842],"type":"Point"}
}