{
  "type": "Feature",
  "properties": {
    "iso:country":"US",
    "sg:address":"712 James Ct",
    "sg:city":"West Bend",
    "sg:classifiers":[
        {
            "category":"Building & Trades",
            "subcategory":"Construction",
            "type":"Services"
        }
    ],
    "sg:phone":"+1 262 338 8610",
    "sg:postcode":"53095",
    "sg:province":"WI",
    "sg:tags":[
        "contractor"
    ],
    "wof:name":"D W Mc Elhatton Plaster",
    "wof:placetype":"venue"
},
  "geometry": {"coordinates":[-88.167665,43.414864],"type":"Point"}
}