{
  "type": "Feature",
  "properties": {
    "addr:full":"3498 County Line Rd Colgate WI 53017",
    "addr:housenumber":"3498",
    "addr:postcode":"53017",
    "addr:street":"County Line Rd Colgate",
    "iso:country":"US",
    "sg:address":"3498 County Line Rd",
    "sg:city":"Colgate",
    "sg:classifiers":[
        {
            "category":"Professional",
            "subcategory":"Employment Agencies",
            "type":"Services"
        }
    ],
    "sg:phone":"+1 414 702 3656",
    "sg:postcode":"53017",
    "sg:province":"WI",
    "wof:name":"Elizabeth L Raap",
    "wof:placetype":"venue"
},
  "geometry": {"coordinates":[-88.221918,43.193021],"type":"Point"}
}