{
  "type": "Feature",
  "properties": {
    "addr:full":"41 S Park Ave Fond Du Lac WI 54935",
    "addr:housenumber":"41",
    "addr:postcode":"54935",
    "addr:street":"S Park Ave",
    "iso:country":"US",
    "sg:address":"41 S Park Ave",
    "sg:city":"Fond Du Lac",
    "sg:classifiers":[
        {
            "category":"Freight",
            "type":"Transportation"
        }
    ],
    "sg:phone":"+1 920 929 9709",
    "sg:postcode":"54935",
    "sg:province":"WI",
    "sg:tags":[
        "commercial",
        "storage"
    ],
    "wof:name":"A-Ok Mini Storage",
    "wof:placetype":"venue"
},
  "geometry": {"coordinates":[-88.43887100000001,43.777272],"type":"Point"}
}