{
  "type": "Feature",
  "properties": {
    "iso:country":"US",
    "sg:address":"827 Navarino St",
    "sg:city":"Algoma",
    "sg:classifiers":[
        {
            "category":"Shopping",
            "subcategory":"Used Merchandise",
            "type":"Retail Goods"
        }
    ],
    "sg:phone":"+1 920 487 3069",
    "sg:postcode":"54201",
    "sg:province":"WI",
    "wof:name":"Antique Loft",
    "wof:placetype":"venue"
},
  "geometry": {"coordinates":[-87.44482499999999,44.610529],"type":"Point"}
}