{
  "type": "Feature",
  "properties": {
    "iso:country":"US",
    "sg:address":"999 Riverview Dr",
    "sg:city":"Green Bay",
    "sg:classifiers":[
        {
            "category":"Real Estate",
            "subcategory":"Real Estate Operator",
            "type":"Services"
        }
    ],
    "sg:phone":"+1 920 434 0301",
    "sg:postcode":"54303",
    "sg:province":"WI",
    "sg:tags":[
        "building",
        "nonresidential"
    ],
    "wof:name":"Brunette Properties Green Bay",
    "wof:placetype":"venue"
},
  "geometry": {"coordinates":[-88.061757,44.563738],"type":"Point"}
}