{
  "type": "Feature",
  "properties": {
    "iso:country":"US",
    "sg:address":"5649 Lakeview Dr",
    "sg:city":"Greendale",
    "sg:classifiers":[
        {
            "category":"Real Estate",
            "subcategory":"Real Estate Agent",
            "type":"Services"
        }
    ],
    "sg:phone":"+1 414 421 5748",
    "sg:postcode":"53129",
    "sg:province":"WI",
    "wof:name":"Valuation Wood Assoc LLC",
    "wof:placetype":"venue"
},
  "geometry": {"coordinates":[-87.986469,42.936743],"type":"Point"}
}