{
  "type": "Feature",
  "properties": {
    "addr:full":"1430 Old Bridge Rd Campbellsport WI 53010",
    "addr:housenumber":"1430",
    "addr:postcode":"53010",
    "addr:street":"Old Bridge Rd",
    "iso:country":"US",
    "sg:address":"1430 Old Bridge Rd",
    "sg:city":"Campbellsport",
    "sg:classifiers":[
        {
            "category":"Building & Trades",
            "subcategory":"Plumbing",
            "type":"Services"
        }
    ],
    "sg:phone":"+1 262 626 1605",
    "sg:postcode":"53010",
    "sg:province":"WI",
    "sg:tags":[
        "plumbing",
        "contractor"
    ],
    "wof:name":"Tom Johann Plumbing",
    "wof:placetype":"venue"
},
  "geometry": {"coordinates":[-88.226221,43.55748],"type":"Point"}
}