{
  "type": "Feature",
  "properties": {
    "addr:full":"1048 Lakefield Rd Grafton WI 53024",
    "addr:housenumber":"1048",
    "addr:postcode":"53024",
    "addr:street":"Lakefield Rd",
    "iso:country":"US",
    "sg:address":"1048 Lakefield Rd",
    "sg:city":"Grafton",
    "sg:classifiers":[
        {
            "category":"Recreation",
            "type":"Entertainment"
        }
    ],
    "sg:phone":"+1 262 377 0250",
    "sg:postcode":"53024",
    "sg:province":"WI",
    "sg:tags":[
        "stable"
    ],
    "wof:name":"Northshore Equestrian",
    "wof:placetype":"venue"
},
  "geometry": {"coordinates":[-87.920755,43.294788],"type":"Point"}
}