{
  "type": "Feature",
  "properties": {
    "iso:country":"US",
    "sg:address":"1920 Crest View Dr",
    "sg:city":"Hudson",
    "sg:classifiers":[
        {
            "category":"Cinema",
            "subcategory":"Movie Theater",
            "type":"Entertainment"
        }
    ],
    "sg:phone":"+1 715 381 5639",
    "sg:postcode":"54016",
    "sg:province":"WI",
    "wof:name":"Cinema Entertainment Corp",
    "wof:placetype":"venue"
},
  "geometry": {"coordinates":[-92.73101,44.962608],"type":"Point"}
}