{
  "type": "Feature",
  "properties": {
    "iso:country":"US",
    "sg:address":"5010 Felland Rd",
    "sg:city":"Madison",
    "sg:classifiers":[
        {
            "category":"Building & Trades",
            "subcategory":"Construction",
            "type":"Services"
        }
    ],
    "sg:phone":"+1 608 242 0966",
    "sg:postcode":"53718",
    "sg:province":"WI",
    "sg:tags":[
        "house"
    ],
    "wof:name":"Mark Munson Construction",
    "wof:placetype":"venue"
},
  "geometry": {"coordinates":[-89.276227,43.119287],"type":"Point"}
}