{
  "type": "Feature",
  "properties": {
    "iso:country":"US",
    "sg:address":"2401 Tower Ave",
    "sg:city":"Superior",
    "sg:classifiers":[
        {
            "category":"Social Services",
            "type":"Services"
        }
    ],
    "sg:phone":"+1 715 392 1726",
    "sg:postcode":"54880",
    "sg:province":"WI",
    "sg:tags":[
        "organization",
        "welfare"
    ],
    "wof:name":"Goodwill Industries",
    "wof:placetype":"venue"
},
  "geometry": {"coordinates":[-92.104005,46.707764],"type":"Point"}
}