{
  "type": "Feature",
  "properties": {
    "iso:country":"US",
    "sg:address":"401 S Wright Rd",
    "sg:city":"Janesville",
    "sg:classifiers":[
        {
            "category":"Manufacturing",
            "subcategory":"Tools & Machinery",
            "type":"Manufacturing & Wholesale Goods"
        }
    ],
    "sg:phone":"+1 608 754 2345",
    "sg:postcode":"53546",
    "sg:province":"WI",
    "sg:tags":[
        "physician",
        "surgeon"
    ],
    "sg:website":"www.labsafety.com",
    "wof:name":"Lab Safety Supply Inc",
    "wof:placetype":"venue"
},
  "geometry": {"coordinates":[-88.97326,42.674609],"type":"Point"}
}