{
  "type": "Feature",
  "properties": {
    "addr:full":"1305 Bluff Ave Racine WI 53403",
    "addr:housenumber":"1305",
    "addr:postcode":"53403",
    "addr:street":"Bluff Ave",
    "iso:country":"US",
    "sg:address":"1305 Bluff Ave",
    "sg:city":"Racine",
    "sg:classifiers":[
        {
            "category":"Professional",
            "subcategory":"Business Services",
            "type":"Services"
        }
    ],
    "sg:phone":"+1 262 736 4390",
    "sg:postcode":"53403",
    "sg:province":"WI",
    "wof:name":"Ohana Group Home",
    "wof:placetype":"venue"
},
  "geometry": {"coordinates":[-87.800849,42.715575],"type":"Point"}
}