{
  "type": "Feature",
  "properties": {
    "iso:country":"US",
    "sg:address":"538 Mill St",
    "sg:city":"Green Lake",
    "sg:classifiers":[
        {
            "category":"Bars & Pubs",
            "type":"Food & Drink"
        }
    ],
    "sg:phone":"+1 920 294 9903",
    "sg:postcode":"54941",
    "sg:province":"WI",
    "sg:tags":[
        "tavern"
    ],
    "wof:name":"Adams Ribs",
    "wof:placetype":"venue"
},
  "geometry": {"coordinates":[-88.96009599999999,43.846652],"type":"Point"}
}