{
  "type": "Feature",
  "properties": {
    "iso:country":"US",
    "sg:address":"3519 N Hubbard St",
    "sg:city":"Milwaukee",
    "sg:classifiers":[
        {
            "category":"Wholesale",
            "subcategory":"Dairy",
            "type":"Manufacturing & Wholesale Goods"
        }
    ],
    "sg:phone":"+1 414 264 0040",
    "sg:postcode":"53212",
    "sg:province":"WI",
    "sg:tags":[
        "product",
        "frozen",
        "desserts-manufacturers",
        "ice",
        "distributor",
        "cream"
    ],
    "wof:name":"Wilke Dairy Co",
    "wof:placetype":"venue"
},
  "geometry": {"coordinates":[-87.90860600000001,43.082231],"type":"Point"}
}