{
  "type": "Feature",
  "properties": {
    "addr:full":"2725 Co Rd V Lodi WI 53555",
    "addr:housenumber":"2725",
    "addr:postcode":"53555",
    "addr:street":"Co Rd V",
    "iso:country":"US",
    "sg:address":"2725 Co Rd V",
    "sg:city":"Lodi",
    "sg:classifiers":[
        {
            "category":"Personal",
            "subcategory":"Beauty Salon",
            "type":"Services"
        }
    ],
    "sg:phone":"+1 608 592 7055",
    "sg:postcode":"53555",
    "sg:province":"WI",
    "sg:tags":[
        "shop"
    ],
    "wof:name":"Harmony Grove Barber Shop",
    "wof:placetype":"venue"
},
  "geometry": {"coordinates":[-89.54118,43.376325],"type":"Point"}
}