{
  "type": "Feature",
  "properties": {
    "iso:country":"US",
    "sg:address":"1002 Washington St",
    "sg:city":"Grafton",
    "sg:classifiers":[
        {
            "category":"Building & Trades",
            "subcategory":"Construction",
            "type":"Services"
        }
    ],
    "sg:phone":"+1 262 375 3892",
    "sg:postcode":"53024",
    "sg:province":"WI",
    "sg:tags":[
        "excavation",
        "excavating",
        "contractor"
    ],
    "wof:name":"William Hilgart and Sons",
    "wof:placetype":"venue"
},
  "geometry": {"coordinates":[-87.953034,43.320011],"type":"Point"}
}