{
  "type": "Feature",
  "properties": {
    "addr:full":"248 E Main St Twin Lakes WI 53181",
    "addr:housenumber":"248",
    "addr:postcode":"53181",
    "addr:street":"E Main St",
    "iso:country":"US",
    "sg:address":"248 E Main St",
    "sg:city":"Twin Lakes",
    "sg:classifiers":[
        {
            "category":"Social Services",
            "subcategory":"Child Care",
            "type":"Services"
        }
    ],
    "sg:phone":"+1 262 877 3221",
    "sg:postcode":"53181",
    "sg:province":"WI",
    "wof:name":"Grace Lutheran Child Dev Ctr",
    "wof:placetype":"venue"
},
  "geometry": {"coordinates":[-88.251598,42.531604],"type":"Point"}
}