{
  "type": "Feature",
  "properties": {
    "iso:country":"US",
    "sg:address":"2412 Fox River Pkwy",
    "sg:city":"Waukesha",
    "sg:classifiers":[
        {
            "category":"Real Estate",
            "subcategory":"Real Estate Operator",
            "type":"Services"
        }
    ],
    "sg:phone":"+1 262 574 6964",
    "sg:postcode":"53189",
    "sg:province":"WI",
    "sg:tags":[
        "property",
        "lessor"
    ],
    "wof:name":"Jospeh Eldredge Property",
    "wof:placetype":"venue"
},
  "geometry": {"coordinates":[-88.263011,42.966939],"type":"Point"}
}