{
  "type": "Feature",
  "properties": {
    "iso:country":"US",
    "sg:address":"1207 Burbank Ave",
    "sg:city":"Janesville",
    "sg:classifiers":[
        {
            "category":"Shopping",
            "subcategory":"Used Merchandise",
            "type":"Retail Goods"
        }
    ],
    "sg:phone":"+1 608 314 0851",
    "sg:postcode":"53546",
    "sg:province":"WI",
    "wof:name":"Veterans Thrift Store",
    "wof:placetype":"venue"
},
  "geometry": {"coordinates":[-89.03268300000001,42.646521],"type":"Point"}
}