{
  "type": "Feature",
  "properties": {
    "iso:country":"US",
    "sg:address":"461 N 35th St",
    "sg:city":"Milwaukee",
    "sg:classifiers":[
        {
            "category":"Organizations",
            "subcategory":"Community Association",
            "type":"Services"
        },
        {
            "category":"Social Services",
            "type":"Services"
        }
    ],
    "sg:phone":"+1 414 342 6399",
    "sg:postcode":"53208",
    "sg:province":"WI",
    "wof:name":"Fred Green Community Center",
    "wof:placetype":"venue"
},
  "geometry": {"coordinates":[-87.957796,43.035321],"type":"Point"}
}