{
  "type": "Feature",
  "properties": {
    "iso:country":"US",
    "sg:address":"305 Clay St",
    "sg:city":"Neillsville",
    "sg:classifiers":[
        {
            "category":"Organizations",
            "subcategory":"Community Association",
            "type":"Services"
        }
    ],
    "sg:phone":"+1 715 743 4170",
    "sg:postcode":"54456",
    "sg:province":"WI",
    "wof:name":"Rotary Club of Neillsvill",
    "wof:placetype":"venue"
},
  "geometry": {"coordinates":[-90.599879,44.557537],"type":"Point"}
}