{
  "type": "Feature",
  "properties": {
    "iso:country":"US",
    "sg:address":"205 Oak St",
    "sg:city":"Neillsville",
    "sg:classifiers":[
        {
            "category":"Freight",
            "type":"Transportation"
        }
    ],
    "sg:phone":"+1 715 743 2791",
    "sg:postcode":"54456",
    "sg:province":"WI",
    "sg:tags":[
        "operator",
        "trucking"
    ],
    "wof:name":"Harold Boon",
    "wof:placetype":"venue"
},
  "geometry": {"coordinates":[-90.601385,44.558908],"type":"Point"}
}