{
  "type": "Feature",
  "properties": {
    "iso:country":"US",
    "sg:address":"177 Arrowhead Rd",
    "sg:city":"Fremont",
    "sg:classifiers":[
        {
            "category":"Farming",
            "subcategory":"Farm",
            "type":"Manufacturing & Wholesale Goods"
        }
    ],
    "sg:phone":"+1 920 446 3416",
    "sg:postcode":"54940",
    "sg:province":"WI",
    "sg:tags":[
        "crop",
        "general"
    ],
    "wof:name":"Kohl John",
    "wof:placetype":"venue"
},
  "geometry": {"coordinates":[-88.852275,44.243862],"type":"Point"}
}