{
  "type": "Feature",
  "properties": {
    "iso:country":"US",
    "sg:address":"4600 S Packard Ave",
    "sg:city":"Cudahy",
    "sg:classifiers":[
        {
            "category":"Professional",
            "subcategory":"Lawyer & Legal Services",
            "type":"Services"
        }
    ],
    "sg:phone":"+1 414 744 7960",
    "sg:postcode":"53110",
    "sg:province":"WI",
    "sg:tags":[
        "attorney"
    ],
    "wof:name":"Jursik & Jursik",
    "wof:placetype":"venue"
},
  "geometry": {"coordinates":[-87.860069,42.960041],"type":"Point"}
}