{
  "type": "Feature",
  "properties": {
    "iso:country":"US",
    "sg:address":"5641 Katie Ln",
    "sg:city":"Conover",
    "sg:classifiers":[
        {
            "category":"Building & Trades",
            "subcategory":"Construction",
            "type":"Services"
        }
    ],
    "sg:phone":"+1 715 479 1592",
    "sg:postcode":"54519",
    "sg:province":"WI",
    "sg:tags":[
        "dry wall",
        "contractor"
    ],
    "wof:name":"Steve Lagueux",
    "wof:placetype":"venue"
},
  "geometry": {"coordinates":[-89.31182,46.030425],"type":"Point"}
}