{
  "type": "Feature",
  "properties": {
    "iso:country":"US",
    "sg:address":"2277 N New Franken Rd",
    "sg:city":"New Franken",
    "sg:classifiers":[
        {
            "category":"Farming",
            "subcategory":"Farm",
            "type":"Manufacturing & Wholesale Goods"
        }
    ],
    "sg:phone":"+1 920 845 5691",
    "sg:postcode":"54229",
    "sg:province":"WI",
    "sg:tags":[
        "crop",
        "general"
    ],
    "wof:name":"Bio AG Farm Sply",
    "wof:placetype":"venue"
},
  "geometry": {"coordinates":[-87.825931,44.530952],"type":"Point"}
}