{
  "type": "Feature",
  "properties": {
    "iso:country":"US",
    "sg:address":"2777 N 49th St",
    "sg:city":"Milwaukee",
    "sg:classifiers":[
        {
            "category":"Building & Trades",
            "subcategory":"Construction",
            "type":"Services"
        }
    ],
    "sg:phone":"+1 414 442 7147",
    "sg:postcode":"53210",
    "sg:province":"WI",
    "sg:tags":[
        "residential",
        "concrete",
        "contractor"
    ],
    "wof:name":"J & J Construction",
    "wof:placetype":"venue"
},
  "geometry": {"coordinates":[-87.975004,43.068361],"type":"Point"}
}