{
  "type": "Feature",
  "properties": {
    "iso:country":"US",
    "sg:address":"315 Sumner St",
    "sg:city":"Genoa City",
    "sg:classifiers":[
        {
            "category":"Organizations",
            "subcategory":"Religious Organization",
            "type":"Services"
        }
    ],
    "sg:phone":"+1 262 279 2838",
    "sg:postcode":"53128",
    "sg:province":"WI",
    "sg:tags":[
        "church"
    ],
    "sg:website":"www.anchor-baptist-church.org",
    "wof:name":"Anchor Baptist Church",
    "wof:placetype":"venue"
},
  "geometry": {"coordinates":[-88.328571,42.498425],"type":"Point"}
}