{
  "type": "Feature",
  "properties": {
    "iso:country":"US",
    "sg:address":"305 Adams Ave",
    "sg:city":"Omro",
    "sg:classifiers":[
        {
            "category":"Autos & Motor Vehicles",
            "subcategory":"Boat Sales",
            "type":"Retail Goods"
        }
    ],
    "sg:phone":"+1 920 685 2280",
    "sg:postcode":"54963",
    "sg:province":"WI",
    "sg:tags":[
        "equipment",
        "marine",
        "supply"
    ],
    "wof:name":"Seaworthy Marine",
    "wof:placetype":"venue"
},
  "geometry": {"coordinates":[-88.747208,44.037619],"type":"Point"}
}