{
  "type": "Feature",
  "properties": {
    "iso:country":"US",
    "sg:address":"11790 Co Rd L",
    "sg:city":"Tomahawk",
    "sg:classifiers":[
        {
            "category":"Food & Beverages",
            "subcategory":"Groceries & Convenience Stores",
            "type":"Retail Goods"
        }
    ],
    "sg:phone":"+1 715 453 5888",
    "sg:postcode":"54487",
    "sg:province":"WI",
    "wof:name":"Kracker Barrel",
    "wof:placetype":"venue"
},
  "geometry": {"coordinates":[-89.718675,45.544859],"type":"Point"}
}