{
  "type": "Feature",
  "properties": {
    "addr:full":"933 6th Ave Antigo WI 54409",
    "addr:housenumber":"933",
    "addr:postcode":"54409",
    "addr:street":"6Th Ave",
    "iso:country":"US",
    "sg:address":"933 6th Ave",
    "sg:city":"Antigo",
    "sg:classifiers":[
        {
            "category":"Insurance",
            "subcategory":"Life Insurance",
            "type":"Services"
        }
    ],
    "sg:phone":"+1 715 623 6404",
    "sg:postcode":"54409",
    "sg:province":"WI",
    "sg:tags":[
        "carrier"
    ],
    "wof:name":"Cancer America",
    "wof:placetype":"venue"
},
  "geometry": {"coordinates":[-89.156848,45.139083],"type":"Point"}
}