{
  "type": "Feature",
  "properties": {
    "iso:country":"US",
    "sg:address":"4236 Co Rd Nn",
    "sg:city":"Elkhorn",
    "sg:classifiers":[
        {
            "category":"Building & Trades",
            "subcategory":"Construction",
            "type":"Services"
        }
    ],
    "sg:phone":"+1 262 248 4861",
    "sg:postcode":"53121",
    "sg:province":"WI",
    "sg:tags":[
        "home",
        "family"
    ],
    "wof:name":"Lazzaroni Builders Inc",
    "wof:placetype":"venue"
},
  "geometry": {"coordinates":[-88.46543800000001,42.644416],"type":"Point"}
}