{
  "type": "Feature",
  "properties": {
    "addr:full":"4809 W Center St Wauwatosa WI 53210",
    "addr:housenumber":"4809",
    "addr:postcode":"53210",
    "addr:street":"W Center St",
    "iso:country":"US",
    "sg:address":"4809 W Center St",
    "sg:city":"Wauwatosa",
    "sg:classifiers":[
        {
            "category":"Shopping",
            "subcategory":"Clothing, Apparel, & Fashions",
            "type":"Retail Goods"
        }
    ],
    "sg:phone":"+1 414 447 9718",
    "sg:postcode":"53210",
    "sg:province":"WI",
    "sg:tags":[
        "item",
        "boutique"
    ],
    "wof:name":"Deon's Boutique",
    "wof:placetype":"venue"
},
  "geometry": {"coordinates":[-87.97487,43.067876],"type":"Point"}
}