{
  "type": "Feature",
  "properties": {
    "iso:country":"US",
    "sg:address":"1259 Corporate Center Dr",
    "sg:city":"Oconomowoc",
    "sg:classifiers":[
        {
            "category":"Health Services",
            "subcategory":"Doctor",
            "type":"Services"
        }
    ],
    "sg:phone":"+1 262 567 8400",
    "sg:postcode":"53066",
    "sg:province":"WI",
    "sg:tags":[
        "dentist"
    ],
    "wof:name":"Peter Jahnke DDS",
    "wof:placetype":"venue"
},
  "geometry": {"coordinates":[-88.47277800000001,43.075001],"type":"Point"}
}