{
  "type": "Feature",
  "properties": {
    "addr:full":"5523 Riverview Dr Waunakee WI 53597",
    "addr:housenumber":"5523",
    "addr:postcode":"53597",
    "addr:street":"Riverview Dr",
    "iso:country":"US",
    "sg:address":"5523 Riverview Dr",
    "sg:city":"Waunakee",
    "sg:classifiers":[
        {
            "category":"Manufacturing",
            "subcategory":"Food",
            "type":"Manufacturing & Wholesale Goods"
        }
    ],
    "sg:phone":"+1 608 849 5483",
    "sg:postcode":"53597",
    "sg:province":"WI",
    "sg:tags":[
        "preparation",
        "mfg"
    ],
    "wof:name":"McCormick & Company Inc",
    "wof:placetype":"venue"
},
  "geometry": {"coordinates":[-89.391443,43.157797],"type":"Point"}
}