{
  "type": "Feature",
  "properties": {
    "iso:country":"US",
    "sg:address":"40 W Hosmer St",
    "sg:city":"Marinette",
    "sg:classifiers":[
        {
            "category":"Bars & Pubs",
            "type":"Food & Drink"
        }
    ],
    "sg:phone":"+1 715 735 9849",
    "sg:postcode":"54143",
    "sg:province":"WI",
    "sg:tags":[
        "drinking"
    ],
    "wof:name":"Cactus Tavern",
    "wof:placetype":"venue"
},
  "geometry": {"coordinates":[-87.59928600000001,45.090522],"type":"Point"}
}