{
  "type": "Feature",
  "properties": {
    "iso:country":"US",
    "sg:address":"6555 W Good Hope Rd",
    "sg:city":"Milwaukee",
    "sg:classifiers":[
        {
            "category":"Manufacturing",
            "subcategory":"Retail Goods",
            "type":"Manufacturing & Wholesale Goods"
        }
    ],
    "sg:phone":"+1 414 358 6600",
    "sg:postcode":"53223",
    "sg:province":"WI",
    "sg:tags":[
        "identification"
    ],
    "sg:website":"www.bcw.com",
    "wof:name":"Brady Corp",
    "wof:placetype":"venue"
},
  "geometry": {"coordinates":[-87.999261,43.148566],"type":"Point"}
}