{
  "type": "Feature",
  "properties": {
    "iso:country":"US",
    "sg:address":"95 N Moorland Rd",
    "sg:city":"Brookfield",
    "sg:classifiers":[
        {
            "category":"Real Estate",
            "subcategory":"Real Estate Operator",
            "type":"Services"
        }
    ],
    "sg:phone":"+1 262 797 7245",
    "sg:postcode":"53005",
    "sg:province":"WI",
    "sg:tags":[
        "mall",
        "shopping",
        "center"
    ],
    "wof:name":"Brookfield Sq Shopping Ctr",
    "wof:placetype":"venue"
},
  "geometry": {"coordinates":[-88.106933,43.034839],"type":"Point"}
}