{
  "type": "Feature",
  "properties": {
    "iso:country":"US",
    "sg:address":"3401 Church Rd",
    "sg:city":"Kewaunee",
    "sg:classifiers":[
        {
            "category":"Food & Beverages",
            "subcategory":"Fruits & Vegetables",
            "type":"Retail Goods"
        }
    ],
    "sg:phone":"+1 920 388 4786",
    "sg:postcode":"54216",
    "sg:province":"WI",
    "sg:tags":[
        "produce"
    ],
    "wof:name":"Kraynik's Berry Farm",
    "wof:placetype":"venue"
},
  "geometry": {"coordinates":[-87.633416,44.447185],"type":"Point"}
}