{
  "type": "Feature",
  "properties": {
    "iso:country":"US",
    "sg:address":"2205 Washington Rd",
    "sg:city":"Kenosha",
    "sg:classifiers":[
        {
            "category":"Sports & Exercise",
            "subcategory":"Golf",
            "type":"Entertainment"
        }
    ],
    "sg:phone":"+1 262 653 4090",
    "sg:postcode":"53140",
    "sg:province":"WI",
    "sg:tags":[
        "course"
    ],
    "wof:name":"Washington Park Municipal Golf",
    "wof:placetype":"venue"
},
  "geometry": {"coordinates":[-87.84045999999999,42.602473],"type":"Point"}
}