{
  "type": "Feature",
  "properties": {
    "iso:country":"US",
    "sg:address":"927 Armstrong Ave",
    "sg:city":"Howards Grove",
    "sg:classifiers":[
        {
            "category":"Personal",
            "subcategory":"Tanning Parlor",
            "type":"Services"
        },
        {
            "category":"Personal",
            "type":"Services"
        }
    ],
    "sg:phone":"+1 920 565 3120",
    "sg:postcode":"53083",
    "sg:province":"WI",
    "sg:tags":[
        "salon"
    ],
    "wof:name":"J & R Tanning Salon",
    "wof:placetype":"venue"
},
  "geometry": {"coordinates":[-87.822829,43.834862],"type":"Point"}
}