{
  "type": "Feature",
  "properties": {
    "iso:country":"US",
    "sg:address":"541 W Concordia Ave",
    "sg:city":"Milwaukee",
    "sg:classifiers":[
        {
            "category":"Organizations",
            "subcategory":"Religious Organization",
            "type":"Services"
        }
    ],
    "sg:phone":"+1 414 264 0372",
    "sg:postcode":"53212",
    "sg:province":"WI",
    "sg:tags":[
        "church"
    ],
    "wof:name":"Holy Ghost Lutheran Church",
    "wof:placetype":"venue"
},
  "geometry": {"coordinates":[-87.917948,43.078786],"type":"Point"}
}