{
  "type": "Feature",
  "properties": {
    "iso:country":"US",
    "sg:address":"67295 Highland Rd",
    "sg:city":"Ashland",
    "sg:classifiers":[
        {
            "category":"Building & Trades",
            "subcategory":"Plumbing",
            "type":"Services"
        }
    ],
    "sg:phone":"+1 715 682 8802",
    "sg:postcode":"54806",
    "sg:province":"WI",
    "sg:tags":[
        "contractor"
    ],
    "wof:name":"4 Season Air",
    "wof:placetype":"venue"
},
  "geometry": {"coordinates":[-90.948408,46.516606],"type":"Point"}
}