{
  "type": "Feature",
  "properties": {
    "iso:country":"US",
    "sg:address":"1620 N Union St",
    "sg:city":"Appleton",
    "sg:classifiers":[
        {
            "category":"Organizations",
            "subcategory":"Non-profit Organization",
            "type":"Services"
        }
    ],
    "sg:phone":"+1 920 991 9390",
    "sg:postcode":"54911",
    "sg:province":"WI",
    "sg:tags":[
        "alternative",
        "abortion"
    ],
    "wof:name":"Fox Valley Right To Life",
    "wof:placetype":"venue"
},
  "geometry": {"coordinates":[-88.398204,44.276329],"type":"Point"}
}