{
  "type": "Feature",
  "properties": {
    "iso:country":"US",
    "sg:address":"8031 E State Line Rd",
    "sg:city":"Clinton",
    "sg:classifiers":[
        {
            "category":"Travel",
            "subcategory":"Campground",
            "type":"Entertainment"
        }
    ],
    "sg:phone":"+1 262 296 1800",
    "sg:postcode":"53525",
    "sg:province":"WI",
    "sg:tags":[
        "trailer"
    ],
    "wof:name":"Oaks Campground Inc",
    "wof:placetype":"venue"
},
  "geometry": {"coordinates":[-88.88637799999999,42.49406],"type":"Point"}
}