{
  "type": "Feature",
  "properties": {
    "iso:country":"US",
    "sg:address":"1053 Gillingham Rd",
    "sg:city":"Neenah",
    "sg:classifiers":[
        {
            "category":"Social Services",
            "subcategory":"Child Care",
            "type":"Services"
        }
    ],
    "sg:phone":"+1 920 725 2556",
    "sg:postcode":"54956",
    "sg:province":"WI",
    "sg:tags":[
        "day"
    ],
    "wof:name":"Little Treasures",
    "wof:placetype":"venue"
},
  "geometry": {"coordinates":[-88.48574000000001,44.168018],"type":"Point"}
}