{
  "type": "Feature",
  "properties": {
    "iso:country":"US",
    "sg:address":"3179 Muirfield Rd",
    "sg:city":"Madison",
    "sg:classifiers":[
        {
            "category":"Food & Beverages",
            "subcategory":"Liquor & Beverages",
            "type":"Retail Goods"
        }
    ],
    "sg:phone":"+1 608 848 6128",
    "sg:postcode":"53719",
    "sg:province":"WI",
    "sg:tags":[
        "alcoholic"
    ],
    "wof:name":"Paradise Liquor",
    "wof:placetype":"venue"
},
  "geometry": {"coordinates":[-89.511538,43.016334],"type":"Point"}
}