{
  "type": "Feature",
  "properties": {
    "iso:country":"US",
    "sg:address":"1810 W 6th St",
    "sg:city":"Racine",
    "sg:classifiers":[
        {
            "category":"Personal",
            "subcategory":"Beauty Salon",
            "type":"Services"
        }
    ],
    "sg:phone":"+1 262 632 5381",
    "sg:postcode":"53404",
    "sg:province":"WI",
    "wof:name":"Karen's Braiding",
    "wof:placetype":"venue"
},
  "geometry": {"coordinates":[-87.804075,42.72606],"type":"Point"}
}