{
  "type": "Feature",
  "properties": {
    "iso:country":"US",
    "sg:address":"379 N Falls St",
    "sg:city":"River Falls",
    "sg:classifiers":[
        {
            "category":"Social Services",
            "subcategory":"Child Care",
            "type":"Services"
        }
    ],
    "sg:phone":"+1 715 425 2298",
    "sg:postcode":"54022",
    "sg:province":"WI",
    "sg:tags":[
        "day"
    ],
    "wof:name":"Tiggers Tree School",
    "wof:placetype":"venue"
},
  "geometry": {"coordinates":[-92.633613,44.860919],"type":"Point"}
}