{
  "type": "Feature",
  "properties": {
    "iso:country":"US",
    "sg:address":"1776 Eastern Ave",
    "sg:city":"Plymouth",
    "sg:classifiers":[
        {
            "category":"Sports & Exercise",
            "subcategory":"Golf",
            "type":"Entertainment"
        }
    ],
    "sg:phone":"+1 920 893 8822",
    "sg:postcode":"53073",
    "sg:province":"WI",
    "sg:tags":[
        "course",
        "public"
    ],
    "wof:name":"Evergreen Golf Course",
    "wof:placetype":"venue"
},
  "geometry": {"coordinates":[-87.95788,43.747181],"type":"Point"}
}