{
  "type": "Feature",
  "properties": {
    "addr:full":"518 S Taylor Dr Sheboygan WI 53081",
    "addr:housenumber":"518",
    "addr:postcode":"53081",
    "addr:street":"S Taylor Dr",
    "iso:country":"US",
    "sg:address":"518 S Taylor Dr",
    "sg:city":"Sheboygan",
    "sg:classifiers":[
        {
            "category":"Health Services",
            "subcategory":"Optometrist",
            "type":"Services"
        }
    ],
    "sg:phone":"+1 920 458 5757",
    "sg:postcode":"53081",
    "sg:province":"WI",
    "wof:name":"Shannon Macnab Od",
    "wof:placetype":"venue"
},
  "geometry": {"coordinates":[-87.74968200000001,43.751992],"type":"Point"}
}