{
  "type": "Feature",
  "properties": {
    "addr:full":"3966 Maple Tree Rd Egg Harbor WI 54209",
    "addr:housenumber":"3966",
    "addr:postcode":"54209",
    "addr:street":"Maple Tree Rd",
    "iso:country":"US",
    "sg:address":"3966 Maple Tree Rd",
    "sg:city":"Egg Harbor",
    "sg:classifiers":[
        {
            "category":"Building & Trades",
            "subcategory":"Electrical",
            "type":"Services"
        }
    ],
    "sg:phone":"+1 920 868 3621",
    "sg:postcode":"54209",
    "sg:province":"WI",
    "sg:tags":[
        "electrical",
        "contractor"
    ],
    "wof:name":"Bogies Elec/Maint Service",
    "wof:placetype":"venue"
},
  "geometry": {"coordinates":[-87.232022,45.039799],"type":"Point"}
}