{
  "type": "Feature",
  "properties": {
    "iso:country":"US",
    "sg:address":"403 W Warehouse St",
    "sg:city":"Muscoda",
    "sg:classifiers":[
        {
            "category":"Freight",
            "type":"Transportation"
        }
    ],
    "sg:phone":"+1 608 739 4179",
    "sg:postcode":"53573",
    "sg:province":"WI",
    "sg:tags":[
        "operator",
        "local",
        "trucking"
    ],
    "wof:name":"Moriva Trucking LLC",
    "wof:placetype":"venue"
},
  "geometry": {"coordinates":[-90.447314,43.183472],"type":"Point"}
}