{
  "type": "Feature",
  "properties": {
    "addr:full":"436 1st Ave E Clear Lake WI 54005",
    "addr:housenumber":"436",
    "addr:postcode":"54005",
    "addr:street":"1St Ave E",
    "iso:country":"US",
    "sg:address":"436 1st Ave E",
    "sg:city":"Clear Lake",
    "sg:classifiers":[
        {
            "category":"Retail",
            "subcategory":"Animal Services",
            "type":"Services"
        }
    ],
    "sg:phone":"+1 715 263 3652",
    "sg:postcode":"54005",
    "sg:province":"WI",
    "sg:tags":[
        "pet",
        "boarding",
        "sitting"
    ],
    "wof:name":"Just Paws Pet Boarding & Shawn",
    "wof:placetype":"venue"
},
  "geometry": {"coordinates":[-92.26024,45.252781],"type":"Point"}
}