{
  "type": "Feature",
  "properties": {
    "iso:country":"US",
    "sg:address":"1116 Co Rd T W",
    "sg:city":"Lomira",
    "sg:classifiers":[
        {
            "category":"Shopping",
            "subcategory":"Florist",
            "type":"Retail Goods"
        }
    ],
    "sg:phone":"+1 920 488 4701",
    "sg:postcode":"53048",
    "sg:province":"WI",
    "sg:tags":[
        "nursery"
    ],
    "wof:name":"Park Floral Shop Inc",
    "wof:placetype":"venue"
},
  "geometry": {"coordinates":[-88.451267,43.536426],"type":"Point"}
}