{
  "type": "Feature",
  "properties": {
    "iso:country":"US",
    "sg:address":"9 E Spyglass Ct",
    "sg:city":"Madison",
    "sg:classifiers":[
        {
            "category":"Retail",
            "subcategory":"Laundry & Dry Cleaning",
            "type":"Services"
        }
    ],
    "sg:phone":"+1 608 827 8331",
    "sg:postcode":"53717",
    "sg:province":"WI",
    "wof:name":"Mackesey Carpet Cleaning LLC",
    "wof:placetype":"venue"
},
  "geometry": {"coordinates":[-89.497742,43.076069],"type":"Point"}
}