{
  "type": "Feature",
  "properties": {
    "iso:country":"US",
    "sg:address":"154 Memorial Dr",
    "sg:city":"Barron",
    "sg:classifiers":[
        {
            "category":"Organizations",
            "subcategory":"Religious Organization",
            "type":"Services"
        }
    ],
    "sg:phone":"+1 715 537 3229",
    "sg:postcode":"54812",
    "sg:province":"WI",
    "sg:tags":[
        "church"
    ],
    "sg:website":"www.barronumc.com",
    "wof:name":"First United Methodist Church",
    "wof:placetype":"venue"
},
  "geometry": {"coordinates":[-91.842702,45.399038],"type":"Point"}
}