{
  "type": "Feature",
  "properties": {
    "iso:country":"US",
    "sg:address":"126 Pine St",
    "sg:city":"Green Bay",
    "sg:classifiers":[
        {
            "category":"Arts & Performance",
            "subcategory":"Theater",
            "type":"Entertainment"
        }
    ],
    "sg:phone":"+1 920 435 3465",
    "sg:postcode":"54301",
    "sg:province":"WI",
    "sg:tags":[
        "band",
        "orchestra"
    ],
    "sg:website":"www.greenbaysymphony.org",
    "wof:name":"Green Bay Symphony Orchestra",
    "wof:placetype":"venue"
},
  "geometry": {"coordinates":[-88.01499,44.51626],"type":"Point"}
}