{
  "type": "Feature",
  "properties": {
    "addr:full":"4429 Laurel St Lake Geneva WI 53191",
    "addr:housenumber":"4429",
    "addr:postcode":"53191",
    "addr:street":"Laurel St",
    "iso:country":"US",
    "sg:address":"4429 Laurel St",
    "sg:city":"Lake Geneva",
    "sg:classifiers":[
        {
            "category":"Building & Trades",
            "subcategory":"Construction",
            "type":"Services"
        }
    ],
    "sg:phone":"+1 262 245 9055",
    "sg:postcode":"53191",
    "sg:province":"WI",
    "sg:tags":[
        "general",
        "contractor"
    ],
    "wof:name":"Liljegren & Knight Cnstr",
    "wof:placetype":"venue"
},
  "geometry": {"coordinates":[-88.511674,42.578786],"type":"Point"}
}