{
  "type": "Feature",
  "properties": {
    "iso:country":"US",
    "sg:address":"63770 Toman Rd",
    "sg:city":"Ashland",
    "sg:classifiers":[
        {
            "category":"Home & Garden",
            "subcategory":"Garden Supply",
            "type":"Retail Goods"
        }
    ],
    "sg:phone":"+1 715 746 2255",
    "sg:postcode":"54806",
    "sg:province":"WI",
    "sg:tags":[
        "tree",
        "christmas"
    ],
    "wof:name":"Toman Tree Farm",
    "wof:placetype":"venue"
},
  "geometry": {"coordinates":[-90.99247,46.498273],"type":"Point"}
}