{
  "type": "Feature",
  "properties": {
    "iso:country":"US",
    "sg:address":"22520 Apple Rd",
    "sg:city":"Union Grove",
    "sg:classifiers":[
        {
            "category":"Farming",
            "subcategory":"Livestock Farm",
            "type":"Manufacturing & Wholesale Goods"
        }
    ],
    "sg:phone":"+1 262 534 5850",
    "sg:postcode":"53182",
    "sg:province":"WI",
    "sg:tags":[
        "specialty",
        "animal"
    ],
    "wof:name":"North Cape Honey Farm LLC",
    "wof:placetype":"venue"
},
  "geometry": {"coordinates":[-88.098804,42.771704],"type":"Point"}
}