{
  "type": "Feature",
  "properties": {
    "iso:country":"US",
    "sg:address":"8213 Co Rd Jj",
    "sg:city":"Bancroft",
    "sg:classifiers":[
        {
            "category":"Home & Garden",
            "subcategory":"Hardware",
            "type":"Retail Goods"
        }
    ],
    "sg:phone":"+1 715 335 4534",
    "sg:postcode":"54921",
    "sg:province":"WI",
    "sg:tags":[
        "repair"
    ],
    "wof:name":"Dave Johnson Saw Sales",
    "wof:placetype":"venue"
},
  "geometry": {"coordinates":[-89.488151,44.316057],"type":"Point"}
}