{
  "type": "Feature",
  "properties": {
    "iso:country":"US",
    "sg:address":"10340 S Nicholson Rd",
    "sg:city":"Oak Creek",
    "sg:classifiers":[
        {
            "category":"Professional",
            "type":"Services"
        }
    ],
    "sg:phone":"+1 414 764 6447",
    "sg:postcode":"53154",
    "sg:province":"WI",
    "wof:name":"Sowinski Sewer & Water Inc",
    "wof:placetype":"venue"
},
  "geometry": {"coordinates":[-87.89348699999999,42.856238],"type":"Point"}
}