{
  "type": "Feature",
  "properties": {
    "iso:country":"US",
    "sg:address":"544 East Ogden Avenue, #700-120",
    "sg:city":"Milwaukee",
    "sg:classifiers":[
        {
            "category":"Professional",
            "subcategory":"Business Services",
            "type":"Services"
        }
    ],
    "sg:postcode":"53202 ",
    "sg:province":"WI",
    "sg:website":"http://donovangroupholdings.com/",
    "wof:name":"Donovan Group Holdings LLC",
    "wof:placetype":"venue"
},
  "geometry": {"coordinates":[-87.905214,43.04823],"type":"Point"}
}