{
  "type": "Feature",
  "properties": {
    "iso:country":"US",
    "sg:address":"8375 Michael Dr",
    "sg:city":"Eau Claire",
    "sg:classifiers":[
        {
            "category":"Building & Trades",
            "subcategory":"Construction",
            "type":"Services"
        }
    ],
    "sg:phone":"+1 715 878 9492",
    "sg:postcode":"54701",
    "sg:province":"WI",
    "sg:tags":[
        "house"
    ],
    "wof:name":"Brunkow Builders Inc",
    "wof:placetype":"venue"
},
  "geometry": {"coordinates":[-91.44962099999999,44.712133],"type":"Point"}
}