{
  "type": "Feature",
  "properties": {
    "iso:country":"US",
    "sg:address":"1011 Silver Lake Dr",
    "sg:city":"Portage",
    "sg:classifiers":[
        {
            "category":"Airport",
            "type":"Transportation"
        }
    ],
    "sg:phone":"+1 608 742 3300",
    "sg:postcode":"53901",
    "sg:province":"WI",
    "sg:tags":[
        "equipment"
    ],
    "wof:name":"Portage Municipal Airport",
    "wof:placetype":"venue"
},
  "geometry": {"coordinates":[-89.48187900000001,43.555363],"type":"Point"}
}