{
  "type": "Feature",
  "properties": {
    "iso:country":"US",
    "sg:address":"1211 Sunnyside Dr",
    "sg:city":"Sullivan",
    "sg:classifiers":[
        {
            "category":"Wholesale",
            "subcategory":"Electrical",
            "type":"Manufacturing & Wholesale Goods"
        }
    ],
    "sg:phone":"+1 262 593 2215",
    "sg:postcode":"53178",
    "sg:province":"WI",
    "sg:tags":[
        "equipment",
        "lighting",
        "system"
    ],
    "wof:name":"Innovative Outdoor Products",
    "wof:placetype":"venue"
},
  "geometry": {"coordinates":[-88.595325,43.039819],"type":"Point"}
}