{
  "type": "Feature",
  "properties": {
    "iso:country":"US",
    "sg:address":"1019 Hazel St",
    "sg:city":"Oshkosh",
    "sg:classifiers":[
        {
            "category":"Manufacturing",
            "subcategory":"Metals",
            "type":"Manufacturing & Wholesale Goods"
        }
    ],
    "sg:phone":"+1 920 231 4000",
    "sg:postcode":"54901",
    "sg:province":"WI",
    "sg:tags":[
        "computer",
        "controlled",
        "tire",
        "mfg"
    ],
    "wof:name":"Explorer Engineering Corp",
    "wof:placetype":"venue"
},
  "geometry": {"coordinates":[-88.522626,44.030696],"type":"Point"}
}