{
  "type": "Feature",
  "properties": {
    "addr:full":"206 W Whitewater St Whitewater WI 53190",
    "addr:housenumber":"206",
    "addr:postcode":"53190",
    "addr:street":"W Whitewater St",
    "iso:country":"US",
    "sg:address":"206 W Whitewater St",
    "sg:city":"Whitewater",
    "sg:classifiers":[
        {
            "category":"Professional",
            "subcategory":"Management & Consulting",
            "type":"Services"
        }
    ],
    "sg:phone":"+1 262 473 7166",
    "sg:postcode":"53190",
    "sg:province":"WI",
    "sg:tags":[
        "consultant"
    ],
    "wof:name":"Jillian Mass Backman",
    "wof:placetype":"venue"
},
  "geometry": {"coordinates":[-88.7321,42.832733],"type":"Point"}
}