{
  "type": "Feature",
  "properties": {
    "addr:full":"5371 Park Ave Merrill WI 54452",
    "addr:housenumber":"5371",
    "addr:postcode":"54452",
    "addr:street":"Park Ave",
    "iso:country":"US",
    "sg:address":"5371 Park Ave",
    "sg:city":"Merrill",
    "sg:classifiers":[
        {
            "category":"Farming",
            "subcategory":"Dairy Farm",
            "type":"Manufacturing & Wholesale Goods"
        }
    ],
    "sg:phone":"+1 715 536 5117",
    "sg:postcode":"54452",
    "sg:province":"WI",
    "wof:name":"Park Ave Dairy LLC",
    "wof:placetype":"venue"
},
  "geometry": {"coordinates":[-89.711443,45.145221],"type":"Point"}
}