{
  "type": "Feature",
  "properties": {
    "iso:country":"US",
    "sg:address":"3042 Co Rd G",
    "sg:city":"Cobb",
    "sg:classifiers":[
        {
            "category":"Building & Trades",
            "subcategory":"Plumbing",
            "type":"Services"
        }
    ],
    "sg:phone":"+1 608 623 3215",
    "sg:postcode":"53526",
    "sg:province":"WI",
    "sg:tags":[
        "contractor"
    ],
    "wof:name":"Havlik Plumbing",
    "wof:placetype":"venue"
},
  "geometry": {"coordinates":[-90.329831,42.961737],"type":"Point"}
}