{
  "type": "Feature",
  "properties": {
    "iso:country":"US",
    "sg:address":"1409 Shannon St",
    "sg:city":"Green Bay",
    "sg:classifiers":[
        {
            "category":"Manufacturing",
            "subcategory":"Jewelry",
            "type":"Manufacturing & Wholesale Goods"
        }
    ],
    "sg:phone":"+1 920 494 5371",
    "sg:postcode":"54304",
    "sg:province":"WI",
    "sg:tags":[
        "costume",
        "mfg"
    ],
    "wof:name":"CJ Design",
    "wof:placetype":"venue"
},
  "geometry": {"coordinates":[-88.080338,44.5151],"type":"Point"}
}