{
  "type": "Feature",
  "properties": {
    "iso:country":"US",
    "sg:address":"417 12th St",
    "sg:city":"Baraboo",
    "sg:classifiers":[
        {
            "category":"Health Services",
            "subcategory":"Doctor",
            "type":"Services"
        }
    ],
    "sg:phone":"+1 608 356 4462",
    "sg:postcode":"53913",
    "sg:province":"WI",
    "sg:tags":[
        "dentist"
    ],
    "wof:name":"J P Lobaugh DDS",
    "wof:placetype":"venue"
},
  "geometry": {"coordinates":[-89.736983,43.478582],"type":"Point"}
}