{
  "type": "Feature",
  "properties": {
    "iso:country":"US",
    "sg:address":"6233 39th Ave",
    "sg:city":"Kenosha",
    "sg:classifiers":[
        {
            "category":"Social Services",
            "type":"Services"
        }
    ],
    "sg:phone":"+1 262 654 1004",
    "sg:postcode":"53142",
    "sg:province":"IL",
    "sg:tags":[
        "counseling",
        "problem",
        "alcohol",
        "drug",
        "for"
    ],
    "wof:name":"Professional Svcs Group Inc",
    "wof:placetype":"venue"
},
  "geometry": {"coordinates":[-87.855265,42.578002],"type":"Point"}
}