{
  "type": "Feature",
  "properties": {
    "iso:country":"US",
    "sg:address":"5820 W Bluemound Rd",
    "sg:city":"Milwaukee",
    "sg:classifiers":[
        {
            "category":"Professional",
            "subcategory":"Employment Agencies",
            "type":"Services"
        }
    ],
    "sg:phone":"+1 414 271 0075",
    "sg:postcode":"53213",
    "sg:province":"WI",
    "sg:tags":[
        "help",
        "contractor"
    ],
    "wof:name":"Temporary Office Personnel Svc",
    "wof:placetype":"venue"
},
  "geometry": {"coordinates":[-87.985721,43.036601],"type":"Point"}
}