{
  "type": "Feature",
  "properties": {
    "iso:country":"US",
    "sg:address":"16800 W Greenfield Ave",
    "sg:city":"Brookfield",
    "sg:classifiers":[
        {
            "category":"Professional",
            "subcategory":"Accounting & Tax Preparation",
            "type":"Services"
        }
    ],
    "sg:phone":"+1 262 784 6787",
    "sg:postcode":"53005",
    "sg:province":"WI",
    "sg:tags":[
        "accountant"
    ],
    "wof:name":"Sondra Safer CPA",
    "wof:placetype":"venue"
},
  "geometry": {"coordinates":[-88.12334,43.016822],"type":"Point"}
}