{
  "type": "Feature",
  "properties": {
    "iso:country":"US",
    "sg:address":"6903 Giebel Rd",
    "sg:city":"Eldorado",
    "sg:classifiers":[
        {
            "category":"Real Estate",
            "subcategory":"Real Estate Operator",
            "type":"Services"
        }
    ],
    "sg:phone":"+1 920 922 9415",
    "sg:postcode":"54932",
    "sg:province":"WI",
    "sg:tags":[
        "property",
        "lessor"
    ],
    "wof:name":"Ann Marquardt Et Al",
    "wof:placetype":"venue"
},
  "geometry": {"coordinates":[-88.613978,43.786284],"type":"Point"}
}