{
  "type": "Feature",
  "properties": {
    "iso:country":"US",
    "sg:address":"59 15th St",
    "sg:city":"Fond Du Lac",
    "sg:classifiers":[
        {
            "category":"Real Estate",
            "subcategory":"Real Estate Operator",
            "type":"Services"
        }
    ],
    "sg:phone":"+1 920 926 9629",
    "sg:postcode":"54935",
    "sg:province":"WI",
    "sg:tags":[
        "building",
        "nonresidential"
    ],
    "wof:name":"Fsc Properties LLC",
    "wof:placetype":"venue"
},
  "geometry": {"coordinates":[-88.44696399999999,43.76323],"type":"Point"}
}