{
  "type": "Feature",
  "properties": {
    "iso:country":"US",
    "sg:address":"5635 Broad St",
    "sg:city":"Greendale",
    "sg:classifiers":[
        {
            "category":"Restaurant",
            "type":"Food & Drink"
        }
    ],
    "sg:phone":"+1 414 423 5810",
    "sg:postcode":"53129",
    "sg:province":"WI",
    "sg:tags":[
        "shop",
        "coffee"
    ],
    "wof:name":"Original Coffee Co",
    "wof:placetype":"venue"
},
  "geometry": {"coordinates":[-87.996081,42.941216],"type":"Point"}
}