{
  "type": "Feature",
  "properties": {
    "iso:country":"US",
    "sg:address":"8034 S Wildwood Dr",
    "sg:city":"Oak Creek",
    "sg:classifiers":[
        {
            "category":"Real Estate",
            "subcategory":"Real Estate Operator",
            "type":"Services"
        }
    ],
    "sg:phone":"+1 414 570 8260",
    "sg:postcode":"53154",
    "sg:province":"WI",
    "sg:tags":[
        "building",
        "apartment"
    ],
    "wof:name":"Cherry Creek View Apartments",
    "wof:placetype":"venue"
},
  "geometry": {"coordinates":[-87.925388,42.899553],"type":"Point"}
}