{
  "type": "Feature",
  "properties": {
    "iso:country":"US",
    "sg:address":"46887 Semingson Rd",
    "sg:city":"Strum",
    "sg:classifiers":[
        {
            "category":"Personal",
            "type":"Services"
        }
    ],
    "sg:phone":"+1 715 695 3412",
    "sg:postcode":"54770",
    "sg:province":"WI",
    "wof:name":"Entertaining With Ease LLC",
    "wof:placetype":"venue"
},
  "geometry": {"coordinates":[-91.398561,44.526773],"type":"Point"}
}