{
  "type": "Feature",
  "properties": {
    "iso:country":"US",
    "sg:address":"2596 Jordan Rd",
    "sg:city":"Juda",
    "sg:classifiers":[
        {
            "category":"Farming",
            "subcategory":"Dairy Farm",
            "type":"Manufacturing & Wholesale Goods"
        }
    ],
    "sg:phone":"+1 608 934 5506",
    "sg:postcode":"53550",
    "sg:province":"WI",
    "wof:name":"Figi Valley Farms",
    "wof:placetype":"venue"
},
  "geometry": {"coordinates":[-89.491978,42.538126],"type":"Point"}
}