{
  "type": "Feature",
  "properties": {
    "iso:country":"US",
    "sg:address":"4645 N 134th St",
    "sg:city":"Brookfield",
    "sg:classifiers":[
        {
            "category":"Wholesale",
            "subcategory":"Non-durable Goods",
            "type":"Manufacturing & Wholesale Goods"
        }
    ],
    "sg:phone":"+1 262 781 6414",
    "sg:postcode":"53005",
    "sg:province":"WI",
    "wof:name":"Advanced Advertising Co",
    "wof:placetype":"venue"
},
  "geometry": {"coordinates":[-88.078441,43.099417],"type":"Point"}
}