{
  "type": "Feature",
  "properties": {
    "iso:country":"US",
    "sg:address":"1185 N Port Washington Rd",
    "sg:city":"Grafton",
    "sg:classifiers":[
        {
            "category":"Restaurant",
            "type":"Food & Drink"
        }
    ],
    "sg:phone":"+1 262 377 2238",
    "sg:postcode":"53024",
    "sg:province":"WI",
    "sg:website":"www.dairyqueen.com",
    "wof:name":"Dairy Queen",
    "wof:placetype":"venue"
},
  "geometry": {"coordinates":[-87.925102,43.322601],"type":"Point"}
}