{
  "type": "Feature",
  "properties": {
    "iso:country":"US",
    "sg:address":"522 56th St",
    "sg:city":"Kenosha",
    "sg:classifiers":[
        {
            "category":"Autos & Motor Vehicles",
            "subcategory":"Automobile Sales",
            "type":"Retail Goods"
        }
    ],
    "sg:phone":"+1 262 697 9095",
    "sg:postcode":"53140",
    "sg:province":"WI",
    "sg:tags":[
        "car",
        "dealer"
    ],
    "wof:name":"Nudi Suzuki",
    "wof:placetype":"venue"
},
  "geometry": {"coordinates":[-87.818347,42.58519],"type":"Point"}
}