{
  "type": "Feature",
  "properties": {
    "iso:country":"US",
    "sg:address":"4619 S 46th St",
    "sg:city":"Milwaukee",
    "sg:classifiers":[
        {
            "category":"Building & Trades",
            "subcategory":"Construction",
            "type":"Services"
        }
    ],
    "sg:phone":"+1 414 282 9410",
    "sg:postcode":"53220",
    "sg:province":"WI",
    "sg:tags":[
        "carpentry",
        "contractor"
    ],
    "wof:name":"Rch & Associates Inc",
    "wof:placetype":"venue"
},
  "geometry": {"coordinates":[-87.97234899999999,42.959825],"type":"Point"}
}