{
  "type": "Feature",
  "properties": {
    "iso:country":"US",
    "sg:address":"625 Majesa Hills Ln",
    "sg:city":"Saukville",
    "sg:classifiers":[
        {
            "category":"Insurance",
            "subcategory":"Insurance Agent",
            "type":"Services"
        }
    ],
    "sg:phone":"+1 262 284 6264",
    "sg:postcode":"53080",
    "sg:province":"WI",
    "wof:name":"Majesa Office 33 LLC",
    "wof:placetype":"venue"
},
  "geometry": {"coordinates":[-87.953699,43.373169],"type":"Point"}
}