{
  "type": "Feature",
  "properties": {
    "iso:country":"US",
    "sg:address":"7501 S 75th St",
    "sg:city":"Franklin",
    "sg:classifiers":[
        {
            "category":"Professional",
            "type":"Services"
        }
    ],
    "sg:phone":"+1 414 529 9818",
    "sg:postcode":"53132",
    "sg:province":"WI",
    "wof:name":"Bonnie Pfau",
    "wof:placetype":"venue"
},
  "geometry": {"coordinates":[-88.008555,42.907542],"type":"Point"}
}