{
  "type": "Feature",
  "properties": {
    "iso:country":"US",
    "sg:address":"1104 John Nolen Dr",
    "sg:city":"Madison",
    "sg:classifiers":[
        {
            "category":"Health Services",
            "subcategory":"Doctor",
            "type":"Services"
        }
    ],
    "sg:phone":"+1 608 258 7846",
    "sg:postcode":"53713",
    "sg:province":"WI",
    "sg:tags":[
        "medical"
    ],
    "wof:name":"Shared Mri Facility",
    "wof:placetype":"venue"
},
  "geometry": {"coordinates":[-89.372655,43.046282],"type":"Point"}
}