{
  "type": "Feature",
  "properties": {
    "iso:country":"US",
    "sg:address":"105 Cherry St",
    "sg:city":"Beaver Dam",
    "sg:classifiers":[
        {
            "category":"Social Services",
            "subcategory":"Child Care",
            "type":"Services"
        }
    ],
    "sg:phone":"+1 920 887 2060",
    "sg:postcode":"53916",
    "sg:province":"WI",
    "sg:tags":[
        "day"
    ],
    "wof:name":"Rainbow Connectn Crtv Child Cr",
    "wof:placetype":"venue"
},
  "geometry": {"coordinates":[-88.829613,43.464937],"type":"Point"}
}