{
  "type": "Feature",
  "properties": {
    "addr:full":"123 N Blount St Madison WI 53703",
    "addr:housenumber":"123",
    "addr:postcode":"53703",
    "addr:street":"N Blount St",
    "iso:country":"US",
    "sg:address":"123 N Blount St",
    "sg:city":"Madison",
    "sg:classifiers":[
        {
            "category":"Real Estate",
            "subcategory":"Real Estate Agent",
            "type":"Services"
        }
    ],
    "sg:phone":"+1 608 287 0267",
    "sg:postcode":"53703",
    "sg:province":"WI",
    "wof:name":"123 N Blount Inc",
    "wof:placetype":"venue"
},
  "geometry": {"coordinates":[-89.378784,43.081269],"type":"Point"}
}