{
  "type": "Feature",
  "properties": {
    "addr:full":"5560 US Hwy 151 Fond Du Lac WI 54937",
    "addr:housenumber":"5560",
    "addr:postcode":"54937",
    "addr:street":"Us Hwy 151",
    "iso:country":"US",
    "sg:address":"5560 US Hwy 151",
    "sg:city":"Fond Du Lac",
    "sg:classifiers":[
        {
            "category":"Wholesale",
            "subcategory":"Machinery & Supplies",
            "type":"Manufacturing & Wholesale Goods"
        }
    ],
    "sg:phone":"+1 920 923 1768",
    "sg:postcode":"54937",
    "sg:province":"WI",
    "sg:tags":[
        "contractor"
    ],
    "sg:website":"www.servicemotor.com",
    "wof:name":"Service Motor Co",
    "wof:placetype":"venue"
},
  "geometry": {"coordinates":[-88.508726,43.736454],"type":"Point"}
}