{
  "type": "Feature",
  "properties": {
    "iso:country":"US",
    "sg:address":"414 Klein St",
    "sg:city":"Kaukauna",
    "sg:classifiers":[
        {
            "category":"Building & Trades",
            "subcategory":"Landscaping Services",
            "type":"Services"
        }
    ],
    "sg:phone":"+1 920 766 3959",
    "sg:postcode":"54130",
    "sg:province":"WI",
    "wof:name":"Larson Professional Tree Care",
    "wof:placetype":"venue"
},
  "geometry": {"coordinates":[-88.28178,44.277501],"type":"Point"}
}