{
  "type": "Feature",
  "properties": {
    "addr:full":"1802 Volkman St Schofield WI 54476",
    "addr:housenumber":"1802",
    "addr:postcode":"54476",
    "addr:street":"Volkman St",
    "iso:country":"US",
    "sg:address":"1802 Volkman St",
    "sg:city":"Schofield",
    "sg:classifiers":[
        {
            "category":"Restaurant",
            "type":"Food & Drink"
        }
    ],
    "sg:phone":"+1 715 359 4411",
    "sg:postcode":"54476",
    "sg:province":"WI",
    "sg:tags":[
        "eating"
    ],
    "wof:name":"Topper's Pizza",
    "wof:placetype":"venue"
},
  "geometry": {"coordinates":[-89.608737,44.905389],"type":"Point"}
}