{
  "type": "Feature",
  "properties": {
    "addr:full":"10970 W Boys Camp Rd Hayward WI 54843",
    "addr:housenumber":"10970",
    "addr:postcode":"54843",
    "addr:street":"W Boys Camp Rd",
    "iso:country":"US",
    "sg:address":"10970 W Boys Camp Rd",
    "sg:city":"Hayward",
    "sg:classifiers":[
        {
            "category":"Travel",
            "subcategory":"Campground",
            "type":"Entertainment"
        }
    ],
    "sg:phone":"+1 715 462 3254",
    "sg:postcode":"54843",
    "sg:province":"WI",
    "sg:tags":[
        "camp"
    ],
    "sg:website":"www.northstarcamp.com",
    "wof:name":"North Star Camp For Boys",
    "wof:placetype":"venue"
},
  "geometry": {"coordinates":[-91.24163,46.087853],"type":"Point"}
}