{
  "type": "Feature",
  "properties": {
    "iso:country":"US",
    "sg:address":"5670 Green Bay Rd",
    "sg:city":"Kenosha",
    "sg:classifiers":[
        {
            "category":"Freight",
            "type":"Transportation"
        },
        {
            "category":"Wholesale",
            "subcategory":"Durable Goods & Equipment",
            "type":"Manufacturing & Wholesale Goods"
        }
    ],
    "sg:phone":"+1 262 657 1210",
    "sg:postcode":"53144",
    "sg:province":"WI",
    "sg:tags":[
        "product",
        "forest",
        "trucking"
    ],
    "sg:website":"www.dejnos.com",
    "wof:name":"Dejno's Inc",
    "wof:placetype":"venue"
},
  "geometry": {"coordinates":[-87.884262,42.581742],"type":"Point"}
}