{
  "type": "Feature",
  "properties": {
    "iso:country":"US",
    "sg:address":"10433 W Appleton Ave",
    "sg:city":"Milwaukee",
    "sg:classifiers":[
        {
            "category":"Bars & Pubs",
            "type":"Food & Drink"
        }
    ],
    "sg:phone":"+1 414 353 9941",
    "sg:postcode":"53225",
    "sg:province":"WI",
    "wof:name":"Mitchell's Taverns",
    "wof:placetype":"venue"
},
  "geometry": {"coordinates":[-88.042709,43.125009],"type":"Point"}
}