{
  "type": "Feature",
  "properties": {
    "addr:full":"4208 Ross Ave Schofield WI 54476",
    "addr:housenumber":"4208",
    "addr:postcode":"54476",
    "addr:street":"Ross Ave",
    "iso:country":"US",
    "sg:address":"4208 Ross Ave",
    "sg:city":"Schofield",
    "sg:classifiers":[
        {
            "category":"Building & Trades",
            "subcategory":"Construction",
            "type":"Services"
        }
    ],
    "sg:phone":"+1 715 355 4096",
    "sg:postcode":"54476",
    "sg:province":"WI",
    "sg:tags":[
        "contractor"
    ],
    "wof:name":"Brian Christiansen Cnstr",
    "wof:placetype":"venue"
},
  "geometry": {"coordinates":[-89.570437,44.911625],"type":"Point"}
}