{
  "type": "Feature",
  "properties": {
    "iso:country":"US",
    "sg:address":"1300 Lange Ct",
    "sg:city":"Baraboo",
    "sg:classifiers":[
        {
            "category":"Government",
            "subcategory":"Jail",
            "type":"Public Place"
        }
    ],
    "sg:phone":"+1 608 355 3264",
    "sg:postcode":"53913",
    "sg:province":"WI",
    "sg:tags":[
        "correctional",
        "institution"
    ],
    "wof:name":"Sauk County Huber Center",
    "wof:placetype":"venue"
},
  "geometry": {"coordinates":[-89.76275,43.461089],"type":"Point"}
}