{
  "type": "Feature",
  "properties": {
    "iso:country":"US",
    "sg:address":"1928 US Hwy 8",
    "sg:city":"St Croix Falls",
    "sg:classifiers":[
        {
            "category":"Retail",
            "subcategory":"Repair Shop",
            "type":"Services"
        }
    ],
    "sg:phone":"+1 715 483 1905",
    "sg:postcode":"54024",
    "sg:province":"WI",
    "sg:tags":[
        "water",
        "equipment",
        "softening"
    ],
    "wof:name":"Aquarius Water Conditioning",
    "wof:placetype":"venue"
},
  "geometry": {"coordinates":[-92.555211,45.397433],"type":"Point"}
}