{
  "type": "Feature",
  "properties": {
    "iso:country":"US",
    "sg:address":"220 Ransom St",
    "sg:city":"Ripon",
    "sg:classifiers":[
        {
            "category":"Social Services",
            "subcategory":"Child Care",
            "type":"Services"
        }
    ],
    "sg:phone":"+1 920 748 3493",
    "sg:postcode":"54971",
    "sg:province":"WI",
    "sg:tags":[
        "kindergarten",
        "academic",
        "school"
    ],
    "wof:name":"Discovery Preschool",
    "wof:placetype":"venue"
},
  "geometry": {"coordinates":[-88.840085,43.845387],"type":"Point"}
}