{
  "type": "Feature",
  "properties": {
    "iso:country":"US",
    "sg:address":"2761 Prairie Ave",
    "sg:city":"Beloit",
    "sg:classifiers":[
        {
            "category":"Shopping",
            "subcategory":"Department Store",
            "type":"Retail Goods"
        }
    ],
    "sg:phone":"+1 608 365 5502",
    "sg:postcode":"53511",
    "sg:province":"IL",
    "sg:tags":[
        "dept",
        "discount",
        "optical",
        "center",
        "pharmacy"
    ],
    "wof:name":"Shopko",
    "wof:placetype":"venue"
},
  "geometry": {"coordinates":[-89.011561,42.544963],"type":"Point"}
}