{
  "type": "Feature",
  "properties": {
    "iso:country":"US",
    "sg:address":"8231 Pine Rd",
    "sg:city":"Thorp",
    "sg:classifiers":[
        {
            "category":"Professional",
            "subcategory":"Engineering",
            "type":"Services"
        }
    ],
    "sg:phone":"+1 715 669 7488",
    "sg:postcode":"54771",
    "sg:province":"WI",
    "wof:name":"Jerry Brubaker",
    "wof:placetype":"venue"
},
  "geometry": {"coordinates":[-90.721424,44.973334],"type":"Point"}
}