{
  "type": "Feature",
  "properties": {
    "addr:full":"733 Ferry St Eau Claire WI 54703",
    "addr:housenumber":"733",
    "addr:postcode":"54703",
    "addr:street":"Ferry St",
    "iso:country":"US",
    "sg:address":"733 Ferry St",
    "sg:city":"Eau Claire",
    "sg:classifiers":[
        {
            "category":"Retail",
            "subcategory":"Portrait Studio",
            "type":"Services"
        }
    ],
    "sg:phone":"+1 715 855 9462",
    "sg:postcode":"54703",
    "sg:province":"WI",
    "sg:tags":[
        "photography"
    ],
    "wof:name":"Wink Twinkle & Smile Phtgrphy",
    "wof:placetype":"venue"
},
  "geometry": {"coordinates":[-91.538771,44.791742],"type":"Point"}
}