{
  "type": "Feature",
  "properties": {
    "iso:country":"US",
    "sg:address":"6138 Mineral Point Rd",
    "sg:city":"Madison",
    "sg:classifiers":[
        {
            "category":"Food & Beverages",
            "subcategory":"Bakery",
            "type":"Retail Goods"
        }
    ],
    "sg:phone":"+1 608 232 1597",
    "sg:postcode":"53705",
    "sg:province":"WI",
    "sg:tags":[
        "baker"
    ],
    "wof:name":"Wild Grain's Bakery",
    "wof:placetype":"venue"
},
  "geometry": {"coordinates":[-89.48333700000001,43.060897],"type":"Point"}
}