{
  "type": "Feature",
  "properties": {
    "iso:country":"US",
    "sg:address":"480 Lincoln Dr",
    "sg:city":"Madison",
    "sg:classifiers":[
        {
            "category":"Education",
            "subcategory":"College",
            "type":"Public Place"
        }
    ],
    "sg:phone":"+1 608 263 3053",
    "sg:postcode":"53706",
    "sg:province":"WI",
    "wof:name":"Mathematics Department",
    "wof:placetype":"venue"
},
  "geometry": {"coordinates":[-89.403064,43.07456],"type":"Point"}
}