{
  "type": "Feature",
  "properties": {
    "addr:full":"210 S Main St Fond Du Lac WI 54935",
    "addr:housenumber":"210",
    "addr:postcode":"54935",
    "addr:street":"S Main St",
    "iso:country":"US",
    "sg:address":"210 S Main St",
    "sg:city":"Fond Du Lac",
    "sg:classifiers":[
        {
            "category":"Communications",
            "subcategory":"Radio Station",
            "type":"Services"
        }
    ],
    "sg:phone":"+1 920 924 9697",
    "sg:postcode":"54935",
    "sg:province":"WI",
    "sg:tags":[
        "broadcasting"
    ],
    "wof:name":"WTCX",
    "wof:placetype":"venue"
},
  "geometry": {"coordinates":[-88.447048,43.772783],"type":"Point"}
}