{
  "type": "Feature",
  "properties": {
    "iso:country":"US",
    "sg:address":"543 S Putnam St",
    "sg:city":"Whitewater",
    "sg:classifiers":[
        {
            "category":"Health Services",
            "subcategory":"Chiropractor",
            "type":"Services"
        }
    ],
    "sg:phone":"+1 262 473 7274",
    "sg:postcode":"53190",
    "sg:province":"WI",
    "wof:name":"Veale Chiropractic Office LLC",
    "wof:placetype":"venue"
},
  "geometry": {"coordinates":[-88.742008,42.826927],"type":"Point"}
}