{
  "type": "Feature",
  "properties": {
    "iso:country":"US",
    "sg:address":"1701 Pearl St",
    "sg:city":"Waukesha",
    "sg:classifiers":[
        {
            "category":"Retail",
            "subcategory":"Auto Repair",
            "type":"Services"
        },
        {
            "category":"Manufacturing",
            "subcategory":"Motor Vehicles & Parts",
            "type":"Manufacturing & Wholesale Goods"
        }
    ],
    "sg:phone":"+1 262 513 9511",
    "sg:postcode":"53186",
    "sg:province":"WI",
    "sg:tags":[
        "clutches",
        "mfg"
    ],
    "wof:name":"Industrial Clutch Products",
    "wof:placetype":"venue"
},
  "geometry": {"coordinates":[-88.19964299999999,43.007743],"type":"Point"}
}