{
  "type": "Feature",
  "properties": {
    "iso:country":"US",
    "sg:address":"210 S Water St",
    "sg:city":"Watertown",
    "sg:classifiers":[
        {
            "category":"Food & Beverages",
            "subcategory":"Bakery",
            "type":"Retail Goods"
        }
    ],
    "sg:phone":"+1 920 206 9202",
    "sg:postcode":"53094",
    "sg:province":"WI",
    "sg:tags":[
        "pie"
    ],
    "wof:name":"Upper Krust Pie Shop",
    "wof:placetype":"venue"
},
  "geometry": {"coordinates":[-88.726375,43.193323],"type":"Point"}
}