{
  "type": "Feature",
  "properties": {
    "addr:full":"1101 Silver Dr Baraboo WI 53913",
    "addr:housenumber":"1101",
    "addr:postcode":"53913",
    "addr:street":"Silver Dr",
    "iso:country":"US",
    "sg:address":"1101 Silver Dr",
    "sg:city":"Baraboo",
    "sg:classifiers":[
        {
            "category":"Real Estate",
            "subcategory":"Real Estate Operator",
            "type":"Services"
        }
    ],
    "sg:phone":"+1 608 356 6477",
    "sg:postcode":"53913",
    "sg:province":"WI",
    "sg:tags":[
        "apartment"
    ],
    "wof:name":"Park Ridge Apartments",
    "wof:placetype":"venue"
},
  "geometry": {"coordinates":[-89.747006,43.449234],"type":"Point"}
}