{
  "type": "Feature",
  "properties": {
    "iso:country":"US",
    "sg:address":"5555 N Port Washington Rd",
    "sg:city":"Milwaukee",
    "sg:classifiers":[
        {
            "category":"Professional",
            "subcategory":"Lawyer & Legal Services",
            "type":"Services"
        }
    ],
    "sg:phone":"+1 414 962 7440",
    "sg:postcode":"53217",
    "sg:province":"WI",
    "sg:tags":[
        "attorney"
    ],
    "sg:website":"www.hmrvisa.com",
    "wof:name":"Hochstatter Mc Carthy & Rivas",
    "wof:placetype":"venue"
},
  "geometry": {"coordinates":[-87.916703,43.11785],"type":"Point"}
}