{
  "type": "Feature",
  "properties": {
    "iso:country":"US",
    "sg:address":"1111 E Lilac Ln",
    "sg:city":"Milwaukee",
    "sg:classifiers":[
        {
            "category":"Professional",
            "subcategory":"Accounting & Tax Preparation",
            "type":"Services"
        }
    ],
    "sg:phone":"+1 414 228 0719",
    "sg:postcode":"53217",
    "sg:province":"WI",
    "sg:tags":[
        "billing"
    ],
    "wof:name":"Lakefront Billing Svc Inc",
    "wof:placetype":"venue"
},
  "geometry": {"coordinates":[-87.89319500000001,43.15859],"type":"Point"}
}