{
  "type": "Feature",
  "properties": {
    "addr:full":"11925 W Lake Park Dr Milwaukee WI 53224",
    "addr:housenumber":"11925",
    "addr:postcode":"53224",
    "addr:street":"W Lake Park Dr",
    "iso:country":"US",
    "sg:address":"11925 W Lake Park Dr",
    "sg:city":"Milwaukee",
    "sg:classifiers":[
        {
            "category":"Professional",
            "subcategory":"Management & Consulting",
            "type":"Services"
        },
        {
            "category":"Professional",
            "subcategory":"Employment Agencies",
            "type":"Services"
        }
    ],
    "sg:phone":"+1 414 979 8800",
    "sg:postcode":"53224",
    "sg:province":"WI",
    "sg:tags":[
        "consultant",
        "search",
        "executive",
        "contractor"
    ],
    "sg:website":"http://www.rcmt.com",
    "wof:name":"RCM Technologies",
    "wof:placetype":"venue"
},
  "geometry": {"coordinates":[-88.05908599999999,43.158971],"type":"Point"}
}