{
  "type": "Feature",
  "properties": {
    "addr:full":"1522 S Lincoln St Elkhorn WI 53121",
    "addr:housenumber":"1522",
    "addr:postcode":"53121",
    "addr:street":"S Lincoln St",
    "iso:country":"US",
    "sg:address":"1522 S Lincoln St",
    "sg:city":"Elkhorn",
    "sg:classifiers":[
        {
            "category":"Home & Garden",
            "subcategory":"Garden Supply",
            "type":"Retail Goods"
        }
    ],
    "sg:phone":"+1 262 723 5001",
    "sg:postcode":"53121",
    "sg:province":"WI",
    "wof:name":"Glatz Gardens",
    "wof:placetype":"venue"
},
  "geometry": {"coordinates":[-88.541341,42.649106],"type":"Point"}
}