{
  "type": "Feature",
  "properties": {
    "iso:country":"US",
    "sg:address":"295 W Scott St",
    "sg:city":"Fond Du Lac",
    "sg:classifiers":[
        {
            "category":"Building & Trades",
            "subcategory":"Construction",
            "type":"Services"
        }
    ],
    "sg:phone":"+1 920 923 1000",
    "sg:postcode":"54937",
    "sg:province":"WI",
    "sg:tags":[
        "windows",
        "garage",
        "door",
        "contractor"
    ],
    "wof:name":"Precision Overhead Door Co",
    "wof:placetype":"venue"
},
  "geometry": {"coordinates":[-88.458029,43.791761],"type":"Point"}
}