{
  "type": "Feature",
  "properties": {
    "iso:country":"US",
    "sg:address":"524 Park Ave",
    "sg:city":"De Forest",
    "sg:classifiers":[
        {
            "category":"Professional",
            "subcategory":"Advertising",
            "type":"Services"
        }
    ],
    "sg:phone":"+1 608 846 4093",
    "sg:postcode":"53532",
    "sg:province":"WI",
    "sg:tags":[
        "counselor"
    ],
    "wof:name":"Phoenix Design",
    "wof:placetype":"venue"
},
  "geometry": {"coordinates":[-89.334612,43.24952],"type":"Point"}
}