{
  "type": "Feature",
  "properties": {
    "iso:country":"US",
    "sg:address":"10890 Penny Ln",
    "sg:city":"Baraboo",
    "sg:classifiers":[
        {
            "category":"Farming",
            "subcategory":"Farm & Veterinary Services",
            "type":"Manufacturing & Wholesale Goods"
        }
    ],
    "sg:phone":"+1 608 356 8357",
    "sg:postcode":"53913",
    "sg:province":"WI",
    "sg:tags":[
        "livestock",
        "supply"
    ],
    "sg:website":"www.accelgen.com",
    "wof:name":"Accelerated Genetics",
    "wof:placetype":"venue"
},
  "geometry": {"coordinates":[-89.778127,43.522731],"type":"Point"}
}