{
  "type": "Feature",
  "properties": {
    "iso:country":"US",
    "sg:address":"360 Progress Dr",
    "sg:city":"Cottage Grove",
    "sg:classifiers":[
        {
            "category":"Retail",
            "subcategory":"Laundry & Dry Cleaning",
            "type":"Services"
        }
    ],
    "sg:phone":"+1 608 839 1565",
    "sg:postcode":"53527",
    "sg:province":"WI",
    "sg:tags":[
        "cleaners",
        "rug",
        "carpet"
    ],
    "wof:name":"Preferred Carpet Cleaning",
    "wof:placetype":"venue"
},
  "geometry": {"coordinates":[-89.20666199999999,43.077058],"type":"Point"}
}