{
  "type": "Feature",
  "properties": {
    "addr:full":"3570 N Riverline Dr Oconomowoc WI 53066",
    "addr:housenumber":"3570",
    "addr:postcode":"53066",
    "addr:street":"N Riverline Dr",
    "iso:country":"US",
    "sg:address":"3570 N Riverline Dr",
    "sg:city":"Oconomowoc",
    "sg:classifiers":[
        {
            "category":"Wholesale",
            "subcategory":"Chemicals & Plastics",
            "type":"Manufacturing & Wholesale Goods"
        }
    ],
    "sg:phone":"+1 262 560 0271",
    "sg:postcode":"53066",
    "sg:province":"WI",
    "sg:tags":[
        "contract",
        "hanging"
    ],
    "wof:name":"Pro Coatings Painting Co",
    "wof:placetype":"venue"
},
  "geometry": {"coordinates":[-88.528516,43.085619],"type":"Point"}
}