{
  "type": "Feature",
  "properties": {
    "addr:full":"6698 Odana Rd Madison WI 53719",
    "addr:housenumber":"6698",
    "addr:postcode":"53719",
    "addr:street":"Odana Rd",
    "iso:country":"US",
    "sg:address":"6698 Odana Rd",
    "sg:city":"Madison",
    "sg:classifiers":[
        {
            "category":"Banks & Credit Unions",
            "subcategory":"Bank",
            "type":"Services"
        }
    ],
    "sg:phone":"+1 608 821 1945",
    "sg:postcode":"53719",
    "sg:province":"WI",
    "wof:name":"Amcore Bank",
    "wof:placetype":"venue"
},
  "geometry": {"coordinates":[-89.495458,43.056031],"type":"Point"}
}