{
  "type": "Feature",
  "properties": {
    "addr:full":"5200 Douglas Ave Racine WI 53402",
    "addr:housenumber":"5200",
    "addr:postcode":"53402",
    "addr:street":"Douglas Ave",
    "iso:country":"US",
    "sg:address":"5200 Douglas Ave",
    "sg:city":"Racine",
    "sg:classifiers":[
        {
            "category":"Shopping",
            "type":"Retail Goods"
        }
    ],
    "sg:phone":"+1 262 752 1773",
    "sg:postcode":"53402",
    "sg:province":"WI",
    "sg:tags":[
        "art",
        "gallery",
        "dealer"
    ],
    "wof:name":"American Artisans Gallery",
    "wof:placetype":"venue"
},
  "geometry": {"coordinates":[-87.80986300000001,42.785663],"type":"Point"}
}