{
  "type": "Feature",
  "properties": {
    "addr:full":"10 S Roosevelt Rd Black River Falls WI 54615",
    "addr:housenumber":"10",
    "addr:postcode":"54615",
    "addr:street":"S Roosevelt Rd",
    "iso:country":"US",
    "sg:address":"10 S Roosevelt Rd",
    "sg:city":"Black River Falls",
    "sg:classifiers":[
        {
            "category":"Shopping",
            "subcategory":"Computers & Home Electronics",
            "type":"Retail Goods"
        }
    ],
    "sg:phone":"+1 715 284 5105",
    "sg:postcode":"54615",
    "sg:province":"WI",
    "sg:tags":[
        "repair"
    ],
    "wof:name":"Radio Shack",
    "wof:placetype":"venue"
},
  "geometry": {"coordinates":[-90.843039,44.294269],"type":"Point"}
}