{
  "type": "Feature",
  "properties": {
    "iso:country":"US",
    "sg:address":"311 E Green Bay St",
    "sg:city":"Shawano",
    "sg:classifiers":[
        {
            "category":"Professional",
            "type":"Services"
        }
    ],
    "sg:phone":"+1 715 524 5998",
    "sg:postcode":"54166",
    "sg:province":"WI",
    "sg:tags":[
        "communication"
    ],
    "wof:name":"TLC Communications Corp",
    "wof:placetype":"venue"
},
  "geometry": {"coordinates":[-88.605621,44.782124],"type":"Point"}
}