{
  "type": "Feature",
  "properties": {
    "addr:full":"26241 E Mound Rd Belmont WI 53510",
    "addr:housenumber":"26241",
    "addr:postcode":"53510",
    "addr:street":"E Mound Rd",
    "iso:country":"US",
    "sg:address":"26241 E Mound Rd",
    "sg:city":"Belmont",
    "sg:classifiers":[
        {
            "category":"Farming",
            "subcategory":"Dairy Farm",
            "type":"Manufacturing & Wholesale Goods"
        }
    ],
    "sg:phone":"+1 608 762 5373",
    "sg:postcode":"53510",
    "sg:province":"WI",
    "wof:name":"Donald & Douglas Popp",
    "wof:placetype":"venue"
},
  "geometry": {"coordinates":[-90.348122,42.766044],"type":"Point"}
}