{
  "type": "Feature",
  "properties": {
    "addr:full":"602 Detroit St Sheboygan Falls WI 53085",
    "addr:housenumber":"602",
    "addr:postcode":"53085",
    "addr:street":"Detroit St",
    "iso:country":"US",
    "sg:address":"602 Detroit St",
    "sg:city":"Sheboygan Falls",
    "sg:classifiers":[
        {
            "category":"Shopping",
            "subcategory":"Jewelry",
            "type":"Retail Goods"
        }
    ],
    "sg:phone":"+1 920 467 4675",
    "sg:postcode":"53085",
    "sg:province":"WI",
    "wof:name":"Corner Studio Jwly & Fine Arts",
    "wof:placetype":"venue"
},
  "geometry": {"coordinates":[-87.81259799999999,43.72674],"type":"Point"}
}