{
  "type": "Feature",
  "properties": {
    "iso:country":"US",
    "sg:address":"400 S Prairie Ave",
    "sg:city":"Waukesha",
    "sg:classifiers":[
        {
            "category":"Utilities",
            "subcategory":"Electric",
            "type":"Services"
        }
    ],
    "sg:phone":"+1 262 547 0121",
    "sg:postcode":"53186",
    "sg:province":"WI",
    "sg:tags":[
        "equipment",
        "plant",
        "equipment-repair",
        "power"
    ],
    "sg:website":"http://www.waukeshaelectric.com",
    "wof:name":"Waukesha Electric Systems",
    "wof:placetype":"venue"
},
  "geometry": {"coordinates":[-88.24318700000001,42.997742],"type":"Point"}
}