{
  "type": "Feature",
  "properties": {
    "iso:country":"US",
    "sg:address":"106 153 Rd",
    "sg:city":"Spencer",
    "sg:classifiers":[
        {
            "category":"Building & Trades",
            "subcategory":"Plumbing",
            "type":"Services"
        }
    ],
    "sg:phone":"+1 715 659 3913",
    "sg:postcode":"54479",
    "sg:province":"WI",
    "sg:tags":[
        "contractor"
    ],
    "wof:name":"Advanced Heating & Cooling",
    "wof:placetype":"venue"
},
  "geometry": {"coordinates":[-90.319159,44.800771],"type":"Point"}
}