{
  "type": "Feature",
  "properties": {
    "addr:full":"317 N 6th St Wausau WI 54403",
    "addr:housenumber":"317",
    "addr:postcode":"54403",
    "addr:street":"N 6Th St",
    "iso:country":"US",
    "sg:address":"317 N 6th St",
    "sg:city":"Wausau",
    "sg:classifiers":[
        {
            "category":"Insurance",
            "subcategory":"Insurance Agent",
            "type":"Services"
        }
    ],
    "sg:phone":"+1 715 842 1664",
    "sg:postcode":"54403",
    "sg:province":"WI",
    "wof:name":"Clements Insurance",
    "wof:placetype":"venue"
},
  "geometry": {"coordinates":[-89.623448,44.959385],"type":"Point"}
}