{
  "type": "Feature",
  "properties": {
    "addr:full":"2496 State Rd 80 Cuba City WI 53807",
    "addr:housenumber":"2496;80",
    "addr:postcode":"53807",
    "addr:street":"State Rd",
    "iso:country":"US",
    "sg:address":"2496 State Rd 80",
    "sg:city":"Cuba City",
    "sg:classifiers":[
        {
            "category":"Autos & Motor Vehicles",
            "subcategory":"Automobile Sales",
            "type":"Retail Goods"
        }
    ],
    "sg:phone":"+1 608 744 8822",
    "sg:postcode":"53807",
    "sg:province":"WI",
    "sg:tags":[
        "car",
        "dealer"
    ],
    "wof:name":"Runde Auto Group",
    "wof:placetype":"venue"
},
  "geometry": {"coordinates":[-90.430554,42.587245],"type":"Point"}
}