{
  "type": "Feature",
  "properties": {
    "addr:full":"600 E Layton Ave Milwaukee WI 53207",
    "addr:housenumber":"600",
    "addr:postcode":"53207",
    "addr:street":"E Layton Ave",
    "iso:country":"US",
    "sg:address":"600 E Layton Ave",
    "sg:city":"Milwaukee",
    "sg:classifiers":[
        {
            "category":"Restaurant",
            "type":"Food & Drink"
        }
    ],
    "sg:phone":"+1 414 481 4831",
    "sg:postcode":"53207",
    "sg:province":"WI",
    "sg:tags":[
        "carry"
    ],
    "wof:name":"Feliccis Mama Mia Inc",
    "wof:placetype":"venue"
},
  "geometry": {"coordinates":[-87.899666,42.959161],"type":"Point"}
}