{
  "type": "Feature",
  "properties": {
    "iso:country":"US",
    "sg:address":"33640 115th Ave",
    "sg:city":"Boyd",
    "sg:classifiers":[
        {
            "category":"Farming",
            "subcategory":"Dairy Farm",
            "type":"Manufacturing & Wholesale Goods"
        }
    ],
    "sg:phone":"+1 715 644 2017",
    "sg:postcode":"54726",
    "sg:province":"WI",
    "sg:tags":[
        "beef",
        "feedlot",
        "cattle"
    ],
    "wof:name":"Derks Farms",
    "wof:placetype":"venue"
},
  "geometry": {"coordinates":[-90.993071,45.009508],"type":"Point"}
}