{
  "type": "Feature",
  "properties": {
    "iso:country":"US",
    "sg:address":"300 Interchange N",
    "sg:city":"Lake Geneva",
    "sg:classifiers":[
        {
            "category":"Manufacturing",
            "subcategory":"Metals",
            "type":"Manufacturing & Wholesale Goods"
        }
    ],
    "sg:phone":"+1 262 248 4461",
    "sg:postcode":"53147",
    "sg:province":"WI",
    "sg:tags":[
        "casting",
        "investment"
    ],
    "sg:website":"www.northernprecision.com",
    "wof:name":"Northern Precision Casting Co",
    "wof:placetype":"venue"
},
  "geometry": {"coordinates":[-88.429317,42.605115],"type":"Point"}
}