{
  "type": "Feature",
  "properties": {
    "iso:country":"US",
    "sg:address":"6585 Virginia St",
    "sg:city":"Vesper",
    "sg:classifiers":[
        {
            "category":"Building & Trades",
            "subcategory":"Construction",
            "type":"Services"
        }
    ],
    "sg:phone":"+1 715 569 4111",
    "sg:postcode":"54489",
    "sg:province":"WI",
    "wof:name":"Vesper Lumber Co",
    "wof:placetype":"venue"
},
  "geometry": {"coordinates":[-89.969039,44.484315],"type":"Point"}
}