{
  "type": "Feature",
  "properties": {
    "iso:country":"US",
    "sg:address":"517 Ridgeview Ct",
    "sg:city":"Green Bay",
    "sg:classifiers":[
        {
            "category":"Manufacturing",
            "subcategory":"Tools & Machinery",
            "type":"Manufacturing & Wholesale Goods"
        }
    ],
    "sg:phone":"+1 920 336 2664",
    "sg:postcode":"54301",
    "sg:province":"WI",
    "sg:tags":[
        "physician",
        "surgeon"
    ],
    "wof:name":"Boren Manufacturing Co",
    "wof:placetype":"venue"
},
  "geometry": {"coordinates":[-88.023493,44.461159],"type":"Point"}
}