{
  "type": "Feature",
  "properties": {
    "iso:country":"US",
    "sg:address":"2109 Spring Creek Rd",
    "sg:city":"Rhinelander",
    "sg:classifiers":[
        {
            "category":"Retail",
            "subcategory":"Animal Services",
            "type":"Services"
        }
    ],
    "sg:phone":"+1 715 282 6052",
    "sg:postcode":"54501",
    "sg:province":"WI",
    "wof:name":"Critters Dew Drop Inn",
    "wof:placetype":"venue"
},
  "geometry": {"coordinates":[-89.569327,45.563172],"type":"Point"}
}