{
  "type": "Feature",
  "properties": {
    "addr:full":"9920 Musser Rd Phillips WI 54555",
    "addr:postcode":"9920;54555",
    "addr:street":"Musser Rd",
    "iso:country":"US",
    "sg:address":"9920 Musser Rd",
    "sg:city":"Phillips",
    "sg:classifiers":[
        {
            "category":"Building & Trades",
            "subcategory":"Plumbing",
            "type":"Services"
        }
    ],
    "sg:phone":"+1 715 339 3978",
    "sg:postcode":"54555",
    "sg:province":"WI",
    "sg:tags":[
        "plumbing",
        "contractor"
    ],
    "wof:name":"Devault Plumbing & Heating",
    "wof:placetype":"venue"
},
  "geometry": {"coordinates":[-90.28861999999999,45.737089],"type":"Point"}
}