{
  "type": "Feature",
  "properties": {
    "addr:full":"555 W Grand Ave Wisconsin Rapids WI 54495",
    "addr:housenumber":"555",
    "addr:postcode":"54495",
    "addr:street":"W Grand Ave",
    "iso:country":"US",
    "sg:address":"555 W Grand Ave",
    "sg:city":"Wisconsin Rapids",
    "sg:classifiers":[
        {
            "category":"Banks & Credit Unions",
            "subcategory":"Bank",
            "type":"Services"
        }
    ],
    "sg:phone":"+1 715 423 8100",
    "sg:postcode":"54495",
    "sg:province":"WI",
    "wof:name":"Paper City Savings Assn",
    "wof:placetype":"venue"
},
  "geometry": {"coordinates":[-89.829942,44.39426],"type":"Point"}
}