{
  "type": "Feature",
  "properties": {
    "iso:country":"US",
    "sg:address":"1901 Spring St",
    "sg:city":"Fall Creek",
    "sg:classifiers":[
        {
            "category":"Building & Trades",
            "subcategory":"Construction",
            "type":"Services"
        },
        {
            "category":"Manufacturing",
            "subcategory":"Buildings",
            "type":"Manufacturing & Wholesale Goods"
        }
    ],
    "sg:phone":"+1 715 834 8368",
    "sg:postcode":"54742",
    "sg:province":"WI",
    "sg:tags":[
        "home",
        "prefabricated",
        "builder",
        "wood",
        "mfg"
    ],
    "wof:name":"C D Heal Construction",
    "wof:placetype":"venue"
},
  "geometry": {"coordinates":[-91.35221900000001,44.798634],"type":"Point"}
}