{
  "type": "Feature",
  "properties": {
    "addr:full":"1016 Milwaukee Ave Burlington WI 53105",
    "addr:housenumber":"1016",
    "addr:postcode":"53105",
    "addr:street":"Milwaukee Ave",
    "iso:country":"US",
    "sg:address":"1016 Milwaukee Ave",
    "sg:city":"Burlington",
    "sg:classifiers":[
        {
            "category":"Autos & Motor Vehicles",
            "subcategory":"Auto Supplies",
            "type":"Retail Goods"
        }
    ],
    "sg:phone":"+1 262 767 9714",
    "sg:postcode":"53105",
    "sg:province":"WI",
    "sg:tags":[
        "automobile",
        "parts"
    ],
    "wof:name":"Advance Auto Parts Inc",
    "wof:placetype":"venue"
},
  "geometry": {"coordinates":[-88.26827900000001,42.689589],"type":"Point"}
}