{
  "type": "Feature",
  "properties": {
    "iso:country":"US",
    "sg:address":"125 S Webster St",
    "sg:city":"Madison",
    "sg:classifiers":[
        {
            "category":"Education",
            "subcategory":"School",
            "type":"Public Place"
        }
    ],
    "sg:phone":"+1 608 267 9153",
    "sg:postcode":"53703",
    "sg:province":"WI",
    "wof:name":"Wisconsin State Dept Of Educ",
    "wof:placetype":"venue"
},
  "geometry": {"coordinates":[-89.380352,43.074866],"type":"Point"}
}