{
  "type": "Feature",
  "properties": {
    "addr:full":"508 Alma St Pound WI 54161",
    "addr:housenumber":"508",
    "addr:postcode":"54161",
    "addr:street":"Alma St",
    "iso:country":"US",
    "sg:address":"508 Alma St",
    "sg:city":"Pound",
    "sg:classifiers":[
        {
            "category":"Home & Garden",
            "subcategory":"Hardware",
            "type":"Retail Goods"
        }
    ],
    "sg:phone":"+1 920 897 3535",
    "sg:postcode":"54161",
    "sg:province":"WI",
    "wof:name":"Ace Hardware",
    "wof:placetype":"venue"
},
  "geometry": {"coordinates":[-88.03565999999999,45.092408],"type":"Point"}
}