{
  "type": "Feature",
  "properties": {
    "iso:country":"US",
    "sg:address":"1302 20th Ave",
    "sg:city":"Monroe",
    "sg:classifiers":[
        {
            "category":"Insurance",
            "subcategory":"Insurance Agent",
            "type":"Services"
        }
    ],
    "sg:phone":"+1 608 325 5075",
    "sg:postcode":"53566",
    "sg:province":"WI",
    "wof:name":"State Farm Insurance",
    "wof:placetype":"venue"
},
  "geometry": {"coordinates":[-89.634929,42.599376],"type":"Point"}
}