{
  "type": "Feature",
  "properties": {
    "iso:country":"US",
    "sg:address":"146 S Wisconsin St",
    "sg:city":"Port Washington",
    "sg:classifiers":[
        {
            "category":"Utilities",
            "subcategory":"Electric",
            "type":"Services"
        }
    ],
    "sg:phone":"+1 262 268 3432",
    "sg:postcode":"53074",
    "sg:province":"WI",
    "sg:tags":[
        "plant",
        "power"
    ],
    "wof:name":"Port Washington Power Plant",
    "wof:placetype":"venue"
},
  "geometry": {"coordinates":[-87.870751,43.386045],"type":"Point"}
}