{
  "type": "Feature",
  "properties": {
    "iso:country":"US",
    "sg:address":"4861 State Hwy 49",
    "sg:city":"Brandon",
    "sg:classifiers":[
        {
            "category":"Farming",
            "subcategory":"Dairy Farm",
            "type":"Manufacturing & Wholesale Goods"
        }
    ],
    "sg:phone":"+1 920 346 2310",
    "sg:postcode":"53919",
    "sg:province":"WI",
    "wof:name":"Kyle Homan",
    "wof:placetype":"venue"
},
  "geometry": {"coordinates":[-88.77505499999999,43.714419],"type":"Point"}
}