{
  "type": "Feature",
  "properties": {
    "iso:country":"US",
    "sg:address":"2970 Chapel Valley Rd",
    "sg:city":"Fitchburg",
    "sg:classifiers":[
        {
            "category":"Insurance",
            "subcategory":"Insurance Agent",
            "type":"Services"
        }
    ],
    "sg:phone":"+1 608 273 1776",
    "sg:postcode":"53711",
    "sg:province":"WI",
    "sg:website":"www.auxiant.com",
    "wof:name":"Auxiant",
    "wof:placetype":"venue"
},
  "geometry": {"coordinates":[-89.431827,43.015084],"type":"Point"}
}