{
  "type": "Feature",
  "properties": {
    "addr:full":"1605 Shetland Rd Eau Claire WI 54701",
    "addr:housenumber":"1605",
    "addr:postcode":"54701",
    "addr:street":"Shetland Rd",
    "iso:country":"US",
    "sg:address":"1605 Shetland Rd",
    "sg:city":"Eau Claire",
    "sg:classifiers":[
        {
            "category":"Education",
            "subcategory":"Special Training",
            "type":"Public Place"
        }
    ],
    "sg:phone":"+1 715 834 4129",
    "sg:postcode":"54701",
    "sg:province":"WI",
    "wof:name":"Drivers Education",
    "wof:placetype":"venue"
},
  "geometry": {"coordinates":[-91.47474699999999,44.757702],"type":"Point"}
}