{
  "type": "Feature",
  "properties": {
    "addr:full":"1009 Stand Rock Rd Wisconsin Dells WI 53965",
    "addr:housenumber":"1009",
    "addr:postcode":"53965",
    "addr:street":"Stand Rock Rd",
    "iso:country":"US",
    "sg:address":"1009 Stand Rock Rd",
    "sg:city":"Wisconsin Dells",
    "sg:classifiers":[
        {
            "category":"Shopping",
            "subcategory":"Department Store",
            "type":"Retail Goods"
        }
    ],
    "sg:phone":"+1 608 253 4081",
    "sg:postcode":"53965",
    "sg:province":"WI",
    "sg:tags":[
        "shop"
    ],
    "wof:name":"Family Dollar Store",
    "wof:placetype":"venue"
},
  "geometry": {"coordinates":[-89.784217,43.626852],"type":"Point"}
}