{
  "type": "Feature",
  "properties": {
    "iso:country":"US",
    "sg:address":"2131 Plover Rd",
    "sg:city":"Plover",
    "sg:classifiers":[
        {
            "category":"Recreation",
            "type":"Entertainment"
        }
    ],
    "sg:phone":"+1 715 342 1914",
    "sg:postcode":"54467",
    "sg:province":"WI",
    "sg:tags":[
        "martial",
        "arts",
        "instruction"
    ],
    "wof:name":"O'Keefe's Family Tae KWON Do",
    "wof:placetype":"venue"
},
  "geometry": {"coordinates":[-89.530294,44.453699],"type":"Point"}
}