{
  "type": "Feature",
  "properties": {
    "iso:country":"US",
    "sg:address":"1904 Parmenter St",
    "sg:city":"Middleton",
    "sg:classifiers":[
        {
            "category":"Retail",
            "subcategory":"Portrait Studio",
            "type":"Services"
        }
    ],
    "sg:phone":"+1 608 831 5000",
    "sg:postcode":"53562",
    "sg:province":"WI",
    "sg:tags":[
        "personal",
        "photo"
    ],
    "wof:name":"Forrestal Permenter St Gallery",
    "wof:placetype":"venue"
},
  "geometry": {"coordinates":[-89.51161,43.096824],"type":"Point"}
}