{
  "type": "Feature",
  "properties": {
    "addr:full":"7127 W North Ave Wauwatosa WI 53213",
    "addr:housenumber":"7127",
    "addr:postcode":"53213",
    "addr:street":"W North Ave",
    "iso:country":"US",
    "sg:address":"7127 W North Ave",
    "sg:city":"Wauwatosa",
    "sg:classifiers":[
        {
            "category":"Banks & Credit Unions",
            "subcategory":"Bank",
            "type":"Services"
        }
    ],
    "sg:phone":"+1 414 302 1417",
    "sg:postcode":"53213",
    "sg:province":"WI",
    "sg:tags":[
        "loan",
        "real estate"
    ],
    "wof:name":"Lynn Agency",
    "wof:placetype":"venue"
},
  "geometry": {"coordinates":[-88.001794,43.060666],"type":"Point"}
}