{
  "type": "Feature",
  "properties": {
    "addr:full":"1909 Washington St Two Rivers WI 54241",
    "addr:housenumber":"1909",
    "addr:postcode":"54241",
    "addr:street":"Washington St",
    "iso:country":"US",
    "sg:address":"1909 Washington St",
    "sg:city":"Two Rivers",
    "sg:classifiers":[
        {
            "category":"Home & Garden",
            "subcategory":"Building Materials",
            "type":"Retail Goods"
        }
    ],
    "sg:phone":"+1 920 794 8445",
    "sg:postcode":"54241",
    "sg:province":"WI",
    "sg:tags":[
        "windows"
    ],
    "wof:name":"Door & Window Co The",
    "wof:placetype":"venue"
},
  "geometry": {"coordinates":[-87.56825600000001,44.151615],"type":"Point"}
}