{
  "type": "Feature",
  "properties": {
    "iso:country":"US",
    "sg:address":"220 Locust St",
    "sg:city":"Hudson",
    "sg:classifiers":[
        {
            "category":"Professional",
            "subcategory":"Lawyer & Legal Services",
            "type":"Services"
        }
    ],
    "sg:phone":"+1 715 386 7070",
    "sg:postcode":"54016",
    "sg:province":"WI",
    "sg:tags":[
        "attorney"
    ],
    "wof:name":"Bartholomew Law Office",
    "wof:placetype":"venue"
},
  "geometry": {"coordinates":[-92.756652,44.975879],"type":"Point"}
}