{
  "type": "Feature",
  "properties": {
    "iso:country":"US",
    "sg:address":"21107 Man Cal Rd",
    "sg:city":"Reedsville",
    "sg:classifiers":[
        {
            "category":"Farming",
            "subcategory":"Farm",
            "type":"Manufacturing & Wholesale Goods"
        }
    ],
    "sg:phone":"+1 920 864 3387",
    "sg:postcode":"54230",
    "sg:province":"WI",
    "sg:tags":[
        "crop",
        "general"
    ],
    "wof:name":"Dew Hoyer LLC",
    "wof:placetype":"venue"
},
  "geometry": {"coordinates":[-87.98445,44.240625],"type":"Point"}
}