{
  "type": "Feature",
  "properties": {
    "iso:country":"US",
    "sg:address":"824 Winneconne Ave",
    "sg:city":"Neenah",
    "sg:classifiers":[
        {
            "category":"Recreation",
            "type":"Entertainment"
        }
    ],
    "sg:phone":"+1 920 725 5425",
    "sg:postcode":"54956",
    "sg:province":"WI",
    "sg:tags":[
        "karate",
        "martial",
        "arts",
        "instruction",
        "school"
    ],
    "wof:name":"Karate America Neenah",
    "wof:placetype":"venue"
},
  "geometry": {"coordinates":[-88.480991,44.177336],"type":"Point"}
}