{
  "type": "Feature",
  "properties": {
    "iso:country":"US",
    "sg:address":"218 S Wisconsin Dr",
    "sg:city":"Jefferson",
    "sg:classifiers":[
        {
            "category":"Professional",
            "type":"Services"
        }
    ],
    "sg:phone":"+1 920 674 5133",
    "sg:postcode":"53549",
    "sg:province":"WI",
    "sg:tags":[
        "establishment"
    ],
    "wof:name":"Ken Anderson-North Wire",
    "wof:placetype":"venue"
},
  "geometry": {"coordinates":[-88.811091,43.003929],"type":"Point"}
}