{
  "type": "Feature",
  "properties": {
    "iso:country":"US",
    "sg:address":"1112 Beetown Rd",
    "sg:city":"Lancaster",
    "sg:classifiers":[
        {
            "category":"Manufacturing",
            "subcategory":"Printing",
            "type":"Manufacturing & Wholesale Goods"
        }
    ],
    "sg:phone":"+1 608 723 2204",
    "sg:postcode":"53813",
    "sg:province":"WI",
    "sg:tags":[
        "printer"
    ],
    "wof:name":"Zip Print",
    "wof:placetype":"venue"
},
  "geometry": {"coordinates":[-90.72052499999999,42.841005],"type":"Point"}
}