{
  "type": "Feature",
  "properties": {
    "iso:country":"US",
    "sg:address":"2911 John Ave",
    "sg:city":"Superior",
    "sg:classifiers":[
        {
            "category":"Shopping",
            "subcategory":"Clothing, Apparel, & Fashions",
            "type":"Retail Goods"
        }
    ],
    "sg:phone":"+1 715 394 2522",
    "sg:postcode":"54880",
    "sg:province":"WI",
    "wof:name":"Tuxedo One",
    "wof:placetype":"venue"
},
  "geometry": {"coordinates":[-92.1011,46.704957],"type":"Point"}
}