{
  "type": "Feature",
  "properties": {
    "addr:full":"312 Sugar Bush Ln Elkhart Lake WI 53020",
    "addr:housenumber":"312",
    "addr:postcode":"53020",
    "addr:street":"Sugar Bush Ln",
    "iso:country":"US",
    "sg:address":"312 Sugar Bush Ln",
    "sg:city":"Elkhart Lake",
    "sg:classifiers":[
        {
            "category":"Professional",
            "subcategory":"Business Services",
            "type":"Services"
        },
        {
            "category":"Professional",
            "subcategory":"Management & Consulting",
            "type":"Services"
        }
    ],
    "sg:phone":"+1 920 876 4357",
    "sg:postcode":"53020",
    "sg:province":"WI",
    "sg:tags":[
        "party",
        "planning"
    ],
    "wof:name":"J R's Helping Hands",
    "wof:placetype":"venue"
},
  "geometry": {"coordinates":[-88.01258799999999,43.821269],"type":"Point"}
}