{
  "type": "Feature",
  "properties": {
    "addr:full":"377 N Rolling Meadows Dr Fond Du Lac WI 54937",
    "addr:housenumber":"377",
    "addr:postcode":"54937",
    "addr:street":"N Rolling Meadows Dr",
    "iso:country":"US",
    "sg:address":"377 N Rolling Meadows Dr",
    "sg:city":"Fond Du Lac",
    "sg:classifiers":[
        {
            "category":"Professional",
            "subcategory":"Accounting & Tax Preparation",
            "type":"Services"
        }
    ],
    "sg:phone":"+1 920 924 0493",
    "sg:postcode":"54937",
    "sg:province":"WI",
    "sg:tags":[
        "return",
        "filing"
    ],
    "wof:name":"H & R Block Tax Svc",
    "wof:placetype":"venue"
},
  "geometry": {"coordinates":[-88.486372,43.788971],"type":"Point"}
}