{
  "type": "Feature",
  "properties": {
    "iso:country":"US",
    "sg:address":"110 N 1st St",
    "sg:city":"Whitewater",
    "sg:classifiers":[
        {
            "category":"Insurance",
            "subcategory":"Insurance Agent",
            "type":"Services"
        }
    ],
    "sg:phone":"+1 262 473 5454",
    "sg:postcode":"53190",
    "sg:province":"WI",
    "wof:name":"Knudsen Insurance",
    "wof:placetype":"venue"
},
  "geometry": {"coordinates":[-88.731005,42.835023],"type":"Point"}
}