{
  "type": "Feature",
  "properties": {
    "addr:full":"27775 Shay Ln Arcadia WI 54612",
    "addr:postcode":"27775;54612",
    "addr:street":"Shay Ln",
    "iso:country":"US",
    "sg:address":"27775 Shay Ln",
    "sg:city":"Arcadia",
    "sg:classifiers":[
        {
            "category":"Shopping",
            "subcategory":"Gifts & Souvenirs",
            "type":"Retail Goods"
        }
    ],
    "sg:phone":"+1 608 525 2210",
    "sg:postcode":"54612",
    "sg:province":"WI",
    "wof:name":"Moonpenny Hills Creations",
    "wof:placetype":"venue"
},
  "geometry": {"coordinates":[-91.34435000000001,44.243863],"type":"Point"}
}