{
  "type": "Feature",
  "properties": {
    "addr:full":"2962 Willow Creek Rd Colgate WI 53017",
    "addr:housenumber":"2962",
    "addr:postcode":"53017",
    "addr:street":"Willow Creek Rd Colgate",
    "iso:country":"US",
    "sg:address":"2962 Willow Creek Rd",
    "sg:city":"Colgate",
    "sg:classifiers":[
        {
            "category":"Professional",
            "subcategory":"Advertising",
            "type":"Services"
        }
    ],
    "sg:phone":"+1 262 628 4052",
    "sg:postcode":"53017",
    "sg:province":"WI",
    "sg:tags":[
        "distribution"
    ],
    "wof:name":"G E Consumer Ind",
    "wof:placetype":"venue"
},
  "geometry": {"coordinates":[-88.184888,43.20722],"type":"Point"}
}