{
  "type": "Feature",
  "properties": {
    "iso:country":"US",
    "sg:address":"205 S Holmen Dr Ste 104",
    "sg:city":"Holmen",
    "sg:classifiers":[
        {
            "category":"Autos & Motor Vehicles",
            "subcategory":"Auto Supplies",
            "type":"Retail Goods"
        }
    ],
    "sg:phone":"+1 608 526 5841",
    "sg:postcode":"54636",
    "sg:province":"WI",
    "sg:tags":[
        "automobile",
        "part",
        "accessory"
    ],
    "wof:name":"United Auto Supply",
    "wof:placetype":"venue"
},
  "geometry": {"coordinates":[-91.262142,43.960929],"type":"Point"}
}