{
  "type": "Feature",
  "properties": {
    "iso:country":"US",
    "sg:address":"5745 Shamrock Ln",
    "sg:city":"Hubertus",
    "sg:classifiers":[
        {
            "category":"Wholesale",
            "subcategory":"Auto Parts",
            "type":"Manufacturing & Wholesale Goods"
        }
    ],
    "sg:phone":"+1 262 628 1064",
    "sg:postcode":"53033",
    "sg:province":"WI",
    "sg:tags":[
        "automobile",
        "tire",
        "accessory"
    ],
    "wof:name":"TBA Distributors Inc",
    "wof:placetype":"venue"
},
  "geometry": {"coordinates":[-88.315784,43.229203],"type":"Point"}
}