{
  "type": "Feature",
  "properties": {
    "addr:full":"6617 Old Hwy 18 Stevens Point WI 54481",
    "addr:housenumber":"6617",
    "addr:postcode":"54481",
    "addr:street":"Old Hwy 18",
    "iso:country":"US",
    "sg:address":"6617 Old Hwy 18",
    "sg:city":"Stevens Point",
    "sg:phone":"+1 715 592 4522",
    "sg:postcode":"54481",
    "sg:province":"WI",
    "sg:tags":[
        "farm",
        "corn",
        "cash",
        "crop",
        "field",
        "grain"
    ],
    "wof:name":"Marvin Lutz",
    "wof:placetype":"venue"
},
  "geometry": {"coordinates":[-89.45700600000001,44.510764],"type":"Point"}
}