{
  "type": "Feature",
  "properties": {
    "iso:country":"US",
    "sg:address":"421 Eagle St",
    "sg:city":"Ripon",
    "sg:classifiers":[
        {
            "category":"Retail",
            "subcategory":"Auto Repair",
            "type":"Services"
        }
    ],
    "sg:phone":"+1 920 748 5193",
    "sg:postcode":"54971",
    "sg:province":"WI",
    "sg:tags":[
        "general"
    ],
    "wof:name":"Riverside Automotive Service &",
    "wof:placetype":"venue"
},
  "geometry": {"coordinates":[-88.84280099999999,43.850313],"type":"Point"}
}