{
  "type": "Feature",
  "properties": {
    "iso:country":"US",
    "sg:address":"105 W Park St",
    "sg:city":"Westby",
    "sg:classifiers":[
        {
            "category":"Building & Trades",
            "subcategory":"Construction",
            "type":"Services"
        }
    ],
    "sg:phone":"+1 608 634 4319",
    "sg:postcode":"54667",
    "sg:province":"WI",
    "sg:tags":[
        "excavation",
        "contractor"
    ],
    "wof:name":"Melbys Excavating & Hauling",
    "wof:placetype":"venue"
},
  "geometry": {"coordinates":[-90.857833,43.656587],"type":"Point"}
}