{
  "type": "Feature",
  "properties": {
    "iso:country":"US",
    "sg:address":"2545 Roosevelt Rd",
    "sg:city":"Marinette",
    "sg:classifiers":[
        {
            "category":"Shopping",
            "subcategory":"Used Merchandise",
            "type":"Retail Goods"
        }
    ],
    "sg:phone":"+1 715 732 4004",
    "sg:postcode":"54143",
    "sg:province":"WI",
    "sg:tags":[
        "shop",
        "consignment"
    ],
    "wof:name":"Goodwill Industries",
    "wof:placetype":"venue"
},
  "geometry": {"coordinates":[-87.658372,45.056103],"type":"Point"}
}