{
  "type": "Feature",
  "properties": {
    "iso:country":"US",
    "sg:address":"2520 Eastwood Ln",
    "sg:city":"Brookfield",
    "sg:classifiers":[
        {
            "category":"Autos & Motor Vehicles",
            "subcategory":"Motorcycle Sales",
            "type":"Retail Goods"
        }
    ],
    "sg:phone":"+1 262 938 2348",
    "sg:postcode":"53005",
    "sg:province":"WI",
    "sg:tags":[
        "scooter"
    ],
    "wof:name":"Ironhorse Trading Company",
    "wof:placetype":"venue"
},
  "geometry": {"coordinates":[-88.078752,43.063873],"type":"Point"}
}