{
  "type": "Feature",
  "properties": {
    "iso:country":"US",
    "sg:address":"1117 N Sunnyslope Dr",
    "sg:city":"Racine",
    "sg:classifiers":[
        {
            "category":"Shopping",
            "subcategory":"Gifts & Souvenirs",
            "type":"Retail Goods"
        }
    ],
    "sg:phone":"+1 262 634 1834",
    "sg:postcode":"53406",
    "sg:province":"WI",
    "sg:tags":[
        "shop"
    ],
    "wof:name":"Corner Gift Shoppe",
    "wof:placetype":"venue"
},
  "geometry": {"coordinates":[-87.862961,42.734444],"type":"Point"}
}