{
  "type": "Feature",
  "properties": {
    "iso:country":"US",
    "sg:address":"16650 W Bluemound Rd",
    "sg:city":"Brookfield",
    "sg:classifiers":[
        {
            "category":"Banks & Credit Unions",
            "subcategory":"Investment Brokerage",
            "type":"Services"
        }
    ],
    "sg:phone":"+1 262 782 8914",
    "sg:postcode":"53005",
    "sg:province":"WI",
    "sg:tags":[
        "consultant",
        "planning",
        "financial"
    ],
    "sg:website":"www.waddell.com",
    "wof:name":"Waddell & Reed Inc",
    "wof:placetype":"venue"
},
  "geometry": {"coordinates":[-88.117093,43.036455],"type":"Point"}
}