{
  "type": "Feature",
  "properties": {
    "iso:country":"US",
    "sg:address":"425 S University Ave",
    "sg:city":"Beaver Dam",
    "sg:classifiers":[
        {
            "category":"Professional",
            "subcategory":"Management & Consulting",
            "type":"Services"
        }
    ],
    "sg:phone":"+1 920 887 9785",
    "sg:postcode":"53916",
    "sg:province":"WI",
    "wof:name":"Pro Property Management",
    "wof:placetype":"venue"
},
  "geometry": {"coordinates":[-88.82875900000001,43.45264],"type":"Point"}
}