{
  "type": "Feature",
  "properties": {
    "iso:country":"US",
    "sg:address":"1811 School Rd",
    "sg:city":"Greenleaf",
    "sg:classifiers":[
        {
            "category":"Retail",
            "subcategory":"Repair Shop",
            "type":"Services"
        }
    ],
    "sg:phone":"+1 920 864 7795",
    "sg:postcode":"54126",
    "sg:province":"WI",
    "sg:tags":[
        "operator",
        "sp",
        "truck",
        "mfg"
    ],
    "wof:name":"Renon Randy Trucking",
    "wof:placetype":"venue"
},
  "geometry": {"coordinates":[-88.065338,44.342995],"type":"Point"}
}