{
  "type": "Feature",
  "properties": {
    "addr:full":"6334 W National Ave Milwaukee WI 53214",
    "addr:housenumber":"6334",
    "addr:postcode":"53214",
    "addr:street":"W National Ave",
    "iso:country":"US",
    "sg:address":"6334 W National Ave",
    "sg:city":"Milwaukee",
    "sg:classifiers":[
        {
            "category":"Building & Trades",
            "subcategory":"Construction",
            "type":"Services"
        }
    ],
    "sg:phone":"+1 414 460 9676",
    "sg:postcode":"53214",
    "sg:province":"WI",
    "sg:tags":[
        "general",
        "contractor"
    ],
    "wof:name":"Mandel V Building Inc",
    "wof:placetype":"venue"
},
  "geometry": {"coordinates":[-87.990144,43.016722],"type":"Point"}
}