{
  "type": "Feature",
  "properties": {
    "addr:full":"3127 Ambrose Rd Ladysmith WI 54848",
    "addr:housenumber":"3127",
    "addr:postcode":"54848",
    "addr:street":"Ambrose Rd",
    "iso:country":"US",
    "sg:address":"3127 Ambrose Rd",
    "sg:city":"Ladysmith",
    "sg:classifiers":[
        {
            "category":"Farming",
            "subcategory":"Dairy Farm",
            "type":"Manufacturing & Wholesale Goods"
        }
    ],
    "sg:phone":"+1 715 532 7517",
    "sg:postcode":"54848",
    "sg:province":"WI",
    "wof:name":"Paul Quinnell",
    "wof:placetype":"venue"
},
  "geometry": {"coordinates":[-91.07952899999999,45.401186],"type":"Point"}
}