{
  "type": "Feature",
  "properties": {
    "iso:country":"US",
    "sg:address":"27423 State Hwy 121",
    "sg:city":"Independence",
    "sg:classifiers":[
        {
            "category":"Farming",
            "subcategory":"Dairy Farm",
            "type":"Manufacturing & Wholesale Goods"
        }
    ],
    "sg:phone":"+1 715 985 3721",
    "sg:postcode":"54747",
    "sg:province":"WI",
    "wof:name":"Roger & Larry Roskos",
    "wof:placetype":"venue"
},
  "geometry": {"coordinates":[-91.497015,44.426138],"type":"Point"}
}