{
  "type": "Feature",
  "properties": {
    "iso:country":"US",
    "sg:address":"9675 Townline Rd",
    "sg:city":"Kewaskum",
    "sg:classifiers":[
        {
            "category":"Building & Trades",
            "subcategory":"Construction",
            "type":"Services"
        }
    ],
    "sg:phone":"+1 262 626 1564",
    "sg:postcode":"53040",
    "sg:province":"WI",
    "sg:tags":[
        "house"
    ],
    "wof:name":"K&H Builders LLC",
    "wof:placetype":"venue"
},
  "geometry": {"coordinates":[-88.28119,43.537043],"type":"Point"}
}