{
  "type": "Feature",
  "properties": {
    "iso:country":"US",
    "sg:address":"8989 N Port Washington Rd",
    "sg:city":"Milwaukee",
    "sg:classifiers":[
        {
            "category":"Recreation",
            "type":"Entertainment"
        }
    ],
    "sg:phone":"+1 414 540 3830",
    "sg:postcode":"53217",
    "sg:province":"WI",
    "sg:tags":[
        "instruction",
        "golf"
    ],
    "sg:website":"www.gfw.org",
    "wof:name":"Golf Foundation Of Wisconsin",
    "wof:placetype":"venue"
},
  "geometry": {"coordinates":[-87.91391,43.180891],"type":"Point"}
}