{
  "type": "Feature",
  "properties": {
    "addr:full":"10380 W Silver Spring Dr Milwaukee WI 53225",
    "addr:housenumber":"10380",
    "addr:postcode":"53225",
    "addr:street":"W Silver Spring Dr",
    "iso:country":"US",
    "sg:address":"10380 W Silver Spring Dr",
    "sg:city":"Milwaukee",
    "sg:classifiers":[
        {
            "category":"Banks & Credit Unions",
            "subcategory":"Bank",
            "type":"Services"
        }
    ],
    "sg:phone":"+1 414 410 0575",
    "sg:postcode":"53225",
    "sg:province":"WI",
    "wof:name":"Guaranty Bank",
    "wof:placetype":"venue"
},
  "geometry": {"coordinates":[-88.043707,43.119462],"type":"Point"}
}