{
  "type": "Feature",
  "properties": {
    "iso:country":"US",
    "sg:address":"629 N 8th St",
    "sg:city":"Sheboygan",
    "sg:classifiers":[
        {
            "category":"Professional",
            "subcategory":"Advertising",
            "type":"Services"
        }
    ],
    "sg:phone":"+1 920 457 4077",
    "sg:postcode":"53081",
    "sg:province":"WI",
    "sg:tags":[
        "counselor"
    ],
    "wof:name":"Point De Vue",
    "wof:placetype":"venue"
},
  "geometry": {"coordinates":[-87.712858,43.75166],"type":"Point"}
}