{
  "type": "Feature",
  "properties": {
    "addr:full":"24317 75th St Salem WI 53168",
    "addr:housenumber":"24317",
    "addr:postcode":"53168",
    "addr:street":"75Th St",
    "iso:country":"US",
    "sg:address":"24317 75th St",
    "sg:city":"Salem",
    "sg:classifiers":[
        {
            "category":"Restaurant",
            "type":"Food & Drink"
        }
    ],
    "sg:phone":"+1 262 843 2816",
    "sg:postcode":"53168",
    "sg:province":"WI",
    "wof:name":"Friday's Bar & Grill",
    "wof:placetype":"venue"
},
  "geometry": {"coordinates":[-88.102501,42.5681],"type":"Point"}
}