{
  "type": "Feature",
  "properties": {
    "iso:country":"US",
    "sg:address":"212 S Peterson St",
    "sg:city":"Spring Green",
    "sg:classifiers":[
        {
            "category":"Freight",
            "type":"Transportation"
        }
    ],
    "sg:phone":"+1 608 588 7239",
    "sg:postcode":"53588",
    "sg:province":"WI",
    "sg:tags":[
        "cooperative"
    ],
    "wof:name":"Frontier F S Cooperative",
    "wof:placetype":"venue"
},
  "geometry": {"coordinates":[-90.059076,43.174234],"type":"Point"}
}