{
  "type": "Feature",
  "properties": {
    "iso:country":"US",
    "sg:address":"6929 S County Road T",
    "sg:city":"Brodhead",
    "sg:classifiers":[
        {
            "category":"Fast Food",
            "type":"Food & Drink"
        },
        {
            "category":"Restaurant",
            "type":"Food & Drink"
        }
    ],
    "sg:phone":"+1 608 897 3800",
    "sg:postcode":"53520",
    "sg:province":"WI",
    "sg:tags":[
        "style",
        "family"
    ],
    "wof:name":"Sand Burr Family Restaurant",
    "wof:placetype":"venue"
},
  "geometry": {"coordinates":[-89.36660000000001,42.581773],"type":"Point"}
}