{
  "type": "Feature",
  "properties": {
    "iso:country":"US",
    "sg:address":"2794 Century Lane Rd",
    "sg:city":"Oostburg",
    "sg:classifiers":[
        {
            "category":"Retail",
            "subcategory":"Repair Shop",
            "type":"Services"
        }
    ],
    "sg:phone":"+1 920 564 2747",
    "sg:postcode":"53070",
    "sg:province":"WI",
    "wof:name":"Century Lane Services",
    "wof:placetype":"venue"
},
  "geometry": {"coordinates":[-87.819401,43.634034],"type":"Point"}
}