{
  "type": "Feature",
  "properties": {
    "iso:country":"US",
    "sg:address":"5576 Rocky Ridge Rd",
    "sg:city":"Spooner",
    "sg:classifiers":[
        {
            "category":"Health Services",
            "subcategory":"Nursing And Care Facility",
            "type":"Services"
        }
    ],
    "sg:phone":"+1 715 635 6528",
    "sg:postcode":"54801",
    "sg:province":"WI",
    "sg:tags":[
        "home",
        "convalescent"
    ],
    "wof:name":"Schulz's Shady Oaks",
    "wof:placetype":"venue"
},
  "geometry": {"coordinates":[-91.907523,45.836602],"type":"Point"}
}