{
  "type": "Feature",
  "properties": {
    "iso:country":"US",
    "sg:address":"208 S Wisconsin St",
    "sg:city":"Whitewater",
    "sg:classifiers":[
        {
            "category":"Home & Garden",
            "subcategory":"Garden Supply",
            "type":"Retail Goods"
        },
        {
            "category":"Shopping",
            "subcategory":"Gifts & Souvenirs",
            "type":"Retail Goods"
        },
        {
            "category":"Shopping",
            "subcategory":"Crafts & Fabrics",
            "type":"Retail Goods"
        },
        {
            "category":"Shopping",
            "subcategory":"Florist",
            "type":"Retail Goods"
        }
    ],
    "sg:phone":"+1 262 473 6444",
    "sg:postcode":"53190",
    "sg:province":"WI",
    "sg:tags":[
        "plant",
        "etc-retail",
        "dried",
        "basket",
        "trees-silk",
        "flowers"
    ],
    "sg:website":"http://www.floralvillaflowers.com",
    "wof:name":"Floral Villa Flowers & Gifts",
    "wof:placetype":"venue"
},
  "geometry": {"coordinates":[-88.727463,42.833191],"type":"Point"}
}