{
  "type": "Feature",
  "properties": {
    "addr:full":"117 N 3rd St Medford WI 54451",
    "addr:housenumber":"117",
    "addr:postcode":"54451",
    "addr:street":"N 3Rd St",
    "iso:country":"US",
    "sg:address":"117 N 3rd St",
    "sg:city":"Medford",
    "sg:classifiers":[
        {
            "category":"Organizations",
            "subcategory":"Religious Organization",
            "type":"Services"
        }
    ],
    "sg:phone":"+1 715 748 5919",
    "sg:postcode":"54451",
    "sg:province":"WI",
    "wof:name":"Terry Erickson Pastor",
    "wof:placetype":"venue"
},
  "geometry": {"coordinates":[-90.34396599999999,45.140979],"type":"Point"}
}