{
  "type": "Feature",
  "properties": {
    "iso:country":"US",
    "sg:address":"411 2nd St",
    "sg:city":"Hudson",
    "sg:classifiers":[
        {
            "category":"Shopping",
            "subcategory":"Used Merchandise",
            "type":"Retail Goods"
        }
    ],
    "sg:phone":"+1 715 381 1955",
    "sg:postcode":"54016",
    "sg:province":"WI",
    "wof:name":"Ross & Haines Old Books Co",
    "wof:placetype":"venue"
},
  "geometry": {"coordinates":[-92.756912,44.973877],"type":"Point"}
}