{
  "type": "Feature",
  "properties": {
    "iso:country":"US",
    "sg:address":"7920 Hemlock St",
    "sg:city":"Hewitt",
    "sg:classifiers":[
        {
            "category":"Building & Trades",
            "subcategory":"Construction",
            "type":"Services"
        }
    ],
    "sg:phone":"+1 715 389 1004",
    "sg:postcode":"54441",
    "sg:province":"WI",
    "sg:tags":[
        "house"
    ],
    "wof:name":"Hemlock Constructionm LLC",
    "wof:placetype":"venue"
},
  "geometry": {"coordinates":[-90.110889,44.637182],"type":"Point"}
}