{
  "type": "Feature",
  "properties": {
    "iso:country":"US",
    "sg:address":"113 Main St",
    "sg:city":"Kewaskum",
    "sg:classifiers":[
        {
            "category":"Professional",
            "type":"Services"
        }
    ],
    "sg:phone":"+1 262 626 8192",
    "sg:postcode":"53040",
    "sg:province":"WI",
    "wof:name":"Mikbets Unburied Treasures",
    "wof:placetype":"venue"
},
  "geometry": {"coordinates":[-88.227504,43.520926],"type":"Point"}
}