{
  "type": "Feature",
  "properties": {
    "iso:country":"US",
    "sg:address":"6451 Kestrel Rd",
    "sg:city":"Eau Claire",
    "sg:classifiers":[
        {
            "category":"Building & Trades",
            "subcategory":"Construction",
            "type":"Services"
        }
    ],
    "sg:phone":"+1 715 831 1110",
    "sg:postcode":"54701",
    "sg:province":"WI",
    "sg:tags":[
        "concrete",
        "contractor"
    ],
    "wof:name":"CTI Of Western Wisconsin",
    "wof:placetype":"venue"
},
  "geometry": {"coordinates":[-91.40514899999999,44.731996],"type":"Point"}
}