{
  "type": "Feature",
  "properties": {
    "iso:country":"US",
    "sg:address":"320 Worden Ave E",
    "sg:city":"Ladysmith",
    "sg:classifiers":[
        {
            "category":"Manufacturing",
            "subcategory":"Metals",
            "type":"Manufacturing & Wholesale Goods"
        }
    ],
    "sg:phone":"+1 715 532 7262",
    "sg:postcode":"54848",
    "sg:province":"WI",
    "sg:tags":[
        "windows"
    ],
    "wof:name":"Weather Shield Window Showroom",
    "wof:placetype":"venue"
},
  "geometry": {"coordinates":[-91.097956,45.463244],"type":"Point"}
}