{
  "type": "Feature",
  "properties": {
    "iso:country":"US",
    "sg:address":"26454 Kiln Ave",
    "sg:city":"Wilton",
    "sg:classifiers":[
        {
            "category":"Building & Trades",
            "subcategory":"Equipment Rental",
            "type":"Services"
        }
    ],
    "sg:phone":"+1 608 435 6181",
    "sg:postcode":"54670",
    "sg:province":"WI",
    "wof:name":"Zinke Rentals LLC",
    "wof:placetype":"venue"
},
  "geometry": {"coordinates":[-90.462782,43.867504],"type":"Point"}
}