{
  "type": "Feature",
  "properties": {
    "iso:country":"US",
    "sg:address":"2115 Coulee Rd",
    "sg:city":"Hudson",
    "sg:classifiers":[
        {
            "category":"Food & Beverages",
            "subcategory":"Specialty",
            "type":"Retail Goods"
        }
    ],
    "sg:phone":"+1 715 386 7726",
    "sg:postcode":"54016",
    "sg:province":"WI",
    "sg:tags":[
        "health",
        "diet"
    ],
    "wof:name":"GNC",
    "wof:placetype":"venue"
},
  "geometry": {"coordinates":[-92.732152,44.96351],"type":"Point"}
}