{
  "type": "Feature",
  "properties": {
    "iso:country":"US",
    "sg:address":"20 River St",
    "sg:city":"Belleville",
    "sg:classifiers":[
        {
            "category":"Building & Trades",
            "subcategory":"Construction",
            "type":"Services"
        }
    ],
    "sg:phone":"+1 608 424 3666",
    "sg:postcode":"53508",
    "sg:province":"WI",
    "sg:tags":[
        "marking",
        "maintenance",
        "parking"
    ],
    "wof:name":"Belleville Public Works",
    "wof:placetype":"venue"
},
  "geometry": {"coordinates":[-89.533265,42.860183],"type":"Point"}
}