{
  "type": "Feature",
  "properties": {
    "iso:country":"US",
    "sg:address":"5645 N Green Bay Ave",
    "sg:city":"Milwaukee",
    "sg:classifiers":[
        {
            "category":"Recreation",
            "type":"Entertainment"
        }
    ],
    "sg:phone":"+1 414 871 4644",
    "sg:postcode":"53209",
    "sg:province":"WI",
    "sg:tags":[
        "astrologer"
    ],
    "wof:name":"Jane Laev Astrologer",
    "wof:placetype":"venue"
},
  "geometry": {"coordinates":[-87.93530800000001,43.120353],"type":"Point"}
}