{
  "type": "Feature",
  "properties": {
    "addr:full":"1903 Progress Way Kaukauna WI 54130",
    "addr:housenumber":"1903",
    "addr:postcode":"54130",
    "addr:street":"Progress Way",
    "iso:country":"US",
    "sg:address":"1903 Progress Way",
    "sg:city":"Kaukauna",
    "sg:classifiers":[
        {
            "category":"Home & Garden",
            "subcategory":"Garden Supply",
            "type":"Retail Goods"
        }
    ],
    "sg:phone":"+1 920 759 0119",
    "sg:postcode":"54130",
    "sg:province":"WI",
    "sg:tags":[
        "landscaping",
        "equipment"
    ],
    "wof:name":"Lesco Service Ctr",
    "wof:placetype":"venue"
},
  "geometry": {"coordinates":[-88.26115799999999,44.303991],"type":"Point"}
}