{
  "type": "Feature",
  "properties": {
    "iso:country":"US",
    "sg:address":"1512 N 12th St",
    "sg:city":"Superior",
    "sg:classifiers":[
        {
            "category":"Manufacturing",
            "subcategory":"Printing",
            "type":"Manufacturing & Wholesale Goods"
        }
    ],
    "sg:phone":"+1 715 392 8268",
    "sg:postcode":"54880",
    "sg:province":"WI",
    "sg:tags":[
        "newspaper"
    ],
    "sg:website":"www.catholicherald.org",
    "wof:name":"Catholic Herald",
    "wof:placetype":"venue"
},
  "geometry": {"coordinates":[-92.100773,46.724185],"type":"Point"}
}