{
  "type": "Feature",
  "properties": {
    "iso:country":"US",
    "sg:address":"2400 W Capitol Dr",
    "sg:city":"Milwaukee",
    "sg:classifiers":[
        {
            "category":"Social Services",
            "subcategory":"Child Care",
            "type":"Services"
        }
    ],
    "sg:phone":"+1 414 447 9180",
    "sg:postcode":"53206",
    "sg:province":"WI",
    "wof:name":"Latasha's Learning Enterprise",
    "wof:placetype":"venue"
},
  "geometry": {"coordinates":[-87.94354,43.089731],"type":"Point"}
}