{
  "type": "Feature",
  "properties": {
    "addr:full":"1777 Lake Rd Mukwonago WI 53149",
    "addr:housenumber":"1777",
    "addr:postcode":"53149",
    "addr:street":"Lake Rd",
    "iso:country":"US",
    "sg:address":"1777 Lake Rd",
    "sg:city":"Mukwonago",
    "sg:classifiers":[
        {
            "category":"Building & Trades",
            "subcategory":"Construction",
            "type":"Services"
        }
    ],
    "sg:phone":"+1 262 642 9000",
    "sg:postcode":"53149",
    "sg:province":"WI",
    "sg:tags":[
        "house"
    ],
    "wof:name":"Restoration Services SE Wis",
    "wof:placetype":"venue"
},
  "geometry": {"coordinates":[-88.38973300000001,42.828226],"type":"Point"}
}