{
  "type": "Feature",
  "properties": {
    "iso:country":"US",
    "sg:address":"3171 Yeager Dr",
    "sg:city":"Green Bay",
    "sg:classifiers":[
        {
            "category":"Wholesale",
            "subcategory":"Machinery & Supplies",
            "type":"Manufacturing & Wholesale Goods"
        }
    ],
    "sg:phone":"+1 920 468 3012",
    "sg:postcode":"54311",
    "sg:province":"WI",
    "sg:tags":[
        "repair",
        "industrial",
        "equipment"
    ],
    "wof:name":"Hydraulic Services Inc",
    "wof:placetype":"venue"
},
  "geometry": {"coordinates":[-87.920158,44.477804],"type":"Point"}
}