{
  "type": "Feature",
  "properties": {
    "iso:country":"US",
    "sg:address":"15497 Pinewood Dr",
    "sg:city":"Hayward",
    "sg:classifiers":[
        {
            "category":"Social Services",
            "subcategory":"Adult Care",
            "type":"Services"
        }
    ],
    "sg:phone":"+1 715 634 5767",
    "sg:postcode":"54843",
    "sg:province":"WI",
    "sg:tags":[
        "residential"
    ],
    "wof:name":"Friendship Manor Homes",
    "wof:placetype":"venue"
},
  "geometry": {"coordinates":[-91.46716499999999,46.001703],"type":"Point"}
}