{
  "type": "Feature",
  "properties": {
    "addr:full":"620 E Richmond St Shawano WI 54166",
    "addr:housenumber":"620",
    "addr:postcode":"54166",
    "addr:street":"E Richmond St",
    "iso:country":"US",
    "sg:address":"620 E Richmond St",
    "sg:city":"Shawano",
    "sg:classifiers":[
        {
            "category":"Freight",
            "type":"Transportation"
        }
    ],
    "sg:phone":"+1 715 524 4866",
    "sg:postcode":"54166",
    "sg:province":"WI",
    "sg:tags":[
        "cartage",
        "trucking"
    ],
    "wof:name":"Expedited Freight Systems Inc",
    "wof:placetype":"venue"
},
  "geometry": {"coordinates":[-88.600391,44.774702],"type":"Point"}
}