{
  "type": "Feature",
  "properties": {
    "iso:country":"US",
    "sg:address":"639 W Kemp St",
    "sg:city":"Rhinelander",
    "sg:classifiers":[
        {
            "category":"Government",
            "subcategory":"Office",
            "type":"Public Place"
        }
    ],
    "sg:phone":"+1 715 369 6166",
    "sg:postcode":"54501",
    "sg:province":"WI",
    "sg:tags":[
        "county"
    ],
    "wof:name":"Land Conservation Dept",
    "wof:placetype":"venue"
},
  "geometry": {"coordinates":[-89.421841,45.631906],"type":"Point"}
}