{
  "type": "Feature",
  "properties": {
    "iso:country":"US",
    "sg:address":"3115 Camp Phillips Rd",
    "sg:city":"Wausau",
    "sg:classifiers":[
        {
            "category":"Restaurant",
            "type":"Food & Drink"
        }
    ],
    "sg:phone":"+1 715 848 2202",
    "sg:postcode":"54403",
    "sg:province":"WI",
    "sg:tags":[
        "drinking",
        "eating"
    ],
    "wof:name":"Iozzo's Italian Food",
    "wof:placetype":"venue"
},
  "geometry": {"coordinates":[-89.572256,44.928822],"type":"Point"}
}