{
  "type": "Feature",
  "properties": {
    "iso:country":"US",
    "sg:address":"955 N 14th St",
    "sg:city":"Milwaukee",
    "sg:classifiers":[
        {
            "category":"Real Estate",
            "subcategory":"Real Estate Operator",
            "type":"Services"
        }
    ],
    "sg:phone":"+1 414 344 2024",
    "sg:postcode":"53233",
    "sg:province":"WI",
    "sg:tags":[
        "apartment"
    ],
    "wof:name":"State Street Apartments",
    "wof:placetype":"venue"
},
  "geometry": {"coordinates":[-87.930181,43.042321],"type":"Point"}
}