{
  "type": "Feature",
  "properties": {
    "iso:country":"US",
    "sg:address":"5600 75th St",
    "sg:city":"Kenosha",
    "sg:classifiers":[
        {
            "category":"Shopping",
            "subcategory":"Bicycles & Sporting Goods",
            "type":"Retail Goods"
        }
    ],
    "sg:phone":"+1 262 694 6640",
    "sg:postcode":"53142",
    "sg:province":"WI",
    "sg:tags":[
        "new",
        "used"
    ],
    "wof:name":"Play It Again Sports",
    "wof:placetype":"venue"
},
  "geometry": {"coordinates":[-87.874735,42.566537],"type":"Point"}
}