{
  "type": "Feature",
  "properties": {
    "addr:full":"2680 Mehring Rd Jefferson WI 53549",
    "addr:postcode":"2680;53549",
    "addr:street":"Mehring Rd",
    "iso:country":"US",
    "sg:address":"2680 Mehring Rd",
    "sg:city":"Jefferson",
    "sg:classifiers":[
        {
            "category":"Building & Trades",
            "subcategory":"Construction",
            "type":"Services"
        }
    ],
    "sg:phone":"+1 920 568 1101",
    "sg:postcode":"53549",
    "sg:province":"WI",
    "sg:tags":[
        "general",
        "contractor"
    ],
    "wof:name":"Wileman Construction LLC",
    "wof:placetype":"venue"
},
  "geometry": {"coordinates":[-88.66123,42.937435],"type":"Point"}
}