{
  "type": "Feature",
  "properties": {
    "iso:country":"US",
    "sg:address":"1908 de Koven Ave",
    "sg:city":"Racine",
    "sg:classifiers":[
        {
            "category":"Manufacturing",
            "subcategory":"Tools & Machinery",
            "type":"Manufacturing & Wholesale Goods"
        }
    ],
    "sg:phone":"+1 262 633 5070",
    "sg:postcode":"53403",
    "sg:province":"WI",
    "sg:tags":[
        "dust",
        "collecting",
        "mfg",
        "equipment"
    ],
    "sg:website":"www.ultradustcollectors.com",
    "wof:name":"Ultra Industries Inc",
    "wof:placetype":"venue"
},
  "geometry": {"coordinates":[-87.802999,42.707626],"type":"Point"}
}