{
  "type": "Feature",
  "properties": {
    "iso:country":"US",
    "sg:address":"215 Bader Rd",
    "sg:city":"Luxemburg",
    "sg:classifiers":[
        {
            "category":"Insurance",
            "subcategory":"Insurance Agent",
            "type":"Services"
        }
    ],
    "sg:phone":"+1 920 845 5454",
    "sg:postcode":"54217",
    "sg:province":"WI",
    "wof:name":"AFLAC",
    "wof:placetype":"venue"
},
  "geometry": {"coordinates":[-87.758505,44.639446],"type":"Point"}
}