{
  "type": "Feature",
  "properties": {
    "iso:country":"US",
    "sg:address":"1159 Johnson Dr",
    "sg:city":"New Richmond",
    "sg:classifiers":[
        {
            "category":"Professional",
            "subcategory":"Advertising",
            "type":"Services"
        }
    ],
    "sg:phone":"+1 715 246 5827",
    "sg:postcode":"54017",
    "sg:province":"WI",
    "wof:name":"Ecm Distributors Inc",
    "wof:placetype":"venue"
},
  "geometry": {"coordinates":[-92.528577,45.133761],"type":"Point"}
}