{
  "type": "Feature",
  "properties": {
    "iso:country":"US",
    "sg:address":"1643 Harding Ave",
    "sg:city":"Eau Claire",
    "sg:classifiers":[
        {
            "category":"Professional",
            "subcategory":"Computer Services",
            "type":"Services"
        }
    ],
    "sg:phone":"+1 715 835 8834",
    "sg:postcode":"54701",
    "sg:province":"WI",
    "sg:tags":[
        "consultant",
        "designer"
    ],
    "sg:website":"www.cwcs.com",
    "wof:name":"Clearwater Computer Svc Inc",
    "wof:placetype":"venue"
},
  "geometry": {"coordinates":[-91.477434,44.800295],"type":"Point"}
}