{
  "type": "Feature",
  "properties": {
    "iso:country":"US",
    "sg:address":"2434 N 68th St",
    "sg:city":"Milwaukee",
    "sg:phone":"+1 414 258 8941",
    "sg:postcode":"53213",
    "sg:province":"WI",
    "sg:tags":[
        "farm",
        "corn",
        "soybean"
    ],
    "wof:name":"Robert Swietzer",
    "wof:placetype":"venue"
},
  "geometry": {"coordinates":[-87.997406,43.063748],"type":"Point"}
}