{
  "type": "Feature",
  "properties": {
    "iso:country":"US",
    "sg:address":"1406 Mill Rd",
    "sg:city":"Sturgeon Bay",
    "sg:classifiers":[
        {
            "category":"Farming",
            "subcategory":"Dairy Farm",
            "type":"Manufacturing & Wholesale Goods"
        }
    ],
    "sg:phone":"+1 920 856 6203",
    "sg:postcode":"54235",
    "sg:province":"WI",
    "wof:name":"Kenneth Baudhuin",
    "wof:placetype":"venue"
},
  "geometry": {"coordinates":[-87.48882399999999,44.742659],"type":"Point"}
}