{
  "type": "Feature",
  "properties": {
    "addr:full":"9663 State Hwy 144 Kewaskum WI 53040",
    "addr:housenumber":"9663",
    "addr:postcode":"53040",
    "addr:street":"State Hwy 144",
    "iso:country":"US",
    "sg:address":"9663 State Hwy 144",
    "sg:city":"Kewaskum",
    "sg:classifiers":[
        {
            "category":"Manufacturing",
            "subcategory":"Toys & Sporting Goods",
            "type":"Manufacturing & Wholesale Goods"
        }
    ],
    "sg:phone":"+1 262 692 9870",
    "sg:postcode":"53040",
    "sg:province":"WI",
    "sg:website":"www.twcoa.com",
    "wof:name":"TWC Of America Inc",
    "wof:placetype":"venue"
},
  "geometry": {"coordinates":[-88.088348,43.539556],"type":"Point"}
}