{
  "type": "Feature",
  "properties": {
    "addr:full":"6427 Hyslop Rd Waunakee WI 53597",
    "addr:housenumber":"6427",
    "addr:postcode":"53597",
    "addr:street":"Hyslop Rd",
    "iso:country":"US",
    "sg:address":"6427 Hyslop Rd",
    "sg:city":"Waunakee",
    "sg:classifiers":[
        {
            "category":"Professional",
            "type":"Services"
        }
    ],
    "sg:phone":"+1 608 850 4415",
    "sg:postcode":"53597",
    "sg:province":"WI",
    "wof:name":"Bill Ellickson",
    "wof:placetype":"venue"
},
  "geometry": {"coordinates":[-89.507766,43.209673],"type":"Point"}
}