{
  "type": "Feature",
  "properties": {
    "iso:country":"US",
    "sg:address":"13 Prescott St",
    "sg:city":"Elkhorn",
    "sg:classifiers":[
        {
            "category":"Social Services",
            "subcategory":"Adult Care",
            "type":"Services"
        }
    ],
    "sg:phone":"+1 262 723 2449",
    "sg:postcode":"53121",
    "sg:province":"WI",
    "sg:tags":[
        "home",
        "group"
    ],
    "wof:name":"Elkhorn Adult Group Home",
    "wof:placetype":"venue"
},
  "geometry": {"coordinates":[-88.54292700000001,42.663911],"type":"Point"}
}