{
  "type": "Feature",
  "properties": {
    "iso:country":"US",
    "sg:address":"6353 W Douglas Ave",
    "sg:city":"Milwaukee",
    "sg:classifiers":[
        {
            "category":"Professional",
            "subcategory":"Engineering",
            "type":"Services"
        }
    ],
    "sg:phone":"+1 414 464 2338",
    "sg:postcode":"53218",
    "sg:province":"WI",
    "sg:tags":[
        "engineer"
    ],
    "wof:name":"Terracon",
    "wof:placetype":"venue"
},
  "geometry": {"coordinates":[-87.986663,43.129413],"type":"Point"}
}