{
  "type": "Feature",
  "properties": {
    "addr:full":"4487 E Lakeview St Crandon WI 54520",
    "addr:housenumber":"4487",
    "addr:postcode":"54520",
    "addr:street":"E Lakeview St",
    "iso:country":"US",
    "sg:address":"4487 E Lakeview St",
    "sg:city":"Crandon",
    "sg:classifiers":[
        {
            "category":"Travel",
            "subcategory":"Hotels & Motels",
            "type":"Entertainment"
        }
    ],
    "sg:phone":"+1 715 478 2295",
    "sg:postcode":"54520",
    "sg:province":"WI",
    "wof:name":"Country Suites Motel",
    "wof:placetype":"venue"
},
  "geometry": {"coordinates":[-88.89284600000001,45.55122],"type":"Point"}
}