{
  "type": "Feature",
  "properties": {
    "iso:country":"US",
    "sg:address":"4171 Co Rd H",
    "sg:city":"Edgar",
    "sg:classifiers":[
        {
            "category":"Shopping",
            "type":"Retail Goods"
        }
    ],
    "sg:phone":"+1 715 687 3450",
    "sg:postcode":"54426",
    "sg:province":"WI",
    "sg:tags":[
        "merchandise"
    ],
    "wof:name":"Rocky Run Art",
    "wof:placetype":"venue"
},
  "geometry": {"coordinates":[-89.96414900000001,44.810135],"type":"Point"}
}