{
  "type": "Feature",
  "properties": {
    "iso:country":"US",
    "sg:address":"3188 Manitowoc Rd",
    "sg:city":"Green Bay",
    "sg:classifiers":[
        {
            "category":"Building & Trades",
            "subcategory":"Construction",
            "type":"Services"
        }
    ],
    "sg:phone":"+1 920 863 3941",
    "sg:postcode":"54311",
    "sg:province":"WI",
    "sg:tags":[
        "pipeline",
        "contractor"
    ],
    "wof:name":"Quanta",
    "wof:placetype":"venue"
},
  "geometry": {"coordinates":[-87.924409,44.447202],"type":"Point"}
}