{
  "type": "Feature",
  "properties": {
    "addr:full":"619 State St Madison WI 53703",
    "addr:housenumber":"619",
    "addr:postcode":"53703",
    "addr:street":"State St",
    "iso:country":"US",
    "sg:address":"619 State St",
    "sg:city":"Madison",
    "sg:classifiers":[
        {
            "category":"Shopping",
            "subcategory":"Shoes",
            "type":"Retail Goods"
        }
    ],
    "sg:phone":"+1 608 251 3771",
    "sg:postcode":"53703",
    "sg:province":"WI",
    "wof:name":"Famous Footwear",
    "wof:placetype":"venue"
},
  "geometry": {"coordinates":[-89.396264,43.0748],"type":"Point"}
}