{
  "type": "Feature",
  "properties": {
    "iso:country":"US",
    "sg:address":"156 S Franklin St",
    "sg:city":"Mondovi",
    "sg:classifiers":[
        {
            "category":"Local Transit",
            "type":"Transportation"
        }
    ],
    "sg:phone":"+1 715 926 3772",
    "sg:postcode":"54755",
    "sg:province":"WI",
    "sg:tags":[
        "ambulance"
    ],
    "wof:name":"Mondovi Ambulance Svc",
    "wof:placetype":"venue"
},
  "geometry": {"coordinates":[-91.671921,44.56732],"type":"Point"}
}