{
  "type": "Feature",
  "properties": {
    "addr:full":"2231 Holmgren Way Green Bay WI 54304",
    "addr:housenumber":"2231",
    "addr:postcode":"54304",
    "addr:street":"Holmgren Way",
    "iso:country":"US",
    "sg:address":"2231 Holmgren Way",
    "sg:city":"Green Bay",
    "sg:classifiers":[
        {
            "category":"Manufacturing",
            "subcategory":"Tools & Machinery",
            "type":"Manufacturing & Wholesale Goods"
        }
    ],
    "sg:phone":"+1 920 497 0390",
    "sg:postcode":"54304",
    "sg:province":"WI",
    "sg:tags":[
        "packaging",
        "mfg"
    ],
    "wof:name":"Masa USA LLC",
    "wof:placetype":"venue"
},
  "geometry": {"coordinates":[-88.059015,44.489894],"type":"Point"}
}