{
  "type": "Feature",
  "properties": {
    "iso:country":"US",
    "sg:address":"415 Trowbridge Dr",
    "sg:city":"Fond Du Lac",
    "sg:classifiers":[
        {
            "category":"Manufacturing",
            "subcategory":"Tools & Machinery",
            "type":"Manufacturing & Wholesale Goods"
        }
    ],
    "sg:phone":"+1 920 922 4327",
    "sg:postcode":"54937",
    "sg:province":"WI",
    "sg:tags":[
        "air"
    ],
    "sg:website":"www.hansenrefrigeration.com",
    "wof:name":"Hansen Refrig Machine Co",
    "wof:placetype":"venue"
},
  "geometry": {"coordinates":[-88.47614900000001,43.747161],"type":"Point"}
}