{
  "type": "Feature",
  "properties": {
    "iso:country":"US",
    "sg:address":"832 Kellogg Ave",
    "sg:city":"Janesville",
    "sg:classifiers":[
        {
            "category":"Real Estate",
            "subcategory":"Real Estate Operator",
            "type":"Services"
        }
    ],
    "sg:phone":"+1 608 754 8990",
    "sg:postcode":"53546",
    "sg:province":"WI",
    "sg:tags":[
        "building",
        "apartment"
    ],
    "wof:name":"Southview Terrace",
    "wof:placetype":"venue"
},
  "geometry": {"coordinates":[-89.028664,42.649773],"type":"Point"}
}