{
  "type": "Feature",
  "properties": {
    "iso:country":"US",
    "sg:address":"6844 Beech Rd",
    "sg:city":"Shawano",
    "sg:classifiers":[
        {
            "category":"Government",
            "subcategory":"Office",
            "type":"Public Place"
        }
    ],
    "sg:phone":"+1 715 526 3803",
    "sg:postcode":"54166",
    "sg:province":"WI",
    "sg:tags":[
        "village"
    ],
    "wof:name":"Richmond Road Supervisor",
    "wof:placetype":"venue"
},
  "geometry": {"coordinates":[-88.692517,44.835552],"type":"Point"}
}