{
  "type": "Feature",
  "properties": {
    "iso:country":"US",
    "sg:address":"4370 Townline Rd",
    "sg:city":"Colby",
    "sg:classifiers":[
        {
            "category":"Professional",
            "type":"Services"
        }
    ],
    "sg:phone":"+1 715 223 6159",
    "sg:postcode":"54421",
    "sg:province":"WI",
    "wof:name":"Wayne Sazama",
    "wof:placetype":"venue"
},
  "geometry": {"coordinates":[-90.198465,44.910423],"type":"Point"}
}