{
  "type": "Feature",
  "properties": {
    "iso:country":"US",
    "sg:address":"933 Keith Pl",
    "sg:city":"Onalaska",
    "sg:classifiers":[
        {
            "category":"Banks & Credit Unions",
            "subcategory":"Investment Brokerage",
            "type":"Services"
        }
    ],
    "sg:phone":"+1 608 783 3395",
    "sg:postcode":"54650",
    "sg:province":"WI",
    "sg:tags":[
        "advisory"
    ],
    "wof:name":"Maac Investments",
    "wof:placetype":"venue"
},
  "geometry": {"coordinates":[-91.226192,43.889027],"type":"Point"}
}