{
  "type": "Feature",
  "properties": {
    "iso:country":"US",
    "sg:address":"221 Butternut Dr",
    "sg:city":"Delavan",
    "sg:classifiers":[
        {
            "category":"Communications",
            "subcategory":"Film & Video Production",
            "type":"Services"
        }
    ],
    "sg:phone":"+1 262 745 1743",
    "sg:postcode":"53115",
    "sg:province":"WI",
    "sg:tags":[
        "motion"
    ],
    "wof:name":"Signal Fire Productions",
    "wof:placetype":"venue"
},
  "geometry": {"coordinates":[-88.66941199999999,42.630679],"type":"Point"}
}