{
  "type": "Feature",
  "properties": {
    "iso:country":"US",
    "sg:address":"2987 Gemini Rd",
    "sg:city":"Green Bay",
    "sg:classifiers":[
        {
            "category":"Shopping",
            "subcategory":"Crafts & Fabrics",
            "type":"Retail Goods"
        }
    ],
    "sg:phone":"+1 920 863 6479",
    "sg:postcode":"54311",
    "sg:province":"WI",
    "sg:tags":[
        "sewing"
    ],
    "wof:name":"Needle & Thread Entertainment",
    "wof:placetype":"venue"
},
  "geometry": {"coordinates":[-87.933449,44.450648],"type":"Point"}
}