{
  "type": "Feature",
  "properties": {
    "iso:country":"US",
    "sg:address":"13550 State Hwy 13 S",
    "sg:city":"Wisconsin Rapids",
    "sg:classifiers":[
        {
            "category":"Building & Trades",
            "subcategory":"Landscaping Services",
            "type":"Services"
        }
    ],
    "sg:phone":"+1 715 325 5430",
    "sg:postcode":"54494",
    "sg:province":"WI",
    "wof:name":"Waynes Landscaping Service",
    "wof:placetype":"venue"
},
  "geometry": {"coordinates":[-89.810485,44.271207],"type":"Point"}
}