{
  "type": "Feature",
  "properties": {
    "addr:full":"5321 McCarthy Rd Highland WI 53543",
    "addr:housenumber":"5321",
    "addr:postcode":"53543",
    "addr:street":"Mccarthy Rd",
    "iso:country":"US",
    "sg:address":"5321 McCarthy Rd",
    "sg:city":"Highland",
    "sg:classifiers":[
        {
            "category":"Building & Trades",
            "subcategory":"Construction",
            "type":"Services"
        }
    ],
    "sg:phone":"+1 608 574 2512",
    "sg:postcode":"53543",
    "sg:province":"WI",
    "sg:tags":[
        "home",
        "builder"
    ],
    "wof:name":"Ed Fredericks Custom Homes",
    "wof:placetype":"venue"
},
  "geometry": {"coordinates":[-90.334497,43.06761],"type":"Point"}
}