{
  "type": "Feature",
  "properties": {
    "addr:full":"10732 Newton Lake Rd Athelstane WI 54104",
    "addr:housenumber":"10732",
    "addr:postcode":"54104",
    "addr:street":"Newton Lake Rd",
    "iso:country":"US",
    "sg:address":"10732 Newton Lake Rd",
    "sg:city":"Athelstane",
    "sg:classifiers":[
        {
            "category":"Professional",
            "subcategory":"Computer Services",
            "type":"Services"
        }
    ],
    "sg:phone":"+1 715 757 2837",
    "sg:postcode":"54104",
    "sg:province":"WI",
    "wof:name":"Johnson Computer Svc",
    "wof:placetype":"venue"
},
  "geometry": {"coordinates":[-88.122112,45.342088],"type":"Point"}
}