{
  "type": "Feature",
  "properties": {
    "iso:country":"US",
    "sg:address":"361 1st St",
    "sg:city":"Port Edwards",
    "sg:classifiers":[
        {
            "category":"Social Services",
            "subcategory":"Adult Care",
            "type":"Services"
        }
    ],
    "sg:phone":"+1 715 887 3636",
    "sg:postcode":"54469",
    "sg:province":"WI",
    "sg:tags":[
        "residential",
        "skilled",
        "nursing",
        "facility"
    ],
    "wof:name":"Port Haven Manor Inc",
    "wof:placetype":"venue"
},
  "geometry": {"coordinates":[-89.858766,44.342773],"type":"Point"}
}