{
  "type": "Feature",
  "properties": {
    "iso:country":"US",
    "sg:address":"430 W State St",
    "sg:city":"Iola",
    "sg:classifiers":[
        {
            "category":"Education",
            "subcategory":"School",
            "type":"Public Place"
        }
    ],
    "sg:phone":"+1 715 445 2411",
    "sg:postcode":"54945",
    "sg:province":"WI",
    "wof:name":"Iola Scandinavia Sch Bus Grge",
    "wof:placetype":"venue"
},
  "geometry": {"coordinates":[-89.136094,44.507411],"type":"Point"}
}