{
  "type": "Feature",
  "properties": {
    "iso:country":"US",
    "sg:address":"885 Youth Camp Rd",
    "sg:city":"Campbellsport",
    "sg:classifiers":[
        {
            "category":"Social Services",
            "type":"Services"
        }
    ],
    "sg:phone":"+1 262 626 2149",
    "sg:postcode":"53010",
    "sg:province":"WI",
    "sg:tags":[
        "organization",
        "welfare"
    ],
    "sg:website":"www.matawa.org",
    "wof:name":"Ymca Camp Matawa",
    "wof:placetype":"venue"
},
  "geometry": {"coordinates":[-88.201166,43.580209],"type":"Point"}
}