{
  "type": "Feature",
  "properties": {
    "iso:country":"US",
    "sg:address":"540 Robinhood Way",
    "sg:city":"Sherwood",
    "sg:classifiers":[
        {
            "category":"Retail",
            "subcategory":"Laundry & Dry Cleaning",
            "type":"Services"
        }
    ],
    "sg:phone":"+1 920 989 2425",
    "sg:postcode":"54169",
    "sg:province":"WI",
    "sg:tags":[
        "cleaners",
        "rug",
        "carpet"
    ],
    "wof:name":"R & J Cleaning",
    "wof:placetype":"venue"
},
  "geometry": {"coordinates":[-88.248634,44.179522],"type":"Point"}
}