{
  "type": "Feature",
  "properties": {
    "iso:country":"US",
    "sg:address":"750 Windsor St",
    "sg:city":"Sun Prairie",
    "sg:classifiers":[
        {
            "category":"Wholesale",
            "subcategory":"Machinery & Supplies",
            "type":"Manufacturing & Wholesale Goods"
        },
        {
            "category":"Manufacturing",
            "subcategory":"Soap",
            "type":"Manufacturing & Wholesale Goods"
        }
    ],
    "sg:phone":"+1 608 837 2597",
    "sg:postcode":"53590",
    "sg:province":"WI",
    "sg:tags":[
        "detergent",
        "sanitizers",
        "mfg"
    ],
    "wof:name":"Ecolab Inc",
    "wof:placetype":"venue"
},
  "geometry": {"coordinates":[-89.224243,43.187586],"type":"Point"}
}