{
  "type": "Feature",
  "properties": {
    "iso:country":"US",
    "sg:address":"3410 W Burgandy Ct",
    "sg:city":"Thiensville",
    "sg:classifiers":[
        {
            "category":"Professional",
            "subcategory":"Business Services",
            "type":"Services"
        }
    ],
    "sg:phone":"+1 262 238 1098",
    "sg:postcode":"53092",
    "sg:province":"WI",
    "wof:name":"Town Center Partners LLC",
    "wof:placetype":"venue"
},
  "geometry": {"coordinates":[-87.953669,43.203662],"type":"Point"}
}