{
  "type": "Feature",
  "properties": {
    "iso:country":"US",
    "sg:address":"608 Prairie St",
    "sg:city":"Mount Horeb",
    "sg:classifiers":[
        {
            "category":"Building & Trades",
            "subcategory":"Construction",
            "type":"Services"
        }
    ],
    "sg:phone":"+1 608 437 3352",
    "sg:postcode":"53572",
    "sg:province":"WI",
    "sg:tags":[
        "nonresidential"
    ],
    "wof:name":"Dan Haag Construction LLC",
    "wof:placetype":"venue"
},
  "geometry": {"coordinates":[-89.733323,42.999373],"type":"Point"}
}