{
  "type": "Feature",
  "properties": {
    "iso:country":"US",
    "sg:address":"1378 Main St",
    "sg:city":"Marinette",
    "sg:classifiers":[
        {
            "category":"Restaurant",
            "type":"Food & Drink"
        }
    ],
    "sg:phone":"+1 715 735 3348",
    "sg:postcode":"54143",
    "sg:province":"WI",
    "sg:tags":[
        "eating"
    ],
    "wof:name":"Memories Restaurant",
    "wof:placetype":"venue"
},
  "geometry": {"coordinates":[-87.623502,45.096193],"type":"Point"}
}