{
  "type": "Feature",
  "properties": {
    "iso:country":"US",
    "sg:address":"2636 Toledo Rd",
    "sg:city":"Markesan",
    "sg:classifiers":[
        {
            "category":"Building & Trades",
            "subcategory":"Construction",
            "type":"Services"
        }
    ],
    "sg:phone":"+1 920 398 3090",
    "sg:postcode":"53946",
    "sg:province":"WI",
    "sg:tags":[
        "residential"
    ],
    "wof:name":"Zabel Construction",
    "wof:placetype":"venue"
},
  "geometry": {"coordinates":[-89.06096100000001,43.722522],"type":"Point"}
}