{
  "type": "Feature",
  "properties": {
    "iso:country":"US",
    "sg:address":"450 W Linwood Ave",
    "sg:city":"Oshkosh",
    "sg:classifiers":[
        {
            "category":"Professional",
            "subcategory":"Business Services",
            "type":"Services"
        }
    ],
    "sg:phone":"+1 920 426 8401",
    "sg:postcode":"54901",
    "sg:province":"WI",
    "wof:name":"Sullys Special Services",
    "wof:placetype":"venue"
},
  "geometry": {"coordinates":[-88.54468900000001,44.043066],"type":"Point"}
}