{
  "type": "Feature",
  "properties": {
    "addr:full":"492 Golden Glow Rd Kaukauna WI 54130",
    "addr:housenumber":"492",
    "addr:postcode":"54130",
    "addr:street":"Golden Glow Rd",
    "iso:country":"US",
    "sg:address":"492 Golden Glow Rd",
    "sg:city":"Kaukauna",
    "sg:classifiers":[
        {
            "category":"Food & Beverages",
            "subcategory":"Meat & Fish",
            "type":"Retail Goods"
        }
    ],
    "sg:phone":"+1 920 766 5991",
    "sg:postcode":"54130",
    "sg:province":"WI",
    "wof:name":"Golden Glow Veal",
    "wof:placetype":"venue"
},
  "geometry": {"coordinates":[-88.211354,44.371687],"type":"Point"}
}