{
  "type": "Feature",
  "properties": {
    "addr:full":"701 S Madison St Cuba City WI 53807",
    "addr:housenumber":"701",
    "addr:postcode":"53807",
    "addr:street":"S Madison St",
    "iso:country":"US",
    "sg:address":"701 S Madison St",
    "sg:city":"Cuba City",
    "sg:classifiers":[
        {
            "category":"Social Services",
            "subcategory":"Child Care",
            "type":"Services"
        }
    ],
    "sg:phone":"+1 608 744 2966",
    "sg:postcode":"53807",
    "sg:province":"WI",
    "sg:tags":[
        "kindergarten",
        "academic",
        "school",
        "day"
    ],
    "wof:name":"Mustard Seed Preschool",
    "wof:placetype":"venue"
},
  "geometry": {"coordinates":[-90.43203,42.601096],"type":"Point"}
}