{
  "type": "Feature",
  "properties": {
    "addr:full":"1151 Delanglade St Kaukauna WI 54130",
    "addr:housenumber":"1151",
    "addr:postcode":"54130",
    "addr:street":"Delanglade St",
    "iso:country":"US",
    "sg:address":"1151 Delanglade St",
    "sg:city":"Kaukauna",
    "sg:classifiers":[
        {
            "category":"Manufacturing",
            "subcategory":"Tools & Machinery",
            "type":"Manufacturing & Wholesale Goods"
        }
    ],
    "sg:phone":"+1 920 759 0314",
    "sg:postcode":"54130",
    "sg:province":"WI",
    "sg:tags":[
        "machine",
        "shop"
    ],
    "sg:website":"www.mbii.com",
    "wof:name":"Mid Valley Industries Inc",
    "wof:placetype":"venue"
},
  "geometry": {"coordinates":[-88.269187,44.29637],"type":"Point"}
}