{
  "type": "Feature",
  "properties": {
    "iso:country":"US",
    "sg:address":"212 Main St W",
    "sg:city":"Ashland",
    "sg:classifiers":[
        {
            "category":"Government",
            "subcategory":"Office",
            "type":"Public Place"
        }
    ],
    "sg:phone":"+1 715 682 5945",
    "sg:postcode":"54806",
    "sg:province":"WI",
    "sg:tags":[
        "armed",
        "force",
        "recruiting"
    ],
    "wof:name":"Us Army Recruiting Station",
    "wof:placetype":"venue"
},
  "geometry": {"coordinates":[-90.88453800000001,46.59079],"type":"Point"}
}