{
  "type": "Feature",
  "properties": {
    "iso:country":"US",
    "sg:address":"655 N Janacek Rd",
    "sg:city":"Brookfield",
    "sg:classifiers":[
        {
            "category":"Government",
            "subcategory":"Police Station",
            "type":"Public Place"
        }
    ],
    "sg:phone":"+1 262 796 3798",
    "sg:postcode":"53045",
    "sg:province":"WI",
    "sg:tags":[
        "department",
        "protection"
    ],
    "wof:name":"Brookfield Town of Police Dept",
    "wof:placetype":"venue"
},
  "geometry": {"coordinates":[-88.1567,43.036182],"type":"Point"}
}