{
  "type": "Feature",
  "properties": {
    "iso:country":"US",
    "sg:address":"2024 E Marion St",
    "sg:city":"Milwaukee",
    "sg:classifiers":[
        {
            "category":"Professional",
            "subcategory":"Detective & Security Services",
            "type":"Services"
        }
    ],
    "sg:phone":"+1 414 963 4537",
    "sg:postcode":"53211",
    "sg:province":"WI",
    "sg:tags":[
        "information",
        "bureau"
    ],
    "wof:name":"Seboe It Services",
    "wof:placetype":"venue"
},
  "geometry": {"coordinates":[-87.884641,43.094592],"type":"Point"}
}