{
  "type": "Feature",
  "properties": {
    "addr:full":"19947 Co Hwy Oo Chippewa Falls WI 54729",
    "addr:housenumber":"19947",
    "addr:postcode":"54729",
    "addr:street":"Co Hwy Oo",
    "iso:country":"US",
    "sg:address":"19947 Co Hwy Oo",
    "sg:city":"Chippewa Falls",
    "sg:classifiers":[
        {
            "category":"Farming",
            "subcategory":"Orchard",
            "type":"Manufacturing & Wholesale Goods"
        }
    ],
    "sg:phone":"+1 715 723 6125",
    "sg:postcode":"54729",
    "sg:province":"WI",
    "sg:tags":[
        "grove",
        "management"
    ],
    "wof:name":"Mc Ilquham Orchard",
    "wof:placetype":"venue"
},
  "geometry": {"coordinates":[-91.27426199999999,44.871548],"type":"Point"}
}