{
  "type": "Feature",
  "properties": {
    "iso:country":"US",
    "sg:address":"6525 26th Ave",
    "sg:city":"Kenosha",
    "sg:classifiers":[
        {
            "category":"Food & Beverages",
            "subcategory":"Groceries & Convenience Stores",
            "type":"Retail Goods"
        }
    ],
    "sg:phone":"+1 262 652 8533",
    "sg:postcode":"53143",
    "sg:province":"WI",
    "sg:tags":[
        "grocer"
    ],
    "wof:name":"One Stop Grocery",
    "wof:placetype":"venue"
},
  "geometry": {"coordinates":[-87.84032000000001,42.574272],"type":"Point"}
}