{
  "type": "Feature",
  "properties": {
    "iso:country":"US",
    "sg:address":"7598 Nietzke Rd",
    "sg:city":"Clintonville",
    "sg:classifiers":[
        {
            "category":"Professional",
            "subcategory":"Business Services",
            "type":"Services"
        }
    ],
    "sg:phone":"+1 715 823 3303",
    "sg:postcode":"54929",
    "sg:province":"WI",
    "wof:name":"Gjc Inc",
    "wof:placetype":"venue"
},
  "geometry": {"coordinates":[-88.843572,44.634243],"type":"Point"}
}