{
  "type": "Feature",
  "properties": {
    "iso:country":"US",
    "sg:address":"7377 Krueger Rd",
    "sg:city":"Lake Geneva",
    "sg:classifiers":[
        {
            "category":"Sports & Exercise",
            "subcategory":"Golf",
            "type":"Entertainment"
        }
    ],
    "sg:phone":"+1 262 348 9900",
    "sg:postcode":"53147",
    "sg:province":"WI",
    "sg:tags":[
        "course",
        "public"
    ],
    "sg:website":"www.hawksviewgolfclub.com",
    "wof:name":"Hawks View Golf Club LLC",
    "wof:placetype":"venue"
},
  "geometry": {"coordinates":[-88.447626,42.616674],"type":"Point"}
}