{
  "type": "Feature",
  "properties": {
    "iso:country":"US",
    "sg:address":"3810 60th Pl",
    "sg:city":"Kenosha",
    "sg:classifiers":[
        {
            "category":"Manufacturing",
            "subcategory":"Chemicals & Compounds",
            "type":"Manufacturing & Wholesale Goods"
        }
    ],
    "sg:phone":"+1 262 657 5086",
    "sg:postcode":"53142",
    "sg:province":"WI",
    "sg:tags":[
        "manufacturer"
    ],
    "wof:name":"Power-Fill Inc",
    "wof:placetype":"venue"
},
  "geometry": {"coordinates":[-87.855278,42.580204],"type":"Point"}
}