{
  "type": "Feature",
  "properties": {
    "addr:full":"3103 N 20th St Milwaukee WI 53206",
    "addr:housenumber":"3103",
    "addr:postcode":"53206",
    "addr:street":"N 20Th St",
    "iso:country":"US",
    "sg:address":"3103 N 20th St",
    "sg:city":"Milwaukee",
    "sg:classifiers":[
        {
            "category":"Home & Garden",
            "subcategory":"Building Materials",
            "type":"Retail Goods"
        }
    ],
    "sg:phone":"+1 414 444 5630",
    "sg:postcode":"53206",
    "sg:province":"WI",
    "wof:name":"McCoys Home Improvement",
    "wof:placetype":"venue"
},
  "geometry": {"coordinates":[-87.93742899999999,43.075729],"type":"Point"}
}