{
  "type": "Feature",
  "properties": {
    "addr:full":"308 Edward St Fort Atkinson WI 53538",
    "addr:housenumber":"308",
    "addr:postcode":"53538",
    "addr:street":"Edward St",
    "iso:country":"US",
    "sg:address":"308 Edward St",
    "sg:city":"Fort Atkinson",
    "sg:classifiers":[
        {
            "category":"Building & Trades",
            "subcategory":"Construction",
            "type":"Services"
        }
    ],
    "sg:phone":"+1 920 563 3873",
    "sg:postcode":"53538",
    "sg:province":"WI",
    "sg:tags":[
        "downspouts",
        "gutter"
    ],
    "wof:name":"Southgate Gutter Svc",
    "wof:placetype":"venue"
},
  "geometry": {"coordinates":[-88.83581100000001,42.932468],"type":"Point"}
}