{
  "type": "Feature",
  "properties": {
    "iso:country":"US",
    "sg:address":"2170 S Sanctuary Dr",
    "sg:city":"New Berlin",
    "sg:classifiers":[
        {
            "category":"Professional",
            "type":"Services"
        }
    ],
    "sg:phone":"+1 262 797 8006",
    "sg:postcode":"53151",
    "sg:province":"WI",
    "sg:tags":[
        "establishment"
    ],
    "wof:name":"Arabesque",
    "wof:placetype":"venue"
},
  "geometry": {"coordinates":[-88.104987,43.004565],"type":"Point"}
}