{
  "type": "Feature",
  "properties": {
    "addr:full":"9531 Grimms Rd Reedsville WI 54230",
    "addr:postcode":"9531;54230",
    "addr:street":"Grimms Rd",
    "iso:country":"US",
    "sg:address":"9531 Grimms Rd",
    "sg:city":"Reedsville",
    "sg:classifiers":[
        {
            "category":"Farming",
            "subcategory":"Dairy Farm",
            "type":"Manufacturing & Wholesale Goods"
        }
    ],
    "sg:phone":"+1 920 754 4795",
    "sg:postcode":"54230",
    "sg:province":"WI",
    "wof:name":"Dennis Baroun",
    "wof:placetype":"venue"
},
  "geometry": {"coordinates":[-87.902181,44.208831],"type":"Point"}
}