{
  "type": "Feature",
  "properties": {
    "iso:country":"US",
    "sg:address":"314 Jay St",
    "sg:city":"La Crosse",
    "sg:classifiers":[
        {
            "category":"Shopping",
            "subcategory":"Music",
            "type":"Retail Goods"
        },
        {
            "category":"Shopping",
            "subcategory":"Books",
            "type":"Retail Goods"
        }
    ],
    "sg:phone":"+1 608 784 6350",
    "sg:postcode":"54601",
    "sg:province":"WI",
    "sg:tags":[
        "video",
        "disc",
        "tape",
        "cassette"
    ],
    "wof:name":"Best Buy Books Inc",
    "wof:placetype":"venue"
},
  "geometry": {"coordinates":[-91.25191700000001,43.810933],"type":"Point"}
}