{
  "type": "Feature",
  "properties": {
    "addr:full":"3603 S Business Dr Sheboygan WI 53081",
    "addr:housenumber":"3603",
    "addr:postcode":"53081",
    "addr:street":"S Business Dr",
    "iso:country":"US",
    "sg:address":"3603 S Business Dr",
    "sg:city":"Sheboygan",
    "sg:classifiers":[
        {
            "category":"Education",
            "subcategory":"School",
            "type":"Public Place"
        }
    ],
    "sg:phone":"+1 920 458 6640",
    "sg:postcode":"53081",
    "sg:province":"WI",
    "sg:tags":[
        "academic",
        "special"
    ],
    "wof:name":"Willowglen Academy",
    "wof:placetype":"venue"
},
  "geometry": {"coordinates":[-87.738556,43.717188],"type":"Point"}
}