{
  "type": "Feature",
  "properties": {
    "iso:country":"US",
    "sg:address":"702 Highland Ave",
    "sg:city":"Kewaskum",
    "sg:classifiers":[
        {
            "category":"Real Estate",
            "subcategory":"Real Estate Agent",
            "type":"Services"
        }
    ],
    "sg:phone":"+1 262 626 4526",
    "sg:postcode":"53040",
    "sg:province":"WI",
    "wof:name":"Kudie",
    "wof:placetype":"venue"
},
  "geometry": {"coordinates":[-88.21783600000001,43.519973],"type":"Point"}
}