{
  "type": "Feature",
  "properties": {
    "iso:country":"US",
    "sg:address":"777 E Wisconsin Ave",
    "sg:city":"Milwaukee",
    "sg:classifiers":[
        {
            "category":"Professional",
            "subcategory":"Engineering",
            "type":"Services"
        }
    ],
    "sg:phone":"+1 414 905 7351",
    "sg:postcode":"53202",
    "sg:province":"WI",
    "wof:name":"US Bank Center Company",
    "wof:placetype":"venue"
},
  "geometry": {"coordinates":[-87.902289,43.038906],"type":"Point"}
}