{
  "type": "Feature",
  "properties": {
    "iso:country":"US",
    "sg:address":"600 E Mason St",
    "sg:city":"Milwaukee",
    "sg:classifiers":[
        {
            "category":"Insurance",
            "subcategory":"Insurance Agent",
            "type":"Services"
        }
    ],
    "sg:phone":"+1 414 271 3177",
    "sg:postcode":"53202",
    "sg:province":"WI",
    "sg:tags":[
        "agency"
    ],
    "wof:name":"International Marine Group Inc",
    "wof:placetype":"venue"
},
  "geometry": {"coordinates":[-87.902896,43.040202],"type":"Point"}
}