{
  "type": "Feature",
  "properties": {
    "iso:country":"US",
    "sg:address":"202 W Center St",
    "sg:city":"South Wayne",
    "sg:classifiers":[
        {
            "category":"Education",
            "subcategory":"School",
            "type":"Public Place"
        }
    ],
    "sg:phone":"+1 608 439 5400",
    "sg:postcode":"53587",
    "sg:province":"WI",
    "wof:name":"Black Hawk School District",
    "wof:placetype":"venue"
},
  "geometry": {"coordinates":[-89.881146,42.569007],"type":"Point"}
}