{
  "type": "Feature",
  "properties": {
    "addr:full":"1860 Co Rd Uu Kaukauna WI 54130",
    "addr:housenumber":"1860",
    "addr:postcode":"54130",
    "addr:street":"Co Rd",
    "iso:country":"US",
    "sg:address":"1860 Co Rd Uu",
    "sg:city":"Kaukauna",
    "sg:classifiers":[
        {
            "category":"Building & Trades",
            "subcategory":"Plumbing",
            "type":"Services"
        }
    ],
    "sg:phone":"+1 920 788 0780",
    "sg:postcode":"54130",
    "sg:province":"WI",
    "sg:tags":[
        "plumbing",
        "soil",
        "testing",
        "tank",
        "septic"
    ],
    "wof:name":"Dion Lecker Plumbing",
    "wof:placetype":"venue"
},
  "geometry": {"coordinates":[-88.27972699999999,44.357509],"type":"Point"}
}