{
  "type": "Feature",
  "properties": {
    "iso:country":"US",
    "sg:address":"791 Summit Ave",
    "sg:city":"Oconomowoc",
    "sg:classifiers":[
        {
            "category":"Health Services",
            "subcategory":"Hospital",
            "type":"Services"
        }
    ],
    "sg:phone":"+1 262 569 0640",
    "sg:postcode":"53066",
    "sg:province":"WI",
    "sg:tags":[
        "specialty"
    ],
    "wof:name":"Zoeller Robert L Jr MD",
    "wof:placetype":"venue"
},
  "geometry": {"coordinates":[-88.486779,43.101968],"type":"Point"}
}