{
  "type": "Feature",
  "properties": {
    "addr:full":"11456 360th St Stanley WI 54768",
    "addr:housenumber":"11456",
    "addr:postcode":"54768",
    "addr:street":"360Th St",
    "iso:country":"US",
    "sg:address":"11456 360th St",
    "sg:city":"Stanley",
    "sg:classifiers":[
        {
            "category":"Farming",
            "subcategory":"Dairy Farm",
            "type":"Manufacturing & Wholesale Goods"
        }
    ],
    "sg:phone":"+1 715 644 0466",
    "sg:postcode":"54768",
    "sg:province":"WI",
    "wof:name":"Tibek Dairy",
    "wof:placetype":"venue"
},
  "geometry": {"coordinates":[-90.94381799999999,45.010851],"type":"Point"}
}