{
  "type": "Feature",
  "properties": {
    "iso:country":"US",
    "sg:address":"659 Summer Creek Rd",
    "sg:city":"Oconomowoc",
    "sg:classifiers":[
        {
            "category":"Insurance",
            "subcategory":"Insurance Agent",
            "type":"Services"
        }
    ],
    "sg:phone":"+1 262 567 8295",
    "sg:postcode":"53066",
    "sg:province":"WI",
    "wof:name":"Midwest Insurance Group",
    "wof:placetype":"venue"
},
  "geometry": {"coordinates":[-88.50916700000001,43.100439],"type":"Point"}
}