{
  "type": "Feature",
  "properties": {
    "iso:country":"US",
    "sg:address":"2500 W Beltline Hwy",
    "sg:city":"Middleton",
    "sg:classifiers":[
        {
            "category":"Professional",
            "subcategory":"Management & Consulting",
            "type":"Services"
        }
    ],
    "sg:phone":"+1 608 831 1188",
    "sg:postcode":"53562",
    "sg:province":"WI",
    "sg:tags":[
        "marketing",
        "program"
    ],
    "wof:name":"Radiation Measurements Inc",
    "wof:placetype":"venue"
},
  "geometry": {"coordinates":[-89.51958,43.092622],"type":"Point"}
}