{
  "type": "Feature",
  "properties": {
    "addr:full":"321 Main St La Crosse WI 54601",
    "addr:housenumber":"321",
    "addr:postcode":"54601",
    "addr:street":"Main St",
    "iso:country":"US",
    "sg:address":"321 Main St",
    "sg:city":"La Crosse",
    "sg:classifiers":[
        {
            "category":"Shopping",
            "subcategory":"Bicycles & Sporting Goods",
            "type":"Retail Goods"
        }
    ],
    "sg:phone":"+1 608 782 5500",
    "sg:postcode":"54601",
    "sg:province":"WI",
    "wof:name":"Valley Ski and Bike",
    "wof:placetype":"venue"
},
  "geometry": {"coordinates":[-91.251227,43.812394],"type":"Point"}
}