{
  "type": "Feature",
  "properties": {
    "iso:country":"US",
    "sg:address":"3100 Minnesota Ave",
    "sg:city":"Stevens Point",
    "sg:classifiers":[
        {
            "category":"Manufacturing",
            "subcategory":"Apparel",
            "type":"Manufacturing & Wholesale Goods"
        }
    ],
    "sg:phone":"+1 715 345 7077",
    "sg:postcode":"54481",
    "sg:province":"WI",
    "sg:tags":[
        "printing",
        "commercial",
        "mfg"
    ],
    "wof:name":"Sport Co",
    "wof:placetype":"venue"
},
  "geometry": {"coordinates":[-89.559304,44.505762],"type":"Point"}
}