{
  "type": "Feature",
  "properties": {
    "addr:full":"2087 State Hwy 16 Bangor WI 54614",
    "addr:housenumber":"2087",
    "addr:postcode":"54614",
    "addr:street":"State Hwy 16",
    "iso:country":"US",
    "sg:address":"2087 State Hwy 16",
    "sg:city":"Bangor",
    "sg:classifiers":[
        {
            "category":"Building & Trades",
            "subcategory":"Landscaping Services",
            "type":"Services"
        }
    ],
    "sg:phone":"+1 608 486 2055",
    "sg:postcode":"54614",
    "sg:province":"WI",
    "wof:name":"Koskovich Ed Tree Stump Rmoval",
    "wof:placetype":"venue"
},
  "geometry": {"coordinates":[-91.012269,43.913581],"type":"Point"}
}