{
  "type": "Feature",
  "properties": {
    "iso:country":"US",
    "sg:address":"1944 Quam Point Rd",
    "sg:city":"Stoughton",
    "sg:classifiers":[
        {
            "category":"Building & Trades",
            "subcategory":"Construction",
            "type":"Services"
        }
    ],
    "sg:phone":"+1 608 873 7384",
    "sg:postcode":"53589",
    "sg:province":"WI",
    "sg:tags":[
        "house"
    ],
    "wof:name":"McGuire Engineering & Construc",
    "wof:placetype":"venue"
},
  "geometry": {"coordinates":[-89.264013,42.952412],"type":"Point"}
}