{
  "type": "Feature",
  "properties": {
    "iso:country":"US",
    "sg:address":"109 Miner Ave W",
    "sg:city":"Ladysmith",
    "sg:classifiers":[
        {
            "category":"Professional",
            "subcategory":"Lawyer & Legal Services",
            "type":"Services"
        }
    ],
    "sg:phone":"+1 715 532 3359",
    "sg:postcode":"54848",
    "sg:province":"WI",
    "sg:tags":[
        "attorney"
    ],
    "wof:name":"Allen F Kenyon",
    "wof:placetype":"venue"
},
  "geometry": {"coordinates":[-91.100903,45.464305],"type":"Point"}
}