{
  "type": "Feature",
  "properties": {
    "addr:full":"6915 King Rd Poynette WI 53955",
    "addr:housenumber":"6915",
    "addr:postcode":"53955",
    "addr:street":"King Rd",
    "iso:country":"US",
    "sg:address":"6915 King Rd",
    "sg:city":"Poynette",
    "sg:classifiers":[
        {
            "category":"Retail",
            "subcategory":"Portrait Studio",
            "type":"Services"
        }
    ],
    "sg:phone":"+1 608 635 4908",
    "sg:postcode":"53955",
    "sg:province":"WI",
    "sg:tags":[
        "photo"
    ],
    "wof:name":"Eyrie Studio",
    "wof:placetype":"venue"
},
  "geometry": {"coordinates":[-89.35684000000001,43.39021],"type":"Point"}
}