{
  "type": "Feature",
  "properties": {
    "iso:country":"US",
    "sg:address":"611 W National Ave",
    "sg:city":"Milwaukee",
    "sg:classifiers":[
        {
            "category":"Professional",
            "subcategory":"Printing & Photocopies",
            "type":"Services"
        }
    ],
    "sg:phone":"+1 414 671 8791",
    "sg:postcode":"53204",
    "sg:province":"WI",
    "sg:tags":[
        "photocopying"
    ],
    "wof:name":"True Image Printing",
    "wof:placetype":"venue"
},
  "geometry": {"coordinates":[-87.919569,43.023162],"type":"Point"}
}