{
  "type": "Feature",
  "properties": {
    "iso:country":"US",
    "sg:address":"4002 Mountain Ln",
    "sg:city":"Wausau",
    "sg:classifiers":[
        {
            "category":"Professional",
            "subcategory":"Business Services",
            "type":"Services"
        }
    ],
    "sg:phone":"+1 715 845 7679",
    "sg:postcode":"54401",
    "sg:province":"WI",
    "wof:name":"Mountain Lane Enterprises LLC",
    "wof:placetype":"venue"
},
  "geometry": {"coordinates":[-89.686717,44.929595],"type":"Point"}
}