{
  "type": "Feature",
  "properties": {
    "addr:full":"1639 Ludgate St Chippewa Falls WI 54729",
    "addr:housenumber":"1639",
    "addr:postcode":"54729",
    "addr:street":"Ludgate St",
    "iso:country":"US",
    "sg:address":"1639 Ludgate St",
    "sg:city":"Chippewa Falls",
    "sg:classifiers":[
        {
            "category":"Home & Garden",
            "subcategory":"Carpets & Floor Coverings",
            "type":"Retail Goods"
        }
    ],
    "sg:phone":"+1 715 723 8168",
    "sg:postcode":"54729",
    "sg:province":"WI",
    "wof:name":"Zelms Carpet Service",
    "wof:placetype":"venue"
},
  "geometry": {"coordinates":[-91.41992,44.9265],"type":"Point"}
}