{
  "type": "Feature",
  "properties": {
    "addr:full":"915 Woodland Dr Rhinelander WI 54501",
    "addr:housenumber":"915",
    "addr:postcode":"54501",
    "addr:street":"Woodland Dr",
    "iso:country":"US",
    "sg:address":"915 Woodland Dr",
    "sg:city":"Rhinelander",
    "sg:classifiers":[
        {
            "category":"Building & Trades",
            "subcategory":"Construction",
            "type":"Services"
        }
    ],
    "sg:phone":"+1 715 365 1920",
    "sg:postcode":"54501",
    "sg:province":"WI",
    "sg:tags":[
        "excavation",
        "concrete",
        "product",
        "c",
        "mfg"
    ],
    "wof:name":"Dolson Inc",
    "wof:placetype":"venue"
},
  "geometry": {"coordinates":[-89.39175299999999,45.649226],"type":"Point"}
}