{
  "type": "Feature",
  "properties": {
    "iso:country":"US",
    "sg:address":"106 E 2nd St",
    "sg:city":"Kaukauna",
    "sg:classifiers":[
        {
            "category":"Retail",
            "subcategory":"Photofinishing",
            "type":"Services"
        }
    ],
    "sg:phone":"+1 920 766 6160",
    "sg:postcode":"54130",
    "sg:province":"WI",
    "sg:tags":[
        "photo",
        "finishing"
    ],
    "sg:website":"www.pechmanimaging.com",
    "wof:name":"Pechman Professional Imaging",
    "wof:placetype":"venue"
},
  "geometry": {"coordinates":[-88.27096,44.277275],"type":"Point"}
}