{
  "type": "Feature",
  "properties": {
    "iso:country":"US",
    "sg:address":"510 N 33rd St",
    "sg:city":"Milwaukee",
    "sg:classifiers":[
        {
            "category":"Organizations",
            "subcategory":"Religious Organization",
            "type":"Services"
        }
    ],
    "sg:phone":"+1 414 342 4395",
    "sg:postcode":"53208",
    "sg:province":"WI",
    "sg:tags":[
        "clergy"
    ],
    "wof:name":"Robert L Williams",
    "wof:placetype":"venue"
},
  "geometry": {"coordinates":[-87.955163,43.037387],"type":"Point"}
}