{
  "type": "Feature",
  "properties": {
    "iso:country":"US",
    "sg:address":"1314 Green Bay Rd",
    "sg:city":"Sturgeon Bay",
    "sg:classifiers":[
        {
            "category":"Food & Beverages",
            "subcategory":"Groceries & Convenience Stores",
            "type":"Retail Goods"
        }
    ],
    "sg:phone":"+1 920 743 6383",
    "sg:postcode":"54235",
    "sg:province":"WI",
    "wof:name":"Q Mart",
    "wof:placetype":"venue"
},
  "geometry": {"coordinates":[-87.404983,44.820977],"type":"Point"}
}