{
  "type": "Feature",
  "properties": {
    "iso:country":"US",
    "sg:address":"2468 N 35th St",
    "sg:city":"Milwaukee",
    "sg:classifiers":[
        {
            "category":"Shopping",
            "subcategory":"Clothing, Apparel, & Fashions",
            "type":"Retail Goods"
        }
    ],
    "sg:phone":"+1 414 874 7882",
    "sg:postcode":"53210",
    "sg:province":"WI",
    "wof:name":"Snazzy Ladies",
    "wof:placetype":"venue"
},
  "geometry": {"coordinates":[-87.95740600000001,43.063004],"type":"Point"}
}