{
  "type": "Feature",
  "properties": {
    "iso:country":"US",
    "sg:address":"151 N Park Ave",
    "sg:city":"Fond Du Lac",
    "sg:classifiers":[
        {
            "category":"Social Services",
            "type":"Services"
        }
    ],
    "sg:phone":"+1 920 924 9013",
    "sg:postcode":"54935",
    "sg:province":"WI",
    "sg:tags":[
        "group",
        "for",
        "developmentally",
        "disabled",
        "adult",
        "home"
    ],
    "wof:name":"Park Haven",
    "wof:placetype":"venue"
},
  "geometry": {"coordinates":[-88.439081,43.782432],"type":"Point"}
}