{
  "type": "Feature",
  "properties": {
    "iso:country":"US",
    "sg:address":"415 Division St",
    "sg:city":"Wausau",
    "sg:classifiers":[
        {
            "category":"Personal",
            "type":"Services"
        }
    ],
    "sg:phone":"+1 715 843 9394",
    "sg:postcode":"54403",
    "sg:province":"WI",
    "sg:tags":[
        "therapist",
        "massage"
    ],
    "wof:name":"Massage Therapy Associates",
    "wof:placetype":"venue"
},
  "geometry": {"coordinates":[-89.627147,44.956419],"type":"Point"}
}