{
  "type": "Feature",
  "properties": {
    "iso:country":"US",
    "sg:address":"5111 Douglas Ave",
    "sg:city":"Racine",
    "sg:classifiers":[
        {
            "category":"Food & Beverages",
            "subcategory":"Groceries & Convenience Stores",
            "type":"Retail Goods"
        }
    ],
    "sg:phone":"+1 262 639 2423",
    "sg:postcode":"53402",
    "sg:province":"WI",
    "sg:tags":[
        "grocer"
    ],
    "wof:name":"Kohl's Food Store",
    "wof:placetype":"venue"
},
  "geometry": {"coordinates":[-87.810497,42.787683],"type":"Point"}
}