{
  "type": "Feature",
  "properties": {
    "iso:country":"US",
    "sg:address":"1516 Athletic Ave",
    "sg:city":"Beloit",
    "sg:classifiers":[
        {
            "category":"Organizations",
            "subcategory":"Religious Organization",
            "type":"Services"
        }
    ],
    "sg:phone":"+1 608 362 1471",
    "sg:postcode":"53511",
    "sg:province":"WI",
    "sg:tags":[
        "clergy"
    ],
    "wof:name":"Charles F Hereford",
    "wof:placetype":"venue"
},
  "geometry": {"coordinates":[-89.017062,42.500111],"type":"Point"}
}