{
  "type": "Feature",
  "properties": {
    "iso:country":"US",
    "sg:address":"201 Delafield St",
    "sg:city":"Waukesha",
    "sg:classifiers":[
        {
            "category":"Government",
            "subcategory":"Office",
            "type":"Public Place"
        }
    ],
    "sg:phone":"+1 262 524 3700",
    "sg:postcode":"53188",
    "sg:province":"WI",
    "sg:tags":[
        "city"
    ],
    "wof:name":"Waukesha City Mayor",
    "wof:placetype":"venue"
},
  "geometry": {"coordinates":[-88.235443,43.014246],"type":"Point"}
}