{
  "type": "Feature",
  "properties": {
    "addr:full":"4330 Quade Ln Crandon WI 54520",
    "addr:housenumber":"4330",
    "addr:postcode":"54520",
    "addr:street":"Quade Ln",
    "iso:country":"US",
    "sg:address":"4330 Quade Ln",
    "sg:city":"Crandon",
    "sg:classifiers":[
        {
            "category":"Building & Trades",
            "subcategory":"Construction",
            "type":"Services"
        }
    ],
    "sg:phone":"+1 715 478 3237",
    "sg:postcode":"54520",
    "sg:province":"WI",
    "sg:tags":[
        "house",
        "carpentry",
        "m",
        "contractor"
    ],
    "wof:name":"Carter Construction Inc",
    "wof:placetype":"venue"
},
  "geometry": {"coordinates":[-88.861289,45.531787],"type":"Point"}
}