{
  "type": "Feature",
  "properties": {
    "iso:country":"US",
    "sg:address":"622 N Water St",
    "sg:city":"Milwaukee",
    "sg:classifiers":[
        {
            "category":"Professional",
            "subcategory":"Lawyer & Legal Services",
            "type":"Services"
        }
    ],
    "sg:phone":"+1 414 270 1930",
    "sg:postcode":"53202",
    "sg:province":"WI",
    "sg:tags":[
        "attorney",
        "law",
        "collection"
    ],
    "wof:name":"Schelble Law Firm SC",
    "wof:placetype":"venue"
},
  "geometry": {"coordinates":[-87.90898,43.03767],"type":"Point"}
}