{
  "type": "Feature",
  "properties": {
    "iso:country":"US",
    "sg:address":"4550 Horsehead Lake Rd",
    "sg:city":"Harshaw",
    "sg:classifiers":[
        {
            "category":"Building & Trades",
            "subcategory":"Construction",
            "type":"Services"
        }
    ],
    "sg:phone":"+1 715 282 7271",
    "sg:postcode":"54529",
    "sg:province":"WI",
    "sg:tags":[
        "house"
    ],
    "wof:name":"Jordan Builders",
    "wof:placetype":"venue"
},
  "geometry": {"coordinates":[-89.609698,45.686515],"type":"Point"}
}