{
  "type": "Feature",
  "properties": {
    "iso:country":"US",
    "sg:address":"3354 9th Ave",
    "sg:city":"Hancock",
    "sg:classifiers":[
        {
            "category":"Building & Trades",
            "subcategory":"Construction",
            "type":"Services"
        }
    ],
    "sg:phone":"+1 715 249 3280",
    "sg:postcode":"54943",
    "sg:province":"WI",
    "sg:tags":[
        "material",
        "contractor"
    ],
    "wof:name":"Klabunde Ceramic Tile",
    "wof:placetype":"venue"
},
  "geometry": {"coordinates":[-89.445626,44.106434],"type":"Point"}
}