{
  "type": "Feature",
  "properties": {
    "iso:country":"US",
    "sg:address":"2980 Cahill Main",
    "sg:city":"Madison",
    "sg:classifiers":[
        {
            "category":"Manufacturing",
            "subcategory":"Food",
            "type":"Manufacturing & Wholesale Goods"
        },
        {
            "category":"Restaurant",
            "type":"Food & Drink"
        }
    ],
    "sg:menulink":"http://www.allmenus.com/wi/fitchburg/136796-smoothie-king/menu/",
    "sg:phone":"+1 608 278 1776",
    "sg:postcode":"53711",
    "sg:province":"WI",
    "sg:tags":[
        "smoothy",
        "juice",
        "american"
    ],
    "wof:name":"Smoothie King",
    "wof:placetype":"venue"
},
  "geometry": {"coordinates":[-89.423186,43.017732],"type":"Point"}
}