{
  "type": "Feature",
  "properties": {
    "iso:country":"US",
    "sg:address":"4102 W Co Rd A",
    "sg:city":"Plymouth",
    "sg:classifiers":[
        {
            "category":"Real Estate",
            "subcategory":"Developer",
            "type":"Services"
        }
    ],
    "sg:phone":"+1 920 528 8150",
    "sg:postcode":"53073",
    "sg:province":"WI",
    "wof:name":"Berry Fields",
    "wof:placetype":"venue"
},
  "geometry": {"coordinates":[-88.085247,43.695839],"type":"Point"}
}