{
  "type": "Feature",
  "properties": {
    "iso:country":"US",
    "sg:address":"525 W 20th Ave",
    "sg:city":"Oshkosh",
    "sg:classifiers":[
        {
            "category":"Airport",
            "type":"Transportation"
        }
    ],
    "sg:phone":"+1 920 424 0092",
    "sg:postcode":"54902",
    "sg:province":"WI",
    "sg:tags":[
        "executive"
    ],
    "sg:website":"www.wittmanairport.com",
    "wof:name":"Wittman Regional Airport",
    "wof:placetype":"venue"
},
  "geometry": {"coordinates":[-88.550499,43.995761],"type":"Point"}
}