{
  "type": "Feature",
  "properties": {
    "iso:country":"US",
    "sg:address":"208 Industrial Dr",
    "sg:city":"Verona",
    "sg:classifiers":[
        {
            "category":"Wholesale",
            "subcategory":"Durable Goods & Equipment",
            "type":"Manufacturing & Wholesale Goods"
        }
    ],
    "sg:phone":"+1 608 845 9551",
    "sg:postcode":"53593",
    "sg:province":"WI",
    "sg:tags":[
        "representative",
        "manufacturer"
    ],
    "wof:name":"Hunzicker-Riley Inc",
    "wof:placetype":"venue"
},
  "geometry": {"coordinates":[-89.538503,42.985838],"type":"Point"}
}