{
  "type": "Feature",
  "properties": {
    "iso:country":"US",
    "sg:address":"3155 Commodity Ln",
    "sg:city":"Green Bay",
    "sg:classifiers":[
        {
            "category":"Manufacturing",
            "subcategory":"Rubber & Plastics",
            "type":"Manufacturing & Wholesale Goods"
        }
    ],
    "sg:phone":"+1 920 337 2202",
    "sg:postcode":"54304",
    "sg:province":"WI",
    "wof:name":"Modern Plastics",
    "wof:placetype":"venue"
},
  "geometry": {"coordinates":[-88.103884,44.469316],"type":"Point"}
}