{
  "type": "Feature",
  "properties": {
    "addr:full":"7376 Co Rd Jj Plover WI 54467",
    "addr:housenumber":"7376",
    "addr:postcode":"54467",
    "addr:street":"Co Rd",
    "iso:country":"US",
    "sg:address":"7376 Co Rd Jj",
    "sg:city":"Plover",
    "sg:classifiers":[
        {
            "category":"Building & Trades",
            "subcategory":"Electrical",
            "type":"Services"
        }
    ],
    "sg:phone":"+1 715 342 4775",
    "sg:postcode":"54467",
    "sg:province":"WI",
    "sg:tags":[
        "electric",
        "contractor"
    ],
    "wof:name":"Volt Electric",
    "wof:placetype":"venue"
},
  "geometry": {"coordinates":[-89.420591,44.400328],"type":"Point"}
}