{
  "type": "Feature",
  "properties": {
    "iso:country":"US",
    "sg:address":"6438 W Mill Rd",
    "sg:city":"Milwaukee",
    "sg:classifiers":[
        {
            "category":"Home & Garden",
            "subcategory":"Building Materials",
            "type":"Retail Goods"
        },
        {
            "category":"Building & Trades",
            "subcategory":"Construction",
            "type":"Services"
        }
    ],
    "sg:phone":"+1 414 353 6910",
    "sg:postcode":"53218",
    "sg:province":"WI",
    "sg:tags":[
        "roofing",
        "gutter",
        "siding",
        "contractor",
        "downspouts",
        "window"
    ],
    "sg:website":"http://www.allriteremodeling.com",
    "wof:name":"Allrite Home & Remodeling",
    "wof:placetype":"venue"
},
  "geometry": {"coordinates":[-87.991331,43.134056],"type":"Point"}
}