{
  "type": "Feature",
  "properties": {
    "iso:country":"US",
    "sg:address":"12098 Sunset Dr",
    "sg:city":"La Farge",
    "sg:classifiers":[
        {
            "category":"Farming",
            "subcategory":"Dairy Farm",
            "type":"Manufacturing & Wholesale Goods"
        }
    ],
    "sg:phone":"+1 608 625 4103",
    "sg:postcode":"54639",
    "sg:province":"WI",
    "wof:name":"Eugene Oium",
    "wof:placetype":"venue"
},
  "geometry": {"coordinates":[-90.65248099999999,43.670812],"type":"Point"}
}