{
  "type": "Feature",
  "properties": {
    "iso:country":"US",
    "sg:address":"4251 S 27th St",
    "sg:city":"Milwaukee",
    "sg:classifiers":[
        {
            "category":"Shopping",
            "type":"Retail Goods"
        }
    ],
    "sg:phone":"+1 414 282 6800",
    "sg:postcode":"53221",
    "sg:province":"WI",
    "sg:tags":[
        "equipment",
        "swimming",
        "pool",
        "related",
        "spa"
    ],
    "wof:name":"Allied Pools & Spas",
    "wof:placetype":"venue"
},
  "geometry": {"coordinates":[-87.94864200000001,42.968321],"type":"Point"}
}