{
  "type": "Feature",
  "properties": {
    "iso:country":"US",
    "sg:address":"6797 Kampen Rd",
    "sg:city":"Arlington",
    "sg:classifiers":[
        {
            "category":"Professional",
            "subcategory":"Research",
            "type":"Services"
        }
    ],
    "sg:phone":"+1 608 635 2026",
    "sg:postcode":"53911",
    "sg:province":"WI",
    "sg:tags":[
        "horticulture"
    ],
    "wof:name":"Horticulture Research",
    "wof:placetype":"venue"
},
  "geometry": {"coordinates":[-89.331613,43.324827],"type":"Point"}
}