{
  "type": "Feature",
  "properties": {
    "addr:full":"1004 Rawson Ave South Milwaukee WI 53172",
    "addr:postcode":"1004;53172",
    "addr:street":"Rawson Ave",
    "iso:country":"US",
    "sg:address":"1004 Rawson Ave",
    "sg:city":"South Milwaukee",
    "sg:classifiers":[
        {
            "category":"Organizations",
            "subcategory":"Religious Organization",
            "type":"Services"
        }
    ],
    "sg:phone":"+1 414 764 7783",
    "sg:postcode":"53172",
    "sg:province":"WI",
    "sg:tags":[
        "monastery",
        "convent"
    ],
    "wof:name":"School Sisters Of Notre Dame",
    "wof:placetype":"venue"
},
  "geometry": {"coordinates":[-87.861109,42.915243],"type":"Point"}
}