{
  "type": "Feature",
  "properties": {
    "iso:country":"US",
    "sg:address":"289 N Main St",
    "sg:city":"Fond Du Lac",
    "sg:classifiers":[
        {
            "category":"Education",
            "subcategory":"Special Training",
            "type":"Public Place"
        },
        {
            "category":"Shopping",
            "subcategory":"Musical Instruments",
            "type":"Retail Goods"
        }
    ],
    "sg:phone":"+1 920 923 1925",
    "sg:postcode":"54935",
    "sg:province":"WI",
    "sg:tags":[
        "instruction",
        "music"
    ],
    "sg:website":"www.mikesmusic.net",
    "wof:name":"Mike's Music & Sound Inc",
    "wof:placetype":"venue"
},
  "geometry": {"coordinates":[-88.447026,43.786943],"type":"Point"}
}