{
  "type": "Feature",
  "properties": {
    "iso:country":"US",
    "sg:address":"10419 E Maple Dr Exd",
    "sg:city":"Poplar",
    "sg:classifiers":[
        {
            "category":"Professional",
            "type":"Services"
        }
    ],
    "sg:phone":"+1 715 364 2705",
    "sg:postcode":"54864",
    "sg:province":"WI",
    "wof:name":"Mike Jamison",
    "wof:placetype":"venue"
},
  "geometry": {"coordinates":[-91.759591,46.578222],"type":"Point"}
}