{
  "type": "Feature",
  "properties": {
    "iso:country":"US",
    "sg:address":"20059 Schmickle Valley Rd",
    "sg:city":"Trempealeau",
    "sg:classifiers":[
        {
            "category":"Farming",
            "subcategory":"Dairy Farm",
            "type":"Manufacturing & Wholesale Goods"
        }
    ],
    "sg:phone":"+1 608 539 5391",
    "sg:postcode":"54661",
    "sg:province":"WI",
    "wof:name":"David Kramer Farm",
    "wof:placetype":"venue"
},
  "geometry": {"coordinates":[-91.478534,44.139888],"type":"Point"}
}