{
  "type": "Feature",
  "properties": {
    "iso:country":"US",
    "sg:address":"1404 E South River St",
    "sg:city":"Appleton",
    "sg:classifiers":[
        {
            "category":"Retail",
            "subcategory":"Auto Repair",
            "type":"Services"
        }
    ],
    "sg:phone":"+1 920 733 3881",
    "sg:postcode":"54915",
    "sg:province":"WI",
    "sg:tags":[
        "repairing",
        "automobile"
    ],
    "wof:name":"Grishaber Service Station",
    "wof:placetype":"venue"
},
  "geometry": {"coordinates":[-88.382806,44.25632],"type":"Point"}
}