{
  "type": "Feature",
  "properties": {
    "iso:country":"US",
    "sg:address":"1807 S 92nd St",
    "sg:city":"Milwaukee",
    "sg:classifiers":[
        {
            "category":"Retail",
            "subcategory":"Repair Shop",
            "type":"Services"
        }
    ],
    "sg:phone":"+1 414 259 0796",
    "sg:postcode":"53214",
    "sg:province":"WI",
    "wof:name":"Tenadon Services",
    "wof:placetype":"venue"
},
  "geometry": {"coordinates":[-88.027198,43.01015],"type":"Point"}
}