{
  "type": "Feature",
  "properties": {
    "iso:country":"US",
    "sg:address":"8507 W Lisbon Ave",
    "sg:city":"Milwaukee",
    "sg:classifiers":[
        {
            "category":"Retail",
            "subcategory":"Repair Shop",
            "type":"Services"
        }
    ],
    "sg:phone":"+1 414 464 4001",
    "sg:postcode":"53222",
    "sg:province":"WI",
    "sg:tags":[
        "lock",
        "locksmith"
    ],
    "wof:name":"JLS Lock & Key",
    "wof:placetype":"venue"
},
  "geometry": {"coordinates":[-88.018815,43.081491],"type":"Point"}
}