{
  "type": "Feature",
  "properties": {
    "iso:country":"US",
    "sg:address":"13608 Lakewood Dr",
    "sg:city":"Mequon",
    "sg:classifiers":[
        {
            "category":"Retail",
            "subcategory":"Repair Shop",
            "type":"Services"
        }
    ],
    "sg:phone":"+1 262 243 5543",
    "sg:postcode":"53097",
    "sg:province":"WI",
    "sg:tags":[
        "welding"
    ],
    "wof:name":"Applied Weld Tech",
    "wof:placetype":"venue"
},
  "geometry": {"coordinates":[-87.911038,43.262559],"type":"Point"}
}