{
  "type": "Feature",
  "properties": {
    "addr:full":"240 N Edwards Blvd Lake Geneva WI 53147",
    "addr:housenumber":"240",
    "addr:postcode":"53147",
    "addr:street":"N Edwards Blvd",
    "iso:country":"US",
    "sg:address":"240 N Edwards Blvd",
    "sg:city":"Lake Geneva",
    "sg:classifiers":[
        {
            "category":"Restaurant",
            "type":"Food & Drink"
        }
    ],
    "sg:menulink":"http://www.allmenus.com/wi/lake-geneva/101298-cousins-subs/menu/",
    "sg:phone":"+1 262 249 1225",
    "sg:postcode":"53147",
    "sg:province":"WI",
    "sg:tags":[
        "wrap",
        "american",
        "sandwich"
    ],
    "wof:name":"Cousin's Subs",
    "wof:placetype":"venue"
},
  "geometry": {"coordinates":[-88.414261,42.590078],"type":"Point"}
}