{
  "type": "Feature",
  "properties": {
    "iso:country":"US",
    "sg:address":"4202 W Silver Spring Dr",
    "sg:city":"Milwaukee",
    "sg:classifiers":[
        {
            "category":"Freight",
            "type":"Transportation"
        }
    ],
    "sg:phone":"+1 414 462 8609",
    "sg:postcode":"53209",
    "sg:province":"WI",
    "wof:name":"Trust Transportation",
    "wof:placetype":"venue"
},
  "geometry": {"coordinates":[-87.966246,43.119368],"type":"Point"}
}