{
  "type": "Feature",
  "properties": {
    "iso:country":"US",
    "sg:address":"17309 State Hwy 81",
    "sg:city":"Brodhead",
    "sg:classifiers":[
        {
            "category":"Home & Garden",
            "subcategory":"Building Materials",
            "type":"Retail Goods"
        }
    ],
    "sg:phone":"+1 608 897 2474",
    "sg:postcode":"53520",
    "sg:province":"WI",
    "wof:name":"Barnes Door",
    "wof:placetype":"venue"
},
  "geometry": {"coordinates":[-89.341106,42.567507],"type":"Point"}
}