{
  "type": "Feature",
  "properties": {
    "iso:country":"US",
    "sg:address":"208 W Jefferson St",
    "sg:city":"Burlington",
    "sg:classifiers":[
        {
            "category":"Professional",
            "type":"Services"
        }
    ],
    "sg:phone":"+1 262 767 8502",
    "sg:postcode":"53105",
    "sg:province":"WI",
    "wof:name":"Selina M Hochertz",
    "wof:placetype":"venue"
},
  "geometry": {"coordinates":[-88.281081,42.676723],"type":"Point"}
}