{
  "type": "Feature",
  "properties": {
    "iso:country":"US",
    "sg:address":"421 N Main St",
    "sg:city":"Oshkosh",
    "sg:classifiers":[
        {
            "category":"Professional",
            "subcategory":"Art Services",
            "type":"Services"
        }
    ],
    "sg:phone":"+1 920 235 4459",
    "sg:postcode":"54901",
    "sg:province":"WI",
    "sg:tags":[
        "photographer"
    ],
    "wof:name":"Oswald Photography",
    "wof:placetype":"venue"
},
  "geometry": {"coordinates":[-88.537586,44.017928],"type":"Point"}
}