{
  "type": "Feature",
  "properties": {
    "addr:full":"342 W Cedar St Hilbert WI 54129",
    "addr:housenumber":"342",
    "addr:postcode":"54129",
    "addr:street":"W Cedar St",
    "iso:country":"US",
    "sg:address":"342 W Cedar St",
    "sg:city":"Hilbert",
    "sg:classifiers":[
        {
            "category":"Home & Garden",
            "subcategory":"Furniture",
            "type":"Retail Goods"
        }
    ],
    "sg:phone":"+1 920 853 3014",
    "sg:postcode":"54129",
    "sg:province":"WI",
    "sg:tags":[
        "equipment",
        "kitchen",
        "cabinet"
    ],
    "wof:name":"Hilbert Cabinet",
    "wof:placetype":"venue"
},
  "geometry": {"coordinates":[-88.159234,44.140738],"type":"Point"}
}