{
  "type": "Feature",
  "properties": {
    "iso:country":"US",
    "sg:address":"5026 Voges Rd",
    "sg:city":"Madison",
    "sg:classifiers":[
        {
            "category":"Wholesale",
            "subcategory":"Vending Machines",
            "type":"Manufacturing & Wholesale Goods"
        }
    ],
    "sg:phone":"+1 608 838 2555",
    "sg:postcode":"53718",
    "sg:province":"WI",
    "sg:website":"www.allseasonsservices.com",
    "wof:name":"All Seasons Svc Inc",
    "wof:placetype":"venue"
},
  "geometry": {"coordinates":[-89.296797,43.040665],"type":"Point"}
}