{
  "type": "Feature",
  "properties": {
    "iso:country":"US",
    "sg:address":"406 Delaware St",
    "sg:city":"Sturgeon Bay",
    "sg:classifiers":[
        {
            "category":"Building & Trades",
            "subcategory":"Pest Control",
            "type":"Services"
        }
    ],
    "sg:phone":"+1 920 746 9740",
    "sg:postcode":"54235",
    "sg:province":"WI",
    "wof:name":"Door County Spray & Shine LLC",
    "wof:placetype":"venue"
},
  "geometry": {"coordinates":[-87.378093,44.845675],"type":"Point"}
}