{
  "type": "Feature",
  "properties": {
    "iso:country":"US",
    "sg:address":"810 Dura Beauty Ln",
    "sg:city":"Wisconsin Rapids",
    "sg:classifiers":[
        {
            "category":"Railroad",
            "type":"Transportation"
        }
    ],
    "sg:phone":"+1 715 423 2160",
    "sg:postcode":"54495",
    "sg:province":"WI",
    "sg:tags":[
        "operator",
        "line"
    ],
    "wof:name":"Chicago & Northwestern Trans",
    "wof:placetype":"venue"
},
  "geometry": {"coordinates":[-89.830202,44.403012],"type":"Point"}
}