{
  "type": "Feature",
  "properties": {
    "iso:country":"US",
    "sg:address":"11398 Co Rd F",
    "sg:city":"Phillips",
    "sg:classifiers":[
        {
            "category":"Retail",
            "subcategory":"Repair Shop",
            "type":"Services"
        }
    ],
    "sg:phone":"+1 715 339 3310",
    "sg:postcode":"54555",
    "sg:province":"WI",
    "sg:tags":[
        "taxidermist"
    ],
    "wof:name":"Natur-Al Creations Wildlife",
    "wof:placetype":"venue"
},
  "geometry": {"coordinates":[-90.522255,45.784954],"type":"Point"}
}