{
  "type": "Feature",
  "properties": {
    "iso:country":"US",
    "sg:address":"1502 Co Rd Xx",
    "sg:city":"Berlin",
    "sg:classifiers":[
        {
            "category":"Social Services",
            "type":"Services"
        }
    ],
    "sg:phone":"+1 920 361 0304",
    "sg:postcode":"54923",
    "sg:province":"WI",
    "sg:tags":[
        "care",
        "center",
        "day"
    ],
    "wof:name":"Umos Child Development Program",
    "wof:placetype":"venue"
},
  "geometry": {"coordinates":[-88.931079,44.036916],"type":"Point"}
}