{
  "type": "Feature",
  "properties": {
    "iso:country":"US",
    "sg:address":"4706 Cottage Grove Rd",
    "sg:city":"Madison",
    "sg:classifiers":[
        {
            "category":"Banks & Credit Unions",
            "subcategory":"Bank",
            "type":"Services"
        }
    ],
    "sg:phone":"+1 608 221 5000",
    "sg:postcode":"53716",
    "sg:province":"WI",
    "sg:tags":[
        "loan",
        "real estate"
    ],
    "wof:name":"Wells Fargo Home Mortgage",
    "wof:placetype":"venue"
},
  "geometry": {"coordinates":[-89.30128000000001,43.084303],"type":"Point"}
}