{
  "type": "Feature",
  "properties": {
    "iso:country":"US",
    "sg:address":"2788 Manitowoc Rd",
    "sg:city":"Green Bay",
    "sg:classifiers":[
        {
            "category":"Personal",
            "type":"Services"
        }
    ],
    "sg:phone":"+1 920 469 4325",
    "sg:postcode":"54311",
    "sg:province":"WI",
    "wof:name":"Healthy Touch Massage",
    "wof:placetype":"venue"
},
  "geometry": {"coordinates":[-87.94390799999999,44.46139],"type":"Point"}
}