{
  "type": "Feature",
  "properties": {
    "iso:country":"US",
    "sg:address":"1301 W Edgerton Ave",
    "sg:city":"Milwaukee",
    "sg:classifiers":[
        {
            "category":"Food & Beverages",
            "subcategory":"Groceries & Convenience Stores",
            "type":"Retail Goods"
        }
    ],
    "sg:phone":"+1 414 282 8826",
    "sg:postcode":"53221",
    "sg:province":"WI",
    "wof:name":"Al-Amal",
    "wof:placetype":"venue"
},
  "geometry": {"coordinates":[-87.930911,42.95202],"type":"Point"}
}