{
  "type": "Feature",
  "properties": {
    "addr:full":"1208 9th St Baraboo WI 53913",
    "addr:housenumber":"1208",
    "addr:postcode":"53913",
    "addr:street":"9Th St",
    "iso:country":"US",
    "sg:address":"1208 9th St",
    "sg:city":"Baraboo",
    "sg:classifiers":[
        {
            "category":"Health Services",
            "subcategory":"Medical Lab",
            "type":"Services"
        }
    ],
    "sg:phone":"+1 608 356 2143",
    "sg:postcode":"53913",
    "sg:province":"WI",
    "sg:tags":[
        "laboratory"
    ],
    "wof:name":"D & S Dental Laboratory",
    "wof:placetype":"venue"
},
  "geometry": {"coordinates":[-89.71912500000001,43.475542],"type":"Point"}
}