{
  "type": "Feature",
  "properties": {
    "iso:country":"US",
    "sg:address":"4992 State Hwy 89",
    "sg:city":"Jefferson",
    "sg:classifiers":[
        {
            "category":"Retail",
            "subcategory":"Animal Services",
            "type":"Services"
        }
    ],
    "sg:phone":"+1 920 674 3249",
    "sg:postcode":"53549",
    "sg:province":"WI",
    "sg:tags":[
        "pet",
        "boarding",
        "sitting"
    ],
    "wof:name":"Crystal Acres Kennels",
    "wof:placetype":"venue"
},
  "geometry": {"coordinates":[-88.875192,43.024608],"type":"Point"}
}