{
  "type": "Feature",
  "properties": {
    "iso:country":"US",
    "sg:address":"W62N560 Washington Ave",
    "sg:city":"Cedarburg",
    "sg:classifiers":[
        {
            "category":"Personal",
            "subcategory":"Beauty Salon",
            "type":"Services"
        },
        {
            "category":"Personal",
            "subcategory":"Day Spa",
            "type":"Services"
        }
    ],
    "sg:phone":"+1 262 375 5500",
    "sg:postcode":"53012",
    "sg:province":"WI",
    "sg:tags":[
        "hair"
    ],
    "sg:website":"www.bellalei.com",
    "wof:name":"Bella Lei Salon Spa & Boutique",
    "wof:placetype":"venue"
},
  "geometry": {"coordinates":[-87.98670199999999,43.2948],"type":"Point"}
}