{
  "type": "Feature",
  "properties": {
    "iso:country":"US",
    "sg:address":"3142 Larsen Rd",
    "sg:city":"Madison",
    "sg:classifiers":[
        {
            "category":"Real Estate",
            "subcategory":"Real Estate Agent",
            "type":"Services"
        }
    ],
    "sg:phone":"+1 608 222 9999",
    "sg:postcode":"53711",
    "sg:province":"WI",
    "wof:name":"Directory",
    "wof:placetype":"venue"
},
  "geometry": {"coordinates":[-89.365302,43.017029],"type":"Point"}
}