{
  "type": "Feature",
  "properties": {
    "iso:country":"US",
    "sg:address":"8312 6th St",
    "sg:city":"Amherst Junction",
    "sg:classifiers":[
        {
            "category":"Farming",
            "subcategory":"Dairy Farm",
            "type":"Manufacturing & Wholesale Goods"
        }
    ],
    "sg:phone":"+1 715 824 3120",
    "sg:postcode":"54407",
    "sg:province":"WI",
    "wof:name":"Leon Peplinski",
    "wof:placetype":"venue"
},
  "geometry": {"coordinates":[-89.38232000000001,44.491693],"type":"Point"}
}