{
  "type": "Feature",
  "properties": {
    "iso:country":"US",
    "sg:address":"6702 Stonefield Rd",
    "sg:city":"Middleton",
    "sg:classifiers":[
        {
            "category":"Professional",
            "subcategory":"Lawyer & Legal Services",
            "type":"Services"
        }
    ],
    "sg:phone":"+1 608 836 7667",
    "sg:postcode":"53562",
    "sg:province":"WI",
    "sg:tags":[
        "attorney"
    ],
    "wof:name":"Diane L Mader Law Office",
    "wof:placetype":"venue"
},
  "geometry": {"coordinates":[-89.50057,43.083233],"type":"Point"}
}