{
  "type": "Feature",
  "properties": {
    "addr:full":"622 E 9th St Fond Du Lac WI 54935",
    "addr:housenumber":"622",
    "addr:postcode":"54935",
    "addr:street":"E 9Th St",
    "iso:country":"US",
    "sg:address":"622 E 9th St",
    "sg:city":"Fond Du Lac",
    "sg:classifiers":[
        {
            "category":"Professional",
            "subcategory":"Management & Consulting",
            "type":"Services"
        }
    ],
    "sg:phone":"+1 920 921 4155",
    "sg:postcode":"54935",
    "sg:province":"WI",
    "sg:tags":[
        "testing"
    ],
    "wof:name":"Lynn M Tarpey",
    "wof:placetype":"venue"
},
  "geometry": {"coordinates":[-88.42358400000001,43.768611],"type":"Point"}
}