{
  "type": "Feature",
  "properties": {
    "addr:full":"6441 906th St Elk Mound WI 54739",
    "addr:housenumber":"6441",
    "addr:postcode":"54739",
    "addr:street":"906Th St",
    "iso:country":"US",
    "sg:address":"6441 906th St",
    "sg:city":"Elk Mound",
    "sg:classifiers":[
        {
            "category":"Professional",
            "subcategory":"Art Services",
            "type":"Services"
        }
    ],
    "sg:phone":"+1 715 879 5899",
    "sg:postcode":"54739",
    "sg:province":"WI",
    "sg:tags":[
        "graphic",
        "designer"
    ],
    "wof:name":"T C Imaging",
    "wof:placetype":"venue"
},
  "geometry": {"coordinates":[-91.722786,44.923595],"type":"Point"}
}