{
  "type": "Feature",
  "properties": {
    "addr:full":"4985 State Hwy 50 Delavan WI 53115",
    "addr:housenumber":"4985",
    "addr:postcode":"53115",
    "addr:street":"State Hwy 50",
    "iso:country":"US",
    "sg:address":"4985 State Hwy 50",
    "sg:city":"Delavan",
    "sg:classifiers":[
        {
            "category":"Health Services",
            "subcategory":"Chiropractor",
            "type":"Services"
        }
    ],
    "sg:phone":"+1 262 245 1919",
    "sg:postcode":"53115",
    "sg:province":"WI",
    "wof:name":"Berget Dr John",
    "wof:placetype":"venue"
},
  "geometry": {"coordinates":[-88.625271,42.627559],"type":"Point"}
}