{
  "type": "Feature",
  "properties": {
    "iso:country":"US",
    "sg:address":"1819 Lake Rd",
    "sg:city":"Mukwonago",
    "sg:classifiers":[
        {
            "category":"Recreation",
            "type":"Entertainment"
        }
    ],
    "sg:phone":"+1 262 642 5222",
    "sg:postcode":"53149",
    "sg:province":"WI",
    "sg:tags":[
        "club",
        "membership"
    ],
    "wof:name":"Big Bucks Hunt Club LLC",
    "wof:placetype":"venue"
},
  "geometry": {"coordinates":[-88.392049,42.828292],"type":"Point"}
}