{
  "type": "Feature",
  "properties": {
    "addr:full":"1708 28th St Kenosha WI 53140",
    "addr:housenumber":"1708",
    "addr:postcode":"53140",
    "addr:street":"28Th St",
    "iso:country":"US",
    "sg:address":"1708 28th St",
    "sg:city":"Kenosha",
    "sg:classifiers":[
        {
            "category":"Building & Trades",
            "subcategory":"Cleaning & Sanitation",
            "type":"Services"
        }
    ],
    "sg:phone":"+1 262 657 0759",
    "sg:postcode":"53140",
    "sg:province":"WI",
    "sg:tags":[
        "maintenance"
    ],
    "wof:name":"Jamie Borths",
    "wof:placetype":"venue"
},
  "geometry": {"coordinates":[-87.831121,42.612543],"type":"Point"}
}