{
  "type": "Feature",
  "properties": {
    "iso:country":"US",
    "sg:address":"5125 Pepin Pl",
    "sg:city":"Madison",
    "sg:classifiers":[
        {
            "category":"Social Services",
            "subcategory":"Adult Care",
            "type":"Services"
        }
    ],
    "sg:phone":"+1 608 238 4802",
    "sg:postcode":"53705",
    "sg:province":"WI",
    "sg:tags":[
        "home"
    ],
    "wof:name":"Pepin Group Home",
    "wof:placetype":"venue"
},
  "geometry": {"coordinates":[-89.46914,43.06414],"type":"Point"}
}