{
  "type": "Feature",
  "properties": {
    "iso:country":"US",
    "sg:address":"525 Junction Rd",
    "sg:city":"Madison",
    "sg:classifiers":[
        {
            "category":"Banks & Credit Unions",
            "subcategory":"Bank",
            "type":"Services"
        }
    ],
    "sg:phone":"+1 608 245 6510",
    "sg:postcode":"53717",
    "sg:province":"WI",
    "sg:website":"www.johnsonbank.com",
    "wof:name":"Johnson Bank",
    "wof:placetype":"venue"
},
  "geometry": {"coordinates":[-89.524419,43.069041],"type":"Point"}
}