{
  "type": "Feature",
  "properties": {
    "iso:country":"US",
    "sg:address":"8047 N 47th St",
    "sg:city":"Milwaukee",
    "sg:classifiers":[
        {
            "category":"Building & Trades",
            "subcategory":"Construction",
            "type":"Services"
        }
    ],
    "sg:phone":"+1 414 640 6199",
    "sg:postcode":"53223",
    "sg:province":"WI",
    "sg:tags":[
        "hanging",
        "contractor"
    ],
    "wof:name":"D E Contractors Unlimted",
    "wof:placetype":"venue"
},
  "geometry": {"coordinates":[-87.969848,43.166283],"type":"Point"}
}