{
  "type": "Feature",
  "properties": {
    "iso:country":"US",
    "sg:address":"2908 Douglas Ave",
    "sg:city":"Racine",
    "sg:classifiers":[
        {
            "category":"Building & Trades",
            "subcategory":"Construction",
            "type":"Services"
        }
    ],
    "sg:phone":"+1 262 638 4662",
    "sg:postcode":"53402",
    "sg:province":"WI",
    "sg:tags":[
        "painting",
        "contractor"
    ],
    "wof:name":"Tobin Painting Ltd",
    "wof:placetype":"venue"
},
  "geometry": {"coordinates":[-87.799453,42.755379],"type":"Point"}
}