{
  "type": "Feature",
  "properties": {
    "iso:country":"US",
    "sg:address":"9741 W Beloit Rd",
    "sg:city":"Milwaukee",
    "sg:classifiers":[
        {
            "category":"Place Of Worship",
            "subcategory":"Church",
            "type":"Public Place"
        },
        {
            "category":"Place Of Worship",
            "type":"Public Place"
        },
        {
            "category":"Organizations",
            "subcategory":"Religious Organization",
            "type":"Services"
        }
    ],
    "sg:phone":"+1 414 321 0730",
    "sg:postcode":"53227",
    "sg:province":"WI",
    "sg:tags":[
        "lutheran",
        "synod",
        "churches-lutheran-lutheran",
        "churches-lutheran-evangelical",
        "missouri",
        "america",
        "churches-lutheran",
        "lcms"
    ],
    "sg:website":"http://www.divineshepherdlc.org",
    "wof:name":"Shepherd Divine Lutheran Church Inc",
    "wof:placetype":"venue"
},
  "geometry": {"coordinates":[-88.034436,42.98258],"type":"Point"}
}