{
  "type": "Feature",
  "properties": {
    "addr:full":"100 N Lake Ave Twin Lakes WI 53181",
    "addr:housenumber":"100",
    "addr:postcode":"53181",
    "addr:street":"N Lake Ave",
    "iso:country":"US",
    "sg:address":"100 N Lake Ave",
    "sg:city":"Twin Lakes",
    "sg:classifiers":[
        {
            "category":"Restaurant",
            "type":"Food & Drink"
        }
    ],
    "sg:phone":"+1 262 877 2456",
    "sg:postcode":"53181",
    "sg:province":"WI",
    "wof:name":"Corner Kitchen Family Rstrnt",
    "wof:placetype":"venue"
},
  "geometry": {"coordinates":[-88.24855599999999,42.532205],"type":"Point"}
}