{
  "type": "Feature",
  "properties": {
    "iso:country":"US",
    "sg:address":"5415 Everybodys Rd",
    "sg:city":"Crandon",
    "sg:classifiers":[
        {
            "category":"Government",
            "subcategory":"Office",
            "type":"Public Place"
        }
    ],
    "sg:phone":"+1 715 478 5850",
    "sg:postcode":"54541",
    "sg:province":"WI",
    "sg:tags":[
        "organization",
        "tribal"
    ],
    "wof:name":"Eugene Whitefish",
    "wof:placetype":"venue"
},
  "geometry": {"coordinates":[-88.843845,45.56957],"type":"Point"}
}