{
  "type": "Feature",
  "properties": {
    "iso:country":"US",
    "sg:address":"8215 W Hampton Ave",
    "sg:city":"Milwaukee",
    "sg:classifiers":[
        {
            "category":"Home & Garden",
            "subcategory":"Garden Supply",
            "type":"Retail Goods"
        }
    ],
    "sg:phone":"+1 414 463 4380",
    "sg:postcode":"53218",
    "sg:province":"WI",
    "sg:tags":[
        "equipment",
        "power"
    ],
    "wof:name":"Lawn N Sport Pwr Mower Sls Svc",
    "wof:placetype":"venue"
},
  "geometry": {"coordinates":[-88.01596499999999,43.104911],"type":"Point"}
}