{
  "type": "Feature",
  "properties": {
    "iso:country":"US",
    "sg:address":"4602 5th Ave",
    "sg:city":"Hancock",
    "sg:classifiers":[
        {
            "category":"Personal",
            "subcategory":"Beauty Salon",
            "type":"Services"
        }
    ],
    "sg:phone":"+1 715 249 5060",
    "sg:postcode":"54943",
    "sg:province":"WI",
    "sg:tags":[
        "shop"
    ],
    "wof:name":"Jackies Salon",
    "wof:placetype":"venue"
},
  "geometry": {"coordinates":[-89.522161,44.150726],"type":"Point"}
}