{
  "type": "Feature",
  "properties": {
    "addr:full":"301 Wakefield Downs Wales WI 53183",
    "addr:housenumber":"301",
    "addr:postcode":"53183",
    "addr:street":"Wakefield Downs",
    "iso:country":"US",
    "sg:address":"301 Wakefield Downs",
    "sg:city":"Wales",
    "sg:classifiers":[
        {
            "category":"Food & Beverages",
            "subcategory":"Dairy",
            "type":"Retail Goods"
        }
    ],
    "sg:phone":"+1 262 968 5011",
    "sg:postcode":"53183",
    "sg:province":"WI",
    "sg:tags":[
        "yogurt"
    ],
    "wof:name":"Belcher Enterprises",
    "wof:placetype":"venue"
},
  "geometry": {"coordinates":[-88.387103,42.989879],"type":"Point"}
}