{
  "type": "Feature",
  "properties": {
    "iso:country":"US",
    "sg:address":"4708 Elm Lawn Rd",
    "sg:city":"Oconto Falls",
    "sg:classifiers":[
        {
            "category":"Farming",
            "subcategory":"Farm",
            "type":"Manufacturing & Wholesale Goods"
        }
    ],
    "sg:phone":"+1 920 846 4336",
    "sg:postcode":"54154",
    "sg:province":"WI",
    "sg:tags":[
        "crop",
        "general"
    ],
    "wof:name":"Joe Zeitler",
    "wof:placetype":"venue"
},
  "geometry": {"coordinates":[-88.167502,44.850647],"type":"Point"}
}