{
  "type": "Feature",
  "properties": {
    "iso:country":"US",
    "sg:address":"1238 Red Maple Rd",
    "sg:city":"De Pere",
    "sg:classifiers":[
        {
            "category":"Building & Trades",
            "subcategory":"Construction",
            "type":"Services"
        }
    ],
    "sg:phone":"+1 920 336 4814",
    "sg:postcode":"54115",
    "sg:province":"WI",
    "sg:tags":[
        "hanging",
        "contractor"
    ],
    "wof:name":"Maverick Painting & Staining",
    "wof:placetype":"venue"
},
  "geometry": {"coordinates":[-88.093231,44.417872],"type":"Point"}
}