{
  "type": "Feature",
  "properties": {
    "addr:full":"1820 S 75th St Milwaukee WI 53214",
    "addr:housenumber":"1820",
    "addr:postcode":"53214",
    "addr:street":"S 75Th St",
    "iso:country":"US",
    "sg:address":"1820 S 75th St",
    "sg:city":"Milwaukee",
    "sg:classifiers":[
        {
            "category":"Social Services",
            "subcategory":"Adult Care",
            "type":"Services"
        }
    ],
    "sg:phone":"+1 414 774 4411",
    "sg:postcode":"53214",
    "sg:province":"WI",
    "sg:tags":[
        "residential",
        "intermediate",
        "facility"
    ],
    "wof:name":"Library Square",
    "wof:placetype":"venue"
},
  "geometry": {"coordinates":[-88.006055,43.011287],"type":"Point"}
}