{
  "type": "Feature",
  "properties": {
    "iso:country":"US",
    "sg:address":"334 5th Ave S",
    "sg:city":"La Crosse",
    "sg:classifiers":[
        {
            "category":"Manufacturing",
            "subcategory":"Food",
            "type":"Manufacturing & Wholesale Goods"
        }
    ],
    "sg:phone":"+1 608 782 8488",
    "sg:postcode":"54601",
    "sg:province":"WI",
    "sg:tags":[
        "preparation",
        "product",
        "mfg"
    ],
    "wof:name":"Sara Lee Bakery Group Inc",
    "wof:placetype":"venue"
},
  "geometry": {"coordinates":[-91.250224,43.809242],"type":"Point"}
}