{
  "type": "Feature",
  "properties": {
    "iso:country":"US",
    "sg:address":"2460 Velp Ave",
    "sg:city":"Green Bay",
    "sg:classifiers":[
        {
            "category":"Real Estate",
            "subcategory":"Real Estate Operator",
            "type":"Services"
        }
    ],
    "sg:phone":"+1 920 434 9428",
    "sg:postcode":"54303",
    "sg:province":"WI",
    "sg:tags":[
        "building",
        "nonresidential"
    ],
    "wof:name":"Hair Gallery",
    "wof:placetype":"venue"
},
  "geometry": {"coordinates":[-88.078036,44.568328],"type":"Point"}
}