{
  "type": "Feature",
  "properties": {
    "iso:country":"US",
    "sg:address":"4849 Briarvale Dr",
    "sg:city":"West Bend",
    "sg:classifiers":[
        {
            "category":"Wholesale",
            "subcategory":"Electrical",
            "type":"Manufacturing & Wholesale Goods"
        }
    ],
    "sg:phone":"+1 262 677 4170",
    "sg:postcode":"53095",
    "sg:province":"WI",
    "sg:tags":[
        "control",
        "equipment"
    ],
    "wof:name":"Joslyn Clark Controls Inc",
    "wof:placetype":"venue"
},
  "geometry": {"coordinates":[-88.21639399999999,43.367049],"type":"Point"}
}