{
  "type": "Feature",
  "properties": {
    "iso:country":"US",
    "sg:address":"180 N Jefferson St",
    "sg:city":"Milwaukee",
    "sg:classifiers":[
        {
            "category":"Professional",
            "subcategory":"Business Services",
            "type":"Services"
        }
    ],
    "sg:phone":"+1 414 276 2240",
    "sg:postcode":"53202",
    "sg:province":"WI",
    "sg:tags":[
        "plant",
        "design",
        "maintenance"
    ],
    "sg:website":"www.sweetbushinc.com",
    "wof:name":"Sweetbush Inc",
    "wof:placetype":"venue"
},
  "geometry": {"coordinates":[-87.904411,43.032052],"type":"Point"}
}