{
  "type": "Feature",
  "properties": {
    "addr:full":"4512 Rib Mountain Dr Wausau WI 54401",
    "addr:postcode":"4512;54401",
    "addr:street":"Rib Mountain Dr",
    "iso:country":"US",
    "sg:address":"4512 Rib Mountain Dr",
    "sg:city":"Wausau",
    "sg:classifiers":[
        {
            "category":"Restaurant",
            "type":"Food & Drink"
        }
    ],
    "sg:phone":"+1 715 359 7999",
    "sg:postcode":"54401",
    "sg:province":"WI",
    "sg:tags":[
        "eating",
        "pizza"
    ],
    "wof:name":"Rosati's Pizza",
    "wof:placetype":"venue"
},
  "geometry": {"coordinates":[-89.64943599999999,44.913447],"type":"Point"}
}