{
  "type": "Feature",
  "properties": {
    "iso:country":"US",
    "sg:address":"14267 State Hwy 70",
    "sg:city":"Lac Du Flambeau",
    "sg:classifiers":[
        {
            "category":"Retail",
            "subcategory":"Auto Repair",
            "type":"Services"
        }
    ],
    "sg:phone":"+1 715 588 3146",
    "sg:postcode":"54538",
    "sg:province":"WI",
    "sg:tags":[
        "repairing",
        "automobile"
    ],
    "wof:name":"Tower Service",
    "wof:placetype":"venue"
},
  "geometry": {"coordinates":[-89.914216,45.914562],"type":"Point"}
}