{
  "type": "Feature",
  "properties": {
    "iso:country":"US",
    "sg:address":"112 N 5th St",
    "sg:city":"De Pere",
    "sg:classifiers":[
        {
            "category":"Utilities",
            "subcategory":"Electric",
            "type":"Services"
        }
    ],
    "sg:phone":"+1 920 983 6931",
    "sg:postcode":"54115",
    "sg:province":"WI",
    "sg:tags":[
        "company"
    ],
    "wof:name":"De Pere Energy Ctr",
    "wof:placetype":"venue"
},
  "geometry": {"coordinates":[-88.073246,44.448495],"type":"Point"}
}