{
  "type": "Feature",
  "properties": {
    "iso:country":"US",
    "sg:address":"5100 W Ryan Rd",
    "sg:city":"Franklin",
    "sg:classifiers":[
        {
            "category":"Retail",
            "subcategory":"Laundry & Dry Cleaning",
            "type":"Services"
        }
    ],
    "sg:phone":"+1 414 421 3910",
    "sg:postcode":"53132",
    "sg:province":"WI",
    "sg:tags":[
        "cleaners"
    ],
    "wof:name":"Alpha Cleaners",
    "wof:placetype":"venue"
},
  "geometry": {"coordinates":[-87.985063,42.872605],"type":"Point"}
}