{
  "type": "Feature",
  "properties": {
    "iso:country":"US",
    "sg:address":"4797 Fontana Rd",
    "sg:city":"West Bend",
    "sg:classifiers":[
        {
            "category":"Building & Trades",
            "subcategory":"Electrical",
            "type":"Services"
        },
        {
            "category":"Building & Trades",
            "subcategory":"Landscaping Services",
            "type":"Services"
        }
    ],
    "sg:phone":"+1 262 644 9922",
    "sg:postcode":"53095",
    "sg:province":"WI",
    "wof:name":"Turfmaster Landscape LLC",
    "wof:placetype":"venue"
},
  "geometry": {"coordinates":[-88.269072,43.365093],"type":"Point"}
}