{
  "type": "Feature",
  "properties": {
    "iso:country":"US",
    "sg:address":"5225 N Ironwood Ln",
    "sg:city":"Milwaukee",
    "sg:classifiers":[
        {
            "category":"Real Estate",
            "subcategory":"Real Estate Agent",
            "type":"Services"
        }
    ],
    "sg:phone":"+1 414 962 7711",
    "sg:postcode":"53217",
    "sg:province":"WI",
    "sg:tags":[
        "management"
    ],
    "wof:name":"East Suburban Management Co",
    "wof:placetype":"venue"
},
  "geometry": {"coordinates":[-87.91767,43.143319],"type":"Point"}
}