{
  "type": "Feature",
  "properties": {
    "iso:country":"US",
    "sg:address":"138 Robin Ln",
    "sg:city":"Shawano",
    "sg:classifiers":[
        {
            "category":"Building & Trades",
            "subcategory":"Construction",
            "type":"Services"
        }
    ],
    "sg:phone":"+1 715 526 2384",
    "sg:postcode":"54166",
    "sg:province":"WI",
    "sg:tags":[
        "siding",
        "contractor"
    ],
    "wof:name":"Homestead Building & Remodel",
    "wof:placetype":"venue"
},
  "geometry": {"coordinates":[-88.599715,44.764015],"type":"Point"}
}