{
  "type": "Feature",
  "properties": {
    "iso:country":"US",
    "sg:address":"62682 Rush Creek Rd",
    "sg:city":"Ferryville",
    "sg:classifiers":[
        {
            "category":"Home & Garden",
            "subcategory":"Home Furnishings",
            "type":"Retail Goods"
        }
    ],
    "sg:phone":"+1 608 648 2081",
    "sg:postcode":"54628",
    "sg:province":"WI",
    "wof:name":"Olde Tyme Quilt Shoppe",
    "wof:placetype":"venue"
},
  "geometry": {"coordinates":[-91.118359,43.393452],"type":"Point"}
}