{
  "type": "Feature",
  "properties": {
    "iso:country":"US",
    "sg:address":"6526 7th Ave",
    "sg:city":"Kenosha",
    "sg:classifiers":[
        {
            "category":"Professional",
            "subcategory":"Business Services",
            "type":"Services"
        }
    ],
    "sg:phone":"+1 262 605 1467",
    "sg:postcode":"53143",
    "sg:province":"WI",
    "sg:tags":[
        "liquidator"
    ],
    "wof:name":"Collegiate Funding",
    "wof:placetype":"venue"
},
  "geometry": {"coordinates":[-87.818494,42.574233],"type":"Point"}
}