{
  "type": "Feature",
  "properties": {
    "iso:country":"US",
    "sg:address":"1220 Femrite Dr",
    "sg:city":"Madison",
    "sg:classifiers":[
        {
            "category":"Real Estate",
            "subcategory":"Real Estate Agent",
            "type":"Services"
        }
    ],
    "sg:phone":"+1 608 222 6600",
    "sg:postcode":"53716",
    "sg:province":"WI",
    "wof:name":"Lenz Randy & Team Inc",
    "wof:placetype":"venue"
},
  "geometry": {"coordinates":[-89.311429,43.05048],"type":"Point"}
}