{
  "type": "Feature",
  "properties": {
    "iso:country":"US",
    "sg:address":"4487 Fetke Lake Dr",
    "sg:city":"Rhinelander",
    "sg:classifiers":[
        {
            "category":"Professional",
            "subcategory":"Management & Consulting",
            "type":"Services"
        }
    ],
    "sg:phone":"+1 715 369 3589",
    "sg:postcode":"54501",
    "sg:province":"WI",
    "wof:name":"Glebke & Son",
    "wof:placetype":"venue"
},
  "geometry": {"coordinates":[-89.470222,45.683328],"type":"Point"}
}