{
  "type": "Feature",
  "properties": {
    "iso:country":"US",
    "sg:address":"1311 McDonald St",
    "sg:city":"Oconto",
    "sg:classifiers":[
        {
            "category":"Professional",
            "type":"Services"
        }
    ],
    "sg:phone":"+1 920 834 5308",
    "sg:postcode":"54153",
    "sg:province":"WI",
    "wof:name":"Dustin R Lubus",
    "wof:placetype":"venue"
},
  "geometry": {"coordinates":[-87.90404,44.881568],"type":"Point"}
}