{
  "type": "Feature",
  "properties": {
    "iso:country":"US",
    "sg:address":"2221 Cater Rd",
    "sg:city":"Eau Claire",
    "sg:classifiers":[
        {
            "category":"Personal",
            "subcategory":"Tanning Parlor",
            "type":"Services"
        }
    ],
    "sg:phone":"+1 715 833 2100",
    "sg:postcode":"54701",
    "sg:province":"WI",
    "sg:tags":[
        "salon"
    ],
    "wof:name":"Highland's Fitness Ctr",
    "wof:placetype":"venue"
},
  "geometry": {"coordinates":[-91.498852,44.748535],"type":"Point"}
}