{
  "type": "Feature",
  "properties": {
    "iso:country":"US",
    "sg:address":"121 State Hwy 64",
    "sg:city":"Antigo",
    "sg:classifiers":[
        {
            "category":"Home & Garden",
            "subcategory":"Building Materials",
            "type":"Retail Goods"
        }
    ],
    "sg:phone":"+1 715 627 4292",
    "sg:postcode":"54409",
    "sg:province":"WI",
    "sg:tags":[
        "glass",
        "window",
        "plate"
    ],
    "wof:name":"Auto Glass Specialists",
    "wof:placetype":"venue"
},
  "geometry": {"coordinates":[-89.139894,45.162154],"type":"Point"}
}