{
  "type": "Feature",
  "properties": {
    "addr:full":"2101 S 54th St Milwaukee WI 53219",
    "addr:housenumber":"2101",
    "addr:postcode":"53219",
    "addr:street":"S 54Th St",
    "iso:country":"US",
    "sg:address":"2101 S 54th St",
    "sg:city":"Milwaukee",
    "sg:classifiers":[
        {
            "category":"Building & Trades",
            "subcategory":"Landscaping Services",
            "type":"Services"
        }
    ],
    "sg:phone":"+1 414 281 3114",
    "sg:postcode":"53219",
    "sg:province":"WI",
    "sg:tags":[
        "snowplowing",
        "landscape",
        "contractor"
    ],
    "wof:name":"J R Landscape Management",
    "wof:placetype":"venue"
},
  "geometry": {"coordinates":[-87.980442,43.006623],"type":"Point"}
}