{
  "type": "Feature",
  "properties": {
    "iso:country":"US",
    "sg:address":"100 S Water St",
    "sg:city":"Watertown",
    "sg:classifiers":[
        {
            "category":"Education",
            "subcategory":"Library",
            "type":"Public Place"
        }
    ],
    "sg:phone":"+1 920 261 5757",
    "sg:postcode":"53094",
    "sg:province":"WI",
    "sg:tags":[
        "executive"
    ],
    "wof:name":"Watertown Public Library",
    "wof:placetype":"venue"
},
  "geometry": {"coordinates":[-88.726058,43.19452],"type":"Point"}
}