{
  "type": "Feature",
  "properties": {
    "addr:full":"5218 W Bluemound Rd Milwaukee WI 53208",
    "addr:housenumber":"5218",
    "addr:postcode":"53208",
    "addr:street":"W Bluemound Rd",
    "iso:country":"US",
    "sg:address":"5218 W Bluemound Rd",
    "sg:city":"Milwaukee",
    "sg:classifiers":[
        {
            "category":"Bars & Pubs",
            "type":"Food & Drink"
        }
    ],
    "sg:phone":"+1 414 258 9837",
    "sg:postcode":"53208",
    "sg:province":"WI",
    "sg:website":"www.kellysbleachers.net",
    "wof:name":"S & V Inc Dba Kelly's Bleacher",
    "wof:placetype":"venue"
},
  "geometry": {"coordinates":[-87.979867,43.036714],"type":"Point"}
}