{
  "type": "Feature",
  "properties": {
    "iso:country":"US",
    "sg:address":"1506 N 123rd St",
    "sg:city":"Milwaukee",
    "sg:classifiers":[
        {
            "category":"Professional",
            "type":"Services"
        }
    ],
    "sg:phone":"+1 414 607 3741",
    "sg:postcode":"53226",
    "sg:province":"WI",
    "wof:name":"Jeff Ring",
    "wof:placetype":"venue"
},
  "geometry": {"coordinates":[-88.065561,43.050764],"type":"Point"}
}