{
  "type": "Feature",
  "properties": {
    "iso:country":"US",
    "sg:address":"162 Wood Ave",
    "sg:city":"Nekoosa",
    "sg:classifiers":[
        {
            "category":"Building & Trades",
            "subcategory":"Construction",
            "type":"Services"
        }
    ],
    "sg:phone":"+1 715 886 5571",
    "sg:postcode":"54457",
    "sg:province":"WI",
    "sg:tags":[
        "house"
    ],
    "wof:name":"Keller Construction",
    "wof:placetype":"venue"
},
  "geometry": {"coordinates":[-89.901589,44.312704],"type":"Point"}
}