{
  "type": "Feature",
  "properties": {
    "addr:full":"6151 N Flint Rd Milwaukee WI 53209",
    "addr:housenumber":"6151",
    "addr:postcode":"53209",
    "addr:street":"N Flint Rd",
    "iso:country":"US",
    "sg:address":"6151 N Flint Rd",
    "sg:city":"Milwaukee",
    "sg:classifiers":[
        {
            "category":"Building & Trades",
            "subcategory":"Construction",
            "type":"Services"
        }
    ],
    "sg:phone":"+1 414 352 7731",
    "sg:postcode":"53209",
    "sg:province":"WI",
    "sg:tags":[
        "painting",
        "contractor"
    ],
    "wof:name":"Crain Painting Contractors",
    "wof:placetype":"venue"
},
  "geometry": {"coordinates":[-87.94265,43.130161],"type":"Point"}
}