{
  "type": "Feature",
  "properties": {
    "iso:country":"US",
    "sg:address":"6591 Manitowoc Rd",
    "sg:city":"Menasha",
    "sg:classifiers":[
        {
            "category":"Building & Trades",
            "subcategory":"Construction",
            "type":"Services"
        }
    ],
    "sg:phone":"+1 920 739 3289",
    "sg:postcode":"54952",
    "sg:province":"WI",
    "sg:tags":[
        "painting",
        "sandblasting",
        "contractor"
    ],
    "wof:name":"Luniak Paint & Supply Inc",
    "wof:placetype":"venue"
},
  "geometry": {"coordinates":[-88.368622,44.221612],"type":"Point"}
}