{
  "type": "Feature",
  "properties": {
    "iso:country":"US",
    "sg:address":"1918 Pike Dr",
    "sg:city":"Madison",
    "sg:classifiers":[
        {
            "category":"Education",
            "subcategory":"Special Training",
            "type":"Public Place"
        }
    ],
    "sg:phone":"+1 608 277 0247",
    "sg:postcode":"53713",
    "sg:province":"WI",
    "wof:name":"Auriantal Investment Propertie",
    "wof:placetype":"venue"
},
  "geometry": {"coordinates":[-89.414392,43.029465],"type":"Point"}
}