{
  "type": "Feature",
  "properties": {
    "addr:full":"1911 Russell St Wisconsin Rapids WI 54495",
    "addr:housenumber":"1911",
    "addr:postcode":"54495",
    "addr:street":"Russell St",
    "iso:country":"US",
    "sg:address":"1911 Russell St",
    "sg:city":"Wisconsin Rapids",
    "sg:classifiers":[
        {
            "category":"Arts & Performance",
            "subcategory":"Theater",
            "type":"Entertainment"
        }
    ],
    "sg:phone":"+1 715 424 3657",
    "sg:postcode":"54495",
    "sg:province":"WI",
    "sg:tags":[
        "group"
    ],
    "wof:name":"Macomber Entertainment LLC",
    "wof:placetype":"venue"
},
  "geometry": {"coordinates":[-89.847981,44.3875],"type":"Point"}
}