{
  "type": "Feature",
  "properties": {
    "addr:full":"4257 N 100th St Milwaukee WI 53222",
    "addr:housenumber":"4257",
    "addr:postcode":"53222",
    "addr:street":"N 100Th St",
    "iso:country":"US",
    "sg:address":"4257 N 100th St",
    "sg:city":"Milwaukee",
    "sg:classifiers":[
        {
            "category":"Education",
            "subcategory":"School",
            "type":"Public Place"
        }
    ],
    "sg:phone":"+1 414 466 3706",
    "sg:postcode":"53222",
    "sg:province":"WI",
    "sg:website":"www.dsha.k12.wi.us",
    "wof:name":"Divine Savior-Holy Angels High",
    "wof:placetype":"venue"
},
  "geometry": {"coordinates":[-88.03774900000001,43.094108],"type":"Point"}
}