{
  "type": "Feature",
  "properties": {
    "iso:country":"US",
    "sg:address":"3134 Dorchester Way",
    "sg:city":"Madison",
    "sg:classifiers":[
        {
            "category":"Professional",
            "subcategory":"Computer Services",
            "type":"Services"
        }
    ],
    "sg:phone":"+1 608 273 3243",
    "sg:postcode":"53719",
    "sg:province":"WI",
    "wof:name":"Identity Developments",
    "wof:placetype":"venue"
},
  "geometry": {"coordinates":[-89.487246,43.016509],"type":"Point"}
}