{
  "type": "Feature",
  "properties": {
    "addr:full":"1330 Marine St Green Bay WI 54301",
    "addr:housenumber":"1330",
    "addr:postcode":"54301",
    "addr:street":"Marine St",
    "iso:country":"US",
    "sg:address":"1330 Marine St",
    "sg:city":"Green Bay",
    "sg:classifiers":[
        {
            "category":"Bars & Pubs",
            "type":"Food & Drink"
        }
    ],
    "sg:menulink":"http://www.allmenus.com/wi/allouez/279675-jimmy-seas-pub,-grill--fenders/menu/",
    "sg:phone":"+1 920 438 7640",
    "sg:postcode":"54301",
    "sg:province":"WI",
    "sg:tags":[
        "seafood",
        "american"
    ],
    "wof:name":"Jimmy Seas Pub, Grill & Fenders",
    "wof:placetype":"venue"
},
  "geometry": {"coordinates":[-88.02191500000001,44.496581],"type":"Point"}
}