{
  "type": "Feature",
  "properties": {
    "iso:country":"US",
    "sg:address":"134 Co Rd C",
    "sg:city":"Spencer",
    "sg:classifiers":[
        {
            "category":"Retail",
            "subcategory":"Auto Repair",
            "type":"Services"
        }
    ],
    "sg:phone":"+1 715 659 4300",
    "sg:postcode":"54479",
    "sg:province":"WI",
    "sg:tags":[
        "repairing",
        "automobile",
        "general"
    ],
    "wof:name":"Craig's Auto Repair",
    "wof:placetype":"venue"
},
  "geometry": {"coordinates":[-90.299018,44.757546],"type":"Point"}
}