{
  "type": "Feature",
  "properties": {
    "iso:country":"US",
    "sg:address":"2013 E Mifflin St",
    "sg:city":"Madison",
    "sg:classifiers":[
        {
            "category":"Professional",
            "type":"Services"
        }
    ],
    "sg:phone":"+1 608 241 1030",
    "sg:postcode":"53704",
    "sg:province":"WI",
    "wof:name":"Stacy M Graff",
    "wof:placetype":"venue"
},
  "geometry": {"coordinates":[-89.357046,43.095477],"type":"Point"}
}