{
  "type": "Feature",
  "properties": {
    "iso:country":"US",
    "sg:address":"1010 Declark St",
    "sg:city":"Beaver Dam",
    "sg:classifiers":[
        {
            "category":"Personal",
            "subcategory":"Tanning Parlor",
            "type":"Services"
        }
    ],
    "sg:phone":"+1 920 887 8999",
    "sg:postcode":"53916",
    "sg:province":"WI",
    "sg:tags":[
        "salon"
    ],
    "wof:name":"Key West Tanning Salon",
    "wof:placetype":"venue"
},
  "geometry": {"coordinates":[-88.834783,43.475462],"type":"Point"}
}