{
  "type": "Feature",
  "properties": {
    "addr:full":"7415 W Snow Creek Rd Black River Falls WI 54615",
    "addr:housenumber":"7415",
    "addr:postcode":"54615",
    "addr:street":"W Snow Creek Rd",
    "iso:country":"US",
    "sg:address":"7415 W Snow Creek Rd",
    "sg:city":"Black River Falls",
    "sg:classifiers":[
        {
            "category":"Manufacturing",
            "subcategory":"Lumber",
            "type":"Manufacturing & Wholesale Goods"
        }
    ],
    "sg:phone":"+1 715 284 2893",
    "sg:postcode":"54615",
    "sg:province":"WI",
    "sg:tags":[
        "mill"
    ],
    "wof:name":"Black River Country Log Homes",
    "wof:placetype":"venue"
},
  "geometry": {"coordinates":[-90.84192299999999,44.348735],"type":"Point"}
}