{
  "type": "Feature",
  "properties": {
    "iso:country":"US",
    "sg:address":"7635 W Beloit Rd",
    "sg:city":"Milwaukee",
    "sg:classifiers":[
        {
            "category":"Personal",
            "subcategory":"Beauty Salon",
            "type":"Services"
        }
    ],
    "sg:phone":"+1 414 543 2280",
    "sg:postcode":"53219",
    "sg:province":"WI",
    "wof:name":"Honey Comb Coiffures",
    "wof:placetype":"venue"
},
  "geometry": {"coordinates":[-88.008162,42.996754],"type":"Point"}
}