{
  "type": "Feature",
  "properties": {
    "iso:country":"US",
    "sg:address":"730 W Main St",
    "sg:city":"Watertown",
    "sg:classifiers":[
        {
            "category":"Retail",
            "subcategory":"Repair Shop",
            "type":"Services"
        }
    ],
    "sg:phone":"+1 920 261 4310",
    "sg:postcode":"53094",
    "sg:province":"WI",
    "sg:tags":[
        "millwright",
        "welding"
    ],
    "wof:name":"Sterwald Rndall Wldg Fbrcation",
    "wof:placetype":"venue"
},
  "geometry": {"coordinates":[-88.734515,43.195522],"type":"Point"}
}