{
  "type": "Feature",
  "properties": {
    "iso:country":"US",
    "sg:address":"327 Beaupre St",
    "sg:city":"Green Bay",
    "sg:classifiers":[
        {
            "category":"Freight",
            "type":"Transportation"
        }
    ],
    "sg:phone":"+1 920 437 2547",
    "sg:postcode":"54301",
    "sg:province":"WI",
    "sg:tags":[
        "operator",
        "local",
        "trucking"
    ],
    "wof:name":"TS Trucking Inc",
    "wof:placetype":"venue"
},
  "geometry": {"coordinates":[-88.01403500000001,44.486911],"type":"Point"}
}