{
  "type": "Feature",
  "properties": {
    "iso:country":"US",
    "sg:address":"113 Teddy St",
    "sg:city":"Brooklyn",
    "sg:classifiers":[
        {
            "category":"Farming",
            "subcategory":"Farm",
            "type":"Manufacturing & Wholesale Goods"
        }
    ],
    "sg:phone":"+1 608 455 2072",
    "sg:postcode":"53521",
    "sg:province":"WI",
    "sg:tags":[
        "crop",
        "general"
    ],
    "wof:name":"D Family Farms LLC",
    "wof:placetype":"venue"
},
  "geometry": {"coordinates":[-89.363293,42.8552],"type":"Point"}
}