{
  "type": "Feature",
  "properties": {
    "iso:country":"US",
    "sg:address":"12677 N Neumaier Rd",
    "sg:city":"Hayward",
    "sg:classifiers":[
        {
            "category":"Manufacturing",
            "subcategory":"Glass & Minerals",
            "type":"Manufacturing & Wholesale Goods"
        }
    ],
    "sg:phone":"+1 715 462 3053",
    "sg:postcode":"54843",
    "sg:province":"WI",
    "sg:tags":[
        "refractory",
        "mfg"
    ],
    "wof:name":"Ceramic Factory",
    "wof:placetype":"venue"
},
  "geometry": {"coordinates":[-91.138674,46.083622],"type":"Point"}
}