{
  "type": "Feature",
  "properties": {
    "iso:country":"US",
    "sg:address":"320 Main St",
    "sg:city":"Racine",
    "sg:classifiers":[
        {
            "category":"Home & Garden",
            "subcategory":"Home Furnishings",
            "type":"Retail Goods"
        }
    ],
    "sg:phone":"+1 262 619 9234",
    "sg:postcode":"53403",
    "sg:province":"WI",
    "sg:website":"www.firedupracine.com",
    "wof:name":"Fired Up Racine Inc",
    "wof:placetype":"venue"
},
  "geometry": {"coordinates":[-87.783379,42.729592],"type":"Point"}
}