{
  "type": "Feature",
  "properties": {
    "iso:country":"US",
    "sg:address":"1050 Carey St",
    "sg:city":"Lake Geneva",
    "sg:phone":"+1 262 843 2221",
    "sg:postcode":"53147",
    "sg:province":"WI",
    "sg:tags":[
        "oil"
    ],
    "wof:name":"Swatek Sales Corp",
    "wof:placetype":"venue"
},
  "geometry": {"coordinates":[-88.444982,42.602614],"type":"Point"}
}