{
  "type": "Feature",
  "properties": {
    "iso:country":"US",
    "sg:address":"3558 Hillside Dr",
    "sg:city":"Delafield",
    "sg:classifiers":[
        {
            "category":"Manufacturing",
            "subcategory":"Food",
            "type":"Manufacturing & Wholesale Goods"
        }
    ],
    "sg:phone":"+1 262 646 7817",
    "sg:postcode":"53018",
    "sg:province":"WI",
    "sg:tags":[
        "product",
        "mfg"
    ],
    "wof:name":"Natural Ovens Bakery Inc",
    "wof:placetype":"venue"
},
  "geometry": {"coordinates":[-88.359948,43.049711],"type":"Point"}
}