{
  "type": "Feature",
  "properties": {
    "iso:country":"US",
    "sg:address":"3521 Mathey Rd",
    "sg:city":"Sturgeon Bay",
    "sg:classifiers":[
        {
            "category":"Retail",
            "subcategory":"Repair Shop",
            "type":"Services"
        }
    ],
    "sg:phone":"+1 920 743 1837",
    "sg:postcode":"54235",
    "sg:province":"WI",
    "wof:name":"Honest Engine Small Engin",
    "wof:placetype":"venue"
},
  "geometry": {"coordinates":[-87.31522,44.843724],"type":"Point"}
}