{
  "type": "Feature",
  "properties": {
    "addr:full":"5898 Woodland Dr Waunakee WI 53597",
    "addr:housenumber":"5898",
    "addr:postcode":"53597",
    "addr:street":"Woodland Dr",
    "iso:country":"US",
    "sg:address":"5898 Woodland Dr",
    "sg:city":"Waunakee",
    "sg:classifiers":[
        {
            "category":"Health Services",
            "subcategory":"Doctor",
            "type":"Services"
        }
    ],
    "sg:phone":"+1 608 849 4794",
    "sg:postcode":"53597",
    "sg:province":"WI",
    "sg:tags":[
        "dentist"
    ],
    "wof:name":"Paul T Magio DDS",
    "wof:placetype":"venue"
},
  "geometry": {"coordinates":[-89.447215,43.177443],"type":"Point"}
}