{
  "type": "Feature",
  "properties": {
    "addr:full":"300 E Mullett St Portage WI 53901",
    "addr:housenumber":"300",
    "addr:postcode":"53901",
    "addr:street":"E Mullett St",
    "iso:country":"US",
    "sg:address":"300 E Mullett St",
    "sg:city":"Portage",
    "sg:classifiers":[
        {
            "category":"Manufacturing",
            "subcategory":"Metals",
            "type":"Manufacturing & Wholesale Goods"
        }
    ],
    "sg:phone":"+1 608 742 2144",
    "sg:postcode":"53901",
    "sg:province":"WI",
    "sg:tags":[
        "secondary",
        "refining",
        "smelting"
    ],
    "wof:name":"Samuels Recycling Co",
    "wof:placetype":"venue"
},
  "geometry": {"coordinates":[-89.452184,43.541],"type":"Point"}
}