{
  "type": "Feature",
  "properties": {
    "addr:full":"8615 22nd Ave Kenosha WI 53143",
    "addr:housenumber":"8615",
    "addr:postcode":"53143",
    "addr:street":"22Nd Ave",
    "iso:country":"US",
    "sg:address":"8615 22nd Ave",
    "sg:city":"Kenosha",
    "sg:classifiers":[
        {
            "category":"Personal",
            "subcategory":"Adult",
            "type":"Services"
        }
    ],
    "sg:phone":"+1 262 697 1968",
    "sg:postcode":"53143",
    "sg:province":"WI",
    "wof:name":"Rays Movers",
    "wof:placetype":"venue"
},
  "geometry": {"coordinates":[-87.83485400000001,42.550899],"type":"Point"}
}