{
  "type": "Feature",
  "properties": {
    "iso:country":"US",
    "sg:address":"1374 S 113th St",
    "sg:city":"West Allis",
    "sg:classifiers":[
        {
            "category":"Banks & Credit Unions",
            "subcategory":"Investment Brokerage",
            "type":"Services"
        }
    ],
    "sg:phone":"+1 414 774 9422",
    "sg:postcode":"53214",
    "sg:province":"WI",
    "sg:tags":[
        "stock",
        "bond"
    ],
    "wof:name":"Edward Jones Co",
    "wof:placetype":"venue"
},
  "geometry": {"coordinates":[-88.053316,43.017779],"type":"Point"}
}