{
  "type": "Feature",
  "properties": {
    "iso:country":"US",
    "sg:address":"2900 N Meade St",
    "sg:city":"Appleton",
    "sg:classifiers":[
        {
            "category":"Banks & Credit Unions",
            "subcategory":"Investment Brokerage",
            "type":"Services"
        }
    ],
    "sg:phone":"+1 920 731 3840",
    "sg:postcode":"54911",
    "sg:province":"WI",
    "sg:tags":[
        "advisory"
    ],
    "wof:name":"Wayne D Sportsman",
    "wof:placetype":"venue"
},
  "geometry": {"coordinates":[-88.395675,44.290943],"type":"Point"}
}