{
  "type": "Feature",
  "properties": {
    "addr:full":"292 S Wisconsin St Whitewater WI 53190",
    "addr:housenumber":"292",
    "addr:postcode":"53190",
    "addr:street":"S Wisconsin St",
    "iso:country":"US",
    "sg:address":"292 S Wisconsin St",
    "sg:city":"Whitewater",
    "sg:classifiers":[
        {
            "category":"Organizations",
            "subcategory":"Membership Organization",
            "type":"Services"
        }
    ],
    "sg:phone":"+1 262 473 3321",
    "sg:postcode":"53190",
    "sg:province":"WI",
    "sg:tags":[
        "military",
        "veteran"
    ],
    "wof:name":"American Legion Post 173",
    "wof:placetype":"venue"
},
  "geometry": {"coordinates":[-88.726795,42.831133],"type":"Point"}
}