{
  "type": "Feature",
  "properties": {
    "addr:full":"3340 N 37th St Milwaukee WI 53216",
    "addr:housenumber":"3340",
    "addr:postcode":"53216",
    "addr:street":"N 37Th St",
    "iso:country":"US",
    "sg:address":"3340 N 37th St",
    "sg:city":"Milwaukee",
    "sg:classifiers":[
        {
            "category":"Building & Trades",
            "subcategory":"Cleaning & Sanitation",
            "type":"Services"
        }
    ],
    "sg:phone":"+1 866 489 4139",
    "sg:postcode":"53216",
    "sg:province":"WI",
    "sg:tags":[
        "house"
    ],
    "wof:name":"Classy Cleaning",
    "wof:placetype":"venue"
},
  "geometry": {"coordinates":[-87.959602,43.079899],"type":"Point"}
}