{
  "type": "Feature",
  "properties": {
    "addr:full":"422 Janet Ln Watertown WI 53094",
    "addr:housenumber":"422",
    "addr:postcode":"53094",
    "addr:street":"Janet Ln",
    "iso:country":"US",
    "sg:address":"422 Janet Ln",
    "sg:city":"Watertown",
    "sg:classifiers":[
        {
            "category":"Professional",
            "subcategory":"Business Services",
            "type":"Services"
        }
    ],
    "sg:phone":"+1 920 262 2534",
    "sg:postcode":"53094",
    "sg:province":"WI",
    "wof:name":"Detjen Enterprises Inc",
    "wof:placetype":"venue"
},
  "geometry": {"coordinates":[-88.708046,43.179654],"type":"Point"}
}