{
  "type": "Feature",
  "properties": {
    "addr:full":"1019 Truman St Kimberly WI 54136",
    "addr:housenumber":"1019",
    "addr:postcode":"54136",
    "addr:street":"Truman St",
    "iso:country":"US",
    "sg:address":"1019 Truman St",
    "sg:city":"Kimberly",
    "sg:classifiers":[
        {
            "category":"Real Estate",
            "subcategory":"Architect",
            "type":"Services"
        }
    ],
    "sg:phone":"+1 920 730 9200",
    "sg:postcode":"54136",
    "sg:province":"WI",
    "wof:name":"Birschbach & Assoc LTD",
    "wof:placetype":"venue"
},
  "geometry": {"coordinates":[-88.35008999999999,44.259394],"type":"Point"}
}