{
  "type": "Feature",
  "properties": {
    "iso:country":"US",
    "sg:address":"8311 W Bluemound Rd",
    "sg:city":"Wauwatosa",
    "sg:classifiers":[
        {
            "category":"Education",
            "subcategory":"Vocational School",
            "type":"Public Place"
        }
    ],
    "sg:phone":"+1 414 258 1646",
    "sg:postcode":"53213",
    "sg:province":"WI",
    "sg:tags":[
        "training",
        "computer"
    ],
    "sg:website":"www.mactraining.com",
    "wof:name":"Mactraining Enterprises",
    "wof:placetype":"venue"
},
  "geometry": {"coordinates":[-88.017305,43.035929],"type":"Point"}
}