{
  "type": "Feature",
  "properties": {
    "iso:country":"US",
    "sg:address":"4501 N 127th St",
    "sg:city":"Butler",
    "sg:classifiers":[
        {
            "category":"Manufacturing",
            "subcategory":"Metals",
            "type":"Manufacturing & Wholesale Goods"
        }
    ],
    "sg:phone":"+1 262 781 5568",
    "sg:postcode":"53007",
    "sg:province":"WI",
    "sg:tags":[
        "treating",
        "heat"
    ],
    "wof:name":"Advanced Metal Treating Inc",
    "wof:placetype":"venue"
},
  "geometry": {"coordinates":[-88.06961699999999,43.098908],"type":"Point"}
}