{
  "type": "Feature",
  "properties": {
    "iso:country":"US",
    "sg:address":"6011 S 27th St",
    "sg:city":"Milwaukee",
    "sg:classifiers":[
        {
            "category":"Health Services",
            "subcategory":"Chiropractor",
            "type":"Services"
        }
    ],
    "sg:phone":"+1 414 281 3101",
    "sg:postcode":"53221",
    "sg:province":"WI",
    "wof:name":"David Russell DC",
    "wof:placetype":"venue"
},
  "geometry": {"coordinates":[-87.949312,42.933949],"type":"Point"}
}