{
  "type": "Feature",
  "properties": {
    "iso:country":"US",
    "sg:address":"2455 Tremaine Rd",
    "sg:city":"Clinton",
    "sg:classifiers":[
        {
            "category":"Farming",
            "subcategory":"Dairy Farm",
            "type":"Manufacturing & Wholesale Goods"
        }
    ],
    "sg:phone":"+1 608 676 5139",
    "sg:postcode":"53525",
    "sg:province":"WI",
    "wof:name":"Malcolm Tremaine",
    "wof:placetype":"venue"
},
  "geometry": {"coordinates":[-88.771655,42.57648],"type":"Point"}
}