{
  "type": "Feature",
  "properties": {
    "addr:full":"605 N Holmen Dr Holmen WI 54636",
    "addr:housenumber":"605",
    "addr:postcode":"54636",
    "addr:street":"N Holmen Dr",
    "iso:country":"US",
    "sg:address":"605 N Holmen Dr",
    "sg:city":"Holmen",
    "sg:classifiers":[
        {
            "category":"Real Estate",
            "subcategory":"Real Estate Agent",
            "type":"Services"
        }
    ],
    "sg:phone":"+1 608 526 3344",
    "sg:postcode":"54636",
    "sg:province":"WI",
    "sg:website":"http://www.vikingrealty.us",
    "wof:name":"Viking Realty",
    "wof:placetype":"venue"
},
  "geometry": {"coordinates":[-91.263704,43.968446],"type":"Point"}
}