{
  "type": "Feature",
  "properties": {
    "iso:country":"US",
    "sg:address":"1760 American Dr",
    "sg:city":"Neenah",
    "sg:classifiers":[
        {
            "category":"Professional",
            "subcategory":"Engineering",
            "type":"Services"
        }
    ],
    "sg:phone":"+1 920 725 9009",
    "sg:postcode":"54956",
    "sg:province":"WI",
    "sg:tags":[
        "design"
    ],
    "sg:website":"www.accratec.com",
    "wof:name":"Accratec Engineering Inc",
    "wof:placetype":"venue"
},
  "geometry": {"coordinates":[-88.471276,44.222561],"type":"Point"}
}