{
  "type": "Feature",
  "properties": {
    "iso:country":"US",
    "sg:address":"685 N Bay Rd",
    "sg:city":"Somerset",
    "sg:classifiers":[
        {
            "category":"Building & Trades",
            "subcategory":"Construction",
            "type":"Services"
        }
    ],
    "sg:phone":"+1 715 247 3778",
    "sg:postcode":"54025",
    "sg:province":"WI",
    "sg:tags":[
        "contractor"
    ],
    "wof:name":"Erlitz Drywall",
    "wof:placetype":"venue"
},
  "geometry": {"coordinates":[-92.65906,45.076708],"type":"Point"}
}