{
  "type": "Feature",
  "properties": {
    "iso:country":"US",
    "sg:address":"418 E Grand Ave",
    "sg:city":"Beloit",
    "sg:classifiers":[
        {
            "category":"Professional",
            "subcategory":"Accounting & Tax Preparation",
            "type":"Services"
        }
    ],
    "sg:phone":"+1 608 365 3038",
    "sg:postcode":"53511",
    "sg:province":"IL",
    "sg:tags":[
        "bookkeeping",
        "return"
    ],
    "wof:name":"Jackson Tax Service",
    "wof:placetype":"venue"
},
  "geometry": {"coordinates":[-89.035238,42.499531],"type":"Point"}
}