{
  "type": "Feature",
  "properties": {
    "iso:country":"US",
    "sg:address":"77 W Park St",
    "sg:city":"Montello",
    "sg:classifiers":[
        {
            "category":"Health Services",
            "subcategory":"Clinic",
            "type":"Services"
        }
    ],
    "sg:phone":"+1 608 297 9151",
    "sg:postcode":"53949",
    "sg:province":"WI",
    "sg:tags":[
        "specialty",
        "outpatient"
    ],
    "wof:name":"Department Community Programs",
    "wof:placetype":"venue"
},
  "geometry": {"coordinates":[-89.329845,43.792886],"type":"Point"}
}