{
  "type": "Feature",
  "properties": {
    "addr:full":"110 Blackburn Ripon WI 54971",
    "addr:housenumber":"110",
    "addr:postcode":"54971",
    "addr:street":"Blackburn",
    "iso:country":"US",
    "sg:address":"110 Blackburn",
    "sg:city":"Ripon",
    "sg:classifiers":[
        {
            "category":"Home & Garden",
            "subcategory":"Household Appliances",
            "type":"Retail Goods"
        }
    ],
    "sg:phone":"+1 920 748 4866",
    "sg:postcode":"54971",
    "sg:province":"WI",
    "wof:name":"HI Tech Hydro",
    "wof:placetype":"venue"
},
  "geometry": {"coordinates":[-88.837108,43.845745],"type":"Point"}
}