{
  "type": "Feature",
  "properties": {
    "addr:full":"8298 Northern Rd Minocqua WI 54548",
    "addr:housenumber":"8298",
    "addr:postcode":"54548",
    "addr:street":"Northern Rd",
    "iso:country":"US",
    "sg:address":"8298 Northern Rd",
    "sg:city":"Minocqua",
    "sg:classifiers":[
        {
            "category":"Wholesale",
            "subcategory":"Electrical",
            "type":"Manufacturing & Wholesale Goods"
        }
    ],
    "sg:phone":"+1 715 588 7783",
    "sg:postcode":"54548",
    "sg:province":"WI",
    "sg:tags":[
        "high",
        "repair",
        "electronics"
    ],
    "wof:name":"Bontone Inc",
    "wof:placetype":"venue"
},
  "geometry": {"coordinates":[-89.720024,45.865381],"type":"Point"}
}