{
  "type": "Feature",
  "properties": {
    "iso:country":"US",
    "sg:address":"121 S Pinckney St",
    "sg:city":"Madison",
    "sg:classifiers":[
        {
            "category":"Real Estate",
            "subcategory":"Real Estate Agent",
            "type":"Services"
        }
    ],
    "sg:phone":"+1 608 256 8391",
    "sg:postcode":"53703",
    "sg:province":"WI",
    "sg:tags":[
        "appraiser"
    ],
    "wof:name":"United Real Estate Corp",
    "wof:placetype":"venue"
},
  "geometry": {"coordinates":[-89.381103,43.07418],"type":"Point"}
}