{
  "type": "Feature",
  "properties": {
    "iso:country":"US",
    "sg:address":"121 N 3rd St",
    "sg:city":"Barron",
    "sg:classifiers":[
        {
            "category":"Wholesale",
            "subcategory":"Farm Supplies",
            "type":"Manufacturing & Wholesale Goods"
        }
    ],
    "sg:phone":"+1 715 637 9030",
    "sg:postcode":"54812",
    "sg:province":"WI",
    "sg:tags":[
        "livestock"
    ],
    "wof:name":"Barron Sale Pavilion",
    "wof:placetype":"venue"
},
  "geometry": {"coordinates":[-91.854095,45.40282],"type":"Point"}
}