{
  "type": "Feature",
  "properties": {
    "addr:full":"515 Co Rd Jj Nekoosa WI 54457",
    "addr:housenumber":"515",
    "addr:postcode":"54457",
    "addr:street":"Co Rd",
    "iso:country":"US",
    "sg:address":"515 Co Rd Jj",
    "sg:city":"Nekoosa",
    "sg:classifiers":[
        {
            "category":"Building & Trades",
            "subcategory":"Electrical",
            "type":"Services"
        }
    ],
    "sg:phone":"+1 715 886 1927",
    "sg:postcode":"54457",
    "sg:province":"WI",
    "sg:tags":[
        "electric",
        "contractor"
    ],
    "wof:name":"J & D Pierce Elec Svc LLC",
    "wof:placetype":"venue"
},
  "geometry": {"coordinates":[-89.92434,44.27346],"type":"Point"}
}