{
  "type": "Feature",
  "properties": {
    "iso:country":"US",
    "sg:address":"7213 Co Rd H",
    "sg:city":"Camp Douglas",
    "sg:classifiers":[
        {
            "category":"Farming",
            "subcategory":"Dairy Farm",
            "type":"Manufacturing & Wholesale Goods"
        }
    ],
    "sg:phone":"+1 608 427 6435",
    "sg:postcode":"54618",
    "sg:province":"WI",
    "sg:tags":[
        "field",
        "corn",
        "crop"
    ],
    "wof:name":"Century Acres",
    "wof:placetype":"venue"
},
  "geometry": {"coordinates":[-90.261839,43.908807],"type":"Point"}
}