{
  "type": "Feature",
  "properties": {
    "iso:country":"US",
    "sg:address":"16900 W Bluemound Rd",
    "sg:city":"Brookfield",
    "sg:classifiers":[
        {
            "category":"Shopping",
            "subcategory":"Gifts & Souvenirs",
            "type":"Retail Goods"
        }
    ],
    "sg:phone":"+1 262 821 9640",
    "sg:postcode":"53005",
    "sg:province":"WI",
    "sg:tags":[
        "party",
        "supply"
    ],
    "wof:name":"Factory Card Outlet 140",
    "wof:placetype":"venue"
},
  "geometry": {"coordinates":[-88.121584,43.037055],"type":"Point"}
}