{
  "type": "Feature",
  "properties": {
    "iso:country":"US",
    "sg:address":"21035 Marsh Rd",
    "sg:city":"Chilton",
    "sg:classifiers":[
        {
            "category":"Building & Trades",
            "subcategory":"Construction",
            "type":"Services"
        }
    ],
    "sg:phone":"+1 920 772 4968",
    "sg:postcode":"53014",
    "sg:province":"WI",
    "sg:tags":[
        "excavation",
        "contractor"
    ],
    "wof:name":"Ross Excavating LLC",
    "wof:placetype":"venue"
},
  "geometry": {"coordinates":[-87.97892299999999,44.066273],"type":"Point"}
}