{
  "type": "Feature",
  "properties": {
    "iso:country":"US",
    "sg:address":"832 Niagara Ave",
    "sg:city":"Sheboygan",
    "sg:classifiers":[
        {
            "category":"Insurance",
            "subcategory":"Insurance Agent",
            "type":"Services"
        }
    ],
    "sg:phone":"+1 920 457 7781",
    "sg:postcode":"53081",
    "sg:province":"WI",
    "sg:website":"www.maritime-ins.com",
    "wof:name":"Maritime Insurance Group",
    "wof:placetype":"venue"
},
  "geometry": {"coordinates":[-87.713797,43.754238],"type":"Point"}
}