{
  "type": "Feature",
  "properties": {
    "addr:full":"8710 Ranchwood Dr Racine WI 53406",
    "addr:housenumber":"8710",
    "addr:postcode":"53406",
    "addr:street":"Ranchwood Dr",
    "iso:country":"US",
    "sg:address":"8710 Ranchwood Dr",
    "sg:city":"Racine",
    "sg:classifiers":[
        {
            "category":"Professional",
            "subcategory":"Computer Services",
            "type":"Services"
        }
    ],
    "sg:phone":"+1 262 886 1328",
    "sg:postcode":"53406",
    "sg:province":"WI",
    "sg:tags":[
        "business"
    ],
    "wof:name":"Amrose Enterprises Inc",
    "wof:placetype":"venue"
},
  "geometry": {"coordinates":[-87.89103900000001,42.732188],"type":"Point"}
}