{
  "type": "Feature",
  "properties": {
    "iso:country":"US",
    "sg:address":"1204 39th Ave",
    "sg:city":"Kenosha",
    "sg:classifiers":[
        {
            "category":"Building & Trades",
            "subcategory":"Construction",
            "type":"Services"
        }
    ],
    "sg:phone":"+1 262 551 0210",
    "sg:postcode":"53144",
    "sg:province":"WI",
    "sg:tags":[
        "house"
    ],
    "wof:name":"Willkomm Construction Inc",
    "wof:placetype":"venue"
},
  "geometry": {"coordinates":[-87.854978,42.638142],"type":"Point"}
}