{
  "type": "Feature",
  "properties": {
    "iso:country":"US",
    "sg:address":"8518 W Capitol Dr",
    "sg:city":"Milwaukee",
    "sg:classifiers":[
        {
            "category":"Professional",
            "subcategory":"Accounting & Tax Preparation",
            "type":"Services"
        }
    ],
    "sg:phone":"+1 414 438 0810",
    "sg:postcode":"53222",
    "sg:province":"WI",
    "sg:tags":[
        "payroll"
    ],
    "wof:name":"I H Svc Inc",
    "wof:placetype":"venue"
},
  "geometry": {"coordinates":[-88.019986,43.089873],"type":"Point"}
}