{
  "type": "Feature",
  "properties": {
    "iso:country":"US",
    "sg:address":"14935 Shamrock Ln",
    "sg:city":"Brookfield",
    "sg:classifiers":[
        {
            "category":"Professional",
            "subcategory":"Business Services",
            "type":"Services"
        }
    ],
    "sg:phone":"+1 262 781 1148",
    "sg:postcode":"53005",
    "sg:province":"WI",
    "wof:name":"Dnd Enterprises LLC",
    "wof:placetype":"venue"
},
  "geometry": {"coordinates":[-88.09818,43.096165],"type":"Point"}
}