{
  "type": "Feature",
  "properties": {
    "iso:country":"US",
    "sg:address":"141 Fenceline Dr",
    "sg:city":"Appleton",
    "sg:classifiers":[
        {
            "category":"Building & Trades",
            "subcategory":"Construction",
            "type":"Services"
        }
    ],
    "sg:phone":"+1 920 730 1005",
    "sg:postcode":"54915",
    "sg:province":"WI",
    "sg:tags":[
        "masonry",
        "contractor"
    ],
    "wof:name":"A Plus Masonry Inc",
    "wof:placetype":"venue"
},
  "geometry": {"coordinates":[-88.339265,44.244492],"type":"Point"}
}