{
  "type": "Feature",
  "properties": {
    "iso:country":"US",
    "sg:address":"13116 Reifs Mills Rd",
    "sg:city":"Whitelaw",
    "sg:classifiers":[
        {
            "category":"Building & Trades",
            "subcategory":"Construction",
            "type":"Services"
        }
    ],
    "sg:phone":"+1 920 732 3040",
    "sg:postcode":"54247",
    "sg:province":"WI",
    "sg:tags":[
        "house"
    ],
    "wof:name":"Dugan Builders",
    "wof:placetype":"venue"
},
  "geometry": {"coordinates":[-87.84850900000001,44.182251],"type":"Point"}
}