{
  "type": "Feature",
  "properties": {
    "iso:country":"US",
    "sg:address":"704 N Wildwood Ave",
    "sg:city":"Crandon",
    "sg:classifiers":[
        {
            "category":"Retail",
            "subcategory":"Repair Shop",
            "type":"Services"
        }
    ],
    "sg:phone":"+1 715 478 1238",
    "sg:postcode":"54520",
    "sg:province":"WI",
    "sg:tags":[
        "lock",
        "locksmith"
    ],
    "wof:name":"Short's Locksmith Shop",
    "wof:placetype":"venue"
},
  "geometry": {"coordinates":[-88.89953199999999,45.574288],"type":"Point"}
}