{
  "type": "Feature",
  "properties": {
    "addr:full":"14705 Braun Rd Sturtevant WI 53177",
    "addr:housenumber":"14705",
    "addr:postcode":"53177",
    "addr:street":"Braun Rd",
    "iso:country":"US",
    "sg:address":"14705 Braun Rd",
    "sg:city":"Sturtevant",
    "sg:classifiers":[
        {
            "category":"Freight",
            "type":"Transportation"
        },
        {
            "category":"Real Estate",
            "subcategory":"Developer",
            "type":"Services"
        }
    ],
    "sg:phone":"+1 262 878 4283",
    "sg:postcode":"53177",
    "sg:province":"WI",
    "sg:tags":[
        "cemetery",
        "trucking"
    ],
    "wof:name":"Cem Con Transport",
    "wof:placetype":"venue"
},
  "geometry": {"coordinates":[-87.967438,42.684159],"type":"Point"}
}