{
  "type": "Feature",
  "properties": {
    "iso:country":"US",
    "sg:address":"2163 Wegner Rd",
    "sg:city":"Merrill",
    "sg:classifiers":[
        {
            "category":"Farming",
            "subcategory":"Dairy Farm",
            "type":"Manufacturing & Wholesale Goods"
        }
    ],
    "sg:phone":"+1 715 536 2084",
    "sg:postcode":"54452",
    "sg:province":"WI",
    "wof:name":"Wendt North Woods Dairy Farm",
    "wof:placetype":"venue"
},
  "geometry": {"coordinates":[-89.920023,45.201515],"type":"Point"}
}