{
  "type": "Feature",
  "properties": {
    "iso:country":"US",
    "sg:address":"2604 16th Rd",
    "sg:city":"Mosinee",
    "sg:classifiers":[
        {
            "category":"Professional",
            "subcategory":"Art Services",
            "type":"Services"
        }
    ],
    "sg:phone":"+1 715 341 9801",
    "sg:postcode":"54455",
    "sg:province":"WI",
    "sg:tags":[
        "commercial",
        "design"
    ],
    "wof:name":"Screenmaster Graphics",
    "wof:placetype":"venue"
},
  "geometry": {"coordinates":[-89.597689,44.77536],"type":"Point"}
}