{
  "type": "Feature",
  "properties": {
    "addr:full":"237 River Pine Dr Shawano WI 54166",
    "addr:housenumber":"237",
    "addr:postcode":"54166",
    "addr:street":"River Pine Dr",
    "iso:country":"US",
    "sg:address":"237 River Pine Dr",
    "sg:city":"Shawano",
    "sg:classifiers":[
        {
            "category":"Building & Trades",
            "subcategory":"Landscaping Services",
            "type":"Services"
        }
    ],
    "sg:phone":"+1 715 526 1951",
    "sg:postcode":"54166",
    "sg:province":"WI",
    "sg:tags":[
        "landscape"
    ],
    "wof:name":"Northern Lghts Dvblpment Group",
    "wof:placetype":"venue"
},
  "geometry": {"coordinates":[-88.601906,44.789062],"type":"Point"}
}