{
  "type": "Feature",
  "properties": {
    "addr:full":"3610 N Oakland Ave Milwaukee WI 53211",
    "addr:housenumber":"3610",
    "addr:postcode":"53211",
    "addr:street":"N Oakland Ave",
    "iso:country":"US",
    "sg:address":"3610 N Oakland Ave",
    "sg:city":"Milwaukee",
    "sg:classifiers":[
        {
            "category":"Shopping",
            "subcategory":"Discount & Variety Stores",
            "type":"Retail Goods"
        }
    ],
    "sg:phone":"+1 715 372 5031",
    "sg:postcode":"53211",
    "sg:province":"WI",
    "sg:tags":[
        "post",
        "trading"
    ],
    "wof:name":"North Bay Trading Co",
    "wof:placetype":"venue"
},
  "geometry": {"coordinates":[-87.887507,43.084953],"type":"Point"}
}