{
  "type": "Feature",
  "properties": {
    "iso:country":"US",
    "sg:address":"4375 Stoney Ridge Trl",
    "sg:city":"Oshkosh",
    "sg:classifiers":[
        {
            "category":"Professional",
            "subcategory":"Business Services",
            "type":"Services"
        }
    ],
    "sg:phone":"+1 920 836 3875",
    "sg:postcode":"54904",
    "sg:province":"WI",
    "wof:name":"Stoney Ridge Interiors",
    "wof:placetype":"venue"
},
  "geometry": {"coordinates":[-88.619028,44.160791],"type":"Point"}
}