{
  "type": "Feature",
  "properties": {
    "addr:full":"8625 Co Rd Y Watertown WI 53094",
    "addr:housenumber":"8625",
    "addr:postcode":"53094",
    "addr:street":"Co Rd Y",
    "iso:country":"US",
    "sg:address":"8625 Co Rd Y",
    "sg:city":"Watertown",
    "sg:classifiers":[
        {
            "category":"Organizations",
            "subcategory":"Community Association",
            "type":"Services"
        }
    ],
    "sg:phone":"+1 920 261 7555",
    "sg:postcode":"53094",
    "sg:province":"WI",
    "sg:tags":[
        "club"
    ],
    "wof:name":"Watertown Outboarders Inc",
    "wof:placetype":"venue"
},
  "geometry": {"coordinates":[-88.74865200000001,43.159663],"type":"Point"}
}