{
  "type": "Feature",
  "properties": {
    "iso:country":"US",
    "sg:address":"114 N Avon Ave",
    "sg:city":"Phillips",
    "sg:classifiers":[
        {
            "category":"Banks & Credit Unions",
            "subcategory":"Bank",
            "type":"Services"
        }
    ],
    "sg:phone":"+1 715 339 3052",
    "sg:postcode":"54555",
    "sg:province":"WI",
    "sg:tags":[
        "federal"
    ],
    "wof:name":"Price Credit Union Hq",
    "wof:placetype":"venue"
},
  "geometry": {"coordinates":[-90.39869899999999,45.689555],"type":"Point"}
}