{
  "type": "Feature",
  "properties": {
    "iso:country":"US",
    "sg:address":"8123 State Hwy 57",
    "sg:city":"Baileys Harbor",
    "sg:classifiers":[
        {
            "category":"Restaurant",
            "type":"Food & Drink"
        }
    ],
    "sg:phone":"+1 920 839 9001",
    "sg:postcode":"54202",
    "sg:province":"WI",
    "wof:name":"Weisgerber's Cornerstone Pub",
    "wof:placetype":"venue"
},
  "geometry": {"coordinates":[-87.12367,45.064047],"type":"Point"}
}