{
  "type": "Feature",
  "properties": {
    "addr:full":"517 S Yellowstone Dr Madison WI 53719",
    "addr:housenumber":"517",
    "addr:postcode":"53719",
    "addr:street":"S Yellowstone Dr",
    "iso:country":"US",
    "sg:address":"517 S Yellowstone Dr",
    "sg:city":"Madison",
    "sg:classifiers":[
        {
            "category":"Retail",
            "subcategory":"Auto Repair",
            "type":"Services"
        }
    ],
    "sg:phone":"+1 608 833 0734",
    "sg:postcode":"53719",
    "sg:province":"WI",
    "sg:tags":[
        "repairing",
        "automobile"
    ],
    "wof:name":"Odana Tire & Svc Ctr",
    "wof:placetype":"venue"
},
  "geometry": {"coordinates":[-89.492716,43.056461],"type":"Point"}
}