{
  "type": "Feature",
  "properties": {
    "iso:country":"US",
    "sg:address":"1327 Union Ave",
    "sg:city":"Sheboygan",
    "sg:classifiers":[
        {
            "category":"Building & Trades",
            "subcategory":"Plumbing",
            "type":"Services"
        }
    ],
    "sg:phone":"+1 920 458 2220",
    "sg:postcode":"53081",
    "sg:province":"WI",
    "sg:tags":[
        "heating",
        "contractor"
    ],
    "wof:name":"Vans Heating & Air Cond Inc",
    "wof:placetype":"venue"
},
  "geometry": {"coordinates":[-87.72348100000001,43.732056],"type":"Point"}
}