{
  "type": "Feature",
  "properties": {
    "iso:country":"US",
    "sg:address":"17198 54th Ave",
    "sg:city":"Chippewa Falls",
    "sg:classifiers":[
        {
            "category":"Professional",
            "subcategory":"Art Services",
            "type":"Services"
        }
    ],
    "sg:phone":"+1 715 723 1636",
    "sg:postcode":"54729",
    "sg:province":"WI",
    "sg:tags":[
        "commercial",
        "photography",
        "design"
    ],
    "wof:name":"Blomlie Photography",
    "wof:placetype":"venue"
},
  "geometry": {"coordinates":[-91.323647,44.921242],"type":"Point"}
}