{
  "type": "Feature",
  "properties": {
    "iso:country":"US",
    "sg:address":"1946 Hochheim Rd",
    "sg:city":"Mayville",
    "sg:classifiers":[
        {
            "category":"Farming",
            "subcategory":"Dairy Farm",
            "type":"Manufacturing & Wholesale Goods"
        }
    ],
    "sg:phone":"+1 920 387 2058",
    "sg:postcode":"53050",
    "sg:province":"WI",
    "sg:tags":[
        "corn"
    ],
    "wof:name":"Gods Great Acres",
    "wof:placetype":"venue"
},
  "geometry": {"coordinates":[-88.487432,43.456868],"type":"Point"}
}