{
  "type": "Feature",
  "properties": {
    "addr:full":"2891 S Olson Rd West Salem WI 54669",
    "addr:housenumber":"2891",
    "addr:postcode":"54669",
    "addr:street":"S Olson Rd",
    "iso:country":"US",
    "sg:address":"2891 S Olson Rd",
    "sg:city":"West Salem",
    "sg:classifiers":[
        {
            "category":"Home & Garden",
            "subcategory":"Garden Supply",
            "type":"Retail Goods"
        }
    ],
    "sg:phone":"+1 608 786 1542",
    "sg:postcode":"54669",
    "sg:province":"WI",
    "wof:name":"Labus Tree Farms",
    "wof:placetype":"venue"
},
  "geometry": {"coordinates":[-91.05371700000001,43.969747],"type":"Point"}
}