{
  "type": "Feature",
  "properties": {
    "iso:country":"US",
    "sg:address":"17946 Elm Rd",
    "sg:city":"Hillsboro",
    "sg:classifiers":[
        {
            "category":"Farming",
            "subcategory":"Livestock Farm",
            "type":"Manufacturing & Wholesale Goods"
        }
    ],
    "sg:phone":"+1 608 489 2847",
    "sg:postcode":"54634",
    "sg:province":"WI",
    "sg:tags":[
        "beef",
        "feedlot",
        "cattle"
    ],
    "wof:name":"Rocking E Ranch",
    "wof:placetype":"venue"
},
  "geometry": {"coordinates":[-90.359728,43.681698],"type":"Point"}
}