{
  "type": "Feature",
  "properties": {
    "iso:country":"US",
    "sg:address":"3026 State Hwy 145",
    "sg:city":"Richfield",
    "sg:classifiers":[
        {
            "category":"Manufacturing",
            "subcategory":"Tools & Machinery",
            "type":"Manufacturing & Wholesale Goods"
        }
    ],
    "sg:phone":"+1 262 677 8155",
    "sg:postcode":"53076",
    "sg:province":"WI",
    "sg:tags":[
        "machine",
        "shop",
        "job"
    ],
    "wof:name":"Carlson Manufacturing Co",
    "wof:placetype":"venue"
},
  "geometry": {"coordinates":[-88.18729999999999,43.283902],"type":"Point"}
}