{
  "type": "Feature",
  "properties": {
    "iso:country":"US",
    "sg:address":"215 Middle St",
    "sg:city":"Muscoda",
    "sg:classifiers":[
        {
            "category":"Farming",
            "subcategory":"Nursery",
            "type":"Manufacturing & Wholesale Goods"
        }
    ],
    "sg:phone":"+1 608 739 3625",
    "sg:postcode":"53573",
    "sg:province":"WI",
    "sg:tags":[
        "ornamental",
        "greenhouse"
    ],
    "wof:name":"Hidden Valley Green House",
    "wof:placetype":"venue"
},
  "geometry": {"coordinates":[-90.422871,43.182422],"type":"Point"}
}