{
  "type": "Feature",
  "properties": {
    "iso:country":"US",
    "sg:address":"326 Country Walk Ln",
    "sg:city":"Sister Bay",
    "sg:classifiers":[
        {
            "category":"Restaurant",
            "type":"Food & Drink"
        }
    ],
    "sg:phone":"+1 920 854 7050",
    "sg:postcode":"54234",
    "sg:province":"WI",
    "wof:name":"Village Wok",
    "wof:placetype":"venue"
},
  "geometry": {"coordinates":[-87.127311,45.18341],"type":"Point"}
}