{
  "type": "Feature",
  "properties": {
    "iso:country":"US",
    "sg:address":"2687 State Hwy 114",
    "sg:city":"Hilbert",
    "sg:classifiers":[
        {
            "category":"Building & Trades",
            "subcategory":"Construction",
            "type":"Services"
        }
    ],
    "sg:phone":"+1 920 853 3812",
    "sg:postcode":"54129",
    "sg:province":"WI",
    "sg:tags":[
        "general",
        "contractor"
    ],
    "wof:name":"Woodville Contractors Inc",
    "wof:placetype":"venue"
},
  "geometry": {"coordinates":[-88.17324600000001,44.140005],"type":"Point"}
}