{
  "type": "Feature",
  "properties": {
    "iso:country":"US",
    "sg:address":"120 E Main St",
    "sg:city":"Sun Prairie",
    "sg:classifiers":[
        {
            "category":"Food & Beverages",
            "subcategory":"Liquor & Beverages",
            "type":"Retail Goods"
        }
    ],
    "sg:phone":"+1 608 837 6600",
    "sg:postcode":"53590",
    "sg:province":"WI",
    "wof:name":"Dean's Downtown Liquor",
    "wof:placetype":"venue"
},
  "geometry": {"coordinates":[-89.2135,43.183376],"type":"Point"}
}