{
  "type": "Feature",
  "properties": {
    "addr:full":"16260 W Heatherly Dr New Berlin WI 53151",
    "addr:housenumber":"16260",
    "addr:postcode":"53151",
    "addr:street":"W Heatherly Dr",
    "iso:country":"US",
    "sg:address":"16260 W Heatherly Dr",
    "sg:city":"New Berlin",
    "sg:classifiers":[
        {
            "category":"Professional",
            "type":"Services"
        }
    ],
    "sg:phone":"+1 262 785 1951",
    "sg:postcode":"53151",
    "sg:province":"WI",
    "wof:name":"R & J Yoblin",
    "wof:placetype":"venue"
},
  "geometry": {"coordinates":[-88.117431,42.966498],"type":"Point"}
}