{
  "type": "Feature",
  "properties": {
    "addr:full":"9372 Rocky Run Rd Milladore WI 54454",
    "addr:housenumber":"9372",
    "addr:postcode":"54454",
    "addr:street":"Rocky Run Rd",
    "iso:country":"US",
    "sg:address":"9372 Rocky Run Rd",
    "sg:city":"Milladore",
    "sg:classifiers":[
        {
            "category":"Building & Trades",
            "subcategory":"Construction",
            "type":"Services"
        }
    ],
    "sg:phone":"+1 715 652 3323",
    "sg:postcode":"54454",
    "sg:province":"WI",
    "sg:tags":[
        "house"
    ],
    "wof:name":"Leibl Const",
    "wof:placetype":"venue"
},
  "geometry": {"coordinates":[-89.89576700000001,44.586761],"type":"Point"}
}