{
  "type": "Feature",
  "properties": {
    "iso:country":"US",
    "sg:address":"221 S Scott St",
    "sg:city":"Wautoma",
    "sg:classifiers":[
        {
            "category":"Professional",
            "subcategory":"Lawyer & Legal Services",
            "type":"Services"
        }
    ],
    "sg:phone":"+1 920 787 3515",
    "sg:postcode":"54982",
    "sg:province":"WI",
    "sg:tags":[
        "attorney"
    ],
    "wof:name":"Olson Law Office",
    "wof:placetype":"venue"
},
  "geometry": {"coordinates":[-89.28926,44.073783],"type":"Point"}
}