{
  "type": "Feature",
  "properties": {
    "iso:country":"US",
    "sg:address":"1021 Ashwood Dr",
    "sg:city":"Plover",
    "sg:classifiers":[
        {
            "category":"Shopping",
            "subcategory":"Bicycles & Sporting Goods",
            "type":"Retail Goods"
        }
    ],
    "sg:phone":"+1 715 341 2946",
    "sg:postcode":"54467",
    "sg:province":"WI",
    "wof:name":"Plover Gun Shop",
    "wof:placetype":"venue"
},
  "geometry": {"coordinates":[-89.53415200000001,44.481403],"type":"Point"}
}