{
  "type": "Feature",
  "properties": {
    "iso:country":"US",
    "sg:address":"4941 Town Hall Rd",
    "sg:city":"Delavan",
    "sg:classifiers":[
        {
            "category":"Building & Trades",
            "subcategory":"Construction",
            "type":"Services"
        }
    ],
    "sg:phone":"+1 262 728 5148",
    "sg:postcode":"53115",
    "sg:province":"WI",
    "sg:tags":[
        "water",
        "line",
        "sewer",
        "contractor"
    ],
    "wof:name":"Odling Construction Inc",
    "wof:placetype":"venue"
},
  "geometry": {"coordinates":[-88.56885800000001,42.619043],"type":"Point"}
}