{
  "type": "Feature",
  "properties": {
    "iso:country":"US",
    "sg:address":"550 Water St",
    "sg:city":"Prairie Du Sac",
    "sg:classifiers":[
        {
            "category":"Restaurant",
            "type":"Food & Drink"
        }
    ],
    "sg:phone":"+1 608 643 0837",
    "sg:postcode":"53578",
    "sg:province":"WI",
    "sg:tags":[
        "eating"
    ],
    "sg:website":"www.culvers.com",
    "wof:name":"Blue Spoon Creamery Cafe",
    "wof:placetype":"venue"
},
  "geometry": {"coordinates":[-89.719598,43.289642],"type":"Point"}
}