{
  "type": "Feature",
  "properties": {
    "iso:country":"US",
    "sg:address":"834 Park Ave",
    "sg:city":"Beaver Dam",
    "sg:classifiers":[
        {
            "category":"Social Services",
            "type":"Services"
        }
    ],
    "sg:phone":"+1 920 382 3535",
    "sg:postcode":"53916",
    "sg:province":"WI",
    "sg:tags":[
        "organization",
        "welfare"
    ],
    "wof:name":"CAEMPPF",
    "wof:placetype":"venue"
},
  "geometry": {"coordinates":[-88.821448,43.456248],"type":"Point"}
}