{
  "type": "Feature",
  "properties": {
    "iso:country":"US",
    "sg:address":"2165 State Hwy 95",
    "sg:city":"Neillsville",
    "sg:classifiers":[
        {
            "category":"Manufacturing",
            "subcategory":"Signs",
            "type":"Manufacturing & Wholesale Goods"
        }
    ],
    "sg:phone":"+1 715 743 6129",
    "sg:postcode":"54456",
    "sg:province":"WI",
    "sg:tags":[
        "specialty",
        "mfg"
    ],
    "wof:name":"Action Industries",
    "wof:placetype":"venue"
},
  "geometry": {"coordinates":[-90.599017,44.504922],"type":"Point"}
}