{
  "type": "Feature",
  "properties": {
    "iso:country":"US",
    "sg:address":"8901 Lake Dr",
    "sg:city":"East Troy",
    "sg:classifiers":[
        {
            "category":"Social Services",
            "type":"Services"
        }
    ],
    "sg:phone":"+1 262 642 7466",
    "sg:postcode":"53120",
    "sg:province":"WI",
    "sg:tags":[
        "organization",
        "welfare"
    ],
    "sg:website":"www.campedwards.org",
    "wof:name":"Camp Edwards Ymca",
    "wof:placetype":"venue"
},
  "geometry": {"coordinates":[-88.51278499999999,42.815799],"type":"Point"}
}