{
  "type": "Feature",
  "properties": {
    "addr:full":"407 Franzen St Random Lake WI 53075",
    "addr:housenumber":"407",
    "addr:postcode":"53075",
    "addr:street":"Franzen St",
    "iso:country":"US",
    "sg:address":"407 Franzen St",
    "sg:city":"Random Lake",
    "sg:classifiers":[
        {
            "category":"Autos & Motor Vehicles",
            "subcategory":"Automobile Sales",
            "type":"Retail Goods"
        }
    ],
    "sg:phone":"+1 920 994 2138",
    "sg:postcode":"53075",
    "sg:province":"WI",
    "wof:name":"Random Recreational Inc",
    "wof:placetype":"venue"
},
  "geometry": {"coordinates":[-87.959739,43.553037],"type":"Point"}
}