{
  "type": "Feature",
  "properties": {
    "iso:country":"US",
    "sg:address":"6521 Tower Ave",
    "sg:city":"Superior",
    "sg:classifiers":[
        {
            "category":"Building & Trades",
            "subcategory":"Construction",
            "type":"Services"
        }
    ],
    "sg:phone":"+1 715 394 4815",
    "sg:postcode":"54880",
    "sg:province":"WI",
    "sg:tags":[
        "excavating",
        "contractor"
    ],
    "wof:name":"Udeen Trucking Inc",
    "wof:placetype":"venue"
},
  "geometry": {"coordinates":[-92.104426,46.65981],"type":"Point"}
}