{
  "type": "Feature",
  "properties": {
    "iso:country":"US",
    "sg:address":"300 N Van Buren St",
    "sg:city":"Milwaukee",
    "sg:classifiers":[
        {
            "category":"Real Estate",
            "subcategory":"Real Estate Services",
            "type":"Services"
        },
        {
            "category":"Real Estate",
            "subcategory":"Real Estate Agent",
            "type":"Services"
        }
    ],
    "sg:phone":"+1 414 221 0000",
    "sg:postcode":"53202",
    "sg:province":"WI",
    "sg:tags":[
        "buyer",
        "broker"
    ],
    "wof:name":"Raettig Real Estate",
    "wof:placetype":"venue"
},
  "geometry": {"coordinates":[-87.90220600000001,43.034168],"type":"Point"}
}