{
  "type": "Feature",
  "properties": {
    "iso:country":"US",
    "sg:address":"1500 River Pines Dr",
    "sg:city":"Green Bay",
    "sg:classifiers":[
        {
            "category":"Real Estate",
            "subcategory":"Real Estate Agent",
            "type":"Services"
        }
    ],
    "sg:phone":"+1 920 469 5434",
    "sg:postcode":"54311",
    "sg:province":"WI",
    "wof:name":"Macewen LLC",
    "wof:placetype":"venue"
},
  "geometry": {"coordinates":[-88.006187,44.470963],"type":"Point"}
}