{
  "type": "Feature",
  "properties": {
    "addr:full":"1214 Washington Ave Cedarburg WI 53012",
    "addr:housenumber":"1214",
    "addr:postcode":"53012",
    "addr:street":"Washington Ave",
    "iso:country":"US",
    "sg:address":"1214 Washington Ave",
    "sg:city":"Cedarburg",
    "sg:classifiers":[
        {
            "category":"Home & Garden",
            "subcategory":"Hardware",
            "type":"Retail Goods"
        },
        {
            "category":"Utilities",
            "subcategory":"Cable",
            "type":"Services"
        }
    ],
    "sg:phone":"+1 262 375 4780",
    "sg:postcode":"53012",
    "sg:province":"WI",
    "sg:tags":[
        "cable-non-electric",
        "wire",
        "store",
        "cable-electric"
    ],
    "wof:name":"Classic Connection USA Inc",
    "wof:placetype":"venue"
},
  "geometry": {"coordinates":[-88.002706,43.318193],"type":"Point"}
}