{
  "type": "Feature",
  "properties": {
    "iso:country":"US",
    "sg:address":"100 S Water St",
    "sg:city":"Sparta",
    "sg:classifiers":[
        {
            "category":"Professional",
            "subcategory":"Business Services",
            "type":"Services"
        }
    ],
    "sg:phone":"+1 608 269 1100",
    "sg:postcode":"54656",
    "sg:province":"WI",
    "sg:tags":[
        "appraiser"
    ],
    "wof:name":"Hemstock Appraisal Svc",
    "wof:placetype":"venue"
},
  "geometry": {"coordinates":[-90.81089,43.944393],"type":"Point"}
}