{
  "type": "Feature",
  "properties": {
    "addr:full":"7059 Fern Rd Oxford WI 53952",
    "addr:housenumber":"7059",
    "addr:postcode":"53952",
    "addr:street":"Fern Rd",
    "iso:country":"US",
    "sg:address":"7059 Fern Rd",
    "sg:city":"Oxford",
    "sg:classifiers":[
        {
            "category":"Building & Trades",
            "subcategory":"Construction",
            "type":"Services"
        }
    ],
    "sg:phone":"+1 608 586 4775",
    "sg:postcode":"53952",
    "sg:province":"WI",
    "sg:tags":[
        "house"
    ],
    "wof:name":"Duncan Building & Remodeling",
    "wof:placetype":"venue"
},
  "geometry": {"coordinates":[-89.501428,43.795865],"type":"Point"}
}