{
  "type": "Feature",
  "properties": {
    "iso:country":"US",
    "sg:address":"321 Maple Ln",
    "sg:city":"Coleman",
    "sg:classifiers":[
        {
            "category":"Retail",
            "subcategory":"Laundry & Dry Cleaning",
            "type":"Services"
        }
    ],
    "sg:phone":"+1 920 897 2157",
    "sg:postcode":"54112",
    "sg:province":"WI",
    "sg:tags":[
        "plant"
    ],
    "wof:name":"CMM Dry Cleaning Inc",
    "wof:placetype":"venue"
},
  "geometry": {"coordinates":[-88.028093,45.068215],"type":"Point"}
}