{
  "type": "Feature",
  "properties": {
    "iso:country":"US",
    "sg:address":"4757 N 125th St",
    "sg:city":"Butler",
    "sg:classifiers":[
        {
            "category":"Home & Garden",
            "subcategory":"Furniture",
            "type":"Retail Goods"
        }
    ],
    "sg:phone":"+1 262 781 1003",
    "sg:postcode":"53007",
    "sg:province":"WI",
    "sg:tags":[
        "top",
        "counter"
    ],
    "wof:name":"B & G Designs",
    "wof:placetype":"venue"
},
  "geometry": {"coordinates":[-88.067347,43.104554],"type":"Point"}
}