{
  "type": "Feature",
  "properties": {
    "iso:country":"US",
    "sg:address":"369 N Pioneer Rd",
    "sg:city":"Fond Du Lac",
    "sg:classifiers":[
        {
            "category":"Building & Trades",
            "subcategory":"Construction",
            "type":"Services"
        }
    ],
    "sg:phone":"+1 920 922 9447",
    "sg:postcode":"54935",
    "sg:province":"WI",
    "sg:tags":[
        "house"
    ],
    "wof:name":"Winfield Construction",
    "wof:placetype":"venue"
},
  "geometry": {"coordinates":[-88.481843,43.79038],"type":"Point"}
}