{
  "type": "Feature",
  "properties": {
    "iso:country":"US",
    "sg:address":"18655 State Hwy 131",
    "sg:city":"Tomah",
    "sg:classifiers":[
        {
            "category":"Freight",
            "type":"Transportation"
        }
    ],
    "sg:phone":"+1 608 372 9376",
    "sg:postcode":"54660",
    "sg:province":"WI",
    "sg:tags":[
        "commercial",
        "storage"
    ],
    "wof:name":"A-1 Stow Away Mini Storage",
    "wof:placetype":"venue"
},
  "geometry": {"coordinates":[-90.495261,43.917676],"type":"Point"}
}