{
  "type": "Feature",
  "properties": {
    "addr:full":"103 S Main St Mayville WI 53050",
    "addr:housenumber":"103",
    "addr:postcode":"53050",
    "addr:street":"S Main St",
    "iso:country":"US",
    "sg:address":"103 S Main St",
    "sg:city":"Mayville",
    "sg:classifiers":[
        {
            "category":"Retail",
            "subcategory":"Animal Services",
            "type":"Services"
        }
    ],
    "sg:phone":"+1 920 387 3236",
    "sg:postcode":"53050",
    "sg:province":"WI",
    "wof:name":"Tailored Tails Pet Grooming",
    "wof:placetype":"venue"
},
  "geometry": {"coordinates":[-88.544178,43.494323],"type":"Point"}
}