{
  "type": "Feature",
  "properties": {
    "iso:country":"US",
    "sg:address":"235 N Stevens St",
    "sg:city":"Rhinelander",
    "sg:classifiers":[
        {
            "category":"Organizations",
            "subcategory":"Religious Organization",
            "type":"Services"
        }
    ],
    "sg:phone":"+1 715 362 4258",
    "sg:postcode":"54501",
    "sg:province":"WI",
    "wof:name":"Trinty Evang Luthern Church",
    "wof:placetype":"venue"
},
  "geometry": {"coordinates":[-89.411366,45.640873],"type":"Point"}
}