{
  "type": "Feature",
  "properties": {
    "iso:country":"US",
    "sg:address":"3 Oconto Ct",
    "sg:city":"Madison",
    "sg:classifiers":[
        {
            "category":"Real Estate",
            "subcategory":"Real Estate Operator",
            "type":"Services"
        }
    ],
    "sg:phone":"+1 608 233 2176",
    "sg:postcode":"53705",
    "sg:province":"WI",
    "sg:tags":[
        "building",
        "apartment"
    ],
    "wof:name":"Cooper Apartments",
    "wof:placetype":"venue"
},
  "geometry": {"coordinates":[-89.454538,43.064239],"type":"Point"}
}