{
  "type": "Feature",
  "properties": {
    "addr:full":"1312 Belknap St Superior WI 54880",
    "addr:housenumber":"1312",
    "addr:postcode":"54880",
    "addr:street":"Belknap St",
    "iso:country":"US",
    "sg:address":"1312 Belknap St",
    "sg:city":"Superior",
    "sg:classifiers":[
        {
            "category":"Shopping",
            "subcategory":"Used Merchandise",
            "type":"Retail Goods"
        },
        {
            "category":"Professional",
            "subcategory":"Computer Services",
            "type":"Services"
        }
    ],
    "sg:phone":"+1 715 392 6115",
    "sg:postcode":"54880",
    "sg:province":"WI",
    "sg:tags":[
        "repair",
        "datum"
    ],
    "wof:name":"Elite Computers",
    "wof:placetype":"venue"
},
  "geometry": {"coordinates":[-92.09777099999999,46.720588],"type":"Point"}
}