{
  "type": "Feature",
  "properties": {
    "iso:country":"US",
    "sg:address":"18270 Taywood Cir",
    "sg:city":"Brookfield",
    "sg:classifiers":[
        {
            "category":"Building & Trades",
            "subcategory":"Construction",
            "type":"Services"
        }
    ],
    "sg:phone":"+1 262 794 0279",
    "sg:postcode":"53045",
    "sg:province":"WI",
    "sg:tags":[
        "house"
    ],
    "wof:name":"Serenity Homes",
    "wof:placetype":"venue"
},
  "geometry": {"coordinates":[-88.140323,43.040769],"type":"Point"}
}