{
  "type": "Feature",
  "properties": {
    "iso:country":"US",
    "sg:address":"24806 Columbus St",
    "sg:city":"Kansasville",
    "sg:classifiers":[
        {
            "category":"Professional",
            "subcategory":"Business Services",
            "type":"Services"
        }
    ],
    "sg:phone":"+1 262 878 4714",
    "sg:postcode":"53139",
    "sg:province":"WI",
    "wof:name":"Dlh Enterprises",
    "wof:placetype":"venue"
},
  "geometry": {"coordinates":[-88.136067,42.697441],"type":"Point"}
}