{
  "type": "Feature",
  "properties": {
    "iso:country":"US",
    "sg:address":"2460 Milwaukee Rd",
    "sg:city":"Beloit",
    "sg:classifiers":[
        {
            "category":"Education",
            "subcategory":"Preschool",
            "type":"Public Place"
        }
    ],
    "sg:phone":"+1 608 728 2391",
    "sg:postcode":"53511",
    "sg:province":"WI",
    "sg:tags":[
        "kindergarten"
    ],
    "wof:name":"Kidzworks Pre-School",
    "wof:placetype":"venue"
},
  "geometry": {"coordinates":[-88.995936,42.51935],"type":"Point"}
}