{
  "type": "Feature",
  "properties": {
    "iso:country":"US",
    "sg:address":"1700 East Rd",
    "sg:city":"Waupaca",
    "sg:classifiers":[
        {
            "category":"Manufacturing",
            "subcategory":"Printing",
            "type":"Manufacturing & Wholesale Goods"
        }
    ],
    "sg:phone":"+1 715 256 1917",
    "sg:postcode":"54981",
    "sg:province":"WI",
    "sg:tags":[
        "lithographic",
        "commercial"
    ],
    "wof:name":"Denny S Print Shop",
    "wof:placetype":"venue"
},
  "geometry": {"coordinates":[-89.112759,44.299551],"type":"Point"}
}