{
  "type": "Feature",
  "properties": {
    "iso:country":"US",
    "sg:address":"542 Lester Ave",
    "sg:city":"Onalaska",
    "sg:classifiers":[
        {
            "category":"Home & Garden",
            "subcategory":"Building Materials",
            "type":"Retail Goods"
        }
    ],
    "sg:phone":"+1 608 783 6925",
    "sg:postcode":"54650",
    "sg:province":"WI",
    "sg:tags":[
        "paint"
    ],
    "wof:name":"A & C Johnson Paint Inc",
    "wof:placetype":"venue"
},
  "geometry": {"coordinates":[-91.197852,43.875794],"type":"Point"}
}