{
  "type": "Feature",
  "properties": {
    "iso:country":"US",
    "sg:address":"206 Tara Dr",
    "sg:city":"Tomah",
    "sg:classifiers":[
        {
            "category":"Building & Trades",
            "subcategory":"Construction",
            "type":"Services"
        }
    ],
    "sg:phone":"+1 608 374 4330",
    "sg:postcode":"54660",
    "sg:province":"WI",
    "sg:tags":[
        "general",
        "contractor"
    ],
    "wof:name":"Built Rite LLC",
    "wof:placetype":"venue"
},
  "geometry": {"coordinates":[-90.385577,43.960231],"type":"Point"}
}