{
  "type": "Feature",
  "properties": {
    "iso:country":"US",
    "sg:address":"1530 State Hwy 155",
    "sg:city":"St Germain",
    "sg:classifiers":[
        {
            "category":"Building & Trades",
            "subcategory":"Construction",
            "type":"Services"
        }
    ],
    "sg:phone":"+1 715 542 4663",
    "sg:postcode":"54558",
    "sg:province":"WI",
    "sg:tags":[
        "general",
        "contractor"
    ],
    "wof:name":"Resortland Homes",
    "wof:placetype":"venue"
},
  "geometry": {"coordinates":[-89.487419,45.922251],"type":"Point"}
}