{
  "type": "Feature",
  "properties": {
    "iso:country":"US",
    "sg:address":"1517 N Ashland Ave",
    "sg:city":"De Pere",
    "sg:classifiers":[
        {
            "category":"Building & Trades",
            "subcategory":"Construction",
            "type":"Services"
        }
    ],
    "sg:phone":"+1 920 983 0230",
    "sg:postcode":"54115",
    "sg:province":"WI",
    "sg:tags":[
        "builder",
        "patio",
        "deck"
    ],
    "wof:name":"Valley Plastic Decking Supply",
    "wof:placetype":"venue"
},
  "geometry": {"coordinates":[-88.074994,44.458583],"type":"Point"}
}