{
  "type": "Feature",
  "properties": {
    "iso:country":"US",
    "sg:address":"13671 199th St",
    "sg:city":"Jim Falls",
    "sg:classifiers":[
        {
            "category":"Shopping",
            "subcategory":"Bicycles & Sporting Goods",
            "type":"Retail Goods"
        }
    ],
    "sg:phone":"+1 715 382 5235",
    "sg:postcode":"54748",
    "sg:province":"WI",
    "wof:name":"KSH Outdoors Inc",
    "wof:placetype":"venue"
},
  "geometry": {"coordinates":[-91.27234799999999,45.043171],"type":"Point"}
}