{
  "type": "Feature",
  "properties": {
    "iso:country":"US",
    "sg:address":"1814 Granville Rd",
    "sg:city":"Cedarburg",
    "sg:classifiers":[
        {
            "category":"Restaurant",
            "type":"Food & Drink"
        }
    ],
    "sg:phone":"+1 262 377 8010",
    "sg:postcode":"53012",
    "sg:province":"WI",
    "wof:name":"Country Keg",
    "wof:placetype":"venue"
},
  "geometry": {"coordinates":[-88.044715,43.341343],"type":"Point"}
}