{
  "type": "Feature",
  "properties": {
    "iso:country":"US",
    "sg:address":"828 S 1st St",
    "sg:city":"Milwaukee",
    "sg:classifiers":[
        {
            "category":"Professional",
            "type":"Services"
        }
    ],
    "sg:phone":"+1 414 383 6300",
    "sg:postcode":"53204",
    "sg:province":"WI",
    "wof:name":"Zarate No 1 LLC",
    "wof:placetype":"venue"
},
  "geometry": {"coordinates":[-87.911158,43.022455],"type":"Point"}
}