{
  "type": "Feature",
  "properties": {
    "iso:country":"US",
    "sg:address":"1824 E Bluebird Ln",
    "sg:city":"Appleton",
    "sg:classifiers":[
        {
            "category":"Retail",
            "subcategory":"Laundry & Dry Cleaning",
            "type":"Services"
        }
    ],
    "sg:phone":"+1 920 738 3266",
    "sg:postcode":"54915",
    "sg:province":"WI",
    "wof:name":"Hoffmans Carpet Care LLC",
    "wof:placetype":"venue"
},
  "geometry": {"coordinates":[-88.376627,44.247713],"type":"Point"}
}