{
  "type": "Feature",
  "properties": {
    "addr:full":"30128 Sumac Dr Burlington WI 53105",
    "addr:housenumber":"30128",
    "addr:postcode":"53105",
    "addr:street":"Sumac Dr",
    "iso:country":"US",
    "sg:address":"30128 Sumac Dr",
    "sg:city":"Burlington",
    "sg:classifiers":[
        {
            "category":"Organizations",
            "subcategory":"Religious Organization",
            "type":"Services"
        }
    ],
    "sg:phone":"+1 262 763 6318",
    "sg:postcode":"53105",
    "sg:province":"WI",
    "sg:tags":[
        "church"
    ],
    "wof:name":"Impact Christian Church Inc",
    "wof:placetype":"venue"
},
  "geometry": {"coordinates":[-88.229412,42.693216],"type":"Point"}
}