{
  "type": "Feature",
  "properties": {
    "addr:full":"237 E Caspian Ave Caspian WI 49915",
    "addr:housenumber":"237",
    "addr:postcode":"49915",
    "addr:street":"E Caspian Ave",
    "iso:country":"US",
    "sg:address":"237 E Caspian Ave",
    "sg:city":"Caspian",
    "sg:classifiers":[
        {
            "category":"Social Services",
            "subcategory":"Job Training",
            "type":"Services"
        }
    ],
    "sg:phone":"+1 906 265 0532",
    "sg:postcode":"49915",
    "sg:province":"WI",
    "sg:tags":[
        "employment"
    ],
    "wof:name":"Michigan Works Svc Ctr",
    "wof:placetype":"venue"
},
  "geometry": {"coordinates":[-88.629434,46.064959],"type":"Point"}
}