{
  "type": "Feature",
  "properties": {
    "iso:country":"US",
    "sg:address":"5920 W Bender Ct",
    "sg:city":"Milwaukee",
    "sg:classifiers":[
        {
            "category":"Professional",
            "subcategory":"Business Services",
            "type":"Services"
        }
    ],
    "sg:phone":"+1 414 464 7183",
    "sg:postcode":"53218",
    "sg:province":"WI",
    "sg:tags":[
        "merchandise"
    ],
    "wof:name":"Culligan",
    "wof:placetype":"venue"
},
  "geometry": {"coordinates":[-87.984583,43.130569],"type":"Point"}
}