{
  "type": "Feature",
  "properties": {
    "iso:country":"US",
    "sg:address":"5901 Sugarbush Ct",
    "sg:city":"Greendale",
    "sg:classifiers":[
        {
            "category":"Professional",
            "type":"Services"
        }
    ],
    "sg:phone":"+1 414 421 6589",
    "sg:postcode":"53129",
    "sg:province":"WI",
    "wof:name":"Layton Avenue Service Ltd",
    "wof:placetype":"venue"
},
  "geometry": {"coordinates":[-87.976196,42.934402],"type":"Point"}
}