{
  "type": "Feature",
  "properties": {
    "iso:country":"US",
    "sg:address":"640 Huntington Ct",
    "sg:city":"Darlington",
    "sg:classifiers":[
        {
            "category":"Home & Garden",
            "subcategory":"Garden Supply",
            "type":"Retail Goods"
        }
    ],
    "sg:phone":"+1 608 776 3704",
    "sg:postcode":"53530",
    "sg:province":"WI",
    "sg:tags":[
        "house",
        "bird",
        "feeder"
    ],
    "wof:name":"Taylor Hobby Farm",
    "wof:placetype":"venue"
},
  "geometry": {"coordinates":[-90.121887,42.673747],"type":"Point"}
}