{
  "type": "Feature",
  "properties": {
    "iso:country":"US",
    "sg:address":"1921 E Main St",
    "sg:city":"Little Chute",
    "sg:classifiers":[
        {
            "category":"Cinema",
            "subcategory":"Movie Rental",
            "type":"Entertainment"
        }
    ],
    "sg:phone":"+1 920 766 6087",
    "sg:postcode":"54140",
    "sg:province":"WI",
    "sg:tags":[
        "leasing",
        "video",
        "disc",
        "tape"
    ],
    "wof:name":"Larry's Video",
    "wof:placetype":"venue"
},
  "geometry": {"coordinates":[-88.289847,44.285298],"type":"Point"}
}