{
  "type": "Feature",
  "properties": {
    "iso:country":"US",
    "sg:address":"759 N Milwaukee St",
    "sg:city":"Milwaukee",
    "sg:classifiers":[
        {
            "category":"Social Services",
            "type":"Services"
        }
    ],
    "sg:phone":"+1 414 276 1540",
    "sg:postcode":"53202",
    "sg:province":"WI",
    "sg:tags":[
        "consulting",
        "management"
    ],
    "sg:website":"www.futuremilwaukee.org",
    "wof:name":"Future Milwaukee Inc",
    "wof:placetype":"venue"
},
  "geometry": {"coordinates":[-87.906841,43.040977],"type":"Point"}
}