{
  "type": "Feature",
  "properties": {
    "iso:country":"US",
    "sg:address":"800 Borner St N",
    "sg:city":"Prescott",
    "sg:classifiers":[
        {
            "category":"Government",
            "subcategory":"Fire Station",
            "type":"Public Place"
        }
    ],
    "sg:phone":"+1 715 262 5733",
    "sg:postcode":"54021",
    "sg:province":"WI",
    "sg:tags":[
        "department",
        "volunteer"
    ],
    "wof:name":"Prescott Fire and Rescue",
    "wof:placetype":"venue"
},
  "geometry": {"coordinates":[-92.786755,44.759799],"type":"Point"}
}