{
  "type": "Feature",
  "properties": {
    "iso:country":"US",
    "sg:address":"3565 Deerskin Rd",
    "sg:city":"Phelps",
    "sg:classifiers":[
        {
            "category":"Health Services",
            "subcategory":"Health Practitioner",
            "type":"Services"
        }
    ],
    "sg:phone":"+1 715 545 2011",
    "sg:postcode":"54554",
    "sg:province":"WI",
    "sg:tags":[
        "nutrition",
        "consultant"
    ],
    "wof:name":"Herbalife Distributor",
    "wof:placetype":"venue"
},
  "geometry": {"coordinates":[-89.10173399999999,46.010701],"type":"Point"}
}