{
  "type": "Feature",
  "properties": {
    "iso:country":"US",
    "sg:address":"3239 Dundas Rd",
    "sg:city":"Kaukauna",
    "sg:classifiers":[
        {
            "category":"Bars & Pubs",
            "type":"Food & Drink"
        }
    ],
    "sg:phone":"+1 920 766 0079",
    "sg:postcode":"54130",
    "sg:province":"WI",
    "wof:name":"Double D's",
    "wof:placetype":"venue"
},
  "geometry": {"coordinates":[-88.183512,44.234117],"type":"Point"}
}