{
  "type": "Feature",
  "properties": {
    "addr:full":"3090 S Ridge Rd Green Bay WI 54304",
    "addr:housenumber":"3090",
    "addr:postcode":"54304",
    "addr:street":"S Ridge Rd",
    "iso:country":"US",
    "sg:address":"3090 S Ridge Rd",
    "sg:city":"Green Bay",
    "sg:classifiers":[
        {
            "category":"Communications",
            "subcategory":"Film & Video Production",
            "type":"Services"
        }
    ],
    "sg:phone":"+1 920 662 0105",
    "sg:postcode":"54304",
    "sg:province":"WI",
    "sg:tags":[
        "taping"
    ],
    "wof:name":"I V Media",
    "wof:placetype":"venue"
},
  "geometry": {"coordinates":[-88.09219299999999,44.465862],"type":"Point"}
}