{
  "type": "Feature",
  "properties": {
    "iso:country":"US",
    "sg:address":"201 Kearney Way",
    "sg:city":"Waunakee",
    "sg:classifiers":[
        {
            "category":"Restaurant",
            "type":"Food & Drink"
        }
    ],
    "sg:phone":"+1 608 935 9777",
    "sg:postcode":"53597",
    "sg:province":"WI",
    "sg:tags":[
        "eating",
        "station",
        "gasoline"
    ],
    "wof:name":"Dodgeville Travel Plaza",
    "wof:placetype":"venue"
},
  "geometry": {"coordinates":[-89.453303,43.185771],"type":"Point"}
}