{
  "type": "Feature",
  "properties": {
    "iso:country":"US",
    "sg:address":"152 N Main St",
    "sg:city":"Monticello",
    "sg:classifiers":[
        {
            "category":"Health Services",
            "subcategory":"Doctor",
            "type":"Services"
        }
    ],
    "sg:phone":"+1 608 938 4001",
    "sg:postcode":"53570",
    "sg:province":"WI",
    "sg:tags":[
        "dentist"
    ],
    "wof:name":"James H Winn DDS",
    "wof:placetype":"venue"
},
  "geometry": {"coordinates":[-89.59434,42.747038],"type":"Point"}
}