{
  "type": "Feature",
  "properties": {
    "addr:full":"700 Mandt Pkwy Stoughton WI 53589",
    "addr:housenumber":"700",
    "addr:postcode":"53589",
    "addr:street":"Mandt Pkwy",
    "iso:country":"US",
    "sg:address":"700 Mandt Pkwy",
    "sg:city":"Stoughton",
    "sg:classifiers":[
        {
            "category":"Government",
            "subcategory":"Office",
            "type":"Public Place"
        }
    ],
    "sg:phone":"+1 608 873 3379",
    "sg:postcode":"53589",
    "sg:province":"WI",
    "sg:tags":[
        "village"
    ],
    "wof:name":"Stoughton Sewer Dept",
    "wof:placetype":"venue"
},
  "geometry": {"coordinates":[-89.21384999999999,42.911719],"type":"Point"}
}