{
  "type": "Feature",
  "properties": {
    "iso:country":"US",
    "sg:address":"5131 Linden St",
    "sg:city":"Laona",
    "sg:classifiers":[
        {
            "category":"Bars & Pubs",
            "type":"Food & Drink"
        }
    ],
    "sg:phone":"+1 715 674 4723",
    "sg:postcode":"54541",
    "sg:province":"WI",
    "wof:name":"Klingensmith's Bar",
    "wof:placetype":"venue"
},
  "geometry": {"coordinates":[-88.674,45.559265],"type":"Point"}
}