{
  "type": "Feature",
  "properties": {
    "iso:country":"US",
    "sg:address":"11310 570th St",
    "sg:city":"Wheeler",
    "sg:classifiers":[
        {
            "category":"Building & Trades",
            "subcategory":"Construction",
            "type":"Services"
        }
    ],
    "sg:phone":"+1 715 658 1818",
    "sg:postcode":"54772",
    "sg:province":"WI",
    "sg:tags":[
        "residential",
        "nonresidential"
    ],
    "wof:name":"Northern Lights Construction",
    "wof:placetype":"venue"
},
  "geometry": {"coordinates":[-91.881214,45.085578],"type":"Point"}
}