{
  "type": "Feature",
  "properties": {
    "iso:country":"US",
    "sg:address":"2400 W Villard Ave",
    "sg:city":"Milwaukee",
    "sg:classifiers":[
        {
            "category":"Health Services",
            "subcategory":"Doctor",
            "type":"Services"
        },
        {
            "category":"Health Services",
            "subcategory":"Clinic",
            "type":"Services"
        },
        {
            "category":"Personal",
            "type":"Services"
        },
        {
            "category":"Health Services",
            "subcategory":"Health Practitioner",
            "type":"Services"
        }
    ],
    "sg:phone":"+1 414 874 4560",
    "sg:postcode":"53209",
    "sg:province":"WI",
    "sg:tags":[
        "physician",
        "mental",
        "information",
        "surgeons",
        "outpatient",
        "drug",
        "alcoholism",
        "abuse",
        "treatment",
        "psychiatry",
        "counseling",
        "addiction",
        "surgeon"
    ],
    "wof:name":"Covenant Behavioral Health",
    "wof:placetype":"venue"
},
  "geometry": {"coordinates":[-87.94158299999999,43.112131],"type":"Point"}
}