{
  "type": "Feature",
  "properties": {
    "addr:full":"3291 Hickory Rd Brownsville WI 53006",
    "addr:housenumber":"3291",
    "addr:postcode":"53006",
    "addr:street":"Hickory Rd",
    "iso:country":"US",
    "sg:address":"3291 Hickory Rd",
    "sg:city":"Brownsville",
    "sg:classifiers":[
        {
            "category":"Building & Trades",
            "subcategory":"Plumbing",
            "type":"Services"
        }
    ],
    "sg:phone":"+1 920 583 3094",
    "sg:postcode":"53006",
    "sg:province":"WI",
    "sg:tags":[
        "contractor"
    ],
    "wof:name":"Shafer Construction",
    "wof:placetype":"venue"
},
  "geometry": {"coordinates":[-88.481432,43.660488],"type":"Point"}
}