{
  "type": "Feature",
  "properties": {
    "iso:country":"US",
    "sg:address":"3443 W Mill Rd",
    "sg:city":"Milwaukee",
    "sg:classifiers":[
        {
            "category":"Wholesale",
            "subcategory":"Construction Materials",
            "type":"Manufacturing & Wholesale Goods"
        }
    ],
    "sg:phone":"+1 414 352 2700",
    "sg:postcode":"53209",
    "sg:province":"WI",
    "sg:tags":[
        "control",
        "manufacturer",
        "system",
        "controls",
        "regulators-wholesale"
    ],
    "wof:name":"Northstar Combustion, Inc.",
    "wof:placetype":"venue"
},
  "geometry": {"coordinates":[-87.95583000000001,43.134334],"type":"Point"}
}