{
  "type": "Feature",
  "properties": {
    "iso:country":"US",
    "sg:address":"8520 Kramer Rd",
    "sg:city":"Deerbrook",
    "sg:classifiers":[
        {
            "category":"Retail",
            "subcategory":"Portrait Studio",
            "type":"Services"
        }
    ],
    "sg:phone":"+1 715 627 0118",
    "sg:postcode":"54424",
    "sg:province":"WI",
    "sg:tags":[
        "photo"
    ],
    "wof:name":"Elite Photography",
    "wof:placetype":"venue"
},
  "geometry": {"coordinates":[-89.085456,45.296839],"type":"Point"}
}