{
  "type": "Feature",
  "properties": {
    "iso:country":"US",
    "sg:address":"1232 Western Ave",
    "sg:city":"Green Bay",
    "sg:classifiers":[
        {
            "category":"Building & Trades",
            "subcategory":"Construction",
            "type":"Services"
        },
        {
            "category":"Utilities",
            "type":"Services"
        }
    ],
    "sg:phone":"+1 920 496 9988",
    "sg:postcode":"54303",
    "sg:province":"WI",
    "sg:tags":[
        "sweeping",
        "contractor"
    ],
    "wof:name":"Reliable Sweep and Lawn Care",
    "wof:placetype":"venue"
},
  "geometry": {"coordinates":[-88.048649,44.521522],"type":"Point"}
}