{
  "type": "Feature",
  "properties": {
    "iso:country":"US",
    "sg:address":"383 W Brown Deer Rd",
    "sg:city":"Milwaukee",
    "sg:classifiers":[
        {
            "category":"Home & Garden",
            "subcategory":"Home Furnishings",
            "type":"Retail Goods"
        }
    ],
    "sg:phone":"+1 414 247 9976",
    "sg:postcode":"53217",
    "sg:province":"WI",
    "wof:name":"Past Basket Milwaukee",
    "wof:placetype":"venue"
},
  "geometry": {"coordinates":[-87.909666,43.176635],"type":"Point"}
}