{
  "type": "Feature",
  "properties": {
    "iso:country":"US",
    "sg:address":"1787 Knob Rd",
    "sg:city":"Burlington",
    "sg:classifiers":[
        {
            "category":"Health Services",
            "subcategory":"Doctor",
            "type":"Services"
        }
    ],
    "sg:phone":"+1 262 767 1445",
    "sg:postcode":"53105",
    "sg:province":"WI",
    "sg:tags":[
        "osteopathic"
    ],
    "wof:name":"Rehabilitation Medicine Assoc",
    "wof:placetype":"venue"
},
  "geometry": {"coordinates":[-88.325532,42.637975],"type":"Point"}
}