{
  "type": "Feature",
  "properties": {
    "iso:country":"US",
    "sg:address":"3800 W National Ave",
    "sg:city":"Milwaukee",
    "sg:classifiers":[
        {
            "category":"Organizations",
            "subcategory":"Professional Association",
            "type":"Services"
        }
    ],
    "sg:phone":"+1 414 384 4441",
    "sg:postcode":"53215",
    "sg:province":"WI",
    "wof:name":"Arabian Fest",
    "wof:placetype":"venue"
},
  "geometry": {"coordinates":[-87.961698,43.021367],"type":"Point"}
}