{
  "type": "Feature",
  "properties": {
    "addr:full":"13214 Gollnow Rd Marion WI 54950",
    "addr:housenumber":"13214",
    "addr:postcode":"54950",
    "addr:street":"Gollnow Rd",
    "iso:country":"US",
    "sg:address":"13214 Gollnow Rd",
    "sg:city":"Marion",
    "sg:classifiers":[
        {
            "category":"Building & Trades",
            "subcategory":"Plumbing",
            "type":"Services"
        }
    ],
    "sg:phone":"+1 715 754 5685",
    "sg:postcode":"54950",
    "sg:province":"WI",
    "sg:tags":[
        "conditioning",
        "air",
        "system",
        "contractor"
    ],
    "wof:name":"Maleug Heating & Cooling",
    "wof:placetype":"venue"
},
  "geometry": {"coordinates":[-88.92063400000001,44.686845],"type":"Point"}
}