{
  "type": "Feature",
  "properties": {
    "iso:country":"US",
    "sg:address":"15518 Manser Rd",
    "sg:city":"Melrose",
    "sg:classifiers":[
        {
            "category":"Farming",
            "subcategory":"Dairy Farm",
            "type":"Manufacturing & Wholesale Goods"
        }
    ],
    "sg:phone":"+1 608 488 4931",
    "sg:postcode":"54642",
    "sg:province":"WI",
    "wof:name":"Arlan Spors",
    "wof:placetype":"venue"
},
  "geometry": {"coordinates":[-91.101321,44.110835],"type":"Point"}
}