{
  "type": "Feature",
  "properties": {
    "addr:full":"3907 52nd Ave Kenosha WI 53144",
    "addr:housenumber":"3907",
    "addr:postcode":"53144",
    "addr:street":"52Nd Ave",
    "iso:country":"US",
    "sg:address":"3907 52nd Ave",
    "sg:city":"Kenosha",
    "sg:classifiers":[
        {
            "category":"Fast Food",
            "type":"Food & Drink"
        },
        {
            "category":"Restaurant",
            "type":"Food & Drink"
        },
        {
            "category":"Food & Beverages",
            "subcategory":"Groceries & Convenience Stores",
            "type":"Retail Goods"
        }
    ],
    "sg:phone":"+1 262 652 1550",
    "sg:postcode":"53144",
    "sg:province":"WI",
    "sg:tags":[
        "shop",
        "american",
        "sandwich"
    ],
    "sg:website":"http://www.arbys.com",
    "wof:name":"Arby's",
    "wof:placetype":"venue"
},
  "geometry": {"coordinates":[-87.871072,42.601111],"type":"Point"}
}