{
  "type": "Feature",
  "properties": {
    "addr:full":"1745 85th St New Richmond WI 54017",
    "addr:housenumber":"1745",
    "addr:postcode":"54017",
    "addr:street":"85Th St",
    "iso:country":"US",
    "sg:address":"1745 85th St",
    "sg:city":"New Richmond",
    "sg:classifiers":[
        {
            "category":"Retail",
            "subcategory":"Repair Shop",
            "type":"Services"
        }
    ],
    "sg:phone":"+1 715 246 4137",
    "sg:postcode":"54017",
    "sg:province":"WI",
    "sg:tags":[
        "related"
    ],
    "wof:name":"Peterson Repairs",
    "wof:placetype":"venue"
},
  "geometry": {"coordinates":[-92.62934,45.114669],"type":"Point"}
}