{
  "type": "Feature",
  "properties": {
    "iso:country":"US",
    "sg:address":"1725 W Knapp St",
    "sg:city":"Rice Lake",
    "sg:classifiers":[
        {
            "category":"Shopping",
            "subcategory":"Bicycles & Sporting Goods",
            "type":"Retail Goods"
        }
    ],
    "sg:phone":"+1 715 236 7613",
    "sg:postcode":"54868",
    "sg:province":"WI",
    "wof:name":"Gunsmith Shop",
    "wof:placetype":"venue"
},
  "geometry": {"coordinates":[-91.752877,45.509233],"type":"Point"}
}