{
  "type": "Feature",
  "properties": {
    "iso:country":"US",
    "sg:address":"9115 26th Ave",
    "sg:city":"Kenosha",
    "sg:classifiers":[
        {
            "category":"Professional",
            "subcategory":"Business Services",
            "type":"Services"
        }
    ],
    "sg:phone":"+1 262 658 2679",
    "sg:postcode":"53143",
    "sg:province":"WI",
    "wof:name":"Midwest Office Solutions Inc",
    "wof:placetype":"venue"
},
  "geometry": {"coordinates":[-87.83851900000001,42.537056],"type":"Point"}
}