{
  "type": "Feature",
  "properties": {
    "addr:full":"9699 Deer Lake Ln Phillips WI 54555",
    "addr:housenumber":"9699",
    "addr:postcode":"54555",
    "addr:street":"Deer Lake Ln",
    "iso:country":"US",
    "sg:address":"9699 Deer Lake Ln",
    "sg:city":"Phillips",
    "sg:classifiers":[
        {
            "category":"Travel",
            "subcategory":"Hotels & Motels",
            "type":"Entertainment"
        }
    ],
    "sg:phone":"+1 715 339 4654",
    "sg:postcode":"54555",
    "sg:province":"WI",
    "sg:tags":[
        "resort"
    ],
    "wof:name":"Deer Lake Resort",
    "wof:placetype":"venue"
},
  "geometry": {"coordinates":[-90.41575899999999,45.723539],"type":"Point"}
}