{
  "type": "Feature",
  "properties": {
    "addr:full":"3390 Anderson Rd Waupaca WI 54981",
    "addr:housenumber":"3390",
    "addr:postcode":"54981",
    "addr:street":"Anderson Rd",
    "iso:country":"US",
    "sg:address":"3390 Anderson Rd",
    "sg:city":"Waupaca",
    "sg:classifiers":[
        {
            "category":"Home & Garden",
            "subcategory":"Carpets & Floor Coverings",
            "type":"Retail Goods"
        }
    ],
    "sg:phone":"+1 715 258 5555",
    "sg:postcode":"54981",
    "sg:province":"WI",
    "sg:tags":[
        "dealer",
        "rug"
    ],
    "wof:name":"Discount Carpet",
    "wof:placetype":"venue"
},
  "geometry": {"coordinates":[-89.12465,44.362347],"type":"Point"}
}