{
  "type": "Feature",
  "properties": {
    "addr:full":"110 W Adams St Platteville WI 53818",
    "addr:housenumber":"110",
    "addr:postcode":"53818",
    "addr:street":"W Adams St",
    "iso:country":"US",
    "sg:address":"110 W Adams St",
    "sg:city":"Platteville",
    "sg:classifiers":[
        {
            "category":"Education",
            "subcategory":"School",
            "type":"Public Place"
        }
    ],
    "sg:phone":"+1 608 342 4030",
    "sg:postcode":"53818",
    "sg:province":"WI",
    "wof:name":"O E Gray Early Learning Ctr",
    "wof:placetype":"venue"
},
  "geometry": {"coordinates":[-90.478858,42.737904],"type":"Point"}
}