{
  "type": "Feature",
  "properties": {
    "iso:country":"US",
    "sg:address":"316 W Grand Ave",
    "sg:city":"Port Washington",
    "sg:classifiers":[
        {
            "category":"Recreation",
            "type":"Entertainment"
        }
    ],
    "sg:phone":"+1 262 284 2897",
    "sg:postcode":"53074",
    "sg:province":"WI",
    "sg:tags":[
        "attraction",
        "tourist"
    ],
    "wof:name":"Eghart House",
    "wof:placetype":"venue"
},
  "geometry": {"coordinates":[-87.874296,43.387608],"type":"Point"}
}