{
  "type": "Feature",
  "properties": {
    "iso:country":"US",
    "sg:address":"1725 N Parker Dr",
    "sg:city":"Janesville",
    "sg:classifiers":[
        {
            "category":"Building & Trades",
            "subcategory":"Construction",
            "type":"Services"
        }
    ],
    "sg:phone":"+1 608 290 6902",
    "sg:postcode":"53545",
    "sg:province":"WI",
    "sg:tags":[
        "roofing",
        "contractor"
    ],
    "wof:name":"Raindance Exteriors II",
    "wof:placetype":"venue"
},
  "geometry": {"coordinates":[-89.031648,42.704507],"type":"Point"}
}