{
  "type": "Feature",
  "properties": {
    "iso:country":"US",
    "sg:address":"1835 State Hwy 57",
    "sg:city":"Sturgeon Bay",
    "sg:classifiers":[
        {
            "category":"Farming",
            "subcategory":"Farm",
            "type":"Manufacturing & Wholesale Goods"
        }
    ],
    "sg:phone":"+1 920 825 7218",
    "sg:postcode":"54235",
    "sg:province":"WI",
    "sg:tags":[
        "crop",
        "general"
    ],
    "wof:name":"Duane Corbisier",
    "wof:placetype":"venue"
},
  "geometry": {"coordinates":[-87.550054,44.759371],"type":"Point"}
}