{
  "type": "Feature",
  "properties": {
    "iso:country":"US",
    "sg:address":"570 Evans Dr",
    "sg:city":"Fond Du Lac",
    "sg:classifiers":[
        {
            "category":"Museum",
            "type":"Entertainment"
        }
    ],
    "sg:phone":"+1 920 734 9413",
    "sg:postcode":"54935",
    "sg:province":"WI",
    "sg:tags":[
        "organization",
        "arts",
        "information"
    ],
    "wof:name":"Very Special Arts Wisconsin",
    "wof:placetype":"venue"
},
  "geometry": {"coordinates":[-88.468458,43.768679],"type":"Point"}
}