{
  "type": "Feature",
  "properties": {
    "addr:full":"637 W North St De Forest WI 53532",
    "addr:housenumber":"637",
    "addr:postcode":"53532",
    "addr:street":"W North St",
    "iso:country":"US",
    "sg:address":"637 W North St",
    "sg:city":"De Forest",
    "sg:classifiers":[
        {
            "category":"Restaurant",
            "type":"Food & Drink"
        }
    ],
    "sg:phone":"+1 608 846 9112",
    "sg:postcode":"53532",
    "sg:province":"WI",
    "wof:name":"Firehouse Grill & Pub",
    "wof:placetype":"venue"
},
  "geometry": {"coordinates":[-89.352671,43.252607],"type":"Point"}
}