{
  "type": "Feature",
  "properties": {
    "addr:full":"379 Kearney Rd Burlington WI 53105",
    "addr:housenumber":"379",
    "addr:postcode":"53105",
    "addr:street":"Kearney Rd",
    "iso:country":"US",
    "sg:address":"379 Kearney Rd",
    "sg:city":"Burlington",
    "sg:classifiers":[
        {
            "category":"Professional",
            "type":"Services"
        }
    ],
    "sg:phone":"+1 262 514 3521",
    "sg:postcode":"53105",
    "sg:province":"WI",
    "wof:name":"Field of Beans",
    "wof:placetype":"venue"
},
  "geometry": {"coordinates":[-88.33288,42.718274],"type":"Point"}
}