{
  "type": "Feature",
  "properties": {
    "iso:country":"US",
    "sg:address":"4033 Co Hwy M S",
    "sg:city":"Elk Mound",
    "sg:classifiers":[
        {
            "category":"Manufacturing",
            "subcategory":"Motor Vehicles & Parts",
            "type":"Manufacturing & Wholesale Goods"
        }
    ],
    "sg:phone":"+1 715 874 6552",
    "sg:postcode":"54739",
    "sg:province":"WI",
    "sg:tags":[
        "designer",
        "trailer"
    ],
    "wof:name":"Gullickson Trailer Sales & Svc",
    "wof:placetype":"venue"
},
  "geometry": {"coordinates":[-91.61048,44.900784],"type":"Point"}
}