{
  "type": "Feature",
  "properties": {
    "iso:country":"US",
    "sg:address":"7778 Egg Harbor Rd",
    "sg:city":"Egg Harbor",
    "sg:classifiers":[
        {
            "category":"Food & Beverages",
            "subcategory":"Bakery",
            "type":"Retail Goods"
        }
    ],
    "sg:phone":"+1 920 868 3355",
    "sg:postcode":"54209",
    "sg:province":"WI",
    "sg:tags":[
        "baker"
    ],
    "wof:name":"Dough Exchange Bakery",
    "wof:placetype":"venue"
},
  "geometry": {"coordinates":[-87.279796,45.049176],"type":"Point"}
}