{
  "type": "Feature",
  "properties": {
    "iso:country":"US",
    "sg:address":"1350 14th Ave",
    "sg:city":"Grafton",
    "sg:classifiers":[
        {
            "category":"Professional",
            "subcategory":"Art Services",
            "type":"Services"
        }
    ],
    "sg:phone":"+1 262 377 7955",
    "sg:postcode":"53024",
    "sg:province":"WI",
    "sg:tags":[
        "photographer",
        "photography"
    ],
    "wof:name":"Paul Hundley Photo Graphics",
    "wof:placetype":"venue"
},
  "geometry": {"coordinates":[-87.949082,43.317024],"type":"Point"}
}