{
  "type": "Feature",
  "properties": {
    "iso:country":"US",
    "sg:address":"8601 190th Ave",
    "sg:city":"Bloomer",
    "sg:classifiers":[
        {
            "category":"Building & Trades",
            "subcategory":"Construction",
            "type":"Services"
        }
    ],
    "sg:phone":"+1 715 568 3015",
    "sg:postcode":"54724",
    "sg:province":"WI",
    "sg:tags":[
        "steel",
        "erection",
        "structural"
    ],
    "wof:name":"Abell Construction Inc",
    "wof:placetype":"venue"
},
  "geometry": {"coordinates":[-91.504697,45.120401],"type":"Point"}
}