{
  "type": "Feature",
  "properties": {
    "addr:full":"4255 Branch Rd Park Falls WI 54552",
    "addr:housenumber":"4255",
    "addr:postcode":"54552",
    "addr:street":"Branch Rd",
    "iso:country":"US",
    "sg:address":"4255 Branch Rd",
    "sg:city":"Park Falls",
    "sg:classifiers":[
        {
            "category":"Building & Trades",
            "subcategory":"Construction",
            "type":"Services"
        }
    ],
    "sg:phone":"+1 715 583 4526",
    "sg:postcode":"54552",
    "sg:province":"WI",
    "sg:tags":[
        "house",
        "contractor",
        "concrete"
    ],
    "wof:name":"Knudson's Concrete Design",
    "wof:placetype":"venue"
},
  "geometry": {"coordinates":[-90.14174199999999,46.025416],"type":"Point"}
}