{
  "type": "Feature",
  "properties": {
    "iso:country":"US",
    "sg:address":"10623 Cascade Mountain Rd",
    "sg:city":"Portage",
    "sg:classifiers":[
        {
            "category":"Manufacturing",
            "subcategory":"Rubber & Plastics",
            "type":"Manufacturing & Wholesale Goods"
        },
        {
            "category":"Manufacturing",
            "subcategory":"Tools & Machinery",
            "type":"Manufacturing & Wholesale Goods"
        }
    ],
    "sg:phone":"+1 608 742 6286",
    "sg:postcode":"53901",
    "sg:province":"WI",
    "sg:tags":[
        "mfg",
        "pattern",
        "industrial",
        "casting",
        "molding"
    ],
    "wof:name":"Cascade Mountain Pattern Inc",
    "wof:placetype":"venue"
},
  "geometry": {"coordinates":[-89.532746,43.50838],"type":"Point"}
}