{
  "type": "Feature",
  "properties": {
    "iso:country":"US",
    "sg:address":"118 State St",
    "sg:city":"Madison",
    "sg:classifiers":[
        {
            "category":"Restaurant",
            "type":"Food & Drink"
        }
    ],
    "sg:phone":"+1 608 294 9988",
    "sg:postcode":"53703",
    "sg:province":"WI",
    "sg:tags":[
        "eating"
    ],
    "sg:website":"www.statebarandgrill.com",
    "wof:name":"State Bar & Grill LLC",
    "wof:placetype":"venue"
},
  "geometry": {"coordinates":[-89.387782,43.074809],"type":"Point"}
}