{
  "type": "Feature",
  "properties": {
    "iso:country":"US",
    "sg:address":"5431 Hinker Rd",
    "sg:city":"Greenwood",
    "sg:classifiers":[
        {
            "category":"Manufacturing",
            "subcategory":"Tools & Machinery",
            "type":"Manufacturing & Wholesale Goods"
        }
    ],
    "sg:phone":"+1 715 267 7176",
    "sg:postcode":"54437",
    "sg:province":"WI",
    "sg:tags":[
        "farm",
        "equipment"
    ],
    "wof:name":"Bushman Enterprises Inc",
    "wof:placetype":"venue"
},
  "geometry": {"coordinates":[-90.586986,44.752279],"type":"Point"}
}