{
  "type": "Feature",
  "properties": {
    "iso:country":"US",
    "sg:address":"9872 Fuhrman Dr",
    "sg:city":"Hazelhurst",
    "sg:classifiers":[
        {
            "category":"Building & Trades",
            "subcategory":"Plumbing",
            "type":"Services"
        }
    ],
    "sg:phone":"+1 715 356 9997",
    "sg:postcode":"54531",
    "sg:province":"WI",
    "sg:tags":[
        "sheet",
        "work",
        "metal",
        "contractor"
    ],
    "wof:name":"Royal Sheet Metal",
    "wof:placetype":"venue"
},
  "geometry": {"coordinates":[-89.729747,45.812516],"type":"Point"}
}