{
  "type": "Feature",
  "properties": {
    "addr:full":"500 State Road 35 Somerset WI 54025",
    "addr:housenumber":"500",
    "addr:postcode":"54025",
    "addr:street":"State Road 35",
    "iso:country":"US",
    "sg:address":"500 State Road 35",
    "sg:city":"Somerset",
    "sg:classifiers":[
        {
            "category":"School Buses",
            "type":"Transportation"
        }
    ],
    "sg:phone":"+1 715 247 3376",
    "sg:postcode":"54025",
    "sg:province":"WI",
    "wof:name":"Apple River Eatry",
    "wof:placetype":"venue"
},
  "geometry": {"coordinates":[-92.672521,45.135983],"type":"Point"}
}