{
  "type": "Feature",
  "properties": {
    "iso:country":"US",
    "sg:address":"17098 Pinewood Dr",
    "sg:city":"Stanley",
    "sg:classifiers":[
        {
            "category":"Real Estate",
            "subcategory":"Real Estate Operator",
            "type":"Services"
        }
    ],
    "sg:phone":"+1 715 644 2440",
    "sg:postcode":"54768",
    "sg:province":"WI",
    "sg:tags":[
        "property",
        "lessor"
    ],
    "wof:name":"Laurel France",
    "wof:placetype":"venue"
},
  "geometry": {"coordinates":[-90.916675,45.045795],"type":"Point"}
}