{
  "type": "Feature",
  "properties": {
    "iso:country":"US",
    "sg:address":"714 4th Ave W",
    "sg:city":"Monroe",
    "sg:classifiers":[
        {
            "category":"Health Services",
            "subcategory":"Chiropractor",
            "type":"Services"
        }
    ],
    "sg:phone":"+1 608 328 8304",
    "sg:postcode":"53566",
    "sg:province":"WI",
    "sg:tags":[
        "chiropractic"
    ],
    "wof:name":"Monroe Chiropractic Associates Sc",
    "wof:placetype":"venue"
},
  "geometry": {"coordinates":[-89.661407,42.604591],"type":"Point"}
}