{
  "type": "Feature",
  "properties": {
    "addr:full":"3613 Johns St Madison WI 53714",
    "addr:housenumber":"3613",
    "addr:postcode":"53714",
    "addr:street":"Johns St",
    "iso:country":"US",
    "sg:address":"3613 Johns St",
    "sg:city":"Madison",
    "sg:classifiers":[
        {
            "category":"Retail",
            "subcategory":"Repair Shop",
            "type":"Services"
        }
    ],
    "sg:phone":"+1 608 251 0347",
    "sg:postcode":"53714",
    "sg:province":"WI",
    "sg:tags":[
        "electrical"
    ],
    "wof:name":"Als Appliance Repair",
    "wof:placetype":"venue"
},
  "geometry": {"coordinates":[-89.325412,43.08838],"type":"Point"}
}