{
  "type": "Feature",
  "properties": {
    "iso:country":"US",
    "sg:address":"374 N Falls St",
    "sg:city":"River Falls",
    "sg:classifiers":[
        {
            "category":"Real Estate",
            "subcategory":"Real Estate Agent",
            "type":"Services"
        },
        {
            "category":"Professional",
            "subcategory":"Business Services",
            "type":"Services"
        }
    ],
    "sg:phone":"+1 715 425 2901",
    "sg:postcode":"54022",
    "sg:province":"WI",
    "sg:tags":[
        "appraiser"
    ],
    "wof:name":"Equitable Ind Appraisal Co",
    "wof:placetype":"venue"
},
  "geometry": {"coordinates":[-92.63346300000001,44.860957],"type":"Point"}
}