{
  "type": "Feature",
  "properties": {
    "addr:full":"506 Spring Ct Oconomowoc WI 53066",
    "addr:housenumber":"506",
    "addr:postcode":"53066",
    "addr:street":"Spring Ct",
    "iso:country":"US",
    "sg:address":"506 Spring Ct",
    "sg:city":"Oconomowoc",
    "sg:classifiers":[
        {
            "category":"Professional",
            "subcategory":"Management & Consulting",
            "type":"Services"
        }
    ],
    "sg:phone":"+1 262 646 3557",
    "sg:postcode":"53066",
    "sg:province":"WI",
    "sg:tags":[
        "business"
    ],
    "wof:name":"TSR Consulting Services LLC",
    "wof:placetype":"venue"
},
  "geometry": {"coordinates":[-88.430049,43.027067],"type":"Point"}
}