{
  "type": "Feature",
  "properties": {
    "addr:full":"8609 Durand Ave Sturtevant WI 53177",
    "addr:housenumber":"8609",
    "addr:postcode":"53177",
    "addr:street":"Durand Ave",
    "iso:country":"US",
    "sg:address":"8609 Durand Ave",
    "sg:city":"Sturtevant",
    "sg:classifiers":[
        {
            "category":"Restaurant",
            "type":"Food & Drink"
        }
    ],
    "sg:phone":"+1 262 886 8686",
    "sg:postcode":"53177",
    "sg:province":"WI",
    "wof:name":"Olympic Family Restaurant Inc",
    "wof:placetype":"venue"
},
  "geometry": {"coordinates":[-87.89094799999999,42.697825],"type":"Point"}
}