{
  "type": "Feature",
  "properties": {
    "iso:country":"US",
    "sg:address":"11051 State Hwy 42",
    "sg:city":"Sister Bay",
    "sg:classifiers":[
        {
            "category":"Restaurant",
            "type":"Food & Drink"
        }
    ],
    "sg:phone":"+1 920 854 9693",
    "sg:postcode":"54234",
    "sg:province":"WI",
    "wof:name":"Door County Ice Cream Factory",
    "wof:placetype":"venue"
},
  "geometry": {"coordinates":[-87.11763500000001,45.207718],"type":"Point"}
}