{
  "type": "Feature",
  "properties": {
    "addr:full":"2357 N 40th St Milwaukee WI 53210",
    "addr:housenumber":"2357",
    "addr:postcode":"53210",
    "addr:street":"N 40Th St",
    "iso:country":"US",
    "sg:address":"2357 N 40th St",
    "sg:city":"Milwaukee",
    "sg:classifiers":[
        {
            "category":"Professional",
            "subcategory":"Business Services",
            "type":"Services"
        }
    ],
    "sg:phone":"+1 414 873 3716",
    "sg:postcode":"53210",
    "sg:province":"WI",
    "sg:tags":[
        "consultant",
        "coach"
    ],
    "wof:name":"Abacus Sales Consulting",
    "wof:placetype":"venue"
},
  "geometry": {"coordinates":[-87.96341700000001,43.061406],"type":"Point"}
}