{
  "type": "Feature",
  "properties": {
    "iso:country":"US",
    "sg:address":"940 Hansen Rd",
    "sg:city":"Green Bay",
    "sg:classifiers":[
        {
            "category":"Personal",
            "subcategory":"Tanning Parlor",
            "type":"Services"
        },
        {
            "category":"Shopping",
            "subcategory":"Clothing, Apparel, & Fashions",
            "type":"Retail Goods"
        }
    ],
    "sg:phone":"+1 920 884 2306",
    "sg:postcode":"54304",
    "sg:province":"WI",
    "sg:tags":[
        "salon"
    ],
    "wof:name":"Leilani's Tropical Tan & Gift",
    "wof:placetype":"venue"
},
  "geometry": {"coordinates":[-88.077912,44.477162],"type":"Point"}
}