{
  "type": "Feature",
  "properties": {
    "iso:country":"US",
    "sg:address":"1300 N Lincoln Memorial Dr",
    "sg:city":"Milwaukee",
    "sg:classifiers":[
        {
            "category":"Professional",
            "type":"Services"
        }
    ],
    "sg:phone":"+1 414 270 0422",
    "sg:postcode":"53202",
    "sg:province":"WI",
    "sg:tags":[
        "establishment"
    ],
    "wof:name":"Great Circus Parade",
    "wof:placetype":"venue"
},
  "geometry": {"coordinates":[-87.89393,43.046791],"type":"Point"}
}