{
  "type": "Feature",
  "properties": {
    "addr:full":"1200 N Mayfair Rd Milwaukee WI 53222",
    "addr:housenumber":"1200",
    "addr:postcode":"53222",
    "addr:street":"N Mayfair Rd",
    "iso:country":"US",
    "sg:address":"1200 N Mayfair Rd",
    "sg:city":"Milwaukee",
    "sg:classifiers":[
        {
            "category":"Banks & Credit Unions",
            "subcategory":"Bank",
            "type":"Services"
        }
    ],
    "sg:phone":"+1 414 476 0929",
    "sg:postcode":"53222",
    "sg:province":"WI",
    "sg:tags":[
        "loan",
        "real estate"
    ],
    "wof:name":"Universal Mortgage Corp",
    "wof:placetype":"venue"
},
  "geometry": {"coordinates":[-88.04740700000001,43.046901],"type":"Point"}
}