{
  "type": "Feature",
  "properties": {
    "iso:country":"US",
    "sg:address":"4 N Oak St",
    "sg:city":"Crivitz",
    "sg:classifiers":[
        {
            "category":"Professional",
            "subcategory":"Business Services",
            "type":"Services"
        }
    ],
    "sg:phone":"+1 715 854 3477",
    "sg:postcode":"54114",
    "sg:province":"WI",
    "wof:name":"J & G Enterprises LLC",
    "wof:placetype":"venue"
},
  "geometry": {"coordinates":[-87.998873,45.227247],"type":"Point"}
}