{
  "type": "Feature",
  "properties": {
    "iso:country":"US",
    "sg:address":"111 S Main St",
    "sg:city":"Fond Du Lac",
    "sg:classifiers":[
        {
            "category":"Shopping",
            "subcategory":"Gifts & Souvenirs",
            "type":"Retail Goods"
        }
    ],
    "sg:phone":"+1 920 923 1145",
    "sg:postcode":"54935",
    "sg:province":"WI",
    "wof:name":"Craft Cubboard The",
    "wof:placetype":"venue"
},
  "geometry": {"coordinates":[-88.446917,43.775581],"type":"Point"}
}