{
  "type": "Feature",
  "properties": {
    "iso:country":"US",
    "sg:address":"4602 State Hwy 97",
    "sg:city":"Stratford",
    "sg:classifiers":[
        {
            "category":"Wholesale",
            "subcategory":"Durable Goods & Equipment",
            "type":"Manufacturing & Wholesale Goods"
        }
    ],
    "sg:phone":"+1 715 687 4336",
    "sg:postcode":"54484",
    "sg:province":"WI",
    "sg:tags":[
        "representative",
        "manufacturer"
    ],
    "wof:name":"Industrial Process Services",
    "wof:placetype":"venue"
},
  "geometry": {"coordinates":[-90.079081,44.843862],"type":"Point"}
}