{
  "type": "Feature",
  "properties": {
    "addr:full":"9668 Manitou Ct Woodruff WI 54548",
    "addr:housenumber":"9668",
    "addr:postcode":"54548",
    "addr:street":"Manitou Ct",
    "iso:country":"US",
    "sg:address":"9668 Manitou Ct",
    "sg:city":"Woodruff",
    "sg:classifiers":[
        {
            "category":"Building & Trades",
            "subcategory":"Construction",
            "type":"Services"
        }
    ],
    "sg:phone":"+1 715 358 3049",
    "sg:postcode":"54548",
    "sg:province":"WI",
    "sg:tags":[
        "contractor"
    ],
    "wof:name":"Nelson Brothers Construction",
    "wof:placetype":"venue"
},
  "geometry": {"coordinates":[-89.71065900000001,45.860137],"type":"Point"}
}