{
  "type": "Feature",
  "properties": {
    "iso:country":"US",
    "sg:address":"3967 N Teutonia Ave",
    "sg:city":"Milwaukee",
    "sg:classifiers":[
        {
            "category":"Shopping",
            "subcategory":"Gifts & Souvenirs",
            "type":"Retail Goods"
        }
    ],
    "sg:phone":"+1 414 874 5140",
    "sg:postcode":"53206",
    "sg:province":"WI",
    "sg:tags":[
        "party",
        "supply"
    ],
    "wof:name":"Democratic Party Of Wi",
    "wof:placetype":"venue"
},
  "geometry": {"coordinates":[-87.938666,43.089107],"type":"Point"}
}