{
  "type": "Feature",
  "properties": {
    "iso:country":"US",
    "sg:address":"6838 N Ironwood Ln",
    "sg:city":"Milwaukee",
    "sg:classifiers":[
        {
            "category":"Professional",
            "subcategory":"Business Services",
            "type":"Services"
        }
    ],
    "sg:phone":"+1 414 352 3633",
    "sg:postcode":"53217",
    "sg:province":"WI",
    "wof:name":"Senza Fine Design LLC",
    "wof:placetype":"venue"
},
  "geometry": {"coordinates":[-87.91733000000001,43.140484],"type":"Point"}
}