{
  "type": "Feature",
  "properties": {
    "addr:full":"25616 State Hwy 50 Salem WI 53168",
    "addr:housenumber":"25616",
    "addr:postcode":"53168",
    "addr:street":"State Hwy 50",
    "iso:country":"US",
    "sg:address":"25616 State Hwy 50",
    "sg:city":"Salem",
    "sg:classifiers":[
        {
            "category":"Manufacturing",
            "subcategory":"Signs",
            "type":"Manufacturing & Wholesale Goods"
        }
    ],
    "sg:phone":"+1 262 843 3475",
    "sg:postcode":"53168",
    "sg:province":"WI",
    "wof:name":"Biron Signs & Designs",
    "wof:placetype":"venue"
},
  "geometry": {"coordinates":[-88.12021799999999,42.568361],"type":"Point"}
}