{
  "type": "Feature",
  "properties": {
    "iso:country":"US",
    "sg:address":"1204 Pflaum Rd",
    "sg:city":"Madison",
    "sg:classifiers":[
        {
            "category":"Retail",
            "subcategory":"Auto Repair",
            "type":"Services"
        }
    ],
    "sg:phone":"+1 608 221 9434",
    "sg:postcode":"53716",
    "sg:province":"WI",
    "sg:tags":[
        "automotive"
    ],
    "wof:name":"Tri-County Towing Inc",
    "wof:placetype":"venue"
},
  "geometry": {"coordinates":[-89.311713,43.062324],"type":"Point"}
}