{
  "type": "Feature",
  "properties": {
    "iso:country":"US",
    "sg:address":"2514 N Teutonia Ave",
    "sg:city":"Milwaukee",
    "sg:classifiers":[
        {
            "category":"Bars & Pubs",
            "type":"Food & Drink"
        }
    ],
    "sg:phone":"+1 414 264 0202",
    "sg:postcode":"53206",
    "sg:province":"WI",
    "sg:tags":[
        "drinking"
    ],
    "wof:name":"Zanzibar",
    "wof:placetype":"venue"
},
  "geometry": {"coordinates":[-87.92892000000001,43.065583],"type":"Point"}
}