{
  "type": "Feature",
  "properties": {
    "iso:country":"US",
    "sg:address":"4712 Olson Dr",
    "sg:city":"Eau Claire",
    "sg:classifiers":[
        {
            "category":"Building & Trades",
            "subcategory":"Construction",
            "type":"Services"
        }
    ],
    "sg:phone":"+1 715 832 2675",
    "sg:postcode":"54703",
    "sg:province":"WI",
    "sg:tags":[
        "painter"
    ],
    "wof:name":"B K Painting",
    "wof:placetype":"venue"
},
  "geometry": {"coordinates":[-91.430857,44.836241],"type":"Point"}
}