{
  "type": "Feature",
  "properties": {
    "addr:full":"5158 S 108th St Hales Corners WI 53130",
    "addr:housenumber":"5158",
    "addr:postcode":"53130",
    "addr:street":"S 108Th St",
    "iso:country":"US",
    "sg:address":"5158 S 108th St",
    "sg:city":"Hales Corners",
    "sg:classifiers":[
        {
            "category":"Banks & Credit Unions",
            "subcategory":"Bank",
            "type":"Services"
        }
    ],
    "sg:phone":"+1 414 425 9660",
    "sg:postcode":"53130",
    "sg:province":"WI",
    "sg:tags":[
        "financing"
    ],
    "wof:name":"American General Finance Inc",
    "wof:placetype":"venue"
},
  "geometry": {"coordinates":[-88.048107,42.950379],"type":"Point"}
}