{
  "type": "Feature",
  "properties": {
    "iso:country":"US",
    "sg:address":"35197 Richter Rd",
    "sg:city":"Whitehall",
    "sg:classifiers":[
        {
            "category":"Farming",
            "subcategory":"Dairy Farm",
            "type":"Manufacturing & Wholesale Goods"
        }
    ],
    "sg:phone":"+1 715 538 4051",
    "sg:postcode":"54773",
    "sg:province":"WI",
    "wof:name":"Kulig Farms",
    "wof:placetype":"venue"
},
  "geometry": {"coordinates":[-91.300982,44.352403],"type":"Point"}
}