{
  "type": "Feature",
  "properties": {
    "iso:country":"US",
    "sg:address":"2717 W Capitol Dr",
    "sg:city":"Appleton",
    "sg:classifiers":[
        {
            "category":"Real Estate",
            "subcategory":"Real Estate Agent",
            "type":"Services"
        }
    ],
    "sg:phone":"+1 920 730 0331",
    "sg:postcode":"54914",
    "sg:province":"WI",
    "wof:name":"Fox Cities Real Estate",
    "wof:placetype":"venue"
},
  "geometry": {"coordinates":[-88.448745,44.295042],"type":"Point"}
}