{
  "type": "Feature",
  "properties": {
    "iso:country":"US",
    "sg:address":"232 N Mill St",
    "sg:city":"Juneau",
    "sg:classifiers":[
        {
            "category":"Wholesale",
            "subcategory":"Construction Materials",
            "type":"Manufacturing & Wholesale Goods"
        }
    ],
    "sg:phone":"+1 920 386 0168",
    "sg:postcode":"53039",
    "sg:province":"WI",
    "wof:name":"Custom Wood Cutters",
    "wof:placetype":"venue"
},
  "geometry": {"coordinates":[-88.700312,43.40821],"type":"Point"}
}