{
  "type": "Feature",
  "properties": {
    "iso:country":"US",
    "sg:address":"809 23rd St",
    "sg:city":"Monroe",
    "sg:classifiers":[
        {
            "category":"Retail",
            "subcategory":"Repair Shop",
            "type":"Services"
        }
    ],
    "sg:phone":"+1 608 325 7194",
    "sg:postcode":"53566",
    "sg:province":"WI",
    "sg:tags":[
        "repairing",
        "piano",
        "refinishing"
    ],
    "wof:name":"Mark Scheppele Piano Tuning",
    "wof:placetype":"venue"
},
  "geometry": {"coordinates":[-89.64972,42.59052],"type":"Point"}
}