{
  "type": "Feature",
  "properties": {
    "iso:country":"US",
    "sg:address":"707 Woodard Ave",
    "sg:city":"Tomah",
    "sg:classifiers":[
        {
            "category":"Recreation",
            "type":"Entertainment"
        }
    ],
    "sg:phone":"+1 608 374 7448",
    "sg:postcode":"54660",
    "sg:province":"WI",
    "sg:tags":[
        "parks"
    ],
    "wof:name":"Tomah Parks & Rec Mntnc Bldg",
    "wof:placetype":"venue"
},
  "geometry": {"coordinates":[-90.502397,43.980459],"type":"Point"}
}