{
  "type": "Feature",
  "properties": {
    "iso:country":"US",
    "sg:address":"9321 Gehri Rd",
    "sg:city":"Wonewoc",
    "sg:classifiers":[
        {
            "category":"Professional",
            "type":"Services"
        }
    ],
    "sg:phone":"+1 608 464 3343",
    "sg:postcode":"53968",
    "sg:province":"WI",
    "wof:name":"Wonewoc Environmental",
    "wof:placetype":"venue"
},
  "geometry": {"coordinates":[-90.232331,43.646338],"type":"Point"}
}