{
  "type": "Feature",
  "properties": {
    "addr:full":"731 10th St N La Crosse WI 54601",
    "addr:housenumber":"731",
    "addr:postcode":"54601",
    "addr:street":"10Th St N",
    "iso:country":"US",
    "sg:address":"731 10th St N",
    "sg:city":"La Crosse",
    "sg:classifiers":[
        {
            "category":"Home & Garden",
            "subcategory":"Home Furnishings",
            "type":"Retail Goods"
        }
    ],
    "sg:phone":"+1 608 784 7860",
    "sg:postcode":"54601",
    "sg:province":"WI",
    "sg:tags":[
        "sewing",
        "quilting"
    ],
    "wof:name":"Carol's Corner",
    "wof:placetype":"venue"
},
  "geometry": {"coordinates":[-91.242572,43.819209],"type":"Point"}
}