{
  "type": "Feature",
  "properties": {
    "addr:full":"2755 S Quincy Ave Milwaukee WI 53207",
    "addr:housenumber":"2755",
    "addr:postcode":"53207",
    "addr:street":"S Quincy Ave",
    "iso:country":"US",
    "sg:address":"2755 S Quincy Ave",
    "sg:city":"Milwaukee",
    "sg:classifiers":[
        {
            "category":"Real Estate",
            "subcategory":"Real Estate Services",
            "type":"Services"
        },
        {
            "category":"Real Estate",
            "subcategory":"Real Estate Agent",
            "type":"Services"
        }
    ],
    "sg:phone":"+1 414 483 4430",
    "sg:postcode":"53207",
    "sg:province":"WI",
    "sg:tags":[
        "buyer",
        "broker"
    ],
    "wof:name":"Bayside Real Estate",
    "wof:placetype":"venue"
},
  "geometry": {"coordinates":[-87.90157499999999,42.994605],"type":"Point"}
}