{
  "type": "Feature",
  "properties": {
    "iso:country":"US",
    "sg:address":"222 N 33rd St",
    "sg:city":"Milwaukee",
    "sg:classifiers":[
        {
            "category":"Organizations",
            "subcategory":"Membership Organization",
            "type":"Services"
        }
    ],
    "sg:phone":"+1 414 933 9410",
    "sg:postcode":"53208",
    "sg:province":"WI",
    "wof:name":"Merrill Park Resident Orgnztn",
    "wof:placetype":"venue"
},
  "geometry": {"coordinates":[-87.955206,43.033441],"type":"Point"}
}