{
  "type": "Feature",
  "properties": {
    "iso:country":"US",
    "sg:address":"9521 304th Ave",
    "sg:city":"Burlington",
    "sg:classifiers":[
        {
            "category":"Recreation",
            "type":"Entertainment"
        }
    ],
    "sg:phone":"+1 262 889 4710",
    "sg:postcode":"53105",
    "sg:province":"WI",
    "sg:tags":[
        "parks"
    ],
    "wof:name":"Fox River Park",
    "wof:placetype":"venue"
},
  "geometry": {"coordinates":[-88.17716799999999,42.535266],"type":"Point"}
}