{
  "type": "Feature",
  "properties": {
    "iso:country":"US",
    "sg:address":"550 N Burr Oak Ave",
    "sg:city":"Oregon",
    "sg:classifiers":[
        {
            "category":"Professional",
            "subcategory":"Engineering",
            "type":"Services"
        }
    ],
    "sg:phone":"+1 608 835 9009",
    "sg:postcode":"53575",
    "sg:province":"WI",
    "sg:tags":[
        "consultant",
        "electrical"
    ],
    "sg:website":"www.forstereng.com",
    "wof:name":"Forster Electrical Engineering",
    "wof:placetype":"venue"
},
  "geometry": {"coordinates":[-89.387619,42.931042],"type":"Point"}
}