{
  "type": "Feature",
  "properties": {
    "iso:country":"US",
    "sg:address":"5401 W Burleigh St",
    "sg:city":"Milwaukee",
    "sg:classifiers":[
        {
            "category":"Retail",
            "subcategory":"Auto Repair",
            "type":"Services"
        }
    ],
    "sg:phone":"+1 414 447 9929",
    "sg:postcode":"53210",
    "sg:province":"WI",
    "sg:tags":[
        "repairing",
        "automobile"
    ],
    "wof:name":"Nemi Auto Care Inc",
    "wof:placetype":"venue"
},
  "geometry": {"coordinates":[-87.982006,43.075307],"type":"Point"}
}