{
  "type": "Feature",
  "properties": {
    "iso:country":"US",
    "sg:address":"1223 170th Ave",
    "sg:city":"Balsam Lake",
    "sg:classifiers":[
        {
            "category":"Manufacturing",
            "subcategory":"Furniture",
            "type":"Manufacturing & Wholesale Goods"
        }
    ],
    "sg:phone":"+1 715 268 7650",
    "sg:postcode":"54810",
    "sg:province":"WI",
    "sg:tags":[
        "wood",
        "household",
        "des",
        "commercial",
        "mfg"
    ],
    "wof:name":"Once Upon An Idea LLC",
    "wof:placetype":"venue"
},
  "geometry": {"coordinates":[-92.411675,45.453796],"type":"Point"}
}