{
  "type": "Feature",
  "properties": {
    "iso:country":"US",
    "sg:address":"621 Vine St",
    "sg:city":"Hudson",
    "sg:classifiers":[
        {
            "category":"Building & Trades",
            "subcategory":"Construction",
            "type":"Services"
        }
    ],
    "sg:phone":"+1 715 497 2968",
    "sg:postcode":"54016",
    "sg:province":"WI",
    "sg:tags":[
        "development",
        "property"
    ],
    "wof:name":"Kareem R Ingram LLC",
    "wof:placetype":"venue"
},
  "geometry": {"coordinates":[-92.750626,44.977108],"type":"Point"}
}