{
  "type": "Feature",
  "properties": {
    "iso:country":"US",
    "sg:address":"912 N Hawley Rd",
    "sg:city":"Milwaukee",
    "sg:classifiers":[
        {
            "category":"Government",
            "subcategory":"Office",
            "type":"Public Place"
        }
    ],
    "sg:phone":"+1 414 302 2762",
    "sg:postcode":"53213",
    "sg:province":"WI",
    "wof:name":"Supportive Living Div",
    "wof:placetype":"venue"
},
  "geometry": {"coordinates":[-87.982745,43.042182],"type":"Point"}
}