{
  "type": "Feature",
  "properties": {
    "iso:country":"US",
    "sg:address":"216 Green Bay Rd",
    "sg:city":"Thiensville",
    "sg:classifiers":[
        {
            "category":"Health Services",
            "subcategory":"Doctor",
            "type":"Services"
        }
    ],
    "sg:phone":"+1 262 241 9131",
    "sg:postcode":"53092",
    "sg:province":"WI",
    "wof:name":"Reyes Michele DO",
    "wof:placetype":"venue"
},
  "geometry": {"coordinates":[-87.981481,43.234424],"type":"Point"}
}