{
  "type": "Feature",
  "properties": {
    "iso:country":"US",
    "sg:address":"2969 S Howell Ave",
    "sg:city":"Milwaukee",
    "sg:classifiers":[
        {
            "category":"Education",
            "subcategory":"School",
            "type":"Public Place"
        }
    ],
    "sg:phone":"+1 414 294 1000",
    "sg:postcode":"53207",
    "sg:province":"WI",
    "sg:tags":[
        "middle",
        "combined"
    ],
    "wof:name":"Fritsche leap Middle School",
    "wof:placetype":"venue"
},
  "geometry": {"coordinates":[-87.904324,42.990798],"type":"Point"}
}