{
  "type": "Feature",
  "properties": {
    "addr:full":"338 W College Ave Appleton WI 54911",
    "addr:housenumber":"338",
    "addr:postcode":"54911",
    "addr:street":"W College Ave",
    "iso:country":"US",
    "sg:address":"338 W College Ave",
    "sg:city":"Appleton",
    "sg:classifiers":[
        {
            "category":"Organizations",
            "subcategory":"Professional Association",
            "type":"Services"
        },
        {
            "category":"Insurance",
            "subcategory":"Insurance Agent",
            "type":"Services"
        }
    ],
    "sg:phone":"+1 920 733 8086",
    "sg:postcode":"54911",
    "sg:province":"WI",
    "sg:tags":[
        "broker"
    ],
    "wof:name":"National Assn Of Self Employed",
    "wof:placetype":"venue"
},
  "geometry": {"coordinates":[-88.41022700000001,44.261894],"type":"Point"}
}