{
  "type": "Feature",
  "properties": {
    "addr:full":"6101 S 27th St Milwaukee WI 53221",
    "addr:housenumber":"6101",
    "addr:postcode":"53221",
    "addr:street":"S 27Th St",
    "iso:country":"US",
    "sg:address":"6101 S 27th St",
    "sg:city":"Milwaukee",
    "sg:classifiers":[
        {
            "category":"Autos & Motor Vehicles",
            "subcategory":"Auto Supplies",
            "type":"Retail Goods"
        }
    ],
    "sg:phone":"+1 414 282 2390",
    "sg:postcode":"53221",
    "sg:province":"WI",
    "sg:tags":[
        "automotive",
        "parts"
    ],
    "sg:website":"www.borchardtspeed.com",
    "wof:name":"Borchardt Speed Automotive",
    "wof:placetype":"venue"
},
  "geometry": {"coordinates":[-87.949337,42.932674],"type":"Point"}
}