{
  "type": "Feature",
  "properties": {
    "iso:country":"US",
    "sg:address":"2009 S 96th St",
    "sg:city":"Milwaukee",
    "sg:classifiers":[
        {
            "category":"Retail",
            "subcategory":"Portrait Studio",
            "type":"Services"
        }
    ],
    "sg:phone":"+1 414 328 1408",
    "sg:postcode":"53227",
    "sg:province":"WI",
    "sg:tags":[
        "photo"
    ],
    "wof:name":"Kk Photography LLC",
    "wof:placetype":"venue"
},
  "geometry": {"coordinates":[-88.032152,43.006408],"type":"Point"}
}