{
  "type": "Feature",
  "properties": {
    "addr:full":"757 N Water St Milwaukee WI 53202",
    "addr:housenumber":"757",
    "addr:postcode":"53202",
    "addr:street":"N Water St",
    "iso:country":"US",
    "sg:address":"757 N Water St",
    "sg:city":"Milwaukee",
    "sg:classifiers":[
        {
            "category":"Real Estate",
            "subcategory":"Developer",
            "type":"Services"
        }
    ],
    "sg:phone":"+1 414 272 2274",
    "sg:postcode":"53202",
    "sg:province":"WI",
    "wof:name":"Dermond Associates LLC",
    "wof:placetype":"venue"
},
  "geometry": {"coordinates":[-87.909379,43.040035],"type":"Point"}
}