{
  "type": "Feature",
  "properties": {
    "iso:country":"US",
    "sg:address":"4253 N Broadway Rd",
    "sg:city":"Bonduel",
    "sg:classifiers":[
        {
            "category":"Farming",
            "subcategory":"Dairy Farm",
            "type":"Manufacturing & Wholesale Goods"
        }
    ],
    "sg:phone":"+1 715 758 8004",
    "sg:postcode":"54107",
    "sg:province":"WI",
    "wof:name":"D and Acres",
    "wof:placetype":"venue"
},
  "geometry": {"coordinates":[-88.38443,44.736986],"type":"Point"}
}