{
  "type": "Feature",
  "properties": {
    "iso:country":"US",
    "sg:address":"420 W Sunset Ave",
    "sg:city":"Appleton",
    "sg:classifiers":[
        {
            "category":"Government",
            "subcategory":"Office",
            "type":"Public Place"
        }
    ],
    "sg:phone":"+1 920 738 9311",
    "sg:postcode":"54911",
    "sg:province":"WI",
    "sg:tags":[
        "state",
        "program",
        "health"
    ],
    "wof:name":"PRN Health Svc",
    "wof:placetype":"venue"
},
  "geometry": {"coordinates":[-88.415355,44.293778],"type":"Point"}
}