{
  "type": "Feature",
  "properties": {
    "iso:country":"US",
    "sg:address":"951 E Elizabeth St",
    "sg:city":"Shawano",
    "sg:classifiers":[
        {
            "category":"Government",
            "subcategory":"Office",
            "type":"Public Place"
        }
    ],
    "sg:phone":"+1 715 524 2132",
    "sg:postcode":"54166",
    "sg:province":"WI",
    "sg:tags":[
        "village"
    ],
    "wof:name":"Shawano City Housing",
    "wof:placetype":"venue"
},
  "geometry": {"coordinates":[-88.597003,44.772831],"type":"Point"}
}