{
  "type": "Feature",
  "properties": {
    "iso:country":"US",
    "sg:address":"1924 W Meyer Ln",
    "sg:city":"Oak Creek",
    "sg:classifiers":[
        {
            "category":"Real Estate",
            "subcategory":"Real Estate Agent",
            "type":"Services"
        }
    ],
    "sg:phone":"+1 414 840 4055",
    "sg:postcode":"53154",
    "sg:province":"WI",
    "sg:tags":[
        "residential",
        "property",
        "management",
        "sales",
        "internet"
    ],
    "wof:name":"ML Enterprise",
    "wof:placetype":"venue"
},
  "geometry": {"coordinates":[-87.94248899999999,42.876108],"type":"Point"}
}