{
  "type": "Feature",
  "properties": {
    "iso:country":"US",
    "sg:address":"2623 8th St",
    "sg:city":"Two Rivers",
    "sg:classifiers":[
        {
            "category":"Personal",
            "subcategory":"Beauty Salon",
            "type":"Services"
        }
    ],
    "sg:phone":"+1 920 793 2311",
    "sg:postcode":"54241",
    "sg:province":"WI",
    "sg:tags":[
        "shop"
    ],
    "wof:name":"Vue Hair Salon",
    "wof:placetype":"venue"
},
  "geometry": {"coordinates":[-87.584974,44.140795],"type":"Point"}
}