{
  "type": "Feature",
  "properties": {
    "iso:country":"US",
    "sg:address":"250 Bishops Way",
    "sg:city":"Brookfield",
    "sg:classifiers":[
        {
            "category":"Social Services",
            "type":"Services"
        }
    ],
    "sg:phone":"+1 262 787 8033",
    "sg:postcode":"53005",
    "sg:province":"WI",
    "sg:tags":[
        "instruction",
        "health",
        "care"
    ],
    "sg:website":"www.pathwayhealth.com",
    "wof:name":"Pathway Health Svc",
    "wof:placetype":"venue"
},
  "geometry": {"coordinates":[-88.079309,43.033747],"type":"Point"}
}