{
  "type": "Feature",
  "properties": {
    "iso:country":"US",
    "sg:address":"22650 Washington St",
    "sg:city":"Ettrick",
    "sg:classifiers":[
        {
            "category":"Organizations",
            "subcategory":"Religious Organization",
            "type":"Services"
        }
    ],
    "sg:phone":"+1 608 525 3811",
    "sg:postcode":"54627",
    "sg:province":"WI",
    "sg:tags":[
        "church"
    ],
    "wof:name":"St Bridget's Catholic Church",
    "wof:placetype":"venue"
},
  "geometry": {"coordinates":[-91.267135,44.166723],"type":"Point"}
}