{
  "type": "Feature",
  "properties": {
    "iso:country":"US",
    "sg:address":"817 N Marshall St",
    "sg:city":"Milwaukee",
    "sg:classifiers":[
        {
            "category":"Building & Trades",
            "subcategory":"Landscaping Services",
            "type":"Services"
        }
    ],
    "sg:phone":"+1 414 289 9033",
    "sg:postcode":"53202",
    "sg:province":"WI",
    "sg:tags":[
        "lawn",
        "maintenance",
        "grounds"
    ],
    "wof:name":"Grass Roots Campaigns",
    "wof:placetype":"venue"
},
  "geometry": {"coordinates":[-87.900722,43.042707],"type":"Point"}
}