{
  "type": "Feature",
  "properties": {
    "iso:country":"US",
    "sg:address":"812 W Beacon Ave",
    "sg:city":"New London",
    "sg:classifiers":[
        {
            "category":"Retail",
            "subcategory":"Portrait Studio",
            "type":"Services"
        }
    ],
    "sg:phone":"+1 920 982 0799",
    "sg:postcode":"54961",
    "sg:province":"WI",
    "sg:tags":[
        "photographer"
    ],
    "wof:name":"All Seasons Photo",
    "wof:placetype":"venue"
},
  "geometry": {"coordinates":[-88.74782999999999,44.388246],"type":"Point"}
}