{
  "type": "Feature",
  "properties": {
    "iso:country":"US",
    "sg:address":"835 Custer Ave",
    "sg:city":"Sheboygan",
    "sg:classifiers":[
        {
            "category":"Insurance",
            "subcategory":"Life Insurance",
            "type":"Services"
        }
    ],
    "sg:phone":"+1 920 458 1523",
    "sg:postcode":"53081",
    "sg:province":"WI",
    "sg:tags":[
        "carrier"
    ],
    "wof:name":"Sons of Norway",
    "wof:placetype":"venue"
},
  "geometry": {"coordinates":[-87.714343,43.726869],"type":"Point"}
}