{
  "type": "Feature",
  "properties": {
    "iso:country":"US",
    "sg:address":"5050 S Lake Dr",
    "sg:city":"Cudahy",
    "sg:classifiers":[
        {
            "category":"Government",
            "subcategory":"Police Station",
            "type":"Public Place"
        }
    ],
    "sg:phone":"+1 414 769 2260",
    "sg:postcode":"53110",
    "sg:province":"WI",
    "sg:tags":[
        "department",
        "protection"
    ],
    "wof:name":"Cudahy Police Department",
    "wof:placetype":"venue"
},
  "geometry": {"coordinates":[-87.850116,42.954733],"type":"Point"}
}