{
  "type": "Feature",
  "properties": {
    "iso:country":"US",
    "sg:address":"12000 W Carmen Ave",
    "sg:city":"Milwaukee",
    "sg:classifiers":[
        {
            "category":"Manufacturing",
            "subcategory":"Tools & Machinery",
            "type":"Manufacturing & Wholesale Goods"
        }
    ],
    "sg:phone":"+1 414 462 1300",
    "sg:postcode":"53225",
    "sg:province":"WI",
    "sg:tags":[
        "ophthalmic"
    ],
    "sg:website":"www.herslof.com",
    "wof:name":"Herslof Opticians",
    "wof:placetype":"venue"
},
  "geometry": {"coordinates":[-88.064916,43.122571],"type":"Point"}
}