{
  "type": "Feature",
  "properties": {
    "iso:country":"US",
    "sg:address":"1263 Main St",
    "sg:city":"Green Bay",
    "sg:classifiers":[
        {
            "category":"Professional",
            "subcategory":"Computer Services",
            "type":"Services"
        }
    ],
    "sg:phone":"+1 920 432 0360",
    "sg:postcode":"54302",
    "sg:province":"WI",
    "sg:tags":[
        "hardware",
        "provider",
        "internet",
        "software"
    ],
    "sg:website":"www.netsonic.net",
    "wof:name":"Netsonic",
    "wof:placetype":"venue"
},
  "geometry": {"coordinates":[-87.99614099999999,44.511],"type":"Point"}
}