{
  "type": "Feature",
  "properties": {
    "iso:country":"US",
    "sg:address":"7309 Zander Rd",
    "sg:city":"Sun Prairie",
    "sg:classifiers":[
        {
            "category":"Farming",
            "subcategory":"Dairy Farm",
            "type":"Manufacturing & Wholesale Goods"
        }
    ],
    "sg:phone":"+1 608 837 2728",
    "sg:postcode":"53590",
    "sg:province":"WI",
    "sg:tags":[
        "field",
        "corn",
        "grain",
        "cash",
        "crop"
    ],
    "wof:name":"Zander Farms Inc",
    "wof:placetype":"venue"
},
  "geometry": {"coordinates":[-89.157573,43.248301],"type":"Point"}
}