{
  "type": "Feature",
  "properties": {
    "iso:country":"US",
    "sg:address":"9013 E Biller Loop",
    "sg:city":"Solon Springs",
    "sg:classifiers":[
        {
            "category":"Retail",
            "subcategory":"Funeral Services",
            "type":"Services"
        }
    ],
    "sg:phone":"+1 715 378 2291",
    "sg:postcode":"54873",
    "sg:province":"WI",
    "sg:tags":[
        "director"
    ],
    "wof:name":"Brown Funeral Homes",
    "wof:placetype":"venue"
},
  "geometry": {"coordinates":[-91.824871,46.341701],"type":"Point"}
}