{
  "type": "Feature",
  "properties": {
    "iso:country":"US",
    "sg:address":"607 Planeview Dr",
    "sg:city":"Palmyra",
    "sg:classifiers":[
        {
            "category":"Professional",
            "subcategory":"Management & Consulting",
            "type":"Services"
        }
    ],
    "sg:phone":"+1 262 495 3108",
    "sg:postcode":"53156",
    "sg:province":"WI",
    "sg:tags":[
        "unknown",
        "business",
        "classification"
    ],
    "wof:name":"Around The Corner",
    "wof:placetype":"venue"
},
  "geometry": {"coordinates":[-88.59587,42.882272],"type":"Point"}
}