{
  "type": "Feature",
  "properties": {
    "iso:country":"US",
    "sg:address":"10130 W Appleton Ave",
    "sg:city":"Milwaukee",
    "sg:classifiers":[
        {
            "category":"Health Services",
            "subcategory":"Doctor",
            "type":"Services"
        }
    ],
    "sg:phone":"+1 414 393 0600",
    "sg:postcode":"53225",
    "sg:province":"WI",
    "sg:tags":[
        "physician",
        "surgeon"
    ],
    "wof:name":"Kidney Institute-Wi Northwest",
    "wof:placetype":"venue"
},
  "geometry": {"coordinates":[-88.039793,43.123103],"type":"Point"}
}