{
  "type": "Feature",
  "properties": {
    "addr:full":"1205 West St Wausau WI 54401",
    "addr:housenumber":"1205",
    "addr:postcode":"54401",
    "addr:street":"West St",
    "iso:country":"US",
    "sg:address":"1205 West St",
    "sg:city":"Wausau",
    "sg:classifiers":[
        {
            "category":"Freight",
            "type":"Transportation"
        }
    ],
    "sg:phone":"+1 715 849 9593",
    "sg:postcode":"54401",
    "sg:province":"WI",
    "sg:tags":[
        "operator",
        "trucking"
    ],
    "wof:name":"Vitran Express Inc",
    "wof:placetype":"venue"
},
  "geometry": {"coordinates":[-89.655423,44.953656],"type":"Point"}
}