{
  "type": "Feature",
  "properties": {
    "iso:country":"US",
    "sg:address":"1626 11th St",
    "sg:city":"Monroe",
    "sg:classifiers":[
        {
            "category":"Shopping",
            "subcategory":"Florist",
            "type":"Retail Goods"
        }
    ],
    "sg:phone":"+1 608 325 5421",
    "sg:postcode":"53566",
    "sg:province":"WI",
    "wof:name":"Monroe Floral Shop",
    "wof:placetype":"venue"
},
  "geometry": {"coordinates":[-89.639554,42.601063],"type":"Point"}
}