{
  "type": "Feature",
  "properties": {
    "iso:country":"US",
    "sg:address":"1639 Commanche Ave",
    "sg:city":"Green Bay",
    "sg:classifiers":[
        {
            "category":"Travel",
            "subcategory":"Hotels & Motels",
            "type":"Entertainment"
        },
        {
            "category":"Real Estate",
            "subcategory":"Real Estate Operator",
            "type":"Services"
        }
    ],
    "sg:phone":"+1 920 499 3600",
    "sg:postcode":"54313",
    "sg:province":"WI",
    "sg:tags":[
        "operation",
        "apartment"
    ],
    "sg:website":"www.extendedstaygreenbay.com",
    "wof:name":"Extended Stay Airports",
    "wof:placetype":"venue"
},
  "geometry": {"coordinates":[-88.10504400000001,44.492541],"type":"Point"}
}