{
  "type": "Feature",
  "properties": {
    "addr:full":"627 N Lake St Madison WI 53703",
    "addr:housenumber":"627",
    "addr:postcode":"53703",
    "addr:street":"N Lake St",
    "iso:country":"US",
    "sg:address":"627 N Lake St",
    "sg:city":"Madison",
    "sg:classifiers":[
        {
            "category":"Organizations",
            "subcategory":"Community Association",
            "type":"Services"
        }
    ],
    "sg:phone":"+1 608 256 8822",
    "sg:postcode":"53703",
    "sg:province":"WI",
    "sg:tags":[
        "sorority",
        "fraternity"
    ],
    "wof:name":"Sigma Alpha Epsilon",
    "wof:placetype":"venue"
},
  "geometry": {"coordinates":[-89.39722999999999,43.076845],"type":"Point"}
}