{
  "type": "Feature",
  "properties": {
    "iso:country":"US",
    "sg:address":"7650 Co Rd Y",
    "sg:city":"Sheboygan",
    "sg:classifiers":[
        {
            "category":"Shopping",
            "subcategory":"Used Merchandise",
            "type":"Retail Goods"
        }
    ],
    "sg:phone":"+1 920 565 3612",
    "sg:postcode":"53083",
    "sg:province":"WI",
    "wof:name":"Three Barns Full One",
    "wof:placetype":"venue"
},
  "geometry": {"coordinates":[-87.780925,43.819038],"type":"Point"}
}