{
  "type": "Feature",
  "properties": {
    "iso:country":"US",
    "sg:address":"2350 S Oneida St",
    "sg:city":"Green Bay",
    "sg:classifiers":[
        {
            "category":"Home & Garden",
            "subcategory":"Furniture",
            "type":"Retail Goods"
        }
    ],
    "sg:phone":"+1 920 499 0808",
    "sg:postcode":"54304",
    "sg:province":"WI",
    "sg:website":"www.ethanallen.com",
    "wof:name":"Ethan Allen Home Interiors",
    "wof:placetype":"venue"
},
  "geometry": {"coordinates":[-88.065758,44.48916],"type":"Point"}
}