{
  "type": "Feature",
  "properties": {
    "iso:country":"US",
    "sg:address":"20918 Wildflower Ln",
    "sg:city":"Richland Center",
    "sg:classifiers":[
        {
            "category":"Professional",
            "subcategory":"Research",
            "type":"Services"
        }
    ],
    "sg:phone":"+1 608 647 6769",
    "sg:postcode":"53581",
    "sg:province":"WI",
    "sg:tags":[
        "contract"
    ],
    "wof:name":"Quantum Fields LLC",
    "wof:placetype":"venue"
},
  "geometry": {"coordinates":[-90.459726,43.394751],"type":"Point"}
}