{
  "type": "Feature",
  "properties": {
    "iso:country":"US",
    "sg:address":"1109 Park St",
    "sg:city":"Stevens Point",
    "sg:classifiers":[
        {
            "category":"Bars & Pubs",
            "type":"Food & Drink"
        }
    ],
    "sg:phone":"+1 715 341 9669",
    "sg:postcode":"54481",
    "sg:province":"WI",
    "wof:name":"Big Todds",
    "wof:placetype":"venue"
},
  "geometry": {"coordinates":[-89.57657,44.513676],"type":"Point"}
}