{
  "type": "Feature",
  "properties": {
    "iso:country":"US",
    "sg:address":"4806 Academy Dr",
    "sg:city":"Madison",
    "sg:classifiers":[
        {
            "category":"Professional",
            "type":"Services"
        }
    ],
    "sg:phone":"+1 608 222 3953",
    "sg:postcode":"53716",
    "sg:province":"WI",
    "wof:name":"William Rameker",
    "wof:placetype":"venue"
},
  "geometry": {"coordinates":[-89.295926,43.078051],"type":"Point"}
}