{
  "type": "Feature",
  "properties": {
    "iso:country":"US",
    "sg:address":"1786 Allen Rd",
    "sg:city":"Browntown",
    "sg:classifiers":[
        {
            "category":"Farming",
            "subcategory":"Livestock Farm",
            "type":"Manufacturing & Wholesale Goods"
        }
    ],
    "sg:phone":"+1 608 966 3255",
    "sg:postcode":"53522",
    "sg:province":"WI",
    "sg:tags":[
        "feedlot",
        "hog",
        "or",
        "beef",
        "cattle"
    ],
    "wof:name":"William and Glenda Endrulat",
    "wof:placetype":"venue"
},
  "geometry": {"coordinates":[-89.759574,42.56431],"type":"Point"}
}