{
  "type": "Feature",
  "properties": {
    "iso:country":"US",
    "sg:address":"427 State Hwy 35",
    "sg:city":"Somerset",
    "sg:classifiers":[
        {
            "category":"Freight",
            "type":"Transportation"
        }
    ],
    "sg:phone":"+1 715 247 2626",
    "sg:postcode":"54025",
    "sg:province":"WI",
    "sg:tags":[
        "trucking"
    ],
    "wof:name":"Ristow Trucking Inc",
    "wof:placetype":"venue"
},
  "geometry": {"coordinates":[-92.67251,45.135844],"type":"Point"}
}