{
  "type": "Feature",
  "properties": {
    "iso:country":"US",
    "sg:address":"125 7th St N",
    "sg:city":"La Crosse",
    "sg:classifiers":[
        {
            "category":"Shopping",
            "subcategory":"Bicycles & Sporting Goods",
            "type":"Retail Goods"
        }
    ],
    "sg:phone":"+1 608 784 1175",
    "sg:postcode":"54601",
    "sg:province":"WI",
    "sg:website":"www.smithsbikes.com",
    "wof:name":"Smith's Cycling & Fitness",
    "wof:placetype":"venue"
},
  "geometry": {"coordinates":[-91.24670399999999,43.812726],"type":"Point"}
}