{
  "type": "Feature",
  "properties": {
    "addr:full":"8431 W Keefe Ave Milwaukee WI 53222",
    "addr:housenumber":"8431",
    "addr:postcode":"53222",
    "addr:street":"W Keefe Ave",
    "iso:country":"US",
    "sg:address":"8431 W Keefe Ave",
    "sg:city":"Milwaukee",
    "sg:classifiers":[
        {
            "category":"Building & Trades",
            "subcategory":"Plumbing",
            "type":"Services"
        }
    ],
    "sg:phone":"+1 414 464 9544",
    "sg:postcode":"53222",
    "sg:province":"WI",
    "sg:tags":[
        "contractor"
    ],
    "wof:name":"Laumanns Economy Htg & Coolg",
    "wof:placetype":"venue"
},
  "geometry": {"coordinates":[-88.01849199999999,43.082418],"type":"Point"}
}