{
  "type": "Feature",
  "properties": {
    "iso:country":"US",
    "sg:address":"6531 W North Ave",
    "sg:city":"Milwaukee",
    "sg:classifiers":[
        {
            "category":"Building & Trades",
            "subcategory":"Construction",
            "type":"Services"
        }
    ],
    "sg:phone":"+1 414 453 4220",
    "sg:postcode":"53213",
    "sg:province":"WI",
    "sg:tags":[
        "bathroom",
        "planning",
        "remodeling",
        "kitchen"
    ],
    "sg:website":"http://www.kitchensaver.net",
    "wof:name":"Kitchen Saver Inc",
    "wof:placetype":"venue"
},
  "geometry": {"coordinates":[-87.993979,43.060741],"type":"Point"}
}