{
  "type": "Feature",
  "properties": {
    "iso:country":"US",
    "sg:address":"400 S 69th St",
    "sg:city":"Milwaukee",
    "sg:classifiers":[
        {
            "category":"Real Estate",
            "subcategory":"Real Estate Agent",
            "type":"Services"
        }
    ],
    "sg:phone":"+1 414 476 9757",
    "sg:postcode":"53214",
    "sg:province":"WI",
    "wof:name":"Rl Motorsports",
    "wof:placetype":"venue"
},
  "geometry": {"coordinates":[-87.99867999999999,43.026025],"type":"Point"}
}