{
  "type": "Feature",
  "properties": {
    "iso:country":"US",
    "sg:address":"8371 Heintown Rd",
    "sg:city":"Neillsville",
    "sg:classifiers":[
        {
            "category":"Wholesale",
            "subcategory":"Meat",
            "type":"Manufacturing & Wholesale Goods"
        }
    ],
    "sg:phone":"+1 715 743 3808",
    "sg:postcode":"54456",
    "sg:province":"WI",
    "sg:tags":[
        "farm",
        "veal",
        "calf"
    ],
    "wof:name":"Dean Lis",
    "wof:placetype":"venue"
},
  "geometry": {"coordinates":[-90.735325,44.668447],"type":"Point"}
}