{
  "type": "Feature",
  "properties": {
    "iso:country":"US",
    "sg:address":"2413 W Mitchell St",
    "sg:city":"Milwaukee",
    "sg:classifiers":[
        {
            "category":"Food & Beverages",
            "subcategory":"Groceries & Convenience Stores",
            "type":"Retail Goods"
        }
    ],
    "sg:phone":"+1 414 389 9386",
    "sg:postcode":"53204",
    "sg:province":"WI",
    "sg:tags":[
        "grocer"
    ],
    "wof:name":"Hughes Food Mart",
    "wof:placetype":"venue"
},
  "geometry": {"coordinates":[-87.944956,43.012383],"type":"Point"}
}