{
  "type": "Feature",
  "properties": {
    "iso:country":"US",
    "sg:address":"995 S Sawyer Rd",
    "sg:city":"Oconomowoc",
    "sg:classifiers":[
        {
            "category":"Education",
            "subcategory":"School",
            "type":"Public Place"
        }
    ],
    "sg:phone":"+1 262 965 5178",
    "sg:postcode":"53066",
    "sg:province":"WI",
    "wof:name":"Abundant Life Christn Academy",
    "wof:placetype":"venue"
},
  "geometry": {"coordinates":[-88.44274299999999,43.02147],"type":"Point"}
}