{
  "type": "Feature",
  "properties": {
    "iso:country":"US",
    "sg:address":"3552 Stewart Ave",
    "sg:city":"Wausau",
    "sg:classifiers":[
        {
            "category":"Professional",
            "subcategory":"Lawyer & Legal Services",
            "type":"Services"
        }
    ],
    "sg:phone":"+1 715 842 2088",
    "sg:postcode":"54401",
    "sg:province":"WI",
    "sg:tags":[
        "attorney"
    ],
    "wof:name":"Mary Hogue Law Office",
    "wof:placetype":"venue"
},
  "geometry": {"coordinates":[-89.679137,44.95552],"type":"Point"}
}