{
  "type": "Feature",
  "properties": {
    "iso:country":"US",
    "sg:address":"816 Armour Rd",
    "sg:city":"Oconomowoc",
    "sg:classifiers":[
        {
            "category":"Wholesale",
            "subcategory":"Hardware",
            "type":"Manufacturing & Wholesale Goods"
        },
        {
            "category":"Building & Trades",
            "subcategory":"Plumbing",
            "type":"Services"
        }
    ],
    "sg:phone":"+1 262 567 8666",
    "sg:postcode":"53066",
    "sg:province":"WI",
    "sg:tags":[
        "household",
        "parts",
        "refrigerating",
        "contractor"
    ],
    "wof:name":"Tim's Refrigeration Inc",
    "wof:placetype":"venue"
},
  "geometry": {"coordinates":[-88.48502999999999,43.104503],"type":"Point"}
}