{
  "type": "Feature",
  "properties": {
    "iso:country":"US",
    "sg:address":"37214 Valley Rd",
    "sg:city":"Oconomowoc",
    "sg:classifiers":[
        {
            "category":"Manufacturing",
            "subcategory":"Printing",
            "type":"Manufacturing & Wholesale Goods"
        }
    ],
    "sg:phone":"+1 262 567 5889",
    "sg:postcode":"53066",
    "sg:province":"WI",
    "sg:tags":[
        "printer"
    ],
    "wof:name":"Elite Printing",
    "wof:placetype":"venue"
},
  "geometry": {"coordinates":[-88.484509,43.077734],"type":"Point"}
}