{
  "type": "Feature",
  "properties": {
    "iso:country":"US",
    "sg:address":"116 W Hamilton St",
    "sg:city":"West Salem",
    "sg:classifiers":[
        {
            "category":"Shopping",
            "subcategory":"Used Merchandise",
            "type":"Retail Goods"
        }
    ],
    "sg:phone":"+1 608 786 1116",
    "sg:postcode":"54669",
    "sg:province":"WI",
    "wof:name":"Closet To Closet",
    "wof:placetype":"venue"
},
  "geometry": {"coordinates":[-91.082516,43.89705],"type":"Point"}
}