{
  "type": "Feature",
  "properties": {
    "iso:country":"US",
    "sg:address":"2039 Industrial Dr",
    "sg:city":"Kaukauna",
    "sg:classifiers":[
        {
            "category":"Home & Garden",
            "subcategory":"Building Materials",
            "type":"Retail Goods"
        }
    ],
    "sg:phone":"+1 920 788 3774",
    "sg:postcode":"54130",
    "sg:province":"WI",
    "sg:tags":[
        "glass",
        "window",
        "plate"
    ],
    "wof:name":"Rick's Auto Glass",
    "wof:placetype":"venue"
},
  "geometry": {"coordinates":[-88.288213,44.376421],"type":"Point"}
}