{
  "type": "Feature",
  "properties": {
    "iso:country":"US",
    "sg:address":"307 Main St",
    "sg:city":"Black River Fls",
    "sg:classifiers":[
        {
            "category":"Government",
            "subcategory":"Office",
            "type":"Public Place"
        }
    ],
    "sg:phone":"+1 715 284 0201",
    "sg:postcode":"54615",
    "sg:province":"WI",
    "sg:tags":[
        "county"
    ],
    "sg:website":"www.co.jackson.wi.us",
    "wof:name":"Jackson County Clerk",
    "wof:placetype":"venue"
},
  "geometry": {"coordinates":[-90.851976,44.295061],"type":"Point"}
}