{
  "type": "Feature",
  "properties": {
    "iso:country":"US",
    "sg:address":"1107 4th St S",
    "sg:city":"La Crosse",
    "sg:classifiers":[
        {
            "category":"Wholesale",
            "subcategory":"Non-durable Goods",
            "type":"Manufacturing & Wholesale Goods"
        }
    ],
    "sg:phone":"+1 608 782 9613",
    "sg:postcode":"54601",
    "sg:province":"WI",
    "sg:tags":[
        "glass",
        "product",
        "etched"
    ],
    "wof:name":"Northland Distributors",
    "wof:placetype":"venue"
},
  "geometry": {"coordinates":[-91.251779,43.801563],"type":"Point"}
}