{
  "type": "Feature",
  "properties": {
    "iso:country":"US",
    "sg:address":"12120 W Wirth St",
    "sg:city":"Milwaukee",
    "sg:classifiers":[
        {
            "category":"Wholesale",
            "subcategory":"Machinery & Supplies",
            "type":"Manufacturing & Wholesale Goods"
        },
        {
            "category":"Building & Trades",
            "subcategory":"Equipment Rental",
            "type":"Services"
        }
    ],
    "sg:phone":"+1 414 463 5438",
    "sg:postcode":"53222",
    "sg:province":"WI",
    "sg:tags":[
        "heavy",
        "construction",
        "contractor"
    ],
    "wof:name":"Ideal Crane Rental Inc",
    "wof:placetype":"venue"
},
  "geometry": {"coordinates":[-88.063985,43.083832],"type":"Point"}
}