{
  "type": "Feature",
  "properties": {
    "addr:full":"600 Moore Rd Plover WI 54467",
    "addr:housenumber":"600",
    "addr:postcode":"54467",
    "addr:street":"Moore Rd",
    "iso:country":"US",
    "sg:address":"600 Moore Rd",
    "sg:city":"Plover",
    "sg:classifiers":[
        {
            "category":"Government",
            "subcategory":"Office",
            "type":"Public Place"
        }
    ],
    "sg:phone":"+1 715 345 5972",
    "sg:postcode":"54467",
    "sg:province":"WI",
    "sg:tags":[
        "county",
        "program"
    ],
    "wof:name":"Recycling Education Office",
    "wof:placetype":"venue"
},
  "geometry": {"coordinates":[-89.50008099999999,44.455643],"type":"Point"}
}