{
  "type": "Feature",
  "properties": {
    "iso:country":"US",
    "sg:address":"5448 N 13th St",
    "sg:city":"Milwaukee",
    "sg:classifiers":[
        {
            "category":"Shopping",
            "subcategory":"Bicycles & Sporting Goods",
            "type":"Retail Goods"
        }
    ],
    "sg:phone":"+1 414 228 9792",
    "sg:postcode":"53209",
    "sg:province":"WI",
    "wof:name":"Power Up U S A",
    "wof:placetype":"venue"
},
  "geometry": {"coordinates":[-87.92643,43.116568],"type":"Point"}
}