{
  "type": "Feature",
  "properties": {
    "iso:country":"US",
    "sg:address":"492 Hill St",
    "sg:city":"Green Lake",
    "sg:classifiers":[
        {
            "category":"Government",
            "subcategory":"Court House",
            "type":"Public Place"
        }
    ],
    "sg:phone":"+1 920 294 4142",
    "sg:postcode":"54941",
    "sg:province":"WI",
    "sg:tags":[
        "county"
    ],
    "wof:name":"Green Lake Clerk-Circuit Court",
    "wof:placetype":"venue"
},
  "geometry": {"coordinates":[-88.95993300000001,43.845265],"type":"Point"}
}