{
  "type": "Feature",
  "properties": {
    "iso:country":"US",
    "sg:address":"7622 US Hwy 63",
    "sg:city":"Spring Valley",
    "sg:classifiers":[
        {
            "category":"Manufacturing",
            "subcategory":"Glass & Minerals",
            "type":"Manufacturing & Wholesale Goods"
        }
    ],
    "sg:phone":"+1 715 273 3572",
    "sg:postcode":"54767",
    "sg:province":"WI",
    "sg:tags":[
        "concrete",
        "mfg"
    ],
    "wof:name":"M B & Boys Inc",
    "wof:placetype":"venue"
},
  "geometry": {"coordinates":[-92.410849,44.817084],"type":"Point"}
}