{
  "type": "Feature",
  "properties": {
    "iso:country":"US",
    "sg:address":"2233 S Business Dr",
    "sg:city":"Sheboygan",
    "sg:classifiers":[
        {
            "category":"Retail",
            "subcategory":"Auto Repair",
            "type":"Services"
        }
    ],
    "sg:phone":"+1 920 457 4407",
    "sg:postcode":"53081",
    "sg:province":"WI",
    "sg:tags":[
        "repairing",
        "automobile"
    ],
    "wof:name":"Bret's Towing & Auto Repair",
    "wof:placetype":"venue"
},
  "geometry": {"coordinates":[-87.73058899999999,43.730168],"type":"Point"}
}