{
  "type": "Feature",
  "properties": {
    "iso:country":"US",
    "sg:address":"3120 85th St",
    "sg:city":"Kenosha",
    "sg:classifiers":[
        {
            "category":"Professional",
            "subcategory":"Management & Consulting",
            "type":"Services"
        }
    ],
    "sg:phone":"+1 262 412 3558",
    "sg:postcode":"53142",
    "sg:province":"IL",
    "wof:name":"Turner Group The",
    "wof:placetype":"venue"
},
  "geometry": {"coordinates":[-87.845627,42.551592],"type":"Point"}
}