{
  "type": "Feature",
  "properties": {
    "iso:country":"US",
    "sg:address":"1275 200th Ave",
    "sg:city":"Milltown",
    "sg:classifiers":[
        {
            "category":"Building & Trades",
            "subcategory":"Construction",
            "type":"Services"
        }
    ],
    "sg:phone":"+1 715 825 3832",
    "sg:postcode":"54858",
    "sg:province":"WI",
    "sg:tags":[
        "general",
        "contractor"
    ],
    "wof:name":"R & D Handyman & Contracting",
    "wof:placetype":"venue"
},
  "geometry": {"coordinates":[-92.419259,45.501982],"type":"Point"}
}