{
  "type": "Feature",
  "properties": {
    "addr:full":"15453 Co Rd B Hayward WI 54843",
    "addr:housenumber":"15453",
    "addr:postcode":"54843",
    "addr:street":"Co Rd",
    "iso:country":"US",
    "sg:address":"15453 Co Rd B",
    "sg:city":"Hayward",
    "sg:classifiers":[
        {
            "category":"Organizations",
            "subcategory":"Non-profit Organization",
            "type":"Services"
        }
    ],
    "sg:phone":"+1 715 634 3185",
    "sg:postcode":"54843",
    "sg:province":"WI",
    "sg:tags":[
        "disability"
    ],
    "wof:name":"Fishing Has No Boundaries Inc",
    "wof:placetype":"venue"
},
  "geometry": {"coordinates":[-91.468384,46.004806],"type":"Point"}
}