{
  "type": "Feature",
  "properties": {
    "addr:full":"1303 W State Highway 153 Mosinee WI 54455",
    "addr:housenumber":"1303",
    "addr:postcode":"54455",
    "addr:street":"W State Highway 153",
    "iso:country":"US",
    "sg:address":"1303 W State Highway 153",
    "sg:city":"Mosinee",
    "sg:classifiers":[
        {
            "category":"Restaurant",
            "type":"Food & Drink"
        }
    ],
    "sg:phone":"+1 715 693 7222",
    "sg:postcode":"54455",
    "sg:province":"WI",
    "sg:tags":[
        "grill",
        "bar"
    ],
    "wof:name":"Hog Creek Bar & Grill",
    "wof:placetype":"venue"
},
  "geometry": {"coordinates":[-89.76849,44.791886],"type":"Point"}
}