{
  "type": "Feature",
  "properties": {
    "iso:country":"US",
    "sg:address":"3304 Wilgus Ave",
    "sg:city":"Sheboygan",
    "sg:classifiers":[
        {
            "category":"Restaurant",
            "type":"Food & Drink"
        }
    ],
    "sg:phone":"+1 920 452 3600",
    "sg:postcode":"53081",
    "sg:province":"WI",
    "sg:website":"www.pitstoppizzainc.com",
    "wof:name":"Pit Stop Pizza",
    "wof:placetype":"venue"
},
  "geometry": {"coordinates":[-87.753422,43.758837],"type":"Point"}
}