{
  "type": "Feature",
  "properties": {
    "addr:full":"757 Sommers St N Hudson WI 54016",
    "addr:housenumber":"757",
    "addr:postcode":"54016",
    "addr:street":"Sommers St N",
    "iso:country":"US",
    "sg:address":"757 Sommers St N",
    "sg:city":"Hudson",
    "sg:classifiers":[
        {
            "category":"Wholesale",
            "subcategory":"Hardware",
            "type":"Manufacturing & Wholesale Goods"
        }
    ],
    "sg:phone":"+1 715 381 1036",
    "sg:postcode":"54016",
    "sg:province":"WI",
    "sg:tags":[
        "fastener",
        "industrial",
        "maintenance"
    ],
    "wof:name":"Endries International Inc",
    "wof:placetype":"venue"
},
  "geometry": {"coordinates":[-92.752444,45.001255],"type":"Point"}
}