{
  "type": "Feature",
  "properties": {
    "iso:country":"US",
    "sg:address":"1019 11th Ave",
    "sg:city":"Grafton",
    "sg:classifiers":[
        {
            "category":"Professional",
            "type":"Services"
        }
    ],
    "sg:phone":"+1 262 377 3010",
    "sg:postcode":"53024",
    "sg:province":"WI",
    "sg:tags":[
        "establishment"
    ],
    "wof:name":"Richard J Goldberg LLC",
    "wof:placetype":"venue"
},
  "geometry": {"coordinates":[-87.953128,43.321957],"type":"Point"}
}