{
  "type": "Feature",
  "properties": {
    "addr:full":"1734 Suburban Dr De Pere WI 54115",
    "addr:housenumber":"1734",
    "addr:postcode":"54115",
    "addr:street":"Suburban Dr",
    "iso:country":"US",
    "sg:address":"1734 Suburban Dr",
    "sg:city":"De Pere",
    "sg:classifiers":[
        {
            "category":"Wholesale",
            "subcategory":"Stationery",
            "type":"Manufacturing & Wholesale Goods"
        }
    ],
    "sg:phone":"+1 920 330 0100",
    "sg:postcode":"54115",
    "sg:province":"WI",
    "sg:tags":[
        "product",
        "paper"
    ],
    "wof:name":"Millie's Products",
    "wof:placetype":"venue"
},
  "geometry": {"coordinates":[-88.087785,44.428689],"type":"Point"}
}