{
  "type": "Feature",
  "properties": {
    "iso:country":"US",
    "sg:address":"2155 Holmgren Way",
    "sg:city":"Green Bay",
    "sg:classifiers":[
        {
            "category":"Government",
            "subcategory":"Office",
            "type":"Public Place"
        }
    ],
    "sg:phone":"+1 920 492 2312",
    "sg:postcode":"54304",
    "sg:province":"WI",
    "sg:tags":[
        "civil",
        "defense",
        "agency"
    ],
    "wof:name":"Ashwaubenon Public Safety Dept",
    "wof:placetype":"venue"
},
  "geometry": {"coordinates":[-88.057302,44.492579],"type":"Point"}
}