{
  "type": "Feature",
  "properties": {
    "iso:country":"US",
    "sg:address":"1010 Scenic Ct",
    "sg:city":"Oshkosh",
    "sg:classifiers":[
        {
            "category":"Recreation",
            "subcategory":"Marina",
            "type":"Entertainment"
        }
    ],
    "sg:phone":"+1 920 231 9936",
    "sg:postcode":"54904",
    "sg:province":"WI",
    "sg:tags":[
        "operation"
    ],
    "wof:name":"Ludwigs Marina Ltd",
    "wof:placetype":"venue"
},
  "geometry": {"coordinates":[-88.611515,44.027494],"type":"Point"}
}