{
  "type": "Feature",
  "properties": {
    "iso:country":"US",
    "sg:address":"28006 Rippchen Ln",
    "sg:city":"Richland Center",
    "sg:classifiers":[
        {
            "category":"Farming",
            "subcategory":"Livestock Farm",
            "type":"Manufacturing & Wholesale Goods"
        }
    ],
    "sg:phone":"+1 608 585 4014",
    "sg:postcode":"53581",
    "sg:province":"WI",
    "sg:tags":[
        "animal",
        "general"
    ],
    "wof:name":"Allen Rippchen",
    "wof:placetype":"venue"
},
  "geometry": {"coordinates":[-90.310352,43.393029],"type":"Point"}
}