{
  "type": "Feature",
  "properties": {
    "iso:country":"US",
    "sg:address":"13111 N Port Washington Rd",
    "sg:city":"Mequon",
    "sg:classifiers":[
        {
            "category":"Health Services",
            "subcategory":"Hospital",
            "type":"Services"
        },
        {
            "category":"Health Services",
            "subcategory":"Doctor",
            "type":"Services"
        }
    ],
    "sg:phone":"+1 262 243 7300",
    "sg:postcode":"53097",
    "sg:province":"WI",
    "sg:tags":[
        "clinic",
        "general"
    ],
    "wof:name":"St Mary's Hospital Ozaukee",
    "wof:placetype":"venue"
},
  "geometry": {"coordinates":[-87.924251,43.259403],"type":"Point"}
}