{
  "type": "Feature",
  "properties": {
    "iso:country":"US",
    "sg:address":"8371 Drake Rd",
    "sg:city":"Viola",
    "sg:classifiers":[
        {
            "category":"Farming",
            "subcategory":"Dairy Farm",
            "type":"Manufacturing & Wholesale Goods"
        }
    ],
    "sg:phone":"+1 608 538 3161",
    "sg:postcode":"54664",
    "sg:province":"WI",
    "wof:name":"Darrell Clark",
    "wof:placetype":"venue"
},
  "geometry": {"coordinates":[-90.673533,43.425202],"type":"Point"}
}