{
  "type": "Feature",
  "properties": {
    "addr:full":"3812 W Villard Ave Milwaukee WI 53209",
    "addr:housenumber":"3812",
    "addr:postcode":"53209",
    "addr:street":"W Villard Ave",
    "iso:country":"US",
    "sg:address":"3812 W Villard Ave",
    "sg:city":"Milwaukee",
    "sg:classifiers":[
        {
            "category":"Autos & Motor Vehicles",
            "subcategory":"Auto Supplies",
            "type":"Retail Goods"
        }
    ],
    "sg:phone":"+1 414 438 9630",
    "sg:postcode":"53209",
    "sg:province":"WI",
    "wof:name":"B and D Tires",
    "wof:placetype":"venue"
},
  "geometry": {"coordinates":[-87.960793,43.112014],"type":"Point"}
}