{
  "type": "Feature",
  "properties": {
    "iso:country":"US",
    "sg:address":"8680 Pigeon River Rd",
    "sg:city":"Cassville",
    "sg:classifiers":[
        {
            "category":"Farming",
            "subcategory":"Dairy Farm",
            "type":"Manufacturing & Wholesale Goods"
        }
    ],
    "sg:phone":"+1 608 794 2107",
    "sg:postcode":"53806",
    "sg:province":"WI",
    "wof:name":"Keith Miles",
    "wof:placetype":"venue"
},
  "geometry": {"coordinates":[-90.850514,42.760986],"type":"Point"}
}