{
  "type": "Feature",
  "properties": {
    "iso:country":"US",
    "sg:address":"155 S Main St",
    "sg:city":"Iola",
    "sg:classifiers":[
        {
            "category":"Utilities",
            "subcategory":"Telephone",
            "type":"Services"
        }
    ],
    "sg:phone":"+1 715 445 3711",
    "sg:postcode":"54945",
    "sg:province":"WI",
    "sg:tags":[
        "company"
    ],
    "wof:name":"TDS Telecom",
    "wof:placetype":"venue"
},
  "geometry": {"coordinates":[-89.13086800000001,44.506598],"type":"Point"}
}