{
  "type": "Feature",
  "properties": {
    "addr:full":"2698 Co Hwy I Saukville WI 53080",
    "addr:housenumber":"2698",
    "addr:postcode":"53080",
    "addr:street":"Co Hwy I",
    "iso:country":"US",
    "sg:address":"2698 Co Hwy I",
    "sg:city":"Saukville",
    "sg:classifiers":[
        {
            "category":"Wholesale",
            "subcategory":"Machinery & Supplies",
            "type":"Manufacturing & Wholesale Goods"
        }
    ],
    "sg:phone":"+1 262 284 0058",
    "sg:postcode":"53080",
    "sg:province":"WI",
    "sg:tags":[
        "equipment",
        "industrial"
    ],
    "wof:name":"Garys Machinery Sales",
    "wof:placetype":"venue"
},
  "geometry": {"coordinates":[-87.980113,43.378675],"type":"Point"}
}