{
  "type": "Feature",
  "properties": {
    "iso:country":"US",
    "sg:address":"2312 Wilson Lima Rd",
    "sg:city":"Oostburg",
    "sg:phone":"+1 920 564 2290",
    "sg:postcode":"53070",
    "sg:province":"WI",
    "sg:tags":[
        "neon",
        "sign"
    ],
    "wof:name":"Ten Pas Sign Co",
    "wof:placetype":"venue"
},
  "geometry": {"coordinates":[-87.80998700000001,43.644895],"type":"Point"}
}