{
  "type": "Feature",
  "properties": {
    "iso:country":"US",
    "sg:address":"10324 N Sunnycrest Dr",
    "sg:city":"Thiensville",
    "sg:classifiers":[
        {
            "category":"Manufacturing",
            "subcategory":"Metals",
            "type":"Manufacturing & Wholesale Goods"
        }
    ],
    "sg:phone":"+1 262 242 1720",
    "sg:postcode":"53092",
    "sg:province":"WI",
    "sg:tags":[
        "cylinder",
        "hydraulic",
        "mfg"
    ],
    "wof:name":"Northland Cylinder Co",
    "wof:placetype":"venue"
},
  "geometry": {"coordinates":[-87.931816,43.203976],"type":"Point"}
}