{
  "type": "Feature",
  "properties": {
    "iso:country":"US",
    "sg:address":"5960 State Rd 70",
    "sg:city":"Webster",
    "sg:classifiers":[
        {
            "category":"Building & Trades",
            "subcategory":"Construction",
            "type":"Services"
        }
    ],
    "sg:phone":"+1 715 349 2569",
    "sg:postcode":"54893",
    "sg:province":"WI",
    "sg:tags":[
        "paving",
        "contractor"
    ],
    "wof:name":"Taylor Paving Inc",
    "wof:placetype":"venue"
},
  "geometry": {"coordinates":[-92.295572,45.827374],"type":"Point"}
}