{
  "type": "Feature",
  "properties": {
    "iso:country":"US",
    "sg:address":"2200 E Racine St",
    "sg:city":"Janesville",
    "sg:classifiers":[
        {
            "category":"Government",
            "subcategory":"Office",
            "type":"Public Place"
        }
    ],
    "sg:phone":"+1 608 756 9938",
    "sg:postcode":"53545",
    "sg:province":"WI",
    "sg:tags":[
        "legislative",
        "body"
    ],
    "wof:name":"Palmer Park Tennis Courts",
    "wof:placetype":"venue"
},
  "geometry": {"coordinates":[-88.994055,42.675591],"type":"Point"}
}