{
  "type": "Feature",
  "properties": {
    "addr:full":"730 Prospect St Poy Sippi WI 54967",
    "addr:housenumber":"730",
    "addr:postcode":"54967",
    "addr:street":"Prospect St",
    "iso:country":"US",
    "sg:address":"730 Prospect St",
    "sg:city":"Poy Sippi",
    "sg:classifiers":[
        {
            "category":"Government",
            "subcategory":"Office",
            "type":"Public Place"
        }
    ],
    "sg:phone":"+1 920 987 5341",
    "sg:postcode":"54967",
    "sg:province":"WI",
    "sg:tags":[
        "executive"
    ],
    "wof:name":"Highway Department",
    "wof:placetype":"venue"
},
  "geometry": {"coordinates":[-88.997445,44.139116],"type":"Point"}
}