{
  "type": "Feature",
  "properties": {
    "iso:country":"US",
    "sg:address":"4510 200th Ave",
    "sg:city":"Bristol",
    "sg:classifiers":[
        {
            "category":"Travel",
            "subcategory":"Hotels & Motels",
            "type":"Entertainment"
        }
    ],
    "sg:phone":"+1 262 857 2396",
    "sg:postcode":"53104",
    "sg:province":"WI",
    "sg:tags":[
        "operation"
    ],
    "wof:name":"Bristol Motel",
    "wof:placetype":"venue"
},
  "geometry": {"coordinates":[-88.050845,42.582919],"type":"Point"}
}