{
  "type": "Feature",
  "properties": {
    "iso:country":"US",
    "sg:address":"84830 Siskiwit Lake Dr",
    "sg:city":"Cornucopia",
    "sg:classifiers":[
        {
            "category":"Professional",
            "type":"Services"
        }
    ],
    "sg:phone":"+1 715 742 3276",
    "sg:postcode":"54827",
    "sg:province":"WI",
    "wof:name":"Dale Soltis",
    "wof:placetype":"venue"
},
  "geometry": {"coordinates":[-91.114073,46.800867],"type":"Point"}
}