{
  "type": "Feature",
  "properties": {
    "iso:country":"US",
    "sg:address":"3303 Grand Seasons Dr",
    "sg:city":"Waupaca",
    "sg:classifiers":[
        {
            "category":"Retail",
            "subcategory":"Auto Repair",
            "type":"Services"
        }
    ],
    "sg:phone":"+1 715 258 6030",
    "sg:postcode":"54981",
    "sg:province":"WI",
    "sg:tags":[
        "truck",
        "general"
    ],
    "wof:name":"S & S Trucking Equipment",
    "wof:placetype":"venue"
},
  "geometry": {"coordinates":[-89.123198,44.360353],"type":"Point"}
}