{
  "type": "Feature",
  "properties": {
    "iso:country":"US",
    "sg:address":"1325 Greenway Cross",
    "sg:city":"Madison",
    "sg:classifiers":[
        {
            "category":"Organizations",
            "subcategory":"Religious Organization",
            "type":"Services"
        }
    ],
    "sg:phone":"+1 608 277 0803",
    "sg:postcode":"53713",
    "sg:province":"WI",
    "wof:name":"Chu Vang",
    "wof:placetype":"venue"
},
  "geometry": {"coordinates":[-89.40852,43.031326],"type":"Point"}
}