{
  "type": "Feature",
  "properties": {
    "iso:country":"US",
    "sg:address":"1825 S Riverside Dr",
    "sg:city":"Beloit",
    "sg:classifiers":[
        {
            "category":"Restaurant",
            "type":"Food & Drink"
        }
    ],
    "sg:phone":"+1 608 361 1455",
    "sg:postcode":"53511",
    "sg:province":"IL",
    "sg:tags":[
        "eating"
    ],
    "wof:name":"Riverside Family Restaurant",
    "wof:placetype":"venue"
},
  "geometry": {"coordinates":[-89.034634,42.523114],"type":"Point"}
}