{
  "type": "Feature",
  "properties": {
    "addr:full":"9000 N White Oak Ln Milwaukee WI 53217",
    "addr:housenumber":"9000",
    "addr:postcode":"53217",
    "addr:street":"N White Oak Ln",
    "iso:country":"US",
    "sg:address":"9000 N White Oak Ln",
    "sg:city":"Milwaukee",
    "sg:classifiers":[
        {
            "category":"Home & Garden",
            "subcategory":"Building Materials",
            "type":"Retail Goods"
        },
        {
            "category":"Building & Trades",
            "subcategory":"Construction",
            "type":"Services"
        }
    ],
    "sg:phone":"+1 414 351 4609",
    "sg:postcode":"53217",
    "sg:province":"WI",
    "sg:tags":[
        "roofing",
        "industrial",
        "altering",
        "improvement",
        "contractors-commercial",
        "contractor",
        "remodeling"
    ],
    "wof:name":"Batt's Roofing Company",
    "wof:placetype":"venue"
},
  "geometry": {"coordinates":[-87.914368,43.180349],"type":"Point"}
}