{
  "type": "Feature",
  "properties": {
    "addr:full":"8373 S 42nd St Franklin WI 53132",
    "addr:housenumber":"8373",
    "addr:postcode":"53132",
    "addr:street":"S 42Nd St",
    "iso:country":"US",
    "sg:address":"8373 S 42nd St",
    "sg:city":"Franklin",
    "sg:classifiers":[
        {
            "category":"Building & Trades",
            "subcategory":"Plumbing",
            "type":"Services"
        }
    ],
    "sg:phone":"+1 414 423 8000",
    "sg:postcode":"53132",
    "sg:province":"WI",
    "sg:tags":[
        "plumbing",
        "contractor"
    ],
    "wof:name":"Magnum Plumbing Inc",
    "wof:placetype":"venue"
},
  "geometry": {"coordinates":[-87.969605,42.890958],"type":"Point"}
}