{
  "type": "Feature",
  "properties": {
    "addr:full":"643 S Clay St Green Bay WI 54301",
    "addr:housenumber":"643",
    "addr:postcode":"54301",
    "addr:street":"S Clay St",
    "iso:country":"US",
    "sg:address":"643 S Clay St",
    "sg:city":"Green Bay",
    "sg:classifiers":[
        {
            "category":"Health Services",
            "subcategory":"Clinic",
            "type":"Services"
        },
        {
            "category":"Social Services",
            "subcategory":"Job Training",
            "type":"Services"
        }
    ],
    "sg:phone":"+1 920 437 1487",
    "sg:postcode":"54301",
    "sg:province":"WI",
    "sg:tags":[
        "rehabilitation",
        "outpatient",
        "specialty"
    ],
    "wof:name":"Vocational Consulting Services",
    "wof:placetype":"venue"
},
  "geometry": {"coordinates":[-88.008331,44.502774],"type":"Point"}
}