{
  "type": "Feature",
  "properties": {
    "iso:country":"US",
    "sg:address":"117 29th St",
    "sg:city":"New Auburn",
    "sg:classifiers":[
        {
            "category":"Farming",
            "subcategory":"Dairy Farm",
            "type":"Manufacturing & Wholesale Goods"
        }
    ],
    "sg:phone":"+1 715 237 2258",
    "sg:postcode":"54757",
    "sg:province":"WI",
    "wof:name":"Clyde Brekken",
    "wof:placetype":"venue"
},
  "geometry": {"coordinates":[-91.562168,45.233474],"type":"Point"}
}