{
  "type": "Feature",
  "properties": {
    "iso:country":"US",
    "sg:address":"307 Sheffield Rd",
    "sg:city":"Waukesha",
    "sg:classifiers":[
        {
            "category":"Wholesale",
            "subcategory":"Stationery",
            "type":"Manufacturing & Wholesale Goods"
        }
    ],
    "sg:phone":"+1 262 544 0080",
    "sg:postcode":"53186",
    "sg:province":"WI",
    "sg:tags":[
        "business",
        "form",
        "system"
    ],
    "wof:name":"Proforma Inc",
    "wof:placetype":"venue"
},
  "geometry": {"coordinates":[-88.203108,42.997068],"type":"Point"}
}