{
  "type": "Feature",
  "properties": {
    "addr:full":"13462 Co Hwy D Boyd WI 54726",
    "addr:housenumber":"13462",
    "addr:postcode":"54726",
    "addr:street":"Co Hwy D Boyd",
    "iso:country":"US",
    "sg:address":"13462 Co Hwy D",
    "sg:city":"Boyd",
    "sg:classifiers":[
        {
            "category":"Farming",
            "subcategory":"Dairy Farm",
            "type":"Manufacturing & Wholesale Goods"
        }
    ],
    "sg:phone":"+1 715 289 3848",
    "sg:postcode":"54726",
    "sg:province":"WI",
    "wof:name":"Larry Scheidler",
    "wof:placetype":"venue"
},
  "geometry": {"coordinates":[-91.045114,45.03443],"type":"Point"}
}