{
  "type": "Feature",
  "properties": {
    "iso:country":"US",
    "sg:address":"276 S Falls St",
    "sg:city":"River Falls",
    "sg:classifiers":[
        {
            "category":"Professional",
            "subcategory":"Research",
            "type":"Services"
        }
    ],
    "sg:phone":"+1 715 425 6011",
    "sg:postcode":"54022",
    "sg:province":"WI",
    "sg:tags":[
        "commercial",
        "physical"
    ],
    "wof:name":"Microbasics Inc",
    "wof:placetype":"venue"
},
  "geometry": {"coordinates":[-92.63346799999999,44.856989],"type":"Point"}
}