{
  "type": "Feature",
  "properties": {
    "iso:country":"US",
    "sg:address":"907 Gohres St",
    "sg:city":"La Crosse",
    "sg:classifiers":[
        {
            "category":"Shopping",
            "subcategory":"Beauty & Cosmetics",
            "type":"Retail Goods"
        }
    ],
    "sg:phone":"+1 608 781 6543",
    "sg:postcode":"54603",
    "sg:province":"WI",
    "sg:tags":[
        "merchandise"
    ],
    "wof:name":"Hembd Ellyn",
    "wof:placetype":"venue"
},
  "geometry": {"coordinates":[-91.24261,43.849259],"type":"Point"}
}