{
  "type": "Feature",
  "properties": {
    "iso:country":"US",
    "sg:address":"926 Union Ave",
    "sg:city":"Sheboygan",
    "sg:classifiers":[
        {
            "category":"Social Services",
            "subcategory":"Adult Care",
            "type":"Services"
        }
    ],
    "sg:phone":"+1 920 452 3444",
    "sg:postcode":"53081",
    "sg:province":"WI",
    "sg:tags":[
        "residential"
    ],
    "wof:name":"Rabideaux Adult Family Home",
    "wof:placetype":"venue"
},
  "geometry": {"coordinates":[-87.716003,43.732004],"type":"Point"}
}