{
  "type": "Feature",
  "properties": {
    "iso:country":"US",
    "sg:address":"9021 S 42nd St",
    "sg:city":"Franklin",
    "sg:classifiers":[
        {
            "category":"Building & Trades",
            "subcategory":"Plumbing",
            "type":"Services"
        }
    ],
    "sg:phone":"+1 414 761 9422",
    "sg:postcode":"53132",
    "sg:province":"WI",
    "sg:tags":[
        "contractor"
    ],
    "wof:name":"Barber Plumbing Inc",
    "wof:placetype":"venue"
},
  "geometry": {"coordinates":[-87.969498,42.882301],"type":"Point"}
}