{
  "type": "Feature",
  "properties": {
    "iso:country":"US",
    "sg:address":"3213 W Lapham St",
    "sg:city":"Milwaukee",
    "sg:classifiers":[
        {
            "category":"Organizations",
            "subcategory":"Religious Organization",
            "type":"Services"
        }
    ],
    "sg:phone":"+1 414 384 4060",
    "sg:postcode":"53215",
    "sg:province":"WI",
    "wof:name":"Imanuell Lutheran Church",
    "wof:placetype":"venue"
},
  "geometry": {"coordinates":[-87.955097,43.014026],"type":"Point"}
}