{
  "type": "Feature",
  "properties": {
    "iso:country":"US",
    "sg:address":"2115 Polk St",
    "sg:city":"Janesville",
    "sg:classifiers":[
        {
            "category":"Building & Trades",
            "subcategory":"Construction",
            "type":"Services"
        }
    ],
    "sg:phone":"+1 608 752 9307",
    "sg:postcode":"53546",
    "sg:province":"WI",
    "sg:tags":[
        "handyman"
    ],
    "wof:name":"Everts Home Repair",
    "wof:placetype":"venue"
},
  "geometry": {"coordinates":[-89.01565600000001,42.646057],"type":"Point"}
}