{
  "type": "Feature",
  "properties": {
    "addr:full":"2701 E Winslow Ave Appleton WI 54911",
    "addr:housenumber":"2701",
    "addr:postcode":"54911",
    "addr:street":"E Winslow Ave",
    "iso:country":"US",
    "sg:address":"2701 E Winslow Ave",
    "sg:city":"Appleton",
    "sg:classifiers":[
        {
            "category":"Manufacturing",
            "subcategory":"Tools & Machinery",
            "type":"Manufacturing & Wholesale Goods"
        }
    ],
    "sg:phone":"+1 920 993 0640",
    "sg:postcode":"54911",
    "sg:province":"WI",
    "sg:tags":[
        "machine",
        "shop",
        "job"
    ],
    "sg:website":"www.atozmachine.com",
    "wof:name":"A To Z Machine Co",
    "wof:placetype":"venue"
},
  "geometry": {"coordinates":[-88.363545,44.288968],"type":"Point"}
}