{
  "type": "Feature",
  "properties": {
    "addr:full":"1 Hewett St Neillsville WI 54456",
    "addr:housenumber":"1",
    "addr:postcode":"54456",
    "addr:street":"Hewett St",
    "iso:country":"US",
    "sg:address":"1 Hewett St",
    "sg:city":"Neillsville",
    "sg:classifiers":[
        {
            "category":"Building & Trades",
            "subcategory":"Electrical",
            "type":"Services"
        }
    ],
    "sg:phone":"+1 715 743 4920",
    "sg:postcode":"54456",
    "sg:province":"WI",
    "sg:tags":[
        "booth",
        "equipment",
        "telephone",
        "pay"
    ],
    "wof:name":"Mid America Payphone Inc",
    "wof:placetype":"venue"
},
  "geometry": {"coordinates":[-90.59629700000001,44.554932],"type":"Point"}
}