{
  "type": "Feature",
  "properties": {
    "iso:country":"US",
    "sg:address":"107 N 2nd St",
    "sg:city":"Waterford",
    "sg:classifiers":[
        {
            "category":"Shopping",
            "subcategory":"Hobbies, Toys, & Games",
            "type":"Retail Goods"
        },
        {
            "category":"Shopping",
            "subcategory":"Gifts & Souvenirs",
            "type":"Retail Goods"
        }
    ],
    "sg:phone":"+1 262 662 0742",
    "sg:postcode":"53185",
    "sg:province":"WI",
    "sg:tags":[
        "collectible"
    ],
    "wof:name":"Ty's Toys",
    "wof:placetype":"venue"
},
  "geometry": {"coordinates":[-88.211627,42.764482],"type":"Point"}
}