{
  "type": "Feature",
  "properties": {
    "iso:country":"US",
    "sg:address":"2500 S Maywood Ave",
    "sg:city":"Marshfield",
    "sg:classifiers":[
        {
            "category":"Autos & Motor Vehicles",
            "subcategory":"Automobile Sales",
            "type":"Retail Goods"
        }
    ],
    "sg:phone":"+1 715 387 4824",
    "sg:postcode":"54449",
    "sg:province":"WI",
    "sg:tags":[
        "repair",
        "used",
        "general"
    ],
    "wof:name":"Badger Motors Inc",
    "wof:placetype":"venue"
},
  "geometry": {"coordinates":[-90.163643,44.644755],"type":"Point"}
}