{
  "type": "Feature",
  "properties": {
    "addr:full":"6482 Co Rd K Chippewa Falls WI 54729",
    "addr:housenumber":"6482",
    "addr:postcode":"54729",
    "addr:street":"Co Rd",
    "iso:country":"US",
    "sg:address":"6482 Co Rd K",
    "sg:city":"Chippewa Falls",
    "sg:classifiers":[
        {
            "category":"Recreation",
            "type":"Entertainment"
        }
    ],
    "sg:phone":"+1 715 289 4440",
    "sg:postcode":"54729",
    "sg:province":"WI",
    "sg:tags":[
        "parachute",
        "skydiving",
        "jumping"
    ],
    "wof:name":"Indianhead Skydivers",
    "wof:placetype":"venue"
},
  "geometry": {"coordinates":[-91.267976,44.936823],"type":"Point"}
}