{
  "type": "Feature",
  "properties": {
    "iso:country":"US",
    "sg:address":"379 Deer Vally Dr",
    "sg:city":"Hudson",
    "sg:classifiers":[
        {
            "category":"Professional",
            "subcategory":"Business Services",
            "type":"Services"
        }
    ],
    "sg:phone":"+1 715 377 0948",
    "sg:postcode":"54016",
    "sg:province":"WI",
    "wof:name":"Micro Netic Systems",
    "wof:placetype":"venue"
},
  "geometry": {"coordinates":[-92.72395400000001,44.914521],"type":"Point"}
}