{
  "type": "Feature",
  "properties": {
    "iso:country":"US",
    "sg:address":"6920 Co Rd Bb",
    "sg:city":"Appleton",
    "sg:classifiers":[
        {
            "category":"Recreation",
            "type":"Entertainment"
        }
    ],
    "sg:phone":"+1 920 991 9732",
    "sg:postcode":"54914",
    "sg:province":"WI",
    "sg:tags":[
        "hall",
        "auditorium"
    ],
    "wof:name":"South Greenville Grange Hall",
    "wof:placetype":"venue"
},
  "geometry": {"coordinates":[-88.52570299999999,44.244018],"type":"Point"}
}