{
  "type": "Feature",
  "properties": {
    "addr:full":"401 Milwaukee Ave Burlington WI 53105",
    "addr:housenumber":"401",
    "addr:postcode":"53105",
    "addr:street":"Milwaukee Ave",
    "iso:country":"US",
    "sg:address":"401 Milwaukee Ave",
    "sg:city":"Burlington",
    "sg:classifiers":[
        {
            "category":"Building & Trades",
            "subcategory":"Equipment Rental",
            "type":"Services"
        },
        {
            "category":"Home & Garden",
            "subcategory":"Hardware",
            "type":"Retail Goods"
        }
    ],
    "sg:phone":"+1 262 763 3577",
    "sg:postcode":"53105",
    "sg:province":"WI",
    "sg:tags":[
        "yard",
        "store"
    ],
    "wof:name":"Reineman's True Value Hardware Inc",
    "wof:placetype":"venue"
},
  "geometry": {"coordinates":[-88.27889999999999,42.6791],"type":"Point"}
}