{
  "type": "Feature",
  "properties": {
    "addr:full":"3420 E Calumet St Appleton WI 54915",
    "addr:housenumber":"3420",
    "addr:postcode":"54915",
    "addr:street":"E Calumet St",
    "iso:country":"US",
    "sg:address":"3420 E Calumet St",
    "sg:city":"Appleton",
    "sg:classifiers":[
        {
            "category":"Ice Cream",
            "type":"Food & Drink"
        }
    ],
    "sg:menulink":"http://www.allmenus.com/wi/appleton/184489-cold-stone-creamery/menu/",
    "sg:phone":"+1 920 954 9865",
    "sg:postcode":"54915",
    "sg:province":"WI",
    "sg:tags":[
        "smoothy",
        "juice",
        "american"
    ],
    "wof:name":"Cold Stone Creamery",
    "wof:placetype":"venue"
},
  "geometry": {"coordinates":[-88.369231,44.243908],"type":"Point"}
}