{
  "type": "Feature",
  "properties": {
    "iso:country":"US",
    "sg:address":"4008 Velp Ave",
    "sg:city":"Green Bay",
    "sg:classifiers":[
        {
            "category":"Home & Garden",
            "subcategory":"Hardware",
            "type":"Retail Goods"
        }
    ],
    "sg:phone":"+1 920 661 4060",
    "sg:postcode":"54313",
    "sg:province":"WI",
    "wof:name":"Fastenal Co",
    "wof:placetype":"venue"
},
  "geometry": {"coordinates":[-88.07787,44.588781],"type":"Point"}
}