{
  "type": "Feature",
  "properties": {
    "iso:country":"US",
    "sg:address":"35512 Washington Ave",
    "sg:city":"Honey Creek",
    "sg:classifiers":[
        {
            "category":"Organizations",
            "subcategory":"Religious Organization",
            "type":"Services"
        }
    ],
    "sg:phone":"+1 262 534 3585",
    "sg:postcode":"53138",
    "sg:province":"WI",
    "wof:name":"Honey Creek Community Baptist Church & Hall",
    "wof:placetype":"venue"
},
  "geometry": {"coordinates":[-88.30680099999999,42.7192],"type":"Point"}
}