{
  "type": "Feature",
  "properties": {
    "iso:country":"US",
    "sg:address":"1222 Henrietta St",
    "sg:city":"Wausau",
    "sg:classifiers":[
        {
            "category":"Education",
            "subcategory":"Dance Studio",
            "type":"Public Place"
        }
    ],
    "sg:phone":"+1 715 845 7100",
    "sg:postcode":"54403",
    "sg:province":"WI",
    "wof:name":"Heidis Dance Studio",
    "wof:placetype":"venue"
},
  "geometry": {"coordinates":[-89.61126899999999,44.953446],"type":"Point"}
}