{
  "type": "Feature",
  "properties": {
    "iso:country":"US",
    "sg:address":"1645 Grandview Rd",
    "sg:city":"Green Bay",
    "sg:classifiers":[
        {
            "category":"Building & Trades",
            "subcategory":"Construction",
            "type":"Services"
        }
    ],
    "sg:phone":"+1 920 468 8881",
    "sg:postcode":"54311",
    "sg:province":"WI",
    "sg:tags":[
        "home",
        "contractor",
        "improvement"
    ],
    "wof:name":"Mike Grasse Siding Co",
    "wof:placetype":"venue"
},
  "geometry": {"coordinates":[-87.896813,44.469115],"type":"Point"}
}