{
  "type": "Feature",
  "properties": {
    "addr:full":"10401 W Lincoln Ave # 101 Milwaukee WI 53227",
    "addr:housenumber":"10401",
    "addr:postcode":"53227",
    "addr:street":"W Lincoln Ave # 101",
    "iso:country":"US",
    "sg:address":"10401 W Lincoln Ave # 101",
    "sg:city":"Milwaukee",
    "sg:classifiers":[
        {
            "category":"Health Services",
            "subcategory":"Dentist",
            "type":"Services"
        }
    ],
    "sg:phone":"+1 414 327 4130",
    "sg:postcode":"53227",
    "sg:province":"WI",
    "wof:name":"Oral Surgery Associates Of Southeastern Wisconsin Ltd",
    "wof:placetype":"venue"
},
  "geometry": {"coordinates":[-88.04243099999999,43.002535],"type":"Point"}
}