{
  "type": "Feature",
  "properties": {
    "iso:country":"US",
    "sg:address":"969 Goddard Way",
    "sg:city":"Green Bay",
    "sg:classifiers":[
        {
            "category":"Building & Trades",
            "subcategory":"Electrical",
            "type":"Services"
        }
    ],
    "sg:phone":"+1 920 391 1300",
    "sg:postcode":"54311",
    "sg:province":"WI",
    "sg:tags":[
        "electrical",
        "contractor"
    ],
    "sg:website":"www.jandrinelectric.com",
    "wof:name":"Jandrin Electric Inc",
    "wof:placetype":"venue"
},
  "geometry": {"coordinates":[-87.93022999999999,44.484191],"type":"Point"}
}