{
  "type": "Feature",
  "properties": {
    "iso:country":"US",
    "sg:address":"20930 Lakewood Dr",
    "sg:city":"Grantsburg",
    "sg:classifiers":[
        {
            "category":"Wholesale",
            "subcategory":"Hardware",
            "type":"Manufacturing & Wholesale Goods"
        }
    ],
    "sg:phone":"+1 715 327 4410",
    "sg:postcode":"54840",
    "sg:province":"WI",
    "sg:tags":[
        "plumbing"
    ],
    "wof:name":"Aqua-Man Water Specialists",
    "wof:placetype":"venue"
},
  "geometry": {"coordinates":[-92.607933,45.675895],"type":"Point"}
}