{
  "type": "Feature",
  "properties": {
    "addr:full":"2900 N 58th St Milwaukee WI 53210",
    "addr:housenumber":"2900",
    "addr:postcode":"53210",
    "addr:street":"N 58Th St",
    "iso:country":"US",
    "sg:address":"2900 N 58th St",
    "sg:city":"Milwaukee",
    "sg:classifiers":[
        {
            "category":"Social Services",
            "type":"Services"
        }
    ],
    "sg:phone":"+1 414 875 9651",
    "sg:postcode":"53210",
    "sg:province":"WI",
    "sg:tags":[
        "care",
        "center",
        "day"
    ],
    "wof:name":"Children's Kingdom Learning",
    "wof:placetype":"venue"
},
  "geometry": {"coordinates":[-87.98510899999999,43.07351],"type":"Point"}
}