{
  "type": "Feature",
  "properties": {
    "iso:country":"US",
    "sg:address":"1307 Woodman Rd",
    "sg:city":"Janesville",
    "sg:classifiers":[
        {
            "category":"Food & Beverages",
            "subcategory":"Groceries & Convenience Stores",
            "type":"Retail Goods"
        }
    ],
    "sg:phone":"+1 608 754 1159",
    "sg:postcode":"53545",
    "sg:province":"WI",
    "sg:website":"www.lionsquickmarts.com",
    "wof:name":"Lions Quick Marts Inc",
    "wof:placetype":"venue"
},
  "geometry": {"coordinates":[-89.009097,42.702472],"type":"Point"}
}