{
  "type": "Feature",
  "properties": {
    "iso:country":"US",
    "sg:address":"1266 Velp Ave",
    "sg:city":"Green Bay",
    "sg:classifiers":[
        {
            "category":"Freight",
            "type":"Transportation"
        }
    ],
    "sg:phone":"+1 920 499 2933",
    "sg:postcode":"54303",
    "sg:province":"WI",
    "sg:tags":[
        "warehouse",
        "commercial",
        "storage"
    ],
    "wof:name":"Leicht Transfer & Storage Co",
    "wof:placetype":"venue"
},
  "geometry": {"coordinates":[-88.03628500000001,44.539844],"type":"Point"}
}