{
  "type": "Feature",
  "properties": {
    "iso:country":"US",
    "sg:address":"1440 W Main St",
    "sg:city":"Whitewater",
    "sg:classifiers":[
        {
            "category":"Retail",
            "subcategory":"Auto Rental",
            "type":"Services"
        }
    ],
    "sg:phone":"+1 262 473 5751",
    "sg:postcode":"53190",
    "sg:province":"WI",
    "sg:tags":[
        "renting",
        "truck",
        "leasing"
    ],
    "wof:name":"U-Haul Co",
    "wof:placetype":"venue"
},
  "geometry": {"coordinates":[-88.764845,42.836266],"type":"Point"}
}