{
  "type": "Feature",
  "properties": {
    "addr:full":"1919 Washington St Two Rivers WI 54241",
    "addr:housenumber":"1919",
    "addr:postcode":"54241",
    "addr:street":"Washington St",
    "iso:country":"US",
    "sg:address":"1919 Washington St",
    "sg:city":"Two Rivers",
    "sg:classifiers":[
        {
            "category":"Autos & Motor Vehicles",
            "subcategory":"Auto Supplies",
            "type":"Retail Goods"
        }
    ],
    "sg:phone":"+1 920 793 8676",
    "sg:postcode":"54241",
    "sg:province":"WI",
    "wof:name":"Autozone",
    "wof:placetype":"venue"
},
  "geometry": {"coordinates":[-87.56825499999999,44.151513],"type":"Point"}
}