{
  "type": "Feature",
  "properties": {
    "iso:country":"US",
    "sg:address":"9712 Tannery Rd",
    "sg:city":"Two Rivers",
    "sg:classifiers":[
        {
            "category":"Farming",
            "subcategory":"Dairy Farm",
            "type":"Manufacturing & Wholesale Goods"
        }
    ],
    "sg:phone":"+1 920 794 1467",
    "sg:postcode":"54241",
    "sg:province":"WI",
    "sg:tags":[
        "corn",
        "cash",
        "crop",
        "field",
        "grain",
        "v"
    ],
    "wof:name":"Paul Funk",
    "wof:placetype":"venue"
},
  "geometry": {"coordinates":[-87.58001,44.214941],"type":"Point"}
}