{
  "type": "Feature",
  "properties": {
    "addr:full":"502 George St De Pere WI 54115",
    "addr:housenumber":"502",
    "addr:postcode":"54115",
    "addr:street":"George St",
    "iso:country":"US",
    "sg:address":"502 George St",
    "sg:city":"De Pere",
    "sg:classifiers":[
        {
            "category":"Health Services",
            "subcategory":"Chiropractor",
            "type":"Services"
        }
    ],
    "sg:phone":"+1 920 337 0103",
    "sg:postcode":"54115",
    "sg:province":"WI",
    "wof:name":"Van Drisse Chiropractic Center",
    "wof:placetype":"venue"
},
  "geometry": {"coordinates":[-88.058046,44.448829],"type":"Point"}
}