{
  "type": "Feature",
  "properties": {
    "iso:country":"US",
    "sg:address":"3990 Church Rd",
    "sg:city":"Conover",
    "sg:classifiers":[
        {
            "category":"Organizations",
            "subcategory":"Religious Organization",
            "type":"Services"
        }
    ],
    "sg:phone":"+1 715 479 9735",
    "sg:postcode":"54519",
    "sg:province":"WI",
    "wof:name":"K E Farb Rev",
    "wof:placetype":"venue"
},
  "geometry": {"coordinates":[-89.203062,46.026883],"type":"Point"}
}