{
  "type": "Feature",
  "properties": {
    "iso:country":"US",
    "sg:address":"1109 Professional Dr",
    "sg:city":"Dodgeville",
    "sg:classifiers":[
        {
            "category":"Social Services",
            "type":"Services"
        }
    ],
    "sg:phone":"+1 608 935 3014",
    "sg:postcode":"53533",
    "sg:province":"WI",
    "sg:tags":[
        "probation"
    ],
    "wof:name":"Probation & Parole Office",
    "wof:placetype":"venue"
},
  "geometry": {"coordinates":[-90.128078,42.971799],"type":"Point"}
}