{
  "type": "Feature",
  "properties": {
    "iso:country":"US",
    "sg:address":"200 Main St",
    "sg:city":"Onalaska",
    "sg:classifiers":[
        {
            "category":"Shopping",
            "subcategory":"Used Merchandise",
            "type":"Retail Goods"
        }
    ],
    "sg:phone":"+1 608 779 4121",
    "sg:postcode":"54650",
    "sg:province":"WI",
    "sg:tags":[
        "miscellaneous"
    ],
    "wof:name":"Twice Is Nice",
    "wof:placetype":"venue"
},
  "geometry": {"coordinates":[-91.233071,43.882999],"type":"Point"}
}