{
  "type": "Feature",
  "properties": {
    "iso:country":"US",
    "sg:address":"835 Potts Ave",
    "sg:city":"Green Bay",
    "sg:classifiers":[
        {
            "category":"Real Estate",
            "subcategory":"Real Estate Services",
            "type":"Services"
        }
    ],
    "sg:phone":"+1 920 491 9504",
    "sg:postcode":"54304",
    "sg:province":"WI",
    "sg:tags":[
        "abstract",
        "title"
    ],
    "wof:name":"Highway Title Services Inc",
    "wof:placetype":"venue"
},
  "geometry": {"coordinates":[-88.05724499999999,44.496414],"type":"Point"}
}