{
  "type": "Feature",
  "properties": {
    "addr:full":"I 94 Frontage Rd W Caledonia WI 53108",
    "addr:postcode":"53108",
    "addr:street":"I 94 Frontage Rd W",
    "iso:country":"US",
    "sg:address":"I 94 Frontage Rd W",
    "sg:city":"Caledonia",
    "sg:classifiers":[
        {
            "category":"Sports & Exercise",
            "subcategory":"Golf",
            "type":"Entertainment"
        }
    ],
    "sg:phone":"+1 262 835 2020",
    "sg:postcode":"53108",
    "sg:province":"WI",
    "sg:tags":[
        "mini"
    ],
    "wof:name":"Raymond Heights Golf Center",
    "wof:placetype":"venue"
},
  "geometry": {"coordinates":[-87.933998,42.816898],"type":"Point"}
}