{
  "type": "Feature",
  "properties": {
    "iso:country":"US",
    "sg:address":"1601 Labus Dr",
    "sg:city":"Bangor",
    "sg:classifiers":[
        {
            "category":"Home & Garden",
            "subcategory":"Home Furnishings",
            "type":"Retail Goods"
        }
    ],
    "sg:phone":"+1 608 486 2711",
    "sg:postcode":"54614",
    "sg:province":"WI",
    "wof:name":"Horstman Custom Drapery",
    "wof:placetype":"venue"
},
  "geometry": {"coordinates":[-90.988354,43.887122],"type":"Point"}
}