{
  "type": "Feature",
  "properties": {
    "iso:country":"US",
    "sg:address":"116 23rd St S",
    "sg:city":"La Crosse",
    "sg:classifiers":[
        {
            "category":"Shopping",
            "subcategory":"Gifts & Souvenirs",
            "type":"Retail Goods"
        }
    ],
    "sg:phone":"+1 608 784 7205",
    "sg:postcode":"54601",
    "sg:province":"WI",
    "wof:name":"Emcar Properties Inc",
    "wof:placetype":"venue"
},
  "geometry": {"coordinates":[-91.221843,43.810405],"type":"Point"}
}