{
  "type": "Feature",
  "properties": {
    "iso:country":"US",
    "sg:address":"3716 State Hwy 22",
    "sg:city":"Oconto",
    "sg:classifiers":[
        {
            "category":"Building & Trades",
            "subcategory":"Landscaping Services",
            "type":"Services"
        }
    ],
    "sg:phone":"+1 920 834 3069",
    "sg:postcode":"54153",
    "sg:province":"WI",
    "sg:tags":[
        "tree"
    ],
    "wof:name":"Act Tree Svc",
    "wof:placetype":"venue"
},
  "geometry": {"coordinates":[-87.947229,44.892744],"type":"Point"}
}