{
  "type": "Feature",
  "properties": {
    "iso:country":"US",
    "sg:address":"1919 Omro Rd",
    "sg:city":"Oshkosh",
    "sg:classifiers":[
        {
            "category":"Travel",
            "subcategory":"Hotels & Motels",
            "type":"Entertainment"
        }
    ],
    "sg:phone":"+1 920 233 1200",
    "sg:postcode":"54902",
    "sg:province":"WI",
    "wof:name":"Howard Johnson",
    "wof:placetype":"venue"
},
  "geometry": {"coordinates":[-88.58196599999999,44.032692],"type":"Point"}
}