{
  "type": "Feature",
  "properties": {
    "iso:country":"US",
    "sg:address":"7231 McHenry St",
    "sg:city":"Burlington",
    "sg:classifiers":[
        {
            "category":"Professional",
            "type":"Services"
        },
        {
            "category":"Retail",
            "subcategory":"Photofinishing",
            "type":"Services"
        }
    ],
    "sg:phone":"+1 262 539 3664",
    "sg:postcode":"53105",
    "sg:province":"WI",
    "sg:tags":[
        "establishment",
        "photographic"
    ],
    "wof:name":"Riverbirch Studios Ltd",
    "wof:placetype":"venue"
},
  "geometry": {"coordinates":[-88.28771,42.639568],"type":"Point"}
}