{
  "type": "Feature",
  "properties": {
    "iso:country":"US",
    "sg:address":"9415 W Forest Home Ave",
    "sg:city":"Hales Corners",
    "sg:classifiers":[
        {
            "category":"Banks & Credit Unions",
            "subcategory":"Bank",
            "type":"Services"
        }
    ],
    "sg:phone":"+1 414 525 2910",
    "sg:postcode":"53130",
    "sg:province":"WI",
    "sg:tags":[
        "broker",
        "mortgage"
    ],
    "wof:name":"Summit Mortgage Corporation",
    "wof:placetype":"venue"
},
  "geometry": {"coordinates":[-88.03096,42.947943],"type":"Point"}
}