{
  "type": "Feature",
  "properties": {
    "iso:country":"US",
    "sg:address":"1020 Hyland Ave",
    "sg:city":"Kaukauna",
    "sg:classifiers":[
        {
            "category":"Retail",
            "subcategory":"Repair Shop",
            "type":"Services"
        }
    ],
    "sg:phone":"+1 920 766 4513",
    "sg:postcode":"54130",
    "sg:province":"WI",
    "sg:tags":[
        "sharpening"
    ],
    "wof:name":"Valley Drill Sharpening",
    "wof:placetype":"venue"
},
  "geometry": {"coordinates":[-88.263869,44.29222],"type":"Point"}
}