{
  "type": "Feature",
  "properties": {
    "iso:country":"US",
    "sg:address":"804 E Greenfield Dr",
    "sg:city":"Little Chute",
    "sg:classifiers":[
        {
            "category":"Shopping",
            "subcategory":"Pharmacy",
            "type":"Retail Goods"
        }
    ],
    "sg:phone":"+1 920 788 5072",
    "sg:postcode":"54140",
    "sg:province":"WI",
    "wof:name":"H B Fuller",
    "wof:placetype":"venue"
},
  "geometry": {"coordinates":[-88.305592,44.28795],"type":"Point"}
}