{
  "type": "Feature",
  "properties": {
    "iso:country":"US",
    "sg:address":"1927 W Wisconsin Ave",
    "sg:city":"Milwaukee",
    "sg:classifiers":[
        {
            "category":"Organizations",
            "subcategory":"Religious Organization",
            "type":"Services"
        }
    ],
    "sg:phone":"+1 414 934 9750",
    "sg:postcode":"53233",
    "sg:province":"WI",
    "sg:tags":[
        "church"
    ],
    "wof:name":"Lamb Of God Holiness Church",
    "wof:placetype":"venue"
},
  "geometry": {"coordinates":[-87.937592,43.038597],"type":"Point"}
}