{
  "type": "Feature",
  "properties": {
    "iso:country":"US",
    "sg:address":"1011 Ehlers Rd",
    "sg:city":"Neenah",
    "sg:classifiers":[
        {
            "category":"Manufacturing",
            "subcategory":"Paper Products",
            "type":"Manufacturing & Wholesale Goods"
        }
    ],
    "sg:phone":"+1 920 751 0600",
    "sg:postcode":"54956",
    "sg:province":"WI",
    "sg:tags":[
        "converted",
        "prod"
    ],
    "wof:name":"Northpoint Manufacturing Inc",
    "wof:placetype":"venue"
},
  "geometry": {"coordinates":[-88.47845,44.208084],"type":"Point"}
}