{
  "type": "Feature",
  "properties": {
    "iso:country":"US",
    "sg:address":"21001 Watertown Rd",
    "sg:city":"Waukesha",
    "sg:classifiers":[
        {
            "category":"Manufacturing",
            "subcategory":"Signs",
            "type":"Manufacturing & Wholesale Goods"
        }
    ],
    "sg:phone":"+1 262 717 9700",
    "sg:postcode":"53186",
    "sg:province":"WI",
    "sg:tags":[
        "specialty",
        "mfg"
    ],
    "wof:name":"Alpha Signs",
    "wof:placetype":"venue"
},
  "geometry": {"coordinates":[-88.175448,43.04145],"type":"Point"}
}