{
  "type": "Feature",
  "properties": {
    "iso:country":"US",
    "sg:address":"1014 Dr Martin Luther King Dr",
    "sg:city":"Racine",
    "sg:classifiers":[
        {
            "category":"Social Services",
            "subcategory":"Child Care",
            "type":"Services"
        }
    ],
    "sg:phone":"+1 262 635 0034",
    "sg:postcode":"53404",
    "sg:province":"WI",
    "sg:tags":[
        "kindergarten",
        "academic",
        "school"
    ],
    "wof:name":"Head Start Wrap Around",
    "wof:placetype":"venue"
},
  "geometry": {"coordinates":[-87.795569,42.734059],"type":"Point"}
}