{
  "type": "Feature",
  "properties": {
    "addr:full":"1717 S 12th St Milwaukee WI 53204",
    "addr:housenumber":"1717",
    "addr:postcode":"53204",
    "addr:street":"S 12Th St",
    "iso:country":"US",
    "sg:address":"1717 S 12th St",
    "sg:city":"Milwaukee",
    "sg:classifiers":[
        {
            "category":"Arts & Performance",
            "subcategory":"Art Gallery",
            "type":"Entertainment"
        }
    ],
    "sg:phone":"+1 414 672 4090",
    "sg:postcode":"53204",
    "sg:province":"WI",
    "sg:tags":[
        "fine",
        "artist"
    ],
    "wof:name":"Terry Evelyn Patricia",
    "wof:placetype":"venue"
},
  "geometry": {"coordinates":[-87.926965,43.012085],"type":"Point"}
}