{
  "type": "Feature",
  "properties": {
    "iso:country":"US",
    "sg:address":"4394 Vilas Rd",
    "sg:city":"Cottage Grove",
    "sg:classifiers":[
        {
            "category":"Farming",
            "subcategory":"Dairy Farm",
            "type":"Manufacturing & Wholesale Goods"
        }
    ],
    "sg:phone":"+1 608 839 4655",
    "sg:postcode":"53527",
    "sg:province":"WI",
    "wof:name":"Skaardale Farms",
    "wof:placetype":"venue"
},
  "geometry": {"coordinates":[-89.232838,43.0864],"type":"Point"}
}