{
  "type": "Feature",
  "properties": {
    "addr:full":"1669 Janice Ave Green Bay WI 54304",
    "addr:housenumber":"1669",
    "addr:postcode":"54304",
    "addr:street":"Janice Ave",
    "iso:country":"US",
    "sg:address":"1669 Janice Ave",
    "sg:city":"Green Bay",
    "sg:classifiers":[
        {
            "category":"Organizations",
            "subcategory":"Religious Organization",
            "type":"Services"
        }
    ],
    "sg:phone":"+1 920 499 9143",
    "sg:postcode":"54304",
    "sg:province":"WI",
    "sg:tags":[
        "monastery",
        "convent"
    ],
    "wof:name":"Sisters of St Francis",
    "wof:placetype":"venue"
},
  "geometry": {"coordinates":[-88.07131,44.51835],"type":"Point"}
}