{
  "type": "Feature",
  "properties": {
    "iso:country":"US",
    "sg:address":"1201 S Grandview Blvd",
    "sg:city":"Waukesha",
    "sg:classifiers":[
        {
            "category":"Wholesale",
            "subcategory":"Stationery",
            "type":"Manufacturing & Wholesale Goods"
        },
        {
            "category":"Manufacturing",
            "subcategory":"Rubber & Plastics",
            "type":"Manufacturing & Wholesale Goods"
        }
    ],
    "sg:phone":"+1 262 549 4700",
    "sg:postcode":"53188",
    "sg:province":"WI",
    "sg:tags":[
        "personal",
        "product",
        "industrial",
        "paper",
        "mfg"
    ],
    "sg:website":"www.kgbag.com",
    "wof:name":"K G Marketing & Bag Co Inc",
    "wof:placetype":"venue"
},
  "geometry": {"coordinates":[-88.265795,42.997111],"type":"Point"}
}