{
  "type": "Feature",
  "properties": {
    "iso:country":"US",
    "sg:address":"3741 Buckingham Dr",
    "sg:city":"Janesville",
    "sg:classifiers":[
        {
            "category":"Shopping",
            "subcategory":"Gifts & Souvenirs",
            "type":"Retail Goods"
        }
    ],
    "sg:phone":"+1 608 754 5904",
    "sg:postcode":"53546",
    "sg:province":"WI",
    "wof:name":"Evenson Builders",
    "wof:placetype":"venue"
},
  "geometry": {"coordinates":[-88.97845100000001,42.726166],"type":"Point"}
}