{
  "type": "Feature",
  "properties": {
    "iso:country":"US",
    "sg:address":"13333 State Hwy 32 64",
    "sg:city":"Mountain",
    "sg:classifiers":[
        {
            "category":"Bars & Pubs",
            "type":"Food & Drink"
        }
    ],
    "sg:phone":"+1 715 276 7833",
    "sg:postcode":"54149",
    "sg:province":"WI",
    "wof:name":"Green Lake Tap",
    "wof:placetype":"venue"
},
  "geometry": {"coordinates":[-88.45601000000001,45.166485],"type":"Point"}
}