{
  "type": "Feature",
  "properties": {
    "addr:full":"1403 Berger St Oshkosh WI 54902",
    "addr:housenumber":"1403",
    "addr:postcode":"54902",
    "addr:street":"Berger St",
    "iso:country":"US",
    "sg:address":"1403 Berger St",
    "sg:city":"Oshkosh",
    "sg:classifiers":[
        {
            "category":"Building & Trades",
            "subcategory":"Construction",
            "type":"Services"
        }
    ],
    "sg:phone":"+1 920 232 9306",
    "sg:postcode":"54902",
    "sg:province":"WI",
    "sg:tags":[
        "hanging",
        "contractor"
    ],
    "wof:name":"T & M Painting",
    "wof:placetype":"venue"
},
  "geometry": {"coordinates":[-88.561494,44.004689],"type":"Point"}
}