{
  "type": "Feature",
  "properties": {
    "iso:country":"US",
    "sg:address":"1444 S 7th St",
    "sg:city":"Milwaukee",
    "sg:classifiers":[
        {
            "category":"Organizations",
            "subcategory":"Community Association",
            "type":"Services"
        }
    ],
    "sg:phone":"+1 414 389 1235",
    "sg:postcode":"53204",
    "sg:province":"WI",
    "sg:tags":[
        "club"
    ],
    "wof:name":"Club Corona",
    "wof:placetype":"venue"
},
  "geometry": {"coordinates":[-87.919642,43.016447],"type":"Point"}
}