{
  "type": "Feature",
  "properties": {
    "iso:country":"US",
    "sg:address":"147 Memorial Dr",
    "sg:city":"Berlin",
    "sg:classifiers":[
        {
            "category":"Government",
            "subcategory":"Office",
            "type":"Public Place"
        }
    ],
    "sg:phone":"+1 920 361 0438",
    "sg:postcode":"54923",
    "sg:province":"WI",
    "sg:tags":[
        "state",
        "program"
    ],
    "wof:name":"Transportation Dept",
    "wof:placetype":"venue"
},
  "geometry": {"coordinates":[-88.94593399999999,43.977743],"type":"Point"}
}