{
  "type": "Feature",
  "properties": {
    "iso:country":"US",
    "sg:address":"1219 W Main St",
    "sg:city":"Sun Prairie",
    "sg:classifiers":[
        {
            "category":"Real Estate",
            "subcategory":"Real Estate Agent",
            "type":"Services"
        }
    ],
    "sg:phone":"+1 608 825 7552",
    "sg:postcode":"53590",
    "sg:province":"WI",
    "wof:name":"J S M & Associates",
    "wof:placetype":"venue"
},
  "geometry": {"coordinates":[-89.236294,43.179074],"type":"Point"}
}