{
  "type": "Feature",
  "properties": {
    "iso:country":"US",
    "sg:address":"8207 22nd Ave",
    "sg:city":"Kenosha",
    "sg:classifiers":[
        {
            "category":"Restaurant",
            "type":"Food & Drink"
        }
    ],
    "sg:phone":"+1 262 842 0165",
    "sg:postcode":"53143",
    "sg:province":"WI",
    "wof:name":"Frankie D's Pizzeria",
    "wof:placetype":"venue"
},
  "geometry": {"coordinates":[-87.834993,42.555194],"type":"Point"}
}