{
  "type": "Feature",
  "properties": {
    "iso:country":"US",
    "sg:address":"20946 State Hwy 27",
    "sg:city":"Sparta",
    "sg:classifiers":[
        {
            "category":"Wholesale",
            "subcategory":"Farm Supplies",
            "type":"Manufacturing & Wholesale Goods"
        }
    ],
    "sg:phone":"+1 608 269 7920",
    "sg:postcode":"54656",
    "sg:province":"WI",
    "wof:name":"Endres Farm & Feed Svc",
    "wof:placetype":"venue"
},
  "geometry": {"coordinates":[-90.82935500000001,43.873953],"type":"Point"}
}