{
  "type": "Feature",
  "properties": {
    "iso:country":"US",
    "sg:address":"3514 W Good Hope Rd",
    "sg:city":"Milwaukee",
    "sg:classifiers":[
        {
            "category":"Retail",
            "subcategory":"Auto Rental",
            "type":"Services"
        }
    ],
    "sg:phone":"+1 414 352 4226",
    "sg:postcode":"53209",
    "sg:province":"WI",
    "sg:tags":[
        "automobile",
        "leasing"
    ],
    "wof:name":"Equipment Lease Corp",
    "wof:placetype":"venue"
},
  "geometry": {"coordinates":[-87.955811,43.148575],"type":"Point"}
}