{
  "type": "Feature",
  "properties": {
    "iso:country":"US",
    "sg:address":"1080 Chicago Point Rd",
    "sg:city":"Pelican Lake",
    "sg:classifiers":[
        {
            "category":"Personal",
            "subcategory":"Beauty Salon",
            "type":"Services"
        }
    ],
    "sg:phone":"+1 715 487 4144",
    "sg:postcode":"54463",
    "sg:province":"WI",
    "sg:tags":[
        "shop"
    ],
    "wof:name":"Tangles 2 Curls",
    "wof:placetype":"venue"
},
  "geometry": {"coordinates":[-89.198668,45.511353],"type":"Point"}
}