{
  "type": "Feature",
  "properties": {
    "addr:full":"228 W Wells St Milwaukee WI 53203",
    "addr:housenumber":"228",
    "addr:postcode":"53203",
    "addr:street":"W Wells St",
    "iso:country":"US",
    "sg:address":"228 W Wells St",
    "sg:city":"Milwaukee",
    "sg:classifiers":[
        {
            "category":"Restaurant",
            "type":"Food & Drink"
        }
    ],
    "sg:menulink":"http://www.allmenus.com/wi/milwaukee/145628-subway/menu/",
    "sg:phone":"+1 414 272 0244",
    "sg:postcode":"53203",
    "sg:province":"WI",
    "sg:tags":[
        "american",
        "sandwich"
    ],
    "wof:name":"Subway",
    "wof:placetype":"venue"
},
  "geometry": {"coordinates":[-87.913684,43.040178],"type":"Point"}
}