{
  "type": "Feature",
  "properties": {
    "addr:full":"8820 S 68th St Franklin WI 53132",
    "addr:housenumber":"8820",
    "addr:postcode":"53132",
    "addr:street":"S 68Th St",
    "iso:country":"US",
    "sg:address":"8820 S 68th St",
    "sg:city":"Franklin",
    "sg:classifiers":[
        {
            "category":"Utilities",
            "subcategory":"Refuse",
            "type":"Services"
        }
    ],
    "sg:phone":"+1 414 529 4455",
    "sg:postcode":"53132",
    "sg:province":"WI",
    "sg:tags":[
        "system"
    ],
    "wof:name":"Trashpacker of Wisconsin",
    "wof:placetype":"venue"
},
  "geometry": {"coordinates":[-88.000272,42.874115],"type":"Point"}
}