{
  "type": "Feature",
  "properties": {
    "iso:country":"US",
    "sg:address":"6321 Co Rd K",
    "sg:city":"Endeavor",
    "sg:classifiers":[
        {
            "category":"Professional",
            "subcategory":"Accounting & Tax Preparation",
            "type":"Services"
        }
    ],
    "sg:phone":"+1 608 587 2975",
    "sg:postcode":"53911",
    "sg:province":"WI",
    "sg:tags":[
        "bookkeeping",
        "general"
    ],
    "wof:name":"Best Bookkeeping",
    "wof:placetype":"venue"
},
  "geometry": {"coordinates":[-89.315007,43.310041],"type":"Point"}
}