{
  "type": "Feature",
  "properties": {
    "iso:country":"US",
    "sg:address":"1571 E Sumner St",
    "sg:city":"Hartford",
    "sg:classifiers":[
        {
            "category":"Professional",
            "subcategory":"Accounting & Tax Preparation",
            "type":"Services"
        }
    ],
    "sg:phone":"+1 262 673 5337",
    "sg:postcode":"53027",
    "sg:province":"WI",
    "sg:tags":[
        "accountant"
    ],
    "wof:name":"Larry A Lopas CPA",
    "wof:placetype":"venue"
},
  "geometry": {"coordinates":[-88.353669,43.317566],"type":"Point"}
}