{
  "type": "Feature",
  "properties": {
    "iso:country":"US",
    "sg:address":"904 38th St",
    "sg:city":"Kenosha",
    "sg:classifiers":[
        {
            "category":"Professional",
            "type":"Services"
        }
    ],
    "sg:phone":"+1 262 657 7338",
    "sg:postcode":"53140",
    "sg:province":"WI",
    "wof:name":"Rick Dregne",
    "wof:placetype":"venue"
},
  "geometry": {"coordinates":[-87.82436300000001,42.602612],"type":"Point"}
}