{
  "type": "Feature",
  "properties": {
    "addr:full":"1625 Roosevelt Rd Niagara WI 54151",
    "addr:housenumber":"1625",
    "addr:postcode":"54151",
    "addr:street":"Roosevelt Rd",
    "iso:country":"US",
    "sg:address":"1625 Roosevelt Rd",
    "sg:city":"Niagara",
    "sg:classifiers":[
        {
            "category":"Health Services",
            "subcategory":"Chiropractor",
            "type":"Services"
        }
    ],
    "sg:phone":"+1 715 251 3727",
    "sg:postcode":"54151",
    "sg:province":"WI",
    "wof:name":"Niagara Chiropractic",
    "wof:placetype":"venue"
},
  "geometry": {"coordinates":[-88.005324,45.791849],"type":"Point"}
}