{
  "type": "Feature",
  "properties": {
    "iso:country":"US",
    "sg:address":"596 US Hwy 18 W",
    "sg:city":"Montfort",
    "sg:classifiers":[
        {
            "category":"Building & Trades",
            "subcategory":"Construction",
            "type":"Services"
        }
    ],
    "sg:phone":"+1 608 943 6910",
    "sg:postcode":"53569",
    "sg:province":"WI",
    "sg:tags":[
        "painter"
    ],
    "wof:name":"High Tech Commercial Painting",
    "wof:placetype":"venue"
},
  "geometry": {"coordinates":[-90.44293999999999,42.96648],"type":"Point"}
}