{
  "type": "Feature",
  "properties": {
    "iso:country":"US",
    "sg:address":"2655 N Main St",
    "sg:city":"Oshkosh",
    "sg:classifiers":[
        {
            "category":"Banks & Credit Unions",
            "subcategory":"Bank",
            "type":"Services"
        }
    ],
    "sg:phone":"+1 920 236 7040",
    "sg:postcode":"54901",
    "sg:province":"WI",
    "sg:website":"www.citizenfirst.com",
    "wof:name":"Citizenfirst Credit Union",
    "wof:placetype":"venue"
},
  "geometry": {"coordinates":[-88.53787,44.049517],"type":"Point"}
}