{
  "type": "Feature",
  "properties": {
    "iso:country":"US",
    "sg:address":"8532 W Capitol Dr",
    "sg:city":"Milwaukee",
    "sg:classifiers":[
        {
            "category":"Health Services",
            "subcategory":"Clinic",
            "type":"Services"
        },
        {
            "category":"Health Services",
            "subcategory":"Medical Lab",
            "type":"Services"
        },
        {
            "category":"Personal",
            "type":"Services"
        }
    ],
    "sg:phone":"+1 866 867 0393",
    "sg:postcode":"53222",
    "sg:province":"WI",
    "sg:tags":[
        "laboratory",
        "testing",
        "paternity",
        "drug"
    ],
    "sg:website":"http://milwaukee.citysearch.com/profile/external/604054112/milwaukee_wi/rapid_std_dna_drug_testing_milwaukee.html?publisher=yellowpages&reference_id=1&placement=ypwebsitemip",
    "wof:name":"Rapid STD DNA Drug Testing MILWAUKEE",
    "wof:placetype":"venue"
},
  "geometry": {"coordinates":[-88.019279,43.089864],"type":"Point"}
}