{
  "type": "Feature",
  "properties": {
    "iso:country":"US",
    "sg:address":"692 Dartmouth Dr",
    "sg:city":"Sheboygan Falls",
    "sg:classifiers":[
        {
            "category":"Organizations",
            "subcategory":"Community Association",
            "type":"Services"
        }
    ],
    "sg:phone":"+1 920 467 8144",
    "sg:postcode":"53085",
    "sg:province":"WI",
    "wof:name":"Kiwanis International Inc",
    "wof:placetype":"venue"
},
  "geometry": {"coordinates":[-87.808331,43.721073],"type":"Point"}
}