{
  "type": "Feature",
  "properties": {
    "iso:country":"US",
    "sg:address":"5519 W North Ave",
    "sg:city":"Milwaukee",
    "sg:classifiers":[
        {
            "category":"Social Services",
            "type":"Services"
        }
    ],
    "sg:phone":"+1 414 444 3481",
    "sg:postcode":"53208",
    "sg:province":"WI",
    "sg:tags":[
        "organization",
        "welfare"
    ],
    "wof:name":"Attucks Center Inc",
    "wof:placetype":"venue"
},
  "geometry": {"coordinates":[-87.98291,43.060606],"type":"Point"}
}