{
  "type": "Feature",
  "properties": {
    "addr:full":"2242 W Bluemound Rd Waukesha WI 53186",
    "addr:housenumber":"2242",
    "addr:postcode":"53186",
    "addr:street":"W Bluemound Rd",
    "iso:country":"US",
    "sg:address":"2242 W Bluemound Rd",
    "sg:city":"Waukesha",
    "sg:classifiers":[
        {
            "category":"Manufacturing",
            "subcategory":"Tools & Machinery",
            "type":"Manufacturing & Wholesale Goods"
        },
        {
            "category":"Wholesale",
            "subcategory":"Machinery & Supplies",
            "type":"Manufacturing & Wholesale Goods"
        }
    ],
    "sg:phone":"+1 262 786 6570",
    "sg:postcode":"53186",
    "sg:province":"WI",
    "sg:tags":[
        "machine",
        "equipment",
        "industrial",
        "machinery-new",
        "used"
    ],
    "sg:website":"http://www.statemachinetool.com",
    "wof:name":"State Machine Tool Co Inc",
    "wof:placetype":"venue"
},
  "geometry": {"coordinates":[-88.181369,43.03637],"type":"Point"}
}