{
  "type": "Feature",
  "properties": {
    "iso:country":"US",
    "sg:address":"800 W Center St",
    "sg:city":"Milwaukee",
    "sg:classifiers":[
        {
            "category":"Travel",
            "subcategory":"Hotels & Motels",
            "type":"Entertainment"
        }
    ],
    "sg:phone":"+1 414 372 8674",
    "sg:postcode":"53206",
    "sg:province":"WI",
    "wof:name":"Blues Inn",
    "wof:placetype":"venue"
},
  "geometry": {"coordinates":[-87.922663,43.06762],"type":"Point"}
}