{
  "type": "Feature",
  "properties": {
    "iso:country":"US",
    "sg:address":"1245 Main St",
    "sg:city":"Stevens Point",
    "sg:classifiers":[
        {
            "category":"Organizations",
            "subcategory":"Professional Association",
            "type":"Services"
        }
    ],
    "sg:phone":"+1 715 343 5356",
    "sg:postcode":"54481",
    "sg:province":"WI",
    "wof:name":"Association Of Downtown Bus",
    "wof:placetype":"venue"
},
  "geometry": {"coordinates":[-89.58141,44.523336],"type":"Point"}
}