{
  "type": "Feature",
  "properties": {
    "iso:country":"US",
    "sg:address":"1025 Kelly Dr",
    "sg:city":"Rubicon",
    "sg:classifiers":[
        {
            "category":"Freight",
            "type":"Transportation"
        }
    ],
    "sg:phone":"+1 262 673 2879",
    "sg:postcode":"53078",
    "sg:province":"WI",
    "sg:tags":[
        "operator",
        "local",
        "trucking"
    ],
    "wof:name":"Krueger & Sons Trucking",
    "wof:placetype":"venue"
},
  "geometry": {"coordinates":[-88.446824,43.32845],"type":"Point"}
}