{
  "type": "Feature",
  "properties": {
    "iso:country":"US",
    "sg:address":"121 W Main St",
    "sg:city":"Ellsworth",
    "sg:classifiers":[
        {
            "category":"Government",
            "subcategory":"Office",
            "type":"Public Place"
        }
    ],
    "sg:phone":"+1 715 273 3079",
    "sg:postcode":"54011",
    "sg:province":"WI",
    "sg:tags":[
        "federal",
        "security"
    ],
    "wof:name":"US Army Reserve",
    "wof:placetype":"venue"
},
  "geometry": {"coordinates":[-92.47568200000001,44.732012],"type":"Point"}
}