{
  "type": "Feature",
  "properties": {
    "addr:full":"342 N Water St Milwaukee WI 53202",
    "addr:housenumber":"342",
    "addr:postcode":"53202",
    "addr:street":"N Water St",
    "iso:country":"US",
    "sg:address":"342 N Water St",
    "sg:city":"Milwaukee",
    "sg:classifiers":[
        {
            "category":"Education",
            "subcategory":"Dance Studio",
            "type":"Public Place"
        }
    ],
    "sg:phone":"+1 414 273 0676",
    "sg:postcode":"53202",
    "sg:province":"WI",
    "sg:tags":[
        "instruction",
        "dancing"
    ],
    "wof:name":"Ko Thi Dance Co Inc",
    "wof:placetype":"venue"
},
  "geometry": {"coordinates":[-87.908788,43.034415],"type":"Point"}
}