{
  "type": "Feature",
  "properties": {
    "iso:country":"US",
    "sg:address":"2329 Jackson St",
    "sg:city":"Oshkosh",
    "sg:classifiers":[
        {
            "category":"Building & Trades",
            "subcategory":"Construction",
            "type":"Services"
        }
    ],
    "sg:phone":"+1 920 231 0432",
    "sg:postcode":"54901",
    "sg:province":"WI",
    "sg:tags":[
        "material",
        "contractor"
    ],
    "wof:name":"Hibsch Tile & Marble",
    "wof:placetype":"venue"
},
  "geometry": {"coordinates":[-88.542768,44.045892],"type":"Point"}
}