{
  "type": "Feature",
  "properties": {
    "iso:country":"US",
    "sg:address":"1080 Freedom Ave",
    "sg:city":"Oshkosh",
    "sg:classifiers":[
        {
            "category":"Education",
            "subcategory":"Dance Studio",
            "type":"Public Place"
        }
    ],
    "sg:phone":"+1 920 426 1732",
    "sg:postcode":"54901",
    "sg:province":"WI",
    "wof:name":"Spotlight Dance & Perform Arts",
    "wof:placetype":"venue"
},
  "geometry": {"coordinates":[-88.550833,44.062473],"type":"Point"}
}