{
  "type": "Feature",
  "properties": {
    "iso:country":"US",
    "sg:address":"6835 Lorraine Cir",
    "sg:city":"Waterford",
    "sg:classifiers":[
        {
            "category":"Building & Trades",
            "subcategory":"Plumbing",
            "type":"Services"
        }
    ],
    "sg:phone":"+1 262 895 2703",
    "sg:postcode":"53185",
    "sg:province":"WI",
    "sg:tags":[
        "contractor"
    ],
    "wof:name":"Mjd Services",
    "wof:placetype":"venue"
},
  "geometry": {"coordinates":[-88.144535,42.809793],"type":"Point"}
}