{
  "type": "Feature",
  "properties": {
    "addr:full":"134 Sternberg St Schofield WI 54476",
    "addr:housenumber":"134",
    "addr:postcode":"54476",
    "addr:street":"Sternberg St",
    "iso:country":"US",
    "sg:address":"134 Sternberg St",
    "sg:city":"Schofield",
    "sg:classifiers":[
        {
            "category":"Building & Trades",
            "subcategory":"Landscaping Services",
            "type":"Services"
        }
    ],
    "sg:phone":"+1 715 355 1383",
    "sg:postcode":"54476",
    "sg:province":"WI",
    "wof:name":"Miller Landscaping & Lawn Svc",
    "wof:placetype":"venue"
},
  "geometry": {"coordinates":[-89.611071,44.906703],"type":"Point"}
}