{
  "type": "Feature",
  "properties": {
    "iso:country":"US",
    "sg:address":"1348 Sandy Ln",
    "sg:city":"Cedarburg",
    "sg:classifiers":[
        {
            "category":"Retail",
            "subcategory":"Repair Shop",
            "type":"Services"
        }
    ],
    "sg:phone":"+1 262 677 9925",
    "sg:postcode":"53012",
    "sg:province":"WI",
    "wof:name":"Pro Fork Inc",
    "wof:placetype":"venue"
},
  "geometry": {"coordinates":[-88.102848,43.320402],"type":"Point"}
}