{
  "type": "Feature",
  "properties": {
    "addr:full":"31 S Madison St Evansville WI 53536",
    "addr:housenumber":"31",
    "addr:postcode":"53536",
    "addr:street":"S Madison St",
    "iso:country":"US",
    "sg:address":"31 S Madison St",
    "sg:city":"Evansville",
    "sg:classifiers":[
        {
            "category":"Government",
            "subcategory":"Office",
            "type":"Public Place"
        }
    ],
    "sg:phone":"+1 608 798 3140",
    "sg:postcode":"53536",
    "sg:province":"WI",
    "sg:tags":[
        "city",
        "taxation"
    ],
    "wof:name":"Evansville City Assessor",
    "wof:placetype":"venue"
},
  "geometry": {"coordinates":[-89.299274,42.780116],"type":"Point"}
}