{
  "type": "Feature",
  "properties": {
    "iso:country":"US",
    "sg:address":"219 E Summit Ave",
    "sg:city":"Wales",
    "sg:classifiers":[
        {
            "category":"Retail",
            "subcategory":"Veterinary Services",
            "type":"Services"
        }
    ],
    "sg:phone":"+1 262 968 2507",
    "sg:postcode":"53183",
    "sg:province":"WI",
    "sg:tags":[
        "veterinarian"
    ],
    "wof:name":"Wales Animal Clinic Service",
    "wof:placetype":"venue"
},
  "geometry": {"coordinates":[-88.374687,43.014582],"type":"Point"}
}