{
  "type": "Feature",
  "properties": {
    "iso:country":"US",
    "sg:address":"28951 State Hwy 21",
    "sg:city":"Tomah",
    "sg:classifiers":[
        {
            "category":"Building & Trades",
            "subcategory":"Plumbing",
            "type":"Services"
        }
    ],
    "sg:phone":"+1 608 372 5251",
    "sg:postcode":"54660",
    "sg:province":"WI",
    "sg:tags":[
        "septic"
    ],
    "wof:name":"Wood Septic Svc",
    "wof:placetype":"venue"
},
  "geometry": {"coordinates":[-90.41290499999999,44.029575],"type":"Point"}
}