{
  "type": "Feature",
  "properties": {
    "iso:country":"US",
    "sg:address":"3760 Co Rd J",
    "sg:city":"Hustisford",
    "sg:classifiers":[
        {
            "category":"Utilities",
            "subcategory":"Cable",
            "type":"Services"
        }
    ],
    "sg:phone":"+1 920 349 3201",
    "sg:postcode":"53579",
    "sg:province":"WI",
    "sg:tags":[
        "television"
    ],
    "wof:name":"Charter Communications",
    "wof:placetype":"venue"
},
  "geometry": {"coordinates":[-88.843121,43.320607],"type":"Point"}
}