{
  "type": "Feature",
  "properties": {
    "iso:country":"US",
    "sg:address":"555 W Grand Ave",
    "sg:city":"Wisconsin Rapids",
    "sg:classifiers":[
        {
            "category":"Shopping",
            "subcategory":"Jewelry",
            "type":"Retail Goods"
        }
    ],
    "sg:phone":"+1 715 421 5244",
    "sg:postcode":"54495",
    "sg:province":"WI",
    "sg:tags":[
        "jeweler"
    ],
    "wof:name":"Scanlan Jewelers Inc",
    "wof:placetype":"venue"
},
  "geometry": {"coordinates":[-89.829942,44.39426],"type":"Point"}
}