{
  "type": "Feature",
  "properties": {
    "iso:country":"US",
    "sg:address":"2586 Chesapeake Dr",
    "sg:city":"Madison",
    "sg:classifiers":[
        {
            "category":"Professional",
            "subcategory":"Computer Services",
            "type":"Services"
        }
    ],
    "sg:phone":"+1 608 274 5844",
    "sg:postcode":"53719",
    "sg:province":"WI",
    "sg:tags":[
        "datum"
    ],
    "wof:name":"Doyle Web Services LLC",
    "wof:placetype":"venue"
},
  "geometry": {"coordinates":[-89.48186099999999,43.020523],"type":"Point"}
}