{
  "type": "Feature",
  "properties": {
    "iso:country":"US",
    "sg:address":"3329 Sunset Rd",
    "sg:city":"Sheboygan Falls",
    "sg:classifiers":[
        {
            "category":"Real Estate",
            "subcategory":"Real Estate Agent",
            "type":"Services"
        }
    ],
    "sg:phone":"+1 920 467 2737",
    "sg:postcode":"53085",
    "sg:province":"WI",
    "wof:name":"Moraine Realty",
    "wof:placetype":"venue"
},
  "geometry": {"coordinates":[-87.870449,43.754942],"type":"Point"}
}