{
  "type": "Feature",
  "properties": {
    "addr:full":"8061 State Hwy 106 Fort Atkinson WI 53538",
    "addr:housenumber":"8061",
    "addr:postcode":"53538",
    "addr:street":"State Hwy 106",
    "iso:country":"US",
    "sg:address":"8061 State Hwy 106",
    "sg:city":"Fort Atkinson",
    "sg:phone":"+1 920 563 3113",
    "sg:postcode":"53538",
    "sg:province":"WI",
    "sg:tags":[
        "farm",
        "field",
        "corn",
        "crop"
    ],
    "wof:name":"Frank Meske",
    "wof:placetype":"venue"
},
  "geometry": {"coordinates":[-88.932035,42.926498],"type":"Point"}
}