{
  "type": "Feature",
  "properties": {
    "iso:country":"US",
    "sg:address":"7364 Capital Rd",
    "sg:city":"Greenwood",
    "sg:classifiers":[
        {
            "category":"Farming",
            "subcategory":"Dairy Farm",
            "type":"Manufacturing & Wholesale Goods"
        }
    ],
    "sg:phone":"+1 715 267 7365",
    "sg:postcode":"54437",
    "sg:province":"WI",
    "wof:name":"David Hemann",
    "wof:placetype":"venue"
},
  "geometry": {"coordinates":[-90.69633899999999,44.81414],"type":"Point"}
}