{
  "type": "Feature",
  "properties": {
    "iso:country":"US",
    "sg:address":"1626 Oak St",
    "sg:city":"La Crosse",
    "sg:classifiers":[
        {
            "category":"Food & Beverages",
            "subcategory":"Groceries & Convenience Stores",
            "type":"Retail Goods"
        }
    ],
    "sg:phone":"+1 608 781 8988",
    "sg:postcode":"54603",
    "sg:province":"WI",
    "sg:website":"www.kwiktrip.com",
    "wof:name":"KWIK Trip Inc",
    "wof:placetype":"venue"
},
  "geometry": {"coordinates":[-91.229315,43.847922],"type":"Point"}
}