{
  "type": "Feature",
  "properties": {
    "addr:full":"303 S Barstow St Eau Claire WI 54701",
    "addr:housenumber":"303",
    "addr:postcode":"54701",
    "addr:street":"S Barstow St",
    "iso:country":"US",
    "sg:address":"303 S Barstow St",
    "sg:city":"Eau Claire",
    "sg:classifiers":[
        {
            "category":"Personal",
            "subcategory":"Beauty Salon",
            "type":"Services"
        }
    ],
    "sg:phone":"+1 715 832 3972",
    "sg:postcode":"54701",
    "sg:province":"WI",
    "wof:name":"Lagrande Salon",
    "wof:placetype":"venue"
},
  "geometry": {"coordinates":[-91.498654,44.810185],"type":"Point"}
}