{
  "type": "Feature",
  "properties": {
    "iso:country":"US",
    "sg:address":"1037 Williamson St",
    "sg:city":"Madison",
    "sg:classifiers":[
        {
            "category":"Professional",
            "type":"Services"
        }
    ],
    "sg:phone":"+1 608 251 2099",
    "sg:postcode":"53703",
    "sg:province":"WI",
    "wof:name":"Hand Delivered Happiness",
    "wof:placetype":"venue"
},
  "geometry": {"coordinates":[-89.36653200000001,43.081489],"type":"Point"}
}