{
  "type": "Feature",
  "properties": {
    "iso:country":"US",
    "sg:address":"603 E Division St",
    "sg:city":"Neillsville",
    "sg:classifiers":[
        {
            "category":"Sports & Exercise",
            "subcategory":"Golf",
            "type":"Entertainment"
        }
    ],
    "sg:phone":"+1 715 743 3780",
    "sg:postcode":"54456",
    "sg:province":"WI",
    "sg:tags":[
        "course"
    ],
    "wof:name":"Neillsville Country Club",
    "wof:placetype":"venue"
},
  "geometry": {"coordinates":[-90.588363,44.552766],"type":"Point"}
}