{
  "type": "Feature",
  "properties": {
    "iso:country":"US",
    "sg:address":"7693 State Hwy 64",
    "sg:city":"Bloomer",
    "sg:classifiers":[
        {
            "category":"Freight",
            "type":"Transportation"
        }
    ],
    "sg:phone":"+1 715 568 4652",
    "sg:postcode":"54724",
    "sg:province":"WI",
    "sg:tags":[
        "hauling",
        "trucking"
    ],
    "wof:name":"All-Ways Transit Inc",
    "wof:placetype":"venue"
},
  "geometry": {"coordinates":[-91.530255,45.134832],"type":"Point"}
}