{
  "type": "Feature",
  "properties": {
    "iso:country":"US",
    "sg:address":"2200 US Hwy 8",
    "sg:city":"St Croix Falls",
    "sg:classifiers":[
        {
            "category":"Sports & Exercise",
            "subcategory":"Golf",
            "type":"Entertainment"
        }
    ],
    "sg:phone":"+1 715 483 3377",
    "sg:postcode":"54024",
    "sg:province":"WI",
    "sg:tags":[
        "course"
    ],
    "wof:name":"St Croix Valley Golf Course",
    "wof:placetype":"venue"
},
  "geometry": {"coordinates":[-92.613607,45.398389],"type":"Point"}
}