{
  "type": "Feature",
  "properties": {
    "iso:country":"US",
    "sg:address":"7842 N Faulkner Rd",
    "sg:city":"Milwaukee",
    "sg:classifiers":[
        {
            "category":"Wholesale",
            "subcategory":"Machinery & Supplies",
            "type":"Manufacturing & Wholesale Goods"
        }
    ],
    "sg:phone":"+1 414 355 2000",
    "sg:postcode":"53224",
    "sg:province":"WI",
    "sg:tags":[
        "agricultural",
        "tractor"
    ],
    "wof:name":"Belarus Tractor International",
    "wof:placetype":"venue"
},
  "geometry": {"coordinates":[-88.021113,43.161717],"type":"Point"}
}