{
  "type": "Feature",
  "properties": {
    "iso:country":"US",
    "sg:address":"3527 W National Ave",
    "sg:city":"Milwaukee",
    "sg:classifiers":[
        {
            "category":"Health Services",
            "subcategory":"Doctor",
            "type":"Services"
        }
    ],
    "sg:phone":"+1 414 384 8930",
    "sg:postcode":"53215",
    "sg:province":"WI",
    "sg:tags":[
        "physician",
        "surgeon",
        "medical"
    ],
    "wof:name":"Hispanic Medical Center",
    "wof:placetype":"venue"
},
  "geometry": {"coordinates":[-87.958589,43.021475],"type":"Point"}
}