{
  "type": "Feature",
  "properties": {
    "addr:full":"7255 Edgehill Rd Greendale WI 53129",
    "addr:housenumber":"7255",
    "addr:postcode":"53129",
    "addr:street":"Edgehill Rd",
    "iso:country":"US",
    "sg:address":"7255 Edgehill Rd",
    "sg:city":"Greendale",
    "sg:classifiers":[
        {
            "category":"Shopping",
            "subcategory":"Discount & Variety Stores",
            "type":"Retail Goods"
        },
        {
            "category":"Professional",
            "subcategory":"Business Services",
            "type":"Services"
        }
    ],
    "sg:phone":"+1 414 423 7337",
    "sg:postcode":"53129",
    "sg:province":"WI",
    "sg:tags":[
        "merchandise",
        "general"
    ],
    "wof:name":"P N Professional Sales Inc",
    "wof:placetype":"venue"
},
  "geometry": {"coordinates":[-88.004092,42.940494],"type":"Point"}
}