{
  "type": "Feature",
  "properties": {
    "iso:country":"US",
    "sg:address":"2502 Lake Shore Dr W",
    "sg:city":"Ashland",
    "sg:classifiers":[
        {
            "category":"Autos & Motor Vehicles",
            "subcategory":"Automobile Sales",
            "type":"Retail Goods"
        }
    ],
    "sg:phone":"+1 715 682 9790",
    "sg:postcode":"54806",
    "sg:province":"WI",
    "sg:tags":[
        "repair",
        "general"
    ],
    "wof:name":"Lakeshore Sales & Service",
    "wof:placetype":"venue"
},
  "geometry": {"coordinates":[-90.911147,46.582294],"type":"Point"}
}