{
  "type": "Feature",
  "properties": {
    "addr:full":"4843 N Hopkins St Milwaukee WI 53209",
    "addr:housenumber":"4843",
    "addr:postcode":"53209",
    "addr:street":"N Hopkins St",
    "iso:country":"US",
    "sg:address":"4843 N Hopkins St",
    "sg:city":"Milwaukee",
    "sg:classifiers":[
        {
            "category":"Social Services",
            "subcategory":"Child Care",
            "type":"Services"
        }
    ],
    "sg:phone":"+1 414 464 2622",
    "sg:postcode":"53209",
    "sg:province":"WI",
    "wof:name":"Marc Center Child Dev Acad",
    "wof:placetype":"venue"
},
  "geometry": {"coordinates":[-87.960554,43.105629],"type":"Point"}
}