{
  "type": "Feature",
  "properties": {
    "addr:full":"3569 Co Rd K Watertown WI 53098",
    "addr:housenumber":"3569",
    "addr:postcode":"53098",
    "addr:street":"Co Rd",
    "iso:country":"US",
    "sg:address":"3569 Co Rd K",
    "sg:city":"Watertown",
    "sg:classifiers":[
        {
            "category":"Manufacturing",
            "subcategory":"Tools & Machinery",
            "type":"Manufacturing & Wholesale Goods"
        }
    ],
    "sg:phone":"+1 920 474 4124",
    "sg:postcode":"53098",
    "sg:province":"WI",
    "sg:tags":[
        "industrial",
        "mfg"
    ],
    "wof:name":"Haval Tool & Machine",
    "wof:placetype":"venue"
},
  "geometry": {"coordinates":[-88.783624,43.315188],"type":"Point"}
}