{
  "type": "Feature",
  "properties": {
    "iso:country":"US",
    "sg:address":"215 Martin Luther King Jr Blvd",
    "sg:city":"Madison",
    "sg:classifiers":[
        {
            "category":"Government",
            "subcategory":"Post Office",
            "type":"Public Place"
        }
    ],
    "sg:phone":"+1 608 000 1111",
    "sg:postcode":"53703",
    "sg:province":"WI",
    "wof:name":"US Post Office",
    "wof:placetype":"venue"
},
  "geometry": {"coordinates":[-89.381372,43.072684],"type":"Point"}
}