{
  "type": "Feature",
  "properties": {
    "iso:country":"US",
    "sg:address":"2930 Plover Rd",
    "sg:city":"Wisconsin Rapids",
    "sg:classifiers":[
        {
            "category":"Manufacturing",
            "subcategory":"Signs",
            "type":"Manufacturing & Wholesale Goods"
        }
    ],
    "sg:phone":"+1 715 424 2566",
    "sg:postcode":"54494",
    "sg:province":"WI",
    "sg:tags":[
        "mfg"
    ],
    "wof:name":"Rapid Signs Inc",
    "wof:placetype":"venue"
},
  "geometry": {"coordinates":[-89.79015200000001,44.406742],"type":"Point"}
}