{
  "type": "Feature",
  "properties": {
    "iso:country":"US",
    "sg:address":"10710 W Mill Rd",
    "sg:city":"Milwaukee",
    "sg:classifiers":[
        {
            "category":"Place Of Worship",
            "subcategory":"Church",
            "type":"Public Place"
        },
        {
            "category":"Place Of Worship",
            "type":"Public Place"
        }
    ],
    "sg:phone":"+1 414 353 6747",
    "sg:postcode":"53225",
    "sg:province":"WI",
    "sg:tags":[
        "churches-pentecostal-independent",
        "churches-pentecostal"
    ],
    "wof:name":"Northview United Pentecostal Church",
    "wof:placetype":"venue"
},
  "geometry": {"coordinates":[-88.04533499999999,43.133887],"type":"Point"}
}