{
  "type": "Feature",
  "properties": {
    "iso:country":"US",
    "sg:address":"1121 Radisson St",
    "sg:city":"Green Bay",
    "sg:classifiers":[
        {
            "category":"Autos & Motor Vehicles",
            "subcategory":"Fuel & Gas Station",
            "type":"Retail Goods"
        }
    ],
    "sg:phone":"+1 920 432 0771",
    "sg:postcode":"54302",
    "sg:province":"WI",
    "sg:tags":[
        "oil"
    ],
    "wof:name":"Bay Beach Shell",
    "wof:placetype":"venue"
},
  "geometry": {"coordinates":[-87.991906,44.524995],"type":"Point"}
}