{
  "type": "Feature",
  "properties": {
    "addr:full":"401 Pilot Ct Waukesha WI 53188",
    "addr:housenumber":"401",
    "addr:postcode":"53188",
    "addr:street":"Pilot Ct",
    "iso:country":"US",
    "sg:address":"401 Pilot Ct",
    "sg:city":"Waukesha",
    "sg:classifiers":[
        {
            "category":"Organizations",
            "subcategory":"Religious Organization",
            "type":"Services"
        }
    ],
    "sg:phone":"+1 262 574 1234",
    "sg:postcode":"53188",
    "sg:province":"WI",
    "wof:name":"Oil of Joy Ltd",
    "wof:placetype":"venue"
},
  "geometry": {"coordinates":[-88.227566,43.027682],"type":"Point"}
}