{
  "type": "Feature",
  "properties": {
    "addr:full":"920 Klaus St Green Bay WI 54302",
    "addr:housenumber":"920",
    "addr:postcode":"54302",
    "addr:street":"Klaus St",
    "iso:country":"US",
    "sg:address":"920 Klaus St",
    "sg:city":"Green Bay",
    "sg:classifiers":[
        {
            "category":"Autos & Motor Vehicles",
            "subcategory":"Auto Supplies",
            "type":"Retail Goods"
        }
    ],
    "sg:phone":"+1 920 435 8385",
    "sg:postcode":"54302",
    "sg:province":"WI",
    "sg:tags":[
        "automobile",
        "parts"
    ],
    "wof:name":"Bumper To Bumper",
    "wof:placetype":"venue"
},
  "geometry": {"coordinates":[-87.99619300000001,44.523132],"type":"Point"}
}