{
  "type": "Feature",
  "properties": {
    "iso:country":"US",
    "sg:address":"3640 Dehring Rd",
    "sg:city":"Oakfield",
    "sg:phone":"+1 920 583 3705",
    "sg:postcode":"53065",
    "sg:province":"WI",
    "sg:tags":[
        "farm",
        "grain",
        "cash"
    ],
    "wof:name":"Earl Kettler",
    "wof:placetype":"venue"
},
  "geometry": {"coordinates":[-88.62203100000001,43.671224],"type":"Point"}
}