{
  "type": "Feature",
  "properties": {
    "iso:country":"US",
    "sg:address":"1297 190th Ave",
    "sg:city":"Balsam Lake",
    "sg:classifiers":[
        {
            "category":"Personal",
            "type":"Services"
        }
    ],
    "sg:phone":"+1 715 825 3529",
    "sg:postcode":"54810",
    "sg:province":"WI",
    "wof:name":"Handyman Services",
    "wof:placetype":"venue"
},
  "geometry": {"coordinates":[-92.423916,45.481651],"type":"Point"}
}