{
  "type": "Feature",
  "properties": {
    "iso:country":"US",
    "sg:address":"3540 N 126th St",
    "sg:city":"Brookfield",
    "sg:classifiers":[
        {
            "category":"Professional",
            "type":"Services"
        }
    ],
    "sg:phone":"+1 262 781 3838",
    "sg:postcode":"53005",
    "sg:province":"WI",
    "wof:name":"Cure Water Damage",
    "wof:placetype":"venue"
},
  "geometry": {"coordinates":[-88.068979,43.083819],"type":"Point"}
}