{
  "type": "Feature",
  "properties": {
    "addr:full":"18215 Chevy Chase St Brookfield WI 53045",
    "addr:housenumber":"18215",
    "addr:postcode":"53045",
    "addr:street":"Chevy Chase St",
    "iso:country":"US",
    "sg:address":"18215 Chevy Chase St",
    "sg:city":"Brookfield",
    "sg:classifiers":[
        {
            "category":"Shopping",
            "type":"Retail Goods"
        }
    ],
    "sg:phone":"+1 262 784 9883",
    "sg:postcode":"53045",
    "sg:province":"WI",
    "sg:tags":[
        "educational",
        "material"
    ],
    "wof:name":"Play It Smart",
    "wof:placetype":"venue"
},
  "geometry": {"coordinates":[-88.139323,43.056844],"type":"Point"}
}