{
  "type": "Feature",
  "properties": {
    "iso:country":"US",
    "sg:address":"1130 W Historic Mitchell St",
    "sg:city":"Milwaukee",
    "sg:classifiers":[
        {
            "category":"Shopping",
            "type":"Retail Goods"
        }
    ],
    "sg:phone":"+1 414 384 7786",
    "sg:postcode":"53204",
    "sg:province":"WI",
    "sg:tags":[
        "religious"
    ],
    "wof:name":"Inspiration & Something More",
    "wof:placetype":"venue"
},
  "geometry": {"coordinates":[-87.926536,43.012363],"type":"Point"}
}