{
  "type": "Feature",
  "properties": {
    "iso:country":"US",
    "sg:address":"1003 Washington St",
    "sg:city":"Grafton",
    "sg:classifiers":[
        {
            "category":"Retail",
            "subcategory":"Pet Boarding",
            "type":"Services"
        }
    ],
    "sg:phone":"+1 262 375 0290",
    "sg:postcode":"53024",
    "sg:province":"WI",
    "sg:tags":[
        "boarding/pet",
        "sitting"
    ],
    "wof:name":"Wag'n Tails",
    "wof:placetype":"venue"
},
  "geometry": {"coordinates":[-87.95410200000001,43.32],"type":"Point"}
}