{
  "type": "Feature",
  "properties": {
    "iso:country":"US",
    "sg:address":"1906 86th Pl",
    "sg:city":"Kenosha",
    "sg:classifiers":[
        {
            "category":"Shopping",
            "type":"Retail Goods"
        }
    ],
    "sg:phone":"+1 262 694 0545",
    "sg:postcode":"53143",
    "sg:province":"WI",
    "sg:tags":[
        "merchandise"
    ],
    "wof:name":"Artists Alley",
    "wof:placetype":"venue"
},
  "geometry": {"coordinates":[-87.831781,42.548875],"type":"Point"}
}