{
  "type": "Feature",
  "properties": {
    "iso:country":"US",
    "sg:address":"704 S 15th St",
    "sg:city":"Sheboygan",
    "sg:classifiers":[
        {
            "category":"Manufacturing",
            "subcategory":"Food",
            "type":"Manufacturing & Wholesale Goods"
        }
    ],
    "sg:phone":"+1 920 458 6126",
    "sg:postcode":"53081",
    "sg:province":"WI",
    "sg:tags":[
        "malt",
        "mfg"
    ],
    "sg:website":"www.schreiermalt.com",
    "wof:name":"Cargill Malt Co",
    "wof:placetype":"venue"
},
  "geometry": {"coordinates":[-87.724692,43.746562],"type":"Point"}
}