{
  "type": "Feature",
  "properties": {
    "iso:country":"US",
    "sg:address":"2763 Co Hwy G",
    "sg:city":"Stoughton",
    "sg:classifiers":[
        {
            "category":"Autos & Motor Vehicles",
            "subcategory":"Fuel & Gas Station",
            "type":"Retail Goods"
        }
    ],
    "sg:phone":"+1 608 877 0525",
    "sg:postcode":"53526",
    "sg:province":"WI",
    "sg:tags":[
        "oil"
    ],
    "wof:name":"BP",
    "wof:placetype":"venue"
},
  "geometry": {"coordinates":[-90.329725,42.950238],"type":"Point"}
}