{
  "type": "Feature",
  "properties": {
    "iso:country":"US",
    "sg:address":"101 Kettle Moraine Dr S",
    "sg:city":"Slinger",
    "sg:classifiers":[
        {
            "category":"Professional",
            "subcategory":"Advertising",
            "type":"Services"
        }
    ],
    "sg:phone":"+1 262 644 1961",
    "sg:postcode":"53086",
    "sg:province":"WI",
    "sg:tags":[
        "mail"
    ],
    "wof:name":"Network Marketing",
    "wof:placetype":"venue"
},
  "geometry": {"coordinates":[-88.28510199999999,43.334399],"type":"Point"}
}