{
  "type": "Feature",
  "properties": {
    "iso:country":"US",
    "sg:address":"306 E Main St",
    "sg:city":"Twin Lakes",
    "sg:classifiers":[
        {
            "category":"Food & Beverages",
            "subcategory":"Bakery",
            "type":"Retail Goods"
        }
    ],
    "sg:phone":"+1 262 877 8090",
    "sg:postcode":"53181",
    "sg:province":"WI",
    "sg:tags":[
        "baker"
    ],
    "wof:name":"Bodi's Bake Shop",
    "wof:placetype":"venue"
},
  "geometry": {"coordinates":[-88.250925,42.531758],"type":"Point"}
}