{
  "type": "Feature",
  "properties": {
    "iso:country":"US",
    "sg:address":"3370 Blueberry Rd",
    "sg:city":"Colby",
    "sg:classifiers":[
        {
            "category":"Retail",
            "subcategory":"Auto Repair",
            "type":"Services"
        }
    ],
    "sg:phone":"+1 715 223 2095",
    "sg:postcode":"54421",
    "sg:province":"WI",
    "sg:tags":[
        "engine",
        "diesel"
    ],
    "wof:name":"Diesel Truck Service Inc",
    "wof:placetype":"venue"
},
  "geometry": {"coordinates":[-90.291591,44.888166],"type":"Point"}
}