{
  "type": "Feature",
  "properties": {
    "addr:full":"18272 N Lake Rd Blanchardville WI 53516",
    "addr:housenumber":"18272",
    "addr:postcode":"53516",
    "addr:street":"N Lake Rd",
    "iso:country":"US",
    "sg:address":"18272 N Lake Rd",
    "sg:city":"Blanchardville",
    "sg:classifiers":[
        {
            "category":"Travel",
            "subcategory":"Hotels & Motels",
            "type":"Entertainment"
        }
    ],
    "sg:phone":"+1 608 523 1543",
    "sg:postcode":"53516",
    "sg:province":"WI",
    "sg:tags":[
        "operation",
        "trailer"
    ],
    "wof:name":"Four Seasons Resort",
    "wof:placetype":"venue"
},
  "geometry": {"coordinates":[-89.95198499999999,42.765406],"type":"Point"}
}