{
  "type": "Feature",
  "properties": {
    "iso:country":"US",
    "sg:address":"1631 Livingstone Rd",
    "sg:city":"Hudson",
    "sg:classifiers":[
        {
            "category":"Manufacturing",
            "subcategory":"Signs",
            "type":"Manufacturing & Wholesale Goods"
        }
    ],
    "sg:phone":"+1 715 386 7226",
    "sg:postcode":"54016",
    "sg:province":"WI",
    "sg:tags":[
        "manufacture"
    ],
    "wof:name":"Lebo Sign Works",
    "wof:placetype":"venue"
},
  "geometry": {"coordinates":[-92.736727,44.954603],"type":"Point"}
}