{
  "type": "Feature",
  "properties": {
    "iso:country":"US",
    "sg:address":"3639 Adams Rd",
    "sg:city":"Winter",
    "sg:classifiers":[
        {
            "category":"Travel",
            "subcategory":"Hotels & Motels",
            "type":"Entertainment"
        }
    ],
    "sg:phone":"+1 715 332 5236",
    "sg:postcode":"54896",
    "sg:province":"WI",
    "sg:tags":[
        "resort",
        "operation"
    ],
    "wof:name":"Flambeau Forest Resort",
    "wof:placetype":"venue"
},
  "geometry": {"coordinates":[-90.717837,45.764293],"type":"Point"}
}