{
  "type": "Feature",
  "properties": {
    "iso:country":"US",
    "sg:address":"4583 Schneider Dr",
    "sg:city":"Oregon",
    "sg:classifiers":[
        {
            "category":"Manufacturing",
            "subcategory":"Chemicals & Compounds",
            "type":"Manufacturing & Wholesale Goods"
        }
    ],
    "sg:phone":"+1 608 835 7375",
    "sg:postcode":"53575",
    "sg:province":"WI",
    "sg:tags":[
        "biochemicals",
        "mfg"
    ],
    "wof:name":"Green Hectares",
    "wof:placetype":"venue"
},
  "geometry": {"coordinates":[-89.351759,42.960703],"type":"Point"}
}