{
  "type": "Feature",
  "properties": {
    "iso:country":"US",
    "sg:address":"118 W Main St",
    "sg:city":"Campbellsport",
    "sg:classifiers":[
        {
            "category":"Home & Garden",
            "subcategory":"Building Materials",
            "type":"Retail Goods"
        }
    ],
    "sg:phone":"+1 920 533 4444",
    "sg:postcode":"53010",
    "sg:province":"WI",
    "sg:tags":[
        "hardware"
    ],
    "wof:name":"Village Hardware Hank",
    "wof:placetype":"venue"
},
  "geometry": {"coordinates":[-88.286845,43.598176],"type":"Point"}
}