{
  "type": "Feature",
  "properties": {
    "iso:country":"US",
    "sg:address":"1517 S 12th St",
    "sg:city":"Sheboygan",
    "sg:classifiers":[
        {
            "category":"Recreation",
            "type":"Entertainment"
        }
    ],
    "sg:phone":"+1 920 457 4999",
    "sg:postcode":"53081",
    "sg:province":"WI",
    "sg:tags":[
        "sporting"
    ],
    "wof:name":"Judo No Kata 2 Inc",
    "wof:placetype":"venue"
},
  "geometry": {"coordinates":[-87.719531,43.737502],"type":"Point"}
}