{
  "type": "Feature",
  "properties": {
    "iso:country":"US",
    "sg:address":"6542 River Pkwy",
    "sg:city":"Milwaukee",
    "sg:classifiers":[
        {
            "category":"Retail",
            "subcategory":"Repair Shop",
            "type":"Services"
        }
    ],
    "sg:phone":"+1 414 771 4878",
    "sg:postcode":"53213",
    "sg:province":"WI",
    "wof:name":"Gregs Refinishing",
    "wof:placetype":"venue"
},
  "geometry": {"coordinates":[-87.994701,43.044139],"type":"Point"}
}