{
  "type": "Feature",
  "properties": {
    "iso:country":"US",
    "sg:address":"16214 US Hwy 8",
    "sg:city":"Rice Lake",
    "sg:classifiers":[
        {
            "category":"Bars & Pubs",
            "type":"Food & Drink"
        }
    ],
    "sg:phone":"+1 715 353 2990",
    "sg:postcode":"54868",
    "sg:province":"WI",
    "wof:name":"Bottoms-Up Bar",
    "wof:placetype":"venue"
},
  "geometry": {"coordinates":[-91.512508,45.407619],"type":"Point"}
}