{
  "type": "Feature",
  "properties": {
    "addr:full":"91 Overland Trl Oshkosh WI 54904",
    "addr:housenumber":"91",
    "addr:postcode":"54904",
    "addr:street":"Overland Trl",
    "iso:country":"US",
    "sg:address":"91 Overland Trl",
    "sg:city":"Oshkosh",
    "sg:classifiers":[
        {
            "category":"Sports & Exercise",
            "subcategory":"Gym",
            "type":"Entertainment"
        }
    ],
    "sg:phone":"+1 920 233 2474",
    "sg:postcode":"54904",
    "sg:province":"WI",
    "sg:tags":[
        "fitness",
        "physical",
        "facility"
    ],
    "wof:name":"Jazzercise",
    "wof:placetype":"venue"
},
  "geometry": {"coordinates":[-88.612791,44.019388],"type":"Point"}
}