{
  "type": "Feature",
  "properties": {
    "addr:full":"9136 Short Cut Rd Bloomington WI 53804",
    "addr:housenumber":"9136",
    "addr:postcode":"53804",
    "addr:street":"Short Cut Rd",
    "iso:country":"US",
    "sg:address":"9136 Short Cut Rd",
    "sg:city":"Bloomington",
    "sg:classifiers":[
        {
            "category":"Farming",
            "subcategory":"Farm",
            "type":"Manufacturing & Wholesale Goods"
        }
    ],
    "sg:phone":"+1 608 794 2377",
    "sg:postcode":"53804",
    "sg:province":"WI",
    "sg:tags":[
        "crop",
        "general"
    ],
    "wof:name":"Gerald Mayne",
    "wof:placetype":"venue"
},
  "geometry": {"coordinates":[-90.878685,42.811037],"type":"Point"}
}