{
  "type": "Feature",
  "properties": {
    "addr:full":"515 Main St E Ashland WI 54806",
    "addr:housenumber":"515",
    "addr:postcode":"54806",
    "addr:street":"Main St E",
    "iso:country":"US",
    "sg:address":"515 Main St E",
    "sg:city":"Ashland",
    "sg:classifiers":[
        {
            "category":"Bars & Pubs",
            "type":"Food & Drink"
        }
    ],
    "sg:phone":"+1 715 682 9887",
    "sg:postcode":"54806",
    "sg:province":"WI",
    "sg:tags":[
        "drinking"
    ],
    "wof:name":"Bob & Beckas Packer Inn",
    "wof:placetype":"venue"
},
  "geometry": {"coordinates":[-90.87778,46.593925],"type":"Point"}
}