{
  "type": "Feature",
  "properties": {
    "iso:country":"US",
    "sg:address":"602 N Bay Shore Dr",
    "sg:city":"Sister Bay",
    "sg:classifiers":[
        {
            "category":"Professional",
            "subcategory":"Lawyer & Legal Services",
            "type":"Services"
        }
    ],
    "sg:phone":"+1 920 854 7710",
    "sg:postcode":"54234",
    "sg:province":"WI",
    "wof:name":"Ross Law Office",
    "wof:placetype":"venue"
},
  "geometry": {"coordinates":[-87.121177,45.189023],"type":"Point"}
}