{
  "type": "Feature",
  "properties": {
    "iso:country":"US",
    "sg:address":"833 State St",
    "sg:city":"Ripon",
    "sg:classifiers":[
        {
            "category":"Building & Trades",
            "subcategory":"Landscaping Services",
            "type":"Services"
        }
    ],
    "sg:phone":"+1 920 748 6080",
    "sg:postcode":"54971",
    "sg:province":"WI",
    "sg:tags":[
        "landscape",
        "contractor"
    ],
    "wof:name":"Buy The Yard",
    "wof:placetype":"venue"
},
  "geometry": {"coordinates":[-88.85603500000001,43.845593],"type":"Point"}
}