{
  "type": "Feature",
  "properties": {
    "addr:full":"6627 23rd Ave Kenosha WI 53143",
    "addr:housenumber":"6627",
    "addr:postcode":"53143",
    "addr:street":"23Rd Ave",
    "iso:country":"US",
    "sg:address":"6627 23rd Ave",
    "sg:city":"Kenosha",
    "sg:classifiers":[
        {
            "category":"Home & Garden",
            "subcategory":"Building Materials",
            "type":"Retail Goods"
        },
        {
            "category":"Building & Trades",
            "subcategory":"Construction",
            "type":"Services"
        }
    ],
    "sg:phone":"+1 262 652 8392",
    "sg:postcode":"53143",
    "sg:province":"WI",
    "sg:tags":[
        "chimneys-prefabricated",
        "contractor",
        "chimney",
        "pointing",
        "tuck"
    ],
    "wof:name":"D & H Masonry",
    "wof:placetype":"venue"
},
  "geometry": {"coordinates":[-87.83676699999999,42.574012],"type":"Point"}
}