{
  "type": "Feature",
  "properties": {
    "iso:country":"US",
    "sg:address":"6249 W Port Ave",
    "sg:city":"Milwaukee",
    "sg:classifiers":[
        {
            "category":"Professional",
            "type":"Services"
        }
    ],
    "sg:phone":"+1 414 355 8353",
    "sg:postcode":"53223",
    "sg:province":"WI",
    "wof:name":"Tbi",
    "wof:placetype":"venue"
},
  "geometry": {"coordinates":[-87.991298,43.160145],"type":"Point"}
}