{
  "type": "Feature",
  "properties": {
    "iso:country":"US",
    "sg:address":"1315 N 6th St",
    "sg:city":"Wausau",
    "sg:classifiers":[
        {
            "category":"Organizations",
            "subcategory":"Religious Organization",
            "type":"Services"
        }
    ],
    "sg:phone":"+1 715 842 4283",
    "sg:postcode":"54403",
    "sg:province":"WI",
    "wof:name":"St Michaels Church",
    "wof:placetype":"venue"
},
  "geometry": {"coordinates":[-89.623209,44.968095],"type":"Point"}
}