{
  "type": "Feature",
  "properties": {
    "iso:country":"US",
    "sg:address":"5440 Willow Rd",
    "sg:city":"Waunakee",
    "sg:classifiers":[
        {
            "category":"Professional",
            "subcategory":"Engineering",
            "type":"Services"
        }
    ],
    "sg:phone":"+1 608 441 0715",
    "sg:postcode":"53597",
    "sg:province":"WI",
    "sg:tags":[
        "engineer"
    ],
    "wof:name":"Mc Coy Engineering",
    "wof:placetype":"venue"
},
  "geometry": {"coordinates":[-89.41373,43.15154],"type":"Point"}
}