{
  "type": "Feature",
  "properties": {
    "iso:country":"US",
    "sg:address":"5343 Co Rd V",
    "sg:city":"Pittsville",
    "sg:classifiers":[
        {
            "category":"Government",
            "subcategory":"Office",
            "type":"Public Place"
        }
    ],
    "sg:phone":"+1 715 884 2396",
    "sg:postcode":"54466",
    "sg:province":"WI",
    "sg:tags":[
        "town",
        "govt"
    ],
    "wof:name":"Town of Cary",
    "wof:placetype":"venue"
},
  "geometry": {"coordinates":[-90.259351,44.452091],"type":"Point"}
}