{
  "type": "Feature",
  "properties": {
    "addr:full":"797 Carlin Trl Palmyra WI 53156",
    "addr:housenumber":"797",
    "addr:postcode":"53156",
    "addr:street":"Carlin Trl",
    "iso:country":"US",
    "sg:address":"797 Carlin Trl",
    "sg:city":"Palmyra",
    "sg:classifiers":[
        {
            "category":"Professional",
            "type":"Services"
        }
    ],
    "sg:phone":"+1 262 495 2537",
    "sg:postcode":"53156",
    "sg:province":"WI",
    "sg:tags":[
        "heavy",
        "construction"
    ],
    "wof:name":"Weatherwood Services",
    "wof:placetype":"venue"
},
  "geometry": {"coordinates":[-88.57125499999999,42.87667],"type":"Point"}
}