{
  "type": "Feature",
  "properties": {
    "iso:country":"US",
    "sg:address":"416 E Songbird Ln",
    "sg:city":"Appleton",
    "sg:classifiers":[
        {
            "category":"Professional",
            "subcategory":"Management & Consulting",
            "type":"Services"
        }
    ],
    "sg:phone":"+1 920 730 1088",
    "sg:postcode":"54913",
    "sg:province":"WI",
    "wof:name":"Anxiety Stress Depression Ctr",
    "wof:placetype":"venue"
},
  "geometry": {"coordinates":[-88.400649,44.307078],"type":"Point"}
}