{
  "type": "Feature",
  "properties": {
    "iso:country":"US",
    "sg:address":"392 Brookview Dr",
    "sg:city":"Luxemburg",
    "sg:classifiers":[
        {
            "category":"Building & Trades",
            "subcategory":"Construction",
            "type":"Services"
        }
    ],
    "sg:phone":"+1 920 845 5015",
    "sg:postcode":"54217",
    "sg:province":"WI",
    "sg:tags":[
        "concrete",
        "contractor"
    ],
    "wof:name":"J D Concrete Construction",
    "wof:placetype":"venue"
},
  "geometry": {"coordinates":[-87.70952,44.558085],"type":"Point"}
}