{
  "type": "Feature",
  "properties": {
    "iso:country":"US",
    "sg:address":"605 Night Ct",
    "sg:city":"Green Bay",
    "sg:classifiers":[
        {
            "category":"Professional",
            "type":"Services"
        }
    ],
    "sg:phone":"+1 920 496 2982",
    "sg:postcode":"54313",
    "sg:province":"WI",
    "wof:name":"Docutech LLC",
    "wof:placetype":"venue"
},
  "geometry": {"coordinates":[-88.12790800000001,44.528628],"type":"Point"}
}