{
  "type": "Feature",
  "properties": {
    "iso:country":"US",
    "sg:address":"6466 Mint Rd",
    "sg:city":"Mazomanie",
    "sg:classifiers":[
        {
            "category":"Farming",
            "subcategory":"Farm",
            "type":"Manufacturing & Wholesale Goods"
        }
    ],
    "sg:phone":"+1 608 795 2227",
    "sg:postcode":"53560",
    "sg:province":"WI",
    "wof:name":"Mazo Farms",
    "wof:placetype":"venue"
},
  "geometry": {"coordinates":[-89.769497,43.214667],"type":"Point"}
}