{
  "type": "Feature",
  "properties": {
    "iso:country":"US",
    "sg:address":"2217 Racine St",
    "sg:city":"Racine",
    "sg:classifiers":[
        {
            "category":"Restaurant",
            "type":"Food & Drink"
        }
    ],
    "sg:phone":"+1 262 632 8161",
    "sg:postcode":"53403",
    "sg:province":"WI",
    "sg:tags":[
        "eating"
    ],
    "wof:name":"Mexico Lindo",
    "wof:placetype":"venue"
},
  "geometry": {"coordinates":[-87.79354,42.701587],"type":"Point"}
}