{
  "type": "Feature",
  "properties": {
    "addr:full":"6035 Kumbier Rd Pickett WI 54964",
    "addr:housenumber":"6035",
    "addr:postcode":"54964",
    "addr:street":"Kumbier Rd",
    "iso:country":"US",
    "sg:address":"6035 Kumbier Rd",
    "sg:city":"Pickett",
    "sg:phone":"+1 920 589 5103",
    "sg:postcode":"54964",
    "sg:province":"WI",
    "sg:tags":[
        "farm",
        "field",
        "wheat",
        "crop"
    ],
    "wof:name":"Gary Zahn",
    "wof:placetype":"venue"
},
  "geometry": {"coordinates":[-88.699781,43.901946],"type":"Point"}
}