{
  "type": "Feature",
  "properties": {
    "iso:country":"US",
    "sg:address":"2151 Roosevelt Dr",
    "sg:city":"Plover",
    "sg:classifiers":[
        {
            "category":"Education",
            "subcategory":"Library",
            "type":"Public Place"
        }
    ],
    "sg:phone":"+1 715 341 4007",
    "sg:postcode":"54467",
    "sg:province":"WI",
    "wof:name":"Plover Branch Library",
    "wof:placetype":"venue"
},
  "geometry": {"coordinates":[-89.532045,44.46462],"type":"Point"}
}