{
  "type": "Feature",
  "properties": {
    "iso:country":"US",
    "sg:address":"2555 W Wisconsin St",
    "sg:city":"Portage",
    "sg:classifiers":[
        {
            "category":"Professional",
            "subcategory":"Business Services",
            "type":"Services"
        }
    ],
    "sg:phone":"+1 608 742 6698",
    "sg:postcode":"53901",
    "sg:province":"WI",
    "sg:tags":[
        "car",
        "decorating",
        "custom",
        "fabrication",
        "sign"
    ],
    "wof:name":"L Sign Company",
    "wof:placetype":"venue"
},
  "geometry": {"coordinates":[-89.488643,43.557509],"type":"Point"}
}