{
  "type": "Feature",
  "properties": {
    "iso:country":"US",
    "sg:address":"449 N Main St",
    "sg:city":"West Bend",
    "sg:classifiers":[
        {
            "category":"Wholesale",
            "subcategory":"Auto Parts",
            "type":"Manufacturing & Wholesale Goods"
        }
    ],
    "sg:phone":"+1 262 338 1151",
    "sg:postcode":"53090",
    "sg:province":"WI",
    "sg:tags":[
        "paint",
        "product",
        "related"
    ],
    "wof:name":"Finishmaster Inc",
    "wof:placetype":"venue"
},
  "geometry": {"coordinates":[-88.185956,43.429391],"type":"Point"}
}