{
  "type": "Feature",
  "properties": {
    "iso:country":"US",
    "sg:address":"2460 S Main St",
    "sg:city":"Rice Lake",
    "sg:classifiers":[
        {
            "category":"Utilities",
            "subcategory":"Mobile Phone",
            "type":"Services"
        }
    ],
    "sg:phone":"+1 715 736 2355",
    "sg:postcode":"54868",
    "sg:province":"WI",
    "sg:tags":[
        "communication",
        "radiotelephone"
    ],
    "wof:name":"Wireless Solutions",
    "wof:placetype":"venue"
},
  "geometry": {"coordinates":[-91.735314,45.475591],"type":"Point"}
}