{
  "type": "Feature",
  "properties": {
    "iso:country":"US",
    "sg:address":"5728 E Co Rd X",
    "sg:city":"Beloit",
    "sg:classifiers":[
        {
            "category":"Shopping",
            "subcategory":"Bicycles & Sporting Goods",
            "type":"Retail Goods"
        }
    ],
    "sg:phone":"+1 608 676 5628",
    "sg:postcode":"53511",
    "sg:province":"WI",
    "sg:tags":[
        "repair",
        "firearm",
        "mfg"
    ],
    "wof:name":"R & D Gun Shop Inc",
    "wof:placetype":"venue"
},
  "geometry": {"coordinates":[-88.92582299999999,42.546481],"type":"Point"}
}