{
  "type": "Feature",
  "properties": {
    "iso:country":"US",
    "sg:address":"8050 N Port Washington Rd",
    "sg:city":"Milwaukee",
    "sg:classifiers":[
        {
            "category":"Shopping",
            "subcategory":"Mobile Phones",
            "type":"Retail Goods"
        }
    ],
    "sg:phone":"+1 414 352 9310",
    "sg:postcode":"53217",
    "sg:province":"WI",
    "sg:tags":[
        "home"
    ],
    "wof:name":"Home Source One",
    "wof:placetype":"venue"
},
  "geometry": {"coordinates":[-87.91161200000001,43.163229],"type":"Point"}
}