{
  "type": "Feature",
  "properties": {
    "iso:country":"US",
    "sg:address":"1910 Center Rd",
    "sg:city":"Dorchester",
    "sg:classifiers":[
        {
            "category":"Farming",
            "subcategory":"Dairy Farm",
            "type":"Manufacturing & Wholesale Goods"
        }
    ],
    "sg:phone":"+1 715 654 5219",
    "sg:postcode":"54425",
    "sg:province":"WI",
    "wof:name":"Raymond Mulderink",
    "wof:placetype":"venue"
},
  "geometry": {"coordinates":[-90.407313,44.987714],"type":"Point"}
}