{
  "type": "Feature",
  "properties": {
    "addr:full":"1847 Hill Rd Greenleaf WI 54126",
    "addr:housenumber":"1847",
    "addr:postcode":"54126",
    "addr:street":"Hill Rd",
    "iso:country":"US",
    "sg:address":"1847 Hill Rd",
    "sg:city":"Greenleaf",
    "sg:classifiers":[
        {
            "category":"Farming",
            "subcategory":"Dairy Farm",
            "type":"Manufacturing & Wholesale Goods"
        }
    ],
    "sg:phone":"+1 920 532 4723",
    "sg:postcode":"54126",
    "sg:province":"WI",
    "wof:name":"Jerome Wall",
    "wof:placetype":"venue"
},
  "geometry": {"coordinates":[-88.072568,44.270209],"type":"Point"}
}