{
  "type": "Feature",
  "properties": {
    "iso:country":"US",
    "sg:address":"2934 Fish Hatchery Rd",
    "sg:city":"Madison",
    "sg:classifiers":[
        {
            "category":"Professional",
            "type":"Services"
        }
    ],
    "sg:phone":"+1 608 271 3068",
    "sg:postcode":"53713",
    "sg:province":"WI",
    "wof:name":"Brown Tailors",
    "wof:placetype":"venue"
},
  "geometry": {"coordinates":[-89.411749,43.028008],"type":"Point"}
}