{
  "type": "Feature",
  "properties": {
    "iso:country":"US",
    "sg:address":"1999 State Hwy 54",
    "sg:city":"Waupaca",
    "sg:classifiers":[
        {
            "category":"Wholesale",
            "subcategory":"Auto Parts",
            "type":"Manufacturing & Wholesale Goods"
        }
    ],
    "sg:phone":"+1 715 256 1500",
    "sg:postcode":"54981",
    "sg:province":"WI",
    "sg:tags":[
        "brakes"
    ],
    "wof:name":"Dana Brakes & Chassis",
    "wof:placetype":"venue"
},
  "geometry": {"coordinates":[-89.132964,44.351814],"type":"Point"}
}