{
  "type": "Feature",
  "properties": {
    "iso:country":"US",
    "sg:address":"2267 80th St",
    "sg:city":"New Richmond",
    "sg:classifiers":[
        {
            "category":"Manufacturing",
            "subcategory":"Metals",
            "type":"Manufacturing & Wholesale Goods"
        }
    ],
    "sg:phone":"+1 715 248 3074",
    "sg:postcode":"54017",
    "sg:province":"WI",
    "sg:tags":[
        "product",
        "mfg"
    ],
    "wof:name":"S and S Coatings Inc",
    "wof:placetype":"venue"
},
  "geometry": {"coordinates":[-92.651498,45.192251],"type":"Point"}
}