{
  "type": "Feature",
  "properties": {
    "addr:full":"8302 Belle Plaine Ave Shawano WI 54166",
    "addr:housenumber":"8302",
    "addr:postcode":"54166",
    "addr:street":"Belle Plaine Ave",
    "iso:country":"US",
    "sg:address":"8302 Belle Plaine Ave",
    "sg:city":"Shawano",
    "sg:classifiers":[
        {
            "category":"Organizations",
            "subcategory":"Religious Organization",
            "type":"Services"
        }
    ],
    "sg:phone":"+1 715 526 2563",
    "sg:postcode":"54166",
    "sg:province":"WI",
    "sg:tags":[
        "church"
    ],
    "wof:name":"St Martins Lutheran Chr-ELS",
    "wof:placetype":"venue"
},
  "geometry": {"coordinates":[-88.656527,44.717117],"type":"Point"}
}