{
  "type": "Feature",
  "properties": {
    "iso:country":"US",
    "sg:address":"5850 Hillside School Rd",
    "sg:city":"Spring Green",
    "sg:classifiers":[
        {
            "category":"Building & Trades",
            "subcategory":"Landscaping Services",
            "type":"Services"
        }
    ],
    "sg:phone":"+1 608 588 7701",
    "sg:postcode":"53588",
    "sg:province":"WI",
    "sg:tags":[
        "tree"
    ],
    "wof:name":"Phils Tree Spade Svc",
    "wof:placetype":"venue"
},
  "geometry": {"coordinates":[-90.07199900000001,43.097585],"type":"Point"}
}