{
  "type": "Feature",
  "properties": {
    "addr:full":"238 Main St Darlington WI 53530",
    "addr:housenumber":"238",
    "addr:postcode":"53530",
    "addr:street":"Main St",
    "iso:country":"US",
    "sg:address":"238 Main St",
    "sg:city":"Darlington",
    "sg:classifiers":[
        {
            "category":"Shopping",
            "subcategory":"Used Merchandise",
            "type":"Retail Goods"
        },
        {
            "category":"Shopping",
            "subcategory":"Gifts & Souvenirs",
            "type":"Retail Goods"
        }
    ],
    "sg:phone":"+1 608 776 3070",
    "sg:postcode":"53530",
    "sg:province":"WI",
    "sg:tags":[
        "shop"
    ],
    "wof:name":"Antiques & Accents",
    "wof:placetype":"venue"
},
  "geometry": {"coordinates":[-90.117863,42.678401],"type":"Point"}
}