{
  "type": "Feature",
  "properties": {
    "iso:country":"US",
    "sg:address":"725 Broadway St",
    "sg:city":"Sheboygan Falls",
    "sg:classifiers":[
        {
            "category":"Shopping",
            "subcategory":"Gifts & Souvenirs",
            "type":"Retail Goods"
        }
    ],
    "sg:phone":"+1 920 467 0703",
    "sg:postcode":"53085",
    "sg:province":"WI",
    "wof:name":"Goose N Ewe",
    "wof:placetype":"venue"
},
  "geometry": {"coordinates":[-87.810126,43.72649],"type":"Point"}
}