{
  "type": "Feature",
  "properties": {
    "iso:country":"US",
    "sg:address":"6504 Co Rd G",
    "sg:city":"Denmark",
    "sg:classifiers":[
        {
            "category":"Bars & Pubs",
            "type":"Food & Drink"
        }
    ],
    "sg:phone":"+1 920 864 2239",
    "sg:postcode":"54208",
    "sg:province":"WI",
    "sg:tags":[
        "drinking"
    ],
    "wof:name":"The Coop",
    "wof:placetype":"venue"
},
  "geometry": {"coordinates":[-87.948407,44.327701],"type":"Point"}
}