{
  "type": "Feature",
  "properties": {
    "iso:country":"US",
    "sg:address":"8544 W National Ave",
    "sg:city":"Milwaukee",
    "sg:classifiers":[
        {
            "category":"Food & Beverages",
            "subcategory":"Specialty",
            "type":"Retail Goods"
        }
    ],
    "sg:phone":"+1 414 329 0648",
    "sg:postcode":"53227",
    "sg:province":"WI",
    "sg:tags":[
        "product",
        "health",
        "diet"
    ],
    "sg:website":"www.vhp4.com",
    "wof:name":"Vital Health Products Ltd",
    "wof:placetype":"venue"
},
  "geometry": {"coordinates":[-88.018517,43.009474],"type":"Point"}
}