{
  "type": "Feature",
  "properties": {
    "iso:country":"US",
    "sg:address":"430 Manor Dr",
    "sg:city":"Suring",
    "sg:classifiers":[
        {
            "category":"Health Services",
            "subcategory":"Nursing And Care Facility",
            "type":"Services"
        }
    ],
    "sg:phone":"+1 920 842 2191",
    "sg:postcode":"54174",
    "sg:province":"WI",
    "sg:tags":[
        "skilled",
        "intermediate"
    ],
    "wof:name":"Woodland Vlg Nrsing HM Asssted",
    "wof:placetype":"venue"
},
  "geometry": {"coordinates":[-88.372871,45.002374],"type":"Point"}
}