{
  "type": "Feature",
  "properties": {
    "iso:country":"US",
    "sg:address":"7918 State Hwy 73",
    "sg:city":"Gilman",
    "sg:classifiers":[
        {
            "category":"Building & Trades",
            "subcategory":"Construction",
            "type":"Services"
        }
    ],
    "sg:phone":"+1 715 668 5212",
    "sg:postcode":"54433",
    "sg:province":"WI",
    "sg:tags":[
        "general"
    ],
    "wof:name":"John F Olynik Inc",
    "wof:placetype":"venue"
},
  "geometry": {"coordinates":[-90.781914,45.308549],"type":"Point"}
}