{
  "type": "Feature",
  "properties": {
    "iso:country":"US",
    "sg:address":"2960 Cahill Main",
    "sg:city":"Madison",
    "sg:classifiers":[
        {
            "category":"Bakery",
            "type":"Food & Drink"
        }
    ],
    "sg:menulink":"http://www.allmenus.com/wi/fitchburg/41099-panera-bread/menu/",
    "sg:phone":"+1 608 441 8883",
    "sg:postcode":"53711",
    "sg:province":"WI",
    "sg:tags":[
        "american",
        "sandwich",
        "pastry"
    ],
    "wof:name":"Panera Bread",
    "wof:placetype":"venue"
},
  "geometry": {"coordinates":[-89.422758,43.017122],"type":"Point"}
}