{
  "type": "Feature",
  "properties": {
    "iso:country":"US",
    "sg:address":"890 Elm Grove Rd",
    "sg:city":"Elm Grove",
    "sg:classifiers":[
        {
            "category":"Professional",
            "subcategory":"Art Services",
            "type":"Services"
        },
        {
            "category":"Professional",
            "subcategory":"Advertising",
            "type":"Services"
        }
    ],
    "sg:phone":"+1 262 821 5898",
    "sg:postcode":"53122",
    "sg:province":"WI",
    "sg:tags":[
        "counselor",
        "agency"
    ],
    "sg:website":"www.gen-cg.com",
    "wof:name":"Genesis Creative Group Inc",
    "wof:placetype":"venue"
},
  "geometry": {"coordinates":[-88.078974,43.039592],"type":"Point"}
}