{
  "type": "Feature",
  "properties": {
    "iso:country":"US",
    "sg:address":"9626 W Carmen Ave",
    "sg:city":"Milwaukee",
    "sg:classifiers":[
        {
            "category":"Wholesale",
            "subcategory":"Machinery & Supplies",
            "type":"Manufacturing & Wholesale Goods"
        }
    ],
    "sg:phone":"+1 414 536 0488",
    "sg:postcode":"53225",
    "sg:province":"WI",
    "sg:tags":[
        "equipment",
        "printing"
    ],
    "wof:name":"Hebert Machinery & Equipment",
    "wof:placetype":"venue"
},
  "geometry": {"coordinates":[-88.032923,43.12323],"type":"Point"}
}