{
  "type": "Feature",
  "properties": {
    "addr:full":"W23453 Lake Rd Trempealeau WI 54661",
    "addr:housenumber":"w23453",
    "addr:postcode":"54661",
    "addr:street":"Lake Rd",
    "iso:country":"US",
    "sg:address":"W23453 Lake Rd",
    "sg:city":"Trempealeau",
    "sg:classifiers":[
        {
            "category":"Building & Trades",
            "subcategory":"Landscaping Services",
            "type":"Services"
        }
    ],
    "sg:phone":"+1 608 534 6789",
    "sg:postcode":"54661",
    "sg:province":"WI",
    "sg:tags":[
        "lawn",
        "maintenance"
    ],
    "wof:name":"Phil's Lawn Care",
    "wof:placetype":"venue"
},
  "geometry": {"coordinates":[-91.417957,43.986284],"type":"Point"}
}