{
  "type": "Feature",
  "properties": {
    "iso:country":"US",
    "sg:address":"22 W Spring St",
    "sg:city":"Chippewa Falls",
    "sg:classifiers":[
        {
            "category":"Shopping",
            "subcategory":"Clothing, Apparel, & Fashions",
            "type":"Retail Goods"
        }
    ],
    "sg:phone":"+1 715 720 9449",
    "sg:postcode":"54729",
    "sg:province":"WI",
    "sg:tags":[
        "infant",
        "wear"
    ],
    "wof:name":"Tokens",
    "wof:placetype":"venue"
},
  "geometry": {"coordinates":[-91.392731,44.935075],"type":"Point"}
}