{
  "type": "Feature",
  "properties": {
    "iso:country":"US",
    "sg:address":"440 Krattley Ln",
    "sg:city":"Hudson",
    "sg:classifiers":[
        {
            "category":"Professional",
            "subcategory":"Management & Consulting",
            "type":"Services"
        }
    ],
    "sg:phone":"+1 715 386 9669",
    "sg:postcode":"54016",
    "sg:province":"WI",
    "sg:tags":[
        "consultant",
        "business"
    ],
    "wof:name":"Apostle Islands Consultants",
    "wof:placetype":"venue"
},
  "geometry": {"coordinates":[-92.726401,45.012763],"type":"Point"}
}