{
  "type": "Feature",
  "properties": {
    "addr:full":"10058 1170th Ave Colfax WI 54730",
    "addr:housenumber":"10058",
    "addr:postcode":"54730",
    "addr:street":"1170Th Ave",
    "iso:country":"US",
    "sg:address":"10058 1170th Ave",
    "sg:city":"Colfax",
    "sg:classifiers":[
        {
            "category":"Farming",
            "subcategory":"Dairy Farm",
            "type":"Manufacturing & Wholesale Goods"
        }
    ],
    "sg:phone":"+1 715 568 5163",
    "sg:postcode":"54730",
    "sg:province":"WI",
    "wof:name":"Brad Dietsche",
    "wof:placetype":"venue"
},
  "geometry": {"coordinates":[-91.653806,45.096847],"type":"Point"}
}