{
  "type": "Feature",
  "properties": {
    "iso:country":"US",
    "sg:address":"5441 S 48th St",
    "sg:city":"Milwaukee",
    "sg:classifiers":[
        {
            "category":"Professional",
            "subcategory":"Business Services",
            "type":"Services"
        }
    ],
    "sg:phone":"+1 414 421 3976",
    "sg:postcode":"53220",
    "sg:province":"WI",
    "sg:tags":[
        "trade",
        "set",
        "up",
        "show"
    ],
    "wof:name":"Wisconsin Expo Inc",
    "wof:placetype":"venue"
},
  "geometry": {"coordinates":[-87.975192,42.947671],"type":"Point"}
}