{
  "type": "Feature",
  "properties": {
    "iso:country":"US",
    "sg:address":"3808 E 3rd St",
    "sg:city":"Superior",
    "sg:classifiers":[
        {
            "category":"Restaurant",
            "type":"Food & Drink"
        }
    ],
    "sg:phone":"+1 715 392 6069",
    "sg:postcode":"54880",
    "sg:province":"WI",
    "sg:tags":[
        "eating"
    ],
    "wof:name":"TS Snack Bar",
    "wof:placetype":"venue"
},
  "geometry": {"coordinates":[-92.026103,46.688484],"type":"Point"}
}