{
  "type": "Feature",
  "properties": {
    "iso:country":"US",
    "sg:address":"3595 N 124th St",
    "sg:city":"Brookfield",
    "sg:classifiers":[
        {
            "category":"Retail",
            "subcategory":"Auto Repair",
            "type":"Services"
        }
    ],
    "sg:phone":"+1 262 781 6000",
    "sg:postcode":"53005",
    "sg:province":"WI",
    "sg:tags":[
        "automotive"
    ],
    "wof:name":"A & A Towing",
    "wof:placetype":"venue"
},
  "geometry": {"coordinates":[-88.066669,43.080071],"type":"Point"}
}