{
  "type": "Feature",
  "properties": {
    "iso:country":"US",
    "sg:address":"434 State Farm Rd",
    "sg:city":"Deerfield",
    "sg:classifiers":[
        {
            "category":"Government",
            "subcategory":"Jail",
            "type":"Public Place"
        }
    ],
    "sg:phone":"+1 608 423 3415",
    "sg:postcode":"53561",
    "sg:province":"WI",
    "sg:tags":[
        "community",
        "supervision"
    ],
    "wof:name":"Division Community Corrections",
    "wof:placetype":"venue"
},
  "geometry": {"coordinates":[-89.04592700000001,43.023476],"type":"Point"}
}