{
  "type": "Feature",
  "properties": {
    "addr:full":"555 W Washington Ave Madison WI 53703",
    "addr:housenumber":"555",
    "addr:postcode":"53703",
    "addr:street":"W Washington Ave",
    "iso:country":"US",
    "sg:address":"555 W Washington Ave",
    "sg:city":"Madison",
    "sg:classifiers":[
        {
            "category":"Banks & Credit Unions",
            "subcategory":"Bank",
            "type":"Services"
        }
    ],
    "sg:phone":"+1 608 282 7000",
    "sg:postcode":"53703",
    "sg:province":"WI",
    "sg:website":"www.heartlandcu.org",
    "wof:name":"Heartland Credit Union",
    "wof:placetype":"venue"
},
  "geometry": {"coordinates":[-89.391682,43.069475],"type":"Point"}
}