{
  "type": "Feature",
  "properties": {
    "iso:country":"US",
    "sg:address":"1800 Excalibur Dr",
    "sg:city":"Janesville",
    "sg:classifiers":[
        {
            "category":"Insurance",
            "subcategory":"Health Insurance",
            "type":"Services"
        }
    ],
    "sg:phone":"+1 608 752 6627",
    "sg:postcode":"53546",
    "sg:province":"WI",
    "sg:tags":[
        "carrier"
    ],
    "wof:name":"Order of United Comm Trvlr",
    "wof:placetype":"venue"
},
  "geometry": {"coordinates":[-88.974869,42.70529],"type":"Point"}
}