{
  "type": "Feature",
  "properties": {
    "iso:country":"US",
    "sg:address":"1415 S Rapids Rd",
    "sg:city":"Manitowoc",
    "sg:classifiers":[
        {
            "category":"Health Services",
            "subcategory":"Clinic",
            "type":"Services"
        }
    ],
    "sg:phone":"+1 920 684 7071",
    "sg:postcode":"54220",
    "sg:province":"WI",
    "sg:website":"www.fhcm.org",
    "wof:name":"Franciscan Sisters Christian",
    "wof:placetype":"venue"
},
  "geometry": {"coordinates":[-87.708068,44.082334],"type":"Point"}
}