{
  "type": "Feature",
  "properties": {
    "iso:country":"US",
    "sg:address":"1265 N 4th St",
    "sg:city":"Platteville",
    "sg:classifiers":[
        {
            "category":"Travel",
            "subcategory":"Hotels & Motels",
            "type":"Entertainment"
        }
    ],
    "sg:phone":"+1 608 348 7244",
    "sg:postcode":"53818",
    "sg:province":"WI",
    "sg:tags":[
        "operation"
    ],
    "wof:name":"A D B A Corp",
    "wof:placetype":"venue"
},
  "geometry": {"coordinates":[-90.475674,42.745279],"type":"Point"}
}