{
  "type": "Feature",
  "properties": {
    "iso:country":"US",
    "sg:address":"309 Travis Ln",
    "sg:city":"Waukesha",
    "sg:classifiers":[
        {
            "category":"Retail",
            "subcategory":"Auto Repair",
            "type":"Services"
        }
    ],
    "sg:phone":"+1 262 544 5266",
    "sg:postcode":"53189",
    "sg:province":"WI",
    "sg:tags":[
        "body",
        "automobile",
        "painting"
    ],
    "wof:name":"American Auto Body",
    "wof:placetype":"venue"
},
  "geometry": {"coordinates":[-88.230994,42.975888],"type":"Point"}
}