{
  "type": "Feature",
  "properties": {
    "iso:country":"US",
    "sg:address":"1630 S 38th St",
    "sg:city":"Milwaukee",
    "sg:classifiers":[
        {
            "category":"Retail",
            "subcategory":"Repair Shop",
            "type":"Services"
        }
    ],
    "sg:phone":"+1 414 645 0130",
    "sg:postcode":"53215",
    "sg:province":"WI",
    "sg:tags":[
        "equipment",
        "scale",
        "commercial"
    ],
    "wof:name":"Fairbanks Scales Inc",
    "wof:placetype":"venue"
},
  "geometry": {"coordinates":[-87.96177299999999,43.012857],"type":"Point"}
}