{
  "type": "Feature",
  "properties": {
    "addr:full":"1226 N 8th St Sheboygan WI 53081",
    "addr:housenumber":"1226",
    "addr:postcode":"53081",
    "addr:street":"N 8Th St",
    "iso:country":"US",
    "sg:address":"1226 N 8th St",
    "sg:city":"Sheboygan",
    "sg:classifiers":[
        {
            "category":"Wholesale",
            "subcategory":"Groceries",
            "type":"Manufacturing & Wholesale Goods"
        }
    ],
    "sg:phone":"+1 920 803 0298",
    "sg:postcode":"53081",
    "sg:province":"WI",
    "sg:tags":[
        "record",
        "book"
    ],
    "wof:name":"New Life Christian Book Store",
    "wof:placetype":"venue"
},
  "geometry": {"coordinates":[-87.71301200000001,43.75824],"type":"Point"}
}