{
  "type": "Feature",
  "properties": {
    "addr:full":"1000 Manchester St Baraboo WI 53913",
    "addr:housenumber":"1000",
    "addr:postcode":"53913",
    "addr:street":"Manchester St",
    "iso:country":"US",
    "sg:address":"1000 Manchester St",
    "sg:city":"Baraboo",
    "sg:classifiers":[
        {
            "category":"Government",
            "subcategory":"Office",
            "type":"Public Place"
        }
    ],
    "sg:phone":"+1 608 355 2755",
    "sg:postcode":"53913",
    "sg:province":"WI",
    "sg:tags":[
        "village"
    ],
    "wof:name":"Baraboo City Sewage Treatment",
    "wof:placetype":"venue"
},
  "geometry": {"coordinates":[-89.727794,43.459997],"type":"Point"}
}