{
  "type": "Feature",
  "properties": {
    "iso:country":"US",
    "sg:address":"325 US Hwy 12",
    "sg:city":"Wisconsin Dells",
    "sg:classifiers":[
        {
            "category":"Travel",
            "subcategory":"Hotels & Motels",
            "type":"Entertainment"
        }
    ],
    "sg:phone":"+1 608 254 8443",
    "sg:postcode":"53965",
    "sg:province":"WI",
    "wof:name":"Shady Nook Motel",
    "wof:placetype":"venue"
},
  "geometry": {"coordinates":[-89.79115,43.589003],"type":"Point"}
}