{
  "type": "Feature",
  "properties": {
    "addr:full":"6912 N Lincolnshire Cir Milwaukee WI 53223",
    "addr:housenumber":"6912",
    "addr:postcode":"53223",
    "addr:street":"N Lincolnshire Cir",
    "iso:country":"US",
    "sg:address":"6912 N Lincolnshire Cir",
    "sg:city":"Milwaukee",
    "sg:classifiers":[
        {
            "category":"Wholesale",
            "subcategory":"Vending Machines",
            "type":"Manufacturing & Wholesale Goods"
        }
    ],
    "sg:phone":"+1 414 353 2626",
    "sg:postcode":"53223",
    "sg:province":"WI",
    "sg:tags":[
        "operator"
    ],
    "wof:name":"Mil Wis Vending Inc",
    "wof:placetype":"venue"
},
  "geometry": {"coordinates":[-87.981893,43.144787],"type":"Point"}
}