{
  "type": "Feature",
  "properties": {
    "iso:country":"US",
    "sg:address":"8244 US Hwy 12",
    "sg:city":"Black River Fls",
    "sg:classifiers":[
        {
            "category":"Freight",
            "type":"Transportation"
        }
    ],
    "sg:phone":"+1 715 284 8363",
    "sg:postcode":"54615",
    "sg:province":"WI",
    "sg:tags":[
        "mobile",
        "home"
    ],
    "wof:name":"Lti Mobile Transport Svc",
    "wof:placetype":"venue"
},
  "geometry": {"coordinates":[-90.721609,44.224543],"type":"Point"}
}