{
  "type": "Feature",
  "properties": {
    "iso:country":"US",
    "sg:address":"1011 Vernon St",
    "sg:city":"Altoona",
    "sg:classifiers":[
        {
            "category":"Building & Trades",
            "subcategory":"Construction",
            "type":"Services"
        }
    ],
    "sg:phone":"+1 715 835 3144",
    "sg:postcode":"54720",
    "sg:province":"WI",
    "sg:tags":[
        "glass",
        "installation",
        "contractor"
    ],
    "wof:name":"Piltz Glass & Mirror",
    "wof:placetype":"venue"
},
  "geometry": {"coordinates":[-91.46012899999999,44.798509],"type":"Point"}
}