{
  "type": "Feature",
  "properties": {
    "iso:country":"US",
    "sg:address":"213 60th Ave",
    "sg:city":"Clayton",
    "sg:classifiers":[
        {
            "category":"Building & Trades",
            "subcategory":"Plumbing",
            "type":"Services"
        }
    ],
    "sg:phone":"+1 715 948 2942",
    "sg:postcode":"54004",
    "sg:province":"WI",
    "sg:tags":[
        "contractor"
    ],
    "wof:name":"Olander Heating & AC",
    "wof:placetype":"venue"
},
  "geometry": {"coordinates":[-92.205246,45.295321],"type":"Point"}
}