{
  "type": "Feature",
  "properties": {
    "iso:country":"US",
    "sg:address":"6722 State Rd 50",
    "sg:city":"Lake Geneva",
    "sg:classifiers":[
        {
            "category":"Social Services",
            "subcategory":"Adult Care",
            "type":"Services"
        }
    ],
    "sg:phone":"+1 262 248 2029",
    "sg:postcode":"53147",
    "sg:province":"WI",
    "sg:tags":[
        "home",
        "residential"
    ],
    "wof:name":"Harbor House",
    "wof:placetype":"venue"
},
  "geometry": {"coordinates":[-88.396671,42.595685],"type":"Point"}
}