{
  "type": "Feature",
  "properties": {
    "iso:country":"US",
    "sg:address":"4408 Deer Park Rd",
    "sg:city":"Oconomowoc",
    "sg:classifiers":[
        {
            "category":"Wholesale",
            "subcategory":"Machinery & Supplies",
            "type":"Manufacturing & Wholesale Goods"
        }
    ],
    "sg:phone":"+1 262 569 7171",
    "sg:postcode":"53066",
    "sg:province":"WI",
    "sg:tags":[
        "equipment"
    ],
    "sg:website":"www.odininc.com",
    "wof:name":"Odin International Inc",
    "wof:placetype":"venue"
},
  "geometry": {"coordinates":[-88.476134,43.102732],"type":"Point"}
}