{
  "type": "Feature",
  "properties": {
    "iso:country":"US",
    "sg:address":"1302 Maple Rd",
    "sg:city":"Seymour",
    "sg:classifiers":[
        {
            "category":"Organizations",
            "subcategory":"Religious Organization",
            "type":"Services"
        }
    ],
    "sg:phone":"+1 920 822 5512",
    "sg:postcode":"54165",
    "sg:province":"WI",
    "wof:name":"St Stanislaus Parish",
    "wof:placetype":"venue"
},
  "geometry": {"coordinates":[-88.332904,44.630162],"type":"Point"}
}