{
  "type": "Feature",
  "properties": {
    "addr:full":"206 Avalon Rd Columbus WI 53925",
    "addr:housenumber":"206",
    "addr:postcode":"53925",
    "addr:street":"Avalon Rd",
    "iso:country":"US",
    "sg:address":"206 Avalon Rd",
    "sg:city":"Columbus",
    "sg:classifiers":[
        {
            "category":"Real Estate",
            "subcategory":"Real Estate Operator",
            "type":"Services"
        }
    ],
    "sg:phone":"+1 920 623 3267",
    "sg:postcode":"53925",
    "sg:province":"WI",
    "sg:tags":[
        "property",
        "lessor"
    ],
    "wof:name":"Jerome Derr",
    "wof:placetype":"venue"
},
  "geometry": {"coordinates":[-89.03261000000001,43.325096],"type":"Point"}
}