{
  "type": "Feature",
  "properties": {
    "iso:country":"US",
    "sg:address":"6357 Center Rd",
    "sg:city":"Withee",
    "sg:classifiers":[
        {
            "category":"Farming",
            "subcategory":"Dairy Farm",
            "type":"Manufacturing & Wholesale Goods"
        }
    ],
    "sg:phone":"+1 715 229 4649",
    "sg:postcode":"54498",
    "sg:province":"WI",
    "wof:name":"Marvin Brubaker",
    "wof:placetype":"venue"
},
  "geometry": {"coordinates":[-90.63091799999999,44.987673],"type":"Point"}
}