{
  "type": "Feature",
  "properties": {
    "iso:country":"US",
    "sg:address":"1014 Parkview Rd",
    "sg:city":"Green Bay",
    "sg:classifiers":[
        {
            "category":"Wholesale",
            "subcategory":"Machinery & Supplies",
            "type":"Manufacturing & Wholesale Goods"
        },
        {
            "category":"Retail",
            "subcategory":"Repair Shop",
            "type":"Services"
        }
    ],
    "sg:phone":"+1 920 403 1036",
    "sg:postcode":"54304",
    "sg:province":"WI",
    "sg:tags":[
        "equipment",
        "material",
        "industrial",
        "handling"
    ],
    "sg:website":"www.powerampnorth.com",
    "wof:name":"Poweramp Equipment North",
    "wof:placetype":"venue"
},
  "geometry": {"coordinates":[-88.088089,44.467483],"type":"Point"}
}