{
  "type": "Feature",
  "properties": {
    "iso:country":"US",
    "sg:address":"1195 N Perkins St",
    "sg:city":"Appleton",
    "sg:classifiers":[
        {
            "category":"Wholesale",
            "subcategory":"Metals & Minerals",
            "type":"Manufacturing & Wholesale Goods"
        }
    ],
    "sg:phone":"+1 920 832 1250",
    "sg:postcode":"54914",
    "sg:province":"WI",
    "sg:tags":[
        "center"
    ],
    "wof:name":"Reynolds Building Products",
    "wof:placetype":"venue"
},
  "geometry": {"coordinates":[-88.441324,44.269559],"type":"Point"}
}