{
  "type": "Feature",
  "properties": {
    "iso:country":"US",
    "sg:address":"11801 W Silver Spring Dr",
    "sg:city":"Milwaukee",
    "sg:classifiers":[
        {
            "category":"Organizations",
            "subcategory":"Professional Association",
            "type":"Services"
        }
    ],
    "sg:phone":"+1 414 462 8492",
    "sg:postcode":"53225",
    "sg:province":"WI",
    "wof:name":"Wisconsin Association Mgmt",
    "wof:placetype":"venue"
},
  "geometry": {"coordinates":[-88.06095999999999,43.117029],"type":"Point"}
}