{
  "type": "Feature",
  "properties": {
    "addr:full":"6970 E School St Three Lakes WI 54562",
    "addr:housenumber":"6970",
    "addr:postcode":"54562",
    "addr:street":"E School St",
    "iso:country":"US",
    "sg:address":"6970 E School St",
    "sg:city":"Three Lakes",
    "sg:classifiers":[
        {
            "category":"Government",
            "subcategory":"Post Office",
            "type":"Public Place"
        }
    ],
    "sg:phone":"+1 715 546 3410",
    "sg:postcode":"54562",
    "sg:province":"WI",
    "wof:name":"US Post Office",
    "wof:placetype":"venue"
},
  "geometry": {"coordinates":[-89.167807,45.797932],"type":"Point"}
}