{
  "type": "Feature",
  "properties": {
    "iso:country":"US",
    "sg:address":"1525 Michigan Ave",
    "sg:city":"Sheboygan",
    "sg:classifiers":[
        {
            "category":"Education",
            "subcategory":"Dance Studio",
            "type":"Public Place"
        }
    ],
    "sg:phone":"+1 920 208 3730",
    "sg:postcode":"53081",
    "sg:province":"WI",
    "wof:name":"Tikvah Dance Studio",
    "wof:placetype":"venue"
},
  "geometry": {"coordinates":[-87.72599200000001,43.758496],"type":"Point"}
}