{
  "type": "Feature",
  "properties": {
    "iso:country":"US",
    "sg:address":"888 Jackson St",
    "sg:city":"Oshkosh",
    "sg:classifiers":[
        {
            "category":"Real Estate",
            "subcategory":"Real Estate Services",
            "type":"Services"
        }
    ],
    "sg:phone":"+1 920 235 7760",
    "sg:postcode":"54901",
    "sg:province":"WI",
    "sg:tags":[
        "company",
        "title"
    ],
    "wof:name":"Home Title & Abstract",
    "wof:placetype":"venue"
},
  "geometry": {"coordinates":[-88.542504,44.026786],"type":"Point"}
}