{
  "type": "Feature",
  "properties": {
    "iso:country":"US",
    "sg:address":"3445 Hickory Hills Rd",
    "sg:city":"Chilton",
    "sg:classifiers":[
        {
            "category":"Wholesale",
            "subcategory":"Meat",
            "type":"Manufacturing & Wholesale Goods"
        },
        {
            "category":"Farming",
            "subcategory":"Farm & Veterinary Services",
            "type":"Manufacturing & Wholesale Goods"
        }
    ],
    "sg:phone":"+1 920 849 2618",
    "sg:postcode":"53014",
    "sg:province":"WI",
    "sg:tags":[
        "livestock",
        "butchering"
    ],
    "wof:name":"Bill's Processing",
    "wof:placetype":"venue"
},
  "geometry": {"coordinates":[-88.21001099999999,44.058532],"type":"Point"}
}