{
  "type": "Feature",
  "properties": {
    "iso:country":"US",
    "sg:address":"2 Christopher Columbus",
    "sg:city":"Racine",
    "sg:classifiers":[
        {
            "category":"Restaurant",
            "type":"Food & Drink"
        }
    ],
    "sg:phone":"+1 262 633 6990",
    "sg:postcode":"53403",
    "sg:province":"WI",
    "sg:website":"www.dockswaterfront.com",
    "wof:name":"Lucarelli's Docks Waterfront",
    "wof:placetype":"venue"
},
  "geometry": {"coordinates":[-87.780928,42.729599],"type":"Point"}
}