{
  "type": "Feature",
  "properties": {
    "iso:country":"US",
    "sg:address":"673 105th St",
    "sg:city":"Amery",
    "sg:classifiers":[
        {
            "category":"Retail",
            "subcategory":"Laundry & Dry Cleaning",
            "type":"Services"
        }
    ],
    "sg:phone":"+1 715 268 5242",
    "sg:postcode":"54001",
    "sg:province":"WI",
    "sg:tags":[
        "cleaners",
        "rug",
        "carpet"
    ],
    "wof:name":"Nelson's Carpet Care",
    "wof:placetype":"venue"
},
  "geometry": {"coordinates":[-92.377487,45.307545],"type":"Point"}
}