{
  "type": "Feature",
  "properties": {
    "iso:country":"US",
    "sg:address":"2510 N Murray Ave",
    "sg:city":"Milwaukee",
    "sg:classifiers":[
        {
            "category":"Building & Trades",
            "subcategory":"Cleaning & Sanitation",
            "type":"Services"
        }
    ],
    "sg:phone":"+1 414 967 8611",
    "sg:postcode":"53211",
    "sg:province":"WI",
    "sg:tags":[
        "property",
        "maintenance"
    ],
    "wof:name":"Bell Property Management",
    "wof:placetype":"venue"
},
  "geometry": {"coordinates":[-87.885456,43.064663],"type":"Point"}
}