{
  "type": "Feature",
  "properties": {
    "iso:country":"US",
    "sg:address":"1020 Lakeshore Dr",
    "sg:city":"Rice Lake",
    "sg:classifiers":[
        {
            "category":"Health Services",
            "subcategory":"Doctor",
            "type":"Services"
        }
    ],
    "sg:phone":"+1 715 236 8100",
    "sg:postcode":"54868",
    "sg:province":"WI",
    "sg:tags":[
        "medical"
    ],
    "wof:name":"Daniel Lochmann MD",
    "wof:placetype":"venue"
},
  "geometry": {"coordinates":[-91.73249300000001,45.513529],"type":"Point"}
}