{
  "type": "Feature",
  "properties": {
    "addr:full":"3700 Velp Ave Green Bay WI 54313",
    "addr:postcode":"3700;54313",
    "addr:street":"Velp Ave",
    "iso:country":"US",
    "sg:address":"3700 Velp Ave",
    "sg:city":"Green Bay",
    "sg:classifiers":[
        {
            "category":"Retail",
            "subcategory":"Auto Rental",
            "type":"Services"
        }
    ],
    "sg:phone":"+1 920 434 0594",
    "sg:postcode":"54313",
    "sg:province":"WI",
    "sg:tags":[
        "renting",
        "truck",
        "leasing"
    ],
    "wof:name":"Budget Truck Rental",
    "wof:placetype":"venue"
},
  "geometry": {"coordinates":[-88.07793100000001,44.575541],"type":"Point"}
}