{
  "type": "Feature",
  "properties": {
    "iso:country":"US",
    "sg:address":"6033 Monona Dr",
    "sg:city":"Monona",
    "sg:classifiers":[
        {
            "category":"Manufacturing",
            "subcategory":"Chemicals & Compounds",
            "type":"Manufacturing & Wholesale Goods"
        }
    ],
    "sg:phone":"+1 608 222 5630",
    "sg:postcode":"53716",
    "sg:province":"WI",
    "sg:tags":[
        "electrolysis"
    ],
    "wof:name":"Electrolysis by Deanna",
    "wof:placetype":"venue"
},
  "geometry": {"coordinates":[-89.325272,43.053108],"type":"Point"}
}