{
  "type": "Feature",
  "properties": {
    "iso:country":"US",
    "sg:address":"930 Stewart St",
    "sg:city":"Madison",
    "sg:classifiers":[
        {
            "category":"Social Services",
            "subcategory":"Job Training",
            "type":"Services"
        }
    ],
    "sg:phone":"+1 608 274 8060",
    "sg:postcode":"53713",
    "sg:province":"WI",
    "sg:tags":[
        "rehabilitation"
    ],
    "sg:website":"www.vpind.com",
    "wof:name":"Valley Packaging Industries",
    "wof:placetype":"venue"
},
  "geometry": {"coordinates":[-89.398861,43.030138],"type":"Point"}
}