{
  "type": "Feature",
  "properties": {
    "iso:country":"US",
    "sg:address":"242 N Lexington St",
    "sg:city":"Spring Green",
    "sg:classifiers":[
        {
            "category":"Professional",
            "subcategory":"Art Services",
            "type":"Services"
        }
    ],
    "sg:phone":"+1 608 588 3331",
    "sg:postcode":"53588",
    "sg:province":"WI",
    "sg:tags":[
        "photographer"
    ],
    "wof:name":"Eric Ferguson Photography",
    "wof:placetype":"venue"
},
  "geometry": {"coordinates":[-90.068088,43.178192],"type":"Point"}
}