{
  "type": "Feature",
  "properties": {
    "iso:country":"US",
    "sg:address":"2205 Stella Ln",
    "sg:city":"Conrath",
    "sg:classifiers":[
        {
            "category":"Farming",
            "subcategory":"Farm",
            "type":"Manufacturing & Wholesale Goods"
        }
    ],
    "sg:phone":"+1 715 532 6586",
    "sg:postcode":"54731",
    "sg:province":"WI",
    "sg:tags":[
        "crop",
        "general"
    ],
    "wof:name":"Tomaszewski Michael Frm Lessor",
    "wof:placetype":"venue"
},
  "geometry": {"coordinates":[-91.07972100000001,45.367589],"type":"Point"}
}