{
  "type": "Feature",
  "properties": {
    "addr:full":"440 Sunshine Ave Delavan WI 53115",
    "addr:housenumber":"440",
    "addr:postcode":"53115",
    "addr:street":"Sunshine Ave",
    "iso:country":"US",
    "sg:address":"440 Sunshine Ave",
    "sg:city":"Delavan",
    "sg:classifiers":[
        {
            "category":"Wholesale",
            "subcategory":"Hardware",
            "type":"Manufacturing & Wholesale Goods"
        },
        {
            "category":"Transit Center",
            "subcategory":"Freight",
            "type":"Transportation"
        },
        {
            "category":"Freight",
            "type":"Transportation"
        }
    ],
    "sg:phone":"+1 262 728 5757",
    "sg:postcode":"53115",
    "sg:province":"WI",
    "sg:tags":[
        "local",
        "hardware-builders",
        "trucking-motor",
        "trucking"
    ],
    "wof:name":"Means Trucking",
    "wof:placetype":"venue"
},
  "geometry": {"coordinates":[-88.62660099999999,42.637839],"type":"Point"}
}