{
  "type": "Feature",
  "properties": {
    "iso:country":"US",
    "sg:address":"1927 W Hampton Ave",
    "sg:city":"Milwaukee",
    "sg:classifiers":[
        {
            "category":"Social Services",
            "subcategory":"Child Care",
            "type":"Services"
        }
    ],
    "sg:phone":"+1 414 264 3256",
    "sg:postcode":"53209",
    "sg:province":"WI",
    "wof:name":"Shanac Family Day Care",
    "wof:placetype":"venue"
},
  "geometry": {"coordinates":[-87.934713,43.104278],"type":"Point"}
}