{
  "type": "Feature",
  "properties": {
    "addr:full":"2900 W Arthur Ave Milwaukee WI 53215",
    "addr:housenumber":"2900",
    "addr:postcode":"53215",
    "addr:street":"W Arthur Ave",
    "iso:country":"US",
    "sg:address":"2900 W Arthur Ave",
    "sg:city":"Milwaukee",
    "sg:classifiers":[
        {
            "category":"Building & Trades",
            "subcategory":"Equipment Rental",
            "type":"Services"
        }
    ],
    "sg:phone":"+1 414 384 4824",
    "sg:postcode":"53215",
    "sg:province":"WI",
    "wof:name":"Tuan Video",
    "wof:placetype":"venue"
},
  "geometry": {"coordinates":[-87.951826,42.999486],"type":"Point"}
}