{
  "type": "Feature",
  "properties": {
    "iso:country":"US",
    "sg:address":"9020 N 96th St",
    "sg:city":"Milwaukee",
    "sg:classifiers":[
        {
            "category":"Building & Trades",
            "subcategory":"Construction",
            "type":"Services"
        }
    ],
    "sg:phone":"+1 414 365 0420",
    "sg:postcode":"53224",
    "sg:province":"WI",
    "sg:tags":[
        "carpentry",
        "contractor"
    ],
    "wof:name":"Affordable Carpentry",
    "wof:placetype":"venue"
},
  "geometry": {"coordinates":[-88.030823,43.183333],"type":"Point"}
}