{
  "type": "Feature",
  "properties": {
    "iso:country":"US",
    "sg:address":"122 S Illinois St",
    "sg:city":"Prairie Du Chien",
    "sg:classifiers":[
        {
            "category":"Building & Trades",
            "subcategory":"Plumbing",
            "type":"Services"
        }
    ],
    "sg:phone":"+1 608 326 2885",
    "sg:postcode":"53821",
    "sg:province":"WI",
    "sg:tags":[
        "product",
        "management",
        "energy",
        "system"
    ],
    "wof:name":"Alliant Energy",
    "wof:placetype":"venue"
},
  "geometry": {"coordinates":[-91.1423,43.051522],"type":"Point"}
}