{
  "type": "Feature",
  "properties": {
    "iso:country":"US",
    "sg:address":"3000 Roosevelt Rd",
    "sg:city":"Kenosha",
    "sg:classifiers":[
        {
            "category":"Shopping",
            "subcategory":"Musical Instruments",
            "type":"Retail Goods"
        }
    ],
    "sg:phone":"+1 262 653 9287",
    "sg:postcode":"53142",
    "sg:province":"IL",
    "sg:tags":[
        "music",
        "dealer"
    ],
    "wof:name":"Lakeside Music LLC",
    "wof:placetype":"venue"
},
  "geometry": {"coordinates":[-87.846437,42.571205],"type":"Point"}
}