{
  "type": "Feature",
  "properties": {
    "iso:country":"US",
    "sg:address":"730 Craftsman Way",
    "sg:city":"Sun Prairie",
    "sg:classifiers":[
        {
            "category":"Wholesale",
            "subcategory":"Groceries",
            "type":"Manufacturing & Wholesale Goods"
        }
    ],
    "sg:phone":"+1 608 825 9087",
    "sg:postcode":"53590",
    "sg:province":"WI",
    "sg:tags":[
        "retail",
        "general",
        "sales",
        "direct"
    ],
    "wof:name":"Schwans Home Service Inc",
    "wof:placetype":"venue"
},
  "geometry": {"coordinates":[-89.224203,43.173905],"type":"Point"}
}