{
  "type": "Feature",
  "properties": {
    "iso:country":"US",
    "sg:address":"3124 Van Roy Rd",
    "sg:city":"Appleton",
    "sg:classifiers":[
        {
            "category":"Social Services",
            "type":"Services"
        }
    ],
    "sg:phone":"+1 920 738 9999",
    "sg:postcode":"54915",
    "sg:province":"WI",
    "wof:name":"Psychology Associates of F",
    "wof:placetype":"venue"
},
  "geometry": {"coordinates":[-88.340391,44.256989],"type":"Point"}
}