{
  "type": "Feature",
  "properties": {
    "iso:country":"US",
    "sg:address":"4332 Galaxy Dr",
    "sg:city":"Janesville",
    "sg:classifiers":[
        {
            "category":"Recreation",
            "type":"Entertainment"
        }
    ],
    "sg:phone":"+1 608 868 7089",
    "sg:postcode":"53546",
    "sg:province":"WI",
    "sg:tags":[
        "entertainers-family",
        "business"
    ],
    "wof:name":"Audio Illusions Entertainment",
    "wof:placetype":"venue"
},
  "geometry": {"coordinates":[-88.963348,42.734503],"type":"Point"}
}