{
  "type": "Feature",
  "properties": {
    "iso:country":"US",
    "sg:address":"19879 Winnebago Rd",
    "sg:city":"Galesville",
    "sg:classifiers":[
        {
            "category":"Autos & Motor Vehicles",
            "subcategory":"Motorcycle Sales",
            "type":"Retail Goods"
        },
        {
            "category":"Retail",
            "subcategory":"Auto Repair",
            "type":"Services"
        }
    ],
    "sg:phone":"+1 608 582 4730",
    "sg:postcode":"54630",
    "sg:province":"WI",
    "sg:tags":[
        "repairing",
        "automobile"
    ],
    "wof:name":"Kross LLC",
    "wof:placetype":"venue"
},
  "geometry": {"coordinates":[-91.350829,44.076707],"type":"Point"}
}