{
  "type": "Feature",
  "properties": {
    "iso:country":"US",
    "sg:address":"5651 Daubner Ln",
    "sg:city":"Sturgeon Bay",
    "sg:classifiers":[
        {
            "category":"Wholesale",
            "subcategory":"Hardware",
            "type":"Manufacturing & Wholesale Goods"
        }
    ],
    "sg:phone":"+1 920 743 1937",
    "sg:postcode":"54235",
    "sg:province":"WI",
    "wof:name":"RAK Co LLC",
    "wof:placetype":"venue"
},
  "geometry": {"coordinates":[-87.344204,44.958675],"type":"Point"}
}