{
  "type": "Feature",
  "properties": {
    "iso:country":"US",
    "sg:address":"721 Racine St",
    "sg:city":"Appleton",
    "sg:classifiers":[
        {
            "category":"Retail",
            "subcategory":"Car Wash",
            "type":"Services"
        }
    ],
    "sg:phone":"+1 920 720 5384",
    "sg:postcode":"54952",
    "sg:province":"WI",
    "sg:tags":[
        "polishing",
        "washing"
    ],
    "wof:name":"Best Wash",
    "wof:placetype":"venue"
},
  "geometry": {"coordinates":[-88.445921,44.212519],"type":"Point"}
}