{
  "type": "Feature",
  "properties": {
    "iso:country":"US",
    "sg:address":"869 Korte Dr",
    "sg:city":"Cochrane",
    "sg:classifiers":[
        {
            "category":"Building & Trades",
            "subcategory":"Equipment Rental",
            "type":"Services"
        }
    ],
    "sg:phone":"+1 608 626 2001",
    "sg:postcode":"54622",
    "sg:province":"WI",
    "sg:tags":[
        "camping"
    ],
    "wof:name":"Mar-V-Les Tents",
    "wof:placetype":"venue"
},
  "geometry": {"coordinates":[-91.703898,44.303867],"type":"Point"}
}