{
  "type": "Feature",
  "properties": {
    "iso:country":"US",
    "sg:address":"1763 60th Ave",
    "sg:city":"Osceola",
    "sg:classifiers":[
        {
            "category":"Professional",
            "type":"Services"
        }
    ],
    "sg:phone":"+1 715 268 7224",
    "sg:postcode":"54020",
    "sg:province":"WI",
    "wof:name":"Technofab",
    "wof:placetype":"venue"
},
  "geometry": {"coordinates":[-92.52565800000001,45.295658],"type":"Point"}
}