{
  "type": "Feature",
  "properties": {
    "iso:country":"US",
    "sg:address":"4244 N 91st St",
    "sg:city":"Milwaukee",
    "sg:classifiers":[
        {
            "category":"Professional",
            "type":"Services"
        }
    ],
    "sg:phone":"+1 414 771 9547",
    "sg:postcode":"53222",
    "sg:province":"WI",
    "wof:name":"Shannon Baylor",
    "wof:placetype":"venue"
},
  "geometry": {"coordinates":[-88.02628799999999,43.094275],"type":"Point"}
}