{
  "type": "Feature",
  "properties": {
    "addr:full":"2003 Holiday Dr Janesville WI 53545",
    "addr:housenumber":"2003",
    "addr:postcode":"53545",
    "addr:street":"Holiday Dr",
    "iso:country":"US",
    "sg:address":"2003 Holiday Dr",
    "sg:city":"Janesville",
    "sg:classifiers":[
        {
            "category":"Shopping",
            "subcategory":"Thrift Store",
            "type":"Retail Goods"
        }
    ],
    "sg:phone":"+1 608 758 8794",
    "sg:postcode":"53545",
    "sg:province":"WI",
    "sg:tags":[
        "shop"
    ],
    "sg:website":"http://www.goodwill.org",
    "wof:name":"Goodwill Stores",
    "wof:placetype":"venue"
},
  "geometry": {"coordinates":[-88.99763900000001,42.713704],"type":"Point"}
}