{
  "type": "Feature",
  "properties": {
    "iso:country":"US",
    "sg:address":"3691 Center Valley Rd",
    "sg:city":"Appleton",
    "sg:classifiers":[
        {
            "category":"Professional",
            "subcategory":"Detective & Security Services",
            "type":"Services"
        }
    ],
    "sg:phone":"+1 920 734 8981",
    "sg:postcode":"54913",
    "sg:province":"WI",
    "sg:tags":[
        "shredding",
        "material"
    ],
    "sg:website":"www.securityshredders.com",
    "wof:name":"Security Shredders Inc",
    "wof:placetype":"venue"
},
  "geometry": {"coordinates":[-88.373175,44.401329],"type":"Point"}
}