{
  "type": "Feature",
  "properties": {
    "iso:country":"US",
    "sg:address":"2440 Shoestring Rd",
    "sg:city":"Cuba City",
    "sg:classifiers":[
        {
            "category":"Farming",
            "subcategory":"Dairy Farm",
            "type":"Manufacturing & Wholesale Goods"
        }
    ],
    "sg:phone":"+1 608 744 2655",
    "sg:postcode":"53807",
    "sg:province":"WI",
    "sg:tags":[
        "hog",
        "or",
        "feedlot"
    ],
    "wof:name":"Earl & Doris Jansen",
    "wof:placetype":"venue"
},
  "geometry": {"coordinates":[-90.56682499999999,42.589063],"type":"Point"}
}