{
  "type": "Feature",
  "properties": {
    "iso:country":"US",
    "sg:address":"531 Cattail Ct",
    "sg:city":"New London",
    "sg:classifiers":[
        {
            "category":"Retail",
            "subcategory":"Portrait Studio",
            "type":"Services"
        }
    ],
    "sg:phone":"+1 920 982 7326",
    "sg:postcode":"54961",
    "sg:province":"WI",
    "sg:tags":[
        "photo"
    ],
    "wof:name":"Peteness Photography",
    "wof:placetype":"venue"
},
  "geometry": {"coordinates":[-88.746049,44.412888],"type":"Point"}
}