{
  "type": "Feature",
  "properties": {
    "addr:full":"702 Raynor Ave Franksville WI 53126",
    "addr:housenumber":"702",
    "addr:postcode":"53126",
    "addr:street":"Raynor Ave",
    "iso:country":"US",
    "sg:address":"702 Raynor Ave",
    "sg:city":"Franksville",
    "sg:classifiers":[
        {
            "category":"Insurance",
            "subcategory":"Insurance Agent",
            "type":"Services"
        }
    ],
    "sg:phone":"+1 414 529 3865",
    "sg:postcode":"53126",
    "sg:province":"WI",
    "wof:name":"Hanover",
    "wof:placetype":"venue"
},
  "geometry": {"coordinates":[-88.07155,42.728995],"type":"Point"}
}