{
  "type": "Feature",
  "properties": {
    "iso:country":"US",
    "sg:address":"812 N 25th St",
    "sg:city":"Milwaukee",
    "sg:classifiers":[
        {
            "category":"Professional",
            "subcategory":"Management & Consulting",
            "type":"Services"
        }
    ],
    "sg:phone":"+1 414 933 7795",
    "sg:postcode":"53233",
    "sg:province":"WI",
    "sg:tags":[
        "personnel",
        "consultant"
    ],
    "wof:name":"Main Line Staffing",
    "wof:placetype":"venue"
},
  "geometry": {"coordinates":[-87.944859,43.041461],"type":"Point"}
}