{
  "type": "Feature",
  "properties": {
    "iso:country":"US",
    "sg:address":"2429 E Bradford Ave",
    "sg:city":"Milwaukee",
    "sg:classifiers":[
        {
            "category":"Personal",
            "subcategory":"Beauty Salon",
            "type":"Services"
        }
    ],
    "sg:phone":"+1 414 963 8457",
    "sg:postcode":"53211",
    "sg:province":"WI",
    "sg:tags":[
        "shop"
    ],
    "wof:name":"Bradford Terrace Beauty Sho",
    "wof:placetype":"venue"
},
  "geometry": {"coordinates":[-87.87939299999999,43.063636],"type":"Point"}
}