{
  "type": "Feature",
  "properties": {
    "iso:country":"US",
    "sg:address":"2114 Wedemeyer St",
    "sg:city":"Sheboygan",
    "sg:classifiers":[
        {
            "category":"Organizations",
            "subcategory":"Religious Organization",
            "type":"Services"
        }
    ],
    "sg:phone":"+1 920 458 1611",
    "sg:postcode":"53081",
    "sg:province":"WI",
    "sg:tags":[
        "christ",
        "church"
    ],
    "wof:name":"Saint Pauls Untd Church Christ",
    "wof:placetype":"venue"
},
  "geometry": {"coordinates":[-87.72101,43.731056],"type":"Point"}
}