{
  "type": "Feature",
  "properties": {
    "iso:country":"US",
    "sg:address":"8822 E Shore Rd",
    "sg:city":"Two Rivers",
    "sg:classifiers":[
        {
            "category":"Personal",
            "subcategory":"Beauty Salon",
            "type":"Services"
        }
    ],
    "sg:phone":"+1 920 652 9122",
    "sg:postcode":"54241",
    "sg:province":"WI",
    "sg:tags":[
        "shop"
    ],
    "wof:name":"Excellence In Styling",
    "wof:placetype":"venue"
},
  "geometry": {"coordinates":[-87.665648,44.204089],"type":"Point"}
}