{
  "type": "Feature",
  "properties": {
    "iso:country":"US",
    "sg:address":"300 W Michigan St",
    "sg:city":"Milwaukee",
    "sg:classifiers":[
        {
            "category":"Travel",
            "subcategory":"Hotels & Motels",
            "type":"Entertainment"
        }
    ],
    "sg:phone":"+1 414 291 4122",
    "sg:postcode":"53203",
    "sg:province":"WI",
    "sg:website":"http://www.marriott.com",
    "wof:name":"Courtyard by Marriott Milwaukee Downtown",
    "wof:placetype":"venue"
},
  "geometry": {"coordinates":[-87.914574,43.037411],"type":"Point"}
}