{
  "type": "Feature",
  "properties": {
    "iso:country":"US",
    "sg:address":"6024 Cameo Ct",
    "sg:city":"Appleton",
    "sg:classifiers":[
        {
            "category":"Real Estate",
            "subcategory":"Real Estate Agent",
            "type":"Services"
        }
    ],
    "sg:phone":"+1 920 954 1766",
    "sg:postcode":"54915",
    "sg:province":"WI",
    "sg:tags":[
        "appraiser"
    ],
    "wof:name":"Vassar Appraisers",
    "wof:placetype":"venue"
},
  "geometry": {"coordinates":[-88.33919899999999,44.242171],"type":"Point"}
}