{
  "type": "Feature",
  "properties": {
    "iso:country":"US",
    "sg:address":"3457 S 60th St",
    "sg:city":"Milwaukee",
    "sg:classifiers":[
        {
            "category":"Retail",
            "subcategory":"Repair Shop",
            "type":"Services"
        }
    ],
    "sg:phone":"+1 414 545 4391",
    "sg:postcode":"53219",
    "sg:province":"WI",
    "wof:name":"Flash Repair & Resale LLC",
    "wof:placetype":"venue"
},
  "geometry": {"coordinates":[-87.987949,42.982207],"type":"Point"}
}