{
  "type": "Feature",
  "properties": {
    "iso:country":"US",
    "sg:address":"1114 W North Ave",
    "sg:city":"Milwaukee",
    "sg:classifiers":[
        {
            "category":"Restaurant",
            "type":"Food & Drink"
        }
    ],
    "sg:phone":"+1 414 264 6500",
    "sg:postcode":"53205",
    "sg:province":"WI",
    "wof:name":"American Subs",
    "wof:placetype":"venue"
},
  "geometry": {"coordinates":[-87.926758,43.060456],"type":"Point"}
}