{
  "type": "Feature",
  "properties": {
    "addr:full":"1830 N Hubbard St Milwaukee WI 53212",
    "addr:housenumber":"1830",
    "addr:postcode":"53212",
    "addr:street":"N Hubbard St",
    "iso:country":"US",
    "sg:address":"1830 N Hubbard St",
    "sg:city":"Milwaukee",
    "sg:classifiers":[
        {
            "category":"Professional",
            "subcategory":"Business Services",
            "type":"Services"
        }
    ],
    "sg:phone":"+1 414 755 1962",
    "sg:postcode":"53212",
    "sg:province":"WI",
    "sg:website":"http://www.harqen.com/",
    "wof:name":"HarQen",
    "wof:placetype":"venue"
},
  "geometry": {"coordinates":[-87.90833600000001,43.054732],"type":"Point"}
}