{
  "type": "Feature",
  "properties": {
    "addr:full":"3255 Yeager Dr Green Bay WI 54311",
    "addr:housenumber":"3255",
    "addr:postcode":"54311",
    "addr:street":"Yeager Dr",
    "iso:country":"US",
    "sg:address":"3255 Yeager Dr",
    "sg:city":"Green Bay",
    "sg:classifiers":[
        {
            "category":"Freight",
            "type":"Transportation"
        }
    ],
    "sg:phone":"+1 920 465 3515",
    "sg:postcode":"54311",
    "sg:province":"WI",
    "sg:tags":[
        "commercial",
        "storage",
        "general"
    ],
    "wof:name":"Guardian Storage LLC",
    "wof:placetype":"venue"
},
  "geometry": {"coordinates":[-87.919275,44.477793],"type":"Point"}
}