{
  "type": "Feature",
  "properties": {
    "addr:full":"420 E Longview Dr Appleton WI 54911",
    "addr:housenumber":"420",
    "addr:postcode":"54911",
    "addr:street":"E Longview Dr",
    "iso:country":"US",
    "sg:address":"420 E Longview Dr",
    "sg:city":"Appleton",
    "sg:classifiers":[
        {
            "category":"Professional",
            "subcategory":"Lawyer & Legal Services",
            "type":"Services"
        }
    ],
    "sg:phone":"+1 920 734 7000",
    "sg:postcode":"54911",
    "sg:province":"WI",
    "sg:tags":[
        "attorney"
    ],
    "wof:name":"Chris J Mares SC",
    "wof:placetype":"venue"
},
  "geometry": {"coordinates":[-88.398605,44.286431],"type":"Point"}
}