{
  "type": "Feature",
  "properties": {
    "addr:full":"910 Gateway Ct West Bend WI 53095",
    "addr:housenumber":"910",
    "addr:postcode":"53095",
    "addr:street":"Gateway Ct",
    "iso:country":"US",
    "sg:address":"910 Gateway Ct",
    "sg:city":"West Bend",
    "sg:classifiers":[
        {
            "category":"Insurance",
            "subcategory":"Insurance Agent",
            "type":"Services"
        }
    ],
    "sg:phone":"+1 262 338 0100",
    "sg:postcode":"53095",
    "sg:province":"WI",
    "wof:name":"AAA Insurance",
    "wof:placetype":"venue"
},
  "geometry": {"coordinates":[-88.18982,43.394929],"type":"Point"}
}