{
  "type": "Feature",
  "properties": {
    "iso:country":"US",
    "sg:address":"112 W Wisconsin Ave",
    "sg:city":"Neenah",
    "sg:classifiers":[
        {
            "category":"Shopping",
            "subcategory":"Clothing, Apparel, & Fashions",
            "type":"Retail Goods"
        }
    ],
    "sg:phone":"+1 920 722 1171",
    "sg:postcode":"54956",
    "sg:province":"WI",
    "sg:tags":[
        "ready"
    ],
    "wof:name":"Bill Paul Ltd",
    "wof:placetype":"venue"
},
  "geometry": {"coordinates":[-88.463183,44.187091],"type":"Point"}
}