{
  "type": "Feature",
  "properties": {
    "iso:country":"US",
    "sg:address":"9435 W Lincoln Ave",
    "sg:city":"Milwaukee",
    "sg:classifiers":[
        {
            "category":"Autos & Motor Vehicles",
            "subcategory":"Auto Supplies",
            "type":"Retail Goods"
        }
    ],
    "sg:phone":"+1 414 329 3260",
    "sg:postcode":"53227",
    "sg:province":"WI",
    "sg:tags":[
        "performance",
        "parts"
    ],
    "wof:name":"Fast Times Performance Center",
    "wof:placetype":"venue"
},
  "geometry": {"coordinates":[-88.030473,43.002589],"type":"Point"}
}