{
  "type": "Feature",
  "properties": {
    "iso:country":"US",
    "sg:address":"453 Grand Ave",
    "sg:city":"Schofield",
    "sg:classifiers":[
        {
            "category":"Government",
            "subcategory":"Jail",
            "type":"Public Place"
        }
    ],
    "sg:phone":"+1 715 241 8890",
    "sg:postcode":"54476",
    "sg:province":"WI",
    "sg:tags":[
        "govt",
        "state",
        "institution"
    ],
    "wof:name":"Corrections Dept Juvenile Div",
    "wof:placetype":"venue"
},
  "geometry": {"coordinates":[-89.623333,44.953227],"type":"Point"}
}