{
  "type": "Feature",
  "properties": {
    "iso:country":"US",
    "sg:address":"622 S Washington St",
    "sg:city":"Viroqua",
    "sg:classifiers":[
        {
            "category":"Building & Trades",
            "subcategory":"Landscaping Services",
            "type":"Services"
        }
    ],
    "sg:phone":"+1 608 637 8215",
    "sg:postcode":"54665",
    "sg:province":"WI",
    "sg:tags":[
        "landscape"
    ],
    "wof:name":"Sacred Ground Landscape Design",
    "wof:placetype":"venue"
},
  "geometry": {"coordinates":[-90.885575,43.550907],"type":"Point"}
}