{
  "type": "Feature",
  "properties": {
    "addr:full":"244 Broad St Lake Geneva WI 53147",
    "addr:housenumber":"244",
    "addr:postcode":"53147",
    "addr:street":"Broad St",
    "iso:country":"US",
    "sg:address":"244 Broad St",
    "sg:city":"Lake Geneva",
    "sg:classifiers":[
        {
            "category":"Cinema",
            "subcategory":"Movie Theater",
            "type":"Entertainment"
        }
    ],
    "sg:phone":"+1 262 248 9208",
    "sg:postcode":"53147",
    "sg:province":"WI",
    "wof:name":"Geneva Theaters",
    "wof:placetype":"venue"
},
  "geometry": {"coordinates":[-88.43525699999999,42.591797],"type":"Point"}
}