{
  "type": "Feature",
  "properties": {
    "iso:country":"US",
    "sg:address":"13301 Big Crooked Lake Ln",
    "sg:city":"Lac Du Flambeau",
    "sg:classifiers":[
        {
            "category":"Building & Trades",
            "subcategory":"Electrical",
            "type":"Services"
        }
    ],
    "sg:phone":"+1 715 588 7889",
    "sg:postcode":"54538",
    "sg:province":"WI",
    "sg:tags":[
        "electrical",
        "contractor"
    ],
    "wof:name":"Kk Electric",
    "wof:placetype":"venue"
},
  "geometry": {"coordinates":[-89.836412,46.037991],"type":"Point"}
}