{
  "type": "Feature",
  "properties": {
    "iso:country":"US",
    "sg:address":"4503 75th St",
    "sg:city":"Kenosha",
    "sg:classifiers":[
        {
            "category":"Retail",
            "subcategory":"Auto Repair",
            "type":"Services"
        }
    ],
    "sg:phone":"+1 262 694 4500",
    "sg:postcode":"53142",
    "sg:province":"WI",
    "sg:tags":[
        "repairing",
        "automobile"
    ],
    "wof:name":"Town & Country Mobil Svc",
    "wof:placetype":"venue"
},
  "geometry": {"coordinates":[-87.864953,42.56622],"type":"Point"}
}