{
  "type": "Feature",
  "properties": {
    "iso:country":"US",
    "sg:address":"217 Houston St",
    "sg:city":"Ripon",
    "sg:classifiers":[
        {
            "category":"Organizations",
            "subcategory":"Religious Organization",
            "type":"Services"
        }
    ],
    "sg:phone":"+1 920 748 2422",
    "sg:postcode":"54971",
    "sg:province":"WI",
    "sg:tags":[
        "church"
    ],
    "sg:website":"www.ripon.episcopalfonddulac.org",
    "wof:name":"Saint Peters Episcopal Church",
    "wof:placetype":"venue"
},
  "geometry": {"coordinates":[-88.835219,43.845151],"type":"Point"}
}