{
  "type": "Feature",
  "properties": {
    "addr:full":"1325 Cornell Rd Green Bay WI 54313",
    "addr:housenumber":"1325",
    "addr:postcode":"54313",
    "addr:street":"Cornell Rd",
    "iso:country":"US",
    "sg:address":"1325 Cornell Rd",
    "sg:city":"Green Bay",
    "sg:classifiers":[
        {
            "category":"Manufacturing",
            "subcategory":"Tools & Machinery",
            "type":"Manufacturing & Wholesale Goods"
        }
    ],
    "sg:phone":"+1 920 434 3272",
    "sg:postcode":"54313",
    "sg:province":"WI",
    "sg:tags":[
        "machine",
        "shop",
        "specialty",
        "mfg"
    ],
    "wof:name":"Steinberger Machine & Tool Inc",
    "wof:placetype":"venue"
},
  "geometry": {"coordinates":[-88.069626,44.573537],"type":"Point"}
}