{
  "type": "Feature",
  "properties": {
    "iso:country":"US",
    "sg:address":"959 Dyke Ave",
    "sg:city":"Adams",
    "sg:classifiers":[
        {
            "category":"Building & Trades",
            "subcategory":"Construction",
            "type":"Services"
        }
    ],
    "sg:phone":"+1 608 339 3573",
    "sg:postcode":"53910",
    "sg:province":"WI",
    "sg:tags":[
        "residential"
    ],
    "wof:name":"Cananaugh Enteprises",
    "wof:placetype":"venue"
},
  "geometry": {"coordinates":[-89.767004,43.908729],"type":"Point"}
}