{
  "type": "Feature",
  "properties": {
    "iso:country":"US",
    "sg:address":"2404 W Clybourn St",
    "sg:city":"Milwaukee",
    "sg:classifiers":[
        {
            "category":"Education",
            "subcategory":"Special Training",
            "type":"Public Place"
        },
        {
            "category":"Manufacturing",
            "subcategory":"Printing",
            "type":"Manufacturing & Wholesale Goods"
        }
    ],
    "sg:phone":"+1 414 342 4000",
    "sg:postcode":"53233",
    "sg:province":"WI",
    "sg:tags":[
        "how",
        "resident",
        "multimedia",
        "us",
        "access",
        "to",
        "organization"
    ],
    "wof:name":"M Ata Community Media",
    "wof:placetype":"venue"
},
  "geometry": {"coordinates":[-87.94257399999999,43.036202],"type":"Point"}
}