{
  "type": "Feature",
  "properties": {
    "iso:country":"US",
    "sg:address":"2263 Cobblestone Ln",
    "sg:city":"Beloit",
    "sg:classifiers":[
        {
            "category":"Government",
            "subcategory":"Office",
            "type":"Public Place"
        }
    ],
    "sg:phone":"+1 608 362 7877",
    "sg:postcode":"53511",
    "sg:province":"WI",
    "sg:tags":[
        "legislative",
        "body"
    ],
    "wof:name":"Timothy Weeden",
    "wof:placetype":"venue"
},
  "geometry": {"coordinates":[-89.001915,42.529056],"type":"Point"}
}