{
  "type": "Feature",
  "properties": {
    "iso:country":"US",
    "sg:address":"12550 State Hwy 32",
    "sg:city":"Suring",
    "sg:classifiers":[
        {
            "category":"Restaurant",
            "type":"Food & Drink"
        }
    ],
    "sg:phone":"+1 715 276 6266",
    "sg:postcode":"54174",
    "sg:province":"WI",
    "wof:name":"Chute Inn Family Restaurant",
    "wof:placetype":"venue"
},
  "geometry": {"coordinates":[-88.439478,45.13462],"type":"Point"}
}