{
  "type": "Feature",
  "properties": {
    "iso:country":"US",
    "sg:address":"1631 4th St",
    "sg:city":"Almena",
    "sg:classifiers":[
        {
            "category":"Farming",
            "subcategory":"Dairy Farm",
            "type":"Manufacturing & Wholesale Goods"
        }
    ],
    "sg:phone":"+1 715 357 3952",
    "sg:postcode":"54805",
    "sg:province":"WI",
    "wof:name":"Scheps Dairy Inc",
    "wof:placetype":"venue"
},
  "geometry": {"coordinates":[-92.074004,45.441214],"type":"Point"}
}