{
  "type": "Feature",
  "properties": {
    "iso:country":"US",
    "sg:address":"316 Center St",
    "sg:city":"Westfield",
    "sg:classifiers":[
        {
            "category":"Building & Trades",
            "subcategory":"Plumbing",
            "type":"Services"
        }
    ],
    "sg:phone":"+1 608 296 9922",
    "sg:postcode":"53964",
    "sg:province":"WI",
    "sg:tags":[
        "plumbing",
        "contractor"
    ],
    "wof:name":"Kopach-Runnels Plumbing",
    "wof:placetype":"venue"
},
  "geometry": {"coordinates":[-89.496886,43.883989],"type":"Point"}
}