{
  "type": "Feature",
  "properties": {
    "iso:country":"US",
    "sg:address":"39641 Sunset Dr",
    "sg:city":"Oconomowoc",
    "sg:classifiers":[
        {
            "category":"Farming",
            "subcategory":"Livestock Farm",
            "type":"Manufacturing & Wholesale Goods"
        }
    ],
    "sg:phone":"+1 262 965 2741",
    "sg:postcode":"53066",
    "sg:province":"WI",
    "sg:tags":[
        "beef",
        "feedlot",
        "cattle"
    ],
    "wof:name":"Meyer Farm",
    "wof:placetype":"venue"
},
  "geometry": {"coordinates":[-88.535451,43.026499],"type":"Point"}
}