{
  "type": "Feature",
  "properties": {
    "iso:country":"US",
    "sg:address":"423 Cornelia St",
    "sg:city":"Janesville",
    "sg:classifiers":[
        {
            "category":"Retail",
            "subcategory":"Repair Shop",
            "type":"Services"
        }
    ],
    "sg:phone":"+1 608 758 3451",
    "sg:postcode":"53545",
    "sg:province":"WI",
    "sg:tags":[
        "appliance",
        "electrical"
    ],
    "wof:name":"Ramsdell's Appliance Repair",
    "wof:placetype":"venue"
},
  "geometry": {"coordinates":[-89.02121,42.689109],"type":"Point"}
}