{
  "type": "Feature",
  "properties": {
    "iso:country":"US",
    "sg:address":"5001 Tonyawatha Trl",
    "sg:city":"Madison",
    "sg:classifiers":[
        {
            "category":"Organizations",
            "subcategory":"Community Association",
            "type":"Services"
        }
    ],
    "sg:phone":"+1 608 222 6225",
    "sg:postcode":"53716",
    "sg:province":"WI",
    "wof:name":"Royal Order of Jesters",
    "wof:placetype":"venue"
},
  "geometry": {"coordinates":[-89.346581,43.065171],"type":"Point"}
}