{
  "type": "Feature",
  "properties": {
    "iso:country":"US",
    "sg:address":"1025 Riders Club Rd",
    "sg:city":"Onalaska",
    "sg:classifiers":[
        {
            "category":"Building & Trades",
            "subcategory":"Construction",
            "type":"Services"
        }
    ],
    "sg:phone":"+1 608 783 4639",
    "sg:postcode":"54650",
    "sg:province":"WI",
    "sg:tags":[
        "home",
        "contractor",
        "land",
        "family",
        "developer"
    ],
    "wof:name":"Evenson Company Inc",
    "wof:placetype":"venue"
},
  "geometry": {"coordinates":[-91.222798,43.905599],"type":"Point"}
}