{
  "type": "Feature",
  "properties": {
    "iso:country":"US",
    "sg:address":"10960 Corning St",
    "sg:city":"Poynette",
    "sg:classifiers":[
        {
            "category":"Restaurant",
            "type":"Food & Drink"
        }
    ],
    "sg:phone":"+1 608 635 2959",
    "sg:postcode":"53955",
    "sg:province":"WI",
    "sg:tags":[
        "drinking",
        "eating"
    ],
    "wof:name":"Lakeside Restaurant & Lounge",
    "wof:placetype":"venue"
},
  "geometry": {"coordinates":[-89.544614,43.386908],"type":"Point"}
}