{
  "type": "Feature",
  "properties": {
    "iso:country":"US",
    "sg:address":"11333 W Burleigh St",
    "sg:city":"Milwaukee",
    "sg:classifiers":[
        {
            "category":"Autos & Motor Vehicles",
            "subcategory":"Automobile Sales",
            "type":"Retail Goods"
        }
    ],
    "sg:phone":"+1 414 328 3500",
    "sg:postcode":"53222",
    "sg:province":"WI",
    "wof:name":"Honda City",
    "wof:placetype":"venue"
},
  "geometry": {"coordinates":[-88.053999,43.074577],"type":"Point"}
}