{
  "type": "Feature",
  "properties": {
    "addr:full":"191 Bay Park Sq Green Bay WI 54304",
    "addr:housenumber":"191",
    "addr:postcode":"54304",
    "addr:street":"Bay Park Sq",
    "iso:country":"US",
    "sg:address":"191 Bay Park Sq",
    "sg:city":"Green Bay",
    "sg:classifiers":[
        {
            "category":"Shopping",
            "subcategory":"Optical Goods",
            "type":"Retail Goods"
        }
    ],
    "sg:phone":"+1 920 498 3430",
    "sg:postcode":"54304",
    "sg:province":"WI",
    "wof:name":"Pearle Vision",
    "wof:placetype":"venue"
},
  "geometry": {"coordinates":[-88.067526,44.484474],"type":"Point"}
}