{
  "type": "Feature",
  "properties": {
    "addr:full":"2104 Neva Rd Antigo WI 54409",
    "addr:housenumber":"2104",
    "addr:postcode":"54409",
    "addr:street":"Neva Rd",
    "iso:country":"US",
    "sg:address":"2104 Neva Rd",
    "sg:city":"Antigo",
    "sg:classifiers":[
        {
            "category":"Restaurant",
            "type":"Food & Drink"
        }
    ],
    "sg:menulink":"http://www.allmenus.com/wi/antigo/79991-pizza-hut/menu/",
    "sg:phone":"+1 715 623 7671",
    "sg:postcode":"54409",
    "sg:province":"WI",
    "sg:tags":[
        "american",
        "pizza"
    ],
    "wof:name":"Pizza Hut",
    "wof:placetype":"venue"
},
  "geometry": {"coordinates":[-89.148037,45.159883],"type":"Point"}
}