{
  "type": "Feature",
  "properties": {
    "iso:country":"US",
    "sg:address":"1910 W Lawn Ave",
    "sg:city":"Madison",
    "sg:classifiers":[
        {
            "category":"Professional",
            "type":"Services"
        }
    ],
    "sg:phone":"+1 608 255 9992",
    "sg:postcode":"53711",
    "sg:province":"WI",
    "wof:name":"Lynn Bjorkman",
    "wof:placetype":"venue"
},
  "geometry": {"coordinates":[-89.41968199999999,43.064453],"type":"Point"}
}