{
  "type": "Feature",
  "properties": {
    "iso:country":"US",
    "sg:address":"2245 W College Ave",
    "sg:city":"Appleton",
    "sg:classifiers":[
        {
            "category":"Autos & Motor Vehicles",
            "subcategory":"Automobile Sales",
            "type":"Retail Goods"
        }
    ],
    "sg:phone":"+1 920 749 5800",
    "sg:postcode":"54914",
    "sg:province":"WI",
    "sg:tags":[
        "car",
        "dealer"
    ],
    "sg:website":"www.bergstromauto.com",
    "wof:name":"Chevrolet-Oldsmobile-Cadillac",
    "wof:placetype":"venue"
},
  "geometry": {"coordinates":[-88.441293,44.261673],"type":"Point"}
}