{
  "type": "Feature",
  "properties": {
    "addr:full":"610 Main St Boyceville WI 54725",
    "addr:housenumber":"610",
    "addr:postcode":"54725",
    "addr:street":"Main St",
    "iso:country":"US",
    "sg:address":"610 Main St",
    "sg:city":"Boyceville",
    "sg:classifiers":[
        {
            "category":"Retail",
            "subcategory":"Auto Repair",
            "type":"Services"
        }
    ],
    "sg:phone":"+1 715 643 7007",
    "sg:postcode":"54725",
    "sg:province":"WI",
    "sg:tags":[
        "repairing",
        "automobile"
    ],
    "wof:name":"Trax Repair",
    "wof:placetype":"venue"
},
  "geometry": {"coordinates":[-92.042878,45.043953],"type":"Point"}
}