{
  "type": "Feature",
  "properties": {
    "iso:country":"US",
    "sg:address":"12242 Clarkson Rd",
    "sg:city":"Waterloo",
    "sg:classifiers":[
        {
            "category":"Freight",
            "type":"Transportation"
        }
    ],
    "sg:phone":"+1 920 478 2534",
    "sg:postcode":"53594",
    "sg:province":"WI",
    "sg:tags":[
        "operator",
        "local",
        "trucking"
    ],
    "wof:name":"Jeff Wagner Trucking",
    "wof:placetype":"venue"
},
  "geometry": {"coordinates":[-88.99559,43.197957],"type":"Point"}
}