{
  "type": "Feature",
  "properties": {
    "addr:full":"16900 W Bluemound Rd Brookfield WI 53005",
    "addr:housenumber":"16900",
    "addr:postcode":"53005",
    "addr:street":"W Bluemound Rd",
    "iso:country":"US",
    "sg:address":"16900 W Bluemound Rd",
    "sg:city":"Brookfield",
    "sg:classifiers":[
        {
            "category":"Professional",
            "type":"Services"
        }
    ],
    "sg:phone":"+1 262 786 1404",
    "sg:postcode":"53005",
    "sg:province":"WI",
    "sg:tags":[
        "establishment"
    ],
    "wof:name":"Village Shop",
    "wof:placetype":"venue"
},
  "geometry": {"coordinates":[-88.121584,43.037055],"type":"Point"}
}