{
  "type": "Feature",
  "properties": {
    "addr:full":"2401 S Williams St Milwaukee WI 53207",
    "addr:housenumber":"2401",
    "addr:postcode":"53207",
    "addr:street":"S Williams St",
    "iso:country":"US",
    "sg:address":"2401 S Williams St",
    "sg:city":"Milwaukee",
    "sg:classifiers":[
        {
            "category":"Food & Beverages",
            "subcategory":"Specialty",
            "type":"Retail Goods"
        }
    ],
    "sg:phone":"+1 414 482 2009",
    "sg:postcode":"53207",
    "sg:province":"WI",
    "wof:name":"Jil Enterprises",
    "wof:placetype":"venue"
},
  "geometry": {"coordinates":[-87.899492,42.999562],"type":"Point"}
}