{
  "type": "Feature",
  "properties": {
    "addr:full":"414 S Jefferson St Green Bay WI 54301",
    "addr:housenumber":"414",
    "addr:postcode":"54301",
    "addr:street":"S Jefferson St",
    "iso:country":"US",
    "sg:address":"414 S Jefferson St",
    "sg:city":"Green Bay",
    "sg:classifiers":[
        {
            "category":"Professional",
            "subcategory":"Lawyer & Legal Services",
            "type":"Services"
        }
    ],
    "sg:phone":"+1 920 435 3734",
    "sg:postcode":"54301",
    "sg:province":"WI",
    "sg:tags":[
        "attorney"
    ],
    "sg:website":"www.eversonlaw.com",
    "wof:name":"Everson Whitney & Brehm Sc",
    "wof:placetype":"venue"
},
  "geometry": {"coordinates":[-88.016383,44.509094],"type":"Point"}
}