{
  "type": "Feature",
  "properties": {
    "iso:country":"US",
    "sg:address":"460 Huron Bay Dr",
    "sg:city":"Montello",
    "sg:classifiers":[
        {
            "category":"Professional",
            "type":"Services"
        }
    ],
    "sg:phone":"+1 920 295 6882",
    "sg:postcode":"53949",
    "sg:province":"WI",
    "wof:name":"Opulent Inc",
    "wof:placetype":"venue"
},
  "geometry": {"coordinates":[-89.180937,43.765667],"type":"Point"}
}