{
  "type": "Feature",
  "properties": {
    "iso:country":"US",
    "sg:address":"3850 River Dr",
    "sg:city":"Waupaca",
    "sg:classifiers":[
        {
            "category":"Building & Trades",
            "subcategory":"Electrical",
            "type":"Services"
        }
    ],
    "sg:phone":"+1 715 258 2196",
    "sg:postcode":"54981",
    "sg:province":"WI",
    "sg:tags":[
        "electrical",
        "contractor"
    ],
    "wof:name":"Soldberg Electric",
    "wof:placetype":"venue"
},
  "geometry": {"coordinates":[-89.15091700000001,44.376725],"type":"Point"}
}