{
  "type": "Feature",
  "properties": {
    "iso:country":"US",
    "sg:address":"1050 Lowater Rd",
    "sg:city":"Chippewa Falls",
    "sg:classifiers":[
        {
            "category":"Professional",
            "subcategory":"Computer Services",
            "type":"Services"
        }
    ],
    "sg:phone":"+1 715 726 4000",
    "sg:postcode":"54729",
    "sg:province":"WI",
    "sg:tags":[
        "consultant",
        "designer"
    ],
    "sg:website":"www.cray.com",
    "wof:name":"Cray Inc",
    "wof:placetype":"venue"
},
  "geometry": {"coordinates":[-91.368323,44.953952],"type":"Point"}
}