{
  "type": "Feature",
  "properties": {
    "addr:full":"4693 W College Ave Appleton WI 54914",
    "addr:housenumber":"4693",
    "addr:postcode":"54914",
    "addr:street":"W College Ave",
    "iso:country":"US",
    "sg:address":"4693 W College Ave",
    "sg:city":"Appleton",
    "sg:classifiers":[
        {
            "category":"Shopping",
            "subcategory":"Stationery & Office Supplies",
            "type":"Retail Goods"
        }
    ],
    "sg:phone":"+1 920 830 9300",
    "sg:postcode":"54914",
    "sg:province":"WI",
    "wof:name":"Office Max",
    "wof:placetype":"venue"
},
  "geometry": {"coordinates":[-88.46941700000001,44.261883],"type":"Point"}
}