{
  "type": "Feature",
  "properties": {
    "iso:country":"US",
    "sg:address":"1308 Wolf Dr",
    "sg:city":"West Bend",
    "sg:classifiers":[
        {
            "category":"Building & Trades",
            "subcategory":"Construction",
            "type":"Services"
        }
    ],
    "sg:phone":"+1 262 335 6497",
    "sg:postcode":"53090",
    "sg:province":"WI",
    "sg:tags":[
        "house"
    ],
    "wof:name":"Krause Family Homes LLC",
    "wof:placetype":"venue"
},
  "geometry": {"coordinates":[-88.227087,43.438438],"type":"Point"}
}