{
  "type": "Feature",
  "properties": {
    "addr:full":"2506 N Dr Martin Luther King Dr Milwaukee WI 53212",
    "addr:housenumber":"2506",
    "addr:postcode":"53212",
    "addr:street":"N Dr Martin Luther King Dr",
    "iso:country":"US",
    "sg:address":"2506 N Dr Martin Luther King Dr",
    "sg:city":"Milwaukee",
    "sg:classifiers":[
        {
            "category":"Real Estate",
            "subcategory":"Real Estate Operator",
            "type":"Services"
        }
    ],
    "sg:phone":"+1 414 264 5070",
    "sg:postcode":"53212",
    "sg:province":"WI",
    "sg:tags":[
        "apartment"
    ],
    "wof:name":"Northwoods Apartments",
    "wof:placetype":"venue"
},
  "geometry": {"coordinates":[-87.91401399999999,43.065622],"type":"Point"}
}