{
  "type": "Feature",
  "properties": {
    "iso:country":"US",
    "sg:address":"732 Industrial Loop Rd",
    "sg:city":"New London",
    "sg:classifiers":[
        {
            "category":"Manufacturing",
            "subcategory":"Wood Products",
            "type":"Manufacturing & Wholesale Goods"
        }
    ],
    "sg:phone":"+1 920 982 5097",
    "sg:postcode":"54961",
    "sg:province":"WI",
    "sg:tags":[
        "pallet",
        "skid"
    ],
    "wof:name":"Newark",
    "wof:placetype":"venue"
},
  "geometry": {"coordinates":[-88.727352,44.374703],"type":"Point"}
}