{
  "type": "Feature",
  "properties": {
    "addr:full":"1106 E Colley Rd Beloit WI 53511",
    "addr:housenumber":"1106",
    "addr:postcode":"53511",
    "addr:street":"E Colley Rd",
    "iso:country":"US",
    "sg:address":"1106 E Colley Rd",
    "sg:city":"Beloit",
    "sg:classifiers":[
        {
            "category":"Retail",
            "subcategory":"Animal Services",
            "type":"Services"
        }
    ],
    "sg:phone":"+1 608 362 6371",
    "sg:postcode":"53511",
    "sg:province":"WI",
    "sg:tags":[
        "horse",
        "training"
    ],
    "wof:name":"Meri-J Stables & Arena",
    "wof:placetype":"venue"
},
  "geometry": {"coordinates":[-89.014505,42.50695],"type":"Point"}
}