{
  "type": "Feature",
  "properties": {
    "iso:country":"US",
    "sg:address":"13055 Cardinal Crest Dr",
    "sg:city":"Brookfield",
    "sg:classifiers":[
        {
            "category":"Real Estate",
            "subcategory":"Real Estate Agent",
            "type":"Services"
        },
        {
            "category":"Professional",
            "subcategory":"Business Services",
            "type":"Services"
        }
    ],
    "sg:phone":"+1 262 780 1136",
    "sg:postcode":"53005",
    "sg:province":"WI",
    "sg:tags":[
        "inspection"
    ],
    "wof:name":"Safe-House Inspection Service",
    "wof:placetype":"venue"
},
  "geometry": {"coordinates":[-88.07505,43.026857],"type":"Point"}
}