{
  "type": "Feature",
  "properties": {
    "iso:country":"US",
    "sg:address":"2522 Golf Rd",
    "sg:city":"Eau Claire",
    "sg:classifiers":[
        {
            "category":"Professional",
            "subcategory":"Lawyer & Legal Services",
            "type":"Services"
        }
    ],
    "sg:phone":"+1 715 858 0889",
    "sg:postcode":"54701",
    "sg:province":"WI",
    "wof:name":"Steiner Erwin H",
    "wof:placetype":"venue"
},
  "geometry": {"coordinates":[-91.463889,44.77123],"type":"Point"}
}