{
  "type": "Feature",
  "properties": {
    "iso:country":"US",
    "sg:address":"2027 Lathrop Ave",
    "sg:city":"Racine",
    "sg:classifiers":[
        {
            "category":"Retail",
            "subcategory":"Self-service Laundry",
            "type":"Services"
        }
    ],
    "sg:phone":"+1 262 633 8013",
    "sg:postcode":"53405",
    "sg:province":"WI",
    "sg:tags":[
        "machine",
        "operator",
        "coin",
        "vending"
    ],
    "wof:name":"Velvet Touch Laundromat",
    "wof:placetype":"venue"
},
  "geometry": {"coordinates":[-87.8259,42.704685],"type":"Point"}
}