{
  "type": "Feature",
  "properties": {
    "addr:full":"9212 Western Rd Cedarburg WI 53012",
    "addr:housenumber":"9212",
    "addr:postcode":"53012",
    "addr:street":"Western Rd",
    "iso:country":"US",
    "sg:address":"9212 Western Rd",
    "sg:city":"Cedarburg",
    "sg:classifiers":[
        {
            "category":"Health Services",
            "subcategory":"Doctor",
            "type":"Services"
        }
    ],
    "sg:phone":"+1 262 377 5164",
    "sg:postcode":"53012",
    "sg:province":"WI",
    "sg:tags":[
        "medical"
    ],
    "wof:name":"Robert F Koebert MD PC",
    "wof:placetype":"venue"
},
  "geometry": {"coordinates":[-88.024142,43.293383],"type":"Point"}
}