{
  "type": "Feature",
  "properties": {
    "iso:country":"US",
    "sg:address":"336 N Jefferson St",
    "sg:city":"Lancaster",
    "sg:classifiers":[
        {
            "category":"Manufacturing",
            "subcategory":"Electronics",
            "type":"Manufacturing & Wholesale Goods"
        }
    ],
    "sg:phone":"+1 608 723 4551",
    "sg:postcode":"53813",
    "sg:province":"WI",
    "sg:tags":[
        "equipment",
        "communications",
        "durable",
        "sig",
        "mfg"
    ],
    "wof:name":"Central State Signing Inc",
    "wof:placetype":"venue"
},
  "geometry": {"coordinates":[-90.710967,42.850565],"type":"Point"}
}