{
  "type": "Feature",
  "properties": {
    "iso:country":"US",
    "sg:address":"8117 1130th Ave",
    "sg:city":"Colfax",
    "sg:classifiers":[
        {
            "category":"Farming",
            "subcategory":"Dairy Farm",
            "type":"Manufacturing & Wholesale Goods"
        }
    ],
    "sg:phone":"+1 715 658 1340",
    "sg:postcode":"54730",
    "sg:province":"WI",
    "wof:name":"Sonnenberg Rolling Acres",
    "wof:placetype":"venue"
},
  "geometry": {"coordinates":[-91.751896,45.088624],"type":"Point"}
}