{
  "type": "Feature",
  "properties": {
    "iso:country":"US",
    "sg:address":"1220 16th Ave",
    "sg:city":"Monroe",
    "sg:classifiers":[
        {
            "category":"Education",
            "subcategory":"School",
            "type":"Public Place"
        }
    ],
    "sg:phone":"+1 608 328 7227",
    "sg:postcode":"53566",
    "sg:province":"WI",
    "sg:tags":[
        "charter"
    ],
    "wof:name":"Monroe Alternative Chrtr Schl",
    "wof:placetype":"venue"
},
  "geometry": {"coordinates":[-89.63982,42.600035],"type":"Point"}
}