{
  "type": "Feature",
  "properties": {
    "iso:country":"US",
    "sg:address":"3332 N Lake Dr",
    "sg:city":"Milwaukee",
    "sg:classifiers":[
        {
            "category":"Building & Trades",
            "subcategory":"Construction",
            "type":"Services"
        }
    ],
    "sg:phone":"+1 414 963 9588",
    "sg:postcode":"53211",
    "sg:province":"WI",
    "sg:tags":[
        "interior",
        "residential",
        "commercial",
        "design"
    ],
    "wof:name":"Innovative Design Services LLC",
    "wof:placetype":"venue"
},
  "geometry": {"coordinates":[-87.872381,43.078264],"type":"Point"}
}