{
  "type": "Feature",
  "properties": {
    "addr:full":"7907 Rainbow Rd Lake Tomahawk WI 54539",
    "addr:housenumber":"7907",
    "addr:postcode":"54539",
    "addr:street":"Rainbow Rd",
    "iso:country":"US",
    "sg:address":"7907 Rainbow Rd",
    "sg:city":"Lake Tomahawk",
    "sg:classifiers":[
        {
            "category":"Personal",
            "type":"Services"
        }
    ],
    "sg:phone":"+1 715 277 2212",
    "sg:postcode":"54539",
    "sg:province":"WI",
    "sg:tags":[
        "therapist",
        "massage"
    ],
    "wof:name":"Stress Recess",
    "wof:placetype":"venue"
},
  "geometry": {"coordinates":[-89.589716,45.817045],"type":"Point"}
}