{
  "type": "Feature",
  "properties": {
    "addr:full":"11606 Sheridan Rd Pleasant Prairie WI 53158",
    "addr:housenumber":"11606",
    "addr:postcode":"53158",
    "addr:street":"Sheridan Rd",
    "iso:country":"US",
    "sg:address":"11606 Sheridan Rd",
    "sg:city":"Pleasant Prairie",
    "sg:classifiers":[
        {
            "category":"Bars & Pubs",
            "type":"Food & Drink"
        }
    ],
    "sg:phone":"+1 262 694 7809",
    "sg:postcode":"53158",
    "sg:province":"WI",
    "wof:name":"Wooden Nickel",
    "wof:placetype":"venue"
},
  "geometry": {"coordinates":[-87.82225800000001,42.495526],"type":"Point"}
}