{
  "type": "Feature",
  "properties": {
    "iso:country":"US",
    "sg:address":"338 Glen Cove Ct",
    "sg:city":"Nekoosa",
    "sg:classifiers":[
        {
            "category":"Freight",
            "type":"Transportation"
        }
    ],
    "sg:phone":"+1 715 325 6400",
    "sg:postcode":"54457",
    "sg:province":"WI",
    "sg:tags":[
        "commercial",
        "storage"
    ],
    "wof:name":"Tri-Lakes Storage",
    "wof:placetype":"venue"
},
  "geometry": {"coordinates":[-89.78726899999999,44.20798],"type":"Point"}
}