{
  "type": "Feature",
  "properties": {
    "iso:country":"US",
    "sg:address":"6710 Big Bend Rd",
    "sg:city":"Waterford",
    "sg:classifiers":[
        {
            "category":"Professional",
            "type":"Services"
        }
    ],
    "sg:phone":"+1 262 895 6268",
    "sg:postcode":"53185",
    "sg:province":"WI",
    "sg:tags":[
        "establishment"
    ],
    "wof:name":"Tichigan Lake Civic Ctr",
    "wof:placetype":"venue"
},
  "geometry": {"coordinates":[-88.198457,42.809935],"type":"Point"}
}