{
  "type": "Feature",
  "properties": {
    "iso:country":"US",
    "sg:address":"2612 W Morgan Ave",
    "sg:city":"Milwaukee",
    "sg:classifiers":[
        {
            "category":"Restaurant",
            "type":"Food & Drink"
        }
    ],
    "sg:phone":"+1 414 645 1333",
    "sg:postcode":"53221",
    "sg:province":"WI",
    "sg:tags":[
        "fast"
    ],
    "wof:name":"McDonalds",
    "wof:placetype":"venue"
},
  "geometry": {"coordinates":[-87.948229,42.981339],"type":"Point"}
}