{
  "type": "Feature",
  "properties": {
    "iso:country":"US",
    "sg:address":"2925 Bradley St",
    "sg:city":"Oshkosh",
    "sg:classifiers":[
        {
            "category":"Freight",
            "type":"Transportation"
        }
    ],
    "sg:phone":"+1 920 235 0505",
    "sg:postcode":"54902",
    "sg:province":"WI",
    "sg:tags":[
        "commercial",
        "storage"
    ],
    "wof:name":"Bradley Mini-Warehousing",
    "wof:placetype":"venue"
},
  "geometry": {"coordinates":[-88.538905,43.983141],"type":"Point"}
}