{
  "type": "Feature",
  "properties": {
    "iso:country":"US",
    "sg:address":"6908 Chickadee Rd",
    "sg:city":"Greenwood",
    "sg:classifiers":[
        {
            "category":"Farming",
            "subcategory":"Livestock Farm",
            "type":"Manufacturing & Wholesale Goods"
        }
    ],
    "sg:phone":"+1 715 267 7577",
    "sg:postcode":"54437",
    "sg:province":"WI",
    "sg:tags":[
        "equine"
    ],
    "wof:name":"Alan Flaatten",
    "wof:placetype":"venue"
},
  "geometry": {"coordinates":[-90.668601,44.727276],"type":"Point"}
}