{
  "type": "Feature",
  "properties": {
    "iso:country":"US",
    "sg:address":"44995 S Lake Owen Dr",
    "sg:city":"Cable",
    "sg:classifiers":[
        {
            "category":"Manufacturing",
            "subcategory":"Pottery",
            "type":"Manufacturing & Wholesale Goods"
        }
    ],
    "sg:phone":"+1 715 798 4480",
    "sg:postcode":"54821",
    "sg:province":"WI",
    "sg:tags":[
        "product",
        "mfg"
    ],
    "wof:name":"Plaid Rabbit Stoneware",
    "wof:placetype":"venue"
},
  "geometry": {"coordinates":[-91.240239,46.225601],"type":"Point"}
}