{
  "type": "Feature",
  "properties": {
    "iso:country":"US",
    "sg:address":"1830 S Military Ave",
    "sg:city":"Green Bay",
    "sg:classifiers":[
        {
            "category":"Organizations",
            "subcategory":"Religious Organization",
            "type":"Services"
        }
    ],
    "sg:phone":"+1 920 494 3647",
    "sg:postcode":"54304",
    "sg:province":"WI",
    "sg:website":"www.highlandcrestbaptist.com",
    "wof:name":"Highland Crest Baptist Church",
    "wof:placetype":"venue"
},
  "geometry": {"coordinates":[-88.066709,44.505347],"type":"Point"}
}