{
  "type": "Feature",
  "properties": {
    "iso:country":"US",
    "sg:address":"1929 Holmgren Way",
    "sg:city":"Green Bay",
    "sg:classifiers":[
        {
            "category":"Shopping",
            "subcategory":"Musical Instruments",
            "type":"Retail Goods"
        }
    ],
    "sg:phone":"+1 920 438 0030",
    "sg:postcode":"54304",
    "sg:province":"WI",
    "wof:name":"Madhouse Music",
    "wof:placetype":"venue"
},
  "geometry": {"coordinates":[-88.05258600000001,44.499462],"type":"Point"}
}