{
  "type": "Feature",
  "properties": {
    "iso:country":"US",
    "sg:address":"1201 Gillingham Rd",
    "sg:city":"Neenah",
    "sg:classifiers":[
        {
            "category":"Organizations",
            "subcategory":"Labor Organization",
            "type":"Services"
        }
    ],
    "sg:phone":"+1 920 722 8520",
    "sg:postcode":"54956",
    "sg:province":"WI",
    "wof:name":"United Paper Workers Intl Un",
    "wof:placetype":"venue"
},
  "geometry": {"coordinates":[-88.485575,44.160055],"type":"Point"}
}