{
  "type": "Feature",
  "properties": {
    "iso:country":"US",
    "sg:address":"2715 32nd St",
    "sg:city":"Two Rivers",
    "sg:classifiers":[
        {
            "category":"Building & Trades",
            "subcategory":"Construction",
            "type":"Services"
        }
    ],
    "sg:phone":"+1 920 793 2502",
    "sg:postcode":"54241",
    "sg:province":"WI",
    "sg:tags":[
        "house",
        "contractor"
    ],
    "wof:name":"Wojta Gerald Builders",
    "wof:placetype":"venue"
},
  "geometry": {"coordinates":[-87.58744,44.162872],"type":"Point"}
}