{
  "type": "Feature",
  "properties": {
    "addr:full":"1055 Prairie Dr Racine WI 53406",
    "addr:housenumber":"1055",
    "addr:postcode":"53406",
    "addr:street":"Prairie Dr",
    "iso:country":"US",
    "sg:address":"1055 Prairie Dr",
    "sg:city":"Racine",
    "sg:classifiers":[
        {
            "category":"Insurance",
            "subcategory":"Insurance Agent",
            "type":"Services"
        }
    ],
    "sg:phone":"+1 262 898 7100",
    "sg:postcode":"53406",
    "sg:province":"WI",
    "sg:tags":[
        "processing"
    ],
    "wof:name":"R K LTD",
    "wof:placetype":"venue"
},
  "geometry": {"coordinates":[-87.867412,42.721654],"type":"Point"}
}