{
  "type": "Feature",
  "properties": {
    "addr:full":"1035 W Paradise Dr West Bend WI 53095",
    "addr:housenumber":"1035",
    "addr:postcode":"53095",
    "addr:street":"W Paradise Dr",
    "iso:country":"US",
    "sg:address":"1035 W Paradise Dr",
    "sg:city":"West Bend",
    "sg:classifiers":[
        {
            "category":"Shopping",
            "subcategory":"Computers & Home Electronics",
            "type":"Retail Goods"
        }
    ],
    "sg:phone":"+1 262 675 0890",
    "sg:postcode":"53095",
    "sg:province":"WI",
    "sg:tags":[
        "software"
    ],
    "wof:name":"Computer Outfitters Inc",
    "wof:placetype":"venue"
},
  "geometry": {"coordinates":[-88.189897,43.397762],"type":"Point"}
}