{
  "type": "Feature",
  "properties": {
    "addr:full":"1206 Spring Valley Rd Jackson WI 53037",
    "addr:housenumber":"1206",
    "addr:postcode":"53037",
    "addr:street":"Spring Valley Rd",
    "iso:country":"US",
    "sg:address":"1206 Spring Valley Rd",
    "sg:city":"Jackson",
    "sg:classifiers":[
        {
            "category":"Building & Trades",
            "subcategory":"Construction",
            "type":"Services"
        }
    ],
    "sg:phone":"+1 262 677 0918",
    "sg:postcode":"53037",
    "sg:province":"WI",
    "sg:tags":[
        "house"
    ],
    "wof:name":"Pine Tree Homes",
    "wof:placetype":"venue"
},
  "geometry": {"coordinates":[-88.10284900000001,43.28684],"type":"Point"}
}