{
  "type": "Feature",
  "properties": {
    "iso:country":"US",
    "sg:address":"1071 Cormier Rd",
    "sg:city":"Green Bay",
    "sg:classifiers":[
        {
            "category":"Health Services",
            "subcategory":"Chiropractor",
            "type":"Services"
        },
        {
            "category":"Health Services",
            "subcategory":"Doctor",
            "type":"Services"
        }
    ],
    "sg:phone":"+1 920 499 0123",
    "sg:postcode":"54304",
    "sg:province":"WI",
    "sg:tags":[
        "medical"
    ],
    "wof:name":"Ashwaubenon Chiropratic Clinic",
    "wof:placetype":"venue"
},
  "geometry": {"coordinates":[-88.072361,44.491799],"type":"Point"}
}