{
  "type": "Feature",
  "properties": {
    "iso:country":"US",
    "sg:address":"6374 Nesbitt Rd",
    "sg:city":"Madison",
    "sg:classifiers":[
        {
            "category":"Building & Trades",
            "subcategory":"Construction",
            "type":"Services"
        }
    ],
    "sg:phone":"+1 608 446 0815",
    "sg:postcode":"53719",
    "sg:province":"WI",
    "sg:tags":[
        "roofing",
        "contractor"
    ],
    "wof:name":"Boren Roofing",
    "wof:placetype":"venue"
},
  "geometry": {"coordinates":[-89.486782,43.00609],"type":"Point"}
}