{
  "type": "Feature",
  "properties": {
    "iso:country":"US",
    "sg:address":"1362 Hillestad Rd",
    "sg:city":"Lodi",
    "sg:classifiers":[
        {
            "category":"Building & Trades",
            "subcategory":"Construction",
            "type":"Services"
        }
    ],
    "sg:phone":"+1 608 592 7265",
    "sg:postcode":"53555",
    "sg:province":"WI",
    "sg:tags":[
        "nonresidential"
    ],
    "wof:name":"Sk Construction",
    "wof:placetype":"venue"
},
  "geometry": {"coordinates":[-89.486795,43.314291],"type":"Point"}
}