{
  "type": "Feature",
  "properties": {
    "addr:full":"101 E Keane St Ridgeway WI 53582",
    "addr:housenumber":"101",
    "addr:postcode":"53582",
    "addr:street":"E Keane St",
    "iso:country":"US",
    "sg:address":"101 E Keane St",
    "sg:city":"Ridgeway",
    "sg:classifiers":[
        {
            "category":"Wholesale",
            "subcategory":"Machinery & Supplies",
            "type":"Manufacturing & Wholesale Goods"
        }
    ],
    "sg:phone":"+1 608 235 1126",
    "sg:postcode":"53582",
    "sg:province":"WI",
    "sg:tags":[
        "equipment",
        "industrial"
    ],
    "wof:name":"Machine Control & Automation",
    "wof:placetype":"venue"
},
  "geometry": {"coordinates":[-89.98715199999999,42.997143],"type":"Point"}
}