{
  "type": "Feature",
  "properties": {
    "addr:full":"2735 S Delaware Ave Milwaukee WI 53207",
    "addr:housenumber":"2735",
    "addr:postcode":"53207",
    "addr:street":"S Delaware Ave",
    "iso:country":"US",
    "sg:address":"2735 S Delaware Ave",
    "sg:city":"Milwaukee",
    "sg:classifiers":[
        {
            "category":"Professional",
            "subcategory":"Accounting & Tax Preparation",
            "type":"Services"
        }
    ],
    "sg:phone":"+1 414 294 4824",
    "sg:postcode":"53207",
    "sg:province":"WI",
    "wof:name":"Data Management Services LLC",
    "wof:placetype":"venue"
},
  "geometry": {"coordinates":[-87.887085,42.994414],"type":"Point"}
}