{
  "type": "Feature",
  "properties": {
    "addr:full":"3135 W Forest Home Ave Milwaukee WI 53215",
    "addr:housenumber":"3135",
    "addr:postcode":"53215",
    "addr:street":"W Forest Home Ave",
    "iso:country":"US",
    "sg:address":"3135 W Forest Home Ave",
    "sg:city":"Milwaukee",
    "sg:classifiers":[
        {
            "category":"Retail",
            "subcategory":"Auto Repair",
            "type":"Services"
        }
    ],
    "sg:phone":"+1 414 384 6360",
    "sg:postcode":"53215",
    "sg:province":"WI",
    "sg:tags":[
        "body",
        "repairing",
        "painting",
        "automobile"
    ],
    "sg:website":"http://www.foresthomeautobody.com",
    "wof:name":"Forest Home Auto Body Inc",
    "wof:placetype":"venue"
},
  "geometry": {"coordinates":[-87.95344299999999,42.997547],"type":"Point"}
}