{
  "type": "Feature",
  "properties": {
    "iso:country":"US",
    "sg:address":"2820 W Fond du Lac Ave",
    "sg:city":"Milwaukee",
    "sg:classifiers":[
        {
            "category":"Wholesale",
            "subcategory":"Electrical",
            "type":"Manufacturing & Wholesale Goods"
        }
    ],
    "sg:phone":"+1 414 263 2091",
    "sg:postcode":"53210",
    "sg:province":"WI",
    "sg:tags":[
        "electric",
        "motor"
    ],
    "wof:name":"H Gallatin Inc",
    "wof:placetype":"venue"
},
  "geometry": {"coordinates":[-87.949551,43.069178],"type":"Point"}
}