{
  "type": "Feature",
  "properties": {
    "iso:country":"US",
    "sg:address":"6217 S 18th St",
    "sg:city":"Sheboygan",
    "sg:classifiers":[
        {
            "category":"Professional",
            "subcategory":"Advertising",
            "type":"Services"
        }
    ],
    "sg:phone":"+1 920 458 7311",
    "sg:postcode":"53081",
    "sg:province":"WI",
    "sg:tags":[
        "agency"
    ],
    "wof:name":"Posewitz Marketing Group",
    "wof:placetype":"venue"
},
  "geometry": {"coordinates":[-87.730334,43.681259],"type":"Point"}
}