{
  "type": "Feature",
  "properties": {
    "iso:country":"US",
    "sg:address":"8626 W National Ave",
    "sg:city":"Milwaukee",
    "sg:classifiers":[
        {
            "category":"Retail",
            "subcategory":"Self-service Laundry",
            "type":"Services"
        }
    ],
    "sg:phone":"+1 414 541 5819",
    "sg:postcode":"53227",
    "sg:province":"WI",
    "sg:tags":[
        "coin"
    ],
    "wof:name":"Washing Well",
    "wof:placetype":"venue"
},
  "geometry": {"coordinates":[-88.017663,43.009741],"type":"Point"}
}