{
  "type": "Feature",
  "properties": {
    "addr:full":"6859 Ohio Rd Allenton WI 53002",
    "addr:housenumber":"6859",
    "addr:postcode":"53002",
    "addr:street":"Ohio Rd",
    "iso:country":"US",
    "sg:address":"6859 Ohio Rd",
    "sg:city":"Allenton",
    "sg:classifiers":[
        {
            "category":"Building & Trades",
            "subcategory":"Landscaping Services",
            "type":"Services"
        }
    ],
    "sg:phone":"+1 262 334 8106",
    "sg:postcode":"53002",
    "sg:province":"WI",
    "wof:name":"Mueller Tree Service",
    "wof:placetype":"venue"
},
  "geometry": {"coordinates":[-88.379158,43.435147],"type":"Point"}
}