{
  "type": "Feature",
  "properties": {
    "iso:country":"US",
    "sg:address":"3516 Bonnie St",
    "sg:city":"Appleton",
    "sg:classifiers":[
        {
            "category":"Retail",
            "subcategory":"Laundry & Dry Cleaning",
            "type":"Services"
        }
    ],
    "sg:phone":"+1 920 687 8929",
    "sg:postcode":"54913",
    "sg:province":"WI",
    "sg:tags":[
        "cleaners",
        "upholstery"
    ],
    "wof:name":"Heaven's Best Carpet Cleaning",
    "wof:placetype":"venue"
},
  "geometry": {"coordinates":[-88.319602,44.365538],"type":"Point"}
}