{
  "type": "Feature",
  "properties": {
    "iso:country":"US",
    "sg:address":"912 Ross Ave",
    "sg:city":"Wausau",
    "sg:classifiers":[
        {
            "category":"Professional",
            "type":"Services"
        }
    ],
    "sg:phone":"+1 715 848 8044",
    "sg:postcode":"54403",
    "sg:province":"WI",
    "sg:tags":[
        "establishment"
    ],
    "wof:name":"WDF Intl",
    "wof:placetype":"venue"
},
  "geometry": {"coordinates":[-89.631785,44.935342],"type":"Point"}
}