{
  "type": "Feature",
  "properties": {
    "iso:country":"US",
    "sg:address":"104 320th St",
    "sg:city":"Wilson",
    "sg:classifiers":[
        {
            "category":"Farming",
            "subcategory":"Dairy Farm",
            "type":"Manufacturing & Wholesale Goods"
        }
    ],
    "sg:phone":"+1 715 772 4530",
    "sg:postcode":"54027",
    "sg:province":"WI",
    "wof:name":"Duane Wilman",
    "wof:placetype":"venue"
},
  "geometry": {"coordinates":[-92.15654000000001,44.872294],"type":"Point"}
}