{
  "type": "Feature",
  "properties": {
    "iso:country":"US",
    "sg:address":"3985 State Hwy 13",
    "sg:city":"Colby",
    "sg:classifiers":[
        {
            "category":"Autos & Motor Vehicles",
            "subcategory":"Automobile Sales",
            "type":"Retail Goods"
        }
    ],
    "sg:phone":"+1 715 223 2444",
    "sg:postcode":"54421",
    "sg:province":"WI",
    "sg:tags":[
        "car",
        "dealer"
    ],
    "wof:name":"Midway Auto",
    "wof:placetype":"venue"
},
  "geometry": {"coordinates":[-90.315603,44.877482],"type":"Point"}
}