{
  "type": "Feature",
  "properties": {
    "iso:country":"US",
    "sg:address":"4791 130th St",
    "sg:city":"Menomonie",
    "sg:classifiers":[
        {
            "category":"Building & Trades",
            "subcategory":"Landscaping Services",
            "type":"Services"
        }
    ],
    "sg:phone":"+1 715 772 3422",
    "sg:postcode":"54751",
    "sg:province":"WI",
    "sg:tags":[
        "lawn",
        "maintenance",
        "grounds"
    ],
    "wof:name":"Traynor's Professional Lawn",
    "wof:placetype":"venue"
},
  "geometry": {"coordinates":[-92.095787,44.855084],"type":"Point"}
}