{
  "type": "Feature",
  "properties": {
    "iso:country":"US",
    "sg:address":"6011 N Teutonia Ave",
    "sg:city":"Milwaukee",
    "sg:classifiers":[
        {
            "category":"Utilities",
            "subcategory":"Mobile Phone",
            "type":"Services"
        }
    ],
    "sg:phone":"+1 414 466 1111",
    "sg:postcode":"53209",
    "sg:province":"WI",
    "sg:tags":[
        "communication",
        "radiotelephone"
    ],
    "wof:name":"Cell U Shack",
    "wof:placetype":"venue"
},
  "geometry": {"coordinates":[-87.952507,43.131151],"type":"Point"}
}