{
  "type": "Feature",
  "properties": {
    "iso:country":"US",
    "sg:address":"7540 Co Rd B",
    "sg:city":"Poynette",
    "sg:classifiers":[
        {
            "category":"Professional",
            "type":"Services"
        }
    ],
    "sg:phone":"+1 608 635 9760",
    "sg:postcode":"53955",
    "sg:province":"WI",
    "sg:tags":[
        "establishment"
    ],
    "wof:name":"Custom Harvest",
    "wof:placetype":"venue"
},
  "geometry": {"coordinates":[-89.374419,43.439272],"type":"Point"}
}