{
  "type": "Feature",
  "properties": {
    "addr:full":"5640 Old Town Hall Rd Eau Claire WI 54701",
    "addr:housenumber":"5640",
    "addr:postcode":"54701",
    "addr:street":"Old;Hall Rd",
    "iso:country":"US",
    "sg:address":"5640 Old Town Hall Rd",
    "sg:city":"Eau Claire",
    "sg:classifiers":[
        {
            "category":"Wholesale",
            "subcategory":"Groceries",
            "type":"Manufacturing & Wholesale Goods"
        },
        {
            "category":"Wholesale",
            "subcategory":"Fruits & Vegetables",
            "type":"Manufacturing & Wholesale Goods"
        }
    ],
    "sg:phone":"+1 715 835 0594",
    "sg:postcode":"54701",
    "sg:province":"WI",
    "sg:tags":[
        "grocer"
    ],
    "wof:name":"Chaput Produce Co Inc",
    "wof:placetype":"venue"
},
  "geometry": {"coordinates":[-91.423281,44.763717],"type":"Point"}
}