{
  "type": "Feature",
  "properties": {
    "addr:full":"8616 Lambert Rd Minocqua WI 54548",
    "addr:housenumber":"8616",
    "addr:postcode":"54548",
    "addr:street":"Lambert Rd",
    "iso:country":"US",
    "sg:address":"8616 Lambert Rd",
    "sg:city":"Minocqua",
    "sg:classifiers":[
        {
            "category":"Restaurant",
            "type":"Food & Drink"
        }
    ],
    "sg:phone":"+1 715 358 5944",
    "sg:postcode":"54548",
    "sg:province":"WI",
    "wof:name":"Prancing Pony",
    "wof:placetype":"venue"
},
  "geometry": {"coordinates":[-89.71960199999999,45.876335],"type":"Point"}
}