{
  "type": "Feature",
  "properties": {
    "iso:country":"US",
    "sg:address":"516 W Wisconsin St",
    "sg:city":"Sparta",
    "sg:classifiers":[
        {
            "category":"Restaurant",
            "type":"Food & Drink"
        }
    ],
    "sg:phone":"+1 608 269 9097",
    "sg:postcode":"54656",
    "sg:province":"WI",
    "sg:tags":[
        "eating"
    ],
    "wof:name":"Asian Buffet",
    "wof:placetype":"venue"
},
  "geometry": {"coordinates":[-90.81687,43.939116],"type":"Point"}
}