{
  "type": "Feature",
  "properties": {
    "iso:country":"US",
    "sg:address":"729 Summit St",
    "sg:city":"Hartford",
    "sg:classifiers":[
        {
            "category":"Building & Trades",
            "subcategory":"Construction",
            "type":"Services"
        }
    ],
    "sg:phone":"+1 262 673 5530",
    "sg:postcode":"53027",
    "sg:province":"WI",
    "sg:tags":[
        "house"
    ],
    "wof:name":"R A W Builders",
    "wof:placetype":"venue"
},
  "geometry": {"coordinates":[-88.387956,43.308897],"type":"Point"}
}