{
  "type": "Feature",
  "properties": {
    "iso:country":"US",
    "sg:address":"1115 S 41st St",
    "sg:city":"Milwaukee",
    "sg:classifiers":[
        {
            "category":"Freight",
            "type":"Transportation"
        }
    ],
    "sg:phone":"+1 414 672 6750",
    "sg:postcode":"53215",
    "sg:province":"WI",
    "sg:tags":[
        "packaging",
        "contract"
    ],
    "wof:name":"S & L Packaging Inc",
    "wof:placetype":"venue"
},
  "geometry": {"coordinates":[-87.964902,43.019701],"type":"Point"}
}