{
  "type": "Feature",
  "properties": {
    "iso:country":"US",
    "sg:address":"6930 39th Ave",
    "sg:city":"Kenosha",
    "sg:classifiers":[
        {
            "category":"Retail",
            "subcategory":"Auto Repair",
            "type":"Services"
        }
    ],
    "sg:phone":"+1 262 308 2297",
    "sg:postcode":"53142",
    "sg:province":"WI",
    "sg:tags":[
        "repairing",
        "automobile"
    ],
    "wof:name":"R & R Automotive",
    "wof:placetype":"venue"
},
  "geometry": {"coordinates":[-87.855282,42.570641],"type":"Point"}
}