{
  "type": "Feature",
  "properties": {
    "iso:country":"US",
    "sg:address":"1 Bromley Cir",
    "sg:city":"Madison",
    "sg:classifiers":[
        {
            "category":"Insurance",
            "subcategory":"Hazard Insurance",
            "type":"Services"
        }
    ],
    "sg:phone":"+1 608 223 0444",
    "sg:postcode":"53714",
    "sg:province":"WI",
    "sg:tags":[
        "mortgage"
    ],
    "wof:name":"PMI Mortgage Insurance Co",
    "wof:placetype":"venue"
},
  "geometry": {"coordinates":[-89.295126,43.085059],"type":"Point"}
}