{
  "type": "Feature",
  "properties": {
    "addr:full":"2425 Upham St Madison WI 53704",
    "addr:housenumber":"2425",
    "addr:postcode":"53704",
    "addr:street":"Upham St",
    "iso:country":"US",
    "sg:address":"2425 Upham St",
    "sg:city":"Madison",
    "sg:classifiers":[
        {
            "category":"Building & Trades",
            "subcategory":"Construction",
            "type":"Services"
        }
    ],
    "sg:phone":"+1 608 279 2235",
    "sg:postcode":"53704",
    "sg:province":"WI",
    "sg:tags":[
        "home",
        "improvement"
    ],
    "wof:name":"Capitol Image Building",
    "wof:placetype":"venue"
},
  "geometry": {"coordinates":[-89.35332,43.102126],"type":"Point"}
}