{
  "type": "Feature",
  "properties": {
    "addr:full":"1467 S 108th St Milwaukee WI 53214",
    "addr:housenumber":"1467",
    "addr:postcode":"53214",
    "addr:street":"S 108Th St",
    "iso:country":"US",
    "sg:address":"1467 S 108th St",
    "sg:city":"Milwaukee",
    "sg:classifiers":[
        {
            "category":"Health Services",
            "subcategory":"Chiropractor",
            "type":"Services"
        }
    ],
    "sg:phone":"+1 414 476 6300",
    "sg:postcode":"53214",
    "sg:province":"WI",
    "wof:name":"Chiropractic Associates",
    "wof:placetype":"venue"
},
  "geometry": {"coordinates":[-88.046818,43.015355],"type":"Point"}
}