{
  "type": "Feature",
  "properties": {
    "addr:full":"24934 75th St Salem WI 53168",
    "addr:housenumber":"24934",
    "addr:postcode":"53168",
    "addr:street":"75Th St",
    "iso:country":"US",
    "sg:address":"24934 75th St",
    "sg:city":"Salem",
    "sg:classifiers":[
        {
            "category":"Professional",
            "subcategory":"Business Services",
            "type":"Services"
        }
    ],
    "sg:phone":"+1 262 843 2230",
    "sg:postcode":"53168",
    "sg:province":"WI",
    "wof:name":"Hometowne Home Inspections",
    "wof:placetype":"venue"
},
  "geometry": {"coordinates":[-88.111853,42.568362],"type":"Point"}
}