{
  "type": "Feature",
  "properties": {
    "addr:full":"811 Myrtle Rd Genoa City WI 53128",
    "addr:housenumber":"811",
    "addr:postcode":"53128",
    "addr:street":"Myrtle Rd",
    "iso:country":"US",
    "sg:address":"811 Myrtle Rd",
    "sg:city":"Genoa City",
    "sg:classifiers":[
        {
            "category":"Building & Trades",
            "subcategory":"Construction",
            "type":"Services"
        }
    ],
    "sg:phone":"+1 262 279 3663",
    "sg:postcode":"53128",
    "sg:province":"WI",
    "sg:tags":[
        "roofing",
        "contractor"
    ],
    "wof:name":"Karefree Exteriors",
    "wof:placetype":"venue"
},
  "geometry": {"coordinates":[-88.35154,42.539364],"type":"Point"}
}