{
  "type": "Feature",
  "properties": {
    "addr:full":"1801 N 12th St Milwaukee WI 53205",
    "addr:housenumber":"1801",
    "addr:postcode":"53205",
    "addr:street":"N 12Th St",
    "iso:country":"US",
    "sg:address":"1801 N 12th St",
    "sg:city":"Milwaukee",
    "sg:classifiers":[
        {
            "category":"Social Services",
            "subcategory":"Child Care",
            "type":"Services"
        }
    ],
    "sg:phone":"+1 414 263 1899",
    "sg:postcode":"53205",
    "sg:province":"WI",
    "sg:tags":[
        "day"
    ],
    "wof:name":"Circle Of Life Child Care",
    "wof:placetype":"venue"
},
  "geometry": {"coordinates":[-87.927015,43.055707],"type":"Point"}
}