{
  "type": "Feature",
  "properties": {
    "iso:country":"US",
    "sg:address":"108 W Mill St",
    "sg:city":"Chaseburg",
    "sg:classifiers":[
        {
            "category":"Retail",
            "subcategory":"Portrait Studio",
            "type":"Services"
        }
    ],
    "sg:phone":"+1 608 483 2305",
    "sg:postcode":"54621",
    "sg:province":"WI",
    "sg:tags":[
        "photo"
    ],
    "wof:name":"Lee Photography",
    "wof:placetype":"venue"
},
  "geometry": {"coordinates":[-91.099838,43.655456],"type":"Point"}
}