{
  "type": "Feature",
  "properties": {
    "addr:full":"713 N Leonard St West Salem WI 54669",
    "addr:housenumber":"713",
    "addr:postcode":"54669",
    "addr:street":"N Leonard St",
    "iso:country":"US",
    "sg:address":"713 N Leonard St",
    "sg:city":"West Salem",
    "sg:classifiers":[
        {
            "category":"Health Services",
            "subcategory":"Clinic",
            "type":"Services"
        }
    ],
    "sg:phone":"+1 608 786 2274",
    "sg:postcode":"54669",
    "sg:province":"WI",
    "sg:tags":[
        "specialty",
        "outpatient"
    ],
    "wof:name":"Mississippi Vly Physcl Rehab",
    "wof:placetype":"venue"
},
  "geometry": {"coordinates":[-91.081249,43.905245],"type":"Point"}
}