{
  "type": "Feature",
  "properties": {
    "iso:country":"US",
    "sg:address":"2705 City Heights Rd",
    "sg:city":"Ashland",
    "sg:classifiers":[
        {
            "category":"Shopping",
            "type":"Retail Goods"
        }
    ],
    "sg:phone":"+1 715 682 0440",
    "sg:postcode":"54806",
    "sg:province":"WI",
    "sg:tags":[
        "merchandise"
    ],
    "wof:name":"Chequamegon Bay Gallery",
    "wof:placetype":"venue"
},
  "geometry": {"coordinates":[-90.91054699999999,46.568846],"type":"Point"}
}