{
  "type": "Feature",
  "properties": {
    "addr:full":"5516 W Burleigh St Milwaukee WI 53210",
    "addr:housenumber":"5516",
    "addr:postcode":"53210",
    "addr:street":"W Burleigh St",
    "iso:country":"US",
    "sg:address":"5516 W Burleigh St",
    "sg:city":"Milwaukee",
    "sg:classifiers":[
        {
            "category":"Professional",
            "type":"Services"
        }
    ],
    "sg:phone":"+1 414 873 3129",
    "sg:postcode":"53210",
    "sg:province":"WI",
    "sg:tags":[
        "establishment"
    ],
    "wof:name":"William Beaudoin & Son Inc",
    "wof:placetype":"venue"
},
  "geometry": {"coordinates":[-87.98294199999999,43.075391],"type":"Point"}
}