{
  "type": "Feature",
  "properties": {
    "iso:country":"US",
    "sg:address":"10988 State Hwy 70 E",
    "sg:city":"Woodruff",
    "sg:classifiers":[
        {
            "category":"Building & Trades",
            "subcategory":"Plumbing",
            "type":"Services"
        }
    ],
    "sg:phone":"+1 715 356 7000",
    "sg:postcode":"54568",
    "sg:province":"WI",
    "sg:tags":[
        "heating",
        "contractor"
    ],
    "wof:name":"Danco Plumbing Heating",
    "wof:placetype":"venue"
},
  "geometry": {"coordinates":[-89.684242,45.920724],"type":"Point"}
}