{
  "type": "Feature",
  "properties": {
    "addr:full":"830 Airport Ave Wisconsin Rapids WI 54494",
    "addr:housenumber":"830",
    "addr:postcode":"54494",
    "addr:street":"Airport Ave",
    "iso:country":"US",
    "sg:address":"830 Airport Ave",
    "sg:city":"Wisconsin Rapids",
    "sg:classifiers":[
        {
            "category":"Insurance",
            "subcategory":"Insurance Agent",
            "type":"Services"
        }
    ],
    "sg:phone":"+1 715 423 3888",
    "sg:postcode":"54494",
    "sg:province":"WI",
    "sg:tags":[
        "life"
    ],
    "wof:name":"Farmers Insurance",
    "wof:placetype":"venue"
},
  "geometry": {"coordinates":[-89.81588000000001,44.3658],"type":"Point"}
}