{
  "type": "Feature",
  "properties": {
    "iso:country":"US",
    "sg:address":"3785 S 108th St",
    "sg:city":"Milwaukee",
    "sg:classifiers":[
        {
            "category":"Shopping",
            "subcategory":"Jewelry",
            "type":"Retail Goods"
        }
    ],
    "sg:phone":"+1 414 321 2300",
    "sg:postcode":"53228",
    "sg:province":"WI",
    "sg:tags":[
        "jeweler"
    ],
    "wof:name":"JSK Jewelers",
    "wof:placetype":"venue"
},
  "geometry": {"coordinates":[-88.047515,42.979257],"type":"Point"}
}