{
  "type": "Feature",
  "properties": {
    "iso:country":"US",
    "sg:address":"3817 Co Hwy A",
    "sg:city":"Elkhorn",
    "sg:phone":"+1 262 642 4776",
    "sg:postcode":"53121",
    "sg:province":"WI",
    "sg:tags":[
        "farm",
        "corn",
        "grain",
        "cash"
    ],
    "wof:name":"Chris Olson",
    "wof:placetype":"venue"
},
  "geometry": {"coordinates":[-88.490573,42.762816],"type":"Point"}
}