{
  "type": "Feature",
  "properties": {
    "iso:country":"US",
    "sg:address":"2821 Muth Ct",
    "sg:city":"Sheboygan",
    "sg:classifiers":[
        {
            "category":"Manufacturing",
            "subcategory":"Motor Vehicles & Parts",
            "type":"Manufacturing & Wholesale Goods"
        }
    ],
    "sg:phone":"+1 920 458 9181",
    "sg:postcode":"53083",
    "sg:province":"WI",
    "sg:tags":[
        "automobile",
        "supply"
    ],
    "sg:website":"www.lear.com",
    "wof:name":"Lear Corp",
    "wof:placetype":"venue"
},
  "geometry": {"coordinates":[-87.731553,43.775893],"type":"Point"}
}