{
  "type": "Feature",
  "properties": {
    "addr:full":"12138 State Hwy 21 Sparta WI 54656",
    "addr:housenumber":"12138",
    "addr:postcode":"54656",
    "addr:street":"State Hwy 21",
    "iso:country":"US",
    "sg:address":"12138 State Hwy 21",
    "sg:city":"Sparta",
    "sg:classifiers":[
        {
            "category":"Manufacturing",
            "subcategory":"Signs",
            "type":"Manufacturing & Wholesale Goods"
        }
    ],
    "sg:phone":"+1 608 269 7446",
    "sg:postcode":"54656",
    "sg:province":"WI",
    "wof:name":"Brown's Sparta Sign",
    "wof:placetype":"venue"
},
  "geometry": {"coordinates":[-90.747545,43.975532],"type":"Point"}
}