{
  "type": "Feature",
  "properties": {
    "iso:country":"US",
    "sg:address":"3210 Laura Ln",
    "sg:city":"Middleton",
    "sg:classifiers":[
        {
            "category":"Utilities",
            "subcategory":"Telephone",
            "type":"Services"
        }
    ],
    "sg:phone":"+1 608 831 1000",
    "sg:postcode":"53562",
    "sg:province":"WI",
    "sg:tags":[
        "company"
    ],
    "wof:name":"TDS Telecom",
    "wof:placetype":"venue"
},
  "geometry": {"coordinates":[-89.51445699999999,43.108957],"type":"Point"}
}