{
  "type": "Feature",
  "properties": {
    "iso:country":"US",
    "sg:address":"329 N Geneva Ave",
    "sg:city":"Sturgeon Bay",
    "sg:classifiers":[
        {
            "category":"Banks & Credit Unions",
            "subcategory":"Financial Services",
            "type":"Services"
        }
    ],
    "sg:phone":"+1 920 746 5241",
    "sg:postcode":"54235",
    "sg:province":"WI",
    "sg:tags":[
        "company",
        "holding"
    ],
    "wof:name":"Melarvie Capital Holdings",
    "wof:placetype":"venue"
},
  "geometry": {"coordinates":[-87.393658,44.832534],"type":"Point"}
}