{
  "type": "Feature",
  "properties": {
    "iso:country":"US",
    "sg:address":"6009 Pearl Dr",
    "sg:city":"Appleton",
    "sg:classifiers":[
        {
            "category":"Building & Trades",
            "subcategory":"Construction",
            "type":"Services"
        }
    ],
    "sg:phone":"+1 920 993 9156",
    "sg:postcode":"54915",
    "sg:province":"WI",
    "sg:tags":[
        "residential"
    ],
    "wof:name":"Dickman Construction LLC",
    "wof:placetype":"venue"
},
  "geometry": {"coordinates":[-88.338222,44.24],"type":"Point"}
}