{
  "type": "Feature",
  "properties": {
    "iso:country":"US",
    "sg:address":"1891 Balsam Rd",
    "sg:city":"Stratford",
    "sg:classifiers":[
        {
            "category":"Bars & Pubs",
            "type":"Food & Drink"
        }
    ],
    "sg:phone":"+1 715 687 2263",
    "sg:postcode":"54484",
    "sg:province":"WI",
    "sg:tags":[
        "drinking"
    ],
    "wof:name":"Shack",
    "wof:placetype":"venue"
},
  "geometry": {"coordinates":[-90.025619,44.7864],"type":"Point"}
}