{
  "type": "Feature",
  "properties": {
    "iso:country":"US",
    "sg:address":"2250 Jaybee Dr",
    "sg:city":"Eau Claire",
    "sg:classifiers":[
        {
            "category":"Professional",
            "subcategory":"Business Services",
            "type":"Services"
        }
    ],
    "sg:phone":"+1 715 552 8300",
    "sg:postcode":"54701",
    "sg:province":"WI",
    "wof:name":"Housemaster Home Inspections",
    "wof:placetype":"venue"
},
  "geometry": {"coordinates":[-91.469323,44.717288],"type":"Point"}
}