{
  "type": "Feature",
  "properties": {
    "iso:country":"US",
    "sg:address":"5720 S 108th St",
    "sg:city":"Hales Corners",
    "sg:classifiers":[
        {
            "category":"Shopping",
            "subcategory":"Discount & Variety Stores",
            "type":"Retail Goods"
        }
    ],
    "sg:phone":"+1 414 427 9901",
    "sg:postcode":"53130",
    "sg:province":"WI",
    "wof:name":"Dollar Discount",
    "wof:placetype":"venue"
},
  "geometry": {"coordinates":[-88.048367,42.940466],"type":"Point"}
}