{
  "type": "Feature",
  "properties": {
    "iso:country":"US",
    "sg:address":"640 N Main St",
    "sg:city":"River Falls",
    "sg:classifiers":[
        {
            "category":"Health Services",
            "subcategory":"Nursing And Care Facility",
            "type":"Services"
        }
    ],
    "sg:phone":"+1 715 425 5353",
    "sg:postcode":"54022",
    "sg:province":"WI",
    "sg:tags":[
        "skilled",
        "day",
        "child"
    ],
    "sg:website":"www.lutheranhome.org",
    "wof:name":"Lutheran Home-River Falls",
    "wof:placetype":"venue"
},
  "geometry": {"coordinates":[-92.62205299999999,44.866123],"type":"Point"}
}