{
  "type": "Feature",
  "properties": {
    "iso:country":"US",
    "sg:address":"2052 Cook Dr",
    "sg:city":"Somerset",
    "sg:classifiers":[
        {
            "category":"Shopping",
            "subcategory":"Used Merchandise",
            "type":"Retail Goods"
        }
    ],
    "sg:phone":"+1 715 246 4323",
    "sg:postcode":"54025",
    "sg:province":"WI",
    "wof:name":"Somerset Rebuilt Appliances",
    "wof:placetype":"venue"
},
  "geometry": {"coordinates":[-92.60927,45.160527],"type":"Point"}
}