{
  "type": "Feature",
  "properties": {
    "iso:country":"US",
    "sg:address":"127 N Main St",
    "sg:city":"Greenwood",
    "sg:classifiers":[
        {
            "category":"Building & Trades",
            "subcategory":"Landscaping Services",
            "type":"Services"
        }
    ],
    "sg:phone":"+1 715 267 6153",
    "sg:postcode":"54437",
    "sg:province":"WI",
    "wof:name":"Norms Lawn Care LLC",
    "wof:placetype":"venue"
},
  "geometry": {"coordinates":[-90.598237,44.768221],"type":"Point"}
}