{
  "type": "Feature",
  "properties": {
    "iso:country":"US",
    "sg:address":"1305 Regent St",
    "sg:city":"Madison",
    "sg:classifiers":[
        {
            "category":"Food & Beverages",
            "subcategory":"Bakery",
            "type":"Retail Goods"
        }
    ],
    "sg:phone":"+1 608 257 1151",
    "sg:postcode":"53715",
    "sg:province":"WI",
    "sg:tags":[
        "baker"
    ],
    "wof:name":"Greenbush Bakery Inc",
    "wof:placetype":"venue"
},
  "geometry": {"coordinates":[-89.408933,43.067676],"type":"Point"}
}