{
  "type": "Feature",
  "properties": {
    "iso:country":"US",
    "sg:address":"7449 Co Rd J",
    "sg:city":"Beldenville",
    "sg:classifiers":[
        {
            "category":"Wholesale",
            "subcategory":"Apparel",
            "type":"Manufacturing & Wholesale Goods"
        }
    ],
    "sg:phone":"+1 715 273 6420",
    "sg:postcode":"54003",
    "sg:province":"WI",
    "sg:tags":[
        "hair",
        "accessory"
    ],
    "wof:name":"Encore Kids Inc",
    "wof:placetype":"venue"
},
  "geometry": {"coordinates":[-92.453225,44.810398],"type":"Point"}
}