{
  "type": "Feature",
  "properties": {
    "iso:country":"US",
    "sg:address":"512 Colan Blvd",
    "sg:city":"Rice Lake",
    "sg:classifiers":[
        {
            "category":"Home & Garden",
            "subcategory":"Hardware",
            "type":"Retail Goods"
        }
    ],
    "sg:phone":"+1 715 234 2477",
    "sg:postcode":"54868",
    "sg:province":"WI",
    "sg:tags":[
        "repair",
        "lawn",
        "chain",
        "mower",
        "s",
        "saw",
        "tractor"
    ],
    "wof:name":"Macs Small Engine Service",
    "wof:placetype":"venue"
},
  "geometry": {"coordinates":[-91.714536,45.494431],"type":"Point"}
}