{
  "type": "Feature",
  "properties": {
    "addr:full":"406 Travis Ln Waukesha WI 53189",
    "addr:housenumber":"406",
    "addr:postcode":"53189",
    "addr:street":"Travis Ln",
    "iso:country":"US",
    "sg:address":"406 Travis Ln",
    "sg:city":"Waukesha",
    "sg:classifiers":[
        {
            "category":"Manufacturing",
            "subcategory":"Metals",
            "type":"Manufacturing & Wholesale Goods"
        }
    ],
    "sg:phone":"+1 262 896 1929",
    "sg:postcode":"53189",
    "sg:province":"WI",
    "sg:tags":[
        "heat",
        "gun"
    ],
    "wof:name":"Pamran Co",
    "wof:placetype":"venue"
},
  "geometry": {"coordinates":[-88.233368,42.975717],"type":"Point"}
}