{
  "type": "Feature",
  "properties": {
    "addr:full":"119 S Silver Lake St Oconomowoc WI 53066",
    "addr:housenumber":"119",
    "addr:postcode":"53066",
    "addr:street":"S Silver;St",
    "iso:country":"US",
    "sg:address":"119 S Silver Lake St",
    "sg:city":"Oconomowoc",
    "sg:classifiers":[
        {
            "category":"Shopping",
            "type":"Retail Goods"
        }
    ],
    "sg:phone":"+1 262 560 0889",
    "sg:postcode":"53066",
    "sg:province":"WI",
    "sg:tags":[
        "hearing",
        "equipment",
        "supply",
        "impaired"
    ],
    "wof:name":"Beltone Hearing Aid Ctr",
    "wof:placetype":"venue"
},
  "geometry": {"coordinates":[-88.49581499999999,43.109478],"type":"Point"}
}