{
  "type": "Feature",
  "properties": {
    "iso:country":"US",
    "sg:address":"13625 Bishops Dr",
    "sg:city":"Brookfield",
    "sg:classifiers":[
        {
            "category":"Restaurant",
            "type":"Food & Drink"
        }
    ],
    "sg:phone":"+1 262 827 0291",
    "sg:postcode":"53005",
    "sg:province":"WI",
    "wof:name":"Buffets Inc",
    "wof:placetype":"venue"
},
  "geometry": {"coordinates":[-88.08213499999999,43.029621],"type":"Point"}
}