{
  "type": "Feature",
  "properties": {
    "iso:country":"US",
    "sg:address":"407 Pilot Ct",
    "sg:city":"Waukesha",
    "sg:classifiers":[
        {
            "category":"Banks & Credit Unions",
            "subcategory":"Financial Services",
            "type":"Services"
        }
    ],
    "sg:phone":"+1 262 650 6600",
    "sg:postcode":"53188",
    "sg:province":"WI",
    "sg:tags":[
        "international",
        "trade"
    ],
    "wof:name":"Tradesmen International",
    "wof:placetype":"venue"
},
  "geometry": {"coordinates":[-88.227497,43.027605],"type":"Point"}
}