{
  "type": "Feature",
  "properties": {
    "addr:full":"3134 Trenton Ln Green Bay WI 54313",
    "addr:housenumber":"3134",
    "addr:postcode":"54313",
    "addr:street":"Trenton Ln",
    "iso:country":"US",
    "sg:address":"3134 Trenton Ln",
    "sg:city":"Green Bay",
    "sg:classifiers":[
        {
            "category":"Professional",
            "subcategory":"Business Services",
            "type":"Services"
        }
    ],
    "sg:phone":"+1 920 662 7526",
    "sg:postcode":"54313",
    "sg:province":"WI",
    "wof:name":"Marshall Fr Enterprises LLC",
    "wof:placetype":"venue"
},
  "geometry": {"coordinates":[-88.062673,44.630874],"type":"Point"}
}