{
  "type": "Feature",
  "properties": {
    "addr:full":"170 Lance Dr Twin Lakes WI 53181",
    "addr:housenumber":"170",
    "addr:postcode":"53181",
    "addr:street":"Lance Dr",
    "iso:country":"US",
    "sg:address":"170 Lance Dr",
    "sg:city":"Twin Lakes",
    "sg:classifiers":[
        {
            "category":"Government",
            "subcategory":"Post Office",
            "type":"Public Place"
        }
    ],
    "sg:phone":"+1 262 877 3116",
    "sg:postcode":"53181",
    "sg:province":"WI",
    "wof:name":"US Post Office",
    "wof:placetype":"venue"
},
  "geometry": {"coordinates":[-88.25623,42.53038],"type":"Point"}
}