{
  "type": "Feature",
  "properties": {
    "iso:country":"US",
    "sg:address":"25851 State Rd 35",
    "sg:city":"Webster",
    "sg:classifiers":[
        {
            "category":"Restaurant",
            "type":"Food & Drink"
        }
    ],
    "sg:phone":"+1 715 866 7265",
    "sg:postcode":"54893",
    "sg:province":"WI",
    "wof:name":"Donny's Oak Grove Supper Club",
    "wof:placetype":"venue"
},
  "geometry": {"coordinates":[-92.365168,45.856846],"type":"Point"}
}