{
  "type": "Feature",
  "properties": {
    "iso:country":"US",
    "sg:address":"4506 Regent St",
    "sg:city":"Madison",
    "sg:classifiers":[
        {
            "category":"Health Services",
            "subcategory":"Medical Lab",
            "type":"Services"
        }
    ],
    "sg:phone":"+1 608 257 8444",
    "sg:postcode":"53705",
    "sg:province":"WI",
    "sg:tags":[
        "laboratory"
    ],
    "wof:name":"Hubbard Dental Laboratory",
    "wof:placetype":"venue"
},
  "geometry": {"coordinates":[-89.45427100000001,43.069018],"type":"Point"}
}