{
  "type": "Feature",
  "properties": {
    "addr:full":"512 Co Rd Ff Hudson WI 54016",
    "addr:housenumber":"512",
    "addr:postcode":"54016",
    "addr:street":"Co Rd",
    "iso:country":"US",
    "sg:address":"512 Co Rd Ff",
    "sg:city":"Hudson",
    "sg:phone":"+1 715 386 9612",
    "sg:postcode":"54016",
    "sg:province":"WI",
    "sg:tags":[
        "farm",
        "corn",
        "soybean"
    ],
    "wof:name":"Daniel Solberg",
    "wof:placetype":"venue"
},
  "geometry": {"coordinates":[-92.69327699999999,44.93118],"type":"Point"}
}