{
  "type": "Feature",
  "properties": {
    "iso:country":"US",
    "sg:address":"1025 Forestedge Dr",
    "sg:city":"Kaukauna",
    "sg:classifiers":[
        {
            "category":"Banks & Credit Unions",
            "subcategory":"Bank",
            "type":"Services"
        }
    ],
    "sg:phone":"+1 920 759 9900",
    "sg:postcode":"54130",
    "sg:province":"WI",
    "sg:tags":[
        "loan",
        "mortgage",
        "real estate"
    ],
    "wof:name":"New Century Mortgages",
    "wof:placetype":"venue"
},
  "geometry": {"coordinates":[-88.258503,44.271158],"type":"Point"}
}