{
  "type": "Feature",
  "properties": {
    "iso:country":"US",
    "sg:address":"179 W Division St",
    "sg:city":"Fond Du Lac",
    "sg:classifiers":[
        {
            "category":"Freight",
            "type":"Transportation"
        }
    ],
    "sg:phone":"+1 920 923 7924",
    "sg:postcode":"54935",
    "sg:province":"WI",
    "sg:tags":[
        "shipping",
        "agent"
    ],
    "wof:name":"Du Frane Mini Storage",
    "wof:placetype":"venue"
},
  "geometry": {"coordinates":[-88.45424800000001,43.778887],"type":"Point"}
}