{
  "type": "Feature",
  "properties": {
    "iso:country":"US",
    "sg:address":"3141 Co Rd K",
    "sg:city":"Hartford",
    "sg:classifiers":[
        {
            "category":"Organizations",
            "subcategory":"Religious Organization",
            "type":"Services"
        }
    ],
    "sg:phone":"+1 262 670 0295",
    "sg:postcode":"53027",
    "sg:province":"WI",
    "wof:name":"Servant House Inc",
    "wof:placetype":"venue"
},
  "geometry": {"coordinates":[-88.354399,43.305523],"type":"Point"}
}