{
  "type": "Feature",
  "properties": {
    "iso:country":"US",
    "sg:address":"2800 Roosevelt Rd",
    "sg:city":"Marinette",
    "sg:classifiers":[
        {
            "category":"Government",
            "subcategory":"Office",
            "type":"Public Place"
        }
    ],
    "sg:phone":"+1 715 732 0829",
    "sg:postcode":"54143",
    "sg:province":"WI",
    "sg:tags":[
        "armed",
        "force",
        "recruiting"
    ],
    "wof:name":"US Army Recruiting",
    "wof:placetype":"venue"
},
  "geometry": {"coordinates":[-87.65868500000001,45.059312],"type":"Point"}
}