{
  "type": "Feature",
  "properties": {
    "addr:full":"6236 State Hwy 57 Sturgeon Bay WI 54235",
    "addr:housenumber":"6236",
    "addr:postcode":"54235",
    "addr:street":"State Hwy 57",
    "iso:country":"US",
    "sg:address":"6236 State Hwy 57",
    "sg:city":"Sturgeon Bay",
    "sg:classifiers":[
        {
            "category":"Organizations",
            "subcategory":"Religious Organization",
            "type":"Services"
        }
    ],
    "sg:phone":"+1 920 823 2480",
    "sg:postcode":"54235",
    "sg:province":"WI",
    "sg:tags":[
        "church"
    ],
    "wof:name":"St Michael's Church",
    "wof:placetype":"venue"
},
  "geometry": {"coordinates":[-87.187416,44.975385],"type":"Point"}
}