{
  "type": "Feature",
  "properties": {
    "iso:country":"US",
    "sg:address":"8816 W North Ave",
    "sg:city":"Milwaukee",
    "sg:classifiers":[
        {
            "category":"Shopping",
            "subcategory":"Gifts & Souvenirs",
            "type":"Retail Goods"
        }
    ],
    "sg:phone":"+1 414 771 1160",
    "sg:postcode":"53226",
    "sg:province":"WI",
    "sg:tags":[
        "cards",
        "greeting"
    ],
    "wof:name":"Avenue Card & Gifts",
    "wof:placetype":"venue"
},
  "geometry": {"coordinates":[-88.023594,43.060576],"type":"Point"}
}