{
  "type": "Feature",
  "properties": {
    "iso:country":"US",
    "sg:address":"2150 Memorial Dr",
    "sg:city":"Green Bay",
    "sg:classifiers":[
        {
            "category":"Professional",
            "subcategory":"Business Services",
            "type":"Services"
        }
    ],
    "sg:phone":"+1 920 336 4248",
    "sg:postcode":"54303",
    "sg:province":"WI",
    "wof:name":"Market Wise International",
    "wof:placetype":"venue"
},
  "geometry": {"coordinates":[-88.069315,44.547881],"type":"Point"}
}