{
  "type": "Feature",
  "properties": {
    "iso:country":"US",
    "sg:address":"4760 S Blue Heron Dr",
    "sg:city":"West Bend",
    "sg:classifiers":[
        {
            "category":"Shopping",
            "subcategory":"Gifts & Souvenirs",
            "type":"Retail Goods"
        }
    ],
    "sg:phone":"+1 262 644 9661",
    "sg:postcode":"53095",
    "sg:province":"WI",
    "wof:name":"Bcs Rentals LLC",
    "wof:placetype":"venue"
},
  "geometry": {"coordinates":[-88.273355,43.392308],"type":"Point"}
}