{
  "type": "Feature",
  "properties": {
    "iso:country":"US",
    "sg:address":"24646 Park Rd",
    "sg:city":"Trempealeau",
    "sg:classifiers":[
        {
            "category":"Building & Trades",
            "subcategory":"Construction",
            "type":"Services"
        }
    ],
    "sg:phone":"+1 608 534 6362",
    "sg:postcode":"54661",
    "sg:province":"WI",
    "sg:tags":[
        "contractor"
    ],
    "wof:name":"Rogers Drywall",
    "wof:placetype":"venue"
},
  "geometry": {"coordinates":[-91.44405500000001,44.016621],"type":"Point"}
}