{
  "type": "Feature",
  "properties": {
    "addr:full":"5297 Co Rd T Holmen WI 54636",
    "addr:housenumber":"5297",
    "addr:postcode":"54636",
    "addr:street":"Co Rd",
    "iso:country":"US",
    "sg:address":"5297 Co Rd T",
    "sg:city":"Holmen",
    "sg:classifiers":[
        {
            "category":"Bars & Pubs",
            "type":"Food & Drink"
        }
    ],
    "sg:phone":"+1 608 526 9415",
    "sg:postcode":"54636",
    "sg:province":"WI",
    "wof:name":"Hilltop Tavern",
    "wof:placetype":"venue"
},
  "geometry": {"coordinates":[-91.16918200000001,44.038562],"type":"Point"}
}