{
  "type": "Feature",
  "properties": {
    "iso:country":"US",
    "sg:address":"8271 State Hwy 170",
    "sg:city":"Colfax",
    "sg:classifiers":[
        {
            "category":"Farming",
            "subcategory":"Dairy Farm",
            "type":"Manufacturing & Wholesale Goods"
        }
    ],
    "sg:phone":"+1 715 962 3335",
    "sg:postcode":"54730",
    "sg:province":"WI",
    "wof:name":"Highland Dairy Farm",
    "wof:placetype":"venue"
},
  "geometry": {"coordinates":[-91.74453,45.01562],"type":"Point"}
}