{
  "type": "Feature",
  "properties": {
    "iso:country":"US",
    "sg:address":"8541 W Coldspring Rd",
    "sg:city":"Milwaukee",
    "sg:classifiers":[
        {
            "category":"Building & Trades",
            "subcategory":"Construction",
            "type":"Services"
        }
    ],
    "sg:phone":"+1 414 727 8296",
    "sg:postcode":"53228",
    "sg:province":"WI",
    "sg:tags":[
        "house"
    ],
    "wof:name":"Mitchell Home Improvement",
    "wof:placetype":"venue"
},
  "geometry": {"coordinates":[-88.022747,42.966397],"type":"Point"}
}