{
  "type": "Feature",
  "properties": {
    "addr:full":"413 S Main St Rice Lake WI 54868",
    "addr:housenumber":"413",
    "addr:postcode":"54868",
    "addr:street":"S Main St",
    "iso:country":"US",
    "sg:address":"413 S Main St",
    "sg:city":"Rice Lake",
    "sg:classifiers":[
        {
            "category":"Health Services",
            "subcategory":"Health Practitioner",
            "type":"Services"
        }
    ],
    "sg:phone":"+1 715 236 2827",
    "sg:postcode":"54868",
    "sg:province":"WI",
    "sg:tags":[
        "specialty",
        "outpatient"
    ],
    "wof:name":"Rice Lake Day Treatment",
    "wof:placetype":"venue"
},
  "geometry": {"coordinates":[-91.733271,45.496211],"type":"Point"}
}