{
  "type": "Feature",
  "properties": {
    "iso:country":"US",
    "sg:address":"5378 Lily Pad Ln",
    "sg:city":"Wild Rose",
    "sg:classifiers":[
        {
            "category":"Manufacturing",
            "subcategory":"Furniture",
            "type":"Manufacturing & Wholesale Goods"
        }
    ],
    "sg:phone":"+1 920 622 5540",
    "sg:postcode":"54984",
    "sg:province":"WI",
    "sg:tags":[
        "mfg"
    ],
    "wof:name":"Hinz Cabinet Inc",
    "wof:placetype":"venue"
},
  "geometry": {"coordinates":[-89.172212,44.172132],"type":"Point"}
}