{
  "type": "Feature",
  "properties": {
    "addr:full":"4561 Feldt Rd Monroe WI 53566",
    "addr:housenumber":"4561",
    "addr:postcode":"53566",
    "addr:street":"Feldt Rd",
    "iso:country":"US",
    "sg:address":"4561 Feldt Rd",
    "sg:city":"Monroe",
    "sg:classifiers":[
        {
            "category":"Farming",
            "subcategory":"Farm",
            "type":"Manufacturing & Wholesale Goods"
        }
    ],
    "sg:phone":"+1 608 325 2252",
    "sg:postcode":"53566",
    "sg:province":"WI",
    "sg:tags":[
        "crop",
        "general"
    ],
    "wof:name":"Dennis Holyoke",
    "wof:placetype":"venue"
},
  "geometry": {"coordinates":[-89.588461,42.668241],"type":"Point"}
}