{
  "type": "Feature",
  "properties": {
    "iso:country":"US",
    "sg:address":"1316 W Lawrence St",
    "sg:city":"Appleton",
    "sg:classifiers":[
        {
            "category":"Education",
            "subcategory":"School",
            "type":"Public Place"
        }
    ],
    "sg:phone":"+1 920 733 1660",
    "sg:postcode":"54914",
    "sg:province":"WI",
    "sg:tags":[
        "elementary",
        "church"
    ],
    "wof:name":"St Matthew Ev Lutheran School",
    "wof:placetype":"venue"
},
  "geometry": {"coordinates":[-88.427989,44.26078],"type":"Point"}
}