{
  "type": "Feature",
  "properties": {
    "iso:country":"US",
    "sg:address":"7546 W Greenfield Ave",
    "sg:city":"Milwaukee",
    "sg:classifiers":[
        {
            "category":"Shopping",
            "subcategory":"Jewelry",
            "type":"Retail Goods"
        }
    ],
    "sg:phone":"+1 414 453 0404",
    "sg:postcode":"53214",
    "sg:province":"WI",
    "sg:tags":[
        "clocks"
    ],
    "wof:name":"Owl Imports",
    "wof:placetype":"venue"
},
  "geometry": {"coordinates":[-88.006736,43.016705],"type":"Point"}
}