{
  "type": "Feature",
  "properties": {
    "iso:country":"US",
    "sg:address":"849 E Washington Ave",
    "sg:city":"Madison",
    "sg:classifiers":[
        {
            "category":"Manufacturing",
            "subcategory":"Printing",
            "type":"Manufacturing & Wholesale Goods"
        },
        {
            "category":"Retail",
            "subcategory":"Photofinishing",
            "type":"Services"
        }
    ],
    "sg:phone":"+1 608 256 9050",
    "sg:postcode":"53703",
    "sg:province":"WI",
    "sg:tags":[
        "imagery",
        "color",
        "photo",
        "engrave",
        "digital",
        "laboratory",
        "finishing"
    ],
    "sg:website":"www.hyperionstudio.com",
    "wof:name":"Hyperion Studios Inc",
    "wof:placetype":"venue"
},
  "geometry": {"coordinates":[-89.374196,43.081752],"type":"Point"}
}