{
  "type": "Feature",
  "properties": {
    "iso:country":"US",
    "sg:address":"5606 Woodhollow Rd",
    "sg:city":"Holmen",
    "sg:classifiers":[
        {
            "category":"Retail",
            "subcategory":"Animal Services",
            "type":"Services"
        }
    ],
    "sg:phone":"+1 608 526 4639",
    "sg:postcode":"54636",
    "sg:province":"WI",
    "sg:tags":[
        "sporting"
    ],
    "wof:name":"Wiggerts Tack",
    "wof:placetype":"venue"
},
  "geometry": {"coordinates":[-91.183238,43.991752],"type":"Point"}
}