{
  "type": "Feature",
  "properties": {
    "iso:country":"US",
    "sg:address":"232 Wolf Run",
    "sg:city":"Mukwonago",
    "sg:classifiers":[
        {
            "category":"Building & Trades",
            "subcategory":"Construction",
            "type":"Services"
        }
    ],
    "sg:phone":"+1 262 363 7141",
    "sg:postcode":"53149",
    "sg:province":"WI",
    "sg:tags":[
        "home",
        "improvement"
    ],
    "wof:name":"Home Depot",
    "wof:placetype":"venue"
},
  "geometry": {"coordinates":[-88.322546,42.846446],"type":"Point"}
}