{
  "type": "Feature",
  "properties": {
    "iso:country":"US",
    "sg:address":"503 S Madison St",
    "sg:city":"Prairie Du Chien",
    "sg:classifiers":[
        {
            "category":"Personal",
            "subcategory":"Beauty Salon",
            "type":"Services"
        }
    ],
    "sg:phone":"+1 608 326 2778",
    "sg:postcode":"53821",
    "sg:province":"WI",
    "sg:tags":[
        "shop"
    ],
    "wof:name":"Creative Cuts",
    "wof:placetype":"venue"
},
  "geometry": {"coordinates":[-91.131329,43.045368],"type":"Point"}
}