{
  "type": "Feature",
  "properties": {
    "iso:country":"US",
    "sg:address":"2803 S Taylor Dr",
    "sg:city":"Sheboygan",
    "sg:classifiers":[
        {
            "category":"Manufacturing",
            "subcategory":"Tools & Machinery",
            "type":"Manufacturing & Wholesale Goods"
        }
    ],
    "sg:phone":"+1 920 452 2110",
    "sg:postcode":"53081",
    "sg:province":"WI",
    "sg:tags":[
        "machine",
        "woodworking",
        "mfg"
    ],
    "sg:website":"www.jenkins-systems.com",
    "wof:name":"Jenkins Systems LLC",
    "wof:placetype":"venue"
},
  "geometry": {"coordinates":[-87.754803,43.727096],"type":"Point"}
}