{
  "type": "Feature",
  "properties": {
    "addr:full":"3412 W National Ave Milwaukee WI 53215",
    "addr:housenumber":"3412",
    "addr:postcode":"53215",
    "addr:street":"W National Ave",
    "iso:country":"US",
    "sg:address":"3412 W National Ave",
    "sg:city":"Milwaukee",
    "sg:classifiers":[
        {
            "category":"Bars & Pubs",
            "type":"Food & Drink"
        }
    ],
    "sg:phone":"+1 414 647 9993",
    "sg:postcode":"53215",
    "sg:province":"WI",
    "wof:name":"Gene's Unicorn II",
    "wof:placetype":"venue"
},
  "geometry": {"coordinates":[-87.957587,43.021695],"type":"Point"}
}