{
  "type": "Feature",
  "properties": {
    "iso:country":"US",
    "sg:address":"1353 S 56th St",
    "sg:city":"Milwaukee",
    "sg:classifiers":[
        {
            "category":"Shopping",
            "subcategory":"Books",
            "type":"Retail Goods"
        }
    ],
    "sg:phone":"+1 414 443 0963",
    "sg:postcode":"53214",
    "sg:province":"WI",
    "wof:name":"Neptune Comics",
    "wof:placetype":"venue"
},
  "geometry": {"coordinates":[-87.982668,43.017611],"type":"Point"}
}