{
  "type": "Feature",
  "properties": {
    "iso:country":"US",
    "sg:address":"1005 Main St",
    "sg:city":"Mukwonago",
    "sg:classifiers":[
        {
            "category":"Restaurant",
            "type":"Food & Drink"
        }
    ],
    "sg:phone":"+1 262 363 0984",
    "sg:postcode":"53149",
    "sg:province":"WI",
    "sg:tags":[
        "shop",
        "coffee"
    ],
    "wof:name":"Kona Cafe",
    "wof:placetype":"venue"
},
  "geometry": {"coordinates":[-88.332659,42.855187],"type":"Point"}
}