{
  "type": "Feature",
  "properties": {
    "iso:country":"US",
    "sg:address":"4035 W Earthrock Rd",
    "sg:city":"Appleton",
    "sg:classifiers":[
        {
            "category":"Professional",
            "subcategory":"Computer Services",
            "type":"Services"
        }
    ],
    "sg:phone":"+1 920 954 1224",
    "sg:postcode":"54913",
    "sg:province":"WI",
    "sg:tags":[
        "datum"
    ],
    "wof:name":"Earthrock Digital",
    "wof:placetype":"venue"
},
  "geometry": {"coordinates":[-88.46841000000001,44.328158],"type":"Point"}
}