{
  "type": "Feature",
  "properties": {
    "iso:country":"US",
    "sg:address":"920 10th St E",
    "sg:city":"Menomonie",
    "sg:classifiers":[
        {
            "category":"Manufacturing",
            "subcategory":"Retail Goods",
            "type":"Manufacturing & Wholesale Goods"
        }
    ],
    "sg:phone":"+1 715 232 9197",
    "sg:postcode":"54751",
    "sg:province":"WI",
    "sg:tags":[
        "product",
        "mfg"
    ],
    "wof:name":"Specially Mfg of Menomonie LL",
    "wof:placetype":"venue"
},
  "geometry": {"coordinates":[-91.91814599999999,44.874394],"type":"Point"}
}