{
  "type": "Feature",
  "properties": {
    "addr:full":"3824 Deerfield Rd Deerfield WI 53531",
    "addr:housenumber":"3824",
    "addr:postcode":"53531",
    "addr:street":"Deerfield Rd",
    "iso:country":"US",
    "sg:address":"3824 Deerfield Rd",
    "sg:city":"Deerfield",
    "sg:classifiers":[
        {
            "category":"Farming",
            "subcategory":"Farm",
            "type":"Manufacturing & Wholesale Goods"
        }
    ],
    "sg:phone":"+1 608 764 8553",
    "sg:postcode":"53531",
    "sg:province":"WI",
    "sg:tags":[
        "crop",
        "general"
    ],
    "wof:name":"Larry Boley",
    "wof:placetype":"venue"
},
  "geometry": {"coordinates":[-89.130595,43.059815],"type":"Point"}
}