{
  "type": "Feature",
  "properties": {
    "addr:full":"1713 Menomonie St Eau Claire WI 54703",
    "addr:postcode":"1713;54703",
    "addr:street":"Menomonie St",
    "iso:country":"US",
    "sg:address":"1713 Menomonie St",
    "sg:city":"Eau Claire",
    "sg:classifiers":[
        {
            "category":"Taxi",
            "type":"Transportation"
        }
    ],
    "sg:phone":"+1 715 835 6220",
    "sg:postcode":"54703",
    "sg:province":"WI",
    "sg:tags":[
        "taxicab"
    ],
    "wof:name":"Pope's Cab",
    "wof:placetype":"venue"
},
  "geometry": {"coordinates":[-91.536181,44.798898],"type":"Point"}
}