{
  "type": "Feature",
  "properties": {
    "iso:country":"US",
    "sg:address":"234 Park Ln",
    "sg:city":"Clintonville",
    "sg:classifiers":[
        {
            "category":"Professional",
            "subcategory":"Accounting & Tax Preparation",
            "type":"Services"
        }
    ],
    "sg:phone":"+1 715 823 6186",
    "sg:postcode":"54929",
    "sg:province":"WI",
    "sg:tags":[
        "return"
    ],
    "wof:name":"Sand Hill Tax & Accountin",
    "wof:placetype":"venue"
},
  "geometry": {"coordinates":[-88.775591,44.623899],"type":"Point"}
}