{
  "type": "Feature",
  "properties": {
    "iso:country":"US",
    "sg:address":"8866 Co Rd D",
    "sg:city":"Kewaskum",
    "sg:classifiers":[
        {
            "category":"Building & Trades",
            "subcategory":"Construction",
            "type":"Services"
        }
    ],
    "sg:phone":"+1 262 626 4143",
    "sg:postcode":"53040",
    "sg:province":"WI",
    "sg:tags":[
        "floor",
        "laying",
        "contractor"
    ],
    "wof:name":"Voge John",
    "wof:placetype":"venue"
},
  "geometry": {"coordinates":[-88.134004,43.557359],"type":"Point"}
}