{
  "type": "Feature",
  "properties": {
    "iso:country":"US",
    "sg:address":"745 S Layton Blvd",
    "sg:city":"Milwaukee",
    "sg:classifiers":[
        {
            "category":"Utilities",
            "subcategory":"Mobile Phone",
            "type":"Services"
        },
        {
            "category":"Shopping",
            "subcategory":"Mobile Phones",
            "type":"Retail Goods"
        }
    ],
    "sg:phone":"+1 414 643 1930",
    "sg:postcode":"53215",
    "sg:province":"WI",
    "sg:tags":[
        "supply",
        "communication",
        "telephone",
        "wireless",
        "equipment",
        "cellular"
    ],
    "sg:website":"http://www.mycricket.com",
    "wof:name":"Cricket Wireless - Mitchell Park",
    "wof:placetype":"venue"
},
  "geometry": {"coordinates":[-87.947866,43.023712],"type":"Point"}
}