{
  "type": "Feature",
  "properties": {
    "iso:country":"US",
    "sg:address":"1590 Van Ess Rd",
    "sg:city":"New Franken",
    "sg:classifiers":[
        {
            "category":"Wholesale",
            "subcategory":"Machinery & Supplies",
            "type":"Manufacturing & Wholesale Goods"
        }
    ],
    "sg:phone":"+1 920 866 9111",
    "sg:postcode":"54229",
    "sg:province":"WI",
    "sg:tags":[
        "tool"
    ],
    "wof:name":"E-Z Lift Power Tool Co",
    "wof:placetype":"venue"
},
  "geometry": {"coordinates":[-87.866443,44.518523],"type":"Point"}
}