{
  "type": "Feature",
  "properties": {
    "addr:full":"4935 Mantz Huntersview Richfield WI 53076",
    "addr:housenumber":"4935",
    "addr:postcode":"53076",
    "addr:street":"Mantz Huntersview",
    "iso:country":"US",
    "sg:address":"4935 Mantz Huntersview",
    "sg:city":"Richfield",
    "sg:classifiers":[
        {
            "category":"Professional",
            "subcategory":"Management & Consulting",
            "type":"Services"
        }
    ],
    "sg:phone":"+1 262 644 1705",
    "sg:postcode":"53076",
    "sg:province":"WI",
    "sg:tags":[
        "marketing",
        "manufacturing"
    ],
    "wof:name":"Sportsflaps Inc",
    "wof:placetype":"venue"
},
  "geometry": {"coordinates":[-88.28239499999999,43.282086],"type":"Point"}
}