{
  "type": "Feature",
  "properties": {
    "addr:full":"8201 Plaza Dr Madison WI 53719",
    "addr:housenumber":"8201",
    "addr:postcode":"53719",
    "addr:street":"Plaza Dr",
    "iso:country":"US",
    "sg:address":"8201 Plaza Dr",
    "sg:city":"Madison",
    "sg:classifiers":[
        {
            "category":"Personal",
            "type":"Services"
        }
    ],
    "sg:phone":"+1 608 833 3069",
    "sg:postcode":"53719",
    "sg:province":"WI",
    "sg:tags":[
        "program",
        "physical",
        "exercise",
        "fitness"
    ],
    "wof:name":"Cortland Commons Apartments",
    "wof:placetype":"venue"
},
  "geometry": {"coordinates":[-89.522876,43.056681],"type":"Point"}
}