{
  "type": "Feature",
  "properties": {
    "iso:country":"US",
    "sg:address":"8210 Co Rd F",
    "sg:city":"Ixonia",
    "sg:classifiers":[
        {
            "category":"Communications",
            "subcategory":"Radio Station",
            "type":"Services"
        }
    ],
    "sg:phone":"+1 920 261 6938",
    "sg:postcode":"53036",
    "sg:province":"WI",
    "sg:tags":[
        "broadcast"
    ],
    "wof:name":"Enron",
    "wof:placetype":"venue"
},
  "geometry": {"coordinates":[-88.592197,43.142943],"type":"Point"}
}