{
  "type": "Feature",
  "properties": {
    "iso:country":"US",
    "sg:address":"305 W Bridge St",
    "sg:city":"Wausau",
    "sg:classifiers":[
        {
            "category":"Wholesale",
            "subcategory":"Groceries",
            "type":"Manufacturing & Wholesale Goods"
        }
    ],
    "sg:phone":"+1 715 845 1449",
    "sg:postcode":"54401",
    "sg:province":"WI",
    "sg:tags":[
        "baker"
    ],
    "wof:name":"Gardner Baking",
    "wof:placetype":"venue"
},
  "geometry": {"coordinates":[-89.640318,44.969965],"type":"Point"}
}