{
  "type": "Feature",
  "properties": {
    "iso:country":"US",
    "sg:address":"1014 19th St S",
    "sg:city":"La Crosse",
    "sg:classifiers":[
        {
            "category":"Restaurant",
            "type":"Food & Drink"
        }
    ],
    "sg:phone":"+1 608 784 8487",
    "sg:postcode":"54601",
    "sg:province":"WI",
    "sg:tags":[
        "shop",
        "coffee",
        "eating"
    ],
    "sg:website":"www.jacksonplaza.com",
    "wof:name":"A J's Java Joint",
    "wof:placetype":"venue"
},
  "geometry": {"coordinates":[-91.228379,43.800114],"type":"Point"}
}