{
  "type": "Feature",
  "properties": {
    "iso:country":"US",
    "sg:address":"20985 Watertown Rd",
    "sg:city":"Waukesha",
    "sg:classifiers":[
        {
            "category":"Building & Trades",
            "subcategory":"Construction",
            "type":"Services"
        }
    ],
    "sg:phone":"+1 262 524 0924",
    "sg:postcode":"53186",
    "sg:province":"WI",
    "sg:tags":[
        "dry wall",
        "contractor"
    ],
    "wof:name":"Jerry Burak Plastering Drywall",
    "wof:placetype":"venue"
},
  "geometry": {"coordinates":[-88.174471,43.040372],"type":"Point"}
}