{
  "type": "Feature",
  "properties": {
    "iso:country":"US",
    "sg:address":"17 E 12th St",
    "sg:city":"Clintonville",
    "sg:classifiers":[
        {
            "category":"Personal",
            "subcategory":"Beauty Salon",
            "type":"Services"
        }
    ],
    "sg:phone":"+1 715 823 8485",
    "sg:postcode":"54929",
    "sg:province":"WI",
    "sg:tags":[
        "shop"
    ],
    "wof:name":"House Of Creations",
    "wof:placetype":"venue"
},
  "geometry": {"coordinates":[-88.758892,44.622634],"type":"Point"}
}