{
  "type": "Feature",
  "properties": {
    "iso:country":"US",
    "sg:address":"935 Brighton Dr",
    "sg:city":"Menasha",
    "sg:classifiers":[
        {
            "category":"Professional",
            "subcategory":"Management & Consulting",
            "type":"Services"
        }
    ],
    "sg:phone":"+1 920 751 9203",
    "sg:postcode":"54952",
    "sg:province":"WI",
    "wof:name":"Persona Inc",
    "wof:placetype":"venue"
},
  "geometry": {"coordinates":[-88.420992,44.2031],"type":"Point"}
}