{
  "type": "Feature",
  "properties": {
    "iso:country":"US",
    "sg:address":"2077 Lawrence Dr",
    "sg:city":"De Pere",
    "sg:classifiers":[
        {
            "category":"Insurance",
            "subcategory":"Insurance Agent",
            "type":"Services"
        }
    ],
    "sg:phone":"+1 920 338 3000",
    "sg:postcode":"54115",
    "sg:province":"WI",
    "sg:website":"www.haack.com",
    "wof:name":"Frank F Haack & Assoc",
    "wof:placetype":"venue"
},
  "geometry": {"coordinates":[-88.106773,44.431118],"type":"Point"}
}