{
  "type": "Feature",
  "properties": {
    "iso:country":"US",
    "sg:address":"1610 N Wisconsin St",
    "sg:city":"Port Washington",
    "sg:classifiers":[
        {
            "category":"Retail",
            "subcategory":"Auto Repair",
            "type":"Services"
        }
    ],
    "sg:phone":"+1 262 268 0923",
    "sg:postcode":"53074",
    "sg:province":"WI",
    "sg:tags":[
        "repairing",
        "automotive",
        "automobile"
    ],
    "wof:name":"Kwiky Lube Plus Inc",
    "wof:placetype":"venue"
},
  "geometry": {"coordinates":[-87.871725,43.407068],"type":"Point"}
}