{
  "type": "Feature",
  "properties": {
    "iso:country":"US",
    "sg:address":"3211 London Rd",
    "sg:city":"Eau Claire",
    "sg:classifiers":[
        {
            "category":"Wholesale",
            "subcategory":"Auto Parts",
            "type":"Manufacturing & Wholesale Goods"
        }
    ],
    "sg:phone":"+1 715 836 0121",
    "sg:postcode":"54701",
    "sg:province":"WI",
    "sg:tags":[
        "supply"
    ],
    "wof:name":"Eau Claire Bumper To Bumper",
    "wof:placetype":"venue"
},
  "geometry": {"coordinates":[-91.463095,44.788404],"type":"Point"}
}