{
  "type": "Feature",
  "properties": {
    "iso:country":"US",
    "sg:address":"120 W Johnson St",
    "sg:city":"Madison",
    "sg:classifiers":[
        {
            "category":"Organizations",
            "subcategory":"Religious Organization",
            "type":"Services"
        }
    ],
    "sg:phone":"+1 608 255 1658",
    "sg:postcode":"53703",
    "sg:province":"WI",
    "wof:name":"Holy Redeemer Inc",
    "wof:placetype":"venue"
},
  "geometry": {"coordinates":[-89.38968,43.075092],"type":"Point"}
}