{
  "type": "Feature",
  "properties": {
    "iso:country":"US",
    "sg:address":"7351 Co Rd P",
    "sg:city":"Muscoda",
    "sg:classifiers":[
        {
            "category":"Freight",
            "type":"Transportation"
        }
    ],
    "sg:phone":"+1 608 739 3025",
    "sg:postcode":"53573",
    "sg:province":"WI",
    "sg:tags":[
        "hog",
        "beef",
        "trucking",
        "cattle",
        "operator",
        "local",
        "feedlot"
    ],
    "wof:name":"David Hach Trucking",
    "wof:placetype":"venue"
},
  "geometry": {"coordinates":[-90.423983,43.177486],"type":"Point"}
}