{
  "type": "Feature",
  "properties": {
    "iso:country":"US",
    "sg:address":"552 Challenger Dr",
    "sg:city":"Green Bay",
    "sg:classifiers":[
        {
            "category":"Building & Trades",
            "subcategory":"Construction",
            "type":"Services"
        }
    ],
    "sg:phone":"+1 920 468 4312",
    "sg:postcode":"54311",
    "sg:province":"WI",
    "sg:tags":[
        "block"
    ],
    "wof:name":"Dahlstrom Construction",
    "wof:placetype":"venue"
},
  "geometry": {"coordinates":[-87.93317,44.489164],"type":"Point"}
}