{
  "type": "Feature",
  "properties": {
    "iso:country":"US",
    "sg:address":"625 Harrison Ave",
    "sg:city":"Beloit",
    "sg:classifiers":[
        {
            "category":"Travel",
            "subcategory":"Hotels & Motels",
            "type":"Entertainment"
        }
    ],
    "sg:phone":"+1 608 362 9534",
    "sg:postcode":"53511",
    "sg:province":"IL",
    "sg:tags":[
        "breakfast",
        "accommodation",
        "bed"
    ],
    "wof:name":"Julius C's B & B",
    "wof:placetype":"venue"
},
  "geometry": {"coordinates":[-89.025392,42.502612],"type":"Point"}
}