{
  "type": "Feature",
  "properties": {
    "addr:full":"226 Spring St Berlin WI 54923",
    "addr:housenumber":"226",
    "addr:postcode":"54923",
    "addr:street":"Spring St",
    "iso:country":"US",
    "sg:address":"226 Spring St",
    "sg:city":"Berlin",
    "sg:classifiers":[
        {
            "category":"Government",
            "subcategory":"Fire Station",
            "type":"Public Place"
        }
    ],
    "sg:phone":"+1 920 000 1111",
    "sg:postcode":"54923",
    "sg:province":"WI",
    "sg:tags":[
        "department"
    ],
    "wof:name":"Berlin Ambulance Svc",
    "wof:placetype":"venue"
},
  "geometry": {"coordinates":[-88.94408799999999,43.964728],"type":"Point"}
}