{
  "type": "Feature",
  "properties": {
    "iso:country":"US",
    "sg:address":"1924 S Oneida St",
    "sg:city":"Appleton",
    "sg:classifiers":[
        {
            "category":"Restaurant",
            "type":"Food & Drink"
        }
    ],
    "sg:menulink":"http://www.allmenus.com/wi/appleton/80001-pizza-hut/menu/",
    "sg:phone":"+1 920 734 8738",
    "sg:postcode":"54915",
    "sg:province":"WI",
    "sg:tags":[
        "american",
        "pizza"
    ],
    "wof:name":"Pizza Hut",
    "wof:placetype":"venue"
},
  "geometry": {"coordinates":[-88.404134,44.245396],"type":"Point"}
}