{
  "type": "Feature",
  "properties": {
    "iso:country":"US",
    "sg:address":"4275 State Hwy 47",
    "sg:city":"Rhinelander",
    "sg:classifiers":[
        {
            "category":"Building & Trades",
            "subcategory":"Landscaping Services",
            "type":"Services"
        }
    ],
    "sg:phone":"+1 715 365 0300",
    "sg:postcode":"54501",
    "sg:province":"WI",
    "sg:tags":[
        "landscape",
        "contractor"
    ],
    "wof:name":"Steinmetz Landscape Design",
    "wof:placetype":"venue"
},
  "geometry": {"coordinates":[-89.46028099999999,45.674454],"type":"Point"}
}