{
  "type": "Feature",
  "properties": {
    "addr:full":"145 E Thomas St Wausau WI 54401",
    "addr:housenumber":"145",
    "addr:postcode":"54401",
    "addr:street":"E Thomas St",
    "iso:country":"US",
    "sg:address":"145 E Thomas St",
    "sg:city":"Wausau",
    "sg:classifiers":[
        {
            "category":"Restaurant",
            "type":"Food & Drink"
        },
        {
            "category":"Ice Cream",
            "type":"Food & Drink"
        }
    ],
    "sg:menulink":"http://www.allmenus.com/wi/wausau/192535-dairy-queen/menu/",
    "sg:phone":"+1 715 845 4744",
    "sg:postcode":"54401",
    "sg:province":"WI",
    "sg:tags":[
        "burger",
        "american",
        "ice",
        "cream"
    ],
    "wof:name":"Dairy Queen",
    "wof:placetype":"venue"
},
  "geometry": {"coordinates":[-89.633888,44.948806],"type":"Point"}
}