{
  "type": "Feature",
  "properties": {
    "iso:country":"US",
    "sg:address":"1800 Highland Dr",
    "sg:city":"Elm Grove",
    "sg:classifiers":[
        {
            "category":"Recreation",
            "type":"Entertainment"
        }
    ],
    "sg:phone":"+1 262 786 7060",
    "sg:postcode":"53122",
    "sg:province":"WI",
    "sg:tags":[
        "club",
        "tennis",
        "court"
    ],
    "sg:website":"www.westernracquetclub.com",
    "wof:name":"Western Racquet Clubhouse",
    "wof:placetype":"venue"
},
  "geometry": {"coordinates":[-88.09645399999999,43.053059],"type":"Point"}
}