{
  "type": "Feature",
  "properties": {
    "iso:country":"US",
    "sg:address":"2701 Riley Rd",
    "sg:city":"Sparta",
    "sg:classifiers":[
        {
            "category":"Retail",
            "subcategory":"Auto Repair",
            "type":"Services"
        }
    ],
    "sg:phone":"+1 608 269 7797",
    "sg:postcode":"54656",
    "sg:province":"WI",
    "sg:tags":[
        "general"
    ],
    "wof:name":"Tri-State Trailer & Rfrgn",
    "wof:placetype":"venue"
},
  "geometry": {"coordinates":[-90.771512,43.940516],"type":"Point"}
}