{
  "type": "Feature",
  "properties": {
    "iso:country":"US",
    "sg:address":"8746 Co Rd Mm",
    "sg:city":"Larsen",
    "sg:classifiers":[
        {
            "category":"Farming",
            "subcategory":"Dairy Farm",
            "type":"Manufacturing & Wholesale Goods"
        }
    ],
    "sg:phone":"+1 920 836 2855",
    "sg:postcode":"54947",
    "sg:province":"WI",
    "wof:name":"Reinert John",
    "wof:placetype":"venue"
},
  "geometry": {"coordinates":[-88.741529,44.204213],"type":"Point"}
}