{
  "type": "Feature",
  "properties": {
    "iso:country":"US",
    "sg:address":"1296 Co Rd K",
    "sg:city":"Sharon",
    "sg:classifiers":[
        {
            "category":"Home & Garden",
            "subcategory":"Garden Supply",
            "type":"Retail Goods"
        }
    ],
    "sg:phone":"+1 262 736 1616",
    "sg:postcode":"53585",
    "sg:province":"WI",
    "sg:tags":[
        "nurseryman"
    ],
    "wof:name":"James Nursery",
    "wof:placetype":"venue"
},
  "geometry": {"coordinates":[-88.678249,42.540422],"type":"Point"}
}