{
  "type": "Feature",
  "properties": {
    "addr:full":"613 Main St Ridgeway WI 53582",
    "addr:housenumber":"613",
    "addr:postcode":"53582",
    "addr:street":"Main St",
    "iso:country":"US",
    "sg:address":"613 Main St",
    "sg:city":"Ridgeway",
    "sg:classifiers":[
        {
            "category":"Government",
            "subcategory":"Post Office",
            "type":"Public Place"
        }
    ],
    "sg:phone":"+1 608 924 6040",
    "sg:postcode":"53582",
    "sg:province":"WI",
    "sg:tags":[
        "postal",
        "us"
    ],
    "wof:name":"US Post Office",
    "wof:placetype":"venue"
},
  "geometry": {"coordinates":[-89.992824,42.999481],"type":"Point"}
}