{
  "type": "Feature",
  "properties": {
    "iso:country":"US",
    "sg:address":"6596 Rose Hill Rd",
    "sg:city":"Black River Fls",
    "sg:classifiers":[
        {
            "category":"Professional",
            "type":"Services"
        }
    ],
    "sg:phone":"+1 715 284 9265",
    "sg:postcode":"54635",
    "sg:province":"WI",
    "sg:tags":[
        "establishment"
    ],
    "wof:name":"Rose Hill Micro-Wave Tower",
    "wof:placetype":"venue"
},
  "geometry": {"coordinates":[-91.00359400000001,44.302237],"type":"Point"}
}