{
  "type": "Feature",
  "properties": {
    "iso:country":"US",
    "sg:address":"820 Summit Ave",
    "sg:city":"Oconomowoc",
    "sg:classifiers":[
        {
            "category":"Health Services",
            "subcategory":"Doctor",
            "type":"Services"
        }
    ],
    "sg:phone":"+1 262 567 4466",
    "sg:postcode":"53066",
    "sg:province":"WI",
    "sg:tags":[
        "dentist"
    ],
    "wof:name":"Leaman Setnicar & Piacsek",
    "wof:placetype":"venue"
},
  "geometry": {"coordinates":[-88.483674,43.099207],"type":"Point"}
}