{
  "type": "Feature",
  "properties": {
    "addr:full":"708 Schuykill Ct De Forest WI 53532",
    "addr:housenumber":"708",
    "addr:postcode":"53532",
    "addr:street":"Schuykill Ct",
    "iso:country":"US",
    "sg:address":"708 Schuykill Ct",
    "sg:city":"De Forest",
    "sg:classifiers":[
        {
            "category":"Building & Trades",
            "subcategory":"Construction",
            "type":"Services"
        }
    ],
    "sg:phone":"+1 608 846 9779",
    "sg:postcode":"53532",
    "sg:province":"WI",
    "sg:tags":[
        "excavation",
        "contractor"
    ],
    "wof:name":"Streamline Excavating LLC",
    "wof:placetype":"venue"
},
  "geometry": {"coordinates":[-89.328621,43.238936],"type":"Point"}
}