{
  "type": "Feature",
  "properties": {
    "iso:country":"US",
    "sg:address":"5085 N 125th St",
    "sg:city":"Butler",
    "sg:classifiers":[
        {
            "category":"Building & Trades",
            "subcategory":"Plumbing",
            "type":"Services"
        }
    ],
    "sg:phone":"+1 262 373 1605",
    "sg:postcode":"53007",
    "sg:province":"WI",
    "sg:tags":[
        "heating",
        "contractor"
    ],
    "wof:name":"Diversified Heating & Cooling",
    "wof:placetype":"venue"
},
  "geometry": {"coordinates":[-88.06720199999999,43.109284],"type":"Point"}
}