{
  "type": "Feature",
  "properties": {
    "iso:country":"US",
    "sg:address":"10324 Larkspur Ln",
    "sg:city":"Germantown",
    "sg:classifiers":[
        {
            "category":"Travel",
            "subcategory":"Travel Agent",
            "type":"Entertainment"
        }
    ],
    "sg:phone":"+1 262 502 9441",
    "sg:postcode":"53022",
    "sg:province":"WI",
    "sg:tags":[
        "agency"
    ],
    "wof:name":"Cruise One",
    "wof:placetype":"venue"
},
  "geometry": {"coordinates":[-88.120498,43.205916],"type":"Point"}
}