{
  "type": "Feature",
  "properties": {
    "iso:country":"US",
    "sg:address":"502 Sacramento St",
    "sg:city":"Berlin",
    "sg:classifiers":[
        {
            "category":"Retail",
            "subcategory":"Auto Repair",
            "type":"Services"
        }
    ],
    "sg:phone":"+1 920 361 3217",
    "sg:postcode":"54923",
    "sg:province":"WI",
    "sg:tags":[
        "general"
    ],
    "wof:name":"J & B Enterprises",
    "wof:placetype":"venue"
},
  "geometry": {"coordinates":[-88.934006,43.977013],"type":"Point"}
}