{
  "type": "Feature",
  "properties": {
    "iso:country":"US",
    "sg:address":"2980 Walker Dr",
    "sg:city":"Green Bay",
    "sg:classifiers":[
        {
            "category":"Wholesale",
            "subcategory":"Computers",
            "type":"Manufacturing & Wholesale Goods"
        }
    ],
    "sg:phone":"+1 920 406 3030",
    "sg:postcode":"54311",
    "sg:province":"WI",
    "sg:tags":[
        "related"
    ],
    "wof:name":"Lake Cos Inc",
    "wof:placetype":"venue"
},
  "geometry": {"coordinates":[-87.931765,44.478589],"type":"Point"}
}