{
  "type": "Feature",
  "properties": {
    "iso:country":"US",
    "sg:address":"9285 Elm Rd",
    "sg:city":"Bancroft",
    "sg:classifiers":[
        {
            "category":"Farming",
            "subcategory":"Livestock Farm",
            "type":"Manufacturing & Wholesale Goods"
        }
    ],
    "sg:phone":"+1 715 335 6584",
    "sg:postcode":"54921",
    "sg:province":"WI",
    "sg:tags":[
        "beef",
        "feedlot",
        "cattle"
    ],
    "wof:name":"Raymond Pichelmann",
    "wof:placetype":"venue"
},
  "geometry": {"coordinates":[-89.589062,44.278036],"type":"Point"}
}