{
  "type": "Feature",
  "properties": {
    "iso:country":"US",
    "sg:address":"20830 75th St",
    "sg:city":"Bristol",
    "sg:classifiers":[
        {
            "category":"Wholesale",
            "subcategory":"Machinery & Supplies",
            "type":"Manufacturing & Wholesale Goods"
        }
    ],
    "sg:phone":"+1 262 857 3306",
    "sg:postcode":"53104",
    "sg:province":"WI",
    "wof:name":"Reinders Inc",
    "wof:placetype":"venue"
},
  "geometry": {"coordinates":[-88.061937,42.568362],"type":"Point"}
}