{
  "type": "Feature",
  "properties": {
    "addr:full":"2358 Lake Nokomis Rd Tomahawk WI 54487",
    "addr:housenumber":"2358",
    "addr:postcode":"54487",
    "addr:street":"Lake Nokomis Rd",
    "iso:country":"US",
    "sg:address":"2358 Lake Nokomis Rd",
    "sg:city":"Tomahawk",
    "sg:classifiers":[
        {
            "category":"Retail",
            "subcategory":"Repair Shop",
            "type":"Services"
        }
    ],
    "sg:phone":"+1 715 453 4198",
    "sg:postcode":"54487",
    "sg:province":"WI",
    "wof:name":"A K Upholsterers",
    "wof:placetype":"venue"
},
  "geometry": {"coordinates":[-89.70827199999999,45.585347],"type":"Point"}
}