{
  "type": "Feature",
  "properties": {
    "iso:country":"US",
    "sg:address":"213 S Adams St",
    "sg:city":"New Lisbon",
    "sg:classifiers":[
        {
            "category":"Autos & Motor Vehicles",
            "subcategory":"Auto Supplies",
            "type":"Retail Goods"
        }
    ],
    "sg:phone":"+1 608 562 3119",
    "sg:postcode":"53950",
    "sg:province":"WI",
    "sg:tags":[
        "repair",
        "general"
    ],
    "wof:name":"Automotive Spclsts Prts & Srvc",
    "wof:placetype":"venue"
},
  "geometry": {"coordinates":[-90.16627699999999,43.87873],"type":"Point"}
}