{
  "type": "Feature",
  "properties": {
    "iso:country":"US",
    "sg:address":"1412 Jefferson St",
    "sg:city":"Oshkosh",
    "sg:classifiers":[
        {
            "category":"Building & Trades",
            "subcategory":"Plumbing",
            "type":"Services"
        }
    ],
    "sg:phone":"+1 920 235 0336",
    "sg:postcode":"54901",
    "sg:province":"WI",
    "sg:tags":[
        "refrigeration",
        "contractor"
    ],
    "wof:name":"A & H Refrigeration",
    "wof:placetype":"venue"
},
  "geometry": {"coordinates":[-88.53629599999999,44.035661],"type":"Point"}
}