{
  "type": "Feature",
  "properties": {
    "addr:full":"519 Briody St Burlington WI 53105",
    "addr:housenumber":"519",
    "addr:postcode":"53105",
    "addr:street":"Briody St",
    "iso:country":"US",
    "sg:address":"519 Briody St",
    "sg:city":"Burlington",
    "sg:classifiers":[
        {
            "category":"Insurance",
            "subcategory":"Insurance Agent",
            "type":"Services"
        }
    ],
    "sg:phone":"+1 262 763 2211",
    "sg:postcode":"53105",
    "sg:province":"WI",
    "wof:name":"Primerica",
    "wof:placetype":"venue"
},
  "geometry": {"coordinates":[-88.288709,42.681778],"type":"Point"}
}