{
  "type": "Feature",
  "properties": {
    "addr:full":"1101 S 41st St Milwaukee WI 53215",
    "addr:housenumber":"1101",
    "addr:postcode":"53215",
    "addr:street":"S 41St St",
    "iso:country":"US",
    "sg:address":"1101 S 41st St",
    "sg:city":"Milwaukee",
    "sg:classifiers":[
        {
            "category":"Building & Trades",
            "subcategory":"Plumbing",
            "type":"Services"
        }
    ],
    "sg:phone":"+1 414 645 0068",
    "sg:postcode":"53215",
    "sg:province":"WI",
    "sg:tags":[
        "clean",
        "boilers-repair"
    ],
    "wof:name":"Milwaukee Boiler International",
    "wof:placetype":"venue"
},
  "geometry": {"coordinates":[-87.964752,43.019507],"type":"Point"}
}