{
  "type": "Feature",
  "properties": {
    "iso:country":"US",
    "sg:address":"2626 Memorial Dr",
    "sg:city":"Two Rivers",
    "sg:classifiers":[
        {
            "category":"Autos & Motor Vehicles",
            "subcategory":"Fuel & Gas Station",
            "type":"Retail Goods"
        }
    ],
    "sg:phone":"+1 920 793 8823",
    "sg:postcode":"54241",
    "sg:province":"WI",
    "sg:tags":[
        "oil"
    ],
    "wof:name":"Citgo Express Mart",
    "wof:placetype":"venue"
},
  "geometry": {"coordinates":[-87.587028,44.137348],"type":"Point"}
}