{
  "type": "Feature",
  "properties": {
    "iso:country":"US",
    "sg:address":"4816 Co Rd B",
    "sg:city":"New London",
    "sg:classifiers":[
        {
            "category":"Building & Trades",
            "subcategory":"Construction",
            "type":"Services"
        }
    ],
    "sg:phone":"+1 920 596 2357",
    "sg:postcode":"54961",
    "sg:province":"WI",
    "sg:tags":[
        "concrete",
        "contractor"
    ],
    "wof:name":"D C Masonry",
    "wof:placetype":"venue"
},
  "geometry": {"coordinates":[-88.89768100000001,44.421234],"type":"Point"}
}