{
  "type": "Feature",
  "properties": {
    "iso:country":"US",
    "sg:address":"7200 Washington Ave",
    "sg:city":"Racine",
    "sg:classifiers":[
        {
            "category":"Professional",
            "type":"Services"
        }
    ],
    "sg:phone":"+1 262 321 0100",
    "sg:postcode":"53406",
    "sg:province":"WI",
    "sg:tags":[
        "establishment"
    ],
    "wof:name":"Dermovation",
    "wof:placetype":"venue"
},
  "geometry": {"coordinates":[-87.869969,42.719422],"type":"Point"}
}