{
  "type": "Feature",
  "properties": {
    "iso:country":"US",
    "sg:address":"1618 Summit Dr",
    "sg:city":"Fort Atkinson",
    "sg:classifiers":[
        {
            "category":"Freight",
            "type":"Transportation"
        }
    ],
    "sg:phone":"+1 920 563 6999",
    "sg:postcode":"53538",
    "sg:province":"WI",
    "sg:tags":[
        "trucking"
    ],
    "wof:name":"Distribution Svc Inc",
    "wof:placetype":"venue"
},
  "geometry": {"coordinates":[-88.850584,42.904693],"type":"Point"}
}