{
  "type": "Feature",
  "properties": {
    "addr:full":"1313 W 2nd St Oconomowoc WI 53066",
    "addr:housenumber":"1313",
    "addr:postcode":"53066",
    "addr:street":"W 2Nd St",
    "iso:country":"US",
    "sg:address":"1313 W 2nd St",
    "sg:city":"Oconomowoc",
    "sg:classifiers":[
        {
            "category":"Building & Trades",
            "subcategory":"Construction",
            "type":"Services"
        }
    ],
    "sg:phone":"+1 262 567 5933",
    "sg:postcode":"53066",
    "sg:province":"WI",
    "sg:tags":[
        "contractor"
    ],
    "wof:name":"Vern Ebben Construction Inc",
    "wof:placetype":"venue"
},
  "geometry": {"coordinates":[-88.517098,43.111716],"type":"Point"}
}