{
  "type": "Feature",
  "properties": {
    "iso:country":"US",
    "sg:address":"3730 Alpine Way",
    "sg:city":"Wisconsin Rapids",
    "sg:classifiers":[
        {
            "category":"Real Estate",
            "subcategory":"Real Estate Agent",
            "type":"Services"
        }
    ],
    "sg:phone":"+1 715 421 1500",
    "sg:postcode":"54494",
    "sg:province":"WI",
    "sg:tags":[
        "inspection"
    ],
    "wof:name":"Complete Home Inspection Svc",
    "wof:placetype":"venue"
},
  "geometry": {"coordinates":[-89.77948000000001,44.347295],"type":"Point"}
}