{
  "type": "Feature",
  "properties": {
    "addr:full":"614 E Division St Dodgeville WI 53533",
    "addr:housenumber":"614",
    "addr:postcode":"53533",
    "addr:street":"E Division St",
    "iso:country":"US",
    "sg:address":"614 E Division St",
    "sg:city":"Dodgeville",
    "sg:classifiers":[
        {
            "category":"Building & Trades",
            "subcategory":"Construction",
            "type":"Services"
        }
    ],
    "sg:phone":"+1 608 935 2512",
    "sg:postcode":"53533",
    "sg:province":"WI",
    "sg:tags":[
        "house"
    ],
    "wof:name":"C L Anderson Construction",
    "wof:placetype":"venue"
},
  "geometry": {"coordinates":[-90.116992,42.960007],"type":"Point"}
}