{
  "type": "Feature",
  "properties": {
    "iso:country":"US",
    "sg:address":"3100 N 78th St",
    "sg:city":"Milwaukee",
    "sg:classifiers":[
        {
            "category":"Professional",
            "type":"Services"
        }
    ],
    "sg:phone":"+1 414 873 8220",
    "sg:postcode":"53222",
    "sg:province":"WI",
    "sg:tags":[
        "establishment"
    ],
    "wof:name":"Chudecke & Assoc",
    "wof:placetype":"venue"
},
  "geometry": {"coordinates":[-88.00985300000001,43.0769],"type":"Point"}
}