{
  "type": "Feature",
  "properties": {
    "iso:country":"US",
    "sg:address":"5764 Durand Ave",
    "sg:city":"Racine",
    "sg:classifiers":[
        {
            "category":"Food & Beverages",
            "subcategory":"Candy",
            "type":"Retail Goods"
        }
    ],
    "sg:phone":"+1 262 554 6225",
    "sg:postcode":"53406",
    "sg:province":"WI",
    "wof:name":"Buddy Squirrel Nut Shops",
    "wof:placetype":"venue"
},
  "geometry": {"coordinates":[-87.848788,42.697352],"type":"Point"}
}