{
  "type": "Feature",
  "properties": {
    "addr:full":"1751 N Farwell Ave Milwaukee WI 53202",
    "addr:housenumber":"1751",
    "addr:postcode":"53202",
    "addr:street":"N Farwell Ave",
    "iso:country":"US",
    "sg:address":"1751 N Farwell Ave",
    "sg:city":"Milwaukee",
    "sg:classifiers":[
        {
            "category":"Shopping",
            "subcategory":"Florist",
            "type":"Retail Goods"
        }
    ],
    "sg:phone":"+1 414 271 4341",
    "sg:postcode":"53202",
    "sg:province":"WI",
    "wof:name":"Grandpa Franks",
    "wof:placetype":"venue"
},
  "geometry": {"coordinates":[-87.89181000000001,43.053487],"type":"Point"}
}