{
  "type": "Feature",
  "properties": {
    "iso:country":"US",
    "sg:address":"3319 N 90th St",
    "sg:city":"Milwaukee",
    "sg:classifiers":[
        {
            "category":"Real Estate",
            "subcategory":"Real Estate Agent",
            "type":"Services"
        }
    ],
    "sg:phone":"+1 414 445 2442",
    "sg:postcode":"53222",
    "sg:province":"WI",
    "wof:name":"KSG Properties",
    "wof:placetype":"venue"
},
  "geometry": {"coordinates":[-88.025183,43.080263],"type":"Point"}
}