{
  "type": "Feature",
  "properties": {
    "addr:full":"2801 S 71st St Milwaukee WI 53219",
    "addr:housenumber":"2801",
    "addr:postcode":"53219",
    "addr:street":"S 71St St",
    "iso:country":"US",
    "sg:address":"2801 S 71st St",
    "sg:city":"Milwaukee",
    "sg:classifiers":[
        {
            "category":"Building & Trades",
            "subcategory":"Construction",
            "type":"Services"
        }
    ],
    "sg:phone":"+1 414 321 9017",
    "sg:postcode":"53219",
    "sg:province":"WI",
    "sg:tags":[
        "house"
    ],
    "wof:name":"Rh Remodeling & Home Repair LL",
    "wof:placetype":"venue"
},
  "geometry": {"coordinates":[-88.00139299999999,42.991941],"type":"Point"}
}