{
  "type": "Feature",
  "properties": {
    "addr:full":"140 Bus Park Cir Stoughton WI 53589",
    "addr:housenumber":"140",
    "addr:postcode":"53589",
    "addr:street":"Bus Park Cir",
    "iso:country":"US",
    "sg:address":"140 Bus Park Cir",
    "sg:city":"Stoughton",
    "sg:classifiers":[
        {
            "category":"Professional",
            "subcategory":"Management & Consulting",
            "type":"Services"
        }
    ],
    "sg:phone":"+1 608 873 1342",
    "sg:postcode":"53589",
    "sg:province":"WI",
    "wof:name":"Paas National Inc",
    "wof:placetype":"venue"
},
  "geometry": {"coordinates":[-89.220332,42.932792],"type":"Point"}
}