{
  "type": "Feature",
  "properties": {
    "iso:country":"US",
    "sg:address":"510 N Adams St",
    "sg:city":"St Croix Falls",
    "sg:classifiers":[
        {
            "category":"Organizations",
            "subcategory":"Religious Organization",
            "type":"Services"
        }
    ],
    "sg:phone":"+1 715 483 3679",
    "sg:postcode":"54024",
    "sg:province":"WI",
    "wof:name":"Christian Alternative Mnstry",
    "wof:placetype":"venue"
},
  "geometry": {"coordinates":[-92.643366,45.419087],"type":"Point"}
}