{
  "type": "Feature",
  "properties": {
    "iso:country":"US",
    "sg:address":"240 E Wisconsin Ave",
    "sg:city":"Neenah",
    "sg:classifiers":[
        {
            "category":"Education",
            "subcategory":"Library",
            "type":"Public Place"
        }
    ],
    "sg:phone":"+1 920 886 6315",
    "sg:postcode":"54956",
    "sg:province":"WI",
    "sg:website":"www.neenahlibrary.org",
    "wof:name":"Neenah Public Library",
    "wof:placetype":"venue"
},
  "geometry": {"coordinates":[-88.45801299999999,44.184882],"type":"Point"}
}