{
  "type": "Feature",
  "properties": {
    "addr:full":"1384 S River Rd Cochrane WI 54622",
    "addr:housenumber":"1384",
    "addr:postcode":"54622",
    "addr:street":"S River Rd",
    "iso:country":"US",
    "sg:address":"1384 S River Rd",
    "sg:city":"Cochrane",
    "sg:classifiers":[
        {
            "category":"Professional",
            "subcategory":"Management & Consulting",
            "type":"Services"
        }
    ],
    "sg:phone":"+1 608 248 2647",
    "sg:postcode":"54622",
    "sg:province":"WI",
    "sg:tags":[
        "business"
    ],
    "wof:name":"Multifactor Management Inc",
    "wof:placetype":"venue"
},
  "geometry": {"coordinates":[-91.82392900000001,44.177379],"type":"Point"}
}