{
  "type": "Feature",
  "properties": {
    "iso:country":"US",
    "sg:address":"4935 19th Ave",
    "sg:city":"Montello",
    "sg:classifiers":[
        {
            "category":"Food & Beverages",
            "subcategory":"Meat & Fish",
            "type":"Retail Goods"
        }
    ],
    "sg:phone":"+1 608 297 2722",
    "sg:postcode":"53949",
    "sg:province":"WI",
    "wof:name":"J M Wildt & Sons Inc",
    "wof:placetype":"venue"
},
  "geometry": {"coordinates":[-89.246556,43.815793],"type":"Point"}
}