{
  "type": "Feature",
  "properties": {
    "iso:country":"US",
    "sg:address":"2674 Ryan Rd",
    "sg:city":"De Pere",
    "sg:classifiers":[
        {
            "category":"Building & Trades",
            "subcategory":"Landscaping Services",
            "type":"Services"
        }
    ],
    "sg:phone":"+1 920 336 5075",
    "sg:postcode":"54115",
    "sg:province":"WI",
    "sg:tags":[
        "landscape",
        "contractor"
    ],
    "wof:name":"Rockland Ridge Enterprises",
    "wof:placetype":"venue"
},
  "geometry": {"coordinates":[-88.06486,44.414973],"type":"Point"}
}