{
  "type": "Feature",
  "properties": {
    "addr:full":"645 Hospital Rd New Richmond WI 54017",
    "addr:housenumber":"645",
    "addr:postcode":"54017",
    "addr:street":"Hospital Rd",
    "iso:country":"US",
    "sg:address":"645 Hospital Rd",
    "sg:city":"New Richmond",
    "sg:classifiers":[
        {
            "category":"Health Services",
            "subcategory":"Doctor",
            "type":"Services"
        }
    ],
    "sg:phone":"+1 715 246 2111",
    "sg:postcode":"54017",
    "sg:province":"WI",
    "sg:tags":[
        "dentist"
    ],
    "wof:name":"Midwest Dental Office",
    "wof:placetype":"venue"
},
  "geometry": {"coordinates":[-92.55329399999999,45.11609],"type":"Point"}
}