{
  "type": "Feature",
  "properties": {
    "iso:country":"US",
    "sg:address":"6328 Main St",
    "sg:city":"Arpin",
    "sg:classifiers":[
        {
            "category":"Bars & Pubs",
            "type":"Food & Drink"
        }
    ],
    "sg:phone":"+1 715 652 6525",
    "sg:postcode":"54410",
    "sg:province":"WI",
    "wof:name":"Dupe's Bar",
    "wof:placetype":"venue"
},
  "geometry": {"coordinates":[-90.03782699999999,44.540737],"type":"Point"}
}