{
  "type": "Feature",
  "properties": {
    "iso:country":"US",
    "sg:address":"4583 Pip Ln",
    "sg:city":"Oshkosh",
    "sg:classifiers":[
        {
            "category":"Building & Trades",
            "subcategory":"Electrical",
            "type":"Services"
        },
        {
            "category":"Wholesale",
            "subcategory":"Electrical",
            "type":"Manufacturing & Wholesale Goods"
        }
    ],
    "sg:phone":"+1 920 235 6423",
    "sg:postcode":"54904",
    "sg:province":"WI",
    "sg:tags":[
        "installation",
        "communications",
        "communication",
        "system",
        "contractor",
        "equipment",
        "radio"
    ],
    "wof:name":"Pipkorn's Of Oshkosh Inc",
    "wof:placetype":"venue"
},
  "geometry": {"coordinates":[-88.576774,44.08368],"type":"Point"}
}