{
  "type": "Feature",
  "properties": {
    "iso:country":"US",
    "sg:address":"111 Worden Ave W",
    "sg:city":"Ladysmith",
    "sg:classifiers":[
        {
            "category":"Bars & Pubs",
            "type":"Food & Drink"
        }
    ],
    "sg:phone":"+1 715 532 5038",
    "sg:postcode":"54848",
    "sg:province":"WI",
    "sg:tags":[
        "drinking"
    ],
    "wof:name":"Sports Page",
    "wof:placetype":"venue"
},
  "geometry": {"coordinates":[-91.102005,45.463355],"type":"Point"}
}