{
  "type": "Feature",
  "properties": {
    "iso:country":"US",
    "sg:address":"22925 Co Hwy Q",
    "sg:city":"Richland Center",
    "sg:classifiers":[
        {
            "category":"Farming",
            "subcategory":"Dairy Farm",
            "type":"Manufacturing & Wholesale Goods"
        }
    ],
    "sg:phone":"+1 608 647 6276",
    "sg:postcode":"53581",
    "sg:province":"WI",
    "wof:name":"Monica M Deaver",
    "wof:placetype":"venue"
},
  "geometry": {"coordinates":[-90.41369,43.332134],"type":"Point"}
}