{
  "type": "Feature",
  "properties": {
    "iso:country":"US",
    "sg:address":"275 Kinzie Ave",
    "sg:city":"Fontana",
    "sg:classifiers":[
        {
            "category":"Organizations",
            "subcategory":"Religious Organization",
            "type":"Services"
        }
    ],
    "sg:phone":"+1 262 275 2808",
    "sg:postcode":"53125",
    "sg:province":"WI",
    "sg:tags":[
        "church"
    ],
    "wof:name":"Fontana Community Church",
    "wof:placetype":"venue"
},
  "geometry": {"coordinates":[-88.575591,42.551294],"type":"Point"}
}