{
  "type": "Feature",
  "properties": {
    "iso:country":"US",
    "sg:address":"1701 Franklin St",
    "sg:city":"Stevens Point",
    "sg:classifiers":[
        {
            "category":"Government",
            "subcategory":"Fire Station",
            "type":"Public Place"
        }
    ],
    "sg:phone":"+1 715 344 1833",
    "sg:postcode":"54481",
    "sg:province":"WI",
    "sg:tags":[
        "department"
    ],
    "wof:name":"Stevens Point Fire Department",
    "wof:placetype":"venue"
},
  "geometry": {"coordinates":[-89.573492,44.527111],"type":"Point"}
}