{
  "type": "Feature",
  "properties": {
    "iso:country":"US",
    "sg:address":"9703 Old 151 Rd",
    "sg:city":"Manitowoc",
    "sg:classifiers":[
        {
            "category":"Building & Trades",
            "subcategory":"Construction",
            "type":"Services"
        }
    ],
    "sg:phone":"+1 920 758 2221",
    "sg:postcode":"54220",
    "sg:province":"WI",
    "sg:tags":[
        "floor",
        "laying",
        "contractor"
    ],
    "wof:name":"Dl Services",
    "wof:placetype":"venue"
},
  "geometry": {"coordinates":[-87.799807,44.073345],"type":"Point"}
}