{
  "type": "Feature",
  "properties": {
    "iso:country":"US",
    "sg:address":"6242 Jones Rd",
    "sg:city":"Burlington",
    "sg:classifiers":[
        {
            "category":"Organizations",
            "subcategory":"Professional Association",
            "type":"Services"
        }
    ],
    "sg:phone":"+1 262 248 8965",
    "sg:postcode":"53105",
    "sg:province":"WI",
    "wof:name":"International Reading Assn",
    "wof:placetype":"venue"
},
  "geometry": {"coordinates":[-88.367592,42.623535],"type":"Point"}
}