{
  "type": "Feature",
  "properties": {
    "addr:full":"37 Old Shore Rd Madison WI 53704",
    "addr:housenumber":"37",
    "addr:postcode":"53704",
    "addr:street":"Old Shore Rd",
    "iso:country":"US",
    "sg:address":"37 Old Shore Rd",
    "sg:city":"Madison",
    "sg:classifiers":[
        {
            "category":"Professional",
            "subcategory":"Management & Consulting",
            "type":"Services"
        }
    ],
    "sg:phone":"+1 608 249 3610",
    "sg:postcode":"53704",
    "sg:province":"WI",
    "wof:name":"Stratton Gilmore Group",
    "wof:placetype":"venue"
},
  "geometry": {"coordinates":[-89.36554599999999,43.103412],"type":"Point"}
}