{
  "type": "Feature",
  "properties": {
    "iso:country":"US",
    "sg:address":"5723 189th St",
    "sg:city":"Chippewa Falls",
    "sg:classifiers":[
        {
            "category":"Building & Trades",
            "subcategory":"Construction",
            "type":"Services"
        }
    ],
    "sg:phone":"+1 715 723 7424",
    "sg:postcode":"54729",
    "sg:province":"WI",
    "sg:tags":[
        "utility",
        "contractor"
    ],
    "wof:name":"WIS Tele-Cable Construction Co",
    "wof:placetype":"venue"
},
  "geometry": {"coordinates":[-91.28972400000001,44.926022],"type":"Point"}
}