{
  "type": "Feature",
  "properties": {
    "iso:country":"US",
    "sg:address":"138 E Main St",
    "sg:city":"Mount Horeb",
    "sg:classifiers":[
        {
            "category":"Utilities",
            "subcategory":"Sewage",
            "type":"Services"
        }
    ],
    "sg:phone":"+1 608 437 3101",
    "sg:postcode":"53572",
    "sg:province":"WI",
    "sg:tags":[
        "system",
        "sewerage"
    ],
    "wof:name":"Sewage Treatment Plant",
    "wof:placetype":"venue"
},
  "geometry": {"coordinates":[-89.739328,43.008734],"type":"Point"}
}