{
  "type": "Feature",
  "properties": {
    "iso:country":"US",
    "sg:address":"7900 Highland Dr",
    "sg:city":"Wausau",
    "sg:classifiers":[
        {
            "category":"Wholesale",
            "subcategory":"Electrical",
            "type":"Manufacturing & Wholesale Goods"
        }
    ],
    "sg:phone":"+1 715 845 8808",
    "sg:postcode":"54401",
    "sg:province":"WI",
    "sg:tags":[
        "equipment",
        "electric",
        "supply"
    ],
    "sg:website":"www.wernerelectric.com",
    "wof:name":"Werner Electric Supply Co",
    "wof:placetype":"venue"
},
  "geometry": {"coordinates":[-89.73333,44.958673],"type":"Point"}
}