{
  "type": "Feature",
  "properties": {
    "iso:country":"US",
    "sg:address":"2300 E John St",
    "sg:city":"Appleton",
    "sg:classifiers":[
        {
            "category":"Freight",
            "type":"Transportation"
        }
    ],
    "sg:phone":"+1 920 733 8629",
    "sg:postcode":"54915",
    "sg:province":"WI",
    "sg:tags":[
        "general"
    ],
    "wof:name":"8th Street Storage LLC",
    "wof:placetype":"venue"
},
  "geometry": {"coordinates":[-88.37110199999999,44.247932],"type":"Point"}
}