{
  "type": "Feature",
  "properties": {
    "iso:country":"US",
    "sg:address":"5600 Pepperbush Ln",
    "sg:city":"Wausau",
    "sg:classifiers":[
        {
            "category":"Bus Charters",
            "type":"Transportation"
        }
    ],
    "sg:phone":"+1 715 355 9668",
    "sg:postcode":"54401",
    "sg:province":"WI",
    "wof:name":"City To City Charter",
    "wof:placetype":"venue"
},
  "geometry": {"coordinates":[-89.70519299999999,44.886517],"type":"Point"}
}