{
  "type": "Feature",
  "properties": {
    "addr:full":"5089 Washington St Butte Des Morts WI 54904",
    "addr:housenumber":"5089",
    "addr:postcode":"54904",
    "addr:street":"Washington St",
    "iso:country":"US",
    "sg:address":"5089 Washington St",
    "sg:city":"Butte Des Morts",
    "sg:classifiers":[
        {
            "category":"Real Estate",
            "subcategory":"Real Estate Agent",
            "type":"Services"
        }
    ],
    "sg:phone":"+1 920 582 4330",
    "sg:postcode":"54904",
    "sg:province":"WI",
    "wof:name":"Kontos Real Estate & Appraisal",
    "wof:placetype":"venue"
},
  "geometry": {"coordinates":[-88.65216599999999,44.099577],"type":"Point"}
}