{
  "type": "Feature",
  "properties": {
    "addr:full":"336 Water St Eau Claire WI 54703",
    "addr:housenumber":"336",
    "addr:postcode":"54703",
    "addr:street":"Water St",
    "iso:country":"US",
    "sg:address":"336 Water St",
    "sg:city":"Eau Claire",
    "sg:classifiers":[
        {
            "category":"Shopping",
            "subcategory":"Shoes",
            "type":"Retail Goods"
        }
    ],
    "sg:phone":"+1 715 834 3248",
    "sg:postcode":"54703",
    "sg:province":"WI",
    "sg:tags":[
        "parlor",
        "boot",
        "shoe"
    ],
    "wof:name":"Ralph's Boot & Shoe",
    "wof:placetype":"venue"
},
  "geometry": {"coordinates":[-91.50705499999999,44.80224],"type":"Point"}
}