{
  "type": "Feature",
  "properties": {
    "iso:country":"US",
    "sg:address":"1885 N Rice Lake Rd",
    "sg:city":"Spooner",
    "sg:classifiers":[
        {
            "category":"Travel",
            "subcategory":"Bed & Breakfast",
            "type":"Entertainment"
        }
    ],
    "sg:phone":"+1 715 635 7229",
    "sg:postcode":"54801",
    "sg:province":"WI",
    "sg:tags":[
        "house",
        "clinic",
        "specialty",
        "outpatient"
    ],
    "wof:name":"Pines Ii(inc)",
    "wof:placetype":"venue"
},
  "geometry": {"coordinates":[-92.07702,45.880208],"type":"Point"}
}