{
  "type": "Feature",
  "properties": {
    "iso:country":"US",
    "sg:address":"2011 E Main St",
    "sg:city":"Little Chute",
    "sg:classifiers":[
        {
            "category":"Autos & Motor Vehicles",
            "subcategory":"Auto Supplies",
            "type":"Retail Goods"
        }
    ],
    "sg:phone":"+1 920 766 3230",
    "sg:postcode":"54140",
    "sg:province":"WI",
    "sg:tags":[
        "automobile",
        "parts"
    ],
    "wof:name":"NAPA Auto Parts",
    "wof:placetype":"venue"
},
  "geometry": {"coordinates":[-88.292912,44.28488],"type":"Point"}
}