{
  "type": "Feature",
  "properties": {
    "iso:country":"US",
    "sg:address":"115 S Main St",
    "sg:city":"Birchwood",
    "sg:classifiers":[
        {
            "category":"Shopping",
            "subcategory":"Gifts & Souvenirs",
            "type":"Retail Goods"
        }
    ],
    "sg:phone":"+1 715 354 3361",
    "sg:postcode":"54817",
    "sg:province":"WI",
    "sg:tags":[
        "shop"
    ],
    "wof:name":"Berry Patch Imporium",
    "wof:placetype":"venue"
},
  "geometry": {"coordinates":[-91.555753,45.655328],"type":"Point"}
}