{
  "type": "Feature",
  "properties": {
    "iso:country":"US",
    "sg:address":"1621 Riverwood Ln",
    "sg:city":"Wisconsin Rapids",
    "sg:classifiers":[
        {
            "category":"Shopping",
            "subcategory":"Crafts & Fabrics",
            "type":"Retail Goods"
        }
    ],
    "sg:phone":"+1 715 421 0100",
    "sg:postcode":"54494",
    "sg:province":"WI",
    "sg:tags":[
        "sewing"
    ],
    "wof:name":"Grand Central Yarns",
    "wof:placetype":"venue"
},
  "geometry": {"coordinates":[-89.83369999999999,44.38123],"type":"Point"}
}