{
  "type": "Feature",
  "properties": {
    "iso:country":"US",
    "sg:address":"2801 N 21st St",
    "sg:city":"Sheboygan",
    "sg:classifiers":[
        {
            "category":"Wholesale",
            "subcategory":"Scrap",
            "type":"Manufacturing & Wholesale Goods"
        }
    ],
    "sg:phone":"+1 920 452 1894",
    "sg:postcode":"53083",
    "sg:province":"WI",
    "sg:tags":[
        "material",
        "metal",
        "iron"
    ],
    "wof:name":"Sheboygan Scrap Metals",
    "wof:placetype":"venue"
},
  "geometry": {"coordinates":[-87.73452899999999,43.775338],"type":"Point"}
}