{
  "type": "Feature",
  "properties": {
    "iso:country":"US",
    "sg:address":"250 Parkside Dr",
    "sg:city":"Dorchester",
    "sg:classifiers":[
        {
            "category":"Freight",
            "type":"Transportation"
        }
    ],
    "sg:phone":"+1 715 654 1190",
    "sg:postcode":"54425",
    "sg:province":"WI",
    "sg:tags":[
        "hauling",
        "trucking"
    ],
    "wof:name":"Blume Farms",
    "wof:placetype":"venue"
},
  "geometry": {"coordinates":[-90.324862,45.001949],"type":"Point"}
}