{
  "type": "Feature",
  "properties": {
    "addr:full":"7226 Old 57 Rd Greenleaf WI 54126",
    "addr:housenumber":"7226",
    "addr:postcode":"54126",
    "addr:street":"Old 57 Rd",
    "iso:country":"US",
    "sg:address":"7226 Old 57 Rd",
    "sg:city":"Greenleaf",
    "sg:classifiers":[
        {
            "category":"Farming",
            "subcategory":"Dairy Farm",
            "type":"Manufacturing & Wholesale Goods"
        }
    ],
    "sg:phone":"+1 920 532 4752",
    "sg:postcode":"54126",
    "sg:province":"WI",
    "sg:tags":[
        "field",
        "crop"
    ],
    "wof:name":"William Clancy",
    "wof:placetype":"venue"
},
  "geometry": {"coordinates":[-88.11081799999999,44.293887],"type":"Point"}
}