{
  "type": "Feature",
  "properties": {
    "addr:full":"6041 W Port Ave Milwaukee WI 53223",
    "addr:housenumber":"6041",
    "addr:postcode":"53223",
    "addr:street":"W Port Ave",
    "iso:country":"US",
    "sg:address":"6041 W Port Ave",
    "sg:city":"Milwaukee",
    "sg:classifiers":[
        {
            "category":"Recreation",
            "type":"Entertainment"
        }
    ],
    "sg:phone":"+1 414 355 9596",
    "sg:postcode":"53223",
    "sg:province":"WI",
    "sg:tags":[
        "club",
        "bridge"
    ],
    "wof:name":"Bridge Center Of Milwaukee",
    "wof:placetype":"venue"
},
  "geometry": {"coordinates":[-87.98715799999999,43.158368],"type":"Point"}
}