{
  "type": "Feature",
  "properties": {
    "iso:country":"US",
    "sg:address":"212 Main St",
    "sg:city":"Balsam Lake",
    "sg:classifiers":[
        {
            "category":"Personal",
            "subcategory":"Beauty Salon",
            "type":"Services"
        }
    ],
    "sg:phone":"+1 715 485 3697",
    "sg:postcode":"54810",
    "sg:province":"WI",
    "wof:name":"Village Hair Care",
    "wof:placetype":"venue"
},
  "geometry": {"coordinates":[-92.453936,45.451356],"type":"Point"}
}