{
  "type": "Feature",
  "properties": {
    "iso:country":"US",
    "sg:address":"7297 Gad Rd",
    "sg:city":"Medford",
    "sg:classifiers":[
        {
            "category":"Freight",
            "type":"Transportation"
        }
    ],
    "sg:phone":"+1 715 748 2598",
    "sg:postcode":"54451",
    "sg:province":"WI",
    "sg:tags":[
        "operator",
        "local",
        "trucking"
    ],
    "wof:name":"M&L Trucking",
    "wof:placetype":"venue"
},
  "geometry": {"coordinates":[-90.18056,45.098308],"type":"Point"}
}