{
  "type": "Feature",
  "properties": {
    "iso:country":"US",
    "sg:address":"63 Valerie Dr",
    "sg:city":"Appleton",
    "sg:classifiers":[
        {
            "category":"Autos & Motor Vehicles",
            "subcategory":"Automobile Sales",
            "type":"Retail Goods"
        }
    ],
    "sg:phone":"+1 920 997 0098",
    "sg:postcode":"54915",
    "sg:province":"WI",
    "wof:name":"All World Auto Mall",
    "wof:placetype":"venue"
},
  "geometry": {"coordinates":[-88.406667,44.239944],"type":"Point"}
}