{
  "type": "Feature",
  "properties": {
    "iso:country":"US",
    "sg:address":"545 High Ave",
    "sg:city":"Oshkosh",
    "sg:classifiers":[
        {
            "category":"Restaurant",
            "type":"Food & Drink"
        }
    ],
    "sg:phone":"+1 920 235 0223",
    "sg:postcode":"54901",
    "sg:province":"WI",
    "wof:name":"Hungri's Submarine Sandwich",
    "wof:placetype":"venue"
},
  "geometry": {"coordinates":[-88.54627,44.021212],"type":"Point"}
}