{
  "type": "Feature",
  "properties": {
    "iso:country":"US",
    "sg:address":"5931 Leeward Ln",
    "sg:city":"Racine",
    "sg:classifiers":[
        {
            "category":"Manufacturing",
            "subcategory":"Metals",
            "type":"Manufacturing & Wholesale Goods"
        }
    ],
    "sg:phone":"+1 262 497 2419",
    "sg:postcode":"53402",
    "sg:province":"WI",
    "sg:tags":[
        "nonferrous"
    ],
    "wof:name":"Mark P Dechant",
    "wof:placetype":"venue"
},
  "geometry": {"coordinates":[-87.852657,42.779688],"type":"Point"}
}