{
  "type": "Feature",
  "properties": {
    "iso:country":"US",
    "sg:address":"4025 N 50th St",
    "sg:city":"Milwaukee",
    "sg:classifiers":[
        {
            "category":"Organizations",
            "subcategory":"Religious Organization",
            "type":"Services"
        }
    ],
    "sg:phone":"+1 414 461 1651",
    "sg:postcode":"53216",
    "sg:province":"WI",
    "sg:tags":[
        "church"
    ],
    "wof:name":"Holy Miracle Church",
    "wof:placetype":"venue"
},
  "geometry": {"coordinates":[-87.975915,43.091241],"type":"Point"}
}