{
  "type": "Feature",
  "properties": {
    "iso:country":"US",
    "sg:address":"1174 Park Village Dr",
    "sg:city":"Neenah",
    "sg:classifiers":[
        {
            "category":"Shopping",
            "subcategory":"Hobbies, Toys, & Games",
            "type":"Retail Goods"
        }
    ],
    "sg:phone":"+1 920 725 7225",
    "sg:postcode":"54956",
    "sg:province":"WI",
    "sg:tags":[
        "model",
        "supply"
    ],
    "wof:name":"P & K Whitehorse Inc",
    "wof:placetype":"venue"
},
  "geometry": {"coordinates":[-88.500729,44.168378],"type":"Point"}
}