{
  "type": "Feature",
  "properties": {
    "iso:country":"US",
    "sg:address":"2187 Sandy Rock Rd",
    "sg:city":"Barneveld",
    "sg:phone":"+1 608 437 5715",
    "sg:postcode":"53507",
    "sg:province":"WI",
    "sg:tags":[
        "farm",
        "field",
        "crop"
    ],
    "wof:name":"Donald Murphy",
    "wof:placetype":"venue"
},
  "geometry": {"coordinates":[-89.86496699999999,42.916509],"type":"Point"}
}