{
  "type": "Feature",
  "properties": {
    "iso:country":"US",
    "sg:address":"2242 W North Ave",
    "sg:city":"Milwaukee",
    "sg:classifiers":[
        {
            "category":"Social Services",
            "subcategory":"Child Care",
            "type":"Services"
        }
    ],
    "sg:phone":"+1 414 931 8880",
    "sg:postcode":"53205",
    "sg:province":"WI",
    "sg:tags":[
        "day"
    ],
    "wof:name":"Sunrise To Sunset Child Care C",
    "wof:placetype":"venue"
},
  "geometry": {"coordinates":[-87.940965,43.060603],"type":"Point"}
}