{
  "type": "Feature",
  "properties": {
    "iso:country":"US",
    "sg:address":"7549 Kempf Ct",
    "sg:city":"Elkhart Lake",
    "sg:classifiers":[
        {
            "category":"Government",
            "subcategory":"Office",
            "type":"Public Place"
        }
    ],
    "sg:phone":"+1 920 894 2370",
    "sg:postcode":"53020",
    "sg:province":"WI",
    "sg:tags":[
        "town"
    ],
    "wof:name":"Town of Russell",
    "wof:placetype":"venue"
},
  "geometry": {"coordinates":[-88.07304000000001,43.884195],"type":"Point"}
}