{
  "type": "Feature",
  "properties": {
    "iso:country":"US",
    "sg:address":"16 N Brown St",
    "sg:city":"Rhinelander",
    "sg:classifiers":[
        {
            "category":"Shopping",
            "subcategory":"Musical Instruments",
            "type":"Retail Goods"
        }
    ],
    "sg:phone":"+1 715 369 3272",
    "sg:postcode":"54501",
    "sg:province":"WI",
    "sg:tags":[
        "music",
        "dealer"
    ],
    "wof:name":"Jerry's Music Inc",
    "wof:placetype":"venue"
},
  "geometry": {"coordinates":[-89.412684,45.638817],"type":"Point"}
}