{
  "type": "Feature",
  "properties": {
    "iso:country":"US",
    "sg:address":"854 Thackeray Trl",
    "sg:city":"Oconomowoc",
    "sg:classifiers":[
        {
            "category":"Restaurant",
            "type":"Food & Drink"
        }
    ],
    "sg:phone":"+1 262 567 6800",
    "sg:postcode":"53066",
    "sg:province":"WI",
    "wof:name":"My Place Coffee House Cafe",
    "wof:placetype":"venue"
},
  "geometry": {"coordinates":[-88.481631,43.096955],"type":"Point"}
}