{
  "type": "Feature",
  "properties": {
    "iso:country":"US",
    "sg:address":"3303 S 103rd St",
    "sg:city":"Milwaukee",
    "sg:classifiers":[
        {
            "category":"Organizations",
            "subcategory":"Labor Organization",
            "type":"Services"
        }
    ],
    "sg:phone":"+1 414 327 5202",
    "sg:postcode":"53227",
    "sg:province":"WI",
    "sg:website":"www.ibew494.com",
    "wof:name":"IBEW",
    "wof:placetype":"venue"
},
  "geometry": {"coordinates":[-88.04044399999999,42.985552],"type":"Point"}
}