{
  "type": "Feature",
  "properties": {
    "iso:country":"US",
    "sg:address":"228 N Main St",
    "sg:city":"Loyal",
    "sg:classifiers":[
        {
            "category":"Education",
            "subcategory":"Library",
            "type":"Public Place"
        }
    ],
    "sg:phone":"+1 715 255 8189",
    "sg:postcode":"54446",
    "sg:province":"WI",
    "wof:name":"Loyal Public Library",
    "wof:placetype":"venue"
},
  "geometry": {"coordinates":[-90.495892,44.73771],"type":"Point"}
}