{
  "type": "Feature",
  "properties": {
    "addr:full":"14484 Co Rd M Thorp WI 54771",
    "addr:housenumber":"14484",
    "addr:postcode":"54771",
    "addr:street":"Co Rd",
    "iso:country":"US",
    "sg:address":"14484 Co Rd M",
    "sg:city":"Thorp",
    "sg:classifiers":[
        {
            "category":"Wholesale",
            "subcategory":"Machinery & Supplies",
            "type":"Manufacturing & Wholesale Goods"
        }
    ],
    "sg:phone":"+1 715 669 5305",
    "sg:postcode":"54771",
    "sg:province":"WI",
    "sg:tags":[
        "farm",
        "equipment"
    ],
    "wof:name":"Area Equipment Inc",
    "wof:placetype":"venue"
},
  "geometry": {"coordinates":[-90.800332,44.934725],"type":"Point"}
}