{
  "type": "Feature",
  "properties": {
    "iso:country":"US",
    "sg:address":"150 Jackson St",
    "sg:city":"Oshkosh",
    "sg:classifiers":[
        {
            "category":"Manufacturing",
            "subcategory":"Printing",
            "type":"Manufacturing & Wholesale Goods"
        }
    ],
    "sg:phone":"+1 920 426 0888",
    "sg:postcode":"54901",
    "sg:province":"WI",
    "sg:tags":[
        "lithographic",
        "printer",
        "commercial"
    ],
    "wof:name":"Park N Print Inc",
    "wof:placetype":"venue"
},
  "geometry": {"coordinates":[-88.542462,44.017781],"type":"Point"}
}