{
  "type": "Feature",
  "properties": {
    "iso:country":"US",
    "sg:address":"3132 Barbara Dr",
    "sg:city":"Racine",
    "sg:classifiers":[
        {
            "category":"Manufacturing",
            "subcategory":"Metals",
            "type":"Manufacturing & Wholesale Goods"
        }
    ],
    "sg:phone":"+1 262 634 6717",
    "sg:postcode":"53404",
    "sg:province":"WI",
    "sg:tags":[
        "machine",
        "screw",
        "product",
        "mfg"
    ],
    "wof:name":"United Automatic Products",
    "wof:placetype":"venue"
},
  "geometry": {"coordinates":[-87.819298,42.748251],"type":"Point"}
}