{
  "type": "Feature",
  "properties": {
    "iso:country":"US",
    "sg:address":"6313 N Prescott St",
    "sg:city":"Arkansaw",
    "sg:classifiers":[
        {
            "category":"Organizations",
            "subcategory":"Religious Organization",
            "type":"Services"
        }
    ],
    "sg:phone":"+1 715 285 5872",
    "sg:postcode":"54721",
    "sg:province":"WI",
    "wof:name":"United Methodist Church",
    "wof:placetype":"venue"
},
  "geometry": {"coordinates":[-92.031321,44.637087],"type":"Point"}
}