{
  "type": "Feature",
  "properties": {
    "iso:country":"US",
    "sg:address":"7036 Quinney Rd",
    "sg:city":"Elkhorn",
    "sg:classifiers":[
        {
            "category":"Farming",
            "subcategory":"Farm",
            "type":"Manufacturing & Wholesale Goods"
        }
    ],
    "sg:phone":"+1 262 728 5361",
    "sg:postcode":"53121",
    "sg:province":"WI",
    "wof:name":"Quinney Farm",
    "wof:placetype":"venue"
},
  "geometry": {"coordinates":[-88.63190899999999,42.687354],"type":"Point"}
}