{
  "type": "Feature",
  "properties": {
    "iso:country":"US",
    "sg:address":"1617 Hamilton St",
    "sg:city":"Racine",
    "sg:classifiers":[
        {
            "category":"Social Services",
            "subcategory":"Child Care",
            "type":"Services"
        }
    ],
    "sg:phone":"+1 262 634 6521",
    "sg:postcode":"53404",
    "sg:province":"WI",
    "wof:name":"Tammie Day Care",
    "wof:placetype":"venue"
},
  "geometry": {"coordinates":[-87.801503,42.73541],"type":"Point"}
}