{
  "type": "Feature",
  "properties": {
    "iso:country":"US",
    "sg:address":"3012 W Beltline Hwy",
    "sg:city":"Middleton",
    "sg:classifiers":[
        {
            "category":"Retail",
            "subcategory":"Auto Rental",
            "type":"Services"
        }
    ],
    "sg:phone":"+1 608 836 7773",
    "sg:postcode":"53562",
    "sg:province":"WI",
    "sg:tags":[
        "passenger",
        "car"
    ],
    "wof:name":"Rent A Car Inc",
    "wof:placetype":"venue"
},
  "geometry": {"coordinates":[-89.518788,43.093956],"type":"Point"}
}