{
  "type": "Feature",
  "properties": {
    "iso:country":"US",
    "sg:address":"5117 N 126th St",
    "sg:city":"Butler",
    "sg:classifiers":[
        {
            "category":"Building & Trades",
            "subcategory":"Construction",
            "type":"Services"
        }
    ],
    "sg:phone":"+1 414 699 3283",
    "sg:postcode":"53007",
    "sg:province":"WI",
    "sg:tags":[
        "house"
    ],
    "wof:name":"Dww Enterprises LLC",
    "wof:placetype":"venue"
},
  "geometry": {"coordinates":[-88.068282,43.110729],"type":"Point"}
}