{
  "type": "Feature",
  "properties": {
    "iso:country":"US",
    "sg:address":"10032 N Wauwatosa Rd",
    "sg:city":"Mequon",
    "sg:classifiers":[
        {
            "category":"Farming",
            "subcategory":"Nursery",
            "type":"Manufacturing & Wholesale Goods"
        },
        {
            "category":"Shopping",
            "subcategory":"Crafts & Fabrics",
            "type":"Retail Goods"
        },
        {
            "category":"Manufacturing",
            "subcategory":"Paper Products",
            "type":"Manufacturing & Wholesale Goods"
        }
    ],
    "sg:phone":"+1 262 242 9200",
    "sg:postcode":"53097",
    "sg:province":"WI",
    "sg:tags":[
        "florists'",
        "nurseries-plants",
        "supply",
        "tree",
        "nursery-wholesale",
        "florist",
        "bamboo",
        "supplies-wholesale",
        "grower",
        "manufacturer"
    ],
    "sg:website":"http://www.waysidenurseries.com",
    "wof:name":"Wayside Nurseries Inc",
    "wof:placetype":"venue"
},
  "geometry": {"coordinates":[-88.00372,43.194161],"type":"Point"}
}