{
  "type": "Feature",
  "properties": {
    "iso:country":"US",
    "sg:address":"7467 Ceaser Rd",
    "sg:city":"Watertown",
    "sg:classifiers":[
        {
            "category":"Farming",
            "subcategory":"Dairy Farm",
            "type":"Manufacturing & Wholesale Goods"
        }
    ],
    "sg:phone":"+1 920 261 3633",
    "sg:postcode":"53094",
    "sg:province":"WI",
    "wof:name":"Ken Blake",
    "wof:placetype":"venue"
},
  "geometry": {"coordinates":[-88.666433,43.110454],"type":"Point"}
}