{
  "type": "Feature",
  "properties": {
    "iso:country":"US",
    "sg:address":"2155 Holmgren Way",
    "sg:city":"Green Bay",
    "sg:classifiers":[
        {
            "category":"Recreation",
            "type":"Entertainment"
        }
    ],
    "sg:phone":"+1 920 492 2331",
    "sg:postcode":"54304",
    "sg:province":"WI",
    "sg:tags":[
        "parks"
    ],
    "sg:website":"www.ashwaubenon.com",
    "wof:name":"Ashwaubenon Recreation Dept",
    "wof:placetype":"venue"
},
  "geometry": {"coordinates":[-88.05730200000001,44.492579],"type":"Point"}
}