{
  "type": "Feature",
  "properties": {
    "iso:country":"US",
    "sg:address":"2303 State Hwy 120",
    "sg:city":"Lake Geneva",
    "sg:classifiers":[
        {
            "category":"Wholesale",
            "subcategory":"Computers",
            "type":"Manufacturing & Wholesale Goods"
        }
    ],
    "sg:phone":"+1 262 249 0110",
    "sg:postcode":"53147",
    "sg:province":"WI",
    "sg:tags":[
        "peripheral",
        "other",
        "software"
    ],
    "wof:name":"Digital Options Inc",
    "wof:placetype":"venue"
},
  "geometry": {"coordinates":[-88.436089,42.574644],"type":"Point"}
}