{
  "type": "Feature",
  "properties": {
    "iso:country":"US",
    "sg:address":"6966 State Hwy 57",
    "sg:city":"Baileys Harbor",
    "sg:classifiers":[
        {
            "category":"Shopping",
            "subcategory":"Shoes",
            "type":"Retail Goods"
        }
    ],
    "sg:phone":"+1 920 823 2000",
    "sg:postcode":"54202",
    "sg:province":"WI",
    "wof:name":"Shoe Box",
    "wof:placetype":"venue"
},
  "geometry": {"coordinates":[-87.1524,45.011073],"type":"Point"}
}