{
  "type": "Feature",
  "properties": {
    "addr:full":"205 S Wright St Delavan WI 53115",
    "addr:housenumber":"205",
    "addr:postcode":"53115",
    "addr:street":"S Wright St",
    "iso:country":"US",
    "sg:address":"205 S Wright St",
    "sg:city":"Delavan",
    "sg:classifiers":[
        {
            "category":"Food & Beverages",
            "subcategory":"Liquor & Beverages",
            "type":"Retail Goods"
        }
    ],
    "sg:phone":"+1 262 728 6070",
    "sg:postcode":"53115",
    "sg:province":"WI",
    "sg:tags":[
        "alcoholic"
    ],
    "wof:name":"Hooch Hut LTD",
    "wof:placetype":"venue"
},
  "geometry": {"coordinates":[-88.626053,42.633688],"type":"Point"}
}