{
  "type": "Feature",
  "properties": {
    "addr:full":"1143 N Bloomfield Rd Lake Geneva WI 53147",
    "addr:housenumber":"1143",
    "addr:postcode":"53147",
    "addr:street":"N Bloomfield Rd",
    "iso:country":"US",
    "sg:address":"1143 N Bloomfield Rd",
    "sg:city":"Lake Geneva",
    "sg:classifiers":[
        {
            "category":"Building & Trades",
            "subcategory":"Construction",
            "type":"Services"
        }
    ],
    "sg:phone":"+1 262 248 1133",
    "sg:postcode":"53147",
    "sg:province":"WI",
    "sg:tags":[
        "builder",
        "patio",
        "deck"
    ],
    "wof:name":"Creative Built Decks",
    "wof:placetype":"venue"
},
  "geometry": {"coordinates":[-88.35838200000001,42.574439],"type":"Point"}
}