{
  "type": "Feature",
  "properties": {
    "iso:country":"US",
    "sg:address":"4096 131st St",
    "sg:city":"Chippewa Falls",
    "sg:classifiers":[
        {
            "category":"Building & Trades",
            "subcategory":"Construction",
            "type":"Services"
        }
    ],
    "sg:phone":"+1 715 726 9886",
    "sg:postcode":"54729",
    "sg:province":"WI",
    "sg:tags":[
        "contractor"
    ],
    "wof:name":"Spruce Up Construction",
    "wof:placetype":"venue"
},
  "geometry": {"coordinates":[-91.40500299999999,44.90249],"type":"Point"}
}