{
  "type": "Feature",
  "properties": {
    "addr:full":"164 Lake Shore Dr Iola WI 54945",
    "addr:housenumber":"164",
    "addr:postcode":"54945",
    "addr:street":"Lake Shore Dr",
    "iso:country":"US",
    "sg:address":"164 Lake Shore Dr",
    "sg:city":"Iola",
    "sg:classifiers":[
        {
            "category":"Professional",
            "type":"Services"
        }
    ],
    "sg:phone":"+1 715 445 9283",
    "sg:postcode":"54945",
    "sg:province":"WI",
    "wof:name":"Bruce & Susan Freistedt",
    "wof:placetype":"venue"
},
  "geometry": {"coordinates":[-89.132274,44.516052],"type":"Point"}
}