{
  "type": "Feature",
  "properties": {
    "addr:full":"100 E Main St Watertown WI 53094",
    "addr:housenumber":"100",
    "addr:postcode":"53094",
    "addr:street":"E Main St",
    "iso:country":"US",
    "sg:address":"100 E Main St",
    "sg:city":"Watertown",
    "sg:classifiers":[
        {
            "category":"Shopping",
            "subcategory":"Musical Instruments",
            "type":"Retail Goods"
        }
    ],
    "sg:phone":"+1 920 206 8597",
    "sg:postcode":"53094",
    "sg:province":"WI",
    "sg:tags":[
        "compact",
        "collectible",
        "disc",
        "rare",
        "string"
    ],
    "wof:name":"Fox Music",
    "wof:placetype":"venue"
},
  "geometry": {"coordinates":[-88.72410600000001,43.194308],"type":"Point"}
}