{
  "type": "Feature",
  "properties": {
    "iso:country":"US",
    "sg:address":"8867 Woodbridge Dr",
    "sg:city":"Greendale",
    "sg:classifiers":[
        {
            "category":"Professional",
            "subcategory":"Detective & Security Services",
            "type":"Services"
        }
    ],
    "sg:phone":"+1 414 529 5074",
    "sg:postcode":"53129",
    "sg:province":"WI",
    "sg:tags":[
        "contracting",
        "private"
    ],
    "wof:name":"Dale E Faesi",
    "wof:placetype":"venue"
},
  "geometry": {"coordinates":[-88.025856,42.945839],"type":"Point"}
}