{
  "type": "Feature",
  "properties": {
    "iso:country":"US",
    "sg:address":"328 N Main St",
    "sg:city":"Walworth",
    "sg:classifiers":[
        {
            "category":"Retail",
            "subcategory":"Auto Repair",
            "type":"Services"
        }
    ],
    "sg:phone":"+1 262 275 0590",
    "sg:postcode":"53184",
    "sg:province":"WI",
    "sg:tags":[
        "automotive"
    ],
    "wof:name":"Platt Electice",
    "wof:placetype":"venue"
},
  "geometry": {"coordinates":[-88.59965200000001,42.535772],"type":"Point"}
}