{
  "type": "Feature",
  "properties": {
    "iso:country":"US",
    "sg:address":"117 E 5th St",
    "sg:city":"Washburn",
    "sg:classifiers":[
        {
            "category":"Government",
            "subcategory":"Office",
            "type":"Public Place"
        }
    ],
    "sg:phone":"+1 715 373 6108",
    "sg:postcode":"54891",
    "sg:province":"WI",
    "wof:name":"Bayfield Clerks Of Courts",
    "wof:placetype":"venue"
},
  "geometry": {"coordinates":[-90.891639,46.676963],"type":"Point"}
}