{
  "type": "Feature",
  "properties": {
    "iso:country":"US",
    "sg:address":"7262 Black Hill Rd",
    "sg:city":"Lodi",
    "sg:classifiers":[
        {
            "category":"Professional",
            "subcategory":"Business Services",
            "type":"Services"
        }
    ],
    "sg:phone":"+1 608 592 5364",
    "sg:postcode":"53555",
    "sg:province":"WI",
    "wof:name":"Ritland Design Ltd",
    "wof:placetype":"venue"
},
  "geometry": {"coordinates":[-89.549677,43.24998],"type":"Point"}
}