{
  "type": "Feature",
  "properties": {
    "addr:full":"1741 Co Rd A Neenah WI 54956",
    "addr:housenumber":"1741",
    "addr:postcode":"54956",
    "addr:street":"Co Rd",
    "iso:country":"US",
    "sg:address":"1741 Co Rd A",
    "sg:city":"Neenah",
    "sg:classifiers":[
        {
            "category":"Building & Trades",
            "subcategory":"Construction",
            "type":"Services"
        }
    ],
    "sg:phone":"+1 920 720 0676",
    "sg:postcode":"54956",
    "sg:province":"WI",
    "sg:tags":[
        "house"
    ],
    "wof:name":"Valley Renovating",
    "wof:placetype":"venue"
},
  "geometry": {"coordinates":[-88.467336,44.135301],"type":"Point"}
}