{
  "type": "Feature",
  "properties": {
    "iso:country":"US",
    "sg:address":"3196 Western Rd",
    "sg:city":"Antigo",
    "sg:classifiers":[
        {
            "category":"Building & Trades",
            "subcategory":"Construction",
            "type":"Services"
        }
    ],
    "sg:phone":"+1 715 627 2217",
    "sg:postcode":"54409",
    "sg:province":"WI",
    "sg:tags":[
        "hanging",
        "contractor"
    ],
    "wof:name":"Langlade Painting",
    "wof:placetype":"venue"
},
  "geometry": {"coordinates":[-89.178462,45.140553],"type":"Point"}
}