{
  "type": "Feature",
  "properties": {
    "addr:full":"400 N 9th Ave Winneconne WI 54986",
    "addr:housenumber":"400",
    "addr:postcode":"54986",
    "addr:street":"N 9Th Ave",
    "iso:country":"US",
    "sg:address":"400 N 9th Ave",
    "sg:city":"Winneconne",
    "sg:classifiers":[
        {
            "category":"Education",
            "subcategory":"School",
            "type":"Public Place"
        }
    ],
    "sg:phone":"+1 920 582 5810",
    "sg:postcode":"54986",
    "sg:province":"WI",
    "wof:name":"Winneconne High School",
    "wof:placetype":"venue"
},
  "geometry": {"coordinates":[-88.69856299999999,44.112427],"type":"Point"}
}