{
  "type": "Feature",
  "properties": {
    "addr:full":"1683 N Van Buren St Milwaukee WI 53202",
    "addr:housenumber":"1683",
    "addr:postcode":"53202",
    "addr:street":"N Van Buren St",
    "iso:country":"US",
    "sg:address":"1683 N Van Buren St",
    "sg:city":"Milwaukee",
    "sg:classifiers":[
        {
            "category":"Bars & Pubs",
            "type":"Food & Drink"
        },
        {
            "category":"Restaurant",
            "type":"Food & Drink"
        }
    ],
    "sg:phone":"+1 414 291 5600",
    "sg:postcode":"53202",
    "sg:province":"WI",
    "sg:tags":[
        "lounge",
        "cocktail"
    ],
    "wof:name":"Giovanni's Restaurant",
    "wof:placetype":"venue"
},
  "geometry": {"coordinates":[-87.903491,43.050956],"type":"Point"}
}