{
  "type": "Feature",
  "properties": {
    "iso:country":"US",
    "sg:address":"7312 100th Ave",
    "sg:city":"Chippewa Falls",
    "sg:classifiers":[
        {
            "category":"Government",
            "subcategory":"Fire Station",
            "type":"Public Place"
        }
    ],
    "sg:phone":"+1 715 288 6156",
    "sg:postcode":"54729",
    "sg:province":"WI",
    "sg:tags":[
        "department",
        "volunteer"
    ],
    "wof:name":"Tilden Volunteer Fire Dept",
    "wof:placetype":"venue"
},
  "geometry": {"coordinates":[-91.52316500000001,44.987855],"type":"Point"}
}