{
  "type": "Feature",
  "properties": {
    "iso:country":"US",
    "sg:address":"449 S Yellowstone Dr",
    "sg:city":"Madison",
    "sg:classifiers":[
        {
            "category":"Personal",
            "subcategory":"Beauty Salon",
            "type":"Services"
        }
    ],
    "sg:phone":"+1 608 274 2370",
    "sg:postcode":"53719",
    "sg:province":"WI",
    "sg:tags":[
        "shop"
    ],
    "wof:name":"Karen For Your Hair",
    "wof:placetype":"venue"
},
  "geometry": {"coordinates":[-89.492578,43.056672],"type":"Point"}
}