{
  "type": "Feature",
  "properties": {
    "iso:country":"US",
    "sg:address":"426 Broad St",
    "sg:city":"Oshkosh",
    "sg:classifiers":[
        {
            "category":"Real Estate",
            "subcategory":"Real Estate Agent",
            "type":"Services"
        }
    ],
    "sg:phone":"+1 920 232 8108",
    "sg:postcode":"54901",
    "sg:province":"WI",
    "wof:name":"Land Pride Properties",
    "wof:placetype":"venue"
},
  "geometry": {"coordinates":[-88.53129,44.018305],"type":"Point"}
}