{
  "type": "Feature",
  "properties": {
    "iso:country":"US",
    "sg:address":"2220 18th St",
    "sg:city":"Hazel Green",
    "sg:classifiers":[
        {
            "category":"Building & Trades",
            "subcategory":"Construction",
            "type":"Services"
        }
    ],
    "sg:phone":"+1 608 854 2489",
    "sg:postcode":"53811",
    "sg:province":"WI",
    "sg:tags":[
        "plastering",
        "contractor"
    ],
    "wof:name":"Tim Droessler Plastering",
    "wof:placetype":"venue"
},
  "geometry": {"coordinates":[-90.429878,42.532023],"type":"Point"}
}