{
  "type": "Feature",
  "properties": {
    "iso:country":"US",
    "sg:address":"7536 W Oklahoma Ave",
    "sg:city":"Milwaukee",
    "sg:classifiers":[
        {
            "category":"Banks & Credit Unions",
            "subcategory":"Bank",
            "type":"Services"
        }
    ],
    "sg:phone":"+1 414 545 1280",
    "sg:postcode":"53219",
    "sg:province":"WI",
    "sg:tags":[
        "personal",
        "financing",
        "institution"
    ],
    "wof:name":"American General Finance Inc",
    "wof:placetype":"venue"
},
  "geometry": {"coordinates":[-88.00519799999999,42.988368],"type":"Point"}
}