{
  "type": "Feature",
  "properties": {
    "iso:country":"US",
    "sg:address":"1700 W Wisconsin St",
    "sg:city":"Sparta",
    "sg:classifiers":[
        {
            "category":"Organizations",
            "subcategory":"Religious Organization",
            "type":"Services"
        }
    ],
    "sg:phone":"+1 608 269 4760",
    "sg:postcode":"54656",
    "sg:province":"WI",
    "sg:tags":[
        "church"
    ],
    "wof:name":"Gospel Baptist Church Inc",
    "wof:placetype":"venue"
},
  "geometry": {"coordinates":[-90.83424,43.938547],"type":"Point"}
}