{
  "type": "Feature",
  "properties": {
    "iso:country":"US",
    "sg:address":"11721 W Carmen Ave",
    "sg:city":"Milwaukee",
    "sg:classifiers":[
        {
            "category":"Real Estate",
            "subcategory":"Real Estate Operator",
            "type":"Services"
        }
    ],
    "sg:phone":"+1 920 262 7368",
    "sg:postcode":"53225",
    "sg:province":"WI",
    "sg:tags":[
        "building",
        "apartment"
    ],
    "wof:name":"Page National Inc",
    "wof:placetype":"venue"
},
  "geometry": {"coordinates":[-88.060311,43.122486],"type":"Point"}
}