{
  "type": "Feature",
  "properties": {
    "addr:full":"3718 Hubertus Rd Hubertus WI 53033",
    "addr:postcode":"3718;53033",
    "addr:street":"Hubertus Rd",
    "iso:country":"US",
    "sg:address":"3718 Hubertus Rd",
    "sg:city":"Hubertus",
    "sg:classifiers":[
        {
            "category":"Restaurant",
            "type":"Food & Drink"
        }
    ],
    "sg:phone":"+1 262 628 7700",
    "sg:postcode":"53033",
    "sg:province":"WI",
    "sg:tags":[
        "eating"
    ],
    "wof:name":"Johnny Manhattan's",
    "wof:placetype":"venue"
},
  "geometry": {"coordinates":[-88.24114899999999,43.236778],"type":"Point"}
}