{
  "type": "Feature",
  "properties": {
    "iso:country":"US",
    "sg:address":"24124 77th St",
    "sg:city":"Salem",
    "sg:classifiers":[
        {
            "category":"Food & Beverages",
            "subcategory":"Candy",
            "type":"Retail Goods"
        }
    ],
    "sg:phone":"+1 262 843 3823",
    "sg:postcode":"53168",
    "sg:province":"WI",
    "wof:name":"Tpr Enterprises",
    "wof:placetype":"venue"
},
  "geometry": {"coordinates":[-88.100144,42.56661],"type":"Point"}
}