{
  "type": "Feature",
  "properties": {
    "iso:country":"US",
    "sg:address":"5811 State Hwy 51",
    "sg:city":"Schofield",
    "sg:classifiers":[
        {
            "category":"Restaurant",
            "type":"Food & Drink"
        }
    ],
    "sg:phone":"+1 715 355 5800",
    "sg:postcode":"54476",
    "sg:province":"WI",
    "sg:tags":[
        "pizza"
    ],
    "wof:name":"Sam's Pizza Palace",
    "wof:placetype":"venue"
},
  "geometry": {"coordinates":[-89.607299,44.903071],"type":"Point"}
}