{
  "type": "Feature",
  "properties": {
    "iso:country":"US",
    "sg:address":"1412 Deleglise St",
    "sg:city":"Antigo",
    "sg:classifiers":[
        {
            "category":"Manufacturing",
            "subcategory":"Signs",
            "type":"Manufacturing & Wholesale Goods"
        }
    ],
    "sg:phone":"+1 715 627 4373",
    "sg:postcode":"54409",
    "sg:province":"WI",
    "sg:tags":[
        "neon",
        "mfg"
    ],
    "wof:name":"Fallon Luminous Products Corp",
    "wof:placetype":"venue"
},
  "geometry": {"coordinates":[-89.161923,45.153291],"type":"Point"}
}