{
  "type": "Feature",
  "properties": {
    "addr:full":"3001 S Washburn St Oshkosh WI 54904",
    "addr:housenumber":"3001",
    "addr:postcode":"54904",
    "addr:street":"S Washburn St",
    "iso:country":"US",
    "sg:address":"3001 S Washburn St",
    "sg:city":"Oshkosh",
    "sg:classifiers":[
        {
            "category":"Shopping",
            "subcategory":"Clothing, Apparel, & Fashions",
            "type":"Retail Goods"
        }
    ],
    "sg:phone":"+1 920 232 9321",
    "sg:postcode":"54904",
    "sg:province":"WI",
    "sg:tags":[
        "used",
        "family",
        "merchandise"
    ],
    "wof:name":"Polo Ralph Lauren Outlet",
    "wof:placetype":"venue"
},
  "geometry": {"coordinates":[-88.58329999999999,43.985],"type":"Point"}
}