{
  "type": "Feature",
  "properties": {
    "iso:country":"US",
    "sg:address":"6314 60th St",
    "sg:city":"Kenosha",
    "sg:classifiers":[
        {
            "category":"Freight",
            "type":"Transportation"
        }
    ],
    "sg:phone":"+1 262 652 2039",
    "sg:postcode":"53144",
    "sg:province":"WI",
    "sg:website":"www.kastransport.com",
    "wof:name":"K As Transportation",
    "wof:placetype":"venue"
},
  "geometry": {"coordinates":[-87.884112,42.581588],"type":"Point"}
}