{
  "type": "Feature",
  "properties": {
    "addr:full":"241 E Park Ave Waukesha WI 53186",
    "addr:housenumber":"241",
    "addr:postcode":"53186",
    "addr:street":"E Park Ave",
    "iso:country":"US",
    "sg:address":"241 E Park Ave",
    "sg:city":"Waukesha",
    "sg:classifiers":[
        {
            "category":"Professional",
            "subcategory":"Management & Consulting",
            "type":"Services"
        }
    ],
    "sg:phone":"+1 262 446 3552",
    "sg:postcode":"53186",
    "sg:province":"WI",
    "wof:name":"Berg Management Co",
    "wof:placetype":"venue"
},
  "geometry": {"coordinates":[-88.230825,43.00871],"type":"Point"}
}