{
  "type": "Feature",
  "properties": {
    "addr:full":"1234 Crescent Dr Chetek WI 54728",
    "addr:housenumber":"1234",
    "addr:postcode":"54728",
    "addr:street":"Crescent Dr",
    "iso:country":"US",
    "sg:address":"1234 Crescent Dr",
    "sg:city":"Chetek",
    "sg:classifiers":[
        {
            "category":"Mining & Drilling",
            "type":"Manufacturing & Wholesale Goods"
        }
    ],
    "sg:phone":"+1 715 924 4945",
    "sg:postcode":"54728",
    "sg:province":"WI",
    "sg:tags":[
        "gravel",
        "crushing"
    ],
    "wof:name":"Rihn Brothers Crushing Inc",
    "wof:placetype":"venue"
},
  "geometry": {"coordinates":[-91.473561,45.334315],"type":"Point"}
}