{
  "type": "Feature",
  "properties": {
    "iso:country":"US",
    "sg:address":"3421 Erie St",
    "sg:city":"Racine",
    "sg:classifiers":[
        {
            "category":"Building & Trades",
            "subcategory":"Construction",
            "type":"Services"
        }
    ],
    "sg:phone":"+1 262 752 0272",
    "sg:postcode":"53402",
    "sg:province":"WI",
    "sg:tags":[
        "general",
        "contractor"
    ],
    "wof:name":"Side-Out Builders",
    "wof:placetype":"venue"
},
  "geometry": {"coordinates":[-87.787074,42.762316],"type":"Point"}
}