{
  "type": "Feature",
  "properties": {
    "addr:full":"2900 W Oklahoma Ave Milwaukee WI 53215",
    "addr:housenumber":"2900",
    "addr:postcode":"53215",
    "addr:street":"W Oklahoma Ave",
    "iso:country":"US",
    "sg:address":"2900 W Oklahoma Ave",
    "sg:city":"Milwaukee",
    "sg:classifiers":[
        {
            "category":"Health Services",
            "subcategory":"Doctor",
            "type":"Services"
        }
    ],
    "sg:phone":"+1 414 649 7200",
    "sg:postcode":"53215",
    "sg:province":"WI",
    "sg:tags":[
        "medical"
    ],
    "wof:name":"Vince Lombardi Cancer Clinic",
    "wof:placetype":"venue"
},
  "geometry": {"coordinates":[-87.95178799999999,42.988527],"type":"Point"}
}