{
  "type": "Feature",
  "properties": {
    "iso:country":"US",
    "sg:address":"5000 W Chambers St",
    "sg:city":"Milwaukee",
    "sg:classifiers":[
        {
            "category":"Health Services",
            "subcategory":"Doctor",
            "type":"Services"
        }
    ],
    "sg:phone":"+1 414 447 2245",
    "sg:postcode":"53210",
    "sg:province":"WI",
    "sg:tags":[
        "medical"
    ],
    "wof:name":"Department of Eternal Medicane",
    "wof:placetype":"venue"
},
  "geometry": {"coordinates":[-87.977367,43.07346],"type":"Point"}
}