{
  "type": "Feature",
  "properties": {
    "iso:country":"US",
    "sg:address":"3154 Midvale Dr",
    "sg:city":"Janesville",
    "sg:classifiers":[
        {
            "category":"Professional",
            "type":"Services"
        }
    ],
    "sg:phone":"+1 608 756 4211",
    "sg:postcode":"53546",
    "sg:province":"WI",
    "wof:name":"Cetcean",
    "wof:placetype":"venue"
},
  "geometry": {"coordinates":[-88.980447,42.7134],"type":"Point"}
}