{
  "type": "Feature",
  "properties": {
    "iso:country":"US",
    "sg:address":"9919 W Lisbon Ave",
    "sg:city":"Milwaukee",
    "sg:classifiers":[
        {
            "category":"Personal",
            "subcategory":"Beauty Salon",
            "type":"Services"
        }
    ],
    "sg:phone":"+1 414 464 7670",
    "sg:postcode":"53222",
    "sg:province":"WI",
    "sg:tags":[
        "shop"
    ],
    "wof:name":"Annie's-A Hair Salon",
    "wof:placetype":"venue"
},
  "geometry": {"coordinates":[-88.035004,43.087922],"type":"Point"}
}