{
  "type": "Feature",
  "properties": {
    "iso:country":"US",
    "sg:address":"3206 Derby Down",
    "sg:city":"Madison",
    "sg:classifiers":[
        {
            "category":"Building & Trades",
            "subcategory":"Electrical",
            "type":"Services"
        }
    ],
    "sg:phone":"+1 608 271 2133",
    "sg:postcode":"53713",
    "sg:province":"WI",
    "sg:tags":[
        "electrical",
        "contractor"
    ],
    "wof:name":"Celestial Sound Systems LLC",
    "wof:placetype":"venue"
},
  "geometry": {"coordinates":[-89.43019099999999,43.027512],"type":"Point"}
}