{
  "type": "Feature",
  "properties": {
    "addr:full":"3215 W Manitoba St Milwaukee WI 53215",
    "addr:housenumber":"3215",
    "addr:postcode":"53215",
    "addr:street":"W Manitoba St",
    "iso:country":"US",
    "sg:address":"3215 W Manitoba St",
    "sg:city":"Milwaukee",
    "sg:classifiers":[
        {
            "category":"Restaurant",
            "type":"Food & Drink"
        }
    ],
    "sg:phone":"+1 414 672 8848",
    "sg:postcode":"53215",
    "sg:province":"WI",
    "sg:tags":[
        "eating"
    ],
    "wof:name":"Joob Inc",
    "wof:placetype":"venue"
},
  "geometry": {"coordinates":[-87.955459,42.9898],"type":"Point"}
}