{
  "type": "Feature",
  "properties": {
    "iso:country":"US",
    "sg:address":"2154 N 52nd St",
    "sg:city":"Milwaukee",
    "sg:classifiers":[
        {
            "category":"Arts & Performance",
            "subcategory":"Theater",
            "type":"Entertainment"
        }
    ],
    "sg:phone":"+1 414 873 5752",
    "sg:postcode":"53208",
    "sg:province":"WI",
    "sg:tags":[
        "group"
    ],
    "wof:name":"Little Blue Crunchy Things",
    "wof:placetype":"venue"
},
  "geometry": {"coordinates":[-87.978697,43.058105],"type":"Point"}
}