{
  "type": "Feature",
  "properties": {
    "addr:full":"12318 Clarkson Rd Waterloo WI 53594",
    "addr:housenumber":"12318",
    "addr:postcode":"53594",
    "addr:street":"Clarkson Rd",
    "iso:country":"US",
    "sg:address":"12318 Clarkson Rd",
    "sg:city":"Waterloo",
    "sg:classifiers":[
        {
            "category":"Wholesale",
            "subcategory":"Machinery & Supplies",
            "type":"Manufacturing & Wholesale Goods"
        }
    ],
    "sg:phone":"+1 920 478 4247",
    "sg:postcode":"53594",
    "sg:province":"WI",
    "sg:tags":[
        "equipment",
        "industrial"
    ],
    "wof:name":"Otis Elevator Company",
    "wof:placetype":"venue"
},
  "geometry": {"coordinates":[-88.999381,43.197921],"type":"Point"}
}