{
  "type": "Feature",
  "properties": {
    "iso:country":"US",
    "sg:address":"8644 Meadow Lark Rd",
    "sg:city":"Sheboygan",
    "sg:classifiers":[
        {
            "category":"Retail",
            "subcategory":"Repair Shop",
            "type":"Services"
        }
    ],
    "sg:phone":"+1 920 565 4756",
    "sg:postcode":"53083",
    "sg:province":"WI",
    "wof:name":"East Central Pumping Inc",
    "wof:placetype":"venue"
},
  "geometry": {"coordinates":[-87.841414,43.861104],"type":"Point"}
}