{
  "type": "Feature",
  "properties": {
    "addr:full":"200 N 1st St Madison WI 53704",
    "addr:housenumber":"200",
    "addr:postcode":"53704",
    "addr:street":"N 1St St",
    "iso:country":"US",
    "sg:address":"200 N 1st St",
    "sg:city":"Madison",
    "sg:classifiers":[
        {
            "category":"Retail",
            "subcategory":"Auto Repair",
            "type":"Services"
        }
    ],
    "sg:phone":"+1 608 246 4541",
    "sg:postcode":"53704",
    "sg:province":"WI",
    "sg:tags":[
        "executive",
        "general"
    ],
    "wof:name":"Madison City Garage",
    "wof:placetype":"venue"
},
  "geometry": {"coordinates":[-89.362199,43.094139],"type":"Point"}
}