{
  "type": "Feature",
  "properties": {
    "iso:country":"US",
    "sg:address":"198 Desplaine Rd",
    "sg:city":"De Pere",
    "sg:classifiers":[
        {
            "category":"Professional",
            "type":"Services"
        }
    ],
    "sg:phone":"+1 920 217 6442",
    "sg:postcode":"54115",
    "sg:province":"WI",
    "wof:name":"Young Community",
    "wof:placetype":"venue"
},
  "geometry": {"coordinates":[-88.02848,44.441049],"type":"Point"}
}