{
  "type": "Feature",
  "properties": {
    "iso:country":"US",
    "sg:address":"2727 Plaza Dr",
    "sg:city":"Wausau",
    "sg:classifiers":[
        {
            "category":"Health Services",
            "subcategory":"Doctor",
            "type":"Services"
        }
    ],
    "sg:phone":"+1 715 847 3254",
    "sg:postcode":"54401",
    "sg:province":"WI",
    "sg:tags":[
        "osteopathic"
    ],
    "wof:name":"Mark E Davis Do",
    "wof:placetype":"venue"
},
  "geometry": {"coordinates":[-89.66631700000001,44.963743],"type":"Point"}
}