{
  "type": "Feature",
  "properties": {
    "iso:country":"US",
    "sg:address":"11580 Rice Lake Rd",
    "sg:city":"Frederic",
    "sg:classifiers":[
        {
            "category":"Farming",
            "subcategory":"Livestock Farm",
            "type":"Manufacturing & Wholesale Goods"
        }
    ],
    "sg:phone":"+1 715 327 4884",
    "sg:postcode":"54837",
    "sg:province":"WI",
    "sg:tags":[
        "feedlot",
        "field",
        "crop",
        "beef",
        "cattle"
    ],
    "wof:name":"R Britton",
    "wof:placetype":"venue"
},
  "geometry": {"coordinates":[-92.57056,45.692931],"type":"Point"}
}