{
  "type": "Feature",
  "properties": {
    "iso:country":"US",
    "sg:address":"4122 Driftwood Ct",
    "sg:city":"Sheboygan",
    "sg:classifiers":[
        {
            "category":"Real Estate",
            "subcategory":"Real Estate Operator",
            "type":"Services"
        }
    ],
    "sg:phone":"+1 920 451 0993",
    "sg:postcode":"53081",
    "sg:province":"WI",
    "sg:tags":[
        "building",
        "apartment"
    ],
    "wof:name":"Mapledale Luxury Apartments",
    "wof:placetype":"venue"
},
  "geometry": {"coordinates":[-87.761959,43.763201],"type":"Point"}
}