{
  "type": "Feature",
  "properties": {
    "iso:country":"US",
    "sg:address":"3830 Pau-Ko-Tuk Ln",
    "sg:city":"Oshkosh",
    "sg:classifiers":[
        {
            "category":"Professional",
            "subcategory":"Management & Consulting",
            "type":"Services"
        }
    ],
    "sg:phone":"+1 920 231 2321",
    "sg:postcode":"54902",
    "sg:province":"WI",
    "sg:tags":[
        "public",
        "relations"
    ],
    "wof:name":"Pjr Promotions Inc",
    "wof:placetype":"venue"
},
  "geometry": {"coordinates":[-88.519868,43.966688],"type":"Point"}
}