{
  "type": "Feature",
  "properties": {
    "addr:full":"3237 Royal Rd Janesville WI 53546",
    "addr:housenumber":"3237",
    "addr:postcode":"53546",
    "addr:street":"Royal Rd",
    "iso:country":"US",
    "sg:address":"3237 Royal Rd",
    "sg:city":"Janesville",
    "sg:classifiers":[
        {
            "category":"Retail",
            "subcategory":"Laundry & Dry Cleaning",
            "type":"Services"
        },
        {
            "category":"Building & Trades",
            "subcategory":"Cleaning & Sanitation",
            "type":"Services"
        }
    ],
    "sg:phone":"+1 608 295 8889",
    "sg:postcode":"53546",
    "sg:province":"WI",
    "sg:tags":[
        "cleaner",
        "house"
    ],
    "wof:name":"Happy Homes Cleaning Crew",
    "wof:placetype":"venue"
},
  "geometry": {"coordinates":[-88.979251,42.682915],"type":"Point"}
}