{
  "type": "Feature",
  "properties": {
    "addr:full":"4143 State Hwy 13 Wisconsin Dells WI 53965",
    "addr:housenumber":"4143",
    "addr:postcode":"53965",
    "addr:street":"State Hwy 13",
    "iso:country":"US",
    "sg:address":"4143 State Hwy 13",
    "sg:city":"Wisconsin Dells",
    "sg:classifiers":[
        {
            "category":"Manufacturing",
            "subcategory":"Printing",
            "type":"Manufacturing & Wholesale Goods"
        }
    ],
    "sg:phone":"+1 608 253 3333",
    "sg:postcode":"53965",
    "sg:province":"WI",
    "sg:tags":[
        "communication"
    ],
    "wof:name":"Verizon",
    "wof:placetype":"venue"
},
  "geometry": {"coordinates":[-89.767127,43.650696],"type":"Point"}
}