{
  "type": "Feature",
  "properties": {
    "addr:full":"1027 N Hillcrest Pkwy Altoona WI 54720",
    "addr:housenumber":"1027",
    "addr:postcode":"54720",
    "addr:street":"N Hillcrest Pkwy",
    "iso:country":"US",
    "sg:address":"1027 N Hillcrest Pkwy",
    "sg:city":"Altoona",
    "sg:classifiers":[
        {
            "category":"Restaurant",
            "type":"Food & Drink"
        }
    ],
    "sg:menulink":"http://www.allmenus.com/wi/altoona/193847-noble-romans/menu/",
    "sg:phone":"+1 715 855 2447",
    "sg:postcode":"54720",
    "sg:province":"WI",
    "sg:tags":[
        "wrap",
        "italian",
        "american",
        "sandwich",
        "pizza"
    ],
    "wof:name":"Noble Roman's",
    "wof:placetype":"venue"
},
  "geometry": {"coordinates":[-91.442876,44.795772],"type":"Point"}
}