{
  "type": "Feature",
  "properties": {
    "addr:full":"820 N Summit Ave Oconomowoc WI 53066",
    "addr:housenumber":"820",
    "addr:postcode":"53066",
    "addr:street":"N Summit Ave",
    "iso:country":"US",
    "sg:address":"820 N Summit Ave",
    "sg:city":"Oconomowoc",
    "sg:classifiers":[
        {
            "category":"Health Services",
            "subcategory":"Doctor",
            "type":"Services"
        }
    ],
    "sg:phone":"+1 262 567 6927",
    "sg:postcode":"53066",
    "sg:province":"WI",
    "sg:tags":[
        "medical"
    ],
    "wof:name":"Kelly Medical Services",
    "wof:placetype":"venue"
},
  "geometry": {"coordinates":[-88.462653,43.041253],"type":"Point"}
}