{
  "type": "Feature",
  "properties": {
    "iso:country":"US",
    "sg:address":"3760 N 169th St",
    "sg:city":"Brookfield",
    "sg:classifiers":[
        {
            "category":"Wholesale",
            "subcategory":"Auto Parts",
            "type":"Manufacturing & Wholesale Goods"
        }
    ],
    "sg:phone":"+1 262 781 8340",
    "sg:postcode":"53005",
    "sg:province":"WI",
    "wof:name":"CAM Distributing Co Inc",
    "wof:placetype":"venue"
},
  "geometry": {"coordinates":[-88.122207,43.086851],"type":"Point"}
}