{
  "type": "Feature",
  "properties": {
    "iso:country":"US",
    "sg:address":"5048 Douglas Ave",
    "sg:city":"Racine",
    "sg:classifiers":[
        {
            "category":"Autos & Motor Vehicles",
            "subcategory":"Auto Supplies",
            "type":"Retail Goods"
        }
    ],
    "sg:phone":"+1 262 639 8881",
    "sg:postcode":"53402",
    "sg:province":"WI",
    "sg:tags":[
        "automotive",
        "general",
        "tire",
        "repair"
    ],
    "wof:name":"Racine Tire & Auto Service",
    "wof:placetype":"venue"
},
  "geometry": {"coordinates":[-87.811645,42.788443],"type":"Point"}
}