{
  "type": "Feature",
  "properties": {
    "iso:country":"US",
    "sg:address":"6701 Bristol Rd",
    "sg:city":"Bristol",
    "sg:classifiers":[
        {
            "category":"Building & Trades",
            "subcategory":"Construction",
            "type":"Services"
        }
    ],
    "sg:phone":"+1 262 857 7455",
    "sg:postcode":"53104",
    "sg:province":"WI",
    "sg:tags":[
        "contractor"
    ],
    "wof:name":"Right Way Roofing LLC",
    "wof:placetype":"venue"
},
  "geometry": {"coordinates":[-88.04673699999999,42.570374],"type":"Point"}
}