{
  "type": "Feature",
  "properties": {
    "iso:country":"US",
    "sg:address":"4026 N Morris Blvd",
    "sg:city":"Milwaukee",
    "sg:classifiers":[
        {
            "category":"Manufacturing",
            "subcategory":"Chemicals & Compounds",
            "type":"Manufacturing & Wholesale Goods"
        }
    ],
    "sg:phone":"+1 414 961 7190",
    "sg:postcode":"53211",
    "sg:province":"WI",
    "sg:tags":[
        "plastic"
    ],
    "wof:name":"Bamberger Polymers Inc",
    "wof:placetype":"venue"
},
  "geometry": {"coordinates":[-87.892276,43.089729],"type":"Point"}
}