{
  "type": "Feature",
  "properties": {
    "iso:country":"US",
    "sg:address":"3875 Hollywood Rd",
    "sg:city":"Marathon",
    "sg:classifiers":[
        {
            "category":"Recreation",
            "type":"Entertainment"
        }
    ],
    "sg:phone":"+1 715 355 5644",
    "sg:postcode":"54448",
    "sg:province":"WI",
    "wof:name":"S & R Ranch",
    "wof:placetype":"venue"
},
  "geometry": {"coordinates":[-89.747916,44.907549],"type":"Point"}
}