{
  "type": "Feature",
  "properties": {
    "addr:full":"85 Riverside Sq Prairie Du Chien WI 53821",
    "addr:housenumber":"85",
    "addr:postcode":"53821",
    "addr:street":"Riverside Sq",
    "iso:country":"US",
    "sg:address":"85 Riverside Sq",
    "sg:city":"Prairie Du Chien",
    "sg:classifiers":[
        {
            "category":"Shopping",
            "subcategory":"Music",
            "type":"Retail Goods"
        },
        {
            "category":"Cinema",
            "subcategory":"Movie Rental",
            "type":"Entertainment"
        }
    ],
    "sg:phone":"+1 608 326 4722",
    "sg:postcode":"53821",
    "sg:province":"WI",
    "sg:tags":[
        "video",
        "disc",
        "tape",
        "cassette"
    ],
    "wof:name":"Box Office Video Inc",
    "wof:placetype":"venue"
},
  "geometry": {"coordinates":[-91.125371,43.026038],"type":"Point"}
}