{
  "type": "Feature",
  "properties": {
    "iso:country":"US",
    "sg:address":"389 N Falls St",
    "sg:city":"River Falls",
    "sg:classifiers":[
        {
            "category":"Professional",
            "subcategory":"Business Services",
            "type":"Services"
        }
    ],
    "sg:phone":"+1 715 426 9738",
    "sg:postcode":"54022",
    "sg:province":"WI",
    "wof:name":"D & P Inspections Ltd",
    "wof:placetype":"venue"
},
  "geometry": {"coordinates":[-92.633613,44.860821],"type":"Point"}
}