{
  "type": "Feature",
  "properties": {
    "iso:country":"US",
    "sg:address":"206 Travis Ln",
    "sg:city":"Waukesha",
    "sg:classifiers":[
        {
            "category":"Building & Trades",
            "subcategory":"Construction",
            "type":"Services"
        }
    ],
    "sg:phone":"+1 262 542 2443",
    "sg:postcode":"53189",
    "sg:province":"WI",
    "sg:tags":[
        "resurfacing",
        "laying",
        "refinishing",
        "floor"
    ],
    "wof:name":"Big Three Performance",
    "wof:placetype":"venue"
},
  "geometry": {"coordinates":[-88.229332,42.976047],"type":"Point"}
}