{
  "type": "Feature",
  "properties": {
    "iso:country":"US",
    "sg:address":"6019 Co Rd Y",
    "sg:city":"Johnson Creek",
    "sg:classifiers":[
        {
            "category":"Restaurant",
            "type":"Food & Drink"
        }
    ],
    "sg:phone":"+1 920 699 5782",
    "sg:postcode":"53038",
    "sg:province":"WI",
    "sg:tags":[
        "eating",
        "caterer"
    ],
    "wof:name":"Capn's Deli",
    "wof:placetype":"venue"
},
  "geometry": {"coordinates":[-88.775872,43.085516],"type":"Point"}
}