{
  "type": "Feature",
  "properties": {
    "iso:country":"US",
    "sg:address":"120 Main St E",
    "sg:city":"Ashland",
    "sg:classifiers":[
        {
            "category":"Real Estate",
            "subcategory":"Architect",
            "type":"Services"
        }
    ],
    "sg:phone":"+1 715 682 0330",
    "sg:postcode":"54806",
    "sg:province":"WI",
    "sg:website":"www.csdesignengineering.com",
    "wof:name":"C & S Design Engineering Inc",
    "wof:placetype":"venue"
},
  "geometry": {"coordinates":[-90.88214,46.591864],"type":"Point"}
}