{
  "type": "Feature",
  "properties": {
    "iso:country":"US",
    "sg:address":"851 E Olson St",
    "sg:city":"Blair",
    "sg:classifiers":[
        {
            "category":"Social Services",
            "subcategory":"Child Care",
            "type":"Services"
        }
    ],
    "sg:phone":"+1 608 989 2784",
    "sg:postcode":"54616",
    "sg:province":"WI",
    "sg:tags":[
        "day"
    ],
    "wof:name":"Wanda Anderegg Daycare",
    "wof:placetype":"venue"
},
  "geometry": {"coordinates":[-91.22030700000001,44.292795],"type":"Point"}
}