{
  "type": "Feature",
  "properties": {
    "addr:full":"131 E Wisconsin Ave Pewaukee WI 53072",
    "addr:housenumber":"131",
    "addr:postcode":"53072",
    "addr:street":"E Wisconsin Ave",
    "iso:country":"US",
    "sg:address":"131 E Wisconsin Ave",
    "sg:city":"Pewaukee",
    "sg:classifiers":[
        {
            "category":"Retail",
            "subcategory":"Laundry & Dry Cleaning",
            "type":"Services"
        }
    ],
    "sg:phone":"+1 262 691 1209",
    "sg:postcode":"53072",
    "sg:province":"WI",
    "sg:tags":[
        "equipment"
    ],
    "wof:name":"Haiges Machinery Inc",
    "wof:placetype":"venue"
},
  "geometry": {"coordinates":[-88.261374,43.081394],"type":"Point"}
}