{
  "type": "Feature",
  "properties": {
    "addr:full":"11225 N Prairie View Ln Mequon WI 53092",
    "addr:housenumber":"11225",
    "addr:postcode":"53092",
    "addr:street":"N Prairie View Ln",
    "iso:country":"US",
    "sg:address":"11225 N Prairie View Ln",
    "sg:city":"Mequon",
    "sg:classifiers":[
        {
            "category":"Real Estate",
            "subcategory":"Real Estate Agent",
            "type":"Services"
        }
    ],
    "sg:phone":"+1 262 241 9755",
    "sg:postcode":"53092",
    "sg:province":"WI",
    "sg:tags":[
        "consultant"
    ],
    "wof:name":"Keith Granzin",
    "wof:placetype":"venue"
},
  "geometry": {"coordinates":[-87.91655799999999,43.223739],"type":"Point"}
}