{
  "type": "Feature",
  "properties": {
    "addr:full":"514 N Webb Ave Reedsburg WI 53959",
    "addr:housenumber":"514",
    "addr:postcode":"53959",
    "addr:street":"N Webb Ave",
    "iso:country":"US",
    "sg:address":"514 N Webb Ave",
    "sg:city":"Reedsburg",
    "sg:classifiers":[
        {
            "category":"Education",
            "subcategory":"Special Training",
            "type":"Public Place"
        }
    ],
    "sg:phone":"+1 608 524 2824",
    "sg:postcode":"53959",
    "sg:province":"WI",
    "wof:name":"Toastmasters International",
    "wof:placetype":"venue"
},
  "geometry": {"coordinates":[-90.010228,43.537742],"type":"Point"}
}