{
  "type": "Feature",
  "properties": {
    "addr:full":"921 1st Ave Woodruff WI 54568",
    "addr:housenumber":"921",
    "addr:postcode":"54568",
    "addr:street":"1St Ave",
    "iso:country":"US",
    "sg:address":"921 1st Ave",
    "sg:city":"Woodruff",
    "sg:classifiers":[
        {
            "category":"Education",
            "subcategory":"Dance Studio",
            "type":"Public Place"
        }
    ],
    "sg:phone":"+1 715 358 1937",
    "sg:postcode":"54568",
    "sg:province":"WI",
    "sg:tags":[
        "instruction",
        "dancing"
    ],
    "wof:name":"Celebration Studios",
    "wof:placetype":"venue"
},
  "geometry": {"coordinates":[-89.698896,45.896662],"type":"Point"}
}