{
  "type": "Feature",
  "properties": {
    "iso:country":"US",
    "sg:address":"2224 W Mallory Ave",
    "sg:city":"Milwaukee",
    "sg:classifiers":[
        {
            "category":"Government",
            "subcategory":"Fire Station",
            "type":"Public Place"
        }
    ],
    "sg:phone":"+1 414 281 0747",
    "sg:postcode":"53221",
    "sg:province":"WI",
    "sg:tags":[
        "consultant",
        "protection"
    ],
    "wof:name":"Milwaukee Fire Department",
    "wof:placetype":"venue"
},
  "geometry": {"coordinates":[-87.942295,42.946004],"type":"Point"}
}