{
  "type": "Feature",
  "properties": {
    "iso:country":"US",
    "sg:address":"6560 Spruce Rd",
    "sg:city":"Arpin",
    "sg:classifiers":[
        {
            "category":"Building & Trades",
            "subcategory":"Landscaping Services",
            "type":"Services"
        }
    ],
    "sg:phone":"+1 715 652 3294",
    "sg:postcode":"54410",
    "sg:province":"WI",
    "wof:name":"Premium Lawn Care",
    "wof:placetype":"venue"
},
  "geometry": {"coordinates":[-90.047862,44.555302],"type":"Point"}
}