{
  "type": "Feature",
  "properties": {
    "iso:country":"US",
    "sg:address":"7365 Co Rd Y",
    "sg:city":"Watertown",
    "sg:classifiers":[
        {
            "category":"Manufacturing",
            "subcategory":"Wood Products",
            "type":"Manufacturing & Wholesale Goods"
        }
    ],
    "sg:phone":"+1 920 699 5931",
    "sg:postcode":"53094",
    "sg:province":"WI",
    "sg:tags":[
        "mfg"
    ],
    "wof:name":"Dennis Timm",
    "wof:placetype":"venue"
},
  "geometry": {"coordinates":[-88.77146,43.110834],"type":"Point"}
}