{
  "type": "Feature",
  "properties": {
    "addr:full":"1110 E Amelia St Cassville WI 53806",
    "addr:housenumber":"1110",
    "addr:postcode":"53806",
    "addr:street":"E Amelia St",
    "iso:country":"US",
    "sg:address":"1110 E Amelia St",
    "sg:city":"Cassville",
    "sg:classifiers":[
        {
            "category":"Restaurant",
            "type":"Food & Drink"
        }
    ],
    "sg:phone":"+1 608 725 5055",
    "sg:postcode":"53806",
    "sg:province":"WI",
    "sg:tags":[
        "center",
        "bowling"
    ],
    "wof:name":"Sand Bar Lounge & Lanes",
    "wof:placetype":"venue"
},
  "geometry": {"coordinates":[-90.98305499999999,42.710201],"type":"Point"}
}