{
  "type": "Feature",
  "properties": {
    "iso:country":"US",
    "sg:address":"3863 Clover Ln",
    "sg:city":"Madison",
    "sg:classifiers":[
        {
            "category":"Retail",
            "subcategory":"Repair Shop",
            "type":"Services"
        }
    ],
    "sg:phone":"+1 608 241 1305",
    "sg:postcode":"53714",
    "sg:province":"WI",
    "wof:name":"Ace Auto Upholstery",
    "wof:placetype":"venue"
},
  "geometry": {"coordinates":[-89.32229700000001,43.085694],"type":"Point"}
}