{
  "type": "Feature",
  "properties": {
    "iso:country":"US",
    "sg:address":"36393 Maranatha Pl",
    "sg:city":"Whitehall",
    "sg:classifiers":[
        {
            "category":"Manufacturing",
            "subcategory":"Signs",
            "type":"Manufacturing & Wholesale Goods"
        }
    ],
    "sg:phone":"+1 715 538 2170",
    "sg:postcode":"54773",
    "sg:province":"WI",
    "sg:tags":[
        "body",
        "auto",
        "specialty",
        "mfg"
    ],
    "wof:name":"Speltz Sign Company",
    "wof:placetype":"venue"
},
  "geometry": {"coordinates":[-91.32456,44.368308],"type":"Point"}
}