{
  "type": "Feature",
  "properties": {
    "iso:country":"US",
    "sg:address":"2616 S Oneida St",
    "sg:city":"Appleton",
    "sg:classifiers":[
        {
            "category":"Organizations",
            "subcategory":"Professional Association",
            "type":"Services"
        }
    ],
    "sg:phone":"+1 920 832 9360",
    "sg:postcode":"54915",
    "sg:province":"WI",
    "sg:tags":[
        "affairs",
        "community"
    ],
    "wof:name":"Volunteer Ctr E Centl WI Inc",
    "wof:placetype":"venue"
},
  "geometry": {"coordinates":[-88.403966,44.238352],"type":"Point"}
}