{
  "type": "Feature",
  "properties": {
    "addr:full":"265 200th Ave Comstock WI 54826",
    "addr:housenumber":"265",
    "addr:postcode":"54826",
    "addr:street":"200Th Ave",
    "iso:country":"US",
    "sg:address":"265 200th Ave",
    "sg:city":"Comstock",
    "sg:classifiers":[
        {
            "category":"Farming",
            "subcategory":"Dairy Farm",
            "type":"Manufacturing & Wholesale Goods"
        }
    ],
    "sg:phone":"+1 715 822 4115",
    "sg:postcode":"54826",
    "sg:province":"WI",
    "wof:name":"Ronald Catlin",
    "wof:placetype":"venue"
},
  "geometry": {"coordinates":[-92.20902100000001,45.496529],"type":"Point"}
}