{
  "type": "Feature",
  "properties": {
    "addr:full":"8697 Moh He Con Nuck Rd Bowler WI 54416",
    "addr:housenumber":"8697",
    "addr:postcode":"54416",
    "addr:street":"Moh;Nuck Rd",
    "iso:country":"US",
    "sg:address":"8697 Moh He Con Nuck Rd",
    "sg:city":"Bowler",
    "sg:classifiers":[
        {
            "category":"Health Services",
            "subcategory":"Nursing And Care Facility",
            "type":"Services"
        }
    ],
    "sg:phone":"+1 715 793 4537",
    "sg:postcode":"54416",
    "sg:province":"WI",
    "sg:tags":[
        "home",
        "retirement",
        "community"
    ],
    "wof:name":"Ella Besaw Ctr",
    "wof:placetype":"venue"
},
  "geometry": {"coordinates":[-88.941152,44.91797],"type":"Point"}
}