{
  "type": "Feature",
  "properties": {
    "iso:country":"US",
    "sg:address":"2090 Oxbo Rd",
    "sg:city":"Stratford",
    "sg:classifiers":[
        {
            "category":"Farming",
            "subcategory":"Farm",
            "type":"Manufacturing & Wholesale Goods"
        }
    ],
    "sg:phone":"+1 715 387 3161",
    "sg:postcode":"54484",
    "sg:province":"WI",
    "sg:tags":[
        "crop",
        "general"
    ],
    "wof:name":"Ken Spindler",
    "wof:placetype":"venue"
},
  "geometry": {"coordinates":[-90.005532,44.757514],"type":"Point"}
}