{
  "type": "Feature",
  "properties": {
    "iso:country":"US",
    "sg:address":"1390 E Adam Dr",
    "sg:city":"De Pere",
    "sg:classifiers":[
        {
            "category":"Professional",
            "subcategory":"Computer Services",
            "type":"Services"
        }
    ],
    "sg:phone":"+1 920 347 1976",
    "sg:postcode":"54115",
    "sg:province":"WI",
    "sg:tags":[
        "consultant",
        "designer"
    ],
    "sg:website":"www.bayten.net",
    "wof:name":"Bay Ten Information Svc Inc",
    "wof:placetype":"venue"
},
  "geometry": {"coordinates":[-88.12049399999999,44.474267],"type":"Point"}
}