{
  "type": "Feature",
  "properties": {
    "iso:country":"US",
    "sg:address":"5498 Main St",
    "sg:city":"Auburndale",
    "sg:classifiers":[
        {
            "category":"Restaurant",
            "type":"Food & Drink"
        }
    ],
    "sg:phone":"+1 715 652 3355",
    "sg:postcode":"54412",
    "sg:province":"WI",
    "wof:name":"Patty K's Cafe",
    "wof:placetype":"venue"
},
  "geometry": {"coordinates":[-89.994767,44.625208],"type":"Point"}
}