{
  "type": "Feature",
  "properties": {
    "addr:full":"3200 S 20th St Milwaukee WI 53215",
    "addr:housenumber":"3200",
    "addr:postcode":"53215",
    "addr:street":"S 20Th St",
    "iso:country":"US",
    "sg:address":"3200 S 20th St",
    "sg:city":"Milwaukee",
    "sg:classifiers":[
        {
            "category":"Health Services",
            "subcategory":"Nursing And Care Facility",
            "type":"Services"
        }
    ],
    "sg:phone":"+1 414 389 3200",
    "sg:postcode":"53215",
    "sg:province":"WI",
    "sg:tags":[
        "skilled"
    ],
    "wof:name":"Terrace At St Francis",
    "wof:placetype":"venue"
},
  "geometry": {"coordinates":[-87.93862300000001,42.984781],"type":"Point"}
}