{
  "type": "Feature",
  "properties": {
    "iso:country":"US",
    "sg:address":"3647 Charles St",
    "sg:city":"Racine",
    "sg:classifiers":[
        {
            "category":"Building & Trades",
            "subcategory":"Pest Control",
            "type":"Services"
        }
    ],
    "sg:phone":"+1 262 639 9267",
    "sg:postcode":"53402",
    "sg:province":"WI",
    "wof:name":"Abel Fraga's Pest Control",
    "wof:placetype":"venue"
},
  "geometry": {"coordinates":[-87.796834,42.765325],"type":"Point"}
}