{
  "type": "Feature",
  "properties": {
    "iso:country":"US",
    "sg:address":"1100 Green Valley Rd",
    "sg:city":"Beaver Dam",
    "sg:classifiers":[
        {
            "category":"Manufacturing",
            "subcategory":"Tools & Machinery",
            "type":"Manufacturing & Wholesale Goods"
        }
    ],
    "sg:phone":"+1 920 356 0372",
    "sg:postcode":"53916",
    "sg:province":"WI",
    "sg:tags":[
        "industry",
        "mfg"
    ],
    "wof:name":"Stainless Equipment Design",
    "wof:placetype":"venue"
},
  "geometry": {"coordinates":[-88.831839,43.474344],"type":"Point"}
}