{
  "type": "Feature",
  "properties": {
    "iso:country":"US",
    "sg:address":"614 Bentwood Dr",
    "sg:city":"Marshall",
    "sg:classifiers":[
        {
            "category":"Professional",
            "subcategory":"Computer Services",
            "type":"Services"
        }
    ],
    "sg:phone":"+1 608 655 4624",
    "sg:postcode":"53559",
    "sg:province":"WI",
    "sg:tags":[
        "datum"
    ],
    "wof:name":"Greencomma Web Designs",
    "wof:placetype":"venue"
},
  "geometry": {"coordinates":[-89.053523,43.172891],"type":"Point"}
}