{
  "type": "Feature",
  "properties": {
    "addr:full":"940 W Heritage Ct Thiensville WI 53092",
    "addr:housenumber":"940",
    "addr:postcode":"53092",
    "addr:street":"W Heritage Ct",
    "iso:country":"US",
    "sg:address":"940 W Heritage Ct",
    "sg:city":"Thiensville",
    "sg:classifiers":[
        {
            "category":"Building & Trades",
            "subcategory":"Construction",
            "type":"Services"
        }
    ],
    "sg:phone":"+1 262 240 0733",
    "sg:postcode":"53092",
    "sg:province":"WI",
    "sg:tags":[
        "contractor"
    ],
    "wof:name":"Kitchens & Grdns By Labor Love",
    "wof:placetype":"venue"
},
  "geometry": {"coordinates":[-87.92097099999999,43.193898],"type":"Point"}
}