{
  "type": "Feature",
  "properties": {
    "iso:country":"US",
    "sg:address":"92 S Main St",
    "sg:city":"Clintonville",
    "sg:classifiers":[
        {
            "category":"Real Estate",
            "subcategory":"Real Estate Agent",
            "type":"Services"
        }
    ],
    "sg:phone":"+1 715 823 7653",
    "sg:postcode":"54929",
    "sg:province":"WI",
    "wof:name":"Schroeder-Luedtke Realty",
    "wof:placetype":"venue"
},
  "geometry": {"coordinates":[-88.762058,44.619584],"type":"Point"}
}