{
  "type": "Feature",
  "properties": {
    "iso:country":"US",
    "sg:address":"6010 Co Rd C",
    "sg:city":"Seymour",
    "sg:phone":"+1 920 833 7952",
    "sg:postcode":"54165",
    "sg:province":"WI",
    "sg:tags":[
        "farm",
        "corn"
    ],
    "wof:name":"Oneida Nation Farms",
    "wof:placetype":"venue"
},
  "geometry": {"coordinates":[-88.330693,44.445057],"type":"Point"}
}