{
  "type": "Feature",
  "properties": {
    "iso:country":"US",
    "sg:address":"18600 Beverly Hills Dr",
    "sg:city":"Brookfield",
    "sg:classifiers":[
        {
            "category":"Home & Garden",
            "subcategory":"Building Materials",
            "type":"Retail Goods"
        },
        {
            "category":"Building & Trades",
            "subcategory":"Construction",
            "type":"Services"
        }
    ],
    "sg:phone":"+1 262 781 9300",
    "sg:postcode":"53045",
    "sg:province":"WI",
    "sg:tags":[
        "concrete-stamped",
        "contractor",
        "concrete",
        "decorative",
        "staining"
    ],
    "sg:website":"http://www.concreteconceptswi.com",
    "wof:name":"Concrete Concepts",
    "wof:placetype":"venue"
},
  "geometry": {"coordinates":[-88.143242,43.079269],"type":"Point"}
}