{
  "type": "Feature",
  "properties": {
    "iso:country":"US",
    "sg:address":"12601 224th Ave",
    "sg:city":"Benet Lake",
    "sg:classifiers":[
        {
            "category":"Wholesale",
            "subcategory":"Durable Goods & Equipment",
            "type":"Manufacturing & Wholesale Goods"
        }
    ],
    "sg:phone":"+1 262 396 4188",
    "sg:postcode":"53102",
    "sg:province":"WI",
    "sg:tags":[
        "representative",
        "manufacturer"
    ],
    "wof:name":"Wilson Tyler Group Inc",
    "wof:placetype":"venue"
},
  "geometry": {"coordinates":[-88.078814,42.498857],"type":"Point"}
}