{
  "type": "Feature",
  "properties": {
    "iso:country":"US",
    "sg:address":"10710 270th Ave",
    "sg:city":"New Auburn",
    "sg:classifiers":[
        {
            "category":"Retail",
            "subcategory":"Repair Shop",
            "type":"Services"
        }
    ],
    "sg:phone":"+1 715 967 2812",
    "sg:postcode":"54757",
    "sg:province":"WI",
    "wof:name":"Midwest Satellite Services",
    "wof:placetype":"venue"
},
  "geometry": {"coordinates":[-91.466508,45.235247],"type":"Point"}
}