{
  "type": "Feature",
  "properties": {
    "iso:country":"US",
    "sg:address":"418 22nd Ave",
    "sg:city":"Somers",
    "sg:classifiers":[
        {
            "category":"Retail",
            "subcategory":"Auto Repair",
            "type":"Services"
        }
    ],
    "sg:phone":"+1 262 886 0838",
    "sg:postcode":"53140",
    "sg:province":"WI",
    "sg:tags":[
        "body",
        "installation",
        "truck",
        "equipment"
    ],
    "wof:name":"Garski Truck and Equipment",
    "wof:placetype":"venue"
},
  "geometry": {"coordinates":[-87.835932,42.653195],"type":"Point"}
}