{
  "type": "Feature",
  "properties": {
    "iso:country":"US",
    "sg:address":"6862 State Hwy 113",
    "sg:city":"Dane",
    "sg:classifiers":[
        {
            "category":"Professional",
            "subcategory":"Business Services",
            "type":"Services"
        }
    ],
    "sg:phone":"+1 608 849 8979",
    "sg:postcode":"53529",
    "sg:province":"WI",
    "wof:name":"Greiber Enterprises",
    "wof:placetype":"venue"
},
  "geometry": {"coordinates":[-89.47134,43.233336],"type":"Point"}
}