{
  "type": "Feature",
  "properties": {
    "addr:full":"202 Pine St Redgranite WI 54970",
    "addr:housenumber":"202",
    "addr:postcode":"54970",
    "addr:street":"Pine St",
    "iso:country":"US",
    "sg:address":"202 Pine St",
    "sg:city":"Redgranite",
    "sg:classifiers":[
        {
            "category":"Social Services",
            "type":"Services"
        }
    ],
    "sg:phone":"+1 920 566 0130",
    "sg:postcode":"54970",
    "sg:province":"WI",
    "wof:name":"Redgranite Nutrition Site",
    "wof:placetype":"venue"
},
  "geometry": {"coordinates":[-89.10915300000001,44.044612],"type":"Point"}
}