{
  "type": "Feature",
  "properties": {
    "iso:country":"US",
    "sg:address":"1134 Bellview Dr",
    "sg:city":"Wisconsin Rapids",
    "sg:classifiers":[
        {
            "category":"Personal",
            "type":"Services"
        }
    ],
    "sg:phone":"+1 715 325 7900",
    "sg:postcode":"54494",
    "sg:province":"WI",
    "wof:name":"Lees Yard & Home Maintenance",
    "wof:placetype":"venue"
},
  "geometry": {"coordinates":[-89.81154100000001,44.317982],"type":"Point"}
}