{
  "type": "Feature",
  "properties": {
    "addr:full":"511 Aber Dr Waterford WI 53185",
    "addr:housenumber":"511",
    "addr:postcode":"53185",
    "addr:street":"Aber Dr",
    "iso:country":"US",
    "sg:address":"511 Aber Dr",
    "sg:city":"Waterford",
    "sg:classifiers":[
        {
            "category":"Health Services",
            "subcategory":"Doctor",
            "type":"Services"
        }
    ],
    "sg:phone":"+1 262 534 6514",
    "sg:postcode":"53185",
    "sg:province":"WI",
    "sg:tags":[
        "dentist"
    ],
    "wof:name":"Sharon Ruetz-Smith DDS",
    "wof:placetype":"venue"
},
  "geometry": {"coordinates":[-88.20687599999999,42.763905],"type":"Point"}
}