{
  "type": "Feature",
  "properties": {
    "addr:full":"7060 Holy Cross Rd Fifield WI 54524",
    "addr:housenumber":"7060",
    "addr:postcode":"54524",
    "addr:street":"Holy Cross Rd",
    "iso:country":"US",
    "sg:address":"7060 Holy Cross Rd",
    "sg:city":"Fifield",
    "sg:classifiers":[
        {
            "category":"Organizations",
            "subcategory":"Religious Organization",
            "type":"Services"
        }
    ],
    "sg:phone":"+1 715 339 4030",
    "sg:postcode":"54524",
    "sg:province":"WI",
    "sg:tags":[
        "church"
    ],
    "wof:name":"Cornerstone Community Church",
    "wof:placetype":"venue"
},
  "geometry": {"coordinates":[-90.40270200000001,45.794105],"type":"Point"}
}