{
  "type": "Feature",
  "properties": {
    "addr:full":"7462 Main St W Webster WI 54893",
    "addr:housenumber":"7462",
    "addr:postcode":"54893",
    "addr:street":"Main St W",
    "iso:country":"US",
    "sg:address":"7462 Main St W",
    "sg:city":"Webster",
    "sg:classifiers":[
        {
            "category":"Bars & Pubs",
            "type":"Food & Drink"
        }
    ],
    "sg:phone":"+1 715 866 8650",
    "sg:postcode":"54893",
    "sg:province":"WI",
    "wof:name":"Black & Orange Liquor & Bwlng",
    "wof:placetype":"venue"
},
  "geometry": {"coordinates":[-92.368075,45.877503],"type":"Point"}
}