{
  "type": "Feature",
  "properties": {
    "iso:country":"US",
    "sg:address":"4590 W Ravine Ln",
    "sg:city":"Milwaukee",
    "sg:classifiers":[
        {
            "category":"Professional",
            "subcategory":"Business Services",
            "type":"Services"
        }
    ],
    "sg:phone":"+1 414 355 6946",
    "sg:postcode":"53223",
    "sg:province":"WI",
    "wof:name":"Gmk Electronics Test & Repair",
    "wof:placetype":"venue"
},
  "geometry": {"coordinates":[-87.96812799999999,43.190246],"type":"Point"}
}