{
  "type": "Feature",
  "properties": {
    "iso:country":"US",
    "sg:address":"473 Countryview Rd",
    "sg:city":"Hudson",
    "sg:classifiers":[
        {
            "category":"Professional",
            "type":"Services"
        }
    ],
    "sg:phone":"+1 715 381 0063",
    "sg:postcode":"54016",
    "sg:province":"WI",
    "wof:name":"Wmrs Inc",
    "wof:placetype":"venue"
},
  "geometry": {"coordinates":[-92.707423,44.966193],"type":"Point"}
}