{
  "type": "Feature",
  "properties": {
    "iso:country":"US",
    "sg:address":"911 E Grand Ave",
    "sg:city":"Beloit",
    "sg:classifiers":[
        {
            "category":"Personal",
            "subcategory":"Beauty Salon",
            "type":"Services"
        }
    ],
    "sg:phone":"+1 608 362 5995",
    "sg:postcode":"53511",
    "sg:province":"WI",
    "sg:tags":[
        "shop"
    ],
    "wof:name":"Shear Images",
    "wof:placetype":"venue"
},
  "geometry": {"coordinates":[-89.026768,42.499727],"type":"Point"}
}