{
  "type": "Feature",
  "properties": {
    "addr:full":"105 S Main St Lodi WI 53555",
    "addr:housenumber":"105",
    "addr:postcode":"53555",
    "addr:street":"S Main St",
    "iso:country":"US",
    "sg:address":"105 S Main St",
    "sg:city":"Lodi",
    "sg:classifiers":[
        {
            "category":"Personal",
            "type":"Services"
        }
    ],
    "sg:phone":"+1 608 592 7866",
    "sg:postcode":"53555",
    "sg:province":"WI",
    "wof:name":"Sunsations Tan Salon",
    "wof:placetype":"venue"
},
  "geometry": {"coordinates":[-89.526589,43.313943],"type":"Point"}
}