{
  "type": "Feature",
  "properties": {
    "iso:country":"US",
    "sg:address":"4733 Green Valley Rd",
    "sg:city":"Krakow",
    "sg:classifiers":[
        {
            "category":"Shopping",
            "subcategory":"Florist",
            "type":"Retail Goods"
        }
    ],
    "sg:phone":"+1 920 899 3404",
    "sg:postcode":"54137",
    "sg:province":"WI",
    "wof:name":"Country Hutch",
    "wof:placetype":"venue"
},
  "geometry": {"coordinates":[-88.270511,44.753469],"type":"Point"}
}