{
  "type": "Feature",
  "properties": {
    "addr:full":"5510 Lacy Rd Fitchburg WI 53711",
    "addr:housenumber":"5510",
    "addr:postcode":"53711",
    "addr:street":"Lacy Rd",
    "iso:country":"US",
    "sg:address":"5510 Lacy Rd",
    "sg:city":"Fitchburg",
    "sg:classifiers":[
        {
            "category":"Social Services",
            "type":"Services"
        }
    ],
    "sg:phone":"+1 608 270 4290",
    "sg:postcode":"53711",
    "sg:province":"WI",
    "sg:tags":[
        "senior",
        "citizen"
    ],
    "wof:name":"Fitchburg Senior Ctr",
    "wof:placetype":"venue"
},
  "geometry": {"coordinates":[-89.413912,43.001767],"type":"Point"}
}