{
  "type": "Feature",
  "properties": {
    "iso:country":"US",
    "sg:address":"7309 Co Rd Jj",
    "sg:city":"Bancroft",
    "sg:classifiers":[
        {
            "category":"Real Estate",
            "subcategory":"Real Estate Agent",
            "type":"Services"
        }
    ],
    "sg:phone":"+1 715 366 4552",
    "sg:postcode":"54921",
    "sg:province":"WI",
    "wof:name":"Rettler Properties",
    "wof:placetype":"venue"
},
  "geometry": {"coordinates":[-89.473657,44.356037],"type":"Point"}
}