{
  "type": "Feature",
  "properties": {
    "iso:country":"US",
    "sg:address":"20 N Wilson Ave",
    "sg:city":"Rice Lake",
    "sg:classifiers":[
        {
            "category":"Utilities",
            "subcategory":"Telephone",
            "type":"Services"
        }
    ],
    "sg:phone":"+1 715 434 4282",
    "sg:postcode":"54868",
    "sg:province":"WI",
    "sg:tags":[
        "communications"
    ],
    "wof:name":"Cdc Telecom",
    "wof:placetype":"venue"
},
  "geometry": {"coordinates":[-91.73616,45.502367],"type":"Point"}
}