{
  "type": "Feature",
  "properties": {
    "iso:country":"US",
    "sg:address":"1631 Crooks St",
    "sg:city":"Green Bay",
    "sg:classifiers":[
        {
            "category":"Marine",
            "type":"Transportation"
        }
    ],
    "sg:phone":"+1 920 465 8727",
    "sg:postcode":"54302",
    "sg:province":"WI",
    "sg:tags":[
        "water",
        "operation",
        "transport"
    ],
    "wof:name":"Trik Sea Charters",
    "wof:placetype":"venue"
},
  "geometry": {"coordinates":[-87.986178,44.499188],"type":"Point"}
}