{
  "type": "Feature",
  "properties": {
    "iso:country":"US",
    "sg:address":"4101 Durand Ave",
    "sg:city":"Racine",
    "sg:classifiers":[
        {
            "category":"Shopping",
            "subcategory":"Discount & Variety Stores",
            "type":"Retail Goods"
        }
    ],
    "sg:phone":"+1 262 554 8701",
    "sg:postcode":"53405",
    "sg:province":"WI",
    "wof:name":"Big Lots",
    "wof:placetype":"venue"
},
  "geometry": {"coordinates":[-87.829633,42.696859],"type":"Point"}
}