{
  "type": "Feature",
  "properties": {
    "iso:country":"US",
    "sg:address":"619 W Wisconsin Ave",
    "sg:city":"Appleton",
    "sg:classifiers":[
        {
            "category":"Social Services",
            "type":"Services"
        }
    ],
    "sg:phone":"+1 920 731 3031",
    "sg:postcode":"54911",
    "sg:province":"WI",
    "sg:tags":[
        "organization",
        "welfare"
    ],
    "wof:name":"Elizabeth Ministry",
    "wof:placetype":"venue"
},
  "geometry": {"coordinates":[-88.415718,44.272837],"type":"Point"}
}