{
  "type": "Feature",
  "properties": {
    "iso:country":"US",
    "sg:address":"2711 S Afton Rd",
    "sg:city":"Beloit",
    "sg:classifiers":[
        {
            "category":"Organizations",
            "subcategory":"Community Association",
            "type":"Services"
        }
    ],
    "sg:phone":"+1 608 362 0299",
    "sg:postcode":"53511",
    "sg:province":"IL",
    "wof:name":"V F W",
    "wof:placetype":"venue"
},
  "geometry": {"coordinates":[-89.055755,42.547264],"type":"Point"}
}