{
  "type": "Feature",
  "properties": {
    "iso:country":"US",
    "sg:address":"17100 W North Ave",
    "sg:city":"Brookfield",
    "sg:classifiers":[
        {
            "category":"Health Services",
            "subcategory":"Doctor",
            "type":"Services"
        }
    ],
    "sg:phone":"+1 262 784 4451",
    "sg:postcode":"53005",
    "sg:province":"WI",
    "sg:tags":[
        "medical"
    ],
    "wof:name":"Michael R La Blanc",
    "wof:placetype":"venue"
},
  "geometry": {"coordinates":[-88.125188,43.061061],"type":"Point"}
}