{
  "type": "Feature",
  "properties": {
    "addr:full":"5877 State Hwy 57 Sturgeon Bay WI 54235",
    "addr:housenumber":"5877",
    "addr:postcode":"54235",
    "addr:street":"State Hwy 57",
    "iso:country":"US",
    "sg:address":"5877 State Hwy 57",
    "sg:city":"Sturgeon Bay",
    "sg:classifiers":[
        {
            "category":"Shopping",
            "type":"Retail Goods"
        }
    ],
    "sg:phone":"+1 920 823 2154",
    "sg:postcode":"54235",
    "sg:province":"WI",
    "sg:tags":[
        "gallery"
    ],
    "wof:name":"Martinez Studio",
    "wof:placetype":"venue"
},
  "geometry": {"coordinates":[-87.222356,44.953365],"type":"Point"}
}