{
  "type": "Feature",
  "properties": {
    "addr:full":"9185 Old Potosi Rd Lancaster WI 53813",
    "addr:housenumber":"9185",
    "addr:postcode":"53813",
    "addr:street":"Old Potosi Rd",
    "iso:country":"US",
    "sg:address":"9185 Old Potosi Rd",
    "sg:city":"Lancaster",
    "sg:classifiers":[
        {
            "category":"Organizations",
            "subcategory":"Non-profit Organization",
            "type":"Services"
        }
    ],
    "sg:phone":"+1 608 723 7551",
    "sg:postcode":"53813",
    "sg:province":"WI",
    "wof:name":"Wisconsin Pork Producers",
    "wof:placetype":"venue"
},
  "geometry": {"coordinates":[-90.72384,42.83179],"type":"Point"}
}