{
  "type": "Feature",
  "properties": {
    "iso:country":"US",
    "sg:address":"3332 W Lisbon Ave",
    "sg:city":"Milwaukee",
    "sg:classifiers":[
        {
            "category":"Organizations",
            "subcategory":"Religious Organization",
            "type":"Services"
        }
    ],
    "sg:phone":"+1 414 342 5522",
    "sg:postcode":"53208",
    "sg:province":"WI",
    "wof:name":"Peace Tmpl Chrch God In Chrst",
    "wof:placetype":"venue"
},
  "geometry": {"coordinates":[-87.956091,43.05456],"type":"Point"}
}