{
  "type": "Feature",
  "properties": {
    "addr:full":"3580 Co Hwy K Solon Springs WI 54871",
    "addr:housenumber":"3580",
    "addr:postcode":"54871",
    "addr:street":"Co Hwy K",
    "iso:country":"US",
    "sg:address":"3580 Co Hwy K",
    "sg:city":"Solon Springs",
    "sg:classifiers":[
        {
            "category":"Food & Beverages",
            "subcategory":"Groceries & Convenience Stores",
            "type":"Retail Goods"
        }
    ],
    "sg:phone":"+1 715 795 3248",
    "sg:postcode":"54871",
    "sg:province":"WI",
    "wof:name":"Friermood Spur",
    "wof:placetype":"venue"
},
  "geometry": {"coordinates":[-91.90862799999999,45.753417],"type":"Point"}
}