{
  "type": "Feature",
  "properties": {
    "iso:country":"US",
    "sg:address":"4209 Coon Valley Rd",
    "sg:city":"Fennimore",
    "sg:classifiers":[
        {
            "category":"Shopping",
            "subcategory":"Hobbies, Toys, & Games",
            "type":"Retail Goods"
        }
    ],
    "sg:phone":"+1 608 375 2493",
    "sg:postcode":"53809",
    "sg:province":"WI",
    "wof:name":"Scrapbook Nook",
    "wof:placetype":"venue"
},
  "geometry": {"coordinates":[-90.625982,43.061619],"type":"Point"}
}