{
  "type": "Feature",
  "properties": {
    "iso:country":"US",
    "sg:address":"8516 Fairway Pl",
    "sg:city":"Middleton",
    "sg:classifiers":[
        {
            "category":"Manufacturing",
            "subcategory":"Paper Products",
            "type":"Manufacturing & Wholesale Goods"
        }
    ],
    "sg:phone":"+1 608 836 7181",
    "sg:postcode":"53562",
    "sg:province":"WI",
    "sg:tags":[
        "packaging",
        "material"
    ],
    "wof:name":"Commercial Packaging",
    "wof:placetype":"venue"
},
  "geometry": {"coordinates":[-89.53531,43.10325],"type":"Point"}
}