{
  "type": "Feature",
  "properties": {
    "addr:full":"1825 Riverside Dr Green Bay WI 54301",
    "addr:housenumber":"1825",
    "addr:postcode":"54301",
    "addr:street":"Riverside Dr",
    "iso:country":"US",
    "sg:address":"1825 Riverside Dr",
    "sg:city":"Green Bay",
    "sg:classifiers":[
        {
            "category":"Organizations",
            "subcategory":"Professional Association",
            "type":"Services"
        }
    ],
    "sg:phone":"+1 920 432 3393",
    "sg:postcode":"54301",
    "sg:province":"WI",
    "wof:name":"United Way",
    "wof:placetype":"venue"
},
  "geometry": {"coordinates":[-88.02775099999999,44.486817],"type":"Point"}
}