{
  "type": "Feature",
  "properties": {
    "iso:country":"US",
    "sg:address":"313 Giddings Ave",
    "sg:city":"Sheboygan Falls",
    "sg:classifiers":[
        {
            "category":"Education",
            "subcategory":"School",
            "type":"Public Place"
        }
    ],
    "sg:phone":"+1 920 467 6291",
    "sg:postcode":"53085",
    "sg:province":"WI",
    "wof:name":"St Mary's School",
    "wof:placetype":"venue"
},
  "geometry": {"coordinates":[-87.815438,43.723122],"type":"Point"}
}