{
  "type": "Feature",
  "properties": {
    "iso:country":"US",
    "sg:address":"333 Wallace St",
    "sg:city":"Combined Locks",
    "sg:classifiers":[
        {
            "category":"Government",
            "subcategory":"Post Office",
            "type":"Public Place"
        }
    ],
    "sg:phone":"+1 920 687 6925",
    "sg:postcode":"54113",
    "sg:province":"WI",
    "sg:tags":[
        "postal",
        "us"
    ],
    "wof:name":"US Post Office",
    "wof:placetype":"venue"
},
  "geometry": {"coordinates":[-88.305626,44.266376],"type":"Point"}
}