{
  "type": "Feature",
  "properties": {
    "addr:full":"336 E Main St Twin Lakes WI 53181",
    "addr:housenumber":"336",
    "addr:postcode":"53181",
    "addr:street":"E Main St",
    "iso:country":"US",
    "sg:address":"336 E Main St",
    "sg:city":"Twin Lakes",
    "sg:classifiers":[
        {
            "category":"Real Estate",
            "subcategory":"Real Estate Agent",
            "type":"Services"
        }
    ],
    "sg:phone":"+1 262 877 2131",
    "sg:postcode":"53181",
    "sg:province":"WI",
    "sg:website":"www.cbprimus.com",
    "wof:name":"Coldwell Banker Primus",
    "wof:placetype":"venue"
},
  "geometry": {"coordinates":[-88.248763,42.532248],"type":"Point"}
}