{
  "type": "Feature",
  "properties": {
    "addr:full":"822 Cormier Rd Green Bay WI 54304",
    "addr:housenumber":"822",
    "addr:postcode":"54304",
    "addr:street":"Cormier Rd",
    "iso:country":"US",
    "sg:address":"822 Cormier Rd",
    "sg:city":"Green Bay",
    "sg:classifiers":[
        {
            "category":"Home & Garden",
            "subcategory":"Building Materials",
            "type":"Retail Goods"
        }
    ],
    "sg:phone":"+1 920 498 8411",
    "sg:postcode":"54304",
    "sg:province":"WI",
    "sg:tags":[
        "paint"
    ],
    "wof:name":"Lasting Impressions",
    "wof:placetype":"venue"
},
  "geometry": {"coordinates":[-88.06464699999999,44.489321],"type":"Point"}
}