{
  "type": "Feature",
  "properties": {
    "iso:country":"US",
    "sg:address":"131 W Maple Ave",
    "sg:city":"Beaver Dam",
    "sg:classifiers":[
        {
            "category":"Social Services",
            "type":"Services"
        }
    ],
    "sg:phone":"+1 920 887 9546",
    "sg:postcode":"53916",
    "sg:province":"WI",
    "sg:tags":[
        "counselor",
        "marriage",
        "family"
    ],
    "wof:name":"Catholic Charities",
    "wof:placetype":"venue"
},
  "geometry": {"coordinates":[-88.83886099999999,43.457241],"type":"Point"}
}