{
  "type": "Feature",
  "properties": {
    "addr:full":"4550 Clover Ln Eland WI 54427",
    "addr:housenumber":"4550",
    "addr:postcode":"54427",
    "addr:street":"Clover Ln",
    "iso:country":"US",
    "sg:address":"4550 Clover Ln",
    "sg:city":"Eland",
    "sg:classifiers":[
        {
            "category":"Freight",
            "type":"Transportation"
        }
    ],
    "sg:phone":"+1 715 454 7169",
    "sg:postcode":"54427",
    "sg:province":"WI",
    "sg:tags":[
        "operator",
        "trucking"
    ],
    "wof:name":"Rite A Way Express LLC",
    "wof:placetype":"venue"
},
  "geometry": {"coordinates":[-89.261268,44.870736],"type":"Point"}
}