{
  "type": "Feature",
  "properties": {
    "addr:full":"6919 Co Rd M Coleman WI 54112",
    "addr:housenumber":"6919",
    "addr:postcode":"54112",
    "addr:street":"Co Rd M",
    "iso:country":"US",
    "sg:address":"6919 Co Rd M",
    "sg:city":"Coleman",
    "sg:phone":"+1 920 897 2363",
    "sg:postcode":"54112",
    "sg:province":"WI",
    "sg:tags":[
        "farm",
        "corn",
        "soybean"
    ],
    "wof:name":"Larry Bittner",
    "wof:placetype":"venue"
},
  "geometry": {"coordinates":[-88.087102,45.009147],"type":"Point"}
}