{
  "type": "Feature",
  "properties": {
    "iso:country":"US",
    "sg:address":"4614 Co Rd A",
    "sg:city":"Oregon",
    "sg:classifiers":[
        {
            "category":"Building & Trades",
            "subcategory":"Plumbing",
            "type":"Services"
        }
    ],
    "sg:phone":"+1 608 835 2997",
    "sg:postcode":"53575",
    "sg:province":"WI",
    "sg:tags":[
        "contractor"
    ],
    "wof:name":"Martinson Drainage",
    "wof:placetype":"venue"
},
  "geometry": {"coordinates":[-89.357706,42.896174],"type":"Point"}
}