{
  "type": "Feature",
  "properties": {
    "iso:country":"US",
    "sg:address":"91 S Main St",
    "sg:city":"Fort Atkinson",
    "sg:classifiers":[
        {
            "category":"Shopping",
            "subcategory":"Gifts & Souvenirs",
            "type":"Retail Goods"
        }
    ],
    "sg:phone":"+1 920 691 0025",
    "sg:postcode":"53538",
    "sg:province":"WI",
    "wof:name":"Soap & Pepper",
    "wof:placetype":"venue"
},
  "geometry": {"coordinates":[-88.836922,42.927425],"type":"Point"}
}