{
  "type": "Feature",
  "properties": {
    "iso:country":"US",
    "sg:address":"515 E Main St",
    "sg:city":"Stoughton",
    "sg:classifiers":[
        {
            "category":"Education",
            "subcategory":"Special Training",
            "type":"Public Place"
        }
    ],
    "sg:phone":"+1 608 873 0717",
    "sg:postcode":"53589",
    "sg:province":"WI",
    "sg:tags":[
        "dramatic",
        "instruction"
    ],
    "wof:name":"Stoughton Center-Perform Arts",
    "wof:placetype":"venue"
},
  "geometry": {"coordinates":[-89.21364199999999,42.91826],"type":"Point"}
}