{
  "type": "Feature",
  "properties": {
    "iso:country":"US",
    "sg:address":"225 S 28th Ave",
    "sg:city":"Wausau",
    "sg:classifiers":[
        {
            "category":"Education",
            "subcategory":"School",
            "type":"Public Place"
        }
    ],
    "sg:phone":"+1 715 842 4857",
    "sg:postcode":"54401",
    "sg:province":"WI",
    "wof:name":"St Matthew Catholic School",
    "wof:placetype":"venue"
},
  "geometry": {"coordinates":[-89.670767,44.961239],"type":"Point"}
}