{
  "type": "Feature",
  "properties": {
    "iso:country":"US",
    "sg:address":"1615 Armstrong St",
    "sg:city":"Marinette",
    "sg:classifiers":[
        {
            "category":"Building & Trades",
            "subcategory":"Pest Control",
            "type":"Services"
        }
    ],
    "sg:phone":"+1 715 789 2811",
    "sg:postcode":"54143",
    "sg:province":"WI",
    "wof:name":"Clean Kill Pest Control",
    "wof:placetype":"venue"
},
  "geometry": {"coordinates":[-87.632021,45.088425],"type":"Point"}
}