{
  "type": "Feature",
  "properties": {
    "iso:country":"US",
    "sg:address":"403 McKenzie Rd",
    "sg:city":"Mukwonago",
    "sg:classifiers":[
        {
            "category":"Building & Trades",
            "subcategory":"Construction",
            "type":"Services"
        }
    ],
    "sg:phone":"+1 262 363 7203",
    "sg:postcode":"53149",
    "sg:province":"WI",
    "sg:tags":[
        "hanging",
        "contractor"
    ],
    "wof:name":"Merit Painting Inc",
    "wof:placetype":"venue"
},
  "geometry": {"coordinates":[-88.320948,42.862876],"type":"Point"}
}