{
  "type": "Feature",
  "properties": {
    "addr:full":"2985 S River Rd Rhinelander WI 54501",
    "addr:housenumber":"2985",
    "addr:postcode":"54501",
    "addr:street":"S River Rd",
    "iso:country":"US",
    "sg:address":"2985 S River Rd",
    "sg:city":"Rhinelander",
    "sg:classifiers":[
        {
            "category":"Building & Trades",
            "subcategory":"Landscaping Services",
            "type":"Services"
        }
    ],
    "sg:phone":"+1 715 493 6960",
    "sg:postcode":"54501",
    "sg:province":"WI",
    "sg:tags":[
        "lawn",
        "tree",
        "maintenance"
    ],
    "wof:name":"Aspen Tree Care",
    "wof:placetype":"venue"
},
  "geometry": {"coordinates":[-89.45950499999999,45.600388],"type":"Point"}
}