{
  "type": "Feature",
  "properties": {
    "addr:full":"3145 Western Ave Jackson WI 53037",
    "addr:housenumber":"3145",
    "addr:postcode":"53037",
    "addr:street":"Western Ave",
    "iso:country":"US",
    "sg:address":"3145 Western Ave",
    "sg:city":"Jackson",
    "sg:classifiers":[
        {
            "category":"Building & Trades",
            "subcategory":"Construction",
            "type":"Services"
        }
    ],
    "sg:phone":"+1 262 677 9799",
    "sg:postcode":"53037",
    "sg:province":"WI",
    "sg:tags":[
        "house",
        "c",
        "hanging",
        "contractor"
    ],
    "wof:name":"Gadow Contracting",
    "wof:placetype":"venue"
},
  "geometry": {"coordinates":[-88.187917,43.295284],"type":"Point"}
}