{
  "type": "Feature",
  "properties": {
    "addr:full":"1600 Carole Ln Green Bay WI 54313",
    "addr:housenumber":"1600",
    "addr:postcode":"54313",
    "addr:street":"Carole Ln",
    "iso:country":"US",
    "sg:address":"1600 Carole Ln",
    "sg:city":"Green Bay",
    "sg:classifiers":[
        {
            "category":"Home & Garden",
            "subcategory":"Building Materials",
            "type":"Retail Goods"
        }
    ],
    "sg:phone":"+1 920 496 6031",
    "sg:postcode":"54313",
    "sg:province":"WI",
    "sg:tags":[
        "glass",
        "leaded"
    ],
    "wof:name":"Erickson Leaded Glass",
    "wof:placetype":"venue"
},
  "geometry": {"coordinates":[-88.10198800000001,44.488679],"type":"Point"}
}