{
  "type": "Feature",
  "properties": {
    "addr:full":"6955 Enterprise Dr Big Bend WI 53103",
    "addr:housenumber":"6955",
    "addr:postcode":"53103",
    "addr:street":"Enterprise Dr",
    "iso:country":"US",
    "sg:address":"6955 Enterprise Dr",
    "sg:city":"Big Bend",
    "sg:classifiers":[
        {
            "category":"Building & Trades",
            "subcategory":"Construction",
            "type":"Services"
        }
    ],
    "sg:phone":"+1 262 662 1040",
    "sg:postcode":"53103",
    "sg:province":"WI",
    "sg:tags":[
        "steel",
        "erection",
        "structural"
    ],
    "wof:name":"Area Erectors Inc",
    "wof:placetype":"venue"
},
  "geometry": {"coordinates":[-88.205449,42.916956],"type":"Point"}
}