{
  "type": "Feature",
  "properties": {
    "iso:country":"US",
    "sg:address":"2950 S 149th St",
    "sg:city":"New Berlin",
    "sg:classifiers":[
        {
            "category":"Building & Trades",
            "subcategory":"Electrical",
            "type":"Services"
        }
    ],
    "sg:phone":"+1 262 782 2938",
    "sg:postcode":"53151",
    "sg:province":"WI",
    "sg:tags":[
        "electrical",
        "contractor"
    ],
    "wof:name":"Dahlke Electric Company Inc",
    "wof:placetype":"venue"
},
  "geometry": {"coordinates":[-88.099243,42.991316],"type":"Point"}
}