{
  "type": "Feature",
  "properties": {
    "iso:country":"US",
    "sg:address":"815 S Division St",
    "sg:city":"Waunakee",
    "sg:classifiers":[
        {
            "category":"Building & Trades",
            "subcategory":"Construction",
            "type":"Services"
        }
    ],
    "sg:phone":"+1 608 849 7277",
    "sg:postcode":"53597",
    "sg:province":"WI",
    "sg:tags":[
        "flooring",
        "contractor"
    ],
    "wof:name":"Mather Wholesale",
    "wof:placetype":"venue"
},
  "geometry": {"coordinates":[-89.446897,43.184551],"type":"Point"}
}