{
  "type": "Feature",
  "properties": {
    "iso:country":"US",
    "sg:address":"8158 Industrial Dr",
    "sg:city":"Barneveld",
    "sg:classifiers":[
        {
            "category":"Wholesale",
            "subcategory":"Construction Materials",
            "type":"Manufacturing & Wholesale Goods"
        },
        {
            "category":"Manufacturing",
            "subcategory":"Glass & Minerals",
            "type":"Manufacturing & Wholesale Goods"
        }
    ],
    "sg:phone":"+1 608 924 1455",
    "sg:postcode":"53507",
    "sg:province":"WI",
    "sg:tags":[
        "concrete",
        "product",
        "mfg"
    ],
    "wof:name":"Crest Concrete Products Inc",
    "wof:placetype":"venue"
},
  "geometry": {"coordinates":[-89.90203200000001,43.009303],"type":"Point"}
}