{
  "type": "Feature",
  "properties": {
    "addr:full":"1212 Sunset Ln River Falls WI 54022",
    "addr:housenumber":"1212",
    "addr:postcode":"54022",
    "addr:street":"Sunset Ln",
    "iso:country":"US",
    "sg:address":"1212 Sunset Ln",
    "sg:city":"River Falls",
    "sg:classifiers":[
        {
            "category":"Farming",
            "subcategory":"Dairy Farm",
            "type":"Manufacturing & Wholesale Goods"
        }
    ],
    "sg:phone":"+1 715 425 9479",
    "sg:postcode":"54022",
    "sg:province":"WI",
    "wof:name":"Puhrman Harlyn",
    "wof:placetype":"venue"
},
  "geometry": {"coordinates":[-92.643236,44.865742],"type":"Point"}
}