{
  "type": "Feature",
  "properties": {
    "iso:country":"US",
    "sg:address":"318 Gladiola Ln E",
    "sg:city":"Altoona",
    "sg:classifiers":[
        {
            "category":"Shopping",
            "subcategory":"Hobbies, Toys, & Games",
            "type":"Retail Goods"
        }
    ],
    "sg:phone":"+1 715 832 3788",
    "sg:postcode":"54720",
    "sg:province":"WI",
    "wof:name":"Fountain Youth Hobbies & Co",
    "wof:placetype":"venue"
},
  "geometry": {"coordinates":[-91.419826,44.798057],"type":"Point"}
}