{
  "type": "Feature",
  "properties": {
    "iso:country":"US",
    "sg:address":"55 Roberta Ct",
    "sg:city":"Fond Du Lac",
    "sg:classifiers":[
        {
            "category":"Organizations",
            "subcategory":"Membership Organization",
            "type":"Services"
        }
    ],
    "sg:phone":"+1 920 922 7616",
    "sg:postcode":"54935",
    "sg:province":"WI",
    "wof:name":"Izaak Walton League of Am",
    "wof:placetype":"venue"
},
  "geometry": {"coordinates":[-88.442386,43.750911],"type":"Point"}
}