{
  "type": "Feature",
  "properties": {
    "addr:full":"691 S Green Bay Rd Neenah WI 54956",
    "addr:housenumber":"691",
    "addr:postcode":"54956",
    "addr:street":"S Green Bay Rd",
    "iso:country":"US",
    "sg:address":"691 S Green Bay Rd",
    "sg:city":"Neenah",
    "sg:classifiers":[
        {
            "category":"Shopping",
            "subcategory":"Computers & Home Electronics",
            "type":"Retail Goods"
        }
    ],
    "sg:phone":"+1 920 886 3630",
    "sg:postcode":"54956",
    "sg:province":"WI",
    "sg:tags":[
        "software"
    ],
    "wof:name":"Verity IA",
    "wof:placetype":"venue"
},
  "geometry": {"coordinates":[-88.485077,44.177619],"type":"Point"}
}