{
  "type": "Feature",
  "properties": {
    "iso:country":"US",
    "sg:address":"16103 Bette Dr",
    "sg:city":"Menomonee Falls",
    "sg:classifiers":[
        {
            "category":"Professional",
            "subcategory":"Business Services",
            "type":"Services"
        }
    ],
    "sg:phone":"+1 262 703 0549",
    "sg:postcode":"53051",
    "sg:province":"WI",
    "wof:name":"Adween Sales Inc",
    "wof:placetype":"venue"
},
  "geometry": {"coordinates":[-88.111041,43.121838],"type":"Point"}
}