{
  "type": "Feature",
  "properties": {
    "iso:country":"US",
    "sg:address":"524 State St",
    "sg:city":"Madison",
    "sg:classifiers":[
        {
            "category":"Personal",
            "subcategory":"Beauty Salon",
            "type":"Services"
        }
    ],
    "sg:phone":"+1 608 251 1545",
    "sg:postcode":"53703",
    "sg:province":"WI",
    "wof:name":"Nogginz Hair Shop",
    "wof:placetype":"venue"
},
  "geometry": {"coordinates":[-89.395011,43.074923],"type":"Point"}
}