{
  "type": "Feature",
  "properties": {
    "iso:country":"US",
    "sg:address":"10201 W Watertown Plank Rd",
    "sg:city":"Milwaukee",
    "sg:classifiers":[
        {
            "category":"Education",
            "subcategory":"School",
            "type":"Public Place"
        }
    ],
    "sg:phone":"+1 414 257 6821",
    "sg:postcode":"53226",
    "sg:province":"WI",
    "wof:name":"Detention Center",
    "wof:placetype":"venue"
},
  "geometry": {"coordinates":[-88.04173,43.045561],"type":"Point"}
}