{
  "type": "Feature",
  "properties": {
    "addr:full":"1547 N Farwell Ave Milwaukee WI 53202",
    "addr:housenumber":"1547",
    "addr:postcode":"53202",
    "addr:street":"N Farwell Ave",
    "iso:country":"US",
    "sg:address":"1547 N Farwell Ave",
    "sg:city":"Milwaukee",
    "sg:classifiers":[
        {
            "category":"Personal",
            "subcategory":"Beauty Salon",
            "type":"Services"
        }
    ],
    "sg:phone":"+1 414 525 0252",
    "sg:postcode":"53202",
    "sg:province":"WI",
    "sg:tags":[
        "treatment",
        "skin"
    ],
    "wof:name":"Face West",
    "wof:placetype":"venue"
},
  "geometry": {"coordinates":[-87.89256399999999,43.052722],"type":"Point"}
}