{
  "type": "Feature",
  "properties": {
    "iso:country":"US",
    "sg:address":"11938 W Silver Spring Dr",
    "sg:city":"Milwaukee",
    "sg:classifiers":[
        {
            "category":"Professional",
            "type":"Services"
        }
    ],
    "sg:phone":"+1 414 461 6263",
    "sg:postcode":"53225",
    "sg:province":"WI",
    "sg:tags":[
        "establishment"
    ],
    "wof:name":"Interstate Bearing Tech",
    "wof:placetype":"venue"
},
  "geometry": {"coordinates":[-88.06334200000001,43.117073],"type":"Point"}
}