{
  "type": "Feature",
  "properties": {
    "iso:country":"US",
    "sg:address":"718 Dekalb St",
    "sg:city":"Wausau",
    "sg:classifiers":[
        {
            "category":"Professional",
            "subcategory":"Advertising",
            "type":"Services"
        }
    ],
    "sg:phone":"+1 715 842 0593",
    "sg:postcode":"54403",
    "sg:province":"WI",
    "sg:tags":[
        "agency"
    ],
    "wof:name":"Wisconsin Weddings",
    "wof:placetype":"venue"
},
  "geometry": {"coordinates":[-89.619457,44.968819],"type":"Point"}
}