{
  "type": "Feature",
  "properties": {
    "iso:country":"US",
    "sg:address":"643 E Industrial Dr",
    "sg:city":"Hartland",
    "sg:classifiers":[
        {
            "category":"Building & Trades",
            "subcategory":"Construction",
            "type":"Services"
        }
    ],
    "sg:phone":"+1 262 367 2753",
    "sg:postcode":"53029",
    "sg:province":"WI",
    "sg:tags":[
        "mfg",
        "house",
        "wood",
        "furn"
    ],
    "wof:name":"Old World Craftsmen Inc",
    "wof:placetype":"venue"
},
  "geometry": {"coordinates":[-88.356827,43.098398],"type":"Point"}
}