{
  "type": "Feature",
  "properties": {
    "addr:full":"5811 Greenleaf Blvd Racine WI 53406",
    "addr:housenumber":"5811",
    "addr:postcode":"53406",
    "addr:street":"Greenleaf Blvd",
    "iso:country":"US",
    "sg:address":"5811 Greenleaf Blvd",
    "sg:city":"Racine",
    "sg:classifiers":[
        {
            "category":"Professional",
            "subcategory":"Art Services",
            "type":"Services"
        }
    ],
    "sg:phone":"+1 262 634 8523",
    "sg:postcode":"53406",
    "sg:province":"WI",
    "sg:tags":[
        "commercial",
        "design"
    ],
    "wof:name":"New Paradigm Graphics Inc",
    "wof:placetype":"venue"
},
  "geometry": {"coordinates":[-87.85189800000001,42.708977],"type":"Point"}
}