{
  "type": "Feature",
  "properties": {
    "iso:country":"US",
    "sg:address":"194 W Main St",
    "sg:city":"Stoughton",
    "sg:classifiers":[
        {
            "category":"Shopping",
            "subcategory":"Gifts & Souvenirs",
            "type":"Retail Goods"
        }
    ],
    "sg:phone":"+1 608 877 7530",
    "sg:postcode":"53589",
    "sg:province":"WI",
    "sg:tags":[
        "shop"
    ],
    "wof:name":"Scentimints",
    "wof:placetype":"venue"
},
  "geometry": {"coordinates":[-89.22146,42.916852],"type":"Point"}
}