{
  "type": "Feature",
  "properties": {
    "iso:country":"US",
    "sg:address":"116 Madison St",
    "sg:city":"Beaver Dam",
    "sg:classifiers":[
        {
            "category":"Autos & Motor Vehicles",
            "subcategory":"Automobile Sales",
            "type":"Retail Goods"
        }
    ],
    "sg:phone":"+1 920 885 6118",
    "sg:postcode":"53916",
    "sg:province":"WI",
    "sg:tags":[
        "repair"
    ],
    "wof:name":"S & R Auto Sales & Repair",
    "wof:placetype":"venue"
},
  "geometry": {"coordinates":[-88.839546,43.455566],"type":"Point"}
}