{
  "type": "Feature",
  "properties": {
    "addr:full":"116 W Sumner St Hartford WI 53027",
    "addr:housenumber":"116",
    "addr:postcode":"53027",
    "addr:street":"W Sumner St",
    "iso:country":"US",
    "sg:address":"116 W Sumner St",
    "sg:city":"Hartford",
    "sg:classifiers":[
        {
            "category":"Banks & Credit Unions",
            "subcategory":"Investment Brokerage",
            "type":"Services"
        },
        {
            "category":"Professional",
            "subcategory":"Management & Consulting",
            "type":"Services"
        }
    ],
    "sg:phone":"+1 262 673 8926",
    "sg:postcode":"53027",
    "sg:province":"WI",
    "sg:tags":[
        "bond",
        "security",
        "b",
        "stock"
    ],
    "sg:website":"www.insurance-fnbhart.com",
    "wof:name":"FNB- Hartford Investment Svcs",
    "wof:placetype":"venue"
},
  "geometry": {"coordinates":[-88.380414,43.317648],"type":"Point"}
}