{
  "type": "Feature",
  "properties": {
    "iso:country":"US",
    "sg:address":"1496 Helminski Rd",
    "sg:city":"Woodruff",
    "sg:classifiers":[
        {
            "category":"Travel",
            "subcategory":"Hotels & Motels",
            "type":"Entertainment"
        }
    ],
    "sg:phone":"+1 715 356 6379",
    "sg:postcode":"54568",
    "sg:province":"WI",
    "sg:tags":[
        "resort"
    ],
    "wof:name":"Strand's Whispering Pines",
    "wof:placetype":"venue"
},
  "geometry": {"coordinates":[-89.659951,45.922834],"type":"Point"}
}