{
  "type": "Feature",
  "properties": {
    "iso:country":"US",
    "sg:address":"6686 Wisconsin Ave",
    "sg:city":"Greenville",
    "sg:classifiers":[
        {
            "category":"Professional",
            "type":"Services"
        }
    ],
    "sg:phone":"+1 920 757 9624",
    "sg:postcode":"54942",
    "sg:province":"WI",
    "wof:name":"Palmbach & Palmbach Inc",
    "wof:placetype":"venue"
},
  "geometry": {"coordinates":[-88.524497,44.273281],"type":"Point"}
}