{
  "type": "Feature",
  "properties": {
    "iso:country":"US",
    "sg:address":"6630 W Coldspring Rd",
    "sg:city":"Milwaukee",
    "sg:classifiers":[
        {
            "category":"Professional",
            "type":"Services"
        }
    ],
    "sg:phone":"+1 414 321 3397",
    "sg:postcode":"53220",
    "sg:province":"WI",
    "wof:name":"Gwz LLC",
    "wof:placetype":"venue"
},
  "geometry": {"coordinates":[-87.995853,42.966667],"type":"Point"}
}