{
  "type": "Feature",
  "properties": {
    "iso:country":"US",
    "sg:address":"200 E Centennial Dr",
    "sg:city":"Oak Creek",
    "sg:classifiers":[
        {
            "category":"Government",
            "subcategory":"Post Office",
            "type":"Public Place"
        }
    ],
    "sg:phone":"+1 414 766 0583",
    "sg:postcode":"53154",
    "sg:province":"WI",
    "sg:tags":[
        "postal",
        "us"
    ],
    "wof:name":"US Post Office",
    "wof:placetype":"venue"
},
  "geometry": {"coordinates":[-87.908586,42.882934],"type":"Point"}
}