{
  "type": "Feature",
  "properties": {
    "iso:country":"US",
    "sg:address":"7866 Konen Rd",
    "sg:city":"Mt Calvary",
    "sg:classifiers":[
        {
            "category":"Building & Trades",
            "subcategory":"Landscaping Services",
            "type":"Services"
        }
    ],
    "sg:phone":"+1 920 921 9550",
    "sg:postcode":"53057",
    "sg:province":"WI",
    "sg:tags":[
        "tree"
    ],
    "wof:name":"Preston Tree Moving & Excavtg",
    "wof:placetype":"venue"
},
  "geometry": {"coordinates":[-88.301525,43.821116],"type":"Point"}
}