{
  "type": "Feature",
  "properties": {
    "addr:full":"653 Triangle Rd Fond Du Lac WI 54935",
    "addr:housenumber":"653",
    "addr:postcode":"54935",
    "addr:street":"Triangle Rd",
    "iso:country":"US",
    "sg:address":"653 Triangle Rd",
    "sg:city":"Fond Du Lac",
    "sg:classifiers":[
        {
            "category":"Communications",
            "subcategory":"Film & Video Production",
            "type":"Services"
        }
    ],
    "sg:phone":"+1 920 921 9050",
    "sg:postcode":"54935",
    "sg:province":"WI",
    "sg:tags":[
        "motion",
        "picture"
    ],
    "wof:name":"Special Mmnts Vdeo Productions",
    "wof:placetype":"venue"
},
  "geometry": {"coordinates":[-88.474996,43.761844],"type":"Point"}
}