{
  "type": "Feature",
  "properties": {
    "addr:full":"11446 N Farmdale Rd Mequon WI 53097",
    "addr:housenumber":"11446",
    "addr:postcode":"53097",
    "addr:street":"N Farmdale Rd",
    "iso:country":"US",
    "sg:address":"11446 N Farmdale Rd",
    "sg:city":"Mequon",
    "sg:classifiers":[
        {
            "category":"Farming",
            "subcategory":"Farm",
            "type":"Manufacturing & Wholesale Goods"
        }
    ],
    "sg:phone":"+1 262 236 4000",
    "sg:postcode":"53097",
    "sg:province":"WI",
    "sg:tags":[
        "crop",
        "general"
    ],
    "sg:website":"www.oldenburgfarm.com",
    "wof:name":"Oldenburg Farm LLC",
    "wof:placetype":"venue"
},
  "geometry": {"coordinates":[-88.033371,43.231503],"type":"Point"}
}