{
  "type": "Feature",
  "properties": {
    "iso:country":"US",
    "sg:address":"726 Water St",
    "sg:city":"Racine",
    "sg:classifiers":[
        {
            "category":"Recreation",
            "subcategory":"Marina",
            "type":"Entertainment"
        }
    ],
    "sg:phone":"+1 262 637 4153",
    "sg:postcode":"53403",
    "sg:province":"WI",
    "wof:name":"Azarian & Sons",
    "wof:placetype":"venue"
},
  "geometry": {"coordinates":[-87.789191,42.727306],"type":"Point"}
}