{
  "type": "Feature",
  "properties": {
    "iso:country":"US",
    "sg:address":"215 N Washington St",
    "sg:city":"Thorp",
    "sg:classifiers":[
        {
            "category":"Personal",
            "subcategory":"Tanning Parlor",
            "type":"Services"
        },
        {
            "category":"Personal",
            "type":"Services"
        }
    ],
    "sg:phone":"+1 715 669 5337",
    "sg:postcode":"54771",
    "sg:province":"WI",
    "sg:tags":[
        "salon"
    ],
    "wof:name":"Sun Place Nice Buty Tan Salon",
    "wof:placetype":"venue"
},
  "geometry": {"coordinates":[-90.80038999999999,44.961035],"type":"Point"}
}