{
  "type": "Feature",
  "properties": {
    "iso:country":"US",
    "sg:address":"813 46th St",
    "sg:city":"Kenosha",
    "sg:classifiers":[
        {
            "category":"Personal",
            "subcategory":"Nail Salon",
            "type":"Services"
        }
    ],
    "sg:phone":"+1 262 652 1563",
    "sg:postcode":"53140",
    "sg:province":"WI",
    "wof:name":"Buttons And Nails Gifts",
    "wof:placetype":"venue"
},
  "geometry": {"coordinates":[-87.821787,42.59446],"type":"Point"}
}