{
  "type": "Feature",
  "properties": {
    "iso:country":"US",
    "sg:address":"216 E Main Ln",
    "sg:city":"Madison",
    "sg:classifiers":[
        {
            "category":"Building & Trades",
            "subcategory":"Plumbing",
            "type":"Services"
        }
    ],
    "sg:phone":"+1 608 231 3888",
    "sg:postcode":"53704",
    "sg:province":"WI",
    "sg:tags":[
        "plumbing",
        "contractor"
    ],
    "wof:name":"Harmony Plumbing",
    "wof:placetype":"venue"
},
  "geometry": {"coordinates":[-89.350992,43.133395],"type":"Point"}
}