{
  "type": "Feature",
  "properties": {
    "iso:country":"US",
    "sg:address":"7527 Devonshire Dr",
    "sg:city":"Cedarburg",
    "sg:classifiers":[
        {
            "category":"Building & Trades",
            "subcategory":"Plumbing",
            "type":"Services"
        }
    ],
    "sg:phone":"+1 262 377 3663",
    "sg:postcode":"53012",
    "sg:province":"WI",
    "sg:tags":[
        "contractor"
    ],
    "wof:name":"Environmental Plumbing Service",
    "wof:placetype":"venue"
},
  "geometry": {"coordinates":[-87.996664,43.333864],"type":"Point"}
}