{
  "type": "Feature",
  "properties": {
    "iso:country":"US",
    "sg:address":"2110 170th St",
    "sg:city":"Milltown",
    "sg:classifiers":[
        {
            "category":"Farming",
            "subcategory":"Livestock Farm",
            "type":"Manufacturing & Wholesale Goods"
        }
    ],
    "sg:phone":"+1 715 825 3114",
    "sg:postcode":"54858",
    "sg:province":"WI",
    "sg:tags":[
        "hog",
        "or",
        "feedlot"
    ],
    "wof:name":"Clayton Johnson",
    "wof:placetype":"venue"
},
  "geometry": {"coordinates":[-92.509146,45.514321],"type":"Point"}
}