{
  "type": "Feature",
  "properties": {
    "iso:country":"US",
    "sg:address":"26499 Schmidt Rd",
    "sg:city":"Eleva",
    "sg:classifiers":[
        {
            "category":"Building & Trades",
            "subcategory":"Construction",
            "type":"Services"
        }
    ],
    "sg:phone":"+1 715 287 3492",
    "sg:postcode":"54738",
    "sg:province":"WI",
    "sg:tags":[
        "roofing",
        "contractor"
    ],
    "wof:name":"C & N Roofing & Construction",
    "wof:placetype":"venue"
},
  "geometry": {"coordinates":[-91.47625600000001,44.538192],"type":"Point"}
}