{
  "type": "Feature",
  "properties": {
    "iso:country":"US",
    "sg:address":"1028 S Sugar Bush Rd",
    "sg:city":"Luxemburg",
    "sg:classifiers":[
        {
            "category":"Professional",
            "type":"Services"
        }
    ],
    "sg:phone":"+1 920 863 2908",
    "sg:postcode":"54217",
    "sg:province":"WI",
    "wof:name":"Adam Sternard LLC",
    "wof:placetype":"venue"
},
  "geometry": {"coordinates":[-87.785667,44.481403],"type":"Point"}
}