{
  "type": "Feature",
  "properties": {
    "addr:full":"675 E Friesland Rd Markesan WI 53946",
    "addr:housenumber":"675",
    "addr:postcode":"53946",
    "addr:street":"E Friesland Rd",
    "iso:country":"US",
    "sg:address":"675 E Friesland Rd",
    "sg:city":"Markesan",
    "sg:classifiers":[
        {
            "category":"Building & Trades",
            "subcategory":"Construction",
            "type":"Services"
        }
    ],
    "sg:phone":"+1 920 398 2220",
    "sg:postcode":"53946",
    "sg:province":"WI",
    "sg:tags":[
        "excavating",
        "contractor"
    ],
    "wof:name":"Top Notch Excavating",
    "wof:placetype":"venue"
},
  "geometry": {"coordinates":[-89.046921,43.654677],"type":"Point"}
}