{
  "type": "Feature",
  "properties": {
    "iso:country":"US",
    "sg:address":"6155 W Forest Home Ave",
    "sg:city":"Milwaukee",
    "sg:classifiers":[
        {
            "category":"Wholesale",
            "subcategory":"Auto Parts",
            "type":"Manufacturing & Wholesale Goods"
        }
    ],
    "sg:phone":"+1 414 543 2343",
    "sg:postcode":"53220",
    "sg:province":"WI",
    "sg:tags":[
        "automotive"
    ],
    "wof:name":"Federated Auto Parts",
    "wof:placetype":"venue"
},
  "geometry": {"coordinates":[-87.990425,42.97537],"type":"Point"}
}