{
  "type": "Feature",
  "properties": {
    "iso:country":"US",
    "sg:address":"2829 N Meade St",
    "sg:city":"Appleton",
    "sg:classifiers":[
        {
            "category":"Building & Trades",
            "subcategory":"Construction",
            "type":"Services"
        }
    ],
    "sg:phone":"+1 920 830 9648",
    "sg:postcode":"54911",
    "sg:province":"WI",
    "sg:tags":[
        "house"
    ],
    "wof:name":"Schlomann Brothers Cnstr",
    "wof:placetype":"venue"
},
  "geometry": {"coordinates":[-88.395833,44.288119],"type":"Point"}
}