{
  "type": "Feature",
  "properties": {
    "addr:full":"5223 US Hwy 151 Platteville WI 53818",
    "addr:housenumber":"5223",
    "addr:postcode":"53818",
    "addr:street":"Us Hwy 151",
    "iso:country":"US",
    "sg:address":"5223 US Hwy 151",
    "sg:city":"Platteville",
    "sg:classifiers":[
        {
            "category":"Farming",
            "subcategory":"Dairy Farm",
            "type":"Manufacturing & Wholesale Goods"
        }
    ],
    "sg:phone":"+1 608 348 9181",
    "sg:postcode":"53818",
    "sg:province":"WI",
    "wof:name":"Leroy & Connie Cardy",
    "wof:placetype":"venue"
},
  "geometry": {"coordinates":[-90.526487,42.695997],"type":"Point"}
}