{
  "type": "Feature",
  "properties": {
    "iso:country":"US",
    "sg:address":"2353 S 15th Pl",
    "sg:city":"Milwaukee",
    "sg:classifiers":[
        {
            "category":"Social Services",
            "type":"Services"
        }
    ],
    "sg:phone":"+1 414 672 1389",
    "sg:postcode":"53215",
    "sg:province":"WI",
    "sg:tags":[
        "organization",
        "welfare"
    ],
    "wof:name":"Jesuit Volunteer Corps",
    "wof:placetype":"venue"
},
  "geometry": {"coordinates":[-87.932535,43.001994],"type":"Point"}
}