{
  "type": "Feature",
  "properties": {
    "iso:country":"US",
    "sg:address":"645 Hospital Rd",
    "sg:city":"New Richmond",
    "sg:classifiers":[
        {
            "category":"Health Services",
            "subcategory":"Doctor",
            "type":"Services"
        }
    ],
    "sg:phone":"+1 715 246 2555",
    "sg:postcode":"54017",
    "sg:province":"WI",
    "wof:name":"Jerome M Kjolsing DDS",
    "wof:placetype":"venue"
},
  "geometry": {"coordinates":[-92.553294,45.11609],"type":"Point"}
}