{
  "type": "Feature",
  "properties": {
    "iso:country":"US",
    "sg:address":"1010 Newton St",
    "sg:city":"Baldwin",
    "sg:classifiers":[
        {
            "category":"Retail",
            "subcategory":"Funeral Services",
            "type":"Services"
        }
    ],
    "sg:phone":"+1 715 684 3434",
    "sg:postcode":"54002",
    "sg:province":"WI",
    "sg:tags":[
        "director"
    ],
    "wof:name":"O'Connell Family Funeral Homes",
    "wof:placetype":"venue"
},
  "geometry": {"coordinates":[-92.376074,44.968663],"type":"Point"}
}