{
  "type": "Feature",
  "properties": {
    "iso:country":"US",
    "sg:address":"2937 Monroe Rd",
    "sg:city":"De Pere",
    "sg:classifiers":[
        {
            "category":"Travel",
            "subcategory":"Travel Agent",
            "type":"Entertainment"
        }
    ],
    "sg:phone":"+1 920 336 1976",
    "sg:postcode":"54115",
    "sg:province":"WI",
    "sg:tags":[
        "operator",
        "tour"
    ],
    "wof:name":"Lamers Tour & Travel",
    "wof:placetype":"venue"
},
  "geometry": {"coordinates":[-87.997513,44.44897],"type":"Point"}
}