{
  "type": "Feature",
  "properties": {
    "iso:country":"US",
    "sg:address":"583 Linden St",
    "sg:city":"Verona",
    "sg:classifiers":[
        {
            "category":"Professional",
            "subcategory":"Management & Consulting",
            "type":"Services"
        }
    ],
    "sg:phone":"+1 608 848 1044",
    "sg:postcode":"53593",
    "sg:province":"WI",
    "wof:name":"Kasieta Research & Consulting",
    "wof:placetype":"venue"
},
  "geometry": {"coordinates":[-89.542363,42.995908],"type":"Point"}
}