{
  "type": "Feature",
  "properties": {
    "iso:country":"US",
    "sg:address":"5736 S Robert Ave",
    "sg:city":"Cudahy",
    "sg:classifiers":[
        {
            "category":"Building & Trades",
            "subcategory":"Cleaning & Sanitation",
            "type":"Services"
        },
        {
            "category":"Building & Trades",
            "subcategory":"Construction",
            "type":"Services"
        }
    ],
    "sg:phone":"+1 414 546 3800",
    "sg:postcode":"53110",
    "sg:province":"WI",
    "sg:tags":[
        "resurfacing",
        "laying",
        "refinishing",
        "maintenance",
        "floor"
    ],
    "wof:name":"Bailey's Quality Wood Floors",
    "wof:placetype":"venue"
},
  "geometry": {"coordinates":[-87.872474,42.939806],"type":"Point"}
}