{
  "type": "Feature",
  "properties": {
    "iso:country":"US",
    "sg:address":"103 S Hazeldell Ave",
    "sg:city":"Crandon",
    "sg:classifiers":[
        {
            "category":"Government",
            "subcategory":"Police Station",
            "type":"Public Place"
        }
    ],
    "sg:phone":"+1 715 478 3821",
    "sg:postcode":"54520",
    "sg:province":"WI",
    "sg:tags":[
        "department"
    ],
    "wof:name":"Crandon City Police",
    "wof:placetype":"venue"
},
  "geometry": {"coordinates":[-88.90437300000001,45.569186],"type":"Point"}
}