{
  "type": "Feature",
  "properties": {
    "iso:country":"US",
    "sg:address":"5129 W Vienna Ave",
    "sg:city":"Milwaukee",
    "sg:classifiers":[
        {
            "category":"Professional",
            "type":"Services"
        }
    ],
    "sg:phone":"+1 414 449 2073",
    "sg:postcode":"53216",
    "sg:province":"WI",
    "wof:name":"Samej",
    "wof:placetype":"venue"
},
  "geometry": {"coordinates":[-87.978083,43.086139],"type":"Point"}
}