{
  "type": "Feature",
  "properties": {
    "iso:country":"US",
    "sg:address":"3737 Shirley Rd",
    "sg:city":"De Pere",
    "sg:classifiers":[
        {
            "category":"Education",
            "subcategory":"School",
            "type":"Public Place"
        }
    ],
    "sg:phone":"+1 920 864 7787",
    "sg:postcode":"54115",
    "sg:province":"WI",
    "sg:tags":[
        "child",
        "day",
        "care"
    ],
    "wof:name":"Shirley Immanuel Luthern Schl",
    "wof:placetype":"venue"
},
  "geometry": {"coordinates":[-87.996411,44.35757],"type":"Point"}
}