{
  "type": "Feature",
  "properties": {
    "addr:full":"222 N Main St Loyal WI 54446",
    "addr:housenumber":"222",
    "addr:postcode":"54446",
    "addr:street":"N Main St",
    "iso:country":"US",
    "sg:address":"222 N Main St",
    "sg:city":"Loyal",
    "sg:classifiers":[
        {
            "category":"Food & Beverages",
            "subcategory":"Groceries & Convenience Stores",
            "type":"Retail Goods"
        }
    ],
    "sg:phone":"+1 715 255 9455",
    "sg:postcode":"54446",
    "sg:province":"WI",
    "wof:name":"Loyal Discount Groceries",
    "wof:placetype":"venue"
},
  "geometry": {"coordinates":[-90.495892,44.737792],"type":"Point"}
}