{
  "type": "Feature",
  "properties": {
    "iso:country":"US",
    "sg:address":"86 E Cedar Lake Rd",
    "sg:city":"Star Prairie",
    "sg:classifiers":[
        {
            "category":"Building & Trades",
            "subcategory":"Cleaning & Sanitation",
            "type":"Services"
        }
    ],
    "sg:phone":"+1 715 248 3600",
    "sg:postcode":"54026",
    "sg:province":"WI",
    "sg:tags":[
        "maintenance"
    ],
    "wof:name":"North American Bldg Maint",
    "wof:placetype":"venue"
},
  "geometry": {"coordinates":[-92.562298,45.220985],"type":"Point"}
}