{
  "type": "Feature",
  "properties": {
    "iso:country":"US",
    "sg:address":"9702 Archer Rd",
    "sg:city":"Almond",
    "sg:classifiers":[
        {
            "category":"Recreation",
            "type":"Entertainment"
        }
    ],
    "sg:phone":"+1 715 787 7239",
    "sg:postcode":"54909",
    "sg:province":"WI",
    "sg:tags":[
        "club",
        "membership"
    ],
    "wof:name":"Oasis Community Club",
    "wof:placetype":"venue"
},
  "geometry": {"coordinates":[-89.365233,44.174016],"type":"Point"}
}