{
  "type": "Feature",
  "properties": {
    "addr:full":"9010 W Portage St Milwaukee WI 53224",
    "addr:housenumber":"9010",
    "addr:postcode":"53224",
    "addr:street":"W Portage St",
    "iso:country":"US",
    "sg:address":"9010 W Portage St",
    "sg:city":"Milwaukee",
    "sg:classifiers":[
        {
            "category":"Professional",
            "subcategory":"Management & Consulting",
            "type":"Services"
        }
    ],
    "sg:phone":"+1 414 371 0737",
    "sg:postcode":"53224",
    "sg:province":"WI",
    "sg:tags":[
        "personnel",
        "consultant"
    ],
    "wof:name":"Prime Staff",
    "wof:placetype":"venue"
},
  "geometry": {"coordinates":[-88.024828,43.155431],"type":"Point"}
}