{
  "type": "Feature",
  "properties": {
    "iso:country":"US",
    "sg:address":"5806 Co Rd I",
    "sg:city":"Oconto Falls",
    "sg:classifiers":[
        {
            "category":"Building & Trades",
            "subcategory":"Construction",
            "type":"Services"
        }
    ],
    "sg:phone":"+1 920 848 8989",
    "sg:postcode":"54154",
    "sg:province":"WI",
    "sg:tags":[
        "masonry",
        "contractor"
    ],
    "wof:name":"Great Lakes Masonry",
    "wof:placetype":"venue"
},
  "geometry": {"coordinates":[-88.125731,44.884254],"type":"Point"}
}