{
  "type": "Feature",
  "properties": {
    "iso:country":"US",
    "sg:address":"615 Werle Ave",
    "sg:city":"Wausau",
    "sg:classifiers":[
        {
            "category":"Building & Trades",
            "subcategory":"Cleaning & Sanitation",
            "type":"Services"
        }
    ],
    "sg:phone":"+1 715 845 7017",
    "sg:postcode":"54401",
    "sg:province":"WI",
    "sg:tags":[
        "janitor"
    ],
    "wof:name":"Ed's Cleaning Svc Inc",
    "wof:placetype":"venue"
},
  "geometry": {"coordinates":[-89.64251,44.957017],"type":"Point"}
}