{
  "type": "Feature",
  "properties": {
    "iso:country":"US",
    "sg:address":"1878 S Brooklyn Dr",
    "sg:city":"Stoughton",
    "sg:classifiers":[
        {
            "category":"Sports & Exercise",
            "subcategory":"Golf",
            "type":"Entertainment"
        }
    ],
    "sg:phone":"+1 608 873 0325",
    "sg:postcode":"53589",
    "sg:province":"WI",
    "sg:tags":[
        "course"
    ],
    "wof:name":"Stoughton Country Club",
    "wof:placetype":"venue"
},
  "geometry": {"coordinates":[-89.254769,42.947425],"type":"Point"}
}