{
  "type": "Feature",
  "properties": {
    "iso:country":"US",
    "sg:address":"14800 Shoreline Dr",
    "sg:city":"Merrill",
    "sg:classifiers":[
        {
            "category":"Building & Trades",
            "subcategory":"Construction",
            "type":"Services"
        }
    ],
    "sg:phone":"+1 715 539 8563",
    "sg:postcode":"54452",
    "sg:province":"WI",
    "sg:tags":[
        "house"
    ],
    "wof:name":"Bb Builders",
    "wof:placetype":"venue"
},
  "geometry": {"coordinates":[-89.62934799999999,45.107649],"type":"Point"}
}