{
  "type": "Feature",
  "properties": {
    "iso:country":"US",
    "sg:address":"240 Johnson St",
    "sg:city":"Wisconsin Rapids",
    "sg:classifiers":[
        {
            "category":"Shopping",
            "type":"Retail Goods"
        }
    ],
    "sg:phone":"+1 715 421 4598",
    "sg:postcode":"54495",
    "sg:province":"WI",
    "sg:tags":[
        "art",
        "gallery",
        "dealer"
    ],
    "wof:name":"Central Wisconsin Cultural Ctr",
    "wof:placetype":"venue"
},
  "geometry": {"coordinates":[-89.828936,44.392473],"type":"Point"}
}