{
  "type": "Feature",
  "properties": {
    "addr:full":"5900 N Port Washington Rd Milwaukee WI 53217",
    "addr:housenumber":"5900",
    "addr:postcode":"53217",
    "addr:street":"N Port Washington Rd",
    "iso:country":"US",
    "sg:address":"5900 N Port Washington Rd",
    "sg:city":"Milwaukee",
    "sg:classifiers":[
        {
            "category":"Shopping",
            "subcategory":"Catalog Store",
            "type":"Retail Goods"
        }
    ],
    "sg:phone":"+1 414 332 7900",
    "sg:postcode":"53217",
    "sg:province":"WI",
    "sg:tags":[
        "department",
        "mail",
        "house"
    ],
    "wof:name":"Sears",
    "wof:placetype":"venue"
},
  "geometry": {"coordinates":[-87.91653100000001,43.118908],"type":"Point"}
}