{
  "type": "Feature",
  "properties": {
    "iso:country":"US",
    "sg:address":"103N1240 W Ranchito Ln",
    "sg:city":"Mequon",
    "sg:classifiers":[
        {
            "category":"Social Services",
            "subcategory":"Child Care",
            "type":"Services"
        },
        {
            "category":"Education",
            "subcategory":"Preschool",
            "type":"Public Place"
        },
        {
            "category":"Education",
            "subcategory":"School",
            "type":"Public Place"
        }
    ],
    "sg:phone":"+1 262 241 4008",
    "sg:postcode":"53097",
    "sg:province":"WI",
    "sg:tags":[
        "elementary",
        "day"
    ],
    "wof:name":"Dezigned 4 Kidz",
    "wof:placetype":"venue"
},
  "geometry": {"coordinates":[-88.012299,43.230801],"type":"Point"}
}