{
  "type": "Feature",
  "properties": {
    "iso:country":"US",
    "sg:address":"5751 N Teutonia Ave",
    "sg:city":"Milwaukee",
    "sg:classifiers":[
        {
            "category":"Shopping",
            "subcategory":"Gifts & Souvenirs",
            "type":"Retail Goods"
        }
    ],
    "sg:phone":"+1 414 527 4625",
    "sg:postcode":"53209",
    "sg:province":"WI",
    "wof:name":"C C S Enterprises",
    "wof:placetype":"venue"
},
  "geometry": {"coordinates":[-87.95113,43.12185],"type":"Point"}
}