{
  "type": "Feature",
  "properties": {
    "iso:country":"US",
    "sg:address":"7264 Hyacinth Ct",
    "sg:city":"Greendale",
    "sg:classifiers":[
        {
            "category":"Professional",
            "subcategory":"Management & Consulting",
            "type":"Services"
        }
    ],
    "sg:phone":"+1 414 425 8483",
    "sg:postcode":"53129",
    "sg:province":"WI",
    "sg:tags":[
        "consultant"
    ],
    "wof:name":"Industrial Development Inc",
    "wof:placetype":"venue"
},
  "geometry": {"coordinates":[-88.003974,42.924866],"type":"Point"}
}