{
  "type": "Feature",
  "properties": {
    "iso:country":"US",
    "sg:address":"131 Locust St",
    "sg:city":"Lodi",
    "sg:classifiers":[
        {
            "category":"Organizations",
            "subcategory":"Religious Organization",
            "type":"Services"
        }
    ],
    "sg:phone":"+1 608 592 7449",
    "sg:postcode":"53555",
    "sg:province":"WI",
    "sg:tags":[
        "clergy"
    ],
    "wof:name":"Walter Scott",
    "wof:placetype":"venue"
},
  "geometry": {"coordinates":[-89.530834,43.315443],"type":"Point"}
}