{
  "type": "Feature",
  "properties": {
    "addr:full":"1620 W Winnebago St Appleton WI 54914",
    "addr:housenumber":"1620",
    "addr:postcode":"54914",
    "addr:street":"W Winnebago St",
    "iso:country":"US",
    "sg:address":"1620 W Winnebago St",
    "sg:city":"Appleton",
    "sg:classifiers":[
        {
            "category":"Organizations",
            "subcategory":"Religious Organization",
            "type":"Services"
        }
    ],
    "sg:phone":"+1 920 733 0797",
    "sg:postcode":"54914",
    "sg:province":"WI",
    "sg:tags":[
        "church"
    ],
    "wof:name":"Iglesia De Cristo Mission Cris",
    "wof:placetype":"venue"
},
  "geometry": {"coordinates":[-88.431617,44.269576],"type":"Point"}
}