{
  "type": "Feature",
  "properties": {
    "iso:country":"US",
    "sg:address":"1117 2nd St",
    "sg:city":"Hudson",
    "sg:classifiers":[
        {
            "category":"Freight",
            "type":"Transportation"
        }
    ],
    "sg:phone":"+1 715 531 1289",
    "sg:postcode":"54016",
    "sg:province":"WI",
    "sg:tags":[
        "operator",
        "local",
        "trucking"
    ],
    "wof:name":"Wulf Trax Delivery",
    "wof:placetype":"venue"
},
  "geometry": {"coordinates":[-92.757262,44.981638],"type":"Point"}
}