{
  "type": "Feature",
  "properties": {
    "iso:country":"US",
    "sg:address":"2940 Lincoln St",
    "sg:city":"Wisconsin Rapids",
    "sg:classifiers":[
        {
            "category":"Organizations",
            "subcategory":"Labor Organization",
            "type":"Services"
        }
    ],
    "sg:phone":"+1 715 424 5226",
    "sg:postcode":"54494",
    "sg:province":"WI",
    "wof:name":"Internationl Assn Machinsts/Ae",
    "wof:placetype":"venue"
},
  "geometry": {"coordinates":[-89.82204,44.368231],"type":"Point"}
}