{
  "type": "Feature",
  "properties": {
    "iso:country":"US",
    "sg:address":"12895 Willow Rd",
    "sg:city":"Ripon",
    "sg:phone":"+1 920 748 2379",
    "sg:postcode":"54971",
    "sg:province":"WI",
    "sg:tags":[
        "farm",
        "corn"
    ],
    "wof:name":"David Fox",
    "wof:placetype":"venue"
},
  "geometry": {"coordinates":[-88.80293,43.822402],"type":"Point"}
}