{
  "type": "Feature",
  "properties": {
    "iso:country":"US",
    "sg:address":"2949 Wood Ln",
    "sg:city":"Green Bay",
    "sg:classifiers":[
        {
            "category":"Freight",
            "type":"Transportation"
        }
    ],
    "sg:phone":"+1 920 434 1504",
    "sg:postcode":"54313",
    "sg:province":"WI",
    "sg:tags":[
        "petroleum",
        "liquid",
        "transport"
    ],
    "wof:name":"Mike Blaser Trucking Inc",
    "wof:placetype":"venue"
},
  "geometry": {"coordinates":[-88.097162,44.616043],"type":"Point"}
}