{
  "type": "Feature",
  "properties": {
    "iso:country":"US",
    "sg:address":"11841 Co Rd M",
    "sg:city":"Thorp",
    "sg:classifiers":[
        {
            "category":"Building & Trades",
            "subcategory":"Construction",
            "type":"Services"
        }
    ],
    "sg:phone":"+1 715 669 5212",
    "sg:postcode":"54771",
    "sg:province":"WI",
    "sg:tags":[
        "housing"
    ],
    "wof:name":"Alger Construction",
    "wof:placetype":"venue"
},
  "geometry": {"coordinates":[-90.800447,44.852515],"type":"Point"}
}