{
  "type": "Feature",
  "properties": {
    "iso:country":"US",
    "sg:address":"5510 Medical Cir",
    "sg:city":"Madison",
    "sg:classifiers":[
        {
            "category":"Banks & Credit Unions",
            "subcategory":"Bank",
            "type":"Services"
        }
    ],
    "sg:phone":"+1 608 273 3554",
    "sg:postcode":"53719",
    "sg:province":"WI",
    "sg:tags":[
        "broker",
        "mortgage"
    ],
    "wof:name":"Mortgage One Financial Svcs",
    "wof:placetype":"venue"
},
  "geometry": {"coordinates":[-89.47787,43.049784],"type":"Point"}
}