{
  "type": "Feature",
  "properties": {
    "iso:country":"US",
    "sg:address":"808 Kennedy St",
    "sg:city":"Rib Lake",
    "sg:classifiers":[
        {
            "category":"Government",
            "subcategory":"Office",
            "type":"Public Place"
        }
    ],
    "sg:phone":"+1 715 427 3101",
    "sg:postcode":"54470",
    "sg:province":"WI",
    "sg:tags":[
        "village"
    ],
    "wof:name":"Rib Lake Water Plant",
    "wof:placetype":"venue"
},
  "geometry": {"coordinates":[-90.20849800000001,45.319876],"type":"Point"}
}