{
  "type": "Feature",
  "properties": {
    "iso:country":"US",
    "sg:address":"108 W Chestnut St",
    "sg:city":"Burlington",
    "sg:classifiers":[
        {
            "category":"Retail",
            "subcategory":"Laundry & Dry Cleaning",
            "type":"Services"
        }
    ],
    "sg:phone":"+1 262 763 5500",
    "sg:postcode":"53105",
    "sg:province":"WI",
    "wof:name":"Michael Todd's Inc",
    "wof:placetype":"venue"
},
  "geometry": {"coordinates":[-88.277603,42.680302],"type":"Point"}
}