{
  "type": "Feature",
  "properties": {
    "addr:full":"10368 Little Rice Ln Boulder Junction WI 54512",
    "addr:housenumber":"10368",
    "addr:postcode":"54512",
    "addr:street":"Little Rice Ln",
    "iso:country":"US",
    "sg:address":"10368 Little Rice Ln",
    "sg:city":"Boulder Junction",
    "sg:classifiers":[
        {
            "category":"Travel",
            "subcategory":"Hotels & Motels",
            "type":"Entertainment"
        }
    ],
    "sg:phone":"+1 715 385 2972",
    "sg:postcode":"54512",
    "sg:province":"WI",
    "wof:name":"Guest House",
    "wof:placetype":"venue"
},
  "geometry": {"coordinates":[-89.64346399999999,46.114069],"type":"Point"}
}