{
  "type": "Feature",
  "properties": {
    "iso:country":"US",
    "sg:address":"5122 Custer Rd",
    "sg:city":"Stevens Point",
    "sg:classifiers":[
        {
            "category":"Farming",
            "subcategory":"Farm",
            "type":"Manufacturing & Wholesale Goods"
        }
    ],
    "sg:phone":"+1 715 341 0721",
    "sg:postcode":"54481",
    "sg:province":"WI",
    "sg:tags":[
        "crop",
        "general"
    ],
    "wof:name":"Dominic Biadasz",
    "wof:placetype":"venue"
},
  "geometry": {"coordinates":[-89.426423,44.43203],"type":"Point"}
}