{
  "type": "Feature",
  "properties": {
    "addr:full":"23932 Larson Rd Grantsburg WI 54840",
    "addr:housenumber":"23932",
    "addr:postcode":"54840",
    "addr:street":"Larson Rd",
    "iso:country":"US",
    "sg:address":"23932 Larson Rd",
    "sg:city":"Grantsburg",
    "sg:classifiers":[
        {
            "category":"Retail",
            "subcategory":"Repair Shop",
            "type":"Services"
        }
    ],
    "sg:phone":"+1 715 463 2149",
    "sg:postcode":"54840",
    "sg:province":"WI",
    "sg:tags":[
        "plumbing",
        "drain",
        "cleaning",
        "sewer"
    ],
    "wof:name":"Rotor-Rooter",
    "wof:placetype":"venue"
},
  "geometry": {"coordinates":[-92.723328,45.781405],"type":"Point"}
}