{
  "type": "Feature",
  "properties": {
    "iso:country":"US",
    "sg:address":"506 N Summit Ave",
    "sg:city":"Oconomowoc",
    "sg:classifiers":[
        {
            "category":"Farming",
            "subcategory":"Farm",
            "type":"Manufacturing & Wholesale Goods"
        }
    ],
    "sg:phone":"+1 262 965 2631",
    "sg:postcode":"53066",
    "sg:province":"WI",
    "sg:tags":[
        "crop",
        "general"
    ],
    "wof:name":"Nettesheim Farm",
    "wof:placetype":"venue"
},
  "geometry": {"coordinates":[-88.462304,43.025934],"type":"Point"}
}