{
  "type": "Feature",
  "properties": {
    "iso:country":"US",
    "sg:address":"1205 Marinette Ave",
    "sg:city":"Marinette",
    "sg:classifiers":[
        {
            "category":"Building & Trades",
            "subcategory":"Equipment Rental",
            "type":"Services"
        }
    ],
    "sg:phone":"+1 715 735 3318",
    "sg:postcode":"54143",
    "sg:province":"WI",
    "sg:tags":[
        "heavy",
        "construction"
    ],
    "wof:name":"Johnson Cranes & Equipment",
    "wof:placetype":"venue"
},
  "geometry": {"coordinates":[-87.646075,45.093607],"type":"Point"}
}