{
  "type": "Feature",
  "properties": {
    "iso:country":"US",
    "sg:address":"33 E 3rd St",
    "sg:city":"Clintonville",
    "sg:classifiers":[
        {
            "category":"Insurance",
            "subcategory":"Insurance Agent",
            "type":"Services"
        }
    ],
    "sg:phone":"+1 715 823 7175",
    "sg:postcode":"54929",
    "sg:province":"WI",
    "wof:name":"Trivent Financial For Lutheran",
    "wof:placetype":"venue"
},
  "geometry": {"coordinates":[-88.762162,44.614514],"type":"Point"}
}