{
  "type": "Feature",
  "properties": {
    "iso:country":"US",
    "sg:address":"3970 N Oakland Ave",
    "sg:city":"Milwaukee",
    "sg:classifiers":[
        {
            "category":"Health Services",
            "subcategory":"Health Practitioner",
            "type":"Services"
        }
    ],
    "sg:phone":"+1 414 963 6330",
    "sg:postcode":"53211",
    "sg:province":"WI",
    "sg:tags":[
        "therapist",
        "physical"
    ],
    "wof:name":"Paul Rossman Physical Therapy",
    "wof:placetype":"venue"
},
  "geometry": {"coordinates":[-87.887427,43.087886],"type":"Point"}
}