{
  "type": "Feature",
  "properties": {
    "iso:country":"US",
    "sg:address":"5981 S Darrow Rd",
    "sg:city":"Superior",
    "sg:classifiers":[
        {
            "category":"Building & Trades",
            "subcategory":"Electrical",
            "type":"Services"
        }
    ],
    "sg:phone":"+1 715 394 3873",
    "sg:postcode":"54880",
    "sg:province":"WI",
    "sg:tags":[
        "electrical",
        "contractor"
    ],
    "wof:name":"Lake City Electric Inc",
    "wof:placetype":"venue"
},
  "geometry": {"coordinates":[-92.087733,46.547887],"type":"Point"}
}