{
  "type": "Feature",
  "properties": {
    "addr:full":"123 S Fieldcrest Dr Neenah WI 54956",
    "addr:housenumber":"123",
    "addr:postcode":"54956",
    "addr:street":"S Fieldcrest Dr",
    "iso:country":"US",
    "sg:address":"123 S Fieldcrest Dr",
    "sg:city":"Neenah",
    "sg:classifiers":[
        {
            "category":"Retail",
            "subcategory":"Auto Repair",
            "type":"Services"
        }
    ],
    "sg:phone":"+1 920 720 6096",
    "sg:postcode":"54956",
    "sg:province":"WI",
    "sg:tags":[
        "body",
        "automobile",
        "painting"
    ],
    "wof:name":"Mirror Image Autobody",
    "wof:placetype":"venue"
},
  "geometry": {"coordinates":[-88.50945400000001,44.198147],"type":"Point"}
}