{
  "type": "Feature",
  "properties": {
    "iso:country":"US",
    "sg:address":"7872 Windmill St",
    "sg:city":"Holmen",
    "sg:classifiers":[
        {
            "category":"Professional",
            "subcategory":"Business Services",
            "type":"Services"
        }
    ],
    "sg:phone":"+1 608 526 2857",
    "sg:postcode":"54636",
    "sg:province":"WI",
    "wof:name":"Home Inspection Co Inc",
    "wof:placetype":"venue"
},
  "geometry": {"coordinates":[-91.298331,43.974897],"type":"Point"}
}