{
  "type": "Feature",
  "properties": {
    "addr:full":"5605 Washington Ave Racine WI 53406",
    "addr:housenumber":"5605",
    "addr:postcode":"53406",
    "addr:street":"Washington Ave",
    "iso:country":"US",
    "sg:address":"5605 Washington Ave",
    "sg:city":"Racine",
    "sg:classifiers":[
        {
            "category":"Health Services",
            "subcategory":"Podiatrist",
            "type":"Services"
        }
    ],
    "sg:phone":"+1 262 886 9404",
    "sg:postcode":"53406",
    "sg:province":"WI",
    "wof:name":"Foot & Ankle Health Center",
    "wof:placetype":"venue"
},
  "geometry": {"coordinates":[-87.848651,42.718889],"type":"Point"}
}