{
  "type": "Feature",
  "properties": {
    "addr:full":"5500 8th Ave Kenosha WI 53140",
    "addr:housenumber":"5500",
    "addr:postcode":"53140",
    "addr:street":"8Th Ave",
    "iso:country":"US",
    "sg:address":"5500 8th Ave",
    "sg:city":"Kenosha",
    "sg:classifiers":[
        {
            "category":"Banks & Credit Unions",
            "subcategory":"Investment Brokerage",
            "type":"Services"
        }
    ],
    "sg:phone":"+1 262 658 4891",
    "sg:postcode":"53140",
    "sg:province":"WI",
    "sg:tags":[
        "stock",
        "bond"
    ],
    "wof:name":"Wachovia Securities",
    "wof:placetype":"venue"
},
  "geometry": {"coordinates":[-87.821028,42.584789],"type":"Point"}
}