{
  "type": "Feature",
  "properties": {
    "addr:full":"660 Grand Ave Hartford WI 53027",
    "addr:housenumber":"660",
    "addr:postcode":"53027",
    "addr:street":"Grand Ave",
    "iso:country":"US",
    "sg:address":"660 Grand Ave",
    "sg:city":"Hartford",
    "sg:classifiers":[
        {
            "category":"Professional",
            "subcategory":"Business Services",
            "type":"Services"
        }
    ],
    "sg:phone":"+1 262 673 7425",
    "sg:postcode":"53027",
    "sg:province":"WI",
    "sg:tags":[
        "fund",
        "promotion",
        "raising"
    ],
    "wof:name":"Northern Lights Productions",
    "wof:placetype":"venue"
},
  "geometry": {"coordinates":[-88.37406300000001,43.309513],"type":"Point"}
}