{
  "type": "Feature",
  "properties": {
    "iso:country":"US",
    "sg:address":"5315 State Hwy 180",
    "sg:city":"Marinette",
    "sg:classifiers":[
        {
            "category":"Retail",
            "subcategory":"Auto Repair",
            "type":"Services"
        }
    ],
    "sg:phone":"+1 715 732 4929",
    "sg:postcode":"54143",
    "sg:province":"WI",
    "sg:tags":[
        "repairing",
        "automobile",
        "general"
    ],
    "wof:name":"Wagner Repair Inc",
    "wof:placetype":"venue"
},
  "geometry": {"coordinates":[-87.715672,45.157268],"type":"Point"}
}