{
  "type": "Feature",
  "properties": {
    "addr:full":"8750 N 51st St Milwaukee WI 53223",
    "addr:housenumber":"8750",
    "addr:postcode":"53223",
    "addr:street":"N 51St St",
    "iso:country":"US",
    "sg:address":"8750 N 51st St",
    "sg:city":"Milwaukee",
    "sg:classifiers":[
        {
            "category":"Social Services",
            "subcategory":"Child Care",
            "type":"Services"
        }
    ],
    "sg:phone":"+1 414 354 3770",
    "sg:postcode":"53223",
    "sg:province":"WI",
    "sg:website":"www.kindercare.com",
    "wof:name":"Kinder Care Learning Ctr",
    "wof:placetype":"venue"
},
  "geometry": {"coordinates":[-87.97448,43.176641],"type":"Point"}
}