{
  "type": "Feature",
  "properties": {
    "iso:country":"US",
    "sg:address":"5001 Monona Dr",
    "sg:city":"Madison",
    "sg:classifiers":[
        {
            "category":"Shopping",
            "subcategory":"Pharmacy",
            "type":"Retail Goods"
        }
    ],
    "sg:phone":"+1 608 226 5039",
    "sg:postcode":"53716",
    "sg:province":"WI",
    "sg:tags":[
        "drug"
    ],
    "wof:name":"Physicians Plus Pharmacy Inc",
    "wof:placetype":"venue"
},
  "geometry": {"coordinates":[-89.326203,43.06697],"type":"Point"}
}