{
  "type": "Feature",
  "properties": {
    "addr:full":"9989 State Rd 80 Livingston WI 53554",
    "addr:housenumber":"9989;80",
    "addr:postcode":"53554",
    "addr:street":"State Rd",
    "iso:country":"US",
    "sg:address":"9989 State Rd 80",
    "sg:city":"Livingston",
    "sg:classifiers":[
        {
            "category":"Farming",
            "subcategory":"Dairy Farm",
            "type":"Manufacturing & Wholesale Goods"
        }
    ],
    "sg:phone":"+1 608 943 6865",
    "sg:postcode":"53554",
    "sg:province":"WI",
    "wof:name":"Brian B Olson",
    "wof:placetype":"venue"
},
  "geometry": {"coordinates":[-90.44700899999999,42.870512],"type":"Point"}
}