{
  "type": "Feature",
  "properties": {
    "iso:country":"US",
    "sg:address":"539 High Ave",
    "sg:city":"Oshkosh",
    "sg:classifiers":[
        {
            "category":"Bars & Pubs",
            "type":"Food & Drink"
        }
    ],
    "sg:phone":"+1 920 232 0067",
    "sg:postcode":"54901",
    "sg:province":"WI",
    "sg:tags":[
        "drinking"
    ],
    "wof:name":"French Quarter",
    "wof:placetype":"venue"
},
  "geometry": {"coordinates":[-88.546357,44.021281],"type":"Point"}
}