{
  "type": "Feature",
  "properties": {
    "iso:country":"US",
    "sg:address":"3050 Monica Ct",
    "sg:city":"Plover",
    "sg:classifiers":[
        {
            "category":"Bars & Pubs",
            "type":"Food & Drink"
        }
    ],
    "sg:phone":"+1 715 342 4065",
    "sg:postcode":"54467",
    "sg:province":"WI",
    "sg:tags":[
        "drinking"
    ],
    "wof:name":"Backstreet Pub",
    "wof:placetype":"venue"
},
  "geometry": {"coordinates":[-89.559697,44.452177],"type":"Point"}
}