{
  "type": "Feature",
  "properties": {
    "addr:full":"4069 US Hwy 141 Pound WI 54161",
    "addr:housenumber":"4069",
    "addr:postcode":"54161",
    "addr:street":"Us Hwy 141",
    "iso:country":"US",
    "sg:address":"4069 US Hwy 141",
    "sg:city":"Pound",
    "sg:classifiers":[
        {
            "category":"Wholesale",
            "subcategory":"Meat",
            "type":"Manufacturing & Wholesale Goods"
        }
    ],
    "sg:phone":"+1 920 897 3108",
    "sg:postcode":"54161",
    "sg:province":"WI",
    "sg:tags":[
        "butchering"
    ],
    "wof:name":"Kinziger Meat Processor",
    "wof:placetype":"venue"
},
  "geometry": {"coordinates":[-88.033715,45.106511],"type":"Point"}
}