{
  "type": "Feature",
  "properties": {
    "iso:country":"US",
    "sg:address":"4797 Hayes Rd",
    "sg:city":"Madison",
    "sg:classifiers":[
        {
            "category":"Organizations",
            "subcategory":"Professional Association",
            "type":"Services"
        }
    ],
    "sg:phone":"+1 608 242 1090",
    "sg:postcode":"53704",
    "sg:province":"WI",
    "sg:website":"www.wasda.org",
    "wof:name":"Wi Association-School Dist Adm",
    "wof:placetype":"venue"
},
  "geometry": {"coordinates":[-89.299553,43.139873],"type":"Point"}
}