{
  "type": "Feature",
  "properties": {
    "iso:country":"US",
    "sg:address":"544 Elizabeth Ct",
    "sg:city":"Sun Prairie",
    "sg:classifiers":[
        {
            "category":"Building & Trades",
            "subcategory":"Construction",
            "type":"Services"
        }
    ],
    "sg:phone":"+1 608 837 2228",
    "sg:postcode":"53590",
    "sg:province":"WI",
    "sg:tags":[
        "nonresidential"
    ],
    "wof:name":"Nucor Building Systems Sales C",
    "wof:placetype":"venue"
},
  "geometry": {"coordinates":[-89.205867,43.187693],"type":"Point"}
}