{
  "type": "Feature",
  "properties": {
    "iso:country":"US",
    "sg:address":"6933 Raymond Rd",
    "sg:city":"Madison",
    "sg:classifiers":[
        {
            "category":"Shopping",
            "subcategory":"Computers & Home Electronics",
            "type":"Retail Goods"
        }
    ],
    "sg:phone":"+1 608 848 8896",
    "sg:postcode":"53711",
    "sg:province":"WI",
    "sg:tags":[
        "equipment",
        "dealer"
    ],
    "wof:name":"Advanced Computer Investigated",
    "wof:placetype":"venue"
},
  "geometry": {"coordinates":[-89.50199,43.031673],"type":"Point"}
}