{
  "type": "Feature",
  "properties": {
    "addr:full":"13197 Church St Pigeon Falls WI 54760",
    "addr:housenumber":"13197",
    "addr:postcode":"54760",
    "addr:street":"Church St Pigeon",
    "iso:country":"US",
    "sg:address":"13197 Church St",
    "sg:city":"Pigeon Falls",
    "sg:classifiers":[
        {
            "category":"Health Services",
            "subcategory":"Nursing And Care Facility",
            "type":"Services"
        }
    ],
    "sg:phone":"+1 715 983 2293",
    "sg:postcode":"54760",
    "sg:province":"WI",
    "sg:tags":[
        "home",
        "convalescent"
    ],
    "sg:website":"www.tchcc.com",
    "wof:name":"Pigeon Falls Health Care Ctr",
    "wof:placetype":"venue"
},
  "geometry": {"coordinates":[-91.20759,44.424033],"type":"Point"}
}