{
  "type": "Feature",
  "properties": {
    "iso:country":"US",
    "sg:address":"4270 Kennedy Cir N",
    "sg:city":"Colgate",
    "sg:classifiers":[
        {
            "category":"Manufacturing",
            "subcategory":"Apparel",
            "type":"Manufacturing & Wholesale Goods"
        }
    ],
    "sg:phone":"+1 262 628 3059",
    "sg:postcode":"53017",
    "sg:province":"WI",
    "sg:tags":[
        "mfg"
    ],
    "wof:name":"Draperies By Margo",
    "wof:placetype":"venue"
},
  "geometry": {"coordinates":[-88.247609,43.20264],"type":"Point"}
}