{
  "type": "Feature",
  "properties": {
    "iso:country":"US",
    "sg:address":"506 E Minerva St",
    "sg:city":"Darlington",
    "sg:classifiers":[
        {
            "category":"Food & Beverages",
            "subcategory":"Dairy",
            "type":"Retail Goods"
        },
        {
            "category":"Wholesale",
            "subcategory":"Dairy",
            "type":"Manufacturing & Wholesale Goods"
        }
    ],
    "sg:phone":"+1 608 776 3672",
    "sg:postcode":"53530",
    "sg:province":"WI",
    "sg:tags":[
        "cheese",
        "product"
    ],
    "wof:name":"Randy Hardyman Grande Cheese",
    "wof:placetype":"venue"
},
  "geometry": {"coordinates":[-90.112782,42.685588],"type":"Point"}
}