{
  "type": "Feature",
  "properties": {
    "iso:country":"US",
    "sg:address":"5090 Haire Rd",
    "sg:city":"Weyauwega",
    "sg:classifiers":[
        {
            "category":"Freight",
            "type":"Transportation"
        }
    ],
    "sg:phone":"+1 920 867 4526",
    "sg:postcode":"54983",
    "sg:province":"WI",
    "sg:tags":[
        "operator",
        "local",
        "trucking"
    ],
    "wof:name":"David Miller Trucking Inc",
    "wof:placetype":"venue"
},
  "geometry": {"coordinates":[-88.974734,44.329991],"type":"Point"}
}