{
  "type": "Feature",
  "properties": {
    "iso:country":"US",
    "sg:address":"2510 Mineral Point Ave",
    "sg:city":"Janesville",
    "sg:classifiers":[
        {
            "category":"Restaurant",
            "type":"Food & Drink"
        }
    ],
    "sg:phone":"+1 608 756 4424",
    "sg:postcode":"53548",
    "sg:province":"WI",
    "sg:tags":[
        "shop",
        "coffee"
    ],
    "wof:name":"Mugshotz",
    "wof:placetype":"venue"
},
  "geometry": {"coordinates":[-89.04833,42.686533],"type":"Point"}
}