{
  "type": "Feature",
  "properties": {
    "iso:country":"US",
    "sg:address":"621 Atlas Ave",
    "sg:city":"Madison",
    "sg:classifiers":[
        {
            "category":"Wholesale",
            "subcategory":"Groceries",
            "type":"Manufacturing & Wholesale Goods"
        }
    ],
    "sg:phone":"+1 608 221 2201",
    "sg:postcode":"53714",
    "sg:province":"WI",
    "wof:name":"Wonder Bread - Hostess Cakes",
    "wof:placetype":"venue"
},
  "geometry": {"coordinates":[-89.307831,43.085411],"type":"Point"}
}