{
  "type": "Feature",
  "properties": {
    "iso:country":"US",
    "sg:address":"2665 Co Rd Qq",
    "sg:city":"King",
    "sg:classifiers":[
        {
            "category":"Government",
            "subcategory":"Office",
            "type":"Public Place"
        }
    ],
    "sg:phone":"+1 715 258 5586",
    "sg:postcode":"54981",
    "sg:province":"WI",
    "sg:tags":[
        "home",
        "veteran"
    ],
    "wof:name":"Wisconsin Veterans Home",
    "wof:placetype":"venue"
},
  "geometry": {"coordinates":[-89.14236699999999,44.336892],"type":"Point"}
}