{
  "type": "Feature",
  "properties": {
    "iso:country":"US",
    "sg:address":"15910 W Company Lake Rd",
    "sg:city":"Hayward",
    "sg:classifiers":[
        {
            "category":"Personal",
            "type":"Services"
        }
    ],
    "sg:phone":"+1 715 634 6333",
    "sg:postcode":"54843",
    "sg:province":"WI",
    "sg:tags":[
        "therapist",
        "massage"
    ],
    "wof:name":"Body Kneads Massage Therapy",
    "wof:placetype":"venue"
},
  "geometry": {"coordinates":[-91.530075,46.042717],"type":"Point"}
}