{
  "type": "Feature",
  "properties": {
    "iso:country":"US",
    "sg:address":"10231 Hawk Cir",
    "sg:city":"Oak Creek",
    "sg:classifiers":[
        {
            "category":"Freight",
            "type":"Transportation"
        }
    ],
    "sg:phone":"+1 414 570 6002",
    "sg:postcode":"53154",
    "sg:province":"WI",
    "sg:tags":[
        "local",
        "trucking"
    ],
    "wof:name":"Gt Services Inc",
    "wof:placetype":"venue"
},
  "geometry": {"coordinates":[-87.90594299999999,42.859293],"type":"Point"}
}