{
  "type": "Feature",
  "properties": {
    "iso:country":"US",
    "sg:address":"2383 State Hwy 17",
    "sg:city":"Phelps",
    "sg:classifiers":[
        {
            "category":"Health Services",
            "subcategory":"Doctor",
            "type":"Services"
        }
    ],
    "sg:phone":"+1 715 545 2710",
    "sg:postcode":"54554",
    "sg:province":"WI",
    "sg:tags":[
        "medical"
    ],
    "wof:name":"Phelps Clinic",
    "wof:placetype":"venue"
},
  "geometry": {"coordinates":[-89.092868,46.059343],"type":"Point"}
}