{
  "type": "Feature",
  "properties": {
    "addr:full":"629 140th St Roberts WI 54023",
    "addr:housenumber":"629",
    "addr:postcode":"54023",
    "addr:street":"140Th St",
    "iso:country":"US",
    "sg:address":"629 140th St",
    "sg:city":"Roberts",
    "sg:classifiers":[
        {
            "category":"Autos & Motor Vehicles",
            "subcategory":"Auto Supplies",
            "type":"Retail Goods"
        }
    ],
    "sg:phone":"+1 715 749 4073",
    "sg:postcode":"54023",
    "sg:province":"WI",
    "wof:name":"River Falls Tire Co",
    "wof:placetype":"venue"
},
  "geometry": {"coordinates":[-92.51720400000001,44.952237],"type":"Point"}
}