{
  "type": "Feature",
  "properties": {
    "iso:country":"US",
    "sg:address":"925 Glenway Rd",
    "sg:city":"Oregon",
    "sg:classifiers":[
        {
            "category":"Professional",
            "subcategory":"Business Services",
            "type":"Services"
        }
    ],
    "sg:phone":"+1 608 835 2966",
    "sg:postcode":"53575",
    "sg:province":"WI",
    "wof:name":"Discovery Toys",
    "wof:placetype":"venue"
},
  "geometry": {"coordinates":[-89.418422,42.909672],"type":"Point"}
}