{
  "type": "Feature",
  "properties": {
    "iso:country":"US",
    "sg:address":"217 E Jefferson St",
    "sg:city":"Viroqua",
    "sg:classifiers":[
        {
            "category":"Travel",
            "subcategory":"Hotels & Motels",
            "type":"Entertainment"
        }
    ],
    "sg:phone":"+1 608 637 8644",
    "sg:postcode":"54665",
    "sg:province":"WI",
    "sg:tags":[
        "breakfast",
        "operation",
        "bed",
        "accommodation"
    ],
    "wof:name":"Eckhart House Bed & Breakfasts",
    "wof:placetype":"venue"
},
  "geometry": {"coordinates":[-90.887927,43.555275],"type":"Point"}
}