{
  "type": "Feature",
  "properties": {
    "iso:country":"US",
    "sg:address":"3041 W Co Rd A",
    "sg:city":"Cascade",
    "sg:classifiers":[
        {
            "category":"Farming",
            "subcategory":"Fish & Marine Products",
            "type":"Manufacturing & Wholesale Goods"
        }
    ],
    "sg:phone":"+1 920 528 8848",
    "sg:postcode":"53011",
    "sg:province":"WI",
    "sg:tags":[
        "preserves",
        "fishing",
        "hunting"
    ],
    "sg:website":"www.thehighlandsclub.com",
    "wof:name":"Highland Sportsmen's Club",
    "wof:placetype":"venue"
},
  "geometry": {"coordinates":[-88.099838,43.657318],"type":"Point"}
}