{
  "type": "Feature",
  "properties": {
    "addr:full":"344 Wausau Center Wausau WI 54403",
    "addr:housenumber":"344",
    "addr:postcode":"54403",
    "iso:country":"US",
    "sg:address":"344 Wausau Center",
    "sg:city":"Wausau",
    "sg:classifiers":[
        {
            "category":"Shopping",
            "subcategory":"Computers & Home Electronics",
            "type":"Retail Goods"
        }
    ],
    "sg:phone":"+1 715 845 8020",
    "sg:postcode":"54403",
    "sg:province":"WI",
    "wof:name":"Radio Shack",
    "wof:placetype":"venue"
},
  "geometry": {"coordinates":[-89.628716,44.958933],"type":"Point"}
}