{
  "type": "Feature",
  "properties": {
    "addr:full":"11485 Cardinal Ave Loyal WI 54446",
    "addr:housenumber":"11485",
    "addr:postcode":"54446",
    "addr:street":"Cardinal Ave",
    "iso:country":"US",
    "sg:address":"11485 Cardinal Ave",
    "sg:city":"Loyal",
    "sg:classifiers":[
        {
            "category":"Farming",
            "subcategory":"Dairy Farm",
            "type":"Manufacturing & Wholesale Goods"
        }
    ],
    "sg:phone":"+1 715 267 7388",
    "sg:postcode":"54446",
    "sg:province":"WI",
    "wof:name":"Roderick Porath",
    "wof:placetype":"venue"
},
  "geometry": {"coordinates":[-90.536745,44.822092],"type":"Point"}
}