{
  "type": "Feature",
  "properties": {
    "addr:full":"1311 Corey Ave Wisconsin Rapids WI 54494",
    "addr:housenumber":"1311",
    "addr:postcode":"54494",
    "addr:street":"Corey Ave",
    "iso:country":"US",
    "sg:address":"1311 Corey Ave",
    "sg:city":"Wisconsin Rapids",
    "sg:classifiers":[
        {
            "category":"Shopping",
            "subcategory":"Bicycles & Sporting Goods",
            "type":"Retail Goods"
        }
    ],
    "sg:phone":"+1 715 424 1139",
    "sg:postcode":"54494",
    "sg:province":"WI",
    "wof:name":"Thelemanns Archery",
    "wof:placetype":"venue"
},
  "geometry": {"coordinates":[-89.81,44.363287],"type":"Point"}
}