{
  "type": "Feature",
  "properties": {
    "iso:country":"US",
    "sg:address":"5498 Hillcrest Dr",
    "sg:city":"Shawano",
    "sg:classifiers":[
        {
            "category":"Building & Trades",
            "subcategory":"Landscaping Services",
            "type":"Services"
        }
    ],
    "sg:phone":"+1 715 745 6751",
    "sg:postcode":"54166",
    "sg:province":"WI",
    "wof:name":"Hillcrest Tree Service",
    "wof:placetype":"venue"
},
  "geometry": {"coordinates":[-88.50726299999999,44.777231],"type":"Point"}
}