{
  "type": "Feature",
  "properties": {
    "iso:country":"US",
    "sg:address":"1007 N Glenview Ave",
    "sg:city":"Milwaukee",
    "sg:classifiers":[
        {
            "category":"Insurance",
            "subcategory":"Insurance Agent",
            "type":"Services"
        }
    ],
    "sg:phone":"+1 414 259 8044",
    "sg:postcode":"53213",
    "sg:province":"WI",
    "wof:name":"Kepri Insurance Group",
    "wof:placetype":"venue"
},
  "geometry": {"coordinates":[-88.013637,43.043064],"type":"Point"}
}