{
  "type": "Feature",
  "properties": {
    "addr:full":"254 S Chestnut St Ellsworth WI 54011",
    "addr:housenumber":"254",
    "addr:postcode":"54011",
    "addr:street":"S Chestnut St",
    "iso:country":"US",
    "sg:address":"254 S Chestnut St",
    "sg:city":"Ellsworth",
    "sg:classifiers":[
        {
            "category":"Freight",
            "type":"Transportation"
        }
    ],
    "sg:phone":"+1 715 273 6279",
    "sg:postcode":"54011",
    "sg:province":"WI",
    "sg:tags":[
        "trucking"
    ],
    "wof:name":"By-Tech Inc",
    "wof:placetype":"venue"
},
  "geometry": {"coordinates":[-92.482978,44.729072],"type":"Point"}
}