{
  "type": "Feature",
  "properties": {
    "iso:country":"US",
    "sg:address":"6774 Acorn Ave",
    "sg:city":"Cataract",
    "sg:classifiers":[
        {
            "category":"Organizations",
            "subcategory":"Religious Organization",
            "type":"Services"
        }
    ],
    "sg:phone":"+1 608 272 3844",
    "sg:postcode":"54656",
    "sg:province":"WI",
    "sg:tags":[
        "church"
    ],
    "wof:name":"Peace Lutheran Church",
    "wof:placetype":"venue"
},
  "geometry": {"coordinates":[-90.85596700000001,44.129097],"type":"Point"}
}