{
  "type": "Feature",
  "properties": {
    "iso:country":"US",
    "sg:address":"6274 Portage Rd",
    "sg:city":"De Forest",
    "sg:classifiers":[
        {
            "category":"Building & Trades",
            "subcategory":"Construction",
            "type":"Services"
        }
    ],
    "sg:phone":"+1 608 846 4611",
    "sg:postcode":"53532",
    "sg:province":"WI",
    "sg:tags":[
        "painter"
    ],
    "wof:name":"Butler Painting & Prefinishing",
    "wof:placetype":"venue"
},
  "geometry": {"coordinates":[-89.292349,43.190293],"type":"Point"}
}