{
  "type": "Feature",
  "properties": {
    "iso:country":"US",
    "sg:address":"265 S 3rd St",
    "sg:city":"Dorchester",
    "sg:classifiers":[
        {
            "category":"Organizations",
            "subcategory":"Religious Organization",
            "type":"Services"
        }
    ],
    "sg:phone":"+1 715 654 5055",
    "sg:postcode":"54425",
    "sg:province":"WI",
    "sg:tags":[
        "church"
    ],
    "wof:name":"St Peter Lutheran Church",
    "wof:placetype":"venue"
},
  "geometry": {"coordinates":[-90.334684,45.000524],"type":"Point"}
}