{
  "type": "Feature",
  "properties": {
    "iso:country":"US",
    "sg:address":"3847 Co Rd G",
    "sg:city":"Caledonia",
    "sg:classifiers":[
        {
            "category":"Building & Trades",
            "subcategory":"Landscaping Services",
            "type":"Services"
        }
    ],
    "sg:phone":"+1 262 835 2507",
    "sg:postcode":"53108",
    "sg:province":"WI",
    "sg:tags":[
        "plant",
        "internal",
        "landscape",
        "care"
    ],
    "wof:name":"Plantscapes",
    "wof:placetype":"venue"
},
  "geometry": {"coordinates":[-87.965074,42.807863],"type":"Point"}
}