{
  "type": "Feature",
  "properties": {
    "addr:full":"4836 W Forest Home Ave Milwaukee WI 53219",
    "addr:housenumber":"4836",
    "addr:postcode":"53219",
    "addr:street":"W Forest Home Ave",
    "iso:country":"US",
    "sg:address":"4836 W Forest Home Ave",
    "sg:city":"Milwaukee",
    "sg:classifiers":[
        {
            "category":"Wholesale",
            "subcategory":"Machinery & Supplies",
            "type":"Manufacturing & Wholesale Goods"
        },
        {
            "category":"Wholesale",
            "subcategory":"Electrical",
            "type":"Manufacturing & Wholesale Goods"
        }
    ],
    "sg:phone":"+1 414 546 2322",
    "sg:postcode":"53219",
    "sg:province":"WI",
    "sg:tags":[
        "equipment",
        "audiometer"
    ],
    "wof:name":"Gordon N Stowe & Associates",
    "wof:placetype":"venue"
},
  "geometry": {"coordinates":[-87.974959,42.984869],"type":"Point"}
}