{
  "type": "Feature",
  "properties": {
    "iso:country":"US",
    "sg:address":"406 S 6th St",
    "sg:city":"Delavan",
    "sg:classifiers":[
        {
            "category":"Organizations",
            "subcategory":"Religious Organization",
            "type":"Services"
        }
    ],
    "sg:phone":"+1 262 728 6730",
    "sg:postcode":"53115",
    "sg:province":"WI",
    "sg:tags":[
        "church"
    ],
    "wof:name":"Wayman Chapel",
    "wof:placetype":"venue"
},
  "geometry": {"coordinates":[-88.640708,42.628235],"type":"Point"}
}