{
  "type": "Feature",
  "properties": {
    "addr:full":"1071 Kenwood St Green Bay WI 54304",
    "addr:housenumber":"1071",
    "addr:postcode":"54304",
    "addr:street":"Kenwood St",
    "iso:country":"US",
    "sg:address":"1071 Kenwood St",
    "sg:city":"Green Bay",
    "sg:classifiers":[
        {
            "category":"Building & Trades",
            "subcategory":"Construction",
            "type":"Services"
        }
    ],
    "sg:phone":"+1 920 497 8772",
    "sg:postcode":"54304",
    "sg:province":"WI",
    "sg:tags":[
        "hanging",
        "contractor"
    ],
    "wof:name":"Lee S Professional Painting",
    "wof:placetype":"venue"
},
  "geometry": {"coordinates":[-88.054751,44.503102],"type":"Point"}
}