{
  "type": "Feature",
  "properties": {
    "iso:country":"US",
    "sg:address":"310 Slate Ave",
    "sg:city":"Mattoon",
    "sg:classifiers":[
        {
            "category":"Utilities",
            "subcategory":"Water",
            "type":"Services"
        }
    ],
    "sg:phone":"+1 715 489 3748",
    "sg:postcode":"54450",
    "sg:province":"WI",
    "sg:tags":[
        "company",
        "sewage"
    ],
    "wof:name":"Mattoon Water Dept",
    "wof:placetype":"venue"
},
  "geometry": {"coordinates":[-89.045089,45.004192],"type":"Point"}
}