{
  "type": "Feature",
  "properties": {
    "iso:country":"US",
    "sg:address":"28820 Henry Clark Ln",
    "sg:city":"Richland Center",
    "sg:classifiers":[
        {
            "category":"Organizations",
            "subcategory":"Religious Organization",
            "type":"Services"
        }
    ],
    "sg:phone":"+1 608 647 3070",
    "sg:postcode":"53581",
    "sg:province":"WI",
    "sg:tags":[
        "church"
    ],
    "wof:name":"Ash Creek United Methodist Chr",
    "wof:placetype":"venue"
},
  "geometry": {"coordinates":[-90.361908,43.279672],"type":"Point"}
}