{
  "type": "Feature",
  "properties": {
    "addr:full":"4875 Co Rd Pp Plymouth WI 53073",
    "addr:housenumber":"4875",
    "addr:postcode":"53073",
    "addr:street":"Co Rd",
    "iso:country":"US",
    "sg:address":"4875 Co Rd Pp",
    "sg:city":"Plymouth",
    "sg:classifiers":[
        {
            "category":"Freight",
            "type":"Transportation"
        }
    ],
    "sg:phone":"+1 920 892 4211",
    "sg:postcode":"53073",
    "sg:province":"WI",
    "sg:tags":[
        "operator",
        "local",
        "trucking"
    ],
    "wof:name":"Truttschel Trucking Co",
    "wof:placetype":"venue"
},
  "geometry": {"coordinates":[-87.939874,43.732654],"type":"Point"}
}