{
  "type": "Feature",
  "properties": {
    "addr:full":"940 Bell Ave Hartford WI 53027",
    "addr:housenumber":"940",
    "addr:postcode":"53027",
    "addr:street":"Bell Ave",
    "iso:country":"US",
    "sg:address":"940 Bell Ave",
    "sg:city":"Hartford",
    "sg:classifiers":[
        {
            "category":"Shopping",
            "type":"Retail Goods"
        }
    ],
    "sg:phone":"+1 262 673 7725",
    "sg:postcode":"53027",
    "sg:province":"WI",
    "sg:tags":[
        "hearing",
        "equipment",
        "supply",
        "impaired"
    ],
    "wof:name":"Avada Audiology & Hearing Care",
    "wof:placetype":"venue"
},
  "geometry": {"coordinates":[-88.364811,43.316435],"type":"Point"}
}