{
  "type": "Feature",
  "properties": {
    "iso:country":"US",
    "sg:address":"1341 N 31st St",
    "sg:city":"Sheboygan",
    "sg:classifiers":[
        {
            "category":"Education",
            "subcategory":"School",
            "type":"Public Place"
        }
    ],
    "sg:phone":"+1 920 208 7520",
    "sg:postcode":"53081",
    "sg:province":"WI",
    "wof:name":"Landmark Christian Care Acad",
    "wof:placetype":"venue"
},
  "geometry": {"coordinates":[-87.747067,43.760592],"type":"Point"}
}