{
  "type": "Feature",
  "properties": {
    "iso:country":"US",
    "sg:address":"435 High Ave",
    "sg:city":"Oshkosh",
    "sg:classifiers":[
        {
            "category":"Shopping",
            "subcategory":"Books",
            "type":"Retail Goods"
        }
    ],
    "sg:phone":"+1 920 966 0007",
    "sg:postcode":"54901",
    "sg:province":"WI",
    "wof:name":"On This Rock Chrstn Book & Gft",
    "wof:placetype":"venue"
},
  "geometry": {"coordinates":[-88.54434999999999,44.020124],"type":"Point"}
}