{
  "type": "Feature",
  "properties": {
    "iso:country":"US",
    "sg:address":"686 Co Rd M",
    "sg:city":"River Falls",
    "sg:classifiers":[
        {
            "category":"Home & Garden",
            "subcategory":"Home Furnishings",
            "type":"Retail Goods"
        }
    ],
    "sg:phone":"+1 715 425 0190",
    "sg:postcode":"54022",
    "sg:province":"WI",
    "sg:tags":[
        "pottery",
        "product",
        "mfg"
    ],
    "wof:name":"Clayton Pottery",
    "wof:placetype":"venue"
},
  "geometry": {"coordinates":[-92.662915,44.862703],"type":"Point"}
}