{
  "type": "Feature",
  "properties": {
    "iso:country":"US",
    "sg:address":"5562 Hiwela Dr",
    "sg:city":"Wild Rose",
    "sg:classifiers":[
        {
            "category":"Banks & Credit Unions",
            "subcategory":"Investment Brokerage",
            "type":"Services"
        },
        {
            "category":"Insurance",
            "subcategory":"Insurance Agent",
            "type":"Services"
        }
    ],
    "sg:phone":"+1 920 622 5600",
    "sg:postcode":"54984",
    "sg:province":"WI",
    "sg:tags":[
        "consultant",
        "planning",
        "financial"
    ],
    "wof:name":"New England Financial Services",
    "wof:placetype":"venue"
},
  "geometry": {"coordinates":[-89.160523,44.166522],"type":"Point"}
}