{
  "type": "Feature",
  "properties": {
    "iso:country":"US",
    "sg:address":"2149 Velp Ave",
    "sg:city":"Green Bay",
    "sg:classifiers":[
        {
            "category":"Health Services",
            "subcategory":"Chiropractor",
            "type":"Services"
        }
    ],
    "sg:phone":"+1 920 471 8973",
    "sg:postcode":"54303",
    "sg:province":"WI",
    "wof:name":"Kay Fogeltanz DC",
    "wof:placetype":"venue"
},
  "geometry": {"coordinates":[-88.06948,44.560109],"type":"Point"}
}