{
  "type": "Feature",
  "properties": {
    "iso:country":"US",
    "sg:address":"5372 Cedardale Dr",
    "sg:city":"West Bend",
    "sg:classifiers":[
        {
            "category":"Airline",
            "type":"Transportation"
        }
    ],
    "sg:phone":"+1 262 644 8595",
    "sg:postcode":"53095",
    "sg:province":"WI",
    "sg:tags":[
        "scheduled",
        "air"
    ],
    "wof:name":"Sport Wings",
    "wof:placetype":"venue"
},
  "geometry": {"coordinates":[-88.266344,43.385842],"type":"Point"}
}