{
  "type": "Feature",
  "properties": {
    "iso:country":"US",
    "sg:address":"6100 W Vliet St",
    "sg:city":"Milwaukee",
    "sg:classifiers":[
        {
            "category":"Personal",
            "subcategory":"Beauty Salon",
            "type":"Services"
        }
    ],
    "sg:phone":"+1 414 258 4444",
    "sg:postcode":"53213",
    "sg:province":"WI",
    "wof:name":"Exprees Yourself Hair Designs",
    "wof:placetype":"venue"
},
  "geometry": {"coordinates":[-87.989477,43.050374],"type":"Point"}
}