{
  "type": "Feature",
  "properties": {
    "addr:full":"101 W Broadway Madison WI 53716",
    "addr:housenumber":"101",
    "addr:postcode":"53716",
    "addr:street":"W Broadway",
    "iso:country":"US",
    "sg:address":"101 W Broadway",
    "sg:city":"Madison",
    "sg:classifiers":[
        {
            "category":"Travel",
            "subcategory":"Hotels & Motels",
            "type":"Entertainment"
        }
    ],
    "sg:phone":"+1 608 222 8601",
    "sg:postcode":"53716",
    "sg:province":"WI",
    "sg:tags":[
        "operation"
    ],
    "wof:name":"AmericInn Lodge & Suite",
    "wof:placetype":"venue"
},
  "geometry": {"coordinates":[-89.326578,43.0476],"type":"Point"}
}