{
  "type": "Feature",
  "properties": {
    "iso:country":"US",
    "sg:address":"1089 Summit Ave",
    "sg:city":"Oconomowoc",
    "sg:classifiers":[
        {
            "category":"Retail",
            "subcategory":"Photofinishing",
            "type":"Services"
        }
    ],
    "sg:phone":"+1 262 560 0787",
    "sg:postcode":"53066",
    "sg:province":"WI",
    "sg:tags":[
        "laboratory",
        "portrait",
        "studio",
        "photo"
    ],
    "wof:name":"Moments & Memories",
    "wof:placetype":"venue"
},
  "geometry": {"coordinates":[-88.48312799999999,43.098554],"type":"Point"}
}