{
  "type": "Feature",
  "properties": {
    "iso:country":"US",
    "sg:address":"853 Division St",
    "sg:city":"Oshkosh",
    "sg:classifiers":[
        {
            "category":"Building & Trades",
            "subcategory":"Construction",
            "type":"Services"
        }
    ],
    "sg:phone":"+1 920 426 3475",
    "sg:postcode":"54901",
    "sg:province":"WI",
    "sg:tags":[
        "roofing",
        "renovation",
        "contractor"
    ],
    "wof:name":"Frank C N Renovations",
    "wof:placetype":"venue"
},
  "geometry": {"coordinates":[-88.538695,44.028415],"type":"Point"}
}