{
  "type": "Feature",
  "properties": {
    "iso:country":"US",
    "sg:address":"36245 Main St",
    "sg:city":"Whitehall",
    "sg:classifiers":[
        {
            "category":"Government",
            "subcategory":"Office",
            "type":"Public Place"
        }
    ],
    "sg:phone":"+1 715 538 2001",
    "sg:postcode":"54773",
    "sg:province":"WI",
    "sg:tags":[
        "county",
        "resource"
    ],
    "wof:name":"Aging & Disability Resource",
    "wof:placetype":"venue"
},
  "geometry": {"coordinates":[-91.316751,44.366575],"type":"Point"}
}