{
  "type": "Feature",
  "properties": {
    "iso:country":"US",
    "sg:address":"605 N 8th St",
    "sg:city":"Sheboygan",
    "sg:classifiers":[
        {
            "category":"Banks & Credit Unions",
            "subcategory":"Investment Brokerage",
            "type":"Services"
        }
    ],
    "sg:phone":"+1 920 457 8516",
    "sg:postcode":"53081",
    "sg:province":"WI",
    "sg:tags":[
        "consultant",
        "planning",
        "financial"
    ],
    "wof:name":"Piper Jaffray Co",
    "wof:placetype":"venue"
},
  "geometry": {"coordinates":[-87.712858,43.751928],"type":"Point"}
}