{
  "type": "Feature",
  "properties": {
    "iso:country":"US",
    "sg:address":"4925 57th Dr",
    "sg:city":"Sturtevant",
    "sg:classifiers":[
        {
            "category":"Professional",
            "type":"Services"
        }
    ],
    "sg:phone":"+1 262 878 1930",
    "sg:postcode":"53177",
    "sg:province":"WI",
    "sg:tags":[
        "establishment"
    ],
    "wof:name":"Softworks",
    "wof:placetype":"venue"
},
  "geometry": {"coordinates":[-88.002408,42.675233],"type":"Point"}
}