{
  "type": "Feature",
  "properties": {
    "iso:country":"US",
    "sg:address":"1408 210th Ave",
    "sg:city":"New Richmond",
    "sg:classifiers":[
        {
            "category":"Building & Trades",
            "subcategory":"Electrical",
            "type":"Services"
        }
    ],
    "sg:phone":"+1 715 246 3702",
    "sg:postcode":"54017",
    "sg:province":"WI",
    "sg:tags":[
        "electrical",
        "contractor"
    ],
    "wof:name":"CB Electric LLC",
    "wof:placetype":"venue"
},
  "geometry": {"coordinates":[-92.52737399999999,45.166042],"type":"Point"}
}