{
  "type": "Feature",
  "properties": {
    "iso:country":"US",
    "sg:address":"8153 975th St",
    "sg:city":"River Falls",
    "sg:classifiers":[
        {
            "category":"Personal",
            "subcategory":"Beauty Salon",
            "type":"Services"
        }
    ],
    "sg:phone":"+1 715 425 9955",
    "sg:postcode":"54022",
    "sg:province":"WI",
    "sg:tags":[
        "shop"
    ],
    "wof:name":"Mane Tamers",
    "wof:placetype":"venue"
},
  "geometry": {"coordinates":[-92.623116,44.835162],"type":"Point"}
}