{
  "type": "Feature",
  "properties": {
    "iso:country":"US",
    "sg:address":"1053 E Green Bay St",
    "sg:city":"Shawano",
    "sg:classifiers":[
        {
            "category":"Insurance",
            "subcategory":"Insurance Agent",
            "type":"Services"
        }
    ],
    "sg:phone":"+1 715 524 3962",
    "sg:postcode":"54166",
    "sg:province":"WI",
    "wof:name":"American Republic Insurance",
    "wof:placetype":"venue"
},
  "geometry": {"coordinates":[-88.590973,44.782211],"type":"Point"}
}