{
  "type": "Feature",
  "properties": {
    "addr:full":"4582 Algonquin Trl Green Bay WI 54313",
    "addr:housenumber":"4582",
    "addr:postcode":"54313",
    "addr:street":"Algonquin Trl",
    "iso:country":"US",
    "sg:address":"4582 Algonquin Trl",
    "sg:city":"Green Bay",
    "sg:classifiers":[
        {
            "category":"Real Estate",
            "subcategory":"Real Estate Agent",
            "type":"Services"
        }
    ],
    "sg:phone":"+1 920 434 7678",
    "sg:postcode":"54313",
    "sg:province":"WI",
    "wof:name":"Smart Homes Building & Realty",
    "wof:placetype":"venue"
},
  "geometry": {"coordinates":[-88.123504,44.55516],"type":"Point"}
}