{
  "type": "Feature",
  "properties": {
    "iso:country":"US",
    "sg:address":"8537 S Pennsylvania Ave",
    "sg:city":"Oak Creek",
    "sg:classifiers":[
        {
            "category":"Education",
            "subcategory":"School",
            "type":"Public Place"
        }
    ],
    "sg:phone":"+1 414 762 3655",
    "sg:postcode":"53154",
    "sg:province":"WI",
    "sg:tags":[
        "organization",
        "religious"
    ],
    "wof:name":"Grace Lutheran Church & School",
    "wof:placetype":"venue"
},
  "geometry": {"coordinates":[-87.882336,42.889404],"type":"Point"}
}