{
  "type": "Feature",
  "properties": {
    "iso:country":"US",
    "sg:address":"7475 Mineral Point Rd",
    "sg:city":"Madison",
    "sg:classifiers":[
        {
            "category":"Restaurant",
            "type":"Food & Drink"
        }
    ],
    "sg:phone":"+1 608 833 8339",
    "sg:postcode":"53705",
    "sg:province":"WI",
    "wof:name":"Topper's Pizza",
    "wof:placetype":"venue"
},
  "geometry": {"coordinates":[-89.512161,43.060509],"type":"Point"}
}