{
  "type": "Feature",
  "properties": {
    "addr:full":"515 Fair St Lodi WI 53555",
    "addr:housenumber":"515",
    "addr:postcode":"53555",
    "addr:street":"Fair St",
    "iso:country":"US",
    "sg:address":"515 Fair St",
    "sg:city":"Lodi",
    "sg:classifiers":[
        {
            "category":"Organizations",
            "subcategory":"Religious Organization",
            "type":"Services"
        }
    ],
    "sg:phone":"+1 608 592 5711",
    "sg:postcode":"53555",
    "sg:province":"WI",
    "sg:tags":[
        "church"
    ],
    "wof:name":"St Patrick's Church & Ctr",
    "wof:placetype":"venue"
},
  "geometry": {"coordinates":[-89.528649,43.318617],"type":"Point"}
}