{
  "type": "Feature",
  "properties": {
    "iso:country":"US",
    "sg:address":"9705 Twin Lakes Rd",
    "sg:city":"Kiel",
    "sg:classifiers":[
        {
            "category":"Freight",
            "type":"Transportation"
        }
    ],
    "sg:phone":"+1 920 773 2910",
    "sg:postcode":"53042",
    "sg:province":"WI",
    "sg:tags":[
        "operator",
        "trucking"
    ],
    "wof:name":"Endries Express Inc",
    "wof:placetype":"venue"
},
  "geometry": {"coordinates":[-87.932271,43.980813],"type":"Point"}
}