{
  "type": "Feature",
  "properties": {
    "addr:full":"5135 N Hollywood Ave Milwaukee WI 53217",
    "addr:housenumber":"5135",
    "addr:postcode":"53217",
    "addr:street":"N Hollywood Ave",
    "iso:country":"US",
    "sg:address":"5135 N Hollywood Ave",
    "sg:city":"Milwaukee",
    "sg:classifiers":[
        {
            "category":"Real Estate",
            "subcategory":"Real Estate Operator",
            "type":"Services"
        }
    ],
    "sg:phone":"+1 414 332 1105",
    "sg:postcode":"53217",
    "sg:province":"WI",
    "sg:tags":[
        "building",
        "nonresidential"
    ],
    "wof:name":"Keren Properties I LLC",
    "wof:placetype":"venue"
},
  "geometry": {"coordinates":[-87.903358,43.110609],"type":"Point"}
}