{
  "type": "Feature",
  "properties": {
    "iso:country":"US",
    "sg:address":"527 E Silver Spring Dr",
    "sg:city":"Milwaukee",
    "sg:classifiers":[
        {
            "category":"Shopping",
            "subcategory":"Gifts & Souvenirs",
            "type":"Retail Goods"
        }
    ],
    "sg:phone":"+1 414 332 8900",
    "sg:postcode":"53217",
    "sg:province":"WI",
    "sg:tags":[
        "shop"
    ],
    "wof:name":"Giraffe Limited",
    "wof:placetype":"venue"
},
  "geometry": {"coordinates":[-87.903318,43.118398],"type":"Point"}
}