{
  "type": "Feature",
  "properties": {
    "iso:country":"US",
    "sg:address":"1156 Dakota Blvd",
    "sg:city":"Friendship",
    "sg:classifiers":[
        {
            "category":"Building & Trades",
            "subcategory":"Construction",
            "type":"Services"
        }
    ],
    "sg:phone":"+1 608 339 2872",
    "sg:postcode":"53934",
    "sg:province":"WI",
    "sg:tags":[
        "contractor"
    ],
    "wof:name":"Borenz Roofing & General Maint",
    "wof:placetype":"venue"
},
  "geometry": {"coordinates":[-89.810895,43.980761],"type":"Point"}
}