{
  "type": "Feature",
  "properties": {
    "addr:full":"4969 S Cave Point Dr Sturgeon Bay WI 54235",
    "addr:housenumber":"4969",
    "addr:postcode":"54235",
    "addr:street":"S Cave Point Dr",
    "iso:country":"US",
    "sg:address":"4969 S Cave Point Dr",
    "sg:city":"Sturgeon Bay",
    "sg:classifiers":[
        {
            "category":"Professional",
            "subcategory":"Computer Services",
            "type":"Services"
        }
    ],
    "sg:phone":"+1 920 743 5226",
    "sg:postcode":"54235",
    "sg:province":"WI",
    "sg:tags":[
        "related"
    ],
    "wof:name":"James A Carley Consulting",
    "wof:placetype":"venue"
},
  "geometry": {"coordinates":[-87.205332,44.917287],"type":"Point"}
}