{
  "type": "Feature",
  "properties": {
    "addr:full":"9001 Lakeshore Dr Pleasant Prairie WI 53158",
    "addr:housenumber":"9001",
    "addr:postcode":"53158",
    "addr:street":"Lakeshore Dr",
    "iso:country":"US",
    "sg:address":"9001 Lakeshore Dr",
    "sg:city":"Pleasant Prairie",
    "sg:classifiers":[
        {
            "category":"Building & Trades",
            "subcategory":"Construction",
            "type":"Services"
        }
    ],
    "sg:phone":"+1 262 638 6000",
    "sg:postcode":"53158",
    "sg:province":"WI",
    "sg:tags":[
        "residential",
        "nonresidential"
    ],
    "wof:name":"Jac Investments Inc",
    "wof:placetype":"venue"
},
  "geometry": {"coordinates":[-87.813891,42.531344],"type":"Point"}
}