{
  "type": "Feature",
  "properties": {
    "addr:full":"4476 N 60th St Milwaukee WI 53218",
    "addr:housenumber":"4476",
    "addr:postcode":"53218",
    "addr:street":"N 60Th St",
    "iso:country":"US",
    "sg:address":"4476 N 60th St",
    "sg:city":"Milwaukee",
    "sg:classifiers":[
        {
            "category":"Social Services",
            "subcategory":"Child Care",
            "type":"Services"
        }
    ],
    "sg:phone":"+1 414 462 0318",
    "sg:postcode":"53218",
    "sg:province":"WI",
    "sg:tags":[
        "day"
    ],
    "wof:name":"Grandmothers Touch Childcare",
    "wof:placetype":"venue"
},
  "geometry": {"coordinates":[-87.98667,43.098452],"type":"Point"}
}