{
  "type": "Feature",
  "properties": {
    "addr:full":"110 E Sutton Pl Waukesha WI 53188",
    "addr:housenumber":"110",
    "addr:postcode":"53188",
    "addr:street":"E Sutton Pl",
    "iso:country":"US",
    "sg:address":"110 E Sutton Pl",
    "sg:city":"Waukesha",
    "sg:classifiers":[
        {
            "category":"Professional",
            "type":"Services"
        }
    ],
    "sg:phone":"+1 262 844 4524",
    "sg:postcode":"53188",
    "sg:province":"WI",
    "sg:tags":[
        "establishment"
    ],
    "wof:name":"World Of Oak",
    "wof:placetype":"venue"
},
  "geometry": {"coordinates":[-88.278173,43.012662],"type":"Point"}
}