{
  "type": "Feature",
  "properties": {
    "addr:full":"165 N Central Ave Richland Center WI 53581",
    "addr:housenumber":"165",
    "addr:postcode":"53581",
    "addr:street":"N Central Ave",
    "iso:country":"US",
    "sg:address":"165 N Central Ave",
    "sg:city":"Richland Center",
    "sg:classifiers":[
        {
            "category":"Professional",
            "subcategory":"Lawyer & Legal Services",
            "type":"Services"
        }
    ],
    "sg:phone":"+1 608 647 5167",
    "sg:postcode":"53581",
    "sg:province":"WI",
    "wof:name":"Karen S Fowell",
    "wof:placetype":"venue"
},
  "geometry": {"coordinates":[-90.385333,43.335832],"type":"Point"}
}