{
  "type": "Feature",
  "properties": {
    "iso:country":"US",
    "sg:address":"8814 W Forest Home Ave",
    "sg:city":"Milwaukee",
    "sg:classifiers":[
        {
            "category":"Health Services",
            "subcategory":"Clinic",
            "type":"Services"
        }
    ],
    "sg:phone":"+1 414 427 9101",
    "sg:postcode":"53228",
    "sg:province":"WI",
    "wof:name":"Accredo",
    "wof:placetype":"venue"
},
  "geometry": {"coordinates":[-88.024391,42.953596],"type":"Point"}
}