{
  "type": "Feature",
  "properties": {
    "addr:full":"5656 State Hwy 26 Brandon WI 53919",
    "addr:housenumber":"5656",
    "addr:postcode":"53919",
    "addr:street":"State Hwy 26",
    "iso:country":"US",
    "sg:address":"5656 State Hwy 26",
    "sg:city":"Brandon",
    "sg:classifiers":[
        {
            "category":"Shopping",
            "subcategory":"Gifts & Souvenirs",
            "type":"Retail Goods"
        }
    ],
    "sg:phone":"+1 920 872 2170",
    "sg:postcode":"53919",
    "sg:province":"WI",
    "wof:name":"Ostrems Husfliden",
    "wof:placetype":"venue"
},
  "geometry": {"coordinates":[-88.67482200000001,43.755161],"type":"Point"}
}