{
  "type": "Feature",
  "properties": {
    "iso:country":"US",
    "sg:address":"2430 W Hopkins St",
    "sg:city":"Milwaukee",
    "sg:classifiers":[
        {
            "category":"Organizations",
            "subcategory":"Religious Organization",
            "type":"Services"
        }
    ],
    "sg:phone":"+1 414 442 0490",
    "sg:postcode":"53206",
    "sg:province":"WI",
    "sg:tags":[
        "god",
        "churches-pentecostal",
        "church"
    ],
    "wof:name":"Golden Rule Church Of God In Christ",
    "wof:placetype":"venue"
},
  "geometry": {"coordinates":[-87.942977,43.080249],"type":"Point"}
}