{
  "type": "Feature",
  "properties": {
    "iso:country":"US",
    "sg:address":"3010 Woodlane Dr",
    "sg:city":"Janesville",
    "sg:classifiers":[
        {
            "category":"Shopping",
            "subcategory":"Discount & Variety Stores",
            "type":"Retail Goods"
        }
    ],
    "sg:phone":"+1 608 741 5050",
    "sg:postcode":"53545",
    "sg:province":"WI",
    "sg:tags":[
        "gen",
        "merchandise"
    ],
    "wof:name":"50-50 Factory Outlet",
    "wof:placetype":"venue"
},
  "geometry": {"coordinates":[-89.000845,42.718981],"type":"Point"}
}