{
  "type": "Feature",
  "properties": {
    "addr:full":"1 E Spring St Chippewa Falls WI 54729",
    "addr:housenumber":"1",
    "addr:postcode":"54729",
    "addr:street":"E Spring St",
    "iso:country":"US",
    "sg:address":"1 E Spring St",
    "sg:city":"Chippewa Falls",
    "sg:classifiers":[
        {
            "category":"Wholesale",
            "subcategory":"Chemicals & Plastics",
            "type":"Manufacturing & Wholesale Goods"
        }
    ],
    "sg:phone":"+1 715 720 0815",
    "sg:postcode":"54729",
    "sg:province":"WI",
    "wof:name":"Powder Plus",
    "wof:placetype":"venue"
},
  "geometry": {"coordinates":[-91.390749,44.936156],"type":"Point"}
}