{
  "type": "Feature",
  "properties": {
    "iso:country":"US",
    "sg:address":"3505 W National Ave",
    "sg:city":"Milwaukee",
    "sg:classifiers":[
        {
            "category":"Shopping",
            "subcategory":"Shoes",
            "type":"Retail Goods"
        }
    ],
    "sg:phone":"+1 414 647 2196",
    "sg:postcode":"53215",
    "sg:province":"WI",
    "wof:name":"Air Shoe Express",
    "wof:placetype":"venue"
},
  "geometry": {"coordinates":[-87.95885,43.021457],"type":"Point"}
}