{
  "type": "Feature",
  "properties": {
    "iso:country":"US",
    "sg:address":"2145 S 28th St",
    "sg:city":"Milwaukee",
    "sg:classifiers":[
        {
            "category":"Building & Trades",
            "subcategory":"Construction",
            "type":"Services"
        }
    ],
    "sg:phone":"+1 414 643 5837",
    "sg:postcode":"53215",
    "sg:province":"WI",
    "sg:tags":[
        "restoration",
        "cleaning",
        "patio",
        "deck"
    ],
    "wof:name":"Gosseck Deck & Patio Cleaning",
    "wof:placetype":"venue"
},
  "geometry": {"coordinates":[-87.949396,43.00575],"type":"Point"}
}