{
  "type": "Feature",
  "properties": {
    "iso:country":"US",
    "sg:address":"1130 Lake Ave W",
    "sg:city":"Ladysmith",
    "sg:classifiers":[
        {
            "category":"Social Services",
            "type":"Services"
        }
    ],
    "sg:phone":"+1 715 532 5580",
    "sg:postcode":"54848",
    "sg:province":"WI",
    "sg:tags":[
        "counselor",
        "marriage",
        "family"
    ],
    "wof:name":"Community Counseling Ctr",
    "wof:placetype":"venue"
},
  "geometry": {"coordinates":[-91.113886,45.464955],"type":"Point"}
}