{
  "type": "Feature",
  "properties": {
    "iso:country":"US",
    "sg:address":"9275 N 75th St",
    "sg:city":"Milwaukee",
    "sg:classifiers":[
        {
            "category":"Taxi",
            "type":"Transportation"
        }
    ],
    "sg:phone":"+1 414 354 5023",
    "sg:postcode":"53223",
    "sg:province":"WI",
    "sg:tags":[
        "taxicab"
    ],
    "wof:name":"Kuranage A Perera",
    "wof:placetype":"venue"
},
  "geometry": {"coordinates":[-88.00290699999999,43.185698],"type":"Point"}
}