{
  "type": "Feature",
  "properties": {
    "addr:full":"2851 Liberty Ln Janesville WI 53545",
    "addr:housenumber":"2851",
    "addr:postcode":"53545",
    "addr:street":"Liberty Ln",
    "iso:country":"US",
    "sg:address":"2851 Liberty Ln",
    "sg:city":"Janesville",
    "sg:classifiers":[
        {
            "category":"Real Estate",
            "subcategory":"Real Estate Services",
            "type":"Services"
        }
    ],
    "sg:phone":"+1 608 741 7000",
    "sg:postcode":"53545",
    "sg:province":"WI",
    "sg:tags":[
        "company",
        "title"
    ],
    "sg:website":"www.titleteamwi.com",
    "wof:name":"Title Team",
    "wof:placetype":"venue"
},
  "geometry": {"coordinates":[-88.990022,42.715792],"type":"Point"}
}