{
  "type": "Feature",
  "properties": {
    "iso:country":"US",
    "sg:address":"3382 Breezewood Ln",
    "sg:city":"Neenah",
    "sg:classifiers":[
        {
            "category":"Farming",
            "subcategory":"Farm",
            "type":"Manufacturing & Wholesale Goods"
        }
    ],
    "sg:phone":"+1 920 836 2519",
    "sg:postcode":"54956",
    "sg:province":"WI",
    "sg:tags":[
        "crop"
    ],
    "wof:name":"Salm Services Inc",
    "wof:placetype":"venue"
},
  "geometry": {"coordinates":[-88.579612,44.155715],"type":"Point"}
}