{
  "type": "Feature",
  "properties": {
    "addr:full":"6378 N Green Bay Ave Milwaukee WI 53209",
    "addr:housenumber":"6378",
    "addr:postcode":"53209",
    "addr:street":"N Green Bay Ave",
    "iso:country":"US",
    "sg:address":"6378 N Green Bay Ave",
    "sg:city":"Milwaukee",
    "sg:classifiers":[
        {
            "category":"Health Services",
            "subcategory":"Nursing And Care Facility",
            "type":"Services"
        }
    ],
    "sg:phone":"+1 414 228 8996",
    "sg:postcode":"53209",
    "sg:province":"WI",
    "wof:name":"Kletzsch Park House",
    "wof:placetype":"venue"
},
  "geometry": {"coordinates":[-87.932315,43.132925],"type":"Point"}
}