{
  "type": "Feature",
  "properties": {
    "iso:country":"US",
    "sg:address":"277 Lawrence St",
    "sg:city":"Westfield",
    "sg:classifiers":[
        {
            "category":"Social Services",
            "subcategory":"Child Care",
            "type":"Services"
        }
    ],
    "sg:phone":"+1 608 296 3696",
    "sg:postcode":"53964",
    "sg:province":"WI",
    "wof:name":"Little Pioneer Child Care Inc",
    "wof:placetype":"venue"
},
  "geometry": {"coordinates":[-89.498954,43.884946],"type":"Point"}
}