{
  "type": "Feature",
  "properties": {
    "iso:country":"US",
    "sg:address":"1218 Oakes Ave",
    "sg:city":"Superior",
    "sg:classifiers":[
        {
            "category":"Recreation",
            "type":"Entertainment"
        }
    ],
    "sg:phone":"+1 715 392 1031",
    "sg:postcode":"54880",
    "sg:province":"WI",
    "sg:tags":[
        "skating",
        "rink"
    ],
    "wof:name":"World Of Wheels Skate Ctr",
    "wof:placetype":"venue"
},
  "geometry": {"coordinates":[-92.106858,46.723331],"type":"Point"}
}