{
  "type": "Feature",
  "properties": {
    "iso:country":"US",
    "sg:address":"528 Highland Ct",
    "sg:city":"Fond Du Lac",
    "sg:classifiers":[
        {
            "category":"Building & Trades",
            "subcategory":"Construction",
            "type":"Services"
        }
    ],
    "sg:phone":"+1 920 921 7883",
    "sg:postcode":"54935",
    "sg:province":"WI",
    "sg:tags":[
        "floor",
        "laying",
        "contractor"
    ],
    "wof:name":"Possehl Installation",
    "wof:placetype":"venue"
},
  "geometry": {"coordinates":[-88.46600100000001,43.77239],"type":"Point"}
}