{
  "type": "Feature",
  "properties": {
    "iso:country":"US",
    "sg:address":"2345 Lost Dauphin Rd",
    "sg:city":"De Pere",
    "sg:classifiers":[
        {
            "category":"Professional",
            "subcategory":"Business Services",
            "type":"Services"
        }
    ],
    "sg:phone":"+1 920 337 0449",
    "sg:postcode":"54115",
    "sg:province":"WI",
    "wof:name":"Darling Family Partnership",
    "wof:placetype":"venue"
},
  "geometry": {"coordinates":[-88.094666,44.413513],"type":"Point"}
}