{
  "type": "Feature",
  "properties": {
    "iso:country":"US",
    "sg:address":"1721 W Forest Home Ave",
    "sg:city":"Milwaukee",
    "sg:classifiers":[
        {
            "category":"Retail",
            "subcategory":"Self-service Laundry",
            "type":"Services"
        }
    ],
    "sg:phone":"+1 414 389 0101",
    "sg:postcode":"53204",
    "sg:province":"WI",
    "wof:name":"Forest Home Maytag Laundry",
    "wof:placetype":"venue"
},
  "geometry": {"coordinates":[-87.935226,43.008145],"type":"Point"}
}