{
  "type": "Feature",
  "properties": {
    "addr:full":"12083 Co Rd V Glen Haven WI 53810",
    "addr:housenumber":"12083",
    "addr:postcode":"53810",
    "addr:street":"Co Rd V",
    "iso:country":"US",
    "sg:address":"12083 Co Rd V",
    "sg:city":"Glen Haven",
    "sg:classifiers":[
        {
            "category":"Home & Garden",
            "subcategory":"Garden Supply",
            "type":"Retail Goods"
        }
    ],
    "sg:phone":"+1 608 794 2180",
    "sg:postcode":"53810",
    "sg:province":"WI",
    "sg:tags":[
        "bulb",
        "seed"
    ],
    "wof:name":"Golden Seed Co",
    "wof:placetype":"venue"
},
  "geometry": {"coordinates":[-91.00881699999999,42.821883],"type":"Point"}
}