{
  "type": "Feature",
  "properties": {
    "iso:country":"US",
    "sg:address":"29420 Engoe Rd",
    "sg:city":"Washburn",
    "sg:classifiers":[
        {
            "category":"Wholesale",
            "subcategory":"Fruits & Vegetables",
            "type":"Manufacturing & Wholesale Goods"
        }
    ],
    "sg:phone":"+1 715 373 2053",
    "sg:postcode":"54891",
    "sg:province":"WI",
    "sg:tags":[
        "shipper"
    ],
    "wof:name":"Don's Berry/Pumpkin Patch",
    "wof:placetype":"venue"
},
  "geometry": {"coordinates":[-90.918972,46.644764],"type":"Point"}
}