{
  "type": "Feature",
  "properties": {
    "iso:country":"US",
    "sg:address":"1860 E Washington Ave",
    "sg:city":"Madison",
    "sg:classifiers":[
        {
            "category":"Restaurant",
            "type":"Food & Drink"
        }
    ],
    "sg:menulink":"http://www.allmenus.com/wi/madison/145571-subway/menu/",
    "sg:phone":"+1 608 246 9090",
    "sg:postcode":"53704",
    "sg:province":"WI",
    "sg:tags":[
        "american",
        "sandwich"
    ],
    "wof:name":"Subway",
    "wof:placetype":"venue"
},
  "geometry": {"coordinates":[-89.36001899999999,43.091814],"type":"Point"}
}