{
  "type": "Feature",
  "properties": {
    "iso:country":"US",
    "sg:address":"7991 R and W Townline Rd",
    "sg:city":"Whitewater",
    "sg:classifiers":[
        {
            "category":"Travel",
            "subcategory":"Campground",
            "type":"Entertainment"
        }
    ],
    "sg:phone":"+1 608 883 2920",
    "sg:postcode":"53190",
    "sg:province":"WI",
    "wof:name":"Scenic RIDGE Campground",
    "wof:placetype":"venue"
},
  "geometry": {"coordinates":[-88.69632300000001,42.755379],"type":"Point"}
}