{
  "type": "Feature",
  "properties": {
    "iso:country":"US",
    "sg:address":"8402 Bluff Rd",
    "sg:city":"Lancaster",
    "sg:classifiers":[
        {
            "category":"Building & Trades",
            "subcategory":"Construction",
            "type":"Services"
        }
    ],
    "sg:phone":"+1 608 723 4386",
    "sg:postcode":"53813",
    "sg:province":"WI",
    "sg:tags":[
        "carpentry",
        "contractor"
    ],
    "wof:name":"Riverview Crpentry Restoration",
    "wof:placetype":"venue"
},
  "geometry": {"coordinates":[-90.636498,42.815685],"type":"Point"}
}