{
  "type": "Feature",
  "properties": {
    "iso:country":"US",
    "sg:address":"7070 S Hill Rd",
    "sg:city":"De Forest",
    "sg:classifiers":[
        {
            "category":"Professional",
            "type":"Services"
        }
    ],
    "sg:phone":"+1 608 846 4549",
    "sg:postcode":"53532",
    "sg:province":"WI",
    "wof:name":"Swenson Rj",
    "wof:placetype":"venue"
},
  "geometry": {"coordinates":[-89.347768,43.235468],"type":"Point"}
}