{
  "type": "Feature",
  "properties": {
    "iso:country":"US",
    "sg:address":"6224 S Business Dr",
    "sg:city":"Sheboygan",
    "sg:classifiers":[
        {
            "category":"Shopping",
            "subcategory":"Department Store",
            "type":"Retail Goods"
        }
    ],
    "sg:phone":"+1 920 451 1244",
    "sg:postcode":"53081",
    "sg:province":"WI",
    "wof:name":"Grand Central Cheese Co LLC",
    "wof:placetype":"venue"
},
  "geometry": {"coordinates":[-87.75187699999999,43.687601],"type":"Point"}
}