{
  "type": "Feature",
  "properties": {
    "iso:country":"US",
    "sg:address":"1775 Co Hwy A",
    "sg:city":"Springbrook",
    "sg:classifiers":[
        {
            "category":"Building & Trades",
            "subcategory":"Construction",
            "type":"Services"
        }
    ],
    "sg:phone":"+1 715 766 2613",
    "sg:postcode":"54875",
    "sg:province":"WI",
    "sg:tags":[
        "concrete",
        "contractor"
    ],
    "wof:name":"Bob's Concrete & Block",
    "wof:placetype":"venue"
},
  "geometry": {"coordinates":[-91.636348,45.870437],"type":"Point"}
}