{
  "type": "Feature",
  "properties": {
    "iso:country":"US",
    "sg:address":"3305 State Hwy 64",
    "sg:city":"Marinette",
    "sg:classifiers":[
        {
            "category":"Bars & Pubs",
            "type":"Food & Drink"
        }
    ],
    "sg:phone":"+1 715 789 3142",
    "sg:postcode":"54143",
    "sg:province":"WI",
    "wof:name":"Pistol Pete's",
    "wof:placetype":"venue"
},
  "geometry": {"coordinates":[-87.65415400000001,45.099488],"type":"Point"}
}