{
  "type": "Feature",
  "properties": {
    "iso:country":"US",
    "sg:address":"300 Mandt Pkwy",
    "sg:city":"Stoughton",
    "sg:classifiers":[
        {
            "category":"Recreation",
            "type":"Entertainment"
        }
    ],
    "sg:phone":"+1 608 873 4653",
    "sg:postcode":"53589",
    "sg:province":"WI",
    "sg:tags":[
        "carnival"
    ],
    "wof:name":"Stoughton Junior Fair",
    "wof:placetype":"venue"
},
  "geometry": {"coordinates":[-89.214046,42.91079],"type":"Point"}
}