{
  "type": "Feature",
  "properties": {
    "iso:country":"US",
    "sg:address":"115 Apache Dr",
    "sg:city":"Janesville",
    "sg:classifiers":[
        {
            "category":"Health Services",
            "subcategory":"Doctor",
            "type":"Services"
        }
    ],
    "sg:phone":"+1 608 757 2001",
    "sg:postcode":"53545",
    "sg:province":"WI",
    "sg:tags":[
        "medical"
    ],
    "wof:name":"Harlan Edelman MD SC",
    "wof:placetype":"venue"
},
  "geometry": {"coordinates":[-88.993576,42.683874],"type":"Point"}
}