{
  "type": "Feature",
  "properties": {
    "addr:full":"4671 Co Hwy Jj Black Earth WI 53515",
    "addr:housenumber":"4671",
    "addr:postcode":"53515",
    "addr:street":"Co Hwy Jj",
    "iso:country":"US",
    "sg:address":"4671 Co Hwy Jj",
    "sg:city":"Black Earth",
    "sg:classifiers":[
        {
            "category":"Building & Trades",
            "subcategory":"Construction",
            "type":"Services"
        }
    ],
    "sg:phone":"+1 608 767 3553",
    "sg:postcode":"53515",
    "sg:province":"WI",
    "wof:name":"Quercus Land",
    "wof:placetype":"venue"
},
  "geometry": {"coordinates":[-89.758888,43.107676],"type":"Point"}
}