{
  "type": "Feature",
  "properties": {
    "addr:full":"112 Swain St Chaseburg WI 54621",
    "addr:housenumber":"112",
    "addr:postcode":"54621",
    "addr:street":"Swain St",
    "iso:country":"US",
    "sg:address":"112 Swain St",
    "sg:city":"Chaseburg",
    "sg:classifiers":[
        {
            "category":"Real Estate",
            "subcategory":"Real Estate Operator",
            "type":"Services"
        }
    ],
    "sg:phone":"+1 608 483 2649",
    "sg:postcode":"54621",
    "sg:province":"WI",
    "sg:tags":[
        "building",
        "apartment"
    ],
    "wof:name":"Bluffview Apts",
    "wof:placetype":"venue"
},
  "geometry": {"coordinates":[-91.09626299999999,43.656306],"type":"Point"}
}