{
  "type": "Feature",
  "properties": {
    "addr:full":"6705 Northway Greendale WI 53129",
    "addr:housenumber":"6705",
    "addr:postcode":"53129",
    "addr:street":"Northway",
    "iso:country":"US",
    "sg:address":"6705 Northway",
    "sg:city":"Greendale",
    "sg:classifiers":[
        {
            "category":"Organizations",
            "subcategory":"Religious Organization",
            "type":"Services"
        }
    ],
    "sg:phone":"+1 414 421 1670",
    "sg:postcode":"53129",
    "sg:province":"WI",
    "sg:tags":[
        "lutheran",
        "church"
    ],
    "wof:name":"St Luke's Lutheran Church",
    "wof:placetype":"venue"
},
  "geometry": {"coordinates":[-87.998319,42.942423],"type":"Point"}
}