{
  "type": "Feature",
  "properties": {
    "iso:country":"US",
    "sg:address":"1145 Rutledge St",
    "sg:city":"Madison",
    "sg:classifiers":[
        {
            "category":"Building & Trades",
            "subcategory":"Construction",
            "type":"Services"
        }
    ],
    "sg:phone":"+1 608 251 5088",
    "sg:postcode":"53703",
    "sg:province":"WI",
    "sg:tags":[
        "bathroom",
        "remodeling",
        "contractor"
    ],
    "sg:website":"http://www.kristopherjohnsonphotography.com",
    "wof:name":"Kris L Johnson",
    "wof:placetype":"venue"
},
  "geometry": {"coordinates":[-89.362759,43.080599],"type":"Point"}
}