{
  "type": "Feature",
  "properties": {
    "iso:country":"US",
    "sg:address":"3607 N Golden Lake Rd",
    "sg:city":"Oconomowoc",
    "sg:classifiers":[
        {
            "category":"Insurance",
            "subcategory":"Insurance Agent",
            "type":"Services"
        }
    ],
    "sg:phone":"+1 262 567 6274",
    "sg:postcode":"53066",
    "sg:province":"WI",
    "wof:name":"Society Insurance",
    "wof:placetype":"venue"
},
  "geometry": {"coordinates":[-88.520775,43.087846],"type":"Point"}
}