{
  "type": "Feature",
  "properties": {
    "addr:full":"633 N 4th St Milwaukee WI 53212",
    "addr:housenumber":"633",
    "addr:postcode":"53212",
    "addr:street":"N 4Th St",
    "iso:country":"US",
    "sg:address":"633 N 4th St",
    "sg:city":"Milwaukee",
    "sg:classifiers":[
        {
            "category":"Parking",
            "type":"Transportation"
        }
    ],
    "sg:phone":"+1 262 253 1316",
    "sg:postcode":"53212",
    "sg:province":"WI",
    "sg:tags":[
        "garage"
    ],
    "wof:name":"CENTRAL Parking",
    "wof:placetype":"venue"
},
  "geometry": {"coordinates":[-87.916085,43.038325],"type":"Point"}
}