{
  "type": "Feature",
  "properties": {
    "addr:full":"790 Hansen Rd Green Bay WI 54304",
    "addr:housenumber":"790",
    "addr:postcode":"54304",
    "addr:street":"Hansen Rd",
    "iso:country":"US",
    "sg:address":"790 Hansen Rd",
    "sg:city":"Green Bay",
    "sg:classifiers":[
        {
            "category":"Sports & Exercise",
            "subcategory":"Gym",
            "type":"Entertainment"
        }
    ],
    "sg:phone":"+1 920 499 9191",
    "sg:postcode":"54304",
    "sg:province":"WI",
    "sg:tags":[
        "club",
        "health",
        "studio",
        "gymnasium"
    ],
    "wof:name":"Fitness America",
    "wof:placetype":"venue"
},
  "geometry": {"coordinates":[-88.07415899999999,44.475848],"type":"Point"}
}