{
  "type": "Feature",
  "properties": {
    "iso:country":"US",
    "sg:address":"709 Borvan Ave",
    "sg:city":"Green Bay",
    "sg:classifiers":[
        {
            "category":"Freight",
            "type":"Transportation"
        }
    ],
    "sg:phone":"+1 920 490 8869",
    "sg:postcode":"54304",
    "sg:province":"WI",
    "sg:tags":[
        "general"
    ],
    "wof:name":"Packer City Mobile Warehouse",
    "wof:placetype":"venue"
},
  "geometry": {"coordinates":[-88.051762,44.492971],"type":"Point"}
}