{
  "type": "Feature",
  "properties": {
    "iso:country":"US",
    "sg:address":"2810 Rib Mountain Dr",
    "sg:city":"Wausau",
    "sg:classifiers":[
        {
            "category":"Insurance",
            "subcategory":"Insurance Agent",
            "type":"Services"
        }
    ],
    "sg:phone":"+1 715 842 3464",
    "sg:postcode":"54401",
    "sg:province":"WI",
    "wof:name":"Wayne Syring Insurance Agency",
    "wof:placetype":"venue"
},
  "geometry": {"coordinates":[-89.655912,44.930792],"type":"Point"}
}