{
  "type": "Feature",
  "properties": {
    "iso:country":"US",
    "sg:address":"1052 N Main St",
    "sg:city":"River Falls",
    "sg:classifiers":[
        {
            "category":"Shopping",
            "type":"Retail Goods"
        }
    ],
    "sg:phone":"+1 715 425 7994",
    "sg:postcode":"54022",
    "sg:province":"WI",
    "sg:tags":[
        "chemical"
    ],
    "sg:website":"www.hagcoultramicrofiber.com",
    "wof:name":"Hagco Industries",
    "wof:placetype":"venue"
},
  "geometry": {"coordinates":[-92.621701,44.872236],"type":"Point"}
}