{
  "type": "Feature",
  "properties": {
    "iso:country":"US",
    "sg:address":"15423 Co Rd B",
    "sg:city":"Hayward",
    "sg:classifiers":[
        {
            "category":"Real Estate",
            "subcategory":"Real Estate Agent",
            "type":"Services"
        }
    ],
    "sg:phone":"+1 715 634 9999",
    "sg:postcode":"54843",
    "sg:province":"WI",
    "sg:website":"www.rayfieldrealty.com",
    "wof:name":"Rayfield Realty",
    "wof:placetype":"venue"
},
  "geometry": {"coordinates":[-91.469048,46.004752],"type":"Point"}
}