{
  "type": "Feature",
  "properties": {
    "iso:country":"US",
    "sg:address":"115 W Main St",
    "sg:city":"Madison",
    "sg:classifiers":[
        {
            "category":"Organizations",
            "subcategory":"Labor Organization",
            "type":"Services"
        }
    ],
    "sg:phone":"+1 608 256 1206",
    "sg:postcode":"53703",
    "sg:province":"WI",
    "wof:name":"Wisconsin State Council-Crpntr",
    "wof:placetype":"venue"
},
  "geometry": {"coordinates":[-89.384956,43.072438],"type":"Point"}
}