{
  "type": "Feature",
  "properties": {
    "iso:country":"US",
    "sg:address":"1493 Leonard Pt Rd",
    "sg:city":"Oshkosh",
    "sg:classifiers":[
        {
            "category":"Building & Trades",
            "subcategory":"Construction",
            "type":"Services"
        }
    ],
    "sg:phone":"+1 920 233 4855",
    "sg:postcode":"54904",
    "sg:province":"WI",
    "sg:tags":[
        "house"
    ],
    "wof:name":"Last Steven W",
    "wof:placetype":"venue"
},
  "geometry": {"coordinates":[-88.62164799999999,44.044542],"type":"Point"}
}