{
  "type": "Feature",
  "properties": {
    "iso:country":"US",
    "sg:address":"128 Krueger Ave",
    "sg:city":"Forestville",
    "sg:classifiers":[
        {
            "category":"Building & Trades",
            "subcategory":"Construction",
            "type":"Services"
        }
    ],
    "sg:phone":"+1 920 856 6600",
    "sg:postcode":"54213",
    "sg:province":"WI",
    "sg:tags":[
        "house"
    ],
    "wof:name":"Krueger Builders",
    "wof:placetype":"venue"
},
  "geometry": {"coordinates":[-87.477047,44.690613],"type":"Point"}
}