{
  "type": "Feature",
  "properties": {
    "iso:country":"US",
    "sg:address":"528 Mill St",
    "sg:city":"Green Lake",
    "sg:classifiers":[
        {
            "category":"Real Estate",
            "subcategory":"Real Estate Agent",
            "type":"Services"
        }
    ],
    "sg:phone":"+1 920 294 0400",
    "sg:postcode":"54941",
    "sg:province":"WI",
    "wof:name":"Malcolm Bay Realty & Land Co",
    "wof:placetype":"venue"
},
  "geometry": {"coordinates":[-88.960012,43.845375],"type":"Point"}
}