{
  "type": "Feature",
  "properties": {
    "iso:country":"US",
    "sg:address":"6870 Van Boxtel Rd",
    "sg:city":"Oneida",
    "sg:classifiers":[
        {
            "category":"Freight",
            "type":"Transportation"
        }
    ],
    "sg:phone":"+1 920 869 1917",
    "sg:postcode":"54155",
    "sg:province":"WI",
    "sg:tags":[
        "special"
    ],
    "wof:name":"Ifc Mini Storage",
    "wof:placetype":"venue"
},
  "geometry": {"coordinates":[-88.23074699999999,44.485193],"type":"Point"}
}