{
  "type": "Feature",
  "properties": {
    "iso:country":"US",
    "sg:address":"4465 N Woodburn St",
    "sg:city":"Milwaukee",
    "sg:classifiers":[
        {
            "category":"Professional",
            "subcategory":"Management & Consulting",
            "type":"Services"
        }
    ],
    "sg:phone":"+1 414 332 1758",
    "sg:postcode":"53211",
    "sg:province":"WI",
    "wof:name":"Profitablelistscom",
    "wof:placetype":"venue"
},
  "geometry": {"coordinates":[-87.893563,43.096249],"type":"Point"}
}