{
  "type": "Feature",
  "properties": {
    "addr:full":"525 Locust Ave Oconto Falls WI 54154",
    "addr:housenumber":"525",
    "addr:postcode":"54154",
    "addr:street":"Locust Ave",
    "iso:country":"US",
    "sg:address":"525 Locust Ave",
    "sg:city":"Oconto Falls",
    "sg:classifiers":[
        {
            "category":"Personal",
            "subcategory":"Beauty Salon",
            "type":"Services"
        }
    ],
    "sg:phone":"+1 920 846 4703",
    "sg:postcode":"54154",
    "sg:province":"WI",
    "sg:tags":[
        "shop"
    ],
    "wof:name":"Perfect 10 Nail & Tanning Salo",
    "wof:placetype":"venue"
},
  "geometry": {"coordinates":[-88.140299,44.882257],"type":"Point"}
}