{
  "type": "Feature",
  "properties": {
    "iso:country":"US",
    "sg:address":"904 Garden St",
    "sg:city":"Eau Claire",
    "sg:classifiers":[
        {
            "category":"Manufacturing",
            "subcategory":"Tools & Machinery",
            "type":"Manufacturing & Wholesale Goods"
        }
    ],
    "sg:phone":"+1 715 552 4536",
    "sg:postcode":"54703",
    "sg:province":"WI",
    "sg:tags":[
        "equipment",
        "industrial",
        "supply"
    ],
    "wof:name":"Rexnord",
    "wof:placetype":"venue"
},
  "geometry": {"coordinates":[-91.521411,44.832699],"type":"Point"}
}