{
  "type": "Feature",
  "properties": {
    "iso:country":"US",
    "sg:address":"425 N Falls St",
    "sg:city":"River Falls",
    "sg:classifiers":[
        {
            "category":"Building & Trades",
            "subcategory":"Construction",
            "type":"Services"
        }
    ],
    "sg:phone":"+1 715 426 7944",
    "sg:postcode":"54022",
    "sg:province":"WI",
    "sg:tags":[
        "house",
        "builder",
        "home"
    ],
    "wof:name":"Brightkeys Building & Developm",
    "wof:placetype":"venue"
},
  "geometry": {"coordinates":[-92.633653,44.861868],"type":"Point"}
}