{
  "type": "Feature",
  "properties": {
    "addr:full":"5520 W Vliet St Milwaukee WI 53208",
    "addr:housenumber":"5520",
    "addr:postcode":"53208",
    "addr:street":"W Vliet St",
    "iso:country":"US",
    "sg:address":"5520 W Vliet St",
    "sg:city":"Milwaukee",
    "sg:classifiers":[
        {
            "category":"Bars & Pubs",
            "type":"Food & Drink"
        }
    ],
    "sg:phone":"+1 414 257 9112",
    "sg:postcode":"53208",
    "sg:province":"WI",
    "sg:tags":[
        "lounge"
    ],
    "wof:name":"Wonder Bar",
    "wof:placetype":"venue"
},
  "geometry": {"coordinates":[-87.98144600000001,43.049438],"type":"Point"}
}