{
  "type": "Feature",
  "properties": {
    "addr:full":"300 W Main St Waukesha WI 53186",
    "addr:housenumber":"300",
    "addr:postcode":"53186",
    "addr:street":"W Main St",
    "iso:country":"US",
    "sg:address":"300 W Main St",
    "sg:city":"Waukesha",
    "sg:classifiers":[
        {
            "category":"Shopping",
            "subcategory":"Gifts & Souvenirs",
            "type":"Retail Goods"
        }
    ],
    "sg:phone":"+1 262 547 1060",
    "sg:postcode":"53186",
    "sg:province":"WI",
    "sg:tags":[
        "shop"
    ],
    "wof:name":"Martha Merrell's Bookstore",
    "wof:placetype":"venue"
},
  "geometry": {"coordinates":[-88.23287500000001,43.011212],"type":"Point"}
}