{
  "type": "Feature",
  "properties": {
    "iso:country":"US",
    "sg:address":"5633 Co Rd Y",
    "sg:city":"Fond Du Lac",
    "sg:classifiers":[
        {
            "category":"Building & Trades",
            "subcategory":"Construction",
            "type":"Services"
        }
    ],
    "sg:phone":"+1 920 929 8870",
    "sg:postcode":"54935",
    "sg:province":"WI",
    "wof:name":"Pro Builders",
    "wof:placetype":"venue"
},
  "geometry": {"coordinates":[-88.436115,43.638695],"type":"Point"}
}