{
  "type": "Feature",
  "properties": {
    "iso:country":"US",
    "sg:address":"324 Cameron St",
    "sg:city":"Eau Claire",
    "sg:classifiers":[
        {
            "category":"Social Services",
            "subcategory":"Child Care",
            "type":"Services"
        },
        {
            "category":"Social Services",
            "type":"Services"
        }
    ],
    "sg:phone":"+1 715 831 0515",
    "sg:postcode":"54703",
    "sg:province":"WI",
    "wof:name":"Jenny's Daycare",
    "wof:placetype":"venue"
},
  "geometry": {"coordinates":[-91.512224,44.816458],"type":"Point"}
}