{
  "type": "Feature",
  "properties": {
    "iso:country":"US",
    "sg:address":"2901 Latham Dr",
    "sg:city":"Madison",
    "sg:classifiers":[
        {
            "category":"Wholesale",
            "subcategory":"Computers",
            "type":"Manufacturing & Wholesale Goods"
        }
    ],
    "sg:phone":"+1 608 277 0215",
    "sg:postcode":"53713",
    "sg:province":"WI",
    "sg:tags":[
        "printer",
        "laser"
    ],
    "wof:name":"International Laser Engraving",
    "wof:placetype":"venue"
},
  "geometry": {"coordinates":[-89.402879,43.030643],"type":"Point"}
}