{
  "type": "Feature",
  "properties": {
    "iso:country":"US",
    "sg:address":"300 W Olson Dr",
    "sg:city":"Grantsburg",
    "sg:classifiers":[
        {
            "category":"Travel",
            "subcategory":"Campground",
            "type":"Entertainment"
        }
    ],
    "sg:phone":"+1 715 463 5832",
    "sg:postcode":"54840",
    "sg:province":"WI",
    "wof:name":"James N Mc Nally Campground",
    "wof:placetype":"venue"
},
  "geometry": {"coordinates":[-92.688469,45.778057],"type":"Point"}
}