{
  "type": "Feature",
  "properties": {
    "iso:country":"US",
    "sg:address":"3133 Market Pl",
    "sg:city":"Onalaska",
    "sg:classifiers":[
        {
            "category":"Food & Beverages",
            "subcategory":"Groceries & Convenience Stores",
            "type":"Retail Goods"
        }
    ],
    "sg:phone":"+1 608 000 1111",
    "sg:postcode":"54650",
    "sg:province":"WI",
    "sg:tags":[
        "grocer"
    ],
    "wof:name":"Aldi",
    "wof:placetype":"venue"
},
  "geometry": {"coordinates":[-91.17962799999999,43.880441],"type":"Point"}
}