{
  "type": "Feature",
  "properties": {
    "iso:country":"US",
    "sg:address":"322 Lincoln Ave",
    "sg:city":"Rio",
    "sg:classifiers":[
        {
            "category":"Organizations",
            "subcategory":"Religious Organization",
            "type":"Services"
        }
    ],
    "sg:phone":"+1 920 992 5112",
    "sg:postcode":"53960",
    "sg:province":"WI",
    "sg:tags":[
        "church"
    ],
    "sg:website":"www.christcongregationalchurch.org",
    "wof:name":"Christ Congregational Church",
    "wof:placetype":"venue"
},
  "geometry": {"coordinates":[-89.239082,43.447028],"type":"Point"}
}