{
  "type": "Feature",
  "properties": {
    "addr:full":"701 N 20th St Superior WI 54880",
    "addr:housenumber":"701",
    "addr:postcode":"54880",
    "addr:street":"N 20Th St",
    "iso:country":"US",
    "sg:address":"701 N 20th St",
    "sg:city":"Superior",
    "sg:classifiers":[
        {
            "category":"Building & Trades",
            "subcategory":"Cleaning & Sanitation",
            "type":"Services"
        }
    ],
    "sg:phone":"+1 715 392 9999",
    "sg:postcode":"54880",
    "sg:province":"WI",
    "sg:tags":[
        "ventilating",
        "system"
    ],
    "wof:name":"Anderson Vent Cleaning Systems",
    "wof:placetype":"venue"
},
  "geometry": {"coordinates":[-92.05601299999999,46.705014],"type":"Point"}
}