{
  "type": "Feature",
  "properties": {
    "iso:country":"US",
    "sg:address":"4055 Co Hwy U",
    "sg:city":"Hartford",
    "sg:classifiers":[
        {
            "category":"Building & Trades",
            "subcategory":"Construction",
            "type":"Services"
        }
    ],
    "sg:phone":"+1 262 673 3508",
    "sg:postcode":"53027",
    "sg:province":"WI",
    "sg:tags":[
        "residential"
    ],
    "wof:name":"Ralph Spaeth & Sons Inc",
    "wof:placetype":"venue"
},
  "geometry": {"coordinates":[-88.393531,43.335926],"type":"Point"}
}