{
  "type": "Feature",
  "properties": {
    "iso:country":"US",
    "sg:address":"1003 W North Ave",
    "sg:city":"Milwaukee",
    "sg:classifiers":[
        {
            "category":"Retail",
            "subcategory":"Laundry & Dry Cleaning",
            "type":"Services"
        }
    ],
    "sg:phone":"+1 414 374 5600",
    "sg:postcode":"53205",
    "sg:province":"WI",
    "sg:tags":[
        "linen",
        "supply"
    ],
    "sg:website":"www.alsco.com",
    "wof:name":"Alsco Inc",
    "wof:placetype":"venue"
},
  "geometry": {"coordinates":[-87.925477,43.060296],"type":"Point"}
}