{
  "type": "Feature",
  "properties": {
    "iso:country":"US",
    "sg:address":"595 Tower Rd",
    "sg:city":"Hudson",
    "sg:classifiers":[
        {
            "category":"Building & Trades",
            "subcategory":"Construction",
            "type":"Services"
        }
    ],
    "sg:phone":"+1 715 381 2967",
    "sg:postcode":"54016",
    "sg:province":"WI",
    "sg:tags":[
        "floor",
        "laying",
        "contractor"
    ],
    "wof:name":"Tesmar Application Tech",
    "wof:placetype":"venue"
},
  "geometry": {"coordinates":[-92.682801,44.940844],"type":"Point"}
}