{
  "type": "Feature",
  "properties": {
    "iso:country":"US",
    "sg:address":"1680 Wolf Run Dr",
    "sg:city":"Richfield",
    "sg:classifiers":[
        {
            "category":"Real Estate",
            "subcategory":"Real Estate Agent",
            "type":"Services"
        }
    ],
    "sg:phone":"+1 262 628 8964",
    "sg:postcode":"53076",
    "sg:province":"WI",
    "wof:name":"Gmd Property Management South",
    "wof:placetype":"venue"
},
  "geometry": {"coordinates":[-88.230385,43.250105],"type":"Point"}
}