{
  "type": "Feature",
  "properties": {
    "addr:full":"1659 Co Rd Z Cuba City WI 53807",
    "addr:housenumber":"1659",
    "addr:postcode":"53807",
    "addr:street":"Co Rd",
    "iso:country":"US",
    "sg:address":"1659 Co Rd Z",
    "sg:city":"Cuba City",
    "sg:classifiers":[
        {
            "category":"Farming",
            "subcategory":"Dairy Farm",
            "type":"Manufacturing & Wholesale Goods"
        }
    ],
    "sg:phone":"+1 608 744 3543",
    "sg:postcode":"53807",
    "sg:province":"WI",
    "wof:name":"Mueller Aryshires",
    "wof:placetype":"venue"
},
  "geometry": {"coordinates":[-90.53725300000001,42.562597],"type":"Point"}
}