{
  "type": "Feature",
  "properties": {
    "addr:full":"9231 Bobolink Rd Reeseville WI 53579",
    "addr:housenumber":"9231",
    "addr:postcode":"53579",
    "addr:street":"Bobolink Rd",
    "iso:country":"US",
    "sg:address":"9231 Bobolink Rd",
    "sg:city":"Reeseville",
    "sg:classifiers":[
        {
            "category":"Manufacturing",
            "subcategory":"Rubber & Plastics",
            "type":"Manufacturing & Wholesale Goods"
        }
    ],
    "sg:phone":"+1 920 927 5366",
    "sg:postcode":"53579",
    "sg:province":"WI",
    "sg:tags":[
        "producer"
    ],
    "wof:name":"Progressive Packaging & Design",
    "wof:placetype":"venue"
},
  "geometry": {"coordinates":[-88.841801,43.292571],"type":"Point"}
}