{
  "type": "Feature",
  "properties": {
    "addr:full":"2114 Jannsen Ct Menomonie WI 54751",
    "addr:postcode":"2114;54751",
    "addr:street":"Jannsen Ct",
    "iso:country":"US",
    "sg:address":"2114 Jannsen Ct",
    "sg:city":"Menomonie",
    "sg:classifiers":[
        {
            "category":"Building & Trades",
            "subcategory":"Construction",
            "type":"Services"
        }
    ],
    "sg:phone":"+1 715 235 1389",
    "sg:postcode":"54751",
    "sg:province":"WI",
    "sg:tags":[
        "water",
        "well",
        "drilling"
    ],
    "wof:name":"Wettstein Well Drilling",
    "wof:placetype":"venue"
},
  "geometry": {"coordinates":[-91.903907,44.859507],"type":"Point"}
}