{
  "type": "Feature",
  "properties": {
    "iso:country":"US",
    "sg:address":"2302 Airport Rd",
    "sg:city":"Brodhead",
    "sg:classifiers":[
        {
            "category":"Building & Trades",
            "subcategory":"Construction",
            "type":"Services"
        }
    ],
    "sg:phone":"+1 608 897 4509",
    "sg:postcode":"53520",
    "sg:province":"WI",
    "sg:tags":[
        "insulation",
        "concrete",
        "heat",
        "contractor"
    ],
    "wof:name":"Wisconsin Insulated Forms",
    "wof:placetype":"venue"
},
  "geometry": {"coordinates":[-89.376819,42.593227],"type":"Point"}
}