{
  "type": "Feature",
  "properties": {
    "iso:country":"US",
    "sg:address":"344 Broadway St",
    "sg:city":"Berlin",
    "sg:classifiers":[
        {
            "category":"Education",
            "subcategory":"School",
            "type":"Public Place"
        }
    ],
    "sg:phone":"+1 920 361 2012",
    "sg:postcode":"54923",
    "sg:province":"WI",
    "wof:name":"Washington Alternative School",
    "wof:placetype":"venue"
},
  "geometry": {"coordinates":[-88.957663,43.968265],"type":"Point"}
}