{
  "type": "Feature",
  "properties": {
    "iso:country":"US",
    "sg:address":"3792 Lakeland Rd",
    "sg:city":"Saukville",
    "sg:classifiers":[
        {
            "category":"Building & Trades",
            "subcategory":"Construction",
            "type":"Services"
        }
    ],
    "sg:phone":"+1 262 675 2218",
    "sg:postcode":"53080",
    "sg:province":"WI",
    "sg:tags":[
        "concrete",
        "product",
        "asphalt",
        "contractor"
    ],
    "wof:name":"Payne & Dolan Inc",
    "wof:placetype":"venue"
},
  "geometry": {"coordinates":[-87.995678,43.421838],"type":"Point"}
}