{
  "type": "Feature",
  "properties": {
    "iso:country":"US",
    "sg:address":"108 Ashland Ave E",
    "sg:city":"Almena",
    "sg:classifiers":[
        {
            "category":"Building & Trades",
            "subcategory":"Construction",
            "type":"Services"
        }
    ],
    "sg:phone":"+1 715 357 6153",
    "sg:postcode":"54805",
    "sg:province":"WI",
    "sg:tags":[
        "residential"
    ],
    "wof:name":"Skinner Jeff Construction",
    "wof:placetype":"venue"
},
  "geometry": {"coordinates":[-92.037564,45.413225],"type":"Point"}
}