{
  "type": "Feature",
  "properties": {
    "addr:full":"15691 Co Rd K Darlington WI 53530",
    "addr:housenumber":"15691",
    "addr:postcode":"53530",
    "addr:street":"Co Rd",
    "iso:country":"US",
    "sg:address":"15691 Co Rd K",
    "sg:city":"Darlington",
    "sg:classifiers":[
        {
            "category":"Organizations",
            "subcategory":"Religious Organization",
            "type":"Services"
        }
    ],
    "sg:phone":"+1 608 776 3566",
    "sg:postcode":"53530",
    "sg:province":"WI",
    "wof:name":"First Baptist Church",
    "wof:placetype":"venue"
},
  "geometry": {"coordinates":[-90.127088,42.660689],"type":"Point"}
}