{
  "type": "Feature",
  "properties": {
    "iso:country":"US",
    "sg:address":"103 Main St",
    "sg:city":"Somerset",
    "sg:classifiers":[
        {
            "category":"Building & Trades",
            "subcategory":"Construction",
            "type":"Services"
        }
    ],
    "sg:phone":"+1 715 247 2742",
    "sg:postcode":"54025",
    "sg:province":"WI",
    "sg:tags":[
        "general",
        "contractor"
    ],
    "wof:name":"Collova Builders Inc",
    "wof:placetype":"venue"
},
  "geometry": {"coordinates":[-92.673624,45.124895],"type":"Point"}
}