{
  "type": "Feature",
  "properties": {
    "iso:country":"US",
    "sg:address":"4710 Lower Hebron Rd",
    "sg:city":"Fort Atkinson",
    "sg:classifiers":[
        {
            "category":"Retail",
            "subcategory":"Laundry & Dry Cleaning",
            "type":"Services"
        }
    ],
    "sg:phone":"+1 920 568 9099",
    "sg:postcode":"53538",
    "sg:province":"WI",
    "sg:tags":[
        "drycleaning",
        "plant"
    ],
    "wof:name":"Spiffy Cleaners Services",
    "wof:placetype":"venue"
},
  "geometry": {"coordinates":[-88.773544,42.917431],"type":"Point"}
}