{
  "type": "Feature",
  "properties": {
    "iso:country":"US",
    "sg:address":"445 S Albert Ave",
    "sg:city":"Reedsburg",
    "sg:classifiers":[
        {
            "category":"Manufacturing",
            "subcategory":"Metals",
            "type":"Manufacturing & Wholesale Goods"
        }
    ],
    "sg:phone":"+1 608 524 3541",
    "sg:postcode":"53959",
    "sg:province":"WI",
    "sg:tags":[
        "fabricator",
        "sheet"
    ],
    "wof:name":"Grinder Sheet Metal Inc",
    "wof:placetype":"venue"
},
  "geometry": {"coordinates":[-90.017795,43.528584],"type":"Point"}
}