{
  "type": "Feature",
  "properties": {
    "iso:country":"US",
    "sg:address":"214 W Cottage Grove Rd",
    "sg:city":"Cottage Grove",
    "sg:classifiers":[
        {
            "category":"Restaurant",
            "type":"Food & Drink"
        }
    ],
    "sg:phone":"+1 608 839 3897",
    "sg:postcode":"53527",
    "sg:province":"WI",
    "wof:name":"Northside Meats & Deli",
    "wof:placetype":"venue"
},
  "geometry": {"coordinates":[-89.201642,43.086772],"type":"Point"}
}