{
  "type": "Feature",
  "properties": {
    "iso:country":"US",
    "sg:address":"2160 Parmenter St",
    "sg:city":"Middleton",
    "sg:classifiers":[
        {
            "category":"Professional",
            "subcategory":"Computer Services",
            "type":"Services"
        }
    ],
    "sg:phone":"+1 608 836 6679",
    "sg:postcode":"53562",
    "sg:province":"WI",
    "sg:tags":[
        "related"
    ],
    "wof:name":"FHB Enterprises",
    "wof:placetype":"venue"
},
  "geometry": {"coordinates":[-89.51156,43.098538],"type":"Point"}
}