{
  "type": "Feature",
  "properties": {
    "iso:country":"US",
    "sg:address":"7500 W North Ave",
    "sg:city":"Milwaukee",
    "sg:classifiers":[
        {
            "category":"Health Services",
            "subcategory":"Nursing And Care Facility",
            "type":"Services"
        }
    ],
    "sg:phone":"+1 414 258 6170",
    "sg:postcode":"53213",
    "sg:province":"WI",
    "sg:tags":[
        "home",
        "skilled",
        "convalescent"
    ],
    "wof:name":"Lutheran Home Inc",
    "wof:placetype":"venue"
},
  "geometry": {"coordinates":[-88.00645799999999,43.060821],"type":"Point"}
}