{
  "type": "Feature",
  "properties": {
    "iso:country":"US",
    "sg:address":"7552 W Appleton Ave",
    "sg:city":"Milwaukee",
    "sg:classifiers":[
        {
            "category":"Retail",
            "subcategory":"Auto Rental",
            "type":"Services"
        }
    ],
    "sg:phone":"+1 414 463 2277",
    "sg:postcode":"53216",
    "sg:province":"WI",
    "sg:tags":[
        "renting",
        "automobile"
    ],
    "wof:name":"AAAA Auto-Van Rental",
    "wof:placetype":"venue"
},
  "geometry": {"coordinates":[-88.006325,43.092643],"type":"Point"}
}