{
  "type": "Feature",
  "properties": {
    "addr:full":"570 9th St S Park Falls WI 54552",
    "addr:housenumber":"570",
    "addr:postcode":"54552",
    "addr:street":"9Th St S",
    "iso:country":"US",
    "sg:address":"570 9th St S",
    "sg:city":"Park Falls",
    "sg:classifiers":[
        {
            "category":"Building & Trades",
            "subcategory":"Electrical",
            "type":"Services"
        }
    ],
    "sg:phone":"+1 715 762 4673",
    "sg:postcode":"54552",
    "sg:province":"WI",
    "sg:tags":[
        "electric",
        "contractor"
    ],
    "wof:name":"Jim Schmidt & Sons Contractors",
    "wof:placetype":"venue"
},
  "geometry": {"coordinates":[-90.45515399999999,45.924046],"type":"Point"}
}