{
  "type": "Feature",
  "properties": {
    "iso:country":"US",
    "sg:address":"6083 Langes Corners Rd",
    "sg:city":"Denmark",
    "sg:classifiers":[
        {
            "category":"Farming",
            "subcategory":"Dairy Farm",
            "type":"Manufacturing & Wholesale Goods"
        }
    ],
    "sg:phone":"+1 920 863 2481",
    "sg:postcode":"54208",
    "sg:province":"WI",
    "wof:name":"Glenn Rentmeester",
    "wof:placetype":"venue"
},
  "geometry": {"coordinates":[-87.789007,44.372052],"type":"Point"}
}