{
  "type": "Feature",
  "properties": {
    "iso:country":"US",
    "sg:address":"17433 McGilvary Rd",
    "sg:city":"Galesville",
    "sg:classifiers":[
        {
            "category":"Farming",
            "subcategory":"Farm & Veterinary Services",
            "type":"Manufacturing & Wholesale Goods"
        }
    ],
    "sg:phone":"+1 608 582 2354",
    "sg:postcode":"54630",
    "sg:province":"WI",
    "sg:tags":[
        "preparation",
        "crop",
        "for",
        "market"
    ],
    "wof:name":"Dennis Pierzina",
    "wof:placetype":"venue"
},
  "geometry": {"coordinates":[-91.354743,44.049315],"type":"Point"}
}