{
  "type": "Feature",
  "properties": {
    "addr:full":"2300 N Mayfair Rd Milwaukee WI 53222",
    "addr:housenumber":"2300",
    "addr:postcode":"53222",
    "addr:street":"N Mayfair Rd",
    "iso:country":"US",
    "sg:address":"2300 N Mayfair Rd",
    "sg:city":"Milwaukee",
    "sg:classifiers":[
        {
            "category":"Professional",
            "subcategory":"Lawyer & Legal Services",
            "type":"Services"
        }
    ],
    "sg:phone":"+1 414 258 2313",
    "sg:postcode":"53222",
    "sg:province":"WI",
    "wof:name":"Ellingson Erik B Atty At Law",
    "wof:placetype":"venue"
},
  "geometry": {"coordinates":[-88.04780700000001,43.06745],"type":"Point"}
}