{
  "type": "Feature",
  "properties": {
    "addr:full":"8069 Sales Rd Van Dyne WI 54979",
    "addr:housenumber":"8069",
    "addr:postcode":"54979",
    "addr:street":"Sales Rd",
    "iso:country":"US",
    "sg:address":"8069 Sales Rd",
    "sg:city":"Van Dyne",
    "sg:classifiers":[
        {
            "category":"Bus Charters",
            "type":"Transportation"
        }
    ],
    "sg:phone":"+1 920 924 4175",
    "sg:postcode":"54979",
    "sg:province":"WI",
    "sg:tags":[
        "rental"
    ],
    "wof:name":"Stagecoach Travel",
    "wof:placetype":"venue"
},
  "geometry": {"coordinates":[-88.544298,43.836798],"type":"Point"}
}