{
  "type": "Feature",
  "properties": {
    "iso:country":"US",
    "sg:address":"100 Evergreen Blvd",
    "sg:city":"Marshall",
    "sg:classifiers":[
        {
            "category":"Real Estate",
            "subcategory":"Real Estate Operator",
            "type":"Services"
        }
    ],
    "sg:phone":"+1 608 655 3857",
    "sg:postcode":"53559",
    "sg:province":"WI",
    "sg:tags":[
        "mobile",
        "home",
        "site",
        "community"
    ],
    "wof:name":"Evergreen Mobile Park",
    "wof:placetype":"venue"
},
  "geometry": {"coordinates":[-89.07317399999999,43.170244],"type":"Point"}
}