{
  "type": "Feature",
  "properties": {
    "addr:full":"219 Broadway St Berlin WI 54923",
    "addr:housenumber":"219",
    "addr:postcode":"54923",
    "addr:street":"Broadway St",
    "iso:country":"US",
    "sg:address":"219 Broadway St",
    "sg:city":"Berlin",
    "sg:classifiers":[
        {
            "category":"Home & Garden",
            "subcategory":"Home Furnishings",
            "type":"Retail Goods"
        }
    ],
    "sg:phone":"+1 920 361 1900",
    "sg:postcode":"54923",
    "sg:province":"WI",
    "sg:tags":[
        "window",
        "floor",
        "treatment",
        "covering"
    ],
    "wof:name":"Knutson & Sons Inc",
    "wof:placetype":"venue"
},
  "geometry": {"coordinates":[-88.95261600000001,43.968425],"type":"Point"}
}