{
  "type": "Feature",
  "properties": {
    "addr:full":"525 N Perkins St Appleton WI 54914",
    "addr:housenumber":"525",
    "addr:postcode":"54914",
    "addr:street":"N Perkins St",
    "iso:country":"US",
    "sg:address":"525 N Perkins St",
    "sg:city":"Appleton",
    "sg:classifiers":[
        {
            "category":"Recreation",
            "type":"Entertainment"
        }
    ],
    "sg:phone":"+1 920 954 5300",
    "sg:postcode":"54914",
    "sg:province":"WI",
    "sg:tags":[
        "range",
        "baseball",
        "batting"
    ],
    "wof:name":"Batter's Box",
    "wof:placetype":"venue"
},
  "geometry": {"coordinates":[-88.440731,44.264851],"type":"Point"}
}