{
  "type": "Feature",
  "properties": {
    "iso:country":"US",
    "sg:address":"303 Bay Park Sq",
    "sg:city":"Green Bay",
    "sg:classifiers":[
        {
            "category":"Shopping",
            "subcategory":"Gifts & Souvenirs",
            "type":"Retail Goods"
        }
    ],
    "sg:phone":"+1 920 499 0064",
    "sg:postcode":"54304",
    "sg:province":"WI",
    "sg:tags":[
        "shop"
    ],
    "wof:name":"Look Sharp",
    "wof:placetype":"venue"
},
  "geometry": {"coordinates":[-88.067604,44.484512],"type":"Point"}
}