{
  "type": "Feature",
  "properties": {
    "iso:country":"US",
    "sg:address":"13480 W Linfield Dr",
    "sg:city":"New Berlin",
    "sg:classifiers":[
        {
            "category":"Professional",
            "subcategory":"Computer Services",
            "type":"Services"
        },
        {
            "category":"Shopping",
            "subcategory":"Computers & Home Electronics",
            "type":"Retail Goods"
        }
    ],
    "sg:phone":"+1 262 782 0159",
    "sg:postcode":"53151",
    "sg:province":"WI",
    "sg:tags":[
        "prepackaged",
        "software"
    ],
    "sg:website":"www.teamanizer.com",
    "wof:name":"Youth Sports Software L L C",
    "wof:placetype":"venue"
},
  "geometry": {"coordinates":[-88.083737,42.969025],"type":"Point"}
}