{
  "type": "Feature",
  "properties": {
    "iso:country":"US",
    "sg:address":"433 Meadowridge Cir",
    "sg:city":"Lake Mills",
    "sg:classifiers":[
        {
            "category":"Building & Trades",
            "subcategory":"Landscaping Services",
            "type":"Services"
        }
    ],
    "sg:phone":"+1 920 648 4783",
    "sg:postcode":"53551",
    "sg:province":"WI",
    "wof:name":"Clean Cut Lawn Care",
    "wof:placetype":"venue"
},
  "geometry": {"coordinates":[-88.911995,43.074228],"type":"Point"}
}