{
  "type": "Feature",
  "properties": {
    "iso:country":"US",
    "sg:address":"720 N Rochester St",
    "sg:city":"Mukwonago",
    "sg:classifiers":[
        {
            "category":"Personal",
            "subcategory":"Beauty Salon",
            "type":"Services"
        }
    ],
    "sg:phone":"+1 262 363 9959",
    "sg:postcode":"53149",
    "sg:province":"WI",
    "wof:name":"Hair Care Co",
    "wof:placetype":"venue"
},
  "geometry": {"coordinates":[-88.336108,42.870669],"type":"Point"}
}