{
  "type": "Feature",
  "properties": {
    "iso:country":"US",
    "sg:address":"816 Donald St",
    "sg:city":"Medford",
    "sg:classifiers":[
        {
            "category":"Wholesale",
            "subcategory":"Construction Materials",
            "type":"Manufacturing & Wholesale Goods"
        }
    ],
    "sg:phone":"+1 715 748 5002",
    "sg:postcode":"54451",
    "sg:province":"WI",
    "wof:name":"Medford Millwork Inc",
    "wof:placetype":"venue"
},
  "geometry": {"coordinates":[-90.334491,45.128418],"type":"Point"}
}