{
  "type": "Feature",
  "properties": {
    "iso:country":"US",
    "sg:address":"1239 Woodland Dr",
    "sg:city":"Milton",
    "sg:classifiers":[
        {
            "category":"Real Estate",
            "subcategory":"Real Estate Agent",
            "type":"Services"
        }
    ],
    "sg:phone":"+1 608 868 7997",
    "sg:postcode":"53563",
    "sg:province":"WI",
    "sg:tags":[
        "inspection"
    ],
    "wof:name":"Home Pro Inspection Svc",
    "wof:placetype":"venue"
},
  "geometry": {"coordinates":[-88.973465,42.787202],"type":"Point"}
}