{
  "type": "Feature",
  "properties": {
    "addr:full":"10500 Co Rd B Crandon WI 54520",
    "addr:housenumber":"10500",
    "addr:postcode":"54520",
    "addr:street":"Co Rd B",
    "iso:country":"US",
    "sg:address":"10500 Co Rd B",
    "sg:city":"Crandon",
    "sg:classifiers":[
        {
            "category":"Building & Trades",
            "subcategory":"Construction",
            "type":"Services"
        }
    ],
    "sg:phone":"+1 715 478 3147",
    "sg:postcode":"54520",
    "sg:province":"WI",
    "sg:tags":[
        "painter"
    ],
    "wof:name":"Allred Painting",
    "wof:placetype":"venue"
},
  "geometry": {"coordinates":[-88.962005,45.527469],"type":"Point"}
}