{
  "type": "Feature",
  "properties": {
    "iso:country":"US",
    "sg:address":"1690 Aqua View Ct",
    "sg:city":"Cedarburg",
    "sg:classifiers":[
        {
            "category":"Professional",
            "subcategory":"Business Services",
            "type":"Services"
        }
    ],
    "sg:phone":"+1 262 377 5953",
    "sg:postcode":"53012",
    "sg:province":"WI",
    "wof:name":"Rohm Associates",
    "wof:placetype":"venue"
},
  "geometry": {"coordinates":[-87.94965500000001,43.281608],"type":"Point"}
}