{
  "type": "Feature",
  "properties": {
    "iso:country":"US",
    "sg:address":"36856 State Hwy 93",
    "sg:city":"Independence",
    "sg:classifiers":[
        {
            "category":"Farming",
            "subcategory":"Farm",
            "type":"Manufacturing & Wholesale Goods"
        }
    ],
    "sg:phone":"+1 715 985 3891",
    "sg:postcode":"54747",
    "sg:province":"WI",
    "wof:name":"Dejno Acres Farm",
    "wof:placetype":"venue"
},
  "geometry": {"coordinates":[-91.427723,44.37433],"type":"Point"}
}