{
  "type": "Feature",
  "properties": {
    "iso:country":"US",
    "sg:address":"435 E Mill St",
    "sg:city":"Plymouth",
    "sg:classifiers":[
        {
            "category":"Professional",
            "subcategory":"Lawyer & Legal Services",
            "type":"Services"
        }
    ],
    "sg:phone":"+1 920 892 6634",
    "sg:postcode":"53073",
    "sg:province":"WI",
    "sg:tags":[
        "attorney"
    ],
    "wof:name":"Daniel J Rostollan Attorney",
    "wof:placetype":"venue"
},
  "geometry": {"coordinates":[-87.975861,43.747483],"type":"Point"}
}