{
  "type": "Feature",
  "properties": {
    "addr:full":"1067 Wren Dr Curtiss WI 54422",
    "addr:housenumber":"1067",
    "addr:postcode":"54422",
    "addr:street":"Wren Dr",
    "iso:country":"US",
    "sg:address":"1067 Wren Dr",
    "sg:city":"Curtiss",
    "sg:classifiers":[
        {
            "category":"Farming",
            "subcategory":"Livestock Farm",
            "type":"Manufacturing & Wholesale Goods"
        }
    ],
    "sg:phone":"+1 715 678 2824",
    "sg:postcode":"54422",
    "sg:province":"WI",
    "sg:tags":[
        "animal",
        "general"
    ],
    "wof:name":"Thunderbird Ranch",
    "wof:placetype":"venue"
},
  "geometry": {"coordinates":[-90.45457399999999,45.060075],"type":"Point"}
}