{
  "type": "Feature",
  "properties": {
    "iso:country":"US",
    "sg:address":"2210 Evergreen Rd",
    "sg:city":"Middleton",
    "sg:classifiers":[
        {
            "category":"Freight",
            "type":"Transportation"
        }
    ],
    "sg:phone":"+1 608 836 5504",
    "sg:postcode":"53562",
    "sg:province":"WI",
    "sg:tags":[
        "commercial",
        "storage"
    ],
    "wof:name":"Golf Green Storage Inc",
    "wof:placetype":"venue"
},
  "geometry": {"coordinates":[-89.536072,43.097783],"type":"Point"}
}