{
  "type": "Feature",
  "properties": {
    "iso:country":"US",
    "sg:address":"7075 Co Rd A",
    "sg:city":"Lena",
    "sg:classifiers":[
        {
            "category":"Building & Trades",
            "subcategory":"Construction",
            "type":"Services"
        }
    ],
    "sg:phone":"+1 920 829 5035",
    "sg:postcode":"54139",
    "sg:province":"WI",
    "sg:tags":[
        "concrete",
        "contractor"
    ],
    "wof:name":"St Louis Concrete Inc",
    "wof:placetype":"venue"
},
  "geometry": {"coordinates":[-88.11505,44.951197],"type":"Point"}
}