{
  "type": "Feature",
  "properties": {
    "iso:country":"US",
    "sg:address":"5622 Lacy Rd",
    "sg:city":"Madison",
    "sg:classifiers":[
        {
            "category":"Shopping",
            "subcategory":"Computers & Home Electronics",
            "type":"Retail Goods"
        }
    ],
    "sg:phone":"+1 608 442 6602",
    "sg:postcode":"53711",
    "sg:province":"WI",
    "wof:name":"M Squared Computer Networks",
    "wof:placetype":"venue"
},
  "geometry": {"coordinates":[-89.436268,43.001337],"type":"Point"}
}