{
  "type": "Feature",
  "properties": {
    "iso:country":"US",
    "sg:address":"1500 State St",
    "sg:city":"Eau Claire",
    "sg:classifiers":[
        {
            "category":"Wholesale",
            "subcategory":"Apparel",
            "type":"Manufacturing & Wholesale Goods"
        }
    ],
    "sg:phone":"+1 715 835 9006",
    "sg:postcode":"54701",
    "sg:province":"WI",
    "sg:tags":[
        "piece",
        "sewing"
    ],
    "wof:name":"Threade Bear",
    "wof:placetype":"venue"
},
  "geometry": {"coordinates":[-91.494999,44.79877],"type":"Point"}
}