{
  "type": "Feature",
  "properties": {
    "iso:country":"US",
    "sg:address":"4670 Glidden Dr",
    "sg:city":"Sturgeon Bay",
    "sg:classifiers":[
        {
            "category":"Restaurant",
            "type":"Food & Drink"
        }
    ],
    "sg:phone":"+1 920 746 9460",
    "sg:postcode":"54235",
    "sg:province":"WI",
    "wof:name":"Donny's Glidden Lodge",
    "wof:placetype":"venue"
},
  "geometry": {"coordinates":[-87.218646,44.897422],"type":"Point"}
}