{
  "type": "Feature",
  "properties": {
    "iso:country":"US",
    "sg:address":"619 Main St",
    "sg:city":"Neenah",
    "sg:classifiers":[
        {
            "category":"Social Services",
            "type":"Services"
        }
    ],
    "sg:phone":"+1 920 729 5721",
    "sg:postcode":"54956",
    "sg:province":"WI",
    "sg:tags":[
        "mission"
    ],
    "wof:name":"International Childrens Fund",
    "wof:placetype":"venue"
},
  "geometry": {"coordinates":[-88.474722,44.188735],"type":"Point"}
}