{
  "type": "Feature",
  "properties": {
    "iso:country":"US",
    "sg:address":"5977 Co Rd J",
    "sg:city":"Plymouth",
    "sg:classifiers":[
        {
            "category":"Government",
            "subcategory":"Office",
            "type":"Public Place"
        }
    ],
    "sg:phone":"+1 920 893 8750",
    "sg:postcode":"53073",
    "sg:province":"WI",
    "sg:tags":[
        "executive"
    ],
    "wof:name":"Plymouth Town Hall",
    "wof:placetype":"venue"
},
  "geometry": {"coordinates":[-87.995043,43.790175],"type":"Point"}
}