{
  "type": "Feature",
  "properties": {
    "addr:full":"324 E Lindbergh St Appleton WI 54911",
    "addr:housenumber":"324",
    "addr:postcode":"54911",
    "addr:street":"E Lindbergh St",
    "iso:country":"US",
    "sg:address":"324 E Lindbergh St",
    "sg:city":"Appleton",
    "sg:classifiers":[
        {
            "category":"Professional",
            "subcategory":"Management & Consulting",
            "type":"Services"
        }
    ],
    "sg:phone":"+1 920 731 9610",
    "sg:postcode":"54911",
    "sg:province":"WI",
    "sg:tags":[
        "business"
    ],
    "wof:name":"Ej Krueger & Associates Inc",
    "wof:placetype":"venue"
},
  "geometry": {"coordinates":[-88.401213,44.283399],"type":"Point"}
}