{
  "type": "Feature",
  "properties": {
    "iso:country":"US",
    "sg:address":"2263 Waters End Rd",
    "sg:city":"Sister Bay",
    "sg:classifiers":[
        {
            "category":"Professional",
            "subcategory":"Business Services",
            "type":"Services"
        }
    ],
    "sg:phone":"+1 920 854 9808",
    "sg:postcode":"54234",
    "sg:province":"WI",
    "wof:name":"Allemande Music",
    "wof:placetype":"venue"
},
  "geometry": {"coordinates":[-87.115786,45.207411],"type":"Point"}
}