{
  "type": "Feature",
  "properties": {
    "iso:country":"US",
    "sg:address":"250 W Main St",
    "sg:city":"Waukesha",
    "sg:classifiers":[
        {
            "category":"Shopping",
            "subcategory":"Stationery & Office Supplies",
            "type":"Retail Goods"
        }
    ],
    "sg:phone":"+1 262 542 4422",
    "sg:postcode":"53186",
    "sg:province":"WI",
    "wof:name":"Zilmer's Office Supplies Inc",
    "wof:placetype":"venue"
},
  "geometry": {"coordinates":[-88.231181,43.011633],"type":"Point"}
}