{
  "type": "Feature",
  "properties": {
    "addr:full":"2976 Co Rd M White Lake WI 54491",
    "addr:housenumber":"2976",
    "addr:postcode":"54491",
    "addr:street":"Co Rd M",
    "iso:country":"US",
    "sg:address":"2976 Co Rd M",
    "sg:city":"White Lake",
    "sg:classifiers":[
        {
            "category":"Farming",
            "subcategory":"Nursery",
            "type":"Manufacturing & Wholesale Goods"
        }
    ],
    "sg:phone":"+1 715 882 3100",
    "sg:postcode":"54491",
    "sg:province":"WI",
    "sg:tags":[
        "agricultural",
        "seed",
        "grower"
    ],
    "sg:website":"www.wolfrivervalleyseeds.com",
    "wof:name":"Wolf River Valley Seeds",
    "wof:placetype":"venue"
},
  "geometry": {"coordinates":[-88.77476299999999,45.139131],"type":"Point"}
}