{
  "type": "Feature",
  "properties": {
    "addr:full":"12780 W North Ave Brookfield WI 53005",
    "addr:housenumber":"12780",
    "addr:postcode":"53005",
    "addr:street":"W North Ave",
    "iso:country":"US",
    "sg:address":"12780 W North Ave",
    "sg:city":"Brookfield",
    "sg:classifiers":[
        {
            "category":"Professional",
            "subcategory":"Management & Consulting",
            "type":"Services"
        },
        {
            "category":"Health Services",
            "subcategory":"Doctor",
            "type":"Services"
        }
    ],
    "sg:phone":"+1 262 782 1800",
    "sg:postcode":"53005",
    "sg:province":"WI",
    "sg:tags":[
        "laboratory",
        "medical",
        "imaging"
    ],
    "wof:name":"Open Advanced Mri of Milwaukee",
    "wof:placetype":"venue"
},
  "geometry": {"coordinates":[-88.072371,43.060147],"type":"Point"}
}