{
  "type": "Feature",
  "properties": {
    "addr:full":"11530 W Layton Ave Milwaukee WI 53228",
    "addr:housenumber":"11530",
    "addr:postcode":"53228",
    "addr:street":"W Layton Ave",
    "iso:country":"US",
    "sg:address":"11530 W Layton Ave",
    "sg:city":"Milwaukee",
    "sg:classifiers":[
        {
            "category":"Organizations",
            "subcategory":"Religious Organization",
            "type":"Services"
        }
    ],
    "sg:phone":"+1 414 425 6181",
    "sg:postcode":"53228",
    "sg:province":"WI",
    "sg:tags":[
        "place",
        "worship",
        "church"
    ],
    "wof:name":"West Layton Assembly of God",
    "wof:placetype":"venue"
},
  "geometry": {"coordinates":[-88.05696,42.95919],"type":"Point"}
}