{
  "type": "Feature",
  "properties": {
    "iso:country":"US",
    "sg:address":"777 N Jefferson St",
    "sg:city":"Milwaukee",
    "sg:classifiers":[
        {
            "category":"Shopping",
            "subcategory":"Used Merchandise",
            "type":"Retail Goods"
        }
    ],
    "sg:phone":"+1 414 276 4742",
    "sg:postcode":"53202",
    "sg:province":"WI",
    "sg:tags":[
        "new",
        "woman",
        "clothing",
        "for"
    ],
    "wof:name":"Cara Carolina",
    "wof:placetype":"venue"
},
  "geometry": {"coordinates":[-87.90554299999999,43.0406],"type":"Point"}
}