{
  "type": "Feature",
  "properties": {
    "iso:country":"US",
    "sg:address":"225 S Main St",
    "sg:city":"Shawano",
    "sg:classifiers":[
        {
            "category":"Government",
            "subcategory":"Office",
            "type":"Public Place"
        }
    ],
    "sg:phone":"+1 715 526 9311",
    "sg:postcode":"54166",
    "sg:province":"WI",
    "wof:name":"Shawano Senior Ctr & Craft",
    "wof:placetype":"venue"
},
  "geometry": {"coordinates":[-88.609362,44.779692],"type":"Point"}
}