{
  "type": "Feature",
  "properties": {
    "iso:country":"US",
    "sg:address":"900 John Nolen Dr",
    "sg:city":"Madison",
    "sg:classifiers":[
        {
            "category":"Professional",
            "subcategory":"Lawyer & Legal Services",
            "type":"Services"
        }
    ],
    "sg:phone":"+1 608 257 4011",
    "sg:postcode":"53713",
    "sg:province":"WI",
    "wof:name":"Dave Smithson Attorney",
    "wof:placetype":"venue"
},
  "geometry": {"coordinates":[-89.371854,43.04559],"type":"Point"}
}