{
  "type": "Feature",
  "properties": {
    "iso:country":"US",
    "sg:address":"111 E Wisconsin Ave Suite 1400",
    "sg:city":"Milwaukee",
    "sg:classifiers":[
        {
            "category":"Professional",
            "subcategory":"Lawyer & Legal Services",
            "type":"Services"
        }
    ],
    "sg:phone":"+1 414 276 5000",
    "sg:postcode":"53202",
    "sg:province":"WI",
    "sg:tags":[
        "litigation",
        "tort",
        "attorney"
    ],
    "wof:name":"Strye Steven L",
    "wof:placetype":"venue"
},
  "geometry": {"coordinates":[-87.909719,43.03862],"type":"Point"}
}