{
  "type": "Feature",
  "properties": {
    "iso:country":"US",
    "sg:address":"4679 Co Rd Y",
    "sg:city":"Montello",
    "sg:classifiers":[
        {
            "category":"Building & Trades",
            "subcategory":"Landscaping Services",
            "type":"Services"
        }
    ],
    "sg:phone":"+1 608 297 9795",
    "sg:postcode":"53949",
    "sg:province":"WI",
    "sg:tags":[
        "landscape",
        "contractor"
    ],
    "wof:name":"Dick Daniels Lawn Care",
    "wof:placetype":"venue"
},
  "geometry": {"coordinates":[-89.3342,43.808698],"type":"Point"}
}