{
  "type": "Feature",
  "properties": {
    "addr:full":"719 Summit Ave Oconomowoc WI 53066",
    "addr:housenumber":"719",
    "addr:postcode":"53066",
    "addr:street":"Summit Ave",
    "iso:country":"US",
    "sg:address":"719 Summit Ave",
    "sg:city":"Oconomowoc",
    "sg:classifiers":[
        {
            "category":"Health Services",
            "subcategory":"Hospital",
            "type":"Services"
        }
    ],
    "sg:phone":"+1 262 569 0263",
    "sg:postcode":"53066",
    "sg:province":"WI",
    "sg:tags":[
        "general"
    ],
    "wof:name":"Oconomooc Hospital",
    "wof:placetype":"venue"
},
  "geometry": {"coordinates":[-88.48572,43.100733],"type":"Point"}
}