{
  "type": "Feature",
  "properties": {
    "iso:country":"US",
    "sg:address":"1859 115th St",
    "sg:city":"Chippewa Falls",
    "sg:classifiers":[
        {
            "category":"Building & Trades",
            "subcategory":"Landscaping Services",
            "type":"Services"
        }
    ],
    "sg:phone":"+1 715 831 8180",
    "sg:postcode":"54729",
    "sg:province":"WI",
    "sg:tags":[
        "tree"
    ],
    "wof:name":"Zielie's Tree Svc",
    "wof:placetype":"venue"
},
  "geometry": {"coordinates":[-91.437945,44.870358],"type":"Point"}
}