{
  "type": "Feature",
  "properties": {
    "addr:full":"3305 S 20th St Milwaukee WI 53215",
    "addr:housenumber":"3305",
    "addr:postcode":"53215",
    "addr:street":"S 20Th St",
    "iso:country":"US",
    "sg:address":"3305 S 20th St",
    "sg:city":"Milwaukee",
    "sg:classifiers":[
        {
            "category":"Shopping",
            "subcategory":"Pharmacy",
            "type":"Retail Goods"
        }
    ],
    "sg:phone":"+1 414 384 4923",
    "sg:postcode":"53215",
    "sg:province":"WI",
    "wof:name":"Aurora Health Care Pharmacy",
    "wof:placetype":"venue"
},
  "geometry": {"coordinates":[-87.938588,42.988169],"type":"Point"}
}