{
  "type": "Feature",
  "properties": {
    "iso:country":"US",
    "sg:address":"2122 Luann Ln",
    "sg:city":"Madison",
    "sg:classifiers":[
        {
            "category":"Organizations",
            "subcategory":"Non-profit Organization",
            "type":"Services"
        }
    ],
    "sg:phone":"+1 608 270 2242",
    "sg:postcode":"53713",
    "sg:province":"WI",
    "sg:tags":[
        "human"
    ],
    "wof:name":"Community Support Network",
    "wof:placetype":"venue"
},
  "geometry": {"coordinates":[-89.415373,43.032799],"type":"Point"}
}