{
  "type": "Feature",
  "properties": {
    "iso:country":"US",
    "sg:address":"11307 N Rosewood Dr",
    "sg:city":"Mequon",
    "sg:classifiers":[
        {
            "category":"Professional",
            "subcategory":"Art Services",
            "type":"Services"
        }
    ],
    "sg:phone":"+1 262 478 0111",
    "sg:postcode":"53092",
    "sg:province":"WI",
    "sg:tags":[
        "graphic",
        "designer"
    ],
    "wof:name":"Koerner Design",
    "wof:placetype":"venue"
},
  "geometry": {"coordinates":[-87.951915,43.225076],"type":"Point"}
}