{
  "type": "Feature",
  "properties": {
    "iso:country":"US",
    "sg:address":"375 Williamstowne",
    "sg:city":"Delafield",
    "sg:classifiers":[
        {
            "category":"Professional",
            "subcategory":"Management & Consulting",
            "type":"Services"
        },
        {
            "category":"Wholesale",
            "subcategory":"Groceries",
            "type":"Manufacturing & Wholesale Goods"
        }
    ],
    "sg:phone":"+1 262 646 4213",
    "sg:postcode":"53018",
    "sg:province":"WI",
    "sg:tags":[
        "food",
        "broker"
    ],
    "wof:name":"Corbranz & Associates",
    "wof:placetype":"venue"
},
  "geometry": {"coordinates":[-88.377376,43.050055],"type":"Point"}
}