{
  "type": "Feature",
  "properties": {
    "iso:country":"US",
    "sg:address":"1500 River St",
    "sg:city":"Merrill",
    "sg:classifiers":[
        {
            "category":"Home & Garden",
            "subcategory":"Furniture",
            "type":"Retail Goods"
        }
    ],
    "sg:phone":"+1 715 536 7246",
    "sg:postcode":"54452",
    "sg:province":"WI",
    "sg:tags":[
        "used",
        "merchandise"
    ],
    "wof:name":"River Street Antique Company",
    "wof:placetype":"venue"
},
  "geometry": {"coordinates":[-89.67884599999999,45.179901],"type":"Point"}
}