{
  "type": "Feature",
  "properties": {
    "addr:full":"6190 Main St Arpin WI 54410",
    "addr:housenumber":"6190",
    "addr:postcode":"54410",
    "addr:street":"Main St",
    "iso:country":"US",
    "sg:address":"6190 Main St",
    "sg:city":"Arpin",
    "sg:classifiers":[
        {
            "category":"Government",
            "subcategory":"Office",
            "type":"Public Place"
        }
    ],
    "sg:phone":"+1 715 652 2010",
    "sg:postcode":"54410",
    "sg:province":"WI",
    "sg:tags":[
        "village"
    ],
    "wof:name":"Arpin City Office",
    "wof:placetype":"venue"
},
  "geometry": {"coordinates":[-90.029386,44.54082],"type":"Point"}
}