{
  "type": "Feature",
  "properties": {
    "iso:country":"US",
    "sg:address":"516 Calvary St",
    "sg:city":"Mt Calvary",
    "sg:classifiers":[
        {
            "category":"Banks & Credit Unions",
            "subcategory":"Bank",
            "type":"Services"
        }
    ],
    "sg:phone":"+1 920 753 4171",
    "sg:postcode":"53057",
    "sg:province":"WI",
    "wof:name":"National Exchange Bank & Trust",
    "wof:placetype":"venue"
},
  "geometry": {"coordinates":[-88.241876,43.830708],"type":"Point"}
}