{
  "type": "Feature",
  "properties": {
    "iso:country":"US",
    "sg:address":"814 W Wisconsin Ave",
    "sg:city":"Milwaukee",
    "sg:classifiers":[
        {
            "category":"Restaurant",
            "type":"Food & Drink"
        }
    ],
    "sg:phone":"+1 414 286 2005",
    "sg:postcode":"53233",
    "sg:province":"WI",
    "sg:tags":[
        "eating"
    ],
    "wof:name":"Coffee With A Conscience",
    "wof:placetype":"venue"
},
  "geometry": {"coordinates":[-87.922967,43.038891],"type":"Point"}
}