{
  "type": "Feature",
  "properties": {
    "addr:full":"1207 Josslyn St Oshkosh WI 54902",
    "addr:housenumber":"1207",
    "addr:postcode":"54902",
    "addr:street":"Josslyn St",
    "iso:country":"US",
    "sg:address":"1207 Josslyn St",
    "sg:city":"Oshkosh",
    "sg:classifiers":[
        {
            "category":"Wholesale",
            "subcategory":"Construction Materials",
            "type":"Manufacturing & Wholesale Goods"
        }
    ],
    "sg:phone":"+1 920 231 5510",
    "sg:postcode":"54902",
    "sg:province":"WI",
    "sg:tags":[
        "carpentry",
        "contractor"
    ],
    "wof:name":"Performance Window",
    "wof:placetype":"venue"
},
  "geometry": {"coordinates":[-88.56482200000001,44.032193],"type":"Point"}
}