{
  "type": "Feature",
  "properties": {
    "iso:country":"US",
    "sg:address":"885 River Rd",
    "sg:city":"Columbus",
    "sg:classifiers":[
        {
            "category":"Farming",
            "subcategory":"Dairy Farm",
            "type":"Manufacturing & Wholesale Goods"
        }
    ],
    "sg:phone":"+1 920 623 5618",
    "sg:postcode":"53925",
    "sg:province":"WI",
    "sg:tags":[
        "corn"
    ],
    "wof:name":"Sennview Farms Inc",
    "wof:placetype":"venue"
},
  "geometry": {"coordinates":[-89.009418,43.306818],"type":"Point"}
}