{
  "type": "Feature",
  "properties": {
    "iso:country":"US",
    "sg:address":"4670 State Hwy 64",
    "sg:city":"Peshtigo",
    "sg:classifiers":[
        {
            "category":"Retail",
            "subcategory":"Auto Repair",
            "type":"Services"
        }
    ],
    "sg:phone":"+1 715 789 2043",
    "sg:postcode":"54157",
    "sg:province":"WI",
    "sg:tags":[
        "automotive"
    ],
    "wof:name":"Tri-County Radiator",
    "wof:placetype":"venue"
},
  "geometry": {"coordinates":[-87.837356,45.106612],"type":"Point"}
}