{
  "type": "Feature",
  "properties": {
    "addr:full":"271 N Main St West Bend WI 53095",
    "addr:housenumber":"271",
    "addr:postcode":"53095",
    "addr:street":"N Main St",
    "iso:country":"US",
    "sg:address":"271 N Main St",
    "sg:city":"West Bend",
    "sg:classifiers":[
        {
            "category":"Bars & Pubs",
            "type":"Food & Drink"
        }
    ],
    "sg:phone":"+1 262 306 0209",
    "sg:postcode":"53095",
    "sg:province":"WI",
    "sg:tags":[
        "drinking"
    ],
    "wof:name":"Neuy's Tap",
    "wof:placetype":"venue"
},
  "geometry": {"coordinates":[-88.18370299999999,43.425645],"type":"Point"}
}