{
  "type": "Feature",
  "properties": {
    "addr:full":"9029 W Hawthorne Ave Milwaukee WI 53226",
    "addr:housenumber":"9029",
    "addr:postcode":"53226",
    "addr:street":"W Hawthorne Ave",
    "iso:country":"US",
    "sg:address":"9029 W Hawthorne Ave",
    "sg:city":"Milwaukee",
    "sg:classifiers":[
        {
            "category":"Professional",
            "type":"Services"
        }
    ],
    "sg:phone":"+1 414 771 6911",
    "sg:postcode":"53226",
    "sg:province":"WI",
    "wof:name":"Brochures Plus",
    "wof:placetype":"venue"
},
  "geometry": {"coordinates":[-88.026208,43.031447],"type":"Point"}
}