{
  "type": "Feature",
  "properties": {
    "iso:country":"US",
    "sg:address":"7520 Century Pl",
    "sg:city":"Middleton",
    "sg:classifiers":[
        {
            "category":"Autos & Motor Vehicles",
            "subcategory":"Automobile Sales",
            "type":"Retail Goods"
        }
    ],
    "sg:phone":"+1 608 255 8023",
    "sg:postcode":"53562",
    "sg:province":"WI",
    "sg:tags":[
        "car",
        "dealer"
    ],
    "wof:name":"Middleton Motors Inc",
    "wof:placetype":"venue"
},
  "geometry": {"coordinates":[-89.510101,43.113753],"type":"Point"}
}