{
  "type": "Feature",
  "properties": {
    "iso:country":"US",
    "sg:address":"201 N Iowa St",
    "sg:city":"Dodgeville",
    "sg:classifiers":[
        {
            "category":"Professional",
            "subcategory":"Lawyer & Legal Services",
            "type":"Services"
        }
    ],
    "sg:phone":"+1 608 935 2042",
    "sg:postcode":"53533",
    "sg:province":"WI",
    "sg:tags":[
        "attorney"
    ],
    "wof:name":"Iowa County Family Court Comm",
    "wof:placetype":"venue"
},
  "geometry": {"coordinates":[-90.13027700000001,42.961804],"type":"Point"}
}