{
  "type": "Feature",
  "properties": {
    "iso:country":"US",
    "sg:address":"1927 43rd St",
    "sg:city":"Caledonia",
    "sg:classifiers":[
        {
            "category":"Building & Trades",
            "subcategory":"Construction",
            "type":"Services"
        }
    ],
    "sg:phone":"+1 262 835 0587",
    "sg:postcode":"53108",
    "sg:province":"WI",
    "sg:tags":[
        "concrete",
        "snowplowing",
        "work",
        "contractor"
    ],
    "wof:name":"Thomforde Concrete Inc",
    "wof:placetype":"venue"
},
  "geometry": {"coordinates":[-87.972604,42.808446],"type":"Point"}
}