{
  "type": "Feature",
  "properties": {
    "iso:country":"US",
    "sg:address":"1006 Mary St",
    "sg:city":"Watertown",
    "sg:classifiers":[
        {
            "category":"Shopping",
            "subcategory":"Computers & Home Electronics",
            "type":"Retail Goods"
        }
    ],
    "sg:phone":"+1 920 261 9200",
    "sg:postcode":"53094",
    "sg:province":"WI",
    "sg:tags":[
        "repair"
    ],
    "wof:name":"Elsners T V Service",
    "wof:placetype":"venue"
},
  "geometry": {"coordinates":[-88.71557900000001,43.179534],"type":"Point"}
}