{
  "type": "Feature",
  "properties": {
    "iso:country":"US",
    "sg:address":"8409 US Hwy 14",
    "sg:city":"Evansville",
    "sg:classifiers":[
        {
            "category":"Building & Trades",
            "subcategory":"Cleaning & Sanitation",
            "type":"Services"
        }
    ],
    "sg:phone":"+1 888 381 6000",
    "sg:postcode":"53536",
    "sg:province":"WI",
    "sg:tags":[
        "truck",
        "maintenance"
    ],
    "wof:name":"Kleen Sweep Inc",
    "wof:placetype":"venue"
},
  "geometry": {"coordinates":[-89.15113100000001,42.738541],"type":"Point"}
}