{
  "type": "Feature",
  "properties": {
    "iso:country":"US",
    "sg:address":"203 Lake Ave E",
    "sg:city":"Ladysmith",
    "sg:classifiers":[
        {
            "category":"Restaurant",
            "type":"Food & Drink"
        }
    ],
    "sg:phone":"+1 715 532 6660",
    "sg:postcode":"54848",
    "sg:province":"WI",
    "wof:name":"Eastern Chinese Restaurant",
    "wof:placetype":"venue"
},
  "geometry": {"coordinates":[-91.09860999999999,45.465199],"type":"Point"}
}