{
  "type": "Feature",
  "properties": {
    "addr:full":"6642 Co Rd B Lake Mills WI 53551",
    "addr:housenumber":"6642",
    "addr:postcode":"53551",
    "addr:street":"Co Rd B",
    "iso:country":"US",
    "sg:address":"6642 Co Rd B",
    "sg:city":"Lake Mills",
    "sg:classifiers":[
        {
            "category":"Autos & Motor Vehicles",
            "subcategory":"Automobile Sales",
            "type":"Retail Goods"
        }
    ],
    "sg:phone":"+1 920 988 7870",
    "sg:postcode":"53551",
    "sg:province":"WI",
    "sg:tags":[
        "car",
        "dealer"
    ],
    "wof:name":"Littleone's Auto Ctr",
    "wof:placetype":"venue"
},
  "geometry": {"coordinates":[-88.86471299999999,43.073002],"type":"Point"}
}