{
  "type": "Feature",
  "properties": {
    "iso:country":"US",
    "sg:address":"7524 W Greenfield Ave",
    "sg:city":"Milwaukee",
    "sg:classifiers":[
        {
            "category":"Restaurant",
            "type":"Food & Drink"
        }
    ],
    "sg:menulink":"http://www.allmenus.com/wi/west-allis/139304-quiznos-sub/menu/",
    "sg:phone":"+1 414 256 7849",
    "sg:postcode":"53214",
    "sg:province":"WI",
    "sg:tags":[
        "wrap",
        "american",
        "sandwich"
    ],
    "wof:name":"Quiznos Sub",
    "wof:placetype":"venue"
},
  "geometry": {"coordinates":[-88.00666,43.016639],"type":"Point"}
}