{
  "type": "Feature",
  "properties": {
    "iso:country":"US",
    "sg:address":"3487 Co Hwy D",
    "sg:city":"West Bend",
    "sg:classifiers":[
        {
            "category":"Shopping",
            "subcategory":"Clothing, Apparel, & Fashions",
            "type":"Retail Goods"
        }
    ],
    "sg:phone":"+1 262 334 2240",
    "sg:postcode":"53090",
    "sg:province":"WI",
    "sg:tags":[
        "western"
    ],
    "wof:name":"South Forty Western Wear",
    "wof:placetype":"venue"
},
  "geometry": {"coordinates":[-88.215379,43.455623],"type":"Point"}
}