{
  "type": "Feature",
  "properties": {
    "iso:country":"US",
    "sg:address":"477 S Peck Ave",
    "sg:city":"Peshtigo",
    "sg:classifiers":[
        {
            "category":"Manufacturing",
            "subcategory":"Wood Products",
            "type":"Manufacturing & Wholesale Goods"
        }
    ],
    "sg:phone":"+1 715 582 4544",
    "sg:postcode":"54157",
    "sg:province":"WI",
    "sg:website":"www.sentinelstructures.com",
    "wof:name":"Sentinel Structures Inc",
    "wof:placetype":"venue"
},
  "geometry": {"coordinates":[-87.754487,45.046577],"type":"Point"}
}