{
  "type": "Feature",
  "properties": {
    "iso:country":"US",
    "sg:address":"819 17th Ave",
    "sg:city":"Bloomer",
    "sg:classifiers":[
        {
            "category":"Building & Trades",
            "subcategory":"Construction",
            "type":"Services"
        }
    ],
    "sg:phone":"+1 715 568 4152",
    "sg:postcode":"54724",
    "sg:province":"WI",
    "sg:tags":[
        "siding",
        "contractor"
    ],
    "wof:name":"Proside",
    "wof:placetype":"venue"
},
  "geometry": {"coordinates":[-91.48296999999999,45.099761],"type":"Point"}
}