{
  "type": "Feature",
  "properties": {
    "iso:country":"US",
    "sg:address":"13000 W Custer Ave",
    "sg:city":"Butler",
    "sg:classifiers":[
        {
            "category":"Manufacturing",
            "subcategory":"Building Materials",
            "type":"Manufacturing & Wholesale Goods"
        }
    ],
    "sg:phone":"+1 262 781 3990",
    "sg:postcode":"53007",
    "sg:province":"WI",
    "sg:tags":[
        "wood",
        "mfg"
    ],
    "wof:name":"Precision Woodwork Inc",
    "wof:placetype":"venue"
},
  "geometry": {"coordinates":[-88.071264,43.115128],"type":"Point"}
}