{
  "type": "Feature",
  "properties": {
    "iso:country":"US",
    "sg:address":"4301 Robertson Rd",
    "sg:city":"Madison",
    "sg:classifiers":[
        {
            "category":"Manufacturing",
            "subcategory":"Glass & Minerals",
            "type":"Manufacturing & Wholesale Goods"
        }
    ],
    "sg:phone":"+1 608 246 8803",
    "sg:postcode":"53714",
    "sg:province":"WI",
    "sg:tags":[
        "granite",
        "product"
    ],
    "sg:website":"www.quarrastone.com",
    "wof:name":"Quarra Stone LLC",
    "wof:placetype":"venue"
},
  "geometry": {"coordinates":[-89.308104,43.092149],"type":"Point"}
}