{
  "type": "Feature",
  "properties": {
    "iso:country":"US",
    "sg:address":"3999 Douglas Ave",
    "sg:city":"Racine",
    "sg:classifiers":[
        {
            "category":"Restaurant",
            "type":"Food & Drink"
        }
    ],
    "sg:menulink":"http://www.allmenus.com/wi/racine/89055-cousins-subs/menu/",
    "sg:phone":"+1 262 681 1101",
    "sg:postcode":"53402",
    "sg:province":"WI",
    "sg:tags":[
        "wrap",
        "american",
        "sandwich"
    ],
    "wof:name":"Cousin's Subs",
    "wof:placetype":"venue"
},
  "geometry": {"coordinates":[-87.802744,42.769719],"type":"Point"}
}