{
  "type": "Feature",
  "properties": {
    "iso:country":"US",
    "sg:address":"1471 Hillside Rd",
    "sg:city":"Cambridge",
    "sg:phone":"+1 608 884 6755",
    "sg:postcode":"53523",
    "sg:province":"WI",
    "sg:tags":[
        "farm",
        "corn",
        "soybean"
    ],
    "wof:name":"Scott Mickelson",
    "wof:placetype":"venue"
},
  "geometry": {"coordinates":[-89.042911,42.934932],"type":"Point"}
}