{
  "type": "Feature",
  "properties": {
    "iso:country":"US",
    "sg:address":"11585 Co Rd V",
    "sg:city":"Lodi",
    "sg:classifiers":[
        {
            "category":"Travel",
            "subcategory":"Hotels & Motels",
            "type":"Entertainment"
        }
    ],
    "sg:phone":"+1 608 592 5599",
    "sg:postcode":"53555",
    "sg:province":"WI",
    "sg:tags":[
        "operation"
    ],
    "wof:name":"Bridge Motel LLC",
    "wof:placetype":"venue"
},
  "geometry": {"coordinates":[-89.576199,43.358918],"type":"Point"}
}