{
  "type": "Feature",
  "properties": {
    "addr:full":"219 N Milwaukee St Milwaukee WI 53202",
    "addr:housenumber":"219",
    "addr:postcode":"53202",
    "addr:street":"N Milwaukee St",
    "iso:country":"US",
    "sg:address":"219 N Milwaukee St",
    "sg:city":"Milwaukee",
    "sg:classifiers":[
        {
            "category":"Professional",
            "subcategory":"Management & Consulting",
            "type":"Services"
        }
    ],
    "sg:phone":"+1 414 274 6420",
    "sg:postcode":"53202",
    "sg:province":"WI",
    "wof:name":"Malek Ej & Associates Inc",
    "wof:placetype":"venue"
},
  "geometry": {"coordinates":[-87.90602,43.033691],"type":"Point"}
}