{
  "type": "Feature",
  "properties": {
    "iso:country":"US",
    "sg:address":"167 Bank St",
    "sg:city":"Waukesha",
    "sg:classifiers":[
        {
            "category":"Manufacturing",
            "subcategory":"Printing",
            "type":"Manufacturing & Wholesale Goods"
        }
    ],
    "sg:phone":"+1 262 549 5511",
    "sg:postcode":"53188",
    "sg:province":"WI",
    "sg:tags":[
        "printer"
    ],
    "wof:name":"PIP Printing",
    "wof:placetype":"venue"
},
  "geometry": {"coordinates":[-88.230445,43.013479],"type":"Point"}
}