{
  "type": "Feature",
  "properties": {
    "iso:country":"US",
    "sg:address":"200 Digital Dr",
    "sg:city":"Clear Lake",
    "sg:classifiers":[
        {
            "category":"Travel",
            "subcategory":"Hotels & Motels",
            "type":"Entertainment"
        }
    ],
    "sg:phone":"+1 715 263 4320",
    "sg:postcode":"54005",
    "sg:province":"WI",
    "sg:tags":[
        "operation"
    ],
    "wof:name":"Clear Lake Motel & Fitness CNT",
    "wof:placetype":"venue"
},
  "geometry": {"coordinates":[-92.282685,45.245992],"type":"Point"}
}