{
  "type": "Feature",
  "properties": {
    "iso:country":"US",
    "sg:address":"1508 Rapids Dr",
    "sg:city":"Racine",
    "sg:classifiers":[
        {
            "category":"Retail",
            "subcategory":"Car Wash",
            "type":"Services"
        }
    ],
    "sg:phone":"+1 262 632 2062",
    "sg:postcode":"53404",
    "sg:province":"WI",
    "sg:tags":[
        "carwash"
    ],
    "wof:name":"National Pride Car Wash",
    "wof:placetype":"venue"
},
  "geometry": {"coordinates":[-87.80018,42.744738],"type":"Point"}
}