{
  "type": "Feature",
  "properties": {
    "iso:country":"US",
    "sg:address":"3200 Cherry Hill Dr",
    "sg:city":"Brookfield",
    "sg:classifiers":[
        {
            "category":"Organizations",
            "subcategory":"Community Association",
            "type":"Services"
        }
    ],
    "sg:phone":"+1 262 783 7839",
    "sg:postcode":"53005",
    "sg:province":"WI",
    "wof:name":"All In Order LLC",
    "wof:placetype":"venue"
},
  "geometry": {"coordinates":[-88.11982,43.077575],"type":"Point"}
}