{
  "type": "Feature",
  "properties": {
    "iso:country":"US",
    "sg:address":"5504 Rib Mountain Dr",
    "sg:city":"Wausau",
    "sg:classifiers":[
        {
            "category":"Shopping",
            "subcategory":"Hobbies, Toys, & Games",
            "type":"Retail Goods"
        }
    ],
    "sg:phone":"+1 715 359 5964",
    "sg:postcode":"54401",
    "sg:province":"WI",
    "sg:tags":[
        "equipment",
        "ceramic",
        "supply"
    ],
    "wof:name":"Roselyn's Ceramics",
    "wof:placetype":"venue"
},
  "geometry": {"coordinates":[-89.65327499999999,44.906155],"type":"Point"}
}