{
  "type": "Feature",
  "properties": {
    "addr:full":"6242 S Packard Ave Cudahy WI 53110",
    "addr:housenumber":"6242",
    "addr:postcode":"53110",
    "addr:street":"S Packard Ave",
    "iso:country":"US",
    "sg:address":"6242 S Packard Ave",
    "sg:city":"Cudahy",
    "sg:classifiers":[
        {
            "category":"Retail",
            "subcategory":"Veterinary Services",
            "type":"Services"
        }
    ],
    "sg:phone":"+1 414 762 5650",
    "sg:postcode":"53110",
    "sg:province":"WI",
    "wof:name":"Cudahy Veterinary Clinic",
    "wof:placetype":"venue"
},
  "geometry": {"coordinates":[-87.860831,42.93237],"type":"Point"}
}