{
  "type": "Feature",
  "properties": {
    "iso:country":"US",
    "sg:address":"1406 5th Ave S",
    "sg:city":"La Crosse",
    "sg:classifiers":[
        {
            "category":"Recreation",
            "type":"Entertainment"
        }
    ],
    "sg:phone":"+1 608 784 2565",
    "sg:postcode":"54601",
    "sg:province":"WI",
    "sg:tags":[
        "amusement"
    ],
    "sg:website":"www.loriknappinc.com",
    "wof:name":"LKI LA Crosse",
    "wof:placetype":"venue"
},
  "geometry": {"coordinates":[-91.250347,43.79789],"type":"Point"}
}