{
  "type": "Feature",
  "properties": {
    "iso:country":"US",
    "sg:address":"165 Gebhardt Rd",
    "sg:city":"Black River Falls",
    "sg:classifiers":[
        {
            "category":"Professional",
            "type":"Services"
        }
    ],
    "sg:phone":"+1 715 284 0784",
    "sg:postcode":"54615",
    "sg:province":"WI",
    "wof:name":"Stuart Taylor",
    "wof:placetype":"venue"
},
  "geometry": {"coordinates":[-90.841953,44.28766],"type":"Point"}
}