{
  "type": "Feature",
  "properties": {
    "addr:full":"2195 1st Ave Grafton WI 53024",
    "addr:housenumber":"2195",
    "addr:postcode":"53024",
    "addr:street":"1St Ave",
    "iso:country":"US",
    "sg:address":"2195 1st Ave",
    "sg:city":"Grafton",
    "sg:classifiers":[
        {
            "category":"Banks & Credit Unions",
            "subcategory":"Bank",
            "type":"Services"
        }
    ],
    "sg:phone":"+1 262 377 0212",
    "sg:postcode":"53024",
    "sg:province":"WI",
    "wof:name":"West Bend Savings Bank",
    "wof:placetype":"venue"
},
  "geometry": {"coordinates":[-87.9646,43.302299],"type":"Point"}
}