{
  "type": "Feature",
  "properties": {
    "addr:full":"7108 State Hwy 38 Caledonia WI 53108",
    "addr:housenumber":"7108",
    "addr:postcode":"53108",
    "addr:street":"State Hwy 38",
    "iso:country":"US",
    "sg:address":"7108 State Hwy 38",
    "sg:city":"Caledonia",
    "sg:classifiers":[
        {
            "category":"Building & Trades",
            "subcategory":"Landscaping Services",
            "type":"Services"
        }
    ],
    "sg:phone":"+1 262 835 7770",
    "sg:postcode":"53108",
    "sg:province":"WI",
    "sg:tags":[
        "stone",
        "landscape",
        "contractor"
    ],
    "wof:name":"Ray Hintz Inc",
    "wof:placetype":"venue"
},
  "geometry": {"coordinates":[-87.91459399999999,42.818251],"type":"Point"}
}