{
  "type": "Feature",
  "properties": {
    "iso:country":"US",
    "sg:address":"231 E Towne Mall",
    "sg:city":"Madison",
    "sg:classifiers":[
        {
            "category":"Restaurant",
            "type":"Food & Drink"
        }
    ],
    "sg:phone":"+1 608 246 4040",
    "sg:postcode":"53704",
    "sg:province":"WI",
    "wof:name":"Mc Donald's",
    "wof:placetype":"venue"
},
  "geometry": {"coordinates":[-89.304187,43.128254],"type":"Point"}
}