{
  "type": "Feature",
  "properties": {
    "iso:country":"US",
    "sg:address":"704 Sletten St",
    "sg:city":"Colfax",
    "sg:classifiers":[
        {
            "category":"Social Services",
            "subcategory":"Child Care",
            "type":"Services"
        }
    ],
    "sg:phone":"+1 715 962 3891",
    "sg:postcode":"54730",
    "sg:province":"WI",
    "sg:tags":[
        "kindergarten",
        "academic",
        "school"
    ],
    "wof:name":"Cesa Headstart",
    "wof:placetype":"venue"
},
  "geometry": {"coordinates":[-91.715987,45.002784],"type":"Point"}
}