{
  "type": "Feature",
  "properties": {
    "iso:country":"US",
    "sg:address":"1719 N 4th St",
    "sg:city":"Milwaukee",
    "sg:classifiers":[
        {
            "category":"Wholesale",
            "subcategory":"Chemicals & Plastics",
            "type":"Manufacturing & Wholesale Goods"
        }
    ],
    "sg:phone":"+1 414 445 8405",
    "sg:postcode":"53212",
    "sg:province":"WI",
    "sg:tags":[
        "gas",
        "carbonic"
    ],
    "wof:name":"Badger Carbonic Distr",
    "wof:placetype":"venue"
},
  "geometry": {"coordinates":[-87.915836,43.053611],"type":"Point"}
}