{
  "type": "Feature",
  "properties": {
    "iso:country":"US",
    "sg:address":"1030 Division St",
    "sg:city":"Mauston",
    "sg:classifiers":[
        {
            "category":"Social Services",
            "subcategory":"Adult Care",
            "type":"Services"
        }
    ],
    "sg:phone":"+1 608 847 2377",
    "sg:postcode":"53948",
    "sg:province":"WI",
    "sg:tags":[
        "residential"
    ],
    "wof:name":"Terrace Heights Retirement",
    "wof:placetype":"venue"
},
  "geometry": {"coordinates":[-90.076736,43.784025],"type":"Point"}
}