{
  "type": "Feature",
  "properties": {
    "iso:country":"US",
    "sg:address":"346 N Main St",
    "sg:city":"Fond Du Lac",
    "sg:classifiers":[
        {
            "category":"Banks & Credit Unions",
            "subcategory":"Bank",
            "type":"Services"
        }
    ],
    "sg:phone":"+1 920 921 7700",
    "sg:postcode":"54935",
    "sg:province":"WI",
    "wof:name":"National Exchange Bank & Trust",
    "wof:placetype":"venue"
},
  "geometry": {"coordinates":[-88.447014,43.787885],"type":"Point"}
}