{
  "type": "Feature",
  "properties": {
    "iso:country":"US",
    "sg:address":"882 Bain Rd",
    "sg:city":"De Pere",
    "sg:classifiers":[
        {
            "category":"Farming",
            "subcategory":"Livestock Farm",
            "type":"Manufacturing & Wholesale Goods"
        }
    ],
    "sg:phone":"+1 920 687 0616",
    "sg:postcode":"54115",
    "sg:province":"WI",
    "sg:tags":[
        "animal",
        "general"
    ],
    "wof:name":"Jacobs Brothers LLC",
    "wof:placetype":"venue"
},
  "geometry": {"coordinates":[-88.206767,44.429778],"type":"Point"}
}