{
  "type": "Feature",
  "properties": {
    "iso:country":"US",
    "sg:address":"33215 Ski Hill Rd",
    "sg:city":"Bayfield",
    "sg:classifiers":[
        {
            "category":"Retail",
            "subcategory":"Repair Shop",
            "type":"Services"
        }
    ],
    "sg:phone":"+1 715 779 5858",
    "sg:postcode":"54814",
    "sg:province":"WI",
    "sg:tags":[
        "welding"
    ],
    "wof:name":"Dehn Repair Service",
    "wof:placetype":"venue"
},
  "geometry": {"coordinates":[-90.870779,46.781385],"type":"Point"}
}