{
  "type": "Feature",
  "properties": {
    "iso:country":"US",
    "sg:address":"1547 N Jackson St",
    "sg:city":"Milwaukee",
    "sg:classifiers":[
        {
            "category":"Restaurant",
            "type":"Food & Drink"
        }
    ],
    "sg:phone":"+1 414 276 9608",
    "sg:postcode":"53202",
    "sg:province":"WI",
    "sg:tags":[
        "dining",
        "fine"
    ],
    "wof:name":"Sanfords",
    "wof:placetype":"venue"
},
  "geometry": {"coordinates":[-87.90477300000001,43.050002],"type":"Point"}
}