{
  "type": "Feature",
  "properties": {
    "addr:full":"230 Airport Hanger Dr Wisconsin Rapids WI 54494",
    "addr:housenumber":"230",
    "addr:postcode":"54494",
    "addr:street":"Airport Hanger Dr",
    "iso:country":"US",
    "sg:address":"230 Airport Hanger Dr",
    "sg:city":"Wisconsin Rapids",
    "sg:classifiers":[
        {
            "category":"Professional",
            "subcategory":"Business Services",
            "type":"Services"
        }
    ],
    "sg:phone":"+1 715 421 0962",
    "sg:postcode":"54494",
    "sg:province":"WI",
    "wof:name":"Strub Enterprises Inc",
    "wof:placetype":"venue"
},
  "geometry": {"coordinates":[-89.829826,44.360309],"type":"Point"}
}