{
  "type": "Feature",
  "properties": {
    "iso:country":"US",
    "sg:address":"885 Western Ave",
    "sg:city":"Fond Du Lac",
    "sg:classifiers":[
        {
            "category":"Wholesale",
            "subcategory":"Electrical",
            "type":"Manufacturing & Wholesale Goods"
        }
    ],
    "sg:phone":"+1 920 923 3653",
    "sg:postcode":"54935",
    "sg:province":"WI",
    "sg:tags":[
        "fire",
        "equipment",
        "protection"
    ],
    "wof:name":"Grunau Fire Protection Inc",
    "wof:placetype":"venue"
},
  "geometry": {"coordinates":[-88.47591799999999,43.773514],"type":"Point"}
}