{
  "type": "Feature",
  "properties": {
    "iso:country":"US",
    "sg:address":"2701 Viebahn St",
    "sg:city":"Manitowoc",
    "sg:classifiers":[
        {
            "category":"Real Estate",
            "subcategory":"Real Estate Operator",
            "type":"Services"
        }
    ],
    "sg:phone":"+1 920 652 9890",
    "sg:postcode":"54220",
    "sg:province":"WI",
    "sg:tags":[
        "apartment"
    ],
    "wof:name":"Viebahn Meadows Greco Prprts",
    "wof:placetype":"venue"
},
  "geometry": {"coordinates":[-87.682681,44.066415],"type":"Point"}
}