{
  "type": "Feature",
  "properties": {
    "iso:country":"US",
    "sg:address":"1376 Kanturk Ln",
    "sg:city":"Hartford",
    "sg:classifiers":[
        {
            "category":"Building & Trades",
            "subcategory":"Cleaning & Sanitation",
            "type":"Services"
        }
    ],
    "sg:phone":"+1 262 673 6493",
    "sg:postcode":"53027",
    "sg:province":"WI",
    "sg:tags":[
        "maintenance"
    ],
    "wof:name":"Rw Services of Hartford LLC",
    "wof:placetype":"venue"
},
  "geometry": {"coordinates":[-88.350617,43.239006],"type":"Point"}
}