{
  "type": "Feature",
  "properties": {
    "iso:country":"US",
    "sg:address":"900 Windsor St",
    "sg:city":"Sun Prairie",
    "sg:classifiers":[
        {
            "category":"Professional",
            "subcategory":"Lawyer & Legal Services",
            "type":"Services"
        }
    ],
    "sg:phone":"+1 608 837 7616",
    "sg:postcode":"53590",
    "sg:province":"WI",
    "sg:tags":[
        "attorney"
    ],
    "wof:name":"Stafford Rosenbaum",
    "wof:placetype":"venue"
},
  "geometry": {"coordinates":[-89.227857,43.187554],"type":"Point"}
}