{
  "type": "Feature",
  "properties": {
    "iso:country":"US",
    "sg:address":"1053 E Green Bay St",
    "sg:city":"Shawano",
    "sg:classifiers":[
        {
            "category":"Personal",
            "subcategory":"Beauty Salon",
            "type":"Services"
        }
    ],
    "sg:phone":"+1 715 524 4000",
    "sg:postcode":"54166",
    "sg:province":"WI",
    "wof:name":"Ebony & Ivory Gallery-Hair",
    "wof:placetype":"venue"
},
  "geometry": {"coordinates":[-88.590973,44.782211],"type":"Point"}
}