{
  "type": "Feature",
  "properties": {
    "iso:country":"US",
    "sg:address":"4527 Cooperstown Rd",
    "sg:city":"Denmark",
    "sg:classifiers":[
        {
            "category":"Farming",
            "subcategory":"Dairy Farm",
            "type":"Manufacturing & Wholesale Goods"
        }
    ],
    "sg:phone":"+1 920 864 2267",
    "sg:postcode":"54208",
    "sg:province":"WI",
    "wof:name":"Krahn Dairy Farm",
    "wof:placetype":"venue"
},
  "geometry": {"coordinates":[-87.900143,44.327745],"type":"Point"}
}