{
  "type": "Feature",
  "properties": {
    "iso:country":"US",
    "sg:address":"4981 Komprood Rd",
    "sg:city":"Gratiot",
    "sg:phone":"+1 608 922 6226",
    "sg:postcode":"53541",
    "sg:province":"WI",
    "sg:tags":[
        "farm",
        "field",
        "corn",
        "crop"
    ],
    "wof:name":"Gene Komprood",
    "wof:placetype":"venue"
},
  "geometry": {"coordinates":[-89.99048999999999,42.557908],"type":"Point"}
}