{
  "type": "Feature",
  "properties": {
    "addr:full":"5238 S 13th St Milwaukee WI 53221",
    "addr:housenumber":"5238",
    "addr:postcode":"53221",
    "addr:street":"S 13Th St",
    "iso:country":"US",
    "sg:address":"5238 S 13th St",
    "sg:city":"Milwaukee",
    "sg:classifiers":[
        {
            "category":"Manufacturing",
            "subcategory":"Metals",
            "type":"Manufacturing & Wholesale Goods"
        }
    ],
    "sg:phone":"+1 414 282 6380",
    "sg:postcode":"53221",
    "sg:province":"WI",
    "sg:tags":[
        "fab",
        "repair",
        "mfg",
        "wire",
        "welding"
    ],
    "wof:name":"An-Kor Plating Rack Co",
    "wof:placetype":"venue"
},
  "geometry": {"coordinates":[-87.92939,42.946566],"type":"Point"}
}