{
  "type": "Feature",
  "properties": {
    "iso:country":"US",
    "sg:address":"930 N 6th St",
    "sg:city":"Sheboygan",
    "sg:classifiers":[
        {
            "category":"Health Services",
            "subcategory":"Nursing And Care Facility",
            "type":"Services"
        }
    ],
    "sg:phone":"+1 920 458 2137",
    "sg:postcode":"53081",
    "sg:province":"WI",
    "sg:tags":[
        "home",
        "retirement",
        "community"
    ],
    "wof:name":"Sheboygan Retirement Home",
    "wof:placetype":"venue"
},
  "geometry": {"coordinates":[-87.70967899999999,43.754904],"type":"Point"}
}