{
  "type": "Feature",
  "properties": {
    "iso:country":"US",
    "sg:address":"111 N 44th Ave",
    "sg:city":"Wausau",
    "sg:classifiers":[
        {
            "category":"Real Estate",
            "subcategory":"Real Estate Operator",
            "type":"Services"
        }
    ],
    "sg:phone":"+1 715 842 4642",
    "sg:postcode":"54401",
    "sg:province":"WI",
    "sg:tags":[
        "building",
        "nonresidential"
    ],
    "wof:name":"Gerum Properties",
    "wof:placetype":"venue"
},
  "geometry": {"coordinates":[-89.691266,44.962393],"type":"Point"}
}