{
  "type": "Feature",
  "properties": {
    "iso:country":"US",
    "sg:address":"2123 W Kendall Ave",
    "sg:city":"Milwaukee",
    "sg:classifiers":[
        {
            "category":"Bars & Pubs",
            "type":"Food & Drink"
        }
    ],
    "sg:phone":"+1 414 228 8225",
    "sg:postcode":"53209",
    "sg:province":"WI",
    "sg:tags":[
        "drinking"
    ],
    "wof:name":"Louies Ancient Chinese Tavern",
    "wof:placetype":"venue"
},
  "geometry": {"coordinates":[-87.939927,43.11999],"type":"Point"}
}