{
  "type": "Feature",
  "properties": {
    "iso:country":"US",
    "sg:address":"1805 Blue Ridge Trl",
    "sg:city":"Waunakee",
    "sg:classifiers":[
        {
            "category":"Building & Trades",
            "subcategory":"Construction",
            "type":"Services"
        }
    ],
    "sg:phone":"+1 608 849 7653",
    "sg:postcode":"53597",
    "sg:province":"WI",
    "sg:tags":[
        "house"
    ],
    "wof:name":"Torger and Sons",
    "wof:placetype":"venue"
},
  "geometry": {"coordinates":[-89.434169,43.17303],"type":"Point"}
}