{
  "type": "Feature",
  "properties": {
    "iso:country":"US",
    "sg:address":"6999 Summit Ln",
    "sg:city":"Custer",
    "sg:classifiers":[
        {
            "category":"Arts & Performance",
            "subcategory":"Theater",
            "type":"Entertainment"
        }
    ],
    "sg:phone":"+1 715 592 4528",
    "sg:postcode":"54423",
    "sg:province":"WI",
    "sg:tags":[
        "group"
    ],
    "wof:name":"Prototype Band",
    "wof:placetype":"venue"
},
  "geometry": {"coordinates":[-89.43487500000001,44.519555],"type":"Point"}
}