{
  "type": "Feature",
  "properties": {
    "addr:full":"5602 W Forest Home Ave Milwaukee WI 53220",
    "addr:housenumber":"5602",
    "addr:postcode":"53220",
    "addr:street":"W Forest Home Ave",
    "iso:country":"US",
    "sg:address":"5602 W Forest Home Ave",
    "sg:city":"Milwaukee",
    "sg:classifiers":[
        {
            "category":"Shopping",
            "subcategory":"Jewelry",
            "type":"Retail Goods"
        },
        {
            "category":"Retail",
            "subcategory":"Repair Shop",
            "type":"Services"
        }
    ],
    "sg:phone":"+1 414 321 5326",
    "sg:postcode":"53220",
    "sg:province":"WI",
    "sg:tags":[
        "clock"
    ],
    "wof:name":"Seisdedos' Clock Repair",
    "wof:placetype":"venue"
},
  "geometry": {"coordinates":[-87.984489,42.979069],"type":"Point"}
}