{
  "type": "Feature",
  "properties": {
    "iso:country":"US",
    "sg:address":"633 Progress Dr",
    "sg:city":"Hartland",
    "sg:classifiers":[
        {
            "category":"Professional",
            "type":"Services"
        }
    ],
    "sg:phone":"+1 262 367 7633",
    "sg:postcode":"53029",
    "sg:province":"WI",
    "wof:name":"CSI",
    "wof:placetype":"venue"
},
  "geometry": {"coordinates":[-88.357326,43.093067],"type":"Point"}
}