{
  "type": "Feature",
  "properties": {
    "addr:full":"5237 Verona Rd Fitchburg WI 53711",
    "addr:housenumber":"5237",
    "addr:postcode":"53711",
    "addr:street":"Verona Rd",
    "iso:country":"US",
    "sg:address":"5237 Verona Rd",
    "sg:city":"Fitchburg",
    "sg:classifiers":[
        {
            "category":"Shopping",
            "subcategory":"Clothing, Apparel, & Fashions",
            "type":"Retail Goods"
        }
    ],
    "sg:phone":"+1 608 271 1042",
    "sg:postcode":"53711",
    "sg:province":"WI",
    "sg:tags":[
        "tuxedo"
    ],
    "sg:website":"www.nedrebos.com",
    "wof:name":"Nedrebo's Formal Wear Inc",
    "wof:placetype":"venue"
},
  "geometry": {"coordinates":[-89.470001,43.021652],"type":"Point"}
}