{
  "type": "Feature",
  "properties": {
    "iso:country":"US",
    "sg:address":"2334 Co Rd K",
    "sg:city":"Rhinelander",
    "sg:classifiers":[
        {
            "category":"Building & Trades",
            "subcategory":"Construction",
            "type":"Services"
        }
    ],
    "sg:phone":"+1 715 362 5074",
    "sg:postcode":"54501",
    "sg:province":"WI",
    "sg:tags":[
        "contractor"
    ],
    "wof:name":"Detienne Masonry Inc",
    "wof:placetype":"venue"
},
  "geometry": {"coordinates":[-89.445636,45.645008],"type":"Point"}
}