{
  "type": "Feature",
  "properties": {
    "iso:country":"US",
    "sg:address":"1322 W Towne Square Rd",
    "sg:city":"Mequon",
    "sg:classifiers":[
        {
            "category":"Recreation",
            "type":"Entertainment"
        }
    ],
    "sg:phone":"+1 262 241 8796",
    "sg:postcode":"53092",
    "sg:province":"WI",
    "sg:tags":[
        "instruction",
        "yoga"
    ],
    "wof:name":"Feel Your Best Yoga",
    "wof:placetype":"venue"
},
  "geometry": {"coordinates":[-87.92471399999999,43.218187],"type":"Point"}
}