{
  "type": "Feature",
  "properties": {
    "iso:country":"US",
    "sg:address":"23527 Covered Bridge Rd",
    "sg:city":"Richland Center",
    "sg:classifiers":[
        {
            "category":"Arts & Performance",
            "subcategory":"Theater",
            "type":"Entertainment"
        }
    ],
    "sg:phone":"+1 608 647 7187",
    "sg:postcode":"53581",
    "sg:province":"WI",
    "sg:tags":[
        "live",
        "music"
    ],
    "wof:name":"Horizon Entertainment",
    "wof:placetype":"venue"
},
  "geometry": {"coordinates":[-90.421621,43.356847],"type":"Point"}
}