{
  "type": "Feature",
  "properties": {
    "iso:country":"US",
    "sg:address":"5825 State Rd 11",
    "sg:city":"Elkhorn",
    "sg:classifiers":[
        {
            "category":"Home & Garden",
            "subcategory":"Building Materials",
            "type":"Retail Goods"
        }
    ],
    "sg:phone":"+1 262 723 4280",
    "sg:postcode":"53121",
    "sg:province":"WI",
    "sg:tags":[
        "lumber"
    ],
    "wof:name":"United Building Center",
    "wof:placetype":"venue"
},
  "geometry": {"coordinates":[-88.586768,42.657808],"type":"Point"}
}