{
  "type": "Feature",
  "properties": {
    "iso:country":"US",
    "sg:address":"14508 Horseshoe Lake Rd",
    "sg:city":"Weyerhaeuser",
    "sg:classifiers":[
        {
            "category":"Farming",
            "subcategory":"Livestock Farm",
            "type":"Manufacturing & Wholesale Goods"
        }
    ],
    "sg:phone":"+1 715 353 3068",
    "sg:postcode":"54895",
    "sg:province":"WI",
    "sg:tags":[
        "beef",
        "feedlot",
        "cattle"
    ],
    "wof:name":"Lou Breezee",
    "wof:placetype":"venue"
},
  "geometry": {"coordinates":[-91.41982,45.364457],"type":"Point"}
}