{
  "type": "Feature",
  "properties": {
    "addr:full":"20720 Watertown Rd Waukesha WI 53186",
    "addr:postcode":"20720;53186",
    "addr:street":"Watertown Rd",
    "iso:country":"US",
    "sg:address":"20720 Watertown Rd",
    "sg:city":"Waukesha",
    "sg:classifiers":[
        {
            "category":"Social Services",
            "type":"Services"
        }
    ],
    "sg:phone":"+1 262 789 7610",
    "sg:postcode":"53186",
    "sg:province":"WI",
    "sg:tags":[
        "counselor",
        "marriage",
        "family"
    ],
    "wof:name":"Gerri Leenhouts",
    "wof:placetype":"venue"
},
  "geometry": {"coordinates":[-88.170976,43.038086],"type":"Point"}
}