{
  "type": "Feature",
  "properties": {
    "iso:country":"US",
    "sg:address":"22090 US Hwy 14",
    "sg:city":"Richland Center",
    "sg:classifiers":[
        {
            "category":"Autos & Motor Vehicles",
            "subcategory":"Auto Supplies",
            "type":"Retail Goods"
        }
    ],
    "sg:phone":"+1 608 647 4444",
    "sg:postcode":"53581",
    "sg:province":"WI",
    "sg:tags":[
        "automobile",
        "used",
        "automotive"
    ],
    "wof:name":"Burke Tire & Auto",
    "wof:placetype":"venue"
},
  "geometry": {"coordinates":[-90.428426,43.348831],"type":"Point"}
}