{
  "type": "Feature",
  "properties": {
    "addr:full":"7496 Co Rd J Beldenville WI 54003",
    "addr:housenumber":"7496",
    "addr:postcode":"54003",
    "addr:street":"Co Rd;Beldenville",
    "iso:country":"US",
    "sg:address":"7496 Co Rd J",
    "sg:city":"Beldenville",
    "sg:phone":"+1 715 273 4866",
    "sg:postcode":"54003",
    "sg:province":"WI",
    "sg:tags":[
        "limestone",
        "quarry",
        "farm",
        "corn",
        "seed",
        "dealership",
        "grave"
    ],
    "wof:name":"Knutson Brothers",
    "wof:placetype":"venue"
},
  "geometry": {"coordinates":[-92.45471499999999,44.808857],"type":"Point"}
}