{
  "type": "Feature",
  "properties": {
    "iso:country":"US",
    "sg:address":"228 Carroll St",
    "sg:city":"Random Lake",
    "sg:classifiers":[
        {
            "category":"Building & Trades",
            "subcategory":"Construction",
            "type":"Services"
        }
    ],
    "sg:phone":"+1 920 994 8107",
    "sg:postcode":"53075",
    "sg:province":"WI",
    "sg:tags":[
        "hanging",
        "contractor"
    ],
    "wof:name":"Premier Painting & Finishing",
    "wof:placetype":"venue"
},
  "geometry": {"coordinates":[-87.961906,43.551258],"type":"Point"}
}