{
  "type": "Feature",
  "properties": {
    "iso:country":"US",
    "sg:address":"760 Bellevue St",
    "sg:city":"Green Bay",
    "sg:classifiers":[
        {
            "category":"Bars & Pubs",
            "type":"Food & Drink"
        }
    ],
    "sg:phone":"+1 920 465 1454",
    "sg:postcode":"54302",
    "sg:province":"WI",
    "sg:tags":[
        "tavern"
    ],
    "wof:name":"Capones Saloon",
    "wof:placetype":"venue"
},
  "geometry": {"coordinates":[-87.99205499999999,44.494893],"type":"Point"}
}