{
  "type": "Feature",
  "properties": {
    "iso:country":"US",
    "sg:address":"3909 Badger Rd",
    "sg:city":"Kewaskum",
    "sg:classifiers":[
        {
            "category":"Building & Trades",
            "subcategory":"Construction",
            "type":"Services"
        }
    ],
    "sg:phone":"+1 262 626 8883",
    "sg:postcode":"53040",
    "sg:province":"WI",
    "sg:tags":[
        "carpentry",
        "contractor"
    ],
    "wof:name":"Roger Kutz",
    "wof:placetype":"venue"
},
  "geometry": {"coordinates":[-88.231986,43.49908],"type":"Point"}
}