{
  "type": "Feature",
  "properties": {
    "iso:country":"US",
    "sg:address":"4435 S 14th St",
    "sg:city":"Milwaukee",
    "sg:classifiers":[
        {
            "category":"Building & Trades",
            "subcategory":"Construction",
            "type":"Services"
        }
    ],
    "sg:phone":"+1 414 331 5695",
    "sg:postcode":"53221",
    "sg:province":"WI",
    "sg:tags":[
        "house"
    ],
    "wof:name":"Geoffs Construction LLC",
    "wof:placetype":"venue"
},
  "geometry": {"coordinates":[-87.930629,42.964379],"type":"Point"}
}