{
  "type": "Feature",
  "properties": {
    "iso:country":"US",
    "sg:address":"6225 7th Ave",
    "sg:city":"Kenosha",
    "sg:classifiers":[
        {
            "category":"Food & Beverages",
            "subcategory":"Specialty",
            "type":"Retail Goods"
        }
    ],
    "sg:phone":"+1 262 658 8494",
    "sg:postcode":"53143",
    "sg:province":"WI",
    "wof:name":"Shaklee Products",
    "wof:placetype":"venue"
},
  "geometry": {"coordinates":[-87.818396,42.577517],"type":"Point"}
}