{
  "type": "Feature",
  "properties": {
    "iso:country":"US",
    "sg:address":"1155 N Main St",
    "sg:city":"Oshkosh",
    "sg:classifiers":[
        {
            "category":"Shopping",
            "subcategory":"Computers & Home Electronics",
            "type":"Retail Goods"
        }
    ],
    "sg:phone":"+1 920 233 0000",
    "sg:postcode":"54901",
    "sg:province":"WI",
    "wof:name":"Computer Corner",
    "wof:placetype":"venue"
},
  "geometry": {"coordinates":[-88.537653,44.031564],"type":"Point"}
}