{
  "type": "Feature",
  "properties": {
    "iso:country":"US",
    "sg:address":"24421 Atlas Ave",
    "sg:city":"Warrens",
    "sg:classifiers":[
        {
            "category":"Retail",
            "subcategory":"Repair Shop",
            "type":"Services"
        }
    ],
    "sg:phone":"+1 608 378 3020",
    "sg:postcode":"54666",
    "sg:province":"WI",
    "sg:tags":[
        "taxidermist"
    ],
    "wof:name":"Art Works Taxidermy",
    "wof:placetype":"venue"
},
  "geometry": {"coordinates":[-90.511419,44.155643],"type":"Point"}
}