{
  "type": "Feature",
  "properties": {
    "iso:country":"US",
    "sg:address":"3062 N 58th St",
    "sg:city":"Milwaukee",
    "sg:classifiers":[
        {
            "category":"Health Services",
            "subcategory":"Health Practitioner",
            "type":"Services"
        }
    ],
    "sg:phone":"+1 414 445 3893",
    "sg:postcode":"53210",
    "sg:province":"WI",
    "wof:name":"Jl Staffing LLC",
    "wof:placetype":"venue"
},
  "geometry": {"coordinates":[-87.985017,43.07418],"type":"Point"}
}