{
  "type": "Feature",
  "properties": {
    "iso:country":"US",
    "sg:address":"14168 Selwood Dr",
    "sg:city":"Prairie Du Sac",
    "sg:classifiers":[
        {
            "category":"Building & Trades",
            "subcategory":"Plumbing",
            "type":"Services"
        }
    ],
    "sg:phone":"+1 608 644 1448",
    "sg:postcode":"53578",
    "sg:province":"WI",
    "sg:tags":[
        "plumbing",
        "contractor"
    ],
    "wof:name":"Selwood Plumbing",
    "wof:placetype":"venue"
},
  "geometry": {"coordinates":[-89.702499,43.325659],"type":"Point"}
}