{
  "type": "Feature",
  "properties": {
    "addr:full":"111 Stoddart St Beaver Dam WI 53916",
    "addr:housenumber":"111",
    "addr:postcode":"53916",
    "addr:street":"Stoddart St",
    "iso:country":"US",
    "sg:address":"111 Stoddart St",
    "sg:city":"Beaver Dam",
    "sg:classifiers":[
        {
            "category":"Farming",
            "subcategory":"Poultry Farm",
            "type":"Manufacturing & Wholesale Goods"
        }
    ],
    "sg:phone":"+1 920 887 1167",
    "sg:postcode":"53916",
    "sg:province":"WI",
    "sg:tags":[
        "hatchery",
        "chicken"
    ],
    "wof:name":"Centurion Poultry Incorporated",
    "wof:placetype":"venue"
},
  "geometry": {"coordinates":[-88.828408,43.469069],"type":"Point"}
}