{
  "type": "Feature",
  "properties": {
    "iso:country":"US",
    "sg:address":"7071 Co Rd Jj",
    "sg:city":"Hortonville",
    "sg:classifiers":[
        {
            "category":"Retail",
            "subcategory":"Repair Shop",
            "type":"Services"
        }
    ],
    "sg:phone":"+1 920 757 6131",
    "sg:postcode":"54944",
    "sg:province":"WI",
    "sg:tags":[
        "engine",
        "equipment",
        "lawn",
        "garden",
        "small"
    ],
    "wof:name":"Dales Small Engine Service",
    "wof:placetype":"venue"
},
  "geometry": {"coordinates":[-88.553296,44.330234],"type":"Point"}
}