{
  "type": "Feature",
  "properties": {
    "iso:country":"US",
    "sg:address":"10130 W Appleton Ave",
    "sg:city":"Milwaukee",
    "sg:classifiers":[
        {
            "category":"Banks & Credit Unions",
            "subcategory":"Bank",
            "type":"Services"
        }
    ],
    "sg:phone":"+1 414 438 2681",
    "sg:postcode":"53225",
    "sg:province":"WI",
    "sg:tags":[
        "federal",
        "savings",
        "institution"
    ],
    "wof:name":"Guaranty Bank",
    "wof:placetype":"venue"
},
  "geometry": {"coordinates":[-88.039793,43.123103],"type":"Point"}
}