{
  "type": "Feature",
  "properties": {
    "iso:country":"US",
    "sg:address":"1844 Wisconsin Ave",
    "sg:city":"Racine",
    "sg:classifiers":[
        {
            "category":"Professional",
            "subcategory":"Management & Consulting",
            "type":"Services"
        }
    ],
    "sg:phone":"+1 262 633 5470",
    "sg:postcode":"53403",
    "sg:province":"WI",
    "sg:tags":[
        "business"
    ],
    "wof:name":"Paradox Partners LLC",
    "wof:placetype":"venue"
},
  "geometry": {"coordinates":[-87.783691,42.707716],"type":"Point"}
}