{
  "type": "Feature",
  "properties": {
    "iso:country":"US",
    "sg:address":"709 S University Ave",
    "sg:city":"Beaver Dam",
    "sg:classifiers":[
        {
            "category":"Health Services",
            "subcategory":"Clinic",
            "type":"Services"
        }
    ],
    "sg:phone":"+1 920 887 4050",
    "sg:postcode":"53916",
    "sg:province":"WI",
    "sg:tags":[
        "home",
        "care"
    ],
    "wof:name":"Hillside Home Care/Hospice",
    "wof:placetype":"venue"
},
  "geometry": {"coordinates":[-88.82822299999999,43.448854],"type":"Point"}
}