{
  "type": "Feature",
  "properties": {
    "iso:country":"US",
    "sg:address":"4035 N 127th St",
    "sg:city":"Brookfield",
    "sg:classifiers":[
        {
            "category":"Professional",
            "subcategory":"Business Services",
            "type":"Services"
        }
    ],
    "sg:phone":"+1 262 790 5730",
    "sg:postcode":"53005",
    "sg:province":"WI",
    "sg:tags":[
        "interior",
        "consultant",
        "design",
        "decorator"
    ],
    "wof:name":"Cityscape Einteriors",
    "wof:placetype":"venue"
},
  "geometry": {"coordinates":[-88.06984,43.091351],"type":"Point"}
}