{
  "type": "Feature",
  "properties": {
    "iso:country":"US",
    "sg:address":"312 Milwaukee St",
    "sg:city":"Johnson Creek",
    "sg:classifiers":[
        {
            "category":"Food & Beverages",
            "subcategory":"Meat & Fish",
            "type":"Retail Goods"
        }
    ],
    "sg:phone":"+1 920 699 6990",
    "sg:postcode":"53038",
    "sg:province":"WI",
    "wof:name":"Pernat Haase Meats LLC",
    "wof:placetype":"venue"
},
  "geometry": {"coordinates":[-88.771489,43.075574],"type":"Point"}
}