{
  "type": "Feature",
  "properties": {
    "addr:full":"400 W Estabrook Blvd Milwaukee WI 53212",
    "addr:housenumber":"400",
    "addr:postcode":"53212",
    "addr:street":"W Estabrook Blvd",
    "iso:country":"US",
    "sg:address":"400 W Estabrook Blvd",
    "sg:city":"Milwaukee",
    "sg:classifiers":[
        {
            "category":"Health Services",
            "subcategory":"Doctor",
            "type":"Services"
        }
    ],
    "sg:phone":"+1 414 332 9960",
    "sg:postcode":"53212",
    "sg:province":"WI",
    "sg:tags":[
        "clinic"
    ],
    "wof:name":"Midwest Nephrology Assoc",
    "wof:placetype":"venue"
},
  "geometry": {"coordinates":[-87.912447,43.096693],"type":"Point"}
}