{
  "type": "Feature",
  "properties": {
    "iso:country":"US",
    "sg:address":"2311 Back Rd",
    "sg:city":"Burlington",
    "sg:classifiers":[
        {
            "category":"Building & Trades",
            "subcategory":"Construction",
            "type":"Services"
        }
    ],
    "sg:phone":"+1 262 248 8520",
    "sg:postcode":"53105",
    "sg:province":"WI",
    "sg:tags":[
        "coping",
        "plastering",
        "tiling",
        "pool",
        "swimming"
    ],
    "wof:name":"All Seasons Kuen's Pool Svc",
    "wof:placetype":"venue"
},
  "geometry": {"coordinates":[-88.379386,42.613284],"type":"Point"}
}