{
  "type": "Feature",
  "properties": {
    "iso:country":"US",
    "sg:address":"10755 Sand Rd",
    "sg:city":"Merrillan",
    "sg:classifiers":[
        {
            "category":"Organizations",
            "subcategory":"Community Association",
            "type":"Services"
        }
    ],
    "sg:phone":"+1 715 333 5105",
    "sg:postcode":"54754",
    "sg:province":"WI",
    "wof:name":"International Assoc of LI",
    "wof:placetype":"venue"
},
  "geometry": {"coordinates":[-90.85072,44.456556],"type":"Point"}
}