{
  "type": "Feature",
  "properties": {
    "iso:country":"US",
    "sg:address":"2006 N 68th St",
    "sg:city":"Milwaukee",
    "sg:classifiers":[
        {
            "category":"Home & Garden",
            "subcategory":"Carpets & Floor Coverings",
            "type":"Retail Goods"
        }
    ],
    "sg:phone":"+1 414 258 6453",
    "sg:postcode":"53213",
    "sg:province":"WI",
    "wof:name":"Elm Grove Carpet & Uphl Clg",
    "wof:placetype":"venue"
},
  "geometry": {"coordinates":[-87.997435,43.056007],"type":"Point"}
}