{
  "type": "Feature",
  "properties": {
    "iso:country":"US",
    "sg:address":"184 US Hwy 51",
    "sg:city":"De Forest",
    "sg:classifiers":[
        {
            "category":"Farming",
            "subcategory":"Dairy Farm",
            "type":"Manufacturing & Wholesale Goods"
        }
    ],
    "sg:phone":"+1 608 846 3113",
    "sg:postcode":"53532",
    "sg:province":"WI",
    "wof:name":"Doug Yelk",
    "wof:placetype":"venue"
},
  "geometry": {"coordinates":[-89.32462599999999,43.292472],"type":"Point"}
}