{
  "type": "Feature",
  "properties": {
    "iso:country":"US",
    "sg:address":"1909 E Moreland Blvd",
    "sg:city":"Waukesha",
    "sg:classifiers":[
        {
            "category":"Personal",
            "type":"Services"
        }
    ],
    "sg:phone":"+1 262 542 9211",
    "sg:postcode":"53186",
    "sg:province":"WI",
    "wof:name":"Hair Expose",
    "wof:placetype":"venue"
},
  "geometry": {"coordinates":[-88.19149899999999,43.026831],"type":"Point"}
}