{
  "type": "Feature",
  "properties": {
    "addr:full":"4046 N 7th St Milwaukee WI 53209",
    "addr:housenumber":"4046",
    "addr:postcode":"53209",
    "addr:street":"N 7Th St",
    "iso:country":"US",
    "sg:address":"4046 N 7th St",
    "sg:city":"Milwaukee",
    "sg:classifiers":[
        {
            "category":"Building & Trades",
            "subcategory":"Construction",
            "type":"Services"
        }
    ],
    "sg:phone":"+1 414 264 5920",
    "sg:postcode":"53209",
    "sg:province":"WI",
    "sg:tags":[
        "contractor"
    ],
    "wof:name":"Minger Drywall",
    "wof:placetype":"venue"
},
  "geometry": {"coordinates":[-87.919521,43.089359],"type":"Point"}
}