{
  "type": "Feature",
  "properties": {
    "iso:country":"US",
    "sg:address":"311 Oak St W",
    "sg:city":"Frederic",
    "sg:classifiers":[
        {
            "category":"Government",
            "subcategory":"Post Office",
            "type":"Public Place"
        }
    ],
    "sg:phone":"+1 715 327 8483",
    "sg:postcode":"54837",
    "sg:province":"WI",
    "wof:name":"US Post Office",
    "wof:placetype":"venue"
},
  "geometry": {"coordinates":[-92.471239,45.659242],"type":"Point"}
}