{
  "type": "Feature",
  "properties": {
    "iso:country":"US",
    "sg:address":"1019 Ogden Ave",
    "sg:city":"Superior",
    "sg:classifiers":[
        {
            "category":"Bars & Pubs",
            "type":"Food & Drink"
        }
    ],
    "sg:phone":"+1 715 394 3004",
    "sg:postcode":"54880",
    "sg:province":"WI",
    "wof:name":"Mama's",
    "wof:placetype":"venue"
},
  "geometry": {"coordinates":[-92.102435,46.725634],"type":"Point"}
}