{
  "type": "Feature",
  "properties": {
    "iso:country":"US",
    "sg:address":"9100 N White Oak Ln",
    "sg:city":"Milwaukee",
    "sg:classifiers":[
        {
            "category":"Personal",
            "type":"Services"
        }
    ],
    "sg:phone":"+1 414 228 8227",
    "sg:postcode":"53217",
    "sg:province":"WI",
    "sg:tags":[
        "consultant",
        "program",
        "health",
        "fitness"
    ],
    "wof:name":"Ruby Associates",
    "wof:placetype":"venue"
},
  "geometry": {"coordinates":[-87.915806,43.180397],"type":"Point"}
}