{
  "type": "Feature",
  "properties": {
    "iso:country":"US",
    "sg:address":"1159 Bellevue St",
    "sg:city":"Green Bay",
    "sg:classifiers":[
        {
            "category":"Government",
            "subcategory":"Office",
            "type":"Public Place"
        }
    ],
    "sg:phone":"+1 920 433 3928",
    "sg:postcode":"54302",
    "sg:province":"WI",
    "sg:tags":[
        "federal"
    ],
    "wof:name":"FARM Service Agency",
    "wof:placetype":"venue"
},
  "geometry": {"coordinates":[-87.99413199999999,44.488847],"type":"Point"}
}