{
  "type": "Feature",
  "properties": {
    "addr:full":"111 S Water St Sparta WI 54656",
    "addr:housenumber":"111",
    "addr:postcode":"54656",
    "addr:street":"S Water St",
    "iso:country":"US",
    "sg:address":"111 S Water St",
    "sg:city":"Sparta",
    "sg:classifiers":[
        {
            "category":"Organizations",
            "subcategory":"Non-profit Organization",
            "type":"Services"
        }
    ],
    "sg:phone":"+1 608 269 5683",
    "sg:postcode":"54656",
    "sg:province":"WI",
    "sg:tags":[
        "human"
    ],
    "wof:name":"Red Cross Sparta Blood Drive",
    "wof:placetype":"venue"
},
  "geometry": {"coordinates":[-90.810813,43.94433],"type":"Point"}
}