{
  "type": "Feature",
  "properties": {
    "iso:country":"US",
    "sg:address":"1631 W Becher St",
    "sg:city":"Milwaukee",
    "sg:classifiers":[
        {
            "category":"Organizations",
            "subcategory":"Religious Organization",
            "type":"Services"
        }
    ],
    "sg:phone":"+1 414 385 9702",
    "sg:postcode":"53215",
    "sg:province":"WI",
    "wof:name":"Iglesia Movimieno Pentecostal",
    "wof:placetype":"venue"
},
  "geometry": {"coordinates":[-87.934059,43.006485],"type":"Point"}
}