{
  "type": "Feature",
  "properties": {
    "iso:country":"US",
    "sg:address":"10930 W Potter Rd",
    "sg:city":"Milwaukee",
    "sg:classifiers":[
        {
            "category":"Professional",
            "subcategory":"Computer Services",
            "type":"Services"
        }
    ],
    "sg:phone":"+1 414 302 5620",
    "sg:postcode":"53226",
    "sg:province":"WI",
    "sg:tags":[
        "repair"
    ],
    "wof:name":"Sentinel Technologies Inc",
    "wof:placetype":"venue"
},
  "geometry": {"coordinates":[-88.04783,43.041141],"type":"Point"}
}