{
  "type": "Feature",
  "properties": {
    "iso:country":"US",
    "sg:address":"330 S Executive Dr Suite 303",
    "sg:city":"Brookfield",
    "sg:classifiers":[
        {
            "category":"Professional",
            "subcategory":"Business Services",
            "type":"Services"
        }
    ],
    "sg:phone":"+1 262 901 0086",
    "sg:postcode":"53005",
    "sg:province":"WI",
    "sg:tags":[
        "consultant",
        "coach",
        "broker"
    ],
    "sg:website":"http://www.sunbeltmidwest.com",
    "wof:name":"Sunbelt Business Brokers",
    "wof:placetype":"venue"
},
  "geometry": {"coordinates":[-88.114474,43.026942],"type":"Point"}
}