{
  "type": "Feature",
  "properties": {
    "iso:country":"US",
    "sg:address":"3712 Lake Thompson Rd",
    "sg:city":"Rhinelander",
    "sg:classifiers":[
        {
            "category":"Autos & Motor Vehicles",
            "subcategory":"Recreational Vehicle Sales",
            "type":"Retail Goods"
        }
    ],
    "sg:phone":"+1 715 369 4070",
    "sg:postcode":"54501",
    "sg:province":"WI",
    "sg:tags":[
        "motorcycle",
        "boat"
    ],
    "wof:name":"L & M Parts",
    "wof:placetype":"venue"
},
  "geometry": {"coordinates":[-89.33110499999999,45.651379],"type":"Point"}
}