{
  "type": "Feature",
  "properties": {
    "addr:full":"6910 N Crestwood Dr Milwaukee WI 53209",
    "addr:housenumber":"6910",
    "addr:postcode":"53209",
    "addr:street":"N Crestwood Dr",
    "iso:country":"US",
    "sg:address":"6910 N Crestwood Dr",
    "sg:city":"Milwaukee",
    "sg:classifiers":[
        {
            "category":"Shopping",
            "subcategory":"Computers & Home Electronics",
            "type":"Retail Goods"
        }
    ],
    "sg:phone":"+1 414 228 8400",
    "sg:postcode":"53209",
    "sg:province":"WI",
    "sg:tags":[
        "equipment",
        "dealer"
    ],
    "wof:name":"Computers On The Move",
    "wof:placetype":"venue"
},
  "geometry": {"coordinates":[-87.941058,43.143576],"type":"Point"}
}