{
  "type": "Feature",
  "properties": {
    "iso:country":"US",
    "sg:address":"600 Liberty St",
    "sg:city":"Green Bay",
    "sg:classifiers":[
        {
            "category":"Manufacturing",
            "subcategory":"Metals",
            "type":"Manufacturing & Wholesale Goods"
        },
        {
            "category":"Professional",
            "subcategory":"Business Services",
            "type":"Services"
        }
    ],
    "sg:phone":"+1 920 435 6676",
    "sg:postcode":"54304",
    "sg:province":"WI",
    "sg:website":"www.barkriver.com",
    "wof:name":"Roland Machinery Company",
    "wof:placetype":"venue"
},
  "geometry": {"coordinates":[-88.036524,44.498503],"type":"Point"}
}