{
  "type": "Feature",
  "properties": {
    "iso:country":"US",
    "sg:address":"9915 39th Ave",
    "sg:city":"Pleasant Prairie",
    "sg:classifiers":[
        {
            "category":"Government",
            "subcategory":"Office",
            "type":"Public Place"
        }
    ],
    "sg:phone":"+1 262 694 1400",
    "sg:postcode":"53158",
    "sg:province":"IL",
    "sg:tags":[
        "village"
    ],
    "wof:name":"Pleasant Prairie Village of",
    "wof:placetype":"venue"
},
  "geometry": {"coordinates":[-87.853883,42.527415],"type":"Point"}
}