{
  "type": "Feature",
  "properties": {
    "addr:full":"5711 Irish Valley Rd Plain WI 53577",
    "addr:housenumber":"5711",
    "addr:postcode":"53577",
    "addr:street":"Irish Valley Rd",
    "iso:country":"US",
    "sg:address":"5711 Irish Valley Rd",
    "sg:city":"Plain",
    "sg:classifiers":[
        {
            "category":"Farming",
            "subcategory":"Dairy Farm",
            "type":"Manufacturing & Wholesale Goods"
        }
    ],
    "sg:phone":"+1 608 546 4151",
    "sg:postcode":"53577",
    "sg:province":"WI",
    "wof:name":"Robert Palmer",
    "wof:placetype":"venue"
},
  "geometry": {"coordinates":[-90.014771,43.314113],"type":"Point"}
}