{
  "type": "Feature",
  "properties": {
    "addr:full":"558 State St Madison WI 53703",
    "addr:housenumber":"558",
    "addr:postcode":"53703",
    "addr:street":"State St",
    "iso:country":"US",
    "sg:address":"558 State St",
    "sg:city":"Madison",
    "sg:classifiers":[
        {
            "category":"Restaurant",
            "type":"Food & Drink"
        }
    ],
    "sg:menulink":"http://www.allmenus.com/wi/madison/261165-maza/menu/",
    "sg:phone":"+1 608 256 9330",
    "sg:postcode":"53703",
    "sg:province":"WI",
    "sg:tags":[
        "afghan"
    ],
    "wof:name":"Maza",
    "wof:placetype":"venue"
},
  "geometry": {"coordinates":[-89.394716,43.074994],"type":"Point"}
}