{
  "type": "Feature",
  "properties": {
    "iso:country":"US",
    "sg:address":"1042 1st Center Ave",
    "sg:city":"Brodhead",
    "sg:classifiers":[
        {
            "category":"Home & Garden",
            "subcategory":"Furniture",
            "type":"Retail Goods"
        }
    ],
    "sg:phone":"+1 608 897 2883",
    "sg:postcode":"53520",
    "sg:province":"WI",
    "wof:name":"Brodhead Furniture",
    "wof:placetype":"venue"
},
  "geometry": {"coordinates":[-89.376738,42.620374],"type":"Point"}
}