{
  "type": "Feature",
  "properties": {
    "iso:country":"US",
    "sg:address":"1157 Amherst Dr",
    "sg:city":"Madison",
    "sg:classifiers":[
        {
            "category":"Professional",
            "type":"Services"
        }
    ],
    "sg:phone":"+1 608 231 6264",
    "sg:postcode":"53705",
    "sg:province":"WI",
    "wof:name":"Natural Path Center",
    "wof:placetype":"venue"
},
  "geometry": {"coordinates":[-89.441545,43.079775],"type":"Point"}
}