{
  "type": "Feature",
  "properties": {
    "iso:country":"US",
    "sg:address":"9126 Co Hwy N",
    "sg:city":"Arpin",
    "sg:classifiers":[
        {
            "category":"Freight",
            "type":"Transportation"
        }
    ],
    "sg:phone":"+1 715 652 3256",
    "sg:postcode":"54410",
    "sg:province":"WI",
    "sg:tags":[
        "operator",
        "trucking"
    ],
    "wof:name":"Paul Fuehrer Transport",
    "wof:placetype":"venue"
},
  "geometry": {"coordinates":[-89.984668,44.569914],"type":"Point"}
}