{
  "type": "Feature",
  "properties": {
    "iso:country":"US",
    "sg:address":"12510 75th St",
    "sg:city":"Bristol",
    "sg:classifiers":[
        {
            "category":"Banks & Credit Unions",
            "subcategory":"Bank",
            "type":"Services"
        }
    ],
    "sg:phone":"+1 262 857 9899",
    "sg:postcode":"53104",
    "sg:province":"WI",
    "sg:tags":[
        "loan",
        "real estate"
    ],
    "wof:name":"Whitestone Mortgage",
    "wof:placetype":"venue"
},
  "geometry": {"coordinates":[-87.96327,42.567645],"type":"Point"}
}