{
  "type": "Feature",
  "properties": {
    "iso:country":"US",
    "sg:address":"9344 W Clovernook St",
    "sg:city":"Milwaukee",
    "sg:classifiers":[
        {
            "category":"Organizations",
            "subcategory":"Non-profit Organization",
            "type":"Services"
        }
    ],
    "sg:phone":"+1 414 760 2184",
    "sg:postcode":"53224",
    "sg:province":"WI",
    "sg:tags":[
        "charity",
        "foundations-educational",
        "philanthropic",
        "research"
    ],
    "wof:name":"Ask Second Chance Home",
    "wof:placetype":"venue"
},
  "geometry": {"coordinates":[-88.02795999999999,43.135802],"type":"Point"}
}