{
  "type": "Feature",
  "properties": {
    "iso:country":"US",
    "sg:address":"897 S German Settlement Rd",
    "sg:city":"Ogema",
    "sg:classifiers":[
        {
            "category":"Organizations",
            "subcategory":"Religious Organization",
            "type":"Services"
        }
    ],
    "sg:phone":"+1 715 427 5209",
    "sg:postcode":"54459",
    "sg:province":"WI",
    "sg:tags":[
        "church"
    ],
    "wof:name":"Zion Evangelical Lutheran Ch",
    "wof:placetype":"venue"
},
  "geometry": {"coordinates":[-90.08417,45.404085],"type":"Point"}
}