{
  "type": "Feature",
  "properties": {
    "iso:country":"US",
    "sg:address":"221 2nd St N",
    "sg:city":"Deer Park",
    "sg:classifiers":[
        {
            "category":"Organizations",
            "subcategory":"Religious Organization",
            "type":"Services"
        }
    ],
    "sg:phone":"+1 715 269 5218",
    "sg:postcode":"54007",
    "sg:province":"WI",
    "wof:name":"United Methodist Church",
    "wof:placetype":"venue"
},
  "geometry": {"coordinates":[-92.387518,45.188775],"type":"Point"}
}