{
  "type": "Feature",
  "properties": {
    "iso:country":"US",
    "sg:address":"270 N Mill St",
    "sg:city":"Saukville",
    "sg:classifiers":[
        {
            "category":"Manufacturing",
            "subcategory":"Metals",
            "type":"Manufacturing & Wholesale Goods"
        }
    ],
    "sg:phone":"+1 262 284 0331",
    "sg:postcode":"53080",
    "sg:province":"WI",
    "sg:tags":[
        "foundry",
        "nonferrous"
    ],
    "sg:website":"www.johnsoncentrifugal.com",
    "wof:name":"Johnson Brass & Machine Inc",
    "wof:placetype":"venue"
},
  "geometry": {"coordinates":[-87.939254,43.383669],"type":"Point"}
}