{
  "type": "Feature",
  "properties": {
    "addr:full":"4818 S 76th St Greenfield WI 53220",
    "addr:housenumber":"4818",
    "addr:postcode":"53220",
    "addr:street":"S 76Th St",
    "iso:country":"US",
    "sg:address":"4818 S 76th St",
    "sg:city":"Greenfield",
    "sg:classifiers":[
        {
            "category":"Insurance",
            "subcategory":"Insurance Agent",
            "type":"Services"
        }
    ],
    "sg:phone":"+1 414 282 1414",
    "sg:postcode":"53220",
    "sg:province":"WI",
    "wof:name":"State Farm Insurance",
    "wof:placetype":"venue"
},
  "geometry": {"coordinates":[-88.008281,42.956543],"type":"Point"}
}