{
  "type": "Feature",
  "properties": {
    "iso:country":"US",
    "sg:address":"4270 N Polaris Pkwy",
    "sg:city":"Janesville",
    "sg:classifiers":[
        {
            "category":"Building & Trades",
            "subcategory":"Construction",
            "type":"Services"
        }
    ],
    "sg:phone":"+1 608 868 7913",
    "sg:postcode":"53546",
    "sg:province":"WI",
    "sg:tags":[
        "house"
    ],
    "wof:name":"Coxey Construction LLC",
    "wof:placetype":"venue"
},
  "geometry": {"coordinates":[-88.96043899999999,42.732033],"type":"Point"}
}