{
  "type": "Feature",
  "properties": {
    "iso:country":"US",
    "sg:address":"2405 130th Ave",
    "sg:city":"Glenwood City",
    "sg:classifiers":[
        {
            "category":"Farming",
            "subcategory":"Dairy Farm",
            "type":"Manufacturing & Wholesale Goods"
        }
    ],
    "sg:phone":"+1 715 684 4644",
    "sg:postcode":"54013",
    "sg:province":"WI",
    "wof:name":"Dean J Shelly Wink or",
    "wof:placetype":"venue"
},
  "geometry": {"coordinates":[-92.31842899999999,45.048218],"type":"Point"}
}