{
  "type": "Feature",
  "properties": {
    "iso:country":"US",
    "sg:address":"4997 28th Rd",
    "sg:city":"Pine River",
    "sg:classifiers":[
        {
            "category":"Real Estate",
            "subcategory":"Real Estate Operator",
            "type":"Services"
        }
    ],
    "sg:phone":"+1 920 987 5612",
    "sg:postcode":"54965",
    "sg:province":"WI",
    "sg:tags":[
        "property",
        "lessor"
    ],
    "wof:name":"Fred Selthofner",
    "wof:placetype":"venue"
},
  "geometry": {"coordinates":[-89.068444,44.155896],"type":"Point"}
}