{
  "type": "Feature",
  "properties": {
    "iso:country":"US",
    "sg:address":"1400 Hwy 35 64",
    "sg:city":"Houlton",
    "sg:classifiers":[
        {
            "category":"Bars & Pubs",
            "type":"Food & Drink"
        }
    ],
    "sg:phone":"+1 715 549 6901",
    "sg:postcode":"54082",
    "sg:province":"WI",
    "sg:tags":[
        "drinking"
    ],
    "wof:name":"Cajun Club",
    "wof:placetype":"venue"
},
  "geometry": {"coordinates":[-92.791769,45.066365],"type":"Point"}
}