{
  "type": "Feature",
  "properties": {
    "iso:country":"US",
    "sg:address":"5309 N 29th St",
    "sg:city":"Milwaukee",
    "sg:classifiers":[
        {
            "category":"Professional",
            "type":"Services"
        }
    ],
    "sg:phone":"+1 414 527 0969",
    "sg:postcode":"53209",
    "sg:province":"WI",
    "wof:name":"Patrick Company",
    "wof:placetype":"venue"
},
  "geometry": {"coordinates":[-87.948953,43.112981],"type":"Point"}
}