{
  "type": "Feature",
  "properties": {
    "addr:full":"3196 N Main St Oshkosh WI 54901",
    "addr:housenumber":"3196",
    "addr:postcode":"54901",
    "addr:street":"N Main St",
    "iso:country":"US",
    "sg:address":"3196 N Main St",
    "sg:city":"Oshkosh",
    "sg:classifiers":[
        {
            "category":"Professional",
            "subcategory":"Business Services",
            "type":"Services"
        }
    ],
    "sg:phone":"+1 920 235 3993",
    "sg:postcode":"54901",
    "sg:province":"WI",
    "sg:tags":[
        "merchandise",
        "mfg"
    ],
    "wof:name":"Oshkosh Trophy",
    "wof:placetype":"venue"
},
  "geometry": {"coordinates":[-88.537859,44.057045],"type":"Point"}
}