{
  "type": "Feature",
  "properties": {
    "addr:full":"17305 Oak Park Row Brookfield WI 53045",
    "addr:housenumber":"17305",
    "addr:postcode":"53045",
    "addr:street":"Oak Park Row",
    "iso:country":"US",
    "sg:address":"17305 Oak Park Row",
    "sg:city":"Brookfield",
    "sg:classifiers":[
        {
            "category":"Professional",
            "subcategory":"Business Services",
            "type":"Services"
        }
    ],
    "sg:phone":"+1 262 786 2185",
    "sg:postcode":"53045",
    "sg:province":"WI",
    "sg:tags":[
        "water",
        "treatment"
    ],
    "wof:name":"Feder Sales & Svc",
    "wof:placetype":"venue"
},
  "geometry": {"coordinates":[-88.128406,43.047194],"type":"Point"}
}