{
  "type": "Feature",
  "properties": {
    "iso:country":"US",
    "sg:address":"116 Edgar Ave",
    "sg:city":"South Milwaukee",
    "sg:classifiers":[
        {
            "category":"Manufacturing",
            "subcategory":"Tools & Machinery",
            "type":"Manufacturing & Wholesale Goods"
        }
    ],
    "sg:phone":"+1 414 764 5210",
    "sg:postcode":"53172",
    "sg:province":"WI",
    "sg:tags":[
        "machine",
        "shop"
    ],
    "wof:name":"ABKO Screw Machines LTD",
    "wof:placetype":"venue"
},
  "geometry": {"coordinates":[-87.862965,42.928794],"type":"Point"}
}