{
  "type": "Feature",
  "properties": {
    "iso:country":"US",
    "sg:address":"321 Main St W",
    "sg:city":"Ashland",
    "sg:classifiers":[
        {
            "category":"Banks & Credit Unions",
            "subcategory":"Financial Services",
            "type":"Services"
        }
    ],
    "sg:phone":"+1 715 682 2772",
    "sg:postcode":"54806",
    "sg:province":"WI",
    "sg:tags":[
        "company",
        "holding"
    ],
    "wof:name":"Bay Area Banking Shares Inc",
    "wof:placetype":"venue"
},
  "geometry": {"coordinates":[-90.885974,46.590328],"type":"Point"}
}