{
  "type": "Feature",
  "properties": {
    "iso:country":"US",
    "sg:address":"515 Highland Ave",
    "sg:city":"Elderon",
    "sg:classifiers":[
        {
            "category":"Bars & Pubs",
            "type":"Food & Drink"
        }
    ],
    "sg:phone":"+1 715 454 6230",
    "sg:postcode":"54457",
    "sg:province":"WI",
    "wof:name":"Mark's Bar",
    "wof:placetype":"venue"
},
  "geometry": {"coordinates":[-89.901601,44.319646],"type":"Point"}
}