{
  "type": "Feature",
  "properties": {
    "iso:country":"US",
    "sg:address":"6300 W Fond du Lac Ave",
    "sg:city":"Milwaukee",
    "sg:classifiers":[
        {
            "category":"Government",
            "subcategory":"Office",
            "type":"Public Place"
        }
    ],
    "sg:phone":"+1 414 463 1799",
    "sg:postcode":"53218",
    "sg:province":"WI",
    "sg:tags":[
        "program",
        "insurance",
        "social"
    ],
    "wof:name":"Ssa District Office",
    "wof:placetype":"venue"
},
  "geometry": {"coordinates":[-87.99048500000001,43.101076],"type":"Point"}
}