{
  "type": "Feature",
  "properties": {
    "iso:country":"US",
    "sg:address":"2601 Fergus Ave",
    "sg:city":"Racine",
    "sg:classifiers":[
        {
            "category":"Manufacturing",
            "subcategory":"Signs",
            "type":"Manufacturing & Wholesale Goods"
        }
    ],
    "sg:phone":"+1 262 634 3000",
    "sg:postcode":"53404",
    "sg:province":"WI",
    "wof:name":"Sign Shop Inc",
    "wof:placetype":"venue"
},
  "geometry": {"coordinates":[-87.814328,42.75227],"type":"Point"}
}