{
  "type": "Feature",
  "properties": {
    "iso:country":"US",
    "sg:address":"14385 Thornhill Dr",
    "sg:city":"Menomonee Falls",
    "sg:classifiers":[
        {
            "category":"Professional",
            "subcategory":"Computer Services",
            "type":"Services"
        }
    ],
    "sg:phone":"+1 262 783 7608",
    "sg:postcode":"53051",
    "sg:province":"WI",
    "sg:tags":[
        "related"
    ],
    "wof:name":"Virtual Assistant 4u LLC",
    "wof:placetype":"venue"
},
  "geometry": {"coordinates":[-88.09024,43.11236],"type":"Point"}
}