{
  "type": "Feature",
  "properties": {
    "iso:country":"US",
    "sg:address":"3136 Longview Ln",
    "sg:city":"Suamico",
    "sg:classifiers":[
        {
            "category":"Social Services",
            "subcategory":"Adult Care",
            "type":"Services"
        }
    ],
    "sg:phone":"+1 920 434 8650",
    "sg:postcode":"54173",
    "sg:province":"WI",
    "sg:tags":[
        "home",
        "residential"
    ],
    "wof:name":"Longview Terrace II",
    "wof:placetype":"venue"
},
  "geometry": {"coordinates":[-88.02901199999999,44.632035],"type":"Point"}
}