{
  "type": "Feature",
  "properties": {
    "iso:country":"US",
    "sg:address":"76 Monroe Ave",
    "sg:city":"Rice Lake",
    "sg:classifiers":[
        {
            "category":"Retail",
            "subcategory":"Auto Repair",
            "type":"Services"
        }
    ],
    "sg:phone":"+1 715 234 7811",
    "sg:postcode":"54868",
    "sg:province":"WI",
    "sg:tags":[
        "body",
        "general"
    ],
    "wof:name":"Dels Repair Service",
    "wof:placetype":"venue"
},
  "geometry": {"coordinates":[-91.723877,45.521711],"type":"Point"}
}