{
  "type": "Feature",
  "properties": {
    "iso:country":"US",
    "sg:address":"2904 Custer St",
    "sg:city":"Manitowoc",
    "sg:classifiers":[
        {
            "category":"Insurance",
            "subcategory":"Insurance Agent",
            "type":"Services"
        }
    ],
    "sg:phone":"+1 920 682 5139",
    "sg:postcode":"54220",
    "sg:province":"WI",
    "wof:name":"American Family Insurance",
    "wof:placetype":"venue"
},
  "geometry": {"coordinates":[-87.68525,44.088313],"type":"Point"}
}