{
  "type": "Feature",
  "properties": {
    "iso:country":"US",
    "sg:address":"1968 S Muskego Ave",
    "sg:city":"Milwaukee",
    "sg:classifiers":[
        {
            "category":"Retail",
            "subcategory":"Repair Shop",
            "type":"Services"
        }
    ],
    "sg:phone":"+1 414 671 4629",
    "sg:postcode":"53204",
    "sg:province":"WI",
    "sg:tags":[
        "related"
    ],
    "wof:name":"Jorge Auto Repair",
    "wof:placetype":"venue"
},
  "geometry": {"coordinates":[-87.940595,43.00974],"type":"Point"}
}