{
  "type": "Feature",
  "properties": {
    "iso:country":"US",
    "sg:address":"1031 Lombardi Ave",
    "sg:city":"Green Bay",
    "sg:classifiers":[
        {
            "category":"Autos & Motor Vehicles",
            "subcategory":"Fuel & Gas Station",
            "type":"Retail Goods"
        }
    ],
    "sg:phone":"+1 920 494 1341",
    "sg:postcode":"54304",
    "sg:province":"WI",
    "sg:tags":[
        "station",
        "gasoline"
    ],
    "wof:name":"Mobil",
    "wof:placetype":"venue"
},
  "geometry": {"coordinates":[-88.050738,44.499548],"type":"Point"}
}