{
  "type": "Feature",
  "properties": {
    "iso:country":"US",
    "sg:address":"3712 Fairway Dr",
    "sg:city":"Reedsville",
    "sg:classifiers":[
        {
            "category":"Building & Trades",
            "subcategory":"Landscaping Services",
            "type":"Services"
        }
    ],
    "sg:phone":"+1 920 732 1133",
    "sg:postcode":"54230",
    "sg:province":"WI",
    "wof:name":"Sunset Tree & Stump Removal",
    "wof:placetype":"venue"
},
  "geometry": {"coordinates":[-87.784714,44.141899],"type":"Point"}
}