{
  "type": "Feature",
  "properties": {
    "iso:country":"US",
    "sg:address":"423 Bluff St",
    "sg:city":"Beloit",
    "sg:classifiers":[
        {
            "category":"Social Services",
            "type":"Services"
        }
    ],
    "sg:phone":"+1 608 365 1244",
    "sg:postcode":"53511",
    "sg:province":"WI",
    "sg:tags":[
        "organization",
        "welfare"
    ],
    "wof:name":"Family Service Assn",
    "wof:placetype":"venue"
},
  "geometry": {"coordinates":[-89.041633,42.500648],"type":"Point"}
}