{
  "type": "Feature",
  "properties": {
    "iso:country":"US",
    "sg:address":"3565 Co Rd H",
    "sg:city":"Ridgeway",
    "sg:classifiers":[
        {
            "category":"Freight",
            "type":"Transportation"
        }
    ],
    "sg:phone":"+1 608 924 9606",
    "sg:postcode":"53582",
    "sg:province":"WI",
    "sg:tags":[
        "trucking"
    ],
    "wof:name":"Hilst Trucking & Cartage LLC",
    "wof:placetype":"venue"
},
  "geometry": {"coordinates":[-89.977241,42.988129],"type":"Point"}
}