{
  "type": "Feature",
  "properties": {
    "addr:full":"409 W Walnut St Green Bay WI 54303",
    "addr:housenumber":"409",
    "addr:postcode":"54303",
    "addr:street":"W Walnut St",
    "iso:country":"US",
    "sg:address":"409 W Walnut St",
    "sg:city":"Green Bay",
    "sg:classifiers":[
        {
            "category":"Personal",
            "subcategory":"Beauty Salon",
            "type":"Services"
        }
    ],
    "sg:phone":"+1 920 436 9444",
    "sg:postcode":"54303",
    "sg:province":"WI",
    "wof:name":"K International Hair Braiding",
    "wof:placetype":"venue"
},
  "geometry": {"coordinates":[-88.022918,44.516648],"type":"Point"}
}