{
  "type": "Feature",
  "properties": {
    "addr:full":"1620 Phillips Ave Racine WI 53403",
    "addr:housenumber":"1620",
    "addr:postcode":"53403",
    "addr:street":"Phillips Ave",
    "iso:country":"US",
    "sg:address":"1620 Phillips Ave",
    "sg:city":"Racine",
    "sg:classifiers":[
        {
            "category":"Personal",
            "subcategory":"Beauty Salon",
            "type":"Services"
        }
    ],
    "sg:phone":"+1 262 633 4196",
    "sg:postcode":"53403",
    "sg:province":"WI",
    "wof:name":"Johnson Salon Lady",
    "wof:placetype":"venue"
},
  "geometry": {"coordinates":[-87.802119,42.711584],"type":"Point"}
}