{
  "type": "Feature",
  "properties": {
    "iso:country":"US",
    "sg:address":"2024 16th Ave",
    "sg:city":"Cameron",
    "sg:classifiers":[
        {
            "category":"Real Estate",
            "subcategory":"Real Estate Operator",
            "type":"Services"
        }
    ],
    "sg:phone":"+1 715 234 7652",
    "sg:postcode":"54822",
    "sg:province":"WI",
    "sg:tags":[
        "property",
        "lessor"
    ],
    "wof:name":"Gerber Rentals",
    "wof:placetype":"venue"
},
  "geometry": {"coordinates":[-91.741499,45.437345],"type":"Point"}
}