{
  "type": "Feature",
  "properties": {
    "iso:country":"US",
    "sg:address":"604 Grove St",
    "sg:city":"Mauston",
    "sg:classifiers":[
        {
            "category":"Social Services",
            "subcategory":"Child Care",
            "type":"Services"
        }
    ],
    "sg:phone":"+1 608 847 6779",
    "sg:postcode":"53948",
    "sg:province":"WI",
    "sg:tags":[
        "day"
    ],
    "wof:name":"Little Ones Family Daycare",
    "wof:placetype":"venue"
},
  "geometry": {"coordinates":[-90.084422,43.796636],"type":"Point"}
}