{
  "type": "Feature",
  "properties": {
    "addr:full":"451 Emerson St Neenah WI 54956",
    "addr:housenumber":"451",
    "addr:postcode":"54956",
    "addr:street":"Emerson St",
    "iso:country":"US",
    "sg:address":"451 Emerson St",
    "sg:city":"Neenah",
    "sg:classifiers":[
        {
            "category":"Professional",
            "subcategory":"Management & Consulting",
            "type":"Services"
        }
    ],
    "sg:phone":"+1 920 720 0573",
    "sg:postcode":"54956",
    "sg:province":"WI",
    "sg:tags":[
        "business"
    ],
    "wof:name":"Waller Research & Publishing",
    "wof:placetype":"venue"
},
  "geometry": {"coordinates":[-88.454763,44.161449],"type":"Point"}
}