{
  "type": "Feature",
  "properties": {
    "addr:full":"3347 Kohler Memorial Dr Sheboygan WI 53081",
    "addr:housenumber":"3347",
    "addr:postcode":"53081",
    "addr:street":"Memorial Dr",
    "iso:country":"US",
    "sg:address":"3347 Kohler Memorial Dr",
    "sg:city":"Sheboygan",
    "sg:classifiers":[
        {
            "category":"Shopping",
            "subcategory":"Gifts & Souvenirs",
            "type":"Retail Goods"
        }
    ],
    "sg:phone":"+1 920 458 7171",
    "sg:postcode":"53081",
    "sg:province":"WI",
    "sg:tags":[
        "shop",
        "engraving",
        "custom"
    ],
    "wof:name":"Things Remembered",
    "wof:placetype":"venue"
},
  "geometry": {"coordinates":[-87.753243,43.756209],"type":"Point"}
}