{
  "type": "Feature",
  "properties": {
    "iso:country":"US",
    "sg:address":"3482 Town Hall Rd",
    "sg:city":"Kewaskum",
    "sg:classifiers":[
        {
            "category":"Government",
            "subcategory":"Office",
            "type":"Public Place"
        }
    ],
    "sg:phone":"+1 262 334 2765",
    "sg:postcode":"53040",
    "sg:province":"WI",
    "sg:tags":[
        "city"
    ],
    "wof:name":"Barton Town Hall Office",
    "wof:placetype":"venue"
},
  "geometry": {"coordinates":[-88.212316,43.462883],"type":"Point"}
}