{
  "type": "Feature",
  "properties": {
    "addr:full":"443 E Cornelia St Darlington WI 53530",
    "addr:housenumber":"443",
    "addr:postcode":"53530",
    "addr:street":"E Cornelia St",
    "iso:country":"US",
    "sg:address":"443 E Cornelia St",
    "sg:city":"Darlington",
    "sg:classifiers":[
        {
            "category":"Professional",
            "subcategory":"Business Services",
            "type":"Services"
        }
    ],
    "sg:phone":"+1 608 776 3714",
    "sg:postcode":"53530",
    "sg:province":"WI",
    "wof:name":"Brushworks",
    "wof:placetype":"venue"
},
  "geometry": {"coordinates":[-90.113691,42.680949],"type":"Point"}
}