{
  "type": "Feature",
  "properties": {
    "iso:country":"US",
    "sg:address":"133 E Main St",
    "sg:city":"Hixton",
    "sg:classifiers":[
        {
            "category":"Restaurant",
            "type":"Food & Drink"
        }
    ],
    "sg:phone":"+1 715 963 4031",
    "sg:postcode":"54635",
    "sg:province":"WI",
    "wof:name":"Hixton Cafe",
    "wof:placetype":"venue"
},
  "geometry": {"coordinates":[-91.01322,44.386364],"type":"Point"}
}