{
  "type": "Feature",
  "properties": {
    "addr:full":"310 N Chestnut St Green Bay WI 54303",
    "addr:housenumber":"310",
    "addr:postcode":"54303",
    "addr:street":"N Chestnut St",
    "iso:country":"US",
    "sg:address":"310 N Chestnut St",
    "sg:city":"Green Bay",
    "sg:classifiers":[
        {
            "category":"Shopping",
            "subcategory":"Clothing, Apparel, & Fashions",
            "type":"Retail Goods"
        }
    ],
    "sg:phone":"+1 920 437 3628",
    "sg:postcode":"54303",
    "sg:province":"WI",
    "wof:name":"Blin Bling Fashion Vrty",
    "wof:placetype":"venue"
},
  "geometry": {"coordinates":[-88.01994000000001,44.52113],"type":"Point"}
}