{
  "type": "Feature",
  "properties": {
    "iso:country":"US",
    "sg:address":"3127 W Wisconsin Ave",
    "sg:city":"Milwaukee",
    "sg:classifiers":[
        {
            "category":"Professional",
            "subcategory":"Lawyer & Legal Services",
            "type":"Services"
        }
    ],
    "sg:phone":"+1 414 908 4262",
    "sg:postcode":"53208",
    "sg:province":"WI",
    "sg:tags":[
        "attorney"
    ],
    "wof:name":"Ceron A Davis",
    "wof:placetype":"venue"
},
  "geometry": {"coordinates":[-87.952787,43.038659],"type":"Point"}
}