{
  "type": "Feature",
  "properties": {
    "iso:country":"US",
    "sg:address":"3316 Leismann Rd",
    "sg:city":"Reeseville",
    "sg:classifiers":[
        {
            "category":"Building & Trades",
            "subcategory":"Plumbing",
            "type":"Services"
        }
    ],
    "sg:phone":"+1 920 927 3379",
    "sg:postcode":"53579",
    "sg:province":"WI",
    "sg:tags":[
        "contractor"
    ],
    "wof:name":"Zielke Heating & Cooling",
    "wof:placetype":"venue"
},
  "geometry": {"coordinates":[-88.891767,43.321466],"type":"Point"}
}