{
  "type": "Feature",
  "properties": {
    "addr:full":"104 S Main St Fond Du Lac WI 54935",
    "addr:housenumber":"104",
    "addr:postcode":"54935",
    "addr:street":"S Main St",
    "iso:country":"US",
    "sg:address":"104 S Main St",
    "sg:city":"Fond Du Lac",
    "sg:classifiers":[
        {
            "category":"Social Services",
            "type":"Services"
        }
    ],
    "sg:phone":"+1 920 322 9100",
    "sg:postcode":"54935",
    "sg:province":"WI",
    "wof:name":"Inside Out Cnsling Dagnstc Ctr",
    "wof:placetype":"venue"
},
  "geometry": {"coordinates":[-88.44707699999999,43.775434],"type":"Point"}
}