{
  "type": "Feature",
  "properties": {
    "iso:country":"US",
    "sg:address":"203 Central Bridge St",
    "sg:city":"Wausau",
    "sg:classifiers":[
        {
            "category":"Autos & Motor Vehicles",
            "subcategory":"Auto Supplies",
            "type":"Retail Goods"
        },
        {
            "category":"Retail",
            "subcategory":"Auto Repair",
            "type":"Services"
        }
    ],
    "sg:phone":"+1 715 845 1101",
    "sg:postcode":"54401",
    "sg:province":"WI",
    "sg:tags":[
        "engine",
        "body",
        "rebuilding",
        "automobile",
        "removal",
        "part",
        "dent",
        "painting",
        "repairing"
    ],
    "sg:website":"http://www.motorsservice.com",
    "wof:name":"Motors Service & Supply Corporation",
    "wof:placetype":"venue"
},
  "geometry": {"coordinates":[-89.634208,44.96955],"type":"Point"}
}