{
  "type": "Feature",
  "properties": {
    "iso:country":"US",
    "sg:address":"1801 N Mayfair Rd",
    "sg:city":"Milwaukee",
    "sg:classifiers":[
        {
            "category":"Autos & Motor Vehicles",
            "subcategory":"Automobile Sales",
            "type":"Retail Goods"
        }
    ],
    "sg:phone":"+1 414 258 8898",
    "sg:postcode":"53226",
    "sg:province":"WI",
    "sg:tags":[
        "new",
        "used"
    ],
    "wof:name":"Renner Oldsmobile",
    "wof:placetype":"venue"
},
  "geometry": {"coordinates":[-88.047633,43.054481],"type":"Point"}
}