{
  "type": "Feature",
  "properties": {
    "iso:country":"US",
    "sg:address":"7298 N 97th St",
    "sg:city":"Milwaukee",
    "sg:classifiers":[
        {
            "category":"Personal",
            "subcategory":"Beauty Salon",
            "type":"Services"
        }
    ],
    "sg:phone":"+1 414 353 4394",
    "sg:postcode":"53224",
    "sg:province":"WI",
    "sg:tags":[
        "shop"
    ],
    "wof:name":"Nails By Alice LLC",
    "wof:placetype":"venue"
},
  "geometry": {"coordinates":[-88.032914,43.150482],"type":"Point"}
}