{
  "type": "Feature",
  "properties": {
    "iso:country":"US",
    "sg:address":"335 Dairyland Dr",
    "sg:city":"Milton",
    "sg:classifiers":[
        {
            "category":"Organizations",
            "subcategory":"Religious Organization",
            "type":"Services"
        }
    ],
    "sg:phone":"+1 608 868 3680",
    "sg:postcode":"53563",
    "sg:province":"WI",
    "wof:name":"Hope Lutheran Church Elca",
    "wof:placetype":"venue"
},
  "geometry": {"coordinates":[-88.96701299999999,42.787239],"type":"Point"}
}