{
  "type": "Feature",
  "properties": {
    "iso:country":"US",
    "sg:address":"512 4th Ave",
    "sg:city":"New Glarus",
    "sg:classifiers":[
        {
            "category":"Real Estate",
            "subcategory":"Real Estate Agent",
            "type":"Services"
        },
        {
            "category":"Professional",
            "subcategory":"Business Services",
            "type":"Services"
        }
    ],
    "sg:phone":"+1 608 527 2508",
    "sg:postcode":"53574",
    "sg:province":"WI",
    "sg:tags":[
        "appraiser"
    ],
    "wof:name":"Phillipson Appraisal Service",
    "wof:placetype":"venue"
},
  "geometry": {"coordinates":[-89.638846,42.816344],"type":"Point"}
}