{
  "type": "Feature",
  "properties": {
    "iso:country":"US",
    "sg:address":"870 N Summit Ave",
    "sg:city":"Oconomowoc",
    "sg:classifiers":[
        {
            "category":"Health Services",
            "subcategory":"Doctor",
            "type":"Services"
        }
    ],
    "sg:phone":"+1 262 567 0280",
    "sg:postcode":"53066",
    "sg:province":"WI",
    "sg:tags":[
        "physician",
        "surgeon"
    ],
    "wof:name":"Duehr Dean Davis MD",
    "wof:placetype":"venue"
},
  "geometry": {"coordinates":[-88.463205,43.042205],"type":"Point"}
}