{
  "type": "Feature",
  "properties": {
    "iso:country":"US",
    "sg:address":"2015 W Spencer St",
    "sg:city":"Appleton",
    "sg:classifiers":[
        {
            "category":"Building & Trades",
            "subcategory":"Landscaping Services",
            "type":"Services"
        }
    ],
    "sg:phone":"+1 920 734 4198",
    "sg:postcode":"54914",
    "sg:province":"WI",
    "sg:tags":[
        "lawn",
        "maintenance",
        "grounds"
    ],
    "wof:name":"Tru Green Chem Lawn",
    "wof:placetype":"venue"
},
  "geometry": {"coordinates":[-88.43723199999999,44.258577],"type":"Point"}
}