{
  "type": "Feature",
  "properties": {
    "addr:full":"9083 N 85th St Milwaukee WI 53224",
    "addr:housenumber":"9083",
    "addr:postcode":"53224",
    "addr:street":"N 85Th St",
    "iso:country":"US",
    "sg:address":"9083 N 85th St",
    "sg:city":"Milwaukee",
    "sg:classifiers":[
        {
            "category":"Social Services",
            "subcategory":"Adult Care",
            "type":"Services"
        }
    ],
    "sg:phone":"+1 414 365 0780",
    "sg:postcode":"53224",
    "sg:province":"WI",
    "sg:tags":[
        "home",
        "group"
    ],
    "wof:name":"Next Generation of Lf Group HM",
    "wof:placetype":"venue"
},
  "geometry": {"coordinates":[-88.01576799999999,43.180409],"type":"Point"}
}