{
  "type": "Feature",
  "properties": {
    "addr:full":"980 E Drexel Ave Oak Creek WI 53154",
    "addr:housenumber":"980",
    "addr:postcode":"53154",
    "addr:street":"E Drexel Ave",
    "iso:country":"US",
    "sg:address":"980 E Drexel Ave",
    "sg:city":"Oak Creek",
    "sg:classifiers":[
        {
            "category":"Real Estate",
            "subcategory":"Architect",
            "type":"Services"
        }
    ],
    "sg:phone":"+1 414 764 0897",
    "sg:postcode":"53154",
    "sg:province":"WI",
    "sg:tags":[
        "architectural"
    ],
    "wof:name":"Tailored Places LTD",
    "wof:placetype":"venue"
},
  "geometry": {"coordinates":[-87.897744,42.901055],"type":"Point"}
}