{
  "type": "Feature",
  "properties": {
    "addr:full":"3259 Peterson Rd Green Bay WI 54311",
    "addr:housenumber":"3259",
    "addr:postcode":"54311",
    "addr:street":"Peterson Rd",
    "iso:country":"US",
    "sg:address":"3259 Peterson Rd",
    "sg:city":"Green Bay",
    "sg:classifiers":[
        {
            "category":"Building & Trades",
            "subcategory":"Construction",
            "type":"Services"
        }
    ],
    "sg:phone":"+1 920 406 6010",
    "sg:postcode":"54311",
    "sg:province":"WI",
    "sg:tags":[
        "concrete",
        "contractor"
    ],
    "wof:name":"Bonjean Concrete",
    "wof:placetype":"venue"
},
  "geometry": {"coordinates":[-87.91979600000001,44.543695],"type":"Point"}
}