{
  "type": "Feature",
  "properties": {
    "iso:country":"US",
    "sg:address":"61134 Wall Ridge Rd",
    "sg:city":"Eastman",
    "sg:phone":"+1 608 874 4394",
    "sg:postcode":"54626",
    "sg:province":"WI",
    "sg:tags":[
        "farm",
        "field",
        "corn",
        "crop"
    ],
    "wof:name":"Frank Pintz",
    "wof:placetype":"venue"
},
  "geometry": {"coordinates":[-91.089142,43.190967],"type":"Point"}
}