{
  "type": "Feature",
  "properties": {
    "iso:country":"US",
    "sg:address":"3817 S Webster Ave",
    "sg:city":"Green Bay",
    "sg:classifiers":[
        {
            "category":"Personal",
            "subcategory":"Beauty Salon",
            "type":"Services"
        }
    ],
    "sg:phone":"+1 920 336 3840",
    "sg:postcode":"54301",
    "sg:province":"WI",
    "sg:tags":[
        "shop"
    ],
    "wof:name":"Ce Bon Beauty Salon",
    "wof:placetype":"venue"
},
  "geometry": {"coordinates":[-88.039947,44.45836],"type":"Point"}
}