{
  "type": "Feature",
  "properties": {
    "addr:full":"612 N Main St Janesville WI 53545",
    "addr:housenumber":"612",
    "addr:postcode":"53545",
    "addr:street":"N Main St",
    "iso:country":"US",
    "sg:address":"612 N Main St",
    "sg:city":"Janesville",
    "sg:classifiers":[
        {
            "category":"Home & Garden",
            "subcategory":"Garden Supply",
            "type":"Retail Goods"
        }
    ],
    "sg:phone":"+1 608 757 0510",
    "sg:postcode":"53545",
    "sg:province":"WI",
    "sg:tags":[
        "on",
        "lawn",
        "sales",
        "tractor"
    ],
    "wof:name":"Rivers Edge Cub Cadet Sls LLC",
    "wof:placetype":"venue"
},
  "geometry": {"coordinates":[-89.02800000000001,42.688172],"type":"Point"}
}