{
  "type": "Feature",
  "properties": {
    "iso:country":"US",
    "sg:address":"6804 Green Bay Rd",
    "sg:city":"Kenosha",
    "sg:classifiers":[
        {
            "category":"Restaurant",
            "type":"Food & Drink"
        }
    ],
    "sg:phone":"+1 262 697 0123",
    "sg:postcode":"53142",
    "sg:province":"IL",
    "sg:tags":[
        "pizza"
    ],
    "sg:website":"www.rosatispizza.com",
    "wof:name":"Rosati's Of Kenosha",
    "wof:placetype":"venue"
},
  "geometry": {"coordinates":[-87.887426,42.567958],"type":"Point"}
}