{
  "type": "Feature",
  "properties": {
    "iso:country":"US",
    "sg:address":"3959 Staadt Ave",
    "sg:city":"Stratford",
    "sg:classifiers":[
        {
            "category":"Real Estate",
            "subcategory":"Real Estate Operator",
            "type":"Services"
        }
    ],
    "sg:phone":"+1 715 687 2160",
    "sg:postcode":"54484",
    "sg:province":"WI",
    "sg:tags":[
        "property",
        "lessor"
    ],
    "wof:name":"Larry Kirsch",
    "wof:placetype":"venue"
},
  "geometry": {"coordinates":[-90.11995400000001,44.787582],"type":"Point"}
}