{
  "type": "Feature",
  "properties": {
    "addr:full":"205 Wright St Waukesha WI 53186",
    "addr:housenumber":"205",
    "addr:postcode":"53186",
    "addr:street":"Wright St",
    "iso:country":"US",
    "sg:address":"205 Wright St",
    "sg:city":"Waukesha",
    "sg:classifiers":[
        {
            "category":"Building & Trades",
            "subcategory":"Construction",
            "type":"Services"
        }
    ],
    "sg:phone":"+1 262 547 1685",
    "sg:postcode":"53186",
    "sg:province":"WI",
    "sg:tags":[
        "house"
    ],
    "wof:name":"York Builders",
    "wof:placetype":"venue"
},
  "geometry": {"coordinates":[-88.225464,43.004028],"type":"Point"}
}