{
  "type": "Feature",
  "properties": {
    "addr:full":"463 S Randall Ave Janesville WI 53545",
    "addr:housenumber":"463",
    "addr:postcode":"53545",
    "addr:street":"S Randall Ave",
    "iso:country":"US",
    "sg:address":"463 S Randall Ave",
    "sg:city":"Janesville",
    "sg:classifiers":[
        {
            "category":"Restaurant",
            "type":"Food & Drink"
        }
    ],
    "sg:phone":"+1 608 754 2226",
    "sg:postcode":"53545",
    "sg:province":"WI",
    "sg:tags":[
        "eating"
    ],
    "wof:name":"Italian House II",
    "wof:placetype":"venue"
},
  "geometry": {"coordinates":[-89.00277800000001,42.679785],"type":"Point"}
}