{
  "type": "Feature",
  "properties": {
    "iso:country":"US",
    "sg:address":"637 W Hudson St",
    "sg:city":"Mondovi",
    "sg:classifiers":[
        {
            "category":"Social Services",
            "subcategory":"Adult Care",
            "type":"Services"
        }
    ],
    "sg:phone":"+1 715 926 5898",
    "sg:postcode":"54755",
    "sg:province":"WI",
    "sg:tags":[
        "home"
    ],
    "wof:name":"Step-By-Step Adult Family Home",
    "wof:placetype":"venue"
},
  "geometry": {"coordinates":[-91.67695,44.566625],"type":"Point"}
}