{
  "type": "Feature",
  "properties": {
    "addr:full":"3037 N 44th St Milwaukee WI 53210",
    "addr:housenumber":"3037",
    "addr:postcode":"53210",
    "addr:street":"N 44Th St",
    "iso:country":"US",
    "sg:address":"3037 N 44th St",
    "sg:city":"Milwaukee",
    "sg:classifiers":[
        {
            "category":"Building & Trades",
            "subcategory":"Cleaning & Sanitation",
            "type":"Services"
        }
    ],
    "sg:phone":"+1 414 442 5030",
    "sg:postcode":"53210",
    "sg:province":"WI",
    "sg:tags":[
        "house"
    ],
    "wof:name":"Spic & Span Home Cleaning Svc",
    "wof:placetype":"venue"
},
  "geometry": {"coordinates":[-87.968762,43.074537],"type":"Point"}
}