{
  "type": "Feature",
  "properties": {
    "iso:country":"US",
    "sg:address":"2146 Krause Rd",
    "sg:city":"Marinette",
    "sg:classifiers":[
        {
            "category":"Manufacturing",
            "subcategory":"Metals",
            "type":"Manufacturing & Wholesale Goods"
        }
    ],
    "sg:phone":"+1 715 732 1719",
    "sg:postcode":"54157",
    "sg:province":"WI",
    "sg:tags":[
        "blast",
        "furnace",
        "works"
    ],
    "wof:name":"Stainless Mfg Inc",
    "wof:placetype":"venue"
},
  "geometry": {"coordinates":[-87.647652,45.039024],"type":"Point"}
}