{
  "type": "Feature",
  "properties": {
    "iso:country":"US",
    "sg:address":"614 Bakke St",
    "sg:city":"De Forest",
    "sg:classifiers":[
        {
            "category":"Wholesale",
            "subcategory":"Motor Vehicles",
            "type":"Manufacturing & Wholesale Goods"
        }
    ],
    "sg:phone":"+1 608 846 0776",
    "sg:postcode":"53532",
    "sg:province":"WI",
    "sg:tags":[
        "bus"
    ],
    "wof:name":"Wisconsin Bus Sales & Svc",
    "wof:placetype":"venue"
},
  "geometry": {"coordinates":[-89.3336,43.254652],"type":"Point"}
}