{
  "type": "Feature",
  "properties": {
    "iso:country":"US",
    "sg:address":"101 Elm St",
    "sg:city":"Odanah",
    "sg:classifiers":[
        {
            "category":"Social Services",
            "type":"Services"
        }
    ],
    "sg:phone":"+1 715 682 8379",
    "sg:postcode":"54801",
    "sg:province":"WI",
    "sg:tags":[
        "information",
        "abuse",
        "treatment",
        "center"
    ],
    "wof:name":"BAD River Domestic Abuse Prg",
    "wof:placetype":"venue"
},
  "geometry": {"coordinates":[-91.887569,45.82765],"type":"Point"}
}