{
  "type": "Feature",
  "properties": {
    "iso:country":"US",
    "sg:address":"9297 Co Rd B",
    "sg:city":"Coleman",
    "sg:classifiers":[
        {
            "category":"Building & Trades",
            "subcategory":"Plumbing",
            "type":"Services"
        }
    ],
    "sg:phone":"+1 920 897 3061",
    "sg:postcode":"54112",
    "sg:province":"WI",
    "sg:tags":[
        "contractor"
    ],
    "wof:name":"Borkowski Plumbing",
    "wof:placetype":"venue"
},
  "geometry": {"coordinates":[-88.064587,45.065799],"type":"Point"}
}