{
  "type": "Feature",
  "properties": {
    "iso:country":"US",
    "sg:address":"531 S Fulton St",
    "sg:city":"Princeton",
    "sg:classifiers":[
        {
            "category":"Government",
            "subcategory":"Police Station",
            "type":"Public Place"
        }
    ],
    "sg:phone":"+1 920 295 6250",
    "sg:postcode":"54968",
    "sg:province":"WI",
    "sg:tags":[
        "department"
    ],
    "wof:name":"Princeton Police Dept",
    "wof:placetype":"venue"
},
  "geometry": {"coordinates":[-89.122952,43.845859],"type":"Point"}
}