{
  "type": "Feature",
  "properties": {
    "iso:country":"US",
    "sg:address":"8532 Co Rd Vv",
    "sg:city":"Berlin",
    "sg:classifiers":[
        {
            "category":"Communications",
            "type":"Services"
        }
    ],
    "sg:phone":"+1 920 361 7710",
    "sg:postcode":"54923",
    "sg:province":"WI",
    "wof:name":"Pinnacle Towers Inc",
    "wof:placetype":"venue"
},
  "geometry": {"coordinates":[-88.93647,43.940057],"type":"Point"}
}