{
  "type": "Feature",
  "properties": {
    "addr:full":"135 E Lake View Ave Milwaukee WI 53217",
    "addr:housenumber":"135",
    "addr:postcode":"53217",
    "addr:street":"E Lake View Ave",
    "iso:country":"US",
    "sg:address":"135 E Lake View Ave",
    "sg:city":"Milwaukee",
    "sg:classifiers":[
        {
            "category":"Organizations",
            "subcategory":"Religious Organization",
            "type":"Services"
        }
    ],
    "sg:phone":"+1 414 332 8666",
    "sg:postcode":"53217",
    "sg:province":"WI",
    "sg:tags":[
        "monastery",
        "convent"
    ],
    "sg:website":"http://www.sinsinawa.org",
    "wof:name":"Dominican Convent",
    "wof:placetype":"venue"
},
  "geometry": {"coordinates":[-87.90924800000001,43.120604],"type":"Point"}
}