{
  "type": "Feature",
  "properties": {
    "iso:country":"US",
    "sg:address":"3080 Market St",
    "sg:city":"Green Bay",
    "sg:classifiers":[
        {
            "category":"Shopping",
            "subcategory":"Hobbies, Toys, & Games",
            "type":"Retail Goods"
        },
        {
            "category":"Autos & Motor Vehicles",
            "subcategory":"Auto Supplies",
            "type":"Retail Goods"
        }
    ],
    "sg:phone":"+1 920 339 5262",
    "sg:postcode":"54304",
    "sg:province":"WI",
    "sg:tags":[
        "trailer",
        "hitch"
    ],
    "wof:name":"Toys For Trucks Inc",
    "wof:placetype":"venue"
},
  "geometry": {"coordinates":[-88.084917,44.464441],"type":"Point"}
}