{
  "type": "Feature",
  "properties": {
    "iso:country":"US",
    "sg:address":"105 Meadow Lark Ln",
    "sg:city":"Osceola",
    "sg:classifiers":[
        {
            "category":"Retail",
            "subcategory":"Repair Shop",
            "type":"Services"
        }
    ],
    "sg:phone":"+1 715 294 3417",
    "sg:postcode":"54020",
    "sg:province":"WI",
    "wof:name":"Bierbrauer Upholstery Etc Ltd",
    "wof:placetype":"venue"
},
  "geometry": {"coordinates":[-92.682994,45.31548],"type":"Point"}
}