{
  "type": "Feature",
  "properties": {
    "iso:country":"US",
    "sg:address":"608 Dorr St",
    "sg:city":"Antigo",
    "sg:classifiers":[
        {
            "category":"Bars & Pubs",
            "type":"Food & Drink"
        }
    ],
    "sg:phone":"+1 715 623 3426",
    "sg:postcode":"54409",
    "sg:province":"WI",
    "wof:name":"Beer 30",
    "wof:placetype":"venue"
},
  "geometry": {"coordinates":[-89.157631,45.141907],"type":"Point"}
}