{
  "type": "Feature",
  "properties": {
    "addr:full":"537 S Nicolet Rd Appleton WI 54914",
    "addr:housenumber":"537",
    "addr:postcode":"54914",
    "addr:street":"S Nicolet Rd",
    "iso:country":"US",
    "sg:address":"537 S Nicolet Rd",
    "sg:city":"Appleton",
    "sg:classifiers":[
        {
            "category":"Shopping",
            "subcategory":"Jewelry",
            "type":"Retail Goods"
        }
    ],
    "sg:phone":"+1 920 734 5525",
    "sg:postcode":"54914",
    "sg:province":"WI",
    "sg:tags":[
        "jeweler"
    ],
    "wof:name":"Rummele's Jewelers",
    "wof:placetype":"venue"
},
  "geometry": {"coordinates":[-88.46922000000001,44.258023],"type":"Point"}
}