{
  "type": "Feature",
  "properties": {
    "iso:country":"US",
    "sg:address":"254 Troon Ct",
    "sg:city":"Hudson",
    "sg:classifiers":[
        {
            "category":"Manufacturing",
            "subcategory":"Printing",
            "type":"Manufacturing & Wholesale Goods"
        }
    ],
    "sg:phone":"+1 715 386 8930",
    "sg:postcode":"54016",
    "sg:province":"WI",
    "sg:tags":[
        "consulting",
        "management",
        "publishing"
    ],
    "wof:name":"Rodney A Brown Co Inc",
    "wof:placetype":"venue"
},
  "geometry": {"coordinates":[-92.739372,44.898752],"type":"Point"}
}