{
  "type": "Feature",
  "properties": {
    "iso:country":"US",
    "sg:address":"123 N Franklin St",
    "sg:city":"Madison",
    "sg:classifiers":[
        {
            "category":"Building & Trades",
            "subcategory":"Construction",
            "type":"Services"
        }
    ],
    "sg:phone":"+1 608 256 5998",
    "sg:postcode":"53703",
    "sg:province":"WI",
    "sg:tags":[
        "house"
    ],
    "wof:name":"Patrick Crean Construction",
    "wof:placetype":"venue"
},
  "geometry": {"coordinates":[-89.382255,43.079956],"type":"Point"}
}