{
  "type": "Feature",
  "properties": {
    "iso:country":"US",
    "sg:address":"9120 W Hampton Ave",
    "sg:city":"Milwaukee",
    "sg:classifiers":[
        {
            "category":"Insurance",
            "subcategory":"Insurance Agent",
            "type":"Services"
        }
    ],
    "sg:phone":"+1 414 466 4280",
    "sg:postcode":"53225",
    "sg:province":"WI",
    "wof:name":"Charles J Eschner Insurance",
    "wof:placetype":"venue"
},
  "geometry": {"coordinates":[-88.027213,43.105032],"type":"Point"}
}