{
  "type": "Feature",
  "properties": {
    "iso:country":"US",
    "sg:address":"1004 Park Ave",
    "sg:city":"West Bend",
    "sg:classifiers":[
        {
            "category":"Bars & Pubs",
            "type":"Food & Drink"
        }
    ],
    "sg:phone":"+1 262 338 6242",
    "sg:postcode":"53090",
    "sg:province":"WI",
    "sg:tags":[
        "drinking"
    ],
    "wof:name":"Park Ave Pub",
    "wof:placetype":"venue"
},
  "geometry": {"coordinates":[-88.189595,43.434218],"type":"Point"}
}