{
  "type": "Feature",
  "properties": {
    "iso:country":"US",
    "sg:address":"464 Old Hwy 51",
    "sg:city":"Mosinee",
    "sg:classifiers":[
        {
            "category":"Building & Trades",
            "subcategory":"Cleaning & Sanitation",
            "type":"Services"
        }
    ],
    "sg:phone":"+1 715 693 6098",
    "sg:postcode":"54455",
    "sg:province":"WI",
    "sg:tags":[
        "maintenance"
    ],
    "wof:name":"Alpha Cleaning",
    "wof:placetype":"venue"
},
  "geometry": {"coordinates":[-89.690825,44.784902],"type":"Point"}
}