{
  "type": "Feature",
  "properties": {
    "addr:full":"110 W Bayfield St Washburn WI 54891",
    "addr:housenumber":"110",
    "addr:postcode":"54891",
    "addr:street":"W Bayfield St",
    "iso:country":"US",
    "sg:address":"110 W Bayfield St",
    "sg:city":"Washburn",
    "sg:classifiers":[
        {
            "category":"Home & Garden",
            "subcategory":"Hardware",
            "type":"Retail Goods"
        }
    ],
    "sg:phone":"+1 715 373 5401",
    "sg:postcode":"54891",
    "sg:province":"WI",
    "wof:name":"Ungrodt Hardware Co",
    "wof:placetype":"venue"
},
  "geometry": {"coordinates":[-90.892771,46.67222],"type":"Point"}
}