{
  "type": "Feature",
  "properties": {
    "addr:full":"320 E Division St Neillsville WI 54456",
    "addr:housenumber":"320",
    "addr:postcode":"54456",
    "addr:street":"E Division St",
    "iso:country":"US",
    "sg:address":"320 E Division St",
    "sg:city":"Neillsville",
    "sg:classifiers":[
        {
            "category":"Food & Beverages",
            "subcategory":"Groceries & Convenience Stores",
            "type":"Retail Goods"
        }
    ],
    "sg:phone":"+1 715 743 4651",
    "sg:postcode":"54456",
    "sg:province":"WI",
    "sg:tags":[
        "grocer"
    ],
    "wof:name":"Marty's Foods Inc",
    "wof:placetype":"venue"
},
  "geometry": {"coordinates":[-90.59306599999999,44.552641],"type":"Point"}
}