{
  "type": "Feature",
  "properties": {
    "addr:full":"7023 State Hwy 81 Cassville WI 53806",
    "addr:housenumber":"7023",
    "addr:postcode":"53806",
    "addr:street":"State Hwy 81",
    "iso:country":"US",
    "sg:address":"7023 State Hwy 81",
    "sg:city":"Cassville",
    "sg:classifiers":[
        {
            "category":"Restaurant",
            "type":"Food & Drink"
        }
    ],
    "sg:phone":"+1 608 725 5416",
    "sg:postcode":"53806",
    "sg:province":"WI",
    "sg:tags":[
        "eating"
    ],
    "wof:name":"San-Ray",
    "wof:placetype":"venue"
},
  "geometry": {"coordinates":[-90.936494,42.763663],"type":"Point"}
}