{
  "type": "Feature",
  "properties": {
    "iso:country":"US",
    "sg:address":"1151 W Macarthur Ave",
    "sg:city":"Eau Claire",
    "sg:classifiers":[
        {
            "category":"Travel",
            "subcategory":"Hotels & Motels",
            "type":"Entertainment"
        }
    ],
    "sg:phone":"+1 715 832 9731",
    "sg:postcode":"54701",
    "sg:province":"WI",
    "sg:tags":[
        "operation"
    ],
    "wof:name":"Road Star Inn",
    "wof:placetype":"venue"
},
  "geometry": {"coordinates":[-91.51790099999999,44.788155],"type":"Point"}
}