{
  "type": "Feature",
  "properties": {
    "addr:full":"2735 Polar Rd Antigo WI 54409",
    "addr:housenumber":"2735",
    "addr:postcode":"54409",
    "addr:street":"Polar Rd",
    "iso:country":"US",
    "sg:address":"2735 Polar Rd",
    "sg:city":"Antigo",
    "sg:classifiers":[
        {
            "category":"Professional",
            "type":"Services"
        }
    ],
    "sg:phone":"+1 715 627 7847",
    "sg:postcode":"54409",
    "sg:province":"WI",
    "wof:name":"Allen Kolpack",
    "wof:placetype":"venue"
},
  "geometry": {"coordinates":[-88.991489,45.123938],"type":"Point"}
}