{
  "type": "Feature",
  "properties": {
    "addr:full":"9844 Cedar Falls Rd Hazelhurst WI 54531",
    "addr:housenumber":"9844",
    "addr:postcode":"54531",
    "addr:street":"Cedar Falls Rd",
    "iso:country":"US",
    "sg:address":"9844 Cedar Falls Rd",
    "sg:city":"Hazelhurst",
    "sg:classifiers":[
        {
            "category":"Organizations",
            "subcategory":"Non-profit Organization",
            "type":"Services"
        }
    ],
    "sg:phone":"+1 715 356 9268",
    "sg:postcode":"54531",
    "sg:province":"WI",
    "sg:tags":[
        "social"
    ],
    "wof:name":"Habitat For Humanity Intl",
    "wof:placetype":"venue"
},
  "geometry": {"coordinates":[-89.728661,45.802043],"type":"Point"}
}