{
  "type": "Feature",
  "properties": {
    "iso:country":"US",
    "sg:address":"840 N Old World Third St",
    "sg:city":"Milwaukee",
    "sg:classifiers":[
        {
            "category":"Real Estate",
            "subcategory":"Real Estate Agent",
            "type":"Services"
        }
    ],
    "sg:phone":"+1 414 277 1212",
    "sg:postcode":"53203",
    "sg:province":"WI",
    "sg:tags":[
        "operator",
        "dwelling"
    ],
    "wof:name":"Kroscher Property Management",
    "wof:placetype":"venue"
},
  "geometry": {"coordinates":[-87.91443099999999,43.040934],"type":"Point"}
}