{
  "type": "Feature",
  "properties": {
    "iso:country":"US",
    "sg:address":"17630 N Main St",
    "sg:city":"Galesville",
    "sg:classifiers":[
        {
            "category":"Professional",
            "subcategory":"Advertising",
            "type":"Services"
        }
    ],
    "sg:phone":"+1 608 582 4328",
    "sg:postcode":"54630",
    "sg:province":"WI",
    "sg:tags":[
        "counselor"
    ],
    "wof:name":"Severson & Assoc",
    "wof:placetype":"venue"
},
  "geometry": {"coordinates":[-91.341983,44.093407],"type":"Point"}
}