{
  "type": "Feature",
  "properties": {
    "iso:country":"US",
    "sg:address":"7332 W State St",
    "sg:city":"Milwaukee",
    "sg:classifiers":[
        {
            "category":"Professional",
            "subcategory":"Computer Services",
            "type":"Services"
        }
    ],
    "sg:phone":"+1 414 443 1950",
    "sg:postcode":"53213",
    "sg:province":"WI",
    "sg:tags":[
        "website",
        "design",
        "datum"
    ],
    "sg:website":"www.3cm.net",
    "wof:name":"3rd Coast Multimedia LLP",
    "wof:placetype":"venue"
},
  "geometry": {"coordinates":[-88.003434,43.048275],"type":"Point"}
}