{
  "type": "Feature",
  "properties": {
    "iso:country":"US",
    "sg:address":"8699 Neimi Dr",
    "sg:city":"Minocqua",
    "sg:classifiers":[
        {
            "category":"Retail",
            "subcategory":"Car Wash",
            "type":"Services"
        }
    ],
    "sg:phone":"+1 715 358 5550",
    "sg:postcode":"54548",
    "sg:province":"WI",
    "sg:tags":[
        "carwash"
    ],
    "wof:name":"Minocqua Hub Scrub Car Wash",
    "wof:placetype":"venue"
},
  "geometry": {"coordinates":[-89.711973,45.887729],"type":"Point"}
}