{
  "type": "Feature",
  "properties": {
    "addr:full":"2490 Cisco Rd Lake Geneva WI 53147",
    "addr:housenumber":"2490",
    "addr:postcode":"53147",
    "addr:street":"Cisco Rd",
    "iso:country":"US",
    "sg:address":"2490 Cisco Rd",
    "sg:city":"Lake Geneva",
    "sg:classifiers":[
        {
            "category":"Shopping",
            "type":"Retail Goods"
        }
    ],
    "sg:phone":"+1 262 245 0202",
    "sg:postcode":"53147",
    "sg:province":"WI",
    "sg:tags":[
        "art",
        "gallery",
        "dealer"
    ],
    "wof:name":"Christian Art Center-Good Co",
    "wof:placetype":"venue"
},
  "geometry": {"coordinates":[-88.50874899999999,42.581925],"type":"Point"}
}