{
  "type": "Feature",
  "properties": {
    "iso:country":"US",
    "sg:address":"2416 N Wright Rd",
    "sg:city":"Janesville",
    "sg:classifiers":[
        {
            "category":"Organizations",
            "subcategory":"Religious Organization",
            "type":"Services"
        }
    ],
    "sg:phone":"+1 608 756 4175",
    "sg:postcode":"53546",
    "sg:province":"WI",
    "sg:tags":[
        "church"
    ],
    "sg:website":"www.nlag.net",
    "wof:name":"New Life Assembly Of God",
    "wof:placetype":"venue"
},
  "geometry": {"coordinates":[-88.973633,42.712927],"type":"Point"}
}