{
  "type": "Feature",
  "properties": {
    "addr:full":"206 S State St Prairie Du Chien WI 53821",
    "addr:housenumber":"206",
    "addr:postcode":"53821",
    "addr:street":"S State St",
    "iso:country":"US",
    "sg:address":"206 S State St",
    "sg:city":"Prairie Du Chien",
    "sg:classifiers":[
        {
            "category":"Building & Trades",
            "subcategory":"Construction",
            "type":"Services"
        }
    ],
    "sg:phone":"+1 608 326 2135",
    "sg:postcode":"53821",
    "sg:province":"WI",
    "sg:tags":[
        "house"
    ],
    "wof:name":"Crowley Const",
    "wof:placetype":"venue"
},
  "geometry": {"coordinates":[-91.136745,43.050325],"type":"Point"}
}