{
  "type": "Feature",
  "properties": {
    "iso:country":"US",
    "sg:address":"1700 E Bolivar Ave",
    "sg:city":"Milwaukee",
    "sg:classifiers":[
        {
            "category":"Professional",
            "subcategory":"Testing Lab",
            "type":"Services"
        }
    ],
    "sg:phone":"+1 414 483 6101",
    "sg:postcode":"53235",
    "sg:province":"WI",
    "sg:tags":[
        "x"
    ],
    "wof:name":"Steege Testing Laboratory",
    "wof:placetype":"venue"
},
  "geometry": {"coordinates":[-87.887015,42.966501],"type":"Point"}
}