{
  "type": "Feature",
  "properties": {
    "iso:country":"US",
    "sg:address":"604 Dells Rd",
    "sg:city":"Silver Lake",
    "sg:classifiers":[
        {
            "category":"Building & Trades",
            "subcategory":"Construction",
            "type":"Services"
        }
    ],
    "sg:phone":"+1 262 889 4819",
    "sg:postcode":"53170",
    "sg:province":"WI",
    "sg:tags":[
        "concrete",
        "contractor"
    ],
    "wof:name":"Nabar Sealcoating",
    "wof:placetype":"venue"
},
  "geometry": {"coordinates":[-88.167768,42.557775],"type":"Point"}
}