{
  "type": "Feature",
  "properties": {
    "iso:country":"US",
    "sg:address":"4460 McHugh Rd",
    "sg:city":"Chilton",
    "sg:classifiers":[
        {
            "category":"Farming",
            "subcategory":"Dairy Farm",
            "type":"Manufacturing & Wholesale Goods"
        }
    ],
    "sg:phone":"+1 920 849 4029",
    "sg:postcode":"53014",
    "sg:province":"WI",
    "wof:name":"Thomas J Kiesner",
    "wof:placetype":"venue"
},
  "geometry": {"coordinates":[-88.18298900000001,44.047345],"type":"Point"}
}