{
  "type": "Feature",
  "properties": {
    "iso:country":"US",
    "sg:address":"36 Fairway Ct",
    "sg:city":"Appleton",
    "sg:classifiers":[
        {
            "category":"Retail",
            "subcategory":"Laundry & Dry Cleaning",
            "type":"Services"
        }
    ],
    "sg:phone":"+1 920 733 0905",
    "sg:postcode":"54915",
    "sg:province":"WI",
    "sg:tags":[
        "duct",
        "furnace",
        "chimney",
        "carpet"
    ],
    "wof:name":"Mr Power Clean of Appleton",
    "wof:placetype":"venue"
},
  "geometry": {"coordinates":[-88.395064,44.245278],"type":"Point"}
}