{
  "type": "Feature",
  "properties": {
    "iso:country":"US",
    "sg:address":"15700 W Cleveland Ave",
    "sg:city":"New Berlin",
    "sg:classifiers":[
        {
            "category":"Manufacturing",
            "subcategory":"Printing",
            "type":"Manufacturing & Wholesale Goods"
        }
    ],
    "sg:phone":"+1 262 798 1234",
    "sg:postcode":"53151",
    "sg:province":"WI",
    "sg:tags":[
        "newspaper"
    ],
    "sg:website":"www.cninewsonline.com",
    "wof:name":"This Week Publications",
    "wof:placetype":"venue"
},
  "geometry": {"coordinates":[-88.109147,42.995602],"type":"Point"}
}