{
  "type": "Feature",
  "properties": {
    "addr:full":"7235 State Hwy 42 Algoma WI 54201",
    "addr:housenumber":"7235",
    "addr:postcode":"54201",
    "addr:street":"State Hwy 42",
    "iso:country":"US",
    "sg:address":"7235 State Hwy 42",
    "sg:city":"Algoma",
    "sg:classifiers":[
        {
            "category":"Home & Garden",
            "subcategory":"Building Materials",
            "type":"Retail Goods"
        }
    ],
    "sg:phone":"+1 920 487 5201",
    "sg:postcode":"54201",
    "sg:province":"WI",
    "sg:tags":[
        "lumber"
    ],
    "wof:name":"Lakeview Lumber Co",
    "wof:placetype":"venue"
},
  "geometry": {"coordinates":[-87.449618,44.583686],"type":"Point"}
}