{
  "type": "Feature",
  "properties": {
    "iso:country":"US",
    "sg:address":"751 Millbrook Dr",
    "sg:city":"Neenah",
    "sg:classifiers":[
        {
            "category":"Professional",
            "subcategory":"Advertising",
            "type":"Services"
        }
    ],
    "sg:phone":"+1 920 729 9110",
    "sg:postcode":"54956",
    "sg:province":"WI",
    "sg:tags":[
        "agency"
    ],
    "wof:name":"Norfscot Group",
    "wof:placetype":"venue"
},
  "geometry": {"coordinates":[-88.474744,44.226578],"type":"Point"}
}