{
  "type": "Feature",
  "properties": {
    "iso:country":"US",
    "sg:address":"400 Chaffee Rd",
    "sg:city":"Oconomowoc",
    "sg:classifiers":[
        {
            "category":"Manufacturing",
            "subcategory":"Tools & Machinery",
            "type":"Manufacturing & Wholesale Goods"
        }
    ],
    "sg:phone":"+1 262 567 5401",
    "sg:postcode":"53066",
    "sg:province":"WI",
    "sg:tags":[
        "industrial",
        "mfg"
    ],
    "wof:name":"Emery Machine & Tool Company",
    "wof:placetype":"venue"
},
  "geometry": {"coordinates":[-88.52210599999999,43.114762],"type":"Point"}
}