{
  "type": "Feature",
  "properties": {
    "iso:country":"US",
    "sg:address":"10015 W Greenfield Ave",
    "sg:city":"Milwaukee",
    "sg:classifiers":[
        {
            "category":"Banks & Credit Unions",
            "subcategory":"Bank",
            "type":"Services"
        }
    ],
    "sg:phone":"+1 414 778 1000",
    "sg:postcode":"53214",
    "sg:province":"WI",
    "sg:tags":[
        "state",
        "loan",
        "broker"
    ],
    "sg:website":"www.statecentral.com",
    "wof:name":"State Central Credit Union",
    "wof:placetype":"venue"
},
  "geometry": {"coordinates":[-88.038382,43.016518],"type":"Point"}
}