{
  "type": "Feature",
  "properties": {
    "iso:country":"US",
    "sg:address":"24136 Leap Rd",
    "sg:city":"Norwalk",
    "sg:classifiers":[
        {
            "category":"Farming",
            "subcategory":"Dairy Farm",
            "type":"Manufacturing & Wholesale Goods"
        }
    ],
    "sg:phone":"+1 608 823 7794",
    "sg:postcode":"54648",
    "sg:province":"WI",
    "wof:name":"Gary Leis",
    "wof:placetype":"venue"
},
  "geometry": {"coordinates":[-90.601544,43.825226],"type":"Point"}
}