{
  "type": "Feature",
  "properties": {
    "iso:country":"US",
    "sg:address":"249 Co Rd F",
    "sg:city":"Armstrong Creek",
    "sg:classifiers":[
        {
            "category":"Freight",
            "type":"Transportation"
        }
    ],
    "sg:phone":"+1 715 336 2557",
    "sg:postcode":"54103",
    "sg:province":"WI",
    "sg:tags":[
        "operator",
        "local",
        "trucking"
    ],
    "wof:name":"Frydrych Richard Trucking",
    "wof:placetype":"venue"
},
  "geometry": {"coordinates":[-88.427787,45.715499],"type":"Point"}
}