{
  "type": "Feature",
  "properties": {
    "addr:full":"7862 S Shore Medford WI 54451",
    "addr:housenumber":"7862",
    "addr:postcode":"54451",
    "addr:street":"S",
    "iso:country":"US",
    "sg:address":"7862 S Shore",
    "sg:city":"Medford",
    "sg:classifiers":[
        {
            "category":"Manufacturing",
            "subcategory":"Lumber",
            "type":"Manufacturing & Wholesale Goods"
        }
    ],
    "sg:phone":"+1 715 785 7497",
    "sg:postcode":"54451",
    "sg:province":"WI",
    "sg:tags":[
        "product",
        "forest",
        "gathering"
    ],
    "wof:name":"Schmidt Ginsing Gardens",
    "wof:placetype":"venue"
},
  "geometry": {"coordinates":[-90.450305,45.212017],"type":"Point"}
}