{
  "type": "Feature",
  "properties": {
    "addr:full":"1014 Lorraine Dr Madison WI 53705",
    "addr:housenumber":"1014",
    "addr:postcode":"53705",
    "addr:street":"Lorraine Dr",
    "iso:country":"US",
    "sg:address":"1014 Lorraine Dr",
    "sg:city":"Madison",
    "sg:classifiers":[
        {
            "category":"Building & Trades",
            "subcategory":"Cleaning & Sanitation",
            "type":"Services"
        }
    ],
    "sg:phone":"+1 608 236 9242",
    "sg:postcode":"53705",
    "sg:province":"WI",
    "sg:tags":[
        "house"
    ],
    "wof:name":"Lifestyle Cleaning",
    "wof:placetype":"venue"
},
  "geometry": {"coordinates":[-89.474334,43.080198],"type":"Point"}
}