{
  "type": "Feature",
  "properties": {
    "iso:country":"US",
    "sg:address":"16095 W Bluemound Rd",
    "sg:city":"Brookfield",
    "sg:classifiers":[
        {
            "category":"Shopping",
            "type":"Retail Goods"
        }
    ],
    "sg:phone":"+1 262 784 2632",
    "sg:postcode":"53005",
    "sg:province":"WI",
    "sg:tags":[
        "pet",
        "shop"
    ],
    "wof:name":"PETCO",
    "wof:placetype":"venue"
},
  "geometry": {"coordinates":[-88.116761,43.036402],"type":"Point"}
}