{
  "type": "Feature",
  "properties": {
    "iso:country":"US",
    "sg:address":"324 Dover Way",
    "sg:city":"Sun Prairie",
    "sg:classifiers":[
        {
            "category":"Professional",
            "subcategory":"Computer Services",
            "type":"Services"
        }
    ],
    "sg:phone":"+1 608 825 4345",
    "sg:postcode":"53590",
    "sg:province":"WI",
    "sg:tags":[
        "consultant",
        "designer"
    ],
    "wof:name":"Compter Technology Integrators",
    "wof:placetype":"venue"
},
  "geometry": {"coordinates":[-89.22991500000001,43.178258],"type":"Point"}
}