{
  "type": "Feature",
  "properties": {
    "iso:country":"US",
    "sg:address":"3161 Port Rd",
    "sg:city":"Wisconsin Rapids",
    "sg:classifiers":[
        {
            "category":"Building & Trades",
            "subcategory":"Construction",
            "type":"Services"
        }
    ],
    "sg:phone":"+1 715 887 2484",
    "sg:postcode":"54495",
    "sg:province":"WI",
    "sg:tags":[
        "excavation",
        "contractor"
    ],
    "wof:name":"Jim Haessly Excavating",
    "wof:placetype":"venue"
},
  "geometry": {"coordinates":[-89.884913,44.359256],"type":"Point"}
}