{
  "type": "Feature",
  "properties": {
    "iso:country":"US",
    "sg:address":"5444 W Forest Home Ave",
    "sg:city":"Milwaukee",
    "sg:classifiers":[
        {
            "category":"Utilities",
            "subcategory":"Telephone",
            "type":"Services"
        }
    ],
    "sg:phone":"+1 414 431 1111",
    "sg:postcode":"53220",
    "sg:province":"WI",
    "sg:tags":[
        "communications"
    ],
    "wof:name":"All In One Communications",
    "wof:placetype":"venue"
},
  "geometry": {"coordinates":[-87.98176100000001,42.980712],"type":"Point"}
}