{
  "type": "Feature",
  "properties": {
    "addr:full":"400 W Main St Durand WI 54736",
    "addr:housenumber":"400",
    "addr:postcode":"54736",
    "addr:street":"W Main St",
    "iso:country":"US",
    "sg:address":"400 W Main St",
    "sg:city":"Durand",
    "sg:classifiers":[
        {
            "category":"Bars & Pubs",
            "type":"Food & Drink"
        }
    ],
    "sg:phone":"+1 715 672 5606",
    "sg:postcode":"54736",
    "sg:province":"WI",
    "sg:tags":[
        "drinking"
    ],
    "wof:name":"Crystal's Landing",
    "wof:placetype":"venue"
},
  "geometry": {"coordinates":[-91.96911799999999,44.627477],"type":"Point"}
}