{
  "type": "Feature",
  "properties": {
    "addr:full":"2622 Hoard St Madison WI 53704",
    "addr:housenumber":"2622",
    "addr:postcode":"53704",
    "addr:street":"Hoard St",
    "iso:country":"US",
    "sg:address":"2622 Hoard St",
    "sg:city":"Madison",
    "sg:classifiers":[
        {
            "category":"Social Services",
            "type":"Services"
        }
    ],
    "sg:phone":"+1 608 244 8491",
    "sg:postcode":"53704",
    "sg:province":"WI",
    "wof:name":"Autism Resources Network",
    "wof:placetype":"venue"
},
  "geometry": {"coordinates":[-89.351117,43.105059],"type":"Point"}
}