{
  "type": "Feature",
  "properties": {
    "iso:country":"US",
    "sg:address":"200 N Executive Dr",
    "sg:city":"Brookfield",
    "sg:classifiers":[
        {
            "category":"Building & Trades",
            "subcategory":"Construction",
            "type":"Services"
        }
    ],
    "sg:phone":"+1 262 780 1470",
    "sg:postcode":"53005",
    "sg:province":"WI",
    "sg:tags":[
        "home",
        "builder"
    ],
    "wof:name":"Monarch Homes",
    "wof:placetype":"venue"
},
  "geometry": {"coordinates":[-88.11474200000001,43.032829],"type":"Point"}
}