{
  "type": "Feature",
  "properties": {
    "iso:country":"US",
    "sg:address":"14 Bowen St",
    "sg:city":"Oshkosh",
    "sg:classifiers":[
        {
            "category":"Insurance",
            "subcategory":"Insurance Agent",
            "type":"Services"
        }
    ],
    "sg:phone":"+1 920 233 2725",
    "sg:postcode":"54901",
    "sg:province":"WI",
    "wof:name":"Marco Agency",
    "wof:placetype":"venue"
},
  "geometry": {"coordinates":[-88.527518,44.011336],"type":"Point"}
}