{
  "type": "Feature",
  "properties": {
    "iso:country":"US",
    "sg:address":"4604 N 89th St",
    "sg:city":"Wausau",
    "sg:classifiers":[
        {
            "category":"Retail",
            "subcategory":"Auto Repair",
            "type":"Services"
        }
    ],
    "sg:phone":"+1 715 848 4807",
    "sg:postcode":"54403",
    "sg:province":"WI",
    "sg:tags":[
        "automobile",
        "restoration",
        "classic"
    ],
    "wof:name":"Zastrow Rod",
    "wof:placetype":"venue"
},
  "geometry": {"coordinates":[-89.51251999999999,45.008572],"type":"Point"}
}