{
  "type": "Feature",
  "properties": {
    "addr:full":"3610 Mall Dr Eau Claire WI 54701",
    "addr:housenumber":"3610",
    "addr:postcode":"54701",
    "addr:street":"Mall Dr",
    "iso:country":"US",
    "sg:address":"3610 Mall Dr",
    "sg:city":"Eau Claire",
    "sg:classifiers":[
        {
            "category":"Shopping",
            "subcategory":"Computers & Home Electronics",
            "type":"Retail Goods"
        }
    ],
    "sg:phone":"+1 715 835 8130",
    "sg:postcode":"54701",
    "sg:province":"WI",
    "sg:tags":[
        "software"
    ],
    "wof:name":"Corporate Technologies",
    "wof:placetype":"venue"
},
  "geometry": {"coordinates":[-91.46081100000001,44.779566],"type":"Point"}
}