{
  "type": "Feature",
  "properties": {
    "iso:country":"US",
    "sg:address":"1744 N Palmer St",
    "sg:city":"Milwaukee",
    "sg:classifiers":[
        {
            "category":"Professional",
            "subcategory":"Business Services",
            "type":"Services"
        }
    ],
    "sg:phone":"+1 414 264 7773",
    "sg:postcode":"53212",
    "sg:province":"WI",
    "wof:name":"Lote Group",
    "wof:placetype":"venue"
},
  "geometry": {"coordinates":[-87.90968599999999,43.053755],"type":"Point"}
}