{
  "type": "Feature",
  "properties": {
    "iso:country":"US",
    "sg:address":"5800 N 87th St",
    "sg:city":"Milwaukee",
    "sg:classifiers":[
        {
            "category":"Retail",
            "subcategory":"Auto Repair",
            "type":"Services"
        }
    ],
    "sg:phone":"+1 414 462 9359",
    "sg:postcode":"53225",
    "sg:province":"WI",
    "sg:tags":[
        "glass",
        "coating",
        "tinting"
    ],
    "wof:name":"Advance Solar Glass Tinting",
    "wof:placetype":"venue"
},
  "geometry": {"coordinates":[-88.01953399999999,43.12385],"type":"Point"}
}