{
  "type": "Feature",
  "properties": {
    "iso:country":"US",
    "sg:address":"424 E Grand Ave",
    "sg:city":"Beloit",
    "sg:classifiers":[
        {
            "category":"Shopping",
            "subcategory":"Gifts & Souvenirs",
            "type":"Retail Goods"
        }
    ],
    "sg:phone":"+1 608 362 1605",
    "sg:postcode":"53511",
    "sg:province":"WI",
    "sg:tags":[
        "party",
        "supply"
    ],
    "wof:name":"Democratic Party Of Wisonsin",
    "wof:placetype":"venue"
},
  "geometry": {"coordinates":[-89.03515,42.499532],"type":"Point"}
}