{
  "type": "Feature",
  "properties": {
    "iso:country":"US",
    "sg:address":"1737 S 32nd St",
    "sg:city":"Milwaukee",
    "sg:classifiers":[
        {
            "category":"Building & Trades",
            "subcategory":"Construction",
            "type":"Services"
        }
    ],
    "sg:phone":"+1 414 383 4680",
    "sg:postcode":"53215",
    "sg:province":"WI",
    "sg:tags":[
        "hanging",
        "contractor"
    ],
    "wof:name":"Lunas Painting Juan Luna",
    "wof:placetype":"venue"
},
  "geometry": {"coordinates":[-87.95413000000001,43.010722],"type":"Point"}
}