{
  "type": "Feature",
  "properties": {
    "iso:country":"US",
    "sg:address":"6300 Enterprise Ln",
    "sg:city":"Madison",
    "sg:classifiers":[
        {
            "category":"Real Estate",
            "subcategory":"Real Estate Agent",
            "type":"Services"
        }
    ],
    "sg:phone":"+1 608 268 6300",
    "sg:postcode":"53719",
    "sg:province":"WI",
    "wof:name":"Alfonsi & Grundahl LLC",
    "wof:placetype":"venue"
},
  "geometry": {"coordinates":[-89.492008,43.057736],"type":"Point"}
}