{
  "type": "Feature",
  "properties": {
    "addr:full":"6482 Greenville Dr Greenville WI 54942",
    "addr:housenumber":"6482",
    "addr:postcode":"54942",
    "addr:street":"Greenville Dr",
    "iso:country":"US",
    "sg:address":"6482 Greenville Dr",
    "sg:city":"Greenville",
    "sg:classifiers":[
        {
            "category":"Food & Beverages",
            "subcategory":"Groceries & Convenience Stores",
            "type":"Retail Goods"
        },
        {
            "category":"Shopping",
            "subcategory":"Crafts & Fabrics",
            "type":"Retail Goods"
        }
    ],
    "sg:phone":"+1 920 757 9905",
    "sg:postcode":"54942",
    "sg:province":"WI",
    "sg:tags":[
        "dry"
    ],
    "wof:name":"Bulk Priced Food Shoppe LLC",
    "wof:placetype":"venue"
},
  "geometry": {"coordinates":[-88.514171,44.289347],"type":"Point"}
}