{
  "type": "Feature",
  "properties": {
    "addr:full":"6037 Sun Valley Pkwy Oregon WI 53575",
    "addr:housenumber":"6037",
    "addr:postcode":"53575",
    "addr:street":"Sun Valley Pkwy",
    "iso:country":"US",
    "sg:address":"6037 Sun Valley Pkwy",
    "sg:city":"Oregon",
    "sg:classifiers":[
        {
            "category":"Wholesale",
            "subcategory":"Machinery & Supplies",
            "type":"Manufacturing & Wholesale Goods"
        }
    ],
    "sg:phone":"+1 608 220 6054",
    "sg:postcode":"53575",
    "sg:province":"WI",
    "sg:tags":[
        "industrial"
    ],
    "wof:name":"FIC Supply Company",
    "wof:placetype":"venue"
},
  "geometry": {"coordinates":[-89.458839,42.929084],"type":"Point"}
}