{
  "type": "Feature",
  "properties": {
    "iso:country":"US",
    "sg:address":"4525 S Co Rd T",
    "sg:city":"Brodhead",
    "sg:phone":"+1 608 897 4459",
    "sg:postcode":"53520",
    "sg:province":"WI",
    "sg:tags":[
        "farm",
        "corn",
        "soybean"
    ],
    "wof:name":"S Edward Kuhse",
    "wof:placetype":"venue"
},
  "geometry": {"coordinates":[-89.366894,42.615558],"type":"Point"}
}