{
  "type": "Feature",
  "properties": {
    "addr:full":"165 W Humble Ave Ellsworth WI 54011",
    "addr:housenumber":"165",
    "addr:postcode":"54011",
    "addr:street":"W Humble Ave",
    "iso:country":"US",
    "sg:address":"165 W Humble Ave",
    "sg:city":"Ellsworth",
    "sg:classifiers":[
        {
            "category":"Farming",
            "subcategory":"Dairy Farm",
            "type":"Manufacturing & Wholesale Goods"
        }
    ],
    "sg:phone":"+1 715 273 3626",
    "sg:postcode":"54011",
    "sg:province":"WI",
    "sg:tags":[
        "field",
        "corn",
        "crop"
    ],
    "wof:name":"Jerome Murphy",
    "wof:placetype":"venue"
},
  "geometry": {"coordinates":[-92.47815900000001,44.725452],"type":"Point"}
}