{
  "type": "Feature",
  "properties": {
    "addr:full":"311 West Blvd Roberts WI 54023",
    "addr:housenumber":"311",
    "addr:postcode":"54023",
    "addr:street":"West Blvd",
    "iso:country":"US",
    "sg:address":"311 West Blvd",
    "sg:city":"Roberts",
    "sg:classifiers":[
        {
            "category":"Retail",
            "subcategory":"Repair Shop",
            "type":"Services"
        }
    ],
    "sg:phone":"+1 715 749 1724",
    "sg:postcode":"54023",
    "sg:province":"WI",
    "wof:name":"Todd Dull Horseshoeing",
    "wof:placetype":"venue"
},
  "geometry": {"coordinates":[-92.557665,44.980734],"type":"Point"}
}