{
  "type": "Feature",
  "properties": {
    "addr:full":"3470 Gateway Rd Brookfield WI 53045",
    "addr:housenumber":"3470",
    "addr:postcode":"53045",
    "addr:street":"Gateway Rd",
    "iso:country":"US",
    "sg:address":"3470 Gateway Rd",
    "sg:city":"Brookfield",
    "sg:classifiers":[
        {
            "category":"Banks & Credit Unions",
            "subcategory":"Bank",
            "type":"Services"
        }
    ],
    "sg:phone":"+1 262 781 0100",
    "sg:postcode":"53045",
    "sg:province":"WI",
    "sg:tags":[
        "saving",
        "commercial"
    ],
    "sg:website":"http://www.uhb-fl.com",
    "wof:name":"M & I Marshall & Ilsley Bank Inc",
    "wof:placetype":"venue"
},
  "geometry": {"coordinates":[-88.181152,43.081589],"type":"Point"}
}