{
  "type": "Feature",
  "properties": {
    "iso:country":"US",
    "sg:address":"665 80th Ave",
    "sg:city":"Amery",
    "sg:classifiers":[
        {
            "category":"Farming",
            "subcategory":"Farm",
            "type":"Manufacturing & Wholesale Goods"
        }
    ],
    "sg:phone":"+1 715 268 2322",
    "sg:postcode":"54001",
    "sg:province":"WI",
    "sg:tags":[
        "corn",
        "dairy",
        "crop",
        "general"
    ],
    "wof:name":"Lawrence Ploszay",
    "wof:placetype":"venue"
},
  "geometry": {"coordinates":[-92.29802,45.32468],"type":"Point"}
}