{
  "type": "Feature",
  "properties": {
    "iso:country":"US",
    "sg:address":"812 S Fisk St",
    "sg:city":"Green Bay",
    "sg:classifiers":[
        {
            "category":"Real Estate",
            "subcategory":"Real Estate Agent",
            "type":"Services"
        }
    ],
    "sg:phone":"+1 920 965 1081",
    "sg:postcode":"54304",
    "sg:province":"WI",
    "wof:name":"Sloan & Assoc Realtors",
    "wof:placetype":"venue"
},
  "geometry": {"coordinates":[-88.062001,44.519228],"type":"Point"}
}