{
  "type": "Feature",
  "properties": {
    "iso:country":"US",
    "sg:address":"2536 Center Ave",
    "sg:city":"Janesville",
    "sg:classifiers":[
        {
            "category":"Home & Garden",
            "subcategory":"Building Materials",
            "type":"Retail Goods"
        },
        {
            "category":"Building & Trades",
            "subcategory":"Construction",
            "type":"Services"
        }
    ],
    "sg:phone":"+1 608 754 4411",
    "sg:postcode":"53546",
    "sg:province":"WI",
    "sg:tags":[
        "glass",
        "window",
        "glazing",
        "contractor",
        "plate"
    ],
    "wof:name":"City Glass Co Inc",
    "wof:placetype":"venue"
},
  "geometry": {"coordinates":[-89.031218,42.645883],"type":"Point"}
}