{
  "type": "Feature",
  "properties": {
    "iso:country":"US",
    "sg:address":"4771 Dovenberg Rd",
    "sg:city":"West Salem",
    "sg:classifiers":[
        {
            "category":"Banks & Credit Unions",
            "subcategory":"Financial Services",
            "type":"Services"
        }
    ],
    "sg:phone":"+1 608 786 1826",
    "sg:postcode":"54669",
    "sg:province":"WI",
    "sg:tags":[
        "investor"
    ],
    "wof:name":"Dovenberg Investments",
    "wof:placetype":"venue"
},
  "geometry": {"coordinates":[-91.03281800000001,43.894286],"type":"Point"}
}