{
  "type": "Feature",
  "properties": {
    "iso:country":"US",
    "sg:address":"407 N Main St",
    "sg:city":"Thiensville",
    "sg:classifiers":[
        {
            "category":"Health Services",
            "subcategory":"Medical Lab",
            "type":"Services"
        }
    ],
    "sg:phone":"+1 262 242 0007",
    "sg:postcode":"53092",
    "sg:province":"WI",
    "sg:tags":[
        "laboratory"
    ],
    "wof:name":"Milwaukee Diagnostic",
    "wof:placetype":"venue"
},
  "geometry": {"coordinates":[-87.985574,43.239768],"type":"Point"}
}