{
  "type": "Feature",
  "properties": {
    "iso:country":"US",
    "sg:address":"2909 Perry St",
    "sg:city":"Madison",
    "sg:classifiers":[
        {
            "category":"Wholesale",
            "subcategory":"Office Equipment",
            "type":"Manufacturing & Wholesale Goods"
        }
    ],
    "sg:phone":"+1 608 276 5559",
    "sg:postcode":"53713",
    "sg:province":"WI",
    "sg:website":"www.imagingsystems.net",
    "wof:name":"Imaging Systems Inc",
    "wof:placetype":"venue"
},
  "geometry": {"coordinates":[-89.396388,43.031357],"type":"Point"}
}