{
  "type": "Feature",
  "properties": {
    "addr:full":"908 Main St Plum City WI 54761",
    "addr:housenumber":"908",
    "addr:postcode":"54761",
    "addr:street":"Main St",
    "iso:country":"US",
    "sg:address":"908 Main St",
    "sg:city":"Plum City",
    "sg:classifiers":[
        {
            "category":"Real Estate",
            "subcategory":"Real Estate Operator",
            "type":"Services"
        }
    ],
    "sg:phone":"+1 715 647 4008",
    "sg:postcode":"54761",
    "sg:province":"WI",
    "sg:tags":[
        "property",
        "lessor"
    ],
    "wof:name":"Barry White",
    "wof:placetype":"venue"
},
  "geometry": {"coordinates":[-92.19277599999999,44.634076],"type":"Point"}
}