{
  "type": "Feature",
  "properties": {
    "iso:country":"US",
    "sg:address":"813 Fox Ln",
    "sg:city":"Waterford",
    "sg:classifiers":[
        {
            "category":"Building & Trades",
            "subcategory":"Construction",
            "type":"Services"
        }
    ],
    "sg:phone":"+1 262 534 1974",
    "sg:postcode":"53185",
    "sg:province":"WI",
    "sg:tags":[
        "contractor"
    ],
    "wof:name":"Dependable Fireplace Co",
    "wof:placetype":"venue"
},
  "geometry": {"coordinates":[-88.200058,42.766392],"type":"Point"}
}