{
  "type": "Feature",
  "properties": {
    "iso:country":"US",
    "sg:address":"303 S Paterson St",
    "sg:city":"Madison",
    "sg:classifiers":[
        {
            "category":"Shopping",
            "subcategory":"Books",
            "type":"Retail Goods"
        }
    ],
    "sg:phone":"+1 608 257 1509",
    "sg:postcode":"53703",
    "sg:province":"WI",
    "sg:tags":[
        "dealer"
    ],
    "wof:name":"Jim Sonny Books",
    "wof:placetype":"venue"
},
  "geometry": {"coordinates":[-89.369925,43.079864],"type":"Point"}
}