{
  "type": "Feature",
  "properties": {
    "iso:country":"US",
    "sg:address":"559 Donofrio Dr",
    "sg:city":"Madison",
    "sg:classifiers":[
        {
            "category":"Professional",
            "subcategory":"Business Services",
            "type":"Services"
        }
    ],
    "sg:phone":"+1 608 833 1845",
    "sg:postcode":"53719",
    "sg:province":"WI",
    "sg:tags":[
        "telemarketing"
    ],
    "wof:name":"Select Enterprises",
    "wof:placetype":"venue"
},
  "geometry": {"coordinates":[-89.515984,43.056808],"type":"Point"}
}