{
  "type": "Feature",
  "properties": {
    "addr:full":"1505 Greenway Ter Waukesha WI 53186",
    "addr:housenumber":"1505",
    "addr:postcode":"53186",
    "addr:street":"Greenway Ter",
    "iso:country":"US",
    "sg:address":"1505 Greenway Ter",
    "sg:city":"Waukesha",
    "sg:classifiers":[
        {
            "category":"Health Services",
            "subcategory":"Nursing And Care Facility",
            "type":"Services"
        }
    ],
    "sg:phone":"+1 262 524 7895",
    "sg:postcode":"53186",
    "sg:province":"WI",
    "wof:name":"Caring For You LLC",
    "wof:placetype":"venue"
},
  "geometry": {"coordinates":[-88.206013,43.026846],"type":"Point"}
}