{
  "type": "Feature",
  "properties": {
    "iso:country":"US",
    "sg:address":"1895 Breezy Bay Rd",
    "sg:city":"Balsam Lake",
    "sg:classifiers":[
        {
            "category":"Professional",
            "subcategory":"Business Services",
            "type":"Services"
        }
    ],
    "sg:phone":"+1 715 825 4188",
    "sg:postcode":"54810",
    "sg:province":"WI",
    "wof:name":"Kountry By Kim",
    "wof:placetype":"venue"
},
  "geometry": {"coordinates":[-92.417178,45.481364],"type":"Point"}
}