{
  "type": "Feature",
  "properties": {
    "addr:full":"642 Campfire Dr West Salem WI 54669",
    "addr:housenumber":"642",
    "addr:postcode":"54669",
    "addr:street":"Campfire Dr",
    "iso:country":"US",
    "sg:address":"642 Campfire Dr",
    "sg:city":"West Salem",
    "sg:classifiers":[
        {
            "category":"Freight",
            "type":"Transportation"
        }
    ],
    "sg:phone":"+1 608 786 3445",
    "sg:postcode":"54669",
    "sg:province":"WI",
    "sg:tags":[
        "trucking"
    ],
    "wof:name":"Logan & Sons Trucking Inc",
    "wof:placetype":"venue"
},
  "geometry": {"coordinates":[-91.095463,43.903647],"type":"Point"}
}