{
  "type": "Feature",
  "properties": {
    "iso:country":"US",
    "sg:address":"149 Shelley Ln",
    "sg:city":"De Pere",
    "sg:classifiers":[
        {
            "category":"Banks & Credit Unions",
            "subcategory":"Bank",
            "type":"Services"
        }
    ],
    "sg:phone":"+1 920 330 9801",
    "sg:postcode":"54115",
    "sg:province":"WI",
    "wof:name":"Irwin Union Bank",
    "wof:placetype":"venue"
},
  "geometry": {"coordinates":[-88.033877,44.443066],"type":"Point"}
}