{
  "type": "Feature",
  "properties": {
    "iso:country":"US",
    "sg:address":"5130 W Forest Home Ave",
    "sg:city":"Milwaukee",
    "sg:classifiers":[
        {
            "category":"Retail",
            "subcategory":"Auto Repair",
            "type":"Services"
        }
    ],
    "sg:phone":"+1 414 327 7200",
    "sg:postcode":"53219",
    "sg:province":"WI",
    "sg:tags":[
        "repairing",
        "automobile",
        "used",
        "car"
    ],
    "sg:website":"http://www.arsautorepair.com",
    "wof:name":"ARS Auto Repair & Towing",
    "wof:placetype":"venue"
},
  "geometry": {"coordinates":[-87.97861399999999,42.982639],"type":"Point"}
}