{
  "type": "Feature",
  "properties": {
    "addr:full":"147 S Main St West Bend WI 53095",
    "addr:housenumber":"147",
    "addr:postcode":"53095",
    "addr:street":"S Main St",
    "iso:country":"US",
    "sg:address":"147 S Main St",
    "sg:city":"West Bend",
    "sg:classifiers":[
        {
            "category":"Restaurant",
            "type":"Food & Drink"
        }
    ],
    "sg:phone":"+1 262 335 0522",
    "sg:postcode":"53095",
    "sg:province":"WI",
    "wof:name":"Simon's Cafe",
    "wof:placetype":"venue"
},
  "geometry": {"coordinates":[-88.182168,43.423069],"type":"Point"}
}