{
  "type": "Feature",
  "properties": {
    "iso:country":"US",
    "sg:address":"123 Elm St",
    "sg:city":"Dousman",
    "sg:classifiers":[
        {
            "category":"Shopping",
            "type":"Retail Goods"
        }
    ],
    "sg:phone":"+1 262 965 3114",
    "sg:postcode":"53118",
    "sg:province":"WI",
    "sg:tags":[
        "merchandise"
    ],
    "wof:name":"Wisconsin Integrated Systems",
    "wof:placetype":"venue"
},
  "geometry": {"coordinates":[-88.471993,43.014333],"type":"Point"}
}