{
  "type": "Feature",
  "properties": {
    "addr:full":"47213 Ellenberger Ln Eleva WI 54738",
    "addr:postcode":"47213;54738",
    "addr:street":"Ellenberger Ln",
    "iso:country":"US",
    "sg:address":"47213 Ellenberger Ln",
    "sg:city":"Eleva",
    "sg:classifiers":[
        {
            "category":"Government",
            "subcategory":"Office",
            "type":"Public Place"
        }
    ],
    "sg:phone":"+1 715 287 3213",
    "sg:postcode":"54738",
    "sg:province":"WI",
    "sg:tags":[
        "village"
    ],
    "wof:name":"Town Of Albion",
    "wof:placetype":"venue"
},
  "geometry": {"coordinates":[-91.46238099999999,44.527591],"type":"Point"}
}