{
  "type": "Feature",
  "properties": {
    "iso:country":"US",
    "sg:address":"714 N Main St",
    "sg:city":"Bruce",
    "sg:classifiers":[
        {
            "category":"Shopping",
            "subcategory":"Florist",
            "type":"Retail Goods"
        }
    ],
    "sg:phone":"+1 715 868 1000",
    "sg:postcode":"54819",
    "sg:province":"WI",
    "wof:name":"Bruce Floral & Tanning",
    "wof:placetype":"venue"
},
  "geometry": {"coordinates":[-91.27346900000001,45.45681],"type":"Point"}
}