{
  "type": "Feature",
  "properties": {
    "iso:country":"US",
    "sg:address":"6097 Lake Dr",
    "sg:city":"Shawano",
    "sg:classifiers":[
        {
            "category":"Professional",
            "type":"Services"
        }
    ],
    "sg:phone":"+1 715 526 5409",
    "sg:postcode":"54166",
    "sg:province":"WI",
    "wof:name":"Richard W Postl",
    "wof:placetype":"venue"
},
  "geometry": {"coordinates":[-88.568933,44.798689],"type":"Point"}
}