{
  "type": "Feature",
  "properties": {
    "iso:country":"US",
    "sg:address":"3410 Oakwood Mall Dr",
    "sg:city":"Eau Claire",
    "sg:classifiers":[
        {
            "category":"Professional",
            "subcategory":"Business Services",
            "type":"Services"
        }
    ],
    "sg:phone":"+1 715 831 9237",
    "sg:postcode":"54701",
    "sg:province":"WI",
    "wof:name":"Kirklands Inc",
    "wof:placetype":"venue"
},
  "geometry": {"coordinates":[-91.445635,44.776386],"type":"Point"}
}