{
  "type": "Feature",
  "properties": {
    "iso:country":"US",
    "sg:address":"705 W Fulton St",
    "sg:city":"Waupaca",
    "sg:classifiers":[
        {
            "category":"Manufacturing",
            "subcategory":"Food",
            "type":"Manufacturing & Wholesale Goods"
        }
    ],
    "sg:phone":"+1 715 258 4040",
    "sg:postcode":"54981",
    "sg:province":"WI",
    "sg:tags":[
        "cheese",
        "mfg",
        "milk",
        "fluid"
    ],
    "wof:name":"Churny Company Inc (del)",
    "wof:placetype":"venue"
},
  "geometry": {"coordinates":[-89.098962,44.357819],"type":"Point"}
}