{
  "type": "Feature",
  "properties": {
    "iso:country":"US",
    "sg:address":"109 S 17th Ave",
    "sg:city":"Wausau",
    "sg:classifiers":[
        {
            "category":"Autos & Motor Vehicles",
            "subcategory":"Fuel & Gas Station",
            "type":"Retail Goods"
        }
    ],
    "sg:phone":"+1 715 849 8825",
    "sg:postcode":"54401",
    "sg:province":"WI",
    "sg:tags":[
        "station",
        "gasoline"
    ],
    "wof:name":"Kwik Trip",
    "wof:placetype":"venue"
},
  "geometry": {"coordinates":[-89.655277,44.961467],"type":"Point"}
}