{
  "type": "Feature",
  "properties": {
    "addr:full":"1540 Buchanan St Little Chute WI 54140",
    "addr:housenumber":"1540",
    "addr:postcode":"54140",
    "addr:street":"Buchanan St",
    "iso:country":"US",
    "sg:address":"1540 Buchanan St",
    "sg:city":"Little Chute",
    "sg:classifiers":[
        {
            "category":"Building & Trades",
            "subcategory":"Plumbing",
            "type":"Services"
        }
    ],
    "sg:phone":"+1 920 788 6442",
    "sg:postcode":"54140",
    "sg:province":"WI",
    "sg:tags":[
        "mechanical",
        "contractor"
    ],
    "sg:website":"www.leescfi.com",
    "wof:name":"Lee's Welding",
    "wof:placetype":"venue"
},
  "geometry": {"coordinates":[-88.30285000000001,44.289787],"type":"Point"}
}