{
  "type": "Feature",
  "properties": {
    "iso:country":"US",
    "sg:address":"1535 Red Oak Ct",
    "sg:city":"Middleton",
    "sg:classifiers":[
        {
            "category":"Sports & Exercise",
            "subcategory":"Gym",
            "type":"Entertainment"
        }
    ],
    "sg:phone":"+1 608 831 1051",
    "sg:postcode":"53562",
    "sg:province":"WI",
    "sg:tags":[
        "fitness",
        "physical",
        "facility"
    ],
    "wof:name":"A Pilates Studio",
    "wof:placetype":"venue"
},
  "geometry": {"coordinates":[-89.511196,43.090637],"type":"Point"}
}