{
  "type": "Feature",
  "properties": {
    "iso:country":"US",
    "sg:address":"3605 N 126th St",
    "sg:city":"Brookfield",
    "sg:classifiers":[
        {
            "category":"Wholesale",
            "subcategory":"Office Equipment",
            "type":"Manufacturing & Wholesale Goods"
        }
    ],
    "sg:phone":"+1 262 790 9400",
    "sg:postcode":"53005",
    "sg:province":"WI",
    "sg:tags":[
        "vault",
        "safe"
    ],
    "sg:website":"http://www.bonafidesafeandlock.com",
    "wof:name":"Bonafide Safe & Lock",
    "wof:placetype":"venue"
},
  "geometry": {"coordinates":[-88.068988,43.083037],"type":"Point"}
}