{
  "type": "Feature",
  "properties": {
    "iso:country":"US",
    "sg:address":"308 4th St S",
    "sg:city":"La Crosse",
    "sg:classifiers":[
        {
            "category":"Bars & Pubs",
            "type":"Food & Drink"
        }
    ],
    "sg:phone":"+1 608 782 9069",
    "sg:postcode":"54601",
    "sg:province":"WI",
    "sg:tags":[
        "drinking"
    ],
    "wof:name":"Popcorn Tavern",
    "wof:placetype":"venue"
},
  "geometry": {"coordinates":[-91.25184900000001,43.810097],"type":"Point"}
}