{
  "type": "Feature",
  "properties": {
    "addr:full":"16817 W Footville Brodhead Rd Brodhead WI 53520",
    "addr:housenumber":"16817",
    "addr:postcode":"53520",
    "addr:street":"W Footville Brodhead Rd",
    "iso:country":"US",
    "sg:address":"16817 W Footville Brodhead Rd",
    "sg:city":"Brodhead",
    "sg:classifiers":[
        {
            "category":"Farming",
            "subcategory":"Dairy Farm",
            "type":"Manufacturing & Wholesale Goods"
        }
    ],
    "sg:phone":"+1 608 897 4397",
    "sg:postcode":"53520",
    "sg:province":"WI",
    "wof:name":"K Albrecht Dairy Farm",
    "wof:placetype":"venue"
},
  "geometry": {"coordinates":[-89.334326,42.651175],"type":"Point"}
}