{
  "type": "Feature",
  "properties": {
    "iso:country":"US",
    "sg:address":"2232 Redtail Dr",
    "sg:city":"Neenah",
    "sg:classifiers":[
        {
            "category":"Building & Trades",
            "subcategory":"Electrical",
            "type":"Services"
        }
    ],
    "sg:phone":"+1 920 749 0886",
    "sg:postcode":"54956",
    "sg:province":"WI",
    "sg:tags":[
        "electrical",
        "contractor"
    ],
    "wof:name":"Master Electric",
    "wof:placetype":"venue"
},
  "geometry": {"coordinates":[-88.477254,44.234806],"type":"Point"}
}