{
  "type": "Feature",
  "properties": {
    "iso:country":"US",
    "sg:address":"11793 State Hwy 127",
    "sg:city":"Portage",
    "sg:classifiers":[
        {
            "category":"Restaurant",
            "type":"Food & Drink"
        }
    ],
    "sg:phone":"+1 608 742 2238",
    "sg:postcode":"53901",
    "sg:province":"WI",
    "sg:tags":[
        "drinking",
        "eating"
    ],
    "wof:name":"Cimaroli's Supper Club",
    "wof:placetype":"venue"
},
  "geometry": {"coordinates":[-89.580389,43.606494],"type":"Point"}
}