{
  "type": "Feature",
  "properties": {
    "addr:full":"307 Riverview Ct Portage WI 53901",
    "addr:housenumber":"307",
    "addr:postcode":"53901",
    "addr:street":"Riverview Ct",
    "iso:country":"US",
    "sg:address":"307 Riverview Ct",
    "sg:city":"Portage",
    "sg:classifiers":[
        {
            "category":"Shopping",
            "type":"Retail Goods"
        }
    ],
    "sg:phone":"+1 608 742 3919",
    "sg:postcode":"53901",
    "sg:province":"WI",
    "sg:tags":[
        "merchandise"
    ],
    "wof:name":"Livin End Candle Shop LLC",
    "wof:placetype":"venue"
},
  "geometry": {"coordinates":[-89.48626899999999,43.54619],"type":"Point"}
}