{
  "type": "Feature",
  "properties": {
    "iso:country":"US",
    "sg:address":"276 Mineral St",
    "sg:city":"Mineral Point",
    "sg:classifiers":[
        {
            "category":"Manufacturing",
            "subcategory":"Pottery",
            "type":"Manufacturing & Wholesale Goods"
        }
    ],
    "sg:phone":"+1 608 987 3669",
    "sg:postcode":"53565",
    "sg:province":"WI",
    "sg:tags":[
        "mfg"
    ],
    "wof:name":"Johnston Pottery",
    "wof:placetype":"venue"
},
  "geometry": {"coordinates":[-90.18172,42.865071],"type":"Point"}
}