{
  "type": "Feature",
  "properties": {
    "iso:country":"US",
    "sg:address":"1516 Church St",
    "sg:city":"Stevens Point",
    "sg:classifiers":[
        {
            "category":"Health Services",
            "subcategory":"Nursing And Care Facility",
            "type":"Services"
        }
    ],
    "sg:phone":"+1 715 343 6284",
    "sg:postcode":"54481",
    "sg:province":"WI",
    "sg:tags":[
        "home",
        "convalescent"
    ],
    "wof:name":"Portage County Health Care Ctr",
    "wof:placetype":"venue"
},
  "geometry": {"coordinates":[-89.580196,44.520858],"type":"Point"}
}