{
  "type": "Feature",
  "properties": {
    "iso:country":"US",
    "sg:address":"19756 Co Hwy X",
    "sg:city":"Chippewa Falls",
    "sg:classifiers":[
        {
            "category":"Food & Beverages",
            "subcategory":"Groceries & Convenience Stores",
            "type":"Retail Goods"
        }
    ],
    "sg:phone":"+1 715 723 7879",
    "sg:postcode":"54729",
    "sg:province":"WI",
    "wof:name":"Express Mart",
    "wof:placetype":"venue"
},
  "geometry": {"coordinates":[-91.273413,44.929691],"type":"Point"}
}