{
  "type": "Feature",
  "properties": {
    "iso:country":"US",
    "sg:address":"1511 Pearl St",
    "sg:city":"Waukesha",
    "sg:classifiers":[
        {
            "category":"Shopping",
            "subcategory":"News",
            "type":"Retail Goods"
        }
    ],
    "sg:phone":"+1 262 574 9310",
    "sg:postcode":"53186",
    "sg:province":"WI",
    "sg:tags":[
        "magazine"
    ],
    "wof:name":"Seewhy Inc",
    "wof:placetype":"venue"
},
  "geometry": {"coordinates":[-88.201692,43.007707],"type":"Point"}
}