{
  "type": "Feature",
  "properties": {
    "addr:full":"226 Killarney Rd Hartford WI 53027",
    "addr:housenumber":"226",
    "addr:postcode":"53027",
    "addr:street":"Killarney Rd",
    "iso:country":"US",
    "sg:address":"226 Killarney Rd",
    "sg:city":"Hartford",
    "sg:classifiers":[
        {
            "category":"Wholesale",
            "subcategory":"Chemicals & Plastics",
            "type":"Manufacturing & Wholesale Goods"
        }
    ],
    "sg:phone":"+1 262 966 1822",
    "sg:postcode":"53027",
    "sg:province":"WI",
    "sg:tags":[
        "cleaning",
        "compound"
    ],
    "wof:name":"Ecolab Inc",
    "wof:placetype":"venue"
},
  "geometry": {"coordinates":[-88.389257,43.198133],"type":"Point"}
}