{
  "type": "Feature",
  "properties": {
    "iso:country":"US",
    "sg:address":"12503 Gerbig Rd",
    "sg:city":"Marion",
    "sg:classifiers":[
        {
            "category":"Real Estate",
            "subcategory":"Real Estate Agent",
            "type":"Services"
        }
    ],
    "sg:phone":"+1 715 823 3525",
    "sg:postcode":"54950",
    "sg:province":"WI",
    "wof:name":"Appraisal South",
    "wof:placetype":"venue"
},
  "geometry": {"coordinates":[-88.881018,44.690557],"type":"Point"}
}