{
  "type": "Feature",
  "properties": {
    "iso:country":"US",
    "sg:address":"6317 Richfield Dr",
    "sg:city":"Arpin",
    "sg:classifiers":[
        {
            "category":"Recreation",
            "type":"Entertainment"
        }
    ],
    "sg:phone":"+1 715 652 3494",
    "sg:postcode":"54410",
    "sg:province":"WI",
    "sg:tags":[
        "riding",
        "stable"
    ],
    "wof:name":"Riata Ranch",
    "wof:placetype":"venue"
},
  "geometry": {"coordinates":[-90.04522,44.569619],"type":"Point"}
}