{
  "type": "Feature",
  "properties": {
    "iso:country":"US",
    "sg:address":"6510 W Forest Home Ave",
    "sg:city":"Milwaukee",
    "sg:classifiers":[
        {
            "category":"Home & Garden",
            "subcategory":"Building Materials",
            "type":"Retail Goods"
        },
        {
            "category":"Professional",
            "subcategory":"Printing & Photocopies",
            "type":"Services"
        },
        {
            "category":"Building & Trades",
            "subcategory":"Locksmith",
            "type":"Services"
        }
    ],
    "sg:phone":"+1 414 321 0500",
    "sg:postcode":"53220",
    "sg:province":"WI",
    "sg:tags":[
        "repair",
        "door",
        "garage",
        "opener",
        "door-overhead",
        "type"
    ],
    "wof:name":"Advance Overhead Door Inc",
    "wof:placetype":"venue"
},
  "geometry": {"coordinates":[-87.99527,42.972383],"type":"Point"}
}