{
  "type": "Feature",
  "properties": {
    "addr:full":"8310 Greenway Blvd Middleton WI 53562",
    "addr:housenumber":"8310",
    "addr:postcode":"53562",
    "addr:street":"Greenway Blvd",
    "iso:country":"US",
    "sg:address":"8310 Greenway Blvd",
    "sg:city":"Middleton",
    "sg:classifiers":[
        {
            "category":"Restaurant",
            "type":"Food & Drink"
        }
    ],
    "sg:menulink":"http://www.allmenus.com/wi/middleton/105607-pancheros/menu/",
    "sg:phone":"+1 608 831 7993",
    "sg:postcode":"53562",
    "sg:province":"WI",
    "sg:tags":[
        "mexican"
    ],
    "wof:name":"Panchero's",
    "wof:placetype":"venue"
},
  "geometry": {"coordinates":[-89.524885,43.090197],"type":"Point"}
}