{
  "type": "Feature",
  "properties": {
    "addr:full":"807 Main Ave De Pere WI 54115",
    "addr:housenumber":"807",
    "addr:postcode":"54115",
    "addr:street":"Main Ave",
    "iso:country":"US",
    "sg:address":"807 Main Ave",
    "sg:city":"De Pere",
    "sg:classifiers":[
        {
            "category":"Restaurant",
            "type":"Food & Drink"
        }
    ],
    "sg:menulink":"http://www.allmenus.com/wi/de-pere/63994-papa-johns-pizza/menu/",
    "sg:phone":"+1 920 983 7272",
    "sg:postcode":"54115",
    "sg:province":"WI",
    "sg:tags":[
        "american",
        "pizza"
    ],
    "wof:name":"Papa John's Pizza",
    "wof:placetype":"venue"
},
  "geometry": {"coordinates":[-88.08123000000001,44.449617],"type":"Point"}
}