{
  "type": "Feature",
  "properties": {
    "iso:country":"US",
    "sg:address":"115 W Mullett St",
    "sg:city":"Portage",
    "sg:classifiers":[
        {
            "category":"Building & Trades",
            "subcategory":"Construction",
            "type":"Services"
        }
    ],
    "sg:phone":"+1 608 742 0351",
    "sg:postcode":"53901",
    "sg:province":"WI",
    "sg:tags":[
        "hanging",
        "painter",
        "contractor"
    ],
    "wof:name":"Who's Yer Painter",
    "wof:placetype":"venue"
},
  "geometry": {"coordinates":[-89.458496,43.53805],"type":"Point"}
}