{
  "type": "Feature",
  "properties": {
    "iso:country":"US",
    "sg:address":"901 Gabes Rd",
    "sg:city":"Mosinee",
    "sg:classifiers":[
        {
            "category":"Professional",
            "subcategory":"Management & Consulting",
            "type":"Services"
        }
    ],
    "sg:phone":"+1 715 693 5333",
    "sg:postcode":"54455",
    "sg:province":"WI",
    "wof:name":"Steudel & Mann Management Cons",
    "wof:placetype":"venue"
},
  "geometry": {"coordinates":[-89.670064,44.834426],"type":"Point"}
}