{
  "type": "Feature",
  "properties": {
    "iso:country":"US",
    "sg:address":"2449 Co Hwy I",
    "sg:city":"Chippewa Falls",
    "sg:classifiers":[
        {
            "category":"Health Services",
            "subcategory":"Doctor",
            "type":"Services"
        }
    ],
    "sg:phone":"+1 715 723 9138",
    "sg:postcode":"54729",
    "sg:province":"WI",
    "sg:tags":[
        "clinic",
        "medical"
    ],
    "wof:name":"Family Health Associates",
    "wof:placetype":"venue"
},
  "geometry": {"coordinates":[-91.362859,44.951558],"type":"Point"}
}