{
  "type": "Feature",
  "properties": {
    "addr:full":"3612 Division Dr Medford WI 54451",
    "addr:housenumber":"3612",
    "addr:postcode":"54451",
    "addr:street":"Division Dr",
    "iso:country":"US",
    "sg:address":"3612 Division Dr",
    "sg:city":"Medford",
    "sg:classifiers":[
        {
            "category":"Government",
            "subcategory":"Office",
            "type":"Public Place"
        }
    ],
    "sg:phone":"+1 715 785 7104",
    "sg:postcode":"54451",
    "sg:province":"WI",
    "sg:tags":[
        "village"
    ],
    "wof:name":"Hammel Town Shop",
    "wof:placetype":"venue"
},
  "geometry": {"coordinates":[-90.49464500000001,45.175733],"type":"Point"}
}