{
  "type": "Feature",
  "properties": {
    "iso:country":"US",
    "sg:address":"7413 Friendship Ln",
    "sg:city":"Middleton",
    "sg:classifiers":[
        {
            "category":"Building & Trades",
            "subcategory":"Construction",
            "type":"Services"
        }
    ],
    "sg:phone":"+1 608 695 3115",
    "sg:postcode":"53562",
    "sg:province":"WI",
    "sg:tags":[
        "house",
        "co"
    ],
    "wof:name":"Robert Lund Construction",
    "wof:placetype":"venue"
},
  "geometry": {"coordinates":[-89.50753400000001,43.113238],"type":"Point"}
}