{
  "type": "Feature",
  "properties": {
    "iso:country":"US",
    "sg:address":"2930 Allied St",
    "sg:city":"Green Bay",
    "sg:classifiers":[
        {
            "category":"Retail",
            "subcategory":"Auto Repair",
            "type":"Services"
        }
    ],
    "sg:phone":"+1 920 337 2424",
    "sg:postcode":"54304",
    "sg:province":"WI",
    "sg:tags":[
        "repairing",
        "tire"
    ],
    "sg:website":"www.wingfootct.com",
    "wof:name":"Wingfoot Commercial Tire Systs",
    "wof:placetype":"venue"
},
  "geometry": {"coordinates":[-88.08207299999999,44.472287],"type":"Point"}
}