{
  "type": "Feature",
  "properties": {
    "iso:country":"US",
    "sg:address":"709 Trout Creek Rd",
    "sg:city":"Oneida",
    "sg:classifiers":[
        {
            "category":"Farming",
            "subcategory":"Farm & Veterinary Services",
            "type":"Manufacturing & Wholesale Goods"
        }
    ],
    "sg:phone":"+1 920 494 1551",
    "sg:postcode":"54155",
    "sg:province":"WI",
    "sg:tags":[
        "preparation",
        "crop",
        "for",
        "market"
    ],
    "wof:name":"Bernard Lemere",
    "wof:placetype":"venue"
},
  "geometry": {"coordinates":[-88.16361499999999,44.538339],"type":"Point"}
}