{
  "type": "Feature",
  "properties": {
    "iso:country":"US",
    "sg:address":"4020 N 29th St",
    "sg:city":"Sheboygan",
    "sg:classifiers":[
        {
            "category":"Manufacturing",
            "subcategory":"Tools & Machinery",
            "type":"Manufacturing & Wholesale Goods"
        }
    ],
    "sg:phone":"+1 920 803 9715",
    "sg:postcode":"53083",
    "sg:province":"WI",
    "sg:tags":[
        "transformer",
        "mfg"
    ],
    "wof:name":"A B B Electric Systems",
    "wof:placetype":"venue"
},
  "geometry": {"coordinates":[-87.746313,43.787953],"type":"Point"}
}