{
  "type": "Feature",
  "properties": {
    "iso:country":"US",
    "sg:address":"7331 Red Banks Rd",
    "sg:city":"Fremont",
    "sg:classifiers":[
        {
            "category":"Travel",
            "subcategory":"Hotels & Motels",
            "type":"Entertainment"
        }
    ],
    "sg:phone":"+1 920 446 2911",
    "sg:postcode":"54940",
    "sg:province":"WI",
    "sg:website":"www.redbanks.net",
    "wof:name":"Red Banks Motel",
    "wof:placetype":"venue"
},
  "geometry": {"coordinates":[-88.856634,44.277066],"type":"Point"}
}