{
  "type": "Feature",
  "properties": {
    "iso:country":"US",
    "sg:address":"9101 Deerbrook Trl",
    "sg:city":"Milwaukee",
    "sg:classifiers":[
        {
            "category":"Autos & Motor Vehicles",
            "subcategory":"Auto Supplies",
            "type":"Retail Goods"
        },
        {
            "category":"Retail",
            "subcategory":"Auto Repair",
            "type":"Services"
        }
    ],
    "sg:phone":"+1 414 355 0500",
    "sg:postcode":"53223",
    "sg:province":"WI",
    "sg:tags":[
        "repairing",
        "automobile",
        "tire"
    ],
    "wof:name":"Team Tires Plus",
    "wof:placetype":"venue"
},
  "geometry": {"coordinates":[-87.966506,43.179989],"type":"Point"}
}