{
  "type": "Feature",
  "properties": {
    "iso:country":"US",
    "sg:address":"233 S Lynndale Dr",
    "sg:city":"Appleton",
    "sg:classifiers":[
        {
            "category":"Social Services",
            "subcategory":"Adult Care",
            "type":"Services"
        }
    ],
    "sg:phone":"+1 920 734 3092",
    "sg:postcode":"54914",
    "sg:province":"WI",
    "wof:name":"Pnuma Health Care Inc",
    "wof:placetype":"venue"
},
  "geometry": {"coordinates":[-88.445942,44.259746],"type":"Point"}
}