{
  "type": "Feature",
  "properties": {
    "iso:country":"US",
    "sg:address":"678 200th St",
    "sg:city":"Baldwin",
    "sg:classifiers":[
        {
            "category":"Real Estate",
            "subcategory":"Real Estate Operator",
            "type":"Services"
        }
    ],
    "sg:phone":"+1 715 684 2596",
    "sg:postcode":"54002",
    "sg:province":"WI",
    "sg:tags":[
        "farm",
        "field",
        "property",
        "crop",
        "lessor"
    ],
    "wof:name":"Dorn-Hof Inc",
    "wof:placetype":"venue"
},
  "geometry": {"coordinates":[-92.395261,44.957779],"type":"Point"}
}