{
  "type": "Feature",
  "properties": {
    "iso:country":"US",
    "sg:address":"2343 Logan Ave",
    "sg:city":"Superior",
    "sg:classifiers":[
        {
            "category":"Professional",
            "type":"Services"
        }
    ],
    "sg:phone":"+1 715 395 8327",
    "sg:postcode":"54880",
    "sg:province":"WI",
    "wof:name":"Integrin L L C",
    "wof:placetype":"venue"
},
  "geometry": {"coordinates":[-92.119169,46.711666],"type":"Point"}
}