{
  "type": "Feature",
  "properties": {
    "addr:full":"5678 Fisk Ave Oshkosh WI 54904",
    "addr:housenumber":"5678",
    "addr:postcode":"54904",
    "addr:street":"Fisk Ave",
    "iso:country":"US",
    "sg:address":"5678 Fisk Ave",
    "sg:city":"Oshkosh",
    "sg:classifiers":[
        {
            "category":"Recreation",
            "type":"Entertainment"
        }
    ],
    "sg:phone":"+1 920 589 5678",
    "sg:postcode":"54904",
    "sg:province":"WI",
    "sg:tags":[
        "club",
        "membership"
    ],
    "wof:name":"Hunter Expo 2005 The",
    "wof:placetype":"venue"
},
  "geometry": {"coordinates":[-88.68881,43.952975],"type":"Point"}
}