{
  "type": "Feature",
  "properties": {
    "iso:country":"US",
    "sg:address":"6849 US Hwy 51",
    "sg:city":"Hazelhurst",
    "sg:classifiers":[
        {
            "category":"Building & Trades",
            "subcategory":"Construction",
            "type":"Services"
        }
    ],
    "sg:phone":"+1 715 356 2043",
    "sg:postcode":"54531",
    "sg:province":"WI",
    "sg:tags":[
        "general",
        "contractor"
    ],
    "wof:name":"Stodala-Maas Construction Inc",
    "wof:placetype":"venue"
},
  "geometry": {"coordinates":[-89.717845,45.795513],"type":"Point"}
}