{
  "type": "Feature",
  "properties": {
    "iso:country":"US",
    "sg:address":"101 N Church St",
    "sg:city":"Watertown",
    "sg:classifiers":[
        {
            "category":"Government",
            "subcategory":"Office",
            "type":"Public Place"
        }
    ],
    "sg:phone":"+1 920 206 6287",
    "sg:postcode":"53094",
    "sg:province":"WI",
    "sg:tags":[
        "village"
    ],
    "wof:name":"City Of Watertown",
    "wof:placetype":"venue"
},
  "geometry": {"coordinates":[-88.72841200000001,43.195845],"type":"Point"}
}