{
  "type": "Feature",
  "properties": {
    "addr:full":"1815 Norman Way Madison WI 53705",
    "addr:housenumber":"1815",
    "addr:postcode":"53705",
    "addr:street":"Norman Way",
    "iso:country":"US",
    "sg:address":"1815 Norman Way",
    "sg:city":"Madison",
    "sg:classifiers":[
        {
            "category":"Restaurant",
            "type":"Food & Drink"
        }
    ],
    "sg:phone":"+1 608 233 3267",
    "sg:postcode":"53705",
    "sg:province":"WI",
    "wof:name":"Dotty Dumplings Dowry Ltd",
    "wof:placetype":"venue"
},
  "geometry": {"coordinates":[-89.47098,43.082544],"type":"Point"}
}