{
  "type": "Feature",
  "properties": {
    "iso:country":"US",
    "sg:address":"130 N Main St",
    "sg:city":"Oregon",
    "sg:classifiers":[
        {
            "category":"Restaurant",
            "type":"Food & Drink"
        }
    ],
    "sg:phone":"+1 608 835 7744",
    "sg:postcode":"53575",
    "sg:province":"WI",
    "sg:tags":[
        "pizza"
    ],
    "sg:website":"www.pizzapit.com",
    "wof:name":"Pizza Pit",
    "wof:placetype":"venue"
},
  "geometry": {"coordinates":[-89.384052,42.927038],"type":"Point"}
}