{
  "type": "Feature",
  "properties": {
    "iso:country":"US",
    "sg:address":"672 Railroad Ave",
    "sg:city":"Chetek",
    "sg:classifiers":[
        {
            "category":"Retail",
            "subcategory":"Auto Repair",
            "type":"Services"
        }
    ],
    "sg:phone":"+1 715 925 2400",
    "sg:postcode":"54728",
    "sg:province":"WI",
    "sg:tags":[
        "wrecker"
    ],
    "wof:name":"Townsend Towing & Garage",
    "wof:placetype":"venue"
},
  "geometry": {"coordinates":[-91.65910700000001,45.31684],"type":"Point"}
}