{
  "type": "Feature",
  "properties": {
    "iso:country":"US",
    "sg:address":"2483 28th St",
    "sg:city":"Rice Lake",
    "sg:classifiers":[
        {
            "category":"Travel",
            "subcategory":"Hotels & Motels",
            "type":"Entertainment"
        }
    ],
    "sg:phone":"+1 715 234 8232",
    "sg:postcode":"54868",
    "sg:province":"WI",
    "sg:tags":[
        "resort"
    ],
    "wof:name":"Hemlock Lake Resort & Camp",
    "wof:placetype":"venue"
},
  "geometry": {"coordinates":[-91.581819,45.564969],"type":"Point"}
}