{
  "type": "Feature",
  "properties": {
    "iso:country":"US",
    "sg:address":"418 Union Ave",
    "sg:city":"Oconto Falls",
    "sg:classifiers":[
        {
            "category":"Restaurant",
            "type":"Food & Drink"
        }
    ],
    "sg:phone":"+1 920 846 4808",
    "sg:postcode":"54154",
    "sg:province":"WI",
    "wof:name":"Avenue Pizza",
    "wof:placetype":"venue"
},
  "geometry": {"coordinates":[-88.13735699999999,44.874721],"type":"Point"}
}