{
  "type": "Feature",
  "properties": {
    "addr:full":"844 Hillside Rd Colgate WI 53017",
    "addr:housenumber":"844",
    "addr:postcode":"53017",
    "addr:street":"Hillside Rd Colgate",
    "iso:country":"US",
    "sg:address":"844 Hillside Rd",
    "sg:city":"Colgate",
    "sg:classifiers":[
        {
            "category":"Building & Trades",
            "subcategory":"Construction",
            "type":"Services"
        }
    ],
    "sg:phone":"+1 262 628 9094",
    "sg:postcode":"53017",
    "sg:province":"WI",
    "sg:tags":[
        "concrete",
        "contractor"
    ],
    "wof:name":"Complete Concrete Plus Inc",
    "wof:placetype":"venue"
},
  "geometry": {"coordinates":[-88.24172,43.215165],"type":"Point"}
}