{
  "type": "Feature",
  "properties": {
    "iso:country":"US",
    "sg:address":"7124 Applewood Dr",
    "sg:city":"Madison",
    "sg:classifiers":[
        {
            "category":"Education",
            "subcategory":"Special Training",
            "type":"Public Place"
        }
    ],
    "sg:phone":"+1 608 833 7549",
    "sg:postcode":"53719",
    "sg:province":"WI",
    "sg:tags":[
        "program"
    ],
    "wof:name":"Leslie Williams Group",
    "wof:placetype":"venue"
},
  "geometry": {"coordinates":[-89.524331,43.047475],"type":"Point"}
}