{
  "type": "Feature",
  "properties": {
    "iso:country":"US",
    "sg:address":"19583 Co Rd F",
    "sg:city":"Trempealeau",
    "sg:classifiers":[
        {
            "category":"Farming",
            "subcategory":"Dairy Farm",
            "type":"Manufacturing & Wholesale Goods"
        }
    ],
    "sg:phone":"+1 608 539 3776",
    "sg:postcode":"54661",
    "sg:province":"WI",
    "wof:name":"R Lilla",
    "wof:placetype":"venue"
},
  "geometry": {"coordinates":[-91.454443,44.121132],"type":"Point"}
}