{
  "type": "Feature",
  "properties": {
    "iso:country":"US",
    "sg:address":"214 N Main St",
    "sg:city":"Rice Lake",
    "sg:classifiers":[
        {
            "category":"Shopping",
            "subcategory":"Bicycles & Sporting Goods",
            "type":"Retail Goods"
        }
    ],
    "sg:phone":"+1 715 234 1618",
    "sg:postcode":"54868",
    "sg:province":"WI",
    "sg:tags":[
        "me",
        "repair",
        "used"
    ],
    "wof:name":"Majestic Pawn",
    "wof:placetype":"venue"
},
  "geometry": {"coordinates":[-91.73357,45.504252],"type":"Point"}
}