{
  "type": "Feature",
  "properties": {
    "iso:country":"US",
    "sg:address":"147 N Rural St",
    "sg:city":"Hartford",
    "sg:classifiers":[
        {
            "category":"Museum",
            "type":"Entertainment"
        }
    ],
    "sg:phone":"+1 262 673 7999",
    "sg:postcode":"53027",
    "sg:province":"WI",
    "sg:tags":[
        "gallery"
    ],
    "wof:name":"Wisconsin Automotive Museum",
    "wof:placetype":"venue"
},
  "geometry": {"coordinates":[-88.380976,43.319652],"type":"Point"}
}