{
  "type": "Feature",
  "properties": {
    "addr:full":"415 Fredonia Ave Fredonia WI 53021",
    "addr:housenumber":"415",
    "addr:postcode":"53021",
    "addr:street":"Fredonia Ave",
    "iso:country":"US",
    "sg:address":"415 Fredonia Ave",
    "sg:city":"Fredonia",
    "sg:classifiers":[
        {
            "category":"Real Estate",
            "subcategory":"Real Estate Agent",
            "type":"Services"
        }
    ],
    "sg:phone":"+1 262 692 3648",
    "sg:postcode":"53021",
    "sg:province":"WI",
    "wof:name":"Capitol Group Real Est & Dev",
    "wof:placetype":"venue"
},
  "geometry": {"coordinates":[-87.95155200000001,43.470002],"type":"Point"}
}