{
  "type": "Feature",
  "properties": {
    "addr:full":"1530A N Cass St Milwaukee WI 53202",
    "addr:housenumber":"1530a",
    "addr:postcode":"53202",
    "addr:street":"N Cass St",
    "iso:country":"US",
    "sg:address":"1530A N Cass St",
    "sg:city":"Milwaukee",
    "sg:classifiers":[
        {
            "category":"Real Estate",
            "subcategory":"Real Estate Services",
            "type":"Services"
        }
    ],
    "sg:phone":"+1 414 277 0185",
    "sg:postcode":"53202",
    "sg:province":"WI",
    "sg:tags":[
        "management"
    ],
    "wof:name":"J M T Properties",
    "wof:placetype":"venue"
},
  "geometry": {"coordinates":[-87.90214400000001,43.049738],"type":"Point"}
}