{
  "type": "Feature",
  "properties": {
    "iso:country":"US",
    "sg:address":"1710 W Bolivar Ave",
    "sg:city":"Milwaukee",
    "sg:classifiers":[
        {
            "category":"Organizations",
            "subcategory":"Religious Organization",
            "type":"Services"
        }
    ],
    "sg:phone":"+1 414 282 9063",
    "sg:postcode":"53221",
    "sg:province":"WI",
    "wof:name":"St Romans Parish",
    "wof:placetype":"venue"
},
  "geometry": {"coordinates":[-87.937681,42.966668],"type":"Point"}
}