{
  "type": "Feature",
  "properties": {
    "addr:full":"5241 State Rd 167 Hubertus WI 53033",
    "addr:housenumber":"5241;167",
    "addr:postcode":"53033",
    "addr:street":"State Rd",
    "iso:country":"US",
    "sg:address":"5241 State Rd 167",
    "sg:city":"Hubertus",
    "sg:classifiers":[
        {
            "category":"Bars & Pubs",
            "type":"Food & Drink"
        }
    ],
    "sg:phone":"+1 262 628 2140",
    "sg:postcode":"53033",
    "sg:province":"WI",
    "wof:name":"Schultz's Bar",
    "wof:placetype":"venue"
},
  "geometry": {"coordinates":[-88.29777199999999,43.251175],"type":"Point"}
}