{
  "type": "Feature",
  "properties": {
    "addr:full":"115 S Oak St Reedsburg WI 53959",
    "addr:housenumber":"115",
    "addr:postcode":"53959",
    "addr:street":"S Oak St",
    "iso:country":"US",
    "sg:address":"115 S Oak St",
    "sg:city":"Reedsburg",
    "sg:classifiers":[
        {
            "category":"Organizations",
            "subcategory":"Religious Organization",
            "type":"Services"
        }
    ],
    "sg:phone":"+1 608 524 8118",
    "sg:postcode":"53959",
    "sg:province":"WI",
    "wof:name":"Reedsburg Seventh-Day Adventis",
    "wof:placetype":"venue"
},
  "geometry": {"coordinates":[-89.99823499999999,43.532461],"type":"Point"}
}