{
  "type": "Feature",
  "properties": {
    "iso:country":"US",
    "sg:address":"878 Hickory Ct",
    "sg:city":"Watertown",
    "sg:classifiers":[
        {
            "category":"Banks & Credit Unions",
            "subcategory":"Investment Brokerage",
            "type":"Services"
        }
    ],
    "sg:phone":"+1 920 262 0089",
    "sg:postcode":"53094",
    "sg:province":"WI",
    "sg:tags":[
        "advisory"
    ],
    "wof:name":"Stafford Investments",
    "wof:placetype":"venue"
},
  "geometry": {"coordinates":[-88.749442,43.185258],"type":"Point"}
}