{
  "type": "Feature",
  "properties": {
    "addr:full":"910 Milwaukee Ave South Milwaukee WI 53172",
    "addr:housenumber":"910",
    "addr:postcode":"53172",
    "addr:street":"Milwaukee Ave",
    "iso:country":"US",
    "sg:address":"910 Milwaukee Ave",
    "sg:city":"South Milwaukee",
    "sg:classifiers":[
        {
            "category":"Building & Trades",
            "subcategory":"Construction",
            "type":"Services"
        }
    ],
    "sg:phone":"+1 414 768 8075",
    "sg:postcode":"53172",
    "sg:province":"WI",
    "sg:tags":[
        "marking",
        "maintenance",
        "parking"
    ],
    "sg:website":"www.ci.south-milwaukee.wi.us",
    "wof:name":"South Milwaukee Street Dept",
    "wof:placetype":"venue"
},
  "geometry": {"coordinates":[-87.860563,42.910755],"type":"Point"}
}