{
  "type": "Feature",
  "properties": {
    "iso:country":"US",
    "sg:address":"607 Eastern Ave",
    "sg:city":"Plymouth",
    "sg:classifiers":[
        {
            "category":"Restaurant",
            "type":"Food & Drink"
        }
    ],
    "sg:phone":"+1 920 893 3022",
    "sg:postcode":"53073",
    "sg:province":"WI",
    "sg:tags":[
        "eating"
    ],
    "wof:name":"Ellas Dela Delicatessen",
    "wof:placetype":"venue"
},
  "geometry": {"coordinates":[-87.97336,43.747602],"type":"Point"}
}