{
  "type": "Feature",
  "properties": {
    "iso:country":"US",
    "sg:address":"6539 N 84th St",
    "sg:city":"Milwaukee",
    "sg:classifiers":[
        {
            "category":"Organizations",
            "subcategory":"Religious Organization",
            "type":"Services"
        }
    ],
    "sg:phone":"+1 414 760 1677",
    "sg:postcode":"53224",
    "sg:province":"WI",
    "sg:tags":[
        "music",
        "ministry"
    ],
    "wof:name":"Meritone Ministries Inc",
    "wof:placetype":"venue"
},
  "geometry": {"coordinates":[-88.016051,43.136292],"type":"Point"}
}