{
  "type": "Feature",
  "properties": {
    "iso:country":"US",
    "sg:address":"5556 S 27th St",
    "sg:city":"Greenfield",
    "sg:classifiers":[
        {
            "category":"Shopping",
            "subcategory":"Clothing, Apparel, & Fashions",
            "type":"Retail Goods"
        },
        {
            "category":"Social Services",
            "type":"Services"
        }
    ],
    "sg:phone":"+1 414 282 7770",
    "sg:postcode":"53221",
    "sg:province":"WI",
    "sg:tags":[
        "employee",
        "assistance",
        "program"
    ],
    "wof:name":"Mexican Treasures LLC",
    "wof:placetype":"venue"
},
  "geometry": {"coordinates":[-87.948995,42.944368],"type":"Point"}
}