{
  "type": "Feature",
  "properties": {
    "iso:country":"US",
    "sg:address":"4850 S Lake Dr",
    "sg:city":"Cudahy",
    "sg:classifiers":[
        {
            "category":"Organizations",
            "subcategory":"Religious Organization",
            "type":"Services"
        }
    ],
    "sg:phone":"+1 414 481 8286",
    "sg:postcode":"53110",
    "sg:province":"WI",
    "sg:tags":[
        "church"
    ],
    "wof:name":"SELC District-Lutheran",
    "wof:placetype":"venue"
},
  "geometry": {"coordinates":[-87.850085,42.95714],"type":"Point"}
}