{
  "type": "Feature",
  "properties": {
    "addr:full":"3311 E Capitol Dr Appleton WI 54911",
    "addr:housenumber":"3311",
    "addr:postcode":"54911",
    "addr:street":"E Capitol Dr",
    "iso:country":"US",
    "sg:address":"3311 E Capitol Dr",
    "sg:city":"Appleton",
    "sg:classifiers":[
        {
            "category":"Manufacturing",
            "subcategory":"Tools & Machinery",
            "type":"Manufacturing & Wholesale Goods"
        }
    ],
    "sg:phone":"+1 920 739 0242",
    "sg:postcode":"54911",
    "sg:province":"WI",
    "sg:tags":[
        "equipment",
        "industrial",
        "supply"
    ],
    "sg:website":"www.engman-taylor.com",
    "wof:name":"Engman-Taylor Co Inc",
    "wof:placetype":"venue"
},
  "geometry": {"coordinates":[-88.35968800000001,44.291816],"type":"Point"}
}