{
  "type": "Feature",
  "properties": {
    "iso:country":"US",
    "sg:address":"1202 S Cesar E Chavez Dr",
    "sg:city":"Milwaukee",
    "sg:classifiers":[
        {
            "category":"Restaurant",
            "type":"Food & Drink"
        }
    ],
    "sg:phone":"+1 414 672 6746",
    "sg:postcode":"53204",
    "sg:province":"WI",
    "sg:tags":[
        "eating"
    ],
    "wof:name":"Don Pancho Taqueria",
    "wof:placetype":"venue"
},
  "geometry": {"coordinates":[-87.93320799999999,43.017001],"type":"Point"}
}