{
  "type": "Feature",
  "properties": {
    "iso:country":"US",
    "sg:address":"415 E Washington Ave",
    "sg:city":"Madison",
    "sg:classifiers":[
        {
            "category":"Real Estate",
            "subcategory":"Real Estate Agent",
            "type":"Services"
        }
    ],
    "sg:phone":"+1 608 257 1487",
    "sg:postcode":"53703",
    "sg:province":"WI",
    "wof:name":"Rider Realty Inc",
    "wof:placetype":"venue"
},
  "geometry": {"coordinates":[-89.379652,43.077775],"type":"Point"}
}