{
  "type": "Feature",
  "properties": {
    "iso:country":"US",
    "sg:address":"2117 Jefferson St",
    "sg:city":"Stevens Point",
    "sg:classifiers":[
        {
            "category":"Wholesale",
            "subcategory":"Hardware",
            "type":"Manufacturing & Wholesale Goods"
        }
    ],
    "sg:phone":"+1 715 344 2602",
    "sg:postcode":"54481",
    "sg:province":"WI",
    "sg:tags":[
        "air",
        "equipment",
        "furnace",
        "conditioning",
        "heating"
    ],
    "wof:name":"Kleenaire Corp",
    "wof:placetype":"venue"
},
  "geometry": {"coordinates":[-89.56815,44.519327],"type":"Point"}
}