{
  "type": "Feature",
  "properties": {
    "addr:full":"333 Lake Ave Racine WI 53403",
    "addr:housenumber":"333",
    "addr:postcode":"53403",
    "addr:street":"Lake Ave",
    "iso:country":"US",
    "sg:address":"333 Lake Ave",
    "sg:city":"Racine",
    "sg:classifiers":[
        {
            "category":"Organizations",
            "subcategory":"Community Association",
            "type":"Services"
        }
    ],
    "sg:phone":"+1 414 482 7476",
    "sg:postcode":"53403",
    "sg:province":"WI",
    "wof:name":"Lakeshore Towers of Racine",
    "wof:placetype":"venue"
},
  "geometry": {"coordinates":[-87.782115,42.729902],"type":"Point"}
}