{
  "type": "Feature",
  "properties": {
    "addr:full":"300 Cottonwood Ave Hartland WI 53029",
    "addr:housenumber":"300",
    "addr:postcode":"53029",
    "addr:street":"Cottonwood Ave",
    "iso:country":"US",
    "sg:address":"300 Cottonwood Ave",
    "sg:city":"Hartland",
    "sg:classifiers":[
        {
            "category":"Restaurant",
            "type":"Food & Drink"
        }
    ],
    "sg:phone":"+1 262 367 3663",
    "sg:postcode":"53029",
    "sg:province":"WI",
    "sg:tags":[
        "drinking",
        "eating"
    ],
    "wof:name":"Bark River Inn Inc",
    "wof:placetype":"venue"
},
  "geometry": {"coordinates":[-88.348461,43.100455],"type":"Point"}
}