{
  "type": "Feature",
  "properties": {
    "iso:country":"US",
    "sg:address":"350 S Sunny Slope Rd",
    "sg:city":"Brookfield",
    "sg:classifiers":[
        {
            "category":"Insurance",
            "subcategory":"Insurance Agent",
            "type":"Services"
        }
    ],
    "sg:phone":"+1 262 786 1090",
    "sg:postcode":"53005",
    "sg:province":"WI",
    "sg:tags":[
        "agency"
    ],
    "wof:name":"UNUM Life Insurance Co Amer",
    "wof:placetype":"venue"
},
  "geometry": {"coordinates":[-88.086888,43.027906],"type":"Point"}
}