{
  "type": "Feature",
  "properties": {
    "addr:full":"17 N Main St Janesville WI 53545",
    "addr:housenumber":"17",
    "addr:postcode":"53545",
    "addr:street":"N Main St",
    "iso:country":"US",
    "sg:address":"17 N Main St",
    "sg:city":"Janesville",
    "sg:classifiers":[
        {
            "category":"Personal",
            "subcategory":"Shoe Repair & Shine",
            "type":"Services"
        }
    ],
    "sg:phone":"+1 608 754 5772",
    "sg:postcode":"53545",
    "sg:province":"WI",
    "sg:tags":[
        "parlor",
        "good"
    ],
    "wof:name":"Weber Shoe Repair",
    "wof:placetype":"venue"
},
  "geometry": {"coordinates":[-89.02330600000001,42.683507],"type":"Point"}
}