{
  "type": "Feature",
  "properties": {
    "iso:country":"US",
    "sg:address":"806 W Main St",
    "sg:city":"Waupun",
    "sg:classifiers":[
        {
            "category":"Home & Garden",
            "subcategory":"Furniture",
            "type":"Retail Goods"
        }
    ],
    "sg:phone":"+1 920 324 9151",
    "sg:postcode":"53963",
    "sg:province":"WI",
    "wof:name":"Ver Hage Furniture Mart",
    "wof:placetype":"venue"
},
  "geometry": {"coordinates":[-88.750218,43.633172],"type":"Point"}
}