{
  "type": "Feature",
  "properties": {
    "iso:country":"US",
    "sg:address":"11447 E Berg Rd",
    "sg:city":"Whitewater",
    "sg:classifiers":[
        {
            "category":"Shopping",
            "subcategory":"Crafts & Fabrics",
            "type":"Retail Goods"
        }
    ],
    "sg:phone":"+1 262 473 5707",
    "sg:postcode":"53190",
    "sg:province":"WI",
    "sg:tags":[
        "sewing"
    ],
    "wof:name":"Country Stitches LLC",
    "wof:placetype":"venue"
},
  "geometry": {"coordinates":[-88.822917,42.770228],"type":"Point"}
}