{
  "type": "Feature",
  "properties": {
    "addr:full":"5334 Locust Grove Rd Oregon WI 53575",
    "addr:housenumber":"5334",
    "addr:postcode":"53575",
    "addr:street":"Locust Grove Rd",
    "iso:country":"US",
    "sg:address":"5334 Locust Grove Rd",
    "sg:city":"Oregon",
    "sg:phone":"+1 608 835 8533",
    "sg:postcode":"53575",
    "sg:province":"WI",
    "sg:tags":[
        "farm",
        "corn",
        "soybean"
    ],
    "wof:name":"Mark W Harring",
    "wof:placetype":"venue"
},
  "geometry": {"coordinates":[-89.403801,42.899999],"type":"Point"}
}