{
  "type": "Feature",
  "properties": {
    "iso:country":"US",
    "sg:address":"1224 Shade Tree Ln",
    "sg:city":"Appleton",
    "sg:classifiers":[
        {
            "category":"Manufacturing",
            "subcategory":"Paper Products",
            "type":"Manufacturing & Wholesale Goods"
        }
    ],
    "sg:phone":"+1 920 954 0322",
    "sg:postcode":"54915",
    "sg:province":"WI",
    "sg:tags":[
        "converted",
        "mfg"
    ],
    "wof:name":"Van Abel John",
    "wof:placetype":"venue"
},
  "geometry": {"coordinates":[-88.386352,44.228442],"type":"Point"}
}