{
  "type": "Feature",
  "properties": {
    "addr:full":"100 W 1st St Crandon WI 54520",
    "addr:housenumber":"100",
    "addr:postcode":"54520",
    "addr:street":"W 1St St",
    "iso:country":"US",
    "sg:address":"100 W 1st St",
    "sg:city":"Crandon",
    "sg:classifiers":[
        {
            "category":"Shopping",
            "subcategory":"Gifts & Souvenirs",
            "type":"Retail Goods"
        }
    ],
    "sg:phone":"+1 715 478 5005",
    "sg:postcode":"54520",
    "sg:province":"WI",
    "wof:name":"Wishing Well",
    "wof:placetype":"venue"
},
  "geometry": {"coordinates":[-88.903914,45.574341],"type":"Point"}
}