{
  "type": "Feature",
  "properties": {
    "addr:full":"2215 E Clairemont Ave Eau Claire WI 54701",
    "addr:housenumber":"2215",
    "addr:postcode":"54701",
    "addr:street":"E Clairemont Ave",
    "iso:country":"US",
    "sg:address":"2215 E Clairemont Ave",
    "sg:city":"Eau Claire",
    "sg:classifiers":[
        {
            "category":"Health Services",
            "subcategory":"Doctor",
            "type":"Services"
        }
    ],
    "sg:phone":"+1 715 835 2332",
    "sg:postcode":"54701",
    "sg:province":"WI",
    "wof:name":"Ross H Johnson DDS",
    "wof:placetype":"venue"
},
  "geometry": {"coordinates":[-91.471709,44.794249],"type":"Point"}
}