{
  "type": "Feature",
  "properties": {
    "iso:country":"US",
    "sg:address":"241 Oak St",
    "sg:city":"Wisconsin Rapids",
    "sg:classifiers":[
        {
            "category":"Shopping",
            "subcategory":"Jewelry",
            "type":"Retail Goods"
        }
    ],
    "sg:phone":"+1 715 421 3131",
    "sg:postcode":"54494",
    "sg:province":"WI",
    "sg:tags":[
        "jeweler"
    ],
    "wof:name":"Paul Gross Jewelers Inc",
    "wof:placetype":"venue"
},
  "geometry": {"coordinates":[-89.82387300000001,44.391328],"type":"Point"}
}