{
  "type": "Feature",
  "properties": {
    "iso:country":"US",
    "sg:address":"504 Juneau St",
    "sg:city":"Watertown",
    "sg:classifiers":[
        {
            "category":"Retail",
            "subcategory":"Animal Services",
            "type":"Services"
        }
    ],
    "sg:phone":"+1 920 261 0621",
    "sg:postcode":"53098",
    "sg:province":"WI",
    "wof:name":"Superior Genetics",
    "wof:placetype":"venue"
},
  "geometry": {"coordinates":[-88.703881,43.211903],"type":"Point"}
}