{
  "type": "Feature",
  "properties": {
    "iso:country":"US",
    "sg:address":"87 Church St",
    "sg:city":"Algoma",
    "sg:classifiers":[
        {
            "category":"Recreation",
            "type":"Entertainment"
        }
    ],
    "sg:phone":"+1 715 374 2449",
    "sg:postcode":"54201",
    "sg:province":"WI",
    "sg:tags":[
        "charter",
        "boat"
    ],
    "wof:name":"Shippa Hoy",
    "wof:placetype":"venue"
},
  "geometry": {"coordinates":[-87.433533,44.610479],"type":"Point"}
}