{
  "type": "Feature",
  "properties": {
    "addr:full":"703 W Thomas St Wausau WI 54401",
    "addr:housenumber":"703",
    "addr:postcode":"54401",
    "addr:street":"W Thomas St",
    "iso:country":"US",
    "sg:address":"703 W Thomas St",
    "sg:city":"Wausau",
    "sg:classifiers":[
        {
            "category":"Professional",
            "subcategory":"Business Services",
            "type":"Services"
        }
    ],
    "sg:phone":"+1 715 842 4859",
    "sg:postcode":"54401",
    "sg:province":"WI",
    "sg:tags":[
        "liquidator"
    ],
    "wof:name":"Custom Liquidation",
    "wof:placetype":"venue"
},
  "geometry": {"coordinates":[-89.645413,44.94828],"type":"Point"}
}