{
  "type": "Feature",
  "properties": {
    "iso:country":"US",
    "sg:address":"8084 Minnesuing Acres Dr",
    "sg:city":"Lake Nebagamon",
    "sg:classifiers":[
        {
            "category":"Travel",
            "subcategory":"Hotels & Motels",
            "type":"Entertainment"
        }
    ],
    "sg:phone":"+1 715 374 2262",
    "sg:postcode":"54849",
    "sg:province":"WI",
    "sg:tags":[
        "building",
        "operator",
        "operation",
        "nonresidential"
    ],
    "wof:name":"Radisson Inn",
    "wof:placetype":"venue"
},
  "geometry": {"coordinates":[-91.758461,46.472039],"type":"Point"}
}