{
  "type": "Feature",
  "properties": {
    "iso:country":"US",
    "sg:address":"1700 Windsor St",
    "sg:city":"Sun Prairie",
    "sg:classifiers":[
        {
            "category":"Retail",
            "subcategory":"Laundry & Dry Cleaning",
            "type":"Services"
        }
    ],
    "sg:phone":"+1 608 837 3937",
    "sg:postcode":"53590",
    "sg:province":"WI",
    "sg:tags":[
        "drycleaning",
        "plant"
    ],
    "wof:name":"Hangers Cleaners",
    "wof:placetype":"venue"
},
  "geometry": {"coordinates":[-89.245925,43.187419],"type":"Point"}
}