{
  "type": "Feature",
  "properties": {
    "iso:country":"US",
    "sg:address":"8377 N 76th St",
    "sg:city":"Milwaukee",
    "sg:classifiers":[
        {
            "category":"Wholesale",
            "subcategory":"Auto Parts",
            "type":"Manufacturing & Wholesale Goods"
        }
    ],
    "sg:phone":"+1 414 354 5955",
    "sg:postcode":"53223",
    "sg:province":"WI",
    "sg:tags":[
        "distributor",
        "battery"
    ],
    "wof:name":"Batteries Plus",
    "wof:placetype":"venue"
},
  "geometry": {"coordinates":[-88.00467500000001,43.167401],"type":"Point"}
}