{
  "type": "Feature",
  "properties": {
    "iso:country":"US",
    "sg:address":"804 E Main St",
    "sg:city":"Suring",
    "sg:classifiers":[
        {
            "category":"Shopping",
            "subcategory":"Gifts & Souvenirs",
            "type":"Retail Goods"
        }
    ],
    "sg:phone":"+1 920 842 4880",
    "sg:postcode":"54174",
    "sg:province":"WI",
    "wof:name":"Halfway To Heaven LLC",
    "wof:placetype":"venue"
},
  "geometry": {"coordinates":[-88.369524,44.999049],"type":"Point"}
}