{
  "type": "Feature",
  "properties": {
    "iso:country":"US",
    "sg:address":"1153 29th Ave",
    "sg:city":"Berlin",
    "sg:classifiers":[
        {
            "category":"Farming",
            "subcategory":"Dairy Farm",
            "type":"Manufacturing & Wholesale Goods"
        }
    ],
    "sg:phone":"+1 920 361 2149",
    "sg:postcode":"54923",
    "sg:province":"WI",
    "wof:name":"Susie Holstein Dairy Farm",
    "wof:placetype":"venue"
},
  "geometry": {"coordinates":[-89.04650599999999,44.026773],"type":"Point"}
}