{
  "type": "Feature",
  "properties": {
    "iso:country":"US",
    "sg:address":"1012 S 3rd St",
    "sg:city":"Watertown",
    "sg:classifiers":[
        {
            "category":"Organizations",
            "subcategory":"Non-profit Organization",
            "type":"Services"
        }
    ],
    "sg:phone":"+1 920 206 9910",
    "sg:postcode":"53094",
    "sg:province":"WI",
    "sg:website":"www.handofhelp.com",
    "wof:name":"Hand Of Help",
    "wof:placetype":"venue"
},
  "geometry": {"coordinates":[-88.723872,43.186378],"type":"Point"}
}