{
  "type": "Feature",
  "properties": {
    "iso:country":"US",
    "sg:address":"1119 Wilson Ave",
    "sg:city":"Green Bay",
    "sg:classifiers":[
        {
            "category":"Shopping",
            "subcategory":"Bicycles & Sporting Goods",
            "type":"Retail Goods"
        }
    ],
    "sg:phone":"+1 920 405 6764",
    "sg:postcode":"54303",
    "sg:province":"WI",
    "wof:name":"Cross Fire Paintball",
    "wof:placetype":"venue"
},
  "geometry": {"coordinates":[-88.035441,44.537453],"type":"Point"}
}