{
  "type": "Feature",
  "properties": {
    "iso:country":"US",
    "sg:address":"1401 W Main St",
    "sg:city":"Sun Prairie",
    "sg:classifiers":[
        {
            "category":"Freight",
            "type":"Transportation"
        }
    ],
    "sg:phone":"+1 608 837 2111",
    "sg:postcode":"53590",
    "sg:province":"WI",
    "sg:tags":[
        "special"
    ],
    "wof:name":"Main Street Storage",
    "wof:placetype":"venue"
},
  "geometry": {"coordinates":[-89.237923,43.178722],"type":"Point"}
}