{
  "type": "Feature",
  "properties": {
    "iso:country":"US",
    "sg:address":"1250 W Campus Dr",
    "sg:city":"Wausau",
    "sg:classifiers":[
        {
            "category":"Professional",
            "subcategory":"Computer Services",
            "type":"Services"
        }
    ],
    "sg:phone":"+1 715 675 8622",
    "sg:postcode":"54401",
    "sg:province":"WI",
    "wof:name":"Happy Mac",
    "wof:placetype":"venue"
},
  "geometry": {"coordinates":[-89.65077599999999,44.988125],"type":"Point"}
}