{
  "type": "Feature",
  "properties": {
    "iso:country":"US",
    "sg:address":"10109 Prairie Rd",
    "sg:city":"Prairie Du Sac",
    "sg:classifiers":[
        {
            "category":"Organizations",
            "subcategory":"Membership Organization",
            "type":"Services"
        }
    ],
    "sg:phone":"+1 608 643 8614",
    "sg:postcode":"53578",
    "sg:province":"WI",
    "sg:tags":[
        "club",
        "snowmobile"
    ],
    "wof:name":"SC Snowmobile Clubs",
    "wof:placetype":"venue"
},
  "geometry": {"coordinates":[-89.818505,43.310834],"type":"Point"}
}