{
  "type": "Feature",
  "properties": {
    "addr:full":"650 N Frontage Rd Wisconsin Dells WI 53965",
    "addr:housenumber":"650",
    "addr:postcode":"53965",
    "addr:street":"N Frontage Rd",
    "iso:country":"US",
    "sg:address":"650 N Frontage Rd",
    "sg:city":"Wisconsin Dells",
    "sg:classifiers":[
        {
            "category":"Autos & Motor Vehicles",
            "subcategory":"Fuel & Gas Station",
            "type":"Retail Goods"
        }
    ],
    "sg:phone":"+1 608 254 7852",
    "sg:postcode":"53965",
    "sg:province":"WI",
    "sg:tags":[
        "grocery",
        "station",
        "gasoline"
    ],
    "wof:name":"Amoco",
    "wof:placetype":"venue"
},
  "geometry": {"coordinates":[-89.79434000000001,43.622894],"type":"Point"}
}