{
  "type": "Feature",
  "properties": {
    "addr:full":"1325 N Main St Viroqua WI 54665",
    "addr:housenumber":"1325",
    "addr:postcode":"54665",
    "addr:street":"N Main St",
    "iso:country":"US",
    "sg:address":"1325 N Main St",
    "sg:city":"Viroqua",
    "sg:classifiers":[
        {
            "category":"Sports & Exercise",
            "subcategory":"Bowling",
            "type":"Entertainment"
        }
    ],
    "sg:phone":"+1 608 637 6460",
    "sg:postcode":"54665",
    "sg:province":"WI",
    "sg:tags":[
        "center"
    ],
    "wof:name":"Bowl A Way Storage Inc",
    "wof:placetype":"venue"
},
  "geometry": {"coordinates":[-90.88888799999999,43.567075],"type":"Point"}
}