{
  "type": "Feature",
  "properties": {
    "iso:country":"US",
    "sg:address":"1717 Superior Ave",
    "sg:city":"Oconto",
    "sg:classifiers":[
        {
            "category":"Education",
            "subcategory":"School",
            "type":"Public Place"
        }
    ],
    "sg:phone":"+1 920 834 7800",
    "sg:postcode":"54153",
    "sg:province":"WI",
    "wof:name":"Oconto High School",
    "wof:placetype":"venue"
},
  "geometry": {"coordinates":[-87.869789,44.905427],"type":"Point"}
}