{
  "type": "Feature",
  "properties": {
    "iso:country":"US",
    "sg:address":"1750 N Mayfair Rd",
    "sg:city":"Milwaukee",
    "sg:classifiers":[
        {
            "category":"Autos & Motor Vehicles",
            "subcategory":"Automobile Sales",
            "type":"Retail Goods"
        }
    ],
    "sg:phone":"+1 414 302 2800",
    "sg:postcode":"53222",
    "sg:province":"WI",
    "sg:tags":[
        "car",
        "dealer"
    ],
    "wof:name":"Ewald Budget Used Cars",
    "wof:placetype":"venue"
},
  "geometry": {"coordinates":[-88.04749,43.055004],"type":"Point"}
}