{
  "type": "Feature",
  "properties": {
    "iso:country":"US",
    "sg:address":"630 S Central Ave",
    "sg:city":"Marshfield",
    "sg:classifiers":[
        {
            "category":"Government",
            "subcategory":"Office",
            "type":"Public Place"
        }
    ],
    "sg:phone":"+1 715 389 1795",
    "sg:postcode":"54449",
    "sg:province":"WI",
    "wof:name":"Victim Witness Program",
    "wof:placetype":"venue"
},
  "geometry": {"coordinates":[-90.176866,44.662155],"type":"Point"}
}