{
  "type": "Feature",
  "properties": {
    "iso:country":"US",
    "sg:address":"1522 Co Rd F",
    "sg:city":"Athens",
    "sg:classifiers":[
        {
            "category":"Home & Garden",
            "subcategory":"Furniture",
            "type":"Retail Goods"
        }
    ],
    "sg:phone":"+1 715 257 1160",
    "sg:postcode":"54411",
    "sg:province":"WI",
    "wof:name":"Whispering Pine Wood Craft",
    "wof:placetype":"venue"
},
  "geometry": {"coordinates":[-90.10142500000001,45.076553],"type":"Point"}
}