{
  "type": "Feature",
  "properties": {
    "iso:country":"US",
    "sg:address":"5825 N 99th St",
    "sg:city":"Milwaukee",
    "sg:classifiers":[
        {
            "category":"Utilities",
            "subcategory":"Mobile Phone",
            "type":"Services"
        }
    ],
    "sg:phone":"+1 414 464 2855",
    "sg:postcode":"53225",
    "sg:province":"WI",
    "sg:tags":[
        "telephone",
        "cellular"
    ],
    "wof:name":"Cingular Wireless",
    "wof:placetype":"venue"
},
  "geometry": {"coordinates":[-88.035781,43.123244],"type":"Point"}
}