{
  "type": "Feature",
  "properties": {
    "iso:country":"US",
    "sg:address":"404 Glenway St",
    "sg:city":"Madison",
    "sg:classifiers":[
        {
            "category":"Real Estate",
            "subcategory":"Architect",
            "type":"Services"
        }
    ],
    "sg:phone":"+1 608 233 8823",
    "sg:postcode":"53711",
    "sg:province":"WI",
    "sg:tags":[
        "engineering",
        "architectural"
    ],
    "wof:name":"Architects-Engineers Inc",
    "wof:placetype":"venue"
},
  "geometry": {"coordinates":[-89.438785,43.06018],"type":"Point"}
}