{
  "type": "Feature",
  "properties": {
    "addr:full":"1577 Westside Rd Lake Geneva WI 53147",
    "addr:housenumber":"1577",
    "addr:postcode":"53147",
    "addr:street":"Westside Rd",
    "iso:country":"US",
    "sg:address":"1577 Westside Rd",
    "sg:city":"Lake Geneva",
    "sg:classifiers":[
        {
            "category":"Farming",
            "subcategory":"Farm",
            "type":"Manufacturing & Wholesale Goods"
        }
    ],
    "sg:phone":"+1 262 248 6482",
    "sg:postcode":"53147",
    "sg:province":"WI",
    "sg:tags":[
        "crop",
        "general"
    ],
    "wof:name":"Phil Esmond",
    "wof:placetype":"venue"
},
  "geometry": {"coordinates":[-88.423312,42.550639],"type":"Point"}
}