{
  "type": "Feature",
  "properties": {
    "iso:country":"US",
    "sg:address":"5253 Harding Ave",
    "sg:city":"Plover",
    "sg:classifiers":[
        {
            "category":"Travel",
            "subcategory":"Hotels & Motels",
            "type":"Entertainment"
        }
    ],
    "sg:phone":"+1 715 341 7300",
    "sg:postcode":"54467",
    "sg:province":"WI",
    "wof:name":"Days Inn",
    "wof:placetype":"venue"
},
  "geometry": {"coordinates":[-89.51498599999999,44.430119],"type":"Point"}
}