{
  "type": "Feature",
  "properties": {
    "iso:country":"US",
    "sg:address":"6252 Kampen Rd",
    "sg:city":"Arlington",
    "sg:phone":"+1 608 635 2073",
    "sg:postcode":"53911",
    "sg:province":"WI",
    "sg:tags":[
        "farm",
        "field",
        "corn",
        "crop"
    ],
    "wof:name":"Robert Stoltenberg",
    "wof:placetype":"venue"
},
  "geometry": {"coordinates":[-89.31296399999999,43.324874],"type":"Point"}
}