{
  "type": "Feature",
  "properties": {
    "iso:country":"US",
    "sg:address":"4815 Co Rd J",
    "sg:city":"Sheboygan",
    "sg:classifiers":[
        {
            "category":"Education",
            "subcategory":"School",
            "type":"Public Place"
        }
    ],
    "sg:phone":"+1 920 459 3595",
    "sg:postcode":"53083",
    "sg:province":"WI",
    "sg:website":"www.sheboygan.k12.wi.us/lerdman",
    "wof:name":"Lincoln Erdman Elementary Schl",
    "wof:placetype":"venue"
},
  "geometry": {"coordinates":[-87.77015900000001,43.78993],"type":"Point"}
}