{
  "type": "Feature",
  "properties": {
    "iso:country":"US",
    "sg:address":"5370 Century Rd",
    "sg:city":"Greenwood",
    "sg:classifiers":[
        {
            "category":"Real Estate",
            "subcategory":"Real Estate Operator",
            "type":"Services"
        }
    ],
    "sg:phone":"+1 715 267 6146",
    "sg:postcode":"54437",
    "sg:province":"WI",
    "sg:tags":[
        "property",
        "lessor"
    ],
    "wof:name":"Harry Johnson",
    "wof:placetype":"venue"
},
  "geometry": {"coordinates":[-90.584647,44.784726],"type":"Point"}
}