{
  "type": "Feature",
  "properties": {
    "addr:full":"4301 Temkin Rd Columbus WI 53925",
    "addr:housenumber":"4301",
    "addr:postcode":"53925",
    "addr:street":"Temkin Rd",
    "iso:country":"US",
    "sg:address":"4301 Temkin Rd",
    "sg:city":"Columbus",
    "sg:classifiers":[
        {
            "category":"Manufacturing",
            "subcategory":"Metals",
            "type":"Manufacturing & Wholesale Goods"
        }
    ],
    "sg:phone":"+1 920 623 2221",
    "sg:postcode":"53925",
    "sg:province":"WI",
    "sg:tags":[
        "steel",
        "product",
        "mfg",
        "food",
        "fabrication",
        "structural"
    ],
    "wof:name":"Langer's Custom Fabrication",
    "wof:placetype":"venue"
},
  "geometry": {"coordinates":[-89.008201,43.344586],"type":"Point"}
}