{
  "type": "Feature",
  "properties": {
    "iso:country":"US",
    "sg:address":"726 E 2nd St",
    "sg:city":"Merrill",
    "sg:classifiers":[
        {
            "category":"Social Services",
            "type":"Services"
        }
    ],
    "sg:phone":"+1 715 539 8080",
    "sg:postcode":"54452",
    "sg:province":"WI",
    "sg:tags":[
        "counseling"
    ],
    "wof:name":"Central Wisconsin Psychlgcl",
    "wof:placetype":"venue"
},
  "geometry": {"coordinates":[-89.690144,45.180629],"type":"Point"}
}