{
  "type": "Feature",
  "properties": {
    "iso:country":"US",
    "sg:address":"7666 Ollinger Rd",
    "sg:city":"Beaver Dam",
    "sg:phone":"+1 920 885 4235",
    "sg:postcode":"53916",
    "sg:province":"WI",
    "sg:tags":[
        "farm",
        "grain",
        "cash"
    ],
    "wof:name":"Edmund Czajka",
    "wof:placetype":"venue"
},
  "geometry": {"coordinates":[-88.79775100000001,43.477186],"type":"Point"}
}