{
  "type": "Feature",
  "properties": {
    "iso:country":"US",
    "sg:address":"5689 Tamarack Trl",
    "sg:city":"Whitewater",
    "sg:classifiers":[
        {
            "category":"Professional",
            "type":"Services"
        }
    ],
    "sg:phone":"+1 262 495 3131",
    "sg:postcode":"53190",
    "sg:province":"WI",
    "wof:name":"Fair Weather Events",
    "wof:placetype":"venue"
},
  "geometry": {"coordinates":[-88.579913,42.822371],"type":"Point"}
}