{
  "type": "Feature",
  "properties": {
    "iso:country":"US",
    "sg:address":"262 Muenter Ave",
    "sg:city":"Fond Du Lac",
    "sg:classifiers":[
        {
            "category":"Social Services",
            "type":"Services"
        }
    ],
    "sg:phone":"+1 920 921 9988",
    "sg:postcode":"54935",
    "sg:province":"WI",
    "sg:tags":[
        "mission"
    ],
    "wof:name":"Winds Of The Spirit Ministries",
    "wof:placetype":"venue"
},
  "geometry": {"coordinates":[-88.46813299999999,43.770676],"type":"Point"}
}