{
  "type": "Feature",
  "properties": {
    "iso:country":"US",
    "sg:address":"5141 Arntz St",
    "sg:city":"Winter",
    "sg:classifiers":[
        {
            "category":"Social Services",
            "subcategory":"Adult Care",
            "type":"Services"
        }
    ],
    "sg:phone":"+1 715 266 2233",
    "sg:postcode":"54896",
    "sg:province":"WI",
    "sg:tags":[
        "organization",
        "senior",
        "citizen"
    ],
    "wof:name":"Winter Senior Citizen Ctr",
    "wof:placetype":"venue"
},
  "geometry": {"coordinates":[-91.01306599999999,45.82137],"type":"Point"}
}