{
  "type": "Feature",
  "properties": {
    "iso:country":"US",
    "sg:address":"6516 Rhine Rd",
    "sg:city":"Watertown",
    "sg:classifiers":[
        {
            "category":"Wholesale",
            "subcategory":"Auto Parts",
            "type":"Manufacturing & Wholesale Goods"
        }
    ],
    "sg:phone":"+1 920 261 4830",
    "sg:postcode":"53098",
    "sg:province":"WI",
    "sg:tags":[
        "automobile",
        "wrecking"
    ],
    "wof:name":"Sellnow's Salvage",
    "wof:placetype":"venue"
},
  "geometry": {"coordinates":[-88.720059,43.215443],"type":"Point"}
}