{
  "type": "Feature",
  "properties": {
    "iso:country":"US",
    "sg:address":"575 Lester Ave",
    "sg:city":"Onalaska",
    "sg:classifiers":[
        {
            "category":"Real Estate",
            "subcategory":"Real Estate Agent",
            "type":"Services"
        }
    ],
    "sg:phone":"+1 608 783 6700",
    "sg:postcode":"54650",
    "sg:province":"WI",
    "sg:website":"www.hoppensrealty.com",
    "wof:name":"Hoppens Realty",
    "wof:placetype":"venue"
},
  "geometry": {"coordinates":[-91.197971,43.873625],"type":"Point"}
}