{
  "type": "Feature",
  "properties": {
    "iso:country":"US",
    "sg:address":"19130 72nd Ave",
    "sg:city":"Chippewa Falls",
    "sg:classifiers":[
        {
            "category":"Farming",
            "subcategory":"Farm",
            "type":"Manufacturing & Wholesale Goods"
        },
        {
            "category":"Home & Garden",
            "subcategory":"Garden Supply",
            "type":"Retail Goods"
        }
    ],
    "sg:phone":"+1 715 723 3414",
    "sg:postcode":"54729",
    "sg:province":"WI",
    "sg:tags":[
        "food",
        "covered",
        "center",
        "crop"
    ],
    "wof:name":"Halfen Garden Center",
    "wof:placetype":"venue"
},
  "geometry": {"coordinates":[-91.284601,44.947123],"type":"Point"}
}