{
  "type": "Feature",
  "properties": {
    "iso:country":"US",
    "sg:address":"3570 US Hwy 8",
    "sg:city":"Argonne",
    "sg:classifiers":[
        {
            "category":"Wholesale",
            "subcategory":"Construction Materials",
            "type":"Manufacturing & Wholesale Goods"
        }
    ],
    "sg:phone":"+1 715 674 6333",
    "sg:postcode":"54511",
    "sg:province":"WI",
    "sg:tags":[
        "product",
        "lumber"
    ],
    "wof:name":"Spread Eagle Hardwoods Inc",
    "wof:placetype":"venue"
},
  "geometry": {"coordinates":[-88.604117,45.657797],"type":"Point"}
}