{
  "type": "Feature",
  "properties": {
    "iso:country":"US",
    "sg:address":"10504 W Bluemound Rd",
    "sg:city":"Milwaukee",
    "sg:classifiers":[
        {
            "category":"Home & Garden",
            "subcategory":"Furniture",
            "type":"Retail Goods"
        }
    ],
    "sg:phone":"+1 414 771 4455",
    "sg:postcode":"53226",
    "sg:province":"WI",
    "wof:name":"Verlo Mattress Factory Stores",
    "wof:placetype":"venue"
},
  "geometry": {"coordinates":[-88.043451,43.034865],"type":"Point"}
}