{
  "type": "Feature",
  "properties": {
    "addr:full":"2810 E Washington Ave Madison WI 53704",
    "addr:housenumber":"2810",
    "addr:postcode":"53704",
    "addr:street":"E Washington Ave",
    "iso:country":"US",
    "sg:address":"2810 E Washington Ave",
    "sg:city":"Madison",
    "sg:classifiers":[
        {
            "category":"Food & Beverages",
            "subcategory":"Bakery",
            "type":"Retail Goods"
        }
    ],
    "sg:phone":"+1 608 245 0404",
    "sg:postcode":"53704",
    "sg:province":"WI",
    "sg:tags":[
        "doughnut"
    ],
    "wof:name":"Peoples Bakery",
    "wof:placetype":"venue"
},
  "geometry": {"coordinates":[-89.344444,43.103221],"type":"Point"}
}