{
  "type": "Feature",
  "properties": {
    "iso:country":"US",
    "sg:address":"684 207th Ave",
    "sg:city":"Somerset",
    "sg:classifiers":[
        {
            "category":"Building & Trades",
            "subcategory":"Construction",
            "type":"Services"
        }
    ],
    "sg:phone":"+1 715 247 5703",
    "sg:postcode":"54025",
    "sg:province":"WI",
    "sg:tags":[
        "housing",
        "family",
        "contractor"
    ],
    "wof:name":"Scott C Thell",
    "wof:placetype":"venue"
},
  "geometry": {"coordinates":[-92.67330699999999,45.161851],"type":"Point"}
}