{
  "type": "Feature",
  "properties": {
    "iso:country":"US",
    "sg:address":"2908 S Gray Bill Dr",
    "sg:city":"Beloit",
    "sg:classifiers":[
        {
            "category":"Shopping",
            "subcategory":"Hobbies, Toys, & Games",
            "type":"Retail Goods"
        }
    ],
    "sg:phone":"+1 608 363 5099",
    "sg:postcode":"53511",
    "sg:province":"WI",
    "sg:tags":[
        "supply",
        "supplies-wholesale",
        "manufacturer"
    ],
    "sg:website":"http://www.patchproducts.com",
    "wof:name":"Patch Products, Inc.",
    "wof:placetype":"venue"
},
  "geometry": {"coordinates":[-89.01964700000001,42.551388],"type":"Point"}
}