{
  "type": "Feature",
  "properties": {
    "iso:country":"US",
    "sg:address":"705 Berlin St",
    "sg:city":"Waupaca",
    "sg:classifiers":[
        {
            "category":"Personal",
            "subcategory":"Beauty Salon",
            "type":"Services"
        }
    ],
    "sg:phone":"+1 715 256 0405",
    "sg:postcode":"54981",
    "sg:province":"WI",
    "sg:tags":[
        "shop"
    ],
    "wof:name":"Crystal Cutting Zone LLC",
    "wof:placetype":"venue"
},
  "geometry": {"coordinates":[-89.080327,44.351318],"type":"Point"}
}