{
  "type": "Feature",
  "properties": {
    "iso:country":"US",
    "sg:address":"3692 Lakeview Dr",
    "sg:city":"Suamico",
    "sg:classifiers":[
        {
            "category":"Farming",
            "subcategory":"Nursery",
            "type":"Manufacturing & Wholesale Goods"
        }
    ],
    "sg:phone":"+1 920 434 4299",
    "sg:postcode":"54173",
    "sg:province":"WI",
    "sg:tags":[
        "ornamental"
    ],
    "wof:name":"Werys Blossom Creek",
    "wof:placetype":"venue"
},
  "geometry": {"coordinates":[-88.039029,44.623935],"type":"Point"}
}