{
  "type": "Feature",
  "properties": {
    "iso:country":"US",
    "sg:address":"115 Williams St",
    "sg:city":"Randolph",
    "sg:classifiers":[
        {
            "category":"Manufacturing",
            "subcategory":"Printing",
            "type":"Manufacturing & Wholesale Goods"
        }
    ],
    "sg:phone":"+1 920 326 3196",
    "sg:postcode":"53956",
    "sg:province":"WI",
    "sg:tags":[
        "commercial",
        "lithographic"
    ],
    "wof:name":"Citizens Neighbors Marketeers",
    "wof:placetype":"venue"
},
  "geometry": {"coordinates":[-89.005071,43.538589],"type":"Point"}
}