{
  "type": "Feature",
  "properties": {
    "addr:full":"137 S Main St Oregon WI 53575",
    "addr:housenumber":"137",
    "addr:postcode":"53575",
    "addr:street":"S Main St",
    "iso:country":"US",
    "sg:address":"137 S Main St",
    "sg:city":"Oregon",
    "sg:classifiers":[
        {
            "category":"Health Services",
            "subcategory":"Doctor",
            "type":"Services"
        }
    ],
    "sg:phone":"+1 608 835 5588",
    "sg:postcode":"53575",
    "sg:province":"WI",
    "sg:tags":[
        "medical"
    ],
    "wof:name":"Uw Health Physicians Plus",
    "wof:placetype":"venue"
},
  "geometry": {"coordinates":[-89.38476300000001,42.925229],"type":"Point"}
}