{
  "type": "Feature",
  "properties": {
    "iso:country":"US",
    "sg:address":"2233 S Hastings Way",
    "sg:city":"Eau Claire",
    "sg:classifiers":[
        {
            "category":"Wholesale",
            "subcategory":"Non-durable Goods",
            "type":"Manufacturing & Wholesale Goods"
        }
    ],
    "sg:phone":"+1 715 835 5555",
    "sg:postcode":"54701",
    "sg:province":"WI",
    "sg:tags":[
        "advertising",
        "specialty"
    ],
    "wof:name":"Dean and Associates Inc",
    "wof:placetype":"venue"
},
  "geometry": {"coordinates":[-91.46190300000001,44.795514],"type":"Point"}
}