{
  "type": "Feature",
  "properties": {
    "iso:country":"US",
    "sg:address":"5551 Little Lake Rd",
    "sg:city":"Marion",
    "sg:classifiers":[
        {
            "category":"Farming",
            "subcategory":"Farm",
            "type":"Manufacturing & Wholesale Goods"
        }
    ],
    "sg:phone":"+1 715 754 5674",
    "sg:postcode":"54950",
    "sg:province":"WI",
    "sg:tags":[
        "crop",
        "general"
    ],
    "wof:name":"Arndt Marlin",
    "wof:placetype":"venue"
},
  "geometry": {"coordinates":[-88.94841599999999,44.637692],"type":"Point"}
}