{
  "type": "Feature",
  "properties": {
    "iso:country":"US",
    "sg:address":"415 N Lake Ave",
    "sg:city":"Twin Lakes",
    "sg:classifiers":[
        {
            "category":"Retail",
            "subcategory":"Car Wash",
            "type":"Services"
        },
        {
            "category":"Retail",
            "subcategory":"Auto Repair",
            "type":"Services"
        }
    ],
    "sg:phone":"+1 262 877 3916",
    "sg:postcode":"53181",
    "sg:province":"WI",
    "sg:tags":[
        "detailing"
    ],
    "sg:website":"www.spray-n-shine.com",
    "wof:name":"Spray N Shine Car Wash & Detail Shop",
    "wof:placetype":"venue"
},
  "geometry": {"coordinates":[-88.246696,42.5369],"type":"Point"}
}