{
  "type": "Feature",
  "properties": {
    "iso:country":"US",
    "sg:address":"1907 S Calhoun Rd",
    "sg:city":"New Berlin",
    "sg:classifiers":[
        {
            "category":"Restaurant",
            "type":"Food & Drink"
        }
    ],
    "sg:phone":"+1 262 786 0456",
    "sg:postcode":"53151",
    "sg:province":"WI",
    "wof:name":"Alpha Gyros",
    "wof:placetype":"venue"
},
  "geometry": {"coordinates":[-88.127385,43.009007],"type":"Point"}
}