{
  "type": "Feature",
  "properties": {
    "iso:country":"US",
    "sg:address":"2525 63rd St",
    "sg:city":"Kenosha",
    "sg:classifiers":[
        {
            "category":"Real Estate",
            "subcategory":"Real Estate Agent",
            "type":"Services"
        }
    ],
    "sg:phone":"+1 262 654 7222",
    "sg:postcode":"53143",
    "sg:province":"WI",
    "wof:name":"First National Real Estate",
    "wof:placetype":"venue"
},
  "geometry": {"coordinates":[-87.83957599999999,42.577623],"type":"Point"}
}