{
  "type": "Feature",
  "properties": {
    "iso:country":"US",
    "sg:address":"10343 W Donna Dr",
    "sg:city":"Milwaukee",
    "sg:classifiers":[
        {
            "category":"Freight",
            "type":"Transportation"
        }
    ],
    "sg:phone":"+1 414 355 8915",
    "sg:postcode":"53224",
    "sg:province":"WI",
    "sg:tags":[
        "operator",
        "local",
        "trucking"
    ],
    "wof:name":"Runway Express",
    "wof:placetype":"venue"
},
  "geometry": {"coordinates":[-88.042968,43.171114],"type":"Point"}
}