{
  "type": "Feature",
  "properties": {
    "iso:country":"US",
    "sg:address":"190 Gardner Ave",
    "sg:city":"Burlington",
    "sg:classifiers":[
        {
            "category":"Health Services",
            "subcategory":"Dentist",
            "type":"Services"
        }
    ],
    "sg:phone":"+1 262 763 8360",
    "sg:postcode":"53105",
    "sg:province":"WI",
    "sg:website":"www.charlespuntillo.com",
    "wof:name":"Puntillo Charles DDS",
    "wof:placetype":"venue"
},
  "geometry": {"coordinates":[-88.279633,42.670608],"type":"Point"}
}