{
  "type": "Feature",
  "properties": {
    "iso:country":"US",
    "sg:address":"1007 E Main St",
    "sg:city":"Merrill",
    "sg:classifiers":[
        {
            "category":"Bars & Pubs",
            "type":"Food & Drink"
        }
    ],
    "sg:phone":"+1 715 539 8866",
    "sg:postcode":"54452",
    "sg:province":"WI",
    "sg:tags":[
        "drinking"
    ],
    "wof:name":"Chatterbox 2",
    "wof:placetype":"venue"
},
  "geometry": {"coordinates":[-89.684392,45.180494],"type":"Point"}
}