{
  "type": "Feature",
  "properties": {
    "iso:country":"US",
    "sg:address":"39142 Hunts Valley Ln",
    "sg:city":"Independence",
    "sg:classifiers":[
        {
            "category":"Farming",
            "subcategory":"Dairy Farm",
            "type":"Manufacturing & Wholesale Goods"
        }
    ],
    "sg:phone":"+1 715 985 3589",
    "sg:postcode":"54747",
    "sg:province":"WI",
    "wof:name":"Little Toggenburg Farms",
    "wof:placetype":"venue"
},
  "geometry": {"coordinates":[-91.509812,44.407709],"type":"Point"}
}