{
  "type": "Feature",
  "properties": {
    "iso:country":"US",
    "sg:address":"803 5th Ave",
    "sg:city":"Prairie Farm",
    "sg:classifiers":[
        {
            "category":"Farming",
            "subcategory":"Dairy Farm",
            "type":"Manufacturing & Wholesale Goods"
        }
    ],
    "sg:phone":"+1 715 455 1628",
    "sg:postcode":"54762",
    "sg:province":"WI",
    "wof:name":"Milo Espeseth Farm",
    "wof:placetype":"venue"
},
  "geometry": {"coordinates":[-91.993275,45.280589],"type":"Point"}
}