{
  "type": "Feature",
  "properties": {
    "iso:country":"US",
    "sg:address":"831 E Appleridge Dr",
    "sg:city":"Janesville",
    "sg:classifiers":[
        {
            "category":"Building & Trades",
            "subcategory":"Construction",
            "type":"Services"
        }
    ],
    "sg:phone":"+1 608 754 6679",
    "sg:postcode":"53545",
    "sg:province":"WI",
    "sg:tags":[
        "excavating",
        "contractor"
    ],
    "wof:name":"Mike Nehls Excavating",
    "wof:placetype":"venue"
},
  "geometry": {"coordinates":[-89.01631999999999,42.742919],"type":"Point"}
}