{
  "type": "Feature",
  "properties": {
    "iso:country":"US",
    "sg:address":"20520 Enterprise Ave",
    "sg:city":"Brookfield",
    "sg:classifiers":[
        {
            "category":"Home & Garden",
            "subcategory":"Building Materials",
            "type":"Retail Goods"
        }
    ],
    "sg:phone":"+1 262 784 8822",
    "sg:postcode":"53045",
    "sg:province":"WI",
    "sg:tags":[
        "door"
    ],
    "sg:website":"www.geisbldg.com",
    "wof:name":"Geis Building Products",
    "wof:placetype":"venue"
},
  "geometry": {"coordinates":[-88.16735799999999,43.052847],"type":"Point"}
}