{
  "type": "Feature",
  "properties": {
    "iso:country":"US",
    "sg:address":"5537 690th Ave",
    "sg:city":"Beldenville",
    "sg:classifiers":[
        {
            "category":"Professional",
            "type":"Services"
        }
    ],
    "sg:phone":"+1 715 273 4057",
    "sg:postcode":"54003",
    "sg:province":"WI",
    "wof:name":"Johnson Sales & Serv",
    "wof:placetype":"venue"
},
  "geometry": {"coordinates":[-92.408935,44.789884],"type":"Point"}
}