{
  "type": "Feature",
  "properties": {
    "addr:full":"470 E Rubicon St Hustisford WI 53034",
    "addr:housenumber":"470",
    "addr:postcode":"53034",
    "addr:street":"E Rubicon St",
    "iso:country":"US",
    "sg:address":"470 E Rubicon St",
    "sg:city":"Hustisford",
    "sg:classifiers":[
        {
            "category":"Health Services",
            "subcategory":"Doctor",
            "type":"Services"
        }
    ],
    "sg:phone":"+1 920 349 3040",
    "sg:postcode":"53034",
    "sg:province":"WI",
    "sg:tags":[
        "dentist"
    ],
    "wof:name":"Paul J Mayer DDS",
    "wof:placetype":"venue"
},
  "geometry": {"coordinates":[-88.594843,43.341538],"type":"Point"}
}