{
  "type": "Feature",
  "properties": {
    "iso:country":"US",
    "sg:address":"4505 Reforestation Rd",
    "sg:city":"Green Bay",
    "sg:classifiers":[
        {
            "category":"Professional",
            "subcategory":"Business Services",
            "type":"Services"
        }
    ],
    "sg:phone":"+1 920 434 6479",
    "sg:postcode":"54313",
    "sg:province":"WI",
    "wof:name":"Precision Design & Drafting",
    "wof:placetype":"venue"
},
  "geometry": {"coordinates":[-88.090385,44.656068],"type":"Point"}
}