{
  "type": "Feature",
  "properties": {
    "addr:full":"6431 96th Ave Kenosha WI 53142",
    "addr:housenumber":"6431",
    "addr:postcode":"53142",
    "addr:street":"96Th Ave",
    "iso:country":"US",
    "sg:address":"6431 96th Ave",
    "sg:city":"Kenosha",
    "sg:classifiers":[
        {
            "category":"Professional",
            "subcategory":"Business Services",
            "type":"Services"
        }
    ],
    "sg:phone":"+1 262 344 0854",
    "sg:postcode":"53142",
    "sg:province":"WI",
    "sg:tags":[
        "holding"
    ],
    "wof:name":"Conquest Holdings",
    "wof:placetype":"venue"
},
  "geometry": {"coordinates":[-87.926182,42.576103],"type":"Point"}
}