{
  "type": "Feature",
  "properties": {
    "iso:country":"US",
    "sg:address":"8830 Bluebird Ln",
    "sg:city":"Waterford",
    "sg:classifiers":[
        {
            "category":"Organizations",
            "subcategory":"Non-profit Organization",
            "type":"Services"
        }
    ],
    "sg:phone":"+1 262 895 6866",
    "sg:postcode":"53185",
    "sg:province":"WI",
    "sg:tags":[
        "medical",
        "management"
    ],
    "wof:name":"Medicare Management Conslnts",
    "wof:placetype":"venue"
},
  "geometry": {"coordinates":[-88.158934,42.842521],"type":"Point"}
}