{
  "type": "Feature",
  "properties": {
    "iso:country":"US",
    "sg:address":"5701 Vineyard Rd",
    "sg:city":"Oregon",
    "sg:classifiers":[
        {
            "category":"Building & Trades",
            "subcategory":"Construction",
            "type":"Services"
        }
    ],
    "sg:phone":"+1 608 835 1635",
    "sg:postcode":"53575",
    "sg:province":"WI",
    "sg:tags":[
        "contractor"
    ],
    "wof:name":"All State Roofing LLC",
    "wof:placetype":"venue"
},
  "geometry": {"coordinates":[-89.43954600000001,42.971333],"type":"Point"}
}