{
  "type": "Feature",
  "properties": {
    "iso:country":"US",
    "sg:address":"1071 Echo Ln",
    "sg:city":"Green Bay",
    "sg:classifiers":[
        {
            "category":"Professional",
            "subcategory":"Business Services",
            "type":"Services"
        }
    ],
    "sg:phone":"+1 920 499 7431",
    "sg:postcode":"54304",
    "sg:province":"WI",
    "wof:name":"Bouchea Enterprises Inc",
    "wof:placetype":"venue"
},
  "geometry": {"coordinates":[-88.070875,44.497224],"type":"Point"}
}