{
  "type": "Feature",
  "properties": {
    "iso:country":"US",
    "sg:address":"2882 Rock Ln",
    "sg:city":"Cuba City",
    "sg:classifiers":[
        {
            "category":"Farming",
            "subcategory":"Farm",
            "type":"Manufacturing & Wholesale Goods"
        }
    ],
    "sg:phone":"+1 608 568 3516",
    "sg:postcode":"53807",
    "sg:province":"WI",
    "wof:name":"Dietzel Farms & Corp",
    "wof:placetype":"venue"
},
  "geometry": {"coordinates":[-90.55852,42.609894],"type":"Point"}
}