{
  "type": "Feature",
  "properties": {
    "iso:country":"US",
    "sg:address":"1485 Oak Opening Dr",
    "sg:city":"Stoughton",
    "sg:classifiers":[
        {
            "category":"Utilities",
            "subcategory":"Telephone",
            "type":"Services"
        }
    ],
    "sg:phone":"+1 608 873 3838",
    "sg:postcode":"53589",
    "sg:province":"WI",
    "sg:tags":[
        "company"
    ],
    "wof:name":"On Track Communication",
    "wof:placetype":"venue"
},
  "geometry": {"coordinates":[-89.253511,42.926946],"type":"Point"}
}