{
  "type": "Feature",
  "properties": {
    "iso:country":"US",
    "sg:address":"1206 N Gaffney Rd",
    "sg:city":"Belleville",
    "sg:classifiers":[
        {
            "category":"Building & Trades",
            "subcategory":"Construction",
            "type":"Services"
        }
    ],
    "sg:phone":"+1 608 424 6526",
    "sg:postcode":"53508",
    "sg:province":"WI",
    "sg:tags":[
        "siding",
        "contractor"
    ],
    "wof:name":"Ralston & Assoc Siding",
    "wof:placetype":"venue"
},
  "geometry": {"coordinates":[-89.549256,42.917388],"type":"Point"}
}