{
  "type": "Feature",
  "properties": {
    "iso:country":"US",
    "sg:address":"115 Bogert St",
    "sg:city":"Beaver Dam",
    "sg:classifiers":[
        {
            "category":"Recreation",
            "type":"Entertainment"
        }
    ],
    "sg:phone":"+1 920 887 1312",
    "sg:postcode":"53916",
    "sg:province":"WI",
    "sg:tags":[
        "goo",
        "mfg"
    ],
    "wof:name":"Z S Archery",
    "wof:placetype":"venue"
},
  "geometry": {"coordinates":[-88.829053,43.462936],"type":"Point"}
}