{
  "type": "Feature",
  "properties": {
    "iso:country":"US",
    "sg:address":"208 190th St",
    "sg:city":"Baldwin",
    "sg:classifiers":[
        {
            "category":"Farming",
            "subcategory":"Farm",
            "type":"Manufacturing & Wholesale Goods"
        }
    ],
    "sg:phone":"+1 715 684 3918",
    "sg:postcode":"54002",
    "sg:province":"WI",
    "sg:tags":[
        "crop",
        "general"
    ],
    "wof:name":"Bob Hansen",
    "wof:placetype":"venue"
},
  "geometry": {"coordinates":[-92.41532,44.896006],"type":"Point"}
}