{
  "type": "Feature",
  "properties": {
    "iso:country":"US",
    "sg:address":"3665 Grondin Rd",
    "sg:city":"Sturgeon Bay",
    "sg:classifiers":[
        {
            "category":"Organizations",
            "subcategory":"Professional Association",
            "type":"Services"
        }
    ],
    "sg:phone":"+1 920 746 9077",
    "sg:postcode":"54235",
    "sg:province":"WI",
    "wof:name":"Hidden Ridge Resort Condo Assn",
    "wof:placetype":"venue"
},
  "geometry": {"coordinates":[-87.407642,44.847483],"type":"Point"}
}