{
  "type": "Feature",
  "properties": {
    "addr:full":"7046 S US Hwy 45 Oshkosh WI 54902",
    "addr:housenumber":"7046",
    "addr:postcode":"54902",
    "addr:street":"S Us Hwy 45",
    "iso:country":"US",
    "sg:address":"7046 S US Hwy 45",
    "sg:city":"Oshkosh",
    "sg:classifiers":[
        {
            "category":"Professional",
            "type":"Services"
        }
    ],
    "sg:phone":"+1 920 688 5104",
    "sg:postcode":"54902",
    "sg:province":"WI",
    "sg:tags":[
        "establishment"
    ],
    "wof:name":"Courter & Courter",
    "wof:placetype":"venue"
},
  "geometry": {"coordinates":[-88.473561,43.909877],"type":"Point"}
}