{
  "type": "Feature",
  "properties": {
    "iso:country":"US",
    "sg:address":"2094 Wildwood Dr",
    "sg:city":"Suamico",
    "sg:classifiers":[
        {
            "category":"Shopping",
            "subcategory":"Clothing, Apparel, & Fashions",
            "type":"Retail Goods"
        }
    ],
    "sg:phone":"+1 920 434 9614",
    "sg:postcode":"54173",
    "sg:province":"WI",
    "wof:name":"Fit Express For Men LLC",
    "wof:placetype":"venue"
},
  "geometry": {"coordinates":[-88.06351100000001,44.668403],"type":"Point"}
}