{
  "type": "Feature",
  "properties": {
    "iso:country":"US",
    "sg:address":"375 Williamstowne",
    "sg:city":"Delafield",
    "sg:classifiers":[
        {
            "category":"Banks & Credit Unions",
            "subcategory":"Investment Brokerage",
            "type":"Services"
        }
    ],
    "sg:phone":"+1 262 646 5073",
    "sg:postcode":"53018",
    "sg:province":"WI",
    "sg:tags":[
        "security"
    ],
    "wof:name":"Edward Jones 04441",
    "wof:placetype":"venue"
},
  "geometry": {"coordinates":[-88.377376,43.050055],"type":"Point"}
}