{
  "type": "Feature",
  "properties": {
    "iso:country":"US",
    "sg:address":"264 Shady Nook Ln",
    "sg:city":"Withee",
    "sg:classifiers":[
        {
            "category":"Retail",
            "subcategory":"Repair Shop",
            "type":"Services"
        }
    ],
    "sg:phone":"+1 715 229 2316",
    "sg:postcode":"54498",
    "sg:province":"WI",
    "sg:tags":[
        "welding"
    ],
    "wof:name":"Central Sanitary Welding LLC",
    "wof:placetype":"venue"
},
  "geometry": {"coordinates":[-90.635046,45.041026],"type":"Point"}
}