{
  "type": "Feature",
  "properties": {
    "addr:full":"725 Pine St Barron WI 54812",
    "addr:housenumber":"725",
    "addr:postcode":"54812",
    "addr:street":"Pine St",
    "iso:country":"US",
    "sg:address":"725 Pine St",
    "sg:city":"Barron",
    "sg:classifiers":[
        {
            "category":"Organizations",
            "subcategory":"Community Association",
            "type":"Services"
        }
    ],
    "sg:phone":"+1 715 637 3551",
    "sg:postcode":"54812",
    "sg:province":"WI",
    "wof:name":"Kiwanis International Inc",
    "wof:placetype":"venue"
},
  "geometry": {"coordinates":[-91.84649,45.391824],"type":"Point"}
}