{
  "type": "Feature",
  "properties": {
    "addr:full":"10832 Co Rd G Osseo WI 54758",
    "addr:housenumber":"10832",
    "addr:postcode":"54758",
    "addr:street":"Co Rd",
    "iso:country":"US",
    "sg:address":"10832 Co Rd G",
    "sg:city":"Osseo",
    "sg:classifiers":[
        {
            "category":"Farming",
            "subcategory":"Farm",
            "type":"Manufacturing & Wholesale Goods"
        }
    ],
    "sg:phone":"+1 715 984 2574",
    "sg:postcode":"54758",
    "sg:province":"WI",
    "sg:tags":[
        "crop",
        "general"
    ],
    "wof:name":"John Larson",
    "wof:placetype":"venue"
},
  "geometry": {"coordinates":[-91.15028599999999,44.464544],"type":"Point"}
}