{
  "type": "Feature",
  "properties": {
    "iso:country":"US",
    "sg:address":"3820 Oak Acre Dr",
    "sg:city":"Fond Du Lac",
    "sg:classifiers":[
        {
            "category":"Professional",
            "subcategory":"Management & Consulting",
            "type":"Services"
        }
    ],
    "sg:phone":"+1 920 924 6060",
    "sg:postcode":"54935",
    "sg:province":"WI",
    "sg:tags":[
        "marketing"
    ],
    "wof:name":"Pinecrest Marketing",
    "wof:placetype":"venue"
},
  "geometry": {"coordinates":[-88.341527,43.740642],"type":"Point"}
}