{
  "type": "Feature",
  "properties": {
    "iso:country":"US",
    "sg:address":"314 N Main St",
    "sg:city":"Brillion",
    "sg:classifiers":[
        {
            "category":"Banks & Credit Unions",
            "subcategory":"Bank",
            "type":"Services"
        }
    ],
    "sg:phone":"+1 920 756 2186",
    "sg:postcode":"54110",
    "sg:province":"WI",
    "sg:tags":[
        "federal",
        "savings",
        "institution"
    ],
    "wof:name":"Bank Mutual",
    "wof:placetype":"venue"
},
  "geometry": {"coordinates":[-88.06430899999999,44.179037],"type":"Point"}
}