{
  "type": "Feature",
  "properties": {
    "iso:country":"US",
    "sg:address":"720 E Main St",
    "sg:city":"Omro",
    "sg:classifiers":[
        {
            "category":"Bars & Pubs",
            "type":"Food & Drink"
        }
    ],
    "sg:phone":"+1 920 685 5707",
    "sg:postcode":"54963",
    "sg:province":"WI",
    "sg:tags":[
        "drinking"
    ],
    "wof:name":"Dugout LLC",
    "wof:placetype":"venue"
},
  "geometry": {"coordinates":[-88.733578,44.039686],"type":"Point"}
}