{
  "type": "Feature",
  "properties": {
    "iso:country":"US",
    "sg:address":"13820 93rd Ave",
    "sg:city":"Chippewa Falls",
    "sg:classifiers":[
        {
            "category":"Freight",
            "type":"Transportation"
        }
    ],
    "sg:phone":"+1 715 720 6160",
    "sg:postcode":"54729",
    "sg:province":"WI",
    "sg:tags":[
        "operator",
        "trucking"
    ],
    "wof:name":"Paul H Sabaska Trucking",
    "wof:placetype":"venue"
},
  "geometry": {"coordinates":[-91.388954,44.979315],"type":"Point"}
}