{
  "type": "Feature",
  "properties": {
    "addr:full":"1922 145th St Balsam Lake WI 54810",
    "addr:housenumber":"1922",
    "addr:postcode":"54810",
    "addr:street":"145Th St",
    "iso:country":"US",
    "sg:address":"1922 145th St",
    "sg:city":"Balsam Lake",
    "sg:classifiers":[
        {
            "category":"Professional",
            "subcategory":"Business Services",
            "type":"Services"
        }
    ],
    "sg:phone":"+1 715 825 3715",
    "sg:postcode":"54810",
    "sg:province":"WI",
    "wof:name":"West Three Partnership",
    "wof:placetype":"venue"
},
  "geometry": {"coordinates":[-92.459834,45.485288],"type":"Point"}
}