{
  "type": "Feature",
  "properties": {
    "addr:full":"248 N Pine St Burlington WI 53105",
    "addr:housenumber":"248",
    "addr:postcode":"53105",
    "addr:street":"N Pine St",
    "iso:country":"US",
    "sg:address":"248 N Pine St",
    "sg:city":"Burlington",
    "sg:classifiers":[
        {
            "category":"Manufacturing",
            "subcategory":"Printing",
            "type":"Manufacturing & Wholesale Goods"
        }
    ],
    "sg:phone":"+1 262 763 2455",
    "sg:postcode":"53105",
    "sg:province":"WI",
    "sg:tags":[
        "newspaper"
    ],
    "wof:name":"Journal-Times",
    "wof:placetype":"venue"
},
  "geometry": {"coordinates":[-88.27485299999999,42.677605],"type":"Point"}
}