{
  "type": "Feature",
  "properties": {
    "iso:country":"US",
    "sg:address":"119 Tennyson St",
    "sg:city":"Potosi",
    "sg:classifiers":[
        {
            "category":"Government",
            "subcategory":"Office",
            "type":"Public Place"
        }
    ],
    "sg:phone":"+1 608 763 2746",
    "sg:postcode":"53820",
    "sg:province":"WI",
    "sg:tags":[
        "village"
    ],
    "wof:name":"Tennyson Village Clerk",
    "wof:placetype":"venue"
},
  "geometry": {"coordinates":[-90.688326,42.689315],"type":"Point"}
}