{
  "type": "Feature",
  "properties": {
    "addr:full":"2338 Harley Dr Fitchburg WI 53711",
    "addr:housenumber":"2338",
    "addr:postcode":"53711",
    "addr:street":"Harley Dr",
    "iso:country":"US",
    "sg:address":"2338 Harley Dr",
    "sg:city":"Fitchburg",
    "sg:classifiers":[
        {
            "category":"Retail",
            "subcategory":"Portrait Studio",
            "type":"Services"
        }
    ],
    "sg:phone":"+1 608 276 4020",
    "sg:postcode":"53711",
    "sg:province":"WI",
    "sg:tags":[
        "photographer"
    ],
    "wof:name":"Appleby Photography",
    "wof:placetype":"venue"
},
  "geometry": {"coordinates":[-89.4666,43.028457],"type":"Point"}
}