{
  "type": "Feature",
  "properties": {
    "iso:country":"US",
    "sg:address":"744 Eddy St",
    "sg:city":"Wisconsin Dells",
    "sg:classifiers":[
        {
            "category":"Bars & Pubs",
            "type":"Food & Drink"
        }
    ],
    "sg:phone":"+1 608 253 3073",
    "sg:postcode":"53965",
    "sg:province":"WI",
    "wof:name":"Sand Bar",
    "wof:placetype":"venue"
},
  "geometry": {"coordinates":[-89.77666499999999,43.627266],"type":"Point"}
}