{
  "type": "Feature",
  "properties": {
    "iso:country":"US",
    "sg:address":"810 E Grand Ave",
    "sg:city":"Beloit",
    "sg:classifiers":[
        {
            "category":"Professional",
            "subcategory":"Employment Agencies",
            "type":"Services"
        }
    ],
    "sg:phone":"+1 608 363 6540",
    "sg:postcode":"53511",
    "sg:province":"IL",
    "sg:tags":[
        "opportunity"
    ],
    "wof:name":"Job Express",
    "wof:placetype":"venue"
},
  "geometry": {"coordinates":[-89.028965,42.499559],"type":"Point"}
}