{
  "type": "Feature",
  "properties": {
    "iso:country":"US",
    "sg:address":"5473 Whittlesey Ave",
    "sg:city":"Medford",
    "sg:classifiers":[
        {
            "category":"Freight",
            "type":"Transportation"
        }
    ],
    "sg:phone":"+1 715 748 3008",
    "sg:postcode":"54451",
    "sg:province":"WI",
    "sg:tags":[
        "operator",
        "local",
        "trucking"
    ],
    "wof:name":"Kraemer Trucking Inc",
    "wof:placetype":"venue"
},
  "geometry": {"coordinates":[-90.326919,45.221769],"type":"Point"}
}