{
  "type": "Feature",
  "properties": {
    "addr:full":"907 Quincy St Sturgeon Bay WI 54235",
    "addr:housenumber":"907",
    "addr:postcode":"54235",
    "addr:street":"Quincy St",
    "iso:country":"US",
    "sg:address":"907 Quincy St",
    "sg:city":"Sturgeon Bay",
    "sg:classifiers":[
        {
            "category":"Shopping",
            "subcategory":"Computers & Home Electronics",
            "type":"Retail Goods"
        }
    ],
    "sg:phone":"+1 920 743 5320",
    "sg:postcode":"54235",
    "sg:province":"WI",
    "sg:tags":[
        "television",
        "radio"
    ],
    "wof:name":"Communication Specialists Inc",
    "wof:placetype":"venue"
},
  "geometry": {"coordinates":[-87.36892899999999,44.832131],"type":"Point"}
}