{
  "type": "Feature",
  "properties": {
    "iso:country":"US",
    "sg:address":"1089 Honey Creek Rd",
    "sg:city":"Oshkosh",
    "sg:classifiers":[
        {
            "category":"Arena",
            "subcategory":"Sports Club",
            "type":"Entertainment"
        }
    ],
    "sg:phone":"+1 920 231 3763",
    "sg:postcode":"54904",
    "sg:province":"WI",
    "wof:name":"Oshkosh Giants Inc",
    "wof:placetype":"venue"
},
  "geometry": {"coordinates":[-88.60997,44.029447],"type":"Point"}
}