{
  "type": "Feature",
  "properties": {
    "iso:country":"US",
    "sg:address":"8839 Wolf River Rd",
    "sg:city":"Fremont",
    "sg:classifiers":[
        {
            "category":"Travel",
            "subcategory":"Hotels & Motels",
            "type":"Entertainment"
        }
    ],
    "sg:phone":"+1 920 446 3874",
    "sg:postcode":"54940",
    "sg:province":"WI",
    "sg:tags":[
        "resort"
    ],
    "wof:name":"Secrets",
    "wof:placetype":"venue"
},
  "geometry": {"coordinates":[-88.832984,44.209667],"type":"Point"}
}