{
  "type": "Feature",
  "properties": {
    "iso:country":"US",
    "sg:address":"230 S Main St",
    "sg:city":"Jefferson",
    "sg:classifiers":[
        {
            "category":"Sports & Exercise",
            "subcategory":"Gym",
            "type":"Entertainment"
        }
    ],
    "sg:phone":"+1 920 674 2700",
    "sg:postcode":"53549",
    "sg:province":"WI",
    "sg:tags":[
        "facility",
        "club",
        "gymnasium",
        "health",
        "fitness",
        "studio",
        "physical"
    ],
    "wof:name":"Curves For Women",
    "wof:placetype":"venue"
},
  "geometry": {"coordinates":[-88.807241,43.003632],"type":"Point"}
}