{
  "type": "Feature",
  "properties": {
    "addr:full":"1046 18th St Cameron WI 54822",
    "addr:housenumber":"1046",
    "addr:postcode":"54822",
    "addr:street":"18Th St",
    "iso:country":"US",
    "sg:address":"1046 18th St",
    "sg:city":"Cameron",
    "sg:classifiers":[
        {
            "category":"Farming",
            "subcategory":"Farm",
            "type":"Manufacturing & Wholesale Goods"
        }
    ],
    "sg:phone":"+1 715 458 2358",
    "sg:postcode":"54822",
    "sg:province":"WI",
    "sg:tags":[
        "crop",
        "general"
    ],
    "wof:name":"James Anderson",
    "wof:placetype":"venue"
},
  "geometry": {"coordinates":[-91.787223,45.351484],"type":"Point"}
}