{
  "type": "Feature",
  "properties": {
    "iso:country":"US",
    "sg:address":"3543 Co Rd L",
    "sg:city":"Tomahawk",
    "sg:classifiers":[
        {
            "category":"Shopping",
            "subcategory":"Gifts & Souvenirs",
            "type":"Retail Goods"
        }
    ],
    "sg:phone":"+1 715 453 2113",
    "sg:postcode":"54487",
    "sg:province":"WI",
    "sg:tags":[
        "shop"
    ],
    "wof:name":"Cabin Crafts & Gifts",
    "wof:placetype":"venue"
},
  "geometry": {"coordinates":[-89.706104,45.62964],"type":"Point"}
}