{
  "type": "Feature",
  "properties": {
    "addr:full":"2425 16th St S La Crosse WI 54601",
    "addr:housenumber":"2425",
    "addr:postcode":"54601",
    "addr:street":"16Th St S",
    "iso:country":"US",
    "sg:address":"2425 16th St S",
    "sg:city":"La Crosse",
    "sg:classifiers":[
        {
            "category":"Building & Trades",
            "subcategory":"Electrical",
            "type":"Services"
        }
    ],
    "sg:phone":"+1 608 788 2553",
    "sg:postcode":"54601",
    "sg:province":"WI",
    "sg:tags":[
        "electric",
        "contractor"
    ],
    "wof:name":"Papenfuss Electric Inc Ofc",
    "wof:placetype":"venue"
},
  "geometry": {"coordinates":[-91.23186099999999,43.787193],"type":"Point"}
}