{
  "type": "Feature",
  "properties": {
    "iso:country":"US",
    "sg:address":"5101 Sarah Ln",
    "sg:city":"Middleton",
    "sg:classifiers":[
        {
            "category":"Wholesale",
            "subcategory":"Durable Goods & Equipment",
            "type":"Manufacturing & Wholesale Goods"
        }
    ],
    "sg:phone":"+1 608 236 4519",
    "sg:postcode":"53562",
    "sg:province":"WI",
    "sg:tags":[
        "representative",
        "manufacturer"
    ],
    "wof:name":"Youngone",
    "wof:placetype":"venue"
},
  "geometry": {"coordinates":[-89.46969199999999,43.111498],"type":"Point"}
}