{
  "type": "Feature",
  "properties": {
    "iso:country":"US",
    "sg:address":"961 S 29th St",
    "sg:city":"Manitowoc",
    "sg:classifiers":[
        {
            "category":"Farming",
            "subcategory":"Nursery",
            "type":"Manufacturing & Wholesale Goods"
        }
    ],
    "sg:phone":"+1 920 682 7711",
    "sg:postcode":"54220",
    "sg:province":"WI",
    "sg:tags":[
        "florist",
        "ornamental",
        "sup"
    ],
    "wof:name":"Roorbach Flowers Inc",
    "wof:placetype":"venue"
},
  "geometry": {"coordinates":[-87.684204,44.089734],"type":"Point"}
}