{
  "type": "Feature",
  "properties": {
    "iso:country":"US",
    "sg:address":"7269 Brick Church Rd",
    "sg:city":"Walworth",
    "sg:classifiers":[
        {
            "category":"Shopping",
            "subcategory":"Bicycles & Sporting Goods",
            "type":"Retail Goods"
        }
    ],
    "sg:phone":"+1 262 275 6596",
    "sg:postcode":"53184",
    "sg:province":"WI",
    "sg:tags":[
        "equipment",
        "golf",
        "supply"
    ],
    "wof:name":"Great White Golf Ball Co",
    "wof:placetype":"venue"
},
  "geometry": {"coordinates":[-88.656649,42.545642],"type":"Point"}
}