{
  "type": "Feature",
  "properties": {
    "iso:country":"US",
    "sg:address":"17035 W Wisconsin Ave",
    "sg:city":"Brookfield",
    "sg:classifiers":[
        {
            "category":"Professional",
            "subcategory":"Employment Agencies",
            "type":"Services"
        }
    ],
    "sg:phone":"+1 262 754 4800",
    "sg:postcode":"53005",
    "sg:province":"WI",
    "sg:tags":[
        "consultant",
        "search",
        "executive"
    ],
    "wof:name":"RPJ Assoc",
    "wof:placetype":"venue"
},
  "geometry": {"coordinates":[-88.124743,43.039543],"type":"Point"}
}