{
  "type": "Feature",
  "properties": {
    "iso:country":"US",
    "sg:address":"248 N 3rd Ave",
    "sg:city":"Stratford",
    "sg:classifiers":[
        {
            "category":"Insurance",
            "subcategory":"Insurance Agent",
            "type":"Services"
        }
    ],
    "sg:phone":"+1 715 687 2481",
    "sg:postcode":"54484",
    "sg:province":"WI",
    "wof:name":"Stratford Insurance",
    "wof:placetype":"venue"
},
  "geometry": {"coordinates":[-90.076314,44.802388],"type":"Point"}
}