{
  "type": "Feature",
  "properties": {
    "iso:country":"US",
    "sg:address":"155 S Main St",
    "sg:city":"Potosi",
    "sg:classifiers":[
        {
            "category":"Retail",
            "subcategory":"Auto Repair",
            "type":"Services"
        }
    ],
    "sg:phone":"+1 608 326 8349",
    "sg:postcode":"53820",
    "sg:province":"WI",
    "sg:tags":[
        "body"
    ],
    "wof:name":"Marquette Body Shop",
    "wof:placetype":"venue"
},
  "geometry": {"coordinates":[-90.719803,42.681851],"type":"Point"}
}