{
  "type": "Feature",
  "properties": {
    "iso:country":"US",
    "sg:address":"103 W Michigan St",
    "sg:city":"Milwaukee",
    "sg:classifiers":[
        {
            "category":"Professional",
            "subcategory":"Business Services",
            "type":"Services"
        }
    ],
    "sg:phone":"+1 414 908 6719",
    "sg:postcode":"53203",
    "sg:province":"WI",
    "wof:name":"Star Purchasing Inc",
    "wof:placetype":"venue"
},
  "geometry": {"coordinates":[-87.911148,43.03728],"type":"Point"}
}