{
  "type": "Feature",
  "properties": {
    "iso:country":"US",
    "sg:address":"102 E Main St",
    "sg:city":"Cobb",
    "sg:classifiers":[
        {
            "category":"Bars & Pubs",
            "type":"Food & Drink"
        }
    ],
    "sg:phone":"+1 608 623 3133",
    "sg:postcode":"53526",
    "sg:province":"WI",
    "sg:tags":[
        "drinking"
    ],
    "wof:name":"Chief's Fire Haus",
    "wof:placetype":"venue"
},
  "geometry": {"coordinates":[-90.329756,42.967434],"type":"Point"}
}