{
  "type": "Feature",
  "properties": {
    "addr:full":"4918 S 74th St Milwaukee WI 53220",
    "addr:housenumber":"4918",
    "addr:postcode":"53220",
    "addr:street":"S 74Th St",
    "iso:country":"US",
    "sg:address":"4918 S 74th St",
    "sg:city":"Milwaukee",
    "sg:classifiers":[
        {
            "category":"Restaurant",
            "type":"Food & Drink"
        }
    ],
    "sg:phone":"+1 414 281 9868",
    "sg:postcode":"53220",
    "sg:province":"WI",
    "wof:name":"Japanica",
    "wof:placetype":"venue"
},
  "geometry": {"coordinates":[-88.00621599999999,42.955251],"type":"Point"}
}