{
  "type": "Feature",
  "properties": {
    "iso:country":"US",
    "sg:address":"14010 Leetsbir Rd",
    "sg:city":"Sturtevant",
    "sg:classifiers":[
        {
            "category":"Building & Trades",
            "subcategory":"Construction",
            "type":"Services"
        },
        {
            "category":"Home & Garden",
            "subcategory":"Furniture",
            "type":"Retail Goods"
        }
    ],
    "sg:phone":"+1 262 321 0010",
    "sg:postcode":"53177",
    "sg:province":"WI",
    "sg:tags":[
        "carpentry",
        "top",
        "counter",
        "contractor"
    ],
    "wof:name":"Specialty Finishing Mfg Co",
    "wof:placetype":"venue"
},
  "geometry": {"coordinates":[-87.957624,42.707355],"type":"Point"}
}