{
  "type": "Feature",
  "properties": {
    "iso:country":"US",
    "sg:address":"1121 14th Ave E",
    "sg:city":"Menomonie",
    "sg:classifiers":[
        {
            "category":"Building & Trades",
            "subcategory":"Landscaping Services",
            "type":"Services"
        }
    ],
    "sg:phone":"+1 715 231 9675",
    "sg:postcode":"54751",
    "sg:province":"WI",
    "sg:tags":[
        "landscape",
        "contractor"
    ],
    "wof:name":"C Worth Landscaping",
    "wof:placetype":"venue"
},
  "geometry": {"coordinates":[-91.916915,44.870194],"type":"Point"}
}