{
  "type": "Feature",
  "properties": {
    "iso:country":"US",
    "sg:address":"204 Lincoln Ave",
    "sg:city":"Rio",
    "sg:classifiers":[
        {
            "category":"Insurance",
            "subcategory":"Insurance Agent",
            "type":"Services"
        }
    ],
    "sg:phone":"+1 920 992 3333",
    "sg:postcode":"53960",
    "sg:province":"WI",
    "wof:name":"Roberts-Hill Insurance",
    "wof:placetype":"venue"
},
  "geometry": {"coordinates":[-89.239103,43.448311],"type":"Point"}
}