{
  "type": "Feature",
  "properties": {
    "iso:country":"US",
    "sg:address":"1800 Innovation Way",
    "sg:city":"Hartford",
    "sg:classifiers":[
        {
            "category":"Manufacturing",
            "subcategory":"Metals",
            "type":"Manufacturing & Wholesale Goods"
        },
        {
            "category":"Banks & Credit Unions",
            "subcategory":"Investment Brokerage",
            "type":"Services"
        }
    ],
    "sg:phone":"+1 262 673 2700",
    "sg:postcode":"53027",
    "sg:province":"WI",
    "sg:tags":[
        "foundry",
        "casting"
    ],
    "sg:website":"http://www.signicast.com",
    "wof:name":"Signicast Investment Castings",
    "wof:placetype":"venue"
},
  "geometry": {"coordinates":[-88.416781,43.337038],"type":"Point"}
}