{
  "type": "Feature",
  "properties": {
    "addr:full":"3915 Gateway Dr Eau Claire WI 54701",
    "addr:housenumber":"3915",
    "addr:postcode":"54701",
    "addr:street":"Gateway Dr",
    "iso:country":"US",
    "sg:address":"3915 Gateway Dr",
    "sg:city":"Eau Claire",
    "sg:classifiers":[
        {
            "category":"Personal",
            "subcategory":"Beauty Salon",
            "type":"Services"
        }
    ],
    "sg:phone":"+1 715 836 9145",
    "sg:postcode":"54701",
    "sg:province":"WI",
    "sg:tags":[
        "shop"
    ],
    "wof:name":"Regal Nails",
    "wof:placetype":"venue"
},
  "geometry": {"coordinates":[-91.431738,44.776032],"type":"Point"}
}