{
  "type": "Feature",
  "properties": {
    "iso:country":"US",
    "sg:address":"7705 Lincoln Rd",
    "sg:city":"Pittsville",
    "sg:classifiers":[
        {
            "category":"Farming",
            "subcategory":"Dairy Farm",
            "type":"Manufacturing & Wholesale Goods"
        }
    ],
    "sg:phone":"+1 715 884 6831",
    "sg:postcode":"54466",
    "sg:province":"WI",
    "wof:name":"Emil Mundt",
    "wof:placetype":"venue"
},
  "geometry": {"coordinates":[-90.099804,44.438837],"type":"Point"}
}