{
  "type": "Feature",
  "properties": {
    "addr:full":"515 State St Madison WI 53703",
    "addr:housenumber":"515",
    "addr:postcode":"53703",
    "addr:street":"State St",
    "iso:country":"US",
    "sg:address":"515 State St",
    "sg:city":"Madison",
    "sg:classifiers":[
        {
            "category":"Cinema",
            "subcategory":"Movie Rental",
            "type":"Entertainment"
        }
    ],
    "sg:phone":"+1 608 251 4141",
    "sg:postcode":"53703",
    "sg:province":"WI",
    "sg:tags":[
        "video",
        "tape"
    ],
    "wof:name":"Blockbuster",
    "wof:placetype":"venue"
},
  "geometry": {"coordinates":[-89.394946,43.074771],"type":"Point"}
}