{
  "type": "Feature",
  "properties": {
    "addr:full":"2123 N 47th St Milwaukee WI 53208",
    "addr:housenumber":"2123",
    "addr:postcode":"53208",
    "addr:street":"N 47Th St",
    "iso:country":"US",
    "sg:address":"2123 N 47th St",
    "sg:city":"Milwaukee",
    "sg:classifiers":[
        {
            "category":"Local Transit",
            "type":"Transportation"
        }
    ],
    "sg:phone":"+1 414 447 8112",
    "sg:postcode":"53208",
    "sg:province":"WI",
    "sg:tags":[
        "public",
        "provider"
    ],
    "wof:name":"Turner Trans.",
    "wof:placetype":"venue"
},
  "geometry": {"coordinates":[-87.972382,43.057567],"type":"Point"}
}