{
  "type": "Feature",
  "properties": {
    "iso:country":"US",
    "sg:address":"7990 Dairy Ln",
    "sg:city":"Cross Plains",
    "sg:classifiers":[
        {
            "category":"Farming",
            "subcategory":"Farm",
            "type":"Manufacturing & Wholesale Goods"
        }
    ],
    "sg:phone":"+1 608 798 2511",
    "sg:postcode":"53528",
    "sg:province":"WI",
    "sg:tags":[
        "crop",
        "general"
    ],
    "wof:name":"Kevin Statz Farms",
    "wof:placetype":"venue"
},
  "geometry": {"coordinates":[-89.605747,43.175567],"type":"Point"}
}