{
  "type": "Feature",
  "properties": {
    "iso:country":"US",
    "sg:address":"1105 Western Ave",
    "sg:city":"Mosinee",
    "sg:classifiers":[
        {
            "category":"Banks & Credit Unions",
            "subcategory":"Bank",
            "type":"Services"
        }
    ],
    "sg:phone":"+1 715 693 3400",
    "sg:postcode":"54455",
    "sg:province":"WI",
    "sg:website":"www.valleycommunities.com",
    "wof:name":"Valley Communities CU",
    "wof:placetype":"venue"
},
  "geometry": {"coordinates":[-89.714876,44.789033],"type":"Point"}
}