{
  "type": "Feature",
  "properties": {
    "addr:full":"1070 River Rd Dresser WI 54009",
    "addr:housenumber":"1070",
    "addr:postcode":"54009",
    "addr:street":"River Rd",
    "iso:country":"US",
    "sg:address":"1070 River Rd",
    "sg:city":"Dresser",
    "sg:classifiers":[
        {
            "category":"Building & Trades",
            "subcategory":"Construction",
            "type":"Services"
        }
    ],
    "sg:phone":"+1 715 294 2450",
    "sg:postcode":"54009",
    "sg:province":"WI",
    "sg:tags":[
        "house"
    ],
    "wof:name":"Bear Stables",
    "wof:placetype":"venue"
},
  "geometry": {"coordinates":[-92.68025799999999,45.3627],"type":"Point"}
}