{
  "type": "Feature",
  "properties": {
    "iso:country":"US",
    "sg:address":"1421 Eastman Ave",
    "sg:city":"Green Bay",
    "sg:classifiers":[
        {
            "category":"Manufacturing",
            "subcategory":"Tools & Machinery",
            "type":"Manufacturing & Wholesale Goods"
        }
    ],
    "sg:phone":"+1 920 448 8000",
    "sg:postcode":"54302",
    "sg:province":"WI",
    "sg:tags":[
        "shop",
        "machine",
        "metalworking",
        "industrial",
        "mfg"
    ],
    "wof:name":"Renco Machine Co Inc",
    "wof:placetype":"venue"
},
  "geometry": {"coordinates":[-87.985567,44.517085],"type":"Point"}
}