{
  "type": "Feature",
  "properties": {
    "iso:country":"US",
    "sg:address":"3985 Co Hwy Nn",
    "sg:city":"Elkhorn",
    "sg:classifiers":[
        {
            "category":"Health Services",
            "subcategory":"Health Practitioner",
            "type":"Services"
        }
    ],
    "sg:phone":"+1 262 741 2147",
    "sg:postcode":"53121",
    "sg:province":"WI",
    "sg:tags":[
        "therapist",
        "physical"
    ],
    "wof:name":"Aurora Rehabilitation Svc",
    "wof:placetype":"venue"
},
  "geometry": {"coordinates":[-88.500172,42.662588],"type":"Point"}
}