{
  "type": "Feature",
  "properties": {
    "iso:country":"US",
    "sg:address":"524 Main St",
    "sg:city":"Racine",
    "sg:classifiers":[
        {
            "category":"Professional",
            "subcategory":"Employment Agencies",
            "type":"Services"
        }
    ],
    "sg:phone":"+1 262 632 9675",
    "sg:postcode":"53403",
    "sg:province":"WI",
    "sg:tags":[
        "opportunity"
    ],
    "wof:name":"Contemporary Medical Staffing",
    "wof:placetype":"venue"
},
  "geometry": {"coordinates":[-87.78293600000001,42.72744],"type":"Point"}
}