{
  "type": "Feature",
  "properties": {
    "iso:country":"US",
    "sg:address":"11033 Co Hwy C",
    "sg:city":"Bloomer",
    "sg:classifiers":[
        {
            "category":"Farming",
            "subcategory":"Poultry Farm",
            "type":"Manufacturing & Wholesale Goods"
        }
    ],
    "sg:phone":"+1 715 288 6065",
    "sg:postcode":"54724",
    "sg:province":"WI",
    "sg:tags":[
        "egg"
    ],
    "wof:name":"Roger Biesterveld",
    "wof:placetype":"venue"
},
  "geometry": {"coordinates":[-91.446788,45.016602],"type":"Point"}
}