{
  "type": "Feature",
  "properties": {
    "iso:country":"US",
    "sg:address":"801 Menasha Ave E",
    "sg:city":"Ladysmith",
    "sg:classifiers":[
        {
            "category":"Building & Trades",
            "subcategory":"Construction",
            "type":"Services"
        }
    ],
    "sg:phone":"+1 715 532 7575",
    "sg:postcode":"54848",
    "sg:province":"WI",
    "sg:tags":[
        "roofing",
        "contractor"
    ],
    "wof:name":"Leonhard Roofing LLC",
    "wof:placetype":"venue"
},
  "geometry": {"coordinates":[-91.091179,45.469183],"type":"Point"}
}