{
  "type": "Feature",
  "properties": {
    "addr:full":"3300 S Oneida St Appleton WI 54915",
    "addr:housenumber":"3300",
    "addr:postcode":"54915",
    "addr:street":"S Oneida St",
    "iso:country":"US",
    "sg:address":"3300 S Oneida St",
    "sg:city":"Appleton",
    "sg:classifiers":[
        {
            "category":"Restaurant",
            "type":"Food & Drink"
        }
    ],
    "sg:menulink":"http://www.allmenus.com/wi/appleton/195793-wendys/menu/",
    "sg:phone":"+1 920 830 0660",
    "sg:postcode":"54915",
    "sg:province":"WI",
    "sg:tags":[
        "burger",
        "american",
        "soup"
    ],
    "wof:name":"Wendy's",
    "wof:placetype":"venue"
},
  "geometry": {"coordinates":[-88.40402,44.238211],"type":"Point"}
}