{
  "type": "Feature",
  "properties": {
    "iso:country":"US",
    "sg:address":"3105 Schneider Rd",
    "sg:city":"Hilbert",
    "sg:classifiers":[
        {
            "category":"Utilities",
            "subcategory":"Refuse",
            "type":"Services"
        }
    ],
    "sg:phone":"+1 920 853 8553",
    "sg:postcode":"54129",
    "sg:province":"WI",
    "sg:tags":[
        "system"
    ],
    "wof:name":"Superior Hickory Meadows Landf",
    "wof:placetype":"venue"
},
  "geometry": {"coordinates":[-88.192584,44.109463],"type":"Point"}
}