{
  "type": "Feature",
  "properties": {
    "iso:country":"US",
    "sg:address":"1230 Broadway St S",
    "sg:city":"Menomonie",
    "sg:classifiers":[
        {
            "category":"Home & Garden",
            "subcategory":"Furniture",
            "type":"Retail Goods"
        }
    ],
    "sg:phone":"+1 715 235 5850",
    "sg:postcode":"54751",
    "sg:province":"WI",
    "wof:name":"Menomonie Home Furnishings",
    "wof:placetype":"venue"
},
  "geometry": {"coordinates":[-91.929688,44.871699],"type":"Point"}
}