{
  "type": "Feature",
  "properties": {
    "addr:full":"767 W Windlake Ave Milwaukee WI 53204",
    "addr:housenumber":"767",
    "addr:postcode":"53204",
    "addr:street":"W Windlake Ave",
    "iso:country":"US",
    "sg:address":"767 W Windlake Ave",
    "sg:city":"Milwaukee",
    "sg:classifiers":[
        {
            "category":"Building & Trades",
            "subcategory":"Electrical",
            "type":"Services"
        }
    ],
    "sg:phone":"+1 414 671 5487",
    "sg:postcode":"53204",
    "sg:province":"WI",
    "sg:tags":[
        "electrical",
        "contractor"
    ],
    "wof:name":"R C Electric",
    "wof:placetype":"venue"
},
  "geometry": {"coordinates":[-87.92108899999999,43.010733],"type":"Point"}
}