{
  "type": "Feature",
  "properties": {
    "iso:country":"US",
    "sg:address":"1500 W Main St",
    "sg:city":"Sun Prairie",
    "sg:classifiers":[
        {
            "category":"Building & Trades",
            "subcategory":"Construction",
            "type":"Services"
        }
    ],
    "sg:phone":"+1 608 256 2121",
    "sg:postcode":"53590",
    "sg:province":"WI",
    "sg:tags":[
        "contractor"
    ],
    "wof:name":"Voyager Builders",
    "wof:placetype":"venue"
},
  "geometry": {"coordinates":[-89.240083,43.17818],"type":"Point"}
}