{
  "type": "Feature",
  "properties": {
    "iso:country":"US",
    "sg:address":"6403 Hubbard Ave",
    "sg:city":"Middleton",
    "sg:classifiers":[
        {
            "category":"Health Services",
            "subcategory":"Doctor",
            "type":"Services"
        }
    ],
    "sg:phone":"+1 608 831 4010",
    "sg:postcode":"53562",
    "sg:province":"WI",
    "sg:tags":[
        "physician",
        "surgeon"
    ],
    "wof:name":"Jennifer A May MD",
    "wof:placetype":"venue"
},
  "geometry": {"coordinates":[-89.496103,43.093736],"type":"Point"}
}