{
  "type": "Feature",
  "properties": {
    "iso:country":"US",
    "sg:address":"5650 Parkridge Dr",
    "sg:city":"Racine",
    "sg:classifiers":[
        {
            "category":"Real Estate",
            "subcategory":"Surveying",
            "type":"Services"
        }
    ],
    "sg:phone":"+1 262 639 1130",
    "sg:postcode":"53402",
    "sg:province":"WI",
    "sg:tags":[
        "surveyor"
    ],
    "wof:name":"Heritage Engineering & Srvyng",
    "wof:placetype":"venue"
},
  "geometry": {"coordinates":[-87.848855,42.782553],"type":"Point"}
}