{
  "type": "Feature",
  "properties": {
    "addr:full":"7045 Aetna Ct Milwaukee WI 53213",
    "addr:postcode":"7045;53213",
    "addr:street":"Aetna Ct",
    "iso:country":"US",
    "sg:address":"7045 Aetna Ct",
    "sg:city":"Milwaukee",
    "sg:classifiers":[
        {
            "category":"Wholesale",
            "subcategory":"Wine & Distilled Alcoholic Beverages",
            "type":"Manufacturing & Wholesale Goods"
        }
    ],
    "sg:phone":"+1 414 774 8428",
    "sg:postcode":"53213",
    "sg:province":"WI",
    "wof:name":"Jansen International LLC",
    "wof:placetype":"venue"
},
  "geometry": {"coordinates":[-88.00184900000001,43.041445],"type":"Point"}
}