{
  "type": "Feature",
  "properties": {
    "iso:country":"US",
    "sg:address":"2900 Red Fox Run",
    "sg:city":"Portage",
    "sg:classifiers":[
        {
            "category":"Social Services",
            "subcategory":"Job Training",
            "type":"Services"
        }
    ],
    "sg:phone":"+1 608 742 5329",
    "sg:postcode":"53901",
    "sg:province":"WI",
    "sg:tags":[
        "residential",
        "care"
    ],
    "wof:name":"Renewal Unlimited Inc",
    "wof:placetype":"venue"
},
  "geometry": {"coordinates":[-89.465211,43.570442],"type":"Point"}
}