{
  "type": "Feature",
  "properties": {
    "iso:country":"US",
    "sg:address":"927 N Meridian St",
    "sg:city":"Curtiss",
    "sg:classifiers":[
        {
            "category":"Restaurant",
            "type":"Food & Drink"
        }
    ],
    "sg:phone":"+1 715 223 3864",
    "sg:postcode":"54422",
    "sg:province":"WI",
    "wof:name":"Molitors Old Saloon & Steakhs",
    "wof:placetype":"venue"
},
  "geometry": {"coordinates":[-90.43407999999999,44.953733],"type":"Point"}
}