{
  "type": "Feature",
  "properties": {
    "iso:country":"US",
    "sg:address":"3325 Clove Dr",
    "sg:city":"Madison",
    "sg:classifiers":[
        {
            "category":"Professional",
            "subcategory":"Art Services",
            "type":"Services"
        }
    ],
    "sg:phone":"+1 608 244 2864",
    "sg:postcode":"53704",
    "sg:province":"WI",
    "sg:tags":[
        "commercial",
        "design"
    ],
    "wof:name":"Da Design",
    "wof:placetype":"venue"
},
  "geometry": {"coordinates":[-89.31792799999999,43.141883],"type":"Point"}
}