{
  "type": "Feature",
  "properties": {
    "iso:country":"US",
    "sg:address":"5735 Co Hwy B",
    "sg:city":"Belgium",
    "sg:classifiers":[
        {
            "category":"Organizations",
            "subcategory":"Membership Organization",
            "type":"Services"
        }
    ],
    "sg:phone":"+1 262 376 8858",
    "sg:postcode":"53004",
    "sg:province":"WI",
    "sg:tags":[
        "athletic"
    ],
    "wof:name":"Red Line Hockey Inc",
    "wof:placetype":"venue"
},
  "geometry": {"coordinates":[-87.90070799999999,43.498298],"type":"Point"}
}