{
  "type": "Feature",
  "properties": {
    "iso:country":"US",
    "sg:address":"630 Co Rd I",
    "sg:city":"Wisconsin Dells",
    "sg:classifiers":[
        {
            "category":"Farming",
            "subcategory":"Farm",
            "type":"Manufacturing & Wholesale Goods"
        }
    ],
    "sg:phone":"+1 608 586 4253",
    "sg:postcode":"53965",
    "sg:province":"WI",
    "sg:tags":[
        "crop",
        "general"
    ],
    "wof:name":"Nichols Enterprises Inc",
    "wof:placetype":"venue"
},
  "geometry": {"coordinates":[-89.705488,43.749022],"type":"Point"}
}