{
  "type": "Feature",
  "properties": {
    "addr:full":"650 Court St Chilton WI 53014",
    "addr:housenumber":"650",
    "addr:postcode":"53014",
    "addr:street":"Court St",
    "iso:country":"US",
    "sg:address":"650 Court St",
    "sg:city":"Chilton",
    "sg:classifiers":[
        {
            "category":"Shopping",
            "type":"Retail Goods"
        }
    ],
    "sg:phone":"+1 920 849 9059",
    "sg:postcode":"53014",
    "sg:province":"WI",
    "sg:tags":[
        "merchandise"
    ],
    "wof:name":"S J Images",
    "wof:placetype":"venue"
},
  "geometry": {"coordinates":[-88.18026,44.0297],"type":"Point"}
}