{
  "type": "Feature",
  "properties": {
    "iso:country":"US",
    "sg:address":"1655 Rybicki Ln",
    "sg:city":"Rudolph",
    "sg:classifiers":[
        {
            "category":"Professional",
            "subcategory":"Business Services",
            "type":"Services"
        }
    ],
    "sg:phone":"+1 715 435 4282",
    "sg:postcode":"54475",
    "sg:province":"WI",
    "wof:name":"Riches Chainsaw Sales & Svcs",
    "wof:placetype":"venue"
},
  "geometry": {"coordinates":[-89.804902,44.49721],"type":"Point"}
}