{
  "type": "Feature",
  "properties": {
    "iso:country":"US",
    "sg:address":"7784 Co Rd M",
    "sg:city":"Coleman",
    "sg:classifiers":[
        {
            "category":"Farming",
            "subcategory":"Dairy Farm",
            "type":"Manufacturing & Wholesale Goods"
        }
    ],
    "sg:phone":"+1 920 829 5554",
    "sg:postcode":"54112",
    "sg:province":"WI",
    "wof:name":"Nicholas Kozlovsky",
    "wof:placetype":"venue"
},
  "geometry": {"coordinates":[-88.162844,45.010171],"type":"Point"}
}