{
  "type": "Feature",
  "properties": {
    "iso:country":"US",
    "sg:address":"109 W Bridge St",
    "sg:city":"Wausau",
    "sg:classifiers":[
        {
            "category":"Shopping",
            "subcategory":"Computers & Home Electronics",
            "type":"Retail Goods"
        }
    ],
    "sg:phone":"+1 715 845 2901",
    "sg:postcode":"54401",
    "sg:province":"WI",
    "sg:tags":[
        "high",
        "fidelity",
        "stereophonic"
    ],
    "wof:name":"X Treme Audio & Custom",
    "wof:placetype":"venue"
},
  "geometry": {"coordinates":[-89.63803299999999,44.97006],"type":"Point"}
}