{
  "type": "Feature",
  "properties": {
    "iso:country":"US",
    "sg:address":"220 E Chapel St",
    "sg:city":"Dodgeville",
    "sg:classifiers":[
        {
            "category":"Professional",
            "subcategory":"Lawyer & Legal Services",
            "type":"Services"
        }
    ],
    "sg:phone":"+1 608 935 9490",
    "sg:postcode":"53533",
    "sg:province":"WI",
    "sg:tags":[
        "attorney"
    ],
    "wof:name":"Frank Law Office",
    "wof:placetype":"venue"
},
  "geometry": {"coordinates":[-90.128739,42.96181],"type":"Point"}
}