{
  "type": "Feature",
  "properties": {
    "addr:full":"406 Main St Genoa WI 54632",
    "addr:housenumber":"406",
    "addr:postcode":"54632",
    "addr:street":"Main St",
    "iso:country":"US",
    "sg:address":"406 Main St",
    "sg:city":"Genoa",
    "sg:classifiers":[
        {
            "category":"Government",
            "subcategory":"Office",
            "type":"Public Place"
        }
    ],
    "sg:phone":"+1 608 689 2180",
    "sg:postcode":"54632",
    "sg:province":"WI",
    "sg:tags":[
        "village"
    ],
    "wof:name":"Genoa Village Shop",
    "wof:placetype":"venue"
},
  "geometry": {"coordinates":[-91.22483099999999,43.576406],"type":"Point"}
}