{
  "type": "Feature",
  "properties": {
    "addr:full":"626 Langdon St Madison WI 53703",
    "addr:housenumber":"626",
    "addr:postcode":"53703",
    "addr:street":"Langdon St",
    "iso:country":"US",
    "sg:address":"626 Langdon St",
    "sg:city":"Madison",
    "sg:classifiers":[
        {
            "category":"Real Estate",
            "subcategory":"Real Estate Operator",
            "type":"Services"
        }
    ],
    "sg:phone":"+1 608 255 6169",
    "sg:postcode":"53703",
    "sg:province":"WI",
    "sg:tags":[
        "apartment"
    ],
    "wof:name":"Round House Apartment Rentals",
    "wof:placetype":"venue"
},
  "geometry": {"coordinates":[-89.396942,43.075869],"type":"Point"}
}