{
  "type": "Feature",
  "properties": {
    "addr:full":"2800 Dam Rd Eagle River WI 54521",
    "addr:housenumber":"2800",
    "addr:postcode":"54521",
    "addr:street":"Dam Rd",
    "iso:country":"US",
    "sg:address":"2800 Dam Rd",
    "sg:city":"Eagle River",
    "sg:classifiers":[
        {
            "category":"Building & Trades",
            "subcategory":"Construction",
            "type":"Services"
        }
    ],
    "sg:phone":"+1 715 477 8885",
    "sg:postcode":"54521",
    "sg:province":"WI",
    "sg:tags":[
        "carpentry",
        "contractor"
    ],
    "wof:name":"Paul The Carpenter",
    "wof:placetype":"venue"
},
  "geometry": {"coordinates":[-89.11856299999999,45.90294],"type":"Point"}
}