{
  "type": "Feature",
  "properties": {
    "iso:country":"US",
    "sg:address":"6469 Viaduct Rd",
    "sg:city":"Dane",
    "sg:classifiers":[
        {
            "category":"Farming",
            "subcategory":"Dairy Farm",
            "type":"Manufacturing & Wholesale Goods"
        }
    ],
    "sg:phone":"+1 608 592 7505",
    "sg:postcode":"53529",
    "sg:province":"WI",
    "sg:tags":[
        "field",
        "crop"
    ],
    "wof:name":"D & K Dairy",
    "wof:placetype":"venue"
},
  "geometry": {"coordinates":[-89.489992,43.27754],"type":"Point"}
}