{
  "type": "Feature",
  "properties": {
    "iso:country":"US",
    "sg:address":"925 Co Rd Aa",
    "sg:city":"Nekoosa",
    "sg:classifiers":[
        {
            "category":"Organizations",
            "subcategory":"Professional Association",
            "type":"Services"
        }
    ],
    "sg:phone":"+1 715 886 4808",
    "sg:postcode":"54457",
    "sg:province":"WI",
    "wof:name":"Nekoosa Conservation Inc",
    "wof:placetype":"venue"
},
  "geometry": {"coordinates":[-89.892965,44.291794],"type":"Point"}
}