{
  "type": "Feature",
  "properties": {
    "iso:country":"US",
    "sg:address":"7657 R and W Townline Rd",
    "sg:city":"Whitewater",
    "sg:classifiers":[
        {
            "category":"Professional",
            "subcategory":"Engineering",
            "type":"Services"
        }
    ],
    "sg:phone":"+1 262 473 6735",
    "sg:postcode":"53190",
    "sg:province":"WI",
    "sg:tags":[
        "electrical",
        "electronic",
        "or",
        "mechanical"
    ],
    "wof:name":"J Dunstan Design Corp",
    "wof:placetype":"venue"
},
  "geometry": {"coordinates":[-88.676478,42.755776],"type":"Point"}
}