{
  "type": "Feature",
  "properties": {
    "iso:country":"US",
    "sg:address":"218 Market St",
    "sg:city":"Plainfield",
    "sg:classifiers":[
        {
            "category":"Freight",
            "type":"Transportation"
        }
    ],
    "sg:phone":"+1 715 335 4312",
    "sg:postcode":"54901",
    "sg:province":"WI",
    "sg:tags":[
        "storage"
    ],
    "wof:name":"Plainfield Mini-Storage",
    "wof:placetype":"venue"
},
  "geometry": {"coordinates":[-88.538696,44.01705],"type":"Point"}
}