{
  "type": "Feature",
  "properties": {
    "addr:full":"151 3rd St Baraboo WI 53913",
    "addr:housenumber":"151",
    "addr:postcode":"53913",
    "addr:street":"3Rd St",
    "iso:country":"US",
    "sg:address":"151 3rd St",
    "sg:city":"Baraboo",
    "sg:classifiers":[
        {
            "category":"Personal",
            "type":"Services"
        }
    ],
    "sg:phone":"+1 608 356 7773",
    "sg:postcode":"53913",
    "sg:province":"WI",
    "wof:name":"Rite Price Tattooing",
    "wof:placetype":"venue"
},
  "geometry": {"coordinates":[-89.741675,43.469983],"type":"Point"}
}