{
  "type": "Feature",
  "properties": {
    "iso:country":"US",
    "sg:address":"200 Cleveland St",
    "sg:city":"Nelson",
    "sg:classifiers":[
        {
            "category":"Government",
            "subcategory":"Post Office",
            "type":"Public Place"
        }
    ],
    "sg:phone":"+1 715 673 4025",
    "sg:postcode":"54756",
    "sg:province":"WI",
    "wof:name":"US Post Office",
    "wof:placetype":"venue"
},
  "geometry": {"coordinates":[-92.009455,44.42083],"type":"Point"}
}