{
  "type": "Feature",
  "properties": {
    "addr:full":"1901 State Hwy 16 Fall River WI 53932",
    "addr:housenumber":"1901",
    "addr:postcode":"53932",
    "addr:street":"State Hwy 16",
    "iso:country":"US",
    "sg:address":"1901 State Hwy 16",
    "sg:city":"Fall River",
    "sg:classifiers":[
        {
            "category":"Farming",
            "subcategory":"Livestock Farm",
            "type":"Manufacturing & Wholesale Goods"
        }
    ],
    "sg:phone":"+1 920 484 3618",
    "sg:postcode":"53932",
    "sg:province":"WI",
    "sg:tags":[
        "hog",
        "or",
        "feedlot"
    ],
    "wof:name":"Fountain Prairie Inn & Farms",
    "wof:placetype":"venue"
},
  "geometry": {"coordinates":[-89.096688,43.390224],"type":"Point"}
}