{
  "type": "Feature",
  "properties": {
    "iso:country":"US",
    "sg:address":"717 Main St W",
    "sg:city":"Ashland",
    "sg:classifiers":[
        {
            "category":"Bars & Pubs",
            "type":"Food & Drink"
        }
    ],
    "sg:phone":"+1 715 682 0649",
    "sg:postcode":"54806",
    "sg:province":"WI",
    "wof:name":"Scott & Ar's",
    "wof:placetype":"venue"
},
  "geometry": {"coordinates":[-90.890778,46.588205],"type":"Point"}
}