{
  "type": "Feature",
  "properties": {
    "iso:country":"US",
    "sg:address":"3659 S 5th Pl",
    "sg:city":"Milwaukee",
    "sg:classifiers":[
        {
            "category":"Shopping",
            "subcategory":"Gifts & Souvenirs",
            "type":"Retail Goods"
        }
    ],
    "sg:phone":"+1 414 481 8208",
    "sg:postcode":"53207",
    "sg:province":"WI",
    "wof:name":"Amvets Aux Dept Wisconsin",
    "wof:placetype":"venue"
},
  "geometry": {"coordinates":[-87.917962,42.977578],"type":"Point"}
}