{
  "type": "Feature",
  "properties": {
    "iso:country":"US",
    "sg:address":"8540 McHenry St",
    "sg:city":"Burlington",
    "sg:classifiers":[
        {
            "category":"Building & Trades",
            "subcategory":"Construction",
            "type":"Services"
        }
    ],
    "sg:phone":"+1 262 767 9438",
    "sg:postcode":"53105",
    "sg:province":"WI",
    "sg:tags":[
        "concrete",
        "contractor"
    ],
    "wof:name":"Kresken Concrete",
    "wof:placetype":"venue"
},
  "geometry": {"coordinates":[-88.303083,42.619049],"type":"Point"}
}