{
  "type": "Feature",
  "properties": {
    "iso:country":"US",
    "sg:address":"322 E 5th St",
    "sg:city":"Shawano",
    "sg:classifiers":[
        {
            "category":"Social Services",
            "type":"Services"
        }
    ],
    "sg:phone":"+1 715 524 8372",
    "sg:postcode":"54166",
    "sg:province":"WI",
    "wof:name":"Verbs Center",
    "wof:placetype":"venue"
},
  "geometry": {"coordinates":[-88.60536999999999,44.783189],"type":"Point"}
}