{
  "type": "Feature",
  "properties": {
    "iso:country":"US",
    "sg:address":"3903 Rib Mountain Dr",
    "sg:city":"Wausau",
    "sg:classifiers":[
        {
            "category":"Home & Garden",
            "subcategory":"Furniture",
            "type":"Retail Goods"
        }
    ],
    "sg:phone":"+1 715 241 9800",
    "sg:postcode":"54401",
    "sg:province":"WI",
    "sg:website":"www.slumberland.com",
    "wof:name":"Slumberland",
    "wof:placetype":"venue"
},
  "geometry": {"coordinates":[-89.652086,44.921145],"type":"Point"}
}