{
  "type": "Feature",
  "properties": {
    "addr:full":"600 Pine St Peshtigo WI 54157",
    "addr:housenumber":"600",
    "addr:postcode":"54157",
    "addr:street":"Pine St",
    "iso:country":"US",
    "sg:address":"600 Pine St",
    "sg:city":"Peshtigo",
    "sg:classifiers":[
        {
            "category":"Health Services",
            "subcategory":"Nursing And Care Facility",
            "type":"Services"
        }
    ],
    "sg:phone":"+1 715 582 9920",
    "sg:postcode":"54157",
    "sg:province":"WI",
    "sg:tags":[
        "home",
        "retirement",
        "community"
    ],
    "wof:name":"Marinette County Elderly Svc",
    "wof:placetype":"venue"
},
  "geometry": {"coordinates":[-87.735039,45.055001],"type":"Point"}
}