{
  "type": "Feature",
  "properties": {
    "iso:country":"US",
    "sg:address":"6388 Clover Rd",
    "sg:city":"Hartford",
    "sg:classifiers":[
        {
            "category":"Farming",
            "subcategory":"Farm",
            "type":"Manufacturing & Wholesale Goods"
        }
    ],
    "sg:phone":"+1 262 673 5035",
    "sg:postcode":"53027",
    "sg:province":"WI",
    "sg:tags":[
        "crop",
        "general"
    ],
    "wof:name":"Norman Beine",
    "wof:placetype":"venue"
},
  "geometry": {"coordinates":[-88.352053,43.339358],"type":"Point"}
}