{
  "type": "Feature",
  "properties": {
    "iso:country":"US",
    "sg:address":"8400 Woodview Dr",
    "sg:city":"Onalaska",
    "sg:classifiers":[
        {
            "category":"Building & Trades",
            "subcategory":"Construction",
            "type":"Services"
        }
    ],
    "sg:phone":"+1 608 782 8196",
    "sg:postcode":"54650",
    "sg:province":"WI",
    "sg:tags":[
        "house"
    ],
    "wof:name":"Favre Home Specialists",
    "wof:placetype":"venue"
},
  "geometry": {"coordinates":[-91.32234,43.942543],"type":"Point"}
}