{
  "type": "Feature",
  "properties": {
    "iso:country":"US",
    "sg:address":"635 Randolph St",
    "sg:city":"Mishicot",
    "sg:classifiers":[
        {
            "category":"Real Estate",
            "subcategory":"Real Estate Agent",
            "type":"Services"
        }
    ],
    "sg:phone":"+1 920 755 2262",
    "sg:postcode":"54228",
    "sg:province":"WI",
    "wof:name":"Krause Management Group LLC",
    "wof:placetype":"venue"
},
  "geometry": {"coordinates":[-87.63462699999999,44.240552],"type":"Point"}
}