{
  "type": "Feature",
  "properties": {
    "iso:country":"US",
    "sg:address":"3005 Post Rd",
    "sg:city":"Stevens Point",
    "sg:classifiers":[
        {
            "category":"Home & Garden",
            "subcategory":"Household Appliances",
            "type":"Retail Goods"
        }
    ],
    "sg:phone":"+1 715 344 2371",
    "sg:postcode":"54481",
    "sg:province":"WI",
    "sg:tags":[
        "machine",
        "sewing"
    ],
    "wof:name":"Hagen's Sew & Vac Ctr",
    "wof:placetype":"venue"
},
  "geometry": {"coordinates":[-89.549447,44.481798],"type":"Point"}
}