{
  "type": "Feature",
  "properties": {
    "iso:country":"US",
    "sg:address":"35353 Richter Rd",
    "sg:city":"Whitehall",
    "sg:classifiers":[
        {
            "category":"Professional",
            "subcategory":"Business Services",
            "type":"Services"
        }
    ],
    "sg:phone":"+1 715 538 4486",
    "sg:postcode":"54773",
    "sg:province":"WI",
    "wof:name":"Kc Ag Inc",
    "wof:placetype":"venue"
},
  "geometry": {"coordinates":[-91.306761,44.353964],"type":"Point"}
}