{
  "type": "Feature",
  "properties": {
    "iso:country":"US",
    "sg:address":"1930 Fieldcrest Ln",
    "sg:city":"Waukesha",
    "sg:classifiers":[
        {
            "category":"Manufacturing",
            "subcategory":"Lumber",
            "type":"Manufacturing & Wholesale Goods"
        }
    ],
    "sg:phone":"+1 262 549 0426",
    "sg:postcode":"53186",
    "sg:province":"WI",
    "sg:tags":[
        "research",
        "writing"
    ],
    "wof:name":"Matthew R Wallrath",
    "wof:placetype":"venue"
},
  "geometry": {"coordinates":[-88.197643,43.029936],"type":"Point"}
}