{
  "type": "Feature",
  "properties": {
    "iso:country":"US",
    "sg:address":"12601 E Mail Rd",
    "sg:city":"Gordon",
    "sg:classifiers":[
        {
            "category":"Bars & Pubs",
            "type":"Food & Drink"
        }
    ],
    "sg:phone":"+1 715 376 4481",
    "sg:postcode":"54838",
    "sg:province":"WI",
    "wof:name":"Log Hause",
    "wof:placetype":"venue"
},
  "geometry": {"coordinates":[-91.64533400000001,46.237105],"type":"Point"}
}