{
  "type": "Feature",
  "properties": {
    "iso:country":"US",
    "sg:address":"5034 6th Ave",
    "sg:city":"Kenosha",
    "sg:classifiers":[
        {
            "category":"Restaurant",
            "type":"Food & Drink"
        }
    ],
    "sg:phone":"+1 262 652 5446",
    "sg:postcode":"53140",
    "sg:province":"WI",
    "wof:name":"Oriental Inn",
    "wof:placetype":"venue"
},
  "geometry": {"coordinates":[-87.819654,42.589794],"type":"Point"}
}