{
  "type": "Feature",
  "properties": {
    "iso:country":"US",
    "sg:address":"232 State Hwy 57",
    "sg:city":"Sister Bay",
    "sg:classifiers":[
        {
            "category":"Travel",
            "subcategory":"Hotels & Motels",
            "type":"Entertainment"
        }
    ],
    "sg:phone":"+1 920 854 4242",
    "sg:postcode":"54234",
    "sg:province":"WI",
    "sg:tags":[
        "operation"
    ],
    "wof:name":"Voyager Inn",
    "wof:placetype":"venue"
},
  "geometry": {"coordinates":[-87.12332,45.185708],"type":"Point"}
}