{
  "type": "Feature",
  "properties": {
    "iso:country":"US",
    "sg:address":"1506 S Oneida St",
    "sg:city":"Appleton",
    "sg:classifiers":[
        {
            "category":"Health Services",
            "subcategory":"Doctor",
            "type":"Services"
        },
        {
            "category":"Health Services",
            "subcategory":"Medical Lab",
            "type":"Services"
        }
    ],
    "sg:phone":"+1 920 831 1200",
    "sg:postcode":"54915",
    "sg:province":"WI",
    "sg:tags":[
        "laboratory"
    ],
    "sg:website":"www.affinityhealth.org",
    "wof:name":"Affinity Health System Breast",
    "wof:placetype":"venue"
},
  "geometry": {"coordinates":[-88.40408100000001,44.230211],"type":"Point"}
}