{
  "type": "Feature",
  "properties": {
    "iso:country":"US",
    "sg:address":"1615 N 4th St",
    "sg:city":"Milwaukee",
    "sg:classifiers":[
        {
            "category":"Wholesale",
            "subcategory":"Plants",
            "type":"Manufacturing & Wholesale Goods"
        }
    ],
    "sg:phone":"+1 414 265 3746",
    "sg:postcode":"53212",
    "sg:province":"WI",
    "sg:tags":[
        "flower",
        "artificial"
    ],
    "wof:name":"Coles Floral Supplies Whl",
    "wof:placetype":"venue"
},
  "geometry": {"coordinates":[-87.915858,43.052362],"type":"Point"}
}