{
  "type": "Feature",
  "properties": {
    "addr:full":"1205 Sherman Ave Madison WI 53703",
    "addr:housenumber":"1205",
    "addr:postcode":"53703",
    "addr:street":"Sherman Ave",
    "iso:country":"US",
    "sg:address":"1205 Sherman Ave",
    "sg:city":"Madison",
    "sg:classifiers":[
        {
            "category":"Health Services",
            "subcategory":"Health Practitioner",
            "type":"Services"
        }
    ],
    "sg:phone":"+1 608 255 4203",
    "sg:postcode":"53703",
    "sg:province":"WI",
    "sg:tags":[
        "therapy",
        "physical"
    ],
    "wof:name":"Functional Therapy LLC",
    "wof:placetype":"venue"
},
  "geometry": {"coordinates":[-89.37355599999999,43.091255],"type":"Point"}
}