{
  "type": "Feature",
  "properties": {
    "iso:country":"US",
    "sg:address":"3138 Country Aire Dr",
    "sg:city":"Cedarburg",
    "sg:phone":"+1 262 377 5717",
    "sg:postcode":"53012",
    "sg:province":"WI",
    "sg:tags":[
        "farm",
        "soybean"
    ],
    "wof:name":"Kathleen Bublitz",
    "wof:placetype":"venue"
},
  "geometry": {"coordinates":[-88.082773,43.295246],"type":"Point"}
}