{
  "type": "Feature",
  "properties": {
    "iso:country":"US",
    "sg:address":"1405 Marinette Ave",
    "sg:city":"Marinette",
    "sg:classifiers":[
        {
            "category":"Insurance",
            "subcategory":"Insurance Agent",
            "type":"Services"
        }
    ],
    "sg:phone":"+1 715 732 4044",
    "sg:postcode":"54143",
    "sg:province":"WI",
    "wof:name":"Mattison Bruce Insurance",
    "wof:placetype":"venue"
},
  "geometry": {"coordinates":[-87.648219,45.091962],"type":"Point"}
}