{
  "type": "Feature",
  "properties": {
    "iso:country":"US",
    "sg:address":"3167 S Clement Ave",
    "sg:city":"Milwaukee",
    "sg:classifiers":[
        {
            "category":"Professional",
            "subcategory":"Business Services",
            "type":"Services"
        }
    ],
    "sg:phone":"+1 414 744 8482",
    "sg:postcode":"53207",
    "sg:province":"WI",
    "wof:name":"Make Ready LLC",
    "wof:placetype":"venue"
},
  "geometry": {"coordinates":[-87.894414,42.987664],"type":"Point"}
}