{
  "type": "Feature",
  "properties": {
    "iso:country":"US",
    "sg:address":"9225 Durand Ave",
    "sg:city":"Sturtevant",
    "sg:classifiers":[
        {
            "category":"Restaurant",
            "type":"Food & Drink"
        }
    ],
    "sg:phone":"+1 262 886 6886",
    "sg:postcode":"53177",
    "sg:province":"WI",
    "wof:name":"Muto's Pizzeria",
    "wof:placetype":"venue"
},
  "geometry": {"coordinates":[-87.89825999999999,42.697935],"type":"Point"}
}