{
  "type": "Feature",
  "properties": {
    "iso:country":"US",
    "sg:address":"2929 N Richmond St",
    "sg:city":"Appleton",
    "sg:classifiers":[
        {
            "category":"Shopping",
            "subcategory":"Computers & Home Electronics",
            "type":"Retail Goods"
        }
    ],
    "sg:phone":"+1 920 832 8292",
    "sg:postcode":"54911",
    "sg:province":"WI",
    "wof:name":"Video Gamestar",
    "wof:placetype":"venue"
},
  "geometry": {"coordinates":[-88.41579,44.28936],"type":"Point"}
}