{
  "type": "Feature",
  "properties": {
    "iso:country":"US",
    "sg:address":"2410 S 76th St",
    "sg:city":"Milwaukee",
    "sg:classifiers":[
        {
            "category":"Retail",
            "subcategory":"Auto Repair",
            "type":"Services"
        }
    ],
    "sg:phone":"+1 414 541 1382",
    "sg:postcode":"53219",
    "sg:province":"WI",
    "sg:tags":[
        "automotive",
        "tune"
    ],
    "wof:name":"Wills Fast Fords",
    "wof:placetype":"venue"
},
  "geometry": {"coordinates":[-88.007479,43.000793],"type":"Point"}
}