{
  "type": "Feature",
  "properties": {
    "iso:country":"US",
    "sg:address":"3858 E Flambeau Rd",
    "sg:city":"Bonduel",
    "sg:classifiers":[
        {
            "category":"Wholesale",
            "subcategory":"Farm Supplies",
            "type":"Manufacturing & Wholesale Goods"
        }
    ],
    "sg:phone":"+1 715 758 6380",
    "sg:postcode":"54107",
    "sg:province":"WI",
    "sg:tags":[
        "buyer",
        "livestock"
    ],
    "wof:name":"Hillcrest Farms",
    "wof:placetype":"venue"
},
  "geometry": {"coordinates":[-88.434342,44.749028],"type":"Point"}
}