{
  "type": "Feature",
  "properties": {
    "iso:country":"US",
    "sg:address":"2331 Lake Shore Rd",
    "sg:city":"Grafton",
    "sg:classifiers":[
        {
            "category":"Farming",
            "subcategory":"Livestock Farm",
            "type":"Manufacturing & Wholesale Goods"
        }
    ],
    "sg:phone":"+1 262 284 2938",
    "sg:postcode":"53024",
    "sg:province":"WI",
    "sg:tags":[
        "horse",
        "boards"
    ],
    "wof:name":"Flying S Ranch",
    "wof:placetype":"venue"
},
  "geometry": {"coordinates":[-87.88558,43.360266],"type":"Point"}
}