{
  "type": "Feature",
  "properties": {
    "iso:country":"US",
    "sg:address":"2880 Roosevelt Rd",
    "sg:city":"Marinette",
    "sg:classifiers":[
        {
            "category":"Communications",
            "subcategory":"Radio Station",
            "type":"Services"
        }
    ],
    "sg:phone":"+1 715 735 6631",
    "sg:postcode":"54143",
    "sg:province":"WI",
    "wof:name":"Wlst-FM",
    "wof:placetype":"venue"
},
  "geometry": {"coordinates":[-87.658539,45.057323],"type":"Point"}
}