{
  "type": "Feature",
  "properties": {
    "iso:country":"US",
    "sg:address":"4455 W Bradley Rd",
    "sg:city":"Milwaukee",
    "sg:classifiers":[
        {
            "category":"Health Services",
            "subcategory":"Doctor",
            "type":"Services"
        }
    ],
    "sg:phone":"+1 414 354 2240",
    "sg:postcode":"53223",
    "sg:province":"WI",
    "sg:tags":[
        "physician",
        "surgeon"
    ],
    "wof:name":"Milwaukee Foot Specialists",
    "wof:placetype":"venue"
},
  "geometry": {"coordinates":[-87.968014,43.163062],"type":"Point"}
}