{
  "type": "Feature",
  "properties": {
    "iso:country":"US",
    "sg:address":"9711 US Hwy 12",
    "sg:city":"Prairie Du Sac",
    "sg:classifiers":[
        {
            "category":"Wholesale",
            "subcategory":"Machinery & Supplies",
            "type":"Manufacturing & Wholesale Goods"
        }
    ],
    "sg:phone":"+1 608 643 3307",
    "sg:postcode":"53578",
    "sg:province":"WI",
    "sg:tags":[
        "contractor"
    ],
    "wof:name":"Mid State Eqpt Sauk Prairie",
    "wof:placetype":"venue"
},
  "geometry": {"coordinates":[-89.759138,43.297549],"type":"Point"}
}