{
  "type": "Feature",
  "properties": {
    "iso:country":"US",
    "sg:address":"6427 N Tichigan Rd",
    "sg:city":"Waterford",
    "sg:classifiers":[
        {
            "category":"Restaurant",
            "type":"Food & Drink"
        }
    ],
    "sg:phone":"+1 262 662 3122",
    "sg:postcode":"53185",
    "sg:province":"WI",
    "sg:tags":[
        "eating"
    ],
    "wof:name":"Jolly's On Harwood",
    "wof:placetype":"venue"
},
  "geometry": {"coordinates":[-88.218584,42.806208],"type":"Point"}
}