{
  "type": "Feature",
  "properties": {
    "addr:full":"6705 Rickyval St Schofield WI 54476",
    "addr:housenumber":"6705",
    "addr:postcode":"54476",
    "addr:street":"Rickyval St",
    "iso:country":"US",
    "sg:address":"6705 Rickyval St",
    "sg:city":"Schofield",
    "sg:classifiers":[
        {
            "category":"Building & Trades",
            "subcategory":"Construction",
            "type":"Services"
        }
    ],
    "sg:phone":"+1 715 241 9017",
    "sg:postcode":"54476",
    "sg:province":"WI",
    "sg:tags":[
        "fabricator",
        "metal"
    ],
    "wof:name":"ADJ Inc",
    "wof:placetype":"venue"
},
  "geometry": {"coordinates":[-89.526579,44.89604],"type":"Point"}
}