{
  "type": "Feature",
  "properties": {
    "iso:country":"US",
    "sg:address":"14858 W Arrowhead Ln",
    "sg:city":"New Berlin",
    "sg:classifiers":[
        {
            "category":"Shopping",
            "type":"Retail Goods"
        },
        {
            "category":"Shopping",
            "subcategory":"Beauty & Cosmetics",
            "type":"Retail Goods"
        }
    ],
    "sg:phone":"+1 262 789 8729",
    "sg:postcode":"53151",
    "sg:province":"WI",
    "sg:tags":[
        "merchandise",
        "perfume"
    ],
    "wof:name":"L'Bri Health & Beauty",
    "wof:placetype":"venue"
},
  "geometry": {"coordinates":[-88.100955,42.959378],"type":"Point"}
}