{
  "type": "Feature",
  "properties": {
    "iso:country":"US",
    "sg:address":"119 Belknap St",
    "sg:city":"Superior",
    "sg:classifiers":[
        {
            "category":"Health Services",
            "subcategory":"Doctor",
            "type":"Services"
        }
    ],
    "sg:phone":"+1 715 392 5131",
    "sg:postcode":"54880",
    "sg:province":"WI",
    "sg:tags":[
        "medical"
    ],
    "wof:name":"Ronald K Scott DDS",
    "wof:placetype":"venue"
},
  "geometry": {"coordinates":[-92.081113,46.720646],"type":"Point"}
}