{
  "type": "Feature",
  "properties": {
    "iso:country":"US",
    "sg:address":"1656 Crestwood Rd",
    "sg:city":"Antigo",
    "sg:classifiers":[
        {
            "category":"Shopping",
            "subcategory":"Bicycles & Sporting Goods",
            "type":"Retail Goods"
        }
    ],
    "sg:phone":"+1 715 627 4648",
    "sg:postcode":"54409",
    "sg:province":"WI",
    "sg:tags":[
        "bait",
        "fishing"
    ],
    "wof:name":"Ja-Da Bait",
    "wof:placetype":"venue"
},
  "geometry": {"coordinates":[-89.063737,45.09841],"type":"Point"}
}