{
  "type": "Feature",
  "properties": {
    "iso:country":"US",
    "sg:address":"222 Linnerud Dr",
    "sg:city":"Sun Prairie",
    "sg:classifiers":[
        {
            "category":"Building & Trades",
            "subcategory":"Plumbing",
            "type":"Services"
        }
    ],
    "sg:phone":"+1 608 837 9367",
    "sg:postcode":"53590",
    "sg:province":"WI",
    "sg:tags":[
        "air",
        "heating",
        "conditioning",
        "contractor"
    ],
    "wof:name":"Cardinal Heating & Air Cond",
    "wof:placetype":"venue"
},
  "geometry": {"coordinates":[-89.21642199999999,43.178004],"type":"Point"}
}