{
  "type": "Feature",
  "properties": {
    "iso:country":"US",
    "sg:address":"2030 E Kenmore Pl",
    "sg:city":"Milwaukee",
    "sg:classifiers":[
        {
            "category":"Building & Trades",
            "subcategory":"Construction",
            "type":"Services"
        }
    ],
    "sg:phone":"+1 414 961 7382",
    "sg:postcode":"53211",
    "sg:province":"WI",
    "sg:tags":[
        "hanging",
        "contractor"
    ],
    "wof:name":"Valid Victorian PTG",
    "wof:placetype":"venue"
},
  "geometry": {"coordinates":[-87.882785,43.090994],"type":"Point"}
}