{
  "type": "Feature",
  "properties": {
    "iso:country":"US",
    "sg:address":"1111 Langlade Rd",
    "sg:city":"Antigo",
    "sg:classifiers":[
        {
            "category":"Health Services",
            "subcategory":"Health Practitioner",
            "type":"Services"
        }
    ],
    "sg:phone":"+1 715 627 2663",
    "sg:postcode":"54409",
    "sg:province":"WI",
    "sg:tags":[
        "audiologists"
    ],
    "wof:name":"Hearing Clinic",
    "wof:placetype":"venue"
},
  "geometry": {"coordinates":[-89.135934,45.145357],"type":"Point"}
}