{
  "type": "Feature",
  "properties": {
    "iso:country":"US",
    "sg:address":"2534 W Wisconsin Ave",
    "sg:city":"Milwaukee",
    "sg:classifiers":[
        {
            "category":"Professional",
            "subcategory":"Accounting & Tax Preparation",
            "type":"Services"
        },
        {
            "category":"Banks & Credit Unions",
            "subcategory":"Bank",
            "type":"Services"
        }
    ],
    "sg:phone":"+1 414 342 4064",
    "sg:postcode":"53233",
    "sg:province":"WI",
    "sg:tags":[
        "cashing",
        "return",
        "check",
        "filing"
    ],
    "wof:name":"Cashland Check Cashing Corp",
    "wof:placetype":"venue"
},
  "geometry": {"coordinates":[-87.94588,43.03877],"type":"Point"}
}