{
  "type": "Feature",
  "properties": {
    "iso:country":"US",
    "sg:address":"1219 Hammond Ave",
    "sg:city":"Superior",
    "sg:classifiers":[
        {
            "category":"Professional",
            "subcategory":"Computer Services",
            "type":"Services"
        }
    ],
    "sg:phone":"+1 715 394 6896",
    "sg:postcode":"54880",
    "sg:province":"WI",
    "sg:tags":[
        "programing",
        "related",
        "custom"
    ],
    "wof:name":"Twin Ports Computer Consulting",
    "wof:placetype":"venue"
},
  "geometry": {"coordinates":[-92.097936,46.723305],"type":"Point"}
}