{
  "type": "Feature",
  "properties": {
    "addr:full":"1612 S Golf Glen Madison WI 53704",
    "addr:housenumber":"1612",
    "addr:postcode":"53704",
    "addr:street":"S Golf Glen",
    "iso:country":"US",
    "sg:address":"1612 S Golf Glen",
    "sg:city":"Madison",
    "sg:classifiers":[
        {
            "category":"Recreation",
            "type":"Entertainment"
        }
    ],
    "sg:phone":"+1 608 242 8673",
    "sg:postcode":"53704",
    "sg:province":"WI",
    "sg:tags":[
        "parks"
    ],
    "wof:name":"Cherokee Park Inc",
    "wof:placetype":"venue"
},
  "geometry": {"coordinates":[-89.36394300000001,43.148422],"type":"Point"}
}