{
  "type": "Feature",
  "properties": {
    "iso:country":"US",
    "sg:address":"543 A J Allen Cir",
    "sg:city":"Wales",
    "sg:classifiers":[
        {
            "category":"Education",
            "subcategory":"Dance Studio",
            "type":"Public Place"
        }
    ],
    "sg:phone":"+1 262 968 1820",
    "sg:postcode":"53183",
    "sg:province":"WI",
    "wof:name":"Studio One Dance Company",
    "wof:placetype":"venue"
},
  "geometry": {"coordinates":[-88.37572,43.016554],"type":"Point"}
}