{
  "type": "Feature",
  "properties": {
    "iso:country":"US",
    "sg:address":"1002 N 11th St",
    "sg:city":"Superior",
    "sg:classifiers":[
        {
            "category":"Real Estate",
            "subcategory":"Real Estate Operator",
            "type":"Services"
        }
    ],
    "sg:phone":"+1 715 392 6445",
    "sg:postcode":"54880",
    "sg:province":"WI",
    "sg:tags":[
        "apartment"
    ],
    "wof:name":"Superior Townhouses",
    "wof:placetype":"venue"
},
  "geometry": {"coordinates":[-92.09336,46.725308],"type":"Point"}
}