{
  "type": "Feature",
  "properties": {
    "addr:full":"915 Nelson Dr Rice Lake WI 54868",
    "addr:housenumber":"915",
    "addr:postcode":"54868",
    "addr:street":"Nelson Dr",
    "iso:country":"US",
    "sg:address":"915 Nelson Dr",
    "sg:city":"Rice Lake",
    "sg:classifiers":[
        {
            "category":"Building & Trades",
            "subcategory":"Construction",
            "type":"Services"
        }
    ],
    "sg:phone":"+1 715 234 4705",
    "sg:postcode":"54868",
    "sg:province":"WI",
    "sg:tags":[
        "general",
        "contractor"
    ],
    "wof:name":"Svacina Construction",
    "wof:placetype":"venue"
},
  "geometry": {"coordinates":[-91.72154,45.490283],"type":"Point"}
}