{
  "type": "Feature",
  "properties": {
    "iso:country":"US",
    "sg:address":"620 17th Ave",
    "sg:city":"Monroe",
    "sg:classifiers":[
        {
            "category":"Building & Trades",
            "subcategory":"Construction",
            "type":"Services"
        }
    ],
    "sg:phone":"+1 608 328 2174",
    "sg:postcode":"53566",
    "sg:province":"WI",
    "sg:tags":[
        "concrete",
        "contractor"
    ],
    "wof:name":"Rufenacht Concrete",
    "wof:placetype":"venue"
},
  "geometry": {"coordinates":[-89.638419,42.606075],"type":"Point"}
}