{
  "type": "Feature",
  "properties": {
    "iso:country":"US",
    "sg:address":"6446 Emery Ansorge Rd",
    "sg:city":"Cecil",
    "sg:classifiers":[
        {
            "category":"Professional",
            "subcategory":"Detective & Security Services",
            "type":"Services"
        }
    ],
    "sg:phone":"+1 715 325 5016",
    "sg:postcode":"54111",
    "sg:province":"WI",
    "sg:tags":[
        "car"
    ],
    "wof:name":"14th Armored Division Assoc",
    "wof:placetype":"venue"
},
  "geometry": {"coordinates":[-88.473348,44.823837],"type":"Point"}
}