{
  "type": "Feature",
  "properties": {
    "iso:country":"US",
    "sg:address":"940 Maritime Dr",
    "sg:city":"Manitowoc",
    "sg:classifiers":[
        {
            "category":"Insurance",
            "subcategory":"Insurance Agent",
            "type":"Services"
        }
    ],
    "sg:phone":"+1 920 682 8410",
    "sg:postcode":"54220",
    "sg:province":"WI",
    "wof:name":"New England Financial",
    "wof:placetype":"venue"
},
  "geometry": {"coordinates":[-87.644159,44.107188],"type":"Point"}
}