{
  "type": "Feature",
  "properties": {
    "addr:full":"470 N Main St Cottage Grove WI 53527",
    "addr:housenumber":"470",
    "addr:postcode":"53527",
    "addr:street":"N Main St",
    "iso:country":"US",
    "sg:address":"470 N Main St",
    "sg:city":"Cottage Grove",
    "sg:classifiers":[
        {
            "category":"Education",
            "subcategory":"School",
            "type":"Public Place"
        }
    ],
    "sg:phone":"+1 608 839 4576",
    "sg:postcode":"53527",
    "sg:province":"WI",
    "wof:name":"Cottage Grove Elementary Schl",
    "wof:placetype":"venue"
},
  "geometry": {"coordinates":[-89.199522,43.082791],"type":"Point"}
}