{
  "type": "Feature",
  "properties": {
    "iso:country":"US",
    "sg:address":"10696 E Harmony Dr",
    "sg:city":"Lodi",
    "sg:classifiers":[
        {
            "category":"Professional",
            "subcategory":"Accounting & Tax Preparation",
            "type":"Services"
        }
    ],
    "sg:phone":"+1 608 592 4971",
    "sg:postcode":"53555",
    "sg:province":"WI",
    "wof:name":"Healthclaims Solutions LLC",
    "wof:placetype":"venue"
},
  "geometry": {"coordinates":[-89.52900200000001,43.372947],"type":"Point"}
}