{
  "type": "Feature",
  "properties": {
    "iso:country":"US",
    "sg:address":"15506 State Hwy 27",
    "sg:city":"Cadott",
    "sg:classifiers":[
        {
            "category":"Bars & Pubs",
            "type":"Food & Drink"
        }
    ],
    "sg:phone":"+1 715 289 3631",
    "sg:postcode":"54727",
    "sg:province":"WI",
    "wof:name":"Reilly's Crescent Tavern",
    "wof:placetype":"venue"
},
  "geometry": {"coordinates":[-91.14691999999999,45.077844],"type":"Point"}
}