{
  "type": "Feature",
  "properties": {
    "iso:country":"US",
    "sg:address":"2025 Moreland Dr",
    "sg:city":"Janesville",
    "sg:classifiers":[
        {
            "category":"Manufacturing",
            "subcategory":"Printing",
            "type":"Manufacturing & Wholesale Goods"
        }
    ],
    "sg:phone":"+1 608 743 2856",
    "sg:postcode":"53548",
    "sg:province":"WI",
    "sg:tags":[
        "newspaper"
    ],
    "wof:name":"Kids & Parents Magazine",
    "wof:placetype":"venue"
},
  "geometry": {"coordinates":[-89.045917,42.699619],"type":"Point"}
}