{
  "type": "Feature",
  "properties": {
    "iso:country":"US",
    "sg:address":"1207 W Knapp St",
    "sg:city":"Rice Lake",
    "sg:classifiers":[
        {
            "category":"Professional",
            "subcategory":"Business Services",
            "type":"Services"
        }
    ],
    "sg:phone":"+1 715 234 2040",
    "sg:postcode":"54868",
    "sg:province":"WI",
    "wof:name":"Hazlewoods Auctn Svc & Realty",
    "wof:placetype":"venue"
},
  "geometry": {"coordinates":[-91.755464,45.509269],"type":"Point"}
}