{
  "type": "Feature",
  "properties": {
    "iso:country":"US",
    "sg:address":"320 S Main St",
    "sg:city":"Greenwood",
    "sg:classifiers":[
        {
            "category":"Freight",
            "type":"Transportation"
        }
    ],
    "sg:phone":"+1 715 267 6091",
    "sg:postcode":"54437",
    "sg:province":"WI",
    "sg:tags":[
        "trucking"
    ],
    "wof:name":"Greenwood Transport",
    "wof:placetype":"venue"
},
  "geometry": {"coordinates":[-90.598073,44.76465],"type":"Point"}
}