{
  "type": "Feature",
  "properties": {
    "iso:country":"US",
    "sg:address":"3861 Leonard Rd",
    "sg:city":"Wisconsin Rapids",
    "sg:classifiers":[
        {
            "category":"Professional",
            "subcategory":"Computer Services",
            "type":"Services"
        }
    ],
    "sg:phone":"+1 715 421 1920",
    "sg:postcode":"54495",
    "sg:province":"WI",
    "sg:tags":[
        "software"
    ],
    "sg:website":"www.minecamp.com",
    "wof:name":"Mine Camp Software",
    "wof:placetype":"venue"
},
  "geometry": {"coordinates":[-89.87047099999999,44.385824],"type":"Point"}
}