{
  "type": "Feature",
  "properties": {
    "addr:full":"121 Division St Mauston WI 53948",
    "addr:housenumber":"121",
    "addr:postcode":"53948",
    "addr:street":"Division St",
    "iso:country":"US",
    "sg:address":"121 Division St",
    "sg:city":"Mauston",
    "sg:classifiers":[
        {
            "category":"Building & Trades",
            "subcategory":"Construction",
            "type":"Services"
        }
    ],
    "sg:phone":"+1 608 847 5687",
    "sg:postcode":"53948",
    "sg:province":"WI",
    "sg:tags":[
        "dry wall",
        "contractor"
    ],
    "wof:name":"Drywall Doctors LLC",
    "wof:placetype":"venue"
},
  "geometry": {"coordinates":[-90.077187,43.797221],"type":"Point"}
}