{
  "type": "Feature",
  "properties": {
    "iso:country":"US",
    "sg:address":"6606 Jacobs Way",
    "sg:city":"Madison",
    "sg:classifiers":[
        {
            "category":"Restaurant",
            "type":"Food & Drink"
        }
    ],
    "sg:phone":"+1 608 831 3773",
    "sg:postcode":"53711",
    "sg:province":"WI",
    "sg:tags":[
        "eating"
    ],
    "wof:name":"Old Town Inn",
    "wof:placetype":"venue"
},
  "geometry": {"coordinates":[-89.494053,43.03672],"type":"Point"}
}