{
  "type": "Feature",
  "properties": {
    "iso:country":"US",
    "sg:address":"3115 S Gothic Cir",
    "sg:city":"Green Bay",
    "sg:classifiers":[
        {
            "category":"Professional",
            "subcategory":"Management & Consulting",
            "type":"Services"
        }
    ],
    "sg:phone":"+1 920 405 8670",
    "sg:postcode":"54313",
    "sg:province":"WI",
    "sg:tags":[
        "retail",
        "sales"
    ],
    "wof:name":"Dynamic Home Concepts",
    "wof:placetype":"venue"
},
  "geometry": {"coordinates":[-88.126367,44.511856],"type":"Point"}
}