{
  "type": "Feature",
  "properties": {
    "iso:country":"US",
    "sg:address":"6305 Hornby Hollow Rd",
    "sg:city":"Viroqua",
    "sg:classifiers":[
        {
            "category":"Building & Trades",
            "subcategory":"Plumbing",
            "type":"Services"
        }
    ],
    "sg:phone":"+1 608 637 3325",
    "sg:postcode":"54665",
    "sg:province":"WI",
    "sg:tags":[
        "heating",
        "contractor"
    ],
    "wof:name":"Furnace Room",
    "wof:placetype":"venue"
},
  "geometry": {"coordinates":[-90.92325099999999,43.486584],"type":"Point"}
}