{
  "type": "Feature",
  "properties": {
    "addr:full":"1018 N Thompson Dr Madison WI 53704",
    "addr:housenumber":"1018",
    "addr:postcode":"53704",
    "addr:street":"N Thompson Dr",
    "iso:country":"US",
    "sg:address":"1018 N Thompson Dr",
    "sg:city":"Madison",
    "sg:classifiers":[
        {
            "category":"Professional",
            "subcategory":"Secretarial Services",
            "type":"Services"
        }
    ],
    "sg:phone":"+1 608 249 9780",
    "sg:postcode":"53704",
    "sg:province":"WI",
    "sg:tags":[
        "convention",
        "court",
        "reporter"
    ],
    "wof:name":"Capitol City Reporters",
    "wof:placetype":"venue"
},
  "geometry": {"coordinates":[-89.296256,43.113055],"type":"Point"}
}