{
  "type": "Feature",
  "properties": {
    "iso:country":"US",
    "sg:address":"13 Grant St",
    "sg:city":"Fort Atkinson",
    "sg:classifiers":[
        {
            "category":"Real Estate",
            "subcategory":"Real Estate Agent",
            "type":"Services"
        }
    ],
    "sg:phone":"+1 920 563 4606",
    "sg:postcode":"53538",
    "sg:province":"WI",
    "wof:name":"Century 21",
    "wof:placetype":"venue"
},
  "geometry": {"coordinates":[-88.83841200000001,42.927376],"type":"Point"}
}