{
  "type": "Feature",
  "properties": {
    "addr:full":"16451 Freeman Rd Gays Mills WI 54631",
    "addr:housenumber":"16451",
    "addr:postcode":"54631",
    "addr:street":"Freeman Rd",
    "iso:country":"US",
    "sg:address":"16451 Freeman Rd",
    "sg:city":"Gays Mills",
    "sg:classifiers":[
        {
            "category":"Farming",
            "subcategory":"Dairy Farm",
            "type":"Manufacturing & Wholesale Goods"
        }
    ],
    "sg:phone":"+1 608 735 4466",
    "sg:postcode":"54631",
    "sg:province":"WI",
    "wof:name":"Swisstine Acres",
    "wof:placetype":"venue"
},
  "geometry": {"coordinates":[-90.900707,43.339354],"type":"Point"}
}