{
  "type": "Feature",
  "properties": {
    "addr:full":"2275 Shawano Ave Green Bay WI 54303",
    "addr:housenumber":"2275",
    "addr:postcode":"54303",
    "addr:street":"Shawano Ave",
    "iso:country":"US",
    "sg:address":"2275 Shawano Ave",
    "sg:city":"Green Bay",
    "sg:classifiers":[
        {
            "category":"Restaurant",
            "type":"Food & Drink"
        }
    ],
    "sg:menulink":"http://www.allmenus.com/wi/howard/145498-subway/menu/",
    "sg:phone":"+1 920 497 4522",
    "sg:postcode":"54303",
    "sg:province":"WI",
    "sg:tags":[
        "american",
        "sandwich"
    ],
    "wof:name":"Subway",
    "wof:placetype":"venue"
},
  "geometry": {"coordinates":[-88.08784,44.541861],"type":"Point"}
}