{
  "type": "Feature",
  "properties": {
    "addr:full":"1205 Noridge Trl Port Washington WI 53074",
    "addr:housenumber":"1205",
    "addr:postcode":"53074",
    "addr:street":"Noridge Trl",
    "iso:country":"US",
    "sg:address":"1205 Noridge Trl",
    "sg:city":"Port Washington",
    "sg:classifiers":[
        {
            "category":"Government",
            "subcategory":"Office",
            "type":"Public Place"
        }
    ],
    "sg:phone":"+1 262 268 6998",
    "sg:postcode":"53074",
    "sg:province":"WI",
    "wof:name":"Representative Mark Gottlieb",
    "wof:placetype":"venue"
},
  "geometry": {"coordinates":[-87.858993,43.403445],"type":"Point"}
}