{
  "type": "Feature",
  "properties": {
    "iso:country":"US",
    "sg:address":"8811 Spangberg Rd",
    "sg:city":"Webster",
    "sg:classifiers":[
        {
            "category":"Shopping",
            "subcategory":"Jewelry",
            "type":"Retail Goods"
        }
    ],
    "sg:phone":"+1 715 349 8021",
    "sg:postcode":"54893",
    "sg:province":"WI",
    "wof:name":"Timberdoodle Mantel Clocks",
    "wof:placetype":"venue"
},
  "geometry": {"coordinates":[-92.446739,45.799008],"type":"Point"}
}