{
  "type": "Feature",
  "properties": {
    "iso:country":"US",
    "sg:address":"1224 Franklin St",
    "sg:city":"Stevens Point",
    "sg:classifiers":[
        {
            "category":"Building & Trades",
            "subcategory":"Equipment Rental",
            "type":"Services"
        }
    ],
    "sg:phone":"+1 715 570 4142",
    "sg:postcode":"54481",
    "sg:province":"WI",
    "wof:name":"Christian Bros Rntl & Rnvtion",
    "wof:placetype":"venue"
},
  "geometry": {"coordinates":[-89.580158,44.527174],"type":"Point"}
}