{
  "type": "Feature",
  "properties": {
    "addr:full":"418 E Silver Spring Dr Milwaukee WI 53217",
    "addr:housenumber":"418",
    "addr:postcode":"53217",
    "addr:street":"E Silver Spring Dr",
    "iso:country":"US",
    "sg:address":"418 E Silver Spring Dr",
    "sg:city":"Milwaukee",
    "sg:classifiers":[
        {
            "category":"Bakery",
            "type":"Food & Drink"
        }
    ],
    "sg:menulink":"http://www.allmenus.com/wi/whitefish-bay/220589-breadsmith/menu/",
    "sg:phone":"+1 414 962 6203",
    "sg:postcode":"53217",
    "sg:province":"WI",
    "sg:tags":[
        "american",
        "pastry"
    ],
    "wof:name":"Breadsmith",
    "wof:placetype":"venue"
},
  "geometry": {"coordinates":[-87.904657,43.118493],"type":"Point"}
}