{
  "type": "Feature",
  "properties": {
    "addr:full":"1457 60th St Lyndon Station WI 53944",
    "addr:housenumber":"1457",
    "addr:postcode":"53944",
    "addr:street":"60Th St",
    "iso:country":"US",
    "sg:address":"1457 60th St",
    "sg:city":"Lyndon Station",
    "sg:classifiers":[
        {
            "category":"Building & Trades",
            "subcategory":"Landscaping Services",
            "type":"Services"
        }
    ],
    "sg:phone":"+1 608 666 2418",
    "sg:postcode":"53944",
    "sg:province":"WI",
    "sg:tags":[
        "tree"
    ],
    "wof:name":"Hall Tree Svc",
    "wof:placetype":"venue"
},
  "geometry": {"coordinates":[-89.848409,43.731074],"type":"Point"}
}