{
  "type": "Feature",
  "properties": {
    "iso:country":"US",
    "sg:address":"2710 Brookside Ln",
    "sg:city":"Brookfield",
    "sg:classifiers":[
        {
            "category":"Real Estate",
            "subcategory":"Real Estate Agent",
            "type":"Services"
        },
        {
            "category":"Real Estate",
            "subcategory":"Real Estate Operator",
            "type":"Services"
        }
    ],
    "sg:phone":"+1 262 784 8490",
    "sg:postcode":"53005",
    "sg:province":"WI",
    "sg:tags":[
        "building",
        "nonresidential"
    ],
    "wof:name":"Stuebner Properties LLC",
    "wof:placetype":"venue"
},
  "geometry": {"coordinates":[-88.091181,43.068814],"type":"Point"}
}