{
  "type": "Feature",
  "properties": {
    "iso:country":"US",
    "sg:address":"430 Rainbow Rd",
    "sg:city":"Hayward",
    "sg:classifiers":[
        {
            "category":"Shopping",
            "subcategory":"Clothing, Apparel, & Fashions",
            "type":"Retail Goods"
        }
    ],
    "sg:phone":"+1 715 634 1019",
    "sg:postcode":"54843",
    "sg:province":"WI",
    "wof:name":"Tees & Sweats",
    "wof:placetype":"venue"
},
  "geometry": {"coordinates":[-91.562426,45.952848],"type":"Point"}
}