{
  "type": "Feature",
  "properties": {
    "iso:country":"US",
    "sg:address":"7107 Town Hall Rd",
    "sg:city":"Ringle",
    "sg:classifiers":[
        {
            "category":"Government",
            "subcategory":"Office",
            "type":"Public Place"
        }
    ],
    "sg:phone":"+1 715 446 3771",
    "sg:postcode":"54471",
    "sg:province":"WI",
    "sg:tags":[
        "village"
    ],
    "wof:name":"Ringle Town Garage",
    "wof:placetype":"venue"
},
  "geometry": {"coordinates":[-89.425141,44.891914],"type":"Point"}
}