{
  "type": "Feature",
  "properties": {
    "iso:country":"US",
    "sg:address":"249 N Main St",
    "sg:city":"Oregon",
    "sg:classifiers":[
        {
            "category":"Social Services",
            "subcategory":"Child Care",
            "type":"Services"
        }
    ],
    "sg:phone":"+1 608 835 1945",
    "sg:postcode":"53575",
    "sg:province":"WI",
    "wof:name":"Little Angel's Preschool",
    "wof:placetype":"venue"
},
  "geometry": {"coordinates":[-89.383667,42.929179],"type":"Point"}
}