{
  "type": "Feature",
  "properties": {
    "addr:full":"4825 Co Rd A Oshkosh WI 54901",
    "addr:housenumber":"4825",
    "addr:postcode":"54901",
    "addr:street":"Co Rd",
    "iso:country":"US",
    "sg:address":"4825 Co Rd A",
    "sg:city":"Oshkosh",
    "sg:classifiers":[
        {
            "category":"Professional",
            "type":"Services"
        }
    ],
    "sg:phone":"+1 920 426 2908",
    "sg:postcode":"54901",
    "sg:province":"WI",
    "wof:name":"100 Block LLC",
    "wof:placetype":"venue"
},
  "geometry": {"coordinates":[-88.512091,44.091035],"type":"Point"}
}