{
  "type": "Feature",
  "properties": {
    "iso:country":"US",
    "sg:address":"720 W Winnebago St",
    "sg:city":"Appleton",
    "sg:classifiers":[
        {
            "category":"Travel",
            "subcategory":"Travel Agent",
            "type":"Entertainment"
        }
    ],
    "sg:phone":"+1 920 993 0974",
    "sg:postcode":"54914",
    "sg:province":"WI",
    "sg:tags":[
        "operator",
        "tour",
        "agency",
        "bureau"
    ],
    "wof:name":"Funtastic Tours LLC",
    "wof:placetype":"venue"
},
  "geometry": {"coordinates":[-88.417197,44.269387],"type":"Point"}
}