{
  "type": "Feature",
  "properties": {
    "iso:country":"US",
    "sg:address":"621 US Hwy 51",
    "sg:city":"Poynette",
    "sg:classifiers":[
        {
            "category":"Food & Beverages",
            "subcategory":"Groceries & Convenience Stores",
            "type":"Retail Goods"
        }
    ],
    "sg:phone":"+1 608 635 2647",
    "sg:postcode":"53955",
    "sg:province":"WI",
    "sg:tags":[
        "grocer"
    ],
    "wof:name":"D & D PIGGLY Wiggly",
    "wof:placetype":"venue"
},
  "geometry": {"coordinates":[-89.395259,43.395506],"type":"Point"}
}