{
  "type": "Feature",
  "properties": {
    "addr:full":"210 Main St Cambridge WI 53523",
    "addr:housenumber":"210",
    "addr:postcode":"53523",
    "addr:street":"Main St",
    "iso:country":"US",
    "sg:address":"210 Main St",
    "sg:city":"Cambridge",
    "sg:classifiers":[
        {
            "category":"Real Estate",
            "subcategory":"Real Estate Agent",
            "type":"Services"
        }
    ],
    "sg:phone":"+1 608 423 9288",
    "sg:postcode":"53523",
    "sg:province":"WI",
    "wof:name":"Mardi O'Brien Real Estate",
    "wof:placetype":"venue"
},
  "geometry": {"coordinates":[-89.036565,42.972794],"type":"Point"}
}