{
  "type": "Feature",
  "properties": {
    "iso:country":"US",
    "sg:address":"233 Center St",
    "sg:city":"Lake Geneva",
    "sg:classifiers":[
        {
            "category":"Recreation",
            "type":"Entertainment"
        }
    ],
    "sg:phone":"+1 262 248 1141",
    "sg:postcode":"53147",
    "sg:province":"WI",
    "sg:tags":[
        "art",
        "gallery"
    ],
    "wof:name":"Sign of The Unicorn Ltd",
    "wof:placetype":"venue"
},
  "geometry": {"coordinates":[-88.433566,42.591922],"type":"Point"}
}