{
  "type": "Feature",
  "properties": {
    "iso:country":"US",
    "sg:address":"505 South Rosa Road, Suite 123  University Research Park",
    "sg:city":"Madison",
    "sg:classifiers":[
        {
            "category":"Professional",
            "subcategory":"Computer Services",
            "type":"Services"
        }
    ],
    "sg:phone":"+1 608 443 2440",
    "sg:postcode":"53719",
    "sg:province":"WI",
    "sg:website":"http://www.nerites.com",
    "wof:name":"NERITES",
    "wof:placetype":"venue"
},
  "geometry": {"coordinates":[-89.47314299999999,43.056207],"type":"Point"}
}