{
  "type": "Feature",
  "properties": {
    "iso:country":"US",
    "sg:address":"97 S Pioneer Rd",
    "sg:city":"Fond Du Lac",
    "sg:classifiers":[
        {
            "category":"Professional",
            "subcategory":"Employment Agencies",
            "type":"Services"
        }
    ],
    "sg:phone":"+1 920 923 1640",
    "sg:postcode":"54935",
    "sg:province":"WI",
    "sg:tags":[
        "temporary",
        "opportunity"
    ],
    "wof:name":"Kelly Services Inc",
    "wof:placetype":"venue"
},
  "geometry": {"coordinates":[-88.48178900000001,43.774681],"type":"Point"}
}