{
  "type": "Feature",
  "properties": {
    "iso:country":"US",
    "sg:address":"118 S Stone St",
    "sg:city":"Augusta",
    "sg:classifiers":[
        {
            "category":"Personal",
            "subcategory":"Beauty Salon",
            "type":"Services"
        }
    ],
    "sg:phone":"+1 715 286 2188",
    "sg:postcode":"54722",
    "sg:province":"WI",
    "wof:name":"Shear Delight Hairstyling",
    "wof:placetype":"venue"
},
  "geometry": {"coordinates":[-91.119984,44.679598],"type":"Point"}
}