{
  "type": "Feature",
  "properties": {
    "addr:full":"1126 S 70th St Milwaukee WI 53214",
    "addr:housenumber":"1126",
    "addr:postcode":"53214",
    "addr:street":"S 70Th St",
    "iso:country":"US",
    "sg:address":"1126 S 70th St",
    "sg:city":"Milwaukee",
    "sg:classifiers":[
        {
            "category":"Professional",
            "subcategory":"Business Services",
            "type":"Services"
        },
        {
            "category":"Professional",
            "subcategory":"Research",
            "type":"Services"
        }
    ],
    "sg:phone":"+1 414 443 1670",
    "sg:postcode":"53214",
    "sg:province":"WI",
    "sg:tags":[
        "market",
        "analysis"
    ],
    "wof:name":"Geomarketing Inc",
    "wof:placetype":"venue"
},
  "geometry": {"coordinates":[-87.99993499999999,43.019398],"type":"Point"}
}