{
  "type": "Feature",
  "properties": {
    "iso:country":"US",
    "sg:address":"3235 Willow Branch Rd",
    "sg:city":"Platteville",
    "sg:classifiers":[
        {
            "category":"Farming",
            "subcategory":"Livestock Farm",
            "type":"Manufacturing & Wholesale Goods"
        }
    ],
    "sg:phone":"+1 608 348 7103",
    "sg:postcode":"53818",
    "sg:province":"WI",
    "sg:tags":[
        "beef",
        "feedlot",
        "cattle"
    ],
    "wof:name":"Gail Tanner",
    "wof:placetype":"venue"
},
  "geometry": {"coordinates":[-90.58388600000001,42.791089],"type":"Point"}
}