{
  "type": "Feature",
  "properties": {
    "iso:country":"US",
    "sg:address":"4786 Co Rd B",
    "sg:city":"Sarona",
    "sg:classifiers":[
        {
            "category":"Retail",
            "subcategory":"Repair Shop",
            "type":"Services"
        }
    ],
    "sg:phone":"+1 715 354 7883",
    "sg:postcode":"54870",
    "sg:province":"WI",
    "wof:name":"Wolf Lawn & Marine",
    "wof:placetype":"venue"
},
  "geometry": {"coordinates":[-91.78758,45.7532],"type":"Point"}
}