{
  "type": "Feature",
  "properties": {
    "iso:country":"US",
    "sg:address":"925 S Spring St",
    "sg:city":"Port Washington",
    "sg:classifiers":[
        {
            "category":"Home & Garden",
            "subcategory":"Building Materials",
            "type":"Retail Goods"
        }
    ],
    "sg:phone":"+1 262 268 1648",
    "sg:postcode":"53074",
    "sg:province":"WI",
    "sg:tags":[
        "glass",
        "window",
        "plate"
    ],
    "wof:name":"Max Glass Co",
    "wof:placetype":"venue"
},
  "geometry": {"coordinates":[-87.889069,43.380698],"type":"Point"}
}