{
  "type": "Feature",
  "properties": {
    "addr:full":"3732 W Wisconsin Ave Milwaukee WI 53208",
    "addr:housenumber":"3732",
    "addr:postcode":"53208",
    "addr:street":"W Wisconsin Ave",
    "iso:country":"US",
    "sg:address":"3732 W Wisconsin Ave",
    "sg:city":"Milwaukee",
    "sg:classifiers":[
        {
            "category":"Social Services",
            "type":"Services"
        }
    ],
    "sg:phone":"+1 414 345 0001",
    "sg:postcode":"53208",
    "sg:province":"WI",
    "sg:tags":[
        "organization",
        "welfare"
    ],
    "wof:name":"Lad Lake Inc",
    "wof:placetype":"venue"
},
  "geometry": {"coordinates":[-87.960463,43.038828],"type":"Point"}
}