{
  "type": "Feature",
  "properties": {
    "iso:country":"US",
    "sg:address":"2071 S Rock River Cir",
    "sg:city":"De Pere",
    "sg:classifiers":[
        {
            "category":"Building & Trades",
            "subcategory":"Construction",
            "type":"Services"
        }
    ],
    "sg:phone":"+1 920 337 0455",
    "sg:postcode":"54115",
    "sg:province":"WI",
    "sg:tags":[
        "contractor"
    ],
    "wof:name":"Spencer Siding Inc",
    "wof:placetype":"venue"
},
  "geometry": {"coordinates":[-88.022631,44.441449],"type":"Point"}
}