{
  "type": "Feature",
  "properties": {
    "iso:country":"US",
    "sg:address":"50 Evanger Rd",
    "sg:city":"Independence",
    "sg:classifiers":[
        {
            "category":"Farming",
            "subcategory":"Dairy Farm",
            "type":"Manufacturing & Wholesale Goods"
        }
    ],
    "sg:phone":"+1 715 946 3985",
    "sg:postcode":"54747",
    "sg:province":"WI",
    "wof:name":"Silver Spring Stock Farm",
    "wof:placetype":"venue"
},
  "geometry": {"coordinates":[-91.52958599999999,44.452312],"type":"Point"}
}