{
  "type": "Feature",
  "properties": {
    "iso:country":"US",
    "sg:address":"938 290th Ave",
    "sg:city":"Frederic",
    "sg:classifiers":[
        {
            "category":"Farming",
            "subcategory":"Dairy Farm",
            "type":"Manufacturing & Wholesale Goods"
        }
    ],
    "sg:phone":"+1 715 472 2980",
    "sg:postcode":"54837",
    "sg:province":"WI",
    "wof:name":"Raymond Jensen",
    "wof:placetype":"venue"
},
  "geometry": {"coordinates":[-92.34583000000001,45.625537],"type":"Point"}
}