{
  "type": "Feature",
  "properties": {
    "iso:country":"US",
    "sg:address":"2574 Sandy Acre Ct",
    "sg:city":"Green Bay",
    "sg:classifiers":[
        {
            "category":"Professional",
            "type":"Services"
        }
    ],
    "sg:phone":"+1 920 662 0216",
    "sg:postcode":"54313",
    "sg:province":"WI",
    "wof:name":"Air Qualty Duct Clg & Svcs",
    "wof:placetype":"venue"
},
  "geometry": {"coordinates":[-88.083802,44.648422],"type":"Point"}
}