{
  "type": "Feature",
  "properties": {
    "iso:country":"US",
    "sg:address":"3620 Spooner Ave",
    "sg:city":"Altoona",
    "sg:classifiers":[
        {
            "category":"Retail",
            "subcategory":"Auto Repair",
            "type":"Services"
        }
    ],
    "sg:phone":"+1 715 832 5502",
    "sg:postcode":"54720",
    "sg:province":"WI",
    "sg:tags":[
        "alternator",
        "starter"
    ],
    "wof:name":"Steves Alternator Starter Svc",
    "wof:placetype":"venue"
},
  "geometry": {"coordinates":[-91.467493,44.807434],"type":"Point"}
}