{
  "type": "Feature",
  "properties": {
    "iso:country":"US",
    "sg:address":"207 James St",
    "sg:city":"Beaver Dam",
    "sg:classifiers":[
        {
            "category":"Building & Trades",
            "subcategory":"Cleaning & Sanitation",
            "type":"Services"
        }
    ],
    "sg:phone":"+1 920 885 5496",
    "sg:postcode":"53916",
    "sg:province":"WI",
    "sg:tags":[
        "maintenance"
    ],
    "wof:name":"Pioneer Floor Maintenance",
    "wof:placetype":"venue"
},
  "geometry": {"coordinates":[-88.83255,43.452044],"type":"Point"}
}