{
  "type": "Feature",
  "properties": {
    "iso:country":"US",
    "sg:address":"4905 Lakeview Ave",
    "sg:city":"Hubertus",
    "sg:classifiers":[
        {
            "category":"Professional",
            "subcategory":"Management & Consulting",
            "type":"Services"
        }
    ],
    "sg:phone":"+1 262 628 1684",
    "sg:postcode":"53033",
    "sg:province":"WI",
    "sg:tags":[
        "business"
    ],
    "wof:name":"M3 Evolution Consulting LLC",
    "wof:placetype":"venue"
},
  "geometry": {"coordinates":[-88.277217,43.242009],"type":"Point"}
}