{
  "type": "Feature",
  "properties": {
    "iso:country":"US",
    "sg:address":"455 Baldwin St",
    "sg:city":"Menasha",
    "sg:classifiers":[
        {
            "category":"Government",
            "subcategory":"Office",
            "type":"Public Place"
        }
    ],
    "sg:phone":"+1 920 967 5160",
    "sg:postcode":"54952",
    "sg:province":"WI",
    "sg:tags":[
        "city"
    ],
    "wof:name":"Public Works",
    "wof:placetype":"venue"
},
  "geometry": {"coordinates":[-88.42822099999999,44.207864],"type":"Point"}
}