{
  "type": "Feature",
  "properties": {
    "iso:country":"US",
    "sg:address":"748 Indian Hills Rd",
    "sg:city":"Fontana",
    "sg:classifiers":[
        {
            "category":"Building & Trades",
            "subcategory":"Construction",
            "type":"Services"
        }
    ],
    "sg:phone":"+1 262 275 5744",
    "sg:postcode":"53125",
    "sg:province":"WI",
    "sg:tags":[
        "contractor"
    ],
    "wof:name":"O'Neil Builders Inc",
    "wof:placetype":"venue"
},
  "geometry": {"coordinates":[-88.561728,42.542753],"type":"Point"}
}