{
  "type": "Feature",
  "properties": {
    "addr:full":"134 Eagle St Reedsburg WI 53959",
    "addr:housenumber":"134",
    "addr:postcode":"53959",
    "addr:street":"Eagle St",
    "iso:country":"US",
    "sg:address":"134 Eagle St",
    "sg:city":"Reedsburg",
    "sg:classifiers":[
        {
            "category":"Wholesale",
            "subcategory":"Construction Materials",
            "type":"Manufacturing & Wholesale Goods"
        }
    ],
    "sg:phone":"+1 608 524 2369",
    "sg:postcode":"53959",
    "sg:province":"WI",
    "sg:tags":[
        "concrete",
        "product"
    ],
    "wof:name":"Reedsburg Concrete Co Inc",
    "wof:placetype":"venue"
},
  "geometry": {"coordinates":[-90.015377,43.532939],"type":"Point"}
}