{
  "type": "Feature",
  "properties": {
    "iso:country":"US",
    "sg:address":"2405 23rd Ave",
    "sg:city":"Rice Lake",
    "sg:classifiers":[
        {
            "category":"Farming",
            "subcategory":"Livestock Farm",
            "type":"Manufacturing & Wholesale Goods"
        }
    ],
    "sg:phone":"+1 715 234 5811",
    "sg:postcode":"54868",
    "sg:province":"WI",
    "sg:tags":[
        "animal",
        "general"
    ],
    "wof:name":"JM Ranch & Arena LLC",
    "wof:placetype":"venue"
},
  "geometry": {"coordinates":[-91.662133,45.537784],"type":"Point"}
}