{
  "type": "Feature",
  "properties": {
    "iso:country":"US",
    "sg:address":"46490 State Hwy 171",
    "sg:city":"Gays Mills",
    "sg:classifiers":[
        {
            "category":"Farming",
            "subcategory":"Orchard",
            "type":"Manufacturing & Wholesale Goods"
        }
    ],
    "sg:phone":"+1 608 735 4637",
    "sg:postcode":"54631",
    "sg:province":"WI",
    "sg:tags":[
        "apple"
    ],
    "sg:website":"www.kickapoo-orchard.com",
    "wof:name":"Kickapoo Orchard Inc",
    "wof:placetype":"venue"
},
  "geometry": {"coordinates":[-90.794653,43.325081],"type":"Point"}
}