{
  "type": "Feature",
  "properties": {
    "iso:country":"US",
    "sg:address":"4050 Co Rd A",
    "sg:city":"Oshkosh",
    "sg:classifiers":[
        {
            "category":"Banks & Credit Unions",
            "subcategory":"Bank",
            "type":"Services"
        }
    ],
    "sg:phone":"+1 920 231 1050",
    "sg:postcode":"54901",
    "sg:province":"WI",
    "wof:name":"Associated Bank",
    "wof:placetype":"venue"
},
  "geometry": {"coordinates":[-88.525092,44.075115],"type":"Point"}
}