{
  "type": "Feature",
  "properties": {
    "iso:country":"US",
    "sg:address":"2279 Co Rd Q",
    "sg:city":"Poynette",
    "sg:phone":"+1 608 635 4527",
    "sg:postcode":"53955",
    "sg:province":"WI",
    "sg:tags":[
        "farm",
        "corn"
    ],
    "wof:name":"William Macleish",
    "wof:placetype":"venue"
},
  "geometry": {"coordinates":[-89.41192100000001,43.377406],"type":"Point"}
}