{
  "type": "Feature",
  "properties": {
    "addr:full":"2591 50th St Plum City WI 54761",
    "addr:housenumber":"2591",
    "addr:postcode":"54761",
    "addr:street":"50Th St",
    "iso:country":"US",
    "sg:address":"2591 50th St",
    "sg:city":"Plum City",
    "sg:classifiers":[
        {
            "category":"Farming",
            "subcategory":"Dairy Farm",
            "type":"Manufacturing & Wholesale Goods"
        }
    ],
    "sg:phone":"+1 715 647 3011",
    "sg:postcode":"54761",
    "sg:province":"WI",
    "wof:name":"Robert Redding",
    "wof:placetype":"venue"
},
  "geometry": {"coordinates":[-92.15505400000001,44.626062],"type":"Point"}
}