{
  "type": "Feature",
  "properties": {
    "addr:full":"635 Cedar St Medford WI 54451",
    "addr:housenumber":"635",
    "addr:postcode":"54451",
    "addr:street":"Cedar St",
    "iso:country":"US",
    "sg:address":"635 Cedar St",
    "sg:city":"Medford",
    "sg:classifiers":[
        {
            "category":"Health Services",
            "subcategory":"Nursing And Care Facility",
            "type":"Services"
        }
    ],
    "sg:phone":"+1 715 748 8855",
    "sg:postcode":"54451",
    "sg:province":"WI",
    "sg:tags":[
        "intermediate"
    ],
    "wof:name":"Country Gardens",
    "wof:placetype":"venue"
},
  "geometry": {"coordinates":[-90.35563999999999,45.134353],"type":"Point"}
}