{
  "type": "Feature",
  "properties": {
    "iso:country":"US",
    "sg:address":"115 N Main St",
    "sg:city":"Waupaca",
    "sg:classifiers":[
        {
            "category":"Real Estate",
            "subcategory":"Real Estate Services",
            "type":"Services"
        }
    ],
    "sg:phone":"+1 715 256 1568",
    "sg:postcode":"54981",
    "sg:province":"WI",
    "sg:tags":[
        "company",
        "title"
    ],
    "wof:name":"Title One Inc",
    "wof:placetype":"venue"
},
  "geometry": {"coordinates":[-89.08499500000001,44.358695],"type":"Point"}
}