{
  "type": "Feature",
  "properties": {
    "iso:country":"US",
    "sg:address":"2803 E Hamilton Ave",
    "sg:city":"Eau Claire",
    "sg:classifiers":[
        {
            "category":"Food & Beverages",
            "subcategory":"Meat & Fish",
            "type":"Retail Goods"
        }
    ],
    "sg:phone":"+1 715 839 8018",
    "sg:postcode":"54701",
    "sg:province":"WI",
    "sg:tags":[
        "seafood"
    ],
    "wof:name":"Dano's Seafood Market",
    "wof:placetype":"venue"
},
  "geometry": {"coordinates":[-91.46203199999999,44.785738],"type":"Point"}
}