{
  "type": "Feature",
  "properties": {
    "iso:country":"US",
    "sg:address":"6741 Mountain Rd",
    "sg:city":"Pickett",
    "sg:classifiers":[
        {
            "category":"Manufacturing",
            "subcategory":"Apparel",
            "type":"Manufacturing & Wholesale Goods"
        }
    ],
    "sg:phone":"+1 920 589 2322",
    "sg:postcode":"54964",
    "sg:province":"WI",
    "wof:name":"Rustic Road Embroidery",
    "wof:placetype":"venue"
},
  "geometry": {"coordinates":[-88.74029,43.920128],"type":"Point"}
}