{
  "type": "Feature",
  "properties": {
    "iso:country":"US",
    "sg:address":"5437 N Bethmaur Ln",
    "sg:city":"Milwaukee",
    "sg:classifiers":[
        {
            "category":"Professional",
            "subcategory":"Advertising",
            "type":"Services"
        }
    ],
    "sg:phone":"+1 414 333 4875",
    "sg:postcode":"53209",
    "sg:province":"WI",
    "sg:tags":[
        "promotion",
        "sale"
    ],
    "wof:name":"Sjc Group Ltd",
    "wof:placetype":"venue"
},
  "geometry": {"coordinates":[-87.94094800000001,43.133659],"type":"Point"}
}