{
  "type": "Feature",
  "properties": {
    "addr:full":"4634 Frontage Rd Sheboygan WI 53081",
    "addr:housenumber":"4634",
    "addr:postcode":"53081",
    "addr:street":"Frontage Rd",
    "iso:country":"US",
    "sg:address":"4634 Frontage Rd",
    "sg:city":"Sheboygan",
    "sg:classifiers":[
        {
            "category":"Shopping",
            "type":"Retail Goods"
        }
    ],
    "sg:phone":"+1 920 451 9071",
    "sg:postcode":"53081",
    "sg:province":"WI",
    "sg:tags":[
        "equipment",
        "merchandise"
    ],
    "wof:name":"Tents Inc of Sheboygan County",
    "wof:placetype":"venue"
},
  "geometry": {"coordinates":[-87.76137199999999,43.702416],"type":"Point"}
}