{
  "type": "Feature",
  "properties": {
    "iso:country":"US",
    "sg:address":"1853 Aspen Ln",
    "sg:city":"Green Bay",
    "sg:classifiers":[
        {
            "category":"Professional",
            "subcategory":"Management & Consulting",
            "type":"Services"
        }
    ],
    "sg:phone":"+1 920 499 4092",
    "sg:postcode":"54303",
    "sg:province":"WI",
    "wof:name":"Rnm Enterprises LLC",
    "wof:placetype":"venue"
},
  "geometry": {"coordinates":[-88.072781,44.525498],"type":"Point"}
}