{
  "type": "Feature",
  "properties": {
    "addr:full":"1139 8th St Baraboo WI 53913",
    "addr:housenumber":"1139",
    "addr:postcode":"53913",
    "addr:street":"8Th St",
    "iso:country":"US",
    "sg:address":"1139 8th St",
    "sg:city":"Baraboo",
    "sg:classifiers":[
        {
            "category":"Home & Garden",
            "subcategory":"Building Materials",
            "type":"Retail Goods"
        }
    ],
    "sg:phone":"+1 608 356 6661",
    "sg:postcode":"53913",
    "sg:province":"WI",
    "sg:tags":[
        "lumber"
    ],
    "wof:name":"Brittingham & Hixon Lumber Co",
    "wof:placetype":"venue"
},
  "geometry": {"coordinates":[-89.72332299999999,43.474759],"type":"Point"}
}