{
  "type": "Feature",
  "properties": {
    "iso:country":"US",
    "sg:address":"517 E Menomonee St",
    "sg:city":"Milwaukee",
    "sg:classifiers":[
        {
            "category":"Shopping",
            "subcategory":"Clothing, Apparel, & Fashions",
            "type":"Retail Goods"
        }
    ],
    "sg:phone":"+1 414 390 0389",
    "sg:postcode":"53202",
    "sg:province":"WI",
    "wof:name":"Ayeshaz Womens Apparel",
    "wof:placetype":"venue"
},
  "geometry": {"coordinates":[-87.90330299999999,43.03158],"type":"Point"}
}