{
  "type": "Feature",
  "properties": {
    "iso:country":"US",
    "sg:address":"950 Prairie St",
    "sg:city":"Prairie Du Sac",
    "sg:classifiers":[
        {
            "category":"Health Services",
            "subcategory":"Nursing And Care Facility",
            "type":"Services"
        }
    ],
    "sg:phone":"+1 608 643 7343",
    "sg:postcode":"53578",
    "sg:province":"WI",
    "sg:tags":[
        "intermediate"
    ],
    "wof:name":"Elder Haus of Prairie Du Sac",
    "wof:placetype":"venue"
},
  "geometry": {"coordinates":[-89.73071,43.29312],"type":"Point"}
}