{
  "type": "Feature",
  "properties": {
    "iso:country":"US",
    "sg:address":"3467 E Manitou Valley Rd",
    "sg:city":"Superior",
    "sg:classifiers":[
        {
            "category":"Travel",
            "subcategory":"Campground",
            "type":"Entertainment"
        }
    ],
    "sg:phone":"+1 715 399 8696",
    "sg:postcode":"54880",
    "sg:province":"WI",
    "wof:name":"Manitou Valley Campground",
    "wof:placetype":"venue"
},
  "geometry": {"coordinates":[-92.124357,46.547485],"type":"Point"}
}