{
  "type": "Feature",
  "properties": {
    "iso:country":"US",
    "sg:address":"626 E Kilbourn Ave",
    "sg:city":"Milwaukee",
    "sg:classifiers":[
        {
            "category":"Banks & Credit Unions",
            "subcategory":"Financial Services",
            "type":"Services"
        }
    ],
    "sg:phone":"+1 414 765 9139",
    "sg:postcode":"53202",
    "sg:province":"WI",
    "sg:tags":[
        "investor"
    ],
    "wof:name":"Tmh Investments LLC",
    "wof:placetype":"venue"
},
  "geometry": {"coordinates":[-87.903475,43.042766],"type":"Point"}
}