{
  "type": "Feature",
  "properties": {
    "iso:country":"US",
    "sg:address":"509 E Briarknoll Ct",
    "sg:city":"Saukville",
    "sg:classifiers":[
        {
            "category":"Building & Trades",
            "subcategory":"Construction",
            "type":"Services"
        }
    ],
    "sg:phone":"+1 262 268 1239",
    "sg:postcode":"53080",
    "sg:province":"WI",
    "sg:tags":[
        "house"
    ],
    "wof:name":"Dr Construction & Fabricating",
    "wof:placetype":"venue"
},
  "geometry": {"coordinates":[-87.94964,43.372019],"type":"Point"}
}