{
  "type": "Feature",
  "properties": {
    "iso:country":"US",
    "sg:address":"38459 US Hwy 18",
    "sg:city":"Prairie Du Chien",
    "sg:classifiers":[
        {
            "category":"Wholesale",
            "subcategory":"Farm Supplies",
            "type":"Manufacturing & Wholesale Goods"
        }
    ],
    "sg:phone":"+1 608 326 6115",
    "sg:postcode":"53821",
    "sg:province":"WI",
    "sg:tags":[
        "buyer",
        "livestock"
    ],
    "wof:name":"Ronald White Live Stock Dealer",
    "wof:placetype":"venue"
},
  "geometry": {"coordinates":[-91.076131,43.012246],"type":"Point"}
}