{
  "type": "Feature",
  "properties": {
    "addr:full":"5 Mann Ln River Falls WI 54022",
    "addr:housenumber":"5",
    "addr:postcode":"54022",
    "addr:street":"Mann Ln",
    "iso:country":"US",
    "sg:address":"5 Mann Ln",
    "sg:city":"River Falls",
    "sg:classifiers":[
        {
            "category":"Building & Trades",
            "subcategory":"Electrical",
            "type":"Services"
        }
    ],
    "sg:phone":"+1 715 425 6202",
    "sg:postcode":"54022",
    "sg:province":"WI",
    "sg:tags":[
        "electrical",
        "contractor"
    ],
    "wof:name":"Prestige Electric LLC",
    "wof:placetype":"venue"
},
  "geometry": {"coordinates":[-92.66486399999999,44.864454],"type":"Point"}
}