{
  "type": "Feature",
  "properties": {
    "iso:country":"US",
    "sg:address":"4650 Romadka Ave",
    "sg:city":"Granton",
    "sg:classifiers":[
        {
            "category":"Real Estate",
            "subcategory":"Real Estate Agent",
            "type":"Services"
        }
    ],
    "sg:phone":"+1 715 743 4320",
    "sg:postcode":"54436",
    "sg:province":"WI",
    "sg:tags":[
        "security",
        "manage"
    ],
    "wof:name":"Garbisch Realty & Investments",
    "wof:placetype":"venue"
},
  "geometry": {"coordinates":[-90.456247,44.589922],"type":"Point"}
}