{
  "type": "Feature",
  "properties": {
    "iso:country":"US",
    "sg:address":"1522 Memorial Dr",
    "sg:city":"Sturgeon Bay",
    "sg:classifiers":[
        {
            "category":"Professional",
            "type":"Services"
        }
    ],
    "sg:phone":"+1 920 743 1221",
    "sg:postcode":"54235",
    "sg:province":"WI",
    "wof:name":"Feathered Star Bed &",
    "wof:placetype":"venue"
},
  "geometry": {"coordinates":[-87.35780200000001,44.824698],"type":"Point"}
}