{
  "type": "Feature",
  "properties": {
    "addr:full":"1789 Shawano Ave Green Bay WI 54303",
    "addr:housenumber":"1789",
    "addr:postcode":"54303",
    "addr:street":"Shawano Ave",
    "iso:country":"US",
    "sg:address":"1789 Shawano Ave",
    "sg:city":"Green Bay",
    "sg:classifiers":[
        {
            "category":"Health Services",
            "subcategory":"Doctor",
            "type":"Services"
        }
    ],
    "sg:phone":"+1 920 499 1428",
    "sg:postcode":"54303",
    "sg:province":"WI",
    "sg:tags":[
        "physician",
        "surgeon"
    ],
    "wof:name":"C T Imaging",
    "wof:placetype":"venue"
},
  "geometry": {"coordinates":[-88.069276,44.532936],"type":"Point"}
}