{
  "type": "Feature",
  "properties": {
    "iso:country":"US",
    "sg:address":"1952 22nd Ave",
    "sg:city":"Kenosha",
    "sg:classifiers":[
        {
            "category":"Organizations",
            "subcategory":"Religious Organization",
            "type":"Services"
        }
    ],
    "sg:phone":"+1 262 925 8884",
    "sg:postcode":"53140",
    "sg:province":"WI",
    "wof:name":"Grace & Truth Tabernacle",
    "wof:placetype":"venue"
},
  "geometry": {"coordinates":[-87.83593399999999,42.618893],"type":"Point"}
}