{
  "type": "Feature",
  "properties": {
    "iso:country":"US",
    "sg:address":"102 Merrill Crest Dr",
    "sg:city":"Madison",
    "sg:classifiers":[
        {
            "category":"Professional",
            "subcategory":"Secretarial Services",
            "type":"Services"
        }
    ],
    "sg:phone":"+1 608 837 0456",
    "sg:postcode":"53705",
    "sg:province":"WI",
    "sg:tags":[
        "reporting"
    ],
    "wof:name":"On Line Transcription Inc",
    "wof:placetype":"venue"
},
  "geometry": {"coordinates":[-89.470294,43.069059],"type":"Point"}
}