{
  "type": "Feature",
  "properties": {
    "iso:country":"US",
    "sg:address":"3918 W. Center Street",
    "sg:city":"Milwaukee",
    "sg:classifiers":[
        {
            "category":"Place Of Worship",
            "subcategory":"Church",
            "type":"Public Place"
        },
        {
            "category":"Place Of Worship",
            "type":"Public Place"
        }
    ],
    "sg:phone":"+1 414 447 1078",
    "sg:postcode":"53210",
    "sg:province":"WI",
    "sg:tags":[
        "christ",
        "churches-christian-disciples",
        "god",
        "churches-church",
        "churches-non-denominational",
        "churches-christian"
    ],
    "sg:website":"http://myspace.comchristcommunitychurch",
    "wof:name":"Christ Community Church",
    "wof:placetype":"venue"
},
  "geometry": {"coordinates":[-87.962377,43.06794],"type":"Point"}
}