{
  "type": "Feature",
  "properties": {
    "iso:country":"US",
    "sg:address":"2824 Harbor Lights Ln",
    "sg:city":"Suamico",
    "sg:classifiers":[
        {
            "category":"Bars & Pubs",
            "type":"Food & Drink"
        }
    ],
    "sg:phone":"+1 920 434 9909",
    "sg:postcode":"54173",
    "sg:province":"WI",
    "sg:tags":[
        "drinking"
    ],
    "wof:name":"Harbor Lights Resort",
    "wof:placetype":"venue"
},
  "geometry": {"coordinates":[-88.01434399999999,44.619662],"type":"Point"}
}