{
  "type": "Feature",
  "properties": {
    "iso:country":"US",
    "sg:address":"1437 W Mineral St",
    "sg:city":"Milwaukee",
    "sg:classifiers":[
        {
            "category":"Local Transit",
            "type":"Transportation"
        }
    ],
    "sg:phone":"+1 414 384 0200",
    "sg:postcode":"53204",
    "sg:province":"WI",
    "sg:tags":[
        "public",
        "provider"
    ],
    "wof:name":"Terry Lynn Transportation",
    "wof:placetype":"venue"
},
  "geometry": {"coordinates":[-87.929721,43.021167],"type":"Point"}
}