{
  "type": "Feature",
  "properties": {
    "iso:country":"US",
    "sg:address":"4616 N 87th St",
    "sg:city":"Milwaukee",
    "sg:classifiers":[
        {
            "category":"Professional",
            "subcategory":"Management & Consulting",
            "type":"Services"
        }
    ],
    "sg:phone":"+1 414 527 1601",
    "sg:postcode":"53225",
    "sg:province":"WI",
    "sg:tags":[
        "retail",
        "sales"
    ],
    "wof:name":"The Talking Drum",
    "wof:placetype":"venue"
},
  "geometry": {"coordinates":[-88.021807,43.101922],"type":"Point"}
}