{
  "type": "Feature",
  "properties": {
    "addr:full":"101 N Water St Albany WI 53502",
    "addr:housenumber":"101",
    "addr:postcode":"53502",
    "addr:street":"N Water St",
    "iso:country":"US",
    "sg:address":"101 N Water St",
    "sg:city":"Albany",
    "sg:classifiers":[
        {
            "category":"Restaurant",
            "type":"Food & Drink"
        }
    ],
    "sg:phone":"+1 608 862 3396",
    "sg:postcode":"53502",
    "sg:province":"WI",
    "wof:name":"Edgewater Cafe",
    "wof:placetype":"venue"
},
  "geometry": {"coordinates":[-89.440084,42.711287],"type":"Point"}
}