{
  "type": "Feature",
  "properties": {
    "iso:country":"US",
    "sg:address":"21357 Glodowski Rd",
    "sg:city":"Arcadia",
    "sg:classifiers":[
        {
            "category":"Retail",
            "subcategory":"Repair Shop",
            "type":"Services"
        }
    ],
    "sg:phone":"+1 608 539 2008",
    "sg:postcode":"54612",
    "sg:province":"WI",
    "wof:name":"Fins Feathers & Furs Taxidermy",
    "wof:placetype":"venue"
},
  "geometry": {"coordinates":[-91.526087,44.146739],"type":"Point"}
}