{
  "type": "Feature",
  "properties": {
    "iso:country":"US",
    "sg:address":"2392 Lake Nokomis Rd",
    "sg:city":"Tomahawk",
    "sg:classifiers":[
        {
            "category":"Manufacturing",
            "subcategory":"Metals",
            "type":"Manufacturing & Wholesale Goods"
        }
    ],
    "sg:phone":"+1 715 453 4350",
    "sg:postcode":"54487",
    "sg:province":"WI",
    "sg:tags":[
        "tool",
        "devices",
        "mfg"
    ],
    "wof:name":"Johnson Level & Tool Mfg Co",
    "wof:placetype":"venue"
},
  "geometry": {"coordinates":[-89.70382,45.584845],"type":"Point"}
}