{
  "type": "Feature",
  "properties": {
    "addr:full":"6414 W Cleveland Ave Milwaukee WI 53219",
    "addr:housenumber":"6414",
    "addr:postcode":"53219",
    "addr:street":"W Cleveland Ave",
    "iso:country":"US",
    "sg:address":"6414 W Cleveland Ave",
    "sg:city":"Milwaukee",
    "sg:classifiers":[
        {
            "category":"Building & Trades",
            "subcategory":"Cleaning & Sanitation",
            "type":"Services"
        }
    ],
    "sg:phone":"+1 414 541 9397",
    "sg:postcode":"53219",
    "sg:province":"WI",
    "sg:tags":[
        "cleaning-industrial",
        "contractor"
    ],
    "wof:name":"Custom Steam Cleaning & Maintenance",
    "wof:placetype":"venue"
},
  "geometry": {"coordinates":[-87.992525,42.995627],"type":"Point"}
}