{
  "type": "Feature",
  "properties": {
    "iso:country":"US",
    "sg:address":"7414 W Hampton Ave",
    "sg:city":"Milwaukee",
    "sg:classifiers":[
        {
            "category":"Shopping",
            "subcategory":"Hobbies, Toys, & Games",
            "type":"Retail Goods"
        }
    ],
    "sg:phone":"+1 414 461 7781",
    "sg:postcode":"53218",
    "sg:province":"WI",
    "wof:name":"Treasure Nook Ceramics Inc",
    "wof:placetype":"venue"
},
  "geometry": {"coordinates":[-88.00639200000001,43.105071],"type":"Point"}
}