{
  "type": "Feature",
  "properties": {
    "iso:country":"US",
    "sg:address":"2240 Tower Dr",
    "sg:city":"Kaukauna",
    "sg:classifiers":[
        {
            "category":"Manufacturing",
            "subcategory":"Furniture",
            "type":"Manufacturing & Wholesale Goods"
        }
    ],
    "sg:phone":"+1 920 759 1451",
    "sg:postcode":"54130",
    "sg:province":"WI",
    "sg:tags":[
        "wood",
        "mfg"
    ],
    "wof:name":"Envision Surfaces LLC",
    "wof:placetype":"venue"
},
  "geometry": {"coordinates":[-88.263304,44.301294],"type":"Point"}
}