{
  "type": "Feature",
  "properties": {
    "addr:full":"121 Park Ave  Pewaukee WI 53072",
    "addr:housenumber":"121",
    "addr:postcode":"53072",
    "addr:street":"Park Ave",
    "iso:country":"US",
    "sg:address":"121 Park Ave ",
    "sg:city":"Pewaukee",
    "sg:classifiers":[
        {
            "category":"Restaurant",
            "type":"Food & Drink"
        }
    ],
    "sg:menulink":"http://www.allmenus.com/wi/pewaukee/292462-park-avenue-pizza-company/menu/",
    "sg:phone":"+1 262 691 0503",
    "sg:postcode":"53072",
    "sg:province":"WI",
    "sg:tags":[
        "pizza"
    ],
    "wof:name":"Park Avenue Pizza Company",
    "wof:placetype":"venue"
},
  "geometry": {"coordinates":[-88.26340399999999,43.08238],"type":"Point"}
}