{
  "type": "Feature",
  "properties": {
    "iso:country":"US",
    "sg:address":"823 Union Ave",
    "sg:city":"Sheboygan",
    "sg:classifiers":[
        {
            "category":"Organizations",
            "subcategory":"Religious Organization",
            "type":"Services"
        }
    ],
    "sg:phone":"+1 920 458 4889",
    "sg:postcode":"53081",
    "sg:province":"WI",
    "sg:tags":[
        "church"
    ],
    "wof:name":"Wesley United Methodist Church",
    "wof:placetype":"venue"
},
  "geometry": {"coordinates":[-87.714352,43.731829],"type":"Point"}
}