{
  "type": "Feature",
  "properties": {
    "addr:full":"5006 60th St Kenosha WI 53144",
    "addr:housenumber":"5006",
    "addr:postcode":"53144",
    "addr:street":"60Th St",
    "iso:country":"US",
    "sg:address":"5006 60th St",
    "sg:city":"Kenosha",
    "sg:classifiers":[
        {
            "category":"Food & Beverages",
            "subcategory":"Groceries & Convenience Stores",
            "type":"Retail Goods"
        }
    ],
    "sg:phone":"+1 262 652 6426",
    "sg:postcode":"53144",
    "sg:province":"WI",
    "wof:name":"Pak Petroleum Shell",
    "wof:placetype":"venue"
},
  "geometry": {"coordinates":[-87.868438,42.580631],"type":"Point"}
}