{
  "type": "Feature",
  "properties": {
    "iso:country":"US",
    "sg:address":"1891 Co Rd B",
    "sg:city":"Platteville",
    "sg:classifiers":[
        {
            "category":"Farming",
            "subcategory":"Livestock Farm",
            "type":"Manufacturing & Wholesale Goods"
        }
    ],
    "sg:phone":"+1 608 348 6224",
    "sg:postcode":"53818",
    "sg:province":"WI",
    "sg:tags":[
        "beef",
        "feedlot",
        "cattle"
    ],
    "wof:name":"B J B Cattle Company LLC",
    "wof:placetype":"venue"
},
  "geometry": {"coordinates":[-90.510362,42.73796],"type":"Point"}
}