{
  "type": "Feature",
  "properties": {
    "iso:country":"US",
    "sg:address":"6702 W Thornapple Dr",
    "sg:city":"Janesville",
    "sg:classifiers":[
        {
            "category":"Shopping",
            "subcategory":"Hobbies, Toys, & Games",
            "type":"Retail Goods"
        }
    ],
    "sg:phone":"+1 608 756 4147",
    "sg:postcode":"53548",
    "sg:province":"WI",
    "sg:tags":[
        "mfg"
    ],
    "wof:name":"Old Memories",
    "wof:placetype":"venue"
},
  "geometry": {"coordinates":[-89.143672,42.742656],"type":"Point"}
}