{
  "type": "Feature",
  "properties": {
    "addr:full":"65 E 12th St Clintonville WI 54929",
    "addr:housenumber":"65",
    "addr:postcode":"54929",
    "addr:street":"E 12Th St",
    "iso:country":"US",
    "sg:address":"65 E 12th St",
    "sg:city":"Clintonville",
    "sg:classifiers":[
        {
            "category":"Utilities",
            "type":"Services"
        }
    ],
    "sg:phone":"+1 715 823 2118",
    "sg:postcode":"54929",
    "sg:province":"WI",
    "sg:tags":[
        "executive",
        "combination"
    ],
    "wof:name":"Clintonville Wtr Elc Utilities",
    "wof:placetype":"venue"
},
  "geometry": {"coordinates":[-88.757266,44.621986],"type":"Point"}
}