{
  "type": "Feature",
  "properties": {
    "addr:full":"2385 S Kinnickinnic Ave Milwaukee WI 53207",
    "addr:housenumber":"2385",
    "addr:postcode":"53207",
    "addr:street":"S Kinnickinnic Ave",
    "iso:country":"US",
    "sg:address":"2385 S Kinnickinnic Ave",
    "sg:city":"Milwaukee",
    "sg:classifiers":[
        {
            "category":"Personal",
            "subcategory":"Beauty Salon",
            "type":"Services"
        }
    ],
    "sg:phone":"+1 414 486 9299",
    "sg:postcode":"53207",
    "sg:province":"WI",
    "sg:tags":[
        "shop"
    ],
    "wof:name":"Hairys Hair Bar",
    "wof:placetype":"venue"
},
  "geometry": {"coordinates":[-87.90311800000001,43.00156],"type":"Point"}
}