{
  "type": "Feature",
  "properties": {
    "iso:country":"US",
    "sg:address":"10903 Elm Grove Rd",
    "sg:city":"Marion",
    "sg:classifiers":[
        {
            "category":"Retail",
            "subcategory":"Repair Shop",
            "type":"Services"
        }
    ],
    "sg:phone":"+1 715 754 2710",
    "sg:postcode":"54950",
    "sg:province":"WI",
    "sg:tags":[
        "refrigeration",
        "refrigerator",
        "freezer"
    ],
    "wof:name":"Niemuth Refrigeration Services",
    "wof:placetype":"venue"
},
  "geometry": {"coordinates":[-88.817677,44.708577],"type":"Point"}
}