{
  "type": "Feature",
  "properties": {
    "iso:country":"US",
    "sg:address":"8170 Co Rd F",
    "sg:city":"Portage",
    "sg:phone":"+1 608 742 7542",
    "sg:postcode":"53901",
    "sg:province":"WI",
    "sg:tags":[
        "vegetable",
        "farm"
    ],
    "wof:name":"Gatzkes Farms Inc",
    "wof:placetype":"venue"
},
  "geometry": {"coordinates":[-89.41739699999999,43.573819],"type":"Point"}
}