{
  "type": "Feature",
  "properties": {
    "addr:full":"3160 Club House Rd Sayner WI 54560",
    "addr:housenumber":"3160",
    "addr:postcode":"54560",
    "addr:street":"Club House Rd",
    "iso:country":"US",
    "sg:address":"3160 Club House Rd",
    "sg:city":"Sayner",
    "sg:classifiers":[
        {
            "category":"Sports & Exercise",
            "subcategory":"Golf",
            "type":"Entertainment"
        }
    ],
    "sg:phone":"+1 715 542 2598",
    "sg:postcode":"54560",
    "sg:province":"WI",
    "sg:tags":[
        "course"
    ],
    "wof:name":"Plum Lake Golf Course",
    "wof:placetype":"venue"
},
  "geometry": {"coordinates":[-89.51862800000001,45.998561],"type":"Point"}
}