{
  "type": "Feature",
  "properties": {
    "iso:country":"US",
    "sg:address":"4619 N 67th St",
    "sg:city":"Milwaukee",
    "sg:classifiers":[
        {
            "category":"Freight",
            "type":"Transportation"
        }
    ],
    "sg:phone":"+1 414 464 6797",
    "sg:postcode":"53218",
    "sg:province":"WI",
    "wof:name":"Dynasty Transportation Svc",
    "wof:placetype":"venue"
},
  "geometry": {"coordinates":[-87.995619,43.102723],"type":"Point"}
}