{
  "type": "Feature",
  "properties": {
    "addr:full":"1488 Kenwood Dr Appleton WI 54952",
    "addr:housenumber":"1488",
    "addr:postcode":"54952",
    "addr:street":"Kenwood Dr",
    "iso:country":"US",
    "sg:address":"1488 Kenwood Dr",
    "sg:city":"Appleton",
    "sg:classifiers":[
        {
            "category":"Professional",
            "subcategory":"Detective & Security Services",
            "type":"Services"
        }
    ],
    "sg:phone":"+1 920 209 5940",
    "sg:postcode":"54952",
    "sg:province":"WI",
    "sg:tags":[
        "agency",
        "private"
    ],
    "wof:name":"Diversified Investigations LLC",
    "wof:placetype":"venue"
},
  "geometry": {"coordinates":[-88.429241,44.229708],"type":"Point"}
}