{
  "type": "Feature",
  "properties": {
    "addr:full":"4331 E Wall St Eagle River WI 54521",
    "addr:housenumber":"4331",
    "addr:postcode":"54521",
    "addr:street":"E Wall St",
    "iso:country":"US",
    "sg:address":"4331 E Wall St",
    "sg:city":"Eagle River",
    "sg:classifiers":[
        {
            "category":"Shopping",
            "subcategory":"Hobbies, Toys, & Games",
            "type":"Retail Goods"
        }
    ],
    "sg:phone":"+1 715 479 5154",
    "sg:postcode":"54521",
    "sg:province":"WI",
    "wof:name":"Pauls Pump and Pantry",
    "wof:placetype":"venue"
},
  "geometry": {"coordinates":[-89.228279,45.913916],"type":"Point"}
}