{
  "type": "Feature",
  "properties": {
    "iso:country":"US",
    "sg:address":"6606 Berkshire Rd",
    "sg:city":"Madison",
    "sg:classifiers":[
        {
            "category":"Shopping",
            "subcategory":"Crafts & Fabrics",
            "type":"Retail Goods"
        }
    ],
    "sg:phone":"+1 608 288 9825",
    "sg:postcode":"53711",
    "sg:province":"WI",
    "sg:tags":[
        "sewing"
    ],
    "wof:name":"Portrait Artist",
    "wof:placetype":"venue"
},
  "geometry": {"coordinates":[-89.494885,43.045747],"type":"Point"}
}