{
  "type": "Feature",
  "properties": {
    "iso:country":"US",
    "sg:address":"401 E Lincoln Ave",
    "sg:city":"Milwaukee",
    "sg:classifiers":[
        {
            "category":"Professional",
            "subcategory":"Lawyer & Legal Services",
            "type":"Services"
        }
    ],
    "sg:phone":"+1 414 744 1399",
    "sg:postcode":"53207",
    "sg:province":"WI",
    "sg:tags":[
        "attorney"
    ],
    "wof:name":"Tammi A Bruce",
    "wof:placetype":"venue"
},
  "geometry": {"coordinates":[-87.90423199999999,43.002908],"type":"Point"}
}