{
  "type": "Feature",
  "properties": {
    "iso:country":"US",
    "sg:address":"3542 Hogarth St",
    "sg:city":"Eau Claire",
    "sg:classifiers":[
        {
            "category":"Wholesale",
            "subcategory":"Hardware",
            "type":"Manufacturing & Wholesale Goods"
        }
    ],
    "sg:phone":"+1 715 830 1800",
    "sg:postcode":"54703",
    "sg:province":"WI",
    "sg:tags":[
        "plumbing",
        "fixture",
        "supply"
    ],
    "sg:website":"www.goodinco.com",
    "wof:name":"Goodin Co",
    "wof:placetype":"venue"
},
  "geometry": {"coordinates":[-91.456254,44.868602],"type":"Point"}
}