{
  "type": "Feature",
  "properties": {
    "iso:country":"US",
    "sg:address":"8425 6 Mile Rd",
    "sg:city":"Caledonia",
    "sg:classifiers":[
        {
            "category":"Recreation",
            "subcategory":"Campground",
            "type":"Entertainment"
        }
    ],
    "sg:phone":"+1 262 835 1424",
    "sg:postcode":"53108",
    "sg:province":"WI",
    "sg:tags":[
        "recreational",
        "park",
        "vehicle"
    ],
    "wof:name":"Jellystone Park Camping Resort",
    "wof:placetype":"venue"
},
  "geometry": {"coordinates":[-87.879715,42.813933],"type":"Point"}
}