{
  "type": "Feature",
  "properties": {
    "iso:country":"US",
    "sg:address":"1205 S Washburn St",
    "sg:city":"Oshkosh",
    "sg:classifiers":[
        {
            "category":"Home & Garden",
            "subcategory":"Furniture",
            "type":"Retail Goods"
        }
    ],
    "sg:phone":"+1 920 233 2607",
    "sg:postcode":"54904",
    "sg:province":"WI",
    "wof:name":"Mc Crory's Furniture Gallery",
    "wof:placetype":"venue"
},
  "geometry": {"coordinates":[-88.58349,44.009145],"type":"Point"}
}