{
  "type": "Feature",
  "properties": {
    "addr:full":"1 Banks Ave Superior WI 54880",
    "addr:housenumber":"1",
    "addr:postcode":"54880",
    "addr:street":"Banks Ave",
    "iso:country":"US",
    "sg:address":"1 Banks Ave",
    "sg:city":"Superior",
    "sg:classifiers":[
        {
            "category":"Manufacturing",
            "subcategory":"Tools & Machinery",
            "type":"Manufacturing & Wholesale Goods"
        }
    ],
    "sg:phone":"+1 715 392 5641",
    "sg:postcode":"54880",
    "sg:province":"WI",
    "sg:tags":[
        "construction"
    ],
    "wof:name":"Barko Hydraulics LLC",
    "wof:placetype":"venue"
},
  "geometry": {"coordinates":[-92.105341,46.737202],"type":"Point"}
}