{
  "type": "Feature",
  "properties": {
    "iso:country":"US",
    "sg:address":"3012 Post Rd",
    "sg:city":"Stevens Point",
    "sg:classifiers":[
        {
            "category":"Social Services",
            "type":"Services"
        }
    ],
    "sg:phone":"+1 715 345 2626",
    "sg:postcode":"54481",
    "sg:province":"WI",
    "wof:name":"Community Project House Corp",
    "wof:placetype":"venue"
},
  "geometry": {"coordinates":[-89.550258,44.485074],"type":"Point"}
}