{
  "type": "Feature",
  "properties": {
    "addr:full":"115 5th Ave S La Crosse WI 54601",
    "addr:housenumber":"115",
    "addr:postcode":"54601",
    "addr:street":"5Th Ave S La Crosse",
    "iso:country":"US",
    "sg:address":"115 5th Ave S",
    "sg:city":"La Crosse",
    "sg:classifiers":[
        {
            "category":"Insurance",
            "subcategory":"Insurance Agent",
            "type":"Services"
        }
    ],
    "sg:phone":"+1 608 784 2002",
    "sg:postcode":"54601",
    "sg:province":"WI",
    "wof:name":"Thrivent Financial-Lutherans",
    "wof:placetype":"venue"
},
  "geometry": {"coordinates":[-91.250063,43.811159],"type":"Point"}
}