{
  "type": "Feature",
  "properties": {
    "iso:country":"US",
    "sg:address":"4044 Oak Park Rd",
    "sg:city":"Deerfield",
    "sg:classifiers":[
        {
            "category":"Manufacturing",
            "subcategory":"Electronics",
            "type":"Manufacturing & Wholesale Goods"
        }
    ],
    "sg:phone":"+1 608 764 6400",
    "sg:postcode":"53531",
    "sg:province":"WI",
    "sg:tags":[
        "devices",
        "mfg"
    ],
    "wof:name":"Rathsburg Associates",
    "wof:placetype":"venue"
},
  "geometry": {"coordinates":[-89.105653,43.075032],"type":"Point"}
}