{
  "type": "Feature",
  "properties": {
    "iso:country":"US",
    "sg:address":"5382 Blue Bill Park Dr S",
    "sg:city":"Madison",
    "sg:classifiers":[
        {
            "category":"Professional",
            "subcategory":"Management & Consulting",
            "type":"Services"
        }
    ],
    "sg:phone":"+1 608 242 1320",
    "sg:postcode":"53704",
    "sg:province":"WI",
    "sg:tags":[
        "business"
    ],
    "wof:name":"P&A Consulting Group Inc",
    "wof:placetype":"venue"
},
  "geometry": {"coordinates":[-89.409966,43.151005],"type":"Point"}
}