{
  "type": "Feature",
  "properties": {
    "iso:country":"US",
    "sg:address":"707 S University Ave",
    "sg:city":"Beaver Dam",
    "sg:classifiers":[
        {
            "category":"Organizations",
            "subcategory":"Non-profit Organization",
            "type":"Services"
        }
    ],
    "sg:phone":"+1 920 885 6800",
    "sg:postcode":"53916",
    "sg:province":"WI",
    "wof:name":"Eye Study Beaver Dam",
    "wof:placetype":"venue"
},
  "geometry": {"coordinates":[-88.828226,43.448874],"type":"Point"}
}