{
  "type": "Feature",
  "properties": {
    "iso:country":"US",
    "sg:address":"1916 Washington St",
    "sg:city":"Two Rivers",
    "sg:classifiers":[
        {
            "category":"Sports & Exercise",
            "subcategory":"Bowling",
            "type":"Entertainment"
        }
    ],
    "sg:phone":"+1 920 794 7323",
    "sg:postcode":"54241",
    "sg:province":"WI",
    "sg:tags":[
        "drinking",
        "center"
    ],
    "wof:name":"Rudys Lanes Inc",
    "wof:placetype":"venue"
},
  "geometry": {"coordinates":[-87.568405,44.151532],"type":"Point"}
}