{
  "type": "Feature",
  "properties": {
    "addr:full":"6120 Rock Falls Rd Eau Claire WI 54701",
    "addr:housenumber":"6120",
    "addr:postcode":"54701",
    "addr:street":"Rock Falls Rd",
    "iso:country":"US",
    "sg:address":"6120 Rock Falls Rd",
    "sg:city":"Eau Claire",
    "sg:classifiers":[
        {
            "category":"Travel",
            "subcategory":"Hotels & Motels",
            "type":"Entertainment"
        }
    ],
    "sg:phone":"+1 715 835 7024",
    "sg:postcode":"54701",
    "sg:province":"WI",
    "sg:tags":[
        "operation"
    ],
    "wof:name":"Country Suites By Carlson",
    "wof:placetype":"venue"
},
  "geometry": {"coordinates":[-91.617824,44.727292],"type":"Point"}
}