{
  "type": "Feature",
  "properties": {
    "iso:country":"US",
    "sg:address":"124 Main St",
    "sg:city":"Menasha",
    "sg:classifiers":[
        {
            "category":"Restaurant",
            "type":"Food & Drink"
        }
    ],
    "sg:phone":"+1 920 725 7777",
    "sg:postcode":"54952",
    "sg:province":"WI",
    "sg:website":"www.nautslanding.com",
    "wof:name":"Naut's Landing Restaurant",
    "wof:placetype":"venue"
},
  "geometry": {"coordinates":[-88.450568,44.200279],"type":"Point"}
}