{
  "type": "Feature",
  "properties": {
    "iso:country":"US",
    "sg:address":"2000 E Cora Ave",
    "sg:city":"Milwaukee",
    "sg:classifiers":[
        {
            "category":"Bars & Pubs",
            "type":"Food & Drink"
        }
    ],
    "sg:phone":"+1 414 481 7742",
    "sg:postcode":"53235",
    "sg:province":"WI",
    "wof:name":"Gordie's",
    "wof:placetype":"venue"
},
  "geometry": {"coordinates":[-87.883376,42.978279],"type":"Point"}
}