{
  "type": "Feature",
  "properties": {
    "iso:country":"US",
    "sg:address":"3333 US Hwy 18",
    "sg:city":"Helenville",
    "sg:classifiers":[
        {
            "category":"Manufacturing",
            "subcategory":"Tools & Machinery",
            "type":"Manufacturing & Wholesale Goods"
        }
    ],
    "sg:phone":"+1 262 593 8041",
    "sg:postcode":"53137",
    "sg:province":"WI",
    "sg:tags":[
        "machine",
        "shop"
    ],
    "wof:name":"D J & R Mfg Inc",
    "wof:placetype":"venue"
},
  "geometry": {"coordinates":[-88.702254,43.012451],"type":"Point"}
}