{
  "type": "Feature",
  "properties": {
    "addr:full":"1901 Market Way Watertown WI 53094",
    "addr:housenumber":"1901",
    "addr:postcode":"53094",
    "addr:street":"Market Way",
    "iso:country":"US",
    "sg:address":"1901 Market Way",
    "sg:city":"Watertown",
    "sg:classifiers":[
        {
            "category":"Restaurant",
            "type":"Food & Drink"
        }
    ],
    "sg:menulink":"http://www.allmenus.com/wi/watertown/145798-subway/menu/",
    "sg:phone":"+1 920 261 6366",
    "sg:postcode":"53094",
    "sg:province":"WI",
    "sg:tags":[
        "american",
        "sandwich"
    ],
    "wof:name":"Subway",
    "wof:placetype":"venue"
},
  "geometry": {"coordinates":[-88.732381,43.163757],"type":"Point"}
}