{
  "type": "Feature",
  "properties": {
    "iso:country":"US",
    "sg:address":"424 N Main St",
    "sg:city":"Mayville",
    "sg:classifiers":[
        {
            "category":"Retail",
            "subcategory":"Repair Shop",
            "type":"Services"
        }
    ],
    "sg:phone":"+1 920 387 3367",
    "sg:postcode":"53050",
    "sg:province":"WI",
    "sg:tags":[
        "reupholsters",
        "upholsterer",
        "furniture"
    ],
    "wof:name":"Kamrath's Custom Upholstery",
    "wof:placetype":"venue"
},
  "geometry": {"coordinates":[-88.543761,43.501793],"type":"Point"}
}