{
  "type": "Feature",
  "properties": {
    "iso:country":"US",
    "sg:address":"12190 Badger Rd",
    "sg:city":"Ellison Bay",
    "sg:classifiers":[
        {
            "category":"Food & Beverages",
            "subcategory":"Specialty",
            "type":"Retail Goods"
        }
    ],
    "sg:phone":"+1 920 854 6131",
    "sg:postcode":"54210",
    "sg:province":"WI",
    "sg:tags":[
        "gourmet",
        "wholesale"
    ],
    "wof:name":"Great Lakes Distribution",
    "wof:placetype":"venue"
},
  "geometry": {"coordinates":[-87.051023,45.263493],"type":"Point"}
}