{
  "type": "Feature",
  "properties": {
    "iso:country":"US",
    "sg:address":"346 S Emery Ave",
    "sg:city":"Peshtigo",
    "sg:classifiers":[
        {
            "category":"Professional",
            "subcategory":"Detective & Security Services",
            "type":"Services"
        }
    ],
    "sg:phone":"+1 715 923 8381",
    "sg:postcode":"54157",
    "sg:province":"WI",
    "sg:tags":[
        "polygraph",
        "examination"
    ],
    "wof:name":"East Wscnsin Plygraph Svcs LLC",
    "wof:placetype":"venue"
},
  "geometry": {"coordinates":[-87.750861,45.049938],"type":"Point"}
}