{
  "type": "Feature",
  "properties": {
    "iso:country":"US",
    "sg:address":"264 Hansen Rd",
    "sg:city":"De Pere",
    "sg:classifiers":[
        {
            "category":"Home & Garden",
            "subcategory":"Carpets & Floor Coverings",
            "type":"Retail Goods"
        }
    ],
    "sg:phone":"+1 920 336 3246",
    "sg:postcode":"54115",
    "sg:province":"WI",
    "wof:name":"Third Floor Whores LLC",
    "wof:placetype":"venue"
},
  "geometry": {"coordinates":[-88.196622,44.415231],"type":"Point"}
}