{
  "type": "Feature",
  "properties": {
    "iso:country":"US",
    "sg:address":"4902 Pflaum Rd",
    "sg:city":"Madison",
    "sg:classifiers":[
        {
            "category":"Wholesale",
            "subcategory":"Electrical",
            "type":"Manufacturing & Wholesale Goods"
        }
    ],
    "sg:phone":"+1 608 222 8500",
    "sg:postcode":"53718",
    "sg:province":"WI",
    "sg:tags":[
        "communication",
        "radio",
        "system",
        "repair"
    ],
    "wof:name":"Evans Industrial Communication",
    "wof:placetype":"venue"
},
  "geometry": {"coordinates":[-89.29533600000001,43.062479],"type":"Point"}
}