{
  "type": "Feature",
  "properties": {
    "iso:country":"US",
    "sg:address":"6790 Milligan Rd",
    "sg:city":"Waupun",
    "sg:classifiers":[
        {
            "category":"Building & Trades",
            "subcategory":"Construction",
            "type":"Services"
        }
    ],
    "sg:phone":"+1 920 324 2134",
    "sg:postcode":"53963",
    "sg:province":"WI",
    "sg:tags":[
        "hanging",
        "contractor"
    ],
    "wof:name":"B K Painting",
    "wof:placetype":"venue"
},
  "geometry": {"coordinates":[-88.73917,43.60498],"type":"Point"}
}