{
  "type": "Feature",
  "properties": {
    "iso:country":"US",
    "sg:address":"20141 Co Hwy X",
    "sg:city":"Chippewa Falls",
    "sg:classifiers":[
        {
            "category":"Professional",
            "type":"Services"
        }
    ],
    "sg:phone":"+1 715 723 1287",
    "sg:postcode":"54729",
    "sg:province":"WI",
    "wof:name":"Cabin Gang Llc",
    "wof:placetype":"venue"
},
  "geometry": {"coordinates":[-91.266164,44.929592],"type":"Point"}
}