{
  "type": "Feature",
  "properties": {
    "addr:full":"2511 State Hwy 23 Green Lake WI 54941",
    "addr:housenumber":"2511",
    "addr:postcode":"54941",
    "addr:street":"State Hwy 23",
    "iso:country":"US",
    "sg:address":"2511 State Hwy 23",
    "sg:city":"Green Lake",
    "sg:classifiers":[
        {
            "category":"Shopping",
            "subcategory":"Books",
            "type":"Retail Goods"
        }
    ],
    "sg:phone":"+1 920 294 7394",
    "sg:postcode":"54941",
    "sg:province":"WI",
    "sg:tags":[
        "dealer"
    ],
    "wof:name":"Norwegian Bay Books & Gifts",
    "wof:placetype":"venue"
},
  "geometry": {"coordinates":[-89.010774,43.836918],"type":"Point"}
}