{
  "type": "Feature",
  "properties": {
    "addr:full":"130 N Monroe St Lancaster WI 53813",
    "addr:housenumber":"130",
    "addr:postcode":"53813",
    "addr:street":"N Monroe St",
    "iso:country":"US",
    "sg:address":"130 N Monroe St",
    "sg:city":"Lancaster",
    "sg:classifiers":[
        {
            "category":"Building & Trades",
            "subcategory":"Pest Control",
            "type":"Services"
        }
    ],
    "sg:phone":"+1 608 723 4720",
    "sg:postcode":"53813",
    "sg:province":"WI",
    "wof:name":"Orkin Exterminating Co Inc",
    "wof:placetype":"venue"
},
  "geometry": {"coordinates":[-90.708527,42.848688],"type":"Point"}
}