{
  "type": "Feature",
  "properties": {
    "iso:country":"US",
    "sg:address":"1009 4th St S",
    "sg:city":"La Crosse",
    "sg:classifiers":[
        {
            "category":"Banks & Credit Unions",
            "subcategory":"Bank",
            "type":"Services"
        }
    ],
    "sg:phone":"+1 608 782 5050",
    "sg:postcode":"54601",
    "sg:province":"WI",
    "wof:name":"River City Community CU",
    "wof:placetype":"venue"
},
  "geometry": {"coordinates":[-91.25177100000001,43.802712],"type":"Point"}
}