{
  "type": "Feature",
  "properties": {
    "addr:full":"720 N Wisconsin St Elkhorn WI 53121",
    "addr:housenumber":"720",
    "addr:postcode":"53121",
    "addr:street":"N Wisconsin St",
    "iso:country":"US",
    "sg:address":"720 N Wisconsin St",
    "sg:city":"Elkhorn",
    "sg:classifiers":[
        {
            "category":"Restaurant",
            "type":"Food & Drink"
        }
    ],
    "sg:phone":"+1 262 723 2140",
    "sg:postcode":"53121",
    "sg:province":"WI",
    "sg:tags":[
        "caterer"
    ],
    "sg:website":"www.sperinos.com",
    "wof:name":"Accustom Catering",
    "wof:placetype":"venue"
},
  "geometry": {"coordinates":[-88.543755,42.68321],"type":"Point"}
}