{
  "type": "Feature",
  "properties": {
    "iso:country":"US",
    "sg:address":"2322 1st St",
    "sg:city":"Cumberland",
    "sg:classifiers":[
        {
            "category":"Farming",
            "subcategory":"Farm",
            "type":"Manufacturing & Wholesale Goods"
        }
    ],
    "sg:phone":"+1 715 822 4275",
    "sg:postcode":"54829",
    "sg:province":"WI",
    "wof:name":"Rouzer Farms Inc",
    "wof:placetype":"venue"
},
  "geometry": {"coordinates":[-92.133683,45.543333],"type":"Point"}
}