{
  "type": "Feature",
  "properties": {
    "iso:country":"US",
    "sg:address":"532 E Milwaukee St",
    "sg:city":"Whitewater",
    "sg:classifiers":[
        {
            "category":"Building & Trades",
            "subcategory":"Plumbing",
            "type":"Services"
        }
    ],
    "sg:phone":"+1 262 495 2590",
    "sg:postcode":"53190",
    "sg:province":"WI",
    "sg:tags":[
        "conditioning",
        "air",
        "system",
        "contractor"
    ],
    "sg:website":"www.tenaska.com",
    "wof:name":"Reynolds Heating AC & Refrig",
    "wof:placetype":"venue"
},
  "geometry": {"coordinates":[-88.72206300000001,42.832757],"type":"Point"}
}