{
  "type": "Feature",
  "properties": {
    "iso:country":"US",
    "sg:address":"2348 N 57th St",
    "sg:city":"Milwaukee",
    "sg:classifiers":[
        {
            "category":"Professional",
            "type":"Services"
        }
    ],
    "sg:phone":"+1 414 444 4564",
    "sg:postcode":"53210",
    "sg:province":"WI",
    "wof:name":"Shades Of Gray",
    "wof:placetype":"venue"
},
  "geometry": {"coordinates":[-87.984098,43.061618],"type":"Point"}
}