{
  "type": "Feature",
  "properties": {
    "iso:country":"US",
    "sg:address":"2950 S Chase Ave",
    "sg:city":"Milwaukee",
    "sg:classifiers":[
        {
            "category":"Utilities",
            "subcategory":"Mobile Phone",
            "type":"Services"
        }
    ],
    "sg:phone":"+1 414 483 2000",
    "sg:postcode":"53207",
    "sg:province":"WI",
    "sg:tags":[
        "wireless",
        "communication"
    ],
    "sg:website":"http://clickserve.dartsearch.net/link/click?lid=43000000308049899",
    "wof:name":"T-Mobile",
    "wof:placetype":"venue"
},
  "geometry": {"coordinates":[-87.909352,42.990646],"type":"Point"}
}