{
  "type": "Feature",
  "properties": {
    "iso:country":"US",
    "sg:address":"3734 N 85th St",
    "sg:city":"Milwaukee",
    "sg:classifiers":[
        {
            "category":"Professional",
            "subcategory":"Art Services",
            "type":"Services"
        }
    ],
    "sg:phone":"+1 414 464 9743",
    "sg:postcode":"53222",
    "sg:province":"WI",
    "sg:tags":[
        "commercial",
        "design"
    ],
    "wof:name":"Kolter Creative",
    "wof:placetype":"venue"
},
  "geometry": {"coordinates":[-88.01880300000001,43.085505],"type":"Point"}
}