{
  "type": "Feature",
  "properties": {
    "addr:full":"116 Main St Cornell WI 54732",
    "addr:housenumber":"116",
    "addr:postcode":"54732",
    "addr:street":"Main St",
    "iso:country":"US",
    "sg:address":"116 Main St",
    "sg:city":"Cornell",
    "sg:classifiers":[
        {
            "category":"Bars & Pubs",
            "type":"Food & Drink"
        }
    ],
    "sg:phone":"+1 715 239 0421",
    "sg:postcode":"54732",
    "sg:province":"WI",
    "wof:name":"Turany Turk",
    "wof:placetype":"venue"
},
  "geometry": {"coordinates":[-91.151735,45.16742],"type":"Point"}
}