{
  "type": "Feature",
  "properties": {
    "addr:full":"18770 Ventura Cir Brookfield WI 53045",
    "addr:housenumber":"18770",
    "addr:postcode":"53045",
    "addr:street":"Ventura Cir",
    "iso:country":"US",
    "sg:address":"18770 Ventura Cir",
    "sg:city":"Brookfield",
    "sg:classifiers":[
        {
            "category":"Manufacturing",
            "subcategory":"Printing",
            "type":"Manufacturing & Wholesale Goods"
        }
    ],
    "sg:phone":"+1 262 781 6161",
    "sg:postcode":"53045",
    "sg:province":"WI",
    "sg:tags":[
        "lithographic",
        "printer",
        "commercial"
    ],
    "wof:name":"Barrette Printing Service",
    "wof:placetype":"venue"
},
  "geometry": {"coordinates":[-88.14524900000001,43.086751],"type":"Point"}
}