{
  "type": "Feature",
  "properties": {
    "iso:country":"US",
    "sg:address":"1010 S Park St",
    "sg:city":"Madison",
    "sg:classifiers":[
        {
            "category":"Manufacturing",
            "subcategory":"Food",
            "type":"Manufacturing & Wholesale Goods"
        }
    ],
    "sg:phone":"+1 608 257 1006",
    "sg:postcode":"53715",
    "sg:province":"WI",
    "sg:tags":[
        "product",
        "mfg",
        "dairy",
        "milk",
        "fluid"
    ],
    "wof:name":"Morningstar Foods",
    "wof:placetype":"venue"
},
  "geometry": {"coordinates":[-89.398319,43.056191],"type":"Point"}
}