{
  "type": "Feature",
  "properties": {
    "iso:country":"US",
    "sg:address":"3573 State Hwy 80",
    "sg:city":"Pittsville",
    "sg:classifiers":[
        {
            "category":"Retail",
            "subcategory":"Repair Shop",
            "type":"Services"
        }
    ],
    "sg:phone":"+1 715 884 2954",
    "sg:postcode":"54466",
    "sg:province":"WI",
    "sg:tags":[
        "snowmobile",
        "maintenance"
    ],
    "wof:name":"Parts Place",
    "wof:placetype":"venue"
},
  "geometry": {"coordinates":[-90.111169,44.376129],"type":"Point"}
}