{
  "type": "Feature",
  "properties": {
    "addr:full":"108 Janesville St Oregon WI 53575",
    "addr:housenumber":"108",
    "addr:postcode":"53575",
    "addr:street":"Janesville St",
    "iso:country":"US",
    "sg:address":"108 Janesville St",
    "sg:city":"Oregon",
    "sg:classifiers":[
        {
            "category":"Personal",
            "subcategory":"Beauty Salon",
            "type":"Services"
        }
    ],
    "sg:phone":"+1 608 835 0682",
    "sg:postcode":"53575",
    "sg:province":"WI",
    "wof:name":"Sache' Salon & Spa",
    "wof:placetype":"venue"
},
  "geometry": {"coordinates":[-89.383501,42.925346],"type":"Point"}
}