{
  "type": "Feature",
  "properties": {
    "iso:country":"US",
    "sg:address":"6520 N 76th St",
    "sg:city":"Milwaukee",
    "sg:classifiers":[
        {
            "category":"Shopping",
            "subcategory":"Clothing, Apparel, & Fashions",
            "type":"Retail Goods"
        }
    ],
    "sg:phone":"+1 414 760 8580",
    "sg:postcode":"53223",
    "sg:province":"WI",
    "wof:name":"Womens World",
    "wof:placetype":"venue"
},
  "geometry": {"coordinates":[-88.005616,43.137341],"type":"Point"}
}