{
  "type": "Feature",
  "properties": {
    "addr:full":"619 Lime Kiln Rd Green Bay WI 54302",
    "addr:housenumber":"619",
    "addr:postcode":"54302",
    "addr:street":"Lime Kiln Rd",
    "iso:country":"US",
    "sg:address":"619 Lime Kiln Rd",
    "sg:city":"Green Bay",
    "sg:phone":"+1 920 469 3192",
    "sg:postcode":"54302",
    "sg:province":"WI",
    "sg:tags":[
        "equipment",
        "commercial"
    ],
    "wof:name":"Stingers Pub",
    "wof:placetype":"venue"
},
  "geometry": {"coordinates":[-87.97741499999999,44.492927],"type":"Point"}
}