{
  "type": "Feature",
  "properties": {
    "iso:country":"US",
    "sg:address":"1872 Alpine Rd",
    "sg:city":"Marathon",
    "sg:classifiers":[
        {
            "category":"Farming",
            "subcategory":"Dairy Farm",
            "type":"Manufacturing & Wholesale Goods"
        }
    ],
    "sg:phone":"+1 715 443 3249",
    "sg:postcode":"54448",
    "sg:province":"WI",
    "wof:name":"Randy Beilke Farm",
    "wof:placetype":"venue"
},
  "geometry": {"coordinates":[-89.789699,44.887122],"type":"Point"}
}