{
  "type": "Feature",
  "properties": {
    "iso:country":"US",
    "sg:address":"2619 N 9th St",
    "sg:city":"Milwaukee",
    "sg:classifiers":[
        {
            "category":"Personal",
            "subcategory":"Beauty Salon",
            "type":"Services"
        }
    ],
    "sg:phone":"+1 414 372 9770",
    "sg:postcode":"53206",
    "sg:province":"WI",
    "sg:tags":[
        "shop"
    ],
    "wof:name":"Octavias Nails",
    "wof:placetype":"venue"
},
  "geometry": {"coordinates":[-87.92273900000001,43.067282],"type":"Point"}
}