{
  "type": "Feature",
  "properties": {
    "iso:country":"US",
    "sg:address":"621 Science Dr",
    "sg:city":"Madison",
    "sg:classifiers":[
        {
            "category":"Health Services",
            "subcategory":"Doctor",
            "type":"Services"
        }
    ],
    "sg:phone":"+1 608 265 8400",
    "sg:postcode":"53711",
    "sg:province":"WI",
    "sg:tags":[
        "physician",
        "surgeon"
    ],
    "wof:name":"Research Park Family Medicine",
    "wof:placetype":"venue"
},
  "geometry": {"coordinates":[-89.470559,43.055153],"type":"Point"}
}