{
  "type": "Feature",
  "properties": {
    "iso:country":"US",
    "sg:address":"1550 US Hwy 41",
    "sg:city":"De Pere",
    "sg:classifiers":[
        {
            "category":"Building & Trades",
            "subcategory":"Plumbing",
            "type":"Services"
        }
    ],
    "sg:phone":"+1 920 336 7112",
    "sg:postcode":"54115",
    "sg:province":"WI",
    "sg:tags":[
        "air",
        "ventilation",
        "work",
        "conditioning",
        "heating"
    ],
    "wof:name":"Comfort Control Systems Inc",
    "wof:placetype":"venue"
},
  "geometry": {"coordinates":[-88.106343,44.434527],"type":"Point"}
}