{
  "type": "Feature",
  "properties": {
    "iso:country":"US",
    "sg:address":"55 Dam Rd",
    "sg:city":"Wisconsin Dells",
    "sg:classifiers":[
        {
            "category":"Travel",
            "subcategory":"Hotels & Motels",
            "type":"Entertainment"
        }
    ],
    "sg:phone":"+1 608 254 8553",
    "sg:postcode":"53965",
    "sg:province":"WI",
    "sg:tags":[
        "resort",
        "operation"
    ],
    "wof:name":"Sandy Lingen's Beach Resort",
    "wof:placetype":"venue"
},
  "geometry": {"coordinates":[-89.767437,43.601905],"type":"Point"}
}