{
  "type": "Feature",
  "properties": {
    "addr:full":"2663 River Rd Fountain City WI 54629",
    "addr:housenumber":"2663",
    "addr:postcode":"54629",
    "addr:street":"River Rd",
    "iso:country":"US",
    "sg:address":"2663 River Rd",
    "sg:city":"Fountain City",
    "sg:classifiers":[
        {
            "category":"Farming",
            "subcategory":"Dairy Farm",
            "type":"Manufacturing & Wholesale Goods"
        }
    ],
    "sg:phone":"+1 608 687 8459",
    "sg:postcode":"54629",
    "sg:province":"WI",
    "wof:name":"Don Doelle",
    "wof:placetype":"venue"
},
  "geometry": {"coordinates":[-91.619832,44.190559],"type":"Point"}
}