{
  "type": "Feature",
  "properties": {
    "addr:full":"8411 Elm Rd Mount Calvary WI 53057",
    "addr:housenumber":"8411",
    "addr:postcode":"53057",
    "addr:street":"Elm Rd",
    "iso:country":"US",
    "sg:address":"8411 Elm Rd",
    "sg:city":"Mount Calvary",
    "sg:classifiers":[
        {
            "category":"Farming",
            "subcategory":"Dairy Farm",
            "type":"Manufacturing & Wholesale Goods"
        }
    ],
    "sg:phone":"+1 920 753 4235",
    "sg:postcode":"53057",
    "sg:province":"WI",
    "wof:name":"Leo Steffes",
    "wof:placetype":"venue"
},
  "geometry": {"coordinates":[-88.257034,43.847459],"type":"Point"}
}