{
  "type": "Feature",
  "properties": {
    "iso:country":"US",
    "sg:address":"6227 Co Rd D",
    "sg:city":"Brooklyn",
    "sg:classifiers":[
        {
            "category":"Manufacturing",
            "subcategory":"Retail Goods",
            "type":"Manufacturing & Wholesale Goods"
        }
    ],
    "sg:phone":"+1 608 835 8682",
    "sg:postcode":"53521",
    "sg:province":"WI",
    "sg:tags":[
        "product",
        "mfg"
    ],
    "wof:name":"Rlk Industries LLC",
    "wof:placetype":"venue"
},
  "geometry": {"coordinates":[-89.48056200000001,42.899863],"type":"Point"}
}