{
  "type": "Feature",
  "properties": {
    "iso:country":"US",
    "sg:address":"4025 N 124th St",
    "sg:city":"Brookfield",
    "sg:classifiers":[
        {
            "category":"Autos & Motor Vehicles",
            "subcategory":"Auto Supplies",
            "type":"Retail Goods"
        }
    ],
    "sg:phone":"+1 262 790 9170",
    "sg:postcode":"53005",
    "sg:province":"WI",
    "sg:tags":[
        "automobile",
        "parts"
    ],
    "wof:name":"Truck Outfitters Of Brookfield",
    "wof:placetype":"venue"
},
  "geometry": {"coordinates":[-88.06641399999999,43.088984],"type":"Point"}
}