{
  "type": "Feature",
  "properties": {
    "iso:country":"US",
    "sg:address":"401 2nd St",
    "sg:city":"Algoma",
    "sg:classifiers":[
        {
            "category":"Bars & Pubs",
            "type":"Food & Drink"
        }
    ],
    "sg:phone":"+1 920 487 2721",
    "sg:postcode":"54201",
    "sg:province":"WI",
    "sg:tags":[
        "drinking",
        "center",
        "bowling"
    ],
    "wof:name":"Algoma Pizza Bowl",
    "wof:placetype":"venue"
},
  "geometry": {"coordinates":[-87.43622999999999,44.609562],"type":"Point"}
}