{
  "type": "Feature",
  "properties": {
    "iso:country":"US",
    "sg:address":"1119 Marshall St",
    "sg:city":"Manitowoc",
    "sg:classifiers":[
        {
            "category":"Personal",
            "subcategory":"Beauty Salon",
            "type":"Services"
        }
    ],
    "sg:phone":"+1 920 682 1793",
    "sg:postcode":"54220",
    "sg:province":"WI",
    "sg:tags":[
        "shop"
    ],
    "wof:name":"KURL Up N Dye",
    "wof:placetype":"venue"
},
  "geometry": {"coordinates":[-87.66315899999999,44.087108],"type":"Point"}
}