{
  "type": "Feature",
  "properties": {
    "iso:country":"US",
    "sg:address":"1904 Dixie Dr",
    "sg:city":"Waukesha",
    "sg:classifiers":[
        {
            "category":"Professional",
            "subcategory":"Computer Services",
            "type":"Services"
        }
    ],
    "sg:phone":"+1 262 547 0799",
    "sg:postcode":"53189",
    "sg:province":"WI",
    "sg:tags":[
        "datum"
    ],
    "wof:name":"David Ellis",
    "wof:placetype":"venue"
},
  "geometry": {"coordinates":[-88.25059299999999,42.978851],"type":"Point"}
}