{
  "type": "Feature",
  "properties": {
    "iso:country":"US",
    "sg:address":"13353 N Murphy Blvd",
    "sg:city":"Hayward",
    "sg:classifiers":[
        {
            "category":"Retail",
            "subcategory":"Animal Services",
            "type":"Services"
        }
    ],
    "sg:phone":"+1 715 462 3037",
    "sg:postcode":"54843",
    "sg:province":"WI",
    "sg:tags":[
        "pet",
        "boarding",
        "sitting"
    ],
    "wof:name":"Canine Cottage",
    "wof:placetype":"venue"
},
  "geometry": {"coordinates":[-91.234048,46.105197],"type":"Point"}
}