{
  "type": "Feature",
  "properties": {
    "iso:country":"US",
    "sg:address":"900 Uniek Dr",
    "sg:city":"Waunakee",
    "sg:classifiers":[
        {
            "category":"Freight",
            "type":"Transportation"
        }
    ],
    "sg:phone":"+1 608 849 6371",
    "sg:postcode":"53597",
    "sg:province":"WI",
    "sg:tags":[
        "carrier",
        "common",
        "contract"
    ],
    "wof:name":"Madison Freight Systems Inc",
    "wof:placetype":"venue"
},
  "geometry": {"coordinates":[-89.436904,43.182328],"type":"Point"}
}