{
  "type": "Feature",
  "properties": {
    "iso:country":"US",
    "sg:address":"249 Grant St",
    "sg:city":"Glidden",
    "sg:classifiers":[
        {
            "category":"Restaurant",
            "type":"Food & Drink"
        }
    ],
    "sg:phone":"+1 715 264 2500",
    "sg:postcode":"54527",
    "sg:province":"WI",
    "wof:name":"Hometown Cafe",
    "wof:placetype":"venue"
},
  "geometry": {"coordinates":[-90.58202900000001,46.13342],"type":"Point"}
}