{
  "type": "Feature",
  "properties": {
    "addr:full":"2491 S Superior St Milwaukee WI 53207",
    "addr:housenumber":"2491",
    "addr:postcode":"53207",
    "addr:street":"S Superior St",
    "iso:country":"US",
    "sg:address":"2491 S Superior St",
    "sg:city":"Milwaukee",
    "sg:classifiers":[
        {
            "category":"Bars & Pubs",
            "type":"Food & Drink"
        }
    ],
    "sg:phone":"+1 414 747 1007",
    "sg:postcode":"53207",
    "sg:province":"WI",
    "wof:name":"Palomino",
    "wof:placetype":"venue"
},
  "geometry": {"coordinates":[-87.890787,42.999956],"type":"Point"}
}