{
  "type": "Feature",
  "properties": {
    "iso:country":"US",
    "sg:address":"5163 Shellamie Rd",
    "sg:city":"Eau Claire",
    "sg:classifiers":[
        {
            "category":"Professional",
            "type":"Services"
        }
    ],
    "sg:phone":"+1 715 835 7496",
    "sg:postcode":"54701",
    "sg:province":"WI",
    "wof:name":"McGrouarys Inc",
    "wof:placetype":"venue"
},
  "geometry": {"coordinates":[-91.451715,44.761027],"type":"Point"}
}