{
  "type": "Feature",
  "properties": {
    "iso:country":"US",
    "sg:address":"1082 Honeysuckle Ln",
    "sg:city":"Neenah",
    "sg:classifiers":[
        {
            "category":"Mining & Drilling",
            "type":"Manufacturing & Wholesale Goods"
        }
    ],
    "sg:phone":"+1 920 751 0152",
    "sg:postcode":"54956",
    "sg:province":"WI",
    "sg:tags":[
        "field"
    ],
    "wof:name":"Neenah Wscnsin Rdon Specialist",
    "wof:placetype":"venue"
},
  "geometry": {"coordinates":[-88.491595,44.169824],"type":"Point"}
}