{
  "type": "Feature",
  "properties": {
    "iso:country":"US",
    "sg:address":"1701 Laurel Ave",
    "sg:city":"Hudson",
    "sg:classifiers":[
        {
            "category":"Professional",
            "subcategory":"Business Services",
            "type":"Services"
        }
    ],
    "sg:phone":"+1 715 381 5602",
    "sg:postcode":"54016",
    "sg:province":"WI",
    "wof:name":"Riverwood Real Estate Group",
    "wof:placetype":"venue"
},
  "geometry": {"coordinates":[-92.73209300000001,44.968531],"type":"Point"}
}