{
  "type": "Feature",
  "properties": {
    "iso:country":"US",
    "sg:address":"1201 N 35th St",
    "sg:city":"Milwaukee",
    "sg:classifiers":[
        {
            "category":"Shopping",
            "subcategory":"Shoes",
            "type":"Retail Goods"
        }
    ],
    "sg:phone":"+1 414 931 7500",
    "sg:postcode":"53208",
    "sg:province":"WI",
    "sg:tags":[
        "shoe",
        "store"
    ],
    "wof:name":"Payless Shoe Source",
    "wof:placetype":"venue"
},
  "geometry": {"coordinates":[-87.95774900000001,43.043948],"type":"Point"}
}