{
  "type": "Feature",
  "properties": {
    "iso:country":"US",
    "sg:address":"798 US Hwy 51",
    "sg:city":"Stoughton",
    "sg:classifiers":[
        {
            "category":"Health Services",
            "subcategory":"Chiropractor",
            "type":"Services"
        }
    ],
    "sg:phone":"+1 608 873 8113",
    "sg:postcode":"53589",
    "sg:province":"WI",
    "sg:website":"www.zelmchiropractic.com",
    "wof:name":"Zelm Chiropractic Ctr",
    "wof:placetype":"venue"
},
  "geometry": {"coordinates":[-89.21243699999999,42.91851],"type":"Point"}
}