{
  "type": "Feature",
  "properties": {
    "iso:country":"US",
    "sg:address":"214 W Warren St",
    "sg:city":"Roberts",
    "sg:classifiers":[
        {
            "category":"Retail",
            "subcategory":"Repair Shop",
            "type":"Services"
        }
    ],
    "sg:phone":"+1 715 749 3929",
    "sg:postcode":"54023",
    "sg:province":"WI",
    "wof:name":"Upholstery Village",
    "wof:placetype":"venue"
},
  "geometry": {"coordinates":[-92.556301,44.982622],"type":"Point"}
}