{
  "type": "Feature",
  "properties": {
    "iso:country":"US",
    "sg:address":"1937 E John St",
    "sg:city":"Appleton",
    "sg:classifiers":[
        {
            "category":"Bars & Pubs",
            "type":"Food & Drink"
        }
    ],
    "sg:phone":"+1 920 731 1265",
    "sg:postcode":"54915",
    "sg:province":"WI",
    "sg:tags":[
        "drinking"
    ],
    "wof:name":"Hank & Karen's Tavern",
    "wof:placetype":"venue"
},
  "geometry": {"coordinates":[-88.37348,44.24958],"type":"Point"}
}