{
  "type": "Feature",
  "properties": {
    "iso:country":"US",
    "sg:address":"625 S Dousman St",
    "sg:city":"Prairie Du Chien",
    "sg:classifiers":[
        {
            "category":"Organizations",
            "subcategory":"Religious Organization",
            "type":"Services"
        }
    ],
    "sg:phone":"+1 608 326 8321",
    "sg:postcode":"53821",
    "sg:province":"WI",
    "sg:tags":[
        "church"
    ],
    "wof:name":"United Methodist Church",
    "wof:placetype":"venue"
},
  "geometry": {"coordinates":[-91.138166,43.044986],"type":"Point"}
}