{
  "type": "Feature",
  "properties": {
    "iso:country":"US",
    "sg:address":"19332 Church Rd",
    "sg:city":"Union Grove",
    "sg:classifiers":[
        {
            "category":"Professional",
            "subcategory":"Management & Consulting",
            "type":"Services"
        }
    ],
    "sg:phone":"+1 262 884 9153",
    "sg:postcode":"53182",
    "sg:province":"WI",
    "sg:tags":[
        "consultant",
        "invention",
        "broker"
    ],
    "wof:name":"Franksville Investments",
    "wof:placetype":"venue"
},
  "geometry": {"coordinates":[-88.052256,42.713348],"type":"Point"}
}