{
  "type": "Feature",
  "properties": {
    "iso:country":"US",
    "sg:address":"925 Burning Wood Way",
    "sg:city":"Madison",
    "sg:classifiers":[
        {
            "category":"Retail",
            "subcategory":"Animal Services",
            "type":"Services"
        }
    ],
    "sg:phone":"+1 608 221 1955",
    "sg:postcode":"53704",
    "sg:province":"WI",
    "sg:tags":[
        "pet",
        "boarding",
        "sitting"
    ],
    "wof:name":"Badger Kennel Club Inc",
    "wof:placetype":"venue"
},
  "geometry": {"coordinates":[-89.38124999999999,43.155307],"type":"Point"}
}