{
  "type": "Feature",
  "properties": {
    "addr:full":"8050 N Mountain Rd Wausau WI 54401",
    "addr:housenumber":"8050",
    "addr:postcode":"54401",
    "addr:street":"N Mountain Rd",
    "iso:country":"US",
    "sg:address":"8050 N Mountain Rd",
    "sg:city":"Wausau",
    "sg:classifiers":[
        {
            "category":"Retail",
            "subcategory":"Auto Repair",
            "type":"Services"
        }
    ],
    "sg:phone":"+1 715 845 3058",
    "sg:postcode":"54401",
    "sg:province":"WI",
    "sg:tags":[
        "body"
    ],
    "wof:name":"Dicks Auto Body",
    "wof:placetype":"venue"
},
  "geometry": {"coordinates":[-89.74568600000001,44.938077],"type":"Point"}
}