{
  "type": "Feature",
  "properties": {
    "iso:country":"US",
    "sg:address":"100 Calvary St",
    "sg:city":"Mt Calvary",
    "sg:classifiers":[
        {
            "category":"Health Services",
            "subcategory":"Doctor",
            "type":"Services"
        }
    ],
    "sg:phone":"+1 920 753 2311",
    "sg:postcode":"53057",
    "sg:province":"WI",
    "sg:tags":[
        "physician",
        "surgeon"
    ],
    "wof:name":"Mt Calvary Clinic",
    "wof:placetype":"venue"
},
  "geometry": {"coordinates":[-88.24181,43.827251],"type":"Point"}
}