{
  "type": "Feature",
  "properties": {
    "addr:full":"1810 Crest View Dr Hudson WI 54016",
    "addr:housenumber":"1810",
    "addr:postcode":"54016",
    "addr:street":"Crest View Dr",
    "iso:country":"US",
    "sg:address":"1810 Crest View Dr",
    "sg:city":"Hudson",
    "sg:classifiers":[
        {
            "category":"Professional",
            "subcategory":"Business Services",
            "type":"Services"
        }
    ],
    "sg:phone":"+1 715 381 6900",
    "sg:postcode":"54016",
    "sg:province":"WI",
    "sg:tags":[
        "interior",
        "consultant",
        "design",
        "decorator"
    ],
    "wof:name":"Sandra Kettering Interior Dsgn",
    "wof:placetype":"venue"
},
  "geometry": {"coordinates":[-92.73577299999999,44.962554],"type":"Point"}
}