{
  "type": "Feature",
  "properties": {
    "iso:country":"US",
    "sg:address":"3403 Main St",
    "sg:city":"Stevens Point",
    "sg:classifiers":[
        {
            "category":"Retail",
            "subcategory":"Laundry & Dry Cleaning",
            "type":"Services"
        }
    ],
    "sg:phone":"+1 715 342 1930",
    "sg:postcode":"54481",
    "sg:province":"WI",
    "sg:tags":[
        "garment",
        "agent"
    ],
    "wof:name":"Hangers Cleaners",
    "wof:placetype":"venue"
},
  "geometry": {"coordinates":[-89.555409,44.523169],"type":"Point"}
}