{
  "type": "Feature",
  "properties": {
    "addr:full":"1510 Bellevue St Green Bay WI 54311",
    "addr:housenumber":"1510",
    "addr:postcode":"54311",
    "addr:street":"Bellevue St",
    "iso:country":"US",
    "sg:address":"1510 Bellevue St",
    "sg:city":"Green Bay",
    "sg:classifiers":[
        {
            "category":"Social Services",
            "subcategory":"Child Care",
            "type":"Services"
        }
    ],
    "sg:phone":"+1 920 468 6503",
    "sg:postcode":"54311",
    "sg:province":"WI",
    "sg:tags":[
        "day"
    ],
    "wof:name":"Bellevue Childrens World",
    "wof:placetype":"venue"
},
  "geometry": {"coordinates":[-87.99991900000001,44.474195],"type":"Point"}
}