{
  "type": "Feature",
  "properties": {
    "addr:full":"5021 Pine Rd Cedarburg WI 53012",
    "addr:housenumber":"5021",
    "addr:postcode":"53012",
    "addr:street":"Pine Rd",
    "iso:country":"US",
    "sg:address":"5021 Pine Rd",
    "sg:city":"Cedarburg",
    "sg:classifiers":[
        {
            "category":"Professional",
            "subcategory":"Engineering",
            "type":"Services"
        }
    ],
    "sg:phone":"+1 262 376 5080",
    "sg:postcode":"53012",
    "sg:province":"WI",
    "sg:tags":[
        "engineer"
    ],
    "wof:name":"MWH",
    "wof:placetype":"venue"
},
  "geometry": {"coordinates":[-87.97295699999999,43.303368],"type":"Point"}
}