{
  "type": "Feature",
  "properties": {
    "iso:country":"US",
    "sg:address":"6567 N 85th St",
    "sg:city":"Milwaukee",
    "sg:classifiers":[
        {
            "category":"Building & Trades",
            "subcategory":"Construction",
            "type":"Services"
        }
    ],
    "sg:phone":"+1 414 353 0367",
    "sg:postcode":"53224",
    "sg:province":"WI",
    "sg:tags":[
        "contractor"
    ],
    "wof:name":"Waynes Construction Inc",
    "wof:placetype":"venue"
},
  "geometry": {"coordinates":[-88.01784600000001,43.137262],"type":"Point"}
}