{
  "type": "Feature",
  "properties": {
    "iso:country":"US",
    "sg:address":"917 Lone Tree Ln",
    "sg:city":"Prairie Du Sac",
    "sg:classifiers":[
        {
            "category":"Travel",
            "subcategory":"Hotels & Motels",
            "type":"Entertainment"
        }
    ],
    "sg:phone":"+1 608 644 1151",
    "sg:postcode":"53578",
    "sg:province":"WI",
    "sg:tags":[
        "operation"
    ],
    "wof:name":"Midwest Inn Crowd LLC",
    "wof:placetype":"venue"
},
  "geometry": {"coordinates":[-89.72946,43.29112],"type":"Point"}
}