{
  "type": "Feature",
  "properties": {
    "iso:country":"US",
    "sg:address":"16513 State Hwy 64",
    "sg:city":"Gilman",
    "sg:classifiers":[
        {
            "category":"Farming",
            "subcategory":"Dairy Farm",
            "type":"Manufacturing & Wholesale Goods"
        }
    ],
    "sg:phone":"+1 715 447 5487",
    "sg:postcode":"54433",
    "sg:province":"WI",
    "wof:name":"Goebel Farm",
    "wof:placetype":"venue"
},
  "geometry": {"coordinates":[-90.90309499999999,45.162752],"type":"Point"}
}