{
  "type": "Feature",
  "properties": {
    "iso:country":"US",
    "sg:address":"3317 13th Pl",
    "sg:city":"Kenosha",
    "sg:classifiers":[
        {
            "category":"Real Estate",
            "subcategory":"Real Estate Operator",
            "type":"Services"
        }
    ],
    "sg:phone":"+1 262 553 2194",
    "sg:postcode":"53144",
    "sg:province":"WI",
    "sg:tags":[
        "apartment"
    ],
    "wof:name":"Wisconsin Apartment Group LLC",
    "wof:placetype":"venue"
},
  "geometry": {"coordinates":[-87.85028,42.634808],"type":"Point"}
}