{
  "type": "Feature",
  "properties": {
    "iso:country":"US",
    "sg:address":"2634 W Vliet St",
    "sg:city":"Milwaukee",
    "sg:classifiers":[
        {
            "category":"Professional",
            "subcategory":"Business Services",
            "type":"Services"
        }
    ],
    "sg:phone":"+1 414 344 7478",
    "sg:postcode":"53205",
    "sg:province":"WI",
    "wof:name":"Christian Civil Liberty Union",
    "wof:placetype":"venue"
},
  "geometry": {"coordinates":[-87.947304,43.048719],"type":"Point"}
}