{
  "type": "Feature",
  "properties": {
    "iso:country":"US",
    "sg:address":"8755 N Port Washington Rd",
    "sg:city":"Milwaukee",
    "sg:classifiers":[
        {
            "category":"Food & Beverages",
            "subcategory":"Groceries & Convenience Stores",
            "type":"Retail Goods"
        }
    ],
    "sg:phone":"+1 414 228 8766",
    "sg:postcode":"53217",
    "sg:province":"WI",
    "sg:tags":[
        "grocer"
    ],
    "wof:name":"Kohl's Food Stores",
    "wof:placetype":"venue"
},
  "geometry": {"coordinates":[-87.912662,43.17374],"type":"Point"}
}