{
  "type": "Feature",
  "properties": {
    "iso:country":"US",
    "sg:address":"305 Lake St",
    "sg:city":"Florence",
    "sg:classifiers":[
        {
            "category":"Building & Trades",
            "subcategory":"Construction",
            "type":"Services"
        }
    ],
    "sg:phone":"+1 715 528 5202",
    "sg:postcode":"54121",
    "sg:province":"WI",
    "sg:tags":[
        "laying",
        "floor",
        "co",
        "contractor"
    ],
    "wof:name":"Rice Construction",
    "wof:placetype":"venue"
},
  "geometry": {"coordinates":[-88.24469,45.910991],"type":"Point"}
}