{
  "type": "Feature",
  "properties": {
    "iso:country":"US",
    "sg:address":"1016 New Haven Cir",
    "sg:city":"Sun Prairie",
    "sg:classifiers":[
        {
            "category":"Professional",
            "subcategory":"Management & Consulting",
            "type":"Services"
        }
    ],
    "sg:phone":"+1 608 825 9750",
    "sg:postcode":"53590",
    "sg:province":"WI",
    "sg:tags":[
        "business"
    ],
    "wof:name":"Winning Edge",
    "wof:placetype":"venue"
},
  "geometry": {"coordinates":[-89.243609,43.194694],"type":"Point"}
}