{
  "type": "Feature",
  "properties": {
    "iso:country":"US",
    "sg:address":"5448 Woodland St",
    "sg:city":"Stevens Point",
    "sg:classifiers":[
        {
            "category":"Shopping",
            "subcategory":"Clothing, Apparel, & Fashions",
            "type":"Retail Goods"
        }
    ],
    "sg:phone":"+1 715 344 9552",
    "sg:postcode":"54481",
    "sg:province":"WI",
    "sg:tags":[
        "alteration"
    ],
    "wof:name":"Fashioned By Design",
    "wof:placetype":"venue"
},
  "geometry": {"coordinates":[-89.517072,44.526086],"type":"Point"}
}