{
  "type": "Feature",
  "properties": {
    "iso:country":"US",
    "sg:address":"307 N Lincoln St",
    "sg:city":"Elkhorn",
    "sg:classifiers":[
        {
            "category":"Real Estate",
            "subcategory":"Developer",
            "type":"Services"
        }
    ],
    "sg:phone":"+1 262 723 4211",
    "sg:postcode":"53121",
    "sg:province":"WI",
    "sg:tags":[
        "cemetery",
        "association"
    ],
    "wof:name":"Elkhorn Cemetery Association",
    "wof:placetype":"venue"
},
  "geometry": {"coordinates":[-88.541315,42.678574],"type":"Point"}
}