{
  "type": "Feature",
  "properties": {
    "iso:country":"US",
    "sg:address":"210 Lewis St",
    "sg:city":"River Falls",
    "sg:classifiers":[
        {
            "category":"Social Services",
            "type":"Services"
        }
    ],
    "sg:phone":"+1 715 425 9932",
    "sg:postcode":"54022",
    "sg:province":"WI",
    "wof:name":"Senior Citizens Center",
    "wof:placetype":"venue"
},
  "geometry": {"coordinates":[-92.627925,44.860631],"type":"Point"}
}