{
  "type": "Feature",
  "properties": {
    "iso:country":"US",
    "sg:address":"22226 Glodowski Rd",
    "sg:city":"Arcadia",
    "sg:classifiers":[
        {
            "category":"Farming",
            "subcategory":"Dairy Farm",
            "type":"Manufacturing & Wholesale Goods"
        }
    ],
    "sg:phone":"+1 608 539 5552",
    "sg:postcode":"54612",
    "sg:province":"WI",
    "wof:name":"Michael J Waletzki",
    "wof:placetype":"venue"
},
  "geometry": {"coordinates":[-91.517867,44.162996],"type":"Point"}
}