{
  "type": "Feature",
  "properties": {
    "iso:country":"US",
    "sg:address":"4214 Maryland Ave",
    "sg:city":"Racine",
    "sg:classifiers":[
        {
            "category":"Professional",
            "type":"Services"
        }
    ],
    "sg:phone":"+1 262 554 3256",
    "sg:postcode":"53405",
    "sg:province":"WI",
    "wof:name":"Excel Service Corp Of N Amer",
    "wof:placetype":"venue"
},
  "geometry": {"coordinates":[-87.8302,42.69331],"type":"Point"}
}