{
  "type": "Feature",
  "properties": {
    "iso:country":"US",
    "sg:address":"3670 Co Rd Y",
    "sg:city":"Eau Galle",
    "sg:classifiers":[
        {
            "category":"Government",
            "subcategory":"Office",
            "type":"Public Place"
        }
    ],
    "sg:phone":"+1 715 283 4343",
    "sg:postcode":"54737",
    "sg:province":"WI",
    "wof:name":"Highway Shop",
    "wof:placetype":"venue"
},
  "geometry": {"coordinates":[-91.975815,44.70567],"type":"Point"}
}