{
  "type": "Feature",
  "properties": {
    "iso:country":"US",
    "sg:address":"1598 Woodlawn Dr",
    "sg:city":"Fort Atkinson",
    "sg:classifiers":[
        {
            "category":"Building & Trades",
            "subcategory":"Construction",
            "type":"Services"
        }
    ],
    "sg:phone":"+1 920 563 9063",
    "sg:postcode":"53538",
    "sg:province":"WI",
    "sg:tags":[
        "concrete",
        "contractor"
    ],
    "wof:name":"Bowar Concrete Construction",
    "wof:placetype":"venue"
},
  "geometry": {"coordinates":[-88.821698,42.896294],"type":"Point"}
}