{
  "type": "Feature",
  "properties": {
    "iso:country":"US",
    "sg:address":"2925 Bartells Dr",
    "sg:city":"Beloit",
    "sg:classifiers":[
        {
            "category":"Manufacturing",
            "subcategory":"Tools & Machinery",
            "type":"Manufacturing & Wholesale Goods"
        }
    ],
    "sg:phone":"+1 608 362 2255",
    "sg:postcode":"53511",
    "sg:province":"WI",
    "sg:tags":[
        "equipment",
        "scientific",
        "mfg"
    ],
    "sg:website":"www.labcraftsmen.com",
    "wof:name":"Laboratory Craftsmen Inc",
    "wof:placetype":"venue"
},
  "geometry": {"coordinates":[-89.021414,42.551185],"type":"Point"}
}