{
  "type": "Feature",
  "properties": {
    "iso:country":"US",
    "sg:address":"1907 Laemle Ave",
    "sg:city":"Marshfield",
    "sg:classifiers":[
        {
            "category":"Manufacturing",
            "subcategory":"Tools & Machinery",
            "type":"Manufacturing & Wholesale Goods"
        }
    ],
    "sg:phone":"+1 715 389 1511",
    "sg:postcode":"54449",
    "sg:province":"WI",
    "sg:tags":[
        "repair",
        "industrial",
        "sheet",
        "mfg",
        "metal",
        "welding"
    ],
    "wof:name":"Innovative Machine Specialists",
    "wof:placetype":"venue"
},
  "geometry": {"coordinates":[-90.141182,44.649795],"type":"Point"}
}