{
  "type": "Feature",
  "properties": {
    "iso:country":"US",
    "sg:address":"851 Kay Kourt",
    "sg:city":"Neenah",
    "sg:classifiers":[
        {
            "category":"Real Estate",
            "subcategory":"Real Estate Operator",
            "type":"Services"
        }
    ],
    "sg:phone":"+1 920 722 1564",
    "sg:postcode":"54956",
    "sg:province":"WI",
    "sg:tags":[
        "condominium"
    ],
    "wof:name":"Sunset Village Condo",
    "wof:placetype":"venue"
},
  "geometry": {"coordinates":[-88.500968,44.204325],"type":"Point"}
}