{
  "type": "Feature",
  "properties": {
    "iso:country":"US",
    "sg:address":"1600 N 14th St",
    "sg:city":"Milwaukee",
    "sg:classifiers":[
        {
            "category":"Government",
            "subcategory":"Office",
            "type":"Public Place"
        }
    ],
    "sg:phone":"+1 414 286 8282",
    "sg:postcode":"53205",
    "sg:province":"WI",
    "sg:tags":[
        "city",
        "program"
    ],
    "wof:name":"Milwaukee Sanitation Div",
    "wof:placetype":"venue"
},
  "geometry": {"coordinates":[-87.929996,43.052592],"type":"Point"}
}