{
  "type": "Feature",
  "properties": {
    "addr:full":"120 S Madison Ave Sturgeon Bay WI 54235",
    "addr:housenumber":"120",
    "addr:postcode":"54235",
    "addr:street":"S Madison Ave",
    "iso:country":"US",
    "sg:address":"120 S Madison Ave",
    "sg:city":"Sturgeon Bay",
    "sg:classifiers":[
        {
            "category":"Manufacturing",
            "subcategory":"Toys & Sporting Goods",
            "type":"Manufacturing & Wholesale Goods"
        }
    ],
    "sg:phone":"+1 920 746 4466",
    "sg:postcode":"54235",
    "sg:province":"WI",
    "sg:tags":[
        "mfg"
    ],
    "wof:name":"M and L Coin",
    "wof:placetype":"venue"
},
  "geometry": {"coordinates":[-87.384355,44.827714],"type":"Point"}
}