{
  "type": "Feature",
  "properties": {
    "iso:country":"US",
    "sg:address":"1446 S Muskego Ave",
    "sg:city":"Milwaukee",
    "sg:classifiers":[
        {
            "category":"Retail",
            "subcategory":"Repair Shop",
            "type":"Services"
        }
    ],
    "sg:phone":"+1 414 649 0825",
    "sg:postcode":"53204",
    "sg:province":"WI",
    "sg:tags":[
        "sharpening",
        "tool",
        "cutting"
    ],
    "wof:name":"Cherf Saw & Tool Service",
    "wof:placetype":"venue"
},
  "geometry": {"coordinates":[-87.933746,43.016334],"type":"Point"}
}