{
  "type": "Feature",
  "properties": {
    "iso:country":"US",
    "sg:address":"5307 Mud Lake Rd",
    "sg:city":"Lake Mills",
    "sg:classifiers":[
        {
            "category":"Farming",
            "subcategory":"Dairy Farm",
            "type":"Manufacturing & Wholesale Goods"
        }
    ],
    "sg:phone":"+1 920 648 2167",
    "sg:postcode":"53551",
    "sg:province":"WI",
    "wof:name":"Zastrow Farm",
    "wof:placetype":"venue"
},
  "geometry": {"coordinates":[-88.914079,43.058968],"type":"Point"}
}