{
  "type": "Feature",
  "properties": {
    "iso:country":"US",
    "sg:address":"5889 Co Rd T",
    "sg:city":"Oshkosh",
    "sg:classifiers":[
        {
            "category":"Farming",
            "subcategory":"Farm",
            "type":"Manufacturing & Wholesale Goods"
        }
    ],
    "sg:phone":"+1 920 231 1852",
    "sg:postcode":"54904",
    "sg:province":"WI",
    "sg:tags":[
        "crop",
        "general"
    ],
    "wof:name":"Ralph Meltz",
    "wof:placetype":"venue"
},
  "geometry": {"coordinates":[-88.58355,44.097521],"type":"Point"}
}