{
  "type": "Feature",
  "properties": {
    "iso:country":"US",
    "sg:address":"209 W Bridge St",
    "sg:city":"Grafton",
    "sg:classifiers":[
        {
            "category":"Building & Trades",
            "subcategory":"Construction",
            "type":"Services"
        }
    ],
    "sg:phone":"+1 262 375 1456",
    "sg:postcode":"53024",
    "sg:province":"WI",
    "sg:tags":[
        "television",
        "telephone",
        "cable",
        "contractor"
    ],
    "wof:name":"Computer Cabling Plus",
    "wof:placetype":"venue"
},
  "geometry": {"coordinates":[-87.969766,43.318275],"type":"Point"}
}