{
  "type": "Feature",
  "properties": {
    "iso:country":"US",
    "sg:address":"6095 W Buckatabon Rd",
    "sg:city":"Conover",
    "sg:classifiers":[
        {
            "category":"Building & Trades",
            "subcategory":"Construction",
            "type":"Services"
        }
    ],
    "sg:phone":"+1 715 479 2110",
    "sg:postcode":"54519",
    "sg:province":"WI",
    "sg:tags":[
        "house"
    ],
    "sg:website":"www.designbuildbyvisner.com",
    "wof:name":"Design/Build By Visner Inc",
    "wof:placetype":"venue"
},
  "geometry": {"coordinates":[-89.347877,46.025464],"type":"Point"}
}