{
  "type": "Feature",
  "properties": {
    "iso:country":"US",
    "sg:address":"8609 Foxwood Ct",
    "sg:city":"Wausau",
    "sg:classifiers":[
        {
            "category":"Manufacturing",
            "subcategory":"Tools & Machinery",
            "type":"Manufacturing & Wholesale Goods"
        }
    ],
    "sg:phone":"+1 715 842 1755",
    "sg:postcode":"54403",
    "sg:province":"WI",
    "sg:tags":[
        "control",
        "mfg"
    ],
    "wof:name":"Weller Technology",
    "wof:placetype":"venue"
},
  "geometry": {"coordinates":[-89.516052,44.954574],"type":"Point"}
}