{
  "type": "Feature",
  "properties": {
    "iso:country":"US",
    "sg:address":"5111 Birch St",
    "sg:city":"Schofield",
    "sg:classifiers":[
        {
            "category":"Health Services",
            "subcategory":"Clinic",
            "type":"Services"
        }
    ],
    "sg:phone":"+1 715 241 0591",
    "sg:postcode":"54476",
    "sg:province":"WI",
    "sg:tags":[
        "home"
    ],
    "wof:name":"New Horizons Of North Central",
    "wof:placetype":"venue"
},
  "geometry": {"coordinates":[-89.582556,44.910202],"type":"Point"}
}