{
  "type": "Feature",
  "properties": {
    "iso:country":"US",
    "sg:address":"66 S Main St",
    "sg:city":"Fond Du Lac",
    "sg:classifiers":[
        {
            "category":"Museum",
            "type":"Entertainment"
        }
    ],
    "sg:phone":"+1 920 929 0707",
    "sg:postcode":"54935",
    "sg:province":"WI",
    "wof:name":"Children's Museum",
    "wof:placetype":"venue"
},
  "geometry": {"coordinates":[-88.447012,43.776274],"type":"Point"}
}