{
  "type": "Feature",
  "properties": {
    "iso:country":"US",
    "sg:address":"1137 Town Hall Rd",
    "sg:city":"Lyndon Station",
    "sg:classifiers":[
        {
            "category":"Government",
            "subcategory":"Office",
            "type":"Public Place"
        }
    ],
    "sg:phone":"+1 608 524 0800",
    "sg:postcode":"53944",
    "sg:province":"WI",
    "sg:tags":[
        "executive"
    ],
    "wof:name":"Town of Dellona",
    "wof:placetype":"venue"
},
  "geometry": {"coordinates":[-89.91764499999999,43.610201],"type":"Point"}
}