{
  "type": "Feature",
  "properties": {
    "addr:full":"5057 S Whitnall Ave Cudahy WI 53110",
    "addr:housenumber":"5057",
    "addr:postcode":"53110",
    "addr:street":"S Whitnall Ave",
    "iso:country":"US",
    "sg:address":"5057 S Whitnall Ave",
    "sg:city":"Cudahy",
    "sg:classifiers":[
        {
            "category":"Retail",
            "subcategory":"Auto Repair",
            "type":"Services"
        }
    ],
    "sg:phone":"+1 414 489 7840",
    "sg:postcode":"53110",
    "sg:province":"WI",
    "sg:tags":[
        "repairing",
        "automobile"
    ],
    "wof:name":"Steve's Auto Repair",
    "wof:placetype":"venue"
},
  "geometry": {"coordinates":[-87.86946399999999,42.954648],"type":"Point"}
}