{
  "type": "Feature",
  "properties": {
    "iso:country":"US",
    "sg:address":"33097 Briten Rd",
    "sg:city":"Blair",
    "sg:classifiers":[
        {
            "category":"Farming",
            "subcategory":"Dairy Farm",
            "type":"Manufacturing & Wholesale Goods"
        }
    ],
    "sg:phone":"+1 608 989 9056",
    "sg:postcode":"54616",
    "sg:province":"WI",
    "wof:name":"Robert Hoff",
    "wof:placetype":"venue"
},
  "geometry": {"coordinates":[-91.306139,44.320555],"type":"Point"}
}