{
  "type": "Feature",
  "properties": {
    "addr:full":"707 Clermont St Antigo WI 54409",
    "addr:housenumber":"707",
    "addr:postcode":"54409",
    "addr:street":"Clermont St",
    "iso:country":"US",
    "sg:address":"707 Clermont St",
    "sg:city":"Antigo",
    "sg:classifiers":[
        {
            "category":"Organizations",
            "subcategory":"Religious Organization",
            "type":"Services"
        }
    ],
    "sg:phone":"+1 715 623 7343",
    "sg:postcode":"54409",
    "sg:province":"WI",
    "wof:name":"Missionaries Mormon",
    "wof:placetype":"venue"
},
  "geometry": {"coordinates":[-89.1541,45.143244],"type":"Point"}
}