{
  "type": "Feature",
  "properties": {
    "iso:country":"US",
    "sg:address":"755 Scheuring Rd",
    "sg:city":"De Pere",
    "sg:classifiers":[
        {
            "category":"Education",
            "subcategory":"School",
            "type":"Public Place"
        }
    ],
    "sg:phone":"+1 920 336 5754",
    "sg:postcode":"54115",
    "sg:province":"WI",
    "sg:tags":[
        "handicapped",
        "for",
        "mentally"
    ],
    "wof:name":"Brown Co Spec Ed Board",
    "wof:placetype":"venue"
},
  "geometry": {"coordinates":[-88.082358,44.43055],"type":"Point"}
}