{
  "type": "Feature",
  "properties": {
    "iso:country":"US",
    "sg:address":"8605 State Hwy 96",
    "sg:city":"Hortonville",
    "sg:classifiers":[
        {
            "category":"Building & Trades",
            "subcategory":"Plumbing",
            "type":"Services"
        }
    ],
    "sg:phone":"+1 920 779 4427",
    "sg:postcode":"54944",
    "sg:province":"WI",
    "sg:tags":[
        "heating",
        "contractor"
    ],
    "wof:name":"Medina Heating & Cooling Inc",
    "wof:placetype":"venue"
},
  "geometry": {"coordinates":[-88.619603,44.272744],"type":"Point"}
}