{
  "type": "Feature",
  "properties": {
    "addr:full":"5855 State Hwy 70 Spooner WI 54801",
    "addr:housenumber":"5855",
    "addr:postcode":"54801",
    "addr:street":"State Hwy 70",
    "iso:country":"US",
    "sg:address":"5855 State Hwy 70",
    "sg:city":"Spooner",
    "sg:classifiers":[
        {
            "category":"Shopping",
            "subcategory":"Bicycles & Sporting Goods",
            "type":"Retail Goods"
        }
    ],
    "sg:phone":"+1 715 635 3874",
    "sg:postcode":"54801",
    "sg:province":"WI",
    "wof:name":"Genes Custom Strings & Archer",
    "wof:placetype":"venue"
},
  "geometry": {"coordinates":[-91.836091,45.813728],"type":"Point"}
}