{
  "type": "Feature",
  "properties": {
    "iso:country":"US",
    "sg:address":"265 English Settlement Rd",
    "sg:city":"Albany",
    "sg:phone":"+1 608 882 5067",
    "sg:postcode":"53502",
    "sg:province":"WI",
    "sg:tags":[
        "farm",
        "corn",
        "soybean"
    ],
    "wof:name":"Daniel Dunphy",
    "wof:placetype":"venue"
},
  "geometry": {"coordinates":[-89.37257700000001,42.755765],"type":"Point"}
}