{
  "type": "Feature",
  "properties": {
    "iso:country":"US",
    "sg:address":"604 W Thomas St",
    "sg:city":"Wausau",
    "sg:classifiers":[
        {
            "category":"Shopping",
            "subcategory":"Used Merchandise",
            "type":"Retail Goods"
        }
    ],
    "sg:phone":"+1 715 845 4018",
    "sg:postcode":"54401",
    "sg:province":"WI",
    "wof:name":"Pre-Owned Superstore",
    "wof:placetype":"venue"
},
  "geometry": {"coordinates":[-89.644189,44.948436],"type":"Point"}
}