{
  "type": "Feature",
  "properties": {
    "iso:country":"US",
    "sg:address":"5466 S Westridge Dr",
    "sg:city":"New Berlin",
    "sg:classifiers":[
        {
            "category":"Manufacturing",
            "subcategory":"Printing",
            "type":"Manufacturing & Wholesale Goods"
        }
    ],
    "sg:phone":"+1 262 784 1764",
    "sg:postcode":"53151",
    "sg:province":"WI",
    "sg:tags":[
        "multimedia"
    ],
    "wof:name":"Qual Media Corp",
    "wof:placetype":"venue"
},
  "geometry": {"coordinates":[-88.11509,42.942744],"type":"Point"}
}