{
  "type": "Feature",
  "properties": {
    "addr:full":"6217 N Teutonia Ave Milwaukee WI 53209",
    "addr:housenumber":"6217",
    "addr:postcode":"53209",
    "addr:street":"N Teutonia Ave",
    "iso:country":"US",
    "sg:address":"6217 N Teutonia Ave",
    "sg:city":"Milwaukee",
    "sg:classifiers":[
        {
            "category":"Professional",
            "subcategory":"Accounting & Tax Preparation",
            "type":"Services"
        },
        {
            "category":"Banks & Credit Unions",
            "subcategory":"Financial Services",
            "type":"Services"
        }
    ],
    "sg:phone":"+1 414 463 5680",
    "sg:postcode":"53209",
    "sg:province":"WI",
    "sg:tags":[
        "return",
        "preparation-business",
        "taxes-consultants",
        "loan",
        "reporting",
        "representative",
        "alternative",
        "bookkeeping"
    ],
    "sg:website":"http://www.hrblock.com",
    "wof:name":"H&R Block",
    "wof:placetype":"venue"
},
  "geometry": {"coordinates":[-87.95231,43.130239],"type":"Point"}
}