{
  "type": "Feature",
  "properties": {
    "iso:country":"US",
    "sg:address":"400 N Farmer St",
    "sg:city":"Princeton",
    "sg:classifiers":[
        {
            "category":"Shopping",
            "subcategory":"Department Store",
            "type":"Retail Goods"
        }
    ],
    "sg:phone":"+1 920 295 6859",
    "sg:postcode":"54968",
    "sg:province":"WI",
    "wof:name":"Hat Tent",
    "wof:placetype":"venue"
},
  "geometry": {"coordinates":[-89.128241,43.853205],"type":"Point"}
}