{
  "type": "Feature",
  "properties": {
    "addr:full":"214 N 7th Ave West Bend WI 53095",
    "addr:housenumber":"214",
    "addr:postcode":"53095",
    "addr:street":"N 7Th Ave",
    "iso:country":"US",
    "sg:address":"214 N 7th Ave",
    "sg:city":"West Bend",
    "sg:classifiers":[
        {
            "category":"Personal",
            "type":"Services"
        }
    ],
    "sg:phone":"+1 262 335 3255",
    "sg:postcode":"53095",
    "sg:province":"WI",
    "wof:name":"Sun Palace",
    "wof:placetype":"venue"
},
  "geometry": {"coordinates":[-88.185052,43.424913],"type":"Point"}
}