{
  "type": "Feature",
  "properties": {
    "addr:full":"1805 785th St Hager City WI 54014",
    "addr:housenumber":"1805",
    "addr:postcode":"54014",
    "addr:street":"785Th St",
    "iso:country":"US",
    "sg:address":"1805 785th St",
    "sg:city":"Hager City",
    "sg:classifiers":[
        {
            "category":"Home & Garden",
            "subcategory":"Building Materials",
            "type":"Retail Goods"
        }
    ],
    "sg:phone":"+1 715 792 5560",
    "sg:postcode":"54014",
    "sg:province":"WI",
    "sg:tags":[
        "glass",
        "window",
        "plate"
    ],
    "wof:name":"Hager City Glass Co",
    "wof:placetype":"venue"
},
  "geometry": {"coordinates":[-92.525854,44.60346],"type":"Point"}
}