{
  "type": "Feature",
  "properties": {
    "iso:country":"US",
    "sg:address":"3495 1210th Ave",
    "sg:city":"Boyceville",
    "sg:classifiers":[
        {
            "category":"Farming",
            "subcategory":"Livestock Farm",
            "type":"Manufacturing & Wholesale Goods"
        }
    ],
    "sg:phone":"+1 715 949 1608",
    "sg:postcode":"54725",
    "sg:province":"WI",
    "sg:tags":[
        "feedlot",
        "field",
        "crop",
        "beef",
        "cattle"
    ],
    "wof:name":"Dennis Schultz",
    "wof:placetype":"venue"
},
  "geometry": {"coordinates":[-91.99536999999999,45.121306],"type":"Point"}
}