{
  "type": "Feature",
  "properties": {
    "iso:country":"US",
    "sg:address":"2926 Hidden Hollow Rd",
    "sg:city":"Oshkosh",
    "sg:classifiers":[
        {
            "category":"Professional",
            "subcategory":"Computer Services",
            "type":"Services"
        }
    ],
    "sg:phone":"+1 920 231 4667",
    "sg:postcode":"54904",
    "sg:province":"WI",
    "sg:tags":[
        "development",
        "custom",
        "software"
    ],
    "wof:name":"Oakwood Solutions LLC",
    "wof:placetype":"venue"
},
  "geometry": {"coordinates":[-88.606279,44.042341],"type":"Point"}
}