{
  "type": "Feature",
  "properties": {
    "iso:country":"US",
    "sg:address":"160 W Wausau Ave",
    "sg:city":"Wausau",
    "sg:classifiers":[
        {
            "category":"Restaurant",
            "type":"Food & Drink"
        }
    ],
    "sg:phone":"+1 715 848 3831",
    "sg:postcode":"54401",
    "sg:province":"WI",
    "sg:tags":[
        "eating"
    ],
    "wof:name":"Orange Julius",
    "wof:placetype":"venue"
},
  "geometry": {"coordinates":[-89.638022,44.973776],"type":"Point"}
}