{
  "type": "Feature",
  "properties": {
    "addr:full":"319 E Lake St Silver Lake WI 53170",
    "addr:housenumber":"319",
    "addr:postcode":"53170",
    "addr:street":"E Lake St",
    "iso:country":"US",
    "sg:address":"319 E Lake St",
    "sg:city":"Silver Lake",
    "sg:classifiers":[
        {
            "category":"Education",
            "subcategory":"Library",
            "type":"Public Place"
        }
    ],
    "sg:phone":"+1 262 889 4606",
    "sg:postcode":"53170",
    "sg:province":"WI",
    "wof:name":"Silver Lake Community Library",
    "wof:placetype":"venue"
},
  "geometry": {"coordinates":[-88.168064,42.549508],"type":"Point"}
}