{
  "type": "Feature",
  "properties": {
    "addr:full":"520 Main St Montello WI 53949",
    "addr:housenumber":"520",
    "addr:postcode":"53949",
    "addr:street":"Main St",
    "iso:country":"US",
    "sg:address":"520 Main St",
    "sg:city":"Montello",
    "sg:classifiers":[
        {
            "category":"Professional",
            "type":"Services"
        }
    ],
    "sg:phone":"+1 608 297 8722",
    "sg:postcode":"53949",
    "sg:province":"WI",
    "wof:name":"Thomas E Hurst",
    "wof:placetype":"venue"
},
  "geometry": {"coordinates":[-89.32585,43.781459],"type":"Point"}
}