{
  "type": "Feature",
  "properties": {
    "addr:full":"7932 Vander Wettering Rd Greenleaf WI 54126",
    "addr:housenumber":"7932",
    "addr:postcode":"54126",
    "addr:street":"Vander Wettering Rd",
    "iso:country":"US",
    "sg:address":"7932 Vander Wettering Rd",
    "sg:city":"Greenleaf",
    "sg:classifiers":[
        {
            "category":"Farming",
            "subcategory":"Dairy Farm",
            "type":"Manufacturing & Wholesale Goods"
        }
    ],
    "sg:phone":"+1 920 532 4761",
    "sg:postcode":"54126",
    "sg:province":"WI",
    "wof:name":"Vande Wettering Brothers",
    "wof:placetype":"venue"
},
  "geometry": {"coordinates":[-88.13181400000001,44.265616],"type":"Point"}
}