{
  "type": "Feature",
  "properties": {
    "iso:country":"US",
    "sg:address":"265 S Green Bay Rd",
    "sg:city":"Neenah",
    "sg:classifiers":[
        {
            "category":"Organizations",
            "subcategory":"Religious Organization",
            "type":"Services"
        }
    ],
    "sg:phone":"+1 920 727 9161",
    "sg:postcode":"54956",
    "sg:province":"WI",
    "sg:tags":[
        "church"
    ],
    "wof:name":"Fox Valley Adventist Church",
    "wof:placetype":"venue"
},
  "geometry": {"coordinates":[-88.485207,44.186024],"type":"Point"}
}