{
  "type": "Feature",
  "properties": {
    "iso:country":"US",
    "sg:address":"2208 Badger Ct",
    "sg:city":"Waukesha",
    "sg:classifiers":[
        {
            "category":"Building & Trades",
            "subcategory":"Construction",
            "type":"Services"
        }
    ],
    "sg:phone":"+1 262 544 6110",
    "sg:postcode":"53188",
    "sg:province":"WI",
    "sg:tags":[
        "product",
        "asphalt"
    ],
    "wof:name":"Rodriguez Construction Corp",
    "wof:placetype":"venue"
},
  "geometry": {"coordinates":[-88.273072,42.992062],"type":"Point"}
}