{
  "type": "Feature",
  "properties": {
    "iso:country":"US",
    "sg:address":"122 High St",
    "sg:city":"Mineral Point",
    "sg:classifiers":[
        {
            "category":"Health Services",
            "subcategory":"Chiropractor",
            "type":"Services"
        }
    ],
    "sg:phone":"+1 608 987 2012",
    "sg:postcode":"53565",
    "sg:province":"WI",
    "wof:name":"Guler Paul E DC",
    "wof:placetype":"venue"
},
  "geometry": {"coordinates":[-90.179546,42.859894],"type":"Point"}
}