{
  "type": "Feature",
  "properties": {
    "addr:full":"9998 Pioneer Ln Ephraim WI 54211",
    "addr:housenumber":"9998",
    "addr:postcode":"54211",
    "addr:street":"Pioneer Ln",
    "iso:country":"US",
    "sg:address":"9998 Pioneer Ln",
    "sg:city":"Ephraim",
    "sg:classifiers":[
        {
            "category":"Museum",
            "type":"Entertainment"
        }
    ],
    "sg:phone":"+1 920 854 2210",
    "sg:postcode":"54211",
    "sg:province":"WI",
    "sg:tags":[
        "organization",
        "arts",
        "information"
    ],
    "wof:name":"Hardy Center For The Arts",
    "wof:placetype":"venue"
},
  "geometry": {"coordinates":[-87.17072,45.156652],"type":"Point"}
}