{
  "type": "Feature",
  "properties": {
    "iso:country":"US",
    "sg:address":"2081 Norgaren Rd",
    "sg:city":"Stoughton",
    "sg:classifiers":[
        {
            "category":"Professional",
            "subcategory":"Business Services",
            "type":"Services"
        }
    ],
    "sg:phone":"+1 608 873 4852",
    "sg:postcode":"53589",
    "sg:province":"WI",
    "wof:name":"Rod Design Works Inc",
    "wof:placetype":"venue"
},
  "geometry": {"coordinates":[-89.177958,42.952068],"type":"Point"}
}