{
  "type": "Feature",
  "properties": {
    "iso:country":"US",
    "sg:address":"7014 Virgin Timber Dr",
    "sg:city":"Rhinelander",
    "sg:classifiers":[
        {
            "category":"Freight",
            "type":"Transportation"
        }
    ],
    "sg:phone":"+1 715 272 1662",
    "sg:postcode":"54501",
    "sg:province":"WI",
    "sg:tags":[
        "operator",
        "local",
        "trucking"
    ],
    "wof:name":"Robinson Trucking LLC",
    "wof:placetype":"venue"
},
  "geometry": {"coordinates":[-89.302151,45.803906],"type":"Point"}
}