{
  "type": "Feature",
  "properties": {
    "iso:country":"US",
    "sg:address":"413 S Union St",
    "sg:city":"Dodgeville",
    "sg:classifiers":[
        {
            "category":"Professional",
            "type":"Services"
        }
    ],
    "sg:phone":"+1 608 937 0865",
    "sg:postcode":"53533",
    "sg:province":"WI",
    "sg:tags":[
        "establishment"
    ],
    "wof:name":"Cornerstone Foundation",
    "wof:placetype":"venue"
},
  "geometry": {"coordinates":[-90.129369,42.95697],"type":"Point"}
}