{
  "type": "Feature",
  "properties": {
    "iso:country":"US",
    "sg:address":"2545 N 100th St",
    "sg:city":"Milwaukee",
    "sg:classifiers":[
        {
            "category":"Building & Trades",
            "subcategory":"Construction",
            "type":"Services"
        }
    ],
    "sg:phone":"+1 414 771 9740",
    "sg:postcode":"53226",
    "sg:province":"WI",
    "sg:tags":[
        "general",
        "contractor"
    ],
    "wof:name":"Gibraltar Construction LLC",
    "wof:placetype":"venue"
},
  "geometry": {"coordinates":[-88.038702,43.064859],"type":"Point"}
}