{
  "type": "Feature",
  "properties": {
    "addr:full":"969 N Military Ave Green Bay WI 54303",
    "addr:housenumber":"969",
    "addr:postcode":"54303",
    "addr:street":"N Military Ave",
    "iso:country":"US",
    "sg:address":"969 N Military Ave",
    "sg:city":"Green Bay",
    "sg:classifiers":[
        {
            "category":"Personal",
            "type":"Services"
        }
    ],
    "sg:phone":"+1 920 405 9324",
    "sg:postcode":"54303",
    "sg:province":"WI",
    "wof:name":"Spirit Halloween",
    "wof:placetype":"venue"
},
  "geometry": {"coordinates":[-88.054507,44.537012],"type":"Point"}
}