{
  "type": "Feature",
  "properties": {
    "addr:full":"830 S Irwin Ave Green Bay WI 54301",
    "addr:housenumber":"830",
    "addr:postcode":"54301",
    "addr:street":"S Irwin Ave",
    "iso:country":"US",
    "sg:address":"830 S Irwin Ave",
    "sg:city":"Green Bay",
    "sg:classifiers":[
        {
            "category":"Travel",
            "subcategory":"Travel Agent",
            "type":"Entertainment"
        }
    ],
    "sg:phone":"+1 920 435 8295",
    "sg:postcode":"54301",
    "sg:province":"WI",
    "sg:tags":[
        "operator",
        "tour"
    ],
    "wof:name":"Peshtigo River Tours",
    "wof:placetype":"venue"
},
  "geometry": {"coordinates":[-88.004694,44.498012],"type":"Point"}
}