{
  "type": "Feature",
  "properties": {
    "iso:country":"US",
    "sg:address":"108 Main St",
    "sg:city":"Elroy",
    "sg:classifiers":[
        {
            "category":"Government",
            "subcategory":"Police Station",
            "type":"Public Place"
        }
    ],
    "sg:phone":"+1 608 462 2423",
    "sg:postcode":"53929",
    "sg:province":"WI",
    "sg:tags":[
        "department"
    ],
    "wof:name":"Elroy City Police Dept",
    "wof:placetype":"venue"
},
  "geometry": {"coordinates":[-90.270056,43.738256],"type":"Point"}
}