{
  "type": "Feature",
  "properties": {
    "iso:country":"US",
    "sg:address":"17100 W North Ave",
    "sg:city":"Brookfield",
    "sg:classifiers":[
        {
            "category":"Professional",
            "subcategory":"Lawyer & Legal Services",
            "type":"Services"
        }
    ],
    "sg:phone":"+1 262 814 0080",
    "sg:postcode":"53005",
    "sg:province":"WI",
    "sg:tags":[
        "attorney"
    ],
    "sg:website":"www.srsc.com",
    "wof:name":"Schmidt & Rupke SC",
    "wof:placetype":"venue"
},
  "geometry": {"coordinates":[-88.125188,43.061061],"type":"Point"}
}