{
  "type": "Feature",
  "properties": {
    "iso:country":"US",
    "sg:address":"5127 Sunset Rd",
    "sg:city":"Manitowoc",
    "sg:classifiers":[
        {
            "category":"Home & Garden",
            "subcategory":"Home Furnishings",
            "type":"Retail Goods"
        }
    ],
    "sg:phone":"+1 920 682 6432",
    "sg:postcode":"54220",
    "sg:province":"WI",
    "sg:tags":[
        "curtain",
        "made",
        "drapery"
    ],
    "wof:name":"Judy's Sunset Draperies LTD",
    "wof:placetype":"venue"
},
  "geometry": {"coordinates":[-87.71443600000001,44.120325],"type":"Point"}
}