{
  "type": "Feature",
  "properties": {
    "iso:country":"US",
    "sg:address":"100 Bartelle St",
    "sg:city":"Camp Douglas",
    "sg:classifiers":[
        {
            "category":"Organizations",
            "subcategory":"Religious Organization",
            "type":"Services"
        }
    ],
    "sg:phone":"+1 608 427 6762",
    "sg:postcode":"54618",
    "sg:province":"WI",
    "sg:tags":[
        "church"
    ],
    "wof:name":"Catholic Rectory",
    "wof:placetype":"venue"
},
  "geometry": {"coordinates":[-90.271548,43.922339],"type":"Point"}
}