{
  "type": "Feature",
  "properties": {
    "iso:country":"US",
    "sg:address":"1611 W Sunset Rd",
    "sg:city":"Port Washington",
    "sg:classifiers":[
        {
            "category":"Manufacturing",
            "subcategory":"Chemicals & Compounds",
            "type":"Manufacturing & Wholesale Goods"
        }
    ],
    "sg:phone":"+1 262 284 6600",
    "sg:postcode":"53074",
    "sg:province":"WI",
    "sg:tags":[
        "polishing",
        "cleaning",
        "sanitation"
    ],
    "wof:name":"Kleen Test Products",
    "wof:placetype":"venue"
},
  "geometry": {"coordinates":[-87.887229,43.375975],"type":"Point"}
}