{
  "type": "Feature",
  "properties": {
    "iso:country":"US",
    "sg:address":"24854 State Hwy 93",
    "sg:city":"Galesville",
    "sg:classifiers":[
        {
            "category":"Recreation",
            "type":"Entertainment"
        },
        {
            "category":"Organizations",
            "subcategory":"Community Association",
            "type":"Services"
        }
    ],
    "sg:phone":"+1 608 539 3651",
    "sg:postcode":"54630",
    "sg:province":"WI",
    "sg:tags":[
        "club",
        "membership"
    ],
    "wof:name":"Centerville Curling Club",
    "wof:placetype":"venue"
},
  "geometry": {"coordinates":[-91.446697,44.070082],"type":"Point"}
}