{
  "type": "Feature",
  "properties": {
    "iso:country":"US",
    "sg:address":"420 Forest Ave",
    "sg:city":"Sheboygan Falls",
    "sg:classifiers":[
        {
            "category":"Manufacturing",
            "subcategory":"Retail Goods",
            "type":"Manufacturing & Wholesale Goods"
        },
        {
            "category":"Manufacturing",
            "subcategory":"Tools & Machinery",
            "type":"Manufacturing & Wholesale Goods"
        }
    ],
    "sg:phone":"+1 920 467 0871",
    "sg:postcode":"53085",
    "sg:province":"WI",
    "sg:tags":[
        "fabricating",
        "industrial",
        "assembly",
        "mfg"
    ],
    "wof:name":"Z & N Machine Co Inc",
    "wof:placetype":"venue"
},
  "geometry": {"coordinates":[-87.80860300000001,43.743153],"type":"Point"}
}