{
  "type": "Feature",
  "properties": {
    "iso:country":"US",
    "sg:address":"1701 E Beverly Rd",
    "sg:city":"Milwaukee",
    "sg:classifiers":[
        {
            "category":"Professional",
            "subcategory":"Lawyer & Legal Services",
            "type":"Services"
        }
    ],
    "sg:phone":"+1 414 967 4826",
    "sg:postcode":"53211",
    "sg:province":"WI",
    "wof:name":"Attorney Geoffrey J Gnadt",
    "wof:placetype":"venue"
},
  "geometry": {"coordinates":[-87.887555,43.086016],"type":"Point"}
}