{
  "type": "Feature",
  "properties": {
    "iso:country":"US",
    "sg:address":"528 4th St",
    "sg:city":"Green Bay",
    "sg:classifiers":[
        {
            "category":"Retail",
            "subcategory":"Laundry & Dry Cleaning",
            "type":"Services"
        }
    ],
    "sg:phone":"+1 920 432 9066",
    "sg:postcode":"54304",
    "sg:province":"WI",
    "wof:name":"Druckrey Carpet Cleaning",
    "wof:placetype":"venue"
},
  "geometry": {"coordinates":[-88.028859,44.509469],"type":"Point"}
}