{
  "type": "Feature",
  "properties": {
    "iso:country":"US",
    "sg:address":"135 E Hickey Ave",
    "sg:city":"Tomahawk",
    "sg:classifiers":[
        {
            "category":"Building & Trades",
            "subcategory":"Construction",
            "type":"Services"
        }
    ],
    "sg:phone":"+1 715 612 3201",
    "sg:postcode":"54487",
    "sg:province":"WI",
    "sg:tags":[
        "general",
        "contractor"
    ],
    "wof:name":"J B Drywall",
    "wof:placetype":"venue"
},
  "geometry": {"coordinates":[-89.732595,45.455497],"type":"Point"}
}