{
  "type": "Feature",
  "properties": {
    "addr:full":"90 East St Boyceville WI 54725",
    "addr:housenumber":"90",
    "addr:postcode":"54725",
    "addr:street":"East St",
    "iso:country":"US",
    "sg:address":"90 East St",
    "sg:city":"Boyceville",
    "sg:classifiers":[
        {
            "category":"Organizations",
            "subcategory":"Religious Organization",
            "type":"Services"
        }
    ],
    "sg:phone":"+1 715 643 5209",
    "sg:postcode":"54725",
    "sg:province":"WI",
    "wof:name":"Faith Evangelical Free Church",
    "wof:placetype":"venue"
},
  "geometry": {"coordinates":[-92.035872,45.050577],"type":"Point"}
}