{
  "type": "Feature",
  "properties": {
    "iso:country":"US",
    "sg:address":"2422 Rose St",
    "sg:city":"La Crosse",
    "sg:classifiers":[
        {
            "category":"Shopping",
            "type":"Retail Goods"
        }
    ],
    "sg:phone":"+1 608 781 6552",
    "sg:postcode":"54603",
    "sg:province":"WI",
    "sg:tags":[
        "cards",
        "sport",
        "baseball",
        "memorabilia"
    ],
    "wof:name":"Dug Out",
    "wof:placetype":"venue"
},
  "geometry": {"coordinates":[-91.243486,43.857128],"type":"Point"}
}