{
  "type": "Feature",
  "properties": {
    "iso:country":"US",
    "sg:address":"703 N Main St",
    "sg:city":"River Falls",
    "sg:classifiers":[
        {
            "category":"Restaurant",
            "type":"Food & Drink"
        }
    ],
    "sg:phone":"+1 715 426 5054",
    "sg:postcode":"54022",
    "sg:province":"WI",
    "wof:name":"Coach's Bar Inc",
    "wof:placetype":"venue"
},
  "geometry": {"coordinates":[-92.62181,44.869022],"type":"Point"}
}