{
  "type": "Feature",
  "properties": {
    "iso:country":"US",
    "sg:address":"12545 W Burleigh Blvd",
    "sg:city":"Brookfield",
    "sg:classifiers":[
        {
            "category":"Real Estate",
            "subcategory":"Real Estate Agent",
            "type":"Services"
        }
    ],
    "sg:phone":"+1 262 784 7221",
    "sg:postcode":"53005",
    "sg:province":"WI",
    "wof:name":"Patrick Murphy Investment Real",
    "wof:placetype":"venue"
},
  "geometry": {"coordinates":[-88.068395,43.074455],"type":"Point"}
}