{
  "type": "Feature",
  "properties": {
    "iso:country":"US",
    "sg:address":"2585 Lineville Rd",
    "sg:city":"Green Bay",
    "sg:classifiers":[
        {
            "category":"Shopping",
            "subcategory":"Discount & Variety Stores",
            "type":"Retail Goods"
        }
    ],
    "sg:phone":"+1 920 662 9450",
    "sg:postcode":"54313",
    "sg:province":"WI",
    "sg:tags":[
        "merchandise",
        "general"
    ],
    "wof:name":"Shopko",
    "wof:placetype":"venue"
},
  "geometry": {"coordinates":[-88.080824,44.590851],"type":"Point"}
}