{
  "type": "Feature",
  "properties": {
    "addr:full":"107 N Bluebird Ln Sheboygan Falls WI 53085",
    "addr:housenumber":"107",
    "addr:postcode":"53085",
    "addr:street":"N Bluebird Ln",
    "iso:country":"US",
    "sg:address":"107 N Bluebird Ln",
    "sg:city":"Sheboygan Falls",
    "sg:classifiers":[
        {
            "category":"Real Estate",
            "subcategory":"Real Estate Agent",
            "type":"Services"
        }
    ],
    "sg:phone":"+1 920 467 3189",
    "sg:postcode":"53085",
    "sg:province":"WI",
    "wof:name":"Premier Real Estate Management",
    "wof:placetype":"venue"
},
  "geometry": {"coordinates":[-87.829958,43.741794],"type":"Point"}
}