{
  "type": "Feature",
  "properties": {
    "iso:country":"US",
    "sg:address":"110 Manchester Dr",
    "sg:city":"Waukesha",
    "sg:classifiers":[
        {
            "category":"Professional",
            "subcategory":"Accounting & Tax Preparation",
            "type":"Services"
        },
        {
            "category":"Insurance",
            "subcategory":"Insurance Agent",
            "type":"Services"
        }
    ],
    "sg:phone":"+1 262 513 1281",
    "sg:postcode":"53188",
    "sg:province":"WI",
    "sg:tags":[
        "processing"
    ],
    "wof:name":"Custom Billing Management LLC",
    "wof:placetype":"venue"
},
  "geometry": {"coordinates":[-88.26696200000001,43.013559],"type":"Point"}
}