{
  "type": "Feature",
  "properties": {
    "iso:country":"US",
    "sg:address":"3210 N Cramer St",
    "sg:city":"Milwaukee",
    "sg:classifiers":[
        {
            "category":"Professional",
            "type":"Services"
        }
    ],
    "sg:phone":"+1 414 229 4411",
    "sg:postcode":"53211",
    "sg:province":"WI",
    "sg:tags":[
        "establishment"
    ],
    "wof:name":"Chemistry Department",
    "wof:placetype":"venue"
},
  "geometry": {"coordinates":[-87.88647400000001,43.077455],"type":"Point"}
}