{
  "type": "Feature",
  "properties": {
    "iso:country":"US",
    "sg:address":"318 10th Ave",
    "sg:city":"New Glarus",
    "sg:classifiers":[
        {
            "category":"Travel",
            "subcategory":"Hotels & Motels",
            "type":"Entertainment"
        }
    ],
    "sg:phone":"+1 608 527 5896",
    "sg:postcode":"53574",
    "sg:province":"WI",
    "wof:name":"Jeanne-Maries Bed & Breakfast",
    "wof:placetype":"venue"
},
  "geometry": {"coordinates":[-89.636501,42.810938],"type":"Point"}
}