{
  "type": "Feature",
  "properties": {
    "iso:country":"US",
    "sg:address":"556 11th St",
    "sg:city":"Prairie Farm",
    "sg:classifiers":[
        {
            "category":"Farming",
            "subcategory":"Dairy Farm",
            "type":"Manufacturing & Wholesale Goods"
        }
    ],
    "sg:phone":"+1 715 455 1580",
    "sg:postcode":"54762",
    "sg:province":"WI",
    "wof:name":"Sleepy Hollow Farms",
    "wof:placetype":"venue"
},
  "geometry": {"coordinates":[-91.93185,45.289461],"type":"Point"}
}