{
  "type": "Feature",
  "properties": {
    "iso:country":"US",
    "sg:address":"1346 George St",
    "sg:city":"La Crosse",
    "sg:classifiers":[
        {
            "category":"Personal",
            "type":"Services"
        }
    ],
    "sg:phone":"+1 608 785 1067",
    "sg:postcode":"54603",
    "sg:province":"WI",
    "wof:name":"Computer Photo",
    "wof:placetype":"venue"
},
  "geometry": {"coordinates":[-91.239601,43.841379],"type":"Point"}
}