{
  "type": "Feature",
  "properties": {
    "iso:country":"US",
    "sg:address":"36342 West St",
    "sg:city":"Whitehall",
    "sg:classifiers":[
        {
            "category":"Manufacturing",
            "subcategory":"Retail Goods",
            "type":"Manufacturing & Wholesale Goods"
        }
    ],
    "sg:phone":"+1 715 538 2902",
    "sg:postcode":"54773",
    "sg:province":"WI",
    "sg:tags":[
        "product",
        "mfg"
    ],
    "wof:name":"Country Home Scents",
    "wof:placetype":"venue"
},
  "geometry": {"coordinates":[-91.321461,44.367391],"type":"Point"}
}