{
  "type": "Feature",
  "properties": {
    "iso:country":"US",
    "sg:address":"1637 E Racine St",
    "sg:city":"Janesville",
    "sg:classifiers":[
        {
            "category":"Bars & Pubs",
            "type":"Food & Drink"
        }
    ],
    "sg:phone":"+1 608 754 5600",
    "sg:postcode":"53545",
    "sg:province":"WI",
    "sg:tags":[
        "drinking"
    ],
    "wof:name":"Park Place",
    "wof:placetype":"venue"
},
  "geometry": {"coordinates":[-89.000623,42.678914],"type":"Point"}
}