{
  "type": "Feature",
  "properties": {
    "iso:country":"US",
    "sg:address":"2231 N 119th St",
    "sg:city":"Milwaukee",
    "sg:classifiers":[
        {
            "category":"Real Estate",
            "subcategory":"Real Estate Agent",
            "type":"Services"
        }
    ],
    "sg:phone":"+1 414 453 8425",
    "sg:postcode":"53226",
    "sg:province":"WI",
    "wof:name":"Scavenger Hunt Estate Sales",
    "wof:placetype":"venue"
},
  "geometry": {"coordinates":[-88.061599,43.059421],"type":"Point"}
}