{
  "type": "Feature",
  "properties": {
    "addr:full":"1020 N Bristol St Sun Prairie WI 53590",
    "addr:housenumber":"1020",
    "addr:postcode":"53590",
    "addr:street":"N Bristol St",
    "iso:country":"US",
    "sg:address":"1020 N Bristol St",
    "sg:city":"Sun Prairie",
    "sg:classifiers":[
        {
            "category":"Health Services",
            "subcategory":"Doctor",
            "type":"Services"
        }
    ],
    "sg:phone":"+1 608 837 7394",
    "sg:postcode":"53590",
    "sg:province":"WI",
    "sg:tags":[
        "dentist"
    ],
    "wof:name":"Randall Straub DDS",
    "wof:placetype":"venue"
},
  "geometry": {"coordinates":[-89.21112599999999,43.193996],"type":"Point"}
}