{
  "type": "Feature",
  "properties": {
    "iso:country":"US",
    "sg:address":"201 E Lake St",
    "sg:city":"Eau Claire",
    "sg:classifiers":[
        {
            "category":"Organizations",
            "subcategory":"Community Association",
            "type":"Services"
        }
    ],
    "sg:phone":"+1 715 855 0081",
    "sg:postcode":"54701",
    "sg:province":"WI",
    "wof:name":"Boys & Girls Club",
    "wof:placetype":"venue"
},
  "geometry": {"coordinates":[-91.497298,44.80862],"type":"Point"}
}