{
  "type": "Feature",
  "properties": {
    "iso:country":"US",
    "sg:address":"3812 W Burleigh St",
    "sg:city":"Milwaukee",
    "sg:classifiers":[
        {
            "category":"Social Services",
            "subcategory":"Child Care",
            "type":"Services"
        }
    ],
    "sg:phone":"+1 414 442 8210",
    "sg:postcode":"53210",
    "sg:province":"WI",
    "wof:name":"Children's World Learning Ctr",
    "wof:placetype":"venue"
},
  "geometry": {"coordinates":[-87.961973,43.075275],"type":"Point"}
}