{
  "type": "Feature",
  "properties": {
    "iso:country":"US",
    "sg:address":"7559 N Pioneer Rd",
    "sg:city":"Fond Du Lac",
    "sg:classifiers":[
        {
            "category":"Home & Garden",
            "subcategory":"Mobile Homes",
            "type":"Retail Goods"
        }
    ],
    "sg:phone":"+1 920 922 2222",
    "sg:postcode":"54937",
    "sg:province":"WI",
    "sg:tags":[
        "mfg"
    ],
    "wof:name":"Flood Homes Inc",
    "wof:placetype":"venue"
},
  "geometry": {"coordinates":[-88.519379,43.820339],"type":"Point"}
}