{
  "type": "Feature",
  "properties": {
    "iso:country":"US",
    "sg:address":"404 E Division St",
    "sg:city":"Neillsville",
    "sg:classifiers":[
        {
            "category":"Retail",
            "subcategory":"Auto Repair",
            "type":"Services"
        }
    ],
    "sg:phone":"+1 715 743 3207",
    "sg:postcode":"54456",
    "sg:province":"WI",
    "sg:tags":[
        "repairing",
        "automobile"
    ],
    "sg:website":"www.grossmotors.com",
    "wof:name":"Gross Motors Inc",
    "wof:placetype":"venue"
},
  "geometry": {"coordinates":[-90.591875,44.552635],"type":"Point"}
}