{
  "type": "Feature",
  "properties": {
    "iso:country":"US",
    "sg:address":"334 Daley St",
    "sg:city":"Spring Green",
    "sg:classifiers":[
        {
            "category":"Home & Garden",
            "subcategory":"Furniture",
            "type":"Retail Goods"
        }
    ],
    "sg:phone":"+1 608 588 7221",
    "sg:postcode":"53588",
    "sg:province":"WI",
    "sg:tags":[
        "gift"
    ],
    "wof:name":"Oak Horse Farm",
    "wof:placetype":"venue"
},
  "geometry": {"coordinates":[-90.071144,43.178777],"type":"Point"}
}