{
  "type": "Feature",
  "properties": {
    "iso:country":"US",
    "sg:address":"1716 Illinois Ave",
    "sg:city":"Sheboygan",
    "sg:classifiers":[
        {
            "category":"Building & Trades",
            "subcategory":"Construction",
            "type":"Services"
        }
    ],
    "sg:phone":"+1 920 458 7119",
    "sg:postcode":"53081",
    "sg:province":"WI",
    "sg:tags":[
        "house"
    ],
    "wof:name":"Kittel Homes No 2 LLC",
    "wof:placetype":"venue"
},
  "geometry": {"coordinates":[-87.728875,43.744377],"type":"Point"}
}