{
  "type": "Feature",
  "properties": {
    "iso:country":"US",
    "sg:address":"3918 Anchor Dr",
    "sg:city":"Madison",
    "sg:classifiers":[
        {
            "category":"Farming",
            "subcategory":"Fish & Marine Products",
            "type":"Manufacturing & Wholesale Goods"
        }
    ],
    "sg:phone":"+1 608 244 7650",
    "sg:postcode":"53714",
    "sg:province":"WI",
    "sg:tags":[
        "management"
    ],
    "wof:name":"Turkey Pete Inc",
    "wof:placetype":"venue"
},
  "geometry": {"coordinates":[-89.316738,43.088726],"type":"Point"}
}