{
  "type": "Feature",
  "properties": {
    "addr:full":"1276 Weiner Rd Columbus WI 53925",
    "addr:housenumber":"1276",
    "addr:postcode":"53925",
    "addr:street":"Weiner Rd",
    "iso:country":"US",
    "sg:address":"1276 Weiner Rd",
    "sg:city":"Columbus",
    "sg:classifiers":[
        {
            "category":"Shopping",
            "type":"Retail Goods"
        }
    ],
    "sg:phone":"+1 920 623 2611",
    "sg:postcode":"53925",
    "sg:province":"WI",
    "sg:tags":[
        "art",
        "gallery",
        "dealer"
    ],
    "sg:website":"www.canvastoclay.com",
    "wof:name":"CANVASTOCLAY.COM",
    "wof:placetype":"venue"
},
  "geometry": {"coordinates":[-89.062546,43.290485],"type":"Point"}
}