{
  "type": "Feature",
  "properties": {
    "addr:full":"2375 State Hwy 44 Oshkosh WI 54904",
    "addr:housenumber":"2375",
    "addr:postcode":"54904",
    "addr:street":"State Hwy 44",
    "iso:country":"US",
    "sg:address":"2375 State Hwy 44",
    "sg:city":"Oshkosh",
    "sg:classifiers":[
        {
            "category":"Insurance",
            "subcategory":"Insurance Agent",
            "type":"Services"
        }
    ],
    "sg:phone":"+1 920 651 9921",
    "sg:postcode":"54904",
    "sg:province":"WI",
    "wof:name":"Thrivent Financial-Lutherans",
    "wof:placetype":"venue"
},
  "geometry": {"coordinates":[-88.589843,43.986896],"type":"Point"}
}