{
  "type": "Feature",
  "properties": {
    "iso:country":"US",
    "sg:address":"21095 Watertown Rd",
    "sg:city":"Waukesha",
    "sg:classifiers":[
        {
            "category":"Wholesale",
            "subcategory":"Machinery & Supplies",
            "type":"Manufacturing & Wholesale Goods"
        }
    ],
    "sg:phone":"+1 262 798 4243",
    "sg:postcode":"53186",
    "sg:province":"WI",
    "sg:tags":[
        "gage"
    ],
    "wof:name":"Hell-Coil Products",
    "wof:placetype":"venue"
},
  "geometry": {"coordinates":[-88.17706,43.042969],"type":"Point"}
}