{
  "type": "Feature",
  "properties": {
    "addr:full":"3425 90th St Sturtevant WI 53177",
    "addr:housenumber":"3425",
    "addr:postcode":"53177",
    "addr:street":"90Th St",
    "iso:country":"US",
    "sg:address":"3425 90th St",
    "sg:city":"Sturtevant",
    "sg:classifiers":[
        {
            "category":"Organizations",
            "subcategory":"Community Association",
            "type":"Services"
        }
    ],
    "sg:phone":"+1 262 886 4043",
    "sg:postcode":"53177",
    "sg:province":"WI",
    "wof:name":"Thrivent Fincl For Lutherans",
    "wof:placetype":"venue"
},
  "geometry": {"coordinates":[-87.89466299999999,42.691795],"type":"Point"}
}