{
  "type": "Feature",
  "properties": {
    "iso:country":"US",
    "sg:address":"633 E Henry Clay St",
    "sg:city":"Milwaukee",
    "sg:classifiers":[
        {
            "category":"Health Services",
            "subcategory":"Doctor",
            "type":"Services"
        }
    ],
    "sg:phone":"+1 414 962 5511",
    "sg:postcode":"53217",
    "sg:province":"WI",
    "sg:tags":[
        "medical"
    ],
    "wof:name":"O Columbia St Marys Hospital",
    "wof:placetype":"venue"
},
  "geometry": {"coordinates":[-87.902475,43.111151],"type":"Point"}
}