{
  "type": "Feature",
  "properties": {
    "iso:country":"US",
    "sg:address":"338 N Milwaukee St",
    "sg:city":"Milwaukee",
    "sg:classifiers":[
        {
            "category":"Shopping",
            "subcategory":"Clothing, Apparel, & Fashions",
            "type":"Retail Goods"
        }
    ],
    "sg:phone":"+1 414 271 3655",
    "sg:postcode":"53202",
    "sg:province":"WI",
    "wof:name":"Dolls Eye",
    "wof:placetype":"venue"
},
  "geometry": {"coordinates":[-87.905984,43.034659],"type":"Point"}
}