{
  "type": "Feature",
  "properties": {
    "iso:country":"US",
    "sg:address":"1360 Waube Ln",
    "sg:city":"Green Bay",
    "sg:classifiers":[
        {
            "category":"Building & Trades",
            "subcategory":"Landscaping Services",
            "type":"Services"
        }
    ],
    "sg:phone":"+1 920 403 1189",
    "sg:postcode":"54304",
    "sg:province":"WI",
    "sg:tags":[
        "landscape",
        "contractor"
    ],
    "wof:name":"First Choice Landscaping LLC",
    "wof:placetype":"venue"
},
  "geometry": {"coordinates":[-88.10211,44.474201],"type":"Point"}
}