{
  "type": "Feature",
  "properties": {
    "iso:country":"US",
    "sg:address":"13046 Amacoy Lake Rd",
    "sg:city":"Bruce",
    "sg:classifiers":[
        {
            "category":"Wholesale",
            "subcategory":"Auto Parts",
            "type":"Manufacturing & Wholesale Goods"
        }
    ],
    "sg:phone":"+1 715 868 6895",
    "sg:postcode":"54819",
    "sg:province":"WI",
    "sg:tags":[
        "used"
    ],
    "wof:name":"G & G Auto Salvage",
    "wof:placetype":"venue"
},
  "geometry": {"coordinates":[-91.346505,45.406813],"type":"Point"}
}