{
  "type": "Feature",
  "properties": {
    "iso:country":"US",
    "sg:address":"532 Milwaukee Ave E",
    "sg:city":"Fort Atkinson",
    "sg:classifiers":[
        {
            "category":"Building & Trades",
            "subcategory":"Plumbing",
            "type":"Services"
        }
    ],
    "sg:phone":"+1 920 568 9194",
    "sg:postcode":"53538",
    "sg:province":"WI",
    "sg:tags":[
        "heating",
        "contractor"
    ],
    "wof:name":"Reynolds Heating AC & Refrig",
    "wof:placetype":"venue"
},
  "geometry": {"coordinates":[-88.827676,42.925741],"type":"Point"}
}