{
  "type": "Feature",
  "properties": {
    "addr:full":"15981 W Carol Dr Hayward WI 54843",
    "addr:housenumber":"15981",
    "addr:postcode":"54843",
    "addr:street":"W Carol Dr",
    "iso:country":"US",
    "sg:address":"15981 W Carol Dr",
    "sg:city":"Hayward",
    "sg:classifiers":[
        {
            "category":"Home & Garden",
            "subcategory":"Home Furnishings",
            "type":"Retail Goods"
        }
    ],
    "sg:phone":"+1 715 634 2754",
    "sg:postcode":"54843",
    "sg:province":"WI",
    "sg:tags":[
        "quilting"
    ],
    "wof:name":"Granma's Workshop",
    "wof:placetype":"venue"
},
  "geometry": {"coordinates":[-91.488724,45.994964],"type":"Point"}
}