{
  "type": "Feature",
  "properties": {
    "addr:full":"133 S Butler St Madison WI 53703",
    "addr:housenumber":"133",
    "addr:postcode":"53703",
    "addr:street":"S Butler St",
    "iso:country":"US",
    "sg:address":"133 S Butler St",
    "sg:city":"Madison",
    "sg:classifiers":[
        {
            "category":"Professional",
            "type":"Services"
        }
    ],
    "sg:phone":"+1 608 251 0993",
    "sg:postcode":"53703",
    "sg:province":"WI",
    "sg:tags":[
        "establishment"
    ],
    "wof:name":"Grassroots Campaigns Inc",
    "wof:placetype":"venue"
},
  "geometry": {"coordinates":[-89.37875099999999,43.075089],"type":"Point"}
}