{
  "type": "Feature",
  "properties": {
    "iso:country":"US",
    "sg:address":"410 N Brown St",
    "sg:city":"Rhinelander",
    "sg:classifiers":[
        {
            "category":"Shopping",
            "subcategory":"Florist",
            "type":"Retail Goods"
        }
    ],
    "sg:phone":"+1 715 362 7600",
    "sg:postcode":"54501",
    "sg:province":"WI",
    "sg:website":"www.forthfloral.com",
    "wof:name":"Forth Floral Inc",
    "wof:placetype":"venue"
},
  "geometry": {"coordinates":[-89.412672,45.643053],"type":"Point"}
}