{
  "type": "Feature",
  "properties": {
    "addr:full":"18227 US Hwy 10 Reedsville WI 54230",
    "addr:housenumber":"18227",
    "addr:postcode":"54230",
    "addr:street":"Us Hwy 10",
    "iso:country":"US",
    "sg:address":"18227 US Hwy 10",
    "sg:city":"Reedsville",
    "sg:classifiers":[
        {
            "category":"Manufacturing",
            "subcategory":"Retail Goods",
            "type":"Manufacturing & Wholesale Goods"
        },
        {
            "category":"Travel",
            "subcategory":"Campground",
            "type":"Entertainment"
        }
    ],
    "sg:phone":"+1 920 754 4142",
    "sg:postcode":"54230",
    "sg:province":"WI",
    "sg:tags":[
        "lead",
        "mfg"
    ],
    "wof:name":"Rainbow's End Campgrounds",
    "wof:placetype":"venue"
},
  "geometry": {"coordinates":[-87.93879200000001,44.153309],"type":"Point"}
}