{
  "type": "Feature",
  "properties": {
    "iso:country":"US",
    "sg:address":"11440 Willow Rd",
    "sg:city":"Stanley",
    "sg:classifiers":[
        {
            "category":"Farming",
            "subcategory":"Livestock Farm",
            "type":"Manufacturing & Wholesale Goods"
        }
    ],
    "sg:phone":"+1 715 644 3620",
    "sg:postcode":"54768",
    "sg:province":"WI",
    "sg:tags":[
        "fruit",
        "tree",
        "specialty",
        "orchard",
        "animal"
    ],
    "wof:name":"Frank Reith",
    "wof:placetype":"venue"
},
  "geometry": {"coordinates":[-90.890157,44.959229],"type":"Point"}
}