{
  "type": "Feature",
  "properties": {
    "iso:country":"US",
    "sg:address":"722 Albion Rd",
    "sg:city":"Edgerton",
    "sg:classifiers":[
        {
            "category":"Retail",
            "subcategory":"Auto Repair",
            "type":"Services"
        }
    ],
    "sg:phone":"+1 608 884 3204",
    "sg:postcode":"53534",
    "sg:province":"WI",
    "sg:tags":[
        "body"
    ],
    "wof:name":"Sherm Larrys Dougs Bdy Pnt Sp",
    "wof:placetype":"venue"
},
  "geometry": {"coordinates":[-89.07466,42.886203],"type":"Point"}
}