{
  "type": "Feature",
  "properties": {
    "iso:country":"US",
    "sg:address":"9597 Co Rd D",
    "sg:city":"Brillion",
    "sg:classifiers":[
        {
            "category":"Farming",
            "subcategory":"Livestock Farm",
            "type":"Manufacturing & Wholesale Goods"
        }
    ],
    "sg:phone":"+1 920 989 3335",
    "sg:postcode":"54110",
    "sg:province":"WI",
    "sg:tags":[
        "beef",
        "feedlot",
        "cattle"
    ],
    "wof:name":"Dunphy Veal Inc",
    "wof:placetype":"venue"
},
  "geometry": {"coordinates":[-88.172616,44.241449],"type":"Point"}
}