{
  "type": "Feature",
  "properties": {
    "iso:country":"US",
    "sg:address":"108 E Co Rd A",
    "sg:city":"Stetsonville",
    "sg:classifiers":[
        {
            "category":"Restaurant",
            "type":"Food & Drink"
        }
    ],
    "sg:phone":"+1 715 678 2992",
    "sg:postcode":"54480",
    "sg:province":"WI",
    "wof:name":"Franke's Bar & Restaurant",
    "wof:placetype":"venue"
},
  "geometry": {"coordinates":[-90.314761,45.077035],"type":"Point"}
}