{
  "type": "Feature",
  "properties": {
    "addr:full":"702 Superior St Antigo WI 54409",
    "addr:housenumber":"702",
    "addr:postcode":"54409",
    "addr:street":"Superior St",
    "iso:country":"US",
    "sg:address":"702 Superior St",
    "sg:city":"Antigo",
    "sg:classifiers":[
        {
            "category":"Food & Beverages",
            "subcategory":"Groceries & Convenience Stores",
            "type":"Retail Goods"
        }
    ],
    "sg:phone":"+1 715 623 3882",
    "sg:postcode":"54409",
    "sg:province":"WI",
    "wof:name":"Marathion Express Mart",
    "wof:placetype":"venue"
},
  "geometry": {"coordinates":[-89.152259,45.143306],"type":"Point"}
}