{
  "type": "Feature",
  "properties": {
    "addr:full":"1381 Sandberg Rd Melrose WI 54642",
    "addr:housenumber":"1381",
    "addr:postcode":"54642",
    "addr:street":"Sandberg Rd",
    "iso:country":"US",
    "sg:address":"1381 Sandberg Rd",
    "sg:city":"Melrose",
    "sg:classifiers":[
        {
            "category":"Retail",
            "subcategory":"Animal Services",
            "type":"Services"
        }
    ],
    "sg:phone":"+1 608 488 4780",
    "sg:postcode":"54642",
    "sg:province":"WI",
    "sg:tags":[
        "pet",
        "boarding",
        "sitting"
    ],
    "wof:name":"Lost Orchard Kennels & Suites",
    "wof:placetype":"venue"
},
  "geometry": {"coordinates":[-91.10283,44.112618],"type":"Point"}
}