{
  "type": "Feature",
  "properties": {
    "iso:country":"US",
    "sg:address":"5153 Spruce Ave",
    "sg:city":"Wisconsin Rapids",
    "sg:classifiers":[
        {
            "category":"Building & Trades",
            "subcategory":"Construction",
            "type":"Services"
        }
    ],
    "sg:phone":"+1 715 325 4050",
    "sg:postcode":"54494",
    "sg:province":"WI",
    "sg:tags":[
        "contractor"
    ],
    "wof:name":"Pro D Drywall",
    "wof:placetype":"venue"
},
  "geometry": {"coordinates":[-89.760525,44.328022],"type":"Point"}
}