{
  "type": "Feature",
  "properties": {
    "iso:country":"US",
    "sg:address":"75 W Main St",
    "sg:city":"Platteville",
    "sg:classifiers":[
        {
            "category":"Manufacturing",
            "subcategory":"Printing",
            "type":"Manufacturing & Wholesale Goods"
        }
    ],
    "sg:phone":"+1 608 348 6635",
    "sg:postcode":"53818",
    "sg:province":"WI",
    "sg:tags":[
        "lithographic",
        "commercial"
    ],
    "wof:name":"Morrissey Printing",
    "wof:placetype":"venue"
},
  "geometry": {"coordinates":[-90.479301,42.734238],"type":"Point"}
}