{
  "type": "Feature",
  "properties": {
    "addr:full":"411 E Mason St Milwaukee WI 53202",
    "addr:housenumber":"411",
    "addr:postcode":"53202",
    "addr:street":"E Mason St",
    "iso:country":"US",
    "sg:address":"411 E Mason St",
    "sg:city":"Milwaukee",
    "sg:classifiers":[
        {
            "category":"Bars & Pubs",
            "type":"Food & Drink"
        },
        {
            "category":"Cafe",
            "type":"Food & Drink"
        }
    ],
    "sg:menulink":"http://www.allmenus.com/wi/milwaukee/8035-metro-cafe--bar/menu/",
    "sg:phone":"+1 414 225 3270",
    "sg:postcode":"53202",
    "sg:province":"WI",
    "sg:tags":[
        "american"
    ],
    "wof:name":"Metro Cafe & Bar",
    "wof:placetype":"venue"
},
  "geometry": {"coordinates":[-87.906578,43.04003],"type":"Point"}
}