{
  "type": "Feature",
  "properties": {
    "iso:country":"US",
    "sg:address":"3018 Longview Ln",
    "sg:city":"Markesan",
    "sg:classifiers":[
        {
            "category":"Professional",
            "subcategory":"Lawyer & Legal Services",
            "type":"Services"
        }
    ],
    "sg:phone":"+1 920 398 2773",
    "sg:postcode":"53946",
    "sg:province":"WI",
    "sg:tags":[
        "attorney"
    ],
    "wof:name":"Peter Hoeper",
    "wof:placetype":"venue"
},
  "geometry": {"coordinates":[-89.033626,43.78403],"type":"Point"}
}