{
  "type": "Feature",
  "properties": {
    "iso:country":"US",
    "sg:address":"796 Sunset Dr",
    "sg:city":"Thorp",
    "sg:classifiers":[
        {
            "category":"Farming",
            "subcategory":"Dairy Farm",
            "type":"Manufacturing & Wholesale Goods"
        }
    ],
    "sg:phone":"+1 715 669 5182",
    "sg:postcode":"54771",
    "sg:province":"WI",
    "wof:name":"Richard Hughes",
    "wof:placetype":"venue"
},
  "geometry": {"coordinates":[-90.861167,45.060646],"type":"Point"}
}