{
  "type": "Feature",
  "properties": {
    "addr:full":"6933 W Mequon Rd Mequon WI 53092",
    "addr:housenumber":"6933",
    "addr:postcode":"53092",
    "addr:street":"W Mequon Rd",
    "iso:country":"US",
    "sg:address":"6933 W Mequon Rd",
    "sg:city":"Mequon",
    "sg:classifiers":[
        {
            "category":"Retail",
            "subcategory":"Auto Repair",
            "type":"Services"
        }
    ],
    "sg:phone":"+1 262 242 1470",
    "sg:postcode":"53092",
    "sg:province":"WI",
    "sg:tags":[
        "shop",
        "repairing",
        "truck",
        "automobile",
        "automotive"
    ],
    "wof:name":"Gierach's Service Inc",
    "wof:placetype":"venue"
},
  "geometry": {"coordinates":[-87.992103,43.221414],"type":"Point"}
}