{
  "type": "Feature",
  "properties": {
    "iso:country":"US",
    "sg:address":"4180 N Lydell St",
    "sg:city":"Milwaukee",
    "sg:classifiers":[
        {
            "category":"Manufacturing",
            "subcategory":"Leather Goods",
            "type":"Manufacturing & Wholesale Goods"
        }
    ],
    "sg:phone":"+1 414 962 9606",
    "sg:postcode":"53212",
    "sg:province":"WI",
    "sg:website":"www.hoodleather.com",
    "wof:name":"Hood Leather Goods Co",
    "wof:placetype":"venue"
},
  "geometry": {"coordinates":[-87.91040599999999,43.093265],"type":"Point"}
}