{
  "type": "Feature",
  "properties": {
    "iso:country":"US",
    "sg:address":"7243 Mayking Rd",
    "sg:city":"Antigo",
    "sg:classifiers":[
        {
            "category":"Farming",
            "subcategory":"Dairy Farm",
            "type":"Manufacturing & Wholesale Goods"
        }
    ],
    "sg:phone":"+1 715 623 7088",
    "sg:postcode":"54409",
    "sg:province":"WI",
    "wof:name":"Depies Terrance and/or Linda",
    "wof:placetype":"venue"
},
  "geometry": {"coordinates":[-88.998039,45.101406],"type":"Point"}
}