{
  "type": "Feature",
  "properties": {
    "iso:country":"US",
    "sg:address":"4473 N 76th St",
    "sg:city":"Milwaukee",
    "sg:classifiers":[
        {
            "category":"Social Services",
            "subcategory":"Child Care",
            "type":"Services"
        }
    ],
    "sg:phone":"+1 414 466 0488",
    "sg:postcode":"53218",
    "sg:province":"WI",
    "wof:name":"Alphabet Street Learning Ctr",
    "wof:placetype":"venue"
},
  "geometry": {"coordinates":[-88.00715,43.097714],"type":"Point"}
}