{
  "type": "Feature",
  "properties": {
    "addr:full":"2317 Parmenter St Middleton WI 53562",
    "addr:housenumber":"2317",
    "addr:postcode":"53562",
    "addr:street":"Parmenter St",
    "iso:country":"US",
    "sg:address":"2317 Parmenter St",
    "sg:city":"Middleton",
    "sg:classifiers":[
        {
            "category":"Manufacturing",
            "subcategory":"Chemicals & Compounds",
            "type":"Manufacturing & Wholesale Goods"
        }
    ],
    "sg:phone":"+1 608 836 1591",
    "sg:postcode":"53562",
    "sg:province":"WI",
    "sg:tags":[
        "detergent",
        "mfg"
    ],
    "wof:name":"Gloss-All Products",
    "wof:placetype":"venue"
},
  "geometry": {"coordinates":[-89.511342,43.101004],"type":"Point"}
}