{
  "type": "Feature",
  "properties": {
    "iso:country":"US",
    "sg:address":"601 Main St",
    "sg:city":"Fall River",
    "sg:classifiers":[
        {
            "category":"Retail",
            "subcategory":"Repair Shop",
            "type":"Services"
        }
    ],
    "sg:phone":"+1 920 484 6017",
    "sg:postcode":"53932",
    "sg:province":"WI",
    "wof:name":"Shufelt S Small Engine",
    "wof:placetype":"venue"
},
  "geometry": {"coordinates":[-89.03718499999999,43.39234],"type":"Point"}
}