{
  "type": "Feature",
  "properties": {
    "addr:full":"9220 N 75th St Milwaukee WI 53223",
    "addr:housenumber":"9220",
    "addr:postcode":"53223",
    "addr:street":"N 75Th St",
    "iso:country":"US",
    "sg:address":"9220 N 75th St",
    "sg:city":"Milwaukee",
    "sg:classifiers":[
        {
            "category":"Building & Trades",
            "subcategory":"Cleaning & Sanitation",
            "type":"Services"
        }
    ],
    "sg:phone":"+1 414 354 7154",
    "sg:postcode":"53223",
    "sg:province":"WI",
    "sg:tags":[
        "maintenance"
    ],
    "wof:name":"CCC",
    "wof:placetype":"venue"
},
  "geometry": {"coordinates":[-88.002752,43.18591],"type":"Point"}
}