{
  "type": "Feature",
  "properties": {
    "iso:country":"US",
    "sg:address":"813 Ingalls Rd",
    "sg:city":"Menomonie",
    "sg:classifiers":[
        {
            "category":"Building & Trades",
            "subcategory":"Landscaping Services",
            "type":"Services"
        }
    ],
    "sg:phone":"+1 715 232 9229",
    "sg:postcode":"54751",
    "sg:province":"WI",
    "wof:name":"Paradise Green Service",
    "wof:placetype":"venue"
},
  "geometry": {"coordinates":[-91.93934400000001,44.861736],"type":"Point"}
}