{
  "type": "Feature",
  "properties": {
    "iso:country":"US",
    "sg:address":"1851 N 14th Ave",
    "sg:city":"Wausau",
    "sg:classifiers":[
        {
            "category":"Professional",
            "subcategory":"Business Services",
            "type":"Services"
        }
    ],
    "sg:phone":"+1 715 843 9577",
    "sg:postcode":"54401",
    "sg:province":"WI",
    "wof:name":"W K S R A",
    "wof:placetype":"venue"
},
  "geometry": {"coordinates":[-89.6514,44.988199],"type":"Point"}
}