{
  "type": "Feature",
  "properties": {
    "addr:full":"4315 N 66th St Milwaukee WI 53216",
    "addr:housenumber":"4315",
    "addr:postcode":"53216",
    "addr:street":"N 66Th St",
    "iso:country":"US",
    "sg:address":"4315 N 66th St",
    "sg:city":"Milwaukee",
    "sg:classifiers":[
        {
            "category":"Social Services",
            "subcategory":"Job Training",
            "type":"Services"
        }
    ],
    "sg:phone":"+1 414 536 4440",
    "sg:postcode":"53216",
    "sg:province":"WI",
    "wof:name":"Caring Touch Inc A",
    "wof:placetype":"venue"
},
  "geometry": {"coordinates":[-87.994528,43.097003],"type":"Point"}
}