{
  "type": "Feature",
  "properties": {
    "iso:country":"US",
    "sg:address":"3279 S 9th St",
    "sg:city":"Milwaukee",
    "sg:classifiers":[
        {
            "category":"Bars & Pubs",
            "type":"Food & Drink"
        }
    ],
    "sg:phone":"+1 414 294 0802",
    "sg:postcode":"53215",
    "sg:province":"WI",
    "wof:name":"C J's Sports Bar",
    "wof:placetype":"venue"
},
  "geometry": {"coordinates":[-87.922864,42.98614],"type":"Point"}
}