{
  "type": "Feature",
  "properties": {
    "iso:country":"US",
    "sg:address":"1208 Skyview Dr",
    "sg:city":"Neenah",
    "sg:classifiers":[
        {
            "category":"Professional",
            "subcategory":"Computer Services",
            "type":"Services"
        }
    ],
    "sg:phone":"+1 920 729 1083",
    "sg:postcode":"54956",
    "sg:province":"WI",
    "sg:tags":[
        "consultant",
        "designer"
    ],
    "sg:website":"www.gologic.com",
    "wof:name":"Gologic Inc",
    "wof:placetype":"venue"
},
  "geometry": {"coordinates":[-88.44689700000001,44.165731],"type":"Point"}
}