{
  "type": "Feature",
  "properties": {
    "iso:country":"US",
    "sg:address":"26237 W Mondovi St",
    "sg:city":"Eleva",
    "sg:classifiers":[
        {
            "category":"Education",
            "subcategory":"School",
            "type":"Public Place"
        }
    ],
    "sg:phone":"+1 715 287 4217",
    "sg:postcode":"54738",
    "sg:province":"WI",
    "sg:tags":[
        "elementary"
    ],
    "wof:name":"Eleva Elementary School",
    "wof:placetype":"venue"
},
  "geometry": {"coordinates":[-91.472738,44.576102],"type":"Point"}
}