{
  "type": "Feature",
  "properties": {
    "iso:country":"US",
    "sg:address":"2140 Short Rd",
    "sg:city":"De Pere",
    "sg:classifiers":[
        {
            "category":"Manufacturing",
            "subcategory":"Signs",
            "type":"Manufacturing & Wholesale Goods"
        },
        {
            "category":"Professional",
            "subcategory":"Art Services",
            "type":"Services"
        }
    ],
    "sg:phone":"+1 920 347 0319",
    "sg:postcode":"54115",
    "sg:province":"WI",
    "sg:tags":[
        "commercial",
        "design"
    ],
    "wof:name":"Precise Packaging & Graphics",
    "wof:placetype":"venue"
},
  "geometry": {"coordinates":[-88.11955500000001,44.474278],"type":"Point"}
}