{
  "type": "Feature",
  "properties": {
    "addr:full":"575 US Hwy 18 Sullivan WI 53178",
    "addr:housenumber":"575",
    "addr:postcode":"53178",
    "addr:street":"Us Hwy 18",
    "iso:country":"US",
    "sg:address":"575 US Hwy 18",
    "sg:city":"Sullivan",
    "sg:classifiers":[
        {
            "category":"Health Services",
            "subcategory":"Doctor",
            "type":"Services"
        }
    ],
    "sg:phone":"+1 262 593 2820",
    "sg:postcode":"53178",
    "sg:province":"WI",
    "sg:tags":[
        "dentist"
    ],
    "wof:name":"Dale P Falk DDS",
    "wof:placetype":"venue"
},
  "geometry": {"coordinates":[-88.600455,43.012927],"type":"Point"}
}