{
  "type": "Feature",
  "properties": {
    "iso:country":"US",
    "sg:address":"5716 35th Ave",
    "sg:city":"Kenosha",
    "sg:classifiers":[
        {
            "category":"Building & Trades",
            "subcategory":"Construction",
            "type":"Services"
        }
    ],
    "sg:phone":"+1 262 697 7813",
    "sg:postcode":"53144",
    "sg:province":"WI",
    "sg:tags":[
        "concrete",
        "contractor"
    ],
    "wof:name":"Northern Landscape & Concrete",
    "wof:placetype":"venue"
},
  "geometry": {"coordinates":[-87.851311,42.582177],"type":"Point"}
}