{
  "type": "Feature",
  "properties": {
    "iso:country":"US",
    "sg:address":"605 Stewart Ave",
    "sg:city":"Wausau",
    "sg:classifiers":[
        {
            "category":"Building & Trades",
            "subcategory":"Construction",
            "type":"Services"
        }
    ],
    "sg:phone":"+1 715 848 4246",
    "sg:postcode":"54401",
    "sg:province":"WI",
    "sg:tags":[
        "utility",
        "contractor"
    ],
    "wof:name":"American Transmission Co",
    "wof:placetype":"venue"
},
  "geometry": {"coordinates":[-89.644052,44.959199],"type":"Point"}
}