{
  "type": "Feature",
  "properties": {
    "iso:country":"US",
    "sg:address":"7050 Lake Forest Dr",
    "sg:city":"Onalaska",
    "sg:classifiers":[
        {
            "category":"Building & Trades",
            "subcategory":"Construction",
            "type":"Services"
        }
    ],
    "sg:phone":"+1 608 526 4503",
    "sg:postcode":"54650",
    "sg:province":"WI",
    "sg:tags":[
        "business",
        "contractor"
    ],
    "wof:name":"Distinctive Finishes Inc",
    "wof:placetype":"venue"
},
  "geometry": {"coordinates":[-91.25766400000001,43.937421],"type":"Point"}
}