{
  "type": "Feature",
  "properties": {
    "iso:country":"US",
    "sg:address":"7188 Country Side Ln",
    "sg:city":"Elkhorn",
    "sg:classifiers":[
        {
            "category":"Professional",
            "type":"Services"
        }
    ],
    "sg:phone":"+1 262 742 3757",
    "sg:postcode":"53121",
    "sg:province":"WI",
    "wof:name":"Midwest Equine Services",
    "wof:placetype":"venue"
},
  "geometry": {"coordinates":[-88.600184,42.752721],"type":"Point"}
}