{
  "type": "Feature",
  "properties": {
    "iso:country":"US",
    "sg:address":"905 S 21st St",
    "sg:city":"Sheboygan",
    "sg:classifiers":[
        {
            "category":"Retail",
            "subcategory":"Repair Shop",
            "type":"Services"
        },
        {
            "category":"Professional",
            "subcategory":"Business Services",
            "type":"Services"
        }
    ],
    "sg:phone":"+1 920 458 4369",
    "sg:postcode":"53081",
    "sg:province":"WI",
    "sg:tags":[
        "hardware",
        "tool",
        "grinding",
        "mfg"
    ],
    "wof:name":"Mid States Carbide Inc",
    "wof:placetype":"venue"
},
  "geometry": {"coordinates":[-87.734549,43.744424],"type":"Point"}
}