{
  "type": "Feature",
  "properties": {
    "iso:country":"US",
    "sg:address":"8097 Co Rd G",
    "sg:city":"Wonewoc",
    "sg:classifiers":[
        {
            "category":"Food & Beverages",
            "subcategory":"Specialty",
            "type":"Retail Goods"
        }
    ],
    "sg:phone":"+1 608 464 7709",
    "sg:postcode":"53968",
    "sg:province":"WI",
    "sg:tags":[
        "health",
        "diet"
    ],
    "sg:website":"www.thin4lifenow.com",
    "wof:name":"Herbalife Distributor-Thin4lif",
    "wof:placetype":"venue"
},
  "geometry": {"coordinates":[-90.172241,43.693199],"type":"Point"}
}