{
  "type": "Feature",
  "properties": {
    "addr:full":"6671 Tippecanoe Trl Elkhorn WI 53121",
    "addr:postcode":"6671;53121",
    "addr:street":"Tippecanoe Trl",
    "iso:country":"US",
    "sg:address":"6671 Tippecanoe Trl",
    "sg:city":"Elkhorn",
    "sg:classifiers":[
        {
            "category":"Professional",
            "subcategory":"Management & Consulting",
            "type":"Services"
        }
    ],
    "sg:phone":"+1 262 742 3840",
    "sg:postcode":"53121",
    "sg:province":"WI",
    "sg:tags":[
        "food",
        "consultant"
    ],
    "wof:name":"Hallenberg & Associates",
    "wof:placetype":"venue"
},
  "geometry": {"coordinates":[-88.572997,42.732232],"type":"Point"}
}