{
  "type": "Feature",
  "properties": {
    "iso:country":"US",
    "sg:address":"251 E 5th St",
    "sg:city":"Montello",
    "sg:classifiers":[
        {
            "category":"Manufacturing",
            "subcategory":"Electronics",
            "type":"Manufacturing & Wholesale Goods"
        }
    ],
    "sg:phone":"+1 608 297 9244",
    "sg:postcode":"53949",
    "sg:province":"WI",
    "sg:tags":[
        "harness",
        "wire",
        "mfg"
    ],
    "wof:name":"Montello Products",
    "wof:placetype":"venue"
},
  "geometry": {"coordinates":[-89.318297,43.780045],"type":"Point"}
}