{
  "type": "Feature",
  "properties": {
    "addr:full":"512 Willis Ave Ashland WI 54806",
    "addr:housenumber":"512",
    "addr:postcode":"54806",
    "addr:street":"Willis Ave",
    "iso:country":"US",
    "sg:address":"512 Willis Ave",
    "sg:city":"Ashland",
    "sg:classifiers":[
        {
            "category":"Food & Beverages",
            "subcategory":"Candy",
            "type":"Retail Goods"
        }
    ],
    "sg:phone":"+1 715 682 5043",
    "sg:postcode":"54806",
    "sg:province":"WI",
    "sg:tags":[
        "confectionery"
    ],
    "wof:name":"Candy Bouquet",
    "wof:placetype":"venue"
},
  "geometry": {"coordinates":[-90.87452399999999,46.5916],"type":"Point"}
}