{
  "type": "Feature",
  "properties": {
    "iso:country":"US",
    "sg:address":"1008 Ruby Dr",
    "sg:city":"Stetsonville",
    "sg:classifiers":[
        {
            "category":"Farming",
            "subcategory":"Dairy Farm",
            "type":"Manufacturing & Wholesale Goods"
        }
    ],
    "sg:phone":"+1 715 678 2718",
    "sg:postcode":"54480",
    "sg:province":"WI",
    "wof:name":"Pitzke Farms Inc",
    "wof:placetype":"venue"
},
  "geometry": {"coordinates":[-90.25804,45.062602],"type":"Point"}
}