{
  "type": "Feature",
  "properties": {
    "iso:country":"US",
    "sg:address":"3901 Sherman Rd",
    "sg:city":"Wausau",
    "sg:classifiers":[
        {
            "category":"Bars & Pubs",
            "type":"Food & Drink"
        }
    ],
    "sg:phone":"+1 715 845 1547",
    "sg:postcode":"54401",
    "sg:province":"WI",
    "sg:tags":[
        "drinking",
        "eating"
    ],
    "wof:name":"Trails End",
    "wof:placetype":"venue"
},
  "geometry": {"coordinates":[-89.685993,44.949084],"type":"Point"}
}