{
  "type": "Feature",
  "properties": {
    "iso:country":"US",
    "sg:address":"504 2nd Ave",
    "sg:city":"Hollandale",
    "sg:classifiers":[
        {
            "category":"Retail",
            "subcategory":"Auto Repair",
            "type":"Services"
        }
    ],
    "sg:phone":"+1 608 967 2666",
    "sg:postcode":"53544",
    "sg:province":"WI",
    "sg:tags":[
        "scooter",
        "motorcycle",
        "motor"
    ],
    "wof:name":"Pit Bull Choppers Inc",
    "wof:placetype":"venue"
},
  "geometry": {"coordinates":[-89.934741,42.875326],"type":"Point"}
}