{
  "type": "Feature",
  "properties": {
    "iso:country":"US",
    "sg:address":"2706 S 9th St",
    "sg:city":"Sheboygan",
    "sg:classifiers":[
        {
            "category":"Building & Trades",
            "subcategory":"Cleaning & Sanitation",
            "type":"Services"
        }
    ],
    "sg:phone":"+1 920 457 1937",
    "sg:postcode":"53081",
    "sg:province":"WI",
    "sg:tags":[
        "maintenance"
    ],
    "wof:name":"Fresh N Clean Carpet Cleaners",
    "wof:placetype":"venue"
},
  "geometry": {"coordinates":[-87.71488,43.725031],"type":"Point"}
}