{
  "type": "Feature",
  "properties": {
    "iso:country":"US",
    "sg:address":"6951 Co Rd A",
    "sg:city":"Lake Mills",
    "sg:classifiers":[
        {
            "category":"Manufacturing",
            "subcategory":"Wood Products",
            "type":"Manufacturing & Wholesale Goods"
        }
    ],
    "sg:phone":"+1 920 648 3247",
    "sg:postcode":"53551",
    "sg:province":"WI",
    "sg:tags":[
        "household",
        "mfg",
        "furniture"
    ],
    "wof:name":"Man In The Woods",
    "wof:placetype":"venue"
},
  "geometry": {"coordinates":[-88.87387,43.097061],"type":"Point"}
}