{
  "type": "Feature",
  "properties": {
    "iso:country":"US",
    "sg:address":"2214 E 14th St",
    "sg:city":"Superior",
    "sg:classifiers":[
        {
            "category":"Freight",
            "type":"Transportation"
        }
    ],
    "sg:phone":"+1 715 398 5851",
    "sg:postcode":"54880",
    "sg:province":"WI",
    "sg:tags":[
        "operator",
        "local",
        "trucking"
    ],
    "wof:name":"Rivord Trucking",
    "wof:placetype":"venue"
},
  "geometry": {"coordinates":[-92.05926599999999,46.699241],"type":"Point"}
}