{
  "type": "Feature",
  "properties": {
    "iso:country":"US",
    "sg:address":"107 N 3rd St",
    "sg:city":"Waterford",
    "sg:classifiers":[
        {
            "category":"Building & Trades",
            "subcategory":"Construction",
            "type":"Services"
        }
    ],
    "sg:phone":"+1 262 534 2581",
    "sg:postcode":"53185",
    "sg:province":"WI",
    "sg:tags":[
        "contractor"
    ],
    "wof:name":"Dan Essman Masonry Inc",
    "wof:placetype":"venue"
},
  "geometry": {"coordinates":[-88.21047900000001,42.764491],"type":"Point"}
}