{
  "type": "Feature",
  "properties": {
    "iso:country":"US",
    "sg:address":"2107 N 83rd St",
    "sg:city":"Milwaukee",
    "sg:classifiers":[
        {
            "category":"Wholesale",
            "subcategory":"Home Furnishings",
            "type":"Manufacturing & Wholesale Goods"
        }
    ],
    "sg:phone":"+1 414 476 1937",
    "sg:postcode":"53213",
    "sg:province":"WI",
    "wof:name":"Baseco Distributors",
    "wof:placetype":"venue"
},
  "geometry": {"coordinates":[-88.016254,43.057194],"type":"Point"}
}