{
  "type": "Feature",
  "properties": {
    "iso:country":"US",
    "sg:address":"1211 W Main St",
    "sg:city":"Merrill",
    "sg:classifiers":[
        {
            "category":"Retail",
            "subcategory":"Auto Repair",
            "type":"Services"
        }
    ],
    "sg:phone":"+1 715 536 4415",
    "sg:postcode":"54452",
    "sg:province":"WI",
    "sg:tags":[
        "body",
        "shop",
        "automobile",
        "collision",
        "automotive",
        "painting"
    ],
    "wof:name":"K B Body Shop Inc",
    "wof:placetype":"venue"
},
  "geometry": {"coordinates":[-89.716568,45.178806],"type":"Point"}
}