{
  "type": "Feature",
  "properties": {
    "iso:country":"US",
    "sg:address":"1015 Parkway Dr",
    "sg:city":"St Germain",
    "sg:classifiers":[
        {
            "category":"Social Services",
            "subcategory":"Child Care",
            "type":"Services"
        }
    ],
    "sg:phone":"+1 715 479 1471",
    "sg:postcode":"54558",
    "sg:province":"WI",
    "sg:tags":[
        "day"
    ],
    "wof:name":"Little Acorn Lodge Too",
    "wof:placetype":"venue"
},
  "geometry": {"coordinates":[-89.487574,45.898844],"type":"Point"}
}