{
  "type": "Feature",
  "properties": {
    "addr:full":"8725 Camelot Trce Sturtevant WI 53177",
    "addr:housenumber":"8725",
    "addr:postcode":"53177",
    "addr:street":"Camelot Trce",
    "iso:country":"US",
    "sg:address":"8725 Camelot Trce",
    "sg:city":"Sturtevant",
    "sg:classifiers":[
        {
            "category":"Shopping",
            "subcategory":"Shoes",
            "type":"Retail Goods"
        }
    ],
    "sg:phone":"+1 262 886 4329",
    "sg:postcode":"53177",
    "sg:province":"WI",
    "wof:name":"AR Matt LLC",
    "wof:placetype":"venue"
},
  "geometry": {"coordinates":[-87.89149999999999,42.688778],"type":"Point"}
}