{
  "type": "Feature",
  "properties": {
    "addr:full":"344 Division St Park Falls WI 54552",
    "addr:housenumber":"344",
    "addr:postcode":"54552",
    "addr:street":"Division St",
    "iso:country":"US",
    "sg:address":"344 Division St",
    "sg:city":"Park Falls",
    "sg:classifiers":[
        {
            "category":"Home & Garden",
            "subcategory":"Household Appliances",
            "type":"Retail Goods"
        }
    ],
    "sg:phone":"+1 715 762 2086",
    "sg:postcode":"54552",
    "sg:province":"WI",
    "wof:name":"Daves Appliance",
    "wof:placetype":"venue"
},
  "geometry": {"coordinates":[-90.45124800000001,45.935225],"type":"Point"}
}