{
  "type": "Feature",
  "properties": {
    "iso:country":"US",
    "sg:address":"2561 Vinland Rd",
    "sg:city":"Appleton",
    "sg:classifiers":[
        {
            "category":"Local Transit",
            "type":"Transportation"
        }
    ],
    "sg:phone":"+1 920 231 1335",
    "sg:postcode":"54901",
    "sg:province":"WI",
    "sg:tags":[
        "passenger",
        "limousine"
    ],
    "wof:name":"Rare Elegance Limousine",
    "wof:placetype":"venue"
},
  "geometry": {"coordinates":[-88.552801,44.049071],"type":"Point"}
}