{
  "type": "Feature",
  "properties": {
    "iso:country":"US",
    "sg:address":"3755 Gateway Dr",
    "sg:city":"Eau Claire",
    "sg:classifiers":[
        {
            "category":"Shopping",
            "subcategory":"Gifts & Souvenirs",
            "type":"Retail Goods"
        }
    ],
    "sg:phone":"+1 715 834 9663",
    "sg:postcode":"54701",
    "sg:province":"WI",
    "sg:website":"www.factorycard.com",
    "wof:name":"Factory Card Outlet",
    "wof:placetype":"venue"
},
  "geometry": {"coordinates":[-91.43152000000001,44.777798],"type":"Point"}
}