{
  "type": "Feature",
  "properties": {
    "iso:country":"US",
    "sg:address":"4532 80th St",
    "sg:city":"Franksville",
    "sg:phone":"+1 262 878 2292",
    "sg:postcode":"53126",
    "sg:province":"WI",
    "sg:tags":[
        "farm",
        "corn",
        "soybean"
    ],
    "wof:name":"Roger Schattner",
    "wof:placetype":"venue"
},
  "geometry": {"coordinates":[-88.01773300000001,42.763961],"type":"Point"}
}