{
  "type": "Feature",
  "properties": {
    "iso:country":"US",
    "sg:address":"201 W Northland Ave",
    "sg:city":"Appleton",
    "sg:classifiers":[
        {
            "category":"Restaurant",
            "type":"Food & Drink"
        }
    ],
    "sg:menulink":"http://www.allmenus.com/wi/appleton/107877-koreana/menu/",
    "sg:phone":"+1 920 733 3205",
    "sg:postcode":"54911",
    "sg:province":"WI",
    "sg:tags":[
        "korean",
        "asian"
    ],
    "wof:name":"Koreana",
    "wof:placetype":"venue"
},
  "geometry": {"coordinates":[-88.40748499999999,44.287257],"type":"Point"}
}