{
  "type": "Feature",
  "properties": {
    "iso:country":"US",
    "sg:address":"1851 Mushroom Rd",
    "sg:city":"Eden",
    "sg:classifiers":[
        {
            "category":"Farming",
            "subcategory":"Dairy Farm",
            "type":"Manufacturing & Wholesale Goods"
        }
    ],
    "sg:phone":"+1 920 922 5587",
    "sg:postcode":"53019",
    "sg:province":"WI",
    "wof:name":"Ronald Loehr",
    "wof:placetype":"venue"
},
  "geometry": {"coordinates":[-88.26084899999999,43.732264],"type":"Point"}
}