{
  "type": "Feature",
  "properties": {
    "addr:full":"476 Russell St Fond Du Lac WI 54935",
    "addr:housenumber":"476",
    "addr:postcode":"54935",
    "addr:street":"Russell St",
    "iso:country":"US",
    "sg:address":"476 Russell St",
    "sg:city":"Fond Du Lac",
    "sg:classifiers":[
        {
            "category":"Professional",
            "subcategory":"Engineering",
            "type":"Services"
        }
    ],
    "sg:phone":"+1 920 929 9192",
    "sg:postcode":"54935",
    "sg:province":"WI",
    "wof:name":"Drynamics LLC",
    "wof:placetype":"venue"
},
  "geometry": {"coordinates":[-88.46487500000001,43.78115],"type":"Point"}
}