{
  "type": "Feature",
  "properties": {
    "addr:full":"839 N 11th St Milwaukee WI 53233",
    "addr:housenumber":"839",
    "addr:postcode":"53233",
    "addr:street":"N 11Th St",
    "iso:country":"US",
    "sg:address":"839 N 11th St",
    "sg:city":"Milwaukee",
    "sg:classifiers":[
        {
            "category":"Real Estate",
            "subcategory":"Real Estate Agent",
            "type":"Services"
        }
    ],
    "sg:phone":"+1 414 274 6010",
    "sg:postcode":"53233",
    "sg:province":"WI",
    "sg:tags":[
        "residential",
        "property",
        "management"
    ],
    "wof:name":"Suburban Management Company",
    "wof:placetype":"venue"
},
  "geometry": {"coordinates":[-87.92589700000001,43.041494],"type":"Point"}
}