{
  "type": "Feature",
  "properties": {
    "iso:country":"US",
    "sg:address":"1947 110th Ave",
    "sg:city":"Dresser",
    "sg:classifiers":[
        {
            "category":"Organizations",
            "subcategory":"Religious Organization",
            "type":"Services"
        }
    ],
    "sg:phone":"+1 715 755 2562",
    "sg:postcode":"54009",
    "sg:province":"WI",
    "sg:tags":[
        "church"
    ],
    "sg:website":"www.bethesdalutheran.ws",
    "wof:name":"Bethesda Lutheran Church",
    "wof:placetype":"venue"
},
  "geometry": {"coordinates":[-92.559852,45.368002],"type":"Point"}
}