{
  "type": "Feature",
  "properties": {
    "iso:country":"US",
    "sg:address":"9075 Thompson Rd",
    "sg:city":"Marshfield",
    "sg:classifiers":[
        {
            "category":"Freight",
            "type":"Transportation"
        }
    ],
    "sg:phone":"+1 715 676 2132",
    "sg:postcode":"54449",
    "sg:province":"WI",
    "sg:tags":[
        "operator",
        "local",
        "trucking"
    ],
    "wof:name":"Jenkins Trucking",
    "wof:placetype":"venue"
},
  "geometry": {"coordinates":[-90.17321,44.576552],"type":"Point"}
}