{
  "type": "Feature",
  "properties": {
    "iso:country":"US",
    "sg:address":"3540 Oakridge Rd",
    "sg:city":"Neenah",
    "sg:classifiers":[
        {
            "category":"Farming",
            "subcategory":"Livestock Farm",
            "type":"Manufacturing & Wholesale Goods"
        }
    ],
    "sg:phone":"+1 920 836 3459",
    "sg:postcode":"54956",
    "sg:province":"WI",
    "sg:tags":[
        "beef",
        "corn",
        "cash",
        "grain",
        "cattle",
        "feedlot"
    ],
    "wof:name":"Thomas Herrmann",
    "wof:placetype":"venue"
},
  "geometry": {"coordinates":[-88.581605,44.170336],"type":"Point"}
}