{
  "type": "Feature",
  "properties": {
    "iso:country":"US",
    "sg:address":"6818 Chester Dr",
    "sg:city":"Madison",
    "sg:classifiers":[
        {
            "category":"Banks & Credit Unions",
            "subcategory":"Investment Brokerage",
            "type":"Services"
        }
    ],
    "sg:phone":"+1 608 848 2703",
    "sg:postcode":"53719",
    "sg:province":"WI",
    "sg:tags":[
        "advisory"
    ],
    "wof:name":"Randall Investment Group",
    "wof:placetype":"venue"
},
  "geometry": {"coordinates":[-89.501364,43.016801],"type":"Point"}
}