{
  "type": "Feature",
  "properties": {
    "addr:full":"230 State Hwy 35 Fountain City WI 54629",
    "addr:housenumber":"230",
    "addr:postcode":"54629",
    "addr:street":"State Hwy 35",
    "iso:country":"US",
    "sg:address":"230 State Hwy 35",
    "sg:city":"Fountain City",
    "sg:classifiers":[
        {
            "category":"Arts & Performance",
            "subcategory":"Theater",
            "type":"Entertainment"
        }
    ],
    "sg:phone":"+1 608 687 9732",
    "sg:postcode":"54629",
    "sg:province":"WI",
    "sg:tags":[
        "entertainer"
    ],
    "wof:name":"4 Mile Gentlemen's Club",
    "wof:placetype":"venue"
},
  "geometry": {"coordinates":[-91.71496,44.128396],"type":"Point"}
}