{
  "type": "Feature",
  "properties": {
    "iso:country":"US",
    "sg:address":"2158 Atwood Ave",
    "sg:city":"Madison",
    "sg:classifiers":[
        {
            "category":"Recreation",
            "type":"Entertainment"
        }
    ],
    "sg:phone":"+1 608 255 2958",
    "sg:postcode":"53704",
    "sg:province":"WI",
    "wof:name":"Watertrail Adventures",
    "wof:placetype":"venue"
},
  "geometry": {"coordinates":[-89.350165,43.093145],"type":"Point"}
}