{
  "type": "Feature",
  "properties": {
    "iso:country":"US",
    "sg:address":"16436 50th Rd",
    "sg:city":"Franksville",
    "sg:classifiers":[
        {
            "category":"Wholesale",
            "subcategory":"Meat",
            "type":"Manufacturing & Wholesale Goods"
        }
    ],
    "sg:phone":"+1 262 878 3120",
    "sg:postcode":"53126",
    "sg:province":"WI",
    "sg:tags":[
        "poultry",
        "processing"
    ],
    "wof:name":"Bremel Poultry Processing",
    "wof:placetype":"venue"
},
  "geometry": {"coordinates":[-88.000182,42.742067],"type":"Point"}
}