{
  "type": "Feature",
  "properties": {
    "iso:country":"US",
    "sg:address":"5225 W Vliet St",
    "sg:city":"Milwaukee",
    "sg:classifiers":[
        {
            "category":"Recreation",
            "type":"Entertainment"
        }
    ],
    "sg:phone":"+1 414 475 8410",
    "sg:postcode":"53208",
    "sg:province":"WI",
    "sg:tags":[
        "parks"
    ],
    "sg:website":"www.milwaukeerecreation.net",
    "wof:name":"Recreation Dept",
    "wof:placetype":"venue"
},
  "geometry": {"coordinates":[-87.97933500000001,43.049057],"type":"Point"}
}