{
  "type": "Feature",
  "properties": {
    "iso:country":"US",
    "sg:address":"2745 W Layton Ave",
    "sg:city":"Milwaukee",
    "sg:classifiers":[
        {
            "category":"Health Services",
            "subcategory":"Doctor",
            "type":"Services"
        }
    ],
    "sg:phone":"+1 414 281 9600",
    "sg:postcode":"53221",
    "sg:province":"WI",
    "sg:tags":[
        "medical"
    ],
    "wof:name":"Urgi Med Walk In Med Clinic",
    "wof:placetype":"venue"
},
  "geometry": {"coordinates":[-87.950707,42.95933],"type":"Point"}
}