{
  "type": "Feature",
  "properties": {
    "addr:full":"11110 W Bonniwell Rd Mequon WI 53097",
    "addr:housenumber":"11110",
    "addr:postcode":"53097",
    "addr:street":"W Bonniwell Rd",
    "iso:country":"US",
    "sg:address":"11110 W Bonniwell Rd",
    "sg:city":"Mequon",
    "sg:classifiers":[
        {
            "category":"Freight",
            "type":"Transportation"
        }
    ],
    "sg:phone":"+1 262 238 8683",
    "sg:postcode":"53097",
    "sg:province":"WI",
    "sg:tags":[
        "trucking"
    ],
    "wof:name":"Michael Haen Trucking Inc",
    "wof:placetype":"venue"
},
  "geometry": {"coordinates":[-88.047343,43.264895],"type":"Point"}
}