{
  "type": "Feature",
  "properties": {
    "iso:country":"US",
    "sg:address":"124 N Leonard St",
    "sg:city":"West Salem",
    "sg:classifiers":[
        {
            "category":"Recreation",
            "type":"Entertainment"
        }
    ],
    "sg:phone":"+1 608 786 2467",
    "sg:postcode":"54669",
    "sg:province":"WI",
    "wof:name":"Northwods Akf Martial Arts LLC",
    "wof:placetype":"venue"
},
  "geometry": {"coordinates":[-91.08137000000001,43.897743],"type":"Point"}
}