{
  "type": "Feature",
  "properties": {
    "iso:country":"US",
    "sg:address":"511 Bruener Rd",
    "sg:city":"Port Edwards",
    "sg:classifiers":[
        {
            "category":"Home & Garden",
            "subcategory":"Building Materials",
            "type":"Retail Goods"
        }
    ],
    "sg:phone":"+1 715 887 3204",
    "sg:postcode":"54469",
    "sg:province":"WI",
    "sg:tags":[
        "lumber"
    ],
    "wof:name":"James Bruener Timber Products",
    "wof:placetype":"venue"
},
  "geometry": {"coordinates":[-89.86447699999999,44.35841],"type":"Point"}
}