{
  "type": "Feature",
  "properties": {
    "iso:country":"US",
    "sg:address":"3302 State Hwy 35",
    "sg:city":"Maiden Rock",
    "sg:classifiers":[
        {
            "category":"Wholesale",
            "subcategory":"Construction Materials",
            "type":"Manufacturing & Wholesale Goods"
        }
    ],
    "sg:phone":"+1 715 448 3006",
    "sg:postcode":"54750",
    "sg:province":"WI",
    "sg:tags":[
        "sand",
        "gravel"
    ],
    "wof:name":"Wisconsin Industrial Sand",
    "wof:placetype":"venue"
},
  "geometry": {"coordinates":[-92.29503699999999,44.542471],"type":"Point"}
}