{
  "type": "Feature",
  "properties": {
    "iso:country":"US",
    "sg:address":"780 132nd Ave",
    "sg:city":"Hudson",
    "sg:classifiers":[
        {
            "category":"Freight",
            "type":"Transportation"
        }
    ],
    "sg:phone":"+1 715 246 0424",
    "sg:postcode":"54016",
    "sg:province":"WI",
    "sg:tags":[
        "operator",
        "trucking"
    ],
    "wof:name":"Danno Trucking",
    "wof:placetype":"venue"
},
  "geometry": {"coordinates":[-92.639151,45.05374],"type":"Point"}
}