{
  "type": "Feature",
  "properties": {
    "addr:full":"609 N Main St Lodi WI 53555",
    "addr:housenumber":"609",
    "addr:postcode":"53555",
    "addr:street":"N Main St",
    "iso:country":"US",
    "sg:address":"609 N Main St",
    "sg:city":"Lodi",
    "sg:classifiers":[
        {
            "category":"Autos & Motor Vehicles",
            "subcategory":"Auto Supplies",
            "type":"Retail Goods"
        }
    ],
    "sg:phone":"+1 608 592 3831",
    "sg:postcode":"53555",
    "sg:province":"WI",
    "sg:tags":[
        "automobile",
        "parts"
    ],
    "wof:name":"Tom's Auto Parts",
    "wof:placetype":"venue"
},
  "geometry": {"coordinates":[-89.5339,43.320321],"type":"Point"}
}