{
  "type": "Feature",
  "properties": {
    "iso:country":"US",
    "sg:address":"611 W Wisconsin Ave",
    "sg:city":"Kaukauna",
    "sg:classifiers":[
        {
            "category":"Restaurant",
            "type":"Food & Drink"
        }
    ],
    "sg:phone":"+1 920 759 2971",
    "sg:postcode":"54130",
    "sg:province":"WI",
    "wof:name":"Taco Bell",
    "wof:placetype":"venue"
},
  "geometry": {"coordinates":[-88.27651,44.284621],"type":"Point"}
}