{
  "type": "Feature",
  "properties": {
    "iso:country":"US",
    "sg:address":"160 Westgate Mall",
    "sg:city":"Madison",
    "sg:classifiers":[
        {
            "category":"Education",
            "subcategory":"Dance Studio",
            "type":"Public Place"
        }
    ],
    "sg:phone":"+1 608 278 1600",
    "sg:postcode":"53711",
    "sg:province":"WI",
    "sg:tags":[
        "instruction",
        "dancing"
    ],
    "wof:name":"Madison Ballet",
    "wof:placetype":"venue"
},
  "geometry": {"coordinates":[-89.471874,43.051955],"type":"Point"}
}