{
  "type": "Feature",
  "properties": {
    "addr:full":"270 Broad St Lake Geneva WI 53147",
    "addr:housenumber":"270",
    "addr:postcode":"53147",
    "addr:street":"Broad St",
    "iso:country":"US",
    "sg:address":"270 Broad St",
    "sg:city":"Lake Geneva",
    "sg:classifiers":[
        {
            "category":"Shopping",
            "subcategory":"Gifts & Souvenirs",
            "type":"Retail Goods"
        }
    ],
    "sg:phone":"+1 262 248 8999",
    "sg:postcode":"53147",
    "sg:province":"WI",
    "sg:tags":[
        "shop"
    ],
    "wof:name":"Artopia",
    "wof:placetype":"venue"
},
  "geometry": {"coordinates":[-88.435249,42.592734],"type":"Point"}
}