{
  "type": "Feature",
  "properties": {
    "addr:full":"520 University Ave Madison WI 53703",
    "addr:housenumber":"520",
    "addr:postcode":"53703",
    "addr:street":"University Ave",
    "iso:country":"US",
    "sg:address":"520 University Ave",
    "sg:city":"Madison",
    "sg:classifiers":[
        {
            "category":"Communications",
            "subcategory":"Film & Video Production",
            "type":"Services"
        }
    ],
    "sg:phone":"+1 608 442 6338",
    "sg:postcode":"53703",
    "sg:province":"WI",
    "sg:tags":[
        "taping"
    ],
    "wof:name":"Zoom Communications",
    "wof:placetype":"venue"
},
  "geometry": {"coordinates":[-89.395448,43.07326],"type":"Point"}
}