{
  "type": "Feature",
  "properties": {
    "iso:country":"US",
    "sg:address":"200 Wisconsin Ave",
    "sg:city":"Marshfield",
    "sg:classifiers":[
        {
            "category":"Building & Trades",
            "subcategory":"Construction",
            "type":"Services"
        }
    ],
    "sg:phone":"+1 715 687 2421",
    "sg:postcode":"54449",
    "sg:province":"WI",
    "sg:tags":[
        "silo"
    ],
    "wof:name":"Foxland Harvestore",
    "wof:placetype":"venue"
},
  "geometry": {"coordinates":[-90.186667,44.669947],"type":"Point"}
}