{
  "type": "Feature",
  "properties": {
    "iso:country":"US",
    "sg:address":"2839 Wyldewood Rd",
    "sg:city":"Oshkosh",
    "sg:classifiers":[
        {
            "category":"Building & Trades",
            "subcategory":"Construction",
            "type":"Services"
        }
    ],
    "sg:phone":"+1 920 233 4425",
    "sg:postcode":"54904",
    "sg:province":"WI",
    "sg:tags":[
        "house"
    ],
    "wof:name":"Blue Ribbon Construction",
    "wof:placetype":"venue"
},
  "geometry": {"coordinates":[-88.603062,44.021276],"type":"Point"}
}