{
  "type": "Feature",
  "properties": {
    "addr:full":"3140 Edmonton Dr Sun Prairie WI 53590",
    "addr:housenumber":"3140",
    "addr:postcode":"53590",
    "addr:street":"Edmonton Dr",
    "iso:country":"US",
    "sg:address":"3140 Edmonton Dr",
    "sg:city":"Sun Prairie",
    "sg:classifiers":[
        {
            "category":"Banks & Credit Unions",
            "subcategory":"Investment Brokerage",
            "type":"Services"
        }
    ],
    "sg:phone":"+1 608 825 8135",
    "sg:postcode":"53590",
    "sg:province":"WI",
    "sg:tags":[
        "security"
    ],
    "wof:name":"Andrew Coopman Invstmt",
    "wof:placetype":"venue"
},
  "geometry": {"coordinates":[-89.278234,43.188254],"type":"Point"}
}