{
  "type": "Feature",
  "properties": {
    "addr:full":"5900 N Port Washington Rd Milwaukee WI 53217",
    "addr:housenumber":"5900",
    "addr:postcode":"53217",
    "addr:street":"N Port Washington Rd",
    "iso:country":"US",
    "sg:address":"5900 N Port Washington Rd",
    "sg:city":"Milwaukee",
    "sg:classifiers":[
        {
            "category":"Restaurant",
            "type":"Food & Drink"
        }
    ],
    "sg:phone":"+1 414 963 0100",
    "sg:postcode":"53217",
    "sg:province":"WI",
    "sg:website":"www.whgonline.com",
    "wof:name":"Applebee's Neighborhood Grill",
    "wof:placetype":"venue"
},
  "geometry": {"coordinates":[-87.91653100000001,43.118908],"type":"Point"}
}