{
  "type": "Feature",
  "properties": {
    "iso:country":"US",
    "sg:address":"933 S Midvale Blvd",
    "sg:city":"Madison",
    "sg:classifiers":[
        {
            "category":"Insurance",
            "subcategory":"Insurance Agent",
            "type":"Services"
        }
    ],
    "sg:phone":"+1 608 274 3830",
    "sg:postcode":"53711",
    "sg:province":"WI",
    "wof:name":"Ward Insurance",
    "wof:placetype":"venue"
},
  "geometry": {"coordinates":[-89.45106800000001,43.043513],"type":"Point"}
}