{
  "type": "Feature",
  "properties": {
    "iso:country":"US",
    "sg:address":"8101 Portland Ave",
    "sg:city":"Milwaukee",
    "sg:classifiers":[
        {
            "category":"Health Services",
            "subcategory":"Clinic",
            "type":"Services"
        }
    ],
    "sg:phone":"+1 414 258 9959",
    "sg:postcode":"53213",
    "sg:province":"WI",
    "sg:tags":[
        "home",
        "agency",
        "employment",
        "care"
    ],
    "sg:website":"www.healthcarerealm.com",
    "wof:name":"Health Care Realm Inc",
    "wof:placetype":"venue"
},
  "geometry": {"coordinates":[-88.01552100000001,43.043248],"type":"Point"}
}