{
  "type": "Feature",
  "properties": {
    "addr:full":"1672 Basel Ln Gleason WI 54435",
    "addr:postcode":"1672;54435",
    "addr:street":"Basel Ln",
    "iso:country":"US",
    "sg:address":"1672 Basel Ln",
    "sg:city":"Gleason",
    "sg:classifiers":[
        {
            "category":"Shopping",
            "type":"Retail Goods"
        }
    ],
    "sg:phone":"+1 715 873 4083",
    "sg:postcode":"54435",
    "sg:province":"WI",
    "sg:tags":[
        "merchandise"
    ],
    "wof:name":"Northwoods Tractors & Auctions",
    "wof:placetype":"venue"
},
  "geometry": {"coordinates":[-89.502698,45.322769],"type":"Point"}
}