{
  "type": "Feature",
  "properties": {
    "iso:country":"US",
    "sg:address":"1819 N Ballard Rd",
    "sg:city":"Appleton",
    "sg:classifiers":[
        {
            "category":"Real Estate",
            "subcategory":"Real Estate Operator",
            "type":"Services"
        }
    ],
    "sg:phone":"+1 920 832 8580",
    "sg:postcode":"54911",
    "sg:province":"WI",
    "sg:tags":[
        "building",
        "nonresidential"
    ],
    "wof:name":"D Jon Properties LLC",
    "wof:placetype":"venue"
},
  "geometry": {"coordinates":[-88.374993,44.278315],"type":"Point"}
}