{
  "type": "Feature",
  "properties": {
    "iso:country":"US",
    "sg:address":"1740 Cornell Rd",
    "sg:city":"Green Bay",
    "sg:classifiers":[
        {
            "category":"Wholesale",
            "subcategory":"Construction Materials",
            "type":"Manufacturing & Wholesale Goods"
        },
        {
            "category":"Home & Garden",
            "subcategory":"Building Materials",
            "type":"Retail Goods"
        }
    ],
    "sg:phone":"+1 920 434 5302",
    "sg:postcode":"54313",
    "sg:province":"WI",
    "sg:tags":[
        "siding"
    ],
    "wof:name":"A S Distributors Inc",
    "wof:placetype":"venue"
},
  "geometry": {"coordinates":[-88.068927,44.590169],"type":"Point"}
}