{
  "type": "Feature",
  "properties": {
    "iso:country":"US",
    "sg:address":"23566 Adams St",
    "sg:city":"Independence",
    "sg:classifiers":[
        {
            "category":"Personal",
            "subcategory":"Beauty Salon",
            "type":"Services"
        }
    ],
    "sg:phone":"+1 715 985 3733",
    "sg:postcode":"54747",
    "sg:province":"WI",
    "sg:tags":[
        "shop"
    ],
    "wof:name":"Olde Mill Hair Salon & Tanning",
    "wof:placetype":"venue"
},
  "geometry": {"coordinates":[-91.42074700000001,44.35746],"type":"Point"}
}