{
  "type": "Feature",
  "properties": {
    "iso:country":"US",
    "sg:address":"1012 Laird St",
    "sg:city":"Marshfield",
    "sg:classifiers":[
        {
            "category":"Health Services",
            "subcategory":"Health Practitioner",
            "type":"Services"
        }
    ],
    "sg:phone":"+1 715 389 2557",
    "sg:postcode":"54449",
    "sg:province":"WI",
    "wof:name":"AJK LLC",
    "wof:placetype":"venue"
},
  "geometry": {"coordinates":[-90.186984,44.681562],"type":"Point"}
}