{
  "type": "Feature",
  "properties": {
    "addr:full":"300 Grace St Waupun WI 53963",
    "addr:housenumber":"300",
    "addr:postcode":"53963",
    "addr:street":"Grace St",
    "iso:country":"US",
    "sg:address":"300 Grace St",
    "sg:city":"Waupun",
    "sg:classifiers":[
        {
            "category":"Personal",
            "subcategory":"Beauty Salon",
            "type":"Services"
        }
    ],
    "sg:phone":"+1 920 324 5647",
    "sg:postcode":"53963",
    "sg:province":"WI",
    "sg:tags":[
        "shop"
    ],
    "wof:name":"Nail Spa",
    "wof:placetype":"venue"
},
  "geometry": {"coordinates":[-88.741327,43.629914],"type":"Point"}
}