{
  "type": "Feature",
  "properties": {
    "iso:country":"US",
    "sg:address":"529 W Main St",
    "sg:city":"Sun Prairie",
    "sg:classifiers":[
        {
            "category":"Restaurant",
            "type":"Food & Drink"
        }
    ],
    "sg:phone":"+1 608 837 4700",
    "sg:postcode":"53590",
    "sg:province":"WI",
    "sg:tags":[
        "eating"
    ],
    "wof:name":"Java Jungle",
    "wof:placetype":"venue"
},
  "geometry": {"coordinates":[-89.221873,43.183007],"type":"Point"}
}