{
  "type": "Feature",
  "properties": {
    "iso:country":"US",
    "sg:address":"3845 Douglas Ave",
    "sg:city":"Racine",
    "sg:classifiers":[
        {
            "category":"Health Services",
            "subcategory":"Chiropractor",
            "type":"Services"
        }
    ],
    "sg:phone":"+1 262 639 9514",
    "sg:postcode":"53402",
    "sg:province":"WI",
    "wof:name":"Racine Chiropractic Inc",
    "wof:placetype":"venue"
},
  "geometry": {"coordinates":[-87.802567,42.768094],"type":"Point"}
}