{
  "type": "Feature",
  "properties": {
    "addr:full":"2900 Mary St Marinette WI 54143",
    "addr:housenumber":"2900",
    "addr:postcode":"54143",
    "addr:street":"Mary St",
    "iso:country":"US",
    "sg:address":"2900 Mary St",
    "sg:city":"Marinette",
    "sg:classifiers":[
        {
            "category":"Manufacturing",
            "subcategory":"Glass & Minerals",
            "type":"Manufacturing & Wholesale Goods"
        }
    ],
    "sg:phone":"+1 715 735 3443",
    "sg:postcode":"54143",
    "sg:province":"WI",
    "sg:tags":[
        "concrete",
        "product",
        "mfg"
    ],
    "wof:name":"Tri County Precast LLC",
    "wof:placetype":"venue"
},
  "geometry": {"coordinates":[-87.651017,45.08939],"type":"Point"}
}