{
  "type": "Feature",
  "properties": {
    "iso:country":"US",
    "sg:address":"4950 N 20th St",
    "sg:city":"Milwaukee",
    "sg:classifiers":[
        {
            "category":"Building & Trades",
            "subcategory":"Construction",
            "type":"Services"
        }
    ],
    "sg:phone":"+1 414 263 0163",
    "sg:postcode":"53209",
    "sg:province":"WI",
    "sg:tags":[
        "shelter"
    ],
    "wof:name":"Resurrection House Inc",
    "wof:placetype":"venue"
},
  "geometry": {"coordinates":[-87.936503,43.107371],"type":"Point"}
}