{
  "type": "Feature",
  "properties": {
    "iso:country":"US",
    "sg:address":"3104 W Wells St",
    "sg:city":"Milwaukee",
    "sg:classifiers":[
        {
            "category":"Personal",
            "subcategory":"Beauty Salon",
            "type":"Services"
        }
    ],
    "sg:phone":"+1 414 933 2898",
    "sg:postcode":"53208",
    "sg:province":"WI",
    "sg:tags":[
        "shop"
    ],
    "wof:name":"Wendella's Hair",
    "wof:placetype":"venue"
},
  "geometry": {"coordinates":[-87.954345,43.040367],"type":"Point"}
}