{
  "type": "Feature",
  "properties": {
    "iso:country":"US",
    "sg:address":"10340 Knoll Ct",
    "sg:city":"Mukwonago",
    "sg:classifiers":[
        {
            "category":"Building & Trades",
            "subcategory":"Landscaping Services",
            "type":"Services"
        }
    ],
    "sg:phone":"+1 262 363 5868",
    "sg:postcode":"53149",
    "sg:province":"WI",
    "wof:name":"Howell Landscape Services",
    "wof:placetype":"venue"
},
  "geometry": {"coordinates":[-88.36431399999999,42.856394],"type":"Point"}
}