{
  "type": "Feature",
  "properties": {
    "iso:country":"US",
    "sg:address":"201 State St",
    "sg:city":"La Crosse",
    "sg:classifiers":[
        {
            "category":"Communications",
            "subcategory":"Radio Station",
            "type":"Services"
        }
    ],
    "sg:phone":"+1 608 796 2595",
    "sg:postcode":"54601",
    "sg:province":"WI",
    "sg:tags":[
        "company",
        "broadcasting"
    ],
    "wof:name":"WTRV The River",
    "wof:placetype":"venue"
},
  "geometry": {"coordinates":[-91.251899,43.813766],"type":"Point"}
}