{
  "type": "Feature",
  "properties": {
    "iso:country":"US",
    "sg:address":"1740 108th St",
    "sg:city":"Balsam Lake",
    "sg:classifiers":[
        {
            "category":"Professional",
            "subcategory":"Engineering",
            "type":"Services"
        }
    ],
    "sg:phone":"+1 715 857 5433",
    "sg:postcode":"54810",
    "sg:province":"WI",
    "wof:name":"Aviation Resource",
    "wof:placetype":"venue"
},
  "geometry": {"coordinates":[-92.382103,45.455953],"type":"Point"}
}