{
  "type": "Feature",
  "properties": {
    "iso:country":"US",
    "sg:address":"231 W Weiland Ave",
    "sg:city":"Appleton",
    "sg:classifiers":[
        {
            "category":"Professional",
            "subcategory":"Business Services",
            "type":"Services"
        }
    ],
    "sg:phone":"+1 920 731 8238",
    "sg:postcode":"54911",
    "sg:province":"WI",
    "wof:name":"Kennedy Appraisals",
    "wof:placetype":"venue"
},
  "geometry": {"coordinates":[-88.40886500000001,44.285895],"type":"Point"}
}