{
  "type": "Feature",
  "properties": {
    "iso:country":"US",
    "sg:address":"710 Dekalb St",
    "sg:city":"Wausau",
    "sg:classifiers":[
        {
            "category":"Professional",
            "subcategory":"Management & Consulting",
            "type":"Services"
        }
    ],
    "sg:phone":"+1 715 848 1024",
    "sg:postcode":"54403",
    "sg:province":"WI",
    "wof:name":"Ask Management LLC",
    "wof:placetype":"venue"
},
  "geometry": {"coordinates":[-89.619276,44.96882],"type":"Point"}
}