{
  "type": "Feature",
  "properties": {
    "iso:country":"US",
    "sg:address":"360 E Birch Ave",
    "sg:city":"Barron",
    "sg:classifiers":[
        {
            "category":"Real Estate",
            "subcategory":"Real Estate Operator",
            "type":"Services"
        }
    ],
    "sg:phone":"+1 715 637 7086",
    "sg:postcode":"54812",
    "sg:province":"WI",
    "sg:tags":[
        "building",
        "apartment"
    ],
    "wof:name":"Nickel River Properties",
    "wof:placetype":"venue"
},
  "geometry": {"coordinates":[-91.856964,45.408173],"type":"Point"}
}