{
  "type": "Feature",
  "properties": {
    "iso:country":"US",
    "sg:address":"727 Water Ave",
    "sg:city":"Hillsboro",
    "sg:classifiers":[
        {
            "category":"Shopping",
            "subcategory":"Pharmacy",
            "type":"Retail Goods"
        }
    ],
    "sg:phone":"+1 608 489 3141",
    "sg:postcode":"54634",
    "sg:province":"WI",
    "sg:website":"www.petersonpharmacy.com",
    "wof:name":"Peterson Pharmacy",
    "wof:placetype":"venue"
},
  "geometry": {"coordinates":[-90.33985,43.650892],"type":"Point"}
}