{
  "type": "Feature",
  "properties": {
    "iso:country":"US",
    "sg:address":"201 E Verona Ave",
    "sg:city":"Verona",
    "sg:classifiers":[
        {
            "category":"Food & Beverages",
            "subcategory":"Groceries & Convenience Stores",
            "type":"Retail Goods"
        }
    ],
    "sg:phone":"+1 608 845 8997",
    "sg:postcode":"53593",
    "sg:province":"WI",
    "wof:name":"KWIK Trip",
    "wof:placetype":"venue"
},
  "geometry": {"coordinates":[-89.530898,42.991353],"type":"Point"}
}