{
  "type": "Feature",
  "properties": {
    "iso:country":"US",
    "sg:address":"3308 US Hwy 18",
    "sg:city":"Helenville",
    "sg:classifiers":[
        {
            "category":"Banks & Credit Unions",
            "subcategory":"Bank",
            "type":"Services"
        }
    ],
    "sg:phone":"+1 920 674 5830",
    "sg:postcode":"53137",
    "sg:province":"WI",
    "wof:name":"American National Bank",
    "wof:placetype":"venue"
},
  "geometry": {"coordinates":[-88.703451,43.012976],"type":"Point"}
}