{
  "type": "Feature",
  "properties": {
    "iso:country":"US",
    "sg:address":"1301 N 24th St",
    "sg:city":"Manitowoc",
    "sg:classifiers":[
        {
            "category":"Social Services",
            "subcategory":"Adult Care",
            "type":"Services"
        }
    ],
    "sg:phone":"+1 920 684 4031",
    "sg:postcode":"54220",
    "sg:province":"WI",
    "sg:tags":[
        "home",
        "group"
    ],
    "wof:name":"Lighthouse Home",
    "wof:placetype":"venue"
},
  "geometry": {"coordinates":[-87.681242,44.114649],"type":"Point"}
}