{
  "type": "Feature",
  "properties": {
    "iso:country":"US",
    "sg:address":"107 W Vinal St",
    "sg:city":"Wittenberg",
    "sg:classifiers":[
        {
            "category":"Professional",
            "subcategory":"Engineering",
            "type":"Services"
        }
    ],
    "sg:phone":"+1 715 253 3663",
    "sg:postcode":"54499",
    "sg:province":"WI",
    "sg:tags":[
        "engineer"
    ],
    "wof:name":"Kapur & Assoc Inc",
    "wof:placetype":"venue"
},
  "geometry": {"coordinates":[-89.168508,44.823485],"type":"Point"}
}