{
  "type": "Feature",
  "properties": {
    "iso:country":"US",
    "sg:address":"3325 Co Rd T T",
    "sg:city":"Columbus",
    "sg:classifiers":[
        {
            "category":"Wholesale",
            "subcategory":"Farm Supplies",
            "type":"Manufacturing & Wholesale Goods"
        }
    ],
    "sg:phone":"+1 920 623 2645",
    "sg:postcode":"53925",
    "sg:province":"WI",
    "sg:tags":[
        "feed",
        "concentrate",
        "supplement"
    ],
    "wof:name":"Priority One",
    "wof:placetype":"venue"
},
  "geometry": {"coordinates":[-88.95628000000001,43.318016],"type":"Point"}
}