{
  "type": "Feature",
  "properties": {
    "iso:country":"US",
    "sg:address":"11603 Felland Rd",
    "sg:city":"Livingston",
    "sg:classifiers":[
        {
            "category":"Farming",
            "subcategory":"Farm",
            "type":"Manufacturing & Wholesale Goods"
        }
    ],
    "sg:phone":"+1 608 943 8479",
    "sg:postcode":"53554",
    "sg:province":"WI",
    "sg:tags":[
        "crop",
        "general"
    ],
    "wof:name":"David W Divine",
    "wof:placetype":"venue"
},
  "geometry": {"coordinates":[-90.447634,42.914763],"type":"Point"}
}