{
  "type": "Feature",
  "properties": {
    "iso:country":"US",
    "sg:address":"1824 Hobbs Dr",
    "sg:city":"Delavan",
    "sg:classifiers":[
        {
            "category":"Manufacturing",
            "subcategory":"Building Materials",
            "type":"Manufacturing & Wholesale Goods"
        }
    ],
    "sg:phone":"+1 262 728 8460",
    "sg:postcode":"53115",
    "sg:province":"WI",
    "sg:tags":[
        "product",
        "wood",
        "special",
        "mfg"
    ],
    "wof:name":"Woodstar Products Inc",
    "wof:placetype":"venue"
},
  "geometry": {"coordinates":[-88.61063,42.638004],"type":"Point"}
}