{
  "type": "Feature",
  "properties": {
    "iso:country":"US",
    "sg:address":"14266 Co Rd P",
    "sg:city":"Owen",
    "sg:classifiers":[
        {
            "category":"Farming",
            "subcategory":"Livestock Farm",
            "type":"Manufacturing & Wholesale Goods"
        }
    ],
    "sg:phone":"+1 715 229 4025",
    "sg:postcode":"54460",
    "sg:province":"WI",
    "sg:tags":[
        "egg",
        "beef",
        "feedlot",
        "cattle"
    ],
    "wof:name":"Buss Albert",
    "wof:placetype":"venue"
},
  "geometry": {"coordinates":[-90.495724,44.943776],"type":"Point"}
}