{
  "type": "Feature",
  "properties": {
    "iso:country":"US",
    "sg:address":"1411 Larson St",
    "sg:city":"Bloomer",
    "sg:classifiers":[
        {
            "category":"Retail",
            "subcategory":"Auto Repair",
            "type":"Services"
        }
    ],
    "sg:phone":"+1 715 568 3061",
    "sg:postcode":"54724",
    "sg:province":"WI",
    "sg:tags":[
        "body"
    ],
    "wof:name":"Tee-Jay Body Shop Inc",
    "wof:placetype":"venue"
},
  "geometry": {"coordinates":[-91.487593,45.102292],"type":"Point"}
}