{
  "type": "Feature",
  "properties": {
    "iso:country":"US",
    "sg:address":"102 Washburn St",
    "sg:city":"Camp Douglas",
    "sg:classifiers":[
        {
            "category":"Government",
            "subcategory":"Office",
            "type":"Public Place"
        }
    ],
    "sg:phone":"+1 608 427 3255",
    "sg:postcode":"54618",
    "sg:province":"WI",
    "sg:tags":[
        "village"
    ],
    "wof:name":"Village Maintenance Shop",
    "wof:placetype":"venue"
},
  "geometry": {"coordinates":[-90.267013,43.918457],"type":"Point"}
}