{
  "type": "Feature",
  "properties": {
    "iso:country":"US",
    "sg:address":"3500 308th Ave",
    "sg:city":"Burlington",
    "sg:classifiers":[
        {
            "category":"Farming",
            "subcategory":"Dairy Farm",
            "type":"Manufacturing & Wholesale Goods"
        }
    ],
    "sg:phone":"+1 262 537 4941",
    "sg:postcode":"53105",
    "sg:province":"WI",
    "wof:name":"Country View Farm",
    "wof:placetype":"venue"
},
  "geometry": {"coordinates":[-88.183515,42.6035],"type":"Point"}
}