{
  "type": "Feature",
  "properties": {
    "iso:country":"US",
    "sg:address":"218 S Main St",
    "sg:city":"Waupaca",
    "sg:classifiers":[
        {
            "category":"Cinema",
            "subcategory":"Movie Theater",
            "type":"Entertainment"
        }
    ],
    "sg:phone":"+1 715 258 2510",
    "sg:postcode":"54981",
    "sg:province":"WI",
    "sg:tags":[
        "building",
        "picture",
        "motion",
        "operator",
        "nonresidential"
    ],
    "wof:name":"Rosa Theatre",
    "wof:placetype":"venue"
},
  "geometry": {"coordinates":[-89.08496700000001,44.35688],"type":"Point"}
}