{
  "type": "Feature",
  "properties": {
    "iso:country":"US",
    "sg:address":"771 E Imperial Dr",
    "sg:city":"Hartland",
    "sg:classifiers":[
        {
            "category":"Building & Trades",
            "subcategory":"Construction",
            "type":"Services"
        }
    ],
    "sg:phone":"+1 262 367 4943",
    "sg:postcode":"53029",
    "sg:province":"WI",
    "sg:tags":[
        "concrete",
        "contractor"
    ],
    "wof:name":"Southeastern Concrete Co Inc",
    "wof:placetype":"venue"
},
  "geometry": {"coordinates":[-88.332121,43.091712],"type":"Point"}
}