{
  "type": "Feature",
  "properties": {
    "iso:country":"US",
    "sg:address":"9051 E Lake Ave",
    "sg:city":"Solon Springs",
    "sg:classifiers":[
        {
            "category":"Health Services",
            "subcategory":"Clinic",
            "type":"Services"
        }
    ],
    "sg:phone":"+1 715 378 2121",
    "sg:postcode":"54873",
    "sg:province":"WI",
    "wof:name":"Duluth Clinic- Solon Sprgs",
    "wof:placetype":"venue"
},
  "geometry": {"coordinates":[-91.82881,46.347727],"type":"Point"}
}