{
  "type": "Feature",
  "properties": {
    "iso:country":"US",
    "sg:address":"2558 Wrenwood Ln",
    "sg:city":"Neenah",
    "sg:classifiers":[
        {
            "category":"Building & Trades",
            "subcategory":"Construction",
            "type":"Services"
        }
    ],
    "sg:phone":"+1 920 969 9527",
    "sg:postcode":"54956",
    "sg:province":"WI",
    "sg:tags":[
        "house"
    ],
    "wof:name":"Cedar Bay Construction",
    "wof:placetype":"venue"
},
  "geometry": {"coordinates":[-88.53227800000001,44.238089],"type":"Point"}
}