{
  "type": "Feature",
  "properties": {
    "iso:country":"US",
    "sg:address":"3452 Farrell Rd",
    "sg:city":"Kaukauna",
    "sg:phone":"+1 920 766 5076",
    "sg:postcode":"54130",
    "sg:province":"WI",
    "sg:tags":[
        "farm",
        "corn"
    ],
    "wof:name":"Robert Oudenhoven",
    "wof:placetype":"venue"
},
  "geometry": {"coordinates":[-88.242031,44.362677],"type":"Point"}
}