{
  "type": "Feature",
  "properties": {
    "iso:country":"US",
    "sg:address":"24 Enterprise Rd",
    "sg:city":"Delafield",
    "sg:classifiers":[
        {
            "category":"Retail",
            "subcategory":"Animal Services",
            "type":"Services"
        }
    ],
    "sg:phone":"+1 262 646 7529",
    "sg:postcode":"53018",
    "sg:province":"WI",
    "sg:tags":[
        "pet",
        "boarding",
        "sitting"
    ],
    "wof:name":"Pooch Playhouse",
    "wof:placetype":"venue"
},
  "geometry": {"coordinates":[-88.419358,43.056315],"type":"Point"}
}