{
  "type": "Feature",
  "properties": {
    "iso:country":"US",
    "sg:address":"16450 W National Ave",
    "sg:city":"New Berlin",
    "sg:classifiers":[
        {
            "category":"Government",
            "subcategory":"Office",
            "type":"Public Place"
        }
    ],
    "sg:phone":"+1 262 786 7086",
    "sg:postcode":"53151",
    "sg:province":"WI",
    "sg:tags":[
        "govt",
        "city"
    ],
    "sg:website":"www.newberlin.org",
    "wof:name":"New Berlin Water Utility",
    "wof:placetype":"venue"
},
  "geometry": {"coordinates":[-88.11823099999999,42.970141],"type":"Point"}
}