{
  "type": "Feature",
  "properties": {
    "iso:country":"US",
    "sg:address":"8440 Old Military Rd",
    "sg:city":"Three Lakes",
    "sg:classifiers":[
        {
            "category":"Professional",
            "subcategory":"Management & Consulting",
            "type":"Services"
        }
    ],
    "sg:phone":"+1 715 546 3221",
    "sg:postcode":"54562",
    "sg:province":"WI",
    "sg:tags":[
        "business"
    ],
    "wof:name":"Lakeland Associates Inc",
    "wof:placetype":"venue"
},
  "geometry": {"coordinates":[-89.073798,45.854786],"type":"Point"}
}