{
  "type": "Feature",
  "properties": {
    "iso:country":"US",
    "sg:address":"4930 S 78th St",
    "sg:city":"Milwaukee",
    "sg:classifiers":[
        {
            "category":"Real Estate",
            "subcategory":"Real Estate Operator",
            "type":"Services"
        }
    ],
    "sg:phone":"+1 414 817 9588",
    "sg:postcode":"53220",
    "sg:province":"WI",
    "sg:tags":[
        "building",
        "nonresidential"
    ],
    "wof:name":"Hafiz Abdul",
    "wof:placetype":"venue"
},
  "geometry": {"coordinates":[-88.01015200000001,42.955546],"type":"Point"}
}