{
  "type": "Feature",
  "properties": {
    "iso:country":"US",
    "sg:address":"305 C P Ave",
    "sg:city":"Lake Mills",
    "sg:classifiers":[
        {
            "category":"Manufacturing",
            "subcategory":"Metals",
            "type":"Manufacturing & Wholesale Goods"
        }
    ],
    "sg:phone":"+1 920 648 8125",
    "sg:postcode":"53551",
    "sg:province":"WI",
    "sg:website":"www.chap2.com",
    "wof:name":"Chapter 2",
    "wof:placetype":"venue"
},
  "geometry": {"coordinates":[-88.898371,43.076304],"type":"Point"}
}