{
  "type": "Feature",
  "properties": {
    "addr:full":"1012 8th St Reedsburg WI 53959",
    "addr:housenumber":"1012",
    "addr:postcode":"53959",
    "addr:street":"8Th St",
    "iso:country":"US",
    "sg:address":"1012 8th St",
    "sg:city":"Reedsburg",
    "sg:classifiers":[
        {
            "category":"Real Estate",
            "subcategory":"Real Estate Operator",
            "type":"Services"
        }
    ],
    "sg:phone":"+1 608 524 2966",
    "sg:postcode":"53959",
    "sg:province":"WI",
    "sg:tags":[
        "property",
        "lessor"
    ],
    "wof:name":"Sandra Molitor",
    "wof:placetype":"venue"
},
  "geometry": {"coordinates":[-89.996219,43.539622],"type":"Point"}
}