{
  "type": "Feature",
  "properties": {
    "iso:country":"US",
    "sg:address":"100 W Mason St",
    "sg:city":"Green Bay",
    "sg:classifiers":[
        {
            "category":"Marine",
            "type":"Transportation"
        }
    ],
    "sg:phone":"+1 920 432 3663",
    "sg:postcode":"54303",
    "sg:province":"WI",
    "sg:tags":[
        "repairing",
        "tugboat",
        "towing",
        "shipbuilding"
    ],
    "wof:name":"Great Lkes Twing C-Cptain Lyle",
    "wof:placetype":"venue"
},
  "geometry": {"coordinates":[-88.02301799999999,44.509274],"type":"Point"}
}