{
  "type": "Feature",
  "properties": {
    "iso:country":"US",
    "sg:address":"615 Gohres St",
    "sg:city":"La Crosse",
    "sg:classifiers":[
        {
            "category":"Real Estate",
            "subcategory":"Real Estate Agent",
            "type":"Services"
        },
        {
            "category":"Government",
            "subcategory":"Office",
            "type":"Public Place"
        }
    ],
    "sg:phone":"+1 608 781 5365",
    "sg:postcode":"54603",
    "sg:province":"WI",
    "sg:tags":[
        "authorities",
        "housing",
        "program"
    ],
    "wof:name":"LA Crosse County Housing Auth",
    "wof:placetype":"venue"
},
  "geometry": {"coordinates":[-91.24697,43.849496],"type":"Point"}
}