{
  "type": "Feature",
  "properties": {
    "iso:country":"US",
    "sg:address":"600 W Kimberly Ave",
    "sg:city":"Kimberly",
    "sg:classifiers":[
        {
            "category":"Banks & Credit Unions",
            "subcategory":"Bank",
            "type":"Services"
        }
    ],
    "sg:phone":"+1 920 738 5210",
    "sg:postcode":"54136",
    "sg:province":"WI",
    "sg:website":"www.associatedbank.com",
    "wof:name":"Associated Bank",
    "wof:placetype":"venue"
},
  "geometry": {"coordinates":[-88.34052800000001,44.2721],"type":"Point"}
}