{
  "type": "Feature",
  "properties": {
    "iso:country":"US",
    "sg:address":"6019 W Howard Ave",
    "sg:city":"Milwaukee",
    "sg:classifiers":[
        {
            "category":"Shopping",
            "type":"Retail Goods"
        }
    ],
    "sg:phone":"+1 414 476 0843",
    "sg:postcode":"53220",
    "sg:province":"WI",
    "sg:tags":[
        "merchandise"
    ],
    "wof:name":"Hollywood Square",
    "wof:placetype":"venue"
},
  "geometry": {"coordinates":[-87.989879,42.973807],"type":"Point"}
}