{
  "type": "Feature",
  "properties": {
    "iso:country":"US",
    "sg:address":"250 N Koeller St",
    "sg:city":"Oshkosh",
    "sg:classifiers":[
        {
            "category":"Real Estate",
            "subcategory":"Real Estate Operator",
            "type":"Services"
        }
    ],
    "sg:phone":"+1 920 233 3390",
    "sg:postcode":"54902",
    "sg:province":"WI",
    "sg:tags":[
        "building",
        "apartment"
    ],
    "wof:name":"Birchwood Apartments",
    "wof:placetype":"venue"
},
  "geometry": {"coordinates":[-88.58141,44.025372],"type":"Point"}
}