{
  "type": "Feature",
  "properties": {
    "iso:country":"US",
    "sg:address":"11490 Halstead St",
    "sg:city":"Humbird",
    "sg:classifiers":[
        {
            "category":"Manufacturing",
            "subcategory":"Electronics",
            "type":"Manufacturing & Wholesale Goods"
        }
    ],
    "sg:phone":"+1 715 964 2001",
    "sg:postcode":"54746",
    "sg:province":"WI",
    "sg:tags":[
        "equipment",
        "mfg",
        "communication"
    ],
    "wof:name":"Jug Electronics",
    "wof:placetype":"venue"
},
  "geometry": {"coordinates":[-90.891334,44.528167],"type":"Point"}
}