{
  "type": "Feature",
  "properties": {
    "iso:country":"US",
    "sg:address":"5618 Thornapple Rd",
    "sg:city":"Ladysmith",
    "sg:classifiers":[
        {
            "category":"Manufacturing",
            "subcategory":"Tools & Machinery",
            "type":"Manufacturing & Wholesale Goods"
        }
    ],
    "sg:phone":"+1 715 868 5000",
    "sg:postcode":"54848",
    "sg:province":"WI",
    "sg:tags":[
        "farm",
        "mfg"
    ],
    "wof:name":"Superior Equipment Co",
    "wof:placetype":"venue"
},
  "geometry": {"coordinates":[-91.236169,45.491702],"type":"Point"}
}