{
  "type": "Feature",
  "properties": {
    "iso:country":"US",
    "sg:address":"4040 S Victoria Cir",
    "sg:city":"New Berlin",
    "sg:classifiers":[
        {
            "category":"Professional",
            "type":"Services"
        }
    ],
    "sg:phone":"+1 262 641 9541",
    "sg:postcode":"53151",
    "sg:province":"WI",
    "wof:name":"Stratecon Inc",
    "wof:placetype":"venue"
},
  "geometry": {"coordinates":[-88.078007,42.971183],"type":"Point"}
}