{
  "type": "Feature",
  "properties": {
    "iso:country":"US",
    "sg:address":"16000 Mark Dr",
    "sg:city":"Brookfield",
    "sg:classifiers":[
        {
            "category":"Manufacturing",
            "subcategory":"Tools & Machinery",
            "type":"Manufacturing & Wholesale Goods"
        }
    ],
    "sg:phone":"+1 262 784 6365",
    "sg:postcode":"53005",
    "sg:province":"WI",
    "sg:tags":[
        "dist",
        "electrical",
        "motor",
        "mfg"
    ],
    "wof:name":"F M Industries LLC",
    "wof:placetype":"venue"
},
  "geometry": {"coordinates":[-88.11209100000001,43.071104],"type":"Point"}
}