{
  "type": "Feature",
  "properties": {
    "addr:full":"4429 Milwaukee St Madison WI 53714",
    "addr:housenumber":"4429",
    "addr:postcode":"53714",
    "addr:street":"Milwaukee St",
    "iso:country":"US",
    "sg:address":"4429 Milwaukee St",
    "sg:city":"Madison",
    "sg:classifiers":[
        {
            "category":"Retail",
            "subcategory":"Repair Shop",
            "type":"Services"
        }
    ],
    "sg:phone":"+1 608 245 0245",
    "sg:postcode":"53714",
    "sg:province":"WI",
    "sg:tags":[
        "electrical"
    ],
    "wof:name":"Brunner Electronics Repair",
    "wof:placetype":"venue"
},
  "geometry": {"coordinates":[-89.305262,43.098677],"type":"Point"}
}