{
  "type": "Feature",
  "properties": {
    "iso:country":"US",
    "sg:address":"400 S Main St",
    "sg:city":"Adams",
    "sg:classifiers":[
        {
            "category":"Restaurant",
            "type":"Food & Drink"
        }
    ],
    "sg:menulink":"http://www.allmenus.com/wi/adams/244998-golden-city/menu/",
    "sg:phone":"+1 608 339 0988",
    "sg:postcode":"53910",
    "sg:province":"WI",
    "sg:tags":[
        "asian",
        "chinese"
    ],
    "wof:name":"Golden City",
    "wof:placetype":"venue"
},
  "geometry": {"coordinates":[-89.817527,43.953282],"type":"Point"}
}