{
  "type": "Feature",
  "properties": {
    "iso:country":"US",
    "sg:address":"15300 W Capitol Dr",
    "sg:city":"Brookfield",
    "sg:classifiers":[
        {
            "category":"Building & Trades",
            "subcategory":"Landscaping Services",
            "type":"Services"
        }
    ],
    "sg:phone":"+1 262 373 1717",
    "sg:postcode":"53005",
    "sg:province":"WI",
    "sg:tags":[
        "lawn"
    ],
    "wof:name":"Arctic Landscape & Design",
    "wof:placetype":"venue"
},
  "geometry": {"coordinates":[-88.101454,43.08976],"type":"Point"}
}