{
  "type": "Feature",
  "properties": {
    "iso:country":"US",
    "sg:address":"3138 S 9th Pl",
    "sg:city":"Milwaukee",
    "sg:classifiers":[
        {
            "category":"Travel",
            "subcategory":"Travel Agent",
            "type":"Entertainment"
        }
    ],
    "sg:phone":"+1 414 489 0435",
    "sg:postcode":"53215",
    "sg:province":"WI",
    "sg:tags":[
        "agency"
    ],
    "wof:name":"Amsterdam Trips LLC",
    "wof:placetype":"venue"
},
  "geometry": {"coordinates":[-87.923903,42.98719],"type":"Point"}
}