{
  "type": "Feature",
  "properties": {
    "iso:country":"US",
    "sg:address":"1440 Terry Andrae Ter",
    "sg:city":"Sheboygan",
    "sg:classifiers":[
        {
            "category":"Professional",
            "subcategory":"Computer Services",
            "type":"Services"
        }
    ],
    "sg:phone":"+1 920 452 8929",
    "sg:postcode":"53081",
    "sg:province":"WI",
    "sg:tags":[
        "datum"
    ],
    "sg:website":"www.webresults.net",
    "wof:name":"Web Results",
    "wof:placetype":"venue"
},
  "geometry": {"coordinates":[-87.724687,43.680403],"type":"Point"}
}