{
  "type": "Feature",
  "properties": {
    "iso:country":"US",
    "sg:address":"314 Mill St",
    "sg:city":"Algoma",
    "sg:classifiers":[
        {
            "category":"Social Services",
            "subcategory":"Child Care",
            "type":"Services"
        }
    ],
    "sg:phone":"+1 920 487 5977",
    "sg:postcode":"54201",
    "sg:province":"WI",
    "sg:tags":[
        "day"
    ],
    "wof:name":"Pals Day Care",
    "wof:placetype":"venue"
},
  "geometry": {"coordinates":[-87.445019,44.610317],"type":"Point"}
}