{
  "type": "Feature",
  "properties": {
    "addr:full":"1839 Lafayette St Janesville WI 53546",
    "addr:housenumber":"1839",
    "addr:postcode":"53546",
    "addr:street":"Lafayette St",
    "iso:country":"US",
    "sg:address":"1839 Lafayette St",
    "sg:city":"Janesville",
    "sg:classifiers":[
        {
            "category":"Personal",
            "subcategory":"Beauty Salon",
            "type":"Services"
        }
    ],
    "sg:phone":"+1 608 757 1022",
    "sg:postcode":"53546",
    "sg:province":"WI",
    "wof:name":"Designer's Touch Hair & Nail",
    "wof:placetype":"venue"
},
  "geometry": {"coordinates":[-89.029172,42.650327],"type":"Point"}
}