{
  "type": "Feature",
  "properties": {
    "iso:country":"US",
    "sg:address":"44 N Main St",
    "sg:city":"Mayville",
    "sg:classifiers":[
        {
            "category":"Professional",
            "subcategory":"Lawyer & Legal Services",
            "type":"Services"
        }
    ],
    "sg:phone":"+1 920 387 2400",
    "sg:postcode":"53050",
    "sg:province":"WI",
    "sg:tags":[
        "attorney"
    ],
    "wof:name":"Quincy Becker Schuessler Chase",
    "wof:placetype":"venue"
},
  "geometry": {"coordinates":[-88.54477,43.497471],"type":"Point"}
}