{
  "type": "Feature",
  "properties": {
    "addr:full":"1809 Deckner Ave Green Bay WI 54302",
    "addr:housenumber":"1809",
    "addr:postcode":"54302",
    "addr:street":"Deckner Ave",
    "iso:country":"US",
    "sg:address":"1809 Deckner Ave",
    "sg:city":"Green Bay",
    "sg:classifiers":[
        {
            "category":"Professional",
            "subcategory":"Business Services",
            "type":"Services"
        }
    ],
    "sg:phone":"+1 920 468 8021",
    "sg:postcode":"54302",
    "sg:province":"WI",
    "sg:tags":[
        "drafting"
    ],
    "wof:name":"Pennywise Solutions LLC",
    "wof:placetype":"venue"
},
  "geometry": {"coordinates":[-87.977037,44.502492],"type":"Point"}
}