{
  "type": "Feature",
  "properties": {
    "addr:full":"9 University Sq Madison WI 53715",
    "addr:housenumber":"9",
    "addr:postcode":"53715",
    "addr:street":"University Sq",
    "iso:country":"US",
    "sg:address":"9 University Sq",
    "sg:city":"Madison",
    "sg:classifiers":[
        {
            "category":"Shopping",
            "subcategory":"Florist",
            "type":"Retail Goods"
        }
    ],
    "sg:phone":"+1 608 251 4884",
    "sg:postcode":"53715",
    "sg:province":"WI",
    "wof:name":"Choles Floral",
    "wof:placetype":"venue"
},
  "geometry": {"coordinates":[-89.40042699999999,43.072413],"type":"Point"}
}