{
  "type": "Feature",
  "properties": {
    "addr:full":"2970 N Brookfield Rd Brookfield WI 53045",
    "addr:housenumber":"2970",
    "addr:postcode":"53045",
    "addr:street":"N Brookfield Rd",
    "iso:country":"US",
    "sg:address":"2970 N Brookfield Rd",
    "sg:city":"Brookfield",
    "sg:classifiers":[
        {
            "category":"Organizations",
            "subcategory":"Membership Organization",
            "type":"Services"
        }
    ],
    "sg:phone":"+1 262 780 0231",
    "sg:postcode":"53045",
    "sg:province":"WI",
    "sg:tags":[
        "athletic"
    ],
    "wof:name":"World Inline Hockey Network",
    "wof:placetype":"venue"
},
  "geometry": {"coordinates":[-88.145814,43.073817],"type":"Point"}
}