{
  "type": "Feature",
  "properties": {
    "iso:country":"US",
    "sg:address":"15867 Tree Farm Rd",
    "sg:city":"Mountain",
    "sg:classifiers":[
        {
            "category":"Travel",
            "subcategory":"Hotels & Motels",
            "type":"Entertainment"
        }
    ],
    "sg:phone":"+1 715 276 6431",
    "sg:postcode":"54149",
    "sg:province":"WI",
    "sg:tags":[
        "operation"
    ],
    "wof:name":"Camp Lake Resort",
    "wof:placetype":"venue"
},
  "geometry": {"coordinates":[-88.561102,45.257151],"type":"Point"}
}