{
  "type": "Feature",
  "properties": {
    "iso:country":"US",
    "sg:address":"4811 S 76th St",
    "sg:city":"Milwaukee",
    "sg:classifiers":[
        {
            "category":"Health Services",
            "subcategory":"Doctor",
            "type":"Services"
        }
    ],
    "sg:phone":"+1 414 281 0404",
    "sg:postcode":"53220",
    "sg:province":"WI",
    "sg:tags":[
        "physician",
        "surgeon"
    ],
    "wof:name":"Allergy & Asthma Ctrs",
    "wof:placetype":"venue"
},
  "geometry": {"coordinates":[-88.008332,42.958622],"type":"Point"}
}