{
  "type": "Feature",
  "properties": {
    "addr:full":"613 E River Rd Hayward WI 54843",
    "addr:housenumber":"613",
    "addr:postcode":"54843",
    "addr:street":"E River Rd",
    "iso:country":"US",
    "sg:address":"613 E River Rd",
    "sg:city":"Hayward",
    "sg:classifiers":[
        {
            "category":"Shopping",
            "subcategory":"Gifts & Souvenirs",
            "type":"Retail Goods"
        }
    ],
    "sg:phone":"+1 715 634 3055",
    "sg:postcode":"54843",
    "sg:province":"WI",
    "sg:tags":[
        "shop"
    ],
    "wof:name":"Coner Bind",
    "wof:placetype":"venue"
},
  "geometry": {"coordinates":[-91.572282,45.978177],"type":"Point"}
}