{
  "type": "Feature",
  "properties": {
    "addr:full":"17341 Co Rd X Fall Creek WI 54742",
    "addr:housenumber":"17341",
    "addr:postcode":"54742",
    "addr:street":"Co Rd X;Creek",
    "iso:country":"US",
    "sg:address":"17341 Co Rd X",
    "sg:city":"Fall Creek",
    "sg:classifiers":[
        {
            "category":"Wholesale",
            "subcategory":"Groceries",
            "type":"Manufacturing & Wholesale Goods"
        }
    ],
    "sg:phone":"+1 715 877 3000",
    "sg:postcode":"54742",
    "sg:province":"WI",
    "sg:tags":[
        "baker"
    ],
    "wof:name":"Bensen Bryon & Rosalie",
    "wof:placetype":"venue"
},
  "geometry": {"coordinates":[-91.17910000000001,44.843446],"type":"Point"}
}