{
  "type": "Feature",
  "properties": {
    "addr:full":"6639 Badger Ct Wild Rose WI 54984",
    "addr:housenumber":"6639",
    "addr:postcode":"54984",
    "addr:street":"Badger Ct",
    "iso:country":"US",
    "sg:address":"6639 Badger Ct",
    "sg:city":"Wild Rose",
    "sg:classifiers":[
        {
            "category":"Wholesale",
            "subcategory":"Non-durable Goods",
            "type":"Manufacturing & Wholesale Goods"
        }
    ],
    "sg:phone":"+1 877 695 8538",
    "sg:postcode":"54984",
    "sg:province":"WI",
    "wof:name":"Kdm Trading  Inc",
    "wof:placetype":"venue"
},
  "geometry": {"coordinates":[-89.20345500000001,44.151908],"type":"Point"}
}