{
  "type": "Feature",
  "properties": {
    "addr:full":"607 5th Ave Antigo WI 54409",
    "addr:housenumber":"607",
    "addr:postcode":"54409",
    "addr:street":"5Th Ave",
    "iso:country":"US",
    "sg:address":"607 5th Ave",
    "sg:city":"Antigo",
    "sg:classifiers":[
        {
            "category":"Bars & Pubs",
            "type":"Food & Drink"
        }
    ],
    "sg:phone":"+1 715 623 4686",
    "sg:postcode":"54409",
    "sg:province":"WI",
    "sg:tags":[
        "drinking",
        "operation"
    ],
    "wof:name":"Boettcher's Bar",
    "wof:placetype":"venue"
},
  "geometry": {"coordinates":[-89.15087699999999,45.140501],"type":"Point"}
}