{
  "type": "Feature",
  "properties": {
    "addr:full":"2211 S West Ave Waukesha WI 53189",
    "addr:housenumber":"2211",
    "addr:postcode":"53189",
    "addr:street":"S West Ave",
    "iso:country":"US",
    "sg:address":"2211 S West Ave",
    "sg:city":"Waukesha",
    "sg:classifiers":[
        {
            "category":"Wholesale",
            "subcategory":"Machinery & Supplies",
            "type":"Manufacturing & Wholesale Goods"
        }
    ],
    "sg:phone":"+1 262 650 0700",
    "sg:postcode":"53189",
    "sg:province":"WI",
    "sg:tags":[
        "repairing"
    ],
    "wof:name":"Machine Tool Svc & Training",
    "wof:placetype":"venue"
},
  "geometry": {"coordinates":[-88.233715,42.97198],"type":"Point"}
}