{
  "type": "Feature",
  "properties": {
    "addr:full":"5508 Sampe Rd Manitowoc WI 54220",
    "addr:housenumber":"5508",
    "addr:postcode":"54220",
    "addr:street":"Sampe Rd",
    "iso:country":"US",
    "sg:address":"5508 Sampe Rd",
    "sg:city":"Manitowoc",
    "sg:classifiers":[
        {
            "category":"Building & Trades",
            "subcategory":"Construction",
            "type":"Services"
        }
    ],
    "sg:phone":"+1 920 682 0906",
    "sg:postcode":"54220",
    "sg:province":"WI",
    "sg:tags":[
        "painter"
    ],
    "wof:name":"Vogel's Painting & Decorating",
    "wof:placetype":"venue"
},
  "geometry": {"coordinates":[-87.723529,44.137241],"type":"Point"}
}