{
  "type": "Feature",
  "properties": {
    "iso:country":"US",
    "sg:address":"1681 N Prospect Ave",
    "sg:city":"Milwaukee",
    "sg:classifiers":[
        {
            "category":"Banks & Credit Unions",
            "subcategory":"Financial Services",
            "type":"Services"
        }
    ],
    "sg:phone":"+1 414 220 4660",
    "sg:postcode":"53202",
    "sg:province":"WI",
    "sg:tags":[
        "company",
        "holding"
    ],
    "wof:name":"Prospect Holdings Group LLC",
    "wof:placetype":"venue"
},
  "geometry": {"coordinates":[-87.89345899999999,43.050025],"type":"Point"}
}