{
  "type": "Feature",
  "properties": {
    "addr:full":"10712 Deer Ln Wausaukee WI 54177",
    "addr:housenumber":"10712",
    "addr:postcode":"54177",
    "addr:street":"Deer Ln",
    "iso:country":"US",
    "sg:address":"10712 Deer Ln",
    "sg:city":"Wausaukee",
    "sg:classifiers":[
        {
            "category":"Local Transit",
            "type":"Transportation"
        }
    ],
    "sg:phone":"+1 715 856 6021",
    "sg:postcode":"54177",
    "sg:province":"WI",
    "sg:tags":[
        "passenger",
        "limousine"
    ],
    "wof:name":"Northern Limousine Service",
    "wof:placetype":"venue"
},
  "geometry": {"coordinates":[-87.855931,45.338504],"type":"Point"}
}