{
  "type": "Feature",
  "properties": {
    "iso:country":"US",
    "sg:address":"1014 Norridge Dr",
    "sg:city":"Sun Prairie",
    "sg:classifiers":[
        {
            "category":"Building & Trades",
            "subcategory":"Construction",
            "type":"Services"
        }
    ],
    "sg:phone":"+1 608 837 5809",
    "sg:postcode":"53590",
    "sg:province":"WI",
    "sg:tags":[
        "residential",
        "nonresidential"
    ],
    "wof:name":"Cole Construction David Inc",
    "wof:placetype":"venue"
},
  "geometry": {"coordinates":[-89.252572,43.193473],"type":"Point"}
}