{
  "type": "Feature",
  "properties": {
    "addr:full":"22196 Co Hwy X Cadott WI 54727",
    "addr:housenumber":"22196",
    "addr:postcode":"54727",
    "addr:street":"Co Hwy X",
    "iso:country":"US",
    "sg:address":"22196 Co Hwy X",
    "sg:city":"Cadott",
    "sg:classifiers":[
        {
            "category":"Wholesale",
            "subcategory":"Petroleum",
            "type":"Manufacturing & Wholesale Goods"
        }
    ],
    "sg:phone":"+1 715 723 2362",
    "sg:postcode":"54727",
    "sg:province":"WI",
    "sg:tags":[
        "pipe",
        "line",
        "company"
    ],
    "wof:name":"Williams Pipeline Co",
    "wof:placetype":"venue"
},
  "geometry": {"coordinates":[-91.22378399999999,44.929611],"type":"Point"}
}