{
  "type": "Feature",
  "properties": {
    "iso:country":"US",
    "sg:address":"4429 W River Ln",
    "sg:city":"Milwaukee",
    "sg:classifiers":[
        {
            "category":"Wholesale",
            "subcategory":"Construction Materials",
            "type":"Manufacturing & Wholesale Goods"
        }
    ],
    "sg:phone":"+1 414 354 8000",
    "sg:postcode":"53223",
    "sg:province":"WI",
    "wof:name":"A P I Supply Company",
    "wof:placetype":"venue"
},
  "geometry": {"coordinates":[-87.966757,43.177483],"type":"Point"}
}