{
  "type": "Feature",
  "properties": {
    "iso:country":"US",
    "sg:address":"332 Corydon Rd",
    "sg:city":"Eau Claire",
    "sg:classifiers":[
        {
            "category":"Building & Trades",
            "subcategory":"Construction",
            "type":"Services"
        }
    ],
    "sg:phone":"+1 715 855 8649",
    "sg:postcode":"54701",
    "sg:province":"WI",
    "sg:tags":[
        "hanging",
        "contractor"
    ],
    "wof:name":"Hetzel Painting & Wallpapering",
    "wof:placetype":"venue"
},
  "geometry": {"coordinates":[-91.501818,44.776221],"type":"Point"}
}