{
  "type": "Feature",
  "properties": {
    "iso:country":"US",
    "sg:address":"5321 Finger Rd",
    "sg:city":"Green Bay",
    "sg:classifiers":[
        {
            "category":"Professional",
            "type":"Services"
        }
    ],
    "sg:phone":"+1 920 863 2477",
    "sg:postcode":"54311",
    "sg:province":"WI",
    "wof:name":"Cory & Cindy Jervis",
    "wof:placetype":"venue"
},
  "geometry": {"coordinates":[-87.815287,44.487617],"type":"Point"}
}