{
  "type": "Feature",
  "properties": {
    "addr:full":"1420 State Hwy 21 Friendship WI 53934",
    "addr:housenumber":"1420",
    "addr:postcode":"53934",
    "addr:street":"State Hwy 21",
    "iso:country":"US",
    "sg:address":"1420 State Hwy 21",
    "sg:city":"Friendship",
    "sg:classifiers":[
        {
            "category":"Utilities",
            "subcategory":"Refuse",
            "type":"Services"
        }
    ],
    "sg:phone":"+1 608 339 9178",
    "sg:postcode":"53934",
    "sg:province":"WI",
    "sg:tags":[
        "landfill"
    ],
    "wof:name":"Adams County Landfill Recycle",
    "wof:placetype":"venue"
},
  "geometry": {"coordinates":[-89.854865,44.024928],"type":"Point"}
}