{
  "type": "Feature",
  "properties": {
    "iso:country":"US",
    "sg:address":"6810 W Villard Ave",
    "sg:city":"Milwaukee",
    "sg:classifiers":[
        {
            "category":"Retail",
            "subcategory":"Self-service Laundry",
            "type":"Services"
        }
    ],
    "sg:phone":"+1 414 464 2163",
    "sg:postcode":"53218",
    "sg:province":"WI",
    "wof:name":"Family Pride Quick Wash",
    "wof:placetype":"venue"
},
  "geometry": {"coordinates":[-87.997238,43.112246],"type":"Point"}
}