{
  "type": "Feature",
  "properties": {
    "iso:country":"US",
    "sg:address":"618 US Hwy 12",
    "sg:city":"Baraboo",
    "sg:classifiers":[
        {
            "category":"Real Estate",
            "subcategory":"Real Estate Agent",
            "type":"Services"
        }
    ],
    "sg:phone":"+1 608 355 9933",
    "sg:postcode":"53913",
    "sg:province":"WI",
    "wof:name":"C & C Realty",
    "wof:placetype":"venue"
},
  "geometry": {"coordinates":[-89.768668,43.476093],"type":"Point"}
}