{
  "type": "Feature",
  "properties": {
    "iso:country":"US",
    "sg:address":"6748 Log House Cir",
    "sg:city":"Oconomowoc",
    "sg:classifiers":[
        {
            "category":"Personal",
            "type":"Services"
        }
    ],
    "sg:phone":"+1 262 966 9984",
    "sg:postcode":"53066",
    "sg:province":"WI",
    "wof:name":"Lake County Renovators",
    "wof:placetype":"venue"
},
  "geometry": {"coordinates":[-88.418426,43.14073],"type":"Point"}
}