{
  "type": "Feature",
  "properties": {
    "iso:country":"US",
    "sg:address":"2229 W Fond du Lac Ave",
    "sg:city":"Milwaukee",
    "sg:classifiers":[
        {
            "category":"Food & Beverages",
            "subcategory":"Liquor & Beverages",
            "type":"Retail Goods"
        }
    ],
    "sg:phone":"+1 414 342 6916",
    "sg:postcode":"53206",
    "sg:province":"WI",
    "wof:name":"MJM Liquor Store",
    "wof:placetype":"venue"
},
  "geometry": {"coordinates":[-87.940231,43.061479],"type":"Point"}
}