{
  "type": "Feature",
  "properties": {
    "iso:country":"US",
    "sg:address":"1987 W Purdue St",
    "sg:city":"Milwaukee",
    "sg:classifiers":[
        {
            "category":"Manufacturing",
            "subcategory":"Rubber & Plastics",
            "type":"Manufacturing & Wholesale Goods"
        }
    ],
    "sg:phone":"+1 414 562 0787",
    "sg:postcode":"53209",
    "sg:province":"WI",
    "sg:tags":[
        "belting",
        "supply"
    ],
    "wof:name":"Reichel-Korfmann Co",
    "wof:placetype":"venue"
},
  "geometry": {"coordinates":[-87.93531900000001,43.100996],"type":"Point"}
}