{
  "type": "Feature",
  "properties": {
    "addr:full":"414 S Division St Roberts WI 54023",
    "addr:housenumber":"414",
    "addr:postcode":"54023",
    "addr:street":"S Division St",
    "iso:country":"US",
    "sg:address":"414 S Division St",
    "sg:city":"Roberts",
    "sg:classifiers":[
        {
            "category":"Professional",
            "type":"Services"
        }
    ],
    "sg:phone":"+1 715 749 3082",
    "sg:postcode":"54023",
    "sg:province":"WI",
    "wof:name":"BSI",
    "wof:placetype":"venue"
},
  "geometry": {"coordinates":[-92.552908,44.979207],"type":"Point"}
}