{
  "type": "Feature",
  "properties": {
    "iso:country":"US",
    "sg:address":"1206 Clune Rd",
    "sg:city":"Kaukauna",
    "sg:classifiers":[
        {
            "category":"Real Estate",
            "subcategory":"Real Estate Operator",
            "type":"Services"
        }
    ],
    "sg:phone":"+1 920 759 2603",
    "sg:postcode":"54130",
    "sg:province":"WI",
    "sg:tags":[
        "property",
        "lessor"
    ],
    "wof:name":"Paul Ruhland",
    "wof:placetype":"venue"
},
  "geometry": {"coordinates":[-88.201521,44.274019],"type":"Point"}
}