{
  "type": "Feature",
  "properties": {
    "iso:country":"US",
    "sg:address":"637 W Layton Ave",
    "sg:city":"Milwaukee",
    "sg:classifiers":[
        {
            "category":"Bars & Pubs",
            "type":"Food & Drink"
        }
    ],
    "sg:phone":"+1 414 481 2667",
    "sg:postcode":"53221",
    "sg:province":"WI",
    "wof:name":"II Amann's",
    "wof:placetype":"venue"
},
  "geometry": {"coordinates":[-87.920374,42.959142],"type":"Point"}
}