{
  "type": "Feature",
  "properties": {
    "iso:country":"US",
    "sg:address":"1000 Green Valley Rd",
    "sg:city":"Beaver Dam",
    "sg:classifiers":[
        {
            "category":"Shopping",
            "type":"Retail Goods"
        }
    ],
    "sg:phone":"+1 920 887 8840",
    "sg:postcode":"53916",
    "sg:province":"WI",
    "sg:tags":[
        "candle"
    ],
    "wof:name":"Earthshine Inc",
    "wof:placetype":"venue"
},
  "geometry": {"coordinates":[-88.831802,43.476639],"type":"Point"}
}