{
  "type": "Feature",
  "properties": {
    "addr:full":"607 Cobble Stone Ln Kimberly WI 54136",
    "addr:housenumber":"607",
    "addr:postcode":"54136",
    "addr:street":"Cobble Stone Ln",
    "iso:country":"US",
    "sg:address":"607 Cobble Stone Ln",
    "sg:city":"Kimberly",
    "sg:classifiers":[
        {
            "category":"Building & Trades",
            "subcategory":"Construction",
            "type":"Services"
        }
    ],
    "sg:phone":"+1 920 788 5900",
    "sg:postcode":"54136",
    "sg:province":"WI",
    "sg:tags":[
        "contractor"
    ],
    "wof:name":"Bm Roofing",
    "wof:placetype":"venue"
},
  "geometry": {"coordinates":[-88.342375,44.263027],"type":"Point"}
}