{
  "type": "Feature",
  "properties": {
    "iso:country":"US",
    "sg:address":"3036 Carney Ave",
    "sg:city":"Marinette",
    "sg:classifiers":[
        {
            "category":"Organizations",
            "subcategory":"Religious Organization",
            "type":"Services"
        }
    ],
    "sg:phone":"+1 715 735 7289",
    "sg:postcode":"54143",
    "sg:province":"WI",
    "sg:website":"www.calvarytempleonline.com",
    "wof:name":"Calvary Temple Assembly Of God",
    "wof:placetype":"venue"
},
  "geometry": {"coordinates":[-87.649573,45.093016],"type":"Point"}
}