{
  "type": "Feature",
  "properties": {
    "iso:country":"US",
    "sg:address":"3553 8th St S",
    "sg:city":"Wisconsin Rapids",
    "sg:classifiers":[
        {
            "category":"Autos & Motor Vehicles",
            "subcategory":"Auto Supplies",
            "type":"Retail Goods"
        }
    ],
    "sg:phone":"+1 715 423 1600",
    "sg:postcode":"54494",
    "sg:province":"WI",
    "sg:tags":[
        "tire"
    ],
    "wof:name":"Schierl Tire & Service",
    "wof:placetype":"venue"
},
  "geometry": {"coordinates":[-89.816752,44.362683],"type":"Point"}
}