{
  "type": "Feature",
  "properties": {
    "iso:country":"US",
    "sg:address":"2501 Harrison St",
    "sg:city":"Oshkosh",
    "sg:classifiers":[
        {
            "category":"Social Services",
            "subcategory":"Adult Care",
            "type":"Services"
        }
    ],
    "sg:phone":"+1 920 424 7772",
    "sg:postcode":"54901",
    "sg:province":"WI",
    "sg:tags":[
        "home",
        "group"
    ],
    "wof:name":"Summit House",
    "wof:placetype":"venue"
},
  "geometry": {"coordinates":[-88.532852,44.049171],"type":"Point"}
}