{
  "type": "Feature",
  "properties": {
    "iso:country":"US",
    "sg:address":"290 5th St",
    "sg:city":"Prairie Du Sac",
    "sg:classifiers":[
        {
            "category":"Real Estate",
            "subcategory":"Surveying",
            "type":"Services"
        }
    ],
    "sg:phone":"+1 608 643 8851",
    "sg:postcode":"53578",
    "sg:province":"WI",
    "sg:tags":[
        "engineering"
    ],
    "sg:website":"www.orionls.com",
    "wof:name":"Orion Land Surveyors",
    "wof:placetype":"venue"
},
  "geometry": {"coordinates":[-89.724913,43.285763],"type":"Point"}
}