{
  "type": "Feature",
  "properties": {
    "iso:country":"US",
    "sg:address":"12336 W Layton Ave",
    "sg:city":"Milwaukee",
    "sg:classifiers":[
        {
            "category":"Professional",
            "subcategory":"Accounting & Tax Preparation",
            "type":"Services"
        }
    ],
    "sg:phone":"+1 414 425 5900",
    "sg:postcode":"53228",
    "sg:province":"WI",
    "sg:tags":[
        "accountant"
    ],
    "wof:name":"Ronald C Molis",
    "wof:placetype":"venue"
},
  "geometry": {"coordinates":[-88.068473,42.959178],"type":"Point"}
}