{
  "type": "Feature",
  "properties": {
    "iso:country":"US",
    "sg:address":"7728 W Mount Vernon Ave",
    "sg:city":"Milwaukee",
    "sg:classifiers":[
        {
            "category":"Manufacturing",
            "subcategory":"Textiles",
            "type":"Manufacturing & Wholesale Goods"
        }
    ],
    "sg:phone":"+1 414 771 1506",
    "sg:postcode":"53213",
    "sg:province":"WI",
    "sg:tags":[
        "mfg"
    ],
    "wof:name":"Eastowne Caprets",
    "wof:placetype":"venue"
},
  "geometry": {"coordinates":[-88.009708,43.033983],"type":"Point"}
}