{
  "type": "Feature",
  "properties": {
    "iso:country":"US",
    "sg:address":"5595 N Long Island Dr",
    "sg:city":"Milwaukee",
    "sg:classifiers":[
        {
            "category":"Retail",
            "subcategory":"Animal Services",
            "type":"Services"
        }
    ],
    "sg:phone":"+1 414 228 9595",
    "sg:postcode":"53209",
    "sg:province":"WI",
    "sg:tags":[
        "pet",
        "grooming",
        "washing"
    ],
    "wof:name":"Stifter's Grooming Salon",
    "wof:placetype":"venue"
},
  "geometry": {"coordinates":[-87.937748,43.11834],"type":"Point"}
}