{
  "type": "Feature",
  "properties": {
    "iso:country":"US",
    "sg:address":"207 Co Rd K",
    "sg:city":"Unity",
    "sg:classifiers":[
        {
            "category":"Freight",
            "type":"Transportation"
        }
    ],
    "sg:phone":"+1 715 223 2128",
    "sg:postcode":"54488",
    "sg:province":"WI",
    "sg:tags":[
        "operator",
        "local",
        "trucking"
    ],
    "wof:name":"Bauer Trucking",
    "wof:placetype":"venue"
},
  "geometry": {"coordinates":[-90.317382,44.851299],"type":"Point"}
}