{
  "type": "Feature",
  "properties": {
    "iso:country":"US",
    "sg:address":"4611 W National Ave",
    "sg:city":"Milwaukee",
    "sg:classifiers":[
        {
            "category":"Wholesale",
            "subcategory":"Electrical",
            "type":"Manufacturing & Wholesale Goods"
        }
    ],
    "sg:phone":"+1 414 671 3333",
    "sg:postcode":"53214",
    "sg:province":"WI",
    "sg:tags":[
        "light",
        "tube",
        "bulb"
    ],
    "wof:name":"Duro-Test Milwaukee",
    "wof:placetype":"venue"
},
  "geometry": {"coordinates":[-87.972273,43.020117],"type":"Point"}
}