{
  "type": "Feature",
  "properties": {
    "iso:country":"US",
    "sg:address":"9465 S Sherwood Dr",
    "sg:city":"Franklin",
    "sg:classifiers":[
        {
            "category":"Freight",
            "type":"Transportation"
        }
    ],
    "sg:phone":"+1 414 421 5506",
    "sg:postcode":"53132",
    "sg:province":"WI",
    "sg:tags":[
        "distance",
        "cartage",
        "long",
        "trucking",
        "trucker",
        "local"
    ],
    "wof:name":"David Bartel Trucking Inc",
    "wof:placetype":"venue"
},
  "geometry": {"coordinates":[-87.964186,42.874038],"type":"Point"}
}