{
  "type": "Feature",
  "properties": {
    "iso:country":"US",
    "sg:address":"885 Calico Ct",
    "sg:city":"Waukesha",
    "sg:classifiers":[
        {
            "category":"Professional",
            "subcategory":"Management & Consulting",
            "type":"Services"
        }
    ],
    "sg:phone":"+1 262 717 9440",
    "sg:postcode":"53186",
    "sg:province":"WI",
    "sg:tags":[
        "consultant",
        "training"
    ],
    "wof:name":"Total Training Systems",
    "wof:placetype":"venue"
},
  "geometry": {"coordinates":[-88.184983,43.022423],"type":"Point"}
}