{
  "type": "Feature",
  "properties": {
    "addr:full":"200 Colonial Pkwy Saukville WI 53080",
    "addr:housenumber":"200",
    "addr:postcode":"53080",
    "addr:street":"Colonial Pkwy",
    "iso:country":"US",
    "sg:address":"200 Colonial Pkwy",
    "sg:city":"Saukville",
    "sg:classifiers":[
        {
            "category":"Organizations",
            "subcategory":"Community Association",
            "type":"Services"
        }
    ],
    "sg:phone":"+1 262 284 2346",
    "sg:postcode":"53080",
    "sg:province":"WI",
    "wof:name":"Beth El BOLFWC",
    "wof:placetype":"venue"
},
  "geometry": {"coordinates":[-87.951089,43.38058],"type":"Point"}
}