{
  "type": "Feature",
  "properties": {
    "addr:full":"710 E Blackhawk Ave Prairie Du Chien WI 53821",
    "addr:housenumber":"710",
    "addr:postcode":"53821",
    "addr:street":"E Blackhawk Ave",
    "iso:country":"US",
    "sg:address":"710 E Blackhawk Ave",
    "sg:city":"Prairie Du Chien",
    "sg:classifiers":[
        {
            "category":"Shopping",
            "subcategory":"Computers & Home Electronics",
            "type":"Retail Goods"
        }
    ],
    "sg:phone":"+1 608 326 4556",
    "sg:postcode":"53821",
    "sg:province":"WI",
    "sg:tags":[
        "equipment",
        "satellite",
        "system"
    ],
    "wof:name":"Dyer Communication Systems",
    "wof:placetype":"venue"
},
  "geometry": {"coordinates":[-91.137782,43.052178],"type":"Point"}
}