{
  "type": "Feature",
  "properties": {
    "iso:country":"US",
    "sg:address":"1400 West St",
    "sg:city":"Union Grove",
    "sg:classifiers":[
        {
            "category":"Real Estate",
            "subcategory":"Real Estate Operator",
            "type":"Services"
        }
    ],
    "sg:phone":"+1 262 878 3280",
    "sg:postcode":"53182",
    "sg:province":"WI",
    "sg:tags":[
        "apartment"
    ],
    "wof:name":"Cathedral Court Apartments",
    "wof:placetype":"venue"
},
  "geometry": {"coordinates":[-88.05671,42.684215],"type":"Point"}
}