{
  "type": "Feature",
  "properties": {
    "iso:country":"US",
    "sg:address":"3419 Royal Rd",
    "sg:city":"Janesville",
    "sg:classifiers":[
        {
            "category":"Building & Trades",
            "subcategory":"Plumbing",
            "type":"Services"
        }
    ],
    "sg:phone":"+1 608 752 2472",
    "sg:postcode":"53546",
    "sg:province":"WI",
    "sg:tags":[
        "contractor"
    ],
    "wof:name":"JC Heating & Cooling",
    "wof:placetype":"venue"
},
  "geometry": {"coordinates":[-88.974598,42.683352],"type":"Point"}
}