{
  "type": "Feature",
  "properties": {
    "iso:country":"US",
    "sg:address":"1721 Utah St",
    "sg:city":"Sturgeon Bay",
    "sg:classifiers":[
        {
            "category":"Banks & Credit Unions",
            "subcategory":"Bank",
            "type":"Services"
        }
    ],
    "sg:phone":"+1 920 746 0444",
    "sg:postcode":"54235",
    "sg:province":"WI",
    "sg:tags":[
        "loan",
        "real estate"
    ],
    "wof:name":"Premier Mortgage",
    "wof:placetype":"venue"
},
  "geometry": {"coordinates":[-87.353645,44.827683],"type":"Point"}
}