{
  "type": "Feature",
  "properties": {
    "iso:country":"US",
    "sg:address":"5861 Persimmon Dr",
    "sg:city":"Fitchburg",
    "sg:classifiers":[
        {
            "category":"Wholesale",
            "subcategory":"Durable Goods & Equipment",
            "type":"Manufacturing & Wholesale Goods"
        },
        {
            "category":"Shopping",
            "subcategory":"Computers & Home Electronics",
            "type":"Retail Goods"
        }
    ],
    "sg:phone":"+1 608 271 7555",
    "sg:postcode":"53711",
    "sg:province":"WI",
    "sg:tags":[
        "m",
        "representative",
        "manufacturer"
    ],
    "wof:name":"STP Marketing LLC",
    "wof:placetype":"venue"
},
  "geometry": {"coordinates":[-89.448531,43.007326],"type":"Point"}
}