{
  "type": "Feature",
  "properties": {
    "iso:country":"US",
    "sg:address":"4600 N 40th St",
    "sg:city":"Milwaukee",
    "sg:classifiers":[
        {
            "category":"Shopping",
            "subcategory":"Shoes",
            "type":"Retail Goods"
        }
    ],
    "sg:phone":"+1 414 873 8004",
    "sg:postcode":"53209",
    "sg:province":"WI",
    "wof:name":"QDBC Clothing & Shoes",
    "wof:placetype":"venue"
},
  "geometry": {"coordinates":[-87.962722,43.102568],"type":"Point"}
}