{
  "type": "Feature",
  "properties": {
    "iso:country":"US",
    "sg:address":"625 W Montclaire Ave",
    "sg:city":"Milwaukee",
    "sg:classifiers":[
        {
            "category":"Manufacturing",
            "subcategory":"Tools & Machinery",
            "type":"Manufacturing & Wholesale Goods"
        },
        {
            "category":"Wholesale",
            "subcategory":"Electrical",
            "type":"Manufacturing & Wholesale Goods"
        }
    ],
    "sg:phone":"+1 708 989 8605",
    "sg:postcode":"53217",
    "sg:province":"WI",
    "sg:tags":[
        "equipment",
        "manufacturer",
        "supplies-wholesale",
        "electric",
        "supply"
    ],
    "wof:name":"Smart Surface Designs",
    "wof:placetype":"venue"
},
  "geometry": {"coordinates":[-87.917356,43.126095],"type":"Point"}
}