{
  "type": "Feature",
  "properties": {
    "addr:full":"5744 N Tarrant Rd Milton WI 53563",
    "addr:housenumber":"5744",
    "addr:postcode":"53563",
    "addr:street":"N Tarrant Rd",
    "iso:country":"US",
    "sg:address":"5744 N Tarrant Rd",
    "sg:city":"Milton",
    "sg:classifiers":[
        {
            "category":"Freight",
            "type":"Transportation"
        }
    ],
    "sg:phone":"+1 608 868 7552",
    "sg:postcode":"53563",
    "sg:province":"WI",
    "sg:tags":[
        "trucking"
    ],
    "wof:name":"F & J Transport Inc",
    "wof:placetype":"venue"
},
  "geometry": {"coordinates":[-88.89578899999999,42.746404],"type":"Point"}
}