{
  "type": "Feature",
  "properties": {
    "iso:country":"US",
    "sg:address":"319 N Wacouta Ave",
    "sg:city":"Prairie Du Chien",
    "sg:classifiers":[
        {
            "category":"Building & Trades",
            "subcategory":"Construction",
            "type":"Services"
        }
    ],
    "sg:phone":"+1 608 326 4614",
    "sg:postcode":"53821",
    "sg:province":"WI",
    "sg:tags":[
        "concrete",
        "contractor"
    ],
    "wof:name":"Larkin Construction",
    "wof:placetype":"venue"
},
  "geometry": {"coordinates":[-91.1453,43.056223],"type":"Point"}
}