{
  "type": "Feature",
  "properties": {
    "iso:country":"US",
    "sg:address":"17808 Co Rd K",
    "sg:city":"Cornell",
    "sg:classifiers":[
        {
            "category":"Building & Trades",
            "subcategory":"Construction",
            "type":"Services"
        }
    ],
    "sg:phone":"+1 715 382 5412",
    "sg:postcode":"54732",
    "sg:province":"WI",
    "sg:tags":[
        "floor",
        "laying",
        "contractor"
    ],
    "wof:name":"Jim G Knitter",
    "wof:placetype":"venue"
},
  "geometry": {"coordinates":[-91.20689299999999,45.099268],"type":"Point"}
}