{
  "type": "Feature",
  "properties": {
    "iso:country":"US",
    "sg:address":"216 S Division St",
    "sg:city":"Janesville",
    "sg:classifiers":[
        {
            "category":"Professional",
            "subcategory":"Art Services",
            "type":"Services"
        }
    ],
    "sg:phone":"+1 608 756 4567",
    "sg:postcode":"53545",
    "sg:province":"WI",
    "sg:tags":[
        "designer",
        "display",
        "producer"
    ],
    "wof:name":"S R Custom Design",
    "wof:placetype":"venue"
},
  "geometry": {"coordinates":[-89.017743,42.681503],"type":"Point"}
}