{
  "type": "Feature",
  "properties": {
    "addr:full":"5300 S Howell Ave Milwaukee WI 53207",
    "addr:housenumber":"5300",
    "addr:postcode":"53207",
    "addr:street":"S Howell Ave",
    "iso:country":"US",
    "sg:address":"5300 S Howell Ave",
    "sg:city":"Milwaukee",
    "sg:classifiers":[
        {
            "category":"Food Court",
            "type":"Food & Drink"
        },
        {
            "category":"Home & Garden",
            "subcategory":"Kitchen Supply",
            "type":"Retail Goods"
        }
    ],
    "sg:phone":"+1 414 747 5252",
    "sg:postcode":"53207",
    "sg:province":"WI",
    "sg:tags":[
        "concession",
        "management",
        "concessionaire"
    ],
    "sg:website":"http://www.sodexo.com",
    "wof:name":"Sodexo, Inc.",
    "wof:placetype":"venue"
},
  "geometry": {"coordinates":[-87.909592,42.947868],"type":"Point"}
}