{
  "type": "Feature",
  "properties": {
    "iso:country":"US",
    "sg:address":"11661 Seitz Rd",
    "sg:city":"Sauk City",
    "sg:classifiers":[
        {
            "category":"Farming",
            "subcategory":"Farm",
            "type":"Manufacturing & Wholesale Goods"
        }
    ],
    "sg:phone":"+1 608 544 4511",
    "sg:postcode":"53583",
    "sg:province":"WI",
    "wof:name":"Loreto Farms Inc",
    "wof:placetype":"venue"
},
  "geometry": {"coordinates":[-89.838399,43.221882],"type":"Point"}
}