{
  "type": "Feature",
  "properties": {
    "addr:full":"10640 State Hwy 13 Marshfield WI 54449",
    "addr:housenumber":"10640",
    "addr:postcode":"54449",
    "addr:street":"State Hwy 13",
    "iso:country":"US",
    "sg:address":"10640 State Hwy 13",
    "sg:city":"Marshfield",
    "sg:classifiers":[
        {
            "category":"Building & Trades",
            "subcategory":"Construction",
            "type":"Services"
        }
    ],
    "sg:phone":"+1 715 384 9902",
    "sg:postcode":"54449",
    "sg:province":"WI",
    "sg:tags":[
        "general",
        "contractor"
    ],
    "wof:name":"Schueller Construction Inc",
    "wof:placetype":"venue"
},
  "geometry": {"coordinates":[-90.179941,44.630143],"type":"Point"}
}