{
  "type": "Feature",
  "properties": {
    "addr:full":"134 4th St Baraboo WI 53913",
    "addr:housenumber":"134",
    "addr:postcode":"53913",
    "addr:street":"4Th St",
    "iso:country":"US",
    "sg:address":"134 4th St",
    "sg:city":"Baraboo",
    "sg:classifiers":[
        {
            "category":"Retail",
            "subcategory":"Auto Repair",
            "type":"Services"
        }
    ],
    "sg:phone":"+1 608 356 4900",
    "sg:postcode":"53913",
    "sg:province":"WI",
    "sg:tags":[
        "automotive",
        "general"
    ],
    "wof:name":"Dons Automotive & Towing",
    "wof:placetype":"venue"
},
  "geometry": {"coordinates":[-89.74203199999999,43.470961],"type":"Point"}
}