{
  "type": "Feature",
  "properties": {
    "iso:country":"US",
    "sg:address":"8027 W Carmen Ave",
    "sg:city":"Milwaukee",
    "sg:classifiers":[
        {
            "category":"Local Transit",
            "type":"Transportation"
        }
    ],
    "sg:phone":"+1 414 466 7898",
    "sg:postcode":"53218",
    "sg:province":"WI",
    "sg:tags":[
        "handicapped"
    ],
    "wof:name":"Trumed Transport Svc",
    "wof:placetype":"venue"
},
  "geometry": {"coordinates":[-88.01183,43.123139],"type":"Point"}
}