{
  "type": "Feature",
  "properties": {
    "addr:full":"515 S Washburn St Oshkosh WI 54904",
    "addr:housenumber":"515",
    "addr:postcode":"54904",
    "addr:street":"S Washburn St",
    "iso:country":"US",
    "sg:address":"515 S Washburn St",
    "sg:city":"Oshkosh",
    "sg:classifiers":[
        {
            "category":"Banks & Credit Unions",
            "subcategory":"Investment Brokerage",
            "type":"Services"
        }
    ],
    "sg:phone":"+1 920 232 8263",
    "sg:postcode":"54904",
    "sg:province":"WI",
    "sg:tags":[
        "retirement",
        "planning"
    ],
    "wof:name":"Valley Employee Svc",
    "wof:placetype":"venue"
},
  "geometry": {"coordinates":[-88.58476,44.011611],"type":"Point"}
}