{
  "type": "Feature",
  "properties": {
    "iso:country":"US",
    "sg:address":"18601 Dayton Ridge Rd",
    "sg:city":"Richland Center",
    "sg:classifiers":[
        {
            "category":"Real Estate",
            "subcategory":"Real Estate Operator",
            "type":"Services"
        }
    ],
    "sg:phone":"+1 608 647 2946",
    "sg:postcode":"53581",
    "sg:province":"WI",
    "sg:tags":[
        "building",
        "management",
        "apartment"
    ],
    "wof:name":"Fenton Apartments",
    "wof:placetype":"venue"
},
  "geometry": {"coordinates":[-90.48014499999999,43.335774],"type":"Point"}
}