{
  "type": "Feature",
  "properties": {
    "iso:country":"US",
    "sg:address":"1520 Main St",
    "sg:city":"Green Bay",
    "sg:classifiers":[
        {
            "category":"Manufacturing",
            "subcategory":"Apparel",
            "type":"Manufacturing & Wholesale Goods"
        }
    ],
    "sg:phone":"+1 920 437 0838",
    "sg:postcode":"54302",
    "sg:province":"WI",
    "sg:tags":[
        "product",
        "mfg"
    ],
    "wof:name":"Earls Awning Inc",
    "wof:placetype":"venue"
},
  "geometry": {"coordinates":[-87.990122,44.508213],"type":"Point"}
}