{
  "type": "Feature",
  "properties": {
    "iso:country":"US",
    "sg:address":"2911 Grove Ave",
    "sg:city":"Wisconsin Rapids",
    "sg:classifiers":[
        {
            "category":"Real Estate",
            "subcategory":"Real Estate Operator",
            "type":"Services"
        }
    ],
    "sg:phone":"+1 715 424 4535",
    "sg:postcode":"54494",
    "sg:province":"WI",
    "sg:tags":[
        "building",
        "nonresidential"
    ],
    "wof:name":"Pickett Properties",
    "wof:placetype":"venue"
},
  "geometry": {"coordinates":[-89.790403,44.369568],"type":"Point"}
}