{
  "type": "Feature",
  "properties": {
    "iso:country":"US",
    "sg:address":"17947 45th Ave",
    "sg:city":"Chippewa Falls",
    "sg:classifiers":[
        {
            "category":"Banks & Credit Unions",
            "subcategory":"Financial Services",
            "type":"Services"
        }
    ],
    "sg:phone":"+1 715 723 5162",
    "sg:postcode":"54729",
    "sg:province":"WI",
    "sg:tags":[
        "investment",
        "closed"
    ],
    "wof:name":"Bell Investments",
    "wof:placetype":"venue"
},
  "geometry": {"coordinates":[-91.308463,44.910392],"type":"Point"}
}