{
  "type": "Feature",
  "properties": {
    "iso:country":"US",
    "sg:address":"112 N Cascade St",
    "sg:city":"Osceola",
    "sg:classifiers":[
        {
            "category":"Personal",
            "subcategory":"Beauty Salon",
            "type":"Services"
        },
        {
            "category":"Personal",
            "subcategory":"Tanning Parlor",
            "type":"Services"
        }
    ],
    "sg:phone":"+1 715 294 4123",
    "sg:postcode":"54020",
    "sg:province":"WI",
    "wof:name":"Unlimited Styling & Hair Care",
    "wof:placetype":"venue"
},
  "geometry": {"coordinates":[-92.705901,45.319804],"type":"Point"}
}