{
  "type": "Feature",
  "properties": {
    "iso:country":"US",
    "sg:address":"2568 16th St",
    "sg:city":"Rice Lake",
    "sg:classifiers":[
        {
            "category":"Building & Trades",
            "subcategory":"Construction",
            "type":"Services"
        }
    ],
    "sg:phone":"+1 715 234 4431",
    "sg:postcode":"54868",
    "sg:province":"WI",
    "sg:tags":[
        "excavation",
        "contractor"
    ],
    "wof:name":"Mancls",
    "wof:placetype":"venue"
},
  "geometry": {"coordinates":[-91.827206,45.571712],"type":"Point"}
}