{
  "type": "Feature",
  "properties": {
    "iso:country":"US",
    "sg:address":"2347 Trillium Dr",
    "sg:city":"Eau Claire",
    "sg:classifiers":[
        {
            "category":"Travel",
            "subcategory":"Travel Agent",
            "type":"Entertainment"
        }
    ],
    "sg:phone":"+1 715 835 1741",
    "sg:postcode":"54701",
    "sg:province":"WI",
    "sg:tags":[
        "agency"
    ],
    "wof:name":"Aumanns Travel",
    "wof:placetype":"venue"
},
  "geometry": {"coordinates":[-91.465715,44.746403],"type":"Point"}
}