{
  "type": "Feature",
  "properties": {
    "iso:country":"US",
    "sg:address":"2425 N Shore Dr",
    "sg:city":"Delavan",
    "sg:classifiers":[
        {
            "category":"Professional",
            "subcategory":"Business Services",
            "type":"Services"
        }
    ],
    "sg:phone":"+1 262 728 5665",
    "sg:postcode":"53115",
    "sg:province":"WI",
    "wof:name":"Almburg Auctioneering",
    "wof:placetype":"venue"
},
  "geometry": {"coordinates":[-88.615363,42.605943],"type":"Point"}
}