{
  "type": "Feature",
  "properties": {
    "iso:country":"US",
    "sg:address":"641 W Main St",
    "sg:city":"Sun Prairie",
    "sg:classifiers":[
        {
            "category":"Retail",
            "subcategory":"Auto Rental",
            "type":"Services"
        }
    ],
    "sg:phone":"+1 608 825 6457",
    "sg:postcode":"53590",
    "sg:province":"WI",
    "sg:tags":[
        "renting",
        "truck",
        "leasing"
    ],
    "wof:name":"Budget Truck Rental",
    "wof:placetype":"venue"
},
  "geometry": {"coordinates":[-89.224163,43.182475],"type":"Point"}
}