{
  "type": "Feature",
  "properties": {
    "iso:country":"US",
    "sg:address":"15865 W 2nd St",
    "sg:city":"Hayward",
    "sg:classifiers":[
        {
            "category":"Real Estate",
            "subcategory":"Real Estate Agent",
            "type":"Services"
        }
    ],
    "sg:phone":"+1 715 634 2996",
    "sg:postcode":"54843",
    "sg:province":"WI",
    "sg:website":"www.tri-r-realty.com",
    "wof:name":"Tri-R Realty Assoc",
    "wof:placetype":"venue"
},
  "geometry": {"coordinates":[-91.48561599999999,46.013647],"type":"Point"}
}