{
  "type": "Feature",
  "properties": {
    "iso:country":"US",
    "sg:address":"1823 Doty St",
    "sg:city":"Oshkosh",
    "sg:classifiers":[
        {
            "category":"Food & Beverages",
            "subcategory":"Candy",
            "type":"Retail Goods"
        }
    ],
    "sg:phone":"+1 920 231 7232",
    "sg:postcode":"54902",
    "sg:province":"WI",
    "wof:name":"Hughes Homemade Chocolates",
    "wof:placetype":"venue"
},
  "geometry": {"coordinates":[-88.539283,43.999004],"type":"Point"}
}