{
  "type": "Feature",
  "properties": {
    "iso:country":"US",
    "sg:address":"6103 Leeward Ln",
    "sg:city":"Racine",
    "sg:classifiers":[
        {
            "category":"Professional",
            "subcategory":"Accounting & Tax Preparation",
            "type":"Services"
        }
    ],
    "sg:phone":"+1 262 681 0697",
    "sg:postcode":"53402",
    "sg:province":"WI",
    "wof:name":"Coy & Diane Investments Inc",
    "wof:placetype":"venue"
},
  "geometry": {"coordinates":[-87.854106,42.779966],"type":"Point"}
}