{
  "type": "Feature",
  "properties": {
    "iso:country":"US",
    "sg:address":"18155 Harvest Ln",
    "sg:city":"Brookfield",
    "sg:classifiers":[
        {
            "category":"Retail",
            "subcategory":"Portrait Studio",
            "type":"Services"
        }
    ],
    "sg:phone":"+1 262 821 1860",
    "sg:postcode":"53045",
    "sg:province":"WI",
    "sg:tags":[
        "photographer"
    ],
    "wof:name":"Wisconsin Sports Photography",
    "wof:placetype":"venue"
},
  "geometry": {"coordinates":[-88.13913700000001,43.052423],"type":"Point"}
}