{
  "type": "Feature",
  "properties": {
    "iso:country":"US",
    "sg:address":"10820 W National Ave",
    "sg:city":"Milwaukee",
    "sg:classifiers":[
        {
            "category":"Health Services",
            "subcategory":"Doctor",
            "type":"Services"
        }
    ],
    "sg:phone":"+1 414 321 7700",
    "sg:postcode":"53227",
    "sg:province":"WI",
    "sg:tags":[
        "dentist"
    ],
    "wof:name":"Peter A Limberatos DDS",
    "wof:placetype":"venue"
},
  "geometry": {"coordinates":[-88.048662,42.992875],"type":"Point"}
}