{
  "type": "Feature",
  "properties": {
    "iso:country":"US",
    "sg:address":"2619 Post Rd",
    "sg:city":"Stevens Point",
    "sg:classifiers":[
        {
            "category":"Manufacturing",
            "subcategory":"Retail Goods",
            "type":"Manufacturing & Wholesale Goods"
        }
    ],
    "sg:phone":"+1 715 341 7140",
    "sg:postcode":"54481",
    "sg:province":"WI",
    "sg:tags":[
        "product",
        "mfg"
    ],
    "wof:name":"Eia Industries",
    "wof:placetype":"venue"
},
  "geometry": {"coordinates":[-89.543802,44.457435],"type":"Point"}
}