{
  "type": "Feature",
  "properties": {
    "iso:country":"US",
    "sg:address":"239 N 3rd Ave",
    "sg:city":"Sturgeon Bay",
    "sg:classifiers":[
        {
            "category":"Arts & Performance",
            "subcategory":"Theater",
            "type":"Entertainment"
        }
    ],
    "sg:phone":"+1 920 743 1760",
    "sg:postcode":"54235",
    "sg:province":"WI",
    "sg:website":"www.thirdavenueplayhouse.com",
    "wof:name":"Third Avenue Playhouse",
    "wof:placetype":"venue"
},
  "geometry": {"coordinates":[-87.37848099999999,44.836378],"type":"Point"}
}