{
  "type": "Feature",
  "properties": {
    "iso:country":"US",
    "sg:address":"315 W Main St",
    "sg:city":"Dickeyville",
    "sg:classifiers":[
        {
            "category":"Autos & Motor Vehicles",
            "subcategory":"Motorcycle Sales",
            "type":"Retail Goods"
        }
    ],
    "sg:phone":"+1 608 568 7200",
    "sg:postcode":"53808",
    "sg:province":"WI",
    "sg:tags":[
        "all",
        "terrain"
    ],
    "wof:name":"Click's Cycle Svc",
    "wof:placetype":"venue"
},
  "geometry": {"coordinates":[-90.594221,42.627623],"type":"Point"}
}