{
  "type": "Feature",
  "properties": {
    "iso:country":"US",
    "sg:address":"599 S Military Ave",
    "sg:city":"Green Bay",
    "sg:classifiers":[
        {
            "category":"Wholesale",
            "subcategory":"Office Equipment",
            "type":"Manufacturing & Wholesale Goods"
        }
    ],
    "sg:phone":"+1 920 494 4792",
    "sg:postcode":"54303",
    "sg:province":"WI",
    "sg:tags":[
        "machine",
        "duplicating",
        "copying"
    ],
    "wof:name":"Bartelt Business Machines Inc",
    "wof:placetype":"venue"
},
  "geometry": {"coordinates":[-88.06285099999999,44.525383],"type":"Point"}
}