{
  "type": "Feature",
  "properties": {
    "iso:country":"US",
    "sg:address":"812 Mount Mary Dr",
    "sg:city":"Green Bay",
    "sg:classifiers":[
        {
            "category":"Professional",
            "subcategory":"Business Services",
            "type":"Services"
        }
    ],
    "sg:phone":"+1 920 468 1292",
    "sg:postcode":"54311",
    "sg:province":"WI",
    "wof:name":"Jls Group LLC",
    "wof:placetype":"venue"
},
  "geometry": {"coordinates":[-87.93624,44.511927],"type":"Point"}
}