{
  "type": "Feature",
  "properties": {
    "addr:full":"928 N Hartwell Ave Waukesha WI 53186",
    "addr:housenumber":"928",
    "addr:postcode":"53186",
    "addr:street":"N Hartwell Ave",
    "iso:country":"US",
    "sg:address":"928 N Hartwell Ave",
    "sg:city":"Waukesha",
    "sg:classifiers":[
        {
            "category":"Restaurant",
            "type":"Food & Drink"
        }
    ],
    "sg:phone":"+1 262 544 4119",
    "sg:postcode":"53186",
    "sg:province":"WI",
    "sg:tags":[
        "eating",
        "product",
        "dairy"
    ],
    "wof:name":"Nikos Gyros & Ice Cream",
    "wof:placetype":"venue"
},
  "geometry": {"coordinates":[-88.221861,43.01315],"type":"Point"}
}