{
  "type": "Feature",
  "properties": {
    "iso:country":"US",
    "sg:address":"11576 290th St",
    "sg:city":"Cadott",
    "sg:classifiers":[
        {
            "category":"Retail",
            "subcategory":"Repair Shop",
            "type":"Services"
        }
    ],
    "sg:phone":"+1 715 289 3313",
    "sg:postcode":"54727",
    "sg:province":"WI",
    "wof:name":"Danville Taxidermy",
    "wof:placetype":"venue"
},
  "geometry": {"coordinates":[-91.085756,45.010336],"type":"Point"}
}