{
  "type": "Feature",
  "properties": {
    "iso:country":"US",
    "sg:address":"904 Valley Dr",
    "sg:city":"Watertown",
    "sg:classifiers":[
        {
            "category":"Professional",
            "subcategory":"Accounting & Tax Preparation",
            "type":"Services"
        }
    ],
    "sg:phone":"+1 920 262 9488",
    "sg:postcode":"53098",
    "sg:province":"WI",
    "sg:tags":[
        "return",
        "filing"
    ],
    "wof:name":"A Tax",
    "wof:placetype":"venue"
},
  "geometry": {"coordinates":[-88.705201,43.209627],"type":"Point"}
}