{
  "type": "Feature",
  "properties": {
    "addr:full":"3008 Co Rd K Wausau WI 54401",
    "addr:housenumber":"3008",
    "addr:postcode":"54401",
    "addr:street":"Co Rd",
    "iso:country":"US",
    "sg:address":"3008 Co Rd K",
    "sg:city":"Wausau",
    "sg:classifiers":[
        {
            "category":"Professional",
            "type":"Services"
        }
    ],
    "sg:phone":"+1 715 675 7732",
    "sg:postcode":"54401",
    "sg:province":"WI",
    "sg:tags":[
        "establishment"
    ],
    "wof:name":"D Becker Inc",
    "wof:placetype":"venue"
},
  "geometry": {"coordinates":[-89.66390699999999,44.996957],"type":"Point"}
}