{
  "type": "Feature",
  "properties": {
    "iso:country":"US",
    "sg:address":"6637 University Ave",
    "sg:city":"Middleton",
    "sg:classifiers":[
        {
            "category":"Food & Beverages",
            "subcategory":"Bakery",
            "type":"Retail Goods"
        }
    ],
    "sg:phone":"+1 608 836 7333",
    "sg:postcode":"53562",
    "sg:province":"WI",
    "sg:tags":[
        "baker"
    ],
    "sg:website":"www.explorewisconsin.com",
    "wof:name":"Scott's Pastry Shoppe Inc",
    "wof:placetype":"venue"
},
  "geometry": {"coordinates":[-89.494709,43.095595],"type":"Point"}
}