{
  "type": "Feature",
  "properties": {
    "iso:country":"US",
    "sg:address":"804 Main St",
    "sg:city":"La Pointe",
    "sg:classifiers":[
        {
            "category":"Food & Beverages",
            "subcategory":"Groceries & Convenience Stores",
            "type":"Retail Goods"
        }
    ],
    "sg:phone":"+1 715 747 6635",
    "sg:postcode":"54850",
    "sg:province":"WI",
    "sg:tags":[
        "grocer"
    ],
    "wof:name":"Island Store",
    "wof:placetype":"venue"
},
  "geometry": {"coordinates":[-90.78358,46.77547],"type":"Point"}
}