{
  "type": "Feature",
  "properties": {
    "iso:country":"US",
    "sg:address":"356 Lac Verde Cir",
    "sg:city":"Green Lake",
    "sg:classifiers":[
        {
            "category":"Real Estate",
            "subcategory":"Real Estate Agent",
            "type":"Services"
        }
    ],
    "sg:phone":"+1 920 294 6453",
    "sg:postcode":"54941",
    "sg:province":"WI",
    "sg:tags":[
        "company",
        "holding"
    ],
    "wof:name":"Baird Real Estate Holding",
    "wof:placetype":"venue"
},
  "geometry": {"coordinates":[-88.945584,43.836569],"type":"Point"}
}