{
  "type": "Feature",
  "properties": {
    "iso:country":"US",
    "sg:address":"5262 N Teutonia Ave",
    "sg:city":"Milwaukee",
    "sg:classifiers":[
        {
            "category":"Shopping",
            "subcategory":"Clothing, Apparel, & Fashions",
            "type":"Retail Goods"
        }
    ],
    "sg:phone":"+1 414 462 4254",
    "sg:postcode":"53209",
    "sg:province":"WI",
    "wof:name":"Knotty Knits",
    "wof:placetype":"venue"
},
  "geometry": {"coordinates":[-87.950033,43.113584],"type":"Point"}
}