{
  "type": "Feature",
  "properties": {
    "addr:full":"3800 Old Town Hall Rd Eau Claire WI 54701",
    "addr:housenumber":"3800",
    "addr:postcode":"54701",
    "addr:street":"Old;Hall Rd",
    "iso:country":"US",
    "sg:address":"3800 Old Town Hall Rd",
    "sg:city":"Eau Claire",
    "sg:classifiers":[
        {
            "category":"Retail",
            "subcategory":"Animal Services",
            "type":"Services"
        }
    ],
    "sg:phone":"+1 715 831 4464",
    "sg:postcode":"54701",
    "sg:province":"WI",
    "wof:name":"Indianhead Kennel Club",
    "wof:placetype":"venue"
},
  "geometry": {"coordinates":[-91.45740600000001,44.764607],"type":"Point"}
}