{
  "type": "Feature",
  "properties": {
    "iso:country":"US",
    "sg:address":"2104 Geele Ave",
    "sg:city":"Sheboygan",
    "sg:classifiers":[
        {
            "category":"Building & Trades",
            "subcategory":"Construction",
            "type":"Services"
        }
    ],
    "sg:phone":"+1 920 453 6781",
    "sg:postcode":"53083",
    "sg:province":"WI",
    "sg:tags":[
        "home",
        "builder"
    ],
    "wof:name":"TLC Homes Inc",
    "wof:placetype":"venue"
},
  "geometry": {"coordinates":[-87.735131,43.768507],"type":"Point"}
}