{
  "type": "Feature",
  "properties": {
    "iso:country":"US",
    "sg:address":"8206 State Hwy 68",
    "sg:city":"Waupun",
    "sg:classifiers":[
        {
            "category":"Retail",
            "subcategory":"Animal Services",
            "type":"Services"
        }
    ],
    "sg:phone":"+1 920 324 3262",
    "sg:postcode":"53963",
    "sg:province":"WI",
    "wof:name":"Rondo Acres Inc",
    "wof:placetype":"venue"
},
  "geometry": {"coordinates":[-88.814397,43.610197],"type":"Point"}
}