{
  "type": "Feature",
  "properties": {
    "iso:country":"US",
    "sg:address":"7102 Evergreen St",
    "sg:city":"Schofield",
    "sg:classifiers":[
        {
            "category":"Real Estate",
            "subcategory":"Real Estate Agent",
            "type":"Services"
        }
    ],
    "sg:phone":"+1 715 359 3115",
    "sg:postcode":"54476",
    "sg:province":"WI",
    "wof:name":"Francis Dr Properties LLC",
    "wof:placetype":"venue"
},
  "geometry": {"coordinates":[-89.596615,44.891883],"type":"Point"}
}