{
  "type": "Feature",
  "properties": {
    "iso:country":"US",
    "sg:address":"941 Pontiac Trl",
    "sg:city":"Madison",
    "sg:classifiers":[
        {
            "category":"Building & Trades",
            "subcategory":"Construction",
            "type":"Services"
        }
    ],
    "sg:phone":"+1 608 278 1919",
    "sg:postcode":"53711",
    "sg:province":"WI",
    "sg:tags":[
        "hanging",
        "contractor"
    ],
    "wof:name":"John Dowling Painting",
    "wof:placetype":"venue"
},
  "geometry": {"coordinates":[-89.45629,43.041905],"type":"Point"}
}