{
  "type": "Feature",
  "properties": {
    "iso:country":"US",
    "sg:address":"607 Wisconsin St",
    "sg:city":"Merrill",
    "sg:classifiers":[
        {
            "category":"Social Services",
            "subcategory":"Child Care",
            "type":"Services"
        }
    ],
    "sg:phone":"+1 715 536 8041",
    "sg:postcode":"54452",
    "sg:province":"WI",
    "sg:tags":[
        "day"
    ],
    "wof:name":"Lots Tots Christian Care LLC",
    "wof:placetype":"venue"
},
  "geometry": {"coordinates":[-89.713519,45.185208],"type":"Point"}
}