{
  "type": "Feature",
  "properties": {
    "iso:country":"US",
    "sg:address":"202 8th Ave W",
    "sg:city":"Washburn",
    "sg:classifiers":[
        {
            "category":"Professional",
            "subcategory":"Business Services",
            "type":"Services"
        }
    ],
    "sg:phone":"+1 715 373 0550",
    "sg:postcode":"54891",
    "sg:province":"WI",
    "wof:name":"Bay Area Design LLC",
    "wof:placetype":"venue"
},
  "geometry": {"coordinates":[-90.905488,46.669536],"type":"Point"}
}