{
  "type": "Feature",
  "properties": {
    "addr:full":"926 S Grove St Ripon WI 54971",
    "addr:housenumber":"926",
    "addr:postcode":"54971",
    "addr:street":"S Grove St",
    "iso:country":"US",
    "sg:address":"926 S Grove St",
    "sg:city":"Ripon",
    "sg:classifiers":[
        {
            "category":"Health Services",
            "subcategory":"Doctor",
            "type":"Services"
        }
    ],
    "sg:phone":"+1 920 748 6628",
    "sg:postcode":"54971",
    "sg:province":"WI",
    "sg:tags":[
        "dentist"
    ],
    "wof:name":"Lawrence A Johnson DDS SC",
    "wof:placetype":"venue"
},
  "geometry": {"coordinates":[-88.842546,43.833928],"type":"Point"}
}