{
  "type": "Feature",
  "properties": {
    "iso:country":"US",
    "sg:address":"340 State St",
    "sg:city":"Madison",
    "sg:classifiers":[
        {
            "category":"Shopping",
            "subcategory":"Clothing, Apparel, & Fashions",
            "type":"Retail Goods"
        }
    ],
    "sg:phone":"+1 608 256 2062",
    "sg:postcode":"53703",
    "sg:province":"WI",
    "sg:tags":[
        "furnishing"
    ],
    "wof:name":"Jazzman",
    "wof:placetype":"venue"
},
  "geometry": {"coordinates":[-89.3912,43.07485],"type":"Point"}
}