{
  "type": "Feature",
  "properties": {
    "iso:country":"US",
    "sg:address":"3315 Co Hwy I",
    "sg:city":"Saukville",
    "sg:classifiers":[
        {
            "category":"Bars & Pubs",
            "type":"Food & Drink"
        }
    ],
    "sg:phone":"+1 262 284 9808",
    "sg:postcode":"53080",
    "sg:province":"WI",
    "wof:name":"Mc Carthy's",
    "wof:placetype":"venue"
},
  "geometry": {"coordinates":[-87.979934,43.39619],"type":"Point"}
}