{
  "type": "Feature",
  "properties": {
    "addr:full":"10136 W Fond du Lac Ave Milwaukee WI 53224",
    "addr:housenumber":"10136",
    "addr:postcode":"53224",
    "addr:street":"W Fond Du Lac Ave",
    "iso:country":"US",
    "sg:address":"10136 W Fond du Lac Ave",
    "sg:city":"Milwaukee",
    "sg:classifiers":[
        {
            "category":"Professional",
            "subcategory":"Business Services",
            "type":"Services"
        }
    ],
    "sg:phone":"+1 414 353 3800",
    "sg:postcode":"53224",
    "sg:province":"WI",
    "wof:name":"Perfection Woodfinishes Corp",
    "wof:placetype":"venue"
},
  "geometry": {"coordinates":[-88.04280799999999,43.141723],"type":"Point"}
}