{
  "type": "Feature",
  "properties": {
    "iso:country":"US",
    "sg:address":"4272 W Highland Blvd",
    "sg:city":"Milwaukee",
    "sg:classifiers":[
        {
            "category":"Building & Trades",
            "subcategory":"Landscaping Services",
            "type":"Services"
        },
        {
            "category":"Social Services",
            "subcategory":"Adult Care",
            "type":"Services"
        }
    ],
    "sg:phone":"+1 414 342 1209",
    "sg:postcode":"53208",
    "sg:province":"WI",
    "sg:tags":[
        "nurses-home",
        "aged",
        "homes-institutional"
    ],
    "wof:name":"Mariah's Family Care Home",
    "wof:placetype":"venue"
},
  "geometry": {"coordinates":[-87.965334,43.048259],"type":"Point"}
}