{
  "type": "Feature",
  "properties": {
    "iso:country":"US",
    "sg:address":"3002 Bollenbeck St",
    "sg:city":"Cross Plains",
    "sg:classifiers":[
        {
            "category":"Real Estate",
            "subcategory":"Real Estate Services",
            "type":"Services"
        }
    ],
    "sg:phone":"+1 608 798 2838",
    "sg:postcode":"53528",
    "sg:province":"WI",
    "sg:tags":[
        "abstract",
        "title"
    ],
    "wof:name":"Titletech",
    "wof:placetype":"venue"
},
  "geometry": {"coordinates":[-89.629735,43.119436],"type":"Point"}
}