{
  "type": "Feature",
  "properties": {
    "iso:country":"US",
    "sg:address":"116 N 2nd St",
    "sg:city":"Delavan",
    "sg:classifiers":[
        {
            "category":"Manufacturing",
            "subcategory":"Printing",
            "type":"Manufacturing & Wholesale Goods"
        }
    ],
    "sg:phone":"+1 262 728 9500",
    "sg:postcode":"53115",
    "sg:province":"WI",
    "sg:tags":[
        "screen"
    ],
    "wof:name":"Murphite Custom Screen Print",
    "wof:placetype":"venue"
},
  "geometry": {"coordinates":[-88.646984,42.633305],"type":"Point"}
}