{
  "type": "Feature",
  "properties": {
    "iso:country":"US",
    "sg:address":"107 Park St",
    "sg:city":"Walworth",
    "sg:classifiers":[
        {
            "category":"Cinema",
            "subcategory":"Movie Rental",
            "type":"Entertainment"
        }
    ],
    "sg:phone":"+1 262 275 2265",
    "sg:postcode":"53184",
    "sg:province":"WI",
    "sg:tags":[
        "leasing",
        "video",
        "disc",
        "tape"
    ],
    "wof:name":"Video Country",
    "wof:placetype":"venue"
},
  "geometry": {"coordinates":[-88.59768,42.532569],"type":"Point"}
}