{
  "type": "Feature",
  "properties": {
    "iso:country":"US",
    "sg:address":"1545 30th Ave",
    "sg:city":"Kenosha",
    "sg:classifiers":[
        {
            "category":"Banks & Credit Unions",
            "subcategory":"Bank",
            "type":"Services"
        }
    ],
    "sg:phone":"+1 262 553 8500",
    "sg:postcode":"53144",
    "sg:province":"WI",
    "wof:name":"Guaranty Bank",
    "wof:placetype":"venue"
},
  "geometry": {"coordinates":[-87.845816,42.629821],"type":"Point"}
}