{
  "type": "Feature",
  "properties": {
    "iso:country":"US",
    "sg:address":"1607 10th St",
    "sg:city":"Monroe",
    "sg:classifiers":[
        {
            "category":"Shopping",
            "subcategory":"Clothing, Apparel, & Fashions",
            "type":"Retail Goods"
        }
    ],
    "sg:phone":"+1 608 325 3178",
    "sg:postcode":"53566",
    "sg:province":"WI",
    "wof:name":"Town & Country Styles",
    "wof:placetype":"venue"
},
  "geometry": {"coordinates":[-89.63864,42.602187],"type":"Point"}
}