{
  "type": "Feature",
  "properties": {
    "iso:country":"US",
    "sg:address":"5767 Monticello Way",
    "sg:city":"Madison",
    "sg:classifiers":[
        {
            "category":"Shopping",
            "subcategory":"Books",
            "type":"Retail Goods"
        }
    ],
    "sg:phone":"+1 608 274 3489",
    "sg:postcode":"53719",
    "sg:province":"WI",
    "wof:name":"Caseys World Books LLC",
    "wof:placetype":"venue"
},
  "geometry": {"coordinates":[-89.477875,43.025953],"type":"Point"}
}