{
  "type": "Feature",
  "properties": {
    "iso:country":"US",
    "sg:address":"104 E Main St",
    "sg:city":"Lena",
    "sg:classifiers":[
        {
            "category":"Restaurant",
            "type":"Food & Drink"
        }
    ],
    "sg:phone":"+1 920 829 5168",
    "sg:postcode":"54139",
    "sg:province":"WI",
    "wof:name":"Bavarian Inn Supper Club",
    "wof:placetype":"venue"
},
  "geometry": {"coordinates":[-88.046774,44.951097],"type":"Point"}
}