{
  "type": "Feature",
  "properties": {
    "addr:full":"4698 State Hwy 16 Sparta WI 54656",
    "addr:housenumber":"4698",
    "addr:postcode":"54656",
    "addr:street":"State Hwy 16",
    "iso:country":"US",
    "sg:address":"4698 State Hwy 16",
    "sg:city":"Sparta",
    "sg:classifiers":[
        {
            "category":"Building & Trades",
            "subcategory":"Construction",
            "type":"Services"
        }
    ],
    "sg:phone":"+1 608 269 2307",
    "sg:postcode":"54656",
    "sg:province":"WI",
    "sg:tags":[
        "painter"
    ],
    "wof:name":"Barsness Painting Co",
    "wof:placetype":"venue"
},
  "geometry": {"coordinates":[-90.89390400000001,43.930238],"type":"Point"}
}