{
  "type": "Feature",
  "properties": {
    "iso:country":"US",
    "sg:address":"5298 Co Hwy A",
    "sg:city":"Deerbrook",
    "sg:classifiers":[
        {
            "category":"Bars & Pubs",
            "type":"Food & Drink"
        }
    ],
    "sg:phone":"+1 715 623 6611",
    "sg:postcode":"54424",
    "sg:province":"WI",
    "wof:name":"Quinn's Bar",
    "wof:placetype":"venue"
},
  "geometry": {"coordinates":[-89.14488299999999,45.219159],"type":"Point"}
}