{
  "type": "Feature",
  "properties": {
    "iso:country":"US",
    "sg:address":"6443 S Farmington Rd",
    "sg:city":"Helenville",
    "sg:classifiers":[
        {
            "category":"Bars & Pubs",
            "type":"Food & Drink"
        }
    ],
    "sg:phone":"+1 920 699 3725",
    "sg:postcode":"53137",
    "sg:province":"WI",
    "sg:tags":[
        "drinking"
    ],
    "wof:name":"Farmington Inn",
    "wof:placetype":"venue"
},
  "geometry": {"coordinates":[-88.67232199999999,43.083428],"type":"Point"}
}