{
  "type": "Feature",
  "properties": {
    "addr:full":"2356 S 102nd St Milwaukee WI 53227",
    "addr:housenumber":"2356",
    "addr:postcode":"53227",
    "addr:street":"S 102Nd St",
    "iso:country":"US",
    "sg:address":"2356 S 102nd St",
    "sg:city":"Milwaukee",
    "sg:classifiers":[
        {
            "category":"Health Services",
            "subcategory":"Clinic",
            "type":"Services"
        }
    ],
    "sg:phone":"+1 414 546 4259",
    "sg:postcode":"53227",
    "sg:province":"WI",
    "sg:tags":[
        "wellness",
        "program"
    ],
    "wof:name":"Sleep Wellness Institute",
    "wof:placetype":"venue"
},
  "geometry": {"coordinates":[-88.040638,43.001536],"type":"Point"}
}