{
  "type": "Feature",
  "properties": {
    "iso:country":"US",
    "sg:address":"970 Green Bay Rd",
    "sg:city":"Kenosha",
    "sg:classifiers":[
        {
            "category":"Building & Trades",
            "subcategory":"Landscaping Services",
            "type":"Services"
        }
    ],
    "sg:phone":"+1 262 553 5532",
    "sg:postcode":"53144",
    "sg:province":"WI",
    "sg:tags":[
        "agricultural"
    ],
    "wof:name":"Randys Landscaping Inc",
    "wof:placetype":"venue"
},
  "geometry": {"coordinates":[-87.876436,42.644746],"type":"Point"}
}