{
  "type": "Feature",
  "properties": {
    "iso:country":"US",
    "sg:address":"8929 State Hwy 110",
    "sg:city":"Fremont",
    "sg:classifiers":[
        {
            "category":"Building & Trades",
            "subcategory":"Landscaping Services",
            "type":"Services"
        }
    ],
    "sg:phone":"+1 920 446 3202",
    "sg:postcode":"54940",
    "sg:province":"WI",
    "sg:tags":[
        "sanitary"
    ],
    "wof:name":"Greenscape Lawn Service",
    "wof:placetype":"venue"
},
  "geometry": {"coordinates":[-88.847521,44.234351],"type":"Point"}
}