{
  "type": "Feature",
  "properties": {
    "iso:country":"US",
    "sg:address":"2104 Beloit Ave",
    "sg:city":"Janesville",
    "sg:classifiers":[
        {
            "category":"Autos & Motor Vehicles",
            "subcategory":"Fuel & Gas Station",
            "type":"Retail Goods"
        }
    ],
    "sg:phone":"+1 608 754 1183",
    "sg:postcode":"53546",
    "sg:province":"WI",
    "sg:tags":[
        "oil"
    ],
    "wof:name":"Rollette Oil Co",
    "wof:placetype":"venue"
},
  "geometry": {"coordinates":[-89.011843,42.647135],"type":"Point"}
}