{
  "type": "Feature",
  "properties": {
    "iso:country":"US",
    "sg:address":"614 Fredrick Ct",
    "sg:city":"Green Bay",
    "sg:classifiers":[
        {
            "category":"Farming",
            "subcategory":"Nursery",
            "type":"Manufacturing & Wholesale Goods"
        }
    ],
    "sg:phone":"+1 920 434 9353",
    "sg:postcode":"54313",
    "sg:province":"WI",
    "sg:tags":[
        "greenhouse"
    ],
    "wof:name":"Canterbury Farm & Greenhouses",
    "wof:placetype":"venue"
},
  "geometry": {"coordinates":[-88.120059,44.561627],"type":"Point"}
}