{
  "type": "Feature",
  "properties": {
    "iso:country":"US",
    "sg:address":"4055 N Teutonia Ave",
    "sg:city":"Milwaukee",
    "sg:classifiers":[
        {
            "category":"Cinema",
            "subcategory":"Movie Rental",
            "type":"Entertainment"
        }
    ],
    "sg:phone":"+1 414 444 9915",
    "sg:postcode":"53209",
    "sg:province":"WI",
    "sg:tags":[
        "video",
        "tape"
    ],
    "wof:name":"Hollywood Video",
    "wof:placetype":"venue"
},
  "geometry": {"coordinates":[-87.939323,43.090278],"type":"Point"}
}