{
  "type": "Feature",
  "properties": {
    "iso:country":"US",
    "sg:address":"5546 Desert Rd",
    "sg:city":"Weyauwega",
    "sg:classifiers":[
        {
            "category":"Banks & Credit Unions",
            "subcategory":"Financial Services",
            "type":"Services"
        }
    ],
    "sg:phone":"+1 920 867 3830",
    "sg:postcode":"54983",
    "sg:province":"WI",
    "sg:tags":[
        "investor"
    ],
    "wof:name":"Moondance Investments LLC",
    "wof:placetype":"venue"
},
  "geometry": {"coordinates":[-88.94845100000001,44.254386],"type":"Point"}
}