{
  "type": "Feature",
  "properties": {
    "iso:country":"US",
    "sg:address":"2502 Longtail Beach Ln",
    "sg:city":"Suamico",
    "sg:classifiers":[
        {
            "category":"Building & Trades",
            "subcategory":"Construction",
            "type":"Services"
        }
    ],
    "sg:phone":"+1 920 434 1262",
    "sg:postcode":"54173",
    "sg:province":"WI",
    "sg:tags":[
        "insulation",
        "contractor"
    ],
    "wof:name":"Schuette Insulators Inc",
    "wof:placetype":"venue"
},
  "geometry": {"coordinates":[-88.014409,44.609798],"type":"Point"}
}