{
  "type": "Feature",
  "properties": {
    "addr:full":"14010 Leetsbir Rd Sturtevant WI 53177",
    "addr:housenumber":"14010",
    "addr:postcode":"53177",
    "addr:street":"Leetsbir Rd",
    "iso:country":"US",
    "sg:address":"14010 Leetsbir Rd",
    "sg:city":"Sturtevant",
    "sg:classifiers":[
        {
            "category":"Home & Garden",
            "subcategory":"Furniture",
            "type":"Retail Goods"
        }
    ],
    "sg:phone":"+1 262 886 6820",
    "sg:postcode":"53177",
    "sg:province":"WI",
    "sg:tags":[
        "equipment",
        "kitchen",
        "cabinet"
    ],
    "wof:name":"Dan Peuschold Designs",
    "wof:placetype":"venue"
},
  "geometry": {"coordinates":[-87.957624,42.707355],"type":"Point"}
}