{
  "type": "Feature",
  "properties": {
    "iso:country":"US",
    "sg:address":"710 Ann St",
    "sg:city":"Delavan",
    "sg:classifiers":[
        {
            "category":"Retail",
            "subcategory":"Auto Repair",
            "type":"Services"
        }
    ],
    "sg:phone":"+1 262 728 2944",
    "sg:postcode":"53115",
    "sg:province":"WI",
    "sg:tags":[
        "repairing",
        "automobile"
    ],
    "wof:name":"Advanced Auto Clinic",
    "wof:placetype":"venue"
},
  "geometry": {"coordinates":[-88.636423,42.630197],"type":"Point"}
}