{
  "type": "Feature",
  "properties": {
    "iso:country":"US",
    "sg:address":"4809 Ellestad Dr",
    "sg:city":"Madison",
    "sg:classifiers":[
        {
            "category":"Retail",
            "subcategory":"Car Wash",
            "type":"Services"
        }
    ],
    "sg:phone":"+1 608 224 0359",
    "sg:postcode":"53716",
    "sg:province":"WI",
    "sg:tags":[
        "carwash"
    ],
    "wof:name":"R & D Detailers",
    "wof:placetype":"venue"
},
  "geometry": {"coordinates":[-89.299047,43.049376],"type":"Point"}
}