{
  "type": "Feature",
  "properties": {
    "addr:full":"3524 N 23rd St Milwaukee WI 53206",
    "addr:housenumber":"3524",
    "addr:postcode":"53206",
    "addr:street":"N 23Rd St",
    "iso:country":"US",
    "sg:address":"3524 N 23rd St",
    "sg:city":"Milwaukee",
    "sg:classifiers":[
        {
            "category":"Professional",
            "type":"Services"
        }
    ],
    "sg:phone":"+1 414 442 1399",
    "sg:postcode":"53206",
    "sg:province":"WI",
    "wof:name":"Covies Play World",
    "wof:placetype":"venue"
},
  "geometry": {"coordinates":[-87.941007,43.083301],"type":"Point"}
}