{
  "type": "Feature",
  "properties": {
    "iso:country":"US",
    "sg:address":"2111 9th Ave",
    "sg:city":"Monroe",
    "sg:classifiers":[
        {
            "category":"Building & Trades",
            "subcategory":"Construction",
            "type":"Services"
        }
    ],
    "sg:phone":"+1 608 325 6342",
    "sg:postcode":"53566",
    "sg:province":"WI",
    "sg:tags":[
        "contractor"
    ],
    "wof:name":"Arnold F Stalder",
    "wof:placetype":"venue"
},
  "geometry": {"coordinates":[-89.648637,42.592138],"type":"Point"}
}