{
  "type": "Feature",
  "properties": {
    "iso:country":"US",
    "sg:address":"4743 Wilderness Ln",
    "sg:city":"Harshaw",
    "sg:classifiers":[
        {
            "category":"Bars & Pubs",
            "type":"Food & Drink"
        }
    ],
    "sg:phone":"+1 715 277 2341",
    "sg:postcode":"54529",
    "sg:province":"WI",
    "sg:tags":[
        "drinking",
        "operation"
    ],
    "wof:name":"Fridays Resort",
    "wof:placetype":"venue"
},
  "geometry": {"coordinates":[-89.606172,45.68999],"type":"Point"}
}