{
  "type": "Feature",
  "properties": {
    "addr:full":"1034 Walnut St Eagle River WI 54521",
    "addr:housenumber":"1034",
    "addr:postcode":"54521",
    "addr:street":"Walnut St",
    "iso:country":"US",
    "sg:address":"1034 Walnut St",
    "sg:city":"Eagle River",
    "sg:classifiers":[
        {
            "category":"Government",
            "subcategory":"Office",
            "type":"Public Place"
        }
    ],
    "sg:phone":"+1 715 479 9561",
    "sg:postcode":"54521",
    "sg:province":"WI",
    "sg:tags":[
        "conservation"
    ],
    "wof:name":"Supreme Soil Testing",
    "wof:placetype":"venue"
},
  "geometry": {"coordinates":[-89.23557,45.919264],"type":"Point"}
}