{
  "type": "Feature",
  "properties": {
    "iso:country":"US",
    "sg:address":"400 Scott St",
    "sg:city":"Wausau",
    "sg:classifiers":[
        {
            "category":"Banks & Credit Unions",
            "subcategory":"Bank",
            "type":"Services"
        }
    ],
    "sg:phone":"+1 715 848 2818",
    "sg:postcode":"54403",
    "sg:province":"WI",
    "sg:website":"www.firstfed.com",
    "wof:name":"Associated Bank",
    "wof:placetype":"venue"
},
  "geometry": {"coordinates":[-89.625491,44.960498],"type":"Point"}
}