{
  "type": "Feature",
  "properties": {
    "iso:country":"US",
    "sg:address":"1300 1st Ave",
    "sg:city":"Eau Claire",
    "sg:classifiers":[
        {
            "category":"Social Services",
            "type":"Services"
        }
    ],
    "sg:phone":"+1 715 835 4977",
    "sg:postcode":"54703",
    "sg:province":"WI",
    "sg:tags":[
        "organization",
        "welfare"
    ],
    "wof:name":"Community Table",
    "wof:placetype":"venue"
},
  "geometry": {"coordinates":[-91.509326,44.814713],"type":"Point"}
}