{
  "type": "Feature",
  "properties": {
    "iso:country":"US",
    "sg:address":"6200 N 39th St",
    "sg:city":"Milwaukee",
    "sg:classifiers":[
        {
            "category":"Wholesale",
            "subcategory":"Chemicals & Plastics",
            "type":"Manufacturing & Wholesale Goods"
        }
    ],
    "sg:phone":"+1 414 393 1901",
    "sg:postcode":"53209",
    "sg:province":"WI",
    "sg:tags":[
        "synthetic",
        "organic"
    ],
    "wof:name":"Panslavia Chemicals LLC",
    "wof:placetype":"venue"
},
  "geometry": {"coordinates":[-87.960831,43.132076],"type":"Point"}
}