{
  "type": "Feature",
  "properties": {
    "addr:full":"12257 N River Rd Mequon WI 53092",
    "addr:housenumber":"12257",
    "addr:postcode":"53092",
    "addr:street":"N River Rd",
    "iso:country":"US",
    "sg:address":"12257 N River Rd",
    "sg:city":"Mequon",
    "sg:classifiers":[
        {
            "category":"Real Estate",
            "subcategory":"Real Estate Agent",
            "type":"Services"
        }
    ],
    "sg:phone":"+1 262 242 9658",
    "sg:postcode":"53092",
    "sg:province":"WI",
    "wof:name":"Brauckhoff River Road",
    "wof:placetype":"venue"
},
  "geometry": {"coordinates":[-87.963905,43.239921],"type":"Point"}
}