{
  "type": "Feature",
  "properties": {
    "iso:country":"US",
    "sg:address":"1707 Co Rd A",
    "sg:city":"Phelps",
    "sg:classifiers":[
        {
            "category":"Retail",
            "subcategory":"Repair Shop",
            "type":"Services"
        }
    ],
    "sg:phone":"+1 715 545 3109",
    "sg:postcode":"54554",
    "sg:province":"WI",
    "sg:tags":[
        "upholsterer"
    ],
    "wof:name":"Barth's Upholstery & Repair",
    "wof:placetype":"venue"
},
  "geometry": {"coordinates":[-89.043173,46.036589],"type":"Point"}
}