{
  "type": "Feature",
  "properties": {
    "iso:country":"US",
    "sg:address":"3814 Jefferson St",
    "sg:city":"Sullivan",
    "sg:phone":"+1 262 593 2923",
    "sg:postcode":"53178",
    "sg:province":"WI",
    "sg:tags":[
        "farm",
        "corn"
    ],
    "wof:name":"Novaks Farm",
    "wof:placetype":"venue"
},
  "geometry": {"coordinates":[-88.63099699999999,42.981421],"type":"Point"}
}