{
  "type": "Feature",
  "properties": {
    "addr:full":"9438 N 107th St Milwaukee WI 53224",
    "addr:housenumber":"9438",
    "addr:postcode":"53224",
    "addr:street":"N 107Th St",
    "iso:country":"US",
    "sg:address":"9438 N 107th St",
    "sg:city":"Milwaukee",
    "sg:classifiers":[
        {
            "category":"Building & Trades",
            "subcategory":"Cleaning & Sanitation",
            "type":"Services"
        }
    ],
    "sg:phone":"+1 414 586 0744",
    "sg:postcode":"53224",
    "sg:province":"WI",
    "sg:tags":[
        "janitor"
    ],
    "wof:name":"Showtime Maintenance LLC",
    "wof:placetype":"venue"
},
  "geometry": {"coordinates":[-88.043801,43.188012],"type":"Point"}
}