{
  "type": "Feature",
  "properties": {
    "iso:country":"US",
    "sg:address":"416 Olive St",
    "sg:city":"Chippewa Falls",
    "sg:classifiers":[
        {
            "category":"Professional",
            "subcategory":"Accounting & Tax Preparation",
            "type":"Services"
        }
    ],
    "sg:phone":"+1 715 723 2642",
    "sg:postcode":"54729",
    "sg:province":"WI",
    "wof:name":"Larry D Martineau",
    "wof:placetype":"venue"
},
  "geometry": {"coordinates":[-91.407633,44.941571],"type":"Point"}
}