{
  "type": "Feature",
  "properties": {
    "iso:country":"US",
    "sg:address":"2455 N 45th St",
    "sg:city":"Milwaukee",
    "sg:classifiers":[
        {
            "category":"Professional",
            "type":"Services"
        }
    ],
    "sg:phone":"+1 414 449 0334",
    "sg:postcode":"53210",
    "sg:province":"WI",
    "wof:name":"Rogge Jerome & Maple",
    "wof:placetype":"venue"
},
  "geometry": {"coordinates":[-87.970096,43.063266],"type":"Point"}
}