{
  "type": "Feature",
  "properties": {
    "iso:country":"US",
    "sg:address":"2428 State Hwy 95",
    "sg:city":"Arcadia",
    "sg:classifiers":[
        {
            "category":"Restaurant",
            "type":"Food & Drink"
        }
    ],
    "sg:phone":"+1 608 323 7044",
    "sg:postcode":"54612",
    "sg:province":"WI",
    "wof:name":"Hansen's Hold Up",
    "wof:placetype":"venue"
},
  "geometry": {"coordinates":[-91.605149,44.242313],"type":"Point"}
}