{
  "type": "Feature",
  "properties": {
    "iso:country":"US",
    "sg:address":"121 2nd St",
    "sg:city":"Taylor",
    "sg:classifiers":[
        {
            "category":"Restaurant",
            "type":"Food & Drink"
        }
    ],
    "sg:phone":"+1 715 662 5400",
    "sg:postcode":"54659",
    "sg:province":"WI",
    "wof:name":"Village Cafe",
    "wof:placetype":"venue"
},
  "geometry": {"coordinates":[-91.124077,44.32165],"type":"Point"}
}