{
  "type": "Feature",
  "properties": {
    "iso:country":"US",
    "sg:address":"558 E Clay St",
    "sg:city":"Whitewater",
    "sg:classifiers":[
        {
            "category":"Retail",
            "subcategory":"Portrait Studio",
            "type":"Services"
        }
    ],
    "sg:phone":"+1 262 473 2490",
    "sg:postcode":"53190",
    "sg:province":"WI",
    "sg:tags":[
        "photographer"
    ],
    "wof:name":"LA Belle Studio Inc",
    "wof:placetype":"venue"
},
  "geometry": {"coordinates":[-88.721687,42.831116],"type":"Point"}
}