{
  "type": "Feature",
  "properties": {
    "addr:full":"5709 Hidden River Cir Schofield WI 54476",
    "addr:housenumber":"5709",
    "addr:postcode":"54476",
    "addr:street":"Hidden River Cir",
    "iso:country":"US",
    "sg:address":"5709 Hidden River Cir",
    "sg:city":"Schofield",
    "sg:classifiers":[
        {
            "category":"Shopping",
            "subcategory":"Stationery & Office Supplies",
            "type":"Retail Goods"
        }
    ],
    "sg:phone":"+1 715 241 9500",
    "sg:postcode":"54476",
    "sg:province":"WI",
    "wof:name":"Medialink Creative Solutions",
    "wof:placetype":"venue"
},
  "geometry": {"coordinates":[-89.551408,44.91623],"type":"Point"}
}