{
  "type": "Feature",
  "properties": {
    "addr:full":"629 5th Ave Antigo WI 54409",
    "addr:housenumber":"629",
    "addr:postcode":"54409",
    "addr:street":"5Th Ave",
    "iso:country":"US",
    "sg:address":"629 5th Ave",
    "sg:city":"Antigo",
    "sg:classifiers":[
        {
            "category":"Building & Trades",
            "subcategory":"Plumbing",
            "type":"Services"
        }
    ],
    "sg:phone":"+1 715 623 4196",
    "sg:postcode":"54409",
    "sg:province":"WI",
    "sg:tags":[
        "contractor"
    ],
    "wof:name":"Heinzen Plumbing & Heating Inc",
    "wof:placetype":"venue"
},
  "geometry": {"coordinates":[-89.15062,45.14042],"type":"Point"}
}