{
  "type": "Feature",
  "properties": {
    "addr:full":"2622 30th Ave Kenosha WI 53144",
    "addr:housenumber":"2622",
    "addr:postcode":"53144",
    "addr:street":"30Th Ave",
    "iso:country":"US",
    "sg:address":"2622 30th Ave",
    "sg:city":"Kenosha",
    "sg:classifiers":[
        {
            "category":"Insurance",
            "subcategory":"Insurance Agent",
            "type":"Services"
        }
    ],
    "sg:phone":"+1 262 551 8600",
    "sg:postcode":"53144",
    "sg:province":"WI",
    "wof:name":"Jerry Werwie",
    "wof:placetype":"venue"
},
  "geometry": {"coordinates":[-87.84590900000001,42.614701],"type":"Point"}
}