{
  "type": "Feature",
  "properties": {
    "addr:full":"3443 S Indiana Ave Milwaukee WI 53207",
    "addr:housenumber":"3443",
    "addr:postcode":"53207",
    "addr:street":"S Indiana Ave",
    "iso:country":"US",
    "sg:address":"3443 S Indiana Ave",
    "sg:city":"Milwaukee",
    "sg:classifiers":[
        {
            "category":"Professional",
            "subcategory":"Accounting & Tax Preparation",
            "type":"Services"
        }
    ],
    "sg:phone":"+1 414 481 9255",
    "sg:postcode":"53207",
    "sg:province":"WI",
    "sg:tags":[
        "return",
        "filing"
    ],
    "wof:name":"T Bear Financial Svc LLC",
    "wof:placetype":"venue"
},
  "geometry": {"coordinates":[-87.876172,42.981693],"type":"Point"}
}