{
  "type": "Feature",
  "properties": {
    "iso:country":"US",
    "sg:address":"10359 W Tower Ave",
    "sg:city":"Milwaukee",
    "sg:classifiers":[
        {
            "category":"Building & Trades",
            "subcategory":"Construction",
            "type":"Services"
        }
    ],
    "sg:phone":"+1 414 354 4090",
    "sg:postcode":"53224",
    "sg:province":"WI",
    "sg:tags":[
        "roofing",
        "contractor"
    ],
    "sg:website":"www.advancedroof.com",
    "wof:name":"Advanced Roofing Svc",
    "wof:placetype":"venue"
},
  "geometry": {"coordinates":[-88.039224,43.164513],"type":"Point"}
}