{
  "type": "Feature",
  "properties": {
    "iso:country":"US",
    "sg:address":"4540 US Hwy 10",
    "sg:city":"Auburndale",
    "sg:classifiers":[
        {
            "category":"Building & Trades",
            "subcategory":"Construction",
            "type":"Services"
        }
    ],
    "sg:phone":"+1 715 652 2236",
    "sg:postcode":"54412",
    "sg:province":"WI",
    "sg:tags":[
        "water",
        "well",
        "drilling"
    ],
    "wof:name":"Haupt Well Drilling Inc",
    "wof:placetype":"venue"
},
  "geometry": {"coordinates":[-89.94776,44.618126],"type":"Point"}
}