{
  "type": "Feature",
  "properties": {
    "addr:full":"4126 W Capitol Dr Milwaukee WI 53216",
    "addr:housenumber":"4126",
    "addr:postcode":"53216",
    "addr:street":"W Capitol Dr",
    "iso:country":"US",
    "sg:address":"4126 W Capitol Dr",
    "sg:city":"Milwaukee",
    "sg:classifiers":[
        {
            "category":"Shopping",
            "subcategory":"Used Merchandise",
            "type":"Retail Goods"
        }
    ],
    "sg:phone":"+1 414 875 9882",
    "sg:postcode":"53216",
    "sg:province":"WI",
    "wof:name":"Ramos Appliance",
    "wof:placetype":"venue"
},
  "geometry": {"coordinates":[-87.965081,43.089891],"type":"Point"}
}