{
  "type": "Feature",
  "properties": {
    "iso:country":"US",
    "sg:address":"406 W Gilman St",
    "sg:city":"Madison",
    "sg:classifiers":[
        {
            "category":"Shopping",
            "subcategory":"Used Merchandise",
            "type":"Retail Goods"
        }
    ],
    "sg:phone":"+1 608 259 9194",
    "sg:postcode":"53703",
    "sg:province":"WI",
    "wof:name":"Gozira Ya",
    "wof:placetype":"venue"
},
  "geometry": {"coordinates":[-89.394875,43.074153],"type":"Point"}
}