{
  "type": "Feature",
  "properties": {
    "iso:country":"US",
    "sg:address":"2325 Deer Trl",
    "sg:city":"Green Bay",
    "sg:classifiers":[
        {
            "category":"Banks & Credit Unions",
            "subcategory":"Financial Services",
            "type":"Services"
        }
    ],
    "sg:phone":"+1 920 468 1133",
    "sg:postcode":"54302",
    "sg:province":"WI",
    "sg:tags":[
        "company",
        "holding"
    ],
    "wof:name":"Gore Holdings LLC",
    "wof:placetype":"venue"
},
  "geometry": {"coordinates":[-87.965222,44.504166],"type":"Point"}
}