{
  "type": "Feature",
  "properties": {
    "iso:country":"US",
    "sg:address":"12719 Westview Rd",
    "sg:city":"Cleveland",
    "sg:classifiers":[
        {
            "category":"Farming",
            "subcategory":"Dairy Farm",
            "type":"Manufacturing & Wholesale Goods"
        }
    ],
    "sg:phone":"+1 920 726 4428",
    "sg:postcode":"53015",
    "sg:province":"WI",
    "wof:name":"Elroy Jaeger Farm",
    "wof:placetype":"venue"
},
  "geometry": {"coordinates":[-87.761784,43.94506],"type":"Point"}
}