{
  "type": "Feature",
  "properties": {
    "iso:country":"US",
    "sg:address":"7115 W Waterford Ave",
    "sg:city":"Milwaukee",
    "sg:classifiers":[
        {
            "category":"Professional",
            "subcategory":"Management & Consulting",
            "type":"Services"
        }
    ],
    "sg:phone":"+1 414 546 2136",
    "sg:postcode":"53220",
    "sg:province":"WI",
    "sg:tags":[
        "business"
    ],
    "wof:name":"Bernhardt & Associates LLC",
    "wof:placetype":"venue"
},
  "geometry": {"coordinates":[-88.00279,42.970304],"type":"Point"}
}