{
  "type": "Feature",
  "properties": {
    "iso:country":"US",
    "sg:address":"7803 90th Ave",
    "sg:city":"Mondovi",
    "sg:classifiers":[
        {
            "category":"Farming",
            "subcategory":"Dairy Farm",
            "type":"Manufacturing & Wholesale Goods"
        }
    ],
    "sg:phone":"+1 715 875 4794",
    "sg:postcode":"54755",
    "sg:province":"WI",
    "wof:name":"Cranberry Creek Dairy LLC",
    "wof:placetype":"venue"
},
  "geometry": {"coordinates":[-91.766881,44.712496],"type":"Point"}
}