{
  "type": "Feature",
  "properties": {
    "iso:country":"US",
    "sg:address":"1457 N 10th St",
    "sg:city":"Manitowoc",
    "sg:classifiers":[
        {
            "category":"Wholesale",
            "subcategory":"Electrical",
            "type":"Manufacturing & Wholesale Goods"
        }
    ],
    "sg:phone":"+1 920 684 2050",
    "sg:postcode":"54220",
    "sg:province":"WI",
    "sg:tags":[
        "control",
        "security",
        "system"
    ],
    "wof:name":"U S Security & Telephone",
    "wof:placetype":"venue"
},
  "geometry": {"coordinates":[-87.66042299999999,44.114734],"type":"Point"}
}