{
  "type": "Feature",
  "properties": {
    "iso:country":"US",
    "sg:address":"9716 S Nelson Rd",
    "sg:city":"Brodhead",
    "sg:classifiers":[
        {
            "category":"Utilities",
            "subcategory":"Refuse",
            "type":"Services"
        }
    ],
    "sg:phone":"+1 608 879 2877",
    "sg:postcode":"53520",
    "sg:province":"WI",
    "sg:tags":[
        "system"
    ],
    "wof:name":"Aej Recycling",
    "wof:placetype":"venue"
},
  "geometry": {"coordinates":[-89.307127,42.541277],"type":"Point"}
}