{
  "type": "Feature",
  "properties": {
    "addr:full":"3200 Washington Ave Racine WI 53405",
    "addr:housenumber":"3200",
    "addr:postcode":"53405",
    "addr:street":"Washington Ave",
    "iso:country":"US",
    "sg:address":"3200 Washington Ave",
    "sg:city":"Racine",
    "sg:classifiers":[
        {
            "category":"Food & Beverages",
            "subcategory":"Bakery",
            "type":"Retail Goods"
        }
    ],
    "sg:phone":"+1 262 633 0365",
    "sg:postcode":"53405",
    "sg:province":"WI",
    "sg:tags":[
        "baker"
    ],
    "sg:website":"www.bendtsensbakery.com",
    "wof:name":"Bendtsen's Bakery",
    "wof:placetype":"venue"
},
  "geometry": {"coordinates":[-87.818535,42.718699],"type":"Point"}
}