{
  "type": "Feature",
  "properties": {
    "iso:country":"US",
    "sg:address":"448 N Main St",
    "sg:city":"Oshkosh",
    "sg:classifiers":[
        {
            "category":"Shopping",
            "subcategory":"Used Merchandise",
            "type":"Retail Goods"
        }
    ],
    "sg:phone":"+1 920 233 3515",
    "sg:postcode":"54901",
    "sg:province":"WI",
    "wof:name":"Main Street Resale",
    "wof:placetype":"venue"
},
  "geometry": {"coordinates":[-88.537448,44.019311],"type":"Point"}
}