{
  "type": "Feature",
  "properties": {
    "iso:country":"US",
    "sg:address":"3037 N 9th St",
    "sg:city":"Milwaukee",
    "sg:classifiers":[
        {
            "category":"Shopping",
            "subcategory":"Clothing, Apparel, & Fashions",
            "type":"Retail Goods"
        }
    ],
    "sg:phone":"+1 414 372 2029",
    "sg:postcode":"53206",
    "sg:province":"WI",
    "sg:tags":[
        "hat"
    ],
    "wof:name":"Virginia's Original Boutique",
    "wof:placetype":"venue"
},
  "geometry": {"coordinates":[-87.922624,43.074218],"type":"Point"}
}