{
  "type": "Feature",
  "properties": {
    "iso:country":"US",
    "sg:address":"7576 Leisch Rd",
    "sg:city":"Trego",
    "sg:classifiers":[
        {
            "category":"Education",
            "subcategory":"School",
            "type":"Public Place"
        }
    ],
    "sg:phone":"+1 715 635 2174",
    "sg:postcode":"54888",
    "sg:province":"WI",
    "wof:name":"Spooner Elementary School",
    "wof:placetype":"venue"
},
  "geometry": {"coordinates":[-91.830044,45.908714],"type":"Point"}
}