{
  "type": "Feature",
  "properties": {
    "iso:country":"US",
    "sg:address":"4182 N Bartlett Ave",
    "sg:city":"Milwaukee",
    "sg:classifiers":[
        {
            "category":"Building & Trades",
            "subcategory":"Construction",
            "type":"Services"
        }
    ],
    "sg:phone":"+1 414 324 6891",
    "sg:postcode":"53211",
    "sg:province":"WI",
    "sg:tags":[
        "home",
        "improvement"
    ],
    "wof:name":"Letts Remodel LLC",
    "wof:placetype":"venue"
},
  "geometry": {"coordinates":[-87.888686,43.093055],"type":"Point"}
}