{
  "type": "Feature",
  "properties": {
    "addr:full":"5140 Sheeder Rd Eau Claire WI 54701",
    "addr:housenumber":"5140",
    "addr:postcode":"54701",
    "addr:street":"Sheeder Rd",
    "iso:country":"US",
    "sg:address":"5140 Sheeder Rd",
    "sg:city":"Eau Claire",
    "sg:classifiers":[
        {
            "category":"Building & Trades",
            "subcategory":"Equipment Rental",
            "type":"Services"
        }
    ],
    "sg:phone":"+1 715 831 6275",
    "sg:postcode":"54701",
    "sg:province":"WI",
    "wof:name":"Apex Rentals",
    "wof:placetype":"venue"
},
  "geometry": {"coordinates":[-91.448453,44.761422],"type":"Point"}
}