{
  "type": "Feature",
  "properties": {
    "iso:country":"US",
    "sg:address":"3201 Park Dr",
    "sg:city":"Sturgeon Bay",
    "sg:classifiers":[
        {
            "category":"Real Estate",
            "subcategory":"Real Estate Operator",
            "type":"Services"
        }
    ],
    "sg:phone":"+1 920 743 5750",
    "sg:postcode":"54235",
    "sg:province":"WI",
    "sg:tags":[
        "property",
        "lessor"
    ],
    "wof:name":"Leroy Liebe",
    "wof:placetype":"venue"
},
  "geometry": {"coordinates":[-87.427784,44.825711],"type":"Point"}
}