{
  "type": "Feature",
  "properties": {
    "iso:country":"US",
    "sg:address":"6819 39th Ave",
    "sg:city":"Kenosha",
    "sg:classifiers":[
        {
            "category":"Education",
            "subcategory":"Dance Studio",
            "type":"Public Place"
        }
    ],
    "sg:phone":"+1 262 909 0523",
    "sg:postcode":"53142",
    "sg:province":"IL",
    "sg:tags":[
        "instruction",
        "dancing"
    ],
    "wof:name":"An Angel's Art Dance School",
    "wof:placetype":"venue"
},
  "geometry": {"coordinates":[-87.855152,42.571531],"type":"Point"}
}