{
  "type": "Feature",
  "properties": {
    "iso:country":"US",
    "sg:address":"524 N Main St",
    "sg:city":"Patch Grove",
    "sg:classifiers":[
        {
            "category":"Personal",
            "subcategory":"Beauty Salon",
            "type":"Services"
        }
    ],
    "sg:phone":"+1 608 994 4247",
    "sg:postcode":"53817",
    "sg:province":"WI",
    "wof:name":"Neises Salon In Patch Grove",
    "wof:placetype":"venue"
},
  "geometry": {"coordinates":[-90.972419,42.949479],"type":"Point"}
}