{
  "type": "Feature",
  "properties": {
    "iso:country":"US",
    "sg:address":"801 Sauk Ave",
    "sg:city":"Baraboo",
    "sg:classifiers":[
        {
            "category":"Manufacturing",
            "subcategory":"Metals",
            "type":"Manufacturing & Wholesale Goods"
        }
    ],
    "sg:phone":"+1 608 356 3919",
    "sg:postcode":"53913",
    "sg:province":"WI",
    "sg:tags":[
        "can"
    ],
    "wof:name":"Seneca Foods Corp",
    "wof:placetype":"venue"
},
  "geometry": {"coordinates":[-89.754861,43.462125],"type":"Point"}
}