{
  "type": "Feature",
  "properties": {
    "addr:full":"2001 10th Ave South Milwaukee WI 53172",
    "addr:housenumber":"2001",
    "addr:postcode":"53172",
    "addr:street":"10Th Ave",
    "iso:country":"US",
    "sg:address":"2001 10th Ave",
    "sg:city":"South Milwaukee",
    "sg:classifiers":[
        {
            "category":"Health Services",
            "subcategory":"Doctor",
            "type":"Services"
        }
    ],
    "sg:phone":"+1 414 762 1112",
    "sg:postcode":"53172",
    "sg:province":"WI",
    "sg:tags":[
        "dentist"
    ],
    "wof:name":"Dental Odyssey",
    "wof:placetype":"venue"
},
  "geometry": {"coordinates":[-87.86071099999999,42.910685],"type":"Point"}
}