{
  "type": "Feature",
  "properties": {
    "addr:full":"205 S Highland Ave Thiensville WI 53092",
    "addr:housenumber":"205",
    "addr:postcode":"53092",
    "addr:street":"S Highland Ave",
    "iso:country":"US",
    "sg:address":"205 S Highland Ave",
    "sg:city":"Thiensville",
    "sg:classifiers":[
        {
            "category":"Building & Trades",
            "subcategory":"Construction",
            "type":"Services"
        }
    ],
    "sg:phone":"+1 262 242 4162",
    "sg:postcode":"53092",
    "sg:province":"WI",
    "sg:tags":[
        "ceiling"
    ],
    "wof:name":"Ceiling Clean",
    "wof:placetype":"venue"
},
  "geometry": {"coordinates":[-87.988437,43.225502],"type":"Point"}
}