{
  "type": "Feature",
  "properties": {
    "iso:country":"US",
    "sg:address":"15911 190th Ave",
    "sg:city":"Bloomer",
    "sg:classifiers":[
        {
            "category":"Personal",
            "subcategory":"Beauty Salon",
            "type":"Services"
        }
    ],
    "sg:phone":"+1 715 288 6455",
    "sg:postcode":"54724",
    "sg:province":"WI",
    "sg:tags":[
        "shop"
    ],
    "wof:name":"Donna Maes Beauty Salon",
    "wof:placetype":"venue"
},
  "geometry": {"coordinates":[-91.35773,45.12118],"type":"Point"}
}