{
  "type": "Feature",
  "properties": {
    "iso:country":"US",
    "sg:address":"1723 Murphy Ct",
    "sg:city":"Green Bay",
    "sg:classifiers":[
        {
            "category":"Professional",
            "subcategory":"Detective & Security Services",
            "type":"Services"
        }
    ],
    "sg:phone":"+1 920 494 9910",
    "sg:postcode":"54303",
    "sg:province":"WI",
    "sg:tags":[
        "car"
    ],
    "wof:name":"Langan Investigations Inc",
    "wof:placetype":"venue"
},
  "geometry": {"coordinates":[-88.062698,44.537364],"type":"Point"}
}