{
  "type": "Feature",
  "properties": {
    "iso:country":"US",
    "sg:address":"3464 State Hwy 106",
    "sg:city":"Fort Atkinson",
    "sg:classifiers":[
        {
            "category":"Farming",
            "subcategory":"Dairy Farm",
            "type":"Manufacturing & Wholesale Goods"
        }
    ],
    "sg:phone":"+1 920 563 6956",
    "sg:postcode":"53538",
    "sg:province":"WI",
    "sg:tags":[
        "corn"
    ],
    "wof:name":"Donald Foerster",
    "wof:placetype":"venue"
},
  "geometry": {"coordinates":[-88.702033,42.931314],"type":"Point"}
}