{
  "type": "Feature",
  "properties": {
    "addr:full":"14 S Madison St Waupun WI 53963",
    "addr:housenumber":"14",
    "addr:postcode":"53963",
    "addr:street":"S Madison St",
    "iso:country":"US",
    "sg:address":"14 S Madison St",
    "sg:city":"Waupun",
    "sg:classifiers":[
        {
            "category":"Insurance",
            "subcategory":"Insurance Agent",
            "type":"Services"
        }
    ],
    "sg:phone":"+1 920 324 3301",
    "sg:postcode":"53963",
    "sg:province":"WI",
    "sg:tags":[
        "life",
        "carrier"
    ],
    "wof:name":"State Farm Insurance",
    "wof:placetype":"venue"
},
  "geometry": {"coordinates":[-88.729868,43.633047],"type":"Point"}
}