{
  "type": "Feature",
  "properties": {
    "iso:country":"US",
    "sg:address":"2708 Omaha Dr",
    "sg:city":"Janesville",
    "sg:classifiers":[
        {
            "category":"Professional",
            "subcategory":"Business Services",
            "type":"Services"
        }
    ],
    "sg:phone":"+1 608 295 3727",
    "sg:postcode":"53546",
    "sg:province":"WI",
    "sg:tags":[
        "water",
        "treatment"
    ],
    "wof:name":"Integrity Water Solution",
    "wof:placetype":"venue"
},
  "geometry": {"coordinates":[-89.052479,42.638332],"type":"Point"}
}