{
  "type": "Feature",
  "properties": {
    "iso:country":"US",
    "sg:address":"4200 University Ave",
    "sg:city":"Madison",
    "sg:classifiers":[
        {
            "category":"Professional",
            "subcategory":"Accounting & Tax Preparation",
            "type":"Services"
        }
    ],
    "sg:phone":"+1 608 233 9769",
    "sg:postcode":"53705",
    "sg:province":"WI",
    "sg:tags":[
        "return",
        "filing"
    ],
    "sg:website":"www.taxproblemsolvers.com",
    "wof:name":"Consulting Services LTD",
    "wof:placetype":"venue"
},
  "geometry": {"coordinates":[-89.450733,43.0754],"type":"Point"}
}