{
  "type": "Feature",
  "properties": {
    "iso:country":"US",
    "sg:address":"13967 Gorman Ave",
    "sg:city":"Thorp",
    "sg:classifiers":[
        {
            "category":"Farming",
            "subcategory":"Farm",
            "type":"Manufacturing & Wholesale Goods"
        }
    ],
    "sg:phone":"+1 715 669 5001",
    "sg:postcode":"54771",
    "sg:province":"WI",
    "sg:tags":[
        "crop",
        "general"
    ],
    "wof:name":"Tom Lipinski",
    "wof:placetype":"venue"
},
  "geometry": {"coordinates":[-90.76034900000001,44.923669],"type":"Point"}
}