{
  "type": "Feature",
  "properties": {
    "iso:country":"US",
    "sg:address":"5401 N 76th St",
    "sg:city":"Milwaukee",
    "sg:classifiers":[
        {
            "category":"Professional",
            "subcategory":"Lawyer & Legal Services",
            "type":"Services"
        }
    ],
    "sg:phone":"+1 414 464 6555",
    "sg:postcode":"53218",
    "sg:province":"WI",
    "wof:name":"Muwonge and Associates",
    "wof:placetype":"venue"
},
  "geometry": {"coordinates":[-88.006028,43.115362],"type":"Point"}
}