{
  "type": "Feature",
  "properties": {
    "addr:full":"205 W 4th St Kaukauna WI 54130",
    "addr:housenumber":"205",
    "addr:postcode":"54130",
    "addr:street":"W 4Th St",
    "iso:country":"US",
    "sg:address":"205 W 4th St",
    "sg:city":"Kaukauna",
    "sg:classifiers":[
        {
            "category":"Banks & Credit Unions",
            "subcategory":"Bank",
            "type":"Services"
        }
    ],
    "sg:phone":"+1 920 766 8160",
    "sg:postcode":"54130",
    "sg:province":"WI",
    "sg:website":"www.fmbanks.com",
    "wof:name":"Citizens Bank",
    "wof:placetype":"venue"
},
  "geometry": {"coordinates":[-88.275959,44.278108],"type":"Point"}
}