{
  "type": "Feature",
  "properties": {
    "iso:country":"US",
    "sg:address":"419 Oak St",
    "sg:city":"Campbellsport",
    "sg:classifiers":[
        {
            "category":"Insurance",
            "subcategory":"Insurance Agent",
            "type":"Services"
        }
    ],
    "sg:phone":"+1 920 533 8398",
    "sg:postcode":"53010",
    "sg:province":"WI",
    "wof:name":"Quick Claims Processing Serv",
    "wof:placetype":"venue"
},
  "geometry": {"coordinates":[-88.295198,43.597962],"type":"Point"}
}