{
  "type": "Feature",
  "properties": {
    "iso:country":"US",
    "sg:address":"1036 Rutledge St",
    "sg:city":"Madison",
    "sg:classifiers":[
        {
            "category":"Professional",
            "subcategory":"Business Services",
            "type":"Services"
        }
    ],
    "sg:phone":"+1 608 663 4996",
    "sg:postcode":"53703",
    "sg:province":"WI",
    "sg:tags":[
        "translator",
        "interpreter"
    ],
    "wof:name":"Speakeasy",
    "wof:placetype":"venue"
},
  "geometry": {"coordinates":[-89.365348,43.078996],"type":"Point"}
}