{
  "type": "Feature",
  "properties": {
    "addr:full":"8125 Northern Rd Minocqua WI 54548",
    "addr:housenumber":"8125",
    "addr:postcode":"54548",
    "addr:street":"Northern Rd",
    "iso:country":"US",
    "sg:address":"8125 Northern Rd",
    "sg:city":"Minocqua",
    "sg:classifiers":[
        {
            "category":"Professional",
            "subcategory":"Management & Consulting",
            "type":"Services"
        }
    ],
    "sg:phone":"+1 715 358 2360",
    "sg:postcode":"54548",
    "sg:province":"WI",
    "wof:name":"Pichler Timber & Land MGT",
    "wof:placetype":"venue"
},
  "geometry": {"coordinates":[-89.713503,45.853737],"type":"Point"}
}