{
  "type": "Feature",
  "properties": {
    "addr:full":"649 Co Rd B B Waterloo WI 53594",
    "addr:housenumber":"649;b",
    "addr:postcode":"53594",
    "addr:street":"Co Rd",
    "iso:country":"US",
    "sg:address":"649 Co Rd B B",
    "sg:city":"Waterloo",
    "sg:classifiers":[
        {
            "category":"Farming",
            "subcategory":"Dairy Farm",
            "type":"Manufacturing & Wholesale Goods"
        }
    ],
    "sg:phone":"+1 920 478 3625",
    "sg:postcode":"53594",
    "sg:province":"WI",
    "wof:name":"Will Ann Farms",
    "wof:placetype":"venue"
},
  "geometry": {"coordinates":[-88.920772,43.21955],"type":"Point"}
}