{
  "type": "Feature",
  "properties": {
    "iso:country":"US",
    "sg:address":"4378 Collier Ave",
    "sg:city":"Neillsville",
    "sg:classifiers":[
        {
            "category":"Farming",
            "subcategory":"Dairy Farm",
            "type":"Manufacturing & Wholesale Goods"
        }
    ],
    "sg:phone":"+1 715 743 4774",
    "sg:postcode":"54456",
    "sg:province":"WI",
    "wof:name":"Whispering Pines",
    "wof:placetype":"venue"
},
  "geometry": {"coordinates":[-90.690284,44.574953],"type":"Point"}
}