{
  "type": "Feature",
  "properties": {
    "iso:country":"US",
    "sg:address":"2222 Milwaukee Rd",
    "sg:city":"Beloit",
    "sg:classifiers":[
        {
            "category":"Shopping",
            "type":"Retail Goods"
        }
    ],
    "sg:phone":"+1 608 365 7033",
    "sg:postcode":"53511",
    "sg:province":"WI",
    "sg:tags":[
        "monument"
    ],
    "wof:name":"Beloit Monument Co",
    "wof:placetype":"venue"
},
  "geometry": {"coordinates":[-89.00256899999999,42.516603],"type":"Point"}
}