{
  "type": "Feature",
  "properties": {
    "iso:country":"US",
    "sg:address":"735 Coronis Cir",
    "sg:city":"Green Bay",
    "sg:classifiers":[
        {
            "category":"Wholesale",
            "subcategory":"Construction Materials",
            "type":"Manufacturing & Wholesale Goods"
        }
    ],
    "sg:phone":"+1 920 983 1515",
    "sg:postcode":"54304",
    "sg:province":"WI",
    "sg:tags":[
        "equipment",
        "maker",
        "cabinet"
    ],
    "wof:name":"Nicholson Hardware Co",
    "wof:placetype":"venue"
},
  "geometry": {"coordinates":[-88.078586,44.459886],"type":"Point"}
}