{
  "type": "Feature",
  "properties": {
    "iso:country":"US",
    "sg:address":"190 Gardner Ave Ste 3",
    "sg:city":"Burlington",
    "sg:classifiers":[
        {
            "category":"Health Services",
            "subcategory":"Doctor",
            "type":"Services"
        },
        {
            "category":"Health Services",
            "subcategory":"Clinic",
            "type":"Services"
        }
    ],
    "sg:phone":"+1 262 763 7766",
    "sg:postcode":"53105",
    "sg:province":"WI",
    "sg:tags":[
        "counseling",
        "mental",
        "psychiatrist"
    ],
    "wof:name":"Behavioral Health Services",
    "wof:placetype":"venue"
},
  "geometry": {"coordinates":[-88.27950300000001,42.670502],"type":"Point"}
}