{
  "type": "Feature",
  "properties": {
    "iso:country":"US",
    "sg:address":"208 E Main St",
    "sg:city":"Waunakee",
    "sg:classifiers":[
        {
            "category":"Food & Beverages",
            "subcategory":"Groceries & Convenience Stores",
            "type":"Retail Goods"
        }
    ],
    "sg:phone":"+1 608 849 5008",
    "sg:postcode":"53597",
    "sg:province":"WI",
    "sg:website":"www.kwiktrip.com",
    "wof:name":"KWIK Trip",
    "wof:placetype":"venue"
},
  "geometry": {"coordinates":[-89.45192900000001,43.191825],"type":"Point"}
}