{
  "type": "Feature",
  "properties": {
    "addr:full":"9523 US Hwy 2 Poplar WI 54864",
    "addr:housenumber":"9523",
    "addr:postcode":"54864",
    "addr:street":"Us Hwy 2",
    "iso:country":"US",
    "sg:address":"9523 US Hwy 2",
    "sg:city":"Poplar",
    "sg:classifiers":[
        {
            "category":"Organizations",
            "subcategory":"Religious Organization",
            "type":"Services"
        }
    ],
    "sg:phone":"+1 715 364 2593",
    "sg:postcode":"54864",
    "sg:province":"WI",
    "sg:tags":[
        "church"
    ],
    "wof:name":"Peace Lutheran Church",
    "wof:placetype":"venue"
},
  "geometry": {"coordinates":[-91.806991,46.588054],"type":"Point"}
}