{
  "type": "Feature",
  "properties": {
    "iso:country":"US",
    "sg:address":"212 Hood St",
    "sg:city":"La Crosse",
    "sg:classifiers":[
        {
            "category":"Manufacturing",
            "subcategory":"Motor Vehicles & Parts",
            "type":"Manufacturing & Wholesale Goods"
        }
    ],
    "sg:phone":"+1 608 782 8766",
    "sg:postcode":"54601",
    "sg:province":"WI",
    "sg:tags":[
        "function",
        "b",
        "manifold",
        "cartridge",
        "mfg",
        "hydraulic"
    ],
    "wof:name":"Gap Manufacturing Inc",
    "wof:placetype":"venue"
},
  "geometry": {"coordinates":[-91.252866,43.798363],"type":"Point"}
}