{
  "type": "Feature",
  "properties": {
    "iso:country":"US",
    "sg:address":"610 Century Ave",
    "sg:city":"Antigo",
    "sg:classifiers":[
        {
            "category":"Food & Beverages",
            "subcategory":"Bakery",
            "type":"Retail Goods"
        }
    ],
    "sg:phone":"+1 715 627 1151",
    "sg:postcode":"54409",
    "sg:province":"WI",
    "wof:name":"Kc Bagels",
    "wof:placetype":"venue"
},
  "geometry": {"coordinates":[-89.150127,45.162237],"type":"Point"}
}