{
  "type": "Feature",
  "properties": {
    "addr:full":"401 Center St Manawa WI 54949",
    "addr:housenumber":"401",
    "addr:postcode":"54949",
    "addr:street":"Center St",
    "iso:country":"US",
    "sg:address":"401 Center St",
    "sg:city":"Manawa",
    "sg:classifiers":[
        {
            "category":"Organizations",
            "subcategory":"Labor Organization",
            "type":"Services"
        }
    ],
    "sg:phone":"+1 920 596 2723",
    "sg:postcode":"54949",
    "sg:province":"WI",
    "wof:name":"United Paperworkers Intl",
    "wof:placetype":"venue"
},
  "geometry": {"coordinates":[-88.916157,44.463246],"type":"Point"}
}