{
  "type": "Feature",
  "properties": {
    "iso:country":"US",
    "sg:address":"1875 Elmwood Ave",
    "sg:city":"Beloit",
    "sg:classifiers":[
        {
            "category":"Retail",
            "subcategory":"Car Wash",
            "type":"Services"
        }
    ],
    "sg:phone":"+1 608 362 3161",
    "sg:postcode":"53511",
    "sg:province":"IL",
    "sg:tags":[
        "carwash"
    ],
    "wof:name":"Beloit Super Wash",
    "wof:placetype":"venue"
},
  "geometry": {"coordinates":[-89.012291,42.541749],"type":"Point"}
}