{
  "type": "Feature",
  "properties": {
    "iso:country":"US",
    "sg:address":"550 E Main St",
    "sg:city":"Mondovi",
    "sg:classifiers":[
        {
            "category":"Restaurant",
            "type":"Food & Drink"
        }
    ],
    "sg:phone":"+1 715 926 5365",
    "sg:postcode":"54755",
    "sg:province":"WI",
    "sg:tags":[
        "eating"
    ],
    "wof:name":"Kathys Sunset Inn",
    "wof:placetype":"venue"
},
  "geometry": {"coordinates":[-91.663425,44.567938],"type":"Point"}
}