{
  "type": "Feature",
  "properties": {
    "iso:country":"US",
    "sg:address":"6710 State Hwy 54",
    "sg:city":"Wisconsin Rapids",
    "sg:classifiers":[
        {
            "category":"Recreation",
            "subcategory":"Arcade",
            "type":"Entertainment"
        }
    ],
    "sg:phone":"+1 715 424 5670",
    "sg:postcode":"54494",
    "sg:province":"WI",
    "sg:tags":[
        "amusement",
        "devices"
    ],
    "wof:name":"Midwest Amusements",
    "wof:placetype":"venue"
},
  "geometry": {"coordinates":[-89.737981,44.420423],"type":"Point"}
}