{
  "type": "Feature",
  "properties": {
    "iso:country":"US",
    "sg:address":"230 E Columbian Ave",
    "sg:city":"Neenah",
    "sg:classifiers":[
        {
            "category":"Professional",
            "subcategory":"Computer Services",
            "type":"Services"
        }
    ],
    "sg:phone":"+1 920 751 0842",
    "sg:postcode":"54956",
    "sg:province":"WI",
    "sg:tags":[
        "related"
    ],
    "wof:name":"Digital Lynx LLC",
    "wof:placetype":"venue"
},
  "geometry": {"coordinates":[-88.459206,44.183397],"type":"Point"}
}