{
  "type": "Feature",
  "properties": {
    "iso:country":"US",
    "sg:address":"610 Lombardi Ave",
    "sg:city":"Green Bay",
    "sg:classifiers":[
        {
            "category":"Wholesale",
            "subcategory":"Electrical",
            "type":"Manufacturing & Wholesale Goods"
        }
    ],
    "sg:phone":"+1 920 437 3284",
    "sg:postcode":"54304",
    "sg:province":"WI",
    "sg:tags":[
        "equipment",
        "electric",
        "supply"
    ],
    "wof:name":"Graybar Electric Co",
    "wof:placetype":"venue"
},
  "geometry": {"coordinates":[-88.03941399999999,44.495354],"type":"Point"}
}