{
  "type": "Feature",
  "properties": {
    "addr:full":"32605 Big Island Rd Danbury WI 54830",
    "addr:housenumber":"32605",
    "addr:postcode":"54830",
    "addr:street":"Big Island Rd",
    "iso:country":"US",
    "sg:address":"32605 Big Island Rd",
    "sg:city":"Danbury",
    "sg:classifiers":[
        {
            "category":"Building & Trades",
            "subcategory":"Construction",
            "type":"Services"
        }
    ],
    "sg:phone":"+1 715 244 4021",
    "sg:postcode":"54830",
    "sg:province":"WI",
    "sg:tags":[
        "hanging",
        "contractor"
    ],
    "wof:name":"ATD Painting",
    "wof:placetype":"venue"
},
  "geometry": {"coordinates":[-92.234004,46.092193],"type":"Point"}
}