{
  "type": "Feature",
  "properties": {
    "iso:country":"US",
    "sg:address":"208 Owen Rd",
    "sg:city":"Monona",
    "sg:classifiers":[
        {
            "category":"Sports & Exercise",
            "subcategory":"Bowling",
            "type":"Entertainment"
        }
    ],
    "sg:phone":"+1 608 222 7361",
    "sg:postcode":"53716",
    "sg:province":"WI",
    "sg:tags":[
        "drinking",
        "center"
    ],
    "wof:name":"Village Lanes",
    "wof:placetype":"venue"
},
  "geometry": {"coordinates":[-89.328714,43.056829],"type":"Point"}
}