{
  "type": "Feature",
  "properties": {
    "iso:country":"US",
    "sg:address":"8132 State Hwy 57",
    "sg:city":"Baileys Harbor",
    "sg:classifiers":[
        {
            "category":"Recreation",
            "subcategory":"Marina",
            "type":"Entertainment"
        }
    ],
    "sg:phone":"+1 920 839 9778",
    "sg:postcode":"54202",
    "sg:province":"WI",
    "sg:tags":[
        "operation"
    ],
    "wof:name":"Bailey's Harbor Town Marina",
    "wof:placetype":"venue"
},
  "geometry": {"coordinates":[-87.123835,45.066164],"type":"Point"}
}