{
  "type": "Feature",
  "properties": {
    "iso:country":"US",
    "sg:address":"834 W Wisconsin St",
    "sg:city":"Sparta",
    "sg:classifiers":[
        {
            "category":"Utilities",
            "subcategory":"Mobile Phone",
            "type":"Services"
        }
    ],
    "sg:phone":"+1 608 269 0988",
    "sg:postcode":"54656",
    "sg:province":"WI",
    "sg:tags":[
        "telephone",
        "cellular"
    ],
    "wof:name":"Us Cellular Inc",
    "wof:placetype":"venue"
},
  "geometry": {"coordinates":[-90.821068,43.939214],"type":"Point"}
}