{
  "type": "Feature",
  "properties": {
    "addr:full":"7100 W Center St Milwaukee WI 53210",
    "addr:housenumber":"7100",
    "addr:postcode":"53210",
    "addr:street":"W Center St",
    "iso:country":"US",
    "sg:address":"7100 W Center St",
    "sg:city":"Milwaukee",
    "sg:classifiers":[
        {
            "category":"Wholesale",
            "subcategory":"Computers",
            "type":"Manufacturing & Wholesale Goods"
        },
        {
            "category":"Professional",
            "subcategory":"Computer Services",
            "type":"Services"
        }
    ],
    "sg:phone":"+1 414 257 9400",
    "sg:postcode":"53210",
    "sg:province":"WI",
    "sg:tags":[
        "publisher",
        "cd-rom",
        "equipment",
        "software",
        "developer"
    ],
    "wof:name":"Cayen Systems",
    "wof:placetype":"venue"
},
  "geometry": {"coordinates":[-88.000702,43.06805],"type":"Point"}
}