{
  "type": "Feature",
  "properties": {
    "addr:full":"7860 Leary Rd Minocqua WI 54548",
    "addr:housenumber":"7860",
    "addr:postcode":"54548",
    "addr:street":"Leary Rd",
    "iso:country":"US",
    "sg:address":"7860 Leary Rd",
    "sg:city":"Minocqua",
    "sg:classifiers":[
        {
            "category":"Freight",
            "type":"Transportation"
        }
    ],
    "sg:phone":"+1 715 356 3722",
    "sg:postcode":"54548",
    "sg:province":"WI",
    "sg:tags":[
        "water"
    ],
    "wof:name":"Bargeco Ltd",
    "wof:placetype":"venue"
},
  "geometry": {"coordinates":[-89.692714,45.845057],"type":"Point"}
}