{
  "type": "Feature",
  "properties": {
    "addr:full":"4101 W Freistadt Rd Mequon WI 53092",
    "addr:housenumber":"4101",
    "addr:postcode":"53092",
    "addr:street":"W Freistadt Rd",
    "iso:country":"US",
    "sg:address":"4101 W Freistadt Rd",
    "sg:city":"Mequon",
    "sg:classifiers":[
        {
            "category":"Wholesale",
            "subcategory":"Non-durable Goods",
            "type":"Manufacturing & Wholesale Goods"
        }
    ],
    "sg:phone":"+1 262 242 5751",
    "sg:postcode":"53092",
    "sg:province":"WI",
    "sg:tags":[
        "advertising"
    ],
    "wof:name":"Turner Sales Promotion",
    "wof:placetype":"venue"
},
  "geometry": {"coordinates":[-87.95845,43.238336],"type":"Point"}
}