{
  "type": "Feature",
  "properties": {
    "iso:country":"US",
    "sg:address":"1516 Church St",
    "sg:city":"Stevens Point",
    "sg:classifiers":[
        {
            "category":"Wholesale",
            "subcategory":"Electrical",
            "type":"Manufacturing & Wholesale Goods"
        }
    ],
    "sg:phone":"+1 715 344 2140",
    "sg:postcode":"54481",
    "sg:province":"WI",
    "sg:tags":[
        "telecommunication"
    ],
    "wof:name":"Portage County Human Svc",
    "wof:placetype":"venue"
},
  "geometry": {"coordinates":[-89.580196,44.520858],"type":"Point"}
}