{
  "type": "Feature",
  "properties": {
    "iso:country":"US",
    "sg:address":"4535 117th St",
    "sg:city":"Chippewa Falls",
    "sg:classifiers":[
        {
            "category":"Retail",
            "subcategory":"Repair Shop",
            "type":"Services"
        }
    ],
    "sg:phone":"+1 715 836 9515",
    "sg:postcode":"54729",
    "sg:province":"WI",
    "sg:tags":[
        "plumbing",
        "drain",
        "cleaning",
        "sewer"
    ],
    "wof:name":"Valley Septic & Sewer Service",
    "wof:placetype":"venue"
},
  "geometry": {"coordinates":[-91.433004,44.9085],"type":"Point"}
}