{
  "type": "Feature",
  "properties": {
    "iso:country":"US",
    "sg:address":"421 E Silver Spring Dr",
    "sg:city":"Milwaukee",
    "sg:classifiers":[
        {
            "category":"Manufacturing",
            "subcategory":"Jewelry",
            "type":"Manufacturing & Wholesale Goods"
        }
    ],
    "sg:phone":"+1 414 962 9273",
    "sg:postcode":"53217",
    "sg:province":"WI",
    "wof:name":"Pettay & Assoc",
    "wof:placetype":"venue"
},
  "geometry": {"coordinates":[-87.90444599999999,43.118414],"type":"Point"}
}