{
  "type": "Feature",
  "properties": {
    "iso:country":"US",
    "sg:address":"1201 Oak St",
    "sg:city":"West Bend",
    "sg:classifiers":[
        {
            "category":"Health Services",
            "subcategory":"Doctor",
            "type":"Services"
        }
    ],
    "sg:phone":"+1 262 334 7172",
    "sg:postcode":"53095",
    "sg:province":"WI",
    "wof:name":"Oral & Maxillofacial Surgery",
    "wof:placetype":"venue"
},
  "geometry": {"coordinates":[-88.191715,43.416119],"type":"Point"}
}