{
  "type": "Feature",
  "properties": {
    "addr:full":"714 N Old World Third St Milwaukee WI 53203",
    "addr:housenumber":"714",
    "addr:postcode":"53203",
    "addr:street":"N Old World Third St",
    "iso:country":"US",
    "sg:address":"714 N Old World Third St",
    "sg:city":"Milwaukee",
    "sg:classifiers":[
        {
            "category":"Personal",
            "subcategory":"Beauty Salon",
            "type":"Services"
        }
    ],
    "sg:phone":"+1 414 298 2076",
    "sg:postcode":"53203",
    "sg:province":"WI",
    "sg:tags":[
        "shop"
    ],
    "wof:name":"Groom LLC",
    "wof:placetype":"venue"
},
  "geometry": {"coordinates":[-87.91444799999999,43.039954],"type":"Point"}
}