{
  "type": "Feature",
  "properties": {
    "iso:country":"US",
    "sg:address":"1305 Gohres St",
    "sg:city":"La Crosse",
    "sg:classifiers":[
        {
            "category":"Organizations",
            "subcategory":"Community Association",
            "type":"Services"
        }
    ],
    "sg:phone":"+1 608 782 9677",
    "sg:postcode":"54603",
    "sg:province":"WI",
    "sg:tags":[
        "club"
    ],
    "wof:name":"Schuh Homes Community Ctr",
    "wof:placetype":"venue"
},
  "geometry": {"coordinates":[-91.236969,43.849301],"type":"Point"}
}