{
  "type": "Feature",
  "properties": {
    "iso:country":"US",
    "sg:address":"3818 Butternut Rd",
    "sg:city":"Stratford",
    "sg:classifiers":[
        {
            "category":"Farming",
            "subcategory":"Dairy Farm",
            "type":"Manufacturing & Wholesale Goods"
        }
    ],
    "sg:phone":"+1 715 687 4283",
    "sg:postcode":"54484",
    "sg:province":"WI",
    "wof:name":"Larry H Custer",
    "wof:placetype":"venue"
},
  "geometry": {"coordinates":[-90.099332,44.872635],"type":"Point"}
}