{
  "type": "Feature",
  "properties": {
    "iso:country":"US",
    "sg:address":"8309 State Hwy 144",
    "sg:city":"Kewaskum",
    "sg:classifiers":[
        {
            "category":"Building & Trades",
            "subcategory":"Construction",
            "type":"Services"
        }
    ],
    "sg:phone":"+1 262 334 3348",
    "sg:postcode":"53040",
    "sg:province":"WI",
    "sg:tags":[
        "excavating",
        "contractor"
    ],
    "wof:name":"Ray Wollner Excavating Inc",
    "wof:placetype":"venue"
},
  "geometry": {"coordinates":[-88.140714,43.490123],"type":"Point"}
}