{
  "type": "Feature",
  "properties": {
    "iso:country":"US",
    "sg:address":"12245 E Lake Shore Rd",
    "sg:city":"Clinton",
    "sg:classifiers":[
        {
            "category":"Real Estate",
            "subcategory":"Real Estate Operator",
            "type":"Services"
        }
    ],
    "sg:phone":"+1 608 676 5340",
    "sg:postcode":"53525",
    "sg:province":"WI",
    "sg:tags":[
        "property",
        "lessor"
    ],
    "wof:name":"Glen Kitzman",
    "wof:placetype":"venue"
},
  "geometry": {"coordinates":[-88.817943,42.547636],"type":"Point"}
}