{
  "type": "Feature",
  "properties": {
    "addr:full":"1165 Fairway Trl Nekoosa WI 54457",
    "addr:housenumber":"1165",
    "addr:postcode":"54457",
    "addr:street":"Fairway Trl",
    "iso:country":"US",
    "sg:address":"1165 Fairway Trl",
    "sg:city":"Nekoosa",
    "sg:classifiers":[
        {
            "category":"Professional",
            "subcategory":"Management & Consulting",
            "type":"Services"
        }
    ],
    "sg:phone":"+1 715 325 3976",
    "sg:postcode":"54457",
    "sg:province":"WI",
    "wof:name":"Dedicated Management Services",
    "wof:placetype":"venue"
},
  "geometry": {"coordinates":[-89.816245,44.196848],"type":"Point"}
}