{
  "type": "Feature",
  "properties": {
    "iso:country":"US",
    "sg:address":"9331 Spring Rd",
    "sg:city":"Fish Creek",
    "sg:classifiers":[
        {
            "category":"Shopping",
            "subcategory":"Jewelry",
            "type":"Retail Goods"
        }
    ],
    "sg:phone":"+1 920 868 3383",
    "sg:postcode":"54212",
    "sg:province":"WI",
    "sg:tags":[
        "jeweler"
    ],
    "wof:name":"Silver Coyote",
    "wof:placetype":"venue"
},
  "geometry": {"coordinates":[-87.230076,45.123696],"type":"Point"}
}