{
  "type": "Feature",
  "properties": {
    "iso:country":"US",
    "sg:address":"2402 Harriet St",
    "sg:city":"Racine",
    "sg:classifiers":[
        {
            "category":"Social Services",
            "subcategory":"Child Care",
            "type":"Services"
        }
    ],
    "sg:phone":"+1 262 634 2577",
    "sg:postcode":"53404",
    "sg:province":"WI",
    "wof:name":"Crystal House Of Love",
    "wof:placetype":"venue"
},
  "geometry": {"coordinates":[-87.810674,42.735216],"type":"Point"}
}