{
  "type": "Feature",
  "properties": {
    "addr:full":"13053 Ballpark Rd Tilleda WI 54416",
    "addr:housenumber":"13053",
    "addr:postcode":"54416",
    "addr:street":"Ballpark Rd",
    "iso:country":"US",
    "sg:address":"13053 Ballpark Rd",
    "sg:city":"Tilleda",
    "sg:classifiers":[
        {
            "category":"Home & Garden",
            "subcategory":"Garden Supply",
            "type":"Retail Goods"
        }
    ],
    "sg:phone":"+1 715 787 3889",
    "sg:postcode":"54416",
    "sg:province":"WI",
    "sg:tags":[
        "nurseryman"
    ],
    "wof:name":"Pony Creek Nursery",
    "wof:placetype":"venue"
},
  "geometry": {"coordinates":[-88.896489,44.81146],"type":"Point"}
}