{
  "type": "Feature",
  "properties": {
    "iso:country":"US",
    "sg:address":"7646 Laverne Rd",
    "sg:city":"Siren",
    "sg:classifiers":[
        {
            "category":"Freight",
            "type":"Transportation"
        }
    ],
    "sg:phone":"+1 715 349 7618",
    "sg:postcode":"54872",
    "sg:province":"WI",
    "sg:tags":[
        "operator",
        "trucking"
    ],
    "wof:name":"Big Ben Trucking",
    "wof:placetype":"venue"
},
  "geometry": {"coordinates":[-92.372005,45.810113],"type":"Point"}
}