{
  "type": "Feature",
  "properties": {
    "addr:full":"7816 Co Rd H Sturgeon Bay WI 54235",
    "addr:housenumber":"7816",
    "addr:postcode":"54235",
    "addr:street":"Co Rd H",
    "iso:country":"US",
    "sg:address":"7816 Co Rd H",
    "sg:city":"Sturgeon Bay",
    "sg:classifiers":[
        {
            "category":"Building & Trades",
            "subcategory":"Construction",
            "type":"Services"
        }
    ],
    "sg:phone":"+1 920 856 6594",
    "sg:postcode":"54235",
    "sg:province":"WI",
    "sg:tags":[
        "floor",
        "covering"
    ],
    "wof:name":"Classic Dreams",
    "wof:placetype":"venue"
},
  "geometry": {"coordinates":[-87.49316899999999,44.747864],"type":"Point"}
}