{
  "type": "Feature",
  "properties": {
    "iso:country":"US",
    "sg:address":"2731 S 11th St",
    "sg:city":"Sheboygan",
    "sg:classifiers":[
        {
            "category":"Building & Trades",
            "subcategory":"Cleaning & Sanitation",
            "type":"Services"
        }
    ],
    "sg:phone":"+1 920 208 6840",
    "sg:postcode":"53081",
    "sg:province":"WI",
    "sg:tags":[
        "ventilating",
        "system"
    ],
    "wof:name":"Air 1 Cleaning Svc LLC",
    "wof:placetype":"venue"
},
  "geometry": {"coordinates":[-87.71772,43.724602],"type":"Point"}
}