{
  "type": "Feature",
  "properties": {
    "iso:country":"US",
    "sg:address":"411 Grove St",
    "sg:city":"Janesville",
    "sg:phone":"+1 608 752 3715",
    "sg:postcode":"53545",
    "sg:province":"WI",
    "sg:tags":[
        "farm",
        "soybean"
    ],
    "wof:name":"Kanes Farm",
    "wof:placetype":"venue"
},
  "geometry": {"coordinates":[-89.008281,42.680002],"type":"Point"}
}