{
  "type": "Feature",
  "properties": {
    "iso:country":"US",
    "sg:address":"724 East Rd",
    "sg:city":"Plainfield",
    "sg:classifiers":[
        {
            "category":"Manufacturing",
            "subcategory":"Metals",
            "type":"Manufacturing & Wholesale Goods"
        }
    ],
    "sg:phone":"+1 715 335 6994",
    "sg:postcode":"54966",
    "sg:province":"WI",
    "sg:tags":[
        "fabrication",
        "structural"
    ],
    "wof:name":"Strut Plus",
    "wof:placetype":"venue"
},
  "geometry": {"coordinates":[-89.485714,44.210199],"type":"Point"}
}