{
  "type": "Feature",
  "properties": {
    "iso:country":"US",
    "sg:address":"5956 Town Hall Dr",
    "sg:city":"Pulaski",
    "sg:classifiers":[
        {
            "category":"Real Estate",
            "subcategory":"Real Estate Operator",
            "type":"Services"
        }
    ],
    "sg:phone":"+1 920 822 5684",
    "sg:postcode":"54162",
    "sg:province":"WI",
    "sg:tags":[
        "property",
        "lessor"
    ],
    "wof:name":"Donald Wagner",
    "wof:placetype":"venue"
},
  "geometry": {"coordinates":[-88.214439,44.621786],"type":"Point"}
}