{
  "type": "Feature",
  "properties": {
    "iso:country":"US",
    "sg:address":"3330 Meadow Ln",
    "sg:city":"Rhinelander",
    "sg:classifiers":[
        {
            "category":"Retail",
            "subcategory":"Repair Shop",
            "type":"Services"
        }
    ],
    "sg:phone":"+1 715 362 6002",
    "sg:postcode":"54501",
    "sg:province":"WI",
    "sg:tags":[
        "contractor"
    ],
    "wof:name":"Huffman's Mobile Heavy Equip",
    "wof:placetype":"venue"
},
  "geometry": {"coordinates":[-89.28288,45.648696],"type":"Point"}
}