{
  "type": "Feature",
  "properties": {
    "addr:full":"760 Meadowbrook Ct Green Bay WI 54313",
    "addr:housenumber":"760",
    "addr:postcode":"54313",
    "addr:street":"Meadowbrook Ct",
    "iso:country":"US",
    "sg:address":"760 Meadowbrook Ct",
    "sg:city":"Green Bay",
    "sg:classifiers":[
        {
            "category":"Professional",
            "subcategory":"Management & Consulting",
            "type":"Services"
        }
    ],
    "sg:phone":"+1 920 434 9496",
    "sg:postcode":"54313",
    "sg:province":"WI",
    "sg:tags":[
        "enforcement",
        "training",
        "law"
    ],
    "wof:name":"Midwest Turnaround Trainers",
    "wof:placetype":"venue"
},
  "geometry": {"coordinates":[-88.090278,44.562147],"type":"Point"}
}