{
  "type": "Feature",
  "properties": {
    "addr:full":"3868 Savage Rd Brandon WI 53919",
    "addr:housenumber":"3868",
    "addr:postcode":"53919",
    "addr:street":"Savage Rd",
    "iso:country":"US",
    "sg:address":"3868 Savage Rd",
    "sg:city":"Brandon",
    "sg:classifiers":[
        {
            "category":"Shopping",
            "subcategory":"Bicycles & Sporting Goods",
            "type":"Retail Goods"
        }
    ],
    "sg:phone":"+1 920 324 9070",
    "sg:postcode":"53919",
    "sg:province":"WI",
    "wof:name":"Fish-On Bait Tackle LLC",
    "wof:placetype":"venue"
},
  "geometry": {"coordinates":[-88.736535,43.685879],"type":"Point"}
}