{
  "type": "Feature",
  "properties": {
    "addr:full":"900 S 5th St Suite 302 Milwaukee WI 53204",
    "addr:housenumber":"900",
    "addr:postcode":"53204",
    "addr:street":"S 5Th St Suite 302",
    "iso:country":"US",
    "sg:address":"900 S 5th St Suite 302",
    "sg:city":"Milwaukee",
    "sg:phone":"+1 414 647 2222",
    "sg:postcode":"53204",
    "sg:province":"WI",
    "sg:website":"http://www.freshstartmke.com",
    "wof:name":"Harness Law Offices, LLC",
    "wof:placetype":"venue"
},
  "geometry": {"coordinates":[-87.91687,43.02216],"type":"Point"}
}