{
  "type": "Feature",
  "properties": {
    "addr:full":"2785 Cross Rd Abrams WI 54101",
    "addr:housenumber":"2785",
    "addr:postcode":"54101",
    "addr:street":"Cross Rd",
    "iso:country":"US",
    "sg:address":"2785 Cross Rd",
    "sg:city":"Abrams",
    "sg:classifiers":[
        {
            "category":"Farming",
            "subcategory":"Farm",
            "type":"Manufacturing & Wholesale Goods"
        }
    ],
    "sg:phone":"+1 920 826 5896",
    "sg:postcode":"54101",
    "sg:province":"WI",
    "sg:tags":[
        "crop",
        "general"
    ],
    "wof:name":"Steve Kusch",
    "wof:placetype":"venue"
},
  "geometry": {"coordinates":[-88.070695,44.774211],"type":"Point"}
}