{
  "type": "Feature",
  "properties": {
    "addr:full":"340 S Main St Fort Atkinson WI 53538",
    "addr:housenumber":"340",
    "addr:postcode":"53538",
    "addr:street":"S Main St",
    "iso:country":"US",
    "sg:address":"340 S Main St",
    "sg:city":"Fort Atkinson",
    "sg:classifiers":[
        {
            "category":"Professional",
            "subcategory":"Employment Agencies",
            "type":"Services"
        }
    ],
    "sg:phone":"+1 920 563 3301",
    "sg:postcode":"53538",
    "sg:province":"WI",
    "sg:tags":[
        "help",
        "contractor"
    ],
    "sg:website":"www.terrastaffing.com",
    "wof:name":"Terra Staffing Svc",
    "wof:placetype":"venue"
},
  "geometry": {"coordinates":[-88.837045,42.924743],"type":"Point"}
}