{
  "type": "Feature",
  "properties": {
    "iso:country":"US",
    "sg:address":"103 S Lincoln Dr",
    "sg:city":"Sheboygan",
    "sg:classifiers":[
        {
            "category":"Retail",
            "subcategory":"Repair Shop",
            "type":"Services"
        }
    ],
    "sg:phone":"+1 920 565 2709",
    "sg:postcode":"53083",
    "sg:province":"WI",
    "wof:name":"Trishs Corner Upholstery",
    "wof:placetype":"venue"
},
  "geometry": {"coordinates":[-87.82586499999999,43.832493],"type":"Point"}
}