{
  "type": "Feature",
  "properties": {
    "iso:country":"US",
    "sg:address":"8001 N Port Washington Rd",
    "sg:city":"Milwaukee",
    "sg:classifiers":[
        {
            "category":"Restaurant",
            "type":"Food & Drink"
        }
    ],
    "sg:phone":"+1 414 352 9303",
    "sg:postcode":"53217",
    "sg:province":"WI",
    "sg:tags":[
        "style",
        "family"
    ],
    "wof:name":"Calderone Club",
    "wof:placetype":"venue"
},
  "geometry": {"coordinates":[-87.911728,43.162209],"type":"Point"}
}