{
  "type": "Feature",
  "properties": {
    "iso:country":"US",
    "sg:address":"11748 W Carroll Rd",
    "sg:city":"Beloit",
    "sg:classifiers":[
        {
            "category":"Shopping",
            "subcategory":"Gifts & Souvenirs",
            "type":"Retail Goods"
        }
    ],
    "sg:phone":"+1 608 879 3044",
    "sg:postcode":"53511",
    "sg:province":"IL",
    "sg:tags":[
        "shop"
    ],
    "wof:name":"C J's Gift Guide",
    "wof:placetype":"venue"
},
  "geometry": {"coordinates":[-89.236077,42.527281],"type":"Point"}
}