{
  "type": "Feature",
  "properties": {
    "iso:country":"US",
    "sg:address":"919 Auto Plaza Dr",
    "sg:city":"Green Bay",
    "sg:classifiers":[
        {
            "category":"Autos & Motor Vehicles",
            "subcategory":"Automobile Sales",
            "type":"Retail Goods"
        }
    ],
    "sg:phone":"+1 920 468 6800",
    "sg:postcode":"54302",
    "sg:province":"WI",
    "sg:tags":[
        "car",
        "dealer"
    ],
    "sg:website":"www.gandrud.com",
    "wof:name":"Gandrud Chevrolet",
    "wof:placetype":"venue"
},
  "geometry": {"coordinates":[-87.96776800000001,44.481564],"type":"Point"}
}