{
  "type": "Feature",
  "properties": {
    "addr:full":"1344 W Wisconsin Ave Appleton WI 54914",
    "addr:housenumber":"1344",
    "addr:postcode":"54914",
    "addr:street":"W Wisconsin Ave",
    "iso:country":"US",
    "sg:address":"1344 W Wisconsin Ave",
    "sg:city":"Appleton",
    "sg:classifiers":[
        {
            "category":"Shopping",
            "type":"Retail Goods"
        }
    ],
    "sg:phone":"+1 920 734 2746",
    "sg:postcode":"54914",
    "sg:province":"WI",
    "sg:tags":[
        "plumbing",
        "supply"
    ],
    "wof:name":"Baron Plumbing Supplies Inc",
    "wof:placetype":"venue"
},
  "geometry": {"coordinates":[-88.428944,44.273174],"type":"Point"}
}