{
  "type": "Feature",
  "properties": {
    "iso:country":"US",
    "sg:address":"1321 Creston Park Dr",
    "sg:city":"Janesville",
    "sg:classifiers":[
        {
            "category":"Health Services",
            "subcategory":"Doctor",
            "type":"Services"
        }
    ],
    "sg:phone":"+1 608 757 1217",
    "sg:postcode":"53545",
    "sg:province":"WI",
    "sg:tags":[
        "medical"
    ],
    "wof:name":"Anshu Luthar MD",
    "wof:placetype":"venue"
},
  "geometry": {"coordinates":[-89.005752,42.701723],"type":"Point"}
}