{
  "type": "Feature",
  "properties": {
    "iso:country":"US",
    "sg:address":"111 Paoli St",
    "sg:city":"Verona",
    "sg:classifiers":[
        {
            "category":"Manufacturing",
            "subcategory":"Building Materials",
            "type":"Manufacturing & Wholesale Goods"
        }
    ],
    "sg:phone":"+1 608 845 9114",
    "sg:postcode":"53593",
    "sg:province":"WI",
    "sg:tags":[
        "mfg",
        "wood",
        "kitchen",
        "cabinet"
    ],
    "wof:name":"Jon Sutcliffe LLC",
    "wof:placetype":"venue"
},
  "geometry": {"coordinates":[-89.53850199999999,42.982269],"type":"Point"}
}