{
  "type": "Feature",
  "properties": {
    "addr:full":"1919 S Oneida St Appleton WI 54915",
    "addr:housenumber":"1919",
    "addr:postcode":"54915",
    "addr:street":"S Oneida St",
    "iso:country":"US",
    "sg:address":"1919 S Oneida St",
    "sg:city":"Appleton",
    "sg:classifiers":[
        {
            "category":"Restaurant",
            "type":"Food & Drink"
        }
    ],
    "sg:phone":"+1 920 730 8929",
    "sg:postcode":"54915",
    "sg:province":"WI",
    "wof:name":"Big Shang Hi Buffet",
    "wof:placetype":"venue"
},
  "geometry": {"coordinates":[-88.40415299999999,44.244285],"type":"Point"}
}