{
  "type": "Feature",
  "properties": {
    "iso:country":"US",
    "sg:address":"2103 Badger Rd",
    "sg:city":"Kaukauna",
    "sg:classifiers":[
        {
            "category":"Wholesale",
            "subcategory":"Machinery & Supplies",
            "type":"Manufacturing & Wholesale Goods"
        }
    ],
    "sg:phone":"+1 920 766 7338",
    "sg:postcode":"54130",
    "sg:province":"WI",
    "sg:tags":[
        "repairing"
    ],
    "wof:name":"Precision Scraping & Alignment",
    "wof:placetype":"venue"
},
  "geometry": {"coordinates":[-88.257926,44.299521],"type":"Point"}
}