{
  "type": "Feature",
  "properties": {
    "iso:country":"US",
    "sg:address":"3839 N Morris Blvd",
    "sg:city":"Milwaukee",
    "sg:classifiers":[
        {
            "category":"Professional",
            "subcategory":"Management & Consulting",
            "type":"Services"
        }
    ],
    "sg:phone":"+1 414 906 1600",
    "sg:postcode":"53211",
    "sg:province":"WI",
    "sg:tags":[
        "business"
    ],
    "wof:name":"Center For Self Suffiency",
    "wof:placetype":"venue"
},
  "geometry": {"coordinates":[-87.892337,43.087259],"type":"Point"}
}