{
  "type": "Feature",
  "properties": {
    "addr:full":"1921 E Blue Mounds Rd Mt Horeb WI 53572",
    "addr:housenumber":"1921",
    "addr:postcode":"53572",
    "addr:street":"E Blue Mounds Rd",
    "iso:country":"US",
    "sg:address":"1921 E Blue Mounds Rd",
    "sg:city":"Mt Horeb",
    "sg:classifiers":[
        {
            "category":"Building & Trades",
            "subcategory":"Plumbing",
            "type":"Services"
        }
    ],
    "sg:phone":"+1 608 437 4333",
    "sg:postcode":"53572",
    "sg:province":"WI",
    "sg:tags":[
        "plumbing",
        "contractor"
    ],
    "wof:name":"Sutter Plumbing Corp",
    "wof:placetype":"venue"
},
  "geometry": {"coordinates":[-89.73534100000001,42.956653],"type":"Point"}
}