{
  "type": "Feature",
  "properties": {
    "iso:country":"US",
    "sg:address":"9523 South Ave",
    "sg:city":"Reedsburg",
    "sg:classifiers":[
        {
            "category":"Insurance",
            "subcategory":"Insurance Agent",
            "type":"Services"
        }
    ],
    "sg:phone":"+1 608 254 5900",
    "sg:postcode":"53959",
    "sg:province":"WI",
    "wof:name":"Freedom Insurance",
    "wof:placetype":"venue"
},
  "geometry": {"coordinates":[-89.845566,43.576079],"type":"Point"}
}