{
  "type": "Feature",
  "properties": {
    "iso:country":"US",
    "sg:address":"500 Elm Grove Rd",
    "sg:city":"Elm Grove",
    "sg:classifiers":[
        {
            "category":"Insurance",
            "subcategory":"Insurance Agent",
            "type":"Services"
        }
    ],
    "sg:phone":"+1 262 784 0863",
    "sg:postcode":"53122",
    "sg:province":"WI",
    "wof:name":"Professional Insurance Svc",
    "wof:placetype":"venue"
},
  "geometry": {"coordinates":[-88.077241,43.036184],"type":"Point"}
}