{
  "type": "Feature",
  "properties": {
    "iso:country":"US",
    "sg:address":"4129 N Port Washington Rd",
    "sg:city":"Milwaukee",
    "sg:classifiers":[
        {
            "category":"Banks & Credit Unions",
            "subcategory":"Investment Brokerage",
            "type":"Services"
        }
    ],
    "sg:phone":"+1 414 964 5000",
    "sg:postcode":"53212",
    "sg:province":"WI",
    "sg:tags":[
        "tape",
        "video",
        "sale",
        "dvds-rental"
    ],
    "sg:website":"http://www.koss.com",
    "wof:name":"Koss Classic Ltd",
    "wof:placetype":"venue"
},
  "geometry": {"coordinates":[-87.917137,43.091873],"type":"Point"}
}