{
  "type": "Feature",
  "properties": {
    "iso:country":"US",
    "sg:address":"1826 Crestwood Dr",
    "sg:city":"Caledonia",
    "sg:classifiers":[
        {
            "category":"Professional",
            "type":"Services"
        }
    ],
    "sg:phone":"+1 262 835 9936",
    "sg:postcode":"53108",
    "sg:province":"WI",
    "wof:name":"Helicopter Flight Service LLC",
    "wof:placetype":"venue"
},
  "geometry": {"coordinates":[-87.960993,42.814619],"type":"Point"}
}