{
  "type": "Feature",
  "properties": {
    "iso:country":"US",
    "sg:address":"9631 State Hwy 13 S",
    "sg:city":"Wisconsin Rapids",
    "sg:classifiers":[
        {
            "category":"Retail",
            "subcategory":"Car Wash",
            "type":"Services"
        }
    ],
    "sg:phone":"+1 715 325 3410",
    "sg:postcode":"54494",
    "sg:province":"WI",
    "sg:tags":[
        "automobile",
        "detail",
        "clean"
    ],
    "wof:name":"J & M Detailing",
    "wof:placetype":"venue"
},
  "geometry": {"coordinates":[-89.810008,44.310675],"type":"Point"}
}