{
  "type": "Feature",
  "properties": {
    "iso:country":"US",
    "sg:address":"180 S Falls St",
    "sg:city":"River Falls",
    "sg:classifiers":[
        {
            "category":"Professional",
            "subcategory":"Printing & Photocopies",
            "type":"Services"
        }
    ],
    "sg:phone":"+1 715 426 1495",
    "sg:postcode":"54022",
    "sg:province":"WI",
    "sg:tags":[
        "duplicating",
        "copying"
    ],
    "wof:name":"Paper Concepts",
    "wof:placetype":"venue"
},
  "geometry": {"coordinates":[-92.633475,44.858082],"type":"Point"}
}