{
  "type": "Feature",
  "properties": {
    "iso:country":"US",
    "sg:address":"13417 State Hwy 32 64",
    "sg:city":"Mountain",
    "sg:classifiers":[
        {
            "category":"Farming",
            "subcategory":"Livestock Farm",
            "type":"Manufacturing & Wholesale Goods"
        }
    ],
    "sg:phone":"+1 715 276 1764",
    "sg:postcode":"54149",
    "sg:province":"WI",
    "sg:tags":[
        "ranch"
    ],
    "wof:name":"Desperado Ranch",
    "wof:placetype":"venue"
},
  "geometry": {"coordinates":[-88.451747,45.164087],"type":"Point"}
}