{
  "type": "Feature",
  "properties": {
    "iso:country":"US",
    "sg:address":"314 State Rd 128",
    "sg:city":"Wilson",
    "sg:classifiers":[
        {
            "category":"Farming",
            "subcategory":"Livestock Farm",
            "type":"Manufacturing & Wholesale Goods"
        }
    ],
    "sg:phone":"+1 715 772 3229",
    "sg:postcode":"54027",
    "sg:province":"WI",
    "sg:tags":[
        "equine"
    ],
    "wof:name":"Vern Lundquist",
    "wof:placetype":"venue"
},
  "geometry": {"coordinates":[-92.19717900000001,44.906134],"type":"Point"}
}