{
  "type": "Feature",
  "properties": {
    "iso:country":"US",
    "sg:address":"2285 Tannenbaum Trl",
    "sg:city":"Appleton",
    "sg:classifiers":[
        {
            "category":"Wholesale",
            "subcategory":"Jewelry",
            "type":"Manufacturing & Wholesale Goods"
        }
    ],
    "sg:phone":"+1 920 734 1631",
    "sg:postcode":"54914",
    "sg:province":"WI",
    "wof:name":"B & B Brokerage Inc",
    "wof:placetype":"venue"
},
  "geometry": {"coordinates":[-88.45241300000001,44.236674],"type":"Point"}
}