{
  "type": "Feature",
  "properties": {
    "addr:full":"11768 Rock School Rd Glen Haven WI 53810",
    "addr:housenumber":"11768",
    "addr:postcode":"53810",
    "addr:street":"Rock School Rd",
    "iso:country":"US",
    "sg:address":"11768 Rock School Rd",
    "sg:city":"Glen Haven",
    "sg:classifiers":[
        {
            "category":"Freight",
            "type":"Transportation"
        }
    ],
    "sg:phone":"+1 608 794 2571",
    "sg:postcode":"53810",
    "sg:province":"WI",
    "sg:tags":[
        "operator",
        "trucking"
    ],
    "wof:name":"Bausch Trucking LLC",
    "wof:placetype":"venue"
},
  "geometry": {"coordinates":[-91.002009,42.829291],"type":"Point"}
}