{
  "type": "Feature",
  "properties": {
    "iso:country":"US",
    "sg:address":"N52W5338 Portland Rd",
    "sg:city":"Cedarburg",
    "sg:classifiers":[
        {
            "category":"Building & Trades",
            "subcategory":"Construction",
            "type":"Services"
        }
    ],
    "sg:phone":"+1 262 377 7070",
    "sg:postcode":"53012",
    "sg:province":"WI",
    "sg:tags":[
        "contractor"
    ],
    "sg:website":"www.federaltool.com",
    "wof:name":"Federal Tool & Engineering Corp",
    "wof:placetype":"venue"
},
  "geometry": {"coordinates":[-87.978104,43.294102],"type":"Point"}
}