{
  "type": "Feature",
  "properties": {
    "iso:country":"US",
    "sg:address":"277 Weil Dr",
    "sg:city":"Slinger",
    "sg:classifiers":[
        {
            "category":"Manufacturing",
            "subcategory":"Metals",
            "type":"Manufacturing & Wholesale Goods"
        }
    ],
    "sg:phone":"+1 262 644 0977",
    "sg:postcode":"53086",
    "sg:province":"WI",
    "sg:tags":[
        "plating"
    ],
    "wof:name":"Niphos Coating Inc",
    "wof:placetype":"venue"
},
  "geometry": {"coordinates":[-88.294083,43.338876],"type":"Point"}
}