{
  "type": "Feature",
  "properties": {
    "iso:country":"US",
    "sg:address":"1107 N Fairbrook Dr",
    "sg:city":"Waunakee",
    "sg:classifiers":[
        {
            "category":"Wholesale",
            "subcategory":"Medical Equipment & Supplies",
            "type":"Manufacturing & Wholesale Goods"
        }
    ],
    "sg:phone":"+1 608 849 8650",
    "sg:postcode":"53597",
    "sg:province":"WI",
    "sg:tags":[
        "physician",
        "surgeon"
    ],
    "wof:name":"Shared Health-Amerinet",
    "wof:placetype":"venue"
},
  "geometry": {"coordinates":[-89.456807,43.20136],"type":"Point"}
}