{
  "type": "Feature",
  "properties": {
    "iso:country":"US",
    "sg:address":"23 N 2nd St",
    "sg:city":"Tomahawk",
    "sg:classifiers":[
        {
            "category":"Government",
            "subcategory":"Office",
            "type":"Public Place"
        }
    ],
    "sg:phone":"+1 715 453 4636",
    "sg:postcode":"54487",
    "sg:province":"WI",
    "sg:tags":[
        "village"
    ],
    "wof:name":"Tomahawk Building Inspector",
    "wof:placetype":"venue"
},
  "geometry": {"coordinates":[-89.732178,45.471825],"type":"Point"}
}