{
  "type": "Feature",
  "properties": {
    "addr:full":"108 E Main St Mt Horeb WI 53572",
    "addr:housenumber":"108",
    "addr:postcode":"53572",
    "addr:street":"E Main St",
    "iso:country":"US",
    "sg:address":"108 E Main St",
    "sg:city":"Mt Horeb",
    "sg:classifiers":[
        {
            "category":"Professional",
            "subcategory":"Lawyer & Legal Services",
            "type":"Services"
        }
    ],
    "sg:phone":"+1 608 437 5525",
    "sg:postcode":"53572",
    "sg:province":"WI",
    "sg:tags":[
        "attorney"
    ],
    "wof:name":"Wagner Law Office",
    "wof:placetype":"venue"
},
  "geometry": {"coordinates":[-89.739619,43.008732],"type":"Point"}
}