{
  "type": "Feature",
  "properties": {
    "addr:full":"3274 N 21st St Milwaukee WI 53206",
    "addr:housenumber":"3274",
    "addr:postcode":"53206",
    "addr:street":"N 21St St",
    "iso:country":"US",
    "sg:address":"3274 N 21st St",
    "sg:city":"Milwaukee",
    "sg:classifiers":[
        {
            "category":"Social Services",
            "subcategory":"Child Care",
            "type":"Services"
        }
    ],
    "sg:phone":"+1 414 442 5739",
    "sg:postcode":"53206",
    "sg:province":"WI",
    "wof:name":"Dorothy's Daycare",
    "wof:placetype":"venue"
},
  "geometry": {"coordinates":[-87.938486,43.076912],"type":"Point"}
}