{
  "type": "Feature",
  "properties": {
    "iso:country":"US",
    "sg:address":"504 14th Ave",
    "sg:city":"Monroe",
    "sg:classifiers":[
        {
            "category":"Wholesale",
            "subcategory":"Dairy",
            "type":"Manufacturing & Wholesale Goods"
        }
    ],
    "sg:phone":"+1 608 325 1222",
    "sg:postcode":"53566",
    "sg:province":"WI",
    "sg:tags":[
        "product",
        "grocery"
    ],
    "wof:name":"Northwood Dairy Sales Ltd",
    "wof:placetype":"venue"
},
  "geometry": {"coordinates":[-89.641555,42.607197],"type":"Point"}
}