{
  "type": "Feature",
  "properties": {
    "iso:country":"US",
    "sg:address":"3404 Co Rd Oo",
    "sg:city":"Sheboygan Falls",
    "sg:classifiers":[
        {
            "category":"Farming",
            "subcategory":"Dairy Farm",
            "type":"Manufacturing & Wholesale Goods"
        }
    ],
    "sg:phone":"+1 920 564 6009",
    "sg:postcode":"53085",
    "sg:province":"WI",
    "wof:name":"Ongna Acres",
    "wof:placetype":"venue"
},
  "geometry": {"coordinates":[-87.876315,43.652854],"type":"Point"}
}