{
  "type": "Feature",
  "properties": {
    "addr:full":"700 Wolske Bay Rd Menomonie WI 54751",
    "addr:housenumber":"700",
    "addr:postcode":"54751",
    "addr:street":"Wolske Bay Rd",
    "iso:country":"US",
    "sg:address":"700 Wolske Bay Rd",
    "sg:city":"Menomonie",
    "sg:classifiers":[
        {
            "category":"Banks & Credit Unions",
            "subcategory":"Investment Brokerage",
            "type":"Services"
        }
    ],
    "sg:phone":"+1 715 235 9561",
    "sg:postcode":"54751",
    "sg:province":"WI",
    "sg:tags":[
        "advisory",
        "financial"
    ],
    "wof:name":"Citifinancial",
    "wof:placetype":"venue"
},
  "geometry": {"coordinates":[-91.92825499999999,44.88625],"type":"Point"}
}