{
  "type": "Feature",
  "properties": {
    "iso:country":"US",
    "sg:address":"423 Robinhood Dr",
    "sg:city":"Sherwood",
    "sg:classifiers":[
        {
            "category":"Shopping",
            "subcategory":"Computers & Home Electronics",
            "type":"Retail Goods"
        }
    ],
    "sg:phone":"+1 920 968 7701",
    "sg:postcode":"54169",
    "sg:province":"WI",
    "sg:tags":[
        "software"
    ],
    "wof:name":"Smartforce",
    "wof:placetype":"venue"
},
  "geometry": {"coordinates":[-88.25058799999999,44.173727],"type":"Point"}
}