{
  "type": "Feature",
  "properties": {
    "iso:country":"US",
    "sg:address":"765 Cleveland Ave",
    "sg:city":"Hartford",
    "sg:classifiers":[
        {
            "category":"Professional",
            "subcategory":"Engineering",
            "type":"Services"
        }
    ],
    "sg:phone":"+1 262 673 4470",
    "sg:postcode":"53027",
    "sg:province":"WI",
    "sg:tags":[
        "engineer"
    ],
    "wof:name":"Transport Engineering Inc",
    "wof:placetype":"venue"
},
  "geometry": {"coordinates":[-88.391882,43.333471],"type":"Point"}
}