{
  "type": "Feature",
  "properties": {
    "iso:country":"US",
    "sg:address":"213 Williamsburg Dr",
    "sg:city":"Thiensville",
    "sg:classifiers":[
        {
            "category":"Professional",
            "subcategory":"Advertising",
            "type":"Services"
        }
    ],
    "sg:phone":"+1 262 238 1371",
    "sg:postcode":"53092",
    "sg:province":"WI",
    "wof:name":"Visual Marketing Concepts Inc",
    "wof:placetype":"venue"
},
  "geometry": {"coordinates":[-87.987017,43.233748],"type":"Point"}
}