{
  "type": "Feature",
  "properties": {
    "iso:country":"US",
    "sg:address":"412 3rd Ave",
    "sg:city":"Clayton",
    "sg:classifiers":[
        {
            "category":"Retail",
            "subcategory":"Repair Shop",
            "type":"Services"
        }
    ],
    "sg:phone":"+1 715 455 1907",
    "sg:postcode":"54004",
    "sg:province":"WI",
    "wof:name":"Action Security",
    "wof:placetype":"venue"
},
  "geometry": {"coordinates":[-92.07298299999999,45.252655],"type":"Point"}
}