{
  "type": "Feature",
  "properties": {
    "iso:country":"US",
    "sg:address":"1310 Fairview St",
    "sg:city":"Oshkosh",
    "sg:classifiers":[
        {
            "category":"Professional",
            "subcategory":"Management & Consulting",
            "type":"Services"
        }
    ],
    "sg:phone":"+1 920 235 0279",
    "sg:postcode":"54901",
    "sg:province":"WI",
    "sg:tags":[
        "consultant"
    ],
    "wof:name":"Public Administration Assoc",
    "wof:placetype":"venue"
},
  "geometry": {"coordinates":[-88.521262,44.034436],"type":"Point"}
}