{
  "type": "Feature",
  "properties": {
    "iso:country":"US",
    "sg:address":"5521 N Lydell Ave",
    "sg:city":"Milwaukee",
    "sg:classifiers":[
        {
            "category":"Professional",
            "subcategory":"Lawyer & Legal Services",
            "type":"Services"
        }
    ],
    "sg:phone":"+1 414 332 1200",
    "sg:postcode":"53217",
    "sg:province":"WI",
    "sg:tags":[
        "attorney"
    ],
    "wof:name":"Henry J Gefke",
    "wof:placetype":"venue"
},
  "geometry": {"coordinates":[-87.911809,43.116442],"type":"Point"}
}