{
  "type": "Feature",
  "properties": {
    "iso:country":"US",
    "sg:address":"2815 N Summit Ave",
    "sg:city":"Milwaukee",
    "sg:classifiers":[
        {
            "category":"Travel",
            "subcategory":"Travel Agent",
            "type":"Entertainment"
        }
    ],
    "sg:phone":"+1 414 964 6449",
    "sg:postcode":"53211",
    "sg:province":"WI",
    "sg:tags":[
        "health",
        "practitioner"
    ],
    "wof:name":"Andrew W Kane & Associates S C",
    "wof:placetype":"venue"
},
  "geometry": {"coordinates":[-87.875757,43.070734],"type":"Point"}
}