{
  "type": "Feature",
  "properties": {
    "iso:country":"US",
    "sg:address":"250 N Sunnyslope Rd",
    "sg:city":"Brookfield",
    "sg:classifiers":[
        {
            "category":"Banks & Credit Unions",
            "subcategory":"Bank",
            "type":"Services"
        }
    ],
    "sg:phone":"+1 262 785 8109",
    "sg:postcode":"53005",
    "sg:province":"WI",
    "sg:tags":[
        "loan",
        "real estate"
    ],
    "wof:name":"Westamerica Mortgage Co",
    "wof:placetype":"venue"
},
  "geometry": {"coordinates":[-88.086804,43.033939],"type":"Point"}
}