{
  "type": "Feature",
  "properties": {
    "iso:country":"US",
    "sg:address":"21410 116th St",
    "sg:city":"Bristol",
    "sg:classifiers":[
        {
            "category":"Manufacturing",
            "subcategory":"Tools & Machinery",
            "type":"Manufacturing & Wholesale Goods"
        }
    ],
    "sg:phone":"+1 262 862 6626",
    "sg:postcode":"53104",
    "sg:province":"WI",
    "sg:tags":[
        "designed",
        "built"
    ],
    "wof:name":"Herrmann Engineering",
    "wof:placetype":"venue"
},
  "geometry": {"coordinates":[-88.066323,42.510362],"type":"Point"}
}