{
  "type": "Feature",
  "properties": {
    "iso:country":"US",
    "sg:address":"1195 Marietta Ave",
    "sg:city":"Ixonia",
    "sg:classifiers":[
        {
            "category":"Banks & Credit Unions",
            "subcategory":"Financial Services",
            "type":"Services"
        },
        {
            "category":"Banks & Credit Unions",
            "subcategory":"Bank",
            "type":"Services"
        }
    ],
    "sg:phone":"+1 920 262 2261",
    "sg:postcode":"53036",
    "sg:province":"WI",
    "sg:tags":[
        "company",
        "holding"
    ],
    "sg:website":"www.isb.com",
    "wof:name":"I Sb Community Bank",
    "wof:placetype":"venue"
},
  "geometry": {"coordinates":[-88.59230599999999,43.142768],"type":"Point"}
}