{
  "type": "Feature",
  "properties": {
    "iso:country":"US",
    "sg:address":"744 Ryan Dr",
    "sg:city":"Hudson",
    "sg:classifiers":[
        {
            "category":"Real Estate",
            "subcategory":"Real Estate Services",
            "type":"Services"
        }
    ],
    "sg:phone":"+1 715 381 6825",
    "sg:postcode":"54016",
    "sg:province":"WI",
    "sg:tags":[
        "company",
        "title"
    ],
    "wof:name":"Northwest Title & Escrow",
    "wof:placetype":"venue"
},
  "geometry": {"coordinates":[-92.678726,44.969195],"type":"Point"}
}