{
  "type": "Feature",
  "properties": {
    "iso:country":"US",
    "sg:address":"17512 N Main St",
    "sg:city":"Galesville",
    "sg:classifiers":[
        {
            "category":"Food & Beverages",
            "subcategory":"Groceries & Convenience Stores",
            "type":"Retail Goods"
        }
    ],
    "sg:phone":"+1 608 582 2208",
    "sg:postcode":"54630",
    "sg:province":"WI",
    "sg:tags":[
        "grocer"
    ],
    "wof:name":"Piggly Wiggly",
    "wof:placetype":"venue"
},
  "geometry": {"coordinates":[-91.342437,44.091739],"type":"Point"}
}