{
  "type": "Feature",
  "properties": {
    "iso:country":"US",
    "sg:address":"863 E Birch Ave",
    "sg:city":"Milwaukee",
    "sg:classifiers":[
        {
            "category":"Professional",
            "subcategory":"Business Services",
            "type":"Services"
        }
    ],
    "sg:phone":"+1 414 963 9643",
    "sg:postcode":"53217",
    "sg:province":"WI",
    "wof:name":"Bay Group LLC",
    "wof:placetype":"venue"
},
  "geometry": {"coordinates":[-87.898714,43.115834],"type":"Point"}
}