{
  "type": "Feature",
  "properties": {
    "iso:country":"US",
    "sg:address":"1578 18th Ave",
    "sg:city":"Barron",
    "sg:classifiers":[
        {
            "category":"Farming",
            "subcategory":"Dairy Farm",
            "type":"Manufacturing & Wholesale Goods"
        }
    ],
    "sg:phone":"+1 715 537 5153",
    "sg:postcode":"54812",
    "sg:province":"WI",
    "wof:name":"Busses Barron Acres Inc",
    "wof:placetype":"venue"
},
  "geometry": {"coordinates":[-91.83027199999999,45.466294],"type":"Point"}
}