{
  "type": "Feature",
  "properties": {
    "iso:country":"US",
    "sg:address":"5205 University Ave",
    "sg:city":"Madison",
    "sg:classifiers":[
        {
            "category":"Retail",
            "subcategory":"Repair Shop",
            "type":"Services"
        }
    ],
    "sg:phone":"+1 608 238 1195",
    "sg:postcode":"53705",
    "sg:province":"WI",
    "sg:tags":[
        "parts",
        "motorcycle",
        "mfg"
    ],
    "sg:website":"www.motorcycleperf.com",
    "wof:name":"Motorcycle Performance",
    "wof:placetype":"venue"
},
  "geometry": {"coordinates":[-89.471315,43.078668],"type":"Point"}
}