{
  "type": "Feature",
  "properties": {
    "iso:country":"US",
    "sg:address":"356 Juneau Ave",
    "sg:city":"Juneau",
    "sg:classifiers":[
        {
            "category":"Professional",
            "type":"Services"
        }
    ],
    "sg:phone":"+1 920 386 9481",
    "sg:postcode":"53039",
    "sg:province":"WI",
    "wof:name":"Cm2 LLC",
    "wof:placetype":"venue"
},
  "geometry": {"coordinates":[-88.707246,43.41093],"type":"Point"}
}