{
  "type": "Feature",
  "properties": {
    "addr:full":"2856 State Hwy 89 Fort Atkinson WI 53538",
    "addr:housenumber":"2856",
    "addr:postcode":"53538",
    "addr:street":"State Hwy 89",
    "iso:country":"US",
    "sg:address":"2856 State Hwy 89",
    "sg:city":"Fort Atkinson",
    "sg:classifiers":[
        {
            "category":"Farming",
            "subcategory":"Dairy Farm",
            "type":"Manufacturing & Wholesale Goods"
        },
        {
            "category":"Manufacturing",
            "subcategory":"Printing",
            "type":"Manufacturing & Wholesale Goods"
        }
    ],
    "sg:phone":"+1 920 563 4822",
    "sg:postcode":"53538",
    "sg:province":"WI",
    "sg:tags":[
        "magazine"
    ],
    "wof:name":"Hoard's Dairyman Farm",
    "wof:placetype":"venue"
},
  "geometry": {"coordinates":[-88.83821500000001,42.945693],"type":"Point"}
}