{
  "type": "Feature",
  "properties": {
    "iso:country":"US",
    "sg:address":"1428 Co Rd A",
    "sg:city":"Edgerton",
    "sg:classifiers":[
        {
            "category":"Real Estate",
            "subcategory":"Real Estate Operator",
            "type":"Services"
        }
    ],
    "sg:phone":"+1 608 884 4890",
    "sg:postcode":"53534",
    "sg:province":"WI",
    "sg:tags":[
        "property",
        "lessor"
    ],
    "wof:name":"Gordon Lindberg",
    "wof:placetype":"venue"
},
  "geometry": {"coordinates":[-89.108158,42.89114],"type":"Point"}
}