{
  "type": "Feature",
  "properties": {
    "iso:country":"US",
    "sg:address":"205 N Madison St",
    "sg:city":"Bonduel",
    "sg:classifiers":[
        {
            "category":"Retail",
            "subcategory":"Repair Shop",
            "type":"Services"
        }
    ],
    "sg:phone":"+1 715 758 2734",
    "sg:postcode":"54107",
    "sg:province":"WI",
    "sg:tags":[
        "repairing",
        "saw"
    ],
    "wof:name":"Schneider Sharpening Svc",
    "wof:placetype":"venue"
},
  "geometry": {"coordinates":[-88.436,44.743083],"type":"Point"}
}