{
  "type": "Feature",
  "properties": {
    "iso:country":"US",
    "sg:address":"707 Center St",
    "sg:city":"Baraboo",
    "sg:classifiers":[
        {
            "category":"Education",
            "subcategory":"School",
            "type":"Public Place"
        }
    ],
    "sg:phone":"+1 608 355 3905",
    "sg:postcode":"53913",
    "sg:province":"WI",
    "wof:name":"West Elementary School",
    "wof:placetype":"venue"
},
  "geometry": {"coordinates":[-89.749151,43.472829],"type":"Point"}
}