{
  "type": "Feature",
  "properties": {
    "iso:country":"US",
    "sg:address":"404 Jays Ln",
    "sg:city":"Waukesha",
    "sg:classifiers":[
        {
            "category":"Shopping",
            "subcategory":"Bicycles & Sporting Goods",
            "type":"Retail Goods"
        }
    ],
    "sg:phone":"+1 262 896 6696",
    "sg:postcode":"53188",
    "sg:province":"WI",
    "wof:name":"HTM Small Game Heads",
    "wof:placetype":"venue"
},
  "geometry": {"coordinates":[-88.26066899999999,43.007967],"type":"Point"}
}