{
  "type": "Feature",
  "properties": {
    "iso:country":"US",
    "sg:address":"6645 Progress Rd",
    "sg:city":"Manawa",
    "sg:classifiers":[
        {
            "category":"Home & Garden",
            "subcategory":"Building Materials",
            "type":"Retail Goods"
        }
    ],
    "sg:phone":"+1 920 596 2653",
    "sg:postcode":"54949",
    "sg:province":"WI",
    "wof:name":"Vaughans Custom Cabinets",
    "wof:placetype":"venue"
},
  "geometry": {"coordinates":[-88.894739,44.475349],"type":"Point"}
}