{
  "type": "Feature",
  "properties": {
    "iso:country":"US",
    "sg:address":"851 N 92nd St",
    "sg:city":"Milwaukee",
    "sg:classifiers":[
        {
            "category":"Social Services",
            "type":"Services"
        }
    ],
    "sg:phone":"+1 414 476 6270",
    "sg:postcode":"53226",
    "sg:province":"WI",
    "wof:name":"Eclipse",
    "wof:placetype":"venue"
},
  "geometry": {"coordinates":[-88.02633,43.04077],"type":"Point"}
}