{
  "type": "Feature",
  "properties": {
    "iso:country":"US",
    "sg:address":"306 E Amelia St",
    "sg:city":"Cassville",
    "sg:classifiers":[
        {
            "category":"Manufacturing",
            "subcategory":"Toys & Sporting Goods",
            "type":"Manufacturing & Wholesale Goods"
        }
    ],
    "sg:phone":"+1 608 725 5054",
    "sg:postcode":"53806",
    "sg:province":"WI",
    "sg:tags":[
        "mfg"
    ],
    "wof:name":"Sheila Suites",
    "wof:placetype":"venue"
},
  "geometry": {"coordinates":[-90.988547,42.713121],"type":"Point"}
}