{
  "type": "Feature",
  "properties": {
    "iso:country":"US",
    "sg:address":"1424 Truax Blvd",
    "sg:city":"Eau Claire",
    "sg:classifiers":[
        {
            "category":"Freight",
            "type":"Transportation"
        }
    ],
    "sg:phone":"+1 715 579 5387",
    "sg:postcode":"54703",
    "sg:province":"WI",
    "wof:name":"Jay Hawk Transport LLC",
    "wof:placetype":"venue"
},
  "geometry": {"coordinates":[-91.527325,44.834403],"type":"Point"}
}