{
  "type": "Feature",
  "properties": {
    "iso:country":"US",
    "sg:address":"16598 Catlin Ave",
    "sg:city":"Dorchester",
    "sg:classifiers":[
        {
            "category":"Farming",
            "subcategory":"Dairy Farm",
            "type":"Manufacturing & Wholesale Goods"
        }
    ],
    "sg:phone":"+1 715 654 5968",
    "sg:postcode":"54425",
    "sg:province":"WI",
    "wof:name":"Lapp Land Dairy",
    "wof:placetype":"venue"
},
  "geometry": {"coordinates":[-90.416512,45.027638],"type":"Point"}
}