{
  "type": "Feature",
  "properties": {
    "iso:country":"US",
    "sg:address":"1113 W Kennedy Ave",
    "sg:city":"Kimberly",
    "sg:classifiers":[
        {
            "category":"Wholesale",
            "subcategory":"Stationery",
            "type":"Manufacturing & Wholesale Goods"
        }
    ],
    "sg:phone":"+1 920 832 2520",
    "sg:postcode":"54136",
    "sg:province":"WI",
    "sg:tags":[
        "product",
        "paper"
    ],
    "sg:website":"www.bradnersmith.com",
    "wof:name":"BRADNER Smith & Co Of Wi",
    "wof:placetype":"venue"
},
  "geometry": {"coordinates":[-88.352699,44.261459],"type":"Point"}
}