{
  "type": "Feature",
  "properties": {
    "addr:full":"509 W Wisconsin Ave Milwaukee WI 53203",
    "addr:housenumber":"509",
    "addr:postcode":"53203",
    "addr:street":"W Wisconsin Ave",
    "iso:country":"US",
    "sg:address":"509 W Wisconsin Ave",
    "sg:city":"Milwaukee",
    "sg:phone":"+1 414 271 7250",
    "sg:postcode":"53203",
    "sg:province":"WI",
    "sg:website":"http://www1.hilton.com/",
    "wof:name":"Hilton Milwaukee City Center",
    "wof:placetype":"venue"
},
  "geometry": {"coordinates":[-87.91758900000001,43.0388],"type":"Point"}
}