{
  "type": "Feature",
  "properties": {
    "addr:full":"1492 Ellis St Green Bay WI 54302",
    "addr:housenumber":"1492",
    "addr:postcode":"54302",
    "addr:street":"Ellis St",
    "iso:country":"US",
    "sg:address":"1492 Ellis St",
    "sg:city":"Green Bay",
    "sg:classifiers":[
        {
            "category":"Manufacturing",
            "subcategory":"Food",
            "type":"Manufacturing & Wholesale Goods"
        }
    ],
    "sg:phone":"+1 920 496 9929",
    "sg:postcode":"54302",
    "sg:province":"WI",
    "sg:tags":[
        "drink",
        "soft",
        "mfg"
    ],
    "wof:name":"Springside Bottling Inc",
    "wof:placetype":"venue"
},
  "geometry": {"coordinates":[-87.988389,44.507597],"type":"Point"}
}