{
  "type": "Feature",
  "properties": {
    "iso:country":"US",
    "sg:address":"1918 N 39th St",
    "sg:city":"Milwaukee",
    "sg:classifiers":[
        {
            "category":"Bars & Pubs",
            "type":"Food & Drink"
        }
    ],
    "sg:phone":"+1 414 344 2517",
    "sg:postcode":"53208",
    "sg:province":"WI",
    "sg:tags":[
        "drinking"
    ],
    "wof:name":"Cheers Cleaning & Services",
    "wof:placetype":"venue"
},
  "geometry": {"coordinates":[-87.962277,43.056226],"type":"Point"}
}