{
  "type": "Feature",
  "properties": {
    "iso:country":"US",
    "sg:address":"1143 W Grand Ave",
    "sg:city":"Rothschild",
    "sg:classifiers":[
        {
            "category":"Home & Garden",
            "subcategory":"Hardware",
            "type":"Retail Goods"
        }
    ],
    "sg:phone":"+1 715 848 6181",
    "sg:postcode":"54474",
    "sg:province":"WI",
    "wof:name":"Rib Mountain Hardware",
    "wof:placetype":"venue"
},
  "geometry": {"coordinates":[-89.61382399999999,44.900708],"type":"Point"}
}