{
  "type": "Feature",
  "properties": {
    "iso:country":"US",
    "sg:address":"2159 E Broadway St",
    "sg:city":"Waukesha",
    "sg:classifiers":[
        {
            "category":"Manufacturing",
            "subcategory":"Metals",
            "type":"Manufacturing & Wholesale Goods"
        }
    ],
    "sg:phone":"+1 262 896 1781",
    "sg:postcode":"53186",
    "sg:province":"WI",
    "sg:tags":[
        "mfg",
        "metalwork",
        "structural"
    ],
    "wof:name":"Top Metal Wisconsin",
    "wof:placetype":"venue"
},
  "geometry": {"coordinates":[-88.188025,43.000137],"type":"Point"}
}