{
  "type": "Feature",
  "properties": {
    "iso:country":"US",
    "sg:address":"1004 Valley Rd",
    "sg:city":"Plymouth",
    "sg:classifiers":[
        {
            "category":"Building & Trades",
            "subcategory":"Construction",
            "type":"Services"
        }
    ],
    "sg:phone":"+1 920 892 4925",
    "sg:postcode":"53073",
    "sg:province":"WI",
    "sg:tags":[
        "marking",
        "maintenance",
        "parking"
    ],
    "wof:name":"Plymouth Street Dept",
    "wof:placetype":"venue"
},
  "geometry": {"coordinates":[-87.963501,43.739884],"type":"Point"}
}