{
  "type": "Feature",
  "properties": {
    "iso:country":"US",
    "sg:address":"480 Main St",
    "sg:city":"Wild Rose",
    "sg:classifiers":[
        {
            "category":"Restaurant",
            "type":"Food & Drink"
        }
    ],
    "sg:phone":"+1 920 622 4550",
    "sg:postcode":"54984",
    "sg:province":"WI",
    "wof:name":"Pioneer Pub",
    "wof:placetype":"venue"
},
  "geometry": {"coordinates":[-89.246909,44.181675],"type":"Point"}
}