{
  "type": "Feature",
  "properties": {
    "iso:country":"US",
    "sg:address":"850 Woodlake Rd",
    "sg:city":"Kohler",
    "sg:classifiers":[
        {
            "category":"Banks & Credit Unions",
            "subcategory":"Bank",
            "type":"Services"
        }
    ],
    "sg:phone":"+1 920 459 2585",
    "sg:postcode":"53044",
    "sg:province":"WI",
    "sg:tags":[
        "state",
        "loan",
        "broker"
    ],
    "sg:website":"www.kohlercu.com",
    "wof:name":"Kohler Credit Union",
    "wof:placetype":"venue"
},
  "geometry": {"coordinates":[-87.780801,43.745807],"type":"Point"}
}