{
  "type": "Feature",
  "properties": {
    "addr:full":"5649 S 25th St Milwaukee WI 53221",
    "addr:housenumber":"5649",
    "addr:postcode":"53221",
    "addr:street":"S 25Th St",
    "iso:country":"US",
    "sg:address":"5649 S 25th St",
    "sg:city":"Milwaukee",
    "sg:classifiers":[
        {
            "category":"Building & Trades",
            "subcategory":"Plumbing",
            "type":"Services"
        }
    ],
    "sg:phone":"+1 414 482 4596",
    "sg:postcode":"53221",
    "sg:province":"WI",
    "sg:tags":[
        "irrigation",
        "contractor"
    ],
    "wof:name":"D-L Mogilka Inc",
    "wof:placetype":"venue"
},
  "geometry": {"coordinates":[-87.94653,42.942376],"type":"Point"}
}