{
  "type": "Feature",
  "properties": {
    "addr:full":"3855 E Barnard Ave Cudahy WI 53110",
    "addr:housenumber":"3855",
    "addr:postcode":"53110",
    "addr:street":"E Barnard Ave",
    "iso:country":"US",
    "sg:address":"3855 E Barnard Ave",
    "sg:city":"Cudahy",
    "sg:classifiers":[
        {
            "category":"Professional",
            "subcategory":"Management & Consulting",
            "type":"Services"
        }
    ],
    "sg:phone":"+1 414 294 0459",
    "sg:postcode":"53110",
    "sg:province":"WI",
    "wof:name":"Wsnh World Marketing LLC",
    "wof:placetype":"venue"
},
  "geometry": {"coordinates":[-87.85376100000001,42.95727],"type":"Point"}
}