{
  "type": "Feature",
  "properties": {
    "iso:country":"US",
    "sg:address":"5207 Rustic Way",
    "sg:city":"Mc Farland",
    "sg:classifiers":[
        {
            "category":"Food & Beverages",
            "subcategory":"Bakery",
            "type":"Retail Goods"
        }
    ],
    "sg:phone":"+1 608 838 6028",
    "sg:postcode":"53558",
    "sg:province":"WI",
    "sg:tags":[
        "baker"
    ],
    "wof:name":"Chris's Confections",
    "wof:placetype":"venue"
},
  "geometry": {"coordinates":[-89.295798,43.022285],"type":"Point"}
}