{
  "type": "Feature",
  "properties": {
    "addr:full":"411 22nd Ave Monroe WI 53566",
    "addr:housenumber":"411",
    "addr:postcode":"53566",
    "addr:street":"22Nd Ave",
    "iso:country":"US",
    "sg:address":"411 22nd Ave",
    "sg:city":"Monroe",
    "sg:classifiers":[
        {
            "category":"Professional",
            "subcategory":"Research",
            "type":"Services"
        }
    ],
    "sg:phone":"+1 608 324 2670",
    "sg:postcode":"53566",
    "sg:province":"WI",
    "sg:tags":[
        "medical"
    ],
    "wof:name":"Monroe Med Found For Research",
    "wof:placetype":"venue"
},
  "geometry": {"coordinates":[-89.632668,42.608155],"type":"Point"}
}