{
  "type": "Feature",
  "properties": {
    "iso:country":"US",
    "sg:address":"6193 N 84th St",
    "sg:city":"Milwaukee",
    "sg:classifiers":[
        {
            "category":"Personal",
            "subcategory":"Beauty Salon",
            "type":"Services"
        }
    ],
    "sg:phone":"+1 414 358 3922",
    "sg:postcode":"53225",
    "sg:province":"WI",
    "wof:name":"Shawanna Beauty Salon",
    "wof:placetype":"venue"
},
  "geometry": {"coordinates":[-88.015754,43.13208],"type":"Point"}
}