{
  "type": "Feature",
  "properties": {
    "iso:country":"US",
    "sg:address":"904 Tenny Ave",
    "sg:city":"Waukesha",
    "sg:classifiers":[
        {
            "category":"Professional",
            "subcategory":"Management & Consulting",
            "type":"Services"
        }
    ],
    "sg:phone":"+1 262 549 1232",
    "sg:postcode":"53186",
    "sg:province":"WI",
    "wof:name":"Asset Management Services Inc",
    "wof:placetype":"venue"
},
  "geometry": {"coordinates":[-88.21948500000001,42.99528],"type":"Point"}
}