{
  "type": "Feature",
  "properties": {
    "iso:country":"US",
    "sg:address":"404 Broadway St",
    "sg:city":"Eau Claire",
    "sg:classifiers":[
        {
            "category":"Social Services",
            "type":"Services"
        }
    ],
    "sg:phone":"+1 715 834 9578",
    "sg:postcode":"54703",
    "sg:province":"WI",
    "sg:tags":[
        "information",
        "abuse",
        "domestic",
        "treatment"
    ],
    "wof:name":"Bolton Refuge House",
    "wof:placetype":"venue"
},
  "geometry": {"coordinates":[-91.509712,44.805121],"type":"Point"}
}