{
  "type": "Feature",
  "properties": {
    "addr:full":"2421 S Stoughton Rd Madison WI 53716",
    "addr:housenumber":"2421",
    "addr:postcode":"53716",
    "addr:street":"S Stoughton Rd",
    "iso:country":"US",
    "sg:address":"2421 S Stoughton Rd",
    "sg:city":"Madison",
    "sg:classifiers":[
        {
            "category":"Restaurant",
            "type":"Food & Drink"
        }
    ],
    "sg:menulink":"http://www.allmenus.com/wi/madison/195830-wendys/menu/",
    "sg:phone":"+1 608 223 1120",
    "sg:postcode":"53716",
    "sg:province":"WI",
    "sg:tags":[
        "burger",
        "american",
        "soup"
    ],
    "wof:name":"Wendy's",
    "wof:placetype":"venue"
},
  "geometry": {"coordinates":[-89.30877700000001,43.063492],"type":"Point"}
}