{
  "type": "Feature",
  "properties": {
    "iso:country":"US",
    "sg:address":"1277 60th St",
    "sg:city":"Amery",
    "sg:classifiers":[
        {
            "category":"Organizations",
            "subcategory":"Religious Organization",
            "type":"Services"
        }
    ],
    "sg:phone":"+1 715 268 7799",
    "sg:postcode":"54001",
    "sg:province":"WI",
    "wof:name":"Elim Lutheran Church",
    "wof:placetype":"venue"
},
  "geometry": {"coordinates":[-92.2847,45.393275],"type":"Point"}
}