{
  "type": "Feature",
  "properties": {
    "iso:country":"US",
    "sg:address":"10050 N Port Washington Rd",
    "sg:city":"Mequon",
    "sg:classifiers":[
        {
            "category":"Organizations",
            "subcategory":"Religious Organization",
            "type":"Services"
        }
    ],
    "sg:phone":"+1 262 478 0414",
    "sg:postcode":"53092",
    "sg:province":"WI",
    "sg:tags":[
        "synagogue"
    ],
    "wof:name":"Agudas Achim Chabad",
    "wof:placetype":"venue"
},
  "geometry": {"coordinates":[-87.924254,43.200361],"type":"Point"}
}