{
  "type": "Feature",
  "properties": {
    "iso:country":"US",
    "sg:address":"6769 State Hwy 187",
    "sg:city":"Shiocton",
    "sg:classifiers":[
        {
            "category":"Building & Trades",
            "subcategory":"Plumbing",
            "type":"Services"
        }
    ],
    "sg:phone":"+1 920 740 8889",
    "sg:postcode":"54170",
    "sg:province":"WI",
    "sg:tags":[
        "concrete",
        "waterproofing"
    ],
    "wof:name":"T C Concrete Designs",
    "wof:placetype":"venue"
},
  "geometry": {"coordinates":[-88.57017399999999,44.476773],"type":"Point"}
}