{
  "type": "Feature",
  "properties": {
    "iso:country":"US",
    "sg:address":"3424 Co Rd C",
    "sg:city":"Medford",
    "sg:classifiers":[
        {
            "category":"Home & Garden",
            "subcategory":"Garden Supply",
            "type":"Retail Goods"
        }
    ],
    "sg:phone":"+1 715 748 6979",
    "sg:postcode":"54451",
    "sg:province":"WI",
    "sg:tags":[
        "nurseryman"
    ],
    "wof:name":"Willow Cottage",
    "wof:placetype":"venue"
},
  "geometry": {"coordinates":[-90.16706600000001,45.162394],"type":"Point"}
}