{
  "type": "Feature",
  "properties": {
    "iso:country":"US",
    "sg:address":"2537 N 33rd St",
    "sg:city":"Milwaukee",
    "sg:classifiers":[
        {
            "category":"Banks & Credit Unions",
            "subcategory":"Financial Services",
            "type":"Services"
        }
    ],
    "sg:phone":"+1 414 871 2908",
    "sg:postcode":"53210",
    "sg:province":"WI",
    "sg:tags":[
        "trust",
        "investment",
        "real estate"
    ],
    "wof:name":"Albert A Jones Irrevocabl",
    "wof:placetype":"venue"
},
  "geometry": {"coordinates":[-87.955297,43.065401],"type":"Point"}
}