{
  "type": "Feature",
  "properties": {
    "iso:country":"US",
    "sg:address":"2104 Cameron St",
    "sg:city":"Eau Claire",
    "sg:classifiers":[
        {
            "category":"Home & Garden",
            "subcategory":"Furniture",
            "type":"Retail Goods"
        }
    ],
    "sg:phone":"+1 715 839 9780",
    "sg:postcode":"54703",
    "sg:province":"WI",
    "wof:name":"Northern Oak Furniture",
    "wof:placetype":"venue"
},
  "geometry": {"coordinates":[-91.53733800000001,44.814342],"type":"Point"}
}