{
  "type": "Feature",
  "properties": {
    "iso:country":"US",
    "sg:address":"115 Main St",
    "sg:city":"Pewaukee",
    "sg:classifiers":[
        {
            "category":"Personal",
            "subcategory":"Beauty Salon",
            "type":"Services"
        }
    ],
    "sg:phone":"+1 262 691 9542",
    "sg:postcode":"53072",
    "sg:province":"WI",
    "wof:name":"Lake Country Salons",
    "wof:placetype":"venue"
},
  "geometry": {"coordinates":[-88.261598,43.080649],"type":"Point"}
}