{
  "type": "Feature",
  "properties": {
    "iso:country":"US",
    "sg:address":"3384 Kozuzek Rd",
    "sg:city":"Marinette",
    "sg:classifiers":[
        {
            "category":"Education",
            "subcategory":"Dance Studio",
            "type":"Public Place"
        }
    ],
    "sg:phone":"+1 715 582 4057",
    "sg:postcode":"54143",
    "sg:province":"WI",
    "wof:name":"North Country Kickers",
    "wof:placetype":"venue"
},
  "geometry": {"coordinates":[-87.738595,45.078441],"type":"Point"}
}