{
  "type": "Feature",
  "properties": {
    "addr:full":"2500 Perry St Madison WI 53713",
    "addr:housenumber":"2500",
    "addr:postcode":"53713",
    "addr:street":"Perry St",
    "iso:country":"US",
    "sg:address":"2500 Perry St",
    "sg:city":"Madison",
    "sg:classifiers":[
        {
            "category":"Travel",
            "subcategory":"Hotels & Motels",
            "type":"Entertainment"
        }
    ],
    "sg:phone":"+1 608 256 0272",
    "sg:postcode":"53713",
    "sg:province":"WI",
    "sg:tags":[
        "operator",
        "property",
        "commercial"
    ],
    "sg:website":"www.mayflowermotel.com",
    "wof:name":"Mayflower Motel & Lounge",
    "wof:placetype":"venue"
},
  "geometry": {"coordinates":[-89.396646,43.037434],"type":"Point"}
}