{
  "type": "Feature",
  "properties": {
    "iso:country":"US",
    "sg:address":"529 Main St",
    "sg:city":"La Crosse",
    "sg:classifiers":[
        {
            "category":"Shopping",
            "type":"Retail Goods"
        }
    ],
    "sg:phone":"+1 608 782 8544",
    "sg:postcode":"54601",
    "sg:province":"WI",
    "sg:tags":[
        "church",
        "supply"
    ],
    "wof:name":"Carl B Noelke Co",
    "wof:placetype":"venue"
},
  "geometry": {"coordinates":[-91.248648,43.811713],"type":"Point"}
}