{
  "type": "Feature",
  "properties": {
    "iso:country":"US",
    "sg:address":"2001 Brookfield Rd",
    "sg:city":"Edgar",
    "sg:classifiers":[
        {
            "category":"Professional",
            "subcategory":"Computer Services",
            "type":"Services"
        }
    ],
    "sg:phone":"+1 715 352 3655",
    "sg:postcode":"54426",
    "sg:province":"WI",
    "sg:tags":[
        "programing",
        "custom"
    ],
    "wof:name":"Data Resource Inc",
    "wof:placetype":"venue"
},
  "geometry": {"coordinates":[-89.906716,44.840845],"type":"Point"}
}