{
  "type": "Feature",
  "properties": {
    "iso:country":"US",
    "sg:address":"2280 N 105th St",
    "sg:city":"Milwaukee",
    "sg:classifiers":[
        {
            "category":"Real Estate",
            "subcategory":"Real Estate Services",
            "type":"Services"
        }
    ],
    "sg:phone":"+1 414 977 8670",
    "sg:postcode":"53226",
    "sg:province":"WI",
    "sg:tags":[
        "company",
        "title"
    ],
    "wof:name":"Horizon Title Svc LP",
    "wof:placetype":"venue"
},
  "geometry": {"coordinates":[-88.043617,43.059102],"type":"Point"}
}