{
  "type": "Feature",
  "properties": {
    "iso:country":"US",
    "sg:address":"7393 Getter Rd",
    "sg:city":"Viroqua",
    "sg:classifiers":[
        {
            "category":"Farming",
            "subcategory":"Dairy Farm",
            "type":"Manufacturing & Wholesale Goods"
        }
    ],
    "sg:phone":"+1 608 637 7489",
    "sg:postcode":"54665",
    "sg:province":"WI",
    "wof:name":"Conrad Anderson",
    "wof:placetype":"venue"
},
  "geometry": {"coordinates":[-90.89294099999999,43.524314],"type":"Point"}
}