{
  "type": "Feature",
  "properties": {
    "iso:country":"US",
    "sg:address":"890 Briar Ridge Dr E",
    "sg:city":"Brookfield",
    "sg:classifiers":[
        {
            "category":"Building & Trades",
            "subcategory":"Plumbing",
            "type":"Services"
        }
    ],
    "sg:phone":"+1 262 784 6886",
    "sg:postcode":"53045",
    "sg:province":"WI",
    "sg:tags":[
        "contractor"
    ],
    "wof:name":"Pipia Graphics and Advertising",
    "wof:placetype":"venue"
},
  "geometry": {"coordinates":[-88.156284,43.039793],"type":"Point"}
}