{
  "type": "Feature",
  "properties": {
    "iso:country":"US",
    "sg:address":"5593 State Hwy 76",
    "sg:city":"Shiocton",
    "sg:classifiers":[
        {
            "category":"Retail",
            "subcategory":"Repair Shop",
            "type":"Services"
        }
    ],
    "sg:phone":"+1 920 986 1247",
    "sg:postcode":"54170",
    "sg:province":"WI",
    "sg:tags":[
        "armature",
        "rewinding"
    ],
    "wof:name":"Electrical Apparatus Svc Co",
    "wof:placetype":"venue"
},
  "geometry": {"coordinates":[-88.580782,44.439539],"type":"Point"}
}