{
  "type": "Feature",
  "properties": {
    "iso:country":"US",
    "sg:address":"702 28th St S",
    "sg:city":"La Crosse",
    "sg:classifiers":[
        {
            "category":"Freight",
            "type":"Transportation"
        }
    ],
    "sg:phone":"+1 608 788 1961",
    "sg:postcode":"54601",
    "sg:province":"WI",
    "sg:tags":[
        "distance",
        "local",
        "long",
        "trucking"
    ],
    "wof:name":"Niedfeldt Trucking",
    "wof:placetype":"venue"
},
  "geometry": {"coordinates":[-91.215001,43.801964],"type":"Point"}
}