{
  "type": "Feature",
  "properties": {
    "iso:country":"US",
    "sg:address":"5639 9th Rd",
    "sg:city":"Algoma",
    "sg:classifiers":[
        {
            "category":"Professional",
            "subcategory":"Engineering",
            "type":"Services"
        }
    ],
    "sg:phone":"+1 920 487 5437",
    "sg:postcode":"54201",
    "sg:province":"WI",
    "wof:name":"Lakeview Engineering",
    "wof:placetype":"venue"
},
  "geometry": {"coordinates":[-87.483752,44.566978],"type":"Point"}
}