{
  "type": "Feature",
  "properties": {
    "addr:full":"33822 High Dr Waterford WI 53120",
    "addr:housenumber":"33822",
    "addr:postcode":"53120",
    "addr:street":"High Dr",
    "iso:country":"US",
    "sg:address":"33822 High Dr",
    "sg:city":"Waterford",
    "sg:classifiers":[
        {
            "category":"Recreation",
            "type":"Entertainment"
        }
    ],
    "sg:phone":"+1 262 514 2797",
    "sg:postcode":"53120",
    "sg:province":"WI",
    "sg:tags":[
        "stable"
    ],
    "wof:name":"Sun Fire Stable",
    "wof:placetype":"venue"
},
  "geometry": {"coordinates":[-88.27919900000001,42.770091],"type":"Point"}
}