{
  "type": "Feature",
  "properties": {
    "iso:country":"US",
    "sg:address":"17280 W North Ave",
    "sg:city":"Brookfield",
    "sg:classifiers":[
        {
            "category":"Health Services",
            "subcategory":"Doctor",
            "type":"Services"
        }
    ],
    "sg:phone":"+1 262 789 9200",
    "sg:postcode":"53045",
    "sg:province":"WI",
    "sg:tags":[
        "dentist"
    ],
    "wof:name":"Christopher A Blake DDS",
    "wof:placetype":"venue"
},
  "geometry": {"coordinates":[-88.127206,43.061101],"type":"Point"}
}