{
  "type": "Feature",
  "properties": {
    "addr:full":"1960 Graham Ln Mosinee WI 54455",
    "addr:housenumber":"1960",
    "addr:postcode":"54455",
    "addr:street":"Graham Ln",
    "iso:country":"US",
    "sg:address":"1960 Graham Ln",
    "sg:city":"Mosinee",
    "sg:classifiers":[
        {
            "category":"Professional",
            "type":"Services"
        }
    ],
    "sg:phone":"+1 715 457 6197",
    "sg:postcode":"54455",
    "sg:province":"WI",
    "wof:name":"James Marchel",
    "wof:placetype":"venue"
},
  "geometry": {"coordinates":[-89.70152299999999,44.705463],"type":"Point"}
}