{
  "type": "Feature",
  "properties": {
    "iso:country":"US",
    "sg:address":"608 Stanton St",
    "sg:city":"Ripon",
    "sg:classifiers":[
        {
            "category":"Home & Garden",
            "subcategory":"Home Furnishings",
            "type":"Retail Goods"
        }
    ],
    "sg:phone":"+1 920 748 7117",
    "sg:postcode":"54971",
    "sg:province":"WI",
    "wof:name":"Wrought Iron Solutions",
    "wof:placetype":"venue"
},
  "geometry": {"coordinates":[-88.82572500000001,43.852668],"type":"Point"}
}