{
  "type": "Feature",
  "properties": {
    "addr:full":"12207 W Bluemound Rd Milwaukee WI 53226",
    "addr:housenumber":"12207",
    "addr:postcode":"53226",
    "addr:street":"W Bluemound Rd",
    "iso:country":"US",
    "sg:address":"12207 W Bluemound Rd",
    "sg:city":"Milwaukee",
    "sg:classifiers":[
        {
            "category":"Building & Trades",
            "subcategory":"Cleaning & Sanitation",
            "type":"Services"
        }
    ],
    "sg:phone":"+1 414 771 1126",
    "sg:postcode":"53226",
    "sg:province":"WI",
    "sg:tags":[
        "maintenance"
    ],
    "wof:name":"Heaven Scent Inc",
    "wof:placetype":"venue"
},
  "geometry": {"coordinates":[-88.0646,43.036351],"type":"Point"}
}