{
  "type": "Feature",
  "properties": {
    "iso:country":"US",
    "sg:address":"1920 Libal St",
    "sg:city":"Green Bay",
    "sg:classifiers":[
        {
            "category":"Shopping",
            "subcategory":"Florist",
            "type":"Retail Goods"
        }
    ],
    "sg:phone":"+1 920 347 1288",
    "sg:postcode":"54301",
    "sg:province":"WI",
    "wof:name":"Avant - Garde Floral Studio",
    "wof:placetype":"venue"
},
  "geometry": {"coordinates":[-88.012378,44.483434],"type":"Point"}
}