{
  "type": "Feature",
  "properties": {
    "iso:country":"US",
    "sg:address":"207 Dodge St",
    "sg:city":"Kaukauna",
    "sg:classifiers":[
        {
            "category":"Autos & Motor Vehicles",
            "subcategory":"Auto Supplies",
            "type":"Retail Goods"
        }
    ],
    "sg:phone":"+1 920 766 0001",
    "sg:postcode":"54130",
    "sg:province":"WI",
    "sg:tags":[
        "repair",
        "tire"
    ],
    "wof:name":"A T F Tires & Service",
    "wof:placetype":"venue"
},
  "geometry": {"coordinates":[-88.271717,44.27637],"type":"Point"}
}