{
  "type": "Feature",
  "properties": {
    "iso:country":"US",
    "sg:address":"2360 S 106th St",
    "sg:city":"Milwaukee",
    "sg:classifiers":[
        {
            "category":"Social Services",
            "subcategory":"Child Care",
            "type":"Services"
        }
    ],
    "sg:phone":"+1 414 545 0100",
    "sg:postcode":"53227",
    "sg:province":"WI",
    "sg:website":"www.aalchildcare.com",
    "wof:name":"All About Learning",
    "wof:placetype":"venue"
},
  "geometry": {"coordinates":[-88.044353,43.002062],"type":"Point"}
}