{
  "type": "Feature",
  "properties": {
    "iso:country":"US",
    "sg:address":"409 N Broadway",
    "sg:city":"Green Bay",
    "sg:classifiers":[
        {
            "category":"Social Services",
            "type":"Services"
        }
    ],
    "sg:phone":"+1 920 437 3766",
    "sg:postcode":"54303",
    "sg:province":"WI",
    "wof:name":"New Community Shelter Inc",
    "wof:placetype":"venue"
},
  "geometry": {"coordinates":[-88.018116,44.522062],"type":"Point"}
}