{
  "type": "Feature",
  "properties": {
    "addr:full":"7867 Iband Ave Sparta WI 54656",
    "addr:housenumber":"7867",
    "addr:postcode":"54656",
    "addr:street":"Iband Ave",
    "iso:country":"US",
    "sg:address":"7867 Iband Ave",
    "sg:city":"Sparta",
    "sg:classifiers":[
        {
            "category":"Building & Trades",
            "subcategory":"Construction",
            "type":"Services"
        }
    ],
    "sg:phone":"+1 608 269 4226",
    "sg:postcode":"54656",
    "sg:province":"WI",
    "sg:tags":[
        "water",
        "well",
        "drilling"
    ],
    "wof:name":"Tri-County Well Drilling",
    "wof:placetype":"venue"
},
  "geometry": {"coordinates":[-90.834952,43.920852],"type":"Point"}
}