{
  "type": "Feature",
  "properties": {
    "iso:country":"US",
    "sg:address":"2524 Lake Shore Dr W",
    "sg:city":"Ashland",
    "sg:classifiers":[
        {
            "category":"Autos & Motor Vehicles",
            "subcategory":"Automobile Sales",
            "type":"Retail Goods"
        }
    ],
    "sg:phone":"+1 715 685 0030",
    "sg:postcode":"54806",
    "sg:province":"WI",
    "sg:tags":[
        "car",
        "dealer"
    ],
    "wof:name":"Quality Truck & Auto-Ashland",
    "wof:placetype":"venue"
},
  "geometry": {"coordinates":[-90.91664400000001,46.582444],"type":"Point"}
}