{
  "type": "Feature",
  "properties": {
    "iso:country":"US",
    "sg:address":"3811 Spring St",
    "sg:city":"Racine",
    "sg:classifiers":[
        {
            "category":"Health Services",
            "subcategory":"Doctor",
            "type":"Services"
        }
    ],
    "sg:phone":"+1 262 687 5800",
    "sg:postcode":"53405",
    "sg:province":"WI",
    "sg:tags":[
        "physician",
        "surgeon"
    ],
    "wof:name":"All Saints Medical Group",
    "wof:placetype":"venue"
},
  "geometry": {"coordinates":[-87.825698,42.733588],"type":"Point"}
}