{
  "type": "Feature",
  "properties": {
    "addr:full":"626 Pierce Rd Rockland WI 54653",
    "addr:housenumber":"626",
    "addr:postcode":"54653",
    "addr:street":"Pierce Rd",
    "iso:country":"US",
    "sg:address":"626 Pierce Rd",
    "sg:city":"Rockland",
    "sg:classifiers":[
        {
            "category":"Farming",
            "subcategory":"Livestock Farm",
            "type":"Manufacturing & Wholesale Goods"
        }
    ],
    "sg:phone":"+1 608 486 2579",
    "sg:postcode":"54653",
    "sg:province":"WI",
    "sg:tags":[
        "beef",
        "feedlot",
        "cattle"
    ],
    "wof:name":"John W Jones",
    "wof:placetype":"venue"
},
  "geometry": {"coordinates":[-90.936656,43.843896],"type":"Point"}
}