{
  "type": "Feature",
  "properties": {
    "iso:country":"US",
    "sg:address":"209 S Main St",
    "sg:city":"Greenwood",
    "sg:classifiers":[
        {
            "category":"Personal",
            "subcategory":"Barber",
            "type":"Services"
        }
    ],
    "sg:phone":"+1 715 267 6800",
    "sg:postcode":"54437",
    "sg:province":"WI",
    "wof:name":"His & Her Hairstyling",
    "wof:placetype":"venue"
},
  "geometry": {"coordinates":[-90.598223,44.765715],"type":"Point"}
}