{
  "type": "Feature",
  "properties": {
    "iso:country":"US",
    "sg:address":"6501 W Layton Ave",
    "sg:city":"Milwaukee",
    "sg:classifiers":[
        {
            "category":"Home & Garden",
            "subcategory":"Furniture",
            "type":"Retail Goods"
        }
    ],
    "sg:phone":"+1 414 282 4334",
    "sg:postcode":"53220",
    "sg:province":"WI",
    "sg:tags":[
        "mattress"
    ],
    "wof:name":"Verlo Mattress Factory Stores",
    "wof:placetype":"venue"
},
  "geometry": {"coordinates":[-87.996307,42.959327],"type":"Point"}
}