{
  "type": "Feature",
  "properties": {
    "iso:country":"US",
    "sg:address":"15 W 5th Ave",
    "sg:city":"Shell Lake",
    "sg:classifiers":[
        {
            "category":"Professional",
            "subcategory":"Business Services",
            "type":"Services"
        }
    ],
    "sg:phone":"+1 715 468 4020",
    "sg:postcode":"54871",
    "sg:province":"WI",
    "sg:tags":[
        "auctioneer"
    ],
    "wof:name":"Lutz Auction Svc",
    "wof:placetype":"venue"
},
  "geometry": {"coordinates":[-91.925443,45.743119],"type":"Point"}
}