{
  "type": "Feature",
  "properties": {
    "iso:country":"US",
    "sg:address":"1835 Gopher Hill Rd",
    "sg:city":"Ixonia",
    "sg:classifiers":[
        {
            "category":"Building & Trades",
            "subcategory":"Construction",
            "type":"Services"
        }
    ],
    "sg:phone":"+1 920 261 2983",
    "sg:postcode":"53036",
    "sg:province":"WI",
    "sg:tags":[
        "family",
        "farm",
        "builder",
        "contractor",
        "home",
        "remodeling"
    ],
    "wof:name":"Albert Damrow Construction",
    "wof:placetype":"venue"
},
  "geometry": {"coordinates":[-88.619716,43.172687],"type":"Point"}
}