{
  "type": "Feature",
  "properties": {
    "iso:country":"US",
    "sg:address":"555 W Waukau Ave",
    "sg:city":"Oshkosh",
    "sg:classifiers":[
        {
            "category":"Manufacturing",
            "subcategory":"Metals",
            "type":"Manufacturing & Wholesale Goods"
        }
    ],
    "sg:phone":"+1 920 235 7770",
    "sg:postcode":"54902",
    "sg:province":"WI",
    "sg:tags":[
        "engraver"
    ],
    "sg:website":"www.oecgraphics.com",
    "wof:name":"OEC Graphics Inc",
    "wof:placetype":"venue"
},
  "geometry": {"coordinates":[-88.55175199999999,43.981158],"type":"Point"}
}