{
  "type": "Feature",
  "properties": {
    "addr:full":"3201 N Mayfair Rd Milwaukee WI 53222",
    "addr:housenumber":"3201",
    "addr:postcode":"53222",
    "addr:street":"N Mayfair Rd",
    "iso:country":"US",
    "sg:address":"3201 N Mayfair Rd",
    "sg:city":"Milwaukee",
    "sg:classifiers":[
        {
            "category":"Shopping",
            "subcategory":"Department Store",
            "type":"Retail Goods"
        }
    ],
    "sg:phone":"+1 414 453 5800",
    "sg:postcode":"53222",
    "sg:province":"WI",
    "wof:name":"Kmart",
    "wof:placetype":"venue"
},
  "geometry": {"coordinates":[-88.047968,43.075317],"type":"Point"}
}