{
  "type": "Feature",
  "properties": {
    "iso:country":"US",
    "sg:address":"105 7th St S",
    "sg:city":"La Crosse",
    "sg:classifiers":[
        {
            "category":"Bus Charters",
            "type":"Transportation"
        }
    ],
    "sg:phone":"+1 608 782 8360",
    "sg:postcode":"54601",
    "sg:province":"WI",
    "sg:tags":[
        "rental"
    ],
    "wof:name":"North Central Lines Inc",
    "wof:placetype":"venue"
},
  "geometry": {"coordinates":[-91.24669299999999,43.810034],"type":"Point"}
}