{
  "type": "Feature",
  "properties": {
    "iso:country":"US",
    "sg:address":"8750 S Howell Ave",
    "sg:city":"Oak Creek",
    "sg:classifiers":[
        {
            "category":"Restaurant",
            "type":"Food & Drink"
        }
    ],
    "sg:menulink":"http://www.allmenus.com/wi/oak-creek/41085-qdoba/menu/",
    "sg:phone":"+1 414 435 0117",
    "sg:postcode":"53154",
    "sg:province":"WI",
    "sg:tags":[
        "mexican"
    ],
    "wof:name":"Qdoba",
    "wof:placetype":"venue"
},
  "geometry": {"coordinates":[-87.91127299999999,42.90205],"type":"Point"}
}