{
  "type": "Feature",
  "properties": {
    "iso:country":"US",
    "sg:address":"1705 Winter St",
    "sg:city":"Superior",
    "sg:classifiers":[
        {
            "category":"Shopping",
            "subcategory":"Bicycles & Sporting Goods",
            "type":"Retail Goods"
        }
    ],
    "sg:phone":"+1 715 394 4982",
    "sg:postcode":"54880",
    "sg:province":"WI",
    "sg:tags":[
        "sport",
        "gun",
        "gunsmith"
    ],
    "sg:website":"www.superiorshooterssupply.com",
    "wof:name":"Superior Shooters Supply Ltd",
    "wof:placetype":"venue"
},
  "geometry": {"coordinates":[-92.103835,46.727977],"type":"Point"}
}