{
  "type": "Feature",
  "properties": {
    "addr:full":"12695 Co Rd U Strum WI 54770",
    "addr:housenumber":"12695",
    "addr:postcode":"54770",
    "addr:street":"Co Rd",
    "iso:country":"US",
    "sg:address":"12695 Co Rd U",
    "sg:city":"Strum",
    "sg:classifiers":[
        {
            "category":"Professional",
            "subcategory":"Business Services",
            "type":"Services"
        }
    ],
    "sg:phone":"+1 715 878 9221",
    "sg:postcode":"54770",
    "sg:province":"WI",
    "wof:name":"C L Pro Pool Service",
    "wof:placetype":"venue"
},
  "geometry": {"coordinates":[-91.397507,44.645174],"type":"Point"}
}