{
  "type": "Feature",
  "properties": {
    "iso:country":"US",
    "sg:address":"1820 Hammond Ave",
    "sg:city":"Superior",
    "sg:classifiers":[
        {
            "category":"Health Services",
            "subcategory":"Health Practitioner",
            "type":"Services"
        }
    ],
    "sg:phone":"+1 715 392 4806",
    "sg:postcode":"54880",
    "sg:province":"WI",
    "wof:name":"Personal Physical Therapies",
    "wof:placetype":"venue"
},
  "geometry": {"coordinates":[-92.097841,46.716281],"type":"Point"}
}