{
  "type": "Feature",
  "properties": {
    "iso:country":"US",
    "sg:address":"726 Oakwood Ct",
    "sg:city":"Jefferson",
    "sg:classifiers":[
        {
            "category":"Professional",
            "subcategory":"Business Services",
            "type":"Services"
        }
    ],
    "sg:phone":"+1 920 674 5500",
    "sg:postcode":"53549",
    "sg:province":"WI",
    "sg:tags":[
        "auctioneer"
    ],
    "wof:name":"Bill Stade Auction & Realty Co",
    "wof:placetype":"venue"
},
  "geometry": {"coordinates":[-88.820302,42.99107],"type":"Point"}
}