{
  "type": "Feature",
  "properties": {
    "iso:country":"US",
    "sg:address":"525 Progress Ave",
    "sg:city":"Waukesha",
    "sg:classifiers":[
        {
            "category":"Building & Trades",
            "subcategory":"Plumbing",
            "type":"Services"
        }
    ],
    "sg:phone":"+1 262 513 4688",
    "sg:postcode":"53186",
    "sg:province":"WI",
    "sg:tags":[
        "mechanical",
        "contractor"
    ],
    "wof:name":"Mechanical Installation & Svc",
    "wof:placetype":"venue"
},
  "geometry": {"coordinates":[-88.243002,42.991381],"type":"Point"}
}