{
  "type": "Feature",
  "properties": {
    "iso:country":"US",
    "sg:address":"4746 Hillside Rd",
    "sg:city":"West Bend",
    "sg:classifiers":[
        {
            "category":"Building & Trades",
            "subcategory":"Construction",
            "type":"Services"
        }
    ],
    "sg:phone":"+1 262 644 6068",
    "sg:postcode":"53095",
    "sg:province":"WI",
    "sg:tags":[
        "sandblasting"
    ],
    "wof:name":"Blast Craft Svc Inc",
    "wof:placetype":"venue"
},
  "geometry": {"coordinates":[-88.241122,43.36347],"type":"Point"}
}