{
  "type": "Feature",
  "properties": {
    "iso:country":"US",
    "sg:address":"6420 375th Ave",
    "sg:city":"Burlington",
    "sg:classifiers":[
        {
            "category":"Professional",
            "subcategory":"Management & Consulting",
            "type":"Services"
        }
    ],
    "sg:phone":"+1 262 537 2203",
    "sg:postcode":"53105",
    "sg:province":"WI",
    "sg:tags":[
        "public",
        "relations"
    ],
    "wof:name":"Twin b Sales & Service",
    "wof:placetype":"venue"
},
  "geometry": {"coordinates":[-88.26429400000001,42.577863],"type":"Point"}
}