{
  "type": "Feature",
  "properties": {
    "iso:country":"US",
    "sg:address":"1939 Lewis Rd",
    "sg:city":"Mount Horeb",
    "sg:classifiers":[
        {
            "category":"Farming",
            "subcategory":"Dairy Farm",
            "type":"Manufacturing & Wholesale Goods"
        }
    ],
    "sg:phone":"+1 608 832 6648",
    "sg:postcode":"53572",
    "sg:province":"WI",
    "wof:name":"James Hanson",
    "wof:placetype":"venue"
},
  "geometry": {"coordinates":[-89.701507,42.961582],"type":"Point"}
}