{
  "type": "Feature",
  "properties": {
    "addr:full":"1350 N 60th St Milwaukee WI 53208",
    "addr:housenumber":"1350",
    "addr:postcode":"53208",
    "addr:street":"N 60Th St",
    "iso:country":"US",
    "sg:address":"1350 N 60th St",
    "sg:city":"Milwaukee",
    "sg:classifiers":[
        {
            "category":"Building & Trades",
            "subcategory":"Cleaning & Sanitation",
            "type":"Services"
        }
    ],
    "sg:phone":"+1 414 259 6004",
    "sg:postcode":"53208",
    "sg:province":"WI",
    "sg:tags":[
        "janitor"
    ],
    "wof:name":"Clean Team Svc",
    "wof:placetype":"venue"
},
  "geometry": {"coordinates":[-87.987472,43.048643],"type":"Point"}
}