{
  "type": "Feature",
  "properties": {
    "iso:country":"US",
    "sg:address":"600 W Verona Ave",
    "sg:city":"Verona",
    "sg:classifiers":[
        {
            "category":"Organizations",
            "subcategory":"Religious Organization",
            "type":"Services"
        }
    ],
    "sg:phone":"+1 608 848 4965",
    "sg:postcode":"53593",
    "sg:province":"WI",
    "sg:tags":[
        "church"
    ],
    "wof:name":"Resurrection Lutheran Church",
    "wof:placetype":"venue"
},
  "geometry": {"coordinates":[-89.545773,42.988406],"type":"Point"}
}