{
  "type": "Feature",
  "properties": {
    "iso:country":"US",
    "sg:address":"5545 Commerce Rd",
    "sg:city":"Onalaska",
    "sg:classifiers":[
        {
            "category":"Retail",
            "subcategory":"Laundry & Dry Cleaning",
            "type":"Services"
        }
    ],
    "sg:phone":"+1 608 783 8899",
    "sg:postcode":"54650",
    "sg:province":"WI",
    "sg:tags":[
        "launderer",
        "linen",
        "industrial",
        "coin",
        "supply"
    ],
    "wof:name":"G&K Services Inc",
    "wof:placetype":"venue"
},
  "geometry": {"coordinates":[-91.245291,43.920773],"type":"Point"}
}