{
  "type": "Feature",
  "properties": {
    "addr:full":"2540 S Creek Rd Genoa WI 54624",
    "addr:housenumber":"2540",
    "addr:postcode":"54624",
    "addr:street":"S Creek Rd",
    "iso:country":"US",
    "sg:address":"2540 S Creek Rd",
    "sg:city":"Genoa",
    "sg:classifiers":[
        {
            "category":"Professional",
            "type":"Services"
        }
    ],
    "sg:phone":"+1 608 689 2048",
    "sg:postcode":"54624",
    "sg:province":"WI",
    "sg:tags":[
        "establishment"
    ],
    "wof:name":"Walnut Valley",
    "wof:placetype":"venue"
},
  "geometry": {"coordinates":[-91.151978,43.538081],"type":"Point"}
}