{
  "type": "Feature",
  "properties": {
    "addr:full":"39957 State Hwy 16 Oconomowoc WI 53066",
    "addr:housenumber":"39957",
    "addr:postcode":"53066",
    "addr:street":"State Hwy 16",
    "iso:country":"US",
    "sg:address":"39957 State Hwy 16",
    "sg:city":"Oconomowoc",
    "sg:classifiers":[
        {
            "category":"Food & Beverages",
            "subcategory":"Liquor & Beverages",
            "type":"Retail Goods"
        }
    ],
    "sg:phone":"+1 262 560 1266",
    "sg:postcode":"53066",
    "sg:province":"WI",
    "wof:name":"Big Al's House Of Fine Spirits",
    "wof:placetype":"venue"
},
  "geometry": {"coordinates":[-88.53931799999999,43.129081],"type":"Point"}
}