{
  "type": "Feature",
  "properties": {
    "iso:country":"US",
    "sg:address":"1110 18th Ave",
    "sg:city":"Monroe",
    "sg:classifiers":[
        {
            "category":"Government",
            "subcategory":"Office",
            "type":"Public Place"
        }
    ],
    "sg:phone":"+1 608 329 2536",
    "sg:postcode":"53566",
    "sg:province":"WI",
    "sg:tags":[
        "city",
        "taxation"
    ],
    "wof:name":"Monroe City Assessor",
    "wof:placetype":"venue"
},
  "geometry": {"coordinates":[-89.63737500000001,42.601027],"type":"Point"}
}