{
  "type": "Feature",
  "properties": {
    "iso:country":"US",
    "sg:address":"2206 Howland Ave",
    "sg:city":"Schofield",
    "sg:classifiers":[
        {
            "category":"Building & Trades",
            "subcategory":"Electrical",
            "type":"Services"
        }
    ],
    "sg:phone":"+1 715 359 9850",
    "sg:postcode":"54476",
    "sg:province":"WI",
    "sg:tags":[
        "electrical",
        "electric",
        "contractor"
    ],
    "wof:name":"G M Electric Inc",
    "wof:placetype":"venue"
},
  "geometry": {"coordinates":[-89.59404000000001,44.865832],"type":"Point"}
}