{
  "type": "Feature",
  "properties": {
    "iso:country":"US",
    "sg:address":"3173 Farrell Rd",
    "sg:city":"Kaukauna",
    "sg:classifiers":[
        {
            "category":"Real Estate",
            "subcategory":"Real Estate Operator",
            "type":"Services"
        }
    ],
    "sg:phone":"+1 920 766 2398",
    "sg:postcode":"54130",
    "sg:province":"WI",
    "sg:tags":[
        "property",
        "lessor"
    ],
    "wof:name":"Gerald Daul",
    "wof:placetype":"venue"
},
  "geometry": {"coordinates":[-88.242082,44.352581],"type":"Point"}
}