{
  "type": "Feature",
  "properties": {
    "iso:country":"US",
    "sg:address":"4055 Meyers Rd",
    "sg:city":"Monroe",
    "sg:classifiers":[
        {
            "category":"Organizations",
            "subcategory":"Membership Organization",
            "type":"Services"
        }
    ],
    "sg:phone":"+1 608 328 1031",
    "sg:postcode":"53566",
    "sg:province":"WI",
    "sg:tags":[
        "sell",
        "art",
        "show",
        "to",
        "promote",
        "opportunity"
    ],
    "wof:name":"Artists Alliance Green County",
    "wof:placetype":"venue"
},
  "geometry": {"coordinates":[-89.57380000000001,42.655218],"type":"Point"}
}