{
  "type": "Feature",
  "properties": {
    "addr:full":"1322 Robin Dr Stetsonville WI 54480",
    "addr:housenumber":"1322",
    "addr:postcode":"54480",
    "addr:street":"Robin Dr",
    "iso:country":"US",
    "sg:address":"1322 Robin Dr",
    "sg:city":"Stetsonville",
    "sg:classifiers":[
        {
            "category":"Farming",
            "subcategory":"Dairy Farm",
            "type":"Manufacturing & Wholesale Goods"
        }
    ],
    "sg:phone":"+1 715 678 2575",
    "sg:postcode":"54480",
    "sg:province":"WI",
    "wof:name":"Pitzke Farms",
    "wof:placetype":"venue"
},
  "geometry": {"coordinates":[-90.27912600000001,45.087829],"type":"Point"}
}