{
  "type": "Feature",
  "properties": {
    "iso:country":"US",
    "sg:address":"507 W Johnson St",
    "sg:city":"Fond Du Lac",
    "sg:classifiers":[
        {
            "category":"Home & Garden",
            "subcategory":"Household Appliances",
            "type":"Retail Goods"
        }
    ],
    "sg:phone":"+1 920 921 5386",
    "sg:postcode":"54935",
    "sg:province":"WI",
    "sg:tags":[
        "machine",
        "sewing"
    ],
    "sg:website":"www.heuerssewing.com",
    "wof:name":"Heuer's Sewing & Vacuum Ctr",
    "wof:placetype":"venue"
},
  "geometry": {"coordinates":[-88.467005,43.78434],"type":"Point"}
}