{
  "type": "Feature",
  "properties": {
    "iso:country":"US",
    "sg:address":"2222 Roosevelt Rd",
    "sg:city":"Kenosha",
    "sg:classifiers":[
        {
            "category":"Organizations",
            "subcategory":"Non-profit Organization",
            "type":"Services"
        },
        {
            "category":"Social Services",
            "type":"Services"
        }
    ],
    "sg:phone":"+1 262 658 2222",
    "sg:postcode":"53143",
    "sg:province":"WI",
    "sg:tags":[
        "alternative",
        "abortion"
    ],
    "wof:name":"Care Net Pregnancy Center",
    "wof:placetype":"venue"
},
  "geometry": {"coordinates":[-87.836596,42.57667],"type":"Point"}
}