{
  "type": "Feature",
  "properties": {
    "iso:country":"US",
    "sg:address":"6217 N 118th St",
    "sg:city":"Milwaukee",
    "sg:classifiers":[
        {
            "category":"Professional",
            "subcategory":"Business Services",
            "type":"Services"
        }
    ],
    "sg:phone":"+1 414 353 5347",
    "sg:postcode":"53225",
    "sg:province":"WI",
    "wof:name":"Able Body Painting Co",
    "wof:placetype":"venue"
},
  "geometry": {"coordinates":[-88.059048,43.131529],"type":"Point"}
}