{
  "type": "Feature",
  "properties": {
    "iso:country":"US",
    "sg:address":"1792 25th Ave",
    "sg:city":"Rice Lake",
    "sg:classifiers":[
        {
            "category":"Professional",
            "subcategory":"Management & Consulting",
            "type":"Services"
        }
    ],
    "sg:phone":"+1 715 736 1792",
    "sg:postcode":"54868",
    "sg:province":"WI",
    "wof:name":"Slender Body Solutions",
    "wof:placetype":"venue"
},
  "geometry": {"coordinates":[-91.788306,45.567257],"type":"Point"}
}