{
  "type": "Feature",
  "properties": {
    "iso:country":"US",
    "sg:address":"519 Small Farm Rd",
    "sg:city":"Mukwonago",
    "sg:classifiers":[
        {
            "category":"Professional",
            "type":"Services"
        }
    ],
    "sg:phone":"+1 262 363 4136",
    "sg:postcode":"53149",
    "sg:province":"WI",
    "sg:tags":[
        "establishment"
    ],
    "wof:name":"Walter & Walter",
    "wof:placetype":"venue"
},
  "geometry": {"coordinates":[-88.32323,42.86201],"type":"Point"}
}