{
  "type": "Feature",
  "properties": {
    "iso:country":"US",
    "sg:address":"1919 Baxter Ave",
    "sg:city":"Superior",
    "sg:classifiers":[
        {
            "category":"Manufacturing",
            "subcategory":"Tools & Machinery",
            "type":"Manufacturing & Wholesale Goods"
        }
    ],
    "sg:phone":"+1 715 392 7530",
    "sg:postcode":"54880",
    "sg:province":"WI",
    "sg:tags":[
        "mfg"
    ],
    "wof:name":"Kem Orr Odor Elimination Svc",
    "wof:placetype":"venue"
},
  "geometry": {"coordinates":[-92.095019,46.715358],"type":"Point"}
}