{
  "type": "Feature",
  "properties": {
    "iso:country":"US",
    "sg:address":"19850 W Bluemound Rd",
    "sg:city":"Brookfield",
    "sg:classifiers":[
        {
            "category":"Restaurant",
            "type":"Food & Drink"
        }
    ],
    "sg:menulink":"http://www.allmenus.com/wi/brookfield/8033-melting-pot/menu/",
    "sg:phone":"+1 262 782 6358",
    "sg:postcode":"53045",
    "sg:province":"WI",
    "sg:tags":[
        "new",
        "american"
    ],
    "wof:name":"Melting Pot",
    "wof:placetype":"venue"
},
  "geometry": {"coordinates":[-88.159237,43.036212],"type":"Point"}
}