{
  "type": "Feature",
  "properties": {
    "iso:country":"US",
    "sg:address":"6635 Lake Dr",
    "sg:city":"Shawano",
    "sg:classifiers":[
        {
            "category":"Retail",
            "subcategory":"Repair Shop",
            "type":"Services"
        }
    ],
    "sg:phone":"+1 715 745 6433",
    "sg:postcode":"54166",
    "sg:province":"WI",
    "sg:tags":[
        "consultant",
        "jewelry"
    ],
    "wof:name":"Stubies Consultants Inc",
    "wof:placetype":"venue"
},
  "geometry": {"coordinates":[-88.572312,44.796402],"type":"Point"}
}