{
  "type": "Feature",
  "properties": {
    "addr:full":"881 N Grant Ave Exeland WI 54835",
    "addr:housenumber":"881",
    "addr:postcode":"54835",
    "addr:street":"N Grant Ave",
    "iso:country":"US",
    "sg:address":"881 N Grant Ave",
    "sg:city":"Exeland",
    "sg:classifiers":[
        {
            "category":"Wholesale",
            "subcategory":"Machinery & Supplies",
            "type":"Manufacturing & Wholesale Goods"
        }
    ],
    "sg:phone":"+1 715 943 2654",
    "sg:postcode":"54835",
    "sg:province":"WI",
    "sg:tags":[
        "glass",
        "product",
        "fiber"
    ],
    "wof:name":"Fiberglass Reinforced Products",
    "wof:placetype":"venue"
},
  "geometry": {"coordinates":[-91.24242599999999,45.667917],"type":"Point"}
}