{
  "type": "Feature",
  "properties": {
    "iso:country":"US",
    "sg:address":"13137 W Glendale Ave",
    "sg:city":"Butler",
    "sg:classifiers":[
        {
            "category":"Wholesale",
            "subcategory":"Machinery & Supplies",
            "type":"Manufacturing & Wholesale Goods"
        }
    ],
    "sg:phone":"+1 262 783 4500",
    "sg:postcode":"53007",
    "sg:province":"WI",
    "sg:tags":[
        "detergent",
        "manufacturer",
        "soap",
        "chemicals-wholesale"
    ],
    "sg:website":"http://www.wausauchemical.com",
    "wof:name":"Wausau Chemical",
    "wof:placetype":"venue"
},
  "geometry": {"coordinates":[-88.075039,43.100449],"type":"Point"}
}