{
  "type": "Feature",
  "properties": {
    "addr:full":"601 Lake Ave Racine WI 53403",
    "addr:housenumber":"601",
    "addr:postcode":"53403",
    "addr:street":"Lake Ave",
    "iso:country":"US",
    "sg:address":"601 Lake Ave",
    "sg:city":"Racine",
    "sg:classifiers":[
        {
            "category":"Banks & Credit Unions",
            "subcategory":"Investment Brokerage",
            "type":"Services"
        }
    ],
    "sg:phone":"+1 262 633 8233",
    "sg:postcode":"53403",
    "sg:province":"WI",
    "sg:tags":[
        "stock",
        "bond"
    ],
    "wof:name":"Wachovia Securities",
    "wof:placetype":"venue"
},
  "geometry": {"coordinates":[-87.78142699999999,42.725969],"type":"Point"}
}