{
  "type": "Feature",
  "properties": {
    "iso:country":"US",
    "sg:address":"3601 N 11th St",
    "sg:city":"Milwaukee",
    "sg:classifiers":[
        {
            "category":"Building & Trades",
            "subcategory":"Construction",
            "type":"Services"
        }
    ],
    "sg:phone":"+1 414 264 1120",
    "sg:postcode":"53206",
    "sg:province":"WI",
    "sg:tags":[
        "interior",
        "commercial",
        "exterior",
        "painter"
    ],
    "wof:name":"Midtown Painting & Decorating",
    "wof:placetype":"venue"
},
  "geometry": {"coordinates":[-87.92476499999999,43.084498],"type":"Point"}
}