{
  "type": "Feature",
  "properties": {
    "iso:country":"US",
    "sg:address":"1926 Two Tree Ln",
    "sg:city":"Milwaukee",
    "sg:classifiers":[
        {
            "category":"Home & Garden",
            "subcategory":"Home Furnishings",
            "type":"Retail Goods"
        }
    ],
    "sg:phone":"+1 414 774 7540",
    "sg:postcode":"53213",
    "sg:province":"WI",
    "wof:name":"Jrb V LLC",
    "wof:placetype":"venue"
},
  "geometry": {"coordinates":[-87.98965800000001,43.055749],"type":"Point"}
}