{
  "type": "Feature",
  "properties": {
    "addr:full":"106 2nd Ave E Ashland WI 54806",
    "addr:housenumber":"106",
    "addr:postcode":"54806",
    "addr:street":"2Nd Ave E",
    "iso:country":"US",
    "sg:address":"106 2nd Ave E",
    "sg:city":"Ashland",
    "sg:classifiers":[
        {
            "category":"Organizations",
            "subcategory":"Religious Organization",
            "type":"Services"
        }
    ],
    "sg:phone":"+1 715 682 4523",
    "sg:postcode":"54806",
    "sg:province":"WI",
    "sg:tags":[
        "church"
    ],
    "wof:name":"Ashland Catholic Church",
    "wof:placetype":"venue"
},
  "geometry": {"coordinates":[-90.882651,46.592943],"type":"Point"}
}