{
  "type": "Feature",
  "properties": {
    "iso:country":"US",
    "sg:address":"32636 Bogus Valley Ln",
    "sg:city":"Muscoda",
    "sg:classifiers":[
        {
            "category":"Building & Trades",
            "subcategory":"Construction",
            "type":"Services"
        }
    ],
    "sg:phone":"+1 608 220 3977",
    "sg:postcode":"53573",
    "sg:province":"WI",
    "sg:tags":[
        "house"
    ],
    "wof:name":"Fraser Home Improvements",
    "wof:placetype":"venue"
},
  "geometry": {"coordinates":[-90.348133,43.230974],"type":"Point"}
}