{
  "type": "Feature",
  "properties": {
    "iso:country":"US",
    "sg:address":"1111 Gohres St",
    "sg:city":"La Crosse",
    "sg:classifiers":[
        {
            "category":"Personal",
            "subcategory":"Beauty Salon",
            "type":"Services"
        }
    ],
    "sg:phone":"+1 608 785 2020",
    "sg:postcode":"54603",
    "sg:province":"WI",
    "wof:name":"L A Hair Designers",
    "wof:placetype":"venue"
},
  "geometry": {"coordinates":[-91.239867,43.849274],"type":"Point"}
}