{
  "type": "Feature",
  "properties": {
    "iso:country":"US",
    "sg:address":"182 N Main St",
    "sg:city":"Richland Center",
    "sg:classifiers":[
        {
            "category":"Wholesale",
            "subcategory":"Farm Supplies",
            "type":"Manufacturing & Wholesale Goods"
        }
    ],
    "sg:phone":"+1 608 647 4488",
    "sg:postcode":"53581",
    "sg:province":"WI",
    "sg:tags":[
        "equipment",
        "dairy"
    ],
    "wof:name":"Agri-Dairy Service Inc",
    "wof:placetype":"venue"
},
  "geometry": {"coordinates":[-90.38661399999999,43.335522],"type":"Point"}
}