{
  "type": "Feature",
  "properties": {
    "iso:country":"US",
    "sg:address":"201 Lance Dr",
    "sg:city":"Twin Lakes",
    "sg:classifiers":[
        {
            "category":"Travel",
            "subcategory":"Hotels & Motels",
            "type":"Entertainment"
        }
    ],
    "sg:phone":"+1 262 877 2783",
    "sg:postcode":"53181",
    "sg:province":"WI",
    "wof:name":"Pink House Resort & Motel the",
    "wof:placetype":"venue"
},
  "geometry": {"coordinates":[-88.241997,42.527],"type":"Point"}
}