{
  "type": "Feature",
  "properties": {
    "iso:country":"US",
    "sg:address":"2328 W Capitol Dr",
    "sg:city":"Milwaukee",
    "sg:classifiers":[
        {
            "category":"Organizations",
            "subcategory":"Religious Organization",
            "type":"Services"
        }
    ],
    "sg:phone":"+1 414 442 4720",
    "sg:postcode":"53206",
    "sg:province":"WI",
    "wof:name":"Jerusalem Baptist Church",
    "wof:placetype":"venue"
},
  "geometry": {"coordinates":[-87.941717,43.089768],"type":"Point"}
}