{
  "type": "Feature",
  "properties": {
    "iso:country":"US",
    "sg:address":"10827 W Belmar Ave",
    "sg:city":"Maribel",
    "sg:classifiers":[
        {
            "category":"Home & Garden",
            "subcategory":"Building Materials",
            "type":"Retail Goods"
        }
    ],
    "sg:phone":"+1 920 864 7980",
    "sg:postcode":"54227",
    "sg:province":"WI",
    "sg:tags":[
        "mixed",
        "concrete"
    ],
    "wof:name":"Fred Fels Concrete Ready Mix",
    "wof:placetype":"venue"
},
  "geometry": {"coordinates":[-87.81583999999999,44.276365],"type":"Point"}
}