{
  "type": "Feature",
  "properties": {
    "iso:country":"US",
    "sg:address":"2306 North Ave",
    "sg:city":"Sheboygan",
    "sg:classifiers":[
        {
            "category":"Autos & Motor Vehicles",
            "subcategory":"Automobile Sales",
            "type":"Retail Goods"
        }
    ],
    "sg:phone":"+1 920 458 9050",
    "sg:postcode":"53083",
    "sg:province":"WI",
    "sg:tags":[
        "car",
        "used",
        "dealer"
    ],
    "wof:name":"Darrell Widder Motors Inc",
    "wof:placetype":"venue"
},
  "geometry": {"coordinates":[-87.73721399999999,43.774032],"type":"Point"}
}