{
  "type": "Feature",
  "properties": {
    "iso:country":"US",
    "sg:address":"6409 Frontage Rd",
    "sg:city":"Plainfield",
    "sg:classifiers":[
        {
            "category":"Food & Beverages",
            "subcategory":"Groceries & Convenience Stores",
            "type":"Retail Goods"
        }
    ],
    "sg:phone":"+1 715 335 6188",
    "sg:postcode":"54966",
    "sg:province":"WI",
    "wof:name":"Plainfield Truck Stop",
    "wof:placetype":"venue"
},
  "geometry": {"coordinates":[-89.524755,44.202973],"type":"Point"}
}