{
  "type": "Feature",
  "properties": {
    "iso:country":"US",
    "sg:address":"7411 Clemens Rd",
    "sg:city":"Dane",
    "sg:classifiers":[
        {
            "category":"Building & Trades",
            "subcategory":"Construction",
            "type":"Services"
        }
    ],
    "sg:phone":"+1 608 575 5396",
    "sg:postcode":"53529",
    "sg:province":"WI",
    "sg:tags":[
        "painting",
        "contractor"
    ],
    "wof:name":"Rural Paint & Paper",
    "wof:placetype":"venue"
},
  "geometry": {"coordinates":[-89.48131100000001,43.263598],"type":"Point"}
}