{
  "type": "Feature",
  "properties": {
    "iso:country":"US",
    "sg:address":"3202 26th St S",
    "sg:city":"La Crosse",
    "sg:classifiers":[
        {
            "category":"Sports & Exercise",
            "subcategory":"Race Track",
            "type":"Entertainment"
        }
    ],
    "sg:phone":"+1 608 788 2379",
    "sg:postcode":"54601",
    "sg:province":"WI",
    "sg:tags":[
        "operation",
        "racing",
        "or"
    ],
    "wof:name":"Ljj Enterprises",
    "wof:placetype":"venue"
},
  "geometry": {"coordinates":[-91.217046,43.774941],"type":"Point"}
}