{
  "type": "Feature",
  "properties": {
    "addr:full":"1445 N 124th St Elm Grove WI 53122",
    "addr:housenumber":"1445",
    "addr:postcode":"53122",
    "addr:street":"N 124Th St",
    "iso:country":"US",
    "sg:address":"1445 N 124th St",
    "sg:city":"Elm Grove",
    "sg:classifiers":[
        {
            "category":"Building & Trades",
            "subcategory":"Construction",
            "type":"Services"
        }
    ],
    "sg:phone":"+1 262 784 1026",
    "sg:postcode":"53122",
    "sg:province":"WI",
    "sg:tags":[
        "contractor"
    ],
    "wof:name":"Roofing Co of Milwaukee LLC",
    "wof:placetype":"venue"
},
  "geometry": {"coordinates":[-88.066969,43.048501],"type":"Point"}
}