{
  "type": "Feature",
  "properties": {
    "iso:country":"US",
    "sg:address":"9600 55th St",
    "sg:city":"Kenosha",
    "sg:classifiers":[
        {
            "category":"Manufacturing",
            "subcategory":"Rubber & Plastics",
            "type":"Manufacturing & Wholesale Goods"
        }
    ],
    "sg:phone":"+1 262 605 9000",
    "sg:postcode":"53144",
    "sg:province":"WI",
    "sg:tags":[
        "manufacture",
        "assembles",
        "design",
        "molded",
        "injection"
    ],
    "wof:name":"Xten Industries LLC",
    "wof:placetype":"venue"
},
  "geometry": {"coordinates":[-87.923474,42.586731],"type":"Point"}
}