{
  "type": "Feature",
  "properties": {
    "iso:country":"US",
    "sg:address":"809 Cambridge Ave",
    "sg:city":"Waukesha",
    "sg:classifiers":[
        {
            "category":"Professional",
            "type":"Services"
        },
        {
            "category":"Professional",
            "subcategory":"Advertising",
            "type":"Services"
        },
        {
            "category":"Professional",
            "subcategory":"Art Services",
            "type":"Services"
        }
    ],
    "sg:phone":"+1 262 436 0247",
    "sg:postcode":"53188",
    "sg:province":"WI",
    "sg:tags":[
        "product",
        "designer",
        "producer",
        "fair",
        "trade",
        "exposition",
        "advertising-promotional",
        "display",
        "shows"
    ],
    "wof:name":"Valley Exposition Service",
    "wof:placetype":"venue"
},
  "geometry": {"coordinates":[-88.27272499999999,43.002365],"type":"Point"}
}