{
  "type": "Feature",
  "properties": {
    "addr:full":"7041 S 27th St Franklin WI 53132",
    "addr:housenumber":"7041",
    "addr:postcode":"53132",
    "addr:street":"S 27Th St",
    "iso:country":"US",
    "sg:address":"7041 S 27th St",
    "sg:city":"Franklin",
    "sg:classifiers":[
        {
            "category":"Restaurant",
            "type":"Food & Drink"
        }
    ],
    "sg:phone":"+1 414 304 7200",
    "sg:postcode":"53132",
    "sg:province":"WI",
    "wof:name":"Omega Restaurant",
    "wof:placetype":"venue"
},
  "geometry": {"coordinates":[-87.94994699999999,42.917889],"type":"Point"}
}