{
  "type": "Feature",
  "properties": {
    "iso:country":"US",
    "sg:address":"12545 W Burleigh Blvd",
    "sg:city":"Brookfield",
    "sg:classifiers":[
        {
            "category":"Health Services",
            "subcategory":"Medical Lab",
            "type":"Services"
        }
    ],
    "sg:phone":"+1 262 827 0667",
    "sg:postcode":"53005",
    "sg:province":"WI",
    "sg:tags":[
        "detection",
        "equipment",
        "drug"
    ],
    "wof:name":"Medyx Mobile Health",
    "wof:placetype":"venue"
},
  "geometry": {"coordinates":[-88.068395,43.074455],"type":"Point"}
}