{
  "type": "Feature",
  "properties": {
    "iso:country":"US",
    "sg:address":"323 Glen Oak Ct",
    "sg:city":"Delafield",
    "sg:classifiers":[
        {
            "category":"Insurance",
            "subcategory":"Insurance Agent",
            "type":"Services"
        }
    ],
    "sg:phone":"+1 262 646 5221",
    "sg:postcode":"53018",
    "sg:province":"WI",
    "sg:tags":[
        "broker"
    ],
    "wof:name":"Star Adjusters",
    "wof:placetype":"venue"
},
  "geometry": {"coordinates":[-88.422209,43.051888],"type":"Point"}
}