{
  "type": "Feature",
  "properties": {
    "iso:country":"US",
    "sg:address":"313 Frederic St",
    "sg:city":"Cassville",
    "sg:classifiers":[
        {
            "category":"Retail",
            "subcategory":"Funeral Services",
            "type":"Services"
        }
    ],
    "sg:phone":"+1 608 725 5790",
    "sg:postcode":"53806",
    "sg:province":"WI",
    "sg:tags":[
        "director"
    ],
    "wof:name":"Martin Page Funeral Home",
    "wof:placetype":"venue"
},
  "geometry": {"coordinates":[-90.989214,42.714053],"type":"Point"}
}