{
  "type": "Feature",
  "properties": {
    "addr:full":"2402 Weston Ave Schofield WI 54476",
    "addr:housenumber":"2402",
    "addr:postcode":"54476",
    "addr:street":"Weston Ave",
    "iso:country":"US",
    "sg:address":"2402 Weston Ave",
    "sg:city":"Schofield",
    "sg:classifiers":[
        {
            "category":"Freight",
            "type":"Transportation"
        }
    ],
    "sg:phone":"+1 715 359 8248",
    "sg:postcode":"54476",
    "sg:province":"WI",
    "sg:tags":[
        "distance",
        "long",
        "trucking"
    ],
    "wof:name":"Four Seasons Express Inc",
    "wof:placetype":"venue"
},
  "geometry": {"coordinates":[-89.59452,44.887493],"type":"Point"}
}