{
  "type": "Feature",
  "properties": {
    "addr:full":"7505 Harwood Ave Milwaukee WI 53213",
    "addr:housenumber":"7505",
    "addr:postcode":"53213",
    "addr:street":"Harwood Ave",
    "iso:country":"US",
    "sg:address":"7505 Harwood Ave",
    "sg:city":"Milwaukee",
    "sg:classifiers":[
        {
            "category":"Shopping",
            "subcategory":"Discount & Variety Stores",
            "type":"Retail Goods"
        }
    ],
    "sg:phone":"+1 414 774 7440",
    "sg:postcode":"53213",
    "sg:province":"WI",
    "wof:name":"Drews V & S Variety",
    "wof:placetype":"venue"
},
  "geometry": {"coordinates":[-88.006919,43.050096],"type":"Point"}
}