{
  "type": "Feature",
  "properties": {
    "addr:full":"1120 N Mason St Appleton WI 54914",
    "addr:housenumber":"1120",
    "addr:postcode":"54914",
    "addr:street":"N Mason St",
    "iso:country":"US",
    "sg:address":"1120 N Mason St",
    "sg:city":"Appleton",
    "sg:classifiers":[
        {
            "category":"Retail",
            "subcategory":"Auto Repair",
            "type":"Services"
        }
    ],
    "sg:phone":"+1 920 739 2337",
    "sg:postcode":"54914",
    "sg:province":"WI",
    "sg:tags":[
        "repairing",
        "automobile"
    ],
    "wof:name":"Robert's Automotive Repair",
    "wof:placetype":"venue"
},
  "geometry": {"coordinates":[-88.42576800000001,44.271967],"type":"Point"}
}