{
  "type": "Feature",
  "properties": {
    "iso:country":"US",
    "sg:address":"1011 Shawano Ave",
    "sg:city":"Green Bay",
    "sg:classifiers":[
        {
            "category":"Retail",
            "subcategory":"Laundry & Dry Cleaning",
            "type":"Services"
        }
    ],
    "sg:phone":"+1 920 432 0707",
    "sg:postcode":"54303",
    "sg:province":"WI",
    "sg:tags":[
        "cleaners",
        "rug",
        "carpet"
    ],
    "wof:name":"Affordable Carpet Care",
    "wof:placetype":"venue"
},
  "geometry": {"coordinates":[-88.036168,44.521575],"type":"Point"}
}