{
  "type": "Feature",
  "properties": {
    "iso:country":"US",
    "sg:address":"764 Bragg St",
    "sg:city":"Fond Du Lac",
    "sg:classifiers":[
        {
            "category":"Real Estate",
            "subcategory":"Architect",
            "type":"Services"
        }
    ],
    "sg:phone":"+1 920 923 1174",
    "sg:postcode":"54935",
    "sg:province":"WI",
    "sg:tags":[
        "building",
        "engineering",
        "design",
        "structural"
    ],
    "wof:name":"Building Design & Engineering",
    "wof:placetype":"venue"
},
  "geometry": {"coordinates":[-88.478076,43.775202],"type":"Point"}
}