{
  "type": "Feature",
  "properties": {
    "iso:country":"US",
    "sg:address":"5141 Halle Ave",
    "sg:city":"Neillsville",
    "sg:classifiers":[
        {
            "category":"Farming",
            "subcategory":"Dairy Farm",
            "type":"Manufacturing & Wholesale Goods"
        }
    ],
    "sg:phone":"+1 715 743 4033",
    "sg:postcode":"54456",
    "sg:province":"WI",
    "wof:name":"Glen Luchterhand",
    "wof:placetype":"venue"
},
  "geometry": {"coordinates":[-90.547779,44.610946],"type":"Point"}
}