{
  "type": "Feature",
  "properties": {
    "iso:country":"US",
    "sg:address":"9213 Micke Rd",
    "sg:city":"Brillion",
    "sg:classifiers":[
        {
            "category":"Farming",
            "subcategory":"Livestock Farm",
            "type":"Manufacturing & Wholesale Goods"
        }
    ],
    "sg:phone":"+1 920 989 1924",
    "sg:postcode":"54110",
    "sg:province":"WI",
    "sg:tags":[
        "beef",
        "for",
        "crop",
        "preparation",
        "feedlot",
        "cattle",
        "market"
    ],
    "wof:name":"Micke Farms",
    "wof:placetype":"venue"
},
  "geometry": {"coordinates":[-88.163501,44.224],"type":"Point"}
}