{
  "type": "Feature",
  "properties": {
    "iso:country":"US",
    "sg:address":"711 Torke Ter",
    "sg:city":"Plymouth",
    "sg:classifiers":[
        {
            "category":"Building & Trades",
            "subcategory":"Construction",
            "type":"Services"
        }
    ],
    "sg:phone":"+1 920 892 4345",
    "sg:postcode":"53073",
    "sg:province":"WI",
    "sg:tags":[
        "concrete",
        "contractor"
    ],
    "wof:name":"Nelson Concrete Cnstr LLC",
    "wof:placetype":"venue"
},
  "geometry": {"coordinates":[-87.972627,43.756684],"type":"Point"}
}