{
  "type": "Feature",
  "properties": {
    "addr:full":"701 E Mill St Withee WI 54498",
    "addr:housenumber":"701",
    "addr:postcode":"54498",
    "addr:street":"E Mill St",
    "iso:country":"US",
    "sg:address":"701 E Mill St",
    "sg:city":"Withee",
    "sg:classifiers":[
        {
            "category":"Autos & Motor Vehicles",
            "subcategory":"Fuel & Gas Station",
            "type":"Retail Goods"
        }
    ],
    "sg:phone":"+1 715 229 2661",
    "sg:postcode":"54498",
    "sg:province":"WI",
    "sg:tags":[
        "oil"
    ],
    "wof:name":"Withee Oil Co",
    "wof:placetype":"venue"
},
  "geometry": {"coordinates":[-90.595671,44.951351],"type":"Point"}
}