{
  "type": "Feature",
  "properties": {
    "iso:country":"US",
    "sg:address":"2966 Oneida Lake Rd",
    "sg:city":"Harshaw",
    "sg:classifiers":[
        {
            "category":"Professional",
            "subcategory":"Business Services",
            "type":"Services"
        }
    ],
    "sg:phone":"+1 715 282 6530",
    "sg:postcode":"54529",
    "sg:province":"WI",
    "sg:tags":[
        "auto",
        "general",
        "repair"
    ],
    "wof:name":"Bill Zs Auto & Trck Finder Svc",
    "wof:placetype":"venue"
},
  "geometry": {"coordinates":[-89.639966,45.612597],"type":"Point"}
}