{
  "type": "Feature",
  "properties": {
    "iso:country":"US",
    "sg:address":"510 Partridge Ct",
    "sg:city":"Pewaukee",
    "sg:classifiers":[
        {
            "category":"Building & Trades",
            "subcategory":"Construction",
            "type":"Services"
        }
    ],
    "sg:phone":"+1 262 844 2696",
    "sg:postcode":"53072",
    "sg:province":"WI",
    "sg:tags":[
        "roofing",
        "contractor"
    ],
    "wof:name":"Star Lake County Home",
    "wof:placetype":"venue"
},
  "geometry": {"coordinates":[-88.265723,43.089999],"type":"Point"}
}