{
  "type": "Feature",
  "properties": {
    "addr:full":"151 S University Dr West Bend WI 53095",
    "addr:housenumber":"151",
    "addr:postcode":"53095",
    "addr:street":"S University Dr",
    "iso:country":"US",
    "sg:address":"151 S University Dr",
    "sg:city":"West Bend",
    "sg:classifiers":[
        {
            "category":"Banks & Credit Unions",
            "subcategory":"Bank",
            "type":"Services"
        }
    ],
    "sg:phone":"+1 262 338 0607",
    "sg:postcode":"53095",
    "sg:province":"WI",
    "sg:tags":[
        "loan",
        "real estate"
    ],
    "wof:name":"Option Home Lending",
    "wof:placetype":"venue"
},
  "geometry": {"coordinates":[-88.211011,43.421962],"type":"Point"}
}