{
  "type": "Feature",
  "properties": {
    "iso:country":"US",
    "sg:address":"6450 Hackett Rd",
    "sg:city":"Hawkins",
    "sg:classifiers":[
        {
            "category":"Real Estate",
            "subcategory":"Real Estate Agent",
            "type":"Services"
        }
    ],
    "sg:phone":"+1 715 322 5222",
    "sg:postcode":"54530",
    "sg:province":"WI",
    "sg:website":"www.kaiserrealestate.com",
    "wof:name":"Kaiser Realty Inc",
    "wof:placetype":"venue"
},
  "geometry": {"coordinates":[-90.801937,45.519295],"type":"Point"}
}