{
  "type": "Feature",
  "properties": {
    "iso:country":"US",
    "sg:address":"350 N Stephenson Ave",
    "sg:city":"Peshtigo",
    "sg:classifiers":[
        {
            "category":"Education",
            "subcategory":"School",
            "type":"Public Place"
        }
    ],
    "sg:phone":"+1 715 582 1175",
    "sg:postcode":"54157",
    "sg:province":"WI",
    "wof:name":"River Cities Christian School",
    "wof:placetype":"venue"
},
  "geometry": {"coordinates":[-87.738596,45.058689],"type":"Point"}
}