{
  "type": "Feature",
  "properties": {
    "addr:full":"7501 S Howell Ave Oak Creek WI 53154",
    "addr:housenumber":"7501",
    "addr:postcode":"53154",
    "addr:street":"S Howell Ave",
    "iso:country":"US",
    "sg:address":"7501 S Howell Ave",
    "sg:city":"Oak Creek",
    "sg:classifiers":[
        {
            "category":"Sports & Exercise",
            "subcategory":"Bowling",
            "type":"Entertainment"
        }
    ],
    "sg:phone":"+1 414 764 1120",
    "sg:postcode":"53154",
    "sg:province":"WI",
    "sg:tags":[
        "drinking",
        "center"
    ],
    "sg:website":"www.bowlcec.com",
    "wof:name":"Classic Lanes Oak Creek",
    "wof:placetype":"venue"
},
  "geometry": {"coordinates":[-87.911337,42.906899],"type":"Point"}
}