{
  "type": "Feature",
  "properties": {
    "iso:country":"US",
    "sg:address":"4241 Goleys Ln",
    "sg:city":"Racine",
    "sg:classifiers":[
        {
            "category":"Recreation",
            "type":"Entertainment"
        }
    ],
    "sg:phone":"+1 262 639 4631",
    "sg:postcode":"53404",
    "sg:province":"WI",
    "sg:tags":[
        "guide"
    ],
    "wof:name":"John Gross",
    "wof:placetype":"venue"
},
  "geometry": {"coordinates":[-87.814886,42.773341],"type":"Point"}
}