{
  "type": "Feature",
  "properties": {
    "iso:country":"US",
    "sg:address":"1747 Center Ave",
    "sg:city":"Janesville",
    "sg:classifiers":[
        {
            "category":"Autos & Motor Vehicles",
            "subcategory":"Fuel & Gas Station",
            "type":"Retail Goods"
        }
    ],
    "sg:phone":"+1 608 752 5980",
    "sg:postcode":"53546",
    "sg:province":"WI",
    "sg:tags":[
        "station",
        "gasoline"
    ],
    "wof:name":"Shell Express Mart",
    "wof:placetype":"venue"
},
  "geometry": {"coordinates":[-89.031126,42.65596],"type":"Point"}
}