{
  "type": "Feature",
  "properties": {
    "iso:country":"US",
    "sg:address":"110 S Dickinson St",
    "sg:city":"Madison",
    "sg:classifiers":[
        {
            "category":"Manufacturing",
            "subcategory":"Tools & Machinery",
            "type":"Manufacturing & Wholesale Goods"
        }
    ],
    "sg:phone":"+1 608 257 2225",
    "sg:postcode":"53703",
    "sg:province":"WI",
    "sg:tags":[
        "water",
        "heater"
    ],
    "sg:website":"www.bockwaterheaters.com",
    "wof:name":"Bock Corp",
    "wof:placetype":"venue"
},
  "geometry": {"coordinates":[-89.36302499999999,43.087442],"type":"Point"}
}