{
  "type": "Feature",
  "properties": {
    "iso:country":"US",
    "sg:address":"13003 US Hwy 151",
    "sg:city":"Valders",
    "sg:classifiers":[
        {
            "category":"Building & Trades",
            "subcategory":"Construction",
            "type":"Services"
        }
    ],
    "sg:phone":"+1 920 775 9212",
    "sg:postcode":"54245",
    "sg:province":"WI",
    "sg:tags":[
        "contractor"
    ],
    "wof:name":"Devooght House & Bldg Movers",
    "wof:placetype":"venue"
},
  "geometry": {"coordinates":[-87.847717,44.075991],"type":"Point"}
}