{
  "type": "Feature",
  "properties": {
    "addr:full":"101 Verburg St Cambridge WI 53523",
    "addr:housenumber":"101",
    "addr:postcode":"53523",
    "addr:street":"Verburg St",
    "iso:country":"US",
    "sg:address":"101 Verburg St",
    "sg:city":"Cambridge",
    "sg:classifiers":[
        {
            "category":"Freight",
            "type":"Transportation"
        }
    ],
    "sg:phone":"+1 608 423 4967",
    "sg:postcode":"53523",
    "sg:province":"WI",
    "sg:tags":[
        "commercial",
        "storage"
    ],
    "wof:name":"Wolf's Mini Storage",
    "wof:placetype":"venue"
},
  "geometry": {"coordinates":[-89.015129,43.012184],"type":"Point"}
}