{
  "type": "Feature",
  "properties": {
    "iso:country":"US",
    "sg:address":"2818 N 23rd St",
    "sg:city":"Milwaukee",
    "sg:classifiers":[
        {
            "category":"Organizations",
            "subcategory":"Religious Organization",
            "type":"Services"
        }
    ],
    "sg:phone":"+1 414 444 6090",
    "sg:postcode":"53206",
    "sg:province":"WI",
    "sg:tags":[
        "school",
        "church"
    ],
    "wof:name":"Emmaus Lutheran Church School",
    "wof:placetype":"venue"
},
  "geometry": {"coordinates":[-87.94108799999999,43.071149],"type":"Point"}
}