{
  "type": "Feature",
  "properties": {
    "iso:country":"US",
    "sg:address":"2432 Maple Grove School Rd",
    "sg:city":"Oconto",
    "sg:classifiers":[
        {
            "category":"Farming",
            "subcategory":"Dairy Farm",
            "type":"Manufacturing & Wholesale Goods"
        }
    ],
    "sg:phone":"+1 920 834 5359",
    "sg:postcode":"54153",
    "sg:province":"WI",
    "wof:name":"Fourway Farms",
    "wof:placetype":"venue"
},
  "geometry": {"coordinates":[-87.88006799999999,44.935526],"type":"Point"}
}