{
  "type": "Feature",
  "properties": {
    "addr:full":"1002 Superior Ave Tomah WI 54660",
    "addr:housenumber":"1002",
    "addr:postcode":"54660",
    "addr:street":"Superior Ave",
    "iso:country":"US",
    "sg:address":"1002 Superior Ave",
    "sg:city":"Tomah",
    "sg:classifiers":[
        {
            "category":"Government",
            "subcategory":"Office",
            "type":"Public Place"
        }
    ],
    "sg:phone":"+1 608 372 7291",
    "sg:postcode":"54660",
    "sg:province":"WI",
    "wof:name":"Monroe County Nutrition",
    "wof:placetype":"venue"
},
  "geometry": {"coordinates":[-90.5047,43.97774],"type":"Point"}
}