{
  "type": "Feature",
  "properties": {
    "iso:country":"US",
    "sg:address":"4001 Mandrake Rd",
    "sg:city":"Madison",
    "sg:classifiers":[
        {
            "category":"Organizations",
            "subcategory":"Religious Organization",
            "type":"Services"
        }
    ],
    "sg:phone":"+1 608 244 6181",
    "sg:postcode":"53704",
    "sg:province":"WI",
    "wof:name":"Lakeview Lutheran Church",
    "wof:placetype":"venue"
},
  "geometry": {"coordinates":[-89.378051,43.140214],"type":"Point"}
}