{
  "type": "Feature",
  "properties": {
    "addr:full":"537 E 3rd St Owen WI 54460",
    "addr:housenumber":"537",
    "addr:postcode":"54460",
    "addr:street":"E 3Rd St",
    "iso:country":"US",
    "sg:address":"537 E 3rd St",
    "sg:city":"Owen",
    "sg:classifiers":[
        {
            "category":"Organizations",
            "subcategory":"Non-profit Organization",
            "type":"Services"
        }
    ],
    "sg:phone":"+1 715 229 2547",
    "sg:postcode":"54460",
    "sg:province":"WI",
    "sg:tags":[
        "action",
        "agency",
        "community"
    ],
    "wof:name":"Indianhead Community Action",
    "wof:placetype":"venue"
},
  "geometry": {"coordinates":[-90.558283,44.947677],"type":"Point"}
}