{
  "type": "Feature",
  "properties": {
    "iso:country":"US",
    "sg:address":"14 Beaver Dam St",
    "sg:city":"Waupun",
    "sg:classifiers":[
        {
            "category":"Health Services",
            "subcategory":"Doctor",
            "type":"Services"
        }
    ],
    "sg:phone":"+1 920 324 9797",
    "sg:postcode":"53963",
    "sg:province":"WI",
    "sg:tags":[
        "physician",
        "surgeon"
    ],
    "wof:name":"Angesian Healthcare",
    "wof:placetype":"venue"
},
  "geometry": {"coordinates":[-88.74491999999999,43.632976],"type":"Point"}
}