{
  "type": "Feature",
  "properties": {
    "iso:country":"US",
    "sg:address":"1402 Parkside Dr",
    "sg:city":"Madison",
    "sg:classifiers":[
        {
            "category":"Freight",
            "type":"Transportation"
        }
    ],
    "sg:phone":"+1 608 244 5030",
    "sg:postcode":"53704",
    "sg:province":"WI",
    "sg:tags":[
        "commercial",
        "storage"
    ],
    "wof:name":"East Towne Storage Ctr",
    "wof:placetype":"venue"
},
  "geometry": {"coordinates":[-89.315291,43.119894],"type":"Point"}
}