{
  "type": "Feature",
  "properties": {
    "iso:country":"US",
    "sg:address":"104 13th St",
    "sg:city":"Hudson",
    "sg:classifiers":[
        {
            "category":"Professional",
            "subcategory":"Business Services",
            "type":"Services"
        }
    ],
    "sg:phone":"+1 715 386 7067",
    "sg:postcode":"54016",
    "sg:province":"WI",
    "wof:name":"Kast Assoc",
    "wof:placetype":"venue"
},
  "geometry": {"coordinates":[-92.74145,44.972758],"type":"Point"}
}