{
  "type": "Feature",
  "properties": {
    "addr:full":"140 Rainbow Ridge Oak Creek WI 53154",
    "addr:housenumber":"140",
    "addr:postcode":"53154",
    "addr:street":"Rainbow Ridge",
    "iso:country":"US",
    "sg:address":"140 Rainbow Ridge",
    "sg:city":"Oak Creek",
    "sg:classifiers":[
        {
            "category":"Professional",
            "subcategory":"Management & Consulting",
            "type":"Services"
        }
    ],
    "sg:phone":"+1 414 571 9900",
    "sg:postcode":"53154",
    "sg:province":"WI",
    "sg:tags":[
        "training",
        "business",
        "i",
        "custom",
        "computer",
        "software"
    ],
    "wof:name":"Quality Services 9000 Inc",
    "wof:placetype":"venue"
},
  "geometry": {"coordinates":[-87.91579400000001,42.888465],"type":"Point"}
}