{
  "type": "Feature",
  "properties": {
    "addr:full":"3998 North Rd Markesan WI 53946",
    "addr:housenumber":"3998",
    "addr:postcode":"53946",
    "addr:street":"North Rd",
    "iso:country":"US",
    "sg:address":"3998 North Rd",
    "sg:city":"Markesan",
    "sg:classifiers":[
        {
            "category":"Farming",
            "subcategory":"Dairy Farm",
            "type":"Manufacturing & Wholesale Goods"
        }
    ],
    "sg:phone":"+1 920 398 3574",
    "sg:postcode":"53946",
    "sg:province":"WI",
    "wof:name":"A & B Dairy",
    "wof:placetype":"venue"
},
  "geometry": {"coordinates":[-89.08561,43.715683],"type":"Point"}
}