{
  "type": "Feature",
  "properties": {
    "iso:country":"US",
    "sg:address":"2426 Forest Manor Ct",
    "sg:city":"Neenah",
    "sg:classifiers":[
        {
            "category":"Professional",
            "subcategory":"Management & Consulting",
            "type":"Services"
        }
    ],
    "sg:phone":"+1 920 725 0365",
    "sg:postcode":"54956",
    "sg:province":"WI",
    "wof:name":"R B Hospitality LLC",
    "wof:placetype":"venue"
},
  "geometry": {"coordinates":[-88.469838,44.152134],"type":"Point"}
}