{
  "type": "Feature",
  "properties": {
    "iso:country":"US",
    "sg:address":"1756 Michigan St",
    "sg:city":"Sturgeon Bay",
    "sg:classifiers":[
        {
            "category":"Organizations",
            "subcategory":"Religious Organization",
            "type":"Services"
        }
    ],
    "sg:phone":"+1 920 743 7750",
    "sg:postcode":"54235",
    "sg:province":"WI",
    "sg:tags":[
        "church"
    ],
    "wof:name":"Prince Peace Lutheran Church",
    "wof:placetype":"venue"
},
  "geometry": {"coordinates":[-87.352697,44.835131],"type":"Point"}
}