{
  "type": "Feature",
  "properties": {
    "iso:country":"US",
    "sg:address":"910 S 11th Ave",
    "sg:city":"Wausau",
    "sg:classifiers":[
        {
            "category":"Retail",
            "subcategory":"Animal Services",
            "type":"Services"
        }
    ],
    "sg:phone":"+1 715 848 1104",
    "sg:postcode":"54401",
    "sg:province":"WI",
    "wof:name":"TLC Grooming",
    "wof:placetype":"venue"
},
  "geometry": {"coordinates":[-89.649092,44.950295],"type":"Point"}
}