{
  "type": "Feature",
  "properties": {
    "iso:country":"US",
    "sg:address":"1221 Whipple St",
    "sg:city":"Eau Claire",
    "sg:classifiers":[
        {
            "category":"Health Services",
            "subcategory":"Clinic",
            "type":"Services"
        }
    ],
    "sg:phone":"+1 715 838 3311",
    "sg:postcode":"54702",
    "sg:province":"WI",
    "sg:tags":[
        "agency",
        "welfare"
    ],
    "sg:website":"www.luthermidelfort.org",
    "wof:name":"Luther Midelfort-Mayo Health",
    "wof:placetype":"venue"
},
  "geometry": {"coordinates":[-91.51346100000001,44.813356],"type":"Point"}
}