{
  "type": "Feature",
  "properties": {
    "iso:country":"US",
    "sg:address":"1310 Brocoin Way",
    "sg:city":"Green Bay",
    "sg:classifiers":[
        {
            "category":"Freight",
            "type":"Transportation"
        }
    ],
    "sg:phone":"+1 920 498 9740",
    "sg:postcode":"54304",
    "sg:province":"WI",
    "sg:tags":[
        "operator",
        "local",
        "trucking"
    ],
    "wof:name":"Little Horse Trucking LLC",
    "wof:placetype":"venue"
},
  "geometry": {"coordinates":[-88.106435,44.519403],"type":"Point"}
}