{
  "type": "Feature",
  "properties": {
    "iso:country":"US",
    "sg:address":"5102 Douglas Ave",
    "sg:city":"Racine",
    "sg:classifiers":[
        {
            "category":"Manufacturing",
            "subcategory":"Rubber & Plastics",
            "type":"Manufacturing & Wholesale Goods"
        }
    ],
    "sg:phone":"+1 262 639 3941",
    "sg:postcode":"53402",
    "sg:province":"WI",
    "sg:tags":[
        "injection",
        "component"
    ],
    "wof:name":"Fred Knapp Engraving Company",
    "wof:placetype":"venue"
},
  "geometry": {"coordinates":[-87.810598,42.787551],"type":"Point"}
}