{
  "type": "Feature",
  "properties": {
    "iso:country":"US",
    "sg:address":"7647 Helmar Rd",
    "sg:city":"Minocqua",
    "sg:classifiers":[
        {
            "category":"Travel",
            "subcategory":"Hotels & Motels",
            "type":"Entertainment"
        }
    ],
    "sg:phone":"+1 715 356 7084",
    "sg:postcode":"54548",
    "sg:province":"WI",
    "sg:tags":[
        "resort"
    ],
    "wof:name":"Bellen Terre Resort",
    "wof:placetype":"venue"
},
  "geometry": {"coordinates":[-89.74632699999999,45.834764],"type":"Point"}
}