{
  "type": "Feature",
  "properties": {
    "iso:country":"US",
    "sg:address":"1421 Gilson St",
    "sg:city":"Madison",
    "sg:classifiers":[
        {
            "category":"Building & Trades",
            "subcategory":"Construction",
            "type":"Services"
        }
    ],
    "sg:phone":"+1 608 256 2388",
    "sg:postcode":"53715",
    "sg:province":"WI",
    "sg:tags":[
        "roofing",
        "contractor"
    ],
    "wof:name":"Tilsen Roofing Co Inc",
    "wof:placetype":"venue"
},
  "geometry": {"coordinates":[-89.391279,43.051021],"type":"Point"}
}