{
  "type": "Feature",
  "properties": {
    "iso:country":"US",
    "sg:address":"2405 W Main St",
    "sg:city":"Merrill",
    "sg:classifiers":[
        {
            "category":"Personal",
            "type":"Services"
        }
    ],
    "sg:phone":"+1 715 536 3847",
    "sg:postcode":"54452",
    "sg:province":"WI",
    "wof:name":"Kathy & Cals Club 64",
    "wof:placetype":"venue"
},
  "geometry": {"coordinates":[-89.734573,45.176804],"type":"Point"}
}