{
  "type": "Feature",
  "properties": {
    "addr:full":"420 W Whitefish Rd Port Washington WI 53074",
    "addr:housenumber":"420",
    "addr:postcode":"53074",
    "addr:street":"W Whitefish Rd",
    "iso:country":"US",
    "sg:address":"420 W Whitefish Rd",
    "sg:city":"Port Washington",
    "sg:classifiers":[
        {
            "category":"Organizations",
            "subcategory":"Religious Organization",
            "type":"Services"
        }
    ],
    "sg:phone":"+1 262 284 5411",
    "sg:postcode":"53074",
    "sg:province":"WI",
    "sg:tags":[
        "church"
    ],
    "sg:website":"www.christkingonline.org",
    "wof:name":"Christ The King Lutheran Chr",
    "wof:placetype":"venue"
},
  "geometry": {"coordinates":[-87.87588100000001,43.400576],"type":"Point"}
}