{
  "type": "Feature",
  "properties": {
    "addr:full":"6651 Co Rd J Plover WI 54467",
    "addr:housenumber":"6651",
    "addr:postcode":"54467",
    "addr:street":"Co Rd",
    "iso:country":"US",
    "sg:address":"6651 Co Rd J",
    "sg:city":"Plover",
    "sg:classifiers":[
        {
            "category":"Retail",
            "subcategory":"Animal Services",
            "type":"Services"
        }
    ],
    "sg:phone":"+1 715 295 9752",
    "sg:postcode":"54467",
    "sg:province":"WI",
    "sg:tags":[
        "pet",
        "boarding",
        "sitting"
    ],
    "wof:name":"Reliable House & Sitting Svc",
    "wof:placetype":"venue"
},
  "geometry": {"coordinates":[-89.433081,44.378789],"type":"Point"}
}