{
  "type": "Feature",
  "properties": {
    "iso:country":"US",
    "sg:address":"10404 W Fountain Ave",
    "sg:city":"Milwaukee",
    "sg:classifiers":[
        {
            "category":"Communications",
            "type":"Services"
        }
    ],
    "sg:phone":"+1 414 354 5115",
    "sg:postcode":"53224",
    "sg:province":"WI",
    "wof:name":"Jeah Communications LLC",
    "wof:placetype":"venue"
},
  "geometry": {"coordinates":[-88.040181,43.157417],"type":"Point"}
}