{
  "type": "Feature",
  "properties": {
    "iso:country":"US",
    "sg:address":"10593 Cascade Mountain Rd",
    "sg:city":"Portage",
    "sg:classifiers":[
        {
            "category":"Freight",
            "type":"Transportation"
        }
    ],
    "sg:phone":"+1 608 745 3388",
    "sg:postcode":"53901",
    "sg:province":"WI",
    "sg:tags":[
        "shipping",
        "agent"
    ],
    "wof:name":"Ship Rec",
    "wof:placetype":"venue"
},
  "geometry": {"coordinates":[-89.521727,43.507137],"type":"Point"}
}