{
  "type": "Feature",
  "properties": {
    "iso:country":"US",
    "sg:address":"195 W Court St",
    "sg:city":"Richland Center",
    "sg:classifiers":[
        {
            "category":"Banks & Credit Unions",
            "subcategory":"Investment Brokerage",
            "type":"Services"
        }
    ],
    "sg:phone":"+1 608 647 8467",
    "sg:postcode":"53581",
    "sg:province":"WI",
    "sg:tags":[
        "security"
    ],
    "wof:name":"Rcb Investments Inc",
    "wof:placetype":"venue"
},
  "geometry": {"coordinates":[-90.385783,43.335434],"type":"Point"}
}