{
  "type": "Feature",
  "properties": {
    "iso:country":"US",
    "sg:address":"311 S Concord Ave",
    "sg:city":"Watertown",
    "sg:classifiers":[
        {
            "category":"Insurance",
            "subcategory":"Insurance Agent",
            "type":"Services"
        }
    ],
    "sg:phone":"+1 920 261 1346",
    "sg:postcode":"53094",
    "sg:province":"WI",
    "wof:name":"Al Moran Insurance",
    "wof:placetype":"venue"
},
  "geometry": {"coordinates":[-88.705174,43.182788],"type":"Point"}
}