{
  "type": "Feature",
  "properties": {
    "iso:country":"US",
    "sg:address":"130 Washington Ave",
    "sg:city":"Wisconsin Dells",
    "sg:classifiers":[
        {
            "category":"Bars & Pubs",
            "type":"Food & Drink"
        }
    ],
    "sg:phone":"+1 608 253 2255",
    "sg:postcode":"53965",
    "sg:province":"WI",
    "wof:name":"Firehouse",
    "wof:placetype":"venue"
},
  "geometry": {"coordinates":[-89.775885,43.626007],"type":"Point"}
}