{
  "type": "Feature",
  "properties": {
    "iso:country":"US",
    "sg:address":"1102 Spaight St",
    "sg:city":"Madison",
    "sg:classifiers":[
        {
            "category":"Organizations",
            "subcategory":"Non-profit Organization",
            "type":"Services"
        }
    ],
    "sg:phone":"+1 608 251 6007",
    "sg:postcode":"53703",
    "sg:province":"WI",
    "wof:name":"Walden Homes LTD",
    "wof:placetype":"venue"
},
  "geometry": {"coordinates":[-89.362696,43.081975],"type":"Point"}
}