{
  "type": "Feature",
  "properties": {
    "iso:country":"US",
    "sg:address":"1946 S Stoughton Rd",
    "sg:city":"Madison",
    "sg:classifiers":[
        {
            "category":"Home & Garden",
            "subcategory":"Building Materials",
            "type":"Retail Goods"
        }
    ],
    "sg:phone":"+1 608 226 0602",
    "sg:postcode":"53716",
    "sg:province":"WI",
    "sg:tags":[
        "paint"
    ],
    "wof:name":"Sherwin-Williams Paints",
    "wof:placetype":"venue"
},
  "geometry": {"coordinates":[-89.30992500000001,43.072664],"type":"Point"}
}