{
  "type": "Feature",
  "properties": {
    "iso:country":"US",
    "sg:address":"2815 S 171st St",
    "sg:city":"New Berlin",
    "sg:classifiers":[
        {
            "category":"Manufacturing",
            "subcategory":"Tools & Machinery",
            "type":"Manufacturing & Wholesale Goods"
        }
    ],
    "sg:phone":"+1 262 938 0938",
    "sg:postcode":"53151",
    "sg:province":"WI",
    "sg:tags":[
        "equipment",
        "original",
        "mfg"
    ],
    "wof:name":"Howe Industries Inc",
    "wof:placetype":"venue"
},
  "geometry": {"coordinates":[-88.126172,42.991699],"type":"Point"}
}