{
  "type": "Feature",
  "properties": {
    "addr:full":"435 N Main St Oshkosh WI 54901",
    "addr:housenumber":"435",
    "addr:postcode":"54901",
    "addr:street":"N Main St",
    "iso:country":"US",
    "sg:address":"435 N Main St",
    "sg:city":"Oshkosh",
    "sg:classifiers":[
        {
            "category":"Shopping",
            "subcategory":"Shoes",
            "type":"Retail Goods"
        }
    ],
    "sg:phone":"+1 920 235 5520",
    "sg:postcode":"54901",
    "sg:province":"WI",
    "wof:name":"The Bootery",
    "wof:placetype":"venue"
},
  "geometry": {"coordinates":[-88.537601,44.019584],"type":"Point"}
}