{
  "type": "Feature",
  "properties": {
    "iso:country":"US",
    "sg:address":"322 Mulberry St",
    "sg:city":"Lake Mills",
    "sg:classifiers":[
        {
            "category":"Building & Trades",
            "subcategory":"Construction",
            "type":"Services"
        }
    ],
    "sg:phone":"+1 920 648 8421",
    "sg:postcode":"53551",
    "sg:province":"WI",
    "sg:tags":[
        "contractor"
    ],
    "wof:name":"Klosset Kompany",
    "wof:placetype":"venue"
},
  "geometry": {"coordinates":[-88.908166,43.081345],"type":"Point"}
}