{
  "type": "Feature",
  "properties": {
    "addr:full":"1280 W Main St Sun Prairie WI 53590",
    "addr:housenumber":"1280",
    "addr:postcode":"53590",
    "addr:street":"W Main St",
    "iso:country":"US",
    "sg:address":"1280 W Main St",
    "sg:city":"Sun Prairie",
    "sg:classifiers":[
        {
            "category":"Personal",
            "subcategory":"Beauty Salon",
            "type":"Services"
        }
    ],
    "sg:phone":"+1 608 834 9055",
    "sg:postcode":"53590",
    "sg:province":"WI",
    "wof:name":"Skin Deep",
    "wof:placetype":"venue"
},
  "geometry": {"coordinates":[-89.235489,43.179546],"type":"Point"}
}