{
  "type": "Feature",
  "properties": {
    "addr:full":"1717 E Calumet St Appleton WI 54915",
    "addr:housenumber":"1717",
    "addr:postcode":"54915",
    "addr:street":"E Calumet St",
    "iso:country":"US",
    "sg:address":"1717 E Calumet St",
    "sg:city":"Appleton",
    "sg:classifiers":[
        {
            "category":"Personal",
            "subcategory":"Beauty Salon",
            "type":"Services"
        }
    ],
    "sg:phone":"+1 920 730 8887",
    "sg:postcode":"54915",
    "sg:province":"WI",
    "sg:tags":[
        "shop"
    ],
    "wof:name":"Accent On Style LTD",
    "wof:placetype":"venue"
},
  "geometry": {"coordinates":[-88.3764,44.243927],"type":"Point"}
}