{
  "type": "Feature",
  "properties": {
    "iso:country":"US",
    "sg:address":"388 Park St",
    "sg:city":"Oregon",
    "sg:classifiers":[
        {
            "category":"Building & Trades",
            "subcategory":"Construction",
            "type":"Services"
        }
    ],
    "sg:phone":"+1 608 835 3441",
    "sg:postcode":"53575",
    "sg:province":"WI",
    "sg:tags":[
        "marking",
        "maintenance",
        "parking"
    ],
    "wof:name":"Oregon Public Works",
    "wof:placetype":"venue"
},
  "geometry": {"coordinates":[-89.375962,42.923685],"type":"Point"}
}