{
  "type": "Feature",
  "properties": {
    "addr:full":"238 E Main St Chilton WI 53014",
    "addr:housenumber":"238",
    "addr:postcode":"53014",
    "addr:street":"E Main St",
    "iso:country":"US",
    "sg:address":"238 E Main St",
    "sg:city":"Chilton",
    "sg:classifiers":[
        {
            "category":"Shopping",
            "subcategory":"Used Merchandise",
            "type":"Retail Goods"
        }
    ],
    "sg:phone":"+1 920 849 4990",
    "sg:postcode":"53014",
    "sg:province":"WI",
    "sg:tags":[
        "antique"
    ],
    "wof:name":"Attic Treasures",
    "wof:placetype":"venue"
},
  "geometry": {"coordinates":[-88.15526,44.032966],"type":"Point"}
}