{
  "type": "Feature",
  "properties": {
    "addr:full":"5813 Sandhill Dr Middleton WI 53562",
    "addr:housenumber":"5813",
    "addr:postcode":"53562",
    "addr:street":"Sandhill Dr",
    "iso:country":"US",
    "sg:address":"5813 Sandhill Dr",
    "sg:city":"Middleton",
    "sg:classifiers":[
        {
            "category":"Professional",
            "subcategory":"Research",
            "type":"Services"
        }
    ],
    "sg:phone":"+1 608 836 9361",
    "sg:postcode":"53562",
    "sg:province":"WI",
    "sg:tags":[
        "development",
        "electronic"
    ],
    "wof:name":"MTG",
    "wof:placetype":"venue"
},
  "geometry": {"coordinates":[-89.476872,43.121024],"type":"Point"}
}