{
  "type": "Feature",
  "properties": {
    "iso:country":"US",
    "sg:address":"1440 Main St",
    "sg:city":"Racine",
    "sg:classifiers":[
        {
            "category":"Real Estate",
            "subcategory":"Real Estate Operator",
            "type":"Services"
        }
    ],
    "sg:phone":"+1 262 554 0208",
    "sg:postcode":"53403",
    "sg:province":"WI",
    "sg:tags":[
        "apartment"
    ],
    "wof:name":"Wolf Bldg/Anna B Apartments",
    "wof:placetype":"venue"
},
  "geometry": {"coordinates":[-87.782551,42.71467],"type":"Point"}
}