{
  "type": "Feature",
  "properties": {
    "iso:country":"US",
    "sg:address":"7247 Co Hwy B",
    "sg:city":"Chippewa Falls",
    "sg:classifiers":[
        {
            "category":"Farming",
            "subcategory":"Livestock Farm",
            "type":"Manufacturing & Wholesale Goods"
        }
    ],
    "sg:phone":"+1 715 288 6155",
    "sg:postcode":"54729",
    "sg:province":"WI",
    "sg:tags":[
        "beef",
        "feedlot",
        "cattle"
    ],
    "wof:name":"Robert Michels",
    "wof:placetype":"venue"
},
  "geometry": {"coordinates":[-91.536125,45.001629],"type":"Point"}
}