{
  "type": "Feature",
  "properties": {
    "addr:full":"405 Wallace St Combined Locks WI 54113",
    "addr:housenumber":"405",
    "addr:postcode":"54113",
    "addr:street":"Wallace St",
    "iso:country":"US",
    "sg:address":"405 Wallace St",
    "sg:city":"Combined Locks",
    "sg:classifiers":[
        {
            "category":"Professional",
            "subcategory":"Management & Consulting",
            "type":"Services"
        }
    ],
    "sg:phone":"+1 920 788 7744",
    "sg:postcode":"54113",
    "sg:province":"WI",
    "sg:tags":[
        "executive"
    ],
    "wof:name":"Wisconsin Public Service Corp",
    "wof:placetype":"venue"
},
  "geometry": {"coordinates":[-88.30605199999999,44.26653],"type":"Point"}
}