{
  "type": "Feature",
  "properties": {
    "iso:country":"US",
    "sg:address":"3560 Hillside Rd",
    "sg:city":"Slinger",
    "sg:classifiers":[
        {
            "category":"Building & Trades",
            "subcategory":"Landscaping Services",
            "type":"Services"
        }
    ],
    "sg:phone":"+1 262 644 8332",
    "sg:postcode":"53086",
    "sg:province":"WI",
    "wof:name":"Countryside Landscaping",
    "wof:placetype":"venue"
},
  "geometry": {"coordinates":[-88.240875,43.320843],"type":"Point"}
}