{
  "type": "Feature",
  "properties": {
    "iso:country":"US",
    "sg:address":"2701 N 76th St",
    "sg:city":"Milwaukee",
    "sg:classifiers":[
        {
            "category":"Wholesale",
            "subcategory":"Tobacco Products",
            "type":"Manufacturing & Wholesale Goods"
        }
    ],
    "sg:phone":"+1 414 456 0663",
    "sg:postcode":"53222",
    "sg:province":"WI",
    "sg:tags":[
        "cigarette"
    ],
    "wof:name":"Cigarette Depot",
    "wof:placetype":"venue"
},
  "geometry": {"coordinates":[-88.007436,43.068953],"type":"Point"}
}