{
  "type": "Feature",
  "properties": {
    "iso:country":"US",
    "sg:address":"1207 Main Ave",
    "sg:city":"Sheboygan",
    "sg:classifiers":[
        {
            "category":"Organizations",
            "subcategory":"Labor Organization",
            "type":"Services"
        }
    ],
    "sg:phone":"+1 920 459 7383",
    "sg:postcode":"53083",
    "sg:province":"WI",
    "wof:name":"American Federation-State Empl",
    "wof:placetype":"venue"
},
  "geometry": {"coordinates":[-87.720601,43.772912],"type":"Point"}
}