{
  "type": "Feature",
  "properties": {
    "addr:full":"7723 N Mariners St Milwaukee WI 53224",
    "addr:housenumber":"7723",
    "addr:postcode":"53224",
    "addr:street":"N Mariners St",
    "iso:country":"US",
    "sg:address":"7723 N Mariners St",
    "sg:city":"Milwaukee",
    "sg:classifiers":[
        {
            "category":"Shopping",
            "subcategory":"Musical Instruments",
            "type":"Retail Goods"
        }
    ],
    "sg:phone":"+1 414 355 5788",
    "sg:postcode":"53224",
    "sg:province":"WI",
    "wof:name":"Shabach Music",
    "wof:placetype":"venue"
},
  "geometry": {"coordinates":[-88.035777,43.158933],"type":"Point"}
}