{
  "type": "Feature",
  "properties": {
    "addr:full":"730 W Mitchell St Milwaukee WI 53204",
    "addr:housenumber":"730",
    "addr:postcode":"53204",
    "addr:street":"W Mitchell St",
    "iso:country":"US",
    "sg:address":"730 W Mitchell St",
    "sg:city":"Milwaukee",
    "sg:classifiers":[
        {
            "category":"Restaurant",
            "type":"Food & Drink"
        }
    ],
    "sg:phone":"+1 414 431 3377",
    "sg:postcode":"53204",
    "sg:province":"WI",
    "wof:name":"Vista Mar",
    "wof:placetype":"venue"
},
  "geometry": {"coordinates":[-87.920896,43.01237],"type":"Point"}
}