{
  "type": "Feature",
  "properties": {
    "iso:country":"US",
    "sg:address":"383 Park St",
    "sg:city":"Oregon",
    "sg:classifiers":[
        {
            "category":"Government",
            "subcategory":"Police Station",
            "type":"Public Place"
        }
    ],
    "sg:phone":"+1 608 835 3111",
    "sg:postcode":"53575",
    "sg:province":"WI",
    "sg:tags":[
        "department",
        "protection"
    ],
    "wof:name":"Oregon Police Department",
    "wof:placetype":"venue"
},
  "geometry": {"coordinates":[-89.37608299999999,42.92376],"type":"Point"}
}