{
  "type": "Feature",
  "properties": {
    "iso:country":"US",
    "sg:address":"2830 Post Rd",
    "sg:city":"Plover",
    "sg:classifiers":[
        {
            "category":"Bars & Pubs",
            "type":"Food & Drink"
        }
    ],
    "sg:phone":"+1 715 341 0554",
    "sg:postcode":"54467",
    "sg:province":"WI",
    "wof:name":"Sandy's Bar",
    "wof:placetype":"venue"
},
  "geometry": {"coordinates":[-89.543731,44.456288],"type":"Point"}
}