{
  "type": "Feature",
  "properties": {
    "iso:country":"US",
    "sg:address":"2411 Evans Rd",
    "sg:city":"Mc Farland",
    "sg:classifiers":[
        {
            "category":"Real Estate",
            "subcategory":"Real Estate Agent",
            "type":"Services"
        }
    ],
    "sg:phone":"+1 608 838 4711",
    "sg:postcode":"53558",
    "sg:province":"WI",
    "wof:name":"Acker Management LLC",
    "wof:placetype":"venue"
},
  "geometry": {"coordinates":[-89.31734,42.983311],"type":"Point"}
}