{
  "type": "Feature",
  "properties": {
    "iso:country":"US",
    "sg:address":"2511 W Carrington Ave",
    "sg:city":"Oak Creek",
    "sg:classifiers":[
        {
            "category":"Professional",
            "subcategory":"Engineering",
            "type":"Services"
        }
    ],
    "sg:phone":"+1 414 761 2267",
    "sg:postcode":"53154",
    "sg:province":"WI",
    "wof:name":"Performance Engineering",
    "wof:placetype":"venue"
},
  "geometry": {"coordinates":[-87.946837,42.925948],"type":"Point"}
}