{
  "type": "Feature",
  "properties": {
    "iso:country":"US",
    "sg:address":"301 S Park St",
    "sg:city":"Madison",
    "sg:classifiers":[
        {
            "category":"Food & Beverages",
            "subcategory":"Groceries & Convenience Stores",
            "type":"Retail Goods"
        }
    ],
    "sg:phone":"+1 608 255 5864",
    "sg:postcode":"53715",
    "sg:province":"WI",
    "sg:tags":[
        "grocer"
    ],
    "wof:name":"Asian Midway Foods",
    "wof:placetype":"venue"
},
  "geometry": {"coordinates":[-89.400751,43.063711],"type":"Point"}
}