{
  "type": "Feature",
  "properties": {
    "iso:country":"US",
    "sg:address":"4991 Arthur Rd",
    "sg:city":"Slinger",
    "sg:classifiers":[
        {
            "category":"Travel",
            "subcategory":"Hotels & Motels",
            "type":"Entertainment"
        }
    ],
    "sg:phone":"+1 262 644 9232",
    "sg:postcode":"53086",
    "sg:province":"WI",
    "wof:name":"Cedar Lake Motel",
    "wof:placetype":"venue"
},
  "geometry": {"coordinates":[-88.282894,43.353489],"type":"Point"}
}