{
  "type": "Feature",
  "properties": {
    "iso:country":"US",
    "sg:address":"718 S 21st St",
    "sg:city":"Manitowoc",
    "sg:classifiers":[
        {
            "category":"Shopping",
            "subcategory":"Books",
            "type":"Retail Goods"
        }
    ],
    "sg:phone":"+1 920 682 0740",
    "sg:postcode":"54220",
    "sg:province":"WI",
    "wof:name":"Worship Thanks and Praise",
    "wof:placetype":"venue"
},
  "geometry": {"coordinates":[-87.674725,44.092475],"type":"Point"}
}