{
  "type": "Feature",
  "properties": {
    "addr:full":"927 Loring St Altoona WI 54720",
    "addr:housenumber":"927",
    "addr:postcode":"54720",
    "addr:street":"Loring St",
    "iso:country":"US",
    "sg:address":"927 Loring St",
    "sg:city":"Altoona",
    "sg:classifiers":[
        {
            "category":"Personal",
            "type":"Services"
        }
    ],
    "sg:phone":"+1 715 835 6016",
    "sg:postcode":"54720",
    "sg:province":"WI",
    "sg:tags":[
        "therapist",
        "massage"
    ],
    "wof:name":"Natural Healing Center",
    "wof:placetype":"venue"
},
  "geometry": {"coordinates":[-91.46633300000001,44.80127],"type":"Point"}
}