{
  "type": "Feature",
  "properties": {
    "iso:country":"US",
    "sg:address":"719 Jeannie Ln",
    "sg:city":"Beloit",
    "sg:classifiers":[
        {
            "category":"Arts & Performance",
            "subcategory":"Theater",
            "type":"Entertainment"
        }
    ],
    "sg:phone":"+1 608 897 4444",
    "sg:postcode":"53511",
    "sg:province":"WI",
    "sg:tags":[
        "group",
        "religious",
        "organization"
    ],
    "wof:name":"Salty Strings",
    "wof:placetype":"venue"
},
  "geometry": {"coordinates":[-89.0509,42.532191],"type":"Point"}
}