{
  "type": "Feature",
  "properties": {
    "addr:full":"5418 Jarmen Rd Sturgeon Bay WI 54235",
    "addr:housenumber":"5418",
    "addr:postcode":"54235",
    "addr:street":"Jarmen Rd",
    "iso:country":"US",
    "sg:address":"5418 Jarmen Rd",
    "sg:city":"Sturgeon Bay",
    "sg:classifiers":[
        {
            "category":"Farming",
            "subcategory":"Dairy Farm",
            "type":"Manufacturing & Wholesale Goods"
        }
    ],
    "sg:phone":"+1 920 743 5857",
    "sg:postcode":"54235",
    "sg:province":"WI",
    "wof:name":"Kenneth Staats",
    "wof:placetype":"venue"
},
  "geometry": {"coordinates":[-87.30649,44.926297],"type":"Point"}
}