{
  "type": "Feature",
  "properties": {
    "iso:country":"US",
    "sg:address":"18571 Ibsen Rd",
    "sg:city":"Sparta",
    "sg:classifiers":[
        {
            "category":"Building & Trades",
            "subcategory":"Construction",
            "type":"Services"
        }
    ],
    "sg:phone":"+1 608 269 5973",
    "sg:postcode":"54656",
    "sg:province":"WI",
    "sg:tags":[
        "general",
        "contractor"
    ],
    "wof:name":"Jim Leis Construction LLC",
    "wof:placetype":"venue"
},
  "geometry": {"coordinates":[-90.868562,43.900292],"type":"Point"}
}