{
  "type": "Feature",
  "properties": {
    "addr:full":"833 S Rolling Meadows Dr Fond Du Lac WI 54937",
    "addr:housenumber":"833",
    "addr:postcode":"54937",
    "addr:street":"S Rolling Meadows Dr",
    "iso:country":"US",
    "sg:address":"833 S Rolling Meadows Dr",
    "sg:city":"Fond Du Lac",
    "sg:classifiers":[
        {
            "category":"Government",
            "subcategory":"Office",
            "type":"Public Place"
        }
    ],
    "sg:phone":"+1 920 929 3724",
    "sg:postcode":"54937",
    "sg:province":"WI",
    "sg:tags":[
        "state",
        "program"
    ],
    "wof:name":"Transportation Dept",
    "wof:placetype":"venue"
},
  "geometry": {"coordinates":[-88.47887,43.757471],"type":"Point"}
}