{
  "type": "Feature",
  "properties": {
    "addr:full":"210 N 37th St Milwaukee WI 53208",
    "addr:housenumber":"210",
    "addr:postcode":"53208",
    "addr:street":"N 37Th St",
    "iso:country":"US",
    "sg:address":"210 N 37th St",
    "sg:city":"Milwaukee",
    "sg:classifiers":[
        {
            "category":"Community Center",
            "subcategory":"Youth",
            "type":"Public Place"
        }
    ],
    "sg:phone":"+1 414 483 2293",
    "sg:postcode":"53208",
    "sg:province":"WI",
    "wof:name":"Young Womens Inst Global Studies",
    "wof:placetype":"venue"
},
  "geometry": {"coordinates":[-87.960159,43.032776],"type":"Point"}
}