{
  "type": "Feature",
  "properties": {
    "iso:country":"US",
    "sg:address":"15383 State Hwy 29",
    "sg:city":"Tigerton",
    "sg:classifiers":[
        {
            "category":"Building & Trades",
            "subcategory":"Construction",
            "type":"Services"
        }
    ],
    "sg:phone":"+1 715 535 2452",
    "sg:postcode":"54486",
    "sg:province":"WI",
    "sg:tags":[
        "grading",
        "contractor"
    ],
    "wof:name":"Shawano Highway Dept Western",
    "wof:placetype":"venue"
},
  "geometry": {"coordinates":[-89.021143,44.803648],"type":"Point"}
}