{
  "type": "Feature",
  "properties": {
    "addr:full":"6174 Aerotech Dr Appleton WI 54914",
    "addr:housenumber":"6174",
    "addr:postcode":"54914",
    "addr:street":"Aerotech Dr",
    "iso:country":"US",
    "sg:address":"6174 Aerotech Dr",
    "sg:city":"Appleton",
    "sg:classifiers":[
        {
            "category":"Utilities",
            "subcategory":"Telephone",
            "type":"Services"
        }
    ],
    "sg:phone":"+1 920 882 3330",
    "sg:postcode":"54914",
    "sg:province":"WI",
    "sg:tags":[
        "distance",
        "long"
    ],
    "wof:name":"TDS Metrocom",
    "wof:placetype":"venue"
},
  "geometry": {"coordinates":[-88.49706,44.261423],"type":"Point"}
}