{
  "type": "Feature",
  "properties": {
    "iso:country":"US",
    "sg:address":"5909 W Burnham St",
    "sg:city":"Milwaukee",
    "sg:classifiers":[
        {
            "category":"Food & Beverages",
            "subcategory":"Meat & Fish",
            "type":"Retail Goods"
        }
    ],
    "sg:phone":"+1 414 545 6144",
    "sg:postcode":"53219",
    "sg:province":"WI",
    "sg:tags":[
        "seafood",
        "seafood-wholesale",
        "market"
    ],
    "wof:name":"West Allis Fish Market",
    "wof:placetype":"venue"
},
  "geometry": {"coordinates":[-87.986296,43.010182],"type":"Point"}
}