{
  "type": "Feature",
  "properties": {
    "iso:country":"US",
    "sg:address":"3070 N 77th St",
    "sg:city":"Milwaukee",
    "sg:classifiers":[
        {
            "category":"Banks & Credit Unions",
            "subcategory":"Bank",
            "type":"Services"
        }
    ],
    "sg:phone":"+1 414 444 7671",
    "sg:postcode":"53222",
    "sg:province":"WI",
    "sg:tags":[
        "loan",
        "broker",
        "financing"
    ],
    "wof:name":"First City Mortgage Corp",
    "wof:placetype":"venue"
},
  "geometry": {"coordinates":[-88.00859800000001,43.074002],"type":"Point"}
}