{
  "type": "Feature",
  "properties": {
    "addr:full":"1418 Fremont Ave Madison WI 53704",
    "addr:housenumber":"1418",
    "addr:postcode":"53704",
    "addr:street":"Fremont Ave",
    "iso:country":"US",
    "sg:address":"1418 Fremont Ave",
    "sg:city":"Madison",
    "sg:classifiers":[
        {
            "category":"Manufacturing",
            "subcategory":"Jewelry",
            "type":"Manufacturing & Wholesale Goods"
        }
    ],
    "sg:phone":"+1 608 245 0494",
    "sg:postcode":"53704",
    "sg:province":"WI",
    "sg:tags":[
        "costume",
        "mfg"
    ],
    "wof:name":"Glass Gem",
    "wof:placetype":"venue"
},
  "geometry": {"coordinates":[-89.36503999999999,43.11625],"type":"Point"}
}