{
  "type": "Feature",
  "properties": {
    "addr:full":"1717 Paramount Dr Waukesha WI 53186",
    "addr:housenumber":"1717",
    "addr:postcode":"53186",
    "addr:street":"Paramount Dr",
    "iso:country":"US",
    "sg:address":"1717 Paramount Dr",
    "sg:city":"Waukesha",
    "sg:classifiers":[
        {
            "category":"Social Services",
            "type":"Services"
        }
    ],
    "sg:phone":"+1 262 547 8459",
    "sg:postcode":"53186",
    "sg:province":"WI",
    "sg:tags":[
        "organization",
        "welfare"
    ],
    "sg:website":"www.unitedwaywaukesha.org",
    "wof:name":"United Way",
    "wof:placetype":"venue"
},
  "geometry": {"coordinates":[-88.19913699999999,43.02497],"type":"Point"}
}