{
  "type": "Feature",
  "properties": {
    "iso:country":"US",
    "sg:address":"608 N Grove St",
    "sg:city":"Chippewa Falls",
    "sg:classifiers":[
        {
            "category":"Building & Trades",
            "subcategory":"Construction",
            "type":"Services"
        }
    ],
    "sg:phone":"+1 715 726 1979",
    "sg:postcode":"54729",
    "sg:province":"WI",
    "sg:tags":[
        "house"
    ],
    "wof:name":"Callaghan Construction",
    "wof:placetype":"venue"
},
  "geometry": {"coordinates":[-91.392458,44.942161],"type":"Point"}
}