{
  "type": "Feature",
  "properties": {
    "iso:country":"US",
    "sg:address":"20335 W Gale Ave",
    "sg:city":"Galesville",
    "sg:classifiers":[
        {
            "category":"Organizations",
            "subcategory":"Religious Organization",
            "type":"Services"
        }
    ],
    "sg:phone":"+1 608 582 2818",
    "sg:postcode":"54630",
    "sg:province":"WI",
    "sg:tags":[
        "church"
    ],
    "wof:name":"Zion Lutheran Church",
    "wof:placetype":"venue"
},
  "geometry": {"coordinates":[-91.359336,44.082398],"type":"Point"}
}