{
  "type": "Feature",
  "properties": {
    "addr:full":"2125 Deer Run Delavan WI 53115",
    "addr:housenumber":"2125",
    "addr:postcode":"53115",
    "addr:street":"Deer Run",
    "iso:country":"US",
    "sg:address":"2125 Deer Run",
    "sg:city":"Delavan",
    "sg:classifiers":[
        {
            "category":"Professional",
            "subcategory":"Business Services",
            "type":"Services"
        }
    ],
    "sg:phone":"+1 262 903 6686",
    "sg:postcode":"53115",
    "sg:province":"WI",
    "sg:tags":[
        "holding"
    ],
    "wof:name":"Hu J Holdings",
    "wof:placetype":"venue"
},
  "geometry": {"coordinates":[-88.622001,42.612219],"type":"Point"}
}