{
  "type": "Feature",
  "properties": {
    "iso:country":"US",
    "sg:address":"1400 River Run Dr",
    "sg:city":"Wisconsin Rapids",
    "sg:classifiers":[
        {
            "category":"Health Services",
            "subcategory":"Nursing And Care Facility",
            "type":"Services"
        }
    ],
    "sg:phone":"+1 715 421 1400",
    "sg:postcode":"54494",
    "sg:province":"WI",
    "sg:tags":[
        "residential",
        "skilled"
    ],
    "wof:name":"River Run Rtrment Living Cmnty",
    "wof:placetype":"venue"
},
  "geometry": {"coordinates":[-89.811087,44.378252],"type":"Point"}
}