{
  "type": "Feature",
  "properties": {
    "iso:country":"US",
    "sg:address":"8801 W Heather Ave",
    "sg:city":"Milwaukee",
    "sg:classifiers":[
        {
            "category":"Shopping",
            "subcategory":"Computers & Home Electronics",
            "type":"Retail Goods"
        }
    ],
    "sg:phone":"+1 414 355 1330",
    "sg:postcode":"53224",
    "sg:province":"WI",
    "sg:tags":[
        "software"
    ],
    "sg:website":"www.hamacher.com",
    "wof:name":"Hamacher Resource Group",
    "wof:placetype":"venue"
},
  "geometry": {"coordinates":[-88.021354,43.173512],"type":"Point"}
}