{
  "type": "Feature",
  "properties": {
    "iso:country":"US",
    "sg:address":"10319 22nd St E",
    "sg:city":"Necedah",
    "sg:classifiers":[
        {
            "category":"Farming",
            "subcategory":"Nursery",
            "type":"Manufacturing & Wholesale Goods"
        }
    ],
    "sg:phone":"+1 608 565 2230",
    "sg:postcode":"54646",
    "sg:province":"WI",
    "sg:tags":[
        "ornamental"
    ],
    "wof:name":"Van Hoof Farm Gardens",
    "wof:placetype":"venue"
},
  "geometry": {"coordinates":[-90.05452,44.019376],"type":"Point"}
}