{
  "type": "Feature",
  "properties": {
    "iso:country":"US",
    "sg:address":"1676 Main St",
    "sg:city":"Green Bay",
    "sg:classifiers":[
        {
            "category":"Insurance",
            "subcategory":"Insurance Agent",
            "type":"Services"
        }
    ],
    "sg:phone":"+1 920 465 6090",
    "sg:postcode":"54302",
    "sg:province":"WI",
    "wof:name":"Allstate",
    "wof:placetype":"venue"
},
  "geometry": {"coordinates":[-87.980711,44.498849],"type":"Point"}
}