{
  "type": "Feature",
  "properties": {
    "iso:country":"US",
    "sg:address":"201 W Green Bay St",
    "sg:city":"Bonduel",
    "sg:classifiers":[
        {
            "category":"Wholesale",
            "subcategory":"Machinery & Supplies",
            "type":"Manufacturing & Wholesale Goods"
        }
    ],
    "sg:phone":"+1 715 758 6798",
    "sg:postcode":"54107",
    "sg:province":"WI",
    "sg:tags":[
        "tractor"
    ],
    "wof:name":"Village Tractor & Repair LLC",
    "wof:placetype":"venue"
},
  "geometry": {"coordinates":[-88.448939,44.74116],"type":"Point"}
}