{
  "type": "Feature",
  "properties": {
    "iso:country":"US",
    "sg:address":"1366 Suburban Ave",
    "sg:city":"Green Bay",
    "sg:classifiers":[
        {
            "category":"Food & Beverages",
            "subcategory":"Specialty",
            "type":"Retail Goods"
        }
    ],
    "sg:phone":"+1 920 437 4227",
    "sg:postcode":"54304",
    "sg:province":"WI",
    "sg:tags":[
        "spice"
    ],
    "wof:name":"Watkins Products Distr",
    "wof:placetype":"venue"
},
  "geometry": {"coordinates":[-88.064064,44.506849],"type":"Point"}
}