{
  "type": "Feature",
  "properties": {
    "iso:country":"US",
    "sg:address":"1125 W State St",
    "sg:city":"Marshfield",
    "sg:classifiers":[
        {
            "category":"Building & Trades",
            "subcategory":"Landscaping Services",
            "type":"Services"
        }
    ],
    "sg:phone":"+1 715 384 7027",
    "sg:postcode":"54449",
    "sg:province":"WI",
    "wof:name":"Midwest Athletic Surfaces",
    "wof:placetype":"venue"
},
  "geometry": {"coordinates":[-90.19385,44.671844],"type":"Point"}
}