{
  "type": "Feature",
  "properties": {
    "iso:country":"US",
    "sg:address":"306 W State St",
    "sg:city":"Fox Lake",
    "sg:classifiers":[
        {
            "category":"Shopping",
            "subcategory":"Department Store",
            "type":"Retail Goods"
        }
    ],
    "sg:phone":"+1 920 928 2440",
    "sg:postcode":"53933",
    "sg:province":"WI",
    "sg:tags":[
        "shop"
    ],
    "wof:name":"Fox Lake General Store LLC",
    "wof:placetype":"venue"
},
  "geometry": {"coordinates":[-88.910074,43.566065],"type":"Point"}
}