{
  "type": "Feature",
  "properties": {
    "addr:full":"324 State Hwy 57 Sister Bay WI 54234",
    "addr:housenumber":"324",
    "addr:postcode":"54234",
    "addr:street":"State Hwy 57",
    "iso:country":"US",
    "sg:address":"324 State Hwy 57",
    "sg:city":"Sister Bay",
    "sg:classifiers":[
        {
            "category":"Shopping",
            "subcategory":"Gifts & Souvenirs",
            "type":"Retail Goods"
        }
    ],
    "sg:phone":"+1 920 854 9005",
    "sg:postcode":"54234",
    "sg:province":"WI",
    "sg:tags":[
        "shop"
    ],
    "wof:name":"Domicile",
    "wof:placetype":"venue"
},
  "geometry": {"coordinates":[-87.122962,45.185431],"type":"Point"}
}