{
  "type": "Feature",
  "properties": {
    "iso:country":"US",
    "sg:address":"1517 N Ashland Ave",
    "sg:city":"De Pere",
    "sg:classifiers":[
        {
            "category":"Home & Garden",
            "subcategory":"Garden Supply",
            "type":"Retail Goods"
        }
    ],
    "sg:phone":"+1 920 339 1039",
    "sg:postcode":"54115",
    "sg:province":"WI",
    "sg:tags":[
        "fountain",
        "display"
    ],
    "wof:name":"Koi Shop",
    "wof:placetype":"venue"
},
  "geometry": {"coordinates":[-88.074994,44.458583],"type":"Point"}
}