{
  "type": "Feature",
  "properties": {
    "addr:full":"404 E Main St Hortonville WI 54944",
    "addr:housenumber":"404",
    "addr:postcode":"54944",
    "addr:street":"E Main St",
    "iso:country":"US",
    "sg:address":"404 E Main St",
    "sg:city":"Hortonville",
    "sg:classifiers":[
        {
            "category":"Home & Garden",
            "subcategory":"Garden Supply",
            "type":"Retail Goods"
        }
    ],
    "sg:phone":"+1 920 779 6784",
    "sg:postcode":"54944",
    "sg:province":"WI",
    "sg:tags":[
        "equipment",
        "lawn"
    ],
    "wof:name":"A1 Service & Sales",
    "wof:placetype":"venue"
},
  "geometry": {"coordinates":[-88.625294,44.335436],"type":"Point"}
}