{
  "type": "Feature",
  "properties": {
    "iso:country":"US",
    "sg:address":"431 S River Rd",
    "sg:city":"West Bend",
    "sg:classifiers":[
        {
            "category":"Professional",
            "subcategory":"Business Services",
            "type":"Services"
        }
    ],
    "sg:phone":"+1 262 335 0944",
    "sg:postcode":"53095",
    "sg:province":"WI",
    "wof:name":"New Age Typing Service",
    "wof:placetype":"venue"
},
  "geometry": {"coordinates":[-88.161176,43.413173],"type":"Point"}
}