{
  "type": "Feature",
  "properties": {
    "iso:country":"US",
    "sg:address":"1236 Barberry Dr",
    "sg:city":"Janesville",
    "sg:classifiers":[
        {
            "category":"Home & Garden",
            "subcategory":"Furniture",
            "type":"Retail Goods"
        }
    ],
    "sg:phone":"+1 608 754 1123",
    "sg:postcode":"53545",
    "sg:province":"WI",
    "sg:tags":[
        "cabinet"
    ],
    "wof:name":"Marling Distributors",
    "wof:placetype":"venue"
},
  "geometry": {"coordinates":[-89.006878,42.716727],"type":"Point"}
}