{
  "type": "Feature",
  "properties": {
    "iso:country":"US",
    "sg:address":"269 Sydo Rd",
    "sg:city":"Columbus",
    "sg:classifiers":[
        {
            "category":"Real Estate",
            "subcategory":"Surveying",
            "type":"Services"
        }
    ],
    "sg:phone":"+1 920 210 4126",
    "sg:postcode":"53925",
    "sg:province":"WI",
    "sg:tags":[
        "surveyor"
    ],
    "wof:name":"Topline Survey LLC",
    "wof:placetype":"venue"
},
  "geometry": {"coordinates":[-89.014791,43.290141],"type":"Point"}
}