{
  "type": "Feature",
  "properties": {
    "iso:country":"US",
    "sg:address":"1205 W Circle Dr",
    "sg:city":"Sparta",
    "sg:classifiers":[
        {
            "category":"Health Services",
            "subcategory":"Doctor",
            "type":"Services"
        }
    ],
    "sg:phone":"+1 608 269 6200",
    "sg:postcode":"54656",
    "sg:province":"WI",
    "sg:tags":[
        "physician",
        "surgeon"
    ],
    "wof:name":"Krohn Clinic",
    "wof:placetype":"venue"
},
  "geometry": {"coordinates":[-90.829581,43.943477],"type":"Point"}
}