{
  "type": "Feature",
  "properties": {
    "iso:country":"US",
    "sg:address":"1102 N 3rd St",
    "sg:city":"Superior",
    "sg:classifiers":[
        {
            "category":"Retail",
            "subcategory":"Repair Shop",
            "type":"Services"
        }
    ],
    "sg:phone":"+1 715 392 4202",
    "sg:postcode":"54880",
    "sg:province":"WI",
    "sg:tags":[
        "armature",
        "electrical",
        "rewinding",
        "equipment"
    ],
    "wof:name":"Tm Electric",
    "wof:placetype":"venue"
},
  "geometry": {"coordinates":[-92.094253,46.735081],"type":"Point"}
}