{
  "type": "Feature",
  "properties": {
    "iso:country":"US",
    "sg:address":"8440 W Forest Home Ave",
    "sg:city":"Milwaukee",
    "sg:classifiers":[
        {
            "category":"Insurance",
            "subcategory":"Insurance Agent",
            "type":"Services"
        }
    ],
    "sg:phone":"+1 414 425 1088",
    "sg:postcode":"53228",
    "sg:province":"WI",
    "wof:name":"State Farm Insurance",
    "wof:placetype":"venue"
},
  "geometry": {"coordinates":[-88.020107,42.956868],"type":"Point"}
}