{
  "type": "Feature",
  "properties": {
    "iso:country":"US",
    "sg:address":"6966 Neupert Rd",
    "sg:city":"Lake Mills",
    "sg:classifiers":[
        {
            "category":"Professional",
            "subcategory":"Research",
            "type":"Services"
        }
    ],
    "sg:phone":"+1 920 648 8796",
    "sg:postcode":"53551",
    "sg:province":"WI",
    "sg:tags":[
        "organization",
        "noncommercial"
    ],
    "wof:name":"Plus Ultra Discoverie LLC",
    "wof:placetype":"venue"
},
  "geometry": {"coordinates":[-88.905575,43.10021],"type":"Point"}
}