{
  "type": "Feature",
  "properties": {
    "addr:full":"324 S Sanborn Ave Jefferson WI 53549",
    "addr:housenumber":"324",
    "addr:postcode":"53549",
    "addr:street":"S Sanborn Ave",
    "iso:country":"US",
    "sg:address":"324 S Sanborn Ave",
    "sg:city":"Jefferson",
    "sg:classifiers":[
        {
            "category":"Organizations",
            "subcategory":"Religious Organization",
            "type":"Services"
        }
    ],
    "sg:phone":"+1 920 674 2370",
    "sg:postcode":"53549",
    "sg:province":"WI",
    "sg:tags":[
        "church"
    ],
    "wof:name":"St Mark's Lutheran Church",
    "wof:placetype":"venue"
},
  "geometry": {"coordinates":[-88.803287,43.003101],"type":"Point"}
}