{
  "type": "Feature",
  "properties": {
    "iso:country":"US",
    "sg:address":"3671 State Hwy 59",
    "sg:city":"Monroe",
    "sg:classifiers":[
        {
            "category":"Retail",
            "subcategory":"Animal Services",
            "type":"Services"
        }
    ],
    "sg:phone":"+1 608 325 4783",
    "sg:postcode":"53566",
    "sg:province":"WI",
    "wof:name":"Wisconsin Paint Horse Club",
    "wof:placetype":"venue"
},
  "geometry": {"coordinates":[-89.537679,42.65141],"type":"Point"}
}