{
  "type": "Feature",
  "properties": {
    "iso:country":"US",
    "sg:address":"291 State Hwy 35",
    "sg:city":"Nelson",
    "sg:classifiers":[
        {
            "category":"Shopping",
            "subcategory":"Jewelry",
            "type":"Retail Goods"
        },
        {
            "category":"Shopping",
            "subcategory":"Gifts & Souvenirs",
            "type":"Retail Goods"
        }
    ],
    "sg:phone":"+1 715 673 4299",
    "sg:postcode":"54756",
    "sg:province":"WI",
    "sg:tags":[
        "shop"
    ],
    "wof:name":"Peeling Shutters",
    "wof:placetype":"venue"
},
  "geometry": {"coordinates":[-92.008976,44.420817],"type":"Point"}
}