{
  "type": "Feature",
  "properties": {
    "iso:country":"US",
    "sg:address":"3823 Parker Dr",
    "sg:city":"Lake Geneva",
    "sg:classifiers":[
        {
            "category":"Building & Trades",
            "subcategory":"Construction",
            "type":"Services"
        }
    ],
    "sg:phone":"+1 262 249 1956",
    "sg:postcode":"53147",
    "sg:province":"WI",
    "sg:tags":[
        "contractor"
    ],
    "wof:name":"Lake Cabin Roofing",
    "wof:placetype":"venue"
},
  "geometry": {"coordinates":[-88.48525100000001,42.550384],"type":"Point"}
}