{
  "type": "Feature",
  "properties": {
    "iso:country":"US",
    "sg:address":"4331 N 61st St",
    "sg:city":"Milwaukee",
    "sg:classifiers":[
        {
            "category":"Social Services",
            "type":"Services"
        }
    ],
    "sg:phone":"+1 414 234 1024",
    "sg:postcode":"53216",
    "sg:province":"WI",
    "sg:tags":[
        "center"
    ],
    "wof:name":"Ground Level LLC",
    "wof:placetype":"venue"
},
  "geometry": {"coordinates":[-87.98817099999999,43.096714],"type":"Point"}
}