{
  "type": "Feature",
  "properties": {
    "addr:full":"2855 S 163rd St New Berlin WI 53151",
    "addr:housenumber":"2855",
    "addr:postcode":"53151",
    "addr:street":"S 163Rd St",
    "iso:country":"US",
    "sg:address":"2855 S 163rd St",
    "sg:city":"New Berlin",
    "sg:classifiers":[
        {
            "category":"Wholesale",
            "subcategory":"Machinery & Supplies",
            "type":"Manufacturing & Wholesale Goods"
        }
    ],
    "sg:phone":"+1 262 797 8500",
    "sg:postcode":"53151",
    "sg:province":"WI",
    "sg:tags":[
        "equipment",
        "welding"
    ],
    "wof:name":"Airgas",
    "wof:placetype":"venue"
},
  "geometry": {"coordinates":[-88.11694300000001,42.992298],"type":"Point"}
}