{
  "type": "Feature",
  "properties": {
    "iso:country":"US",
    "sg:address":"1121 Witzel Ave",
    "sg:city":"Oshkosh",
    "sg:classifiers":[
        {
            "category":"Personal",
            "subcategory":"Barber",
            "type":"Services"
        }
    ],
    "sg:phone":"+1 920 233 0125",
    "sg:postcode":"54902",
    "sg:province":"WI",
    "sg:tags":[
        "shop"
    ],
    "wof:name":"Handle Bar Barber Shop",
    "wof:placetype":"venue"
},
  "geometry": {"coordinates":[-88.567155,44.017848],"type":"Point"}
}