{
  "type": "Feature",
  "properties": {
    "addr:full":"622 Peace Pipe Rd Lac Du Flambeau WI 54538",
    "addr:housenumber":"622",
    "addr:postcode":"54538",
    "addr:street":"Peace Pipe Rd",
    "iso:country":"US",
    "sg:address":"622 Peace Pipe Rd",
    "sg:city":"Lac Du Flambeau",
    "sg:classifiers":[
        {
            "category":"Government",
            "subcategory":"Post Office",
            "type":"Public Place"
        }
    ],
    "sg:phone":"+1 715 588 3122",
    "sg:postcode":"54538",
    "sg:province":"WI",
    "sg:tags":[
        "postal",
        "us"
    ],
    "wof:name":"US Post Office",
    "wof:placetype":"venue"
},
  "geometry": {"coordinates":[-89.89228300000001,45.970338],"type":"Point"}
}