{
  "type": "Feature",
  "properties": {
    "addr:full":"8355 US Hwy 10 Neillsville WI 54456",
    "addr:housenumber":"8355",
    "addr:postcode":"54456",
    "addr:street":"Us Hwy 10",
    "iso:country":"US",
    "sg:address":"8355 US Hwy 10",
    "sg:city":"Neillsville",
    "sg:classifiers":[
        {
            "category":"Travel",
            "subcategory":"Campground",
            "type":"Entertainment"
        }
    ],
    "sg:phone":"+1 715 743 3620",
    "sg:postcode":"54456",
    "sg:province":"WI",
    "sg:tags":[
        "trailer"
    ],
    "wof:name":"Norm & Ann's Campground",
    "wof:placetype":"venue"
},
  "geometry": {"coordinates":[-90.740405,44.579994],"type":"Point"}
}