{
  "type": "Feature",
  "properties": {
    "iso:country":"US",
    "sg:address":"617 Public Ave",
    "sg:city":"Beloit",
    "sg:classifiers":[
        {
            "category":"Place Of Worship",
            "subcategory":"Church",
            "type":"Public Place"
        },
        {
            "category":"Place Of Worship",
            "type":"Public Place"
        }
    ],
    "sg:phone":"+1 608 365 8455",
    "sg:postcode":"53511",
    "sg:province":"WI",
    "sg:tags":[
        "churches-baptist-general",
        "churches-baptist"
    ],
    "wof:name":"First Baptist Church",
    "wof:placetype":"venue"
},
  "geometry": {"coordinates":[-89.030676,42.500568],"type":"Point"}
}