{
  "type": "Feature",
  "properties": {
    "addr:full":"716 Goold St Racine WI 53402",
    "addr:housenumber":"716",
    "addr:postcode":"53402",
    "addr:street":"Goold St",
    "iso:country":"US",
    "sg:address":"716 Goold St",
    "sg:city":"Racine",
    "sg:classifiers":[
        {
            "category":"Professional",
            "subcategory":"Computer Services",
            "type":"Services"
        }
    ],
    "sg:phone":"+1 262 635 8188",
    "sg:postcode":"53402",
    "sg:province":"WI",
    "sg:tags":[
        "website",
        "design"
    ],
    "sg:website":"www.racineweb.com",
    "wof:name":"Racine Web Svc Inc",
    "wof:placetype":"venue"
},
  "geometry": {"coordinates":[-87.78856500000001,42.747826],"type":"Point"}
}