{
  "type": "Feature",
  "properties": {
    "iso:country":"US",
    "sg:address":"2486 S 12th St",
    "sg:city":"Milwaukee",
    "sg:classifiers":[
        {
            "category":"Wholesale",
            "subcategory":"Apparel",
            "type":"Manufacturing & Wholesale Goods"
        }
    ],
    "sg:phone":"+1 414 383 9490",
    "sg:postcode":"53215",
    "sg:province":"WI",
    "sg:tags":[
        "clothing"
    ],
    "wof:name":"Latoyas Little Blessings",
    "wof:placetype":"venue"
},
  "geometry": {"coordinates":[-87.927214,43.00101],"type":"Point"}
}