{
  "type": "Feature",
  "properties": {
    "iso:country":"US",
    "sg:address":"301 Keller Ave S",
    "sg:city":"Amery",
    "sg:classifiers":[
        {
            "category":"Professional",
            "subcategory":"Accounting & Tax Preparation",
            "type":"Services"
        }
    ],
    "sg:phone":"+1 715 268 7999",
    "sg:postcode":"54001",
    "sg:province":"WI",
    "sg:tags":[
        "accountant"
    ],
    "wof:name":"Carlson Highland & Co LLC",
    "wof:placetype":"venue"
},
  "geometry": {"coordinates":[-92.362099,45.309031],"type":"Point"}
}