{
  "type": "Feature",
  "properties": {
    "iso:country":"US",
    "sg:address":"839 Oak Rd",
    "sg:city":"Mosinee",
    "sg:classifiers":[
        {
            "category":"Retail",
            "subcategory":"Repair Shop",
            "type":"Services"
        }
    ],
    "sg:phone":"+1 715 692 3000",
    "sg:postcode":"54455",
    "sg:province":"WI",
    "sg:tags":[
        "taxidermist"
    ],
    "wof:name":"Custom Robotic Wildlife Inc",
    "wof:placetype":"venue"
},
  "geometry": {"coordinates":[-89.634362,44.802031],"type":"Point"}
}