{
  "type": "Feature",
  "properties": {
    "iso:country":"US",
    "sg:address":"315 King St",
    "sg:city":"Dodgeville",
    "sg:classifiers":[
        {
            "category":"Sports & Exercise",
            "subcategory":"Gym",
            "type":"Entertainment"
        }
    ],
    "sg:phone":"+1 608 588 3123",
    "sg:postcode":"53533",
    "sg:province":"WI",
    "sg:tags":[
        "fitness",
        "physical",
        "facility"
    ],
    "wof:name":"Curves Spring Green",
    "wof:placetype":"venue"
},
  "geometry": {"coordinates":[-90.137144,42.974519],"type":"Point"}
}