{
  "type": "Feature",
  "properties": {
    "iso:country":"US",
    "sg:address":"716 Clara Ave",
    "sg:city":"Sheboygan",
    "sg:classifiers":[
        {
            "category":"Manufacturing",
            "subcategory":"Paper Products",
            "type":"Manufacturing & Wholesale Goods"
        }
    ],
    "sg:phone":"+1 920 458 8373",
    "sg:postcode":"53081",
    "sg:province":"WI",
    "sg:tags":[
        "box"
    ],
    "wof:name":"Sheboygan Paper Box Co",
    "wof:placetype":"venue"
},
  "geometry": {"coordinates":[-87.712754,43.738424],"type":"Point"}
}