{
  "type": "Feature",
  "properties": {
    "addr:full":"8255 Co Rd I Custer WI 54423",
    "addr:housenumber":"8255",
    "addr:postcode":"54423",
    "addr:street":"Co Rd I",
    "iso:country":"US",
    "sg:address":"8255 Co Rd I",
    "sg:city":"Custer",
    "sg:classifiers":[
        {
            "category":"Farming",
            "subcategory":"Livestock Farm",
            "type":"Manufacturing & Wholesale Goods"
        }
    ],
    "sg:phone":"+1 715 592 4876",
    "sg:postcode":"54423",
    "sg:province":"WI",
    "sg:tags":[
        "beef",
        "feedlot",
        "cattle"
    ],
    "wof:name":"Jeff Genskow",
    "wof:placetype":"venue"
},
  "geometry": {"coordinates":[-89.370045,44.54169],"type":"Point"}
}