{
  "type": "Feature",
  "properties": {
    "iso:country":"US",
    "sg:address":"625 Commerce Dr",
    "sg:city":"Hudson",
    "sg:classifiers":[
        {
            "category":"Utilities",
            "subcategory":"Electric",
            "type":"Services"
        },
        {
            "category":"Building & Trades",
            "subcategory":"Electrical",
            "type":"Services"
        }
    ],
    "sg:phone":"+1 715 381 1331",
    "sg:postcode":"54016",
    "sg:province":"WI",
    "sg:tags":[
        "equipment-repair",
        "industrial",
        "electrician",
        "contractors-commercial"
    ],
    "wof:name":"B & B Electric Inc",
    "wof:placetype":"venue"
},
  "geometry": {"coordinates":[-92.675304,44.966067],"type":"Point"}
}