{
  "type": "Feature",
  "properties": {
    "iso:country":"US",
    "sg:address":"455 S Jefferson St",
    "sg:city":"Waterford",
    "sg:classifiers":[
        {
            "category":"Organizations",
            "subcategory":"Religious Organization",
            "type":"Services"
        }
    ],
    "sg:phone":"+1 262 534 2313",
    "sg:postcode":"53185",
    "sg:province":"WI",
    "wof:name":"Community Untd Methdst Church",
    "wof:placetype":"venue"
},
  "geometry": {"coordinates":[-88.22265299999999,42.757307],"type":"Point"}
}