{
  "type": "Feature",
  "properties": {
    "iso:country":"US",
    "sg:address":"411 N Grand Ave",
    "sg:city":"Waukesha",
    "sg:classifiers":[
        {
            "category":"Health Services",
            "subcategory":"Optometrist",
            "type":"Services"
        }
    ],
    "sg:phone":"+1 262 542 3300",
    "sg:postcode":"53186",
    "sg:province":"WI",
    "wof:name":"Dr Alfred Waltke",
    "wof:placetype":"venue"
},
  "geometry": {"coordinates":[-88.23161,43.007674],"type":"Point"}
}