{
  "type": "Feature",
  "properties": {
    "addr:full":"3041 N Mayfair Rd Milwaukee WI 53222",
    "addr:housenumber":"3041",
    "addr:postcode":"53222",
    "addr:street":"N Mayfair Rd",
    "iso:country":"US",
    "sg:address":"3041 N Mayfair Rd",
    "sg:city":"Milwaukee",
    "sg:classifiers":[
        {
            "category":"Restaurant",
            "type":"Food & Drink"
        }
    ],
    "sg:menulink":"http://www.allmenus.com/wi/wauwatosa/9544-aliotos/menu/",
    "sg:phone":"+1 414 476 6900",
    "sg:postcode":"53222",
    "sg:province":"WI",
    "sg:tags":[
        "american",
        "steakhouse"
    ],
    "wof:name":"Alioto's",
    "wof:placetype":"venue"
},
  "geometry": {"coordinates":[-88.048739,43.073847],"type":"Point"}
}