{
  "type": "Feature",
  "properties": {
    "iso:country":"US",
    "sg:address":"6528 W North Ave",
    "sg:city":"Milwaukee",
    "sg:classifiers":[
        {
            "category":"Personal",
            "type":"Services"
        }
    ],
    "sg:phone":"+1 414 258 2826",
    "sg:postcode":"53213",
    "sg:province":"WI",
    "wof:name":"Tjs Caribbean Tan LLC",
    "wof:placetype":"venue"
},
  "geometry": {"coordinates":[-87.994588,43.060801],"type":"Point"}
}