{
  "type": "Feature",
  "properties": {
    "iso:country":"US",
    "sg:address":"95 N Moorland Rd",
    "sg:city":"Brookfield",
    "sg:classifiers":[
        {
            "category":"Shopping",
            "subcategory":"Gifts & Souvenirs",
            "type":"Retail Goods"
        }
    ],
    "sg:phone":"+1 262 827 0760",
    "sg:postcode":"53005",
    "sg:province":"WI",
    "sg:tags":[
        "shop",
        "cards",
        "greeting",
        "item"
    ],
    "sg:website":"www.kirlinshallmark.com",
    "wof:name":"Kirlin's Hallmark",
    "wof:placetype":"venue"
},
  "geometry": {"coordinates":[-88.106933,43.034839],"type":"Point"}
}