{
  "type": "Feature",
  "properties": {
    "iso:country":"US",
    "sg:address":"1523 Rose St",
    "sg:city":"La Crosse",
    "sg:classifiers":[
        {
            "category":"Professional",
            "subcategory":"Advertising",
            "type":"Services"
        }
    ],
    "sg:phone":"+1 608 784 1166",
    "sg:postcode":"54603",
    "sg:province":"WI",
    "sg:tags":[
        "counselor"
    ],
    "sg:website":"www.centuryexpo.com",
    "wof:name":"Century Expo LTD",
    "wof:placetype":"venue"
},
  "geometry": {"coordinates":[-91.248223,43.846037],"type":"Point"}
}