{
  "type": "Feature",
  "properties": {
    "addr:full":"1402 W Weiland Ln Appleton WI 54914",
    "addr:housenumber":"1402",
    "addr:postcode":"54914",
    "addr:street":"W Weiland Ln",
    "iso:country":"US",
    "sg:address":"1402 W Weiland Ln",
    "sg:city":"Appleton",
    "sg:classifiers":[
        {
            "category":"Retail",
            "subcategory":"Repair Shop",
            "type":"Services"
        }
    ],
    "sg:phone":"+1 920 739 4876",
    "sg:postcode":"54914",
    "sg:province":"WI",
    "wof:name":"Donald Nett",
    "wof:placetype":"venue"
},
  "geometry": {"coordinates":[-88.427329,44.286568],"type":"Point"}
}