{
  "type": "Feature",
  "properties": {
    "iso:country":"US",
    "sg:address":"2209 33rd Ave",
    "sg:city":"Eau Claire",
    "sg:classifiers":[
        {
            "category":"Professional",
            "type":"Services"
        }
    ],
    "sg:phone":"+1 715 833 2145",
    "sg:postcode":"54703",
    "sg:province":"WI",
    "wof:name":"Whitetails Unlimited Inc",
    "wof:placetype":"venue"
},
  "geometry": {"coordinates":[-91.46102999999999,44.840684],"type":"Point"}
}