{
  "type": "Feature",
  "properties": {
    "iso:country":"US",
    "sg:address":"1231 Menomonie St",
    "sg:city":"Eau Claire",
    "sg:classifiers":[
        {
            "category":"Social Services",
            "type":"Services"
        }
    ],
    "sg:phone":"+1 715 833 2279",
    "sg:postcode":"54703",
    "sg:province":"WI",
    "sg:tags":[
        "information",
        "planning",
        "center",
        "family"
    ],
    "wof:name":"Planned Parenthood",
    "wof:placetype":"venue"
},
  "geometry": {"coordinates":[-91.528216,44.800024],"type":"Point"}
}