{
  "type": "Feature",
  "properties": {
    "addr:full":"254 S 5th Ave West Bend WI 53095",
    "addr:housenumber":"254",
    "addr:postcode":"53095",
    "addr:street":"S 5Th Ave",
    "iso:country":"US",
    "sg:address":"254 S 5th Ave",
    "sg:city":"West Bend",
    "sg:classifiers":[
        {
            "category":"Building & Trades",
            "subcategory":"Construction",
            "type":"Services"
        }
    ],
    "sg:phone":"+1 262 335 9394",
    "sg:postcode":"53095",
    "sg:province":"WI",
    "sg:tags":[
        "house"
    ],
    "wof:name":"R C Renovations LLC",
    "wof:placetype":"venue"
},
  "geometry": {"coordinates":[-88.182445,43.421378],"type":"Point"}
}