{
  "type": "Feature",
  "properties": {
    "addr:full":"8417 W Cleveland Ave Milwaukee WI 53227",
    "addr:housenumber":"8417",
    "addr:postcode":"53227",
    "addr:street":"W Cleveland Ave",
    "iso:country":"US",
    "sg:address":"8417 W Cleveland Ave",
    "sg:city":"Milwaukee",
    "sg:classifiers":[
        {
            "category":"Restaurant",
            "type":"Food & Drink"
        }
    ],
    "sg:menulink":"http://www.allmenus.com/wi/west-allis/142623-michaels-family-restaurant-of-west-allis-inc/menu/",
    "sg:phone":"+1 414 545 2302",
    "sg:postcode":"53227",
    "sg:province":"WI",
    "sg:tags":[
        "american"
    ],
    "wof:name":"Michael's Family Restaurant Of West Allis Inc",
    "wof:placetype":"venue"
},
  "geometry": {"coordinates":[-88.018089,42.995062],"type":"Point"}
}