{
  "type": "Feature",
  "properties": {
    "iso:country":"US",
    "sg:address":"1133 Horicon St",
    "sg:city":"Mayville",
    "sg:classifiers":[
        {
            "category":"Retail",
            "subcategory":"Car Wash",
            "type":"Services"
        }
    ],
    "sg:phone":"+1 920 387 2155",
    "sg:postcode":"53050",
    "sg:province":"WI",
    "sg:tags":[
        "carwash"
    ],
    "wof:name":"Schmids Ultra-Spray Car Wash",
    "wof:placetype":"venue"
},
  "geometry": {"coordinates":[-88.559331,43.494036],"type":"Point"}
}