{
  "type": "Feature",
  "properties": {
    "iso:country":"US",
    "sg:address":"213 W Weiland Ave",
    "sg:city":"Appleton",
    "sg:classifiers":[
        {
            "category":"Wholesale",
            "subcategory":"Jewelry",
            "type":"Manufacturing & Wholesale Goods"
        }
    ],
    "sg:phone":"+1 920 734 8385",
    "sg:postcode":"54911",
    "sg:province":"WI",
    "sg:tags":[
        "durable",
        "merchandise",
        "general"
    ],
    "wof:name":"Magoon Ltd Inc",
    "wof:placetype":"venue"
},
  "geometry": {"coordinates":[-88.408931,44.285895],"type":"Point"}
}