{
  "type": "Feature",
  "properties": {
    "iso:country":"US",
    "sg:address":"218 W Main St",
    "sg:city":"Sparta",
    "sg:classifiers":[
        {
            "category":"Health Services",
            "subcategory":"Hospital",
            "type":"Services"
        }
    ],
    "sg:phone":"+1 608 269 1588",
    "sg:postcode":"54656",
    "sg:province":"WI",
    "sg:tags":[
        "mental"
    ],
    "wof:name":"Gundersen Lutheran Behavioral",
    "wof:placetype":"venue"
},
  "geometry": {"coordinates":[-90.813524,43.944444],"type":"Point"}
}