{
  "type": "Feature",
  "properties": {
    "iso:country":"US",
    "sg:address":"163 E 1st St",
    "sg:city":"Fond Du Lac",
    "sg:classifiers":[
        {
            "category":"Building & Trades",
            "subcategory":"Construction",
            "type":"Services"
        }
    ],
    "sg:phone":"+1 920 517 1706",
    "sg:postcode":"54935",
    "sg:province":"WI",
    "sg:tags":[
        "concrete",
        "contractor"
    ],
    "wof:name":"RR Concrete Construction",
    "wof:placetype":"venue"
},
  "geometry": {"coordinates":[-88.441857,43.776102],"type":"Point"}
}