{
  "type": "Feature",
  "properties": {
    "addr:full":"5509 30th Rd Pine River WI 54965",
    "addr:housenumber":"5509",
    "addr:postcode":"54965",
    "addr:street":"30Th Rd",
    "iso:country":"US",
    "sg:address":"5509 30th Rd",
    "sg:city":"Pine River",
    "sg:classifiers":[
        {
            "category":"Government",
            "subcategory":"Office",
            "type":"Public Place"
        }
    ],
    "sg:phone":"+1 920 987 5062",
    "sg:postcode":"54965",
    "sg:province":"WI",
    "sg:tags":[
        "general"
    ],
    "wof:name":"Town of Saxeville",
    "wof:placetype":"venue"
},
  "geometry": {"coordinates":[-89.02346300000001,44.184398],"type":"Point"}
}