{
  "type": "Feature",
  "properties": {
    "iso:country":"US",
    "sg:address":"553 Fair Rd",
    "sg:city":"Wrightstown",
    "sg:classifiers":[
        {
            "category":"Building & Trades",
            "subcategory":"Construction",
            "type":"Services"
        }
    ],
    "sg:phone":"+1 920 532 0966",
    "sg:postcode":"54180",
    "sg:province":"WI",
    "sg:tags":[
        "house"
    ],
    "wof:name":"Gary Vanstraten Construct",
    "wof:placetype":"venue"
},
  "geometry": {"coordinates":[-88.146701,44.324293],"type":"Point"}
}