{
  "type": "Feature",
  "properties": {
    "iso:country":"US",
    "sg:address":"2923 N Teutonia Ave",
    "sg:city":"Milwaukee",
    "sg:classifiers":[
        {
            "category":"Autos & Motor Vehicles",
            "subcategory":"Auto Supplies",
            "type":"Retail Goods"
        }
    ],
    "sg:phone":"+1 414 562 6211",
    "sg:postcode":"53206",
    "sg:province":"WI",
    "sg:tags":[
        "tire"
    ],
    "wof:name":"T & N Tire Svc",
    "wof:placetype":"venue"
},
  "geometry": {"coordinates":[-87.930582,43.071454],"type":"Point"}
}