{
  "type": "Feature",
  "properties": {
    "iso:country":"US",
    "sg:address":"5903 Prairie St",
    "sg:city":"Schofield",
    "sg:classifiers":[
        {
            "category":"Wholesale",
            "subcategory":"Machinery & Supplies",
            "type":"Manufacturing & Wholesale Goods"
        },
        {
            "category":"Home & Garden",
            "subcategory":"Building Materials",
            "type":"Retail Goods"
        }
    ],
    "sg:phone":"+1 715 359 1800",
    "sg:postcode":"54476",
    "sg:province":"WI",
    "sg:tags":[
        "equipment",
        "door"
    ],
    "wof:name":"Block Iron & Supply",
    "wof:placetype":"venue"
},
  "geometry": {"coordinates":[-89.55938,44.903819],"type":"Point"}
}