{
  "type": "Feature",
  "properties": {
    "iso:country":"US",
    "sg:address":"10220 S County Line Rd",
    "sg:city":"Lodi",
    "sg:classifiers":[
        {
            "category":"Real Estate",
            "subcategory":"Real Estate Operator",
            "type":"Services"
        }
    ],
    "sg:phone":"+1 608 592 3371",
    "sg:postcode":"53555",
    "sg:province":"WI",
    "sg:tags":[
        "property",
        "lessor"
    ],
    "wof:name":"Alfred Johnson",
    "wof:placetype":"venue"
},
  "geometry": {"coordinates":[-89.50714000000001,43.293875],"type":"Point"}
}