{
  "type": "Feature",
  "properties": {
    "iso:country":"US",
    "sg:address":"509 McMillen St",
    "sg:city":"Fort Atkinson",
    "sg:classifiers":[
        {
            "category":"Insurance",
            "subcategory":"Insurance Agent",
            "type":"Services"
        }
    ],
    "sg:phone":"+1 920 568 1200",
    "sg:postcode":"53538",
    "sg:province":"WI",
    "wof:name":"Professional Services Group",
    "wof:placetype":"venue"
},
  "geometry": {"coordinates":[-88.82766599999999,42.935257],"type":"Point"}
}