{
  "type": "Feature",
  "properties": {
    "addr:full":"2831 Parmenter St Middleton WI 53562",
    "addr:housenumber":"2831",
    "addr:postcode":"53562",
    "addr:street":"Parmenter St",
    "iso:country":"US",
    "sg:address":"2831 Parmenter St",
    "sg:city":"Middleton",
    "sg:classifiers":[
        {
            "category":"Restaurant",
            "type":"Food & Drink"
        }
    ],
    "sg:menulink":"http://www.allmenus.com/wi/middleton/101310-cousins-subs/menu/",
    "sg:phone":"+1 608 831 0488",
    "sg:postcode":"53562",
    "sg:province":"WI",
    "sg:tags":[
        "wrap",
        "american",
        "sandwich"
    ],
    "wof:name":"Cousin's Subs",
    "wof:placetype":"venue"
},
  "geometry": {"coordinates":[-89.51078800000001,43.104923],"type":"Point"}
}