{
  "type": "Feature",
  "properties": {
    "iso:country":"US",
    "sg:address":"626 E Kilbourn Ave",
    "sg:city":"Milwaukee",
    "sg:classifiers":[
        {
            "category":"Professional",
            "subcategory":"Engineering",
            "type":"Services"
        }
    ],
    "sg:phone":"+1 414 202 5928",
    "sg:postcode":"53202",
    "sg:province":"WI",
    "sg:tags":[
        "specializing",
        "work",
        "general",
        "contractor"
    ],
    "wof:name":"Keith Corzine",
    "wof:placetype":"venue"
},
  "geometry": {"coordinates":[-87.903475,43.042766],"type":"Point"}
}