{
  "type": "Feature",
  "properties": {
    "addr:full":"3260 W Highview Dr Appleton WI 54914",
    "addr:housenumber":"3260",
    "addr:postcode":"54914",
    "addr:street":"W Highview Dr",
    "iso:country":"US",
    "sg:address":"3260 W Highview Dr",
    "sg:city":"Appleton",
    "sg:classifiers":[
        {
            "category":"Wholesale",
            "subcategory":"Machinery & Supplies",
            "type":"Manufacturing & Wholesale Goods"
        }
    ],
    "sg:phone":"+1 920 993 0786",
    "sg:postcode":"54914",
    "sg:province":"WI",
    "sg:tags":[
        "transmission",
        "electrical",
        "power",
        "mechanical"
    ],
    "wof:name":"Weimer Bearing & Transmission",
    "wof:placetype":"venue"
},
  "geometry": {"coordinates":[-88.4511,44.266709],"type":"Point"}
}