{
  "type": "Feature",
  "properties": {
    "iso:country":"US",
    "sg:address":"1446 Horicon St",
    "sg:city":"Mayville",
    "sg:classifiers":[
        {
            "category":"Insurance",
            "subcategory":"Insurance Agent",
            "type":"Services"
        }
    ],
    "sg:phone":"+1 920 387 5070",
    "sg:postcode":"53050",
    "sg:province":"WI",
    "wof:name":"Marx Brad State Farm Insur",
    "wof:placetype":"venue"
},
  "geometry": {"coordinates":[-88.563143,43.494579],"type":"Point"}
}