{
  "type": "Feature",
  "properties": {
    "iso:country":"US",
    "sg:address":"731 Race St",
    "sg:city":"Wisconsin Dells",
    "sg:classifiers":[
        {
            "category":"Shopping",
            "type":"Retail Goods"
        }
    ],
    "sg:phone":"+1 608 254 7908",
    "sg:postcode":"53965",
    "sg:province":"WI",
    "sg:tags":[
        "merchandise"
    ],
    "wof:name":"Kaminski Coin Co",
    "wof:placetype":"venue"
},
  "geometry": {"coordinates":[-89.763124,43.627024],"type":"Point"}
}