{
  "type": "Feature",
  "properties": {
    "iso:country":"US",
    "sg:address":"860 E Main St",
    "sg:city":"Mondovi",
    "sg:classifiers":[
        {
            "category":"Travel",
            "subcategory":"Hotels & Motels",
            "type":"Entertainment"
        }
    ],
    "sg:phone":"+1 715 926 5926",
    "sg:postcode":"54755",
    "sg:province":"WI",
    "sg:tags":[
        "operation"
    ],
    "wof:name":"Mondovi Inn Motel",
    "wof:placetype":"venue"
},
  "geometry": {"coordinates":[-91.658552,44.56895],"type":"Point"}
}