{
  "type": "Feature",
  "properties": {
    "addr:full":"6870 N Santa Monica Blvd Milwaukee WI 53217",
    "addr:housenumber":"6870",
    "addr:postcode":"53217",
    "addr:street":"N Santa Monica Blvd",
    "iso:country":"US",
    "sg:address":"6870 N Santa Monica Blvd",
    "sg:city":"Milwaukee",
    "sg:classifiers":[
        {
            "category":"Sports & Exercise",
            "subcategory":"Gym",
            "type":"Entertainment"
        }
    ],
    "sg:phone":"+1 414 540 1266",
    "sg:postcode":"53217",
    "sg:province":"WI",
    "sg:tags":[
        "facility",
        "club",
        "gymnasium",
        "health",
        "fitness",
        "studio",
        "physical"
    ],
    "wof:name":"Curves For Women",
    "wof:placetype":"venue"
},
  "geometry": {"coordinates":[-87.903462,43.140265],"type":"Point"}
}