{
  "type": "Feature",
  "properties": {
    "iso:country":"US",
    "sg:address":"119 E 2nd St",
    "sg:city":"New Richmond",
    "sg:classifiers":[
        {
            "category":"Organizations",
            "subcategory":"Professional Association",
            "type":"Services"
        }
    ],
    "sg:phone":"+1 715 246 2144",
    "sg:postcode":"54017",
    "sg:province":"WI",
    "wof:name":"Masonic Lodge",
    "wof:placetype":"venue"
},
  "geometry": {"coordinates":[-92.537294,45.121731],"type":"Point"}
}