{
  "type": "Feature",
  "properties": {
    "iso:country":"US",
    "sg:address":"8032 State Rd",
    "sg:city":"Chippewa Falls",
    "sg:classifiers":[
        {
            "category":"Farming",
            "subcategory":"Farm & Veterinary Services",
            "type":"Manufacturing & Wholesale Goods"
        }
    ],
    "sg:phone":"+1 715 723 8158",
    "sg:postcode":"54729",
    "sg:province":"WI",
    "sg:tags":[
        "drying",
        "grain"
    ],
    "wof:name":"Mill & Farm Supply Inc",
    "wof:placetype":"venue"
},
  "geometry": {"coordinates":[-91.388625,44.961628],"type":"Point"}
}