{
  "type": "Feature",
  "properties": {
    "addr:full":"16058 US Hwy 63 Hayward WI 54843",
    "addr:postcode":"16058;54843",
    "addr:street":"Us Hwy 63",
    "iso:country":"US",
    "sg:address":"16058 US Hwy 63",
    "sg:city":"Hayward",
    "sg:classifiers":[
        {
            "category":"Wholesale",
            "subcategory":"Electrical",
            "type":"Manufacturing & Wholesale Goods"
        }
    ],
    "sg:phone":"+1 715 634 2301",
    "sg:postcode":"54843",
    "sg:province":"WI",
    "sg:tags":[
        "supply"
    ],
    "wof:name":"Lights Algow Lighting Studio",
    "wof:placetype":"venue"
},
  "geometry": {"coordinates":[-91.492828,46.00722],"type":"Point"}
}