{
  "type": "Feature",
  "properties": {
    "iso:country":"US",
    "sg:address":"3803 Soda Creek Rd",
    "sg:city":"Marathon",
    "sg:classifiers":[
        {
            "category":"Retail",
            "subcategory":"Portrait Studio",
            "type":"Services"
        }
    ],
    "sg:phone":"+1 715 443 6363",
    "sg:postcode":"54448",
    "sg:province":"WI",
    "sg:tags":[
        "photo"
    ],
    "sg:website":"www.laurajstudios.com",
    "wof:name":"Laura J Studios",
    "wof:placetype":"venue"
},
  "geometry": {"coordinates":[-89.89447,44.916143],"type":"Point"}
}