{
  "type": "Feature",
  "properties": {
    "addr:full":"114 E Union St Waupaca WI 54981",
    "addr:housenumber":"114",
    "addr:postcode":"54981",
    "addr:street":"E Union St",
    "iso:country":"US",
    "sg:address":"114 E Union St",
    "sg:city":"Waupaca",
    "sg:classifiers":[
        {
            "category":"Banks & Credit Unions",
            "subcategory":"Bank",
            "type":"Services"
        }
    ],
    "sg:phone":"+1 715 258 3898",
    "sg:postcode":"54981",
    "sg:province":"WI",
    "sg:tags":[
        "national",
        "commercial"
    ],
    "wof:name":"First State Bank",
    "wof:placetype":"venue"
},
  "geometry": {"coordinates":[-89.084767,44.357004],"type":"Point"}
}