{
  "type": "Feature",
  "properties": {
    "iso:country":"US",
    "sg:address":"1019 Michigan Ave",
    "sg:city":"Sheboygan",
    "sg:classifiers":[
        {
            "category":"Insurance",
            "subcategory":"Insurance Agent",
            "type":"Services"
        }
    ],
    "sg:phone":"+1 920 458 8400",
    "sg:postcode":"53081",
    "sg:province":"WI",
    "sg:website":"www.keyinsuranceinc.com",
    "wof:name":"Key Insurance Svc",
    "wof:placetype":"venue"
},
  "geometry": {"coordinates":[-87.717725,43.758469],"type":"Point"}
}