{
  "type": "Feature",
  "properties": {
    "iso:country":"US",
    "sg:address":"2341 Fawn Rd",
    "sg:city":"Mosinee",
    "sg:classifiers":[
        {
            "category":"Bars & Pubs",
            "type":"Food & Drink"
        }
    ],
    "sg:phone":"+1 715 693 1909",
    "sg:postcode":"54455",
    "sg:province":"WI",
    "wof:name":"Half Moon Bar",
    "wof:placetype":"venue"
},
  "geometry": {"coordinates":[-89.690707,44.85377],"type":"Point"}
}