{
  "type": "Feature",
  "properties": {
    "iso:country":"US",
    "sg:address":"5662 Glendale Ave",
    "sg:city":"Green Bay",
    "sg:classifiers":[
        {
            "category":"Manufacturing",
            "subcategory":"Furniture",
            "type":"Manufacturing & Wholesale Goods"
        }
    ],
    "sg:phone":"+1 920 865 7307",
    "sg:postcode":"54313",
    "sg:province":"WI",
    "sg:tags":[
        "building",
        "structural",
        "metal",
        "public",
        "mfg"
    ],
    "sg:website":"www.jwindustriesinc.com",
    "wof:name":"J W Industries Inc",
    "wof:placetype":"venue"
},
  "geometry": {"coordinates":[-88.180193,44.587438],"type":"Point"}
}