{
  "type": "Feature",
  "properties": {
    "iso:country":"US",
    "sg:address":"4153 Lily Rd",
    "sg:city":"West Bend",
    "sg:classifiers":[
        {
            "category":"Retail",
            "subcategory":"Repair Shop",
            "type":"Services"
        }
    ],
    "sg:phone":"+1 262 677 0626",
    "sg:postcode":"53095",
    "sg:province":"WI",
    "sg:tags":[
        "welding"
    ],
    "wof:name":"J P Streets Welding",
    "wof:placetype":"venue"
},
  "geometry": {"coordinates":[-88.23233,43.350777],"type":"Point"}
}