{
  "type": "Feature",
  "properties": {
    "addr:full":"7695 State Hwy 64 Merrill WI 54452",
    "addr:housenumber":"7695",
    "addr:postcode":"54452",
    "addr:street":"State Hwy 64",
    "iso:country":"US",
    "sg:address":"7695 State Hwy 64",
    "sg:city":"Merrill",
    "sg:classifiers":[
        {
            "category":"Bars & Pubs",
            "type":"Food & Drink"
        }
    ],
    "sg:phone":"+1 715 536 5608",
    "sg:postcode":"54452",
    "sg:province":"WI",
    "sg:tags":[
        "drinking"
    ],
    "wof:name":"Dipper Little",
    "wof:placetype":"venue"
},
  "geometry": {"coordinates":[-89.810697,45.177987],"type":"Point"}
}