{
  "type": "Feature",
  "properties": {
    "iso:country":"US",
    "sg:address":"5402 Mineral Point Rd",
    "sg:city":"Madison",
    "sg:classifiers":[
        {
            "category":"Real Estate",
            "subcategory":"Real Estate Agent",
            "type":"Services"
        }
    ],
    "sg:phone":"+1 608 233 7171",
    "sg:postcode":"53705",
    "sg:province":"WI",
    "wof:name":"Metro Brokers Advantage Group",
    "wof:placetype":"venue"
},
  "geometry": {"coordinates":[-89.478429,43.060918],"type":"Point"}
}