{
  "type": "Feature",
  "properties": {
    "addr:full":"4731 W Willow Rd Thiensville WI 53092",
    "addr:housenumber":"4731",
    "addr:postcode":"53092",
    "addr:street":"W Willow Rd",
    "iso:country":"US",
    "sg:address":"4731 W Willow Rd",
    "sg:city":"Thiensville",
    "sg:classifiers":[
        {
            "category":"Retail",
            "subcategory":"Repair Shop",
            "type":"Services"
        }
    ],
    "sg:phone":"+1 262 512 1411",
    "sg:postcode":"53092",
    "sg:province":"WI",
    "wof:name":"Arrowhd Piano Svc",
    "wof:placetype":"venue"
},
  "geometry": {"coordinates":[-87.97176399999999,43.196795],"type":"Point"}
}