{
  "type": "Feature",
  "properties": {
    "addr:full":"710 Wolf River Dr Fremont WI 54940",
    "addr:housenumber":"710",
    "addr:postcode":"54940",
    "addr:street":"Wolf River Dr",
    "iso:country":"US",
    "sg:address":"710 Wolf River Dr",
    "sg:city":"Fremont",
    "sg:classifiers":[
        {
            "category":"Restaurant",
            "type":"Food & Drink"
        }
    ],
    "sg:phone":"+1 920 446 3261",
    "sg:postcode":"54940",
    "sg:province":"WI",
    "wof:name":"Grandview Supper Club",
    "wof:placetype":"venue"
},
  "geometry": {"coordinates":[-88.878139,44.264466],"type":"Point"}
}