{
  "type": "Feature",
  "properties": {
    "iso:country":"US",
    "sg:address":"9101 N 107th St",
    "sg:city":"Milwaukee",
    "sg:classifiers":[
        {
            "category":"Internet Cafe",
            "subcategory":"None",
            "type":"Food & Drink"
        },
        {
            "category":"Professional",
            "subcategory":"Computer Services",
            "type":"Services"
        }
    ],
    "sg:phone":"+1 414 362 1514",
    "sg:postcode":"53224",
    "sg:province":"WI",
    "sg:tags":[
        "product",
        "isp",
        "provider"
    ],
    "wof:name":"Bandwidthcom",
    "wof:placetype":"venue"
},
  "geometry": {"coordinates":[-88.044057,43.182763],"type":"Point"}
}