{
  "type": "Feature",
  "properties": {
    "addr:full":"839 N 6th St Manitowoc WI 54220",
    "addr:housenumber":"839",
    "addr:postcode":"54220",
    "addr:street":"N 6Th St",
    "iso:country":"US",
    "sg:address":"839 N 6th St",
    "sg:city":"Manitowoc",
    "sg:classifiers":[
        {
            "category":"Building & Trades",
            "subcategory":"Construction",
            "type":"Services"
        }
    ],
    "sg:phone":"+1 920 682 6016",
    "sg:postcode":"54220",
    "sg:province":"WI",
    "sg:tags":[
        "contractor"
    ],
    "wof:name":"Personal Restoration Finishes",
    "wof:placetype":"venue"
},
  "geometry": {"coordinates":[-87.654731,44.104255],"type":"Point"}
}