{
  "type": "Feature",
  "properties": {
    "iso:country":"US",
    "sg:address":"3450 US Hwy 51 N",
    "sg:city":"Woodruff",
    "sg:classifiers":[
        {
            "category":"Travel",
            "subcategory":"Hotels & Motels",
            "type":"Entertainment"
        }
    ],
    "sg:phone":"+1 715 385 2994",
    "sg:postcode":"54568",
    "sg:province":"WI",
    "sg:tags":[
        "resort"
    ],
    "wof:name":"Franklin Coon's Lodge",
    "wof:placetype":"venue"
},
  "geometry": {"coordinates":[-89.695927,46.013762],"type":"Point"}
}