{
  "type": "Feature",
  "properties": {
    "iso:country":"US",
    "sg:address":"2483 Woodhaven Rd",
    "sg:city":"Eau Claire",
    "sg:classifiers":[
        {
            "category":"Manufacturing",
            "subcategory":"Printing",
            "type":"Manufacturing & Wholesale Goods"
        }
    ],
    "sg:phone":"+1 715 835 8929",
    "sg:postcode":"54703",
    "sg:province":"WI",
    "sg:tags":[
        "newspaper"
    ],
    "wof:name":"Senior Review",
    "wof:placetype":"venue"
},
  "geometry": {"coordinates":[-91.44267499999999,44.84651],"type":"Point"}
}