{
  "type": "Feature",
  "properties": {
    "iso:country":"US",
    "sg:address":"6320 Monona Dr",
    "sg:city":"Monona",
    "sg:classifiers":[
        {
            "category":"Real Estate",
            "subcategory":"Real Estate Services",
            "type":"Services"
        }
    ],
    "sg:phone":"+1 608 221 0420",
    "sg:postcode":"53716",
    "sg:province":"WI",
    "sg:tags":[
        "company",
        "title"
    ],
    "wof:name":"Park View Title Research Assoc",
    "wof:placetype":"venue"
},
  "geometry": {"coordinates":[-89.325183,43.053057],"type":"Point"}
}