{
  "type": "Feature",
  "properties": {
    "addr:full":"316 E Buffalo St Milwaukee WI 53202",
    "addr:housenumber":"316",
    "addr:postcode":"53202",
    "addr:street":"E Buffalo St",
    "iso:country":"US",
    "sg:address":"316 E Buffalo St",
    "sg:city":"Milwaukee",
    "sg:classifiers":[
        {
            "category":"Professional",
            "subcategory":"Accounting & Tax Preparation",
            "type":"Services"
        }
    ],
    "sg:phone":"+1 414 727 2361",
    "sg:postcode":"53202",
    "sg:province":"WI",
    "sg:tags":[
        "accountant"
    ],
    "wof:name":"Sequence Inc",
    "wof:placetype":"venue"
},
  "geometry": {"coordinates":[-87.906125,43.03398],"type":"Point"}
}