{
  "type": "Feature",
  "properties": {
    "iso:country":"US",
    "sg:address":"7415 W Becher St",
    "sg:city":"Milwaukee",
    "sg:classifiers":[
        {
            "category":"Banks & Credit Unions",
            "subcategory":"Bank",
            "type":"Services"
        }
    ],
    "sg:phone":"+1 414 431 0070",
    "sg:postcode":"53219",
    "sg:province":"WI",
    "sg:tags":[
        "loan",
        "real estate"
    ],
    "wof:name":"Castle Mortgage",
    "wof:placetype":"venue"
},
  "geometry": {"coordinates":[-88.006097,43.006261],"type":"Point"}
}