{
  "type": "Feature",
  "properties": {
    "iso:country":"US",
    "sg:address":"5986 Co Rd B",
    "sg:city":"Pittsville",
    "sg:classifiers":[
        {
            "category":"Farming",
            "subcategory":"Farm",
            "type":"Manufacturing & Wholesale Goods"
        }
    ],
    "sg:phone":"+1 715 884 6918",
    "sg:postcode":"54466",
    "sg:province":"WI",
    "sg:tags":[
        "crop",
        "general"
    ],
    "wof:name":"Carls Farm",
    "wof:placetype":"venue"
},
  "geometry": {"coordinates":[-90.219096,44.453378],"type":"Point"}
}