{
  "type": "Feature",
  "properties": {
    "iso:country":"US",
    "sg:address":"3220 48th St S",
    "sg:city":"Wisconsin Rapids",
    "sg:classifiers":[
        {
            "category":"Retail",
            "subcategory":"Repair Shop",
            "type":"Services"
        }
    ],
    "sg:phone":"+1 715 424 2991",
    "sg:postcode":"54494",
    "sg:province":"WI",
    "sg:tags":[
        "taxidermist"
    ],
    "wof:name":"Pro Fish Taxidermy",
    "wof:placetype":"venue"
},
  "geometry": {"coordinates":[-89.765419,44.365778],"type":"Point"}
}