{
  "type": "Feature",
  "properties": {
    "iso:country":"US",
    "sg:address":"325 N Washington St",
    "sg:city":"Berlin",
    "sg:classifiers":[
        {
            "category":"Retail",
            "subcategory":"Repair Shop",
            "type":"Services"
        }
    ],
    "sg:phone":"+1 920 361 0353",
    "sg:postcode":"54923",
    "sg:province":"WI",
    "sg:tags":[
        "armature",
        "rewinding",
        "merchandise",
        "mfg"
    ],
    "wof:name":"Electric Motor Service",
    "wof:placetype":"venue"
},
  "geometry": {"coordinates":[-88.956974,43.97672],"type":"Point"}
}