{
  "type": "Feature",
  "properties": {
    "addr:full":"222 S Main St River Falls WI 54022",
    "addr:housenumber":"222",
    "addr:postcode":"54022",
    "addr:street":"S Main St",
    "iso:country":"US",
    "sg:address":"222 S Main St",
    "sg:city":"River Falls",
    "sg:classifiers":[
        {
            "category":"Bars & Pubs",
            "type":"Food & Drink"
        }
    ],
    "sg:phone":"+1 715 425 2053",
    "sg:postcode":"54022",
    "sg:province":"WI",
    "wof:name":"Emma's Bar",
    "wof:placetype":"venue"
},
  "geometry": {"coordinates":[-92.62682599999999,44.856474],"type":"Point"}
}