{
  "type": "Feature",
  "properties": {
    "iso:country":"US",
    "sg:address":"1230 Crossing Meadows Dr",
    "sg:city":"Onalaska",
    "sg:classifiers":[
        {
            "category":"Banks & Credit Unions",
            "subcategory":"Bank",
            "type":"Services"
        }
    ],
    "sg:phone":"+1 608 783 7643",
    "sg:postcode":"54650",
    "sg:province":"WI",
    "sg:tags":[
        "loan",
        "real estate"
    ],
    "wof:name":"Beneficial Wisconsin Inc",
    "wof:placetype":"venue"
},
  "geometry": {"coordinates":[-91.214422,43.870091],"type":"Point"}
}