{
  "type": "Feature",
  "properties": {
    "iso:country":"US",
    "sg:address":"2837 Sylvester Dr",
    "sg:city":"Hartland",
    "sg:classifiers":[
        {
            "category":"Building & Trades",
            "subcategory":"Landscaping Services",
            "type":"Services"
        }
    ],
    "sg:phone":"+1 262 367 7257",
    "sg:postcode":"53029",
    "sg:province":"WI",
    "sg:tags":[
        "landscape",
        "contractor"
    ],
    "wof:name":"Mr Tree & Landscaping",
    "wof:placetype":"venue"
},
  "geometry": {"coordinates":[-88.384072,43.082942],"type":"Point"}
}