{
  "type": "Feature",
  "properties": {
    "addr:full":"2341 Effingham Way Sun Prairie WI 53590",
    "addr:housenumber":"2341",
    "addr:postcode":"53590",
    "addr:street":"Effingham Way",
    "iso:country":"US",
    "sg:address":"2341 Effingham Way",
    "sg:city":"Sun Prairie",
    "sg:classifiers":[
        {
            "category":"Real Estate",
            "subcategory":"Real Estate Agent",
            "type":"Services"
        }
    ],
    "sg:phone":"+1 608 837 5125",
    "sg:postcode":"53590",
    "sg:province":"WI",
    "wof:name":"Ray Unker",
    "wof:placetype":"venue"
},
  "geometry": {"coordinates":[-89.255263,43.188029],"type":"Point"}
}