{
  "type": "Feature",
  "properties": {
    "iso:country":"US",
    "sg:address":"3456 Moens Lake Dr",
    "sg:city":"Rhinelander",
    "sg:classifiers":[
        {
            "category":"Building & Trades",
            "subcategory":"Construction",
            "type":"Services"
        }
    ],
    "sg:phone":"+1 715 369 2872",
    "sg:postcode":"54501",
    "sg:province":"WI",
    "sg:tags":[
        "excavation",
        "excavating",
        "contractor"
    ],
    "wof:name":"Oettinger Excavating Inc",
    "wof:placetype":"venue"
},
  "geometry": {"coordinates":[-89.285966,45.664248],"type":"Point"}
}