{
  "type": "Feature",
  "properties": {
    "iso:country":"US",
    "sg:address":"8877 Long Rd",
    "sg:city":"Watertown",
    "sg:classifiers":[
        {
            "category":"Real Estate",
            "subcategory":"Real Estate Operator",
            "type":"Services"
        }
    ],
    "sg:phone":"+1 920 261 0702",
    "sg:postcode":"53098",
    "sg:province":"WI",
    "sg:tags":[
        "property",
        "lessor"
    ],
    "wof:name":"Raymond Peirick",
    "wof:placetype":"venue"
},
  "geometry": {"coordinates":[-88.83502300000001,43.22677],"type":"Point"}
}