{
  "type": "Feature",
  "properties": {
    "iso:country":"US",
    "sg:address":"2353 W Central Ave",
    "sg:city":"Brantwood",
    "sg:classifiers":[
        {
            "category":"Freight",
            "type":"Transportation"
        }
    ],
    "sg:phone":"+1 715 564 2492",
    "sg:postcode":"54513",
    "sg:province":"WI",
    "sg:tags":[
        "operator",
        "local",
        "trucking"
    ],
    "wof:name":"Beaumont Trucking",
    "wof:placetype":"venue"
},
  "geometry": {"coordinates":[-90.161231,45.539232],"type":"Point"}
}