{
  "type": "Feature",
  "properties": {
    "iso:country":"US",
    "sg:address":"601 N Military Ave",
    "sg:city":"Green Bay",
    "sg:classifiers":[
        {
            "category":"Autos & Motor Vehicles",
            "subcategory":"Fuel & Gas Station",
            "type":"Retail Goods"
        }
    ],
    "sg:phone":"+1 920 497 7704",
    "sg:postcode":"54303",
    "sg:province":"WI",
    "sg:tags":[
        "oil"
    ],
    "wof:name":"Fox Convenience",
    "wof:placetype":"venue"
},
  "geometry": {"coordinates":[-88.052993,44.539957],"type":"Point"}
}