{
  "type": "Feature",
  "properties": {
    "iso:country":"US",
    "sg:address":"9809 W Oklahoma Ave",
    "sg:city":"Milwaukee",
    "sg:classifiers":[
        {
            "category":"Restaurant",
            "type":"Food & Drink"
        }
    ],
    "sg:menulink":"http://www.allmenus.com/wi/milwaukee/114323-rosatis-pizza/menu/",
    "sg:phone":"+1 414 543 1300",
    "sg:postcode":"53227",
    "sg:province":"WI",
    "sg:tags":[
        "american",
        "pizza"
    ],
    "wof:name":"Rosati's Pizza",
    "wof:placetype":"venue"
},
  "geometry": {"coordinates":[-88.034969,42.988022],"type":"Point"}
}