{
  "type": "Feature",
  "properties": {
    "iso:country":"US",
    "sg:address":"763 S River Rd",
    "sg:city":"West Bend",
    "sg:classifiers":[
        {
            "category":"Real Estate",
            "subcategory":"Real Estate Agent",
            "type":"Services"
        }
    ],
    "sg:phone":"+1 262 338 3975",
    "sg:postcode":"53095",
    "sg:province":"WI",
    "wof:name":"Leno Realty Co",
    "wof:placetype":"venue"
},
  "geometry": {"coordinates":[-88.161168,43.412314],"type":"Point"}
}