{
  "type": "Feature",
  "properties": {
    "iso:country":"US",
    "sg:address":"560 Jefferson St",
    "sg:city":"Platteville",
    "sg:classifiers":[
        {
            "category":"Restaurant",
            "type":"Food & Drink"
        }
    ],
    "sg:phone":"+1 608 348 6761",
    "sg:postcode":"53818",
    "sg:province":"WI",
    "sg:tags":[
        "eating"
    ],
    "wof:name":"McDermotts Cafe On The Main",
    "wof:placetype":"venue"
},
  "geometry": {"coordinates":[-90.472857,42.738244],"type":"Point"}
}