{
  "type": "Feature",
  "properties": {
    "iso:country":"US",
    "sg:address":"519 Oak Park Ave",
    "sg:city":"Watertown",
    "sg:phone":"+1 920 261 0421",
    "sg:postcode":"53098",
    "sg:province":"WI",
    "sg:tags":[
        "communications",
        "telegraph"
    ],
    "wof:name":"Wika Instrument Corp",
    "wof:placetype":"venue"
},
  "geometry": {"coordinates":[-88.711656,43.207526],"type":"Point"}
}