{
  "type": "Feature",
  "properties": {
    "iso:country":"US",
    "sg:address":"7303 W Center St",
    "sg:city":"Milwaukee",
    "sg:classifiers":[
        {
            "category":"Professional",
            "subcategory":"Business Services",
            "type":"Services"
        }
    ],
    "sg:phone":"+1 414 273 2202",
    "sg:postcode":"53210",
    "sg:province":"WI",
    "sg:tags":[
        "recording",
        "studio"
    ],
    "wof:name":"Surround In Sound Studio",
    "wof:placetype":"venue"
},
  "geometry": {"coordinates":[-88.005043,43.067963],"type":"Point"}
}