{
  "type": "Feature",
  "properties": {
    "iso:country":"US",
    "sg:address":"27680 265th St",
    "sg:city":"Holcombe",
    "sg:classifiers":[
        {
            "category":"Professional",
            "subcategory":"Business Services",
            "type":"Services"
        }
    ],
    "sg:phone":"+1 715 595 4964",
    "sg:postcode":"54745",
    "sg:province":"WI",
    "wof:name":"Bluff Country Enterprises LLC",
    "wof:placetype":"venue"
},
  "geometry": {"coordinates":[-91.141219,45.24942],"type":"Point"}
}