{
  "type": "Feature",
  "properties": {
    "iso:country":"US",
    "sg:address":"418 Corbett Ave W",
    "sg:city":"Ladysmith",
    "sg:classifiers":[
        {
            "category":"Social Services",
            "subcategory":"Child Care",
            "type":"Services"
        }
    ],
    "sg:phone":"+1 715 532 9719",
    "sg:postcode":"54848",
    "sg:province":"WI",
    "sg:tags":[
        "kindergarten",
        "academic",
        "school"
    ],
    "wof:name":"Ladysmith Montessori Preschool",
    "wof:placetype":"venue"
},
  "geometry": {"coordinates":[-91.105924,45.461239],"type":"Point"}
}