{
  "type": "Feature",
  "properties": {
    "iso:country":"US",
    "sg:address":"12601 W Janesville Rd",
    "sg:city":"Muskego",
    "sg:classifiers":[
        {
            "category":"Building & Trades",
            "subcategory":"Landscaping Services",
            "type":"Services"
        }
    ],
    "sg:phone":"+1 414 425 4331",
    "sg:postcode":"53150",
    "sg:province":"WI",
    "sg:tags":[
        "lawn"
    ],
    "wof:name":"Naturescape",
    "wof:placetype":"venue"
},
  "geometry": {"coordinates":[-88.071707,42.931963],"type":"Point"}
}