{
  "type": "Feature",
  "properties": {
    "iso:country":"US",
    "sg:address":"2206 N Quincy St",
    "sg:city":"Green Bay",
    "sg:classifiers":[
        {
            "category":"Wholesale",
            "subcategory":"Petroleum",
            "type":"Manufacturing & Wholesale Goods"
        }
    ],
    "sg:phone":"+1 920 436 4000",
    "sg:postcode":"54302",
    "sg:province":"WI",
    "sg:tags":[
        "product"
    ],
    "wof:name":"Halron Oil Co Inc",
    "wof:placetype":"venue"
},
  "geometry": {"coordinates":[-87.99401400000001,44.532859],"type":"Point"}
}