{
  "type": "Feature",
  "properties": {
    "iso:country":"US",
    "sg:address":"1601 Glacier Hill Dr",
    "sg:city":"Madison",
    "sg:classifiers":[
        {
            "category":"Real Estate",
            "subcategory":"Real Estate Operator",
            "type":"Services"
        }
    ],
    "sg:phone":"+1 608 204 9855",
    "sg:postcode":"53704",
    "sg:province":"WI",
    "sg:tags":[
        "apartment"
    ],
    "wof:name":"Steinhofer Properties",
    "wof:placetype":"venue"
},
  "geometry": {"coordinates":[-89.29122099999999,43.120512],"type":"Point"}
}