{
  "type": "Feature",
  "properties": {
    "addr:full":"820 E Wisconsin St Delavan WI 53115",
    "addr:housenumber":"820",
    "addr:postcode":"53115",
    "addr:street":"E Wisconsin St",
    "iso:country":"US",
    "sg:address":"820 E Wisconsin St",
    "sg:city":"Delavan",
    "sg:classifiers":[
        {
            "category":"Building & Trades",
            "subcategory":"Construction",
            "type":"Services"
        }
    ],
    "sg:phone":"+1 262 740 1678",
    "sg:postcode":"53115",
    "sg:province":"WI",
    "sg:tags":[
        "woodworker"
    ],
    "wof:name":"Big Timber Technology",
    "wof:placetype":"venue"
},
  "geometry": {"coordinates":[-88.635994,42.631808],"type":"Point"}
}