{
  "type": "Feature",
  "properties": {
    "iso:country":"US",
    "sg:address":"1702 W Center Rd",
    "sg:city":"Saukville",
    "sg:classifiers":[
        {
            "category":"Building & Trades",
            "subcategory":"Cleaning & Sanitation",
            "type":"Services"
        }
    ],
    "sg:phone":"+1 262 284 0296",
    "sg:postcode":"53080",
    "sg:province":"WI",
    "sg:tags":[
        "maintenance"
    ],
    "wof:name":"Watrys Maintenance Svc",
    "wof:placetype":"venue"
},
  "geometry": {"coordinates":[-87.948196,43.411558],"type":"Point"}
}