{
  "type": "Feature",
  "properties": {
    "iso:country":"US",
    "sg:address":"8158 Sunset Ln",
    "sg:city":"Ixonia",
    "sg:classifiers":[
        {
            "category":"Shopping",
            "subcategory":"Clothing, Apparel, & Fashions",
            "type":"Retail Goods"
        }
    ],
    "sg:phone":"+1 262 567 2713",
    "sg:postcode":"53036",
    "sg:province":"WI",
    "sg:tags":[
        "shop",
        "bridal"
    ],
    "wof:name":"Lake Country Bridal",
    "wof:placetype":"venue"
},
  "geometry": {"coordinates":[-88.557959,43.137214],"type":"Point"}
}