{
  "type": "Feature",
  "properties": {
    "addr:full":"3510 W Howard Ave Milwaukee WI 53221",
    "addr:housenumber":"3510",
    "addr:postcode":"53221",
    "addr:street":"W Howard Ave",
    "iso:country":"US",
    "sg:address":"3510 W Howard Ave",
    "sg:city":"Milwaukee",
    "sg:classifiers":[
        {
            "category":"Autos & Motor Vehicles",
            "subcategory":"Recreational Vehicle Sales",
            "type":"Retail Goods"
        }
    ],
    "sg:phone":"+1 414 281 8858",
    "sg:postcode":"53221",
    "sg:province":"WI",
    "wof:name":"Busy Bee Rv Sales Parts & Svc",
    "wof:placetype":"venue"
},
  "geometry": {"coordinates":[-87.959504,42.973992],"type":"Point"}
}