{
  "type": "Feature",
  "properties": {
    "iso:country":"US",
    "sg:address":"21001 Watertown Rd",
    "sg:city":"Waukesha",
    "sg:classifiers":[
        {
            "category":"Wholesale",
            "subcategory":"Durable Goods & Equipment",
            "type":"Manufacturing & Wholesale Goods"
        }
    ],
    "sg:phone":"+1 262 786 4400",
    "sg:postcode":"53186",
    "sg:province":"WI",
    "sg:tags":[
        "representative",
        "manufacturer"
    ],
    "sg:website":"www.techtronwi.com",
    "wof:name":"Tech Tron Sales",
    "wof:placetype":"venue"
},
  "geometry": {"coordinates":[-88.175448,43.04145],"type":"Point"}
}