{
  "type": "Feature",
  "properties": {
    "iso:country":"US",
    "sg:address":"1724 N Silverspring Dr",
    "sg:city":"Appleton",
    "sg:classifiers":[
        {
            "category":"Bus Charters",
            "type":"Transportation"
        }
    ],
    "sg:phone":"+1 920 722 1400",
    "sg:postcode":"54913",
    "sg:province":"WI",
    "sg:tags":[
        "rental"
    ],
    "wof:name":"Lorvel Express",
    "wof:placetype":"venue"
},
  "geometry": {"coordinates":[-88.48223299999999,44.274754],"type":"Point"}
}