{
  "type": "Feature",
  "properties": {
    "iso:country":"US",
    "sg:address":"222 S Spring St",
    "sg:city":"Beaver Dam",
    "sg:classifiers":[
        {
            "category":"Professional",
            "subcategory":"Accounting & Tax Preparation",
            "type":"Services"
        }
    ],
    "sg:phone":"+1 920 887 2200",
    "sg:postcode":"53916",
    "sg:province":"WI",
    "sg:tags":[
        "accountant"
    ],
    "wof:name":"L R Peck Inc",
    "wof:placetype":"venue"
},
  "geometry": {"coordinates":[-88.836979,43.455042],"type":"Point"}
}