{
  "type": "Feature",
  "properties": {
    "iso:country":"US",
    "sg:address":"5501 Barton Rd",
    "sg:city":"Madison",
    "sg:classifiers":[
        {
            "category":"Real Estate",
            "subcategory":"Real Estate Operator",
            "type":"Services"
        }
    ],
    "sg:phone":"+1 608 271 0604",
    "sg:postcode":"53711",
    "sg:province":"WI",
    "sg:tags":[
        "building",
        "nonresidential"
    ],
    "wof:name":"Barton Road Ltd Partnership",
    "wof:placetype":"venue"
},
  "geometry": {"coordinates":[-89.477644,43.035872],"type":"Point"}
}