{
  "type": "Feature",
  "properties": {
    "iso:country":"US",
    "sg:address":"5927 Middle Rd",
    "sg:city":"Racine",
    "sg:classifiers":[
        {
            "category":"Building & Trades",
            "subcategory":"Construction",
            "type":"Services"
        },
        {
            "category":"Building & Trades",
            "subcategory":"Landscaping Services",
            "type":"Services"
        }
    ],
    "sg:phone":"+1 262 639 0296",
    "sg:postcode":"53402",
    "sg:province":"WI",
    "sg:tags":[
        "excavation",
        "landscape",
        "contractor"
    ],
    "wof:name":"Macemon & Sons Inc",
    "wof:placetype":"venue"
},
  "geometry": {"coordinates":[-87.81603699999999,42.797809],"type":"Point"}
}