{
  "type": "Feature",
  "properties": {
    "iso:country":"US",
    "sg:address":"1800 River St",
    "sg:city":"Rhinelander",
    "sg:classifiers":[
        {
            "category":"Building & Trades",
            "subcategory":"Plumbing",
            "type":"Services"
        }
    ],
    "sg:phone":"+1 715 369 7621",
    "sg:postcode":"54501",
    "sg:province":"WI",
    "sg:tags":[
        "plumbing",
        "contractor"
    ],
    "wof:name":"Metz Plumbing Inc",
    "wof:placetype":"venue"
},
  "geometry": {"coordinates":[-89.438818,45.644899],"type":"Point"}
}