{
  "type": "Feature",
  "properties": {
    "iso:country":"US",
    "sg:address":"8524 W Capitol Dr",
    "sg:city":"Milwaukee",
    "sg:classifiers":[
        {
            "category":"Personal",
            "subcategory":"Barber",
            "type":"Services"
        }
    ],
    "sg:phone":"+1 414 466 1234",
    "sg:postcode":"53222",
    "sg:province":"WI",
    "sg:tags":[
        "shop",
        "mobile",
        "site",
        "operator",
        "home",
        "drinking"
    ],
    "wof:name":"Bills Barber Shop",
    "wof:placetype":"venue"
},
  "geometry": {"coordinates":[-88.019862,43.089874],"type":"Point"}
}