{
  "type": "Feature",
  "properties": {
    "iso:country":"US",
    "sg:address":"6205 N 84th St",
    "sg:city":"Milwaukee",
    "sg:classifiers":[
        {
            "category":"Recreation",
            "type":"Entertainment"
        }
    ],
    "sg:phone":"+1 414 760 3024",
    "sg:postcode":"53225",
    "sg:province":"WI",
    "sg:tags":[
        "amusement"
    ],
    "wof:name":"Miss Margaret's Playschool",
    "wof:placetype":"venue"
},
  "geometry": {"coordinates":[-88.015756,43.131863],"type":"Point"}
}