{
  "type": "Feature",
  "properties": {
    "iso:country":"US",
    "sg:address":"2818 Lincolnshire Ct",
    "sg:city":"Waukesha",
    "sg:classifiers":[
        {
            "category":"Personal",
            "subcategory":"Beauty Salon",
            "type":"Services"
        }
    ],
    "sg:phone":"+1 262 574 9328",
    "sg:postcode":"53188",
    "sg:province":"WI",
    "sg:tags":[
        "shop"
    ],
    "wof:name":"Blush Beauty Inc",
    "wof:placetype":"venue"
},
  "geometry": {"coordinates":[-88.276988,43.039903],"type":"Point"}
}