{
  "type": "Feature",
  "properties": {
    "addr:full":"1401 Donald St Green Bay WI 54303",
    "addr:housenumber":"1401",
    "addr:postcode":"54303",
    "addr:street":"Donald St",
    "iso:country":"US",
    "sg:address":"1401 Donald St",
    "sg:city":"Green Bay",
    "sg:classifiers":[
        {
            "category":"Autos & Motor Vehicles",
            "subcategory":"Automobile Sales",
            "type":"Retail Goods"
        }
    ],
    "sg:phone":"+1 920 499 0930",
    "sg:postcode":"54303",
    "sg:province":"WI",
    "sg:tags":[
        "car",
        "dealer"
    ],
    "wof:name":"Y-M Auto Sales",
    "wof:placetype":"venue"
},
  "geometry": {"coordinates":[-88.04458099999999,44.547218],"type":"Point"}
}