{
  "type": "Feature",
  "properties": {
    "addr:full":"609 W 10 1/2 St Monroe WI 53566",
    "addr:housenumber":"609;1 / 2",
    "addr:postcode":"53566",
    "addr:street":"W 10;St",
    "iso:country":"US",
    "sg:address":"609 W 10 1/2 St",
    "sg:city":"Monroe",
    "sg:classifiers":[
        {
            "category":"Autos & Motor Vehicles",
            "subcategory":"Fuel & Gas Station",
            "type":"Retail Goods"
        },
        {
            "category":"Autos & Motor Vehicles",
            "subcategory":"Auto Supplies",
            "type":"Retail Goods"
        }
    ],
    "sg:phone":"+1 608 329 5823",
    "sg:postcode":"53566",
    "sg:province":"WI",
    "sg:tags":[
        "lube",
        "oil"
    ],
    "wof:name":"Badger Express Lube",
    "wof:placetype":"venue"
},
  "geometry": {"coordinates":[-89.664405,42.601341],"type":"Point"}
}