{
  "type": "Feature",
  "properties": {
    "iso:country":"US",
    "sg:address":"3704 Sheridan Rd",
    "sg:city":"Kenosha",
    "sg:classifiers":[
        {
            "category":"Freight",
            "type":"Transportation"
        }
    ],
    "sg:phone":"+1 414 777 5549",
    "sg:postcode":"53140",
    "sg:province":"WI",
    "wof:name":"All American Star Pkg Crating",
    "wof:placetype":"venue"
},
  "geometry": {"coordinates":[-87.82315800000001,42.602846],"type":"Point"}
}