{
  "type": "Feature",
  "properties": {
    "iso:country":"US",
    "sg:address":"702 S Randall Ave",
    "sg:city":"Madison",
    "sg:classifiers":[
        {
            "category":"Museum",
            "subcategory":"Botanical Garden",
            "type":"Entertainment"
        }
    ],
    "sg:phone":"+1 608 258 1460",
    "sg:postcode":"53715",
    "sg:province":"WI",
    "sg:tags":[
        "zoo"
    ],
    "wof:name":"Zoological Society Henry Vilas",
    "wof:placetype":"venue"
},
  "geometry": {"coordinates":[-89.409058,43.060958],"type":"Point"}
}