{
  "type": "Feature",
  "properties": {
    "addr:city":"Madison",
    "addr:full":"702 S Randall Avenue Madison, Wi 53715-1600",
    "addr:house_number":"702",
    "addr:housenumber":"702",
    "addr:phone":"+1 608-266-4732",
    "addr:postcode":"53715-1600",
    "addr:road":"S Randall Avenue",
    "addr:state":"WI",
    "addr:street":"S Randall Ave",
    "iso:country":"US",
    "sg:address":"702 S Randall Ave",
    "sg:city":"Madison",
    "sg:classifiers":[
        {
            "category":"Museum",
            "subcategory":"Botanical Garden",
            "type":"Entertainment"
        }
    ],
    "sg:phone":"+1 608 258 1460",
    "sg:postcode":"53715",
    "sg:province":"WI",
    "sg:tags":[
        "zoo"
    ],
    "wof:airports":[
        102525659
    ],
    "wof:name":"Henry Vilas Zoo",
    "wof:placetype":"venue"
},
  "geometry": {"coordinates":[-89.40904,43.06092],"type":"Point"}
}