{
  "type": "Feature",
  "properties": {
    "iso:country":"US",
    "sg:address":"24050 3rd St",
    "sg:city":"Trempealeau",
    "sg:classifiers":[
        {
            "category":"Banks & Credit Unions",
            "subcategory":"Bank",
            "type":"Services"
        }
    ],
    "sg:phone":"+1 608 534 6335",
    "sg:postcode":"54661",
    "sg:province":"WI",
    "sg:tags":[
        "state",
        "commercial"
    ],
    "wof:name":"Citizens State Bank",
    "wof:placetype":"venue"
},
  "geometry": {"coordinates":[-91.434007,44.004141],"type":"Point"}
}