{
  "type": "Feature",
  "properties": {
    "addr:full":"1716 W Layton Ave Milwaukee WI 53221",
    "addr:housenumber":"1716",
    "addr:postcode":"53221",
    "addr:street":"W Layton Ave",
    "iso:country":"US",
    "sg:address":"1716 W Layton Ave",
    "sg:city":"Milwaukee",
    "sg:classifiers":[
        {
            "category":"Travel",
            "subcategory":"Hotels & Motels",
            "type":"Entertainment"
        }
    ],
    "sg:phone":"+1 414 282 7000",
    "sg:postcode":"53221",
    "sg:province":"WI",
    "sg:tags":[
        "operation",
        "eating",
        "drinking"
    ],
    "sg:website":"www.howardjohnson.com",
    "wof:name":"Howard Johnson",
    "wof:placetype":"venue"
},
  "geometry": {"coordinates":[-87.935157,42.959373],"type":"Point"}
}