{
  "type": "Feature",
  "properties": {
    "addr:full":"2222 S 114th St Milwaukee WI 53227",
    "addr:housenumber":"2222",
    "addr:postcode":"53227",
    "addr:street":"S 114Th St",
    "iso:country":"US",
    "sg:address":"2222 S 114th St",
    "sg:city":"Milwaukee",
    "sg:classifiers":[
        {
            "category":"Autos & Motor Vehicles",
            "subcategory":"Automobile Sales",
            "type":"Retail Goods"
        }
    ],
    "sg:phone":"+1 414 329 2886",
    "sg:postcode":"53227",
    "sg:province":"WI",
    "sg:tags":[
        "car",
        "dealer"
    ],
    "sg:website":"www.cufleet.com",
    "wof:name":"C U Fleet Department",
    "wof:placetype":"venue"
},
  "geometry": {"coordinates":[-88.054281,43.004896],"type":"Point"}
}