{
  "type": "Feature",
  "properties": {
    "iso:country":"US",
    "sg:address":"1010 High St",
    "sg:city":"Colfax",
    "sg:classifiers":[
        {
            "category":"Health Services",
            "subcategory":"Doctor",
            "type":"Services"
        }
    ],
    "sg:phone":"+1 715 962 3117",
    "sg:postcode":"54730",
    "sg:province":"WI",
    "sg:tags":[
        "physician",
        "surgeon"
    ],
    "wof:name":"Midelfort Clinic-Colfax",
    "wof:placetype":"venue"
},
  "geometry": {"coordinates":[-91.714738,45.002728],"type":"Point"}
}