{
  "type": "Feature",
  "properties": {
    "iso:country":"US",
    "sg:address":"225 Kings Lynn Rd",
    "sg:city":"Stoughton",
    "sg:classifiers":[
        {
            "category":"Shopping",
            "type":"Retail Goods"
        }
    ],
    "sg:phone":"+1 608 873 8357",
    "sg:postcode":"53589",
    "sg:province":"WI",
    "sg:tags":[
        "merchandise"
    ],
    "wof:name":"Cashroom Solutions Inc",
    "wof:placetype":"venue"
},
  "geometry": {"coordinates":[-89.240574,42.919397],"type":"Point"}
}