{
  "type": "Feature",
  "properties": {
    "addr:full":"5570 290th St Elmwood WI 54740",
    "addr:housenumber":"5570",
    "addr:postcode":"54740",
    "addr:street":"290Th St",
    "iso:country":"US",
    "sg:address":"5570 290th St",
    "sg:city":"Elmwood",
    "sg:classifiers":[
        {
            "category":"Farming",
            "subcategory":"Dairy Farm",
            "type":"Manufacturing & Wholesale Goods"
        }
    ],
    "sg:phone":"+1 715 639 6582",
    "sg:postcode":"54740",
    "sg:province":"WI",
    "wof:name":"Mike Raleigh",
    "wof:placetype":"venue"
},
  "geometry": {"coordinates":[-92.277271,44.741567],"type":"Point"}
}