{
  "type": "Feature",
  "properties": {
    "iso:country":"US",
    "sg:address":"2314 N Grandview Blvd",
    "sg:city":"Waukesha",
    "sg:classifiers":[
        {
            "category":"Banks & Credit Unions",
            "subcategory":"Bank",
            "type":"Services"
        }
    ],
    "sg:phone":"+1 262 548 6330",
    "sg:postcode":"53188",
    "sg:province":"WI",
    "sg:tags":[
        "loan",
        "real estate"
    ],
    "wof:name":"CLA Mortgage Inc",
    "wof:placetype":"venue"
},
  "geometry": {"coordinates":[-88.256083,43.03303],"type":"Point"}
}