{
  "type": "Feature",
  "properties": {
    "iso:country":"US",
    "sg:address":"1025 Regent St",
    "sg:city":"Madison",
    "sg:classifiers":[
        {
            "category":"Health Services",
            "subcategory":"Optometrist",
            "type":"Services"
        }
    ],
    "sg:phone":"+1 608 282 2000",
    "sg:postcode":"53715",
    "sg:province":"WI",
    "sg:website":"www.deancare.com",
    "wof:name":"Davis Deuhr Dean",
    "wof:placetype":"venue"
},
  "geometry": {"coordinates":[-89.403744,43.067611],"type":"Point"}
}