{
  "type": "Feature",
  "properties": {
    "iso:country":"US",
    "sg:address":"39151 Delafield Rd",
    "sg:city":"Oconomowoc",
    "sg:classifiers":[
        {
            "category":"Retail",
            "subcategory":"Veterinary Services",
            "type":"Services"
        }
    ],
    "sg:phone":"+1 262 569 1550",
    "sg:postcode":"53066",
    "sg:province":"WI",
    "sg:tags":[
        "medical"
    ],
    "sg:website":"www.wisconsinequineclinic.com",
    "wof:name":"Wisconsin Equine Clinic",
    "wof:placetype":"venue"
},
  "geometry": {"coordinates":[-88.52356,43.060979],"type":"Point"}
}