{
  "type": "Feature",
  "properties": {
    "iso:country":"US",
    "sg:address":"85850 Stage Rd",
    "sg:city":"Cornucopia",
    "sg:classifiers":[
        {
            "category":"Building & Trades",
            "subcategory":"Construction",
            "type":"Services"
        }
    ],
    "sg:phone":"+1 715 742 3227",
    "sg:postcode":"54827",
    "sg:province":"WI",
    "sg:tags":[
        "repair",
        "contractor",
        "welding",
        "mfg"
    ],
    "wof:name":"Somerset Systems",
    "wof:placetype":"venue"
},
  "geometry": {"coordinates":[-91.069925,46.822482],"type":"Point"}
}