{
  "type": "Feature",
  "properties": {
    "addr:full":"2412 W Nordale Dr Appleton WI 54914",
    "addr:housenumber":"2412",
    "addr:postcode":"54914",
    "addr:street":"W Nordale Dr",
    "iso:country":"US",
    "sg:address":"2412 W Nordale Dr",
    "sg:city":"Appleton",
    "sg:classifiers":[
        {
            "category":"Professional",
            "subcategory":"Business Services",
            "type":"Services"
        },
        {
            "category":"Shopping",
            "subcategory":"Bicycles & Sporting Goods",
            "type":"Retail Goods"
        }
    ],
    "sg:phone":"+1 920 993 1230",
    "sg:postcode":"54914",
    "sg:province":"WI",
    "sg:tags":[
        "embroidery"
    ],
    "sg:website":"www.gerrydavis.com",
    "wof:name":"Big League Connection LLC",
    "wof:placetype":"venue"
},
  "geometry": {"coordinates":[-88.443223,44.286518],"type":"Point"}
}