{
  "type": "Feature",
  "properties": {
    "addr:full":"1515 Aldoro Dr Waukesha WI 53188",
    "addr:housenumber":"1515",
    "addr:postcode":"53188",
    "addr:street":"Aldoro Dr",
    "iso:country":"US",
    "sg:address":"1515 Aldoro Dr",
    "sg:city":"Waukesha",
    "sg:classifiers":[
        {
            "category":"Organizations",
            "subcategory":"Community Association",
            "type":"Services"
        }
    ],
    "sg:phone":"+1 262 549 0472",
    "sg:postcode":"53188",
    "sg:province":"WI",
    "wof:name":"Eagles Roost LLC",
    "wof:placetype":"venue"
},
  "geometry": {"coordinates":[-88.24884,43.030816],"type":"Point"}
}