{
  "type": "Feature",
  "properties": {
    "iso:country":"US",
    "sg:address":"3460 E Layton Ave",
    "sg:city":"Cudahy",
    "sg:classifiers":[
        {
            "category":"Bars & Pubs",
            "type":"Food & Drink"
        }
    ],
    "sg:phone":"+1 414 483 4359",
    "sg:postcode":"53110",
    "sg:province":"WI",
    "wof:name":"Club 300",
    "wof:placetype":"venue"
},
  "geometry": {"coordinates":[-87.86281,42.959186],"type":"Point"}
}