{
  "type": "Feature",
  "properties": {
    "iso:country":"US",
    "sg:address":"2325 S Kinnickinnic Ave",
    "sg:city":"Milwaukee",
    "sg:classifiers":[
        {
            "category":"Professional",
            "subcategory":"Employment Agencies",
            "type":"Services"
        }
    ],
    "sg:phone":"+1 414 294 5841",
    "sg:postcode":"53207",
    "sg:province":"WI",
    "sg:tags":[
        "opportunity"
    ],
    "wof:name":"Midwest Labor & Hospitality Co",
    "wof:placetype":"venue"
},
  "geometry": {"coordinates":[-87.903756,43.002315],"type":"Point"}
}