{
  "type": "Feature",
  "properties": {
    "iso:country":"US",
    "sg:address":"211 W Main St",
    "sg:city":"Mt Horeb",
    "sg:classifiers":[
        {
            "category":"Real Estate",
            "subcategory":"Real Estate Agent",
            "type":"Services"
        }
    ],
    "sg:phone":"+1 608 437 4651",
    "sg:postcode":"53572",
    "sg:province":"WI",
    "wof:name":"Rural Realty & Auction Svc",
    "wof:placetype":"venue"
},
  "geometry": {"coordinates":[-89.740523,43.008581],"type":"Point"}
}