{
  "type": "Feature",
  "properties": {
    "iso:country":"US",
    "sg:address":"3932 Woodland Dr",
    "sg:city":"Rhinelander",
    "sg:classifiers":[
        {
            "category":"Retail",
            "subcategory":"Repair Shop",
            "type":"Services"
        }
    ],
    "sg:phone":"+1 715 369 1983",
    "sg:postcode":"54501",
    "sg:province":"WI",
    "wof:name":"Zaffran Machine Inc",
    "wof:placetype":"venue"
},
  "geometry": {"coordinates":[-89.317831,45.656276],"type":"Point"}
}