{
  "type": "Feature",
  "properties": {
    "iso:country":"US",
    "sg:address":"16959 State Hwy 131",
    "sg:city":"Tomah",
    "sg:classifiers":[
        {
            "category":"Professional",
            "type":"Services"
        }
    ],
    "sg:phone":"+1 608 372 2355",
    "sg:postcode":"54660",
    "sg:province":"WI",
    "sg:tags":[
        "establishment"
    ],
    "wof:name":"Gerke Gerke",
    "wof:placetype":"venue"
},
  "geometry": {"coordinates":[-90.502851,43.936572],"type":"Point"}
}