{
  "type": "Feature",
  "properties": {
    "iso:country":"US",
    "sg:address":"1320 21st Ave S",
    "sg:city":"Wisconsin Rapids",
    "sg:classifiers":[
        {
            "category":"Health Services",
            "subcategory":"Hospital",
            "type":"Services"
        },
        {
            "category":"Health Services",
            "subcategory":"Clinic",
            "type":"Services"
        }
    ],
    "sg:phone":"+1 715 421 5405",
    "sg:postcode":"54495",
    "sg:province":"WI",
    "sg:tags":[
        "mental",
        "outpatient",
        "specialty"
    ],
    "wof:name":"Crossroads Mental Health Svcs",
    "wof:placetype":"venue"
},
  "geometry": {"coordinates":[-89.849583,44.383783],"type":"Point"}
}