{
  "type": "Feature",
  "properties": {
    "addr:full":"11120 W Bluemound Rd Wauwatosa WI 53226",
    "addr:housenumber":"11120",
    "addr:postcode":"53226",
    "addr:street":"W Bluemound Rd",
    "iso:country":"US",
    "sg:address":"11120 W Bluemound Rd",
    "sg:city":"Wauwatosa",
    "sg:classifiers":[
        {
            "category":"Restaurant",
            "type":"Food & Drink"
        }
    ],
    "sg:menulink":"http://www.allmenus.com/wi/wauwatosa/114318-peony/menu/",
    "sg:phone":"+1 414 443 6455",
    "sg:postcode":"53226",
    "sg:province":"WI",
    "sg:tags":[
        "dim",
        "sum",
        "asian"
    ],
    "wof:name":"Peony",
    "wof:placetype":"venue"
},
  "geometry": {"coordinates":[-88.052071,43.035705],"type":"Point"}
}