{
  "type": "Feature",
  "properties": {
    "addr:full":"5795 Co Rd M Boulder Junction WI 54512",
    "addr:housenumber":"5795",
    "addr:postcode":"54512",
    "addr:street":"Co Rd M",
    "iso:country":"US",
    "sg:address":"5795 Co Rd M",
    "sg:city":"Boulder Junction",
    "sg:classifiers":[
        {
            "category":"Building & Trades",
            "subcategory":"Plumbing",
            "type":"Services"
        }
    ],
    "sg:phone":"+1 715 385 2518",
    "sg:postcode":"54512",
    "sg:province":"WI",
    "sg:tags":[
        "heating",
        "contractor"
    ],
    "wof:name":"Lakeland Heating Inc",
    "wof:placetype":"venue"
},
  "geometry": {"coordinates":[-89.631704,46.125823],"type":"Point"}
}