{
  "type": "Feature",
  "properties": {
    "addr:full":"4623 N 124th St Butler WI 53007",
    "addr:housenumber":"4623",
    "addr:postcode":"53007",
    "addr:street":"N 124Th St",
    "iso:country":"US",
    "sg:address":"4623 N 124th St",
    "sg:city":"Butler",
    "sg:classifiers":[
        {
            "category":"Building & Trades",
            "subcategory":"Construction",
            "type":"Services"
        }
    ],
    "sg:phone":"+1 262 781 5484",
    "sg:postcode":"53007",
    "sg:province":"WI",
    "sg:tags":[
        "resurfaces",
        "alley",
        "bowling"
    ],
    "wof:name":"Bowl Rite Resurfacing Inc",
    "wof:placetype":"venue"
},
  "geometry": {"coordinates":[-88.06620599999999,43.101035],"type":"Point"}
}