{
  "type": "Feature",
  "properties": {
    "iso:country":"US",
    "sg:address":"1019 Squire Ct",
    "sg:city":"Nekoosa",
    "sg:classifiers":[
        {
            "category":"Health Services",
            "subcategory":"Medical Lab",
            "type":"Services"
        }
    ],
    "sg:phone":"+1 715 325 2710",
    "sg:postcode":"54457",
    "sg:province":"WI",
    "sg:tags":[
        "detection",
        "equipment",
        "drug"
    ],
    "wof:name":"Trutest Drug & Alcohol Testing",
    "wof:placetype":"venue"
},
  "geometry": {"coordinates":[-89.78463600000001,44.200191],"type":"Point"}
}