{
  "type": "Feature",
  "properties": {
    "addr:full":"8333 W Appleton Ave Milwaukee WI 53218",
    "addr:housenumber":"8333",
    "addr:postcode":"53218",
    "addr:street":"W Appleton Ave",
    "iso:country":"US",
    "sg:address":"8333 W Appleton Ave",
    "sg:city":"Milwaukee",
    "sg:classifiers":[
        {
            "category":"Shopping",
            "type":"Retail Goods"
        }
    ],
    "sg:phone":"+1 414 393 0507",
    "sg:postcode":"53218",
    "sg:province":"WI",
    "sg:tags":[
        "merchandise"
    ],
    "wof:name":"Dollar Discount",
    "wof:placetype":"venue"
},
  "geometry": {"coordinates":[-88.01594799999999,43.104615],"type":"Point"}
}