{
  "type": "Feature",
  "properties": {
    "iso:country":"US",
    "sg:address":"1201 3rd Ct",
    "sg:city":"Stevens Point",
    "sg:classifiers":[
        {
            "category":"Food & Beverages",
            "subcategory":"Specialty",
            "type":"Retail Goods"
        }
    ],
    "sg:phone":"+1 715 342 3778",
    "sg:postcode":"54481",
    "sg:province":"WI",
    "sg:tags":[
        "health",
        "diet"
    ],
    "wof:name":"GNC",
    "wof:placetype":"venue"
},
  "geometry": {"coordinates":[-89.58444299999999,44.524205],"type":"Point"}
}