{
  "type": "Feature",
  "properties": {
    "iso:country":"US",
    "sg:address":"712 Riverfront Dr",
    "sg:city":"Sheboygan",
    "sg:classifiers":[
        {
            "category":"Professional",
            "subcategory":"Accounting & Tax Preparation",
            "type":"Services"
        }
    ],
    "sg:phone":"+1 920 458 0341",
    "sg:postcode":"53081",
    "sg:province":"WI",
    "sg:tags":[
        "business"
    ],
    "wof:name":"Barth Tina CPA",
    "wof:placetype":"venue"
},
  "geometry": {"coordinates":[-87.712301,43.745471],"type":"Point"}
}