{
  "type": "Feature",
  "properties": {
    "iso:country":"US",
    "sg:address":"9897 Cherry Ave",
    "sg:city":"Loyal",
    "sg:classifiers":[
        {
            "category":"Farming",
            "subcategory":"Livestock Farm",
            "type":"Manufacturing & Wholesale Goods"
        }
    ],
    "sg:phone":"+1 715 255 8436",
    "sg:postcode":"54446",
    "sg:province":"WI",
    "sg:tags":[
        "hog",
        "or",
        "feedlot"
    ],
    "wof:name":"Swine Haus Inc",
    "wof:placetype":"venue"
},
  "geometry": {"coordinates":[-90.407902,44.778612],"type":"Point"}
}