{
  "type": "Feature",
  "properties": {
    "iso:country":"US",
    "sg:address":"413 US-12",
    "sg:city":"Baraboo",
    "sg:classifiers":[
        {
            "category":"Restaurant",
            "type":"Food & Drink"
        }
    ],
    "sg:menulink":"http://www.allmenus.com/wi/west-baraboo/85774-dominos-pizza/menu/",
    "sg:phone":"+1 608 355 5080",
    "sg:postcode":"53913",
    "sg:province":"WI",
    "sg:tags":[
        "american",
        "wing",
        "pizza"
    ],
    "wof:name":"Domino's Pizza",
    "wof:placetype":"venue"
},
  "geometry": {"coordinates":[-89.76883599999999,43.473024],"type":"Point"}
}