{
  "type": "Feature",
  "properties": {
    "iso:country":"US",
    "sg:address":"25211 Minnetonka Dr",
    "sg:city":"Kansasville",
    "sg:classifiers":[
        {
            "category":"Retail",
            "subcategory":"Auto Repair",
            "type":"Services"
        }
    ],
    "sg:phone":"+1 262 878 1886",
    "sg:postcode":"53139",
    "sg:province":"WI",
    "sg:tags":[
        "general"
    ],
    "wof:name":"Marios Auto Service",
    "wof:placetype":"venue"
},
  "geometry": {"coordinates":[-88.14068899999999,42.7054],"type":"Point"}
}