{
  "type": "Feature",
  "properties": {
    "iso:country":"US",
    "sg:address":"1985 Velp Ave",
    "sg:city":"Green Bay",
    "sg:classifiers":[
        {
            "category":"Bars & Pubs",
            "type":"Food & Drink"
        }
    ],
    "sg:phone":"+1 920 405 6699",
    "sg:postcode":"54303",
    "sg:province":"WI",
    "sg:tags":[
        "drinking"
    ],
    "wof:name":"Kim's Place",
    "wof:placetype":"venue"
},
  "geometry": {"coordinates":[-88.063313,44.55816],"type":"Point"}
}