{
  "type": "Feature",
  "properties": {
    "iso:country":"US",
    "sg:address":"17450 W North Ave",
    "sg:city":"Brookfield",
    "sg:classifiers":[
        {
            "category":"Real Estate",
            "subcategory":"Real Estate Services",
            "type":"Services"
        }
    ],
    "sg:phone":"+1 262 785 9555",
    "sg:postcode":"53045",
    "sg:province":"WI",
    "sg:tags":[
        "company",
        "title"
    ],
    "wof:name":"Heritage Title Svc Inc",
    "wof:placetype":"venue"
},
  "geometry": {"coordinates":[-88.128047,43.061115],"type":"Point"}
}