{
  "type": "Feature",
  "properties": {
    "iso:country":"US",
    "sg:address":"1372 McKinley Rd",
    "sg:city":"Eau Claire",
    "sg:classifiers":[
        {
            "category":"Manufacturing",
            "subcategory":"Wood Products",
            "type":"Manufacturing & Wholesale Goods"
        }
    ],
    "sg:phone":"+1 715 832 1299",
    "sg:postcode":"54703",
    "sg:province":"WI",
    "sg:tags":[
        "mfg"
    ],
    "wof:name":"Midthun Wood Studio",
    "wof:placetype":"venue"
},
  "geometry": {"coordinates":[-91.457903,44.828752],"type":"Point"}
}