{
  "type": "Feature",
  "properties": {
    "addr:full":"N2030 Spring St Ste 3 Stockholm WI 54769",
    "addr:housenumber":"n2030",
    "addr:postcode":"54769",
    "addr:street":"Spring St Ste 3",
    "iso:country":"US",
    "sg:address":"N2030 Spring St Ste 3",
    "sg:city":"Stockholm",
    "sg:classifiers":[
        {
            "category":"Professional",
            "subcategory":"Art Services",
            "type":"Services"
        }
    ],
    "sg:phone":"+1 715 442 2266",
    "sg:postcode":"54769",
    "sg:province":"WI",
    "sg:tags":[
        "interior",
        "designer",
        "decorator"
    ],
    "sg:website":"http://www.abodeinteriors.com",
    "wof:name":"Abode Interiors Ltd",
    "wof:placetype":"venue"
},
  "geometry": {"coordinates":[-92.26142900000001,44.483849],"type":"Point"}
}