{
  "type": "Feature",
  "properties": {
    "addr:full":"5150 Lakewind Dr Butte Des Morts WI 54927",
    "addr:housenumber":"5150",
    "addr:postcode":"54927",
    "addr:street":"Lakewind Dr;Des Morts",
    "iso:country":"US",
    "sg:address":"5150 Lakewind Dr",
    "sg:city":"Butte Des Morts",
    "sg:classifiers":[
        {
            "category":"Building & Trades",
            "subcategory":"Construction",
            "type":"Services"
        }
    ],
    "sg:phone":"+1 920 582 7048",
    "sg:postcode":"54927",
    "sg:province":"WI",
    "sg:tags":[
        "painter"
    ],
    "wof:name":"Jeff Miller Painting",
    "wof:placetype":"venue"
},
  "geometry": {"coordinates":[-88.657676,44.102789],"type":"Point"}
}