{
  "type": "Feature",
  "properties": {
    "iso:country":"US",
    "sg:address":"1237 Co Rd Tt",
    "sg:city":"Roberts",
    "sg:classifiers":[
        {
            "category":"Farming",
            "subcategory":"Dairy Farm",
            "type":"Manufacturing & Wholesale Goods"
        }
    ],
    "sg:phone":"+1 715 749 3508",
    "sg:postcode":"54023",
    "sg:province":"WI",
    "wof:name":"Wayne Miller",
    "wof:placetype":"venue"
},
  "geometry": {"coordinates":[-92.548466,44.978094],"type":"Point"}
}