{
  "type": "Feature",
  "properties": {
    "iso:country":"US",
    "sg:address":"7586 Christmas Tree Ln",
    "sg:city":"Shawano",
    "sg:classifiers":[
        {
            "category":"Farming",
            "subcategory":"Farm",
            "type":"Manufacturing & Wholesale Goods"
        },
        {
            "category":"Manufacturing",
            "subcategory":"Lumber",
            "type":"Manufacturing & Wholesale Goods"
        }
    ],
    "sg:phone":"+1 715 526 6411",
    "sg:postcode":"54166",
    "sg:province":"WI",
    "sg:tags":[
        "operation",
        "timber",
        "tract"
    ],
    "wof:name":"Hanauer's Tree Farms",
    "wof:placetype":"venue"
},
  "geometry": {"coordinates":[-88.628366,44.824895],"type":"Point"}
}