{
  "type": "Feature",
  "properties": {
    "iso:country":"US",
    "sg:address":"1021 Ash St",
    "sg:city":"Baraboo",
    "sg:classifiers":[
        {
            "category":"Organizations",
            "subcategory":"Religious Organization",
            "type":"Services"
        }
    ],
    "sg:phone":"+1 608 356 8641",
    "sg:postcode":"53913",
    "sg:province":"WI",
    "sg:tags":[
        "monastery",
        "convent"
    ],
    "wof:name":"Franciscan Sisters Mary Hope",
    "wof:placetype":"venue"
},
  "geometry": {"coordinates":[-89.740691,43.474717],"type":"Point"}
}