{
  "type": "Feature",
  "properties": {
    "iso:country":"US",
    "sg:address":"14615 W Meadowshire Dr",
    "sg:city":"New Berlin",
    "sg:classifiers":[
        {
            "category":"Real Estate",
            "subcategory":"Real Estate Agent",
            "type":"Services"
        }
    ],
    "sg:phone":"+1 262 782 2692",
    "sg:postcode":"53151",
    "sg:province":"WI",
    "sg:tags":[
        "inspection"
    ],
    "wof:name":"Accurate& Reliable Hm Inspctn",
    "wof:placetype":"venue"
},
  "geometry": {"coordinates":[-88.096073,43.003315],"type":"Point"}
}