{
  "type": "Feature",
  "properties": {
    "iso:country":"US",
    "sg:address":"102 Keller Ave S",
    "sg:city":"Amery",
    "sg:classifiers":[
        {
            "category":"Health Services",
            "subcategory":"Chiropractor",
            "type":"Services"
        }
    ],
    "sg:phone":"+1 715 268 7500",
    "sg:postcode":"54001",
    "sg:province":"WI",
    "wof:name":"Toftness Chiropractic Office",
    "wof:placetype":"venue"
},
  "geometry": {"coordinates":[-92.36218100000001,45.311409],"type":"Point"}
}