{
  "type": "Feature",
  "properties": {
    "iso:country":"US",
    "sg:address":"5887 Elm Lake Ln",
    "sg:city":"Wisconsin Rapids",
    "sg:classifiers":[
        {
            "category":"Farming",
            "subcategory":"Berry Farm",
            "type":"Manufacturing & Wholesale Goods"
        }
    ],
    "sg:phone":"+1 715 424 4147",
    "sg:postcode":"54495",
    "sg:province":"WI",
    "sg:tags":[
        "producer",
        "cranberry"
    ],
    "wof:name":"Elm Lake Cranberry Co",
    "wof:placetype":"venue"
},
  "geometry": {"coordinates":[-90.007074,44.387278],"type":"Point"}
}