{
  "type": "Feature",
  "properties": {
    "iso:country":"US",
    "sg:address":"966 Shawano Ave",
    "sg:city":"Green Bay",
    "sg:classifiers":[
        {
            "category":"Education",
            "subcategory":"School",
            "type":"Public Place"
        }
    ],
    "sg:phone":"+1 920 492 2600",
    "sg:postcode":"54303",
    "sg:province":"WI",
    "sg:tags":[
        "high"
    ],
    "sg:website":"www.greenbay.k12.wi.us",
    "wof:name":"West High School",
    "wof:placetype":"venue"
},
  "geometry": {"coordinates":[-88.034997,44.521343],"type":"Point"}
}