{
  "type": "Feature",
  "properties": {
    "iso:country":"US",
    "sg:address":"5265 N Port Washington Rd",
    "sg:city":"Milwaukee",
    "sg:classifiers":[
        {
            "category":"Bakery",
            "type":"Food & Drink"
        }
    ],
    "sg:menulink":"http://www.allmenus.com/wi/glendale/102349-perkins-restaurant--bakery/menu/",
    "sg:phone":"+1 414 962 0623",
    "sg:postcode":"53217",
    "sg:province":"WI",
    "sg:tags":[
        "sandwich",
        "salad",
        "soup",
        "american",
        "pastry",
        "wrap"
    ],
    "wof:name":"Perkins Restaurant & Bakery",
    "wof:placetype":"venue"
},
  "geometry": {"coordinates":[-87.91725,43.113179],"type":"Point"}
}