{
  "type": "Feature",
  "properties": {
    "addr:full":"1201 E Broadway Madison WI 53716",
    "addr:housenumber":"1201",
    "addr:postcode":"53716",
    "addr:street":"E Broadway",
    "iso:country":"US",
    "sg:address":"1201 E Broadway",
    "sg:city":"Madison",
    "sg:classifiers":[
        {
            "category":"Restaurant",
            "type":"Food & Drink"
        }
    ],
    "sg:menulink":"http://www.allmenus.com/wi/monona/7997-dennys/menu/",
    "sg:phone":"+1 608 222 8822",
    "sg:postcode":"53716",
    "sg:province":"WI",
    "sg:tags":[
        "american",
        "diner"
    ],
    "wof:name":"Denny's",
    "wof:placetype":"venue"
},
  "geometry": {"coordinates":[-89.311533,43.048529],"type":"Point"}
}