{
  "type": "Feature",
  "properties": {
    "iso:country":"US",
    "sg:address":"4417 Spring Rd",
    "sg:city":"Omro",
    "sg:classifiers":[
        {
            "category":"Farming",
            "subcategory":"Dairy Farm",
            "type":"Manufacturing & Wholesale Goods"
        }
    ],
    "sg:phone":"+1 920 685 5925",
    "sg:postcode":"54963",
    "sg:province":"WI",
    "wof:name":"Gerald Rogers",
    "wof:placetype":"venue"
},
  "geometry": {"coordinates":[-88.85524700000001,44.061447],"type":"Point"}
}