{
  "type": "Feature",
  "properties": {
    "iso:country":"US",
    "sg:address":"4136 State Hwy 42",
    "sg:city":"Sheboygan",
    "sg:classifiers":[
        {
            "category":"Food & Beverages",
            "subcategory":"Bakery",
            "type":"Retail Goods"
        }
    ],
    "sg:phone":"+1 920 457 2253",
    "sg:postcode":"53083",
    "sg:province":"WI",
    "wof:name":"Highway Bakery & Coffee Shop",
    "wof:placetype":"venue"
},
  "geometry": {"coordinates":[-87.758306,43.788967],"type":"Point"}
}