{
  "type": "Feature",
  "properties": {
    "iso:country":"US",
    "sg:address":"4702 1390th Ave",
    "sg:city":"Ridgeland",
    "sg:classifiers":[
        {
            "category":"Freight",
            "type":"Transportation"
        }
    ],
    "sg:phone":"+1 715 949 1127",
    "sg:postcode":"54763",
    "sg:province":"WI",
    "sg:tags":[
        "operator",
        "local",
        "trucking"
    ],
    "wof:name":"Holland Trucking",
    "wof:placetype":"venue"
},
  "geometry": {"coordinates":[-91.921255,45.186085],"type":"Point"}
}