{
  "type": "Feature",
  "properties": {
    "iso:country":"US",
    "sg:address":"2497 Slinger Rd",
    "sg:city":"Richfield",
    "sg:classifiers":[
        {
            "category":"Retail",
            "subcategory":"Animal Services",
            "type":"Services"
        }
    ],
    "sg:phone":"+1 262 644 5739",
    "sg:postcode":"53076",
    "sg:province":"WI",
    "wof:name":"Erins Edge Labradors & Supply",
    "wof:placetype":"venue"
},
  "geometry": {"coordinates":[-88.281051,43.281208],"type":"Point"}
}