{
  "type": "Feature",
  "properties": {
    "iso:country":"US",
    "sg:address":"2020 Riverside Dr",
    "sg:city":"Green Bay",
    "sg:classifiers":[
        {
            "category":"Health Services",
            "subcategory":"Doctor",
            "type":"Services"
        }
    ],
    "sg:phone":"+1 920 496 4700",
    "sg:postcode":"54301",
    "sg:province":"WI",
    "sg:tags":[
        "clinic"
    ],
    "wof:name":"Prevea Rehab Physicians",
    "wof:placetype":"venue"
},
  "geometry": {"coordinates":[-88.028959,44.485464],"type":"Point"}
}