{
  "type": "Feature",
  "properties": {
    "addr:full":"5294 Co Hwy A Deerbrook WI 54424",
    "addr:housenumber":"5294",
    "addr:postcode":"54424",
    "addr:street":"Co Hwy A",
    "iso:country":"US",
    "sg:address":"5294 Co Hwy A",
    "sg:city":"Deerbrook",
    "sg:classifiers":[
        {
            "category":"Food & Beverages",
            "subcategory":"Groceries & Convenience Stores",
            "type":"Retail Goods"
        }
    ],
    "sg:phone":"+1 715 623 2000",
    "sg:postcode":"54424",
    "sg:province":"WI",
    "sg:tags":[
        "grocer"
    ],
    "wof:name":"Sikora Groceries",
    "wof:placetype":"venue"
},
  "geometry": {"coordinates":[-89.144947,45.219266],"type":"Point"}
}