{
  "type": "Feature",
  "properties": {
    "addr:full":"2244 S 20th St Milwaukee WI 53215",
    "addr:housenumber":"2244",
    "addr:postcode":"53215",
    "addr:street":"S 20Th St",
    "iso:country":"US",
    "sg:address":"2244 S 20th St",
    "sg:city":"Milwaukee",
    "sg:classifiers":[
        {
            "category":"Building & Trades",
            "subcategory":"Construction",
            "type":"Services"
        }
    ],
    "sg:phone":"+1 414 643 1472",
    "sg:postcode":"53215",
    "sg:province":"WI",
    "sg:tags":[
        "roofing",
        "siding",
        "contractor"
    ],
    "wof:name":"Finch Home Improvement",
    "wof:placetype":"venue"
},
  "geometry": {"coordinates":[-87.93815600000001,43.003816],"type":"Point"}
}