{
  "type": "Feature",
  "properties": {
    "iso:country":"US",
    "sg:address":"5909 Co Hwy K",
    "sg:city":"Hartford",
    "sg:classifiers":[
        {
            "category":"Social Services",
            "subcategory":"Child Care",
            "type":"Services"
        }
    ],
    "sg:phone":"+1 262 644 8631",
    "sg:postcode":"53027",
    "sg:province":"WI",
    "sg:tags":[
        "preschool"
    ],
    "wof:name":"St Lawrnce 4 Yr Child Look Ctr",
    "wof:placetype":"venue"
},
  "geometry": {"coordinates":[-88.33149,43.36963],"type":"Point"}
}