{
  "type": "Feature",
  "properties": {
    "addr:full":"845 Madison St Beaver Dam WI 53916",
    "addr:housenumber":"845",
    "addr:postcode":"53916",
    "addr:street":"Madison St",
    "iso:country":"US",
    "sg:address":"845 Madison St",
    "sg:city":"Beaver Dam",
    "sg:classifiers":[
        {
            "category":"Building & Trades",
            "subcategory":"Construction",
            "type":"Services"
        }
    ],
    "sg:phone":"+1 920 885 3999",
    "sg:postcode":"53916",
    "sg:province":"WI",
    "sg:tags":[
        "shelter"
    ],
    "wof:name":"New Beginnings Homeless Shltr",
    "wof:placetype":"venue"
},
  "geometry": {"coordinates":[-88.849408,43.447212],"type":"Point"}
}