{
  "type": "Feature",
  "properties": {
    "iso:country":"US",
    "sg:address":"23748 State Hwy 95",
    "sg:city":"Arcadia",
    "sg:classifiers":[
        {
            "category":"Farming",
            "subcategory":"Farm",
            "type":"Manufacturing & Wholesale Goods"
        }
    ],
    "sg:phone":"+1 608 323 7017",
    "sg:postcode":"54612",
    "sg:province":"WI",
    "sg:tags":[
        "crop",
        "general"
    ],
    "wof:name":"Patzner John",
    "wof:placetype":"venue"
},
  "geometry": {"coordinates":[-91.42310500000001,44.253659],"type":"Point"}
}