{
  "type": "Feature",
  "properties": {
    "iso:country":"US",
    "sg:address":"23514 31st St",
    "sg:city":"Salem",
    "sg:classifiers":[
        {
            "category":"Retail",
            "subcategory":"Animal Services",
            "type":"Services"
        }
    ],
    "sg:phone":"+1 262 878 3080",
    "sg:postcode":"53168",
    "sg:province":"WI",
    "wof:name":"Willo Siberians",
    "wof:placetype":"venue"
},
  "geometry": {"coordinates":[-88.09669,42.612064],"type":"Point"}
}