{
  "type": "Feature",
  "properties": {
    "addr:full":"S77w18426 Janesville Rd Muskego WI 53150",
    "addr:housenumber":"s77w18426",
    "addr:postcode":"53150",
    "addr:street":"Janesville Rd",
    "iso:country":"US",
    "sg:address":"S77w18426 Janesville Rd",
    "sg:city":"Muskego",
    "sg:classifiers":[
        {
            "category":"Place Of Worship",
            "subcategory":"Church",
            "type":"Public Place"
        },
        {
            "category":"Place Of Worship",
            "type":"Public Place"
        }
    ],
    "sg:phone":"+1 262 679 1616",
    "sg:postcode":"53150",
    "sg:province":"WI",
    "sg:tags":[
        "lutheran",
        "america",
        "elca",
        "churches-lutheran",
        "churches-lutheran-evangelical"
    ],
    "sg:website":"http://www.bethelmuskego.org",
    "wof:name":"Bethel Lutheran Church ELCA",
    "wof:placetype":"venue"
},
  "geometry": {"coordinates":[-88.083141,42.928885],"type":"Point"}
}