{
  "type": "Feature",
  "properties": {
    "iso:country":"US",
    "sg:address":"3903 N Shore Dr",
    "sg:city":"Rhinelander",
    "sg:classifiers":[
        {
            "category":"Education",
            "subcategory":"Dance Studio",
            "type":"Public Place"
        }
    ],
    "sg:phone":"+1 715 362 3455",
    "sg:postcode":"54501",
    "sg:province":"WI",
    "sg:tags":[
        "school"
    ],
    "wof:name":"Northwoods School of Dance",
    "wof:placetype":"venue"
},
  "geometry": {"coordinates":[-89.319056,45.63761],"type":"Point"}
}