{
  "type": "Feature",
  "properties": {
    "iso:country":"US",
    "sg:address":"1634 Saemann Ave",
    "sg:city":"Sheboygan",
    "sg:classifiers":[
        {
            "category":"Building & Trades",
            "subcategory":"Landscaping Services",
            "type":"Services"
        }
    ],
    "sg:phone":"+1 920 458 6490",
    "sg:postcode":"53081",
    "sg:province":"WI",
    "wof:name":"Dennys Landscaping",
    "wof:placetype":"venue"
},
  "geometry": {"coordinates":[-87.727708,43.764394],"type":"Point"}
}