{
  "type": "Feature",
  "properties": {
    "iso:country":"US",
    "sg:address":"2217 Ravenswood Rd",
    "sg:city":"Madison",
    "sg:classifiers":[
        {
            "category":"Arts & Performance",
            "subcategory":"Theater",
            "type":"Entertainment"
        }
    ],
    "sg:phone":"+1 608 271 0727",
    "sg:postcode":"53711",
    "sg:province":"WI",
    "sg:tags":[
        "group"
    ],
    "wof:name":"Level 10 Entertainment",
    "wof:placetype":"venue"
},
  "geometry": {"coordinates":[-89.49119,43.026313],"type":"Point"}
}