{
  "type": "Feature",
  "properties": {
    "addr:full":"516 Reed St Plymouth WI 53073",
    "addr:housenumber":"516",
    "addr:postcode":"53073",
    "addr:street":"Reed St",
    "iso:country":"US",
    "sg:address":"516 Reed St",
    "sg:city":"Plymouth",
    "sg:classifiers":[
        {
            "category":"Professional",
            "type":"Services"
        }
    ],
    "sg:phone":"+1 920 892 4661",
    "sg:postcode":"53073",
    "sg:province":"WI",
    "wof:name":"West & Hallanger",
    "wof:placetype":"venue"
},
  "geometry": {"coordinates":[-87.974717,43.744628],"type":"Point"}
}