{
  "type": "Feature",
  "properties": {
    "addr:full":"6905 Parkview Dr Greenville WI 54942",
    "addr:housenumber":"6905",
    "addr:postcode":"54942",
    "addr:street":"Parkview Dr",
    "iso:country":"US",
    "sg:address":"6905 Parkview Dr",
    "sg:city":"Greenville",
    "sg:classifiers":[
        {
            "category":"Health Services",
            "subcategory":"Health Practitioner",
            "type":"Services"
        }
    ],
    "sg:phone":"+1 920 757 9887",
    "sg:postcode":"54942",
    "sg:province":"WI",
    "sg:tags":[
        "acupuncture"
    ],
    "wof:name":"Acupuncture One LLC",
    "wof:placetype":"venue"
},
  "geometry": {"coordinates":[-88.53915000000001,44.303259],"type":"Point"}
}