{
  "type": "Feature",
  "properties": {
    "addr:full":"627 Main St Darlington WI 53530",
    "addr:housenumber":"627",
    "addr:postcode":"53530",
    "addr:street":"Main St",
    "iso:country":"US",
    "sg:address":"627 Main St",
    "sg:city":"Darlington",
    "sg:classifiers":[
        {
            "category":"Government",
            "subcategory":"Police Station",
            "type":"Public Place"
        }
    ],
    "sg:phone":"+1 608 776 4980",
    "sg:postcode":"53530",
    "sg:province":"WI",
    "sg:tags":[
        "department"
    ],
    "wof:name":"Darlington Police Dept",
    "wof:placetype":"venue"
},
  "geometry": {"coordinates":[-90.117644,42.682622],"type":"Point"}
}