{
  "type": "Feature",
  "properties": {
    "iso:country":"US",
    "sg:address":"104 W Linden Dr",
    "sg:city":"Jefferson",
    "sg:classifiers":[
        {
            "category":"Health Services",
            "subcategory":"Doctor",
            "type":"Services"
        }
    ],
    "sg:phone":"+1 920 674 6399",
    "sg:postcode":"53549",
    "sg:province":"WI",
    "wof:name":"Dr J E Schoen",
    "wof:placetype":"venue"
},
  "geometry": {"coordinates":[-88.808323,43.002447],"type":"Point"}
}