{
  "type": "Feature",
  "properties": {
    "iso:country":"US",
    "sg:address":"1922 Co Rd Mm",
    "sg:city":"Fitchburg",
    "sg:classifiers":[
        {
            "category":"Autos & Motor Vehicles",
            "subcategory":"Recreational Vehicle Sales",
            "type":"Retail Goods"
        }
    ],
    "sg:phone":"+1 608 835 5398",
    "sg:postcode":"53575",
    "sg:province":"WI",
    "sg:tags":[
        "travel",
        "camper",
        "trailer"
    ],
    "wof:name":"Camper Corral Inc",
    "wof:placetype":"venue"
},
  "geometry": {"coordinates":[-89.374545,42.958249],"type":"Point"}
}