{
  "type": "Feature",
  "properties": {
    "iso:country":"US",
    "sg:address":"805 Elm St",
    "sg:city":"Watertown",
    "sg:classifiers":[
        {
            "category":"Wholesale",
            "subcategory":"Office Equipment",
            "type":"Manufacturing & Wholesale Goods"
        }
    ],
    "sg:phone":"+1 920 262 1789",
    "sg:postcode":"53098",
    "sg:province":"WI",
    "sg:tags":[
        "bank",
        "supply"
    ],
    "wof:name":"TRS",
    "wof:placetype":"venue"
},
  "geometry": {"coordinates":[-88.73607199999999,43.200251],"type":"Point"}
}