{
  "type": "Feature",
  "properties": {
    "iso:country":"US",
    "sg:address":"733 N Van Buren St",
    "sg:city":"Milwaukee",
    "sg:classifiers":[
        {
            "category":"Professional",
            "subcategory":"Advertising",
            "type":"Services"
        }
    ],
    "sg:phone":"+1 414 227 1550",
    "sg:postcode":"53202",
    "sg:province":"WI",
    "sg:tags":[
        "counselor"
    ],
    "wof:name":"CKPR",
    "wof:placetype":"venue"
},
  "geometry": {"coordinates":[-87.90289900000001,43.03937],"type":"Point"}
}