{
  "type": "Feature",
  "properties": {
    "iso:country":"US",
    "sg:address":"17015 Winfield Rd",
    "sg:city":"Bristol",
    "sg:classifiers":[
        {
            "category":"Professional",
            "subcategory":"Business Services",
            "type":"Services"
        }
    ],
    "sg:phone":"+1 262 857 7015",
    "sg:postcode":"53104",
    "sg:province":"WI",
    "wof:name":"Lv Vik Enterprises Ltd",
    "wof:placetype":"venue"
},
  "geometry": {"coordinates":[-88.013324,42.519444],"type":"Point"}
}