{
  "type": "Feature",
  "properties": {
    "addr:full":"221 Mineral St Mineral Point WI 53565",
    "addr:housenumber":"221",
    "addr:postcode":"53565",
    "addr:street":"Mineral St",
    "iso:country":"US",
    "sg:address":"221 Mineral St",
    "sg:city":"Mineral Point",
    "sg:classifiers":[
        {
            "category":"Wholesale",
            "subcategory":"Non-durable Goods",
            "type":"Manufacturing & Wholesale Goods"
        }
    ],
    "sg:phone":"+1 608 987 3531",
    "sg:postcode":"53565",
    "sg:province":"WI",
    "wof:name":"Dolphin Distributing",
    "wof:placetype":"venue"
},
  "geometry": {"coordinates":[-90.181325,42.865078],"type":"Point"}
}