{
  "type": "Feature",
  "properties": {
    "iso:country":"US",
    "sg:address":"2451 Plover Rd",
    "sg:city":"Plover",
    "sg:classifiers":[
        {
            "category":"Personal",
            "subcategory":"Beauty Salon",
            "type":"Services"
        }
    ],
    "sg:phone":"+1 715 343 7980",
    "sg:postcode":"54467",
    "sg:province":"WI",
    "sg:tags":[
        "shop",
        "barber"
    ],
    "wof:name":"Seventh Heaven Salon",
    "wof:placetype":"venue"
},
  "geometry": {"coordinates":[-89.537419,44.453588],"type":"Point"}
}