{
  "type": "Feature",
  "properties": {
    "iso:country":"US",
    "sg:address":"3303 Grand Seasons Dr",
    "sg:city":"Waupaca",
    "sg:classifiers":[
        {
            "category":"Wholesale",
            "subcategory":"Motor Vehicles",
            "type":"Manufacturing & Wholesale Goods"
        }
    ],
    "sg:phone":"+1 715 942 0038",
    "sg:postcode":"54981",
    "sg:province":"WI",
    "sg:tags":[
        "automobile",
        "truck",
        "broker"
    ],
    "wof:name":"WIL Truk Inc",
    "wof:placetype":"venue"
},
  "geometry": {"coordinates":[-89.123198,44.360353],"type":"Point"}
}