{
  "type": "Feature",
  "properties": {
    "iso:country":"US",
    "sg:address":"7901 Co Rd T",
    "sg:city":"Fond Du Lac",
    "sg:classifiers":[
        {
            "category":"Farming",
            "subcategory":"Livestock Farm",
            "type":"Manufacturing & Wholesale Goods"
        }
    ],
    "sg:phone":"+1 920 923 4427",
    "sg:postcode":"54937",
    "sg:province":"WI",
    "sg:tags":[
        "animal",
        "general"
    ],
    "wof:name":"Hiden Paradise Farms",
    "wof:placetype":"venue"
},
  "geometry": {"coordinates":[-88.563561,43.762831],"type":"Point"}
}