{
  "type": "Feature",
  "properties": {
    "iso:country":"US",
    "sg:address":"6302 W Richmond Ave",
    "sg:city":"Milwaukee",
    "sg:classifiers":[
        {
            "category":"Building & Trades",
            "subcategory":"Plumbing",
            "type":"Services"
        }
    ],
    "sg:phone":"+1 414 447 6005",
    "sg:postcode":"53210",
    "sg:province":"WI",
    "sg:tags":[
        "contractor"
    ],
    "wof:name":"Advantage Heating Service",
    "wof:placetype":"venue"
},
  "geometry": {"coordinates":[-87.991402,43.070863],"type":"Point"}
}