{
  "type": "Feature",
  "properties": {
    "iso:country":"US",
    "sg:address":"575 Swan Rd",
    "sg:city":"De Pere",
    "sg:classifiers":[
        {
            "category":"Banks & Credit Unions",
            "subcategory":"Bank",
            "type":"Services"
        }
    ],
    "sg:phone":"+1 920 983 5333",
    "sg:postcode":"54115",
    "sg:province":"WI",
    "wof:name":"North Shore Bank",
    "wof:placetype":"venue"
},
  "geometry": {"coordinates":[-88.035331,44.438037],"type":"Point"}
}