{
  "type": "Feature",
  "properties": {
    "addr:full":"1000 Pine St Green Bay WI 54301",
    "addr:housenumber":"1000",
    "addr:postcode":"54301",
    "addr:street":"Pine St",
    "iso:country":"US",
    "sg:address":"1000 Pine St",
    "sg:city":"Green Bay",
    "sg:classifiers":[
        {
            "category":"Professional",
            "subcategory":"Art Services",
            "type":"Services"
        }
    ],
    "sg:phone":"+1 920 437 6200",
    "sg:postcode":"54301",
    "sg:province":"WI",
    "sg:tags":[
        "photo",
        "photography",
        "commercial",
        "studio",
        "portrait"
    ],
    "sg:website":"www.sandersonphotography.com",
    "wof:name":"Sanderson Photography",
    "wof:placetype":"venue"
},
  "geometry": {"coordinates":[-88.002084,44.511745],"type":"Point"}
}