{
  "type": "Feature",
  "properties": {
    "iso:country":"US",
    "sg:address":"5822 Church Ave",
    "sg:city":"Merrill",
    "sg:classifiers":[
        {
            "category":"Personal",
            "subcategory":"Beauty Salon",
            "type":"Services"
        }
    ],
    "sg:phone":"+1 715 536 8488",
    "sg:postcode":"54452",
    "sg:province":"WI",
    "sg:tags":[
        "shop"
    ],
    "wof:name":"Dianes Country Curl",
    "wof:placetype":"venue"
},
  "geometry": {"coordinates":[-89.727665,45.127304],"type":"Point"}
}