{
  "type": "Feature",
  "properties": {
    "addr:full":"702 Wedgewood Way Madison WI 53711",
    "addr:housenumber":"702",
    "addr:postcode":"53711",
    "addr:street":"Wedgewood Way",
    "iso:country":"US",
    "sg:address":"702 Wedgewood Way",
    "sg:city":"Madison",
    "sg:classifiers":[
        {
            "category":"Retail",
            "subcategory":"Repair Shop",
            "type":"Services"
        }
    ],
    "sg:phone":"+1 608 661 8294",
    "sg:postcode":"53711",
    "sg:province":"WI",
    "wof:name":"Band Instrument Repair Shop",
    "wof:placetype":"venue"
},
  "geometry": {"coordinates":[-89.463705,43.049106],"type":"Point"}
}