{
  "type": "Feature",
  "properties": {
    "iso:country":"US",
    "sg:address":"2208 E 5th St",
    "sg:city":"Superior",
    "sg:classifiers":[
        {
            "category":"Manufacturing",
            "subcategory":"Printing",
            "type":"Manufacturing & Wholesale Goods"
        }
    ],
    "sg:phone":"+1 715 398 7465",
    "sg:postcode":"54880",
    "sg:province":"WI",
    "sg:tags":[
        "commercial"
    ],
    "wof:name":"A2z Printing Of Superior Inc",
    "wof:placetype":"venue"
},
  "geometry": {"coordinates":[-92.049167,46.703774],"type":"Point"}
}