{
  "type": "Feature",
  "properties": {
    "iso:country":"US",
    "sg:address":"28773 Brown Church Dr",
    "sg:city":"Lone Rock",
    "sg:classifiers":[
        {
            "category":"Farming",
            "subcategory":"Dairy Farm",
            "type":"Manufacturing & Wholesale Goods"
        }
    ],
    "sg:phone":"+1 608 583 2109",
    "sg:postcode":"53556",
    "sg:province":"WI",
    "wof:name":"Kaul Farms LLC",
    "wof:placetype":"venue"
},
  "geometry": {"coordinates":[-90.202147,43.286022],"type":"Point"}
}