{
  "type": "Feature",
  "properties": {
    "iso:country":"US",
    "sg:address":"2947 Indian Creek Rd",
    "sg:city":"Fountain City",
    "sg:classifiers":[
        {
            "category":"Travel",
            "subcategory":"Hotels & Motels",
            "type":"Entertainment"
        },
        {
            "category":"Bars & Pubs",
            "type":"Food & Drink"
        }
    ],
    "sg:phone":"+1 608 687 9581",
    "sg:postcode":"54629",
    "sg:province":"WI",
    "sg:tags":[
        "resort",
        "drinking"
    ],
    "wof:name":"Indian Creek Resorts",
    "wof:placetype":"venue"
},
  "geometry": {"coordinates":[-91.771602,44.167431],"type":"Point"}
}