{
  "type": "Feature",
  "properties": {
    "iso:country":"US",
    "sg:address":"10111 W Capitol Dr",
    "sg:city":"Milwaukee",
    "sg:classifiers":[
        {
            "category":"Shopping",
            "subcategory":"Bicycles & Sporting Goods",
            "type":"Retail Goods"
        }
    ],
    "sg:phone":"+1 414 461 5600",
    "sg:postcode":"53222",
    "sg:province":"WI",
    "sg:tags":[
        "new",
        "used"
    ],
    "sg:website":"www.playitagainsports.com",
    "wof:name":"Play It Again Sports",
    "wof:placetype":"venue"
},
  "geometry": {"coordinates":[-88.04031500000001,43.089606],"type":"Point"}
}