{
  "type": "Feature",
  "properties": {
    "addr:full":"240 E Summit Ave Wales WI 53183",
    "addr:housenumber":"240",
    "addr:postcode":"53183",
    "addr:street":"E Summit Ave",
    "iso:country":"US",
    "sg:address":"240 E Summit Ave",
    "sg:city":"Wales",
    "sg:classifiers":[
        {
            "category":"Restaurant",
            "type":"Food & Drink"
        }
    ],
    "sg:phone":"+1 262 968 2894",
    "sg:postcode":"53183",
    "sg:province":"WI",
    "sg:tags":[
        "parlor",
        "drive",
        "ice",
        "cream"
    ],
    "wof:name":"Le Duc Frozen Custard Drive In",
    "wof:placetype":"venue"
},
  "geometry": {"coordinates":[-88.37766000000001,43.013623],"type":"Point"}
}