{
  "type": "Feature",
  "properties": {
    "addr:full":"5872 Durand Ave Racine WI 53406",
    "addr:housenumber":"5872",
    "addr:postcode":"53406",
    "addr:street":"Durand Ave",
    "iso:country":"US",
    "sg:address":"5872 Durand Ave",
    "sg:city":"Racine",
    "sg:classifiers":[
        {
            "category":"Education",
            "subcategory":"Vocational School",
            "type":"Public Place"
        }
    ],
    "sg:phone":"+1 262 554 9277",
    "sg:postcode":"53406",
    "sg:province":"WI",
    "sg:tags":[
        "training",
        "computer"
    ],
    "wof:name":"Compunet Data Syst Wisconsin",
    "wof:placetype":"venue"
},
  "geometry": {"coordinates":[-87.846216,42.697301],"type":"Point"}
}