{
  "type": "Feature",
  "properties": {
    "iso:country":"US",
    "sg:address":"6966 Johnson Ave",
    "sg:city":"Viroqua",
    "sg:classifiers":[
        {
            "category":"Freight",
            "type":"Transportation"
        }
    ],
    "sg:phone":"+1 608 675 3689",
    "sg:postcode":"54665",
    "sg:province":"WI",
    "wof:name":"Fbj Transport Inc",
    "wof:placetype":"venue"
},
  "geometry": {"coordinates":[-90.992946,43.478388],"type":"Point"}
}