{
  "type": "Feature",
  "properties": {
    "iso:country":"US",
    "sg:address":"214 N Washington St",
    "sg:city":"Berlin",
    "sg:classifiers":[
        {
            "category":"Wholesale",
            "subcategory":"Electrical",
            "type":"Manufacturing & Wholesale Goods"
        }
    ],
    "sg:phone":"+1 920 361 1725",
    "sg:postcode":"54923",
    "sg:province":"WI",
    "sg:tags":[
        "communication",
        "radio",
        "system"
    ],
    "sg:website":"www.hark.com",
    "wof:name":"Hark Com",
    "wof:placetype":"venue"
},
  "geometry": {"coordinates":[-88.956754,43.971305],"type":"Point"}
}