{
  "type": "Feature",
  "properties": {
    "iso:country":"US",
    "sg:address":"12126 S Bergen Rd",
    "sg:city":"Clinton",
    "sg:classifiers":[
        {
            "category":"Manufacturing",
            "subcategory":"Metals",
            "type":"Manufacturing & Wholesale Goods"
        }
    ],
    "sg:phone":"+1 262 296 1234",
    "sg:postcode":"53525",
    "sg:province":"WI",
    "sg:tags":[
        "steel",
        "erectors"
    ],
    "wof:name":"Ideal Steel Erectors",
    "wof:placetype":"venue"
},
  "geometry": {"coordinates":[-88.864993,42.495604],"type":"Point"}
}