{
  "type": "Feature",
  "properties": {
    "iso:country":"US",
    "sg:address":"7466 Co Rd Q",
    "sg:city":"Watertown",
    "sg:classifiers":[
        {
            "category":"Real Estate",
            "subcategory":"Real Estate Operator",
            "type":"Services"
        }
    ],
    "sg:phone":"+1 920 261 7660",
    "sg:postcode":"53098",
    "sg:province":"WI",
    "sg:tags":[
        "lessor",
        "farm",
        "corn",
        "crop",
        "field",
        "property"
    ],
    "wof:name":"Mapel Row Farms",
    "wof:placetype":"venue"
},
  "geometry": {"coordinates":[-88.769131,43.241377],"type":"Point"}
}