{
  "type": "Feature",
  "properties": {
    "iso:country":"US",
    "sg:address":"119 Deerfield Rd",
    "sg:city":"Marshall",
    "sg:classifiers":[
        {
            "category":"Manufacturing",
            "subcategory":"Printing",
            "type":"Manufacturing & Wholesale Goods"
        }
    ],
    "sg:phone":"+1 608 655 4686",
    "sg:postcode":"53559",
    "sg:province":"WI",
    "sg:tags":[
        "commercial"
    ],
    "wof:name":"Liberty Printer",
    "wof:placetype":"venue"
},
  "geometry": {"coordinates":[-89.064443,43.167109],"type":"Point"}
}