{
  "type": "Feature",
  "properties": {
    "addr:full":"138 Junction Rd Madison WI 53719",
    "addr:housenumber":"138",
    "addr:postcode":"53719",
    "addr:street":"Junction Rd",
    "iso:country":"US",
    "sg:address":"138 Junction Rd",
    "sg:city":"Madison",
    "sg:classifiers":[
        {
            "category":"Health Services",
            "subcategory":"Doctor",
            "type":"Services"
        }
    ],
    "sg:phone":"+1 608 833 1100",
    "sg:postcode":"53719",
    "sg:province":"WI",
    "sg:tags":[
        "dentist"
    ],
    "sg:website":"www.1stchoicedental.com",
    "wof:name":"First Choice Dental Group SC",
    "wof:placetype":"venue"
},
  "geometry": {"coordinates":[-89.52514499999999,43.074906],"type":"Point"}
}