{
  "type": "Feature",
  "properties": {
    "addr:full":"1052 Main St Stevens Point WI 54481",
    "addr:housenumber":"1052",
    "addr:postcode":"54481",
    "addr:street":"Main St",
    "iso:country":"US",
    "sg:address":"1052 Main St",
    "sg:city":"Stevens Point",
    "sg:classifiers":[
        {
            "category":"Insurance",
            "subcategory":"Insurance Agent",
            "type":"Services"
        }
    ],
    "sg:phone":"+1 715 341 1211",
    "sg:postcode":"54481",
    "sg:province":"WI",
    "wof:name":"Dave Roman & Associates",
    "wof:placetype":"venue"
},
  "geometry": {"coordinates":[-89.584667,44.523478],"type":"Point"}
}