{
  "type": "Feature",
  "properties": {
    "addr:full":"422 Linn St Baraboo WI 53913",
    "addr:housenumber":"422",
    "addr:postcode":"53913",
    "addr:street":"Linn St",
    "iso:country":"US",
    "sg:address":"422 Linn St",
    "sg:city":"Baraboo",
    "sg:classifiers":[
        {
            "category":"Autos & Motor Vehicles",
            "subcategory":"Automobile Sales",
            "type":"Retail Goods"
        }
    ],
    "sg:phone":"+1 608 356 5512",
    "sg:postcode":"53913",
    "sg:province":"WI",
    "sg:tags":[
        "car",
        "dealer"
    ],
    "sg:website":"www.donlarson.com",
    "wof:name":"Don Larson Chevrolet Inc",
    "wof:placetype":"venue"
},
  "geometry": {"coordinates":[-89.765552,43.474721],"type":"Point"}
}