{
  "type": "Feature",
  "properties": {
    "addr:full":"6788 Co Rd G Scandinavia WI 54977",
    "addr:housenumber":"6788",
    "addr:postcode":"54977",
    "addr:street":"Co Rd",
    "iso:country":"US",
    "sg:address":"6788 Co Rd G",
    "sg:city":"Scandinavia",
    "sg:classifiers":[
        {
            "category":"Farming",
            "subcategory":"Dairy Farm",
            "type":"Manufacturing & Wholesale Goods"
        }
    ],
    "sg:phone":"+1 715 445 2624",
    "sg:postcode":"54977",
    "sg:province":"WI",
    "wof:name":"Nygaard Farms",
    "wof:placetype":"venue"
},
  "geometry": {"coordinates":[-89.153659,44.483011],"type":"Point"}
}