{
  "type": "Feature",
  "properties": {
    "addr:full":"1229 8th St Reedsburg WI 53959",
    "addr:housenumber":"1229",
    "addr:postcode":"53959",
    "addr:street":"8Th St",
    "iso:country":"US",
    "sg:address":"1229 8th St",
    "sg:city":"Reedsburg",
    "sg:classifiers":[
        {
            "category":"Organizations",
            "subcategory":"Religious Organization",
            "type":"Services"
        }
    ],
    "sg:phone":"+1 608 524 4719",
    "sg:postcode":"53959",
    "sg:province":"WI",
    "sg:tags":[
        "church"
    ],
    "wof:name":"New Life Assembly Of God",
    "wof:placetype":"venue"
},
  "geometry": {"coordinates":[-89.987134,43.539823],"type":"Point"}
}