{
  "type": "Feature",
  "properties": {
    "addr:full":"443 Connie St Cottage Grove WI 53527",
    "addr:housenumber":"443",
    "addr:postcode":"53527",
    "addr:street":"Connie St",
    "iso:country":"US",
    "sg:address":"443 Connie St",
    "sg:city":"Cottage Grove",
    "sg:classifiers":[
        {
            "category":"Professional",
            "subcategory":"Computer Services",
            "type":"Services"
        }
    ],
    "sg:phone":"+1 608 839 5931",
    "sg:postcode":"53527",
    "sg:province":"WI",
    "sg:tags":[
        "processing",
        "datum"
    ],
    "wof:name":"ADP Dealer Svc",
    "wof:placetype":"venue"
},
  "geometry": {"coordinates":[-89.202572,43.083686],"type":"Point"}
}