{
  "type": "Feature",
  "properties": {
    "addr:full":"1756 University Ave Green Bay WI 54302",
    "addr:housenumber":"1756",
    "addr:postcode":"54302",
    "addr:street":"University Ave",
    "iso:country":"US",
    "sg:address":"1756 University Ave",
    "sg:city":"Green Bay",
    "sg:classifiers":[
        {
            "category":"Professional",
            "subcategory":"Research",
            "type":"Services"
        },
        {
            "category":"Manufacturing",
            "subcategory":"Chemicals & Compounds",
            "type":"Manufacturing & Wholesale Goods"
        }
    ],
    "sg:phone":"+1 920 430 1910",
    "sg:postcode":"54302",
    "sg:province":"WI",
    "sg:tags":[
        "development",
        "biological",
        "product",
        "mfg",
        "laboratory"
    ],
    "wof:name":"Mv Processing Inc",
    "wof:placetype":"venue"
},
  "geometry": {"coordinates":[-87.97833799999999,44.512272],"type":"Point"}
}