{
  "type": "Feature",
  "properties": {
    "iso:country":"US",
    "sg:address":"2301 S Green Bay Rd",
    "sg:city":"Racine",
    "sg:classifiers":[
        {
            "category":"Shopping",
            "subcategory":"Stationery & Office Supplies",
            "type":"Retail Goods"
        }
    ],
    "sg:phone":"+1 262 638 5520",
    "sg:postcode":"53406",
    "sg:province":"WI",
    "wof:name":"Office Max",
    "wof:placetype":"venue"
},
  "geometry": {"coordinates":[-87.85268499999999,42.702405],"type":"Point"}
}