{
  "type": "Feature",
  "properties": {
    "iso:country":"US",
    "sg:address":"468 Gulch Ave",
    "sg:city":"Wisconsin Dells",
    "sg:classifiers":[
        {
            "category":"Government",
            "subcategory":"Office",
            "type":"Public Place"
        }
    ],
    "sg:phone":"+1 608 253 6051",
    "sg:postcode":"53965",
    "sg:province":"WI",
    "sg:tags":[
        "educational",
        "program",
        "administrative"
    ],
    "wof:name":"Tomorrows World Inc",
    "wof:placetype":"venue"
},
  "geometry": {"coordinates":[-89.688956,43.643199],"type":"Point"}
}