{
  "type": "Feature",
  "properties": {
    "addr:full":"2622 Co Rd Y Helenville WI 53137",
    "addr:housenumber":"2622",
    "addr:postcode":"53137",
    "addr:street":"Co Rd Y Helenville",
    "iso:country":"US",
    "sg:address":"2622 Co Rd Y",
    "sg:city":"Helenville",
    "sg:classifiers":[
        {
            "category":"Retail",
            "subcategory":"Animal Services",
            "type":"Services"
        }
    ],
    "sg:phone":"+1 262 593 2539",
    "sg:postcode":"53137",
    "sg:province":"WI",
    "wof:name":"Mike Hachtel Inc",
    "wof:placetype":"venue"
},
  "geometry": {"coordinates":[-88.67845199999999,42.97474],"type":"Point"}
}