{
  "type": "Feature",
  "properties": {
    "addr:full":"20 E Pine St Sturgeon Bay WI 54235",
    "addr:housenumber":"20",
    "addr:postcode":"54235",
    "addr:street":"E Pine St",
    "iso:country":"US",
    "sg:address":"20 E Pine St",
    "sg:city":"Sturgeon Bay",
    "sg:classifiers":[
        {
            "category":"Building & Trades",
            "subcategory":"Electrical",
            "type":"Services"
        }
    ],
    "sg:phone":"+1 920 743 6770",
    "sg:postcode":"54235",
    "sg:province":"WI",
    "sg:tags":[
        "electrical",
        "electric",
        "contractor"
    ],
    "wof:name":"Gordon's West Side Electric Co",
    "wof:placetype":"venue"
},
  "geometry": {"coordinates":[-87.382414,44.826959],"type":"Point"}
}