{
  "type": "Feature",
  "properties": {
    "iso:country":"US",
    "sg:address":"15827 French Town Ave",
    "sg:city":"Withee",
    "sg:classifiers":[
        {
            "category":"Farming",
            "subcategory":"Farm",
            "type":"Manufacturing & Wholesale Goods"
        }
    ],
    "sg:phone":"+1 715 229 4733",
    "sg:postcode":"54498",
    "sg:province":"WI",
    "sg:tags":[
        "crop",
        "general"
    ],
    "wof:name":"Michael Riemer",
    "wof:placetype":"venue"
},
  "geometry": {"coordinates":[-90.628644,44.99764],"type":"Point"}
}