{
  "type": "Feature",
  "properties": {
    "iso:country":"US",
    "sg:address":"2930 Lawe St",
    "sg:city":"Kaukauna",
    "sg:classifiers":[
        {
            "category":"Restaurant",
            "type":"Food & Drink"
        }
    ],
    "sg:phone":"+1 920 759 1800",
    "sg:postcode":"54130",
    "sg:province":"WI",
    "wof:name":"Cruise In Diner",
    "wof:placetype":"venue"
},
  "geometry": {"coordinates":[-88.255425,44.29443],"type":"Point"}
}