{
  "type": "Feature",
  "properties": {
    "iso:country":"US",
    "sg:address":"208 5th Ave",
    "sg:city":"Baraboo",
    "sg:classifiers":[
        {
            "category":"Social Services",
            "subcategory":"Child Care",
            "type":"Services"
        }
    ],
    "sg:phone":"+1 608 356 3074",
    "sg:postcode":"53913",
    "sg:province":"WI",
    "sg:tags":[
        "day"
    ],
    "wof:name":"Happy Hearts",
    "wof:placetype":"venue"
},
  "geometry": {"coordinates":[-89.745867,43.471965],"type":"Point"}
}