{
  "type": "Feature",
  "properties": {
    "iso:country":"US",
    "sg:address":"3778 Matthews Ln",
    "sg:city":"Viroqua",
    "sg:classifiers":[
        {
            "category":"Real Estate",
            "subcategory":"Real Estate Operator",
            "type":"Services"
        }
    ],
    "sg:phone":"+1 608 483 2139",
    "sg:postcode":"54665",
    "sg:province":"WI",
    "sg:tags":[
        "building",
        "nonresidential"
    ],
    "wof:name":"Boegen Matthews Properties LLC",
    "wof:placetype":"venue"
},
  "geometry": {"coordinates":[-91.074135,43.59127],"type":"Point"}
}