{
  "type": "Feature",
  "properties": {
    "iso:country":"US",
    "sg:address":"29 E Wilson St",
    "sg:city":"Madison",
    "sg:classifiers":[
        {
            "category":"Social Services",
            "type":"Services"
        }
    ],
    "sg:phone":"+1 608 257 8753",
    "sg:postcode":"53703",
    "sg:province":"WI",
    "sg:tags":[
        "support",
        "group"
    ],
    "wof:name":"Columbia Support Network",
    "wof:placetype":"venue"
},
  "geometry": {"coordinates":[-89.380371,43.073062],"type":"Point"}
}