{
  "type": "Feature",
  "properties": {
    "addr:full":"600 N Park St Madison WI 53715",
    "addr:housenumber":"600",
    "addr:postcode":"53715",
    "addr:street":"N Park St",
    "iso:country":"US",
    "sg:address":"600 N Park St",
    "sg:city":"Madison",
    "sg:classifiers":[
        {
            "category":"Education",
            "subcategory":"College",
            "type":"Public Place"
        }
    ],
    "sg:phone":"+1 608 263 3800",
    "sg:postcode":"53715",
    "sg:province":"WI",
    "sg:tags":[
        "department",
        "english"
    ],
    "wof:name":"Department of English",
    "wof:placetype":"venue"
},
  "geometry": {"coordinates":[-89.40058399999999,43.076972],"type":"Point"}
}