{
  "type": "Feature",
  "properties": {
    "iso:country":"US",
    "sg:address":"1565 US Hwy 51 N",
    "sg:city":"Woodruff",
    "sg:classifiers":[
        {
            "category":"Home & Garden",
            "subcategory":"Furniture",
            "type":"Retail Goods"
        }
    ],
    "sg:phone":"+1 715 356 9220",
    "sg:postcode":"54568",
    "sg:province":"WI",
    "sg:tags":[
        "bedding",
        "carpeting"
    ],
    "wof:name":"Sleep Central",
    "wof:placetype":"venue"
},
  "geometry": {"coordinates":[-89.695696,45.923438],"type":"Point"}
}