{
  "type": "Feature",
  "properties": {
    "addr:full":"23985 Co Rd H Shell Lake WI 54871",
    "addr:housenumber":"23985",
    "addr:postcode":"54871",
    "addr:street":"Co Rd H",
    "iso:country":"US",
    "sg:address":"23985 Co Rd H",
    "sg:city":"Shell Lake",
    "sg:classifiers":[
        {
            "category":"Building & Trades",
            "subcategory":"Construction",
            "type":"Services"
        }
    ],
    "sg:phone":"+1 715 244 3474",
    "sg:postcode":"54871",
    "sg:province":"WI",
    "sg:tags":[
        "house"
    ],
    "wof:name":"Stelsel Construction",
    "wof:placetype":"venue"
},
  "geometry": {"coordinates":[-92.09405700000001,45.78161],"type":"Point"}
}