{
  "type": "Feature",
  "properties": {
    "iso:country":"US",
    "sg:address":"102 Lincoln Ct",
    "sg:city":"Mt Horeb",
    "sg:classifiers":[
        {
            "category":"Social Services",
            "type":"Services"
        }
    ],
    "sg:phone":"+1 608 437 7887",
    "sg:postcode":"53572",
    "sg:province":"WI",
    "sg:tags":[
        "organization",
        "welfare"
    ],
    "wof:name":"Mt Horeb Area Food Pantry",
    "wof:placetype":"venue"
},
  "geometry": {"coordinates":[-89.727304,43.008181],"type":"Point"}
}