{
  "type": "Feature",
  "properties": {
    "addr:full":"1333 S 53rd St Apt 3 Milwaukee WI 53214",
    "addr:housenumber":"1333;3",
    "addr:postcode":"53214",
    "addr:street":"S 53Rd St Apt",
    "iso:country":"US",
    "sg:address":"1333 S 53rd St Apt 3",
    "sg:city":"Milwaukee",
    "sg:classifiers":[
        {
            "category":"Structure",
            "subcategory":"Office Building",
            "type":"Public Place"
        }
    ],
    "sg:phone":"+1 414 510 5103",
    "sg:postcode":"53214",
    "sg:province":"WI",
    "sg:tags":[
        "park"
    ],
    "wof:name":"Templemere Properties",
    "wof:placetype":"venue"
},
  "geometry": {"coordinates":[-87.979134,43.017523],"type":"Point"}
}