{
  "type": "Feature",
  "properties": {
    "addr:full":"105 W Main St Madison WI 53703",
    "addr:housenumber":"105",
    "addr:postcode":"53703",
    "addr:street":"W Main St",
    "iso:country":"US",
    "sg:address":"105 W Main St",
    "sg:city":"Madison",
    "sg:classifiers":[
        {
            "category":"Bars & Pubs",
            "type":"Food & Drink"
        }
    ],
    "sg:phone":"+1 608 255 4770",
    "sg:postcode":"53703",
    "sg:province":"WI",
    "sg:website":"www.gennaslounge.com",
    "wof:name":"Gennas Lounge",
    "wof:placetype":"venue"
},
  "geometry": {"coordinates":[-89.38503799999999,43.072381],"type":"Point"}
}