{
  "type": "Feature",
  "properties": {
    "iso:country":"US",
    "sg:address":"1190 Richards Rd",
    "sg:city":"Hartland",
    "sg:classifiers":[
        {
            "category":"Professional",
            "subcategory":"Art Services",
            "type":"Services"
        }
    ],
    "sg:phone":"+1 262 367 9999",
    "sg:postcode":"53029",
    "sg:province":"WI",
    "sg:tags":[
        "graphic",
        "designer"
    ],
    "sg:website":"www.straightupsports.com",
    "wof:name":"Straight-Up Sportswear",
    "wof:placetype":"venue"
},
  "geometry": {"coordinates":[-88.358148,43.085],"type":"Point"}
}