{
  "type": "Feature",
  "properties": {
    "iso:country":"US",
    "sg:address":"1825 N Richmond St",
    "sg:city":"Appleton",
    "sg:classifiers":[
        {
            "category":"Wholesale",
            "subcategory":"Office Equipment",
            "type":"Manufacturing & Wholesale Goods"
        }
    ],
    "sg:phone":"+1 920 731 8130",
    "sg:postcode":"54911",
    "sg:province":"WI",
    "sg:tags":[
        "machine",
        "duplicating",
        "copying"
    ],
    "wof:name":"Herrmann Business Machines",
    "wof:placetype":"venue"
},
  "geometry": {"coordinates":[-88.41578699999999,44.277944],"type":"Point"}
}