{
  "type": "Feature",
  "properties": {
    "addr:full":"2408 Marshall St Manitowoc WI 54220",
    "addr:housenumber":"2408",
    "addr:postcode":"54220",
    "addr:street":"Marshall St",
    "iso:country":"US",
    "sg:address":"2408 Marshall St",
    "sg:city":"Manitowoc",
    "sg:classifiers":[
        {
            "category":"Building & Trades",
            "subcategory":"Construction",
            "type":"Services"
        }
    ],
    "sg:phone":"+1 920 684 2939",
    "sg:postcode":"54220",
    "sg:province":"WI",
    "sg:tags":[
        "hanging",
        "painter",
        "contractor"
    ],
    "wof:name":"J P Painting",
    "wof:placetype":"venue"
},
  "geometry": {"coordinates":[-87.679068,44.087361],"type":"Point"}
}