{
  "type": "Feature",
  "properties": {
    "iso:country":"US",
    "sg:address":"943 Depot St",
    "sg:city":"Manawa",
    "sg:classifiers":[
        {
            "category":"Manufacturing",
            "subcategory":"Food",
            "type":"Manufacturing & Wholesale Goods"
        }
    ],
    "sg:phone":"+1 920 596 3424",
    "sg:postcode":"54949",
    "sg:province":"WI",
    "sg:tags":[
        "canned",
        "specialty",
        "mfg"
    ],
    "wof:name":"Ripon Pickle Co",
    "wof:placetype":"venue"
},
  "geometry": {"coordinates":[-88.926057,44.456093],"type":"Point"}
}