{
  "type": "Feature",
  "properties": {
    "addr:full":"10670 Tritz Rd Portage WI 53901",
    "addr:housenumber":"10670",
    "addr:postcode":"53901",
    "addr:street":"Tritz Rd",
    "iso:country":"US",
    "sg:address":"10670 Tritz Rd",
    "sg:city":"Portage",
    "sg:classifiers":[
        {
            "category":"Travel",
            "subcategory":"Campground",
            "type":"Entertainment"
        }
    ],
    "sg:phone":"+1 608 742 5599",
    "sg:postcode":"53901",
    "sg:province":"WI",
    "sg:tags":[
        "trailer"
    ],
    "wof:name":"Camp Dakota Campgrounds",
    "wof:placetype":"venue"
},
  "geometry": {"coordinates":[-89.531925,43.514999],"type":"Point"}
}