{
  "type": "Feature",
  "properties": {
    "addr:full":"1111 S 46th St Milwaukee WI 53214",
    "addr:housenumber":"1111",
    "addr:postcode":"53214",
    "addr:street":"S 46Th St",
    "iso:country":"US",
    "sg:address":"1111 S 46th St",
    "sg:city":"Milwaukee",
    "sg:classifiers":[
        {
            "category":"Recreation",
            "type":"Entertainment"
        }
    ],
    "sg:phone":"+1 414 672 7583",
    "sg:postcode":"53214",
    "sg:province":"WI",
    "sg:tags":[
        "boxing",
        "instruction"
    ],
    "wof:name":"Ace Boxing Club",
    "wof:placetype":"venue"
},
  "geometry": {"coordinates":[-87.971441,43.019068],"type":"Point"}
}