{
  "type": "Feature",
  "properties": {
    "iso:country":"US",
    "sg:address":"352 N Washington St",
    "sg:city":"Berlin",
    "sg:classifiers":[
        {
            "category":"Retail",
            "subcategory":"Repair Shop",
            "type":"Services"
        }
    ],
    "sg:phone":"+1 920 361 3150",
    "sg:postcode":"54923",
    "sg:province":"WI",
    "sg:tags":[
        "sporting",
        "scooter",
        "motor",
        "motorcycle"
    ],
    "wof:name":"Ace's Cycle Work",
    "wof:placetype":"venue"
},
  "geometry": {"coordinates":[-88.956794,43.978851],"type":"Point"}
}