{
  "type": "Feature",
  "properties": {
    "iso:country":"US",
    "sg:address":"4138 Co Rd B",
    "sg:city":"Wisconsin Dells",
    "sg:classifiers":[
        {
            "category":"Organizations",
            "subcategory":"Religious Organization",
            "type":"Services"
        }
    ],
    "sg:phone":"+1 608 253 4325",
    "sg:postcode":"53965",
    "sg:province":"WI",
    "sg:tags":[
        "church"
    ],
    "sg:website":"www.miracleshealingcenter.com",
    "wof:name":"Miracles Healing Center",
    "wof:placetype":"venue"
},
  "geometry": {"coordinates":[-89.715461,43.655437],"type":"Point"}
}