{
  "type": "Feature",
  "properties": {
    "iso:country":"US",
    "sg:address":"300 Prairie Ave",
    "sg:city":"Green Bay",
    "sg:classifiers":[
        {
            "category":"Professional",
            "type":"Services"
        }
    ],
    "sg:phone":"+1 920 436 5900",
    "sg:postcode":"54303",
    "sg:province":"WI",
    "sg:tags":[
        "establishment"
    ],
    "wof:name":"Fox Valley & Western LTD",
    "wof:placetype":"venue"
},
  "geometry": {"coordinates":[-88.01778899999999,44.533941],"type":"Point"}
}