{
  "type": "Feature",
  "properties": {
    "iso:country":"US",
    "sg:address":"2132 W Shore Dr",
    "sg:city":"Delafield",
    "sg:classifiers":[
        {
            "category":"Manufacturing",
            "subcategory":"Paper Products",
            "type":"Manufacturing & Wholesale Goods"
        }
    ],
    "sg:phone":"+1 262 646 5772",
    "sg:postcode":"53018",
    "sg:province":"WI",
    "sg:tags":[
        "converted",
        "mfg"
    ],
    "wof:name":"S D Warren Company",
    "wof:placetype":"venue"
},
  "geometry": {"coordinates":[-88.39865500000001,43.074737],"type":"Point"}
}