{
  "type": "Feature",
  "properties": {
    "iso:country":"US",
    "sg:address":"215 N Clifton St",
    "sg:city":"Livingston",
    "sg:classifiers":[
        {
            "category":"Wholesale",
            "subcategory":"Farm Supplies",
            "type":"Manufacturing & Wholesale Goods"
        }
    ],
    "sg:phone":"+1 608 943 6402",
    "sg:postcode":"53554",
    "sg:province":"WI",
    "sg:tags":[
        "livestock"
    ],
    "wof:name":"Yalinek Livestock",
    "wof:placetype":"venue"
},
  "geometry": {"coordinates":[-90.436536,42.901332],"type":"Point"}
}