{
  "type": "Feature",
  "properties": {
    "iso:country":"US",
    "sg:address":"2215 S Oneida St",
    "sg:city":"Appleton",
    "sg:classifiers":[
        {
            "category":"Shopping",
            "subcategory":"Department Store",
            "type":"Retail Goods"
        }
    ],
    "sg:phone":"+1 920 733 3175",
    "sg:postcode":"54915",
    "sg:province":"WI",
    "sg:tags":[
        "shop"
    ],
    "wof:name":"Pierce Co Store",
    "wof:placetype":"venue"
},
  "geometry": {"coordinates":[-88.403998,44.24181],"type":"Point"}
}