{
  "type": "Feature",
  "properties": {
    "addr:full":"621 N Westhill Blvd Appleton WI 54914",
    "addr:housenumber":"621",
    "addr:postcode":"54914",
    "addr:street":"N Westhill Blvd",
    "iso:country":"US",
    "sg:address":"621 N Westhill Blvd",
    "sg:city":"Appleton",
    "sg:classifiers":[
        {
            "category":"Banks & Credit Unions",
            "subcategory":"Bank",
            "type":"Services"
        }
    ],
    "sg:phone":"+1 920 733 9066",
    "sg:postcode":"54914",
    "sg:province":"WI",
    "sg:tags":[
        "loan",
        "real estate"
    ],
    "wof:name":"Wells Fargo Financial",
    "wof:placetype":"venue"
},
  "geometry": {"coordinates":[-88.46115,44.266243],"type":"Point"}
}