{
  "type": "Feature",
  "properties": {
    "iso:country":"US",
    "sg:address":"1230 N Knowles Ave",
    "sg:city":"New Richmond",
    "sg:classifiers":[
        {
            "category":"Freight",
            "type":"Transportation"
        }
    ],
    "sg:phone":"+1 715 246 2633",
    "sg:postcode":"54017",
    "sg:province":"WI",
    "sg:tags":[
        "operator",
        "local",
        "trucking"
    ],
    "wof:name":"Pete Za Delivery New Richmo",
    "wof:placetype":"venue"
},
  "geometry": {"coordinates":[-92.534147,45.134421],"type":"Point"}
}