{
  "type": "Feature",
  "properties": {
    "addr:full":"4523 Wedge Rd Bonduel WI 54107",
    "addr:housenumber":"4523",
    "addr:postcode":"54107",
    "addr:street":"Wedge Rd",
    "iso:country":"US",
    "sg:address":"4523 Wedge Rd",
    "sg:city":"Bonduel",
    "sg:classifiers":[
        {
            "category":"Professional",
            "subcategory":"Management & Consulting",
            "type":"Services"
        }
    ],
    "sg:phone":"+1 715 758 7144",
    "sg:postcode":"54107",
    "sg:province":"WI",
    "sg:tags":[
        "business"
    ],
    "wof:name":"Stern Crop Consulting LLC",
    "wof:placetype":"venue"
},
  "geometry": {"coordinates":[-88.4768,44.749463],"type":"Point"}
}