{
  "type": "Feature",
  "properties": {
    "iso:country":"US",
    "sg:address":"20311 Co Hwy S N",
    "sg:city":"Gilman",
    "sg:classifiers":[
        {
            "category":"Farming",
            "subcategory":"Dairy Farm",
            "type":"Manufacturing & Wholesale Goods"
        }
    ],
    "sg:phone":"+1 715 447 8473",
    "sg:postcode":"54433",
    "sg:province":"WI",
    "wof:name":"Stanek Farms",
    "wof:placetype":"venue"
},
  "geometry": {"coordinates":[-90.948215,45.137171],"type":"Point"}
}