{
  "type": "Feature",
  "properties": {
    "iso:country":"US",
    "sg:address":"204 Ski Ct",
    "sg:city":"Madison",
    "sg:classifiers":[
        {
            "category":"Building & Trades",
            "subcategory":"Construction",
            "type":"Services"
        }
    ],
    "sg:phone":"+1 608 271 8588",
    "sg:postcode":"53713",
    "sg:province":"WI",
    "sg:tags":[
        "contractor"
    ],
    "wof:name":"Steven Topp Construction",
    "wof:placetype":"venue"
},
  "geometry": {"coordinates":[-89.386549,43.033241],"type":"Point"}
}