{
  "type": "Feature",
  "properties": {
    "iso:country":"US",
    "sg:address":"102 Arneson Rd",
    "sg:city":"Barneveld",
    "sg:classifiers":[
        {
            "category":"Social Services",
            "subcategory":"Adult Care",
            "type":"Services"
        }
    ],
    "sg:phone":"+1 608 924 8743",
    "sg:postcode":"53507",
    "sg:province":"WI",
    "sg:tags":[
        "organization",
        "senior",
        "citizen"
    ],
    "wof:name":"Seniors United For Nutrition",
    "wof:placetype":"venue"
},
  "geometry": {"coordinates":[-89.892899,43.015533],"type":"Point"}
}