{
  "type": "Feature",
  "properties": {
    "iso:country":"US",
    "sg:address":"2128 E Norse Ave",
    "sg:city":"Cudahy",
    "sg:classifiers":[
        {
            "category":"Shopping",
            "subcategory":"Clothing, Apparel, & Fashions",
            "type":"Retail Goods"
        }
    ],
    "sg:phone":"+1 414 744 5700",
    "sg:postcode":"53110",
    "sg:province":"WI",
    "sg:tags":[
        "pattern",
        "maker"
    ],
    "wof:name":"Finn Pattern Co. Inc.",
    "wof:placetype":"venue"
},
  "geometry": {"coordinates":[-87.883076,42.936599],"type":"Point"}
}