{
  "type": "Feature",
  "properties": {
    "iso:country":"US",
    "sg:address":"3201 Tommys Tpke",
    "sg:city":"Plover",
    "sg:classifiers":[
        {
            "category":"Professional",
            "type":"Services"
        }
    ],
    "sg:phone":"+1 715 342 4365",
    "sg:postcode":"54467",
    "sg:province":"WI",
    "wof:name":"Kurt L Gullikson",
    "wof:placetype":"venue"
},
  "geometry": {"coordinates":[-89.55214700000001,44.481671],"type":"Point"}
}