{
  "type": "Feature",
  "properties": {
    "iso:country":"US",
    "sg:address":"1531 E Racine Ave",
    "sg:city":"Waukesha",
    "sg:classifiers":[
        {
            "category":"Social Services",
            "subcategory":"Child Care",
            "type":"Services"
        }
    ],
    "sg:phone":"+1 262 544 1316",
    "sg:postcode":"53186",
    "sg:province":"WI",
    "sg:tags":[
        "day"
    ],
    "wof:name":"Bluemund Pre Schols Child Care",
    "wof:placetype":"venue"
},
  "geometry": {"coordinates":[-88.20697800000001,42.997233],"type":"Point"}
}