{
  "type": "Feature",
  "properties": {
    "iso:country":"US",
    "sg:address":"18675 Saint Andrew Ln",
    "sg:city":"Brookfield",
    "sg:classifiers":[
        {
            "category":"Professional",
            "subcategory":"Management & Consulting",
            "type":"Services"
        },
        {
            "category":"Professional",
            "subcategory":"Advertising",
            "type":"Services"
        }
    ],
    "sg:phone":"+1 262 783 5100",
    "sg:postcode":"53045",
    "sg:province":"WI",
    "sg:tags":[
        "motion",
        "counselor"
    ],
    "wof:name":"TMC Marketing Communications",
    "wof:placetype":"venue"
},
  "geometry": {"coordinates":[-88.144138,43.089398],"type":"Point"}
}