{
  "type": "Feature",
  "properties": {
    "iso:country":"US",
    "sg:address":"1244 West Blvd",
    "sg:city":"Racine",
    "sg:classifiers":[
        {
            "category":"Banks & Credit Unions",
            "subcategory":"Investment Brokerage",
            "type":"Services"
        }
    ],
    "sg:phone":"+1 262 635 0088",
    "sg:postcode":"53405",
    "sg:province":"WI",
    "sg:tags":[
        "advisory"
    ],
    "wof:name":"Lifetime Trusted Advisors",
    "wof:placetype":"venue"
},
  "geometry": {"coordinates":[-87.816262,42.717744],"type":"Point"}
}