{
  "type": "Feature",
  "properties": {
    "addr:full":"9303 Schiff Rd South Range WI 54874",
    "addr:postcode":"9303;54874",
    "addr:street":"Schiff Rd",
    "iso:country":"US",
    "sg:address":"9303 Schiff Rd",
    "sg:city":"South Range",
    "sg:classifiers":[
        {
            "category":"Shopping",
            "subcategory":"Clothing, Apparel, & Fashions",
            "type":"Retail Goods"
        }
    ],
    "sg:phone":"+1 715 364 8461",
    "sg:postcode":"54874",
    "sg:province":"WI",
    "sg:tags":[
        "sell",
        "equipment",
        "horse",
        "western",
        "clothes"
    ],
    "wof:name":"Rocking Horse Ridge",
    "wof:placetype":"venue"
},
  "geometry": {"coordinates":[-91.820038,46.655304],"type":"Point"}
}