{
  "type": "Feature",
  "properties": {
    "iso:country":"US",
    "sg:address":"284 S Falls St",
    "sg:city":"River Falls",
    "sg:classifiers":[
        {
            "category":"Building & Trades",
            "subcategory":"Landscaping Services",
            "type":"Services"
        }
    ],
    "sg:phone":"+1 715 425 8484",
    "sg:postcode":"54022",
    "sg:province":"WI",
    "wof:name":"Grasshopper Lawn Service Inc",
    "wof:placetype":"venue"
},
  "geometry": {"coordinates":[-92.633467,44.856894],"type":"Point"}
}