{
  "type": "Feature",
  "properties": {
    "iso:country":"US",
    "sg:address":"536 Monument Sq",
    "sg:city":"Racine",
    "sg:classifiers":[
        {
            "category":"Restaurant",
            "type":"Food & Drink"
        }
    ],
    "sg:phone":"+1 262 619 9830",
    "sg:postcode":"53403",
    "sg:province":"WI",
    "wof:name":"Reed's Carry Out Restaurant",
    "wof:placetype":"venue"
},
  "geometry": {"coordinates":[-87.783332,42.727254],"type":"Point"}
}