{
  "type": "Feature",
  "properties": {
    "iso:country":"US",
    "sg:address":"314 W Main St",
    "sg:city":"Arcadia",
    "sg:classifiers":[
        {
            "category":"Communications",
            "subcategory":"Radio Station",
            "type":"Services"
        }
    ],
    "sg:phone":"+1 608 323 3322",
    "sg:postcode":"54612",
    "sg:province":"WI",
    "sg:tags":[
        "company",
        "broadcasting"
    ],
    "wof:name":"KWNO",
    "wof:placetype":"venue"
},
  "geometry": {"coordinates":[-91.50275000000001,44.252886],"type":"Point"}
}