{
  "type": "Feature",
  "properties": {
    "addr:full":"1004 W Crescent Dr Manitowoc WI 54220",
    "addr:housenumber":"1004",
    "addr:postcode":"54220",
    "addr:street":"W Crescent Dr",
    "iso:country":"US",
    "sg:address":"1004 W Crescent Dr",
    "sg:city":"Manitowoc",
    "sg:classifiers":[
        {
            "category":"Restaurant",
            "type":"Food & Drink"
        }
    ],
    "sg:phone":"+1 920 684 3956",
    "sg:postcode":"54220",
    "sg:province":"WI",
    "sg:tags":[
        "eating"
    ],
    "wof:name":"Clipper Drive LLC",
    "wof:placetype":"venue"
},
  "geometry": {"coordinates":[-87.692809,44.108665],"type":"Point"}
}