{
  "type": "Feature",
  "properties": {
    "iso:country":"US",
    "sg:address":"759 N Milwaukee St",
    "sg:city":"Milwaukee",
    "sg:classifiers":[
        {
            "category":"Professional",
            "subcategory":"Employment Agencies",
            "type":"Services"
        }
    ],
    "sg:phone":"+1 414 273 7111",
    "sg:postcode":"53202",
    "sg:province":"WI",
    "sg:tags":[
        "consultant",
        "search",
        "executive"
    ],
    "wof:name":"Vogel & Assoc",
    "wof:placetype":"venue"
},
  "geometry": {"coordinates":[-87.906841,43.040977],"type":"Point"}
}