{
  "type": "Feature",
  "properties": {
    "iso:country":"US",
    "sg:address":"2837 W Golf Cir",
    "sg:city":"Thiensville",
    "sg:classifiers":[
        {
            "category":"Real Estate",
            "subcategory":"Real Estate Operator",
            "type":"Services"
        }
    ],
    "sg:phone":"+1 262 238 0663",
    "sg:postcode":"53092",
    "sg:province":"WI",
    "sg:tags":[
        "building",
        "apartment"
    ],
    "wof:name":"Cardinal Realty",
    "wof:placetype":"venue"
},
  "geometry": {"coordinates":[-87.946552,43.244075],"type":"Point"}
}