{
  "type": "Feature",
  "properties": {
    "iso:country":"US",
    "sg:address":"8915 Pickerel Lake Rd",
    "sg:city":"Pickerel",
    "sg:classifiers":[
        {
            "category":"Travel",
            "subcategory":"Hotels & Motels",
            "type":"Entertainment"
        }
    ],
    "sg:phone":"+1 715 484 2703",
    "sg:postcode":"54465",
    "sg:province":"WI",
    "sg:tags":[
        "resort"
    ],
    "wof:name":"Jerry's",
    "wof:placetype":"venue"
},
  "geometry": {"coordinates":[-88.88918700000001,45.400849],"type":"Point"}
}