{
  "type": "Feature",
  "properties": {
    "iso:country":"US",
    "sg:address":"2611 Co Rd V",
    "sg:city":"Reedsburg",
    "sg:classifiers":[
        {
            "category":"Professional",
            "subcategory":"Management & Consulting",
            "type":"Services"
        }
    ],
    "sg:phone":"+1 608 524 6637",
    "sg:postcode":"53959",
    "sg:province":"WI",
    "sg:tags":[
        "business"
    ],
    "wof:name":"Citetek LLC",
    "wof:placetype":"venue"
},
  "geometry": {"coordinates":[-90.011624,43.545017],"type":"Point"}
}