{
  "type": "Feature",
  "properties": {
    "iso:country":"US",
    "sg:address":"218 W River St",
    "sg:city":"Wautoma",
    "sg:classifiers":[
        {
            "category":"Farming",
            "subcategory":"Farm",
            "type":"Manufacturing & Wholesale Goods"
        }
    ],
    "sg:phone":"+1 920 787 4775",
    "sg:postcode":"54982",
    "sg:province":"WI",
    "sg:tags":[
        "crop",
        "general"
    ],
    "wof:name":"Gordon Detlor",
    "wof:placetype":"venue"
},
  "geometry": {"coordinates":[-89.29015,44.072134],"type":"Point"}
}