{
  "type": "Feature",
  "properties": {
    "iso:country":"US",
    "sg:address":"15 N Vine Ave",
    "sg:city":"Marshfield",
    "sg:classifiers":[
        {
            "category":"Railroad",
            "type":"Transportation"
        }
    ],
    "sg:phone":"+1 715 384 8742",
    "sg:postcode":"54449",
    "sg:province":"WI",
    "sg:tags":[
        "rail"
    ],
    "wof:name":"Wisconsin Central LTD",
    "wof:placetype":"venue"
},
  "geometry": {"coordinates":[-90.167653,44.665649],"type":"Point"}
}