{
  "type": "Feature",
  "properties": {
    "iso:country":"US",
    "sg:address":"109 Walnut St",
    "sg:city":"Baraboo",
    "sg:classifiers":[
        {
            "category":"Bars & Pubs",
            "type":"Food & Drink"
        }
    ],
    "sg:phone":"+1 608 356 6434",
    "sg:postcode":"53913",
    "sg:province":"WI",
    "sg:tags":[
        "drinking"
    ],
    "wof:name":"Bumps",
    "wof:placetype":"venue"
},
  "geometry": {"coordinates":[-89.740587,43.466132],"type":"Point"}
}