{
  "type": "Feature",
  "properties": {
    "iso:country":"US",
    "sg:address":"2315 Bramblewood Ct",
    "sg:city":"Waukesha",
    "sg:classifiers":[
        {
            "category":"Professional",
            "subcategory":"Business Services",
            "type":"Services"
        }
    ],
    "sg:phone":"+1 262 574 9010",
    "sg:postcode":"53188",
    "sg:province":"WI",
    "wof:name":"Dalne Group LLC",
    "wof:placetype":"venue"
},
  "geometry": {"coordinates":[-88.26506000000001,43.03334],"type":"Point"}
}