{
  "type": "Feature",
  "properties": {
    "iso:country":"US",
    "sg:address":"949 Cameron Bridge Dr",
    "sg:city":"Amery",
    "sg:classifiers":[
        {
            "category":"Retail",
            "subcategory":"Auto Repair",
            "type":"Services"
        }
    ],
    "sg:phone":"+1 715 268 5290",
    "sg:postcode":"54001",
    "sg:province":"WI",
    "sg:tags":[
        "automotive",
        "used",
        "general"
    ],
    "wof:name":"Quality Auto Sales & Lube",
    "wof:placetype":"venue"
},
  "geometry": {"coordinates":[-92.353692,45.346731],"type":"Point"}
}