{
  "type": "Feature",
  "properties": {
    "iso:country":"US",
    "sg:address":"1783 Thierer Rd",
    "sg:city":"Madison",
    "sg:classifiers":[
        {
            "category":"Professional",
            "subcategory":"Employment Agencies",
            "type":"Services"
        }
    ],
    "sg:phone":"+1 608 241 1500",
    "sg:postcode":"53704",
    "sg:province":"WI",
    "sg:tags":[
        "opportunity"
    ],
    "wof:name":"Adecco",
    "wof:placetype":"venue"
},
  "geometry": {"coordinates":[-89.313436,43.122893],"type":"Point"}
}