{
  "type": "Feature",
  "properties": {
    "iso:country":"US",
    "sg:address":"5152 W Netherwood Rd",
    "sg:city":"Oregon",
    "sg:classifiers":[
        {
            "category":"Farming",
            "subcategory":"Livestock Farm",
            "type":"Manufacturing & Wholesale Goods"
        }
    ],
    "sg:phone":"+1 608 835 3353",
    "sg:postcode":"53575",
    "sg:province":"WI",
    "sg:tags":[
        "beef",
        "feedlot",
        "cattle"
    ],
    "wof:name":"Alpine Dairy Inc",
    "wof:placetype":"venue"
},
  "geometry": {"coordinates":[-89.388851,42.936256],"type":"Point"}
}