{
  "type": "Feature",
  "properties": {
    "iso:country":"US",
    "sg:address":"4477 Co Rd I",
    "sg:city":"Lowell",
    "sg:classifiers":[
        {
            "category":"Building & Trades",
            "subcategory":"Construction",
            "type":"Services"
        }
    ],
    "sg:phone":"+1 920 927 3367",
    "sg:postcode":"53557",
    "sg:province":"WI",
    "sg:tags":[
        "grading",
        "contractor"
    ],
    "wof:name":"Justmann Grading",
    "wof:placetype":"venue"
},
  "geometry": {"coordinates":[-88.806359,43.355808],"type":"Point"}
}