{
  "type": "Feature",
  "properties": {
    "iso:country":"US",
    "sg:address":"1003 Willis Ave",
    "sg:city":"Ashland",
    "sg:classifiers":[
        {
            "category":"Professional",
            "subcategory":"Business Services",
            "type":"Services"
        }
    ],
    "sg:phone":"+1 715 682 6874",
    "sg:postcode":"54806",
    "sg:province":"WI",
    "wof:name":"Star Signs Inc",
    "wof:placetype":"venue"
},
  "geometry": {"coordinates":[-90.870982,46.587403],"type":"Point"}
}