{
  "type": "Feature",
  "properties": {
    "iso:country":"US",
    "sg:address":"2423 Tower Ave",
    "sg:city":"Superior",
    "sg:classifiers":[
        {
            "category":"Personal",
            "subcategory":"Beauty Salon",
            "type":"Services"
        }
    ],
    "sg:phone":"+1 715 392 8834",
    "sg:postcode":"54880",
    "sg:province":"WI",
    "sg:tags":[
        "shop"
    ],
    "wof:name":"Cost Cutters",
    "wof:placetype":"venue"
},
  "geometry": {"coordinates":[-92.104079,46.707939],"type":"Point"}
}