{
  "type": "Feature",
  "properties": {
    "addr:full":"1023 N 9th St Manitowoc WI 54220",
    "addr:housenumber":"1023",
    "addr:postcode":"54220",
    "addr:street":"N 9Th St",
    "iso:country":"US",
    "sg:address":"1023 N 9th St",
    "sg:city":"Manitowoc",
    "sg:classifiers":[
        {
            "category":"Wholesale",
            "subcategory":"Stationery",
            "type":"Manufacturing & Wholesale Goods"
        }
    ],
    "sg:phone":"+1 920 686 0994",
    "sg:postcode":"54220",
    "sg:province":"WI",
    "sg:tags":[
        "map"
    ],
    "wof:name":"Backcountry Enterprises",
    "wof:placetype":"venue"
},
  "geometry": {"coordinates":[-87.659046,44.107931],"type":"Point"}
}