{
  "type": "Feature",
  "properties": {
    "iso:country":"US",
    "sg:address":"3056 140th St",
    "sg:city":"Frederic",
    "sg:classifiers":[
        {
            "category":"Travel",
            "subcategory":"Travel Agent",
            "type":"Entertainment"
        }
    ],
    "sg:phone":"+1 715 327 4640",
    "sg:postcode":"54837",
    "sg:province":"WI",
    "sg:tags":[
        "agency",
        "bureau"
    ],
    "wof:name":"Four Seasons Travel",
    "wof:placetype":"venue"
},
  "geometry": {"coordinates":[-92.447667,45.65417],"type":"Point"}
}