{
  "type": "Feature",
  "properties": {
    "iso:country":"US",
    "sg:address":"413 Tower Ave",
    "sg:city":"Superior",
    "sg:classifiers":[
        {
            "category":"Bars & Pubs",
            "type":"Food & Drink"
        }
    ],
    "sg:phone":"+1 715 394 9747",
    "sg:postcode":"54880",
    "sg:province":"WI",
    "sg:tags":[
        "drinking"
    ],
    "wof:name":"Anderson Thomas",
    "wof:placetype":"venue"
},
  "geometry": {"coordinates":[-92.103917,46.73271],"type":"Point"}
}