{
  "type": "Feature",
  "properties": {
    "iso:country":"US",
    "sg:address":"100 E Geneva Sq",
    "sg:city":"Lake Geneva",
    "sg:classifiers":[
        {
            "category":"Food & Beverages",
            "subcategory":"Groceries & Convenience Stores",
            "type":"Retail Goods"
        }
    ],
    "sg:phone":"+1 262 248 8798",
    "sg:postcode":"53147",
    "sg:province":"WI",
    "sg:tags":[
        "supermarket"
    ],
    "wof:name":"Pick-N-Save",
    "wof:placetype":"venue"
},
  "geometry": {"coordinates":[-88.424688,42.606454],"type":"Point"}
}