{
  "type": "Feature",
  "properties": {
    "addr:full":"3340 San Marcos Dr Brookfield WI 53005",
    "addr:housenumber":"3340",
    "addr:postcode":"53005",
    "addr:street":"San Marcos Dr",
    "iso:country":"US",
    "sg:address":"3340 San Marcos Dr",
    "sg:city":"Brookfield",
    "sg:classifiers":[
        {
            "category":"Professional",
            "subcategory":"Business Services",
            "type":"Services"
        }
    ],
    "sg:phone":"+1 262 781 4041",
    "sg:postcode":"53005",
    "sg:province":"WI",
    "sg:tags":[
        "translator",
        "interpreter"
    ],
    "wof:name":"FGT Interantional",
    "wof:placetype":"venue"
},
  "geometry": {"coordinates":[-88.09822200000001,43.080648],"type":"Point"}
}