{
  "type": "Feature",
  "properties": {
    "iso:country":"US",
    "sg:address":"1636 Quincy Ave",
    "sg:city":"Racine",
    "sg:classifiers":[
        {
            "category":"Social Services",
            "subcategory":"Child Care",
            "type":"Services"
        }
    ],
    "sg:phone":"+1 262 631 1377",
    "sg:postcode":"53405",
    "sg:province":"WI",
    "sg:tags":[
        "day"
    ],
    "wof:name":"Coenekas Development Center",
    "wof:placetype":"venue"
},
  "geometry": {"coordinates":[-87.813743,42.71133],"type":"Point"}
}