{
  "type": "Feature",
  "properties": {
    "addr:full":"6148 170th St Elmwood WI 54740",
    "addr:housenumber":"6148",
    "addr:postcode":"54740",
    "addr:street":"170Th St",
    "iso:country":"US",
    "sg:address":"6148 170th St",
    "sg:city":"Elmwood",
    "sg:classifiers":[
        {
            "category":"Farming",
            "subcategory":"Dairy Farm",
            "type":"Manufacturing & Wholesale Goods"
        }
    ],
    "sg:phone":"+1 715 639 3205",
    "sg:postcode":"54740",
    "sg:province":"WI",
    "wof:name":"Blueberry Hill Bison",
    "wof:placetype":"venue"
},
  "geometry": {"coordinates":[-92.216539,44.759419],"type":"Point"}
}