{
  "type": "Feature",
  "properties": {
    "addr:full":"14478 Deer Run Rd Muscoda WI 53573",
    "addr:housenumber":"14478",
    "addr:postcode":"53573",
    "addr:street":"Deer Run Rd",
    "iso:country":"US",
    "sg:address":"14478 Deer Run Rd",
    "sg:city":"Muscoda",
    "sg:classifiers":[
        {
            "category":"Farming",
            "subcategory":"Livestock Farm",
            "type":"Manufacturing & Wholesale Goods"
        }
    ],
    "sg:phone":"+1 608 536 3518",
    "sg:postcode":"53573",
    "sg:province":"WI",
    "sg:tags":[
        "beef",
        "feedlot",
        "cattle"
    ],
    "wof:name":"Mark Storms",
    "wof:placetype":"venue"
},
  "geometry": {"coordinates":[-90.556766,43.357991],"type":"Point"}
}