{
  "type": "Feature",
  "properties": {
    "iso:country":"US",
    "sg:address":"300 5th St",
    "sg:city":"Racine",
    "sg:classifiers":[
        {
            "category":"Professional",
            "type":"Services"
        }
    ],
    "sg:phone":"+1 262 636 9330",
    "sg:postcode":"53403",
    "sg:province":"WI",
    "sg:tags":[
        "establishment"
    ],
    "wof:name":"Crime Stoppers",
    "wof:placetype":"venue"
},
  "geometry": {"coordinates":[-87.78523800000001,42.727782],"type":"Point"}
}