{
  "type": "Feature",
  "properties": {
    "addr:full":"1215 Winter St Superior WI 54880",
    "addr:housenumber":"1215",
    "addr:postcode":"54880",
    "addr:street":"Winter St",
    "iso:country":"US",
    "sg:address":"1215 Winter St",
    "sg:city":"Superior",
    "sg:classifiers":[
        {
            "category":"Retail",
            "subcategory":"Auto Rental",
            "type":"Services"
        }
    ],
    "sg:phone":"+1 715 392 9005",
    "sg:postcode":"54880",
    "sg:province":"WI",
    "sg:tags":[
        "renting",
        "truck",
        "leasing"
    ],
    "wof:name":"Budget Truck Rental",
    "wof:placetype":"venue"
},
  "geometry": {"coordinates":[-92.09617,46.727951],"type":"Point"}
}