{
  "type": "Feature",
  "properties": {
    "addr:full":"2644 State Hwy 116 Waukau WI 54980",
    "addr:housenumber":"2644",
    "addr:postcode":"54980",
    "addr:street":"State Hwy 116",
    "iso:country":"US",
    "sg:address":"2644 State Hwy 116",
    "sg:city":"Waukau",
    "sg:classifiers":[
        {
            "category":"Organizations",
            "subcategory":"Religious Organization",
            "type":"Services"
        }
    ],
    "sg:phone":"+1 920 685 5389",
    "sg:postcode":"54980",
    "sg:province":"WI",
    "sg:tags":[
        "church"
    ],
    "wof:name":"Waukau United Methodist Church",
    "wof:placetype":"venue"
},
  "geometry": {"coordinates":[-88.77171300000001,43.988913],"type":"Point"}
}