{
  "type": "Feature",
  "properties": {
    "iso:country":"US",
    "sg:address":"7065 Pine Forest Rd",
    "sg:city":"Phillips",
    "sg:classifiers":[
        {
            "category":"Shopping",
            "subcategory":"Clothing, Apparel, & Fashions",
            "type":"Retail Goods"
        }
    ],
    "sg:phone":"+1 715 339 4864",
    "sg:postcode":"54555",
    "sg:province":"WI",
    "wof:name":"Mill Creek Apparel",
    "wof:placetype":"venue"
},
  "geometry": {"coordinates":[-90.420332,45.692169],"type":"Point"}
}