{
  "type": "Feature",
  "properties": {
    "iso:country":"US",
    "sg:address":"8217 S 27th St",
    "sg:city":"Franklin",
    "sg:classifiers":[
        {
            "category":"Shopping",
            "type":"Retail Goods"
        }
    ],
    "sg:phone":"+1 414 304 1010",
    "sg:postcode":"53132",
    "sg:province":"WI",
    "sg:tags":[
        "telephone",
        "cellular"
    ],
    "wof:name":"Cell U All",
    "wof:placetype":"venue"
},
  "geometry": {"coordinates":[-87.950553,42.900216],"type":"Point"}
}