{
  "type": "Feature",
  "properties": {
    "iso:country":"US",
    "sg:address":"13085 Woodfield Ln",
    "sg:city":"New Berlin",
    "sg:classifiers":[
        {
            "category":"Real Estate",
            "subcategory":"Real Estate Agent",
            "type":"Services"
        }
    ],
    "sg:phone":"+1 414 427 9968",
    "sg:postcode":"53151",
    "sg:province":"WI",
    "wof:name":"Shorewest Realtors",
    "wof:placetype":"venue"
},
  "geometry": {"coordinates":[-88.078907,42.941011],"type":"Point"}
}