{
  "type": "Feature",
  "properties": {
    "iso:country":"US",
    "sg:address":"3151 S Nevada St",
    "sg:city":"Milwaukee",
    "sg:classifiers":[
        {
            "category":"Building & Trades",
            "subcategory":"Construction",
            "type":"Services"
        }
    ],
    "sg:phone":"+1 414 483 8011",
    "sg:postcode":"53207",
    "sg:province":"WI",
    "sg:tags":[
        "concrete",
        "masonry",
        "contractor"
    ],
    "wof:name":"Johnmark Inc",
    "wof:placetype":"venue"
},
  "geometry": {"coordinates":[-87.891983,42.987356],"type":"Point"}
}