{
  "type": "Feature",
  "properties": {
    "iso:country":"US",
    "sg:address":"2001 Jay Eye See Ave",
    "sg:city":"Racine",
    "sg:classifiers":[
        {
            "category":"Building & Trades",
            "subcategory":"Construction",
            "type":"Services"
        }
    ],
    "sg:phone":"+1 262 632 2269",
    "sg:postcode":"53403",
    "sg:province":"WI",
    "sg:tags":[
        "home",
        "improvement"
    ],
    "wof:name":"Mike Jorgenson Home Improvemnt",
    "wof:placetype":"venue"
},
  "geometry": {"coordinates":[-87.803039,42.704249],"type":"Point"}
}