{
  "type": "Feature",
  "properties": {
    "iso:country":"US",
    "sg:address":"4902 Cottage Grove Rd",
    "sg:city":"Madison",
    "sg:classifiers":[
        {
            "category":"Real Estate",
            "subcategory":"Real Estate Operator",
            "type":"Services"
        }
    ],
    "sg:phone":"+1 608 221 1364",
    "sg:postcode":"53716",
    "sg:province":"WI",
    "sg:tags":[
        "building",
        "apartment"
    ],
    "wof:name":"Garden Court Apts Inc",
    "wof:placetype":"venue"
},
  "geometry": {"coordinates":[-89.297224,43.084374],"type":"Point"}
}