{
  "type": "Feature",
  "properties": {
    "iso:country":"US",
    "sg:address":"5324 N Shoreland Ave",
    "sg:city":"Milwaukee",
    "sg:classifiers":[
        {
            "category":"Education",
            "subcategory":"Special Training",
            "type":"Public Place"
        }
    ],
    "sg:phone":"+1 414 962 6259",
    "sg:postcode":"53217",
    "sg:province":"WI",
    "wof:name":"Alamelus Culinary Enterprise",
    "wof:placetype":"venue"
},
  "geometry": {"coordinates":[-87.90798599999999,43.115651],"type":"Point"}
}