{
  "type": "Feature",
  "properties": {
    "iso:country":"US",
    "sg:address":"650 Oak Park Ave",
    "sg:city":"Fond Du Lac",
    "sg:classifiers":[
        {
            "category":"Manufacturing",
            "subcategory":"Metals",
            "type":"Manufacturing & Wholesale Goods"
        }
    ],
    "sg:phone":"+1 920 922 5066",
    "sg:postcode":"54935",
    "sg:province":"WI",
    "sg:tags":[
        "chrome",
        "plating",
        "hard",
        "electroplating"
    ],
    "wof:name":"U S Chrome Corp Of Wisconsin",
    "wof:placetype":"venue"
},
  "geometry": {"coordinates":[-88.467554,43.761301],"type":"Point"}
}