{
  "type": "Feature",
  "properties": {
    "iso:country":"US",
    "sg:address":"4701 Hillcrest Dr",
    "sg:city":"West Bend",
    "sg:classifiers":[
        {
            "category":"Manufacturing",
            "subcategory":"Retail Goods",
            "type":"Manufacturing & Wholesale Goods"
        }
    ],
    "sg:phone":"+1 262 629 9980",
    "sg:postcode":"53095",
    "sg:province":"WI",
    "sg:tags":[
        "product",
        "mfg"
    ],
    "wof:name":"Lean Mfg Systems LLC",
    "wof:placetype":"venue"
},
  "geometry": {"coordinates":[-88.27093499999999,43.413028],"type":"Point"}
}