{
  "type": "Feature",
  "properties": {
    "iso:country":"US",
    "sg:address":"1575 S 10th St",
    "sg:city":"Milwaukee",
    "sg:classifiers":[
        {
            "category":"Organizations",
            "subcategory":"Religious Organization",
            "type":"Services"
        }
    ],
    "sg:phone":"+1 414 643 6055",
    "sg:postcode":"53204",
    "sg:province":"WI",
    "wof:name":"Siggenauk Center",
    "wof:placetype":"venue"
},
  "geometry": {"coordinates":[-87.924077,43.015518],"type":"Point"}
}