{
  "type": "Feature",
  "properties": {
    "iso:country":"US",
    "sg:address":"616 S Military Rd",
    "sg:city":"Fond Du Lac",
    "sg:classifiers":[
        {
            "category":"Building & Trades",
            "subcategory":"Electrical",
            "type":"Services"
        }
    ],
    "sg:phone":"+1 920 921 6550",
    "sg:postcode":"54935",
    "sg:province":"WI",
    "sg:tags":[
        "electric",
        "contractor"
    ],
    "wof:name":"W J Leasa Electric Contractor",
    "wof:placetype":"venue"
},
  "geometry": {"coordinates":[-88.464731,43.76497],"type":"Point"}
}