{
  "type": "Feature",
  "properties": {
    "iso:country":"US",
    "sg:address":"657 Deerwood Dr",
    "sg:city":"Hudson",
    "sg:classifiers":[
        {
            "category":"Wholesale",
            "subcategory":"Fruits & Vegetables",
            "type":"Manufacturing & Wholesale Goods"
        }
    ],
    "sg:phone":"+1 715 386 8080",
    "sg:postcode":"54016",
    "sg:province":"WI",
    "wof:name":"Casallis Produce",
    "wof:placetype":"venue"
},
  "geometry": {"coordinates":[-92.660116,44.943329],"type":"Point"}
}