{
  "type": "Feature",
  "properties": {
    "iso:country":"US",
    "sg:address":"4610 Co Rd H",
    "sg:city":"Fredonia",
    "sg:classifiers":[
        {
            "category":"Manufacturing",
            "subcategory":"Tools & Machinery",
            "type":"Manufacturing & Wholesale Goods"
        }
    ],
    "sg:phone":"+1 262 692 9396",
    "sg:postcode":"53021",
    "sg:province":"WI",
    "sg:tags":[
        "machine",
        "mfg"
    ],
    "wof:name":"Northern Magnetic LLC",
    "wof:placetype":"venue"
},
  "geometry": {"coordinates":[-88.014299,43.493027],"type":"Point"}
}