{
  "type": "Feature",
  "properties": {
    "addr:full":"2200 Center Ave Janesville WI 53546",
    "addr:housenumber":"2200",
    "addr:postcode":"53546",
    "addr:street":"Center Ave",
    "iso:country":"US",
    "sg:address":"2200 Center Ave",
    "sg:city":"Janesville",
    "sg:classifiers":[
        {
            "category":"Banks & Credit Unions",
            "subcategory":"Bank",
            "type":"Services"
        }
    ],
    "sg:phone":"+1 608 756 0116",
    "sg:postcode":"53546",
    "sg:province":"WI",
    "sg:tags":[
        "state"
    ],
    "wof:name":"Teamsters Credit Union",
    "wof:placetype":"venue"
},
  "geometry": {"coordinates":[-89.031228,42.649344],"type":"Point"}
}