{
  "type": "Feature",
  "properties": {
    "iso:country":"US",
    "sg:address":"1310 E Bay Point Rd",
    "sg:city":"Milwaukee",
    "sg:classifiers":[
        {
            "category":"Professional",
            "subcategory":"Management & Consulting",
            "type":"Services"
        }
    ],
    "sg:phone":"+1 414 228 1211",
    "sg:postcode":"53217",
    "sg:province":"WI",
    "sg:tags":[
        "personnel",
        "consultant"
    ],
    "wof:name":"Banks & Dean",
    "wof:placetype":"venue"
},
  "geometry": {"coordinates":[-87.892258,43.186166],"type":"Point"}
}