{
  "type": "Feature",
  "properties": {
    "iso:country":"US",
    "sg:address":"6253 N 118th St",
    "sg:city":"Milwaukee",
    "sg:classifiers":[
        {
            "category":"Professional",
            "subcategory":"Management & Consulting",
            "type":"Services"
        }
    ],
    "sg:phone":"+1 414 353 5422",
    "sg:postcode":"53225",
    "sg:province":"WI",
    "sg:tags":[
        "small",
        "web",
        "develops",
        "for",
        "business"
    ],
    "wof:name":"Brew City Internet",
    "wof:placetype":"venue"
},
  "geometry": {"coordinates":[-88.059066,43.130872],"type":"Point"}
}