{
  "type": "Feature",
  "properties": {
    "iso:country":"US",
    "sg:address":"7246 Co Rd Q",
    "sg:city":"Endeavor",
    "sg:classifiers":[
        {
            "category":"Farming",
            "subcategory":"Livestock Farm",
            "type":"Manufacturing & Wholesale Goods"
        }
    ],
    "sg:phone":"+1 608 981 2368",
    "sg:postcode":"53955",
    "sg:province":"WI",
    "sg:tags":[
        "beef",
        "feedlot",
        "cattle"
    ],
    "wof:name":"Fountain Farms",
    "wof:placetype":"venue"
},
  "geometry": {"coordinates":[-89.360587,43.4048],"type":"Point"}
}