{
  "type": "Feature",
  "properties": {
    "iso:country":"US",
    "sg:address":"4919 W Good Hope Rd",
    "sg:city":"Milwaukee",
    "sg:classifiers":[
        {
            "category":"Professional",
            "subcategory":"Business Services",
            "type":"Services"
        }
    ],
    "sg:phone":"+1 414 351 1100",
    "sg:postcode":"53223",
    "sg:province":"WI",
    "wof:name":"Reynolds & Company Inc",
    "wof:placetype":"venue"
},
  "geometry": {"coordinates":[-87.976588,43.148494],"type":"Point"}
}