{
  "type": "Feature",
  "properties": {
    "iso:country":"US",
    "sg:address":"1126 S Quincy St",
    "sg:city":"Green Bay",
    "sg:classifiers":[
        {
            "category":"Wholesale",
            "subcategory":"Durable Goods & Equipment",
            "type":"Manufacturing & Wholesale Goods"
        }
    ],
    "sg:phone":"+1 920 437 0633",
    "sg:postcode":"54301",
    "sg:province":"WI",
    "sg:tags":[
        "importer"
    ],
    "wof:name":"Varimpex International Co",
    "wof:placetype":"venue"
},
  "geometry": {"coordinates":[-88.018813,44.49798],"type":"Point"}
}