{
  "type": "Feature",
  "properties": {
    "iso:country":"US",
    "sg:address":"1218 Gohres St",
    "sg:city":"La Crosse",
    "sg:classifiers":[
        {
            "category":"Shopping",
            "subcategory":"Used Merchandise",
            "type":"Retail Goods"
        },
        {
            "category":"Shopping",
            "subcategory":"Gifts & Souvenirs",
            "type":"Retail Goods"
        }
    ],
    "sg:phone":"+1 608 785 2866",
    "sg:postcode":"54603",
    "sg:province":"WI",
    "sg:tags":[
        "antique"
    ],
    "wof:name":"Purple Pig",
    "wof:placetype":"venue"
},
  "geometry": {"coordinates":[-91.238537,43.849138],"type":"Point"}
}