{
  "type": "Feature",
  "properties": {
    "addr:full":"2427 Factory Rd Stitzer WI 53825",
    "addr:housenumber":"2427",
    "addr:postcode":"53825",
    "addr:street":"Factory Rd",
    "iso:country":"US",
    "sg:address":"2427 Factory Rd",
    "sg:city":"Stitzer",
    "sg:classifiers":[
        {
            "category":"Manufacturing",
            "subcategory":"Building Materials",
            "type":"Manufacturing & Wholesale Goods"
        }
    ],
    "sg:phone":"+1 608 943 1130",
    "sg:postcode":"53825",
    "sg:province":"WI",
    "sg:tags":[
        "mfg",
        "wood",
        "kitchen",
        "cabinet"
    ],
    "wof:name":"Shady Grove Cabinets",
    "wof:placetype":"venue"
},
  "geometry": {"coordinates":[-90.54313399999999,42.933269],"type":"Point"}
}