{
  "type": "Feature",
  "properties": {
    "iso:country":"US",
    "sg:address":"6633 W Donges Bay Rd",
    "sg:city":"Mequon",
    "sg:classifiers":[
        {
            "category":"Building & Trades",
            "subcategory":"Landscaping Services",
            "type":"Services"
        }
    ],
    "sg:phone":"+1 262 242 7800",
    "sg:postcode":"53092",
    "sg:province":"WI",
    "sg:tags":[
        "landscape",
        "contractor"
    ],
    "wof:name":"Clean Cut Lawn Care",
    "wof:placetype":"venue"
},
  "geometry": {"coordinates":[-87.984854,43.207029],"type":"Point"}
}