{
  "type": "Feature",
  "properties": {
    "iso:country":"US",
    "sg:address":"812 S Fisk St",
    "sg:city":"Green Bay",
    "sg:classifiers":[
        {
            "category":"Building & Trades",
            "subcategory":"Construction",
            "type":"Services"
        }
    ],
    "sg:phone":"+1 920 483 5490",
    "sg:postcode":"54304",
    "sg:province":"WI",
    "sg:tags":[
        "steel",
        "reinforcing"
    ],
    "wof:name":"Viking Steel",
    "wof:placetype":"venue"
},
  "geometry": {"coordinates":[-88.062001,44.519228],"type":"Point"}
}