{
  "type": "Feature",
  "properties": {
    "iso:country":"US",
    "sg:address":"402 N Spring St",
    "sg:city":"Sparta",
    "sg:classifiers":[
        {
            "category":"Health Services",
            "subcategory":"Hospital",
            "type":"Services"
        }
    ],
    "sg:phone":"+1 608 269 6126",
    "sg:postcode":"54656",
    "sg:province":"WI",
    "sg:tags":[
        "specialty"
    ],
    "wof:name":"N L Kewin",
    "wof:placetype":"venue"
},
  "geometry": {"coordinates":[-90.809467,43.948891],"type":"Point"}
}