{
  "type": "Feature",
  "properties": {
    "addr:full":"300 Schweitzer Dr Verona WI 53593",
    "addr:housenumber":"300",
    "addr:postcode":"53593",
    "addr:street":"Schweitzer Dr",
    "iso:country":"US",
    "sg:address":"300 Schweitzer Dr",
    "sg:city":"Verona",
    "sg:classifiers":[
        {
            "category":"Restaurant",
            "type":"Food & Drink"
        }
    ],
    "sg:phone":"+1 608 845 1311",
    "sg:postcode":"53593",
    "sg:province":"WI",
    "sg:tags":[
        "eating"
    ],
    "wof:name":"Haldemans Hot Dawg Hut",
    "wof:placetype":"venue"
},
  "geometry": {"coordinates":[-89.52842,42.987925],"type":"Point"}
}