{
  "type": "Feature",
  "properties": {
    "addr:full":"1320 Wisconsin Ave Racine WI 53403",
    "addr:housenumber":"1320",
    "addr:postcode":"53403",
    "addr:street":"Wisconsin Ave",
    "iso:country":"US",
    "sg:address":"1320 Wisconsin Ave",
    "sg:city":"Racine",
    "sg:classifiers":[
        {
            "category":"Social Services",
            "type":"Services"
        }
    ],
    "sg:phone":"+1 262 636 2401",
    "sg:postcode":"53403",
    "sg:province":"WI",
    "sg:tags":[
        "counselor",
        "marriage",
        "family"
    ],
    "wof:name":"Mental Health Svc-St Lukes",
    "wof:placetype":"venue"
},
  "geometry": {"coordinates":[-87.783728,42.715849],"type":"Point"}
}