{
  "type": "Feature",
  "properties": {
    "iso:country":"US",
    "sg:address":"130 W Edgerton Ave",
    "sg:city":"Milwaukee",
    "sg:classifiers":[
        {
            "category":"Freight",
            "type":"Transportation"
        }
    ],
    "sg:phone":"+1 414 747 8420",
    "sg:postcode":"53207",
    "sg:province":"WI",
    "sg:tags":[
        "operator",
        "local",
        "trucking"
    ],
    "wof:name":"Tyson Wisconsin",
    "wof:placetype":"venue"
},
  "geometry": {"coordinates":[-87.912623,42.952015],"type":"Point"}
}