{
  "type": "Feature",
  "properties": {
    "iso:country":"US",
    "sg:address":"2721 Century Dr",
    "sg:city":"Campbellsport",
    "sg:classifiers":[
        {
            "category":"Building & Trades",
            "subcategory":"Landscaping Services",
            "type":"Services"
        }
    ],
    "sg:phone":"+1 920 533 4312",
    "sg:postcode":"53010",
    "sg:province":"WI",
    "wof:name":"Seefeldt Gary Maintanence Svcs",
    "wof:placetype":"venue"
},
  "geometry": {"coordinates":[-88.292354,43.579326],"type":"Point"}
}