{
  "type": "Feature",
  "properties": {
    "iso:country":"US",
    "sg:address":"4639 Douglas Ave",
    "sg:city":"Racine",
    "sg:classifiers":[
        {
            "category":"Building & Trades",
            "subcategory":"Construction",
            "type":"Services"
        }
    ],
    "sg:phone":"+1 262 639 3769",
    "sg:postcode":"53402",
    "sg:province":"WI",
    "sg:tags":[
        "maker",
        "cabinet"
    ],
    "wof:name":"Crystal Cabinet & Supply Inc",
    "wof:placetype":"venue"
},
  "geometry": {"coordinates":[-87.806782,42.779881],"type":"Point"}
}