{
  "type": "Feature",
  "properties": {
    "iso:country":"US",
    "sg:address":"3114 Union Ave",
    "sg:city":"Sheboygan",
    "sg:classifiers":[
        {
            "category":"Health Services",
            "subcategory":"Clinic",
            "type":"Services"
        }
    ],
    "sg:phone":"+1 920 803 8244",
    "sg:postcode":"53081",
    "sg:province":"WI",
    "sg:tags":[
        "banks",
        "blood",
        "center"
    ],
    "wof:name":"Bio Life Plasma Svc",
    "wof:placetype":"venue"
},
  "geometry": {"coordinates":[-87.745285,43.732168],"type":"Point"}
}