{
  "type": "Feature",
  "properties": {
    "addr:full":"4903 Co Hwy U Hartford WI 53027",
    "addr:housenumber":"4903",
    "addr:postcode":"53027",
    "addr:street":"Co Hwy U",
    "iso:country":"US",
    "sg:address":"4903 Co Hwy U",
    "sg:city":"Hartford",
    "sg:classifiers":[
        {
            "category":"Building & Trades",
            "subcategory":"Landscaping Services",
            "type":"Services"
        }
    ],
    "sg:phone":"+1 262 670 6321",
    "sg:postcode":"53027",
    "sg:province":"WI",
    "sg:tags":[
        "snow",
        "removal"
    ],
    "wof:name":"Sterman Services",
    "wof:placetype":"venue"
},
  "geometry": {"coordinates":[-88.40158599999999,43.370891],"type":"Point"}
}