{
  "type": "Feature",
  "properties": {
    "iso:country":"US",
    "sg:address":"1211 Depot St",
    "sg:city":"Manawa",
    "sg:classifiers":[
        {
            "category":"Manufacturing",
            "subcategory":"Metals",
            "type":"Manufacturing & Wholesale Goods"
        }
    ],
    "sg:phone":"+1 920 596 2501",
    "sg:postcode":"54949",
    "sg:province":"WI",
    "sg:tags":[
        "windows"
    ],
    "wof:name":"Kolbe Vinyl Windows",
    "wof:placetype":"venue"
},
  "geometry": {"coordinates":[-88.927186,44.44961],"type":"Point"}
}