{
  "type": "Feature",
  "properties": {
    "iso:country":"US",
    "sg:address":"3225 Van Roy Rd",
    "sg:city":"Appleton",
    "sg:classifiers":[
        {
            "category":"Recreation",
            "type":"Entertainment"
        }
    ],
    "sg:phone":"+1 920 830 6900",
    "sg:postcode":"54915",
    "sg:province":"WI",
    "wof:name":"Badger Sports Park",
    "wof:placetype":"venue"
},
  "geometry": {"coordinates":[-88.349579,44.257915],"type":"Point"}
}