{
  "type": "Feature",
  "properties": {
    "iso:country":"US",
    "sg:address":"312 Llanos St",
    "sg:city":"Verona",
    "sg:classifiers":[
        {
            "category":"Building & Trades",
            "subcategory":"Construction",
            "type":"Services"
        }
    ],
    "sg:phone":"+1 608 845 7538",
    "sg:postcode":"53593",
    "sg:province":"WI",
    "sg:tags":[
        "general",
        "contractor"
    ],
    "wof:name":"Integrity Building & Design",
    "wof:placetype":"venue"
},
  "geometry": {"coordinates":[-89.529436,42.99907],"type":"Point"}
}