{
  "type": "Feature",
  "properties": {
    "iso:country":"US",
    "sg:address":"1410 N 52nd St",
    "sg:city":"Milwaukee",
    "sg:classifiers":[
        {
            "category":"Professional",
            "type":"Services"
        }
    ],
    "sg:phone":"+1 414 607 7280",
    "sg:postcode":"53208",
    "sg:province":"WI",
    "wof:name":"Linda Jones",
    "wof:placetype":"venue"
},
  "geometry": {"coordinates":[-87.978727,43.051453],"type":"Point"}
}