{
  "type": "Feature",
  "properties": {
    "addr:full":"7107 Co Hwy C Monticello WI 53570",
    "addr:housenumber":"7107",
    "addr:postcode":"53570",
    "addr:street":"Co Hwy C",
    "iso:country":"US",
    "sg:address":"7107 Co Hwy C",
    "sg:city":"Monticello",
    "sg:classifiers":[
        {
            "category":"Wholesale",
            "subcategory":"Machinery & Supplies",
            "type":"Manufacturing & Wholesale Goods"
        }
    ],
    "sg:phone":"+1 608 938 4261",
    "sg:postcode":"53570",
    "sg:province":"WI",
    "sg:tags":[
        "feed",
        "repair",
        "lot",
        "equipment"
    ],
    "wof:name":"Norton Feedlot Equipment Inc",
    "wof:placetype":"venue"
},
  "geometry": {"coordinates":[-89.711202,42.731837],"type":"Point"}
}