{
  "type": "Feature",
  "properties": {
    "addr:full":"24696 Threshold Rd S Hertel WI 54845",
    "addr:housenumber":"24696",
    "addr:postcode":"54845",
    "addr:street":"Threshold Rd",
    "iso:country":"US",
    "sg:address":"24696 Threshold Rd S",
    "sg:city":"Hertel",
    "sg:classifiers":[
        {
            "category":"Government",
            "subcategory":"Office",
            "type":"Public Place"
        }
    ],
    "sg:phone":"+1 715 468 7084",
    "sg:postcode":"54845",
    "sg:province":"WI",
    "sg:tags":[
        "legislative",
        "body"
    ],
    "wof:name":"Lafollette Township",
    "wof:placetype":"venue"
},
  "geometry": {"coordinates":[-92.150156,45.809929],"type":"Point"}
}