{
  "type": "Feature",
  "properties": {
    "addr:full":"1215 Appleton Rd Menasha WI 54952",
    "addr:housenumber":"1215",
    "addr:postcode":"54952",
    "addr:street":"Appleton Rd",
    "iso:country":"US",
    "sg:address":"1215 Appleton Rd",
    "sg:city":"Menasha",
    "sg:classifiers":[
        {
            "category":"Building & Trades",
            "subcategory":"Construction",
            "type":"Services"
        }
    ],
    "sg:phone":"+1 920 725 8779",
    "sg:postcode":"54952",
    "sg:province":"WI",
    "sg:tags":[
        "shed",
        "utility"
    ],
    "wof:name":"Feed Shed",
    "wof:placetype":"venue"
},
  "geometry": {"coordinates":[-88.426293,44.223567],"type":"Point"}
}