{
  "type": "Feature",
  "properties": {
    "iso:country":"US",
    "sg:address":"4917 N 67th St",
    "sg:city":"Milwaukee",
    "sg:classifiers":[
        {
            "category":"Retail",
            "subcategory":"Repair Shop",
            "type":"Services"
        }
    ],
    "sg:phone":"+1 414 438 9700",
    "sg:postcode":"53218",
    "sg:province":"WI",
    "sg:tags":[
        "upholsterer"
    ],
    "wof:name":"Newby's Upholstery",
    "wof:placetype":"venue"
},
  "geometry": {"coordinates":[-87.994953,43.109696],"type":"Point"}
}