{
  "type": "Feature",
  "properties": {
    "iso:country":"US",
    "sg:address":"328 Crescent St",
    "sg:city":"Rhinelander",
    "sg:classifiers":[
        {
            "category":"Organizations",
            "subcategory":"Community Association",
            "type":"Services"
        }
    ],
    "sg:phone":"+1 715 362 2691",
    "sg:postcode":"54501",
    "sg:province":"WI",
    "sg:tags":[
        "club"
    ],
    "wof:name":"Hodag Bmx Club Inc",
    "wof:placetype":"venue"
},
  "geometry": {"coordinates":[-89.430188,45.641979],"type":"Point"}
}