{
  "type": "Feature",
  "properties": {
    "iso:country":"US",
    "sg:address":"2830 Dryden Dr",
    "sg:city":"Madison",
    "sg:classifiers":[
        {
            "category":"Personal",
            "type":"Services"
        }
    ],
    "sg:phone":"+1 608 241 8848",
    "sg:postcode":"53704",
    "sg:province":"WI",
    "sg:tags":[
        "hair",
        "surgical",
        "restoration"
    ],
    "sg:website":"www.midwestrealhair.com",
    "wof:name":"Madison Hair Transplant Clinic",
    "wof:placetype":"venue"
},
  "geometry": {"coordinates":[-89.35915199999999,43.128885],"type":"Point"}
}