{
  "type": "Feature",
  "properties": {
    "iso:country":"US",
    "sg:address":"309 3rd Ave W",
    "sg:city":"Durand",
    "sg:classifiers":[
        {
            "category":"Professional",
            "subcategory":"Computer Services",
            "type":"Services"
        }
    ],
    "sg:phone":"+1 715 672 5343",
    "sg:postcode":"54736",
    "sg:province":"WI",
    "sg:tags":[
        "repair"
    ],
    "wof:name":"Wollynet Internet Solutions",
    "wof:placetype":"venue"
},
  "geometry": {"coordinates":[-91.96764899999999,44.627692],"type":"Point"}
}