{
  "type": "Feature",
  "properties": {
    "iso:country":"US",
    "sg:address":"110 N 2nd St",
    "sg:city":"Whitewater",
    "sg:classifiers":[
        {
            "category":"Personal",
            "subcategory":"Barber",
            "type":"Services"
        }
    ],
    "sg:phone":"+1 262 473 5320",
    "sg:postcode":"53190",
    "sg:province":"WI",
    "sg:tags":[
        "shop"
    ],
    "wof:name":"Pete's Barber Shop",
    "wof:placetype":"venue"
},
  "geometry": {"coordinates":[-88.732236,42.835034],"type":"Point"}
}