{
  "type": "Feature",
  "properties": {
    "iso:country":"US",
    "sg:address":"5110 Main St",
    "sg:city":"Stevens Point",
    "sg:classifiers":[
        {
            "category":"Travel",
            "subcategory":"Hotels & Motels",
            "type":"Entertainment"
        }
    ],
    "sg:phone":"+1 715 341 5110",
    "sg:postcode":"54481",
    "sg:province":"WI",
    "wof:name":"Best Western Royale Inn",
    "wof:placetype":"venue"
},
  "geometry": {"coordinates":[-89.527641,44.523239],"type":"Point"}
}