{
  "type": "Feature",
  "properties": {
    "iso:country":"US",
    "sg:address":"8610 43rd Ave",
    "sg:city":"Kenosha",
    "sg:classifiers":[
        {
            "category":"Building & Trades",
            "subcategory":"Construction",
            "type":"Services"
        }
    ],
    "sg:phone":"+1 262 694 8781",
    "sg:postcode":"53142",
    "sg:province":"IL",
    "sg:tags":[
        "residential"
    ],
    "wof:name":"Du Four Michael",
    "wof:placetype":"venue"
},
  "geometry": {"coordinates":[-87.859659,42.548768],"type":"Point"}
}