{
  "type": "Feature",
  "properties": {
    "addr:full":"909 Blackstone Ave Waukesha WI 53186",
    "addr:housenumber":"909",
    "addr:postcode":"53186",
    "addr:street":"Blackstone Ave",
    "iso:country":"US",
    "sg:address":"909 Blackstone Ave",
    "sg:city":"Waukesha",
    "sg:classifiers":[
        {
            "category":"Professional",
            "subcategory":"Research",
            "type":"Services"
        }
    ],
    "sg:phone":"+1 262 446 3949",
    "sg:postcode":"53186",
    "sg:province":"WI",
    "sg:tags":[
        "commercial",
        "physical"
    ],
    "wof:name":"Mascot Technologies",
    "wof:placetype":"venue"
},
  "geometry": {"coordinates":[-88.210196,43.015997],"type":"Point"}
}