{
  "type": "Feature",
  "properties": {
    "iso:country":"US",
    "sg:address":"3907 Jenkel Ter",
    "sg:city":"Green Bay",
    "sg:classifiers":[
        {
            "category":"Freight",
            "type":"Transportation"
        }
    ],
    "sg:phone":"+1 920 983 1174",
    "sg:postcode":"54301",
    "sg:province":"WI",
    "sg:tags":[
        "operator",
        "local",
        "trucking"
    ],
    "wof:name":"Mansfield Trucking Inc",
    "wof:placetype":"venue"
},
  "geometry": {"coordinates":[-88.03067299999999,44.451475],"type":"Point"}
}