{
  "type": "Feature",
  "properties": {
    "addr:full":"2965 Mill Rd Waupun WI 53963",
    "addr:housenumber":"2965",
    "addr:postcode":"53963",
    "addr:street":"Mill Rd",
    "iso:country":"US",
    "sg:address":"2965 Mill Rd",
    "sg:city":"Waupun",
    "sg:classifiers":[
        {
            "category":"Farming",
            "subcategory":"Dairy Farm",
            "type":"Manufacturing & Wholesale Goods"
        }
    ],
    "sg:phone":"+1 920 324 2833",
    "sg:postcode":"53963",
    "sg:province":"WI",
    "wof:name":"Anthony Alsum",
    "wof:placetype":"venue"
},
  "geometry": {"coordinates":[-88.689173,43.650139],"type":"Point"}
}