{
  "type": "Feature",
  "properties": {
    "iso:country":"US",
    "sg:address":"2100 Omro Rd",
    "sg:city":"Oshkosh",
    "sg:classifiers":[
        {
            "category":"Banks & Credit Unions",
            "subcategory":"Investment Brokerage",
            "type":"Services"
        }
    ],
    "sg:phone":"+1 920 426 4040",
    "sg:postcode":"54904",
    "sg:province":"WI",
    "sg:tags":[
        "security"
    ],
    "wof:name":"A G Edwards & Sons Inc",
    "wof:placetype":"venue"
},
  "geometry": {"coordinates":[-88.58535500000001,44.032658],"type":"Point"}
}