{
  "type": "Feature",
  "properties": {
    "iso:country":"US",
    "sg:address":"628 US Hwy 12",
    "sg:city":"Baraboo",
    "sg:classifiers":[
        {
            "category":"Retail",
            "subcategory":"Auto Rental",
            "type":"Services"
        }
    ],
    "sg:phone":"+1 608 355 7600",
    "sg:postcode":"53913",
    "sg:province":"WI",
    "sg:tags":[
        "renting",
        "automobile"
    ],
    "wof:name":"Enterprise Rent-A-Car",
    "wof:placetype":"venue"
},
  "geometry": {"coordinates":[-89.768665,43.476917],"type":"Point"}
}