{
  "type": "Feature",
  "properties": {
    "iso:country":"US",
    "sg:address":"1215 Universal Blvd",
    "sg:city":"Whitewater",
    "sg:classifiers":[
        {
            "category":"Manufacturing",
            "subcategory":"Rubber & Plastics",
            "type":"Manufacturing & Wholesale Goods"
        }
    ],
    "sg:phone":"+1 262 473 6023",
    "sg:postcode":"53190",
    "sg:province":"WI",
    "sg:tags":[
        "product",
        "mfg"
    ],
    "sg:website":"www.corky.com",
    "wof:name":"Lavelle Industries Inc",
    "wof:placetype":"venue"
},
  "geometry": {"coordinates":[-88.702074,42.840908],"type":"Point"}
}