{
  "type": "Feature",
  "properties": {
    "iso:country":"US",
    "sg:address":"3226 Lower Woodland Dr",
    "sg:city":"Colgate",
    "sg:classifiers":[
        {
            "category":"Building & Trades",
            "subcategory":"Construction",
            "type":"Services"
        }
    ],
    "sg:phone":"+1 262 251 7870",
    "sg:postcode":"53017",
    "sg:province":"WI",
    "sg:tags":[
        "house"
    ],
    "wof:name":"Dlk Contracting",
    "wof:placetype":"venue"
},
  "geometry": {"coordinates":[-88.198871,43.198644],"type":"Point"}
}