{
  "type": "Feature",
  "properties": {
    "iso:country":"US",
    "sg:address":"1930 32nd St N",
    "sg:city":"Wisconsin Rapids",
    "sg:classifiers":[
        {
            "category":"Wholesale",
            "subcategory":"Machinery & Supplies",
            "type":"Manufacturing & Wholesale Goods"
        }
    ],
    "sg:phone":"+1 715 421 0336",
    "sg:postcode":"54494",
    "sg:province":"WI",
    "sg:tags":[
        "equipment",
        "welding"
    ],
    "sg:website":"www.airgas.com",
    "wof:name":"Airgas",
    "wof:placetype":"venue"
},
  "geometry": {"coordinates":[-89.786653,44.404887],"type":"Point"}
}