{
  "type": "Feature",
  "properties": {
    "iso:country":"US",
    "sg:address":"1900 N Calhoun Rd",
    "sg:city":"Brookfield",
    "sg:classifiers":[
        {
            "category":"Education",
            "subcategory":"Library",
            "type":"Public Place"
        }
    ],
    "sg:phone":"+1 262 782 9650",
    "sg:postcode":"53005",
    "sg:province":"WI",
    "wof:name":"Brookfield Public Library",
    "wof:placetype":"venue"
},
  "geometry": {"coordinates":[-88.126086,43.056327],"type":"Point"}
}