{
  "type": "Feature",
  "properties": {
    "addr:full":"W61N286 Washington Ave Cedarburg WI 53012",
    "addr:postcode":"53012",
    "addr:street":"W61N286 Washington Ave",
    "iso:country":"US",
    "sg:address":"W61N286 Washington Ave",
    "sg:city":"Cedarburg",
    "sg:classifiers":[
        {
            "category":"Food & Beverages",
            "subcategory":"Groceries & Convenience Stores",
            "type":"Retail Goods"
        }
    ],
    "sg:phone":"+1 262 375 4474",
    "sg:postcode":"53012",
    "sg:province":"WI",
    "wof:name":"Piggly Wiggly",
    "wof:placetype":"venue"
},
  "geometry": {"coordinates":[-87.98629800000001,43.286701],"type":"Point"}
}