{
  "type": "Feature",
  "properties": {
    "addr:full":"111 Blackburn Ripon WI 54971",
    "addr:housenumber":"111",
    "addr:postcode":"54971",
    "addr:street":"Blackburn",
    "iso:country":"US",
    "sg:address":"111 Blackburn",
    "sg:city":"Ripon",
    "sg:classifiers":[
        {
            "category":"Wholesale",
            "subcategory":"Farm Supplies",
            "type":"Manufacturing & Wholesale Goods"
        }
    ],
    "sg:phone":"+1 920 748 1266",
    "sg:postcode":"54971",
    "sg:province":"WI",
    "sg:tags":[
        "chemical",
        "agricultural",
        "fertilizer"
    ],
    "wof:name":"Agri-Blenders",
    "wof:placetype":"venue"
},
  "geometry": {"coordinates":[-88.837108,43.845741],"type":"Point"}
}