{
  "type": "Feature",
  "properties": {
    "iso:country":"US",
    "sg:address":"1825 Mills St",
    "sg:city":"Green Bay",
    "sg:classifiers":[
        {
            "category":"Shopping",
            "subcategory":"Computers & Home Electronics",
            "type":"Retail Goods"
        }
    ],
    "sg:phone":"+1 920 469 9198",
    "sg:postcode":"54302",
    "sg:province":"WI",
    "sg:tags":[
        "audio"
    ],
    "wof:name":"Stryke Audio LLC",
    "wof:placetype":"venue"
},
  "geometry": {"coordinates":[-87.97806300000001,44.504155],"type":"Point"}
}