{
  "type": "Feature",
  "properties": {
    "iso:country":"US",
    "sg:address":"1960 Main St",
    "sg:city":"Green Bay",
    "sg:classifiers":[
        {
            "category":"Home & Garden",
            "subcategory":"Furniture",
            "type":"Retail Goods"
        }
    ],
    "sg:phone":"+1 920 468 8425",
    "sg:postcode":"54302",
    "sg:province":"WI",
    "sg:tags":[
        "store"
    ],
    "wof:name":"Inside Home Furnishings",
    "wof:placetype":"venue"
},
  "geometry": {"coordinates":[-87.975209,44.491886],"type":"Point"}
}