{
  "type": "Feature",
  "properties": {
    "iso:country":"US",
    "sg:address":"227 S Main St",
    "sg:city":"Cottage Grove",
    "sg:classifiers":[
        {
            "category":"Bars & Pubs",
            "type":"Food & Drink"
        }
    ],
    "sg:phone":"+1 608 839 5205",
    "sg:postcode":"53527",
    "sg:province":"WI",
    "wof:name":"Out Post",
    "wof:placetype":"venue"
},
  "geometry": {"coordinates":[-89.199816,43.07604],"type":"Point"}
}