{
  "type": "Feature",
  "properties": {
    "addr:full":"5330 State Hwy 42 Sheboygan WI 53083",
    "addr:housenumber":"5330",
    "addr:postcode":"53083",
    "addr:street":"State Hwy 42",
    "iso:country":"US",
    "sg:address":"5330 State Hwy 42",
    "sg:city":"Sheboygan",
    "sg:classifiers":[
        {
            "category":"Manufacturing",
            "subcategory":"Tools & Machinery",
            "type":"Manufacturing & Wholesale Goods"
        }
    ],
    "sg:phone":"+1 920 565 4049",
    "sg:postcode":"53083",
    "sg:province":"WI",
    "sg:tags":[
        "machine",
        "shop",
        "industrial",
        "mfg"
    ],
    "wof:name":"Koenig Machines Co Inc",
    "wof:placetype":"venue"
},
  "geometry": {"coordinates":[-87.769994,43.797296],"type":"Point"}
}