{
  "type": "Feature",
  "properties": {
    "iso:country":"US",
    "sg:address":"610 Madison Ave",
    "sg:city":"Cascade",
    "sg:classifiers":[
        {
            "category":"Education",
            "subcategory":"Special Training",
            "type":"Public Place"
        }
    ],
    "sg:phone":"+1 920 528 7296",
    "sg:postcode":"53011",
    "sg:province":"WI",
    "wof:name":"Delightful Little Herbs",
    "wof:placetype":"venue"
},
  "geometry": {"coordinates":[-88.004097,43.659541],"type":"Point"}
}