{
  "type": "Feature",
  "properties": {
    "iso:country":"US",
    "sg:address":"1531 W Lincoln Ave",
    "sg:city":"Milwaukee",
    "sg:classifiers":[
        {
            "category":"Restaurant",
            "type":"Food & Drink"
        }
    ],
    "sg:phone":"+1 414 384 1563",
    "sg:postcode":"53215",
    "sg:province":"WI",
    "sg:tags":[
        "eating"
    ],
    "wof:name":"Taqueria Aranda",
    "wof:placetype":"venue"
},
  "geometry": {"coordinates":[-87.93181800000001,43.002832],"type":"Point"}
}