{
  "type": "Feature",
  "properties": {
    "addr:full":"28438 Co Hwy Y Richland Center WI 53581",
    "addr:housenumber":"28438",
    "addr:postcode":"53581",
    "addr:street":"Co Hwy Y",
    "iso:country":"US",
    "sg:address":"28438 Co Hwy Y",
    "sg:city":"Richland Center",
    "sg:classifiers":[
        {
            "category":"Professional",
            "subcategory":"Business Services",
            "type":"Services"
        }
    ],
    "sg:phone":"+1 608 647 8310",
    "sg:postcode":"53581",
    "sg:province":"WI",
    "wof:name":"Leffler Family Partnership",
    "wof:placetype":"venue"
},
  "geometry": {"coordinates":[-90.458624,43.287764],"type":"Point"}
}