{
  "type": "Feature",
  "properties": {
    "addr:full":"4310 Broadway St Manitowoc WI 54220",
    "addr:housenumber":"4310",
    "addr:postcode":"54220",
    "addr:street":"Broadway St",
    "iso:country":"US",
    "sg:address":"4310 Broadway St",
    "sg:city":"Manitowoc",
    "sg:classifiers":[
        {
            "category":"Retail",
            "subcategory":"Repair Shop",
            "type":"Services"
        }
    ],
    "sg:phone":"+1 920 682 0602",
    "sg:postcode":"54220",
    "sg:province":"WI",
    "sg:tags":[
        "sharpening"
    ],
    "wof:name":"Jerry's Sharp All Shop",
    "wof:placetype":"venue"
},
  "geometry": {"coordinates":[-87.703895,44.097459],"type":"Point"}
}