{
  "type": "Feature",
  "properties": {
    "addr:full":"139 E Capitol Dr Hartland WI 53029",
    "addr:housenumber":"139",
    "addr:postcode":"53029",
    "addr:street":"E Capitol Dr",
    "iso:country":"US",
    "sg:address":"139 E Capitol Dr",
    "sg:city":"Hartland",
    "sg:classifiers":[
        {
            "category":"Wholesale",
            "subcategory":"Groceries",
            "type":"Manufacturing & Wholesale Goods"
        }
    ],
    "sg:phone":"+1 262 367 8464",
    "sg:postcode":"53029",
    "sg:province":"WI",
    "sg:tags":[
        "baker"
    ],
    "wof:name":"MOST Fantastic Foods",
    "wof:placetype":"venue"
},
  "geometry": {"coordinates":[-88.34357199999999,43.104651],"type":"Point"}
}