{
  "type": "Feature",
  "properties": {
    "iso:country":"US",
    "sg:address":"624 N Bridge St",
    "sg:city":"Chippewa Falls",
    "sg:classifiers":[
        {
            "category":"Food & Beverages",
            "subcategory":"Groceries & Convenience Stores",
            "type":"Retail Goods"
        }
    ],
    "sg:phone":"+1 715 723 4953",
    "sg:postcode":"54729",
    "sg:province":"WI",
    "wof:name":"Sokups John Market",
    "wof:placetype":"venue"
},
  "geometry": {"coordinates":[-91.396427,44.939578],"type":"Point"}
}