{
  "type": "Feature",
  "properties": {
    "iso:country":"US",
    "sg:address":"2876 State Hwy 107",
    "sg:city":"Merrill",
    "sg:classifiers":[
        {
            "category":"Freight",
            "type":"Transportation"
        }
    ],
    "sg:phone":"+1 715 536 7379",
    "sg:postcode":"54452",
    "sg:province":"WI",
    "sg:tags":[
        "operator",
        "local",
        "trucking"
    ],
    "wof:name":"Kasper Specialized Carriers",
    "wof:placetype":"venue"
},
  "geometry": {"coordinates":[-89.774359,45.22084],"type":"Point"}
}