{
  "type": "Feature",
  "properties": {
    "iso:country":"US",
    "sg:address":"524 Bay St",
    "sg:city":"Chippewa Falls",
    "sg:classifiers":[
        {
            "category":"Real Estate",
            "subcategory":"Real Estate Agent",
            "type":"Services"
        }
    ],
    "sg:phone":"+1 715 723 1195",
    "sg:postcode":"54729",
    "sg:province":"WI",
    "wof:name":"Century 21",
    "wof:placetype":"venue"
},
  "geometry": {"coordinates":[-91.39697099999999,44.938064],"type":"Point"}
}