{
  "type": "Feature",
  "properties": {
    "iso:country":"US",
    "sg:address":"37320 W Bresette Hill Rd",
    "sg:city":"Bayfield",
    "sg:classifiers":[
        {
            "category":"Personal",
            "subcategory":"Beauty Salon",
            "type":"Services"
        }
    ],
    "sg:phone":"+1 715 779 5050",
    "sg:postcode":"54814",
    "sg:province":"WI",
    "wof:name":"Naomi's Hair Care",
    "wof:placetype":"venue"
},
  "geometry": {"coordinates":[-90.795322,46.84576],"type":"Point"}
}