{
  "type": "Feature",
  "properties": {
    "iso:country":"US",
    "sg:address":"2000 N 31st St",
    "sg:city":"Milwaukee",
    "sg:phone":"+1 414 442 1400",
    "sg:postcode":"53208",
    "sg:province":"WI",
    "wof:name":"Steele's Welding",
    "wof:placetype":"venue"
},
  "geometry": {"coordinates":[-87.95255299999999,43.056412],"type":"Point"}
}