{
  "type": "Feature",
  "properties": {
    "iso:country":"US",
    "sg:address":"7163 Allen Rd",
    "sg:city":"Sobieski",
    "sg:classifiers":[
        {
            "category":"Farming",
            "subcategory":"Farm",
            "type":"Manufacturing & Wholesale Goods"
        }
    ],
    "sg:phone":"+1 920 822 5125",
    "sg:postcode":"54171",
    "sg:province":"WI",
    "sg:tags":[
        "crop",
        "general"
    ],
    "wof:name":"Leo Leja",
    "wof:placetype":"venue"
},
  "geometry": {"coordinates":[-88.12596000000001,44.706083],"type":"Point"}
}