{
  "type": "Feature",
  "properties": {
    "iso:country":"US",
    "sg:address":"1339 Speer Rd",
    "sg:city":"Waupaca",
    "sg:classifiers":[
        {
            "category":"Shopping",
            "type":"Retail Goods"
        }
    ],
    "sg:phone":"+1 715 258 7218",
    "sg:postcode":"54981",
    "sg:province":"WI",
    "sg:tags":[
        "merchandise"
    ],
    "wof:name":"Westwood Framing",
    "wof:placetype":"venue"
},
  "geometry": {"coordinates":[-89.178465,44.292071],"type":"Point"}
}