{
  "type": "Feature",
  "properties": {
    "iso:country":"US",
    "sg:address":"104 E Maple St",
    "sg:city":"Stanley",
    "sg:classifiers":[
        {
            "category":"Professional",
            "type":"Services"
        }
    ],
    "sg:phone":"+1 715 644 0377",
    "sg:postcode":"54768",
    "sg:province":"WI",
    "sg:tags":[
        "establishment"
    ],
    "wof:name":"OMI",
    "wof:placetype":"venue"
},
  "geometry": {"coordinates":[-90.937523,44.958743],"type":"Point"}
}