{
  "type": "Feature",
  "properties": {
    "addr:full":"4240 E Towne Blvd Madison WI 53704",
    "addr:housenumber":"4240",
    "addr:postcode":"53704",
    "addr:street":"E Towne Blvd",
    "iso:country":"US",
    "sg:address":"4240 E Towne Blvd",
    "sg:city":"Madison",
    "sg:classifiers":[
        {
            "category":"Shopping",
            "subcategory":"Beauty & Cosmetics",
            "type":"Retail Goods"
        }
    ],
    "sg:phone":"+1 608 244 0408",
    "sg:postcode":"53704",
    "sg:province":"WI",
    "wof:name":"Merle Norman Cosmetics",
    "wof:placetype":"venue"
},
  "geometry": {"coordinates":[-89.312068,43.123128],"type":"Point"}
}