{
  "type": "Feature",
  "properties": {
    "iso:country":"US",
    "sg:address":"3269 N Summit Ave",
    "sg:city":"Milwaukee",
    "sg:classifiers":[
        {
            "category":"Professional",
            "subcategory":"Management & Consulting",
            "type":"Services"
        }
    ],
    "sg:phone":"+1 414 962 3726",
    "sg:postcode":"53211",
    "sg:province":"WI",
    "wof:name":"Wilberg & Assoc Janice",
    "wof:placetype":"venue"
},
  "geometry": {"coordinates":[-87.87565600000001,43.076258],"type":"Point"}
}