{
  "type": "Feature",
  "properties": {
    "addr:full":"945 N 12th St Milwaukee WI 53233",
    "addr:housenumber":"945",
    "addr:postcode":"53233",
    "addr:street":"N 12Th St",
    "iso:country":"US",
    "sg:address":"945 N 12th St",
    "sg:city":"Milwaukee",
    "sg:classifiers":[
        {
            "category":"Health Services",
            "subcategory":"Doctor",
            "type":"Services"
        }
    ],
    "sg:phone":"+1 414 219 7918",
    "sg:postcode":"53233",
    "sg:province":"WI",
    "sg:tags":[
        "physician",
        "surgeon"
    ],
    "wof:name":"Issam Al-Bitar MD",
    "wof:placetype":"venue"
},
  "geometry": {"coordinates":[-87.927235,43.042474],"type":"Point"}
}