{
  "type": "Feature",
  "properties": {
    "addr:full":"2606 Ward Ave La Crosse WI 54601",
    "addr:housenumber":"2606",
    "addr:postcode":"54601",
    "addr:street":"Ward Ave",
    "iso:country":"US",
    "sg:address":"2606 Ward Ave",
    "sg:city":"La Crosse",
    "sg:classifiers":[
        {
            "category":"Personal",
            "subcategory":"Beauty Salon",
            "type":"Services"
        }
    ],
    "sg:phone":"+1 608 788 2875",
    "sg:postcode":"54601",
    "sg:province":"WI",
    "sg:tags":[
        "shop"
    ],
    "wof:name":"B Chelson Salon Centers",
    "wof:placetype":"venue"
},
  "geometry": {"coordinates":[-91.215473,43.783195],"type":"Point"}
}