{
  "type": "Feature",
  "properties": {
    "iso:country":"US",
    "sg:address":"109 N 28th St",
    "sg:city":"Superior",
    "sg:classifiers":[
        {
            "category":"Shopping",
            "type":"Retail Goods"
        }
    ],
    "sg:phone":"+1 715 392 2273",
    "sg:postcode":"54880",
    "sg:province":"WI",
    "sg:tags":[
        "merchandise"
    ],
    "wof:name":"Hearing Assoc",
    "wof:placetype":"venue"
},
  "geometry": {"coordinates":[-92.07872,46.706264],"type":"Point"}
}