{
  "type": "Feature",
  "properties": {
    "iso:country":"US",
    "sg:address":"3030 State Hwy 29",
    "sg:city":"Elk Mound",
    "sg:classifiers":[
        {
            "category":"Manufacturing",
            "subcategory":"Motor Vehicles & Parts",
            "type":"Manufacturing & Wholesale Goods"
        }
    ],
    "sg:phone":"+1 715 874 6552",
    "sg:postcode":"54739",
    "sg:province":"WI",
    "sg:tags":[
        "trailer",
        "mfg"
    ],
    "wof:name":"Gullickson Trailer Sales & Svc",
    "wof:placetype":"venue"
},
  "geometry": {"coordinates":[-91.608974,44.900501],"type":"Point"}
}