{
  "type": "Feature",
  "properties": {
    "iso:country":"US",
    "sg:address":"6131 Old Y Rd",
    "sg:city":"Maribel",
    "sg:phone":"+1 920 755 4395",
    "sg:postcode":"54227",
    "sg:province":"WI",
    "sg:tags":[
        "farm",
        "grain",
        "cash"
    ],
    "wof:name":"D J Farms",
    "wof:placetype":"venue"
},
  "geometry": {"coordinates":[-87.739266,44.254616],"type":"Point"}
}