{
  "type": "Feature",
  "properties": {
    "iso:country":"US",
    "sg:address":"5799 Auburn Dr",
    "sg:city":"Madison",
    "sg:classifiers":[
        {
            "category":"Professional",
            "subcategory":"Engineering",
            "type":"Services"
        }
    ],
    "sg:phone":"+1 608 273 8758",
    "sg:postcode":"53711",
    "sg:province":"WI",
    "wof:name":"I S O Rel Inc",
    "wof:placetype":"venue"
},
  "geometry": {"coordinates":[-89.442876,43.021071],"type":"Point"}
}