{
  "type": "Feature",
  "properties": {
    "addr:full":"7655 W Luscher Ave Milwaukee WI 53218",
    "addr:housenumber":"7655",
    "addr:postcode":"53218",
    "addr:street":"W Luscher Ave",
    "iso:country":"US",
    "sg:address":"7655 W Luscher Ave",
    "sg:city":"Milwaukee",
    "sg:classifiers":[
        {
            "category":"Personal",
            "subcategory":"Beauty Salon",
            "type":"Services"
        }
    ],
    "sg:phone":"+1 414 464 6617",
    "sg:postcode":"53218",
    "sg:province":"WI",
    "wof:name":"Metou Africa Hair Braiding",
    "wof:placetype":"venue"
},
  "geometry": {"coordinates":[-88.008994,43.105829],"type":"Point"}
}