{
  "type": "Feature",
  "properties": {
    "addr:full":"2739 N Beaumont Ave Waterford WI 53185",
    "addr:housenumber":"2739",
    "addr:postcode":"53185",
    "addr:street":"N Beaumont Ave",
    "iso:country":"US",
    "sg:address":"2739 N Beaumont Ave",
    "sg:city":"Waterford",
    "sg:classifiers":[
        {
            "category":"Wholesale",
            "subcategory":"Electrical",
            "type":"Manufacturing & Wholesale Goods"
        }
    ],
    "sg:phone":"+1 262 534 3749",
    "sg:postcode":"53185",
    "sg:province":"WI",
    "sg:tags":[
        "alarm",
        "burglar",
        "system"
    ],
    "wof:name":"Maximum Security Systems Inc",
    "wof:placetype":"venue"
},
  "geometry": {"coordinates":[-88.110952,42.751211],"type":"Point"}
}