{
  "type": "Feature",
  "properties": {
    "addr:full":"715 S Lake Ave Phillips WI 54555",
    "addr:housenumber":"715",
    "addr:postcode":"54555",
    "addr:street":"S Lake Ave",
    "iso:country":"US",
    "sg:address":"715 S Lake Ave",
    "sg:city":"Phillips",
    "sg:classifiers":[
        {
            "category":"Autos & Motor Vehicles",
            "subcategory":"Motorcycle Sales",
            "type":"Retail Goods"
        }
    ],
    "sg:phone":"+1 715 339 2421",
    "sg:postcode":"54555",
    "sg:province":"WI",
    "sg:tags":[
        "all",
        "terrain"
    ],
    "wof:name":"Rasmussen Service Ctr",
    "wof:placetype":"venue"
},
  "geometry": {"coordinates":[-90.39089,45.680589],"type":"Point"}
}