{
  "type": "Feature",
  "properties": {
    "iso:country":"US",
    "sg:address":"608 Broadway St",
    "sg:city":"Sheboygan Falls",
    "sg:classifiers":[
        {
            "category":"Shopping",
            "type":"Retail Goods"
        }
    ],
    "sg:phone":"+1 920 467 3359",
    "sg:postcode":"53085",
    "sg:province":"WI",
    "sg:tags":[
        "wedding",
        "supply"
    ],
    "wof:name":"Weddings By Design",
    "wof:placetype":"venue"
},
  "geometry": {"coordinates":[-87.810528,43.727439],"type":"Point"}
}