{
  "type": "Feature",
  "properties": {
    "iso:country":"US",
    "sg:address":"1873 Siesta Ln",
    "sg:city":"Green Bay",
    "sg:classifiers":[
        {
            "category":"Manufacturing",
            "subcategory":"Tools & Machinery",
            "type":"Manufacturing & Wholesale Goods"
        }
    ],
    "sg:phone":"+1 920 434 8860",
    "sg:postcode":"54313",
    "sg:province":"WI",
    "sg:tags":[
        "process",
        "control",
        "fluid",
        "devices",
        "mfg"
    ],
    "sg:website":"www.ksentry.com",
    "wof:name":"Krueger Sentry Gauge Co",
    "wof:placetype":"venue"
},
  "geometry": {"coordinates":[-88.057555,44.623827],"type":"Point"}
}