{
  "type": "Feature",
  "properties": {
    "iso:country":"US",
    "sg:address":"2119 N Quincy St",
    "sg:city":"Green Bay",
    "sg:classifiers":[
        {
            "category":"Wholesale",
            "subcategory":"Petroleum",
            "type":"Manufacturing & Wholesale Goods"
        }
    ],
    "sg:phone":"+1 920 432 3223",
    "sg:postcode":"54302",
    "sg:province":"WI",
    "sg:tags":[
        "pipe",
        "line",
        "company"
    ],
    "wof:name":"West Shore Pipe Line Co",
    "wof:placetype":"venue"
},
  "geometry": {"coordinates":[-87.993718,44.533792],"type":"Point"}
}