{
  "type": "Feature",
  "properties": {
    "addr:full":"1860 Renaissance Blvd Sturtevant WI 53177",
    "addr:housenumber":"1860",
    "addr:postcode":"53177",
    "addr:street":"Renaissance Blvd",
    "iso:country":"US",
    "sg:address":"1860 Renaissance Blvd",
    "sg:city":"Sturtevant",
    "sg:classifiers":[
        {
            "category":"Manufacturing",
            "subcategory":"Tools & Machinery",
            "type":"Manufacturing & Wholesale Goods"
        }
    ],
    "sg:phone":"+1 262 884 4577",
    "sg:postcode":"53177",
    "sg:province":"WI",
    "sg:tags":[
        "farm",
        "mfg"
    ],
    "wof:name":"Ikadan System USA Inc",
    "wof:placetype":"venue"
},
  "geometry": {"coordinates":[-87.91103699999999,42.718098],"type":"Point"}
}