{
  "type": "Feature",
  "properties": {
    "addr:full":"11112 Pleasant View Rd Darlington WI 53530",
    "addr:housenumber":"11112",
    "addr:postcode":"53530",
    "addr:street":"Pleasant View Rd",
    "iso:country":"US",
    "sg:address":"11112 Pleasant View Rd",
    "sg:city":"Darlington",
    "sg:classifiers":[
        {
            "category":"Restaurant",
            "type":"Food & Drink"
        }
    ],
    "sg:phone":"+1 608 762 5313",
    "sg:postcode":"53530",
    "sg:province":"WI",
    "sg:tags":[
        "eating"
    ],
    "wof:name":"Riechers Beef",
    "wof:placetype":"venue"
},
  "geometry": {"coordinates":[-90.289152,42.662275],"type":"Point"}
}