{
  "type": "Feature",
  "properties": {
    "iso:country":"US",
    "sg:address":"711 Washington St",
    "sg:city":"Kiel",
    "sg:classifiers":[
        {
            "category":"Building & Trades",
            "subcategory":"Plumbing",
            "type":"Services"
        }
    ],
    "sg:phone":"+1 920 894 3201",
    "sg:postcode":"53042",
    "sg:province":"WI",
    "sg:tags":[
        "heating",
        "contractor"
    ],
    "wof:name":"F Pritchard & Son Heating Inc",
    "wof:placetype":"venue"
},
  "geometry": {"coordinates":[-88.04087,43.911486],"type":"Point"}
}