{
  "type": "Feature",
  "properties": {
    "iso:country":"US",
    "sg:address":"3603 Lake St",
    "sg:city":"Burlington",
    "sg:classifiers":[
        {
            "category":"Professional",
            "type":"Services"
        }
    ],
    "sg:phone":"+1 262 763 5663",
    "sg:postcode":"53105",
    "sg:province":"WI",
    "wof:name":"Gbb - LLC",
    "wof:placetype":"venue"
},
  "geometry": {"coordinates":[-88.254811,42.686628],"type":"Point"}
}