{
  "type": "Feature",
  "properties": {
    "addr:full":"1933 S 1st St Milwaukee WI 53204",
    "addr:housenumber":"1933",
    "addr:postcode":"53204",
    "addr:street":"S 1St St",
    "iso:country":"US",
    "sg:address":"1933 S 1st St",
    "sg:city":"Milwaukee",
    "sg:classifiers":[
        {
            "category":"Recreation",
            "subcategory":"Marina",
            "type":"Entertainment"
        }
    ],
    "sg:phone":"+1 414 384 8300",
    "sg:postcode":"53204",
    "sg:province":"WI",
    "sg:tags":[
        "operation"
    ],
    "wof:name":"Milwaukee Marine Yacht",
    "wof:placetype":"venue"
},
  "geometry": {"coordinates":[-87.911219,43.010853],"type":"Point"}
}