{
  "type": "Feature",
  "properties": {
    "iso:country":"US",
    "sg:address":"392 Stone Ct",
    "sg:city":"Pewaukee",
    "sg:classifiers":[
        {
            "category":"Professional",
            "subcategory":"Art Services",
            "type":"Services"
        }
    ],
    "sg:phone":"+1 262 691 4503",
    "sg:postcode":"53072",
    "sg:province":"WI",
    "sg:tags":[
        "commercial",
        "design"
    ],
    "wof:name":"Sterling Images Inc",
    "wof:placetype":"venue"
},
  "geometry": {"coordinates":[-88.236952,43.077989],"type":"Point"}
}