{
  "type": "Feature",
  "properties": {
    "iso:country":"US",
    "sg:address":"8990 West Rd",
    "sg:city":"Watertown",
    "sg:classifiers":[
        {
            "category":"Building & Trades",
            "subcategory":"Construction",
            "type":"Services"
        },
        {
            "category":"Home & Garden",
            "subcategory":"Furniture",
            "type":"Retail Goods"
        }
    ],
    "sg:phone":"+1 920 261 5207",
    "sg:postcode":"53094",
    "sg:province":"WI",
    "sg:tags":[
        "mfr",
        "wood",
        "maker",
        "cabinet",
        "custom"
    ],
    "wof:name":"Wood Original",
    "wof:placetype":"venue"
},
  "geometry": {"coordinates":[-88.822751,43.173438],"type":"Point"}
}