{
  "type": "Feature",
  "properties": {
    "addr:full":"3416 University Ave Madison WI 53705",
    "addr:housenumber":"3416",
    "addr:postcode":"53705",
    "addr:street":"University Ave",
    "iso:country":"US",
    "sg:address":"3416 University Ave",
    "sg:city":"Madison",
    "sg:classifiers":[
        {
            "category":"Shopping",
            "subcategory":"Shoes",
            "type":"Retail Goods"
        }
    ],
    "sg:phone":"+1 608 233 9406",
    "sg:postcode":"53705",
    "sg:province":"WI",
    "sg:website":"www.famousfootwear.com",
    "wof:name":"Famous Footwear",
    "wof:placetype":"venue"
},
  "geometry": {"coordinates":[-89.444659,43.0753],"type":"Point"}
}