{
  "type": "Feature",
  "properties": {
    "addr:full":"6955 Hillcrest Dr Hartford WI 53027",
    "addr:housenumber":"6955",
    "addr:postcode":"53027",
    "addr:street":"Hillcrest Dr",
    "iso:country":"US",
    "sg:address":"6955 Hillcrest Dr",
    "sg:city":"Hartford",
    "sg:classifiers":[
        {
            "category":"Farming",
            "subcategory":"Dairy Farm",
            "type":"Manufacturing & Wholesale Goods"
        }
    ],
    "sg:phone":"+1 262 629 9014",
    "sg:postcode":"53027",
    "sg:province":"WI",
    "wof:name":"Gundrum Farms Inc",
    "wof:placetype":"venue"
},
  "geometry": {"coordinates":[-88.384399,43.406226],"type":"Point"}
}