{
  "type": "Feature",
  "properties": {
    "iso:country":"US",
    "sg:address":"5690 Co Rd C",
    "sg:city":"Packwaukee",
    "sg:classifiers":[
        {
            "category":"Building & Trades",
            "subcategory":"Landscaping Services",
            "type":"Services"
        }
    ],
    "sg:phone":"+1 608 589 5617",
    "sg:postcode":"53949",
    "sg:province":"WI",
    "sg:tags":[
        "tree"
    ],
    "wof:name":"J L Lapp Tree Svc",
    "wof:placetype":"venue"
},
  "geometry": {"coordinates":[-89.434431,43.773587],"type":"Point"}
}