{
  "type": "Feature",
  "properties": {
    "iso:country":"US",
    "sg:address":"8217 W Becher St",
    "sg:city":"Milwaukee",
    "sg:classifiers":[
        {
            "category":"Real Estate",
            "subcategory":"Real Estate Operator",
            "type":"Services"
        }
    ],
    "sg:phone":"+1 414 541 1772",
    "sg:postcode":"53219",
    "sg:province":"WI",
    "sg:tags":[
        "building",
        "apartment",
        "nonresidential"
    ],
    "wof:name":"Executive Bldg",
    "wof:placetype":"venue"
},
  "geometry": {"coordinates":[-88.01518299999999,43.006302],"type":"Point"}
}