{
  "type": "Feature",
  "properties": {
    "addr:full":"1344 N 4th St Milwaukee WI 53212",
    "addr:housenumber":"1344",
    "addr:postcode":"53212",
    "addr:street":"N 4Th St",
    "iso:country":"US",
    "sg:address":"1344 N 4th St",
    "sg:city":"Milwaukee",
    "sg:classifiers":[
        {
            "category":"Manufacturing",
            "subcategory":"Tools & Machinery",
            "type":"Manufacturing & Wholesale Goods"
        },
        {
            "category":"Manufacturing",
            "subcategory":"Electronics",
            "type":"Manufacturing & Wholesale Goods"
        },
        {
            "category":"Shopping",
            "subcategory":"Computers & Home Electronics",
            "type":"Retail Goods"
        }
    ],
    "sg:phone":"+1 414 273 1177",
    "sg:postcode":"53212",
    "sg:province":"WI",
    "sg:tags":[
        "electric",
        "supplies-wholesale",
        "equipment-testing",
        "equipment",
        "consumer",
        "manufacturer"
    ],
    "sg:website":"http://www.ced-aec.com",
    "wof:name":"C E D",
    "wof:placetype":"venue"
},
  "geometry": {"coordinates":[-87.91584400000001,43.047698],"type":"Point"}
}