{
  "type": "Feature",
  "properties": {
    "iso:country":"US",
    "sg:address":"403 Lakewood Dr",
    "sg:city":"Williams Bay",
    "sg:classifiers":[
        {
            "category":"Retail",
            "subcategory":"Car Wash",
            "type":"Services"
        }
    ],
    "sg:phone":"+1 262 745 1020",
    "sg:postcode":"53191",
    "sg:province":"WI",
    "sg:tags":[
        "carwash"
    ],
    "wof:name":"Williams Bay Dent & Detail LLC",
    "wof:placetype":"venue"
},
  "geometry": {"coordinates":[-88.556162,42.579816],"type":"Point"}
}