{
  "type": "Feature",
  "properties": {
    "iso:country":"US",
    "sg:address":"640 Moasis Dr",
    "sg:city":"Little Chute",
    "sg:classifiers":[
        {
            "category":"Wholesale",
            "subcategory":"Electrical",
            "type":"Manufacturing & Wholesale Goods"
        }
    ],
    "sg:phone":"+1 920 788 8800",
    "sg:postcode":"54140",
    "sg:province":"WI",
    "sg:tags":[
        "equipment",
        "lighting",
        "system"
    ],
    "wof:name":"Verheyden Electric",
    "wof:placetype":"venue"
},
  "geometry": {"coordinates":[-88.308289,44.296035],"type":"Point"}
}