{
  "type": "Feature",
  "properties": {
    "iso:country":"US",
    "sg:address":"414 S Park St",
    "sg:city":"Oconomowoc",
    "sg:classifiers":[
        {
            "category":"Building & Trades",
            "subcategory":"Construction",
            "type":"Services"
        }
    ],
    "sg:phone":"+1 262 567 7410",
    "sg:postcode":"53066",
    "sg:province":"WI",
    "sg:tags":[
        "downspouts",
        "gutter",
        "contractor"
    ],
    "wof:name":"Bark River Seamless Gutters",
    "wof:placetype":"venue"
},
  "geometry": {"coordinates":[-88.510793,43.107573],"type":"Point"}
}