{
  "type": "Feature",
  "properties": {
    "iso:country":"US",
    "sg:address":"5701 Lake Mendota Dr",
    "sg:city":"Madison",
    "sg:classifiers":[
        {
            "category":"Wholesale",
            "subcategory":"Electrical",
            "type":"Manufacturing & Wholesale Goods"
        }
    ],
    "sg:phone":"+1 608 233 1520",
    "sg:postcode":"53705",
    "sg:province":"WI",
    "sg:tags":[
        "professional",
        "visual",
        "audio",
        "equipment"
    ],
    "wof:name":"David Fisher & Associates",
    "wof:placetype":"venue"
},
  "geometry": {"coordinates":[-89.4772,43.088359],"type":"Point"}
}