{
  "type": "Feature",
  "properties": {
    "iso:country":"US",
    "sg:address":"310 E 1st St",
    "sg:city":"Loyal",
    "sg:classifiers":[
        {
            "category":"Freight",
            "type":"Transportation"
        }
    ],
    "sg:phone":"+1 715 255 8856",
    "sg:postcode":"54446",
    "sg:province":"WI",
    "sg:tags":[
        "operator",
        "local",
        "trucking"
    ],
    "wof:name":"Chips Transport LLC",
    "wof:placetype":"venue"
},
  "geometry": {"coordinates":[-90.492788,44.740083],"type":"Point"}
}