{
  "type": "Feature",
  "properties": {
    "iso:country":"US",
    "sg:address":"10140 W College Ave",
    "sg:city":"Hales Corners",
    "sg:classifiers":[
        {
            "category":"Building & Trades",
            "subcategory":"Construction",
            "type":"Services"
        }
    ],
    "sg:phone":"+1 414 425 6890",
    "sg:postcode":"53130",
    "sg:province":"WI",
    "sg:tags":[
        "home",
        "builder"
    ],
    "wof:name":"Wisconsin Concrete Homes",
    "wof:placetype":"venue"
},
  "geometry": {"coordinates":[-88.035962,42.930332],"type":"Point"}
}