{
  "type": "Feature",
  "properties": {
    "iso:country":"US",
    "sg:address":"1326 State St",
    "sg:city":"Racine",
    "sg:classifiers":[
        {
            "category":"Organizations",
            "subcategory":"Religious Organization",
            "type":"Services"
        }
    ],
    "sg:phone":"+1 262 632 4146",
    "sg:postcode":"53404",
    "sg:province":"WI",
    "sg:tags":[
        "baptist",
        "church"
    ],
    "wof:name":"Greater St Luke Baptist Church",
    "wof:placetype":"venue"
},
  "geometry": {"coordinates":[-87.797264,42.731569],"type":"Point"}
}