{
  "type": "Feature",
  "properties": {
    "addr:full":"20241 W Bluemound Rd Brookfield WI 53045",
    "addr:housenumber":"20241",
    "addr:postcode":"53045",
    "addr:street":"W Bluemound Rd",
    "iso:country":"US",
    "sg:address":"20241 W Bluemound Rd",
    "sg:city":"Brookfield",
    "sg:classifiers":[
        {
            "category":"Cinema",
            "subcategory":"Movie Theater",
            "type":"Entertainment"
        }
    ],
    "sg:phone":"+1 262 797 9230",
    "sg:postcode":"53045",
    "sg:province":"WI",
    "wof:name":"West Point Luxury Cinemas",
    "wof:placetype":"venue"
},
  "geometry": {"coordinates":[-88.16309099999999,43.035945],"type":"Point"}
}