{
  "type": "Feature",
  "properties": {
    "iso:country":"US",
    "sg:address":"149 23rd St S",
    "sg:city":"La Crosse",
    "sg:classifiers":[
        {
            "category":"Professional",
            "subcategory":"Business Services",
            "type":"Services"
        }
    ],
    "sg:phone":"+1 608 784 3094",
    "sg:postcode":"54601",
    "sg:province":"WI",
    "wof:name":"Natural Recording",
    "wof:placetype":"venue"
},
  "geometry": {"coordinates":[-91.22171400000001,43.810936],"type":"Point"}
}