{
  "type": "Feature",
  "properties": {
    "iso:country":"US",
    "sg:address":"106 S Main St",
    "sg:city":"Lake Mills",
    "sg:classifiers":[
        {
            "category":"Shopping",
            "subcategory":"Gifts & Souvenirs",
            "type":"Retail Goods"
        }
    ],
    "sg:phone":"+1 920 648 6947",
    "sg:postcode":"53551",
    "sg:province":"WI",
    "wof:name":"Travelers Alley Studio",
    "wof:placetype":"venue"
},
  "geometry": {"coordinates":[-88.913044,43.07892],"type":"Point"}
}