{
  "type": "Feature",
  "properties": {
    "iso:country":"US",
    "sg:address":"3681 S Arctic Ave",
    "sg:city":"Milwaukee",
    "sg:classifiers":[
        {
            "category":"Professional",
            "subcategory":"Secretarial Services",
            "type":"Services"
        }
    ],
    "sg:phone":"+1 414 481 6858",
    "sg:postcode":"53235",
    "sg:province":"WI",
    "sg:tags":[
        "reporting"
    ],
    "wof:name":"Ayp Services LLC",
    "wof:placetype":"venue"
},
  "geometry": {"coordinates":[-87.882217,42.977173],"type":"Point"}
}