{
  "type": "Feature",
  "properties": {
    "iso:country":"US",
    "sg:address":"124 N Main St",
    "sg:city":"River Falls",
    "sg:classifiers":[
        {
            "category":"Personal",
            "subcategory":"Beauty Salon",
            "type":"Services"
        }
    ],
    "sg:phone":"+1 715 426 6775",
    "sg:postcode":"54022",
    "sg:province":"WI",
    "sg:tags":[
        "shop"
    ],
    "wof:name":"Off The Top",
    "wof:placetype":"venue"
},
  "geometry": {"coordinates":[-92.625732,44.858685],"type":"Point"}
}