{
  "type": "Feature",
  "properties": {
    "iso:country":"US",
    "sg:address":"322 E Michigan St",
    "sg:city":"Milwaukee",
    "sg:classifiers":[
        {
            "category":"Professional",
            "subcategory":"Management & Consulting",
            "type":"Services"
        }
    ],
    "sg:phone":"+1 414 236 0194",
    "sg:postcode":"53202",
    "sg:province":"WI",
    "sg:tags":[
        "marketing",
        "consultant"
    ],
    "sg:website":"www.murphymarketing.com",
    "wof:name":"Murphy Marketing Research",
    "wof:placetype":"venue"
},
  "geometry": {"coordinates":[-87.906679,43.037565],"type":"Point"}
}