{
  "type": "Feature",
  "properties": {
    "iso:country":"US",
    "sg:address":"451 Co Rd K",
    "sg:city":"Hartford",
    "sg:classifiers":[
        {
            "category":"Building & Trades",
            "subcategory":"Landscaping Services",
            "type":"Services"
        }
    ],
    "sg:phone":"+1 262 673 6437",
    "sg:postcode":"53027",
    "sg:province":"WI",
    "sg:tags":[
        "tree"
    ],
    "wof:name":"Accurate Mill Work",
    "wof:placetype":"venue"
},
  "geometry": {"coordinates":[-88.345066,43.196562],"type":"Point"}
}