{
  "type": "Feature",
  "properties": {
    "iso:country":"US",
    "sg:address":"344 E Washington St",
    "sg:city":"Slinger",
    "sg:classifiers":[
        {
            "category":"Insurance",
            "subcategory":"Insurance Agent",
            "type":"Services"
        }
    ],
    "sg:phone":"+1 262 644 6027",
    "sg:postcode":"53086",
    "sg:province":"WI",
    "sg:website":"www.northbrook-ins.com",
    "wof:name":"Northbrook Insurance Assoc Inc",
    "wof:placetype":"venue"
},
  "geometry": {"coordinates":[-88.280934,43.331626],"type":"Point"}
}