{
  "type": "Feature",
  "properties": {
    "iso:country":"US",
    "sg:address":"2127 S 9th St",
    "sg:city":"Sheboygan",
    "sg:classifiers":[
        {
            "category":"Shopping",
            "subcategory":"Hobbies, Toys, & Games",
            "type":"Retail Goods"
        }
    ],
    "sg:phone":"+1 920 565 2538",
    "sg:postcode":"53081",
    "sg:province":"WI",
    "sg:tags":[
        "craft"
    ],
    "wof:name":"Deurchins",
    "wof:placetype":"venue"
},
  "geometry": {"coordinates":[-87.714701,43.731158],"type":"Point"}
}