{
  "type": "Feature",
  "properties": {
    "addr:full":"14525 Co Rd R Maribel WI 54227",
    "addr:housenumber":"14525",
    "addr:postcode":"54227",
    "addr:street":"Co Rd",
    "iso:country":"US",
    "sg:address":"14525 Co Rd R",
    "sg:city":"Maribel",
    "sg:classifiers":[
        {
            "category":"Manufacturing",
            "subcategory":"Tools & Machinery",
            "type":"Manufacturing & Wholesale Goods"
        }
    ],
    "sg:phone":"+1 920 863 5775",
    "sg:postcode":"54227",
    "sg:province":"WI",
    "sg:tags":[
        "measuring",
        "instrument",
        "electrical",
        "mfg"
    ],
    "wof:name":"Lakeshore Test Solutions LLC",
    "wof:placetype":"venue"
},
  "geometry": {"coordinates":[-87.777074,44.283425],"type":"Point"}
}