{
  "type": "Feature",
  "properties": {
    "iso:country":"US",
    "sg:address":"1010 8th St S",
    "sg:city":"Wisconsin Rapids",
    "sg:classifiers":[
        {
            "category":"Retail",
            "subcategory":"Repair Shop",
            "type":"Services"
        }
    ],
    "sg:phone":"+1 715 421 1270",
    "sg:postcode":"54494",
    "sg:province":"WI",
    "sg:tags":[
        "upholsterer"
    ],
    "wof:name":"Les' Upholstery",
    "wof:placetype":"venue"
},
  "geometry": {"coordinates":[-89.817097,44.38248],"type":"Point"}
}