{
  "type": "Feature",
  "properties": {
    "iso:country":"US",
    "sg:address":"5200 Aurora Rd",
    "sg:city":"Hartford",
    "sg:classifiers":[
        {
            "category":"Manufacturing",
            "subcategory":"Glass & Minerals",
            "type":"Manufacturing & Wholesale Goods"
        }
    ],
    "sg:phone":"+1 262 644 5333",
    "sg:postcode":"53027",
    "sg:province":"WI",
    "sg:tags":[
        "ready",
        "concrete",
        "mfg"
    ],
    "wof:name":"McC Incorporated",
    "wof:placetype":"venue"
},
  "geometry": {"coordinates":[-88.30801700000001,43.383205],"type":"Point"}
}