{
  "type": "Feature",
  "properties": {
    "iso:country":"US",
    "sg:address":"493 S Ellis Ave",
    "sg:city":"Peshtigo",
    "sg:classifiers":[
        {
            "category":"Manufacturing",
            "subcategory":"Furniture",
            "type":"Manufacturing & Wholesale Goods"
        }
    ],
    "sg:phone":"+1 715 582 4212",
    "sg:postcode":"54157",
    "sg:province":"WI",
    "sg:tags":[
        "wood",
        "mfg"
    ],
    "wof:name":"Aspen Fixtures LLC",
    "wof:placetype":"venue"
},
  "geometry": {"coordinates":[-87.75251299999999,45.046171],"type":"Point"}
}