{
  "type": "Feature",
  "properties": {
    "iso:country":"US",
    "sg:address":"6569 Soda Rd",
    "sg:city":"Princeton",
    "sg:classifiers":[
        {
            "category":"Wholesale",
            "subcategory":"Hardware",
            "type":"Manufacturing & Wholesale Goods"
        }
    ],
    "sg:phone":"+1 920 295 4275",
    "sg:postcode":"54968",
    "sg:province":"WI",
    "sg:tags":[
        "equipment",
        "heating",
        "system"
    ],
    "wof:name":"Warm Haven Outdoor Heating Sup",
    "wof:placetype":"venue"
},
  "geometry": {"coordinates":[-89.203354,43.880949],"type":"Point"}
}