{
  "type": "Feature",
  "properties": {
    "addr:full":"1133 E Academy St Stoughton WI 53589",
    "addr:housenumber":"1133",
    "addr:postcode":"53589",
    "addr:street":"E Academy St",
    "iso:country":"US",
    "sg:address":"1133 E Academy St",
    "sg:city":"Stoughton",
    "sg:classifiers":[
        {
            "category":"Building & Trades",
            "subcategory":"Landscaping Services",
            "type":"Services"
        }
    ],
    "sg:phone":"+1 608 873 9490",
    "sg:postcode":"53589",
    "sg:province":"WI",
    "sg:tags":[
        "landscape",
        "contractor"
    ],
    "wof:name":"Nelson DW Inc",
    "wof:placetype":"venue"
},
  "geometry": {"coordinates":[-89.204722,42.911215],"type":"Point"}
}