{
  "type": "Feature",
  "properties": {
    "iso:country":"US",
    "sg:address":"1106 Lake Ave W",
    "sg:city":"Ladysmith",
    "sg:classifiers":[
        {
            "category":"Building & Trades",
            "subcategory":"Plumbing",
            "type":"Services"
        }
    ],
    "sg:phone":"+1 715 532 6551",
    "sg:postcode":"54848",
    "sg:province":"WI",
    "sg:tags":[
        "appliance",
        "heating",
        "contractor"
    ],
    "wof:name":"Buchholz Heating and Appliance",
    "wof:placetype":"venue"
},
  "geometry": {"coordinates":[-91.11385199999999,45.464955],"type":"Point"}
}