{
  "type": "Feature",
  "properties": {
    "iso:country":"US",
    "sg:address":"210 W 29th St",
    "sg:city":"Marshfield",
    "sg:classifiers":[
        {
            "category":"Professional",
            "type":"Services"
        }
    ],
    "sg:phone":"+1 715 387 6006",
    "sg:postcode":"54449",
    "sg:province":"WI",
    "sg:tags":[
        "establishment"
    ],
    "wof:name":"Earth Station",
    "wof:placetype":"venue"
},
  "geometry": {"coordinates":[-90.18485699999999,44.641229],"type":"Point"}
}