{
  "type": "Feature",
  "properties": {
    "addr:full":"8025 State Hwy 64 Pound WI 54161",
    "addr:housenumber":"8025",
    "addr:postcode":"54161",
    "addr:street":"State Hwy 64",
    "iso:country":"US",
    "sg:address":"8025 State Hwy 64",
    "sg:city":"Pound",
    "sg:classifiers":[
        {
            "category":"Wholesale",
            "subcategory":"Farm Supplies",
            "type":"Manufacturing & Wholesale Goods"
        }
    ],
    "sg:phone":"+1 920 897 2999",
    "sg:postcode":"54161",
    "sg:province":"WI",
    "sg:tags":[
        "feed",
        "fertilizer",
        "seed"
    ],
    "wof:name":"Zeitler Agri-Center Inc",
    "wof:placetype":"venue"
},
  "geometry": {"coordinates":[-88.156553,45.111019],"type":"Point"}
}