{
  "type": "Feature",
  "properties": {
    "iso:country":"US",
    "sg:address":"406 Technology Dr E",
    "sg:city":"Menomonie",
    "sg:classifiers":[
        {
            "category":"Professional",
            "subcategory":"Lawyer & Legal Services",
            "type":"Services"
        }
    ],
    "sg:phone":"+1 715 235 5556",
    "sg:postcode":"54751",
    "sg:province":"WI",
    "sg:tags":[
        "attorney"
    ],
    "wof:name":"Skinner Law Firm",
    "wof:placetype":"venue"
},
  "geometry": {"coordinates":[-91.891716,44.878907],"type":"Point"}
}