{
  "type": "Feature",
  "properties": {
    "iso:country":"US",
    "sg:address":"3401 N 76th St",
    "sg:city":"Milwaukee",
    "sg:classifiers":[
        {
            "category":"Organizations",
            "subcategory":"Religious Organization",
            "type":"Services"
        }
    ],
    "sg:phone":"+1 414 875 9825",
    "sg:postcode":"53222",
    "sg:province":"WI",
    "sg:tags":[
        "church"
    ],
    "wof:name":"Gethsemane Missionary Bapt Chr",
    "wof:placetype":"venue"
},
  "geometry": {"coordinates":[-88.007319,43.082623],"type":"Point"}
}