{
  "type": "Feature",
  "properties": {
    "iso:country":"US",
    "sg:address":"31950 Peacy Rd",
    "sg:city":"Washburn",
    "sg:classifiers":[
        {
            "category":"Retail",
            "subcategory":"Repair Shop",
            "type":"Services"
        }
    ],
    "sg:phone":"+1 715 373 2348",
    "sg:postcode":"54891",
    "sg:province":"WI",
    "wof:name":"Gary Schlitchting Piano Svc",
    "wof:placetype":"venue"
},
  "geometry": {"coordinates":[-90.908179,46.695385],"type":"Point"}
}