{
  "type": "Feature",
  "properties": {
    "iso:country":"US",
    "sg:address":"6270 Oak Rd",
    "sg:city":"Fennimore",
    "sg:classifiers":[
        {
            "category":"Professional",
            "type":"Services"
        }
    ],
    "sg:phone":"+1 608 988 4265",
    "sg:postcode":"53809",
    "sg:province":"WI",
    "wof:name":"Steven Pasold",
    "wof:placetype":"venue"
},
  "geometry": {"coordinates":[-90.736428,42.98512],"type":"Point"}
}