{
  "type": "Feature",
  "properties": {
    "iso:country":"US",
    "sg:address":"3857 US Hwy 63",
    "sg:city":"Ellsworth",
    "sg:classifiers":[
        {
            "category":"Organizations",
            "subcategory":"Membership Organization",
            "type":"Services"
        }
    ],
    "sg:phone":"+1 715 792 2427",
    "sg:postcode":"54011",
    "sg:province":"WI",
    "wof:name":"Trimbelle Rod & Gun Club",
    "wof:placetype":"venue"
},
  "geometry": {"coordinates":[-92.517525,44.676481],"type":"Point"}
}