{
  "type": "Feature",
  "properties": {
    "addr:full":"10015 278th Ave Trevor WI 53179",
    "addr:housenumber":"10015",
    "addr:postcode":"53179",
    "addr:street":"278Th Ave",
    "iso:country":"US",
    "sg:address":"10015 278th Ave",
    "sg:city":"Trevor",
    "sg:classifiers":[
        {
            "category":"Real Estate",
            "subcategory":"Real Estate Agent",
            "type":"Services"
        }
    ],
    "sg:phone":"+1 262 889 4258",
    "sg:postcode":"53179",
    "sg:province":"WI",
    "wof:name":"Obrien Management Inc",
    "wof:placetype":"venue"
},
  "geometry": {"coordinates":[-88.14707,42.528878],"type":"Point"}
}