{
  "type": "Feature",
  "properties": {
    "iso:country":"US",
    "sg:address":"611 Jefferson St",
    "sg:city":"Sturgeon Bay",
    "sg:classifiers":[
        {
            "category":"Professional",
            "subcategory":"Business Services",
            "type":"Services"
        },
        {
            "category":"Wholesale",
            "subcategory":"Home Furnishings",
            "type":"Manufacturing & Wholesale Goods"
        }
    ],
    "sg:phone":"+1 920 743 4503",
    "sg:postcode":"54235",
    "sg:province":"WI",
    "sg:tags":[
        "interior",
        "consultant",
        "design",
        "decorator"
    ],
    "wof:name":"Objects",
    "wof:placetype":"venue"
},
  "geometry": {"coordinates":[-87.373863,44.838853],"type":"Point"}
}