{
  "type": "Feature",
  "properties": {
    "addr:full":"1821 Woodburn Rd Waukesha WI 53188",
    "addr:housenumber":"1821",
    "addr:postcode":"53188",
    "addr:street":"Woodburn Rd",
    "iso:country":"US",
    "sg:address":"1821 Woodburn Rd",
    "sg:city":"Waukesha",
    "sg:classifiers":[
        {
            "category":"Social Services",
            "subcategory":"Child Care",
            "type":"Services"
        }
    ],
    "sg:phone":"+1 262 524 9566",
    "sg:postcode":"53188",
    "sg:province":"WI",
    "sg:tags":[
        "kindergarten",
        "academic",
        "school"
    ],
    "sg:website":"www.lapetite.com",
    "wof:name":"LA Petite Academy",
    "wof:placetype":"venue"
},
  "geometry": {"coordinates":[-88.256214,43.036965],"type":"Point"}
}