{
  "type": "Feature",
  "properties": {
    "iso:country":"US",
    "sg:address":"8548 Dolgner Rd",
    "sg:city":"Pardeeville",
    "sg:classifiers":[
        {
            "category":"Shopping",
            "subcategory":"Shoes",
            "type":"Retail Goods"
        }
    ],
    "sg:phone":"+1 608 429 4036",
    "sg:postcode":"53954",
    "sg:province":"WI",
    "sg:tags":[
        "boot"
    ],
    "wof:name":"J & K Shoes and Boots",
    "wof:placetype":"venue"
},
  "geometry": {"coordinates":[-89.26258300000001,43.592219],"type":"Point"}
}