{
  "type": "Feature",
  "properties": {
    "iso:country":"US",
    "sg:address":"950 N 72nd St",
    "sg:city":"Milwaukee",
    "sg:classifiers":[
        {
            "category":"Freight",
            "type":"Transportation"
        }
    ],
    "sg:phone":"+1 414 456 9164",
    "sg:postcode":"53213",
    "sg:province":"WI",
    "sg:tags":[
        "operator",
        "trucking"
    ],
    "wof:name":"Hellner Trucking",
    "wof:placetype":"venue"
},
  "geometry": {"coordinates":[-88.002391,43.042345],"type":"Point"}
}