{
  "type": "Feature",
  "properties": {
    "iso:country":"US",
    "sg:address":"2526 Pleasant View Ln",
    "sg:city":"Waupaca",
    "sg:classifiers":[
        {
            "category":"Building & Trades",
            "subcategory":"Construction",
            "type":"Services"
        }
    ],
    "sg:phone":"+1 715 258 3701",
    "sg:postcode":"54981",
    "sg:province":"WI",
    "sg:tags":[
        "operative",
        "contractor"
    ],
    "wof:name":"Quality RE Investments LLC",
    "wof:placetype":"venue"
},
  "geometry": {"coordinates":[-89.073933,44.33091],"type":"Point"}
}