{
  "type": "Feature",
  "properties": {
    "iso:country":"US",
    "sg:address":"9226 Minderhaud Rd",
    "sg:city":"Oostburg",
    "sg:phone":"+1 920 564 3384",
    "sg:postcode":"53070",
    "sg:province":"WI",
    "sg:tags":[
        "farm",
        "corn",
        "soybean"
    ],
    "wof:name":"Wayne Hilbelink",
    "wof:placetype":"venue"
},
  "geometry": {"coordinates":[-87.784341,43.642909],"type":"Point"}
}