{
  "type": "Feature",
  "properties": {
    "iso:country":"US",
    "sg:address":"606 Louisa St",
    "sg:city":"Crivitz",
    "sg:classifiers":[
        {
            "category":"Education",
            "subcategory":"Library",
            "type":"Public Place"
        }
    ],
    "sg:phone":"+1 715 854 7562",
    "sg:postcode":"54114",
    "sg:province":"WI",
    "wof:name":"Crivitz Area Library",
    "wof:placetype":"venue"
},
  "geometry": {"coordinates":[-88.004282,45.23297],"type":"Point"}
}