{
  "type": "Feature",
  "properties": {
    "iso:country":"US",
    "sg:address":"301 W Vinal St",
    "sg:city":"Wittenberg",
    "sg:classifiers":[
        {
            "category":"Personal",
            "subcategory":"Beauty Salon",
            "type":"Services"
        }
    ],
    "sg:phone":"+1 715 253 2783",
    "sg:postcode":"54499",
    "sg:province":"WI",
    "sg:tags":[
        "shop"
    ],
    "wof:name":"Joan's Beauty Bar",
    "wof:placetype":"venue"
},
  "geometry": {"coordinates":[-89.170389,44.822444],"type":"Point"}
}