{
  "type": "Feature",
  "properties": {
    "iso:country":"US",
    "sg:address":"8871 Ridge Rd",
    "sg:city":"Van Dyne",
    "sg:classifiers":[
        {
            "category":"Shopping",
            "subcategory":"Computers & Home Electronics",
            "type":"Retail Goods"
        }
    ],
    "sg:phone":"+1 920 924 7624",
    "sg:postcode":"54979",
    "sg:province":"WI",
    "wof:name":"Associated Computer Services",
    "wof:placetype":"venue"
},
  "geometry": {"coordinates":[-88.581135,43.879362],"type":"Point"}
}