{
  "type": "Feature",
  "properties": {
    "iso:country":"US",
    "sg:address":"205 6th St",
    "sg:city":"Racine",
    "sg:classifiers":[
        {
            "category":"Professional",
            "subcategory":"Lawyer & Legal Services",
            "type":"Services"
        }
    ],
    "sg:phone":"+1 262 633 6374",
    "sg:postcode":"53403",
    "sg:province":"WI",
    "wof:name":"Charles H Pehlivanian",
    "wof:placetype":"venue"
},
  "geometry": {"coordinates":[-87.783077,42.726789],"type":"Point"}
}