{
  "type": "Feature",
  "properties": {
    "iso:country":"US",
    "sg:address":"7837 W Beechwood Ave",
    "sg:city":"Milwaukee",
    "sg:classifiers":[
        {
            "category":"Real Estate",
            "subcategory":"Real Estate Agent",
            "type":"Services"
        }
    ],
    "sg:phone":"+1 414 760 1041",
    "sg:postcode":"53223",
    "sg:province":"WI",
    "wof:name":"Enterprise Realty LLC",
    "wof:placetype":"venue"
},
  "geometry": {"coordinates":[-88.008913,43.142271],"type":"Point"}
}