{
  "type": "Feature",
  "properties": {
    "iso:country":"US",
    "sg:address":"6420 S Howell Ave",
    "sg:city":"Oak Creek",
    "sg:classifiers":[
        {
            "category":"Professional",
            "type":"Services"
        }
    ],
    "sg:phone":"+1 414 571 8963",
    "sg:postcode":"53154",
    "sg:province":"WI",
    "wof:name":"Tj Mobile",
    "wof:placetype":"venue"
},
  "geometry": {"coordinates":[-87.910247,42.927646],"type":"Point"}
}