{
  "type": "Feature",
  "properties": {
    "iso:country":"US",
    "sg:address":"7713 W Sheridan Ave",
    "sg:city":"Milwaukee",
    "sg:classifiers":[
        {
            "category":"Professional",
            "subcategory":"Business Services",
            "type":"Services"
        }
    ],
    "sg:phone":"+1 414 463 7311",
    "sg:postcode":"53218",
    "sg:province":"WI",
    "wof:name":"Minstrels Music Productions",
    "wof:placetype":"venue"
},
  "geometry": {"coordinates":[-88.008225,43.118124],"type":"Point"}
}