{
  "type": "Feature",
  "properties": {
    "iso:country":"US",
    "sg:address":"801 Hickory St",
    "sg:city":"Pewaukee",
    "sg:classifiers":[
        {
            "category":"Wholesale",
            "subcategory":"Electrical",
            "type":"Manufacturing & Wholesale Goods"
        }
    ],
    "sg:phone":"+1 262 691 9000",
    "sg:postcode":"53072",
    "sg:province":"WI",
    "sg:tags":[
        "equipment",
        "electric",
        "supply"
    ],
    "wof:name":"Ja-Mar Electric Supply Inc",
    "wof:placetype":"venue"
},
  "geometry": {"coordinates":[-88.248427,43.080219],"type":"Point"}
}