{
  "type": "Feature",
  "properties": {
    "iso:country":"US",
    "sg:address":"904 8th Ave",
    "sg:city":"Baraboo",
    "sg:classifiers":[
        {
            "category":"Social Services",
            "subcategory":"Child Care",
            "type":"Services"
        }
    ],
    "sg:phone":"+1 608 355 0672",
    "sg:postcode":"53913",
    "sg:province":"WI",
    "sg:tags":[
        "day"
    ],
    "wof:name":"Golden Apple Pre-School",
    "wof:placetype":"venue"
},
  "geometry": {"coordinates":[-89.758242,43.475335],"type":"Point"}
}