{
  "type": "Feature",
  "properties": {
    "addr:full":"1750 Wisconsin Ave Grafton WI 53024",
    "addr:housenumber":"1750",
    "addr:postcode":"53024",
    "addr:street":"Wisconsin Ave",
    "iso:country":"US",
    "sg:address":"1750 Wisconsin Ave",
    "sg:city":"Grafton",
    "sg:classifiers":[
        {
            "category":"Home & Garden",
            "subcategory":"Hardware",
            "type":"Retail Goods"
        }
    ],
    "sg:phone":"+1 262 377 1190",
    "sg:postcode":"53024",
    "sg:province":"WI",
    "sg:tags":[
        "store"
    ],
    "wof:name":"Ozaukee Ace Hardware",
    "wof:placetype":"venue"
},
  "geometry": {"coordinates":[-87.95700100000001,43.3116],"type":"Point"}
}