{
  "type": "Feature",
  "properties": {
    "iso:country":"US",
    "sg:address":"6345 W Plaza Cir",
    "sg:city":"Milwaukee",
    "sg:classifiers":[
        {
            "category":"Professional",
            "subcategory":"Computer Services",
            "type":"Services"
        }
    ],
    "sg:phone":"+1 414 491 1745",
    "sg:postcode":"53223",
    "sg:province":"WI",
    "sg:tags":[
        "programing",
        "custom"
    ],
    "wof:name":"Development Center New Co",
    "wof:placetype":"venue"
},
  "geometry": {"coordinates":[-87.986886,43.180343],"type":"Point"}
}