{
  "type": "Feature",
  "properties": {
    "iso:country":"US",
    "sg:address":"612 High St",
    "sg:city":"Racine",
    "sg:classifiers":[
        {
            "category":"Home & Garden",
            "subcategory":"Home Furnishings",
            "type":"Retail Goods"
        }
    ],
    "sg:phone":"+1 262 637 2884",
    "sg:postcode":"53402",
    "sg:province":"WI",
    "sg:tags":[
        "blind",
        "made",
        "drapery",
        "custom"
    ],
    "sg:website":"www.uniquedrapery.com",
    "wof:name":"Unique Drapery LTD",
    "wof:placetype":"venue"
},
  "geometry": {"coordinates":[-87.787464,42.742416],"type":"Point"}
}