{
  "type": "Feature",
  "properties": {
    "addr:full":"41 E Doty St Madison WI 53703",
    "addr:housenumber":"41",
    "addr:postcode":"53703",
    "addr:street":"E Doty St",
    "iso:country":"US",
    "sg:address":"41 E Doty St",
    "sg:city":"Madison",
    "sg:classifiers":[
        {
            "category":"Arena",
            "subcategory":"Sports Club",
            "type":"Entertainment"
        }
    ],
    "sg:phone":"+1 608 825 1553",
    "sg:postcode":"53703",
    "sg:province":"WI",
    "wof:name":"Club Net Inc",
    "wof:placetype":"venue"
},
  "geometry": {"coordinates":[-89.38142499999999,43.073621],"type":"Point"}
}