{
  "type": "Feature",
  "properties": {
    "iso:country":"US",
    "sg:address":"1350 6th Ave",
    "sg:city":"Baldwin",
    "sg:classifiers":[
        {
            "category":"Manufacturing",
            "subcategory":"Buildings",
            "type":"Manufacturing & Wholesale Goods"
        }
    ],
    "sg:phone":"+1 715 684 2888",
    "sg:postcode":"54002",
    "sg:province":"WI",
    "sg:tags":[
        "mobile",
        "home",
        "mfg"
    ],
    "wof:name":"Traynors Mobile Home",
    "wof:placetype":"venue"
},
  "geometry": {"coordinates":[-92.369857,44.962751],"type":"Point"}
}