{
  "type": "Feature",
  "properties": {
    "iso:country":"US",
    "sg:address":"10908 S Union Rd",
    "sg:city":"Newton",
    "sg:classifiers":[
        {
            "category":"Building & Trades",
            "subcategory":"Construction",
            "type":"Services"
        }
    ],
    "sg:phone":"+1 920 726 4760",
    "sg:postcode":"53063",
    "sg:province":"WI",
    "sg:tags":[
        "house"
    ],
    "wof:name":"Meyers Maintenance & Construc",
    "wof:placetype":"venue"
},
  "geometry": {"coordinates":[-87.781361,43.976844],"type":"Point"}
}