{
  "type": "Feature",
  "properties": {
    "iso:country":"US",
    "sg:address":"1050 Broadway St",
    "sg:city":"Wrightstown",
    "sg:classifiers":[
        {
            "category":"Banks & Credit Unions",
            "subcategory":"Bank",
            "type":"Services"
        }
    ],
    "sg:phone":"+1 920 532 0100",
    "sg:postcode":"54180",
    "sg:province":"WI",
    "sg:tags":[
        "personal",
        "state",
        "commercial"
    ],
    "wof:name":"Denmark State Bank",
    "wof:placetype":"venue"
},
  "geometry": {"coordinates":[-88.175994,44.328068],"type":"Point"}
}