{
  "type": "Feature",
  "properties": {
    "iso:country":"US",
    "sg:address":"3552 E Barnard Ave",
    "sg:city":"Cudahy",
    "sg:classifiers":[
        {
            "category":"Health Services",
            "subcategory":"Chiropractor",
            "type":"Services"
        }
    ],
    "sg:phone":"+1 414 482 1776",
    "sg:postcode":"53110",
    "sg:province":"WI",
    "wof:name":"Bykowski Chiropractic Office",
    "wof:placetype":"venue"
},
  "geometry": {"coordinates":[-87.861126,42.957373],"type":"Point"}
}