{
  "type": "Feature",
  "properties": {
    "addr:full":"324 S Spring St Beaver Dam WI 53916",
    "addr:housenumber":"324",
    "addr:postcode":"53916",
    "addr:street":"S Spring St",
    "iso:country":"US",
    "sg:address":"324 S Spring St",
    "sg:city":"Beaver Dam",
    "sg:classifiers":[
        {
            "category":"Real Estate",
            "subcategory":"Surveying",
            "type":"Services"
        }
    ],
    "sg:phone":"+1 920 885 3904",
    "sg:postcode":"53916",
    "sg:province":"WI",
    "sg:tags":[
        "surveyor"
    ],
    "wof:name":"New Frontier Land Surveying",
    "wof:placetype":"venue"
},
  "geometry": {"coordinates":[-88.836922,43.453906],"type":"Point"}
}