{
  "type": "Feature",
  "properties": {
    "iso:country":"US",
    "sg:address":"229 N West Ave",
    "sg:city":"Waukesha",
    "sg:classifiers":[
        {
            "category":"Banks & Credit Unions",
            "subcategory":"Bank",
            "type":"Services"
        }
    ],
    "sg:phone":"+1 262 547 8329",
    "sg:postcode":"53186",
    "sg:province":"WI",
    "sg:tags":[
        "truck",
        "finance",
        "lease"
    ],
    "wof:name":"Peterbilt of Wisconsin Inc",
    "wof:placetype":"venue"
},
  "geometry": {"coordinates":[-88.23662299999999,43.005243],"type":"Point"}
}