{
  "type": "Feature",
  "properties": {
    "iso:country":"US",
    "sg:address":"595 Sykora Rd",
    "sg:city":"River Falls",
    "sg:classifiers":[
        {
            "category":"Real Estate",
            "subcategory":"Real Estate Agent",
            "type":"Services"
        }
    ],
    "sg:phone":"+1 715 425 8600",
    "sg:postcode":"54022",
    "sg:province":"WI",
    "sg:tags":[
        "inspection"
    ],
    "wof:name":"Lasting Home Inspection",
    "wof:placetype":"venue"
},
  "geometry": {"coordinates":[-92.680272,44.887034],"type":"Point"}
}