{
  "type": "Feature",
  "properties": {
    "iso:country":"US",
    "sg:address":"919 N Summit Ave",
    "sg:city":"Oconomowoc",
    "sg:classifiers":[
        {
            "category":"Social Services",
            "type":"Services"
        }
    ],
    "sg:phone":"+1 262 567 9709",
    "sg:postcode":"53066",
    "sg:province":"WI",
    "sg:tags":[
        "organization",
        "welfare"
    ],
    "wof:name":"Waukesha County Elderly",
    "wof:placetype":"venue"
},
  "geometry": {"coordinates":[-88.463982,43.042977],"type":"Point"}
}