{
  "type": "Feature",
  "properties": {
    "iso:country":"US",
    "sg:address":"1449 Fair Rd",
    "sg:city":"Greenleaf",
    "sg:classifiers":[
        {
            "category":"Farming",
            "subcategory":"Livestock Farm",
            "type":"Manufacturing & Wholesale Goods"
        }
    ],
    "sg:phone":"+1 920 532 4268",
    "sg:postcode":"54126",
    "sg:province":"WI",
    "wof:name":"Petersen John",
    "wof:placetype":"venue"
},
  "geometry": {"coordinates":[-88.100993,44.320813],"type":"Point"}
}