{
  "type": "Feature",
  "properties": {
    "addr:full":"1402 52nd St Kenosha WI 53140",
    "addr:housenumber":"1402",
    "addr:postcode":"53140",
    "addr:street":"52Nd St",
    "iso:country":"US",
    "sg:address":"1402 52nd St",
    "sg:city":"Kenosha",
    "sg:classifiers":[
        {
            "category":"Bars & Pubs",
            "type":"Food & Drink"
        }
    ],
    "sg:phone":"+1 262 657 1818",
    "sg:postcode":"53140",
    "sg:province":"WI",
    "sg:tags":[
        "drinking"
    ],
    "wof:name":"Keiths Kenosha Tavern",
    "wof:placetype":"venue"
},
  "geometry": {"coordinates":[-87.82991800000001,42.588062],"type":"Point"}
}