{
  "type": "Feature",
  "properties": {
    "iso:country":"US",
    "sg:address":"9 Brodhead St",
    "sg:city":"Mazomanie",
    "sg:classifiers":[
        {
            "category":"Government",
            "subcategory":"Office",
            "type":"Public Place"
        }
    ],
    "sg:phone":"+1 608 795 2105",
    "sg:postcode":"53560",
    "sg:province":"WI",
    "sg:tags":[
        "village"
    ],
    "wof:name":"Mazomanie Community Building",
    "wof:placetype":"venue"
},
  "geometry": {"coordinates":[-89.794111,43.176526],"type":"Point"}
}