{
  "type": "Feature",
  "properties": {
    "iso:country":"US",
    "sg:address":"4600 52nd Ave",
    "sg:city":"Kenosha",
    "sg:classifiers":[
        {
            "category":"Social Services",
            "subcategory":"Adult Care",
            "type":"Services"
        }
    ],
    "sg:phone":"+1 262 654 5183",
    "sg:postcode":"53144",
    "sg:province":"WI",
    "sg:tags":[
        "home",
        "residential"
    ],
    "wof:name":"Encore Senior Villa-Kenosha",
    "wof:placetype":"venue"
},
  "geometry": {"coordinates":[-87.870649,42.592565],"type":"Point"}
}