{
  "type": "Feature",
  "properties": {
    "iso:country":"US",
    "sg:address":"213 Greenwood Dr",
    "sg:city":"Rothschild",
    "sg:classifiers":[
        {
            "category":"Building & Trades",
            "subcategory":"Construction",
            "type":"Services"
        }
    ],
    "sg:phone":"+1 715 359 1093",
    "sg:postcode":"54474",
    "sg:province":"WI",
    "sg:tags":[
        "contractor"
    ],
    "wof:name":"More Than Drywall",
    "wof:placetype":"venue"
},
  "geometry": {"coordinates":[-89.612697,44.888572],"type":"Point"}
}