{
  "type": "Feature",
  "properties": {
    "iso:country":"US",
    "sg:address":"3770 Egg Harbor Rd",
    "sg:city":"Sturgeon Bay",
    "sg:classifiers":[
        {
            "category":"Real Estate",
            "subcategory":"Developer",
            "type":"Services"
        }
    ],
    "sg:phone":"+1 920 743 6581",
    "sg:postcode":"54235",
    "sg:province":"WI",
    "sg:tags":[
        "company",
        "land"
    ],
    "wof:name":"Peninsula Realty LTD",
    "wof:placetype":"venue"
},
  "geometry": {"coordinates":[-87.36179199999999,44.848121],"type":"Point"}
}