{
  "type": "Feature",
  "properties": {
    "iso:country":"US",
    "sg:address":"7667 W Congress St",
    "sg:city":"Milwaukee",
    "sg:classifiers":[
        {
            "category":"Government",
            "subcategory":"Office",
            "type":"Public Place"
        }
    ],
    "sg:phone":"+1 414 393 4200",
    "sg:postcode":"53218",
    "sg:province":"WI",
    "sg:tags":[
        "township",
        "government-city",
        "village"
    ],
    "wof:name":"Milwaukee City of",
    "wof:placetype":"venue"
},
  "geometry": {"coordinates":[-88.007963,43.097172],"type":"Point"}
}