{
  "type": "Feature",
  "properties": {
    "iso:country":"US",
    "sg:address":"229 E Wisconsin Ave",
    "sg:city":"Milwaukee",
    "sg:classifiers":[
        {
            "category":"Social Services",
            "type":"Services"
        }
    ],
    "sg:phone":"+1 414 347 1774",
    "sg:postcode":"53202",
    "sg:province":"WI",
    "wof:name":"Benedict Center",
    "wof:placetype":"venue"
},
  "geometry": {"coordinates":[-87.90816,43.038552],"type":"Point"}
}