{
  "type": "Feature",
  "properties": {
    "addr:full":"5044 Elm Valley Rd Ogdensburg WI 54962",
    "addr:housenumber":"5044",
    "addr:postcode":"54962",
    "addr:street":"Elm Valley Rd",
    "iso:country":"US",
    "sg:address":"5044 Elm Valley Rd",
    "sg:city":"Ogdensburg",
    "sg:classifiers":[
        {
            "category":"Building & Trades",
            "subcategory":"Construction",
            "type":"Services"
        },
        {
            "category":"Home & Garden",
            "subcategory":"Furniture",
            "type":"Retail Goods"
        }
    ],
    "sg:phone":"+1 715 467 2748",
    "sg:postcode":"54962",
    "sg:province":"WI",
    "sg:tags":[
        "woodworking",
        "cabinet",
        "machinery",
        "maker",
        "mfg"
    ],
    "wof:name":"Little Wolf Cabinet Co",
    "wof:placetype":"venue"
},
  "geometry": {"coordinates":[-89.092119,44.419278],"type":"Point"}
}