{
  "type": "Feature",
  "properties": {
    "iso:country":"US",
    "sg:address":"962 W Northland Ave",
    "sg:city":"Appleton",
    "sg:classifiers":[
        {
            "category":"Shopping",
            "type":"Retail Goods"
        }
    ],
    "sg:phone":"+1 920 993 1335",
    "sg:postcode":"54914",
    "sg:province":"WI",
    "sg:tags":[
        "merchandise"
    ],
    "wof:name":"D JS Speed Zone",
    "wof:placetype":"venue"
},
  "geometry": {"coordinates":[-88.419867,44.287433],"type":"Point"}
}