{
  "type": "Feature",
  "properties": {
    "addr:full":"124 Oakridge Dr North Prairie WI 53153",
    "addr:housenumber":"124",
    "addr:postcode":"53153",
    "addr:street":"Oakridge Dr",
    "iso:country":"US",
    "sg:address":"124 Oakridge Dr",
    "sg:city":"North Prairie",
    "sg:classifiers":[
        {
            "category":"Building & Trades",
            "subcategory":"Construction",
            "type":"Services"
        }
    ],
    "sg:phone":"+1 262 392 2540",
    "sg:postcode":"53153",
    "sg:province":"WI",
    "sg:tags":[
        "repair",
        "well",
        "sales",
        "water",
        "pump",
        "drilling"
    ],
    "wof:name":"Aqua Well & Pump Systems Inc",
    "wof:placetype":"venue"
},
  "geometry": {"coordinates":[-88.39641899999999,42.9378],"type":"Point"}
}