{
  "type": "Feature",
  "properties": {
    "iso:country":"US",
    "sg:address":"9730 W Bluemound Rd",
    "sg:city":"Milwaukee",
    "sg:classifiers":[
        {
            "category":"Building & Trades",
            "subcategory":"Cleaning & Sanitation",
            "type":"Services"
        }
    ],
    "sg:phone":"+1 414 461 8448",
    "sg:postcode":"53226",
    "sg:province":"WI",
    "sg:tags":[
        "janitorial"
    ],
    "wof:name":"Admiral Janitorial Service",
    "wof:placetype":"venue"
},
  "geometry": {"coordinates":[-88.034963,43.035174],"type":"Point"}
}