{
  "type": "Feature",
  "properties": {
    "addr:full":"4245 S 99th St Milwaukee WI 53228",
    "addr:housenumber":"4245",
    "addr:postcode":"53228",
    "addr:street":"S 99Th St",
    "iso:country":"US",
    "sg:address":"4245 S 99th St",
    "sg:city":"Milwaukee",
    "sg:classifiers":[
        {
            "category":"Retail",
            "subcategory":"Laundry & Dry Cleaning",
            "type":"Services"
        }
    ],
    "sg:phone":"+1 414 543 9650",
    "sg:postcode":"53228",
    "sg:province":"WI",
    "wof:name":"Bonniestop To Bottom Upholstry",
    "wof:placetype":"venue"
},
  "geometry": {"coordinates":[-88.03666800000001,42.966988],"type":"Point"}
}