{
  "type": "Feature",
  "properties": {
    "iso:country":"US",
    "sg:address":"604 S Main St",
    "sg:city":"Waupaca",
    "sg:classifiers":[
        {
            "category":"Travel",
            "subcategory":"Hotels & Motels",
            "type":"Entertainment"
        }
    ],
    "sg:phone":"+1 715 258 5171",
    "sg:postcode":"54981",
    "sg:province":"WI",
    "sg:tags":[
        "operation"
    ],
    "wof:name":"Green Fountain Inn",
    "wof:placetype":"venue"
},
  "geometry": {"coordinates":[-89.085016,44.352485],"type":"Point"}
}