{
  "type": "Feature",
  "properties": {
    "iso:country":"US",
    "sg:address":"5726 S 108th St",
    "sg:city":"Hales Corners",
    "sg:classifiers":[
        {
            "category":"Recreation",
            "type":"Entertainment"
        }
    ],
    "sg:phone":"+1 414 425 2971",
    "sg:postcode":"53130",
    "sg:province":"WI",
    "wof:name":"East West Connection",
    "wof:placetype":"venue"
},
  "geometry": {"coordinates":[-88.048365,42.940591],"type":"Point"}
}