{
  "type": "Feature",
  "properties": {
    "iso:country":"US",
    "sg:address":"708 Elm Ave E",
    "sg:city":"Menomonie",
    "sg:classifiers":[
        {
            "category":"Shopping",
            "subcategory":"Department Store",
            "type":"Retail Goods"
        }
    ],
    "sg:phone":"+1 715 235 3991",
    "sg:postcode":"54751",
    "sg:province":"WI",
    "sg:tags":[
        "shop"
    ],
    "wof:name":"Ben Franklin",
    "wof:placetype":"venue"
},
  "geometry": {"coordinates":[-91.923751,44.897255],"type":"Point"}
}