{
  "type": "Feature",
  "properties": {
    "iso:country":"US",
    "sg:address":"36389 20th Ave",
    "sg:city":"Stanley",
    "sg:classifiers":[
        {
            "category":"Building & Trades",
            "subcategory":"Construction",
            "type":"Services"
        }
    ],
    "sg:phone":"+1 715 644 2285",
    "sg:postcode":"54768",
    "sg:province":"WI",
    "sg:tags":[
        "contractor"
    ],
    "wof:name":"Midstate Drywall & Painting",
    "wof:placetype":"venue"
},
  "geometry": {"coordinates":[-90.93447,44.871882],"type":"Point"}
}