{
  "type": "Feature",
  "properties": {
    "addr:full":"712 State Hwy 23 Wisconsin Dells WI 53965",
    "addr:housenumber":"712",
    "addr:postcode":"53965",
    "addr:street":"State Hwy 23",
    "iso:country":"US",
    "sg:address":"712 State Hwy 23",
    "sg:city":"Wisconsin Dells",
    "sg:classifiers":[
        {
            "category":"Sports & Exercise",
            "subcategory":"Golf",
            "type":"Entertainment"
        }
    ],
    "sg:phone":"+1 608 254 2165",
    "sg:postcode":"53965",
    "sg:province":"WI",
    "sg:tags":[
        "course",
        "public"
    ],
    "wof:name":"Pinecrest PAR 3 Golf Course",
    "wof:placetype":"venue"
},
  "geometry": {"coordinates":[-89.71600100000001,43.650478],"type":"Point"}
}