{
  "type": "Feature",
  "properties": {
    "iso:country":"US",
    "sg:address":"11634 Settlement Rd",
    "sg:city":"Cassville",
    "sg:classifiers":[
        {
            "category":"Farming",
            "subcategory":"Dairy Farm",
            "type":"Manufacturing & Wholesale Goods"
        }
    ],
    "sg:phone":"+1 608 725 5393",
    "sg:postcode":"53806",
    "sg:province":"WI",
    "wof:name":"Gene Mumm",
    "wof:placetype":"venue"
},
  "geometry": {"coordinates":[-90.993949,42.771516],"type":"Point"}
}