{
  "type": "Feature",
  "properties": {
    "iso:country":"US",
    "sg:address":"400 E Wisconsin Ave",
    "sg:city":"Milwaukee",
    "sg:classifiers":[
        {
            "category":"Banks & Credit Unions",
            "subcategory":"Financial Services",
            "type":"Services"
        }
    ],
    "sg:phone":"+1 414 615 4500",
    "sg:postcode":"53202",
    "sg:province":"WI",
    "sg:tags":[
        "company",
        "venture",
        "capital"
    ],
    "wof:name":"Quaestus Management Corp",
    "wof:placetype":"venue"
},
  "geometry": {"coordinates":[-87.90527,43.038809],"type":"Point"}
}