{
  "type": "Feature",
  "properties": {
    "addr:full":"2000 Johnston Dr Manitowoc WI 54220",
    "addr:housenumber":"2000",
    "addr:postcode":"54220",
    "addr:street":"Johnston Dr",
    "iso:country":"US",
    "sg:address":"2000 Johnston Dr",
    "sg:city":"Manitowoc",
    "sg:classifiers":[
        {
            "category":"Real Estate",
            "subcategory":"Real Estate Operator",
            "type":"Services"
        }
    ],
    "sg:phone":"+1 920 682 9360",
    "sg:postcode":"54220",
    "sg:province":"WI",
    "sg:tags":[
        "mobile",
        "home",
        "site"
    ],
    "wof:name":"Trails End Mobile Home Pk & M",
    "wof:placetype":"venue"
},
  "geometry": {"coordinates":[-87.640556,44.125053],"type":"Point"}
}