{
  "type": "Feature",
  "properties": {
    "iso:country":"US",
    "sg:address":"3798 Shady Ln",
    "sg:city":"Saukville",
    "sg:classifiers":[
        {
            "category":"Real Estate",
            "subcategory":"Real Estate Operator",
            "type":"Services"
        }
    ],
    "sg:phone":"+1 262 692 9110",
    "sg:postcode":"53080",
    "sg:province":"WI",
    "sg:tags":[
        "building",
        "nonresidential"
    ],
    "wof:name":"Autumglo Properties LLC",
    "wof:placetype":"venue"
},
  "geometry": {"coordinates":[-87.980365,43.462233],"type":"Point"}
}