{
  "type": "Feature",
  "properties": {
    "iso:country":"US",
    "sg:address":"510 Pine St",
    "sg:city":"Pepin",
    "sg:classifiers":[
        {
            "category":"Education",
            "subcategory":"School",
            "type":"Public Place"
        }
    ],
    "sg:phone":"+1 715 442 3151",
    "sg:postcode":"54759",
    "sg:province":"WI",
    "wof:name":"Pepin Elementary School",
    "wof:placetype":"venue"
},
  "geometry": {"coordinates":[-92.147807,44.444423],"type":"Point"}
}