{
  "type": "Feature",
  "properties": {
    "iso:country":"US",
    "sg:address":"1707 Vogt Dr",
    "sg:city":"Jackson",
    "sg:classifiers":[
        {
            "category":"Building & Trades",
            "subcategory":"Construction",
            "type":"Services"
        }
    ],
    "sg:phone":"+1 262 306 1004",
    "sg:postcode":"53095",
    "sg:province":"WI",
    "sg:tags":[
        "home",
        "carpentry",
        "contractor",
        "general",
        "custom"
    ],
    "wof:name":"Moore Designs Inc",
    "wof:placetype":"venue"
},
  "geometry": {"coordinates":[-88.197852,43.399461],"type":"Point"}
}