{
  "type": "Feature",
  "properties": {
    "iso:country":"US",
    "sg:address":"16900 W Bluemound Rd",
    "sg:city":"Brookfield",
    "sg:classifiers":[
        {
            "category":"Shopping",
            "subcategory":"Crafts & Fabrics",
            "type":"Retail Goods"
        }
    ],
    "sg:phone":"+1 262 785 9929",
    "sg:postcode":"53005",
    "sg:province":"WI",
    "sg:tags":[
        "shop",
        "sewing"
    ],
    "wof:name":"Jo-Ann Fabrics & Crafts",
    "wof:placetype":"venue"
},
  "geometry": {"coordinates":[-88.121584,43.037055],"type":"Point"}
}