{
  "type": "Feature",
  "properties": {
    "iso:country":"US",
    "sg:address":"1103 N Water St",
    "sg:city":"Milwaukee",
    "sg:classifiers":[
        {
            "category":"Real Estate",
            "subcategory":"Real Estate Services",
            "type":"Services"
        },
        {
            "category":"Real Estate",
            "subcategory":"Real Estate Operator",
            "type":"Services"
        }
    ],
    "sg:phone":"+1 414 272 7721",
    "sg:postcode":"53202",
    "sg:province":"WI",
    "sg:tags":[
        "vacancy",
        "apartment",
        "rental",
        "finder",
        "listing"
    ],
    "wof:name":"Water Street Apts.",
    "wof:placetype":"venue"
},
  "geometry": {"coordinates":[-87.911051,43.044631],"type":"Point"}
}