{
  "type": "Feature",
  "properties": {
    "iso:country":"US",
    "sg:address":"8570 Storms Rd",
    "sg:city":"Phillips",
    "sg:classifiers":[
        {
            "category":"Professional",
            "subcategory":"Business Services",
            "type":"Services"
        }
    ],
    "sg:phone":"+1 715 339 2746",
    "sg:postcode":"54555",
    "sg:province":"WI",
    "sg:tags":[
        "event"
    ],
    "wof:name":"Ride Of A Lifetime",
    "wof:placetype":"venue"
},
  "geometry": {"coordinates":[-90.41635100000001,45.683074],"type":"Point"}
}