{
  "type": "Feature",
  "properties": {
    "addr:full":"701 E Main St Merrill WI 54452",
    "addr:housenumber":"701",
    "addr:postcode":"54452",
    "addr:street":"E Main St",
    "iso:country":"US",
    "sg:address":"701 E Main St",
    "sg:city":"Merrill",
    "sg:classifiers":[
        {
            "category":"Insurance",
            "subcategory":"Insurance Agent",
            "type":"Services"
        }
    ],
    "sg:phone":"+1 715 536 2742",
    "sg:postcode":"54452",
    "sg:province":"WI",
    "wof:name":"State Farm Insurance",
    "wof:placetype":"venue"
},
  "geometry": {"coordinates":[-89.688406,45.179566],"type":"Point"}
}