{
  "type": "Feature",
  "properties": {
    "iso:country":"US",
    "sg:address":"1428 N Dousman Rd",
    "sg:city":"Oconomowoc",
    "sg:classifiers":[
        {
            "category":"Professional",
            "subcategory":"Management & Consulting",
            "type":"Services"
        }
    ],
    "sg:phone":"+1 262 560 1505",
    "sg:postcode":"53066",
    "sg:province":"WI",
    "sg:tags":[
        "business"
    ],
    "wof:name":"Remedialtion Unlimited",
    "wof:placetype":"venue"
},
  "geometry": {"coordinates":[-88.485782,43.050507],"type":"Point"}
}