{
  "type": "Feature",
  "properties": {
    "iso:country":"US",
    "sg:address":"409 Steele St",
    "sg:city":"Algoma",
    "sg:classifiers":[
        {
            "category":"Professional",
            "subcategory":"Lawyer & Legal Services",
            "type":"Services"
        }
    ],
    "sg:phone":"+1 920 487 5571",
    "sg:postcode":"54201",
    "sg:province":"WI",
    "sg:tags":[
        "attorney"
    ],
    "wof:name":"Blazkovec Blazkovec & Wisnicky",
    "wof:placetype":"venue"
},
  "geometry": {"coordinates":[-87.439721,44.608771],"type":"Point"}
}