{
  "type": "Feature",
  "properties": {
    "iso:country":"US",
    "sg:address":"11211 E Bloomingdale Rd",
    "sg:city":"Westby",
    "sg:classifiers":[
        {
            "category":"Shopping",
            "subcategory":"Gifts & Souvenirs",
            "type":"Retail Goods"
        }
    ],
    "sg:phone":"+1 608 625 4076",
    "sg:postcode":"54667",
    "sg:province":"WI",
    "sg:tags":[
        "shop"
    ],
    "wof:name":"Valley Hammers",
    "wof:placetype":"venue"
},
  "geometry": {"coordinates":[-90.713606,43.640516],"type":"Point"}
}