{
  "type": "Feature",
  "properties": {
    "addr:full":"7432 Mineral Point Rd Madison WI 53717",
    "addr:housenumber":"7432",
    "addr:postcode":"53717",
    "addr:street":"Mineral Point Rd",
    "iso:country":"US",
    "sg:address":"7432 Mineral Point Rd",
    "sg:city":"Madison",
    "sg:classifiers":[
        {
            "category":"Shopping",
            "type":"Retail Goods"
        }
    ],
    "sg:phone":"+1 608 829 4980",
    "sg:postcode":"53717",
    "sg:province":"WI",
    "sg:tags":[
        "cellular",
        "merchandise",
        "telephone"
    ],
    "wof:name":"Cingular Wireless Comm",
    "wof:placetype":"venue"
},
  "geometry": {"coordinates":[-89.51228500000001,43.060655],"type":"Point"}
}