{
  "type": "Feature",
  "properties": {
    "iso:country":"US",
    "sg:address":"116 W Vintage Dr",
    "sg:city":"Thiensville",
    "sg:classifiers":[
        {
            "category":"Real Estate",
            "subcategory":"Real Estate Operator",
            "type":"Services"
        }
    ],
    "sg:phone":"+1 262 241 3017",
    "sg:postcode":"53092",
    "sg:province":"WI",
    "sg:tags":[
        "building",
        "nonresidential"
    ],
    "wof:name":"Lieberman Properties LLC",
    "wof:placetype":"venue"
},
  "geometry": {"coordinates":[-87.906944,43.200122],"type":"Point"}
}