{
  "type": "Feature",
  "properties": {
    "iso:country":"US",
    "sg:address":"5656 S Packard Ave",
    "sg:city":"Cudahy",
    "sg:classifiers":[
        {
            "category":"Shopping",
            "subcategory":"Jewelry",
            "type":"Retail Goods"
        }
    ],
    "sg:phone":"+1 414 769 6666",
    "sg:postcode":"53110",
    "sg:province":"WI",
    "sg:tags":[
        "gift",
        "jeweler"
    ],
    "wof:name":"Kelvin D Schroeder Jewelers",
    "wof:placetype":"venue"
},
  "geometry": {"coordinates":[-87.859877,42.940931],"type":"Point"}
}