{
  "type": "Feature",
  "properties": {
    "iso:country":"US",
    "sg:address":"705 A St",
    "sg:city":"Chippewa Falls",
    "sg:classifiers":[
        {
            "category":"Insurance",
            "subcategory":"Insurance Agent",
            "type":"Services"
        }
    ],
    "sg:phone":"+1 715 723 2506",
    "sg:postcode":"54729",
    "sg:province":"WI",
    "wof:name":"Dean Williams",
    "wof:placetype":"venue"
},
  "geometry": {"coordinates":[-91.38417800000001,44.916668],"type":"Point"}
}