{
  "type": "Feature",
  "properties": {
    "iso:country":"US",
    "sg:address":"124 E Ann St",
    "sg:city":"Darlington",
    "sg:classifiers":[
        {
            "category":"Retail",
            "subcategory":"Repair Shop",
            "type":"Services"
        }
    ],
    "sg:phone":"+1 608 776 3779",
    "sg:postcode":"53530",
    "sg:province":"WI",
    "wof:name":"Milestone Upholstery",
    "wof:placetype":"venue"
},
  "geometry": {"coordinates":[-90.11756200000001,42.679323],"type":"Point"}
}