{
  "type": "Feature",
  "properties": {
    "iso:country":"US",
    "sg:address":"1305 W Wisconsin Ave",
    "sg:city":"Oconomowoc",
    "sg:classifiers":[
        {
            "category":"Manufacturing",
            "subcategory":"Tools & Machinery",
            "type":"Manufacturing & Wholesale Goods"
        }
    ],
    "sg:phone":"+1 262 567 1026",
    "sg:postcode":"53066",
    "sg:province":"WI",
    "sg:tags":[
        "electrical",
        "mfg"
    ],
    "wof:name":"Venture Electric",
    "wof:placetype":"venue"
},
  "geometry": {"coordinates":[-88.520642,43.11956],"type":"Point"}
}