{
  "type": "Feature",
  "properties": {
    "iso:country":"US",
    "sg:address":"30744 River Valley Rd",
    "sg:city":"Arcadia",
    "sg:phone":"+1 608 323 3542",
    "sg:postcode":"54612",
    "sg:province":"WI",
    "sg:tags":[
        "farm",
        "corn"
    ],
    "wof:name":"Robert Sobieck",
    "wof:placetype":"venue"
},
  "geometry": {"coordinates":[-91.45219400000001,44.286884],"type":"Point"}
}