{
  "type": "Feature",
  "properties": {
    "iso:country":"US",
    "sg:address":"103 Lincoln St",
    "sg:city":"Verona",
    "sg:classifiers":[
        {
            "category":"Organizations",
            "subcategory":"Membership Organization",
            "type":"Services"
        }
    ],
    "sg:phone":"+1 608 845 6926",
    "sg:postcode":"53593",
    "sg:province":"WI",
    "sg:tags":[
        "athletic"
    ],
    "wof:name":"Southwest Eagles Hockey Assoc",
    "wof:placetype":"venue"
},
  "geometry": {"coordinates":[-89.528366,42.991169],"type":"Point"}
}