{
  "type": "Feature",
  "properties": {
    "addr:full":"5407 W Mckinley Ave Milwaukee WI 53208",
    "addr:housenumber":"5407",
    "addr:postcode":"53208",
    "addr:street":"W Mckinley Ave",
    "iso:country":"US",
    "sg:address":"5407 W Mckinley Ave",
    "sg:city":"Milwaukee",
    "sg:classifiers":[
        {
            "category":"Communications",
            "subcategory":"Radio Station",
            "type":"Services"
        }
    ],
    "sg:phone":"+1 414 978 9000",
    "sg:postcode":"53208",
    "sg:province":"WI",
    "sg:tags":[
        "broadcast"
    ],
    "wof:name":"Wklh",
    "wof:placetype":"venue"
},
  "geometry": {"coordinates":[-87.981257,43.047464],"type":"Point"}
}