{
  "type": "Feature",
  "properties": {
    "iso:country":"US",
    "sg:address":"3200 S Herman St",
    "sg:city":"Milwaukee",
    "sg:classifiers":[
        {
            "category":"Social Services",
            "subcategory":"Child Care",
            "type":"Services"
        }
    ],
    "sg:phone":"+1 414 482 0073",
    "sg:postcode":"53207",
    "sg:province":"WI",
    "sg:tags":[
        "day"
    ],
    "wof:name":"Mary Linsmeier School",
    "wof:placetype":"venue"
},
  "geometry": {"coordinates":[-87.895629,42.984638],"type":"Point"}
}