{
  "type": "Feature",
  "properties": {
    "iso:country":"US",
    "sg:address":"1342 S Broadway",
    "sg:city":"Green Bay",
    "sg:classifiers":[
        {
            "category":"Bars & Pubs",
            "type":"Food & Drink"
        }
    ],
    "sg:phone":"+1 920 437 9926",
    "sg:postcode":"54304",
    "sg:province":"WI",
    "sg:tags":[
        "drinking",
        "eating"
    ],
    "wof:name":"Packer Stadium Lounge",
    "wof:placetype":"venue"
},
  "geometry": {"coordinates":[-88.03144899999999,44.501786],"type":"Point"}
}