{
  "type": "Feature",
  "properties": {
    "iso:country":"US",
    "sg:address":"325 S Oborn St",
    "sg:city":"Waupaca",
    "sg:classifiers":[
        {
            "category":"Government",
            "subcategory":"Office",
            "type":"Public Place"
        }
    ],
    "sg:phone":"+1 715 258 4424",
    "sg:postcode":"54981",
    "sg:province":"WI",
    "sg:tags":[
        "village"
    ],
    "wof:name":"Sewage Treatment Plant",
    "wof:placetype":"venue"
},
  "geometry": {"coordinates":[-89.074591,44.35629],"type":"Point"}
}