{
  "type": "Feature",
  "properties": {
    "iso:country":"US",
    "sg:address":"6328 W Mitchell St",
    "sg:city":"Milwaukee",
    "sg:classifiers":[
        {
            "category":"Shopping",
            "subcategory":"Jewelry",
            "type":"Retail Goods"
        }
    ],
    "sg:phone":"+1 414 321 0626",
    "sg:postcode":"53214",
    "sg:province":"WI",
    "wof:name":"Charmed",
    "wof:placetype":"venue"
},
  "geometry": {"coordinates":[-87.991905,43.01233],"type":"Point"}
}