{
  "type": "Feature",
  "properties": {
    "addr:full":"316 N 5th St Delavan WI 53115",
    "addr:housenumber":"316",
    "addr:postcode":"53115",
    "addr:street":"N 5Th St",
    "iso:country":"US",
    "sg:address":"316 N 5th St",
    "sg:city":"Delavan",
    "sg:classifiers":[
        {
            "category":"Building & Trades",
            "subcategory":"Pest Control",
            "type":"Services"
        }
    ],
    "sg:phone":"+1 262 728 2145",
    "sg:postcode":"53115",
    "sg:province":"WI",
    "wof:name":"Bugmaster Pest Control",
    "wof:placetype":"venue"
},
  "geometry": {"coordinates":[-88.64241,42.635537],"type":"Point"}
}