{
  "type": "Feature",
  "properties": {
    "addr:full":"423 Technology Dr E Menomonie WI 54751",
    "addr:housenumber":"423",
    "addr:postcode":"54751",
    "addr:street":"Technology Dr E",
    "iso:country":"US",
    "sg:address":"423 Technology Dr E",
    "sg:city":"Menomonie",
    "sg:classifiers":[
        {
            "category":"Travel",
            "subcategory":"Hotels & Motels",
            "type":"Entertainment"
        }
    ],
    "sg:phone":"+1 715 235 6155",
    "sg:postcode":"54751",
    "sg:province":"WI",
    "sg:tags":[
        "breakfast",
        "accommodation",
        "bed"
    ],
    "sg:website":"www.oaklawnbnb.com",
    "wof:name":"Oaklawn Bed & Breakfast",
    "wof:placetype":"venue"
},
  "geometry": {"coordinates":[-91.892038,44.881163],"type":"Point"}
}