{
  "type": "Feature",
  "properties": {
    "iso:country":"US",
    "sg:address":"924 E Main St",
    "sg:city":"Suring",
    "sg:classifiers":[
        {
            "category":"Education",
            "subcategory":"Library",
            "type":"Public Place"
        }
    ],
    "sg:phone":"+1 920 842 4451",
    "sg:postcode":"54174",
    "sg:province":"WI",
    "wof:name":"Suring Area Public Library",
    "wof:placetype":"venue"
},
  "geometry": {"coordinates":[-88.365977,44.998823],"type":"Point"}
}