{
  "type": "Feature",
  "properties": {
    "iso:country":"US",
    "sg:address":"20375 Tuckaway Valley Rd",
    "sg:city":"Richland Center",
    "sg:classifiers":[
        {
            "category":"Building & Trades",
            "subcategory":"Construction",
            "type":"Services"
        }
    ],
    "sg:phone":"+1 608 647 8292",
    "sg:postcode":"53581",
    "sg:province":"WI",
    "sg:tags":[
        "contractor"
    ],
    "wof:name":"Sidin n Stuff",
    "wof:placetype":"venue"
},
  "geometry": {"coordinates":[-90.46124399999999,43.352523],"type":"Point"}
}