{
  "type": "Feature",
  "properties": {
    "iso:country":"US",
    "sg:address":"322 Sherry Ave",
    "sg:city":"Park Falls",
    "sg:classifiers":[
        {
            "category":"Retail",
            "subcategory":"Funeral Services",
            "type":"Services"
        }
    ],
    "sg:phone":"+1 715 762 3287",
    "sg:postcode":"54552",
    "sg:province":"WI",
    "sg:tags":[
        "director"
    ],
    "wof:name":"Novitzke Funeral Home Inc",
    "wof:placetype":"venue"
},
  "geometry": {"coordinates":[-90.441886,45.93437],"type":"Point"}
}