{
  "type": "Feature",
  "properties": {
    "iso:country":"US",
    "sg:address":"5677 Meadow Ln",
    "sg:city":"Genoa",
    "sg:classifiers":[
        {
            "category":"Retail",
            "subcategory":"Portrait Studio",
            "type":"Services"
        }
    ],
    "sg:phone":"+1 608 689 2639",
    "sg:postcode":"54632",
    "sg:province":"WI",
    "sg:tags":[
        "photographer"
    ],
    "wof:name":"Sandy Trussoni Photography",
    "wof:placetype":"venue"
},
  "geometry": {"coordinates":[-91.215372,43.524385],"type":"Point"}
}