{
  "type": "Feature",
  "properties": {
    "addr:full":"125 S 1st St Bayfield WI 54814",
    "addr:housenumber":"125",
    "addr:postcode":"54814",
    "addr:street":"S 1St St",
    "iso:country":"US",
    "sg:address":"125 S 1st St",
    "sg:city":"Bayfield",
    "sg:classifiers":[
        {
            "category":"Government",
            "subcategory":"Office",
            "type":"Public Place"
        }
    ],
    "sg:phone":"+1 715 779 5712",
    "sg:postcode":"54814",
    "sg:province":"WI",
    "sg:tags":[
        "city"
    ],
    "wof:name":"Bayfield City Hall",
    "wof:placetype":"venue"
},
  "geometry": {"coordinates":[-90.81471999999999,46.809006],"type":"Point"}
}