{
  "type": "Feature",
  "properties": {
    "iso:country":"US",
    "sg:address":"127 N Broadway",
    "sg:city":"De Pere",
    "sg:classifiers":[
        {
            "category":"Restaurant",
            "type":"Food & Drink"
        }
    ],
    "sg:phone":"+1 920 337 0265",
    "sg:postcode":"54115",
    "sg:province":"WI",
    "wof:name":"Ivan's Of De Pere",
    "wof:placetype":"venue"
},
  "geometry": {"coordinates":[-88.060537,44.449785],"type":"Point"}
}