{
  "type": "Feature",
  "properties": {
    "addr:full":"12201 State Hwy 81 Beloit WI 53511",
    "addr:housenumber":"12201",
    "addr:postcode":"53511",
    "addr:street":"State Hwy 81",
    "iso:country":"US",
    "sg:address":"12201 State Hwy 81",
    "sg:city":"Beloit",
    "sg:classifiers":[
        {
            "category":"Utilities",
            "subcategory":"Fuel Oil & Lpg",
            "type":"Services"
        }
    ],
    "sg:phone":"+1 608 879 2665",
    "sg:postcode":"53511",
    "sg:province":"WI",
    "sg:tags":[
        "firewood"
    ],
    "wof:name":"Blue Enterprises",
    "wof:placetype":"venue"
},
  "geometry": {"coordinates":[-89.242982,42.533623],"type":"Point"}
}