{
  "type": "Feature",
  "properties": {
    "iso:country":"US",
    "sg:address":"809 Clyman St",
    "sg:city":"Watertown",
    "sg:classifiers":[
        {
            "category":"Professional",
            "subcategory":"Lawyer & Legal Services",
            "type":"Services"
        }
    ],
    "sg:phone":"+1 920 261 5956",
    "sg:postcode":"53094",
    "sg:province":"WI",
    "sg:tags":[
        "attorney"
    ],
    "wof:name":"Steven Luchsinger",
    "wof:placetype":"venue"
},
  "geometry": {"coordinates":[-88.71840400000001,43.186495],"type":"Point"}
}