{
  "type": "Feature",
  "properties": {
    "addr:full":"1111 S 120th St Milwaukee WI 53214",
    "addr:housenumber":"1111",
    "addr:postcode":"53214",
    "addr:street":"S 120Th St",
    "iso:country":"US",
    "sg:address":"1111 S 120th St",
    "sg:city":"Milwaukee",
    "sg:classifiers":[
        {
            "category":"Professional",
            "subcategory":"Art Services",
            "type":"Services"
        }
    ],
    "sg:phone":"+1 414 453 3003",
    "sg:postcode":"53214",
    "sg:province":"WI",
    "sg:tags":[
        "commercial",
        "design"
    ],
    "wof:name":"Regazzi Design",
    "wof:placetype":"venue"
},
  "geometry": {"coordinates":[-88.062122,43.018254],"type":"Point"}
}