{
  "type": "Feature",
  "properties": {
    "addr:full":"2617 W Chestnut Rd Thiensville WI 53092",
    "addr:housenumber":"2617",
    "addr:postcode":"53092",
    "addr:street":"W Chestnut Rd",
    "iso:country":"US",
    "sg:address":"2617 W Chestnut Rd",
    "sg:city":"Thiensville",
    "sg:classifiers":[
        {
            "category":"Banks & Credit Unions",
            "subcategory":"Financial Services",
            "type":"Services"
        }
    ],
    "sg:phone":"+1 414 546 8500",
    "sg:postcode":"53092",
    "sg:province":"WI",
    "sg:tags":[
        "company",
        "holding"
    ],
    "wof:name":"Intec Industries Inc",
    "wof:placetype":"venue"
},
  "geometry": {"coordinates":[-87.94535,43.225306],"type":"Point"}
}