{
  "type": "Feature",
  "properties": {
    "iso:country":"US",
    "sg:address":"110 Main St",
    "sg:city":"Mukwonago",
    "sg:classifiers":[
        {
            "category":"Shopping",
            "subcategory":"Jewelry",
            "type":"Retail Goods"
        }
    ],
    "sg:phone":"+1 262 363 8932",
    "sg:postcode":"53149",
    "sg:province":"WI",
    "sg:tags":[
        "jeweler"
    ],
    "wof:name":"Mukwonago Jewelers Inc",
    "wof:placetype":"venue"
},
  "geometry": {"coordinates":[-88.332309,42.862941],"type":"Point"}
}