{
  "type": "Feature",
  "properties": {
    "addr:full":"701 Basswood Ave Verona WI 53593",
    "addr:housenumber":"701",
    "addr:postcode":"53593",
    "addr:street":"Basswood Ave",
    "iso:country":"US",
    "sg:address":"701 Basswood Ave",
    "sg:city":"Verona",
    "sg:classifiers":[
        {
            "category":"Building & Trades",
            "subcategory":"Construction",
            "type":"Services"
        }
    ],
    "sg:phone":"+1 608 332 1341",
    "sg:postcode":"53593",
    "sg:province":"WI",
    "sg:tags":[
        "painter"
    ],
    "wof:name":"Quality Affordable Painting",
    "wof:placetype":"venue"
},
  "geometry": {"coordinates":[-89.545508,42.99677],"type":"Point"}
}