{
  "type": "Feature",
  "properties": {
    "iso:country":"US",
    "sg:address":"789 N Central Ave",
    "sg:city":"Richland Center",
    "sg:classifiers":[
        {
            "category":"Professional",
            "subcategory":"Management & Consulting",
            "type":"Services"
        }
    ],
    "sg:phone":"+1 608 647 4210",
    "sg:postcode":"53581",
    "sg:province":"WI",
    "wof:name":"C C D L-Consumer Cr Counseling",
    "wof:placetype":"venue"
},
  "geometry": {"coordinates":[-90.385239,43.341066],"type":"Point"}
}