{
  "type": "Feature",
  "properties": {
    "addr:full":"95 N Moorland Rd Brookfield WI 53005",
    "addr:housenumber":"95",
    "addr:postcode":"53005",
    "addr:street":"N Moorland Rd",
    "iso:country":"US",
    "sg:address":"95 N Moorland Rd",
    "sg:city":"Brookfield",
    "sg:classifiers":[
        {
            "category":"Shopping",
            "type":"Retail Goods"
        },
        {
            "category":"Shopping",
            "subcategory":"Beauty & Cosmetics",
            "type":"Retail Goods"
        }
    ],
    "sg:phone":"+1 262 782 4406",
    "sg:postcode":"53005",
    "sg:province":"WI",
    "sg:tags":[
        "merchandise",
        "perfume"
    ],
    "wof:name":"Merle Norman Cosmetics",
    "wof:placetype":"venue"
},
  "geometry": {"coordinates":[-88.106933,43.034839],"type":"Point"}
}