{
  "type": "Feature",
  "properties": {
    "addr:full":"222 S Madison Ave Sturgeon Bay WI 54235",
    "addr:housenumber":"222",
    "addr:postcode":"54235",
    "addr:street":"S Madison Ave",
    "iso:country":"US",
    "sg:address":"222 S Madison Ave",
    "sg:city":"Sturgeon Bay",
    "sg:classifiers":[
        {
            "category":"Food & Beverages",
            "subcategory":"Groceries & Convenience Stores",
            "type":"Retail Goods"
        }
    ],
    "sg:phone":"+1 920 746 0064",
    "sg:postcode":"54235",
    "sg:province":"WI",
    "wof:name":"Jandu Petroleum 2",
    "wof:placetype":"venue"
},
  "geometry": {"coordinates":[-87.384355,44.826652],"type":"Point"}
}