{
  "type": "Feature",
  "properties": {
    "iso:country":"US",
    "sg:address":"2392 Co Hwy M",
    "sg:city":"New Auburn",
    "sg:classifiers":[
        {
            "category":"Retail",
            "subcategory":"Animal Services",
            "type":"Services"
        }
    ],
    "sg:phone":"+1 715 925 2020",
    "sg:postcode":"54757",
    "sg:province":"WI",
    "sg:tags":[
        "pet",
        "grooming",
        "washing"
    ],
    "wof:name":"Rustic Rover",
    "wof:placetype":"venue"
},
  "geometry": {"coordinates":[-91.637293,45.171934],"type":"Point"}
}