{
  "type": "Feature",
  "properties": {
    "iso:country":"US",
    "sg:address":"3627 W Lisbon Ave",
    "sg:city":"Milwaukee",
    "sg:classifiers":[
        {
            "category":"Food & Beverages",
            "subcategory":"Groceries & Convenience Stores",
            "type":"Retail Goods"
        }
    ],
    "sg:phone":"+1 414 342 1343",
    "sg:postcode":"53208",
    "sg:province":"WI",
    "wof:name":"Ashraf Food Market",
    "wof:placetype":"venue"
},
  "geometry": {"coordinates":[-87.959671,43.054807],"type":"Point"}
}