{
  "type": "Feature",
  "properties": {
    "addr:full":"9225 W Beloit Rd Milwaukee WI 53227",
    "addr:housenumber":"9225",
    "addr:postcode":"53227",
    "addr:street":"W Beloit Rd",
    "iso:country":"US",
    "sg:address":"9225 W Beloit Rd",
    "sg:city":"Milwaukee",
    "sg:classifiers":[
        {
            "category":"Farming",
            "subcategory":"Nursery",
            "type":"Manufacturing & Wholesale Goods"
        }
    ],
    "sg:phone":"+1 414 545 2500",
    "sg:postcode":"53227",
    "sg:province":"WI",
    "sg:tags":[
        "ornamental"
    ],
    "wof:name":"Classic Florals",
    "wof:placetype":"venue"
},
  "geometry": {"coordinates":[-88.02897,42.985603],"type":"Point"}
}