{
  "type": "Feature",
  "properties": {
    "iso:country":"US",
    "sg:address":"1512 Water St",
    "sg:city":"Stevens Point",
    "sg:classifiers":[
        {
            "category":"Building & Trades",
            "subcategory":"Plumbing",
            "type":"Services"
        }
    ],
    "sg:phone":"+1 715 344 4066",
    "sg:postcode":"54481",
    "sg:province":"WI",
    "sg:tags":[
        "plumbing",
        "contractor"
    ],
    "wof:name":"Robert J Soik Plumbing Heating",
    "wof:placetype":"venue"
},
  "geometry": {"coordinates":[-89.583112,44.519692],"type":"Point"}
}