{
  "type": "Feature",
  "properties": {
    "addr:full":"5701 W Good Hope Rd Milwaukee WI 53223",
    "addr:housenumber":"5701",
    "addr:postcode":"53223",
    "addr:street":"W Good Hope Rd",
    "iso:country":"US",
    "sg:address":"5701 W Good Hope Rd",
    "sg:city":"Milwaukee",
    "sg:classifiers":[
        {
            "category":"Retail",
            "subcategory":"Auto Rental",
            "type":"Services"
        }
    ],
    "sg:phone":"+1 414 353 5850",
    "sg:postcode":"53223",
    "sg:province":"WI",
    "sg:tags":[
        "renting",
        "truck",
        "leasing"
    ],
    "wof:name":"U-Haul Co",
    "wof:placetype":"venue"
},
  "geometry": {"coordinates":[-87.98370300000001,43.148473],"type":"Point"}
}