{
  "type": "Feature",
  "properties": {
    "iso:country":"US",
    "sg:address":"6646 250th St",
    "sg:city":"Cadott",
    "sg:classifiers":[
        {
            "category":"Organizations",
            "subcategory":"Professional Association",
            "type":"Services"
        }
    ],
    "sg:phone":"+1 715 289 3338",
    "sg:postcode":"54727",
    "sg:province":"WI",
    "sg:tags":[
        "chambers",
        "commerce"
    ],
    "wof:name":"Chamber Of Commerce",
    "wof:placetype":"venue"
},
  "geometry": {"coordinates":[-91.16588299999999,44.932073],"type":"Point"}
}