{
  "type": "Feature",
  "properties": {
    "addr:full":"1528 US Hwy 51 Stoughton WI 53589",
    "addr:housenumber":"1528",
    "addr:postcode":"53589",
    "addr:street":"Us Hwy 51",
    "iso:country":"US",
    "sg:address":"1528 US Hwy 51",
    "sg:city":"Stoughton",
    "sg:classifiers":[
        {
            "category":"Autos & Motor Vehicles",
            "subcategory":"Auto Supplies",
            "type":"Retail Goods"
        }
    ],
    "sg:phone":"+1 608 877 2890",
    "sg:postcode":"53589",
    "sg:province":"WI",
    "sg:tags":[
        "automobile",
        "parts"
    ],
    "wof:name":"Advance Auto Parts Inc",
    "wof:placetype":"venue"
},
  "geometry": {"coordinates":[-89.233845,42.917494],"type":"Point"}
}