{
  "type": "Feature",
  "properties": {
    "iso:country":"US",
    "sg:address":"9015 Lake Bernice Dr",
    "sg:city":"Allenton",
    "sg:phone":"+1 262 626 4793",
    "sg:postcode":"53002",
    "sg:province":"WI",
    "sg:tags":[
        "farm",
        "field",
        "corn",
        "crop"
    ],
    "wof:name":"Spoerl John",
    "wof:placetype":"venue"
},
  "geometry": {"coordinates":[-88.301469,43.518567],"type":"Point"}
}