{
  "type": "Feature",
  "properties": {
    "addr:full":"502 E Lincoln Ave Fall Creek WI 54742",
    "addr:housenumber":"502",
    "addr:postcode":"54742",
    "addr:street":"E Lincoln Ave",
    "iso:country":"US",
    "sg:address":"502 E Lincoln Ave",
    "sg:city":"Fall Creek",
    "sg:classifiers":[
        {
            "category":"Farming",
            "subcategory":"Farm & Veterinary Services",
            "type":"Manufacturing & Wholesale Goods"
        }
    ],
    "sg:phone":"+1 715 877 2922",
    "sg:postcode":"54742",
    "sg:province":"WI",
    "sg:tags":[
        "drying",
        "grain"
    ],
    "wof:name":"Northwest Grain Equipment",
    "wof:placetype":"venue"
},
  "geometry": {"coordinates":[-91.270702,44.763454],"type":"Point"}
}