{
  "type": "Feature",
  "properties": {
    "addr:full":"223 6th St Racine WI 53403",
    "addr:housenumber":"223",
    "addr:postcode":"53403",
    "addr:street":"6Th St",
    "iso:country":"US",
    "sg:address":"223 6th St",
    "sg:city":"Racine",
    "sg:classifiers":[
        {
            "category":"Personal",
            "subcategory":"Beauty Salon",
            "type":"Services"
        }
    ],
    "sg:phone":"+1 262 637 2747",
    "sg:postcode":"53403",
    "sg:province":"WI",
    "wof:name":"Crispy Cuts Hair Designs",
    "wof:placetype":"venue"
},
  "geometry": {"coordinates":[-87.78384,42.726701],"type":"Point"}
}