{
  "type": "Feature",
  "properties": {
    "addr:full":"1224 Stead Dr Menasha WI 54952",
    "addr:housenumber":"1224",
    "addr:postcode":"54952",
    "addr:street":"Stead Dr",
    "iso:country":"US",
    "sg:address":"1224 Stead Dr",
    "sg:city":"Menasha",
    "sg:classifiers":[
        {
            "category":"Personal",
            "type":"Services"
        }
    ],
    "sg:phone":"+1 920 725 2779",
    "sg:postcode":"54952",
    "sg:province":"WI",
    "wof:name":"Herbalife Independent Distr",
    "wof:placetype":"venue"
},
  "geometry": {"coordinates":[-88.412182,44.223507],"type":"Point"}
}