{
  "type": "Feature",
  "properties": {
    "iso:country":"US",
    "sg:address":"4875 Fairgrounds Rd",
    "sg:city":"Spooner",
    "sg:classifiers":[
        {
            "category":"Retail",
            "subcategory":"Auto Repair",
            "type":"Services"
        }
    ],
    "sg:phone":"+1 715 635 7115",
    "sg:postcode":"54801",
    "sg:province":"WI",
    "sg:tags":[
        "body",
        "automobile",
        "painting"
    ],
    "wof:name":"Severson's Auto Body",
    "wof:placetype":"venue"
},
  "geometry": {"coordinates":[-91.900842,45.812142],"type":"Point"}
}