{
  "type": "Feature",
  "properties": {
    "iso:country":"US",
    "sg:address":"303 Walnut St",
    "sg:city":"Sauk City",
    "sg:classifiers":[
        {
            "category":"Shopping",
            "subcategory":"Catalog Store",
            "type":"Retail Goods"
        }
    ],
    "sg:phone":"+1 608 643 0987",
    "sg:postcode":"53583",
    "sg:province":"WI",
    "sg:tags":[
        "mail",
        "house"
    ],
    "wof:name":"Julie Nicholson",
    "wof:placetype":"venue"
},
  "geometry": {"coordinates":[-89.73224,43.278335],"type":"Point"}
}