{
  "type": "Feature",
  "properties": {
    "iso:country":"US",
    "sg:address":"3950 N 77th St",
    "sg:city":"Milwaukee",
    "sg:classifiers":[
        {
            "category":"Retail",
            "subcategory":"Repair Shop",
            "type":"Services"
        }
    ],
    "sg:phone":"+1 414 466 1519",
    "sg:postcode":"53222",
    "sg:province":"WI",
    "sg:tags":[
        "refrigeration"
    ],
    "wof:name":"Jr Refrigeration",
    "wof:placetype":"venue"
},
  "geometry": {"coordinates":[-88.008484,43.088968],"type":"Point"}
}