{
  "type": "Feature",
  "properties": {
    "iso:country":"US",
    "sg:address":"8112 Fairview St",
    "sg:city":"Onalaska",
    "sg:classifiers":[
        {
            "category":"Wholesale",
            "subcategory":"Electrical",
            "type":"Manufacturing & Wholesale Goods"
        }
    ],
    "sg:phone":"+1 608 781 1332",
    "sg:postcode":"54650",
    "sg:province":"WI",
    "sg:tags":[
        "equipment"
    ],
    "wof:name":"Saf Systems",
    "wof:placetype":"venue"
},
  "geometry": {"coordinates":[-91.311842,43.946829],"type":"Point"}
}