{
  "type": "Feature",
  "properties": {
    "iso:country":"US",
    "sg:address":"200 Lulu Ave W",
    "sg:city":"Almena",
    "sg:classifiers":[
        {
            "category":"Building & Trades",
            "subcategory":"Construction",
            "type":"Services"
        }
    ],
    "sg:phone":"+1 715 357 3216",
    "sg:postcode":"54805",
    "sg:province":"WI",
    "sg:tags":[
        "residential",
        "commercial",
        "contractor"
    ],
    "wof:name":"KUHL Construction",
    "wof:placetype":"venue"
},
  "geometry": {"coordinates":[-92.04355,45.41693],"type":"Point"}
}