{
  "type": "Feature",
  "properties": {
    "iso:country":"US",
    "sg:address":"4709 N Devonshire Dr",
    "sg:city":"Appleton",
    "sg:classifiers":[
        {
            "category":"Real Estate",
            "subcategory":"Real Estate Agent",
            "type":"Services"
        },
        {
            "category":"Professional",
            "subcategory":"Business Services",
            "type":"Services"
        }
    ],
    "sg:phone":"+1 920 730 8388",
    "sg:postcode":"54913",
    "sg:province":"WI",
    "sg:tags":[
        "appraiser"
    ],
    "wof:name":"Tri County Appraisals",
    "wof:placetype":"venue"
},
  "geometry": {"coordinates":[-88.376462,44.311412],"type":"Point"}
}