{
  "type": "Feature",
  "properties": {
    "iso:country":"US",
    "sg:address":"513 E 17th St",
    "sg:city":"Marshfield",
    "sg:classifiers":[
        {
            "category":"Recreation",
            "type":"Entertainment"
        }
    ],
    "sg:phone":"+1 715 387 1261",
    "sg:postcode":"54449",
    "sg:province":"WI",
    "sg:tags":[
        "fairground"
    ],
    "sg:website":"www.centralwisconsinstatefair.com",
    "wof:name":"Central Wi State Fair",
    "wof:placetype":"venue"
},
  "geometry": {"coordinates":[-90.174248,44.652053],"type":"Point"}
}