{
  "type": "Feature",
  "properties": {
    "iso:country":"US",
    "sg:address":"831 5th Ave",
    "sg:city":"Antigo",
    "sg:classifiers":[
        {
            "category":"Shopping",
            "subcategory":"Computers & Home Electronics",
            "type":"Retail Goods"
        }
    ],
    "sg:phone":"+1 715 623 5394",
    "sg:postcode":"54409",
    "sg:province":"WI",
    "sg:tags":[
        "game",
        "video"
    ],
    "wof:name":"Con's Recreation Ctr",
    "wof:placetype":"venue"
},
  "geometry": {"coordinates":[-89.155799,45.140491],"type":"Point"}
}