{
  "type": "Feature",
  "properties": {
    "iso:country":"US",
    "sg:address":"8205 US Highway 41",
    "sg:city":"Caledonia",
    "sg:classifiers":[
        {
            "category":"Travel",
            "subcategory":"Hotels & Motels",
            "type":"Entertainment"
        }
    ],
    "sg:phone":"+1 262 835 2622",
    "sg:postcode":"53108",
    "sg:province":"WI",
    "wof:name":"Seven Mile Motel",
    "wof:placetype":"venue"
},
  "geometry": {"coordinates":[-87.952003,42.829899],"type":"Point"}
}