{
  "type": "Feature",
  "properties": {
    "iso:country":"US",
    "sg:address":"2702 Monroe St",
    "sg:city":"Madison",
    "sg:classifiers":[
        {
            "category":"Insurance",
            "subcategory":"Insurance Agent",
            "type":"Services"
        }
    ],
    "sg:phone":"+1 608 231 2461",
    "sg:postcode":"53711",
    "sg:province":"WI",
    "wof:name":"American Family",
    "wof:placetype":"venue"
},
  "geometry": {"coordinates":[-89.429677,43.056751],"type":"Point"}
}