{
  "type": "Feature",
  "properties": {
    "iso:country":"US",
    "sg:address":"621 Brickl Rd",
    "sg:city":"West Salem",
    "sg:classifiers":[
        {
            "category":"Building & Trades",
            "subcategory":"Construction",
            "type":"Services"
        },
        {
            "category":"Home & Garden",
            "subcategory":"Furniture",
            "type":"Retail Goods"
        }
    ],
    "sg:phone":"+1 608 786 2110",
    "sg:postcode":"54669",
    "sg:province":"WI",
    "sg:tags":[
        "top",
        "counter",
        "contractor"
    ],
    "wof:name":"Salem Custom Countertops LLC",
    "wof:placetype":"venue"
},
  "geometry": {"coordinates":[-91.089021,43.904917],"type":"Point"}
}