{
  "type": "Feature",
  "properties": {
    "addr:full":"333 Lincoln St Rhinelander WI 54501",
    "addr:housenumber":"333",
    "addr:postcode":"54501",
    "addr:street":"Lincoln St",
    "iso:country":"US",
    "sg:address":"333 Lincoln St",
    "sg:city":"Rhinelander",
    "sg:classifiers":[
        {
            "category":"Restaurant",
            "type":"Food & Drink"
        }
    ],
    "sg:menulink":"http://www.allmenus.com/wi/rhinelander/218349-burger-king/menu/",
    "sg:phone":"+1 715 362 5300",
    "sg:postcode":"54501",
    "sg:province":"WI",
    "sg:tags":[
        "american"
    ],
    "wof:name":"Burger King",
    "wof:placetype":"venue"
},
  "geometry": {"coordinates":[-89.408019,45.633351],"type":"Point"}
}