{
  "type": "Feature",
  "properties": {
    "iso:country":"US",
    "sg:address":"608 11th St S",
    "sg:city":"La Crosse",
    "sg:classifiers":[
        {
            "category":"Health Services",
            "subcategory":"Clinic",
            "type":"Services"
        }
    ],
    "sg:phone":"+1 608 782 9325",
    "sg:postcode":"54601",
    "sg:province":"WI",
    "sg:tags":[
        "specialty",
        "outpatient"
    ],
    "wof:name":"Siena Hall Halfway House",
    "wof:placetype":"venue"
},
  "geometry": {"coordinates":[-91.241069,43.804723],"type":"Point"}
}