{
  "type": "Feature",
  "properties": {
    "addr:full":"3707 N 92nd St Milwaukee WI 53222",
    "addr:housenumber":"3707",
    "addr:postcode":"53222",
    "addr:street":"N 92Nd St",
    "iso:country":"US",
    "sg:address":"3707 N 92nd St",
    "sg:city":"Milwaukee",
    "sg:classifiers":[
        {
            "category":"Professional",
            "type":"Services"
        }
    ],
    "sg:phone":"+1 414 527 9684",
    "sg:postcode":"53222",
    "sg:province":"WI",
    "wof:name":"Vegan Essentials",
    "wof:placetype":"venue"
},
  "geometry": {"coordinates":[-88.027759,43.084969],"type":"Point"}
}