{
  "type": "Feature",
  "properties": {
    "addr:full":"2635 N Mayfair Rd Milwaukee WI 53226",
    "addr:housenumber":"2635",
    "addr:postcode":"53226",
    "addr:street":"N Mayfair Rd",
    "iso:country":"US",
    "sg:address":"2635 N Mayfair Rd",
    "sg:city":"Milwaukee",
    "sg:classifiers":[
        {
            "category":"Restaurant",
            "type":"Food & Drink"
        }
    ],
    "sg:phone":"+1 414 476 7117",
    "sg:postcode":"53226",
    "sg:province":"WI",
    "sg:tags":[
        "eating"
    ],
    "wof:name":"Bennigans",
    "wof:placetype":"venue"
},
  "geometry": {"coordinates":[-88.047911,43.074745],"type":"Point"}
}