{
  "type": "Feature",
  "properties": {
    "iso:country":"US",
    "sg:address":"1706 Knoll Crest Dr",
    "sg:city":"Sheboygan",
    "sg:classifiers":[
        {
            "category":"Professional",
            "type":"Services"
        }
    ],
    "sg:phone":"+1 920 783 0300",
    "sg:postcode":"53081",
    "sg:province":"WI",
    "wof:name":"Andrea & Dennis Oshefsky",
    "wof:placetype":"venue"
},
  "geometry": {"coordinates":[-87.73018399999999,43.71178],"type":"Point"}
}