{
  "type": "Feature",
  "properties": {
    "addr:full":"10000 N Ellendale Rd Edgerton WI 53534",
    "addr:housenumber":"10000",
    "addr:postcode":"53534",
    "addr:street":"N Ellendale Rd",
    "iso:country":"US",
    "sg:address":"10000 N Ellendale Rd",
    "sg:city":"Edgerton",
    "sg:classifiers":[
        {
            "category":"Government",
            "subcategory":"Office",
            "type":"Public Place"
        }
    ],
    "sg:phone":"+1 608 868 7273",
    "sg:postcode":"53534",
    "sg:province":"WI",
    "sg:tags":[
        "state"
    ],
    "wof:name":"Natural Resources Dept",
    "wof:placetype":"venue"
},
  "geometry": {"coordinates":[-89.04170999999999,42.825951],"type":"Point"}
}