{
  "type": "Feature",
  "properties": {
    "iso:country":"US",
    "sg:address":"330 Woodland Dr",
    "sg:city":"Whitewater",
    "sg:classifiers":[
        {
            "category":"Organizations",
            "subcategory":"Political Organization",
            "type":"Services"
        }
    ],
    "sg:phone":"+1 262 473 7210",
    "sg:postcode":"53190",
    "sg:province":"WI",
    "wof:name":"League of Women Voters of US",
    "wof:placetype":"venue"
},
  "geometry": {"coordinates":[-88.75757,42.83047],"type":"Point"}
}