{
  "type": "Feature",
  "properties": {
    "iso:country":"US",
    "sg:address":"120 S Main St",
    "sg:city":"Lodi",
    "sg:classifiers":[
        {
            "category":"Shopping",
            "subcategory":"Clothing, Apparel, & Fashions",
            "type":"Retail Goods"
        }
    ],
    "sg:phone":"+1 608 592 4114",
    "sg:postcode":"53555",
    "sg:province":"WI",
    "wof:name":"Irene's Boutique",
    "wof:placetype":"venue"
},
  "geometry": {"coordinates":[-89.526679,43.313796],"type":"Point"}
}