{
  "type": "Feature",
  "properties": {
    "iso:country":"US",
    "sg:address":"1480 Co Hwy Nn",
    "sg:city":"West Bend",
    "sg:classifiers":[
        {
            "category":"Home & Garden",
            "subcategory":"Carpets & Floor Coverings",
            "type":"Retail Goods"
        },
        {
            "category":"Building & Trades",
            "subcategory":"Construction",
            "type":"Services"
        }
    ],
    "sg:phone":"+1 262 675 6727",
    "sg:postcode":"53095",
    "sg:province":"WI",
    "sg:tags":[
        "tile",
        "dealer"
    ],
    "wof:name":"Butschlick's Floor Covering",
    "wof:placetype":"venue"
},
  "geometry": {"coordinates":[-88.09843600000001,43.368069],"type":"Point"}
}