{
  "type": "Feature",
  "properties": {
    "iso:country":"US",
    "sg:address":"1619 Co Hwy Nn",
    "sg:city":"West Bend",
    "sg:classifiers":[
        {
            "category":"Farming",
            "subcategory":"Dairy Farm",
            "type":"Manufacturing & Wholesale Goods"
        }
    ],
    "sg:phone":"+1 262 675 2225",
    "sg:postcode":"53095",
    "sg:province":"WI",
    "wof:name":"Allen Gierach",
    "wof:placetype":"venue"
},
  "geometry": {"coordinates":[-88.110604,43.368097],"type":"Point"}
}