{
  "type": "Feature",
  "properties": {
    "addr:full":"1649 Loomis St La Crosse WI 54603",
    "addr:housenumber":"1649",
    "addr:postcode":"54603",
    "addr:street":"Loomis St",
    "iso:country":"US",
    "sg:address":"1649 Loomis St",
    "sg:city":"La Crosse",
    "sg:classifiers":[
        {
            "category":"Building & Trades",
            "subcategory":"Electrical",
            "type":"Services"
        }
    ],
    "sg:phone":"+1 608 781 4528",
    "sg:postcode":"54603",
    "sg:province":"WI",
    "sg:tags":[
        "electrical",
        "contractor"
    ],
    "wof:name":"B T Electric LLC",
    "wof:placetype":"venue"
},
  "geometry": {"coordinates":[-91.23699499999999,43.847241],"type":"Point"}
}