{
  "type": "Feature",
  "properties": {
    "iso:country":"US",
    "sg:address":"5056 970th Ave",
    "sg:city":"Wheeler",
    "sg:classifiers":[
        {
            "category":"Real Estate",
            "subcategory":"Architect",
            "type":"Services"
        }
    ],
    "sg:phone":"+1 715 632 2523",
    "sg:postcode":"54772",
    "sg:province":"WI",
    "sg:tags":[
        "engineering",
        "architectural"
    ],
    "wof:name":"Timper Associates Engineers",
    "wof:placetype":"venue"
},
  "geometry": {"coordinates":[-91.908203,45.030792],"type":"Point"}
}