{
  "type": "Feature",
  "properties": {
    "iso:country":"US",
    "sg:address":"7520 Water St",
    "sg:city":"Danbury",
    "sg:classifiers":[
        {
            "category":"Organizations",
            "subcategory":"Religious Organization",
            "type":"Services"
        }
    ],
    "sg:phone":"+1 715 656 4370",
    "sg:postcode":"54830",
    "sg:province":"WI",
    "wof:name":"Danbury United Methodist",
    "wof:placetype":"venue"
},
  "geometry": {"coordinates":[-92.370224,46.008091],"type":"Point"}
}