{
  "type": "Feature",
  "properties": {
    "iso:country":"US",
    "sg:address":"10625 S Cleveland Rd",
    "sg:city":"Cleveland",
    "sg:phone":"+1 920 693 8575",
    "sg:postcode":"53015",
    "sg:province":"WI",
    "sg:tags":[
        "farm",
        "soybean"
    ],
    "wof:name":"Randy Bender",
    "wof:placetype":"venue"
},
  "geometry": {"coordinates":[-87.82808199999999,43.906169],"type":"Point"}
}