{
  "type": "Feature",
  "properties": {
    "iso:country":"US",
    "sg:address":"630 Water St",
    "sg:city":"Eau Claire",
    "sg:classifiers":[
        {
            "category":"Real Estate",
            "subcategory":"Real Estate Agent",
            "type":"Services"
        }
    ],
    "sg:phone":"+1 715 838 2000",
    "sg:postcode":"54703",
    "sg:province":"WI",
    "wof:name":"M C Q Properties",
    "wof:placetype":"venue"
},
  "geometry": {"coordinates":[-91.51331,44.802238],"type":"Point"}
}