{
  "type": "Feature",
  "properties": {
    "iso:country":"US",
    "sg:address":"11295 Co Rd V",
    "sg:city":"Glen Haven",
    "sg:classifiers":[
        {
            "category":"Farming",
            "subcategory":"Dairy Farm",
            "type":"Manufacturing & Wholesale Goods"
        }
    ],
    "sg:phone":"+1 608 794 2579",
    "sg:postcode":"53810",
    "sg:province":"WI",
    "wof:name":"Robert & Sheila Balmer",
    "wof:placetype":"venue"
},
  "geometry": {"coordinates":[-90.970545,42.815619],"type":"Point"}
}