{
  "type": "Feature",
  "properties": {
    "iso:country":"US",
    "sg:address":"130 S Central Ave",
    "sg:city":"Richland Center",
    "sg:classifiers":[
        {
            "category":"Personal",
            "subcategory":"Beauty Salon",
            "type":"Services"
        }
    ],
    "sg:phone":"+1 608 647 9052",
    "sg:postcode":"53581",
    "sg:province":"WI",
    "sg:tags":[
        "shop"
    ],
    "wof:name":"Pampered Pleasures",
    "wof:placetype":"venue"
},
  "geometry": {"coordinates":[-90.385502,43.335243],"type":"Point"}
}