{
  "type": "Feature",
  "properties": {
    "addr:full":"730 S Jackson St Green Bay WI 54301",
    "addr:housenumber":"730",
    "addr:postcode":"54301",
    "addr:street":"S Jackson St",
    "iso:country":"US",
    "sg:address":"730 S Jackson St",
    "sg:city":"Green Bay",
    "sg:classifiers":[
        {
            "category":"Freight",
            "type":"Transportation"
        }
    ],
    "sg:phone":"+1 920 437 7992",
    "sg:postcode":"54301",
    "sg:province":"WI",
    "sg:tags":[
        "special"
    ],
    "wof:name":"Community Storage",
    "wof:placetype":"venue"
},
  "geometry": {"coordinates":[-88.013696,44.502848],"type":"Point"}
}