{
  "type": "Feature",
  "properties": {
    "iso:country":"US",
    "sg:address":"129 N Durkee St",
    "sg:city":"Appleton",
    "sg:classifiers":[
        {
            "category":"Personal",
            "subcategory":"Barber",
            "type":"Services"
        }
    ],
    "sg:phone":"+1 920 739 1805",
    "sg:postcode":"54911",
    "sg:province":"WI",
    "sg:tags":[
        "shop"
    ],
    "wof:name":"Campus Barber Shop",
    "wof:placetype":"venue"
},
  "geometry": {"coordinates":[-88.402824,44.262885],"type":"Point"}
}