{
  "type": "Feature",
  "properties": {
    "addr:full":"2701 S Kinnickinnic Ave Milwaukee WI 53207",
    "addr:housenumber":"2701",
    "addr:postcode":"53207",
    "addr:street":"S Kinnickinnic Ave",
    "iso:country":"US",
    "sg:address":"2701 S Kinnickinnic Ave",
    "sg:city":"Milwaukee",
    "sg:classifiers":[
        {
            "category":"Banks & Credit Unions",
            "subcategory":"Bank",
            "type":"Services"
        }
    ],
    "sg:phone":"+1 414 482 4800",
    "sg:postcode":"53207",
    "sg:province":"WI",
    "sg:website":"www.mibank.com",
    "wof:name":"M & I Bank",
    "wof:placetype":"venue"
},
  "geometry": {"coordinates":[-87.89552399999999,42.995236],"type":"Point"}
}