{
  "type": "Feature",
  "properties": {
    "iso:country":"US",
    "sg:address":"4444 Beechnut Cir",
    "sg:city":"New Franken",
    "sg:classifiers":[
        {
            "category":"Building & Trades",
            "subcategory":"Construction",
            "type":"Services"
        }
    ],
    "sg:phone":"+1 920 866 2144",
    "sg:postcode":"54229",
    "sg:province":"WI",
    "sg:tags":[
        "house"
    ],
    "wof:name":"Superior Homes",
    "wof:placetype":"venue"
},
  "geometry": {"coordinates":[-87.857467,44.546735],"type":"Point"}
}