{
  "type": "Feature",
  "properties": {
    "iso:country":"US",
    "sg:address":"8089 Doyle Rd",
    "sg:city":"Theresa",
    "sg:classifiers":[
        {
            "category":"Farming",
            "subcategory":"Livestock Farm",
            "type":"Manufacturing & Wholesale Goods"
        }
    ],
    "sg:phone":"+1 920 488 2128",
    "sg:postcode":"53091",
    "sg:province":"WI",
    "sg:tags":[
        "feedlot",
        "hog",
        "or",
        "beef",
        "cattle"
    ],
    "wof:name":"David Straub",
    "wof:placetype":"venue"
},
  "geometry": {"coordinates":[-88.430216,43.481891],"type":"Point"}
}