{
  "type": "Feature",
  "properties": {
    "addr:full":"1316 12th Ave Grafton WI 53024",
    "addr:housenumber":"1316",
    "addr:postcode":"53024",
    "addr:street":"12Th Ave",
    "iso:country":"US",
    "sg:address":"1316 12th Ave",
    "sg:city":"Grafton",
    "sg:classifiers":[
        {
            "category":"Retail",
            "subcategory":"Portrait Studio",
            "type":"Services"
        }
    ],
    "sg:phone":"+1 262 268 3805",
    "sg:postcode":"53024",
    "sg:province":"WI",
    "sg:tags":[
        "photo"
    ],
    "wof:name":"Elite Photography",
    "wof:placetype":"venue"
},
  "geometry": {"coordinates":[-87.951607,43.316582],"type":"Point"}
}