{
  "type": "Feature",
  "properties": {
    "addr:full":"2124 W Grand Ave Beloit WI 53511",
    "addr:housenumber":"2124",
    "addr:postcode":"53511",
    "addr:street":"W Grand Ave",
    "iso:country":"US",
    "sg:address":"2124 W Grand Ave",
    "sg:city":"Beloit",
    "sg:classifiers":[
        {
            "category":"Building & Trades",
            "subcategory":"Construction",
            "type":"Services"
        }
    ],
    "sg:phone":"+1 608 365 0472",
    "sg:postcode":"53511",
    "sg:province":"WI",
    "sg:tags":[
        "concrete",
        "contractor"
    ],
    "wof:name":"Windsor Concrete",
    "wof:placetype":"venue"
},
  "geometry": {"coordinates":[-89.068197,42.501657],"type":"Point"}
}