{
  "type": "Feature",
  "properties": {
    "iso:country":"US",
    "sg:address":"6889 US Hwy 8",
    "sg:city":"Niagara",
    "sg:classifiers":[
        {
            "category":"Government",
            "subcategory":"Office",
            "type":"Public Place"
        }
    ],
    "sg:phone":"+1 715 251 1545",
    "sg:postcode":"54151",
    "sg:province":"WI",
    "sg:tags":[
        "village"
    ],
    "wof:name":"Niagara Twp Hall",
    "wof:placetype":"venue"
},
  "geometry": {"coordinates":[-87.942682,45.747068],"type":"Point"}
}