{
  "type": "Feature",
  "properties": {
    "addr:full":"88045 Bark Point Rd Herbster WI 54844",
    "addr:housenumber":"88045",
    "addr:postcode":"54844",
    "addr:street":"Bark Point Rd",
    "iso:country":"US",
    "sg:address":"88045 Bark Point Rd",
    "sg:city":"Herbster",
    "sg:classifiers":[
        {
            "category":"Shopping",
            "subcategory":"Gifts & Souvenirs",
            "type":"Retail Goods"
        }
    ],
    "sg:phone":"+1 715 372 5599",
    "sg:postcode":"54844",
    "sg:province":"WI",
    "wof:name":"This Old Bunkhouse",
    "wof:placetype":"venue"
},
  "geometry": {"coordinates":[-91.251772,46.839793],"type":"Point"}
}