{
  "type": "Feature",
  "properties": {
    "iso:country":"US",
    "sg:address":"3618 W River Dr",
    "sg:city":"Janesville",
    "sg:classifiers":[
        {
            "category":"Professional",
            "type":"Services"
        }
    ],
    "sg:phone":"+1 608 751 3713",
    "sg:postcode":"53548",
    "sg:province":"WI",
    "sg:tags":[
        "establishment"
    ],
    "wof:name":"Jack Of Trades",
    "wof:placetype":"venue"
},
  "geometry": {"coordinates":[-89.06015,42.730104],"type":"Point"}
}