{
  "type": "Feature",
  "properties": {
    "iso:country":"US",
    "sg:address":"2900 N 24th St",
    "sg:city":"Milwaukee",
    "sg:classifiers":[
        {
            "category":"Food & Beverages",
            "subcategory":"Groceries & Convenience Stores",
            "type":"Retail Goods"
        }
    ],
    "sg:phone":"+1 414 442 8112",
    "sg:postcode":"53206",
    "sg:province":"WI",
    "sg:tags":[
        "grocer"
    ],
    "wof:name":"Save More Food Market",
    "wof:placetype":"venue"
},
  "geometry": {"coordinates":[-87.942364,43.073326],"type":"Point"}
}