{
  "type": "Feature",
  "properties": {
    "addr:full":"1612 63rd St Kenosha WI 53143",
    "addr:housenumber":"1612",
    "addr:postcode":"53143",
    "addr:street":"63Rd St",
    "iso:country":"US",
    "sg:address":"1612 63rd St",
    "sg:city":"Kenosha",
    "sg:classifiers":[
        {
            "category":"Professional",
            "type":"Services"
        }
    ],
    "sg:phone":"+1 262 653 8840",
    "sg:postcode":"53143",
    "sg:province":"WI",
    "wof:name":"Kidzone",
    "wof:placetype":"venue"
},
  "geometry": {"coordinates":[-87.83082899999999,42.577764],"type":"Point"}
}