{
  "type": "Feature",
  "properties": {
    "iso:country":"US",
    "sg:address":"1639 S 23rd St",
    "sg:city":"Milwaukee",
    "sg:classifiers":[
        {
            "category":"Government",
            "subcategory":"Office",
            "type":"Public Place"
        },
        {
            "category":"Health Services",
            "subcategory":"Doctor",
            "type":"Services"
        }
    ],
    "sg:phone":"+1 414 286 8620",
    "sg:postcode":"53204",
    "sg:province":"WI",
    "sg:tags":[
        "city",
        "program",
        "center"
    ],
    "wof:name":"Southside Health Center",
    "wof:placetype":"venue"
},
  "geometry": {"coordinates":[-87.942362,43.013424],"type":"Point"}
}