{
  "type": "Feature",
  "properties": {
    "addr:full":"5103 9th Street Rd Oshkosh WI 54904",
    "addr:housenumber":"5103",
    "addr:postcode":"54904",
    "addr:street":"9Th Street Rd",
    "iso:country":"US",
    "sg:address":"5103 9th Street Rd",
    "sg:city":"Oshkosh",
    "sg:phone":"+1 920 231 3782",
    "sg:postcode":"54904",
    "sg:province":"WI",
    "sg:tags":[
        "beef",
        "farm",
        "cash",
        "grain",
        "cattle",
        "feedlot"
    ],
    "wof:name":"Gunz Farms",
    "wof:placetype":"venue"
},
  "geometry": {"coordinates":[-88.66931599999999,44.011362],"type":"Point"}
}