{
  "type": "Feature",
  "properties": {
    "addr:full":"742 Basswood Ave Verona WI 53593",
    "addr:housenumber":"742",
    "addr:postcode":"53593",
    "addr:street":"Basswood Ave",
    "iso:country":"US",
    "sg:address":"742 Basswood Ave",
    "sg:city":"Verona",
    "sg:classifiers":[
        {
            "category":"Professional",
            "type":"Services"
        }
    ],
    "sg:phone":"+1 608 845 9545",
    "sg:postcode":"53593",
    "sg:province":"WI",
    "wof:name":"Herb- Delehanty",
    "wof:placetype":"venue"
},
  "geometry": {"coordinates":[-89.546646,42.996673],"type":"Point"}
}