{
  "type": "Feature",
  "properties": {
    "iso:country":"US",
    "sg:address":"5930 Duck Point Ln",
    "sg:city":"Tomahawk",
    "sg:classifiers":[
        {
            "category":"Professional",
            "type":"Services"
        }
    ],
    "sg:phone":"+1 715 453 1464",
    "sg:postcode":"54487",
    "sg:province":"WI",
    "wof:name":"Richard C Hipler",
    "wof:placetype":"venue"
},
  "geometry": {"coordinates":[-89.733801,45.503156],"type":"Point"}
}