{
  "type": "Feature",
  "properties": {
    "iso:country":"US",
    "sg:address":"513 N Bay Shore Dr",
    "sg:city":"Sister Bay",
    "sg:classifiers":[
        {
            "category":"Shopping",
            "subcategory":"Clothing, Apparel, & Fashions",
            "type":"Retail Goods"
        }
    ],
    "sg:phone":"+1 920 854 6040",
    "sg:postcode":"54234",
    "sg:province":"WI",
    "wof:name":"Baywear Too",
    "wof:placetype":"venue"
},
  "geometry": {"coordinates":[-87.122253,45.188097],"type":"Point"}
}