{
  "type": "Feature",
  "properties": {
    "iso:country":"US",
    "sg:address":"415 Oak St",
    "sg:city":"River Falls",
    "sg:classifiers":[
        {
            "category":"Professional",
            "subcategory":"Management & Consulting",
            "type":"Services"
        }
    ],
    "sg:phone":"+1 715 426 3200",
    "sg:postcode":"54022",
    "sg:province":"WI",
    "wof:name":"Dominion Enterprises",
    "wof:placetype":"venue"
},
  "geometry": {"coordinates":[-92.625361,44.855163],"type":"Point"}
}