{
  "type": "Feature",
  "properties": {
    "addr:full":"6056 Bisson Rd Glen Flora WI 54526",
    "addr:postcode":"6056;54526",
    "addr:street":"Bisson Rd",
    "iso:country":"US",
    "sg:address":"6056 Bisson Rd",
    "sg:city":"Glen Flora",
    "sg:classifiers":[
        {
            "category":"Food & Beverages",
            "subcategory":"Groceries & Convenience Stores",
            "type":"Retail Goods"
        }
    ],
    "sg:phone":"+1 715 322 5656",
    "sg:postcode":"54526",
    "sg:province":"WI",
    "wof:name":"Big Bear Amusements",
    "wof:placetype":"venue"
},
  "geometry": {"coordinates":[-90.82244900000001,45.50895],"type":"Point"}
}