{
  "type": "Feature",
  "properties": {
    "addr:full":"15700 W Bluemound Rd Brookfield WI 53005",
    "addr:housenumber":"15700",
    "addr:postcode":"53005",
    "addr:street":"W Bluemound Rd",
    "iso:country":"US",
    "sg:address":"15700 W Bluemound Rd",
    "sg:city":"Brookfield",
    "sg:classifiers":[
        {
            "category":"Professional",
            "subcategory":"Lawyer & Legal Services",
            "type":"Services"
        }
    ],
    "sg:phone":"+1 262 782 7984",
    "sg:postcode":"53005",
    "sg:province":"WI",
    "sg:tags":[
        "attorney"
    ],
    "wof:name":"Action Estate Planning",
    "wof:placetype":"venue"
},
  "geometry": {"coordinates":[-88.108503,43.036224],"type":"Point"}
}