{
  "type": "Feature",
  "properties": {
    "iso:country":"US",
    "sg:address":"11321 W Greenfield Ave",
    "sg:city":"Milwaukee",
    "sg:classifiers":[
        {
            "category":"Retail",
            "subcategory":"Auto Repair",
            "type":"Services"
        }
    ],
    "sg:phone":"+1 414 774 8863",
    "sg:postcode":"53214",
    "sg:province":"WI",
    "sg:tags":[
        "general"
    ],
    "wof:name":"Auto Diagnostics Inc",
    "wof:placetype":"venue"
},
  "geometry": {"coordinates":[-88.054379,43.016333],"type":"Point"}
}