{
  "type": "Feature",
  "properties": {
    "iso:country":"US",
    "sg:address":"5011 N Berkeley Blvd",
    "sg:city":"Milwaukee",
    "sg:classifiers":[
        {
            "category":"Professional",
            "subcategory":"Business Services",
            "type":"Services"
        }
    ],
    "sg:phone":"+1 414 332 4872",
    "sg:postcode":"53217",
    "sg:province":"WI",
    "wof:name":"Peter Jones",
    "wof:placetype":"venue"
},
  "geometry": {"coordinates":[-87.905739,43.109262],"type":"Point"}
}