{
  "type": "Feature",
  "properties": {
    "iso:country":"US",
    "sg:address":"2493 Co Rd Es",
    "sg:city":"East Troy",
    "sg:classifiers":[
        {
            "category":"Professional",
            "subcategory":"Management & Consulting",
            "type":"Services"
        }
    ],
    "sg:phone":"+1 262 642 3303",
    "sg:postcode":"53120",
    "sg:province":"WI",
    "sg:tags":[
        "agricultural",
        "consultant"
    ],
    "wof:name":"Michael Fields Agricultural",
    "wof:placetype":"venue"
},
  "geometry": {"coordinates":[-88.426939,42.783009],"type":"Point"}
}