{
  "type": "Feature",
  "properties": {
    "addr:full":"9089 Bicentennial Rd Wautoma WI 54982",
    "addr:housenumber":"9089",
    "addr:postcode":"54982",
    "addr:street":"Bicentennial Rd",
    "iso:country":"US",
    "sg:address":"9089 Bicentennial Rd",
    "sg:city":"Wautoma",
    "sg:classifiers":[
        {
            "category":"Retail",
            "subcategory":"Animal Services",
            "type":"Services"
        }
    ],
    "sg:phone":"+1 920 787 2973",
    "sg:postcode":"54982",
    "sg:province":"WI",
    "wof:name":"Lil Macs Kennel",
    "wof:placetype":"venue"
},
  "geometry": {"coordinates":[-89.33434099999999,44.089839],"type":"Point"}
}