{
  "type": "Feature",
  "properties": {
    "iso:country":"US",
    "sg:address":"1219 Appleton Rd",
    "sg:city":"Menasha",
    "sg:classifiers":[
        {
            "category":"Recreation",
            "subcategory":"Arcade",
            "type":"Entertainment"
        }
    ],
    "sg:phone":"+1 920 722 1233",
    "sg:postcode":"54952",
    "sg:province":"WI",
    "sg:tags":[
        "device",
        "operator",
        "machine",
        "vending",
        "amusement"
    ],
    "wof:name":"Amusement Devices Inc",
    "wof:placetype":"venue"
},
  "geometry": {"coordinates":[-88.426371,44.223439],"type":"Point"}
}