{
  "type": "Feature",
  "properties": {
    "iso:country":"US",
    "sg:address":"245 W Main St",
    "sg:city":"Hilbert",
    "sg:classifiers":[
        {
            "category":"Bars & Pubs",
            "type":"Food & Drink"
        }
    ],
    "sg:phone":"+1 920 853 3017",
    "sg:postcode":"54129",
    "sg:province":"WI",
    "wof:name":"Who's The Boss",
    "wof:placetype":"venue"
},
  "geometry": {"coordinates":[-88.157285,44.139316],"type":"Point"}
}