{
  "type": "Feature",
  "properties": {
    "iso:country":"US",
    "sg:address":"1707 N Prospect Ave",
    "sg:city":"Milwaukee",
    "sg:classifiers":[
        {
            "category":"Banks & Credit Unions",
            "subcategory":"Investment Brokerage",
            "type":"Services"
        }
    ],
    "sg:phone":"+1 414 277 1435",
    "sg:postcode":"53202",
    "sg:province":"WI",
    "sg:tags":[
        "advice"
    ],
    "wof:name":"Kademian Financial Group",
    "wof:placetype":"venue"
},
  "geometry": {"coordinates":[-87.890299,43.05335],"type":"Point"}
}