{
  "type": "Feature",
  "properties": {
    "iso:country":"US",
    "sg:address":"2705 E Washington Ave",
    "sg:city":"Madison",
    "sg:classifiers":[
        {
            "category":"Government",
            "subcategory":"Office",
            "type":"Public Place"
        },
        {
            "category":"Health Services",
            "subcategory":"Medical Lab",
            "type":"Services"
        }
    ],
    "sg:phone":"+1 608 243 2351",
    "sg:postcode":"53704",
    "sg:province":"WI",
    "sg:tags":[
        "city",
        "program",
        "laboratory"
    ],
    "wof:name":"Madison Dept of Public Health",
    "wof:placetype":"venue"
},
  "geometry": {"coordinates":[-89.347244,43.101833],"type":"Point"}
}