{
  "type": "Feature",
  "properties": {
    "addr:full":"1017 2nd Ave Gleason WI 54435",
    "addr:housenumber":"1017",
    "addr:postcode":"54435",
    "addr:street":"2Nd Ave",
    "iso:country":"US",
    "sg:address":"1017 2nd Ave",
    "sg:city":"Gleason",
    "sg:classifiers":[
        {
            "category":"Freight",
            "type":"Transportation"
        }
    ],
    "sg:phone":"+1 715 873 4830",
    "sg:postcode":"54435",
    "sg:province":"WI",
    "sg:tags":[
        "hauling",
        "trucking"
    ],
    "wof:name":"Pat Walker Trucking",
    "wof:placetype":"venue"
},
  "geometry": {"coordinates":[-89.467995,45.314879],"type":"Point"}
}