{
  "type": "Feature",
  "properties": {
    "addr:full":"4606 Tonyawatha Trl Madison WI 53716",
    "addr:housenumber":"4606",
    "addr:postcode":"53716",
    "addr:street":"Tonyawatha Trl",
    "iso:country":"US",
    "sg:address":"4606 Tonyawatha Trl",
    "sg:city":"Madison",
    "sg:classifiers":[
        {
            "category":"Professional",
            "subcategory":"Business Services",
            "type":"Services"
        }
    ],
    "sg:phone":"+1 608 221 3845",
    "sg:postcode":"53716",
    "sg:province":"WI",
    "wof:name":"Kuzma Enterprises LLC",
    "wof:placetype":"venue"
},
  "geometry": {"coordinates":[-89.338964,43.071415],"type":"Point"}
}