{
  "type": "Feature",
  "properties": {
    "iso:country":"US",
    "sg:address":"1145 N Military Ave",
    "sg:city":"Green Bay",
    "sg:classifiers":[
        {
            "category":"Retail",
            "subcategory":"Repair Shop",
            "type":"Services"
        }
    ],
    "sg:phone":"+1 920 499 8898",
    "sg:postcode":"54303",
    "sg:province":"WI",
    "sg:tags":[
        "leather"
    ],
    "wof:name":"Great Lake Taxidermy",
    "wof:placetype":"venue"
},
  "geometry": {"coordinates":[-88.052384,44.540035],"type":"Point"}
}