{
  "type": "Feature",
  "properties": {
    "iso:country":"US",
    "sg:address":"1011 S Main St",
    "sg:city":"Necedah",
    "sg:classifiers":[
        {
            "category":"Autos & Motor Vehicles",
            "subcategory":"Automobile Sales",
            "type":"Retail Goods"
        }
    ],
    "sg:phone":"+1 608 565 2857",
    "sg:postcode":"54646",
    "sg:province":"WI",
    "wof:name":"Mid-State Snowmobile Salvage",
    "wof:placetype":"venue"
},
  "geometry": {"coordinates":[-90.067183,44.015141],"type":"Point"}
}