{
  "type": "Feature",
  "properties": {
    "iso:country":"US",
    "sg:address":"3599 Co Rd CC",
    "sg:city":"Maiden Rock",
    "sg:classifiers":[
        {
            "category":"Retail",
            "subcategory":"Auto Repair",
            "type":"Services"
        }
    ],
    "sg:phone":"+1 715 647 3585",
    "sg:postcode":"54750",
    "sg:province":"WI",
    "sg:tags":[
        "general"
    ],
    "wof:name":"Salem Town Garage",
    "wof:placetype":"venue"
},
  "geometry": {"coordinates":[-92.256529,44.667137],"type":"Point"}
}