{
  "type": "Feature",
  "properties": {
    "addr:full":"35 University Houses Madison WI 53705",
    "addr:housenumber":"35",
    "addr:postcode":"53705",
    "addr:street":"University Houses",
    "iso:country":"US",
    "sg:address":"35 University Houses",
    "sg:city":"Madison",
    "sg:classifiers":[
        {
            "category":"Social Services",
            "subcategory":"Child Care",
            "type":"Services"
        }
    ],
    "sg:phone":"+1 608 238 3955",
    "sg:postcode":"53705",
    "sg:province":"WI",
    "sg:tags":[
        "kindergarten",
        "academic",
        "school",
        "day"
    ],
    "wof:name":"University Houses Nursery Schl",
    "wof:placetype":"venue"
},
  "geometry": {"coordinates":[-89.43810000000001,43.085276],"type":"Point"}
}