{
  "type": "Feature",
  "properties": {
    "iso:country":"US",
    "sg:address":"5370 Fisher Rd",
    "sg:city":"Wisconsin Rapids",
    "sg:classifiers":[
        {
            "category":"Farming",
            "subcategory":"Livestock Farm",
            "type":"Manufacturing & Wholesale Goods"
        }
    ],
    "sg:phone":"+1 715 421 2996",
    "sg:postcode":"54495",
    "sg:province":"WI",
    "sg:tags":[
        "corn",
        "grain",
        "cash"
    ],
    "wof:name":"Armagost John",
    "wof:placetype":"venue"
},
  "geometry": {"coordinates":[-89.895356,44.444892],"type":"Point"}
}