{
  "type": "Feature",
  "properties": {
    "iso:country":"US",
    "sg:address":"10210 Rangeline Rd",
    "sg:city":"Wisconsin Rapids",
    "sg:classifiers":[
        {
            "category":"Professional",
            "subcategory":"Management & Consulting",
            "type":"Services"
        }
    ],
    "sg:phone":"+1 715 325 2470",
    "sg:postcode":"54494",
    "sg:province":"WI",
    "sg:tags":[
        "retail",
        "direct",
        "sales"
    ],
    "wof:name":"Cupboard Wagon",
    "wof:placetype":"venue"
},
  "geometry": {"coordinates":[-89.84403399999999,44.302664],"type":"Point"}
}