{
  "type": "Feature",
  "properties": {
    "iso:country":"US",
    "sg:address":"406 S Park St",
    "sg:city":"Madison",
    "sg:classifiers":[
        {
            "category":"Restaurant",
            "type":"Food & Drink"
        }
    ],
    "sg:phone":"+1 608 251 3000",
    "sg:postcode":"53715",
    "sg:province":"WI",
    "sg:tags":[
        "eating"
    ],
    "wof:name":"Kosher & Subs Inc",
    "wof:placetype":"venue"
},
  "geometry": {"coordinates":[-89.400834,43.062653],"type":"Point"}
}