{
  "type": "Feature",
  "properties": {
    "iso:country":"US",
    "sg:address":"6405 Lake Rd",
    "sg:city":"Stone Lake",
    "sg:classifiers":[
        {
            "category":"Building & Trades",
            "subcategory":"Plumbing",
            "type":"Services"
        }
    ],
    "sg:phone":"+1 715 865 2826",
    "sg:postcode":"54876",
    "sg:province":"WI",
    "sg:tags":[
        "heating",
        "contractor"
    ],
    "wof:name":"Stone Lake Heating & Sheet Mtl",
    "wof:placetype":"venue"
},
  "geometry": {"coordinates":[-91.561669,45.866428],"type":"Point"}
}