{
  "type": "Feature",
  "properties": {
    "iso:country":"US",
    "sg:address":"400 N Executive Dr",
    "sg:city":"Brookfield",
    "sg:classifiers":[
        {
            "category":"Professional",
            "subcategory":"Lawyer & Legal Services",
            "type":"Services"
        }
    ],
    "sg:phone":"+1 262 789 2735",
    "sg:postcode":"53005",
    "sg:province":"WI",
    "sg:tags":[
        "attorney",
        "practice",
        "general"
    ],
    "wof:name":"Capwell & Berthelsen",
    "wof:placetype":"venue"
},
  "geometry": {"coordinates":[-88.114724,43.035749],"type":"Point"}
}