{
  "type": "Feature",
  "properties": {
    "iso:country":"US",
    "sg:address":"1616 Pierce Ave",
    "sg:city":"Marinette",
    "sg:classifiers":[
        {
            "category":"Professional",
            "subcategory":"Accounting & Tax Preparation",
            "type":"Services"
        }
    ],
    "sg:phone":"+1 715 735 9450",
    "sg:postcode":"54143",
    "sg:province":"WI",
    "sg:tags":[
        "return",
        "filing"
    ],
    "wof:name":"Hanneman Bookkeeping & Tax Svc",
    "wof:placetype":"venue"
},
  "geometry": {"coordinates":[-87.629419,45.088759],"type":"Point"}
}