{
  "type": "Feature",
  "properties": {
    "iso:country":"US",
    "sg:address":"10926 W Co Rd B",
    "sg:city":"Hayward",
    "sg:classifiers":[
        {
            "category":"Food & Beverages",
            "subcategory":"Specialty",
            "type":"Retail Goods"
        },
        {
            "category":"Shopping",
            "subcategory":"Gifts & Souvenirs",
            "type":"Retail Goods"
        }
    ],
    "sg:phone":"+1 715 462 4336",
    "sg:postcode":"54843",
    "sg:province":"WI",
    "sg:tags":[
        "gourmet",
        "shop"
    ],
    "wof:name":"Ma Good's Marinated Fish",
    "wof:placetype":"venue"
},
  "geometry": {"coordinates":[-91.21277000000001,45.982125],"type":"Point"}
}