{
  "type": "Feature",
  "properties": {
    "iso:country":"US",
    "sg:address":"2175 Main St",
    "sg:city":"Green Bay",
    "sg:classifiers":[
        {
            "category":"Retail",
            "subcategory":"Auto Repair",
            "type":"Services"
        }
    ],
    "sg:phone":"+1 920 469 1960",
    "sg:postcode":"54302",
    "sg:province":"WI",
    "sg:tags":[
        "repairing",
        "automobile"
    ],
    "sg:website":"www.tiresplus.com",
    "wof:name":"Tires Plus",
    "wof:placetype":"venue"
},
  "geometry": {"coordinates":[-87.971426,44.486573],"type":"Point"}
}