{
  "type": "Feature",
  "properties": {
    "iso:country":"US",
    "sg:address":"3056 S Delaware Ave",
    "sg:city":"Milwaukee",
    "sg:classifiers":[
        {
            "category":"Shopping",
            "subcategory":"Used Merchandise",
            "type":"Retail Goods"
        }
    ],
    "sg:phone":"+1 414 481 1522",
    "sg:postcode":"53207",
    "sg:province":"WI",
    "sg:tags":[
        "antique"
    ],
    "wof:name":"Calico Cat Antiques",
    "wof:placetype":"venue"
},
  "geometry": {"coordinates":[-87.878797,42.98908],"type":"Point"}
}