{
  "type": "Feature",
  "properties": {
    "iso:country":"US",
    "sg:address":"18759 Icebox Rd",
    "sg:city":"Sparta",
    "sg:classifiers":[
        {
            "category":"Health Services",
            "subcategory":"Doctor",
            "type":"Services"
        }
    ],
    "sg:phone":"+1 608 269 7370",
    "sg:postcode":"54656",
    "sg:province":"WI",
    "sg:tags":[
        "physician",
        "surgeon"
    ],
    "wof:name":"Axle Doctor",
    "wof:placetype":"venue"
},
  "geometry": {"coordinates":[-90.850178,43.914643],"type":"Point"}
}