{
  "type": "Feature",
  "properties": {
    "iso:country":"US",
    "sg:address":"2691 Calaway Dr",
    "sg:city":"Green Bay",
    "sg:classifiers":[
        {
            "category":"Retail",
            "subcategory":"Auto Repair",
            "type":"Services"
        }
    ],
    "sg:phone":"+1 920 405 9788",
    "sg:postcode":"54313",
    "sg:province":"WI",
    "sg:tags":[
        "repairing",
        "automobile"
    ],
    "wof:name":"Airport Auto & Truck Repair",
    "wof:placetype":"venue"
},
  "geometry": {"coordinates":[-88.110173,44.489732],"type":"Point"}
}