{
  "type": "Feature",
  "properties": {
    "iso:country":"US",
    "sg:address":"1851 Division St",
    "sg:city":"East Troy",
    "sg:classifiers":[
        {
            "category":"Professional",
            "type":"Services"
        }
    ],
    "sg:phone":"+1 262 642 3864",
    "sg:postcode":"53120",
    "sg:province":"WI",
    "wof:name":"Kathy A Lee",
    "wof:placetype":"venue"
},
  "geometry": {"coordinates":[-88.405852,42.793695],"type":"Point"}
}