{
  "type": "Feature",
  "properties": {
    "iso:country":"US",
    "sg:address":"200 William St",
    "sg:city":"Mazomanie",
    "sg:classifiers":[
        {
            "category":"Building & Trades",
            "subcategory":"Plumbing",
            "type":"Services"
        }
    ],
    "sg:phone":"+1 608 795 2741",
    "sg:postcode":"53506",
    "sg:province":"WI",
    "sg:tags":[
        "contractor"
    ],
    "wof:name":"AC Lindley & Sons Inc",
    "wof:placetype":"venue"
},
  "geometry": {"coordinates":[-90.328828,43.179459],"type":"Point"}
}