{
  "type": "Feature",
  "properties": {
    "iso:country":"US",
    "sg:address":"351 Edwards Blvd",
    "sg:city":"Lake Geneva",
    "sg:classifiers":[
        {
            "category":"Shopping",
            "subcategory":"Pharmacy",
            "type":"Retail Goods"
        }
    ],
    "sg:phone":"+1 262 248 8296",
    "sg:postcode":"53147",
    "sg:province":"WI",
    "wof:name":"Walgreens",
    "wof:placetype":"venue"
},
  "geometry": {"coordinates":[-88.41179700000001,42.582274],"type":"Point"}
}