{
  "type": "Feature",
  "properties": {
    "iso:country":"US",
    "sg:address":"3601 Oregon St",
    "sg:city":"Oshkosh",
    "sg:classifiers":[
        {
            "category":"Education",
            "subcategory":"Special Training",
            "type":"Public Place"
        }
    ],
    "sg:phone":"+1 920 424 0747",
    "sg:postcode":"54902",
    "sg:province":"WI",
    "sg:tags":[
        "aircraft",
        "school"
    ],
    "sg:website":"www.fvtc.edu",
    "wof:name":"Fox Valley Technical College",
    "wof:placetype":"venue"
},
  "geometry": {"coordinates":[-88.54294299999999,43.973402],"type":"Point"}
}