{
  "type": "Feature",
  "properties": {
    "iso:country":"US",
    "sg:address":"6744 School Rd",
    "sg:city":"Greenville",
    "sg:classifiers":[
        {
            "category":"Building & Trades",
            "subcategory":"Construction",
            "type":"Services"
        }
    ],
    "sg:phone":"+1 920 757 8856",
    "sg:postcode":"54942",
    "sg:province":"WI",
    "sg:tags":[
        "residential"
    ],
    "wof:name":"Jim McCarthy Construction",
    "wof:placetype":"venue"
},
  "geometry": {"coordinates":[-88.530766,44.287624],"type":"Point"}
}