{
  "type": "Feature",
  "properties": {
    "iso:country":"US",
    "sg:address":"3 S Main St",
    "sg:city":"Rice Lake",
    "sg:classifiers":[
        {
            "category":"Health Services",
            "subcategory":"Clinic",
            "type":"Services"
        }
    ],
    "sg:phone":"+1 715 736 1234",
    "sg:postcode":"54868",
    "sg:province":"WI",
    "wof:name":"Us Healthcare Compliance",
    "wof:placetype":"venue"
},
  "geometry": {"coordinates":[-91.733351,45.501631],"type":"Point"}
}