{
  "type": "Feature",
  "properties": {
    "iso:country":"US",
    "sg:address":"710 Center St",
    "sg:city":"Antigo",
    "sg:classifiers":[
        {
            "category":"Organizations",
            "subcategory":"Religious Organization",
            "type":"Services"
        }
    ],
    "sg:phone":"+1 715 623 2802",
    "sg:postcode":"54409",
    "sg:province":"WI",
    "wof:name":"Kingdom Hall Jehovah Witnesses",
    "wof:placetype":"venue"
},
  "geometry": {"coordinates":[-89.15357400000001,45.157764],"type":"Point"}
}