{
  "type": "Feature",
  "properties": {
    "iso:country":"US",
    "sg:address":"8108 Jackrabbit Ave",
    "sg:city":"Sparta",
    "sg:classifiers":[
        {
            "category":"Government",
            "subcategory":"Office",
            "type":"Public Place"
        }
    ],
    "sg:phone":"+1 608 269 5873",
    "sg:postcode":"54656",
    "sg:province":"WI",
    "sg:tags":[
        "city"
    ],
    "wof:name":"Leon Town Hall",
    "wof:placetype":"venue"
},
  "geometry": {"coordinates":[-90.82798099999999,43.889904],"type":"Point"}
}