{
  "type": "Feature",
  "properties": {
    "iso:country":"US",
    "sg:address":"3002 Windross Ln",
    "sg:city":"Little Suamico",
    "sg:classifiers":[
        {
            "category":"Professional",
            "subcategory":"Management & Consulting",
            "type":"Services"
        }
    ],
    "sg:phone":"+1 920 834 3668",
    "sg:postcode":"54141",
    "sg:province":"WI",
    "wof:name":"Countryland Damage Appraisers",
    "wof:placetype":"venue"
},
  "geometry": {"coordinates":[-87.926716,44.779739],"type":"Point"}
}