{
  "type": "Feature",
  "properties": {
    "iso:country":"US",
    "sg:address":"2740 Packerland Dr",
    "sg:city":"Green Bay",
    "sg:classifiers":[
        {
            "category":"Building & Trades",
            "subcategory":"Plumbing",
            "type":"Services"
        }
    ],
    "sg:phone":"+1 920 494 9123",
    "sg:postcode":"54313",
    "sg:province":"WI",
    "sg:tags":[
        "heating",
        "contractor"
    ],
    "wof:name":"Tempcon Inc",
    "wof:placetype":"venue"
},
  "geometry": {"coordinates":[-88.109345,44.487739],"type":"Point"}
}