{
  "type": "Feature",
  "properties": {
    "iso:country":"US",
    "sg:address":"2251 Washington Rd",
    "sg:city":"Stoughton",
    "sg:classifiers":[
        {
            "category":"Real Estate",
            "subcategory":"Real Estate Operator",
            "type":"Services"
        }
    ],
    "sg:phone":"+1 608 873 9071",
    "sg:postcode":"53589",
    "sg:province":"WI",
    "sg:tags":[
        "property",
        "lessor"
    ],
    "wof:name":"Glenn Hagen",
    "wof:placetype":"venue"
},
  "geometry": {"coordinates":[-89.131124,42.966895],"type":"Point"}
}