{
  "type": "Feature",
  "properties": {
    "iso:country":"US",
    "sg:address":"5338 Rainbow Dr",
    "sg:city":"Greendale",
    "sg:classifiers":[
        {
            "category":"Building & Trades",
            "subcategory":"Construction",
            "type":"Services"
        }
    ],
    "sg:phone":"+1 414 421 1600",
    "sg:postcode":"53129",
    "sg:province":"WI",
    "sg:tags":[
        "tile",
        "dealer",
        "contractor"
    ],
    "wof:name":"Mike's Tile Installation",
    "wof:placetype":"venue"
},
  "geometry": {"coordinates":[-87.985938,42.926625],"type":"Point"}
}