{
  "type": "Feature",
  "properties": {
    "iso:country":"US",
    "sg:address":"2200 W Applewood Ln",
    "sg:city":"Milwaukee",
    "sg:classifiers":[
        {
            "category":"Museum",
            "type":"Entertainment"
        }
    ],
    "sg:phone":"+1 414 351 5205",
    "sg:postcode":"53209",
    "sg:province":"WI",
    "sg:tags":[
        "gallery"
    ],
    "wof:name":"Light of Orit LLC",
    "wof:placetype":"venue"
},
  "geometry": {"coordinates":[-87.93759799999999,43.154086],"type":"Point"}
}