{
  "type": "Feature",
  "properties": {
    "iso:country":"US",
    "sg:address":"4355 Forest Ln",
    "sg:city":"Rhinelander",
    "sg:classifiers":[
        {
            "category":"Professional",
            "type":"Services"
        }
    ],
    "sg:phone":"+1 715 369 9668",
    "sg:postcode":"54501",
    "sg:province":"WI",
    "wof:name":"Electronic Guide Service Inc",
    "wof:placetype":"venue"
},
  "geometry": {"coordinates":[-89.47116,45.680313],"type":"Point"}
}