{
  "type": "Feature",
  "properties": {
    "iso:country":"US",
    "sg:address":"1004 6th St W",
    "sg:city":"Ashland",
    "sg:classifiers":[
        {
            "category":"Home & Garden",
            "subcategory":"Carpets & Floor Coverings",
            "type":"Retail Goods"
        }
    ],
    "sg:phone":"+1 715 682 2916",
    "sg:postcode":"54806",
    "sg:province":"WI",
    "wof:name":"Custom Carpet Inc",
    "wof:placetype":"venue"
},
  "geometry": {"coordinates":[-90.891194,46.583154],"type":"Point"}
}