{
  "type": "Feature",
  "properties": {
    "addr:full":"611 Adams St Fort Atkinson WI 53538",
    "addr:housenumber":"611",
    "addr:postcode":"53538",
    "addr:street":"Adams St",
    "iso:country":"US",
    "sg:address":"611 Adams St",
    "sg:city":"Fort Atkinson",
    "sg:classifiers":[
        {
            "category":"Manufacturing",
            "subcategory":"Retail Goods",
            "type":"Manufacturing & Wholesale Goods"
        }
    ],
    "sg:phone":"+1 920 568 8799",
    "sg:postcode":"53538",
    "sg:province":"WI",
    "sg:tags":[
        "manufacturer"
    ],
    "wof:name":"MATC Business Industry",
    "wof:placetype":"venue"
},
  "geometry": {"coordinates":[-88.840688,42.936973],"type":"Point"}
}