{
  "type": "Feature",
  "properties": {
    "iso:country":"US",
    "sg:address":"201 S Pearl St",
    "sg:city":"Green Bay",
    "sg:classifiers":[
        {
            "category":"Freight",
            "type":"Transportation"
        }
    ],
    "sg:phone":"+1 920 432 1414",
    "sg:postcode":"54303",
    "sg:province":"WI",
    "sg:tags":[
        "general"
    ],
    "sg:website":"www.kkwarehousing.com",
    "wof:name":"K & K Warehousing Inc",
    "wof:placetype":"venue"
},
  "geometry": {"coordinates":[-88.022266,44.513722],"type":"Point"}
}