{
  "type": "Feature",
  "properties": {
    "addr:full":"9935 Pleasant Rd Randolph WI 53956",
    "addr:housenumber":"9935",
    "addr:postcode":"53956",
    "addr:street":"Pleasant Rd",
    "iso:country":"US",
    "sg:address":"9935 Pleasant Rd",
    "sg:city":"Randolph",
    "sg:classifiers":[
        {
            "category":"Home & Garden",
            "subcategory":"Building Materials",
            "type":"Retail Goods"
        }
    ],
    "sg:phone":"+1 920 326 3348",
    "sg:postcode":"53956",
    "sg:province":"WI",
    "sg:tags":[
        "energy",
        "conservation",
        "prod"
    ],
    "sg:website":"www.advanceenergy.com",
    "wof:name":"Advanced Energy Control",
    "wof:placetype":"venue"
},
  "geometry": {"coordinates":[-88.986425,43.547963],"type":"Point"}
}