{
  "type": "Feature",
  "properties": {
    "addr:full":"4608 N 103rd St Milwaukee WI 53225",
    "addr:housenumber":"4608",
    "addr:postcode":"53225",
    "addr:street":"N 103Rd St",
    "iso:country":"US",
    "sg:address":"4608 N 103rd St",
    "sg:city":"Milwaukee",
    "sg:classifiers":[
        {
            "category":"Retail",
            "subcategory":"Laundry & Dry Cleaning",
            "type":"Services"
        }
    ],
    "sg:phone":"+1 414 462 0973",
    "sg:postcode":"53225",
    "sg:province":"WI",
    "sg:tags":[
        "garment",
        "agent"
    ],
    "wof:name":"Dryclean 249",
    "wof:placetype":"venue"
},
  "geometry": {"coordinates":[-88.040723,43.102813],"type":"Point"}
}