{
  "type": "Feature",
  "properties": {
    "addr:full":"2651 S Fish Hatchery Rd Fitchburg WI 53711",
    "addr:housenumber":"2651",
    "addr:postcode":"53711",
    "addr:street":"S Fish Hatchery Rd",
    "iso:country":"US",
    "sg:address":"2651 S Fish Hatchery Rd",
    "sg:city":"Fitchburg",
    "sg:classifiers":[
        {
            "category":"Communications",
            "subcategory":"Radio Station",
            "type":"Services"
        }
    ],
    "sg:phone":"+1 608 274 5450",
    "sg:postcode":"53711",
    "sg:province":"WI",
    "sg:tags":[
        "broadcast"
    ],
    "wof:name":"Wiba",
    "wof:placetype":"venue"
},
  "geometry": {"coordinates":[-89.42822,42.998476],"type":"Point"}
}