{
  "type": "Feature",
  "properties": {
    "iso:country":"US",
    "sg:address":"838 Bengal Rd",
    "sg:city":"Neenah",
    "sg:classifiers":[
        {
            "category":"Professional",
            "type":"Services"
        }
    ],
    "sg:phone":"+1 920 722 9970",
    "sg:postcode":"54956",
    "sg:province":"WI",
    "wof:name":"Communityfest-Neenah-Menash",
    "wof:placetype":"venue"
},
  "geometry": {"coordinates":[-88.474113,44.205507],"type":"Point"}
}