{
  "type": "Feature",
  "properties": {
    "iso:country":"US",
    "sg:address":"526 Stoughton Rd",
    "sg:city":"Edgerton",
    "sg:classifiers":[
        {
            "category":"Manufacturing",
            "subcategory":"Metals",
            "type":"Manufacturing & Wholesale Goods"
        }
    ],
    "sg:phone":"+1 608 884 9441",
    "sg:postcode":"53534",
    "sg:province":"WI",
    "sg:tags":[
        "steel",
        "clamp",
        "we",
        "industrial",
        "mfg",
        "stampings",
        "fabrication"
    ],
    "wof:name":"Bryant Fabrication Inc",
    "wof:placetype":"venue"
},
  "geometry": {"coordinates":[-89.081604,42.840784],"type":"Point"}
}