{
  "type": "Feature",
  "properties": {
    "iso:country":"US",
    "sg:address":"1425 S Commercial St",
    "sg:city":"Neenah",
    "sg:classifiers":[
        {
            "category":"Restaurant",
            "type":"Food & Drink"
        }
    ],
    "sg:phone":"+1 920 729 3720",
    "sg:postcode":"54956",
    "sg:province":"WI",
    "sg:tags":[
        "eating"
    ],
    "wof:name":"A &W Restaurants",
    "wof:placetype":"venue"
},
  "geometry": {"coordinates":[-88.46494,44.161222],"type":"Point"}
}