{
  "type": "Feature",
  "properties": {
    "addr:full":"1129 Glacier Hill Dr Madison WI 53714",
    "addr:housenumber":"1129",
    "addr:postcode":"53714",
    "addr:street":"Glacier Hill Dr",
    "iso:country":"US",
    "sg:address":"1129 Glacier Hill Dr",
    "sg:city":"Madison",
    "sg:classifiers":[
        {
            "category":"Professional",
            "subcategory":"Computer Services",
            "type":"Services"
        }
    ],
    "sg:phone":"+1 608 245 1475",
    "sg:postcode":"53714",
    "sg:province":"WI",
    "sg:tags":[
        "related"
    ],
    "wof:name":"Joseph Zitzelsberger",
    "wof:placetype":"venue"
},
  "geometry": {"coordinates":[-89.28930099999999,43.115435],"type":"Point"}
}