{
  "type": "Feature",
  "properties": {
    "iso:country":"US",
    "sg:address":"8102 Island Lake Rd",
    "sg:city":"Spooner",
    "sg:classifiers":[
        {
            "category":"Manufacturing",
            "subcategory":"Wood Products",
            "type":"Manufacturing & Wholesale Goods"
        }
    ],
    "sg:phone":"+1 715 635 5351",
    "sg:postcode":"54801",
    "sg:province":"WI",
    "sg:tags":[
        "mfg"
    ],
    "wof:name":"Posh Designs In Wood",
    "wof:placetype":"venue"
},
  "geometry": {"coordinates":[-91.93043,45.930053],"type":"Point"}
}