{
  "type": "Feature",
  "properties": {
    "iso:country":"US",
    "sg:address":"253 N 1st Ave",
    "sg:city":"Sturgeon Bay",
    "sg:classifiers":[
        {
            "category":"Wholesale",
            "subcategory":"Machinery & Supplies",
            "type":"Manufacturing & Wholesale Goods"
        },
        {
            "category":"Wholesale",
            "subcategory":"Durable Goods & Equipment",
            "type":"Manufacturing & Wholesale Goods"
        }
    ],
    "sg:phone":"+1 920 743 5799",
    "sg:postcode":"54235",
    "sg:province":"WI",
    "sg:tags":[
        "mfg",
        "parts",
        "tack",
        "representative",
        "manufacturer",
        "carpet"
    ],
    "wof:name":"Fal-Kon Enterprises",
    "wof:placetype":"venue"
},
  "geometry": {"coordinates":[-87.380224,44.835505],"type":"Point"}
}