{
  "type": "Feature",
  "properties": {
    "iso:country":"US",
    "sg:address":"540 Bus Park Cir",
    "sg:city":"Stoughton",
    "sg:classifiers":[
        {
            "category":"Manufacturing",
            "subcategory":"Printing",
            "type":"Manufacturing & Wholesale Goods"
        }
    ],
    "sg:phone":"+1 608 873 4500",
    "sg:postcode":"53589",
    "sg:province":"WI",
    "sg:tags":[
        "lithographic",
        "printer",
        "commercial"
    ],
    "sg:website":"www.printinghouseinc.com",
    "wof:name":"Printing House Inc",
    "wof:placetype":"venue"
},
  "geometry": {"coordinates":[-89.21472300000001,42.932259],"type":"Point"}
}