{
  "type": "Feature",
  "properties": {
    "addr:full":"318 2nd Ave W Durand WI 54736",
    "addr:housenumber":"318",
    "addr:postcode":"54736",
    "addr:street":"2Nd Ave W Durand",
    "iso:country":"US",
    "sg:address":"318 2nd Ave W",
    "sg:city":"Durand",
    "sg:classifiers":[
        {
            "category":"Personal",
            "type":"Services"
        }
    ],
    "sg:phone":"+1 715 672 8083",
    "sg:postcode":"54736",
    "sg:province":"WI",
    "sg:tags":[
        "shop",
        "beauty",
        "merchandise"
    ],
    "wof:name":"House Of Beauty",
    "wof:placetype":"venue"
},
  "geometry": {"coordinates":[-91.966669,44.628194],"type":"Point"}
}