{
  "type": "Feature",
  "properties": {
    "addr:full":"226 N Richmond St Appleton WI 54911",
    "addr:housenumber":"226",
    "addr:postcode":"54911",
    "addr:street":"N Richmond St",
    "iso:country":"US",
    "sg:address":"226 N Richmond St",
    "sg:city":"Appleton",
    "sg:classifiers":[
        {
            "category":"Autos & Motor Vehicles",
            "subcategory":"Fuel & Gas Station",
            "type":"Retail Goods"
        }
    ],
    "sg:phone":"+1 920 733 2241",
    "sg:postcode":"54911",
    "sg:province":"WI",
    "sg:tags":[
        "grocery",
        "station",
        "gasoline"
    ],
    "wof:name":"Speedway Superamerica LLC",
    "wof:placetype":"venue"
},
  "geometry": {"coordinates":[-88.41560800000001,44.263644],"type":"Point"}
}