{
  "type": "Feature",
  "properties": {
    "iso:country":"US",
    "sg:address":"805 W Historic Mitchell St",
    "sg:city":"Milwaukee",
    "sg:classifiers":[
        {
            "category":"Shopping",
            "subcategory":"Used Merchandise",
            "type":"Retail Goods"
        },
        {
            "category":"Autos & Motor Vehicles",
            "subcategory":"Automobile Sales",
            "type":"Retail Goods"
        }
    ],
    "sg:phone":"+1 414 647 9676",
    "sg:postcode":"53204",
    "sg:province":"WI",
    "sg:tags":[
        "furniture"
    ],
    "wof:name":"K & E Quality Pre Owned Furn",
    "wof:placetype":"venue"
},
  "geometry": {"coordinates":[-87.922658,43.012219],"type":"Point"}
}