{
  "type": "Feature",
  "properties": {
    "iso:country":"US",
    "sg:address":"107 High St",
    "sg:city":"Waupaca",
    "sg:classifiers":[
        {
            "category":"Real Estate",
            "subcategory":"Real Estate Operator",
            "type":"Services"
        }
    ],
    "sg:phone":"+1 715 258 8682",
    "sg:postcode":"54981",
    "sg:province":"WI",
    "sg:tags":[
        "building",
        "apartment"
    ],
    "wof:name":"Colonial Apartments",
    "wof:placetype":"venue"
},
  "geometry": {"coordinates":[-89.090114,44.357877],"type":"Point"}
}