{
  "type": "Feature",
  "properties": {
    "iso:country":"US",
    "sg:address":"4009 Triangle St",
    "sg:city":"Mc Farland",
    "sg:classifiers":[
        {
            "category":"Mining & Drilling",
            "type":"Manufacturing & Wholesale Goods"
        }
    ],
    "sg:phone":"+1 608 222 3657",
    "sg:postcode":"53558",
    "sg:province":"WI",
    "sg:tags":[
        "company",
        "oil"
    ],
    "wof:name":"Center For Terminal Co Madison",
    "wof:placetype":"venue"
},
  "geometry": {"coordinates":[-89.299804,43.039508],"type":"Point"}
}