{
  "type": "Feature",
  "properties": {
    "iso:country":"US",
    "sg:address":"28713 State Hwy 27",
    "sg:city":"Holcombe",
    "sg:classifiers":[
        {
            "category":"Personal",
            "subcategory":"Beauty Salon",
            "type":"Services"
        }
    ],
    "sg:phone":"+1 715 595 6550",
    "sg:postcode":"54745",
    "sg:province":"WI",
    "sg:tags":[
        "shop"
    ],
    "wof:name":"Hair Magic",
    "wof:placetype":"venue"
},
  "geometry": {"coordinates":[-91.110247,45.253267],"type":"Point"}
}