{
  "type": "Feature",
  "properties": {
    "addr:full":"7972 US Hwy 2 South Range WI 54874",
    "addr:housenumber":"7972",
    "addr:postcode":"54874",
    "addr:street":"Us Hwy 2",
    "iso:country":"US",
    "sg:address":"7972 US Hwy 2",
    "sg:city":"South Range",
    "sg:classifiers":[
        {
            "category":"Building & Trades",
            "subcategory":"Electrical",
            "type":"Services"
        }
    ],
    "sg:phone":"+1 715 398 5526",
    "sg:postcode":"54874",
    "sg:province":"WI",
    "sg:tags":[
        "electrical",
        "electric",
        "contractor"
    ],
    "wof:name":"Tri Star Electric Co",
    "wof:placetype":"venue"
},
  "geometry": {"coordinates":[-91.88866,46.603924],"type":"Point"}
}