{
  "type": "Feature",
  "properties": {
    "iso:country":"US",
    "sg:address":"1313 Frederick St",
    "sg:city":"Eau Claire",
    "sg:classifiers":[
        {
            "category":"Retail",
            "subcategory":"Laundry & Dry Cleaning",
            "type":"Services"
        }
    ],
    "sg:phone":"+1 715 379 3410",
    "sg:postcode":"54701",
    "sg:province":"WI",
    "wof:name":"All Business Solutions",
    "wof:placetype":"venue"
},
  "geometry": {"coordinates":[-91.486264,44.802286],"type":"Point"}
}