{
  "type": "Feature",
  "properties": {
    "iso:country":"US",
    "sg:address":"5596 Briarwood Rd",
    "sg:city":"Elkhorn",
    "sg:classifiers":[
        {
            "category":"Building & Trades",
            "subcategory":"Construction",
            "type":"Services"
        }
    ],
    "sg:phone":"+1 262 742 3194",
    "sg:postcode":"53121",
    "sg:province":"WI",
    "sg:tags":[
        "house"
    ],
    "wof:name":"CJ Hubertz Construction LLC",
    "wof:placetype":"venue"
},
  "geometry": {"coordinates":[-88.575477,42.750247],"type":"Point"}
}