{
  "type": "Feature",
  "properties": {
    "iso:country":"US",
    "sg:address":"1820 Koubenic Rd",
    "sg:city":"Three Lakes",
    "sg:classifiers":[
        {
            "category":"Building & Trades",
            "subcategory":"Construction",
            "type":"Services"
        }
    ],
    "sg:phone":"+1 715 546 3176",
    "sg:postcode":"54562",
    "sg:province":"WI",
    "sg:tags":[
        "home",
        "builder"
    ],
    "wof:name":"Blicharz Builders Inc",
    "wof:placetype":"venue"
},
  "geometry": {"coordinates":[-89.170613,45.82506],"type":"Point"}
}