{
  "type": "Feature",
  "properties": {
    "addr:full":"204 E Edgewater St Portage WI 53901",
    "addr:housenumber":"204",
    "addr:postcode":"53901",
    "addr:street":"E Edgewater St",
    "iso:country":"US",
    "sg:address":"204 E Edgewater St",
    "sg:city":"Portage",
    "sg:classifiers":[
        {
            "category":"Professional",
            "subcategory":"Employment Agencies",
            "type":"Services"
        }
    ],
    "sg:phone":"+1 608 742 1776",
    "sg:postcode":"53901",
    "sg:province":"WI",
    "sg:tags":[
        "temporary",
        "help"
    ],
    "wof:name":"A Life Style Service Inc",
    "wof:placetype":"venue"
},
  "geometry": {"coordinates":[-89.456602,43.540083],"type":"Point"}
}