{
  "type": "Feature",
  "properties": {
    "iso:country":"US",
    "sg:address":"5856 Co Rd R",
    "sg:city":"Denmark",
    "sg:classifiers":[
        {
            "category":"Retail",
            "subcategory":"Auto Repair",
            "type":"Services"
        }
    ],
    "sg:phone":"+1 920 863 2640",
    "sg:postcode":"54208",
    "sg:province":"WI",
    "sg:tags":[
        "body",
        "shop",
        "automotive"
    ],
    "wof:name":"Piontek Auto Body & Wrckr Svc",
    "wof:placetype":"venue"
},
  "geometry": {"coordinates":[-87.853974,44.372132],"type":"Point"}
}