{
  "type": "Feature",
  "properties": {
    "iso:country":"US",
    "sg:address":"1484 9th St",
    "sg:city":"Green Bay",
    "sg:classifiers":[
        {
            "category":"Organizations",
            "subcategory":"Religious Organization",
            "type":"Services"
        }
    ],
    "sg:phone":"+1 920 494 2534",
    "sg:postcode":"54304",
    "sg:province":"WI",
    "sg:tags":[
        "church"
    ],
    "wof:name":"St Agnes Parish",
    "wof:placetype":"venue"
},
  "geometry": {"coordinates":[-88.06799,44.515577],"type":"Point"}
}