{
  "type": "Feature",
  "properties": {
    "iso:country":"US",
    "sg:address":"2200 N Mayfair Rd",
    "sg:city":"Milwaukee",
    "sg:classifiers":[
        {
            "category":"Professional",
            "subcategory":"Lawyer & Legal Services",
            "type":"Services"
        }
    ],
    "sg:phone":"+1 414 342 3580",
    "sg:postcode":"53226",
    "sg:province":"WI",
    "sg:tags":[
        "attorney",
        "accident",
        "business",
        "family",
        "divorce",
        "practice",
        "damage",
        "property",
        "law",
        "bankruptcy"
    ],
    "sg:website":"http://www.figueroaandjackson.com",
    "wof:name":"Figueroa & Jackson",
    "wof:placetype":"venue"
},
  "geometry": {"coordinates":[-88.04750799999999,43.058159],"type":"Point"}
}