{
  "type": "Feature",
  "properties": {
    "iso:country":"US",
    "sg:address":"402 College St",
    "sg:city":"Milton",
    "sg:classifiers":[
        {
            "category":"Real Estate",
            "subcategory":"Real Estate Operator",
            "type":"Services"
        }
    ],
    "sg:phone":"+1 608 868 6849",
    "sg:postcode":"53563",
    "sg:province":"WI",
    "sg:tags":[
        "property",
        "lessor"
    ],
    "wof:name":"Warren Pennycook",
    "wof:placetype":"venue"
},
  "geometry": {"coordinates":[-88.943521,42.775728],"type":"Point"}
}