{
  "type": "Feature",
  "properties": {
    "addr:full":"9807 Bonnin Rd New London WI 54961",
    "addr:housenumber":"9807",
    "addr:postcode":"54961",
    "addr:street":"Bonnin Rd",
    "iso:country":"US",
    "sg:address":"9807 Bonnin Rd",
    "sg:city":"New London",
    "sg:classifiers":[
        {
            "category":"Shopping",
            "subcategory":"Catalog Store",
            "type":"Retail Goods"
        }
    ],
    "sg:phone":"+1 920 982 5776",
    "sg:postcode":"54961",
    "sg:province":"WI",
    "sg:tags":[
        "mail",
        "house"
    ],
    "wof:name":"Dave McNichols",
    "wof:placetype":"venue"
},
  "geometry": {"coordinates":[-88.675607,44.407261],"type":"Point"}
}