{
  "type": "Feature",
  "properties": {
    "iso:country":"US",
    "sg:address":"2083 Autumn Ln",
    "sg:city":"Kaukauna",
    "sg:classifiers":[
        {
            "category":"Organizations",
            "subcategory":"Religious Organization",
            "type":"Services"
        }
    ],
    "sg:phone":"+1 920 759 7424",
    "sg:postcode":"54130",
    "sg:province":"WI",
    "wof:name":"Saint Paul Lutheran Church",
    "wof:placetype":"venue"
},
  "geometry": {"coordinates":[-88.245878,44.258237],"type":"Point"}
}