{
  "type": "Feature",
  "properties": {
    "iso:country":"US",
    "sg:address":"7177 Co Rd I",
    "sg:city":"Fond Du Lac",
    "sg:classifiers":[
        {
            "category":"Professional",
            "type":"Services"
        }
    ],
    "sg:phone":"+1 920 921 2547",
    "sg:postcode":"54937",
    "sg:province":"WI",
    "wof:name":"Rings",
    "wof:placetype":"venue"
},
  "geometry": {"coordinates":[-88.534779,43.804865],"type":"Point"}
}