{
  "type": "Feature",
  "properties": {
    "iso:country":"US",
    "sg:address":"4207 N Prospect Ave",
    "sg:city":"Milwaukee",
    "sg:classifiers":[
        {
            "category":"Communications",
            "type":"Services"
        }
    ],
    "sg:phone":"+1 414 962 1705",
    "sg:postcode":"53211",
    "sg:province":"WI",
    "sg:tags":[
        "consultant",
        "engineer"
    ],
    "wof:name":"Lewis & Associates Inc",
    "wof:placetype":"venue"
},
  "geometry": {"coordinates":[-87.879959,43.093691],"type":"Point"}
}