{
  "type": "Feature",
  "properties": {
    "iso:country":"US",
    "sg:address":"7482 US Hwy 14",
    "sg:city":"Middleton",
    "sg:classifiers":[
        {
            "category":"Freight",
            "type":"Transportation"
        }
    ],
    "sg:phone":"+1 608 831 1969",
    "sg:postcode":"53562",
    "sg:province":"WI",
    "sg:tags":[
        "general"
    ],
    "wof:name":"Out Of Sight Storage LLC",
    "wof:placetype":"venue"
},
  "geometry": {"coordinates":[-89.567936,43.095242],"type":"Point"}
}