{
  "type": "Feature",
  "properties": {
    "addr:full":"4096 750th Ave Menomonie WI 54751",
    "addr:housenumber":"4096",
    "addr:postcode":"54751",
    "addr:street":"750Th Ave",
    "iso:country":"US",
    "sg:address":"4096 750th Ave",
    "sg:city":"Menomonie",
    "sg:phone":"+1 715 235 7403",
    "sg:postcode":"54751",
    "sg:province":"WI",
    "sg:tags":[
        "farm",
        "field",
        "corn",
        "crop"
    ],
    "wof:name":"Willard Hintz",
    "wof:placetype":"venue"
},
  "geometry": {"coordinates":[-91.95949400000001,44.951638],"type":"Point"}
}