{
  "type": "Feature",
  "properties": {
    "addr:full":"2222 N Mayfair Rd Milwaukee WI 53226",
    "addr:housenumber":"2222",
    "addr:postcode":"53226",
    "addr:street":"N Mayfair Rd",
    "iso:country":"US",
    "sg:address":"2222 N Mayfair Rd",
    "sg:city":"Milwaukee",
    "sg:classifiers":[
        {
            "category":"Professional",
            "subcategory":"Lawyer & Legal Services",
            "type":"Services"
        }
    ],
    "sg:phone":"+1 414 755 2400",
    "sg:postcode":"53226",
    "sg:province":"WI",
    "sg:tags":[
        "attorney",
        "law",
        "bankruptcy"
    ],
    "sg:website":"http://www.mydebtadvisors.com",
    "wof:name":"Debt Advisors",
    "wof:placetype":"venue"
},
  "geometry": {"coordinates":[-88.047517,43.058548],"type":"Point"}
}