{
  "type": "Feature",
  "properties": {
    "iso:country":"US",
    "sg:address":"29310 Hanscom Lake Trail Way",
    "sg:city":"Danbury",
    "sg:classifiers":[
        {
            "category":"Wholesale",
            "subcategory":"Seafood",
            "type":"Manufacturing & Wholesale Goods"
        }
    ],
    "sg:phone":"+1 715 259 3012",
    "sg:postcode":"54830",
    "sg:province":"WI",
    "wof:name":"Conroys Gourmet Foods",
    "wof:placetype":"venue"
},
  "geometry": {"coordinates":[-92.15047800000001,45.973486],"type":"Point"}
}