{
  "type": "Feature",
  "properties": {
    "addr:full":"4018 Velp Ave Green Bay WI 54313",
    "addr:postcode":"4018;54313",
    "addr:street":"Velp Ave",
    "iso:country":"US",
    "sg:address":"4018 Velp Ave",
    "sg:city":"Green Bay",
    "sg:classifiers":[
        {
            "category":"Retail",
            "subcategory":"Repair Shop",
            "type":"Services"
        }
    ],
    "sg:phone":"+1 920 434 1035",
    "sg:postcode":"54313",
    "sg:province":"WI",
    "wof:name":"Craigs Small Engine",
    "wof:placetype":"venue"
},
  "geometry": {"coordinates":[-88.07787,44.588579],"type":"Point"}
}