{
  "type": "Feature",
  "properties": {
    "iso:country":"US",
    "sg:address":"601 Schoenhaar Dr",
    "sg:city":"West Bend",
    "sg:classifiers":[
        {
            "category":"Building & Trades",
            "subcategory":"Plumbing",
            "type":"Services"
        }
    ],
    "sg:phone":"+1 262 338 1172",
    "sg:postcode":"53090",
    "sg:province":"WI",
    "sg:tags":[
        "plumbing",
        "heating",
        "contractor"
    ],
    "wof:name":"Albiero Plumbing Inc",
    "wof:placetype":"venue"
},
  "geometry": {"coordinates":[-88.157568,43.427228],"type":"Point"}
}