{
  "type": "Feature",
  "properties": {
    "iso:country":"US",
    "sg:address":"3950 N Downer Ave",
    "sg:city":"Milwaukee",
    "sg:classifiers":[
        {
            "category":"Professional",
            "subcategory":"Management & Consulting",
            "type":"Services"
        }
    ],
    "sg:phone":"+1 414 961 0183",
    "sg:postcode":"53211",
    "sg:province":"WI",
    "sg:tags":[
        "business"
    ],
    "wof:name":"Pegasus Consulting Group Inc",
    "wof:placetype":"venue"
},
  "geometry": {"coordinates":[-87.877496,43.088839],"type":"Point"}
}