{
  "type": "Feature",
  "properties": {
    "iso:country":"US",
    "sg:address":"103 W Balsam Ave",
    "sg:city":"Birchwood",
    "sg:classifiers":[
        {
            "category":"Organizations",
            "subcategory":"Religious Organization",
            "type":"Services"
        }
    ],
    "sg:phone":"+1 715 354 3147",
    "sg:postcode":"54817",
    "sg:province":"WI",
    "sg:tags":[
        "church"
    ],
    "wof:name":"United Methodist Chr-Birchwood",
    "wof:placetype":"venue"
},
  "geometry": {"coordinates":[-91.557232,45.653371],"type":"Point"}
}