{
  "type": "Feature",
  "properties": {
    "iso:country":"US",
    "sg:address":"493 Interchange N",
    "sg:city":"Lake Geneva",
    "sg:classifiers":[
        {
            "category":"Cinema",
            "subcategory":"Movie Rental",
            "type":"Entertainment"
        }
    ],
    "sg:phone":"+1 262 248 6599",
    "sg:postcode":"53147",
    "sg:province":"WI",
    "sg:tags":[
        "to",
        "video",
        "public",
        "general"
    ],
    "wof:name":"Video Galleries",
    "wof:placetype":"venue"
},
  "geometry": {"coordinates":[-88.428748,42.605384],"type":"Point"}
}