{
  "type": "Feature",
  "properties": {
    "addr:full":"913 Summit Ave Oconomowoc WI 53066",
    "addr:housenumber":"913",
    "addr:postcode":"53066",
    "addr:street":"Summit Ave",
    "iso:country":"US",
    "sg:address":"913 Summit Ave",
    "sg:city":"Oconomowoc",
    "sg:classifiers":[
        {
            "category":"Shopping",
            "subcategory":"Pharmacy",
            "type":"Retail Goods"
        }
    ],
    "sg:phone":"+1 262 569 8204",
    "sg:postcode":"53066",
    "sg:province":"WI",
    "wof:name":"Aurora Pharmacy Oconomowoc",
    "wof:placetype":"venue"
},
  "geometry": {"coordinates":[-88.481773,43.097123],"type":"Point"}
}