{
  "type": "Feature",
  "properties": {
    "iso:country":"US",
    "sg:address":"2871 2nd Ave S",
    "sg:city":"Wisconsin Rapids",
    "sg:classifiers":[
        {
            "category":"Building & Trades",
            "subcategory":"Construction",
            "type":"Services"
        }
    ],
    "sg:phone":"+1 715 423 3731",
    "sg:postcode":"54495",
    "sg:province":"WI",
    "sg:tags":[
        "concrete",
        "contractor"
    ],
    "wof:name":"Borgen Masonry",
    "wof:placetype":"venue"
},
  "geometry": {"coordinates":[-89.857461,44.370748],"type":"Point"}
}