{
  "type": "Feature",
  "properties": {
    "iso:country":"US",
    "sg:address":"7751 Bowers Rd",
    "sg:city":"Elkhorn",
    "sg:classifiers":[
        {
            "category":"Retail",
            "subcategory":"Animal Services",
            "type":"Services"
        }
    ],
    "sg:phone":"+1 262 642 2224",
    "sg:postcode":"53121",
    "sg:province":"WI",
    "wof:name":"Windspinner Farm Inc",
    "wof:placetype":"venue"
},
  "geometry": {"coordinates":[-88.445265,42.773381],"type":"Point"}
}