{
  "type": "Feature",
  "properties": {
    "iso:country":"US",
    "sg:address":"282 Stoney Brook Rd",
    "sg:city":"Appleton",
    "sg:classifiers":[
        {
            "category":"Professional",
            "type":"Services"
        }
    ],
    "sg:phone":"+1 920 733 5415",
    "sg:postcode":"54915",
    "sg:province":"WI",
    "wof:name":"Custom Flex LLC",
    "wof:placetype":"venue"
},
  "geometry": {"coordinates":[-88.35186400000001,44.249367],"type":"Point"}
}