{
  "type": "Feature",
  "properties": {
    "iso:country":"US",
    "sg:address":"6476 E Townline Rd",
    "sg:city":"Lake Geneva",
    "sg:phone":"+1 262 248 3106",
    "sg:postcode":"53147",
    "sg:province":"WI",
    "sg:tags":[
        "wheat",
        "farm",
        "corn",
        "crop",
        "field",
        "soybean"
    ],
    "wof:name":"Steve Norem",
    "wof:placetype":"venue"
},
  "geometry": {"coordinates":[-88.38691900000001,42.582083],"type":"Point"}
}