{
  "type": "Feature",
  "properties": {
    "iso:country":"US",
    "sg:address":"4183 4th Ave",
    "sg:city":"Hancock",
    "sg:classifiers":[
        {
            "category":"Bars & Pubs",
            "type":"Food & Drink"
        }
    ],
    "sg:phone":"+1 715 249 5348",
    "sg:postcode":"54943",
    "sg:province":"WI",
    "wof:name":"B J's",
    "wof:placetype":"venue"
},
  "geometry": {"coordinates":[-89.542586,44.127722],"type":"Point"}
}