{
  "type": "Feature",
  "properties": {
    "addr:full":"8135 W Tripoli Ave Milwaukee WI 53220",
    "addr:housenumber":"8135",
    "addr:postcode":"53220",
    "addr:street":"W Tripoli Ave",
    "iso:country":"US",
    "sg:address":"8135 W Tripoli Ave",
    "sg:city":"Milwaukee",
    "sg:classifiers":[
        {
            "category":"Shopping",
            "subcategory":"Clothing, Apparel, & Fashions",
            "type":"Retail Goods"
        }
    ],
    "sg:phone":"+1 414 604 2646",
    "sg:postcode":"53220",
    "sg:province":"WI",
    "sg:tags":[
        "tailor",
        "alterations-clothing"
    ],
    "wof:name":"Ab Tailors",
    "wof:placetype":"venue"
},
  "geometry": {"coordinates":[-88.014376,42.97467],"type":"Point"}
}