{
  "type": "Feature",
  "properties": {
    "iso:country":"US",
    "sg:address":"6479 State Rd 152",
    "sg:city":"Wautoma",
    "sg:classifiers":[
        {
            "category":"Professional",
            "type":"Services"
        },
        {
            "category":"Retail",
            "subcategory":"Animal Services",
            "type":"Services"
        }
    ],
    "sg:phone":"+1 920 787 1557",
    "sg:postcode":"54982",
    "sg:province":"WI",
    "sg:tags":[
        "establishment"
    ],
    "wof:name":"Animal House",
    "wof:placetype":"venue"
},
  "geometry": {"coordinates":[-89.217912,44.083379],"type":"Point"}
}