{
  "type": "Feature",
  "properties": {
    "iso:country":"US",
    "sg:address":"1436 E Forest Hill Ave",
    "sg:city":"Oak Creek",
    "sg:classifiers":[
        {
            "category":"Home & Garden",
            "subcategory":"Garden Supply",
            "type":"Retail Goods"
        }
    ],
    "sg:phone":"+1 414 766 1006",
    "sg:postcode":"53154",
    "sg:province":"WI",
    "wof:name":"A Daughters Garden",
    "wof:placetype":"venue"
},
  "geometry": {"coordinates":[-87.89604,42.89377],"type":"Point"}
}