{
  "type": "Feature",
  "properties": {
    "addr:full":"5141 Shirley Rd Denmark WI 54208",
    "addr:housenumber":"5141",
    "addr:postcode":"54208",
    "addr:street":"Shirley Rd",
    "iso:country":"US",
    "sg:address":"5141 Shirley Rd",
    "sg:city":"Denmark",
    "sg:classifiers":[
        {
            "category":"Farming",
            "subcategory":"Dairy Farm",
            "type":"Manufacturing & Wholesale Goods"
        }
    ],
    "sg:phone":"+1 920 863 8467",
    "sg:postcode":"54208",
    "sg:province":"WI",
    "wof:name":"Chris Lacenski",
    "wof:placetype":"venue"
},
  "geometry": {"coordinates":[-87.85547099999999,44.348909],"type":"Point"}
}