{
  "type": "Feature",
  "properties": {
    "addr:full":"7027 W Capitol Dr Milwaukee WI 53216",
    "addr:housenumber":"7027",
    "addr:postcode":"53216",
    "addr:street":"W Capitol Dr",
    "iso:country":"US",
    "sg:address":"7027 W Capitol Dr",
    "sg:city":"Milwaukee",
    "sg:classifiers":[
        {
            "category":"Health Services",
            "subcategory":"Clinic",
            "type":"Services"
        }
    ],
    "sg:phone":"+1 414 466 8930",
    "sg:postcode":"53216",
    "sg:province":"WI",
    "sg:tags":[
        "outpatient",
        "specialty"
    ],
    "sg:website":"https://www.QualityLifeServices.Org",
    "wof:name":"Quality Life Services, Inc",
    "wof:placetype":"venue"
},
  "geometry": {"coordinates":[-87.99973199999999,43.089907],"type":"Point"}
}