{
  "type": "Feature",
  "properties": {
    "addr:full":"8498 US Hwy 12 Black River Falls WI 54615",
    "addr:housenumber":"8498",
    "addr:postcode":"54615",
    "addr:street":"Us Hwy 12",
    "iso:country":"US",
    "sg:address":"8498 US Hwy 12",
    "sg:city":"Black River Falls",
    "sg:classifiers":[
        {
            "category":"Building & Trades",
            "subcategory":"Plumbing",
            "type":"Services"
        }
    ],
    "sg:phone":"+1 715 284 7613",
    "sg:postcode":"54615",
    "sg:province":"WI",
    "sg:tags":[
        "contractor"
    ],
    "wof:name":"Quality Heating Air",
    "wof:placetype":"venue"
},
  "geometry": {"coordinates":[-90.738544,44.230208],"type":"Point"}
}