{
  "type": "Feature",
  "properties": {
    "iso:country":"US",
    "sg:address":"1066 99th St",
    "sg:city":"Roberts",
    "sg:classifiers":[
        {
            "category":"Professional",
            "subcategory":"Business Services",
            "type":"Services"
        }
    ],
    "sg:phone":"+1 715 749 3955",
    "sg:postcode":"54023",
    "sg:province":"WI",
    "sg:tags":[
        "packaging"
    ],
    "wof:name":"Popey Packaging",
    "wof:placetype":"venue"
},
  "geometry": {"coordinates":[-92.603297,45.00736],"type":"Point"}
}