{
  "type": "Feature",
  "properties": {
    "iso:country":"US",
    "sg:address":"631 George St",
    "sg:city":"Green Bay",
    "sg:classifiers":[
        {
            "category":"Recreation",
            "type":"Entertainment"
        }
    ],
    "sg:phone":"+1 920 469 7773",
    "sg:postcode":"54302",
    "sg:province":"WI",
    "sg:tags":[
        "martial",
        "arts",
        "instruction"
    ],
    "wof:name":"Harris' Karate Academy LLC",
    "wof:placetype":"venue"
},
  "geometry": {"coordinates":[-87.989988,44.496094],"type":"Point"}
}