{
  "type": "Feature",
  "properties": {
    "iso:country":"US",
    "sg:address":"166 S Bristol St",
    "sg:city":"Sun Prairie",
    "sg:classifiers":[
        {
            "category":"Organizations",
            "subcategory":"Membership Organization",
            "type":"Services"
        }
    ],
    "sg:phone":"+1 608 837 0405",
    "sg:postcode":"53590",
    "sg:province":"WI",
    "wof:name":"Sun Prairie Emrgncy Fd Pantry",
    "wof:placetype":"venue"
},
  "geometry": {"coordinates":[-89.213952,43.181309],"type":"Point"}
}