{
  "type": "Feature",
  "properties": {
    "iso:country":"US",
    "sg:address":"651 Leavens Ave",
    "sg:city":"Sheboygan Falls",
    "sg:classifiers":[
        {
            "category":"Professional",
            "subcategory":"Management & Consulting",
            "type":"Services"
        }
    ],
    "sg:phone":"+1 920 467 6976",
    "sg:postcode":"53085",
    "sg:province":"WI",
    "sg:tags":[
        "agricultural",
        "analyst"
    ],
    "wof:name":"Renee R Setzer",
    "wof:placetype":"venue"
},
  "geometry": {"coordinates":[-87.82570699999999,43.732441],"type":"Point"}
}