{
  "type": "Feature",
  "properties": {
    "iso:country":"US",
    "sg:address":"212 E Mill Ave",
    "sg:city":"Cadott",
    "sg:classifiers":[
        {
            "category":"Building & Trades",
            "subcategory":"Construction",
            "type":"Services"
        }
    ],
    "sg:phone":"+1 715 289 3171",
    "sg:postcode":"54727",
    "sg:province":"WI",
    "sg:tags":[
        "general",
        "contractor"
    ],
    "wof:name":"RFS Construction",
    "wof:placetype":"venue"
},
  "geometry": {"coordinates":[-91.150758,44.955514],"type":"Point"}
}