{
  "type": "Feature",
  "properties": {
    "addr:full":"202 E Main St Coleman WI 54112",
    "addr:housenumber":"202",
    "addr:postcode":"54112",
    "addr:street":"E Main St",
    "iso:country":"US",
    "sg:address":"202 E Main St",
    "sg:city":"Coleman",
    "sg:classifiers":[
        {
            "category":"Banks & Credit Unions",
            "subcategory":"Bank",
            "type":"Services"
        }
    ],
    "sg:phone":"+1 920 897 2731",
    "sg:postcode":"54112",
    "sg:province":"WI",
    "wof:name":"Associated Bank",
    "wof:placetype":"venue"
},
  "geometry": {"coordinates":[-88.031712,45.065241],"type":"Point"}
}