{
  "type": "Feature",
  "properties": {
    "iso:country":"US",
    "sg:address":"7999 N Porcupine Lake Rd",
    "sg:city":"Lena",
    "sg:classifiers":[
        {
            "category":"Farming",
            "subcategory":"Dairy Farm",
            "type":"Manufacturing & Wholesale Goods"
        }
    ],
    "sg:phone":"+1 920 829 6232",
    "sg:postcode":"54139",
    "sg:province":"WI",
    "sg:tags":[
        "field",
        "corn",
        "grain",
        "cash",
        "crop"
    ],
    "wof:name":"Jeffrey Pytleski",
    "wof:placetype":"venue"
},
  "geometry": {"coordinates":[-88.14393099999999,44.955452],"type":"Point"}
}