{
  "type": "Feature",
  "properties": {
    "addr:full":"1220 Gohres St La Crosse WI 54603",
    "addr:housenumber":"1220",
    "addr:postcode":"54603",
    "addr:street":"Gohres St",
    "iso:country":"US",
    "sg:address":"1220 Gohres St",
    "sg:city":"La Crosse",
    "sg:classifiers":[
        {
            "category":"Building & Trades",
            "subcategory":"Plumbing",
            "type":"Services"
        }
    ],
    "sg:phone":"+1 608 779 4363",
    "sg:postcode":"54603",
    "sg:province":"WI",
    "sg:tags":[
        "conditioning",
        "air",
        "system",
        "contractor"
    ],
    "wof:name":"A Perfectemp Heating & Cooling",
    "wof:placetype":"venue"
},
  "geometry": {"coordinates":[-91.238636,43.849138],"type":"Point"}
}