{
  "type": "Feature",
  "properties": {
    "addr:full":"4209 S Howell Ave Milwaukee WI 53207",
    "addr:housenumber":"4209",
    "addr:postcode":"53207",
    "addr:street":"S Howell Ave",
    "iso:country":"US",
    "sg:address":"4209 S Howell Ave",
    "sg:city":"Milwaukee",
    "sg:classifiers":[
        {
            "category":"Wholesale",
            "subcategory":"Toys & Hobbies",
            "type":"Manufacturing & Wholesale Goods"
        }
    ],
    "sg:phone":"+1 414 744 6420",
    "sg:postcode":"53207",
    "sg:province":"WI",
    "sg:tags":[
        "stamp"
    ],
    "wof:name":"Adventure Stamps",
    "wof:placetype":"venue"
},
  "geometry": {"coordinates":[-87.90967999999999,42.966617],"type":"Point"}
}