{
  "type": "Feature",
  "properties": {
    "iso:country":"US",
    "sg:address":"4020 State Hwy 52",
    "sg:city":"Antigo",
    "sg:classifiers":[
        {
            "category":"Professional",
            "subcategory":"Business Services",
            "type":"Services"
        },
        {
            "category":"Wholesale",
            "subcategory":"Fruits & Vegetables",
            "type":"Manufacturing & Wholesale Goods"
        }
    ],
    "sg:phone":"+1 715 623 3359",
    "sg:postcode":"54409",
    "sg:province":"WI",
    "sg:tags":[
        "potato"
    ],
    "wof:name":"Spychalla Sales Inc Potatos",
    "wof:placetype":"venue"
},
  "geometry": {"coordinates":[-89.09466,45.176164],"type":"Point"}
}