{
  "type": "Feature",
  "properties": {
    "iso:country":"US",
    "sg:address":"28601 Co Hwy F",
    "sg:city":"Blue River",
    "sg:classifiers":[
        {
            "category":"Building & Trades",
            "subcategory":"Construction",
            "type":"Services"
        }
    ],
    "sg:phone":"+1 608 537 3500",
    "sg:postcode":"53518",
    "sg:province":"WI",
    "sg:tags":[
        "contractor"
    ],
    "wof:name":"Self Roofing & Construction",
    "wof:placetype":"venue"
},
  "geometry": {"coordinates":[-90.635749,43.283103],"type":"Point"}
}