{
  "type": "Feature",
  "properties": {
    "iso:country":"US",
    "sg:address":"140 S Park St",
    "sg:city":"Port Washington",
    "sg:classifiers":[
        {
            "category":"Manufacturing",
            "subcategory":"Tools & Machinery",
            "type":"Manufacturing & Wholesale Goods"
        }
    ],
    "sg:phone":"+1 262 284 1055",
    "sg:postcode":"53074",
    "sg:province":"WI",
    "sg:tags":[
        "physician",
        "surgeon"
    ],
    "wof:name":"Frontier Medical Products",
    "wof:placetype":"venue"
},
  "geometry": {"coordinates":[-87.88144699999999,43.38645],"type":"Point"}
}