{
  "type": "Feature",
  "properties": {
    "iso:country":"US",
    "sg:address":"4890 Van Wey Ln",
    "sg:city":"Ladysmith",
    "sg:classifiers":[
        {
            "category":"Organizations",
            "subcategory":"Religious Organization",
            "type":"Services"
        }
    ],
    "sg:phone":"+1 715 532 3704",
    "sg:postcode":"54848",
    "sg:province":"WI",
    "wof:name":"Northland Fllwship Church-Ifca",
    "wof:placetype":"venue"
},
  "geometry": {"coordinates":[-91.198259,45.464855],"type":"Point"}
}