{
  "type": "Feature",
  "properties": {
    "iso:country":"US",
    "sg:address":"19475 W North Ave",
    "sg:city":"Brookfield",
    "sg:classifiers":[
        {
            "category":"Health Services",
            "subcategory":"Doctor",
            "type":"Services"
        }
    ],
    "sg:phone":"+1 262 784 4406",
    "sg:postcode":"53045",
    "sg:province":"WI",
    "sg:tags":[
        "physician",
        "surgeon"
    ],
    "wof:name":"S Paul Kuwayama MD",
    "wof:placetype":"venue"
},
  "geometry": {"coordinates":[-88.156395,43.061318],"type":"Point"}
}