{
  "type": "Feature",
  "properties": {
    "addr:full":"1700 Livingstone Rd Hudson WI 54016",
    "addr:housenumber":"1700",
    "addr:postcode":"54016",
    "addr:street":"Livingstone Rd",
    "iso:country":"US",
    "sg:address":"1700 Livingstone Rd",
    "sg:city":"Hudson",
    "sg:classifiers":[
        {
            "category":"Building & Trades",
            "subcategory":"Equipment Rental",
            "type":"Services"
        }
    ],
    "sg:phone":"+1 715 386 8406",
    "sg:postcode":"54016",
    "sg:province":"WI",
    "sg:tags":[
        "rent",
        "mfg"
    ],
    "wof:name":"Mrl Rentals",
    "wof:placetype":"venue"
},
  "geometry": {"coordinates":[-92.735896,44.955339],"type":"Point"}
}