{
  "type": "Feature",
  "properties": {
    "iso:country":"US",
    "sg:address":"2340 Torke Rd",
    "sg:city":"Adell",
    "sg:classifiers":[
        {
            "category":"Building & Trades",
            "subcategory":"Landscaping Services",
            "type":"Services"
        }
    ],
    "sg:phone":"+1 920 994 8040",
    "sg:postcode":"53001",
    "sg:province":"WI",
    "sg:tags":[
        "landscape",
        "contractor"
    ],
    "wof:name":"Grand View Lawns & Landscaping",
    "wof:placetype":"venue"
},
  "geometry": {"coordinates":[-88.015772,43.622986],"type":"Point"}
}