{
  "type": "Feature",
  "properties": {
    "iso:country":"US",
    "sg:address":"8855 N 55th St",
    "sg:city":"Milwaukee",
    "sg:classifiers":[
        {
            "category":"Social Services",
            "subcategory":"Job Training",
            "type":"Services"
        },
        {
            "category":"Professional",
            "subcategory":"Engineering",
            "type":"Services"
        }
    ],
    "sg:phone":"+1 414 365 6400",
    "sg:postcode":"53223",
    "sg:province":"WI",
    "sg:tags":[
        "control",
        "consulting",
        "air",
        "engineer",
        "pollution"
    ],
    "sg:website":"http://www.anguil.com",
    "wof:name":"Global Technologies Div",
    "wof:placetype":"venue"
},
  "geometry": {"coordinates":[-87.979331,43.182062],"type":"Point"}
}