{
  "type": "Feature",
  "properties": {
    "iso:country":"US",
    "sg:address":"4281 Argosy Ct",
    "sg:city":"Madison",
    "sg:classifiers":[
        {
            "category":"Retail",
            "subcategory":"Repair Shop",
            "type":"Services"
        }
    ],
    "sg:phone":"+1 608 222 2245",
    "sg:postcode":"53714",
    "sg:province":"WI",
    "wof:name":"Advanced Restoration Cleaning",
    "wof:placetype":"venue"
},
  "geometry": {"coordinates":[-89.31079200000001,43.088133],"type":"Point"}
}