{
  "type": "Feature",
  "properties": {
    "iso:country":"US",
    "sg:address":"1322 Erie Ave",
    "sg:city":"Sheboygan",
    "sg:classifiers":[
        {
            "category":"Restaurant",
            "type":"Food & Drink"
        }
    ],
    "sg:menulink":"http://www.allmenus.com/wi/sheboygan/218353-burger-king/menu/",
    "sg:phone":"+1 920 459 7396",
    "sg:postcode":"53081",
    "sg:province":"WI",
    "sg:tags":[
        "american"
    ],
    "wof:name":"Burger King",
    "wof:placetype":"venue"
},
  "geometry": {"coordinates":[-87.72138099999999,43.756354],"type":"Point"}
}