{
  "type": "Feature",
  "properties": {
    "iso:country":"US",
    "sg:address":"6690 State Hwy 131",
    "sg:city":"Viola",
    "sg:classifiers":[
        {
            "category":"Shopping",
            "subcategory":"Used Merchandise",
            "type":"Retail Goods"
        }
    ],
    "sg:phone":"+1 608 627 1741",
    "sg:postcode":"54664",
    "sg:province":"WI",
    "sg:tags":[
        "material"
    ],
    "wof:name":"Miller Auto Wrecking",
    "wof:placetype":"venue"
},
  "geometry": {"coordinates":[-90.684955,43.487995],"type":"Point"}
}