{
  "type": "Feature",
  "properties": {
    "iso:country":"US",
    "sg:address":"1901 E Rawson Ave",
    "sg:city":"Oak Creek",
    "sg:classifiers":[
        {
            "category":"Home & Garden",
            "subcategory":"Garden Supply",
            "type":"Retail Goods"
        }
    ],
    "sg:phone":"+1 414 571 6565",
    "sg:postcode":"53154",
    "sg:province":"WI",
    "sg:tags":[
        "nurseryman",
        "nursery"
    ],
    "wof:name":"Mega Discount Nursery Inc",
    "wof:placetype":"venue"
},
  "geometry": {"coordinates":[-87.888547,42.915357],"type":"Point"}
}