{
  "type": "Feature",
  "properties": {
    "iso:country":"US",
    "sg:address":"2767 Woodstock Ct",
    "sg:city":"Green Bay",
    "sg:classifiers":[
        {
            "category":"Real Estate",
            "subcategory":"Real Estate Agent",
            "type":"Services"
        }
    ],
    "sg:phone":"+1 920 468 8870",
    "sg:postcode":"54311",
    "sg:province":"WI",
    "wof:name":"Maxim Realty Co",
    "wof:placetype":"venue"
},
  "geometry": {"coordinates":[-87.94572,44.483457],"type":"Point"}
}