{
  "type": "Feature",
  "properties": {
    "addr:full":"5300 S 76th St Greendale WI 53129",
    "addr:housenumber":"5300",
    "addr:postcode":"53129",
    "addr:street":"S 76Th St",
    "iso:country":"US",
    "sg:address":"5300 S 76th St",
    "sg:city":"Greendale",
    "sg:classifiers":[
        {
            "category":"Shopping",
            "subcategory":"Jewelry",
            "type":"Retail Goods"
        }
    ],
    "sg:phone":"+1 414 423 0465",
    "sg:postcode":"53129",
    "sg:province":"WI",
    "wof:name":"Rogers & Holland",
    "wof:placetype":"venue"
},
  "geometry": {"coordinates":[-88.008476,42.946837],"type":"Point"}
}