{
  "type": "Feature",
  "properties": {
    "iso:country":"US",
    "sg:address":"36173 Schansberg Rd",
    "sg:city":"Whitehall",
    "sg:classifiers":[
        {
            "category":"Government",
            "subcategory":"Office",
            "type":"Public Place"
        }
    ],
    "sg:phone":"+1 715 538 4262",
    "sg:postcode":"54773",
    "sg:province":"WI",
    "sg:tags":[
        "village"
    ],
    "wof:name":"Whitehall City Waste Water",
    "wof:placetype":"venue"
},
  "geometry": {"coordinates":[-91.291871,44.367156],"type":"Point"}
}