{
  "type": "Feature",
  "properties": {
    "addr:full":"12047 Little Trade Rd Grantsburg WI 54840",
    "addr:housenumber":"12047",
    "addr:postcode":"54840",
    "addr:street":"Little Trade Rd",
    "iso:country":"US",
    "sg:address":"12047 Little Trade Rd",
    "sg:city":"Grantsburg",
    "sg:classifiers":[
        {
            "category":"Real Estate",
            "subcategory":"Real Estate Agent",
            "type":"Services"
        }
    ],
    "sg:phone":"+1 715 488 2212",
    "sg:postcode":"54840",
    "sg:province":"WI",
    "sg:tags":[
        "manager",
        "appraiser"
    ],
    "wof:name":"C T Appraisals",
    "wof:placetype":"venue"
},
  "geometry": {"coordinates":[-92.606799,45.675712],"type":"Point"}
}