{
  "type": "Feature",
  "properties": {
    "iso:country":"US",
    "sg:address":"123 N Military Ave",
    "sg:city":"Green Bay",
    "sg:classifiers":[
        {
            "category":"Shopping",
            "subcategory":"Pharmacy",
            "type":"Retail Goods"
        }
    ],
    "sg:phone":"+1 920 494 3421",
    "sg:postcode":"54303",
    "sg:province":"WI",
    "wof:name":"Richard C Greene MD",
    "wof:placetype":"venue"
},
  "geometry": {"coordinates":[-88.059141,44.530948],"type":"Point"}
}