{
  "type": "Feature",
  "properties": {
    "iso:country":"US",
    "sg:address":"4763 Country Meadow Rd",
    "sg:city":"Brooklyn",
    "sg:classifiers":[
        {
            "category":"Real Estate",
            "subcategory":"Real Estate Agent",
            "type":"Services"
        },
        {
            "category":"Professional",
            "subcategory":"Business Services",
            "type":"Services"
        }
    ],
    "sg:phone":"+1 608 835 9777",
    "sg:postcode":"53521",
    "sg:province":"WI",
    "sg:tags":[
        "inspection"
    ],
    "sg:website":"www.ableonline.net",
    "wof:name":"Able Home Inspections-Madison",
    "wof:placetype":"venue"
},
  "geometry": {"coordinates":[-89.372564,42.876259],"type":"Point"}
}