{
  "type": "Feature",
  "properties": {
    "iso:country":"US",
    "sg:address":"11911 W Silver Spring Rd",
    "sg:city":"Milwaukee",
    "sg:classifiers":[
        {
            "category":"Home & Garden",
            "subcategory":"Garden Supply",
            "type":"Retail Goods"
        }
    ],
    "sg:phone":"+1 414 527 2300",
    "sg:postcode":"53225",
    "sg:province":"WI",
    "sg:tags":[
        "equipment",
        "snow",
        "removal"
    ],
    "sg:website":"www.am-truck.com",
    "wof:name":"A M Truck Equipment Inc",
    "wof:placetype":"venue"
},
  "geometry": {"coordinates":[-88.060981,43.119089],"type":"Point"}
}