{
  "type": "Feature",
  "properties": {
    "iso:country":"US",
    "sg:address":"7288 Broken Arrow Rd",
    "sg:city":"Conrath",
    "sg:classifiers":[
        {
            "category":"Farming",
            "subcategory":"Livestock Farm",
            "type":"Manufacturing & Wholesale Goods"
        }
    ],
    "sg:phone":"+1 715 452 5125",
    "sg:postcode":"54731",
    "sg:province":"WI",
    "sg:tags":[
        "cattle",
        "trucking"
    ],
    "wof:name":"Jim Meyer Inc",
    "wof:placetype":"venue"
},
  "geometry": {"coordinates":[-91.048671,45.335391],"type":"Point"}
}