{
  "type": "Feature",
  "properties": {
    "iso:country":"US",
    "sg:address":"1812 Pine Tree Ct",
    "sg:city":"Luxemburg",
    "sg:classifiers":[
        {
            "category":"Building & Trades",
            "subcategory":"Construction",
            "type":"Services"
        }
    ],
    "sg:phone":"+1 920 845 5755",
    "sg:postcode":"54217",
    "sg:province":"WI",
    "sg:tags":[
        "painter"
    ],
    "wof:name":"Thiry's Painting",
    "wof:placetype":"venue"
},
  "geometry": {"coordinates":[-87.70938700000001,44.523998],"type":"Point"}
}