{
  "type": "Feature",
  "properties": {
    "iso:country":"US",
    "sg:address":"324 Ilwaco Rd",
    "sg:city":"River Falls",
    "sg:classifiers":[
        {
            "category":"Professional",
            "subcategory":"Business Services",
            "type":"Services"
        }
    ],
    "sg:phone":"+1 715 425 6278",
    "sg:postcode":"54022",
    "sg:province":"WI",
    "wof:name":"Centurion Enterprises",
    "wof:placetype":"venue"
},
  "geometry": {"coordinates":[-92.73663,44.866024],"type":"Point"}
}