{
  "type": "Feature",
  "properties": {
    "addr:full":"11951 W Janesville Rd Hales Corners WI 53130",
    "addr:housenumber":"11951",
    "addr:postcode":"53130",
    "addr:street":"W Janesville Rd",
    "iso:country":"US",
    "sg:address":"11951 W Janesville Rd",
    "sg:city":"Hales Corners",
    "sg:classifiers":[
        {
            "category":"Social Services",
            "type":"Services"
        }
    ],
    "sg:phone":"+1 414 427 5700",
    "sg:postcode":"53130",
    "sg:province":"WI",
    "sg:tags":[
        "care",
        "center",
        "day"
    ],
    "wof:name":"Village Adult Day Ctr",
    "wof:placetype":"venue"
},
  "geometry": {"coordinates":[-88.063727,42.936071],"type":"Point"}
}