{
  "type": "Feature",
  "properties": {
    "iso:country":"US",
    "sg:address":"502 S Nine Mound Rd",
    "sg:city":"Verona",
    "sg:classifiers":[
        {
            "category":"Freight",
            "type":"Transportation"
        }
    ],
    "sg:phone":"+1 608 845 7980",
    "sg:postcode":"53593",
    "sg:province":"WI",
    "sg:tags":[
        "heavy",
        "equipment",
        "hauler"
    ],
    "wof:name":"Millers Trailer Services LLC",
    "wof:placetype":"venue"
},
  "geometry": {"coordinates":[-89.542374,42.985817],"type":"Point"}
}