{
  "type": "Feature",
  "properties": {
    "iso:country":"US",
    "sg:address":"3941 Emerald Dr",
    "sg:city":"Watertown",
    "sg:classifiers":[
        {
            "category":"Autos & Motor Vehicles",
            "subcategory":"Auto Supplies",
            "type":"Retail Goods"
        }
    ],
    "sg:phone":"+1 920 699 2977",
    "sg:postcode":"53094",
    "sg:province":"WI",
    "sg:tags":[
        "radiator"
    ],
    "wof:name":"Jim's Gas Tank & Radiator",
    "wof:placetype":"venue"
},
  "geometry": {"coordinates":[-88.718508,43.115826],"type":"Point"}
}