{
  "type": "Feature",
  "properties": {
    "iso:country":"US",
    "sg:address":"1340 W Towne Square Rd",
    "sg:city":"Thiensville",
    "sg:classifiers":[
        {
            "category":"Retail",
            "subcategory":"Portrait Studio",
            "type":"Services"
        }
    ],
    "sg:phone":"+1 262 241 4320",
    "sg:postcode":"53092",
    "sg:province":"WI",
    "sg:tags":[
        "photo"
    ],
    "wof:name":"Bublitz Richard Photography",
    "wof:placetype":"venue"
},
  "geometry": {"coordinates":[-87.925195,43.218194],"type":"Point"}
}