{
  "type": "Feature",
  "properties": {
    "iso:country":"US",
    "sg:address":"3348 Silver Circle Dr",
    "sg:city":"Oconomowoc",
    "sg:classifiers":[
        {
            "category":"Professional",
            "type":"Services"
        }
    ],
    "sg:phone":"+1 262 567 2101",
    "sg:postcode":"53066",
    "sg:province":"WI",
    "wof:name":"Roans Home Services Inc",
    "wof:placetype":"venue"
},
  "geometry": {"coordinates":[-88.48790099999999,43.080075],"type":"Point"}
}