{
  "type": "Feature",
  "properties": {
    "iso:country":"US",
    "sg:address":"759 N Milwaukee St",
    "sg:city":"Milwaukee",
    "sg:classifiers":[
        {
            "category":"Real Estate",
            "subcategory":"Real Estate Agent",
            "type":"Services"
        },
        {
            "category":"Professional",
            "subcategory":"Management & Consulting",
            "type":"Services"
        }
    ],
    "sg:phone":"+1 414 224 0554",
    "sg:postcode":"53202",
    "sg:province":"WI",
    "sg:tags":[
        "resource",
        "relocation",
        "human"
    ],
    "sg:website":"www.butlergroupllc.com",
    "wof:name":"Leaders Forum Ltd",
    "wof:placetype":"venue"
},
  "geometry": {"coordinates":[-87.906841,43.040977],"type":"Point"}
}