{
  "type": "Feature",
  "properties": {
    "iso:country":"US",
    "sg:address":"6940 N Santa Monica Blvd",
    "sg:city":"Milwaukee",
    "sg:classifiers":[
        {
            "category":"Shopping",
            "subcategory":"Bicycles & Sporting Goods",
            "type":"Retail Goods"
        }
    ],
    "sg:phone":"+1 414 247 8100",
    "sg:postcode":"53217",
    "sg:province":"WI",
    "sg:website":"www.wheelsprocket.com",
    "wof:name":"Wheel & Sprocket",
    "wof:placetype":"venue"
},
  "geometry": {"coordinates":[-87.902501,43.143169],"type":"Point"}
}