{
  "type": "Feature",
  "properties": {
    "iso:country":"US",
    "sg:address":"5903 W Tripp Rd",
    "sg:city":"Janesville",
    "sg:classifiers":[
        {
            "category":"Farming",
            "subcategory":"Dairy Farm",
            "type":"Manufacturing & Wholesale Goods"
        }
    ],
    "sg:phone":"+1 608 752 1193",
    "sg:postcode":"53548",
    "sg:province":"WI",
    "sg:tags":[
        "corn"
    ],
    "wof:name":"Leary Brothers",
    "wof:placetype":"venue"
},
  "geometry": {"coordinates":[-89.115759,42.635283],"type":"Point"}
}