{
  "type": "Feature",
  "properties": {
    "iso:country":"US",
    "sg:address":"1718 E Fox Ln",
    "sg:city":"Milwaukee",
    "sg:classifiers":[
        {
            "category":"Organizations",
            "subcategory":"Non-profit Organization",
            "type":"Services"
        }
    ],
    "sg:phone":"+1 414 228 8551",
    "sg:postcode":"53217",
    "sg:province":"WI",
    "sg:tags":[
        "fund",
        "counselor",
        "raising"
    ],
    "wof:name":"Lauritzen & Assoc",
    "wof:placetype":"venue"
},
  "geometry": {"coordinates":[-87.885779,43.168473],"type":"Point"}
}