{
  "type": "Feature",
  "properties": {
    "iso:country":"US",
    "sg:address":"9300 S 27th St",
    "sg:city":"Oak Creek",
    "sg:classifiers":[
        {
            "category":"Retail",
            "subcategory":"Auto Repair",
            "type":"Services"
        }
    ],
    "sg:phone":"+1 414 761 0050",
    "sg:postcode":"53154",
    "sg:province":"WI",
    "sg:tags":[
        "general"
    ],
    "wof:name":"Farchione Motors Inc",
    "wof:placetype":"venue"
},
  "geometry": {"coordinates":[-87.951272,42.872659],"type":"Point"}
}