{
  "type": "Feature",
  "properties": {
    "iso:country":"US",
    "sg:address":"2854 Summerville Park Rd",
    "sg:city":"Lodi",
    "sg:classifiers":[
        {
            "category":"Utilities",
            "subcategory":"Telephone",
            "type":"Services"
        }
    ],
    "sg:phone":"+1 608 592 2515",
    "sg:postcode":"53555",
    "sg:province":"WI",
    "sg:tags":[
        "telecommunication"
    ],
    "wof:name":"Heiser Telemanagement LLC",
    "wof:placetype":"venue"
},
  "geometry": {"coordinates":[-89.572305,43.373723],"type":"Point"}
}