{
  "type": "Feature",
  "properties": {
    "addr:full":"1646 Douglas Ave Racine WI 53404",
    "addr:housenumber":"1646",
    "addr:postcode":"53404",
    "addr:street":"Douglas Ave",
    "iso:country":"US",
    "sg:address":"1646 Douglas Ave",
    "sg:city":"Racine",
    "sg:classifiers":[
        {
            "category":"Food & Beverages",
            "subcategory":"Candy",
            "type":"Retail Goods"
        },
        {
            "category":"Restaurant",
            "type":"Food & Drink"
        }
    ],
    "sg:phone":"+1 262 634 2651",
    "sg:postcode":"53404",
    "sg:province":"WI",
    "sg:tags":[
        "confectionery",
        "eating"
    ],
    "wof:name":"Sweets & Treats",
    "wof:placetype":"venue"
},
  "geometry": {"coordinates":[-87.794222,42.74141],"type":"Point"}
}