{
  "type": "Feature",
  "properties": {
    "addr:full":"902 Happy Valley Dr Menasha WI 54952",
    "addr:housenumber":"902",
    "addr:postcode":"54952",
    "addr:street":"Happy Valley Dr",
    "iso:country":"US",
    "sg:address":"902 Happy Valley Dr",
    "sg:city":"Menasha",
    "sg:classifiers":[
        {
            "category":"Real Estate",
            "subcategory":"Real Estate Operator",
            "type":"Services"
        }
    ],
    "sg:phone":"+1 920 969 0098",
    "sg:postcode":"54952",
    "sg:province":"WI",
    "sg:tags":[
        "mobile",
        "home",
        "site"
    ],
    "wof:name":"Harbor Lights",
    "wof:placetype":"venue"
},
  "geometry": {"coordinates":[-88.44698200000001,44.217666],"type":"Point"}
}