{
  "type": "Feature",
  "properties": {
    "addr:full":"1241 Bellevue St Green Bay WI 54302",
    "addr:housenumber":"1241",
    "addr:postcode":"54302",
    "addr:street":"Bellevue St",
    "iso:country":"US",
    "sg:address":"1241 Bellevue St",
    "sg:city":"Green Bay",
    "sg:classifiers":[
        {
            "category":"Restaurant",
            "type":"Food & Drink"
        }
    ],
    "sg:phone":"+1 920 468 7901",
    "sg:postcode":"54302",
    "sg:province":"WI",
    "wof:name":"Mavis's Family Restaurant",
    "wof:placetype":"venue"
},
  "geometry": {"coordinates":[-87.994671,44.487972],"type":"Point"}
}