{
  "type": "Feature",
  "properties": {
    "iso:country":"US",
    "sg:address":"4422 N 88th St",
    "sg:city":"Milwaukee",
    "sg:classifiers":[
        {
            "category":"Insurance",
            "subcategory":"Insurance Agent",
            "type":"Services"
        }
    ],
    "sg:phone":"+1 414 466 6169",
    "sg:postcode":"53225",
    "sg:province":"WI",
    "wof:name":"Timothy J & Ann M Finley",
    "wof:placetype":"venue"
},
  "geometry": {"coordinates":[-88.022437,43.097419],"type":"Point"}
}