{
  "type": "Feature",
  "properties": {
    "iso:country":"US",
    "sg:address":"1385 State Hwy 13",
    "sg:city":"Friendship",
    "sg:classifiers":[
        {
            "category":"Food & Beverages",
            "subcategory":"Groceries & Convenience Stores",
            "type":"Retail Goods"
        }
    ],
    "sg:phone":"+1 608 564 7155",
    "sg:postcode":"53934",
    "sg:province":"WI",
    "sg:tags":[
        "grocer"
    ],
    "wof:name":"Country Deli & Grocery",
    "wof:placetype":"venue"
},
  "geometry": {"coordinates":[-89.805916,44.056581],"type":"Point"}
}