{
  "type": "Feature",
  "properties": {
    "addr:full":"989 Co Rd Aa Ridgeland WI 54763",
    "addr:housenumber":"989",
    "addr:postcode":"54763",
    "addr:street":"Co Rd",
    "iso:country":"US",
    "sg:address":"989 Co Rd Aa",
    "sg:city":"Ridgeland",
    "sg:classifiers":[
        {
            "category":"Organizations",
            "subcategory":"Membership Organization",
            "type":"Services"
        }
    ],
    "sg:phone":"+1 715 455 1188",
    "sg:postcode":"54763",
    "sg:province":"WI",
    "wof:name":"Township Building",
    "wof:placetype":"venue"
},
  "geometry": {"coordinates":[-91.904303,45.208385],"type":"Point"}
}