{
  "type": "Feature",
  "properties": {
    "addr:full":"404 S Main St Westfield WI 53964",
    "addr:housenumber":"404",
    "addr:postcode":"53964",
    "addr:street":"S Main St",
    "iso:country":"US",
    "sg:address":"404 S Main St",
    "sg:city":"Westfield",
    "sg:classifiers":[
        {
            "category":"Organizations",
            "subcategory":"Religious Organization",
            "type":"Services"
        }
    ],
    "sg:phone":"+1 608 296 2739",
    "sg:postcode":"53964",
    "sg:province":"WI",
    "sg:tags":[
        "church"
    ],
    "wof:name":"Faith United Methodist Church",
    "wof:placetype":"venue"
},
  "geometry": {"coordinates":[-89.493274,43.883467],"type":"Point"}
}