{
  "type": "Feature",
  "properties": {
    "iso:country":"US",
    "sg:address":"3759 Ridge Dr",
    "sg:city":"Janesville",
    "sg:classifiers":[
        {
            "category":"Professional",
            "type":"Services"
        }
    ],
    "sg:phone":"+1 608 756 0783",
    "sg:postcode":"53545",
    "sg:province":"WI",
    "wof:name":"Browning Bar",
    "wof:placetype":"venue"
},
  "geometry": {"coordinates":[-89.072868,42.6771],"type":"Point"}
}