{
  "type": "Feature",
  "properties": {
    "iso:country":"US",
    "sg:address":"512 Flint St",
    "sg:city":"Onalaska",
    "sg:classifiers":[
        {
            "category":"Building & Trades",
            "subcategory":"Construction",
            "type":"Services"
        }
    ],
    "sg:phone":"+1 608 781 0592",
    "sg:postcode":"54650",
    "sg:province":"WI",
    "sg:tags":[
        "home",
        "contractor",
        "improvement",
        "construct",
        "house"
    ],
    "wof:name":"Barney's Home Improvement",
    "wof:placetype":"venue"
},
  "geometry": {"coordinates":[-91.233232,43.915236],"type":"Point"}
}