{
  "type": "Feature",
  "properties": {
    "iso:country":"US",
    "sg:address":"1502 S Main St",
    "sg:city":"Rice Lake",
    "sg:classifiers":[
        {
            "category":"Wholesale",
            "subcategory":"Construction Materials",
            "type":"Manufacturing & Wholesale Goods"
        }
    ],
    "sg:phone":"+1 715 234 4252",
    "sg:postcode":"54868",
    "sg:province":"WI",
    "wof:name":"Cedar Glass & Door LLC",
    "wof:placetype":"venue"
},
  "geometry": {"coordinates":[-91.733459,45.485588],"type":"Point"}
}