{
  "type": "Feature",
  "properties": {
    "addr:full":"2522 63rd St Kenosha WI 53143",
    "addr:housenumber":"2522",
    "addr:postcode":"53143",
    "addr:street":"63Rd St",
    "iso:country":"US",
    "sg:address":"2522 63rd St",
    "sg:city":"Kenosha",
    "sg:classifiers":[
        {
            "category":"Social Services",
            "type":"Services"
        }
    ],
    "sg:phone":"+1 262 656 9656",
    "sg:postcode":"53143",
    "sg:province":"WI",
    "sg:tags":[
        "organization",
        "welfare"
    ],
    "wof:name":"Margaretann's Place",
    "wof:placetype":"venue"
},
  "geometry": {"coordinates":[-87.84020200000001,42.577696],"type":"Point"}
}