{
  "type": "Feature",
  "properties": {
    "iso:country":"US",
    "sg:address":"7620 Donna Dr",
    "sg:city":"Middleton",
    "sg:classifiers":[
        {
            "category":"Building & Trades",
            "subcategory":"Landscaping Services",
            "type":"Services"
        }
    ],
    "sg:phone":"+1 608 836 7041",
    "sg:postcode":"53562",
    "sg:province":"WI",
    "sg:tags":[
        "designer",
        "landscape"
    ],
    "wof:name":"Bruce Co",
    "wof:placetype":"venue"
},
  "geometry": {"coordinates":[-89.511378,43.105961],"type":"Point"}
}