{
  "type": "Feature",
  "properties": {
    "addr:full":"1901 Maloney Rd Kaukauna WI 54130",
    "addr:housenumber":"1901",
    "addr:postcode":"54130",
    "addr:street":"Maloney Rd",
    "iso:country":"US",
    "sg:address":"1901 Maloney Rd",
    "sg:city":"Kaukauna",
    "sg:classifiers":[
        {
            "category":"Retail",
            "subcategory":"Repair Shop",
            "type":"Services"
        }
    ],
    "sg:phone":"+1 920 766 7121",
    "sg:postcode":"54130",
    "sg:province":"WI",
    "sg:tags":[
        "wood",
        "mfg"
    ],
    "wof:name":"R B Pallet Service Inc",
    "wof:placetype":"venue"
},
  "geometry": {"coordinates":[-88.262529,44.315559],"type":"Point"}
}