{
  "type": "Feature",
  "properties": {
    "iso:country":"US",
    "sg:address":"3713 Kingswood Ct",
    "sg:city":"Eau Claire",
    "sg:classifiers":[
        {
            "category":"Wholesale",
            "subcategory":"Electrical",
            "type":"Manufacturing & Wholesale Goods"
        }
    ],
    "sg:phone":"+1 715 833 8066",
    "sg:postcode":"54701",
    "sg:province":"WI",
    "sg:tags":[
        "equipment"
    ],
    "wof:name":"Starlight Productions LLC",
    "wof:placetype":"venue"
},
  "geometry": {"coordinates":[-91.449546,44.773617],"type":"Point"}
}