{
  "type": "Feature",
  "properties": {
    "iso:country":"US",
    "sg:address":"500 W Main St",
    "sg:city":"Wheeler",
    "sg:classifiers":[
        {
            "category":"Restaurant",
            "type":"Food & Drink"
        }
    ],
    "sg:phone":"+1 715 632 2669",
    "sg:postcode":"54755",
    "sg:province":"WI",
    "sg:tags":[
        "eating"
    ],
    "wof:name":"Retz Inc",
    "wof:placetype":"venue"
},
  "geometry": {"coordinates":[-91.68076499999999,44.567851],"type":"Point"}
}