{
  "type": "Feature",
  "properties": {
    "iso:country":"US",
    "sg:address":"8508 Scott Rd",
    "sg:city":"Black Creek",
    "sg:classifiers":[
        {
            "category":"Freight",
            "type":"Transportation"
        }
    ],
    "sg:phone":"+1 920 525 4496",
    "sg:postcode":"54106",
    "sg:province":"WI",
    "sg:tags":[
        "operator",
        "trucking"
    ],
    "wof:name":"Northwinds Express Inc",
    "wof:placetype":"venue"
},
  "geometry": {"coordinates":[-88.475719,44.559462],"type":"Point"}
}