{
  "type": "Feature",
  "properties": {
    "addr:full":"112 E Monowau St Tomah WI 54660",
    "addr:housenumber":"112",
    "addr:postcode":"54660",
    "addr:street":"E Monowau St",
    "iso:country":"US",
    "sg:address":"112 E Monowau St",
    "sg:city":"Tomah",
    "sg:classifiers":[
        {
            "category":"Local Transit",
            "type":"Transportation"
        }
    ],
    "sg:phone":"+1 608 372 3885",
    "sg:postcode":"54660",
    "sg:province":"WI",
    "sg:tags":[
        "passenger"
    ],
    "wof:name":"Limousines 112",
    "wof:placetype":"venue"
},
  "geometry": {"coordinates":[-90.50464599999999,43.976811],"type":"Point"}
}