{
  "type": "Feature",
  "properties": {
    "iso:country":"US",
    "sg:address":"2640 S High Crest Rd",
    "sg:city":"Beloit",
    "sg:classifiers":[
        {
            "category":"Shopping",
            "type":"Retail Goods"
        }
    ],
    "sg:phone":"+1 608 365 2343",
    "sg:postcode":"53511",
    "sg:province":"WI",
    "sg:tags":[
        "cosmetic",
        "perfume"
    ],
    "wof:name":"Zimmerman Cher",
    "wof:placetype":"venue"
},
  "geometry": {"coordinates":[-89.030277,42.549285],"type":"Point"}
}