{
  "type": "Feature",
  "properties": {
    "iso:country":"US",
    "sg:address":"1011 Crooks Ave",
    "sg:city":"Kaukauna",
    "sg:classifiers":[
        {
            "category":"Restaurant",
            "type":"Food & Drink"
        }
    ],
    "sg:phone":"+1 920 759 1896",
    "sg:postcode":"54130",
    "sg:province":"WI",
    "sg:tags":[
        "family"
    ],
    "wof:name":"Four Star Family Restaurant",
    "wof:placetype":"venue"
},
  "geometry": {"coordinates":[-88.273758,44.271109],"type":"Point"}
}