{
  "type": "Feature",
  "properties": {
    "iso:country":"US",
    "sg:address":"49 Wisconsin Dells Pkwy N",
    "sg:city":"Wisconsin Dells",
    "sg:classifiers":[
        {
            "category":"Restaurant",
            "type":"Food & Drink"
        }
    ],
    "sg:phone":"+1 608 254 8610",
    "sg:postcode":"53965",
    "sg:province":"WI",
    "wof:name":"Haupt Investments",
    "wof:placetype":"venue"
},
  "geometry": {"coordinates":[-89.794033,43.589976],"type":"Point"}
}