{
  "type": "Feature",
  "properties": {
    "addr:full":"801 E Gile Cir De Pere WI 54115",
    "addr:housenumber":"801",
    "addr:postcode":"54115",
    "addr:street":"E Gile Cir",
    "iso:country":"US",
    "sg:address":"801 E Gile Cir",
    "sg:city":"De Pere",
    "sg:classifiers":[
        {
            "category":"Professional",
            "type":"Services"
        }
    ],
    "sg:phone":"+1 920 338 0777",
    "sg:postcode":"54115",
    "sg:province":"WI",
    "wof:name":"Bruce V Besaw",
    "wof:placetype":"venue"
},
  "geometry": {"coordinates":[-88.03303699999999,44.450143],"type":"Point"}
}