{
  "type": "Feature",
  "properties": {
    "iso:country":"US",
    "sg:address":"7710 Riverside Rd",
    "sg:city":"Verona",
    "sg:classifiers":[
        {
            "category":"Professional",
            "subcategory":"Management & Consulting",
            "type":"Services"
        }
    ],
    "sg:phone":"+1 608 848 1001",
    "sg:postcode":"53593",
    "sg:province":"WI",
    "sg:tags":[
        "business"
    ],
    "wof:name":"Seeds Inc",
    "wof:placetype":"venue"
},
  "geometry": {"coordinates":[-89.588918,42.958744],"type":"Point"}
}