{
  "type": "Feature",
  "properties": {
    "iso:country":"US",
    "sg:address":"1328 Superior St",
    "sg:city":"Racine",
    "sg:classifiers":[
        {
            "category":"Bars & Pubs",
            "type":"Food & Drink"
        }
    ],
    "sg:phone":"+1 262 619 1917",
    "sg:postcode":"53404",
    "sg:province":"WI",
    "wof:name":"Five Corners",
    "wof:placetype":"venue"
},
  "geometry": {"coordinates":[-87.790514,42.736315],"type":"Point"}
}