{
  "type": "Feature",
  "properties": {
    "iso:country":"US",
    "sg:address":"11720 26th Ave",
    "sg:city":"Pleasant Prairie",
    "sg:classifiers":[
        {
            "category":"Professional",
            "subcategory":"Management & Consulting",
            "type":"Services"
        }
    ],
    "sg:phone":"+1 262 942 0159",
    "sg:postcode":"53158",
    "sg:province":"IL",
    "sg:tags":[
        "business"
    ],
    "wof:name":"Levans Pharma Manufact Cons",
    "wof:placetype":"venue"
},
  "geometry": {"coordinates":[-87.838477,42.504473],"type":"Point"}
}