{
  "type": "Feature",
  "properties": {
    "iso:country":"US",
    "sg:address":"617 Main St",
    "sg:city":"Brownsville",
    "sg:classifiers":[
        {
            "category":"Food & Beverages",
            "subcategory":"Meat & Fish",
            "type":"Retail Goods"
        }
    ],
    "sg:phone":"+1 920 583 3734",
    "sg:postcode":"53006",
    "sg:province":"WI",
    "wof:name":"Hoff's United Foods",
    "wof:placetype":"venue"
},
  "geometry": {"coordinates":[-88.49206700000001,43.61623],"type":"Point"}
}