{
  "type": "Feature",
  "properties": {
    "iso:country":"US",
    "sg:address":"200 N Durkee St",
    "sg:city":"Appleton",
    "sg:classifiers":[
        {
            "category":"Professional",
            "subcategory":"Lawyer & Legal Services",
            "type":"Services"
        }
    ],
    "sg:phone":"+1 920 739 7085",
    "sg:postcode":"54911",
    "sg:province":"WI",
    "sg:tags":[
        "attorney"
    ],
    "wof:name":"Schubert Law Office LLC",
    "wof:placetype":"venue"
},
  "geometry": {"coordinates":[-88.402746,44.264018],"type":"Point"}
}