{
  "type": "Feature",
  "properties": {
    "addr:full":"6602 W Oklahoma Ave Milwaukee WI 53219",
    "addr:housenumber":"6602",
    "addr:postcode":"53219",
    "addr:street":"W Oklahoma Ave",
    "iso:country":"US",
    "sg:address":"6602 W Oklahoma Ave",
    "sg:city":"Milwaukee",
    "sg:classifiers":[
        {
            "category":"Social Services",
            "subcategory":"Child Care",
            "type":"Services"
        }
    ],
    "sg:phone":"+1 414 543 1846",
    "sg:postcode":"53219",
    "sg:province":"WI",
    "wof:name":"Jamie's Tiny Town",
    "wof:placetype":"venue"
},
  "geometry": {"coordinates":[-87.995887,42.988439],"type":"Point"}
}