{
  "type": "Feature",
  "properties": {
    "iso:country":"US",
    "sg:address":"124 N Adams St",
    "sg:city":"Bonduel",
    "sg:classifiers":[
        {
            "category":"Freight",
            "type":"Transportation"
        }
    ],
    "sg:phone":"+1 715 758 8525",
    "sg:postcode":"54107",
    "sg:province":"WI",
    "sg:tags":[
        "operator",
        "trucking"
    ],
    "wof:name":"Wussow Agri-Service",
    "wof:placetype":"venue"
},
  "geometry": {"coordinates":[-88.439786,44.738202],"type":"Point"}
}