{
  "type": "Feature",
  "properties": {
    "iso:country":"US",
    "sg:address":"4705 Monona Dr",
    "sg:city":"Monona",
    "sg:classifiers":[
        {
            "category":"Building & Trades",
            "subcategory":"Construction",
            "type":"Services"
        }
    ],
    "sg:phone":"+1 608 221 0212",
    "sg:postcode":"53716",
    "sg:province":"WI",
    "sg:tags":[
        "builder",
        "commercial",
        "general",
        "new",
        "home",
        "contractor"
    ],
    "wof:name":"Ultra Construction",
    "wof:placetype":"venue"
},
  "geometry": {"coordinates":[-89.326182,43.06814],"type":"Point"}
}