{
  "type": "Feature",
  "properties": {
    "iso:country":"US",
    "sg:address":"6403 State Rd 70",
    "sg:city":"Siren",
    "sg:classifiers":[
        {
            "category":"Retail",
            "subcategory":"Auto Repair",
            "type":"Services"
        }
    ],
    "sg:phone":"+1 715 349 5878",
    "sg:postcode":"54872",
    "sg:province":"WI",
    "sg:tags":[
        "general"
    ],
    "wof:name":"Mels Auto Shop",
    "wof:placetype":"venue"
},
  "geometry": {"coordinates":[-92.314234,45.822043],"type":"Point"}
}