{
  "type": "Feature",
  "properties": {
    "iso:country":"US",
    "sg:address":"1160 12th St",
    "sg:city":"Fennimore",
    "sg:classifiers":[
        {
            "category":"Bars & Pubs",
            "type":"Food & Drink"
        }
    ],
    "sg:phone":"+1 608 822 6518",
    "sg:postcode":"53809",
    "sg:province":"WI",
    "sg:tags":[
        "drinking",
        "center",
        "bowling"
    ],
    "wof:name":"Fennimore Bowling Lanes",
    "wof:placetype":"venue"
},
  "geometry": {"coordinates":[-90.654933,42.981207],"type":"Point"}
}