{
  "type": "Feature",
  "properties": {
    "iso:country":"US",
    "sg:address":"574 Thronson Dr",
    "sg:city":"Edgerton",
    "sg:classifiers":[
        {
            "category":"Retail",
            "subcategory":"Auto Repair",
            "type":"Services"
        }
    ],
    "sg:phone":"+1 608 884 9000",
    "sg:postcode":"53534",
    "sg:province":"WI",
    "sg:tags":[
        "repairing",
        "automobile",
        "general"
    ],
    "wof:name":"Ted's Auto Repair",
    "wof:placetype":"venue"
},
  "geometry": {"coordinates":[-89.056608,42.847573],"type":"Point"}
}