{
  "type": "Feature",
  "properties": {
    "iso:country":"US",
    "sg:address":"330 Co Rd B",
    "sg:city":"Montello",
    "sg:classifiers":[
        {
            "category":"Bars & Pubs",
            "type":"Food & Drink"
        }
    ],
    "sg:phone":"+1 608 297 2273",
    "sg:postcode":"53949",
    "sg:province":"WI",
    "sg:tags":[
        "drinking"
    ],
    "wof:name":"Rustic Inn",
    "wof:placetype":"venue"
},
  "geometry": {"coordinates":[-89.37817,43.815354],"type":"Point"}
}