{
  "type": "Feature",
  "properties": {
    "iso:country":"US",
    "sg:address":"7911 Co Hwy Y",
    "sg:city":"Monroe",
    "sg:classifiers":[
        {
            "category":"Retail",
            "subcategory":"Animal Services",
            "type":"Services"
        }
    ],
    "sg:phone":"+1 608 325 7452",
    "sg:postcode":"53566",
    "sg:province":"WI",
    "sg:tags":[
        "pet",
        "boarding",
        "sitting"
    ],
    "wof:name":"Rolan Hills Kennels",
    "wof:placetype":"venue"
},
  "geometry": {"coordinates":[-89.76366299999999,42.629611],"type":"Point"}
}