{
  "type": "Feature",
  "properties": {
    "addr:full":"505 Marion Rd Oshkosh WI 54901",
    "addr:housenumber":"505",
    "addr:postcode":"54901",
    "addr:street":"Marion Rd",
    "iso:country":"US",
    "sg:address":"505 Marion Rd",
    "sg:city":"Oshkosh",
    "sg:classifiers":[
        {
            "category":"Manufacturing",
            "subcategory":"Tools & Machinery",
            "type":"Manufacturing & Wholesale Goods"
        }
    ],
    "sg:phone":"+1 920 231 9181",
    "sg:postcode":"54901",
    "sg:province":"WI",
    "sg:tags":[
        "turbine"
    ],
    "sg:website":"www.mercurymarine.com",
    "wof:name":"Mercury Marine",
    "wof:placetype":"venue"
},
  "geometry": {"coordinates":[-88.54835799999999,44.018576],"type":"Point"}
}