{
  "type": "Feature",
  "properties": {
    "addr:full":"1116 Ridge Ct Kaukauna WI 54130",
    "addr:housenumber":"1116",
    "addr:postcode":"54130",
    "addr:street":"Ridge Ct",
    "iso:country":"US",
    "sg:address":"1116 Ridge Ct",
    "sg:city":"Kaukauna",
    "sg:classifiers":[
        {
            "category":"Building & Trades",
            "subcategory":"Construction",
            "type":"Services"
        }
    ],
    "sg:phone":"+1 920 759 9457",
    "sg:postcode":"54130",
    "sg:province":"WI",
    "sg:tags":[
        "house"
    ],
    "wof:name":"Alpine Home Development",
    "wof:placetype":"venue"
},
  "geometry": {"coordinates":[-88.261019,44.271154],"type":"Point"}
}