{
  "type": "Feature",
  "properties": {
    "iso:country":"US",
    "sg:address":"2841 Brookside Dr",
    "sg:city":"Appleton",
    "sg:classifiers":[
        {
            "category":"Personal",
            "type":"Services"
        }
    ],
    "sg:phone":"+1 920 734 5517",
    "sg:postcode":"54913",
    "sg:province":"WI",
    "sg:tags":[
        "wedding",
        "chapel"
    ],
    "wof:name":"Country Chapel LLC",
    "wof:placetype":"venue"
},
  "geometry": {"coordinates":[-88.332361,44.336453],"type":"Point"}
}