{
  "type": "Feature",
  "properties": {
    "iso:country":"US",
    "sg:address":"15440 W Beloit Rd",
    "sg:city":"New Berlin",
    "sg:classifiers":[
        {
            "category":"Personal",
            "subcategory":"Beauty Salon",
            "type":"Services"
        }
    ],
    "sg:phone":"+1 262 780 2900",
    "sg:postcode":"53151",
    "sg:province":"WI",
    "sg:tags":[
        "shop"
    ],
    "wof:name":"Hair Solution",
    "wof:placetype":"venue"
},
  "geometry": {"coordinates":[-88.105904,42.955933],"type":"Point"}
}