{
  "type": "Feature",
  "properties": {
    "iso:country":"US",
    "sg:address":"805 4th St",
    "sg:city":"Chetek",
    "sg:classifiers":[
        {
            "category":"Shopping",
            "subcategory":"Gifts & Souvenirs",
            "type":"Retail Goods"
        }
    ],
    "sg:phone":"+1 715 924 1858",
    "sg:postcode":"54728",
    "sg:province":"WI",
    "wof:name":"Elise Vik",
    "wof:placetype":"venue"
},
  "geometry": {"coordinates":[-91.653916,45.31726],"type":"Point"}
}