{
  "type": "Feature",
  "properties": {
    "iso:country":"US",
    "sg:address":"7030 Buchanan St",
    "sg:city":"Cedarburg",
    "sg:classifiers":[
        {
            "category":"Restaurant",
            "type":"Food & Drink"
        }
    ],
    "sg:phone":"+1 262 375 2844",
    "sg:postcode":"53012",
    "sg:province":"WI",
    "sg:tags":[
        "eating"
    ],
    "wof:name":"Twenty Five Inn LLC",
    "wof:placetype":"venue"
},
  "geometry": {"coordinates":[-87.997377,43.287743],"type":"Point"}
}