{
  "type": "Feature",
  "properties": {
    "iso:country":"US",
    "sg:address":"790 N Milwaukee St",
    "sg:city":"Milwaukee",
    "sg:classifiers":[
        {
            "category":"Professional",
            "subcategory":"Computer Services",
            "type":"Services"
        }
    ],
    "sg:phone":"+1 414 220 9000",
    "sg:postcode":"53202",
    "sg:province":"WI",
    "sg:tags":[
        "datum"
    ],
    "wof:name":"It Data Center",
    "wof:placetype":"venue"
},
  "geometry": {"coordinates":[-87.90660200000001,43.04018],"type":"Point"}
}