{
  "type": "Feature",
  "properties": {
    "iso:country":"US",
    "sg:address":"311 W Silver Spring Dr",
    "sg:city":"Milwaukee",
    "sg:classifiers":[
        {
            "category":"Shopping",
            "subcategory":"Bicycles & Sporting Goods",
            "type":"Retail Goods"
        }
    ],
    "sg:phone":"+1 414 962 0911",
    "sg:postcode":"53209",
    "sg:province":"WI",
    "wof:name":"Benz Cyclery",
    "wof:placetype":"venue"
},
  "geometry": {"coordinates":[-87.913983,43.118549],"type":"Point"}
}