{
  "type": "Feature",
  "properties": {
    "iso:country":"US",
    "sg:address":"3410 W Fond du Lac Ave",
    "sg:city":"Milwaukee",
    "sg:classifiers":[
        {
            "category":"Personal",
            "subcategory":"Barber",
            "type":"Services"
        }
    ],
    "sg:phone":"+1 414 445 6522",
    "sg:postcode":"53210",
    "sg:province":"WI",
    "sg:tags":[
        "shop"
    ],
    "wof:name":"Fade Masters",
    "wof:placetype":"venue"
},
  "geometry": {"coordinates":[-87.957174,43.075139],"type":"Point"}
}