{
  "type": "Feature",
  "properties": {
    "iso:country":"US",
    "sg:address":"405 S Marquette Rd",
    "sg:city":"Prairie Du Chien",
    "sg:classifiers":[
        {
            "category":"Professional",
            "subcategory":"Advertising",
            "type":"Services"
        }
    ],
    "sg:phone":"+1 608 326 2457",
    "sg:postcode":"53821",
    "sg:province":"WI",
    "sg:tags":[
        "guide"
    ],
    "wof:name":"Wisconsin Iowa Shopping News",
    "wof:placetype":"venue"
},
  "geometry": {"coordinates":[-91.140969,43.047773],"type":"Point"}
}