{
  "type": "Feature",
  "properties": {
    "iso:country":"US",
    "sg:address":"3130 W Wisconsin Ave",
    "sg:city":"Appleton",
    "sg:classifiers":[
        {
            "category":"Autos & Motor Vehicles",
            "subcategory":"Automobile Sales",
            "type":"Retail Goods"
        }
    ],
    "sg:phone":"+1 920 734 4100",
    "sg:postcode":"54914",
    "sg:province":"WI",
    "sg:tags":[
        "car",
        "dealer"
    ],
    "wof:name":"K & B Auto Co Inc",
    "wof:placetype":"venue"
},
  "geometry": {"coordinates":[-88.453093,44.27336],"type":"Point"}
}