{
  "type": "Feature",
  "properties": {
    "iso:country":"US",
    "sg:address":"4518 Pleasant Hill Rd",
    "sg:city":"Richfield",
    "sg:classifiers":[
        {
            "category":"Travel",
            "subcategory":"Travel Agent",
            "type":"Entertainment"
        }
    ],
    "sg:phone":"+1 262 628 1549",
    "sg:postcode":"53076",
    "sg:province":"WI",
    "sg:tags":[
        "operator",
        "tour"
    ],
    "wof:name":"Top Tours",
    "wof:placetype":"venue"
},
  "geometry": {"coordinates":[-88.264707,43.265888],"type":"Point"}
}