{
  "type": "Feature",
  "properties": {
    "iso:country":"US",
    "sg:address":"5709 S 104th St",
    "sg:city":"Hales Corners",
    "sg:classifiers":[
        {
            "category":"Freight",
            "type":"Transportation"
        }
    ],
    "sg:phone":"+1 414 427 2161",
    "sg:postcode":"53130",
    "sg:province":"WI",
    "sg:tags":[
        "operator",
        "local",
        "trucking"
    ],
    "wof:name":"Dkj Trucking LLC",
    "wof:placetype":"venue"
},
  "geometry": {"coordinates":[-88.043403,42.93988],"type":"Point"}
}