{
  "type": "Feature",
  "properties": {
    "iso:country":"US",
    "sg:address":"417 E Milwaukee St",
    "sg:city":"Jefferson",
    "sg:classifiers":[
        {
            "category":"Restaurant",
            "type":"Food & Drink"
        }
    ],
    "sg:phone":"+1 920 674 2547",
    "sg:postcode":"53549",
    "sg:province":"WI",
    "wof:name":"Ken's Towne Inn",
    "wof:placetype":"venue"
},
  "geometry": {"coordinates":[-88.799886,43.004279],"type":"Point"}
}