{
  "type": "Feature",
  "properties": {
    "iso:country":"US",
    "sg:address":"2512 Crooks Ave",
    "sg:city":"Kaukauna",
    "sg:classifiers":[
        {
            "category":"Retail",
            "subcategory":"Auto Repair",
            "type":"Services"
        }
    ],
    "sg:phone":"+1 920 759 1130",
    "sg:postcode":"54130",
    "sg:province":"WI",
    "sg:tags":[
        "automobile",
        "lubrication"
    ],
    "wof:name":"Valvoline Instant Oil Change",
    "wof:placetype":"venue"
},
  "geometry": {"coordinates":[-88.273753,44.259465],"type":"Point"}
}