{
  "type": "Feature",
  "properties": {
    "iso:country":"US",
    "sg:address":"626 Beech Dr",
    "sg:city":"East Troy",
    "sg:classifiers":[
        {
            "category":"Manufacturing",
            "subcategory":"Musical Instruments",
            "type":"Manufacturing & Wholesale Goods"
        }
    ],
    "sg:phone":"+1 262 642 3649",
    "sg:postcode":"53120",
    "sg:province":"WI",
    "sg:tags":[
        "mfg"
    ],
    "wof:name":"Mussejhl & Westphal",
    "wof:placetype":"venue"
},
  "geometry": {"coordinates":[-88.333905,42.804378],"type":"Point"}
}