{
  "type": "Feature",
  "properties": {
    "iso:country":"US",
    "sg:address":"5724 Durand Ave",
    "sg:city":"Racine",
    "sg:classifiers":[
        {
            "category":"Shopping",
            "subcategory":"Clothing, Apparel, & Fashions",
            "type":"Retail Goods"
        }
    ],
    "sg:phone":"+1 262 554 6479",
    "sg:postcode":"53406",
    "sg:province":"WI",
    "sg:website":"www.buckle.com",
    "wof:name":"Buckle",
    "wof:placetype":"venue"
},
  "geometry": {"coordinates":[-87.849204,42.69737],"type":"Point"}
}