{
  "type": "Feature",
  "properties": {
    "iso:country":"US",
    "sg:address":"105 Conroy Cir",
    "sg:city":"Beaver Dam",
    "sg:classifiers":[
        {
            "category":"Building & Trades",
            "subcategory":"Construction",
            "type":"Services"
        }
    ],
    "sg:phone":"+1 920 356 0351",
    "sg:postcode":"53916",
    "sg:province":"WI",
    "sg:tags":[
        "painter"
    ],
    "wof:name":"Wall Creations By Michelle",
    "wof:placetype":"venue"
},
  "geometry": {"coordinates":[-88.83744900000001,43.444291],"type":"Point"}
}