{
  "type": "Feature",
  "properties": {
    "iso:country":"US",
    "sg:address":"910 E High St",
    "sg:city":"Milton",
    "sg:classifiers":[
        {
            "category":"Organizations",
            "subcategory":"Religious Organization",
            "type":"Services"
        }
    ],
    "sg:phone":"+1 608 868 4771",
    "sg:postcode":"53563",
    "sg:province":"WI",
    "wof:name":"Saint Jhns Evang Lthran Church",
    "wof:placetype":"venue"
},
  "geometry": {"coordinates":[-88.935712,42.772775],"type":"Point"}
}