{
  "type": "Feature",
  "properties": {
    "iso:country":"US",
    "sg:address":"2255 E Main St",
    "sg:city":"Reedsburg",
    "sg:classifiers":[
        {
            "category":"Home & Garden",
            "subcategory":"Building Materials",
            "type":"Retail Goods"
        }
    ],
    "sg:phone":"+1 608 524 1714",
    "sg:postcode":"53959",
    "sg:province":"WI",
    "wof:name":"Reedsburg Glass Company",
    "wof:placetype":"venue"
},
  "geometry": {"coordinates":[-89.976057,43.53259],"type":"Point"}
}