{
  "type": "Feature",
  "properties": {
    "addr:full":"5420 W Electric Ave Milwaukee WI 53219",
    "addr:housenumber":"5420",
    "addr:postcode":"53219",
    "addr:street":"W Electric Ave",
    "iso:country":"US",
    "sg:address":"5420 W Electric Ave",
    "sg:city":"Milwaukee",
    "sg:classifiers":[
        {
            "category":"Wholesale",
            "subcategory":"Durable Goods & Equipment",
            "type":"Manufacturing & Wholesale Goods"
        }
    ],
    "sg:phone":"+1 414 321 8230",
    "sg:postcode":"53219",
    "sg:province":"WI",
    "sg:tags":[
        "representative",
        "manufacturer"
    ],
    "wof:name":"Robert C Kaminski & Assoc",
    "wof:placetype":"venue"
},
  "geometry": {"coordinates":[-87.98136599999999,43.003142],"type":"Point"}
}