{
  "type": "Feature",
  "properties": {
    "iso:country":"US",
    "sg:address":"1139 Pebble Beach Ct",
    "sg:city":"Twin Lakes",
    "sg:classifiers":[
        {
            "category":"Building & Trades",
            "subcategory":"Landscaping Services",
            "type":"Services"
        }
    ],
    "sg:phone":"+1 262 877 9086",
    "sg:postcode":"53181",
    "sg:province":"WI",
    "sg:tags":[
        "landscape"
    ],
    "wof:name":"Browns Land & Pondscapes LLC",
    "wof:placetype":"venue"
},
  "geometry": {"coordinates":[-88.233272,42.530122],"type":"Point"}
}