{
  "type": "Feature",
  "properties": {
    "addr:full":"8201 570th Ave Ellsworth WI 54011",
    "addr:housenumber":"8201",
    "addr:postcode":"54011",
    "addr:street":"570Th Ave",
    "iso:country":"US",
    "sg:address":"8201 570th Ave",
    "sg:city":"Ellsworth",
    "sg:classifiers":[
        {
            "category":"Retail",
            "subcategory":"Auto Repair",
            "type":"Services"
        }
    ],
    "sg:phone":"+1 715 273 4300",
    "sg:postcode":"54011",
    "sg:province":"WI",
    "sg:tags":[
        "automotive"
    ],
    "wof:name":"Melstrom Towing",
    "wof:placetype":"venue"
},
  "geometry": {"coordinates":[-92.542726,44.747934],"type":"Point"}
}