{
  "type": "Feature",
  "properties": {
    "iso:country":"US",
    "sg:address":"205 N Main St",
    "sg:city":"Janesville",
    "sg:classifiers":[
        {
            "category":"Social Services",
            "type":"Services"
        }
    ],
    "sg:phone":"+1 608 756 4281",
    "sg:postcode":"53545",
    "sg:province":"WI",
    "sg:tags":[
        "senior",
        "citizen"
    ],
    "wof:name":"Retired Senior Volunteer",
    "wof:placetype":"venue"
},
  "geometry": {"coordinates":[-89.024358,42.684298],"type":"Point"}
}