{
  "type": "Feature",
  "properties": {
    "iso:country":"US",
    "sg:address":"9639 N Columbia Creek Ln",
    "sg:city":"Thiensville",
    "sg:classifiers":[
        {
            "category":"Banks & Credit Unions",
            "subcategory":"Investment Brokerage",
            "type":"Services"
        }
    ],
    "sg:phone":"+1 262 240 1041",
    "sg:postcode":"53092",
    "sg:province":"WI",
    "sg:tags":[
        "advisory"
    ],
    "wof:name":"Asset Mgt For Professionals",
    "wof:placetype":"venue"
},
  "geometry": {"coordinates":[-87.937579,43.193486],"type":"Point"}
}