{
  "type": "Feature",
  "properties": {
    "iso:country":"US",
    "sg:address":"16 S 1st St",
    "sg:city":"Barron",
    "sg:phone":"+1 715 537 3307",
    "sg:postcode":"54812",
    "sg:province":"WI",
    "sg:tags":[
        "vegetable",
        "farm",
        "green",
        "house"
    ],
    "wof:name":"Dragsmith Farms",
    "wof:placetype":"venue"
},
  "geometry": {"coordinates":[-91.856527,45.401256],"type":"Point"}
}