{
  "type": "Feature",
  "properties": {
    "iso:country":"US",
    "sg:address":"2219 Wisconsin Ave",
    "sg:city":"New Holstein",
    "sg:classifiers":[
        {
            "category":"Shopping",
            "subcategory":"Gifts & Souvenirs",
            "type":"Retail Goods"
        }
    ],
    "sg:phone":"+1 920 898 4637",
    "sg:postcode":"53061",
    "sg:province":"WI",
    "sg:tags":[
        "store"
    ],
    "wof:name":"Heart To Heart",
    "wof:placetype":"venue"
},
  "geometry": {"coordinates":[-88.096454,43.949667],"type":"Point"}
}