{
  "type": "Feature",
  "properties": {
    "iso:country":"US",
    "sg:address":"24924 Breezy Point Rd",
    "sg:city":"Waterford",
    "sg:classifiers":[
        {
            "category":"Building & Trades",
            "subcategory":"Plumbing",
            "type":"Services"
        }
    ],
    "sg:phone":"+1 262 895 3004",
    "sg:postcode":"53185",
    "sg:province":"WI",
    "sg:tags":[
        "contractor"
    ],
    "wof:name":"Franklin Heating & Cooling",
    "wof:placetype":"venue"
},
  "geometry": {"coordinates":[-88.13693600000001,42.81651],"type":"Point"}
}