{
  "type": "Feature",
  "properties": {
    "iso:country":"US",
    "sg:address":"346 W Main St",
    "sg:city":"Waukesha",
    "sg:classifiers":[
        {
            "category":"Shopping",
            "type":"Retail Goods"
        }
    ],
    "sg:phone":"+1 262 896 9308",
    "sg:postcode":"53186",
    "sg:province":"WI",
    "sg:tags":[
        "art",
        "gallery",
        "dealer"
    ],
    "wof:name":"Ashton Arts Studio/Gallery",
    "wof:placetype":"venue"
},
  "geometry": {"coordinates":[-88.23406799999999,43.010984],"type":"Point"}
}