{
  "type": "Feature",
  "properties": {
    "iso:country":"US",
    "sg:address":"7926 15th Ave",
    "sg:city":"Kenosha",
    "sg:classifiers":[
        {
            "category":"Real Estate",
            "subcategory":"Real Estate Agent",
            "type":"Services"
        }
    ],
    "sg:phone":"+1 262 653 0370",
    "sg:postcode":"53143",
    "sg:province":"WI",
    "sg:tags":[
        "management"
    ],
    "wof:name":"Baltic Supply Inc",
    "wof:placetype":"venue"
},
  "geometry": {"coordinates":[-87.828001,42.559017],"type":"Point"}
}