{
  "type": "Feature",
  "properties": {
    "iso:country":"US",
    "sg:address":"6694 Hill Ridge Dr",
    "sg:city":"Greendale",
    "sg:classifiers":[
        {
            "category":"Professional",
            "type":"Services"
        }
    ],
    "sg:phone":"+1 414 425 3528",
    "sg:postcode":"53129",
    "sg:province":"WI",
    "wof:name":"Wendy Stager",
    "wof:placetype":"venue"
},
  "geometry": {"coordinates":[-88.005831,42.924826],"type":"Point"}
}