{
  "type": "Feature",
  "properties": {
    "addr:full":"3536 Parma Ln Kewaunee WI 54216",
    "addr:housenumber":"3536",
    "addr:postcode":"54216",
    "addr:street":"Parma Ln",
    "iso:country":"US",
    "sg:address":"3536 Parma Ln",
    "sg:city":"Kewaunee",
    "sg:classifiers":[
        {
            "category":"Real Estate",
            "subcategory":"Real Estate Operator",
            "type":"Services"
        }
    ],
    "sg:phone":"+1 920 776 1291",
    "sg:postcode":"54216",
    "sg:province":"WI",
    "sg:tags":[
        "property",
        "lessor"
    ],
    "wof:name":"Parma Sylvester",
    "wof:placetype":"venue"
},
  "geometry": {"coordinates":[-87.583462,44.349397],"type":"Point"}
}