{
  "type": "Feature",
  "properties": {
    "iso:country":"US",
    "sg:address":"1927 Erie Ave",
    "sg:city":"Sheboygan",
    "sg:classifiers":[
        {
            "category":"Manufacturing",
            "subcategory":"Paper Products",
            "type":"Manufacturing & Wholesale Goods"
        }
    ],
    "sg:phone":"+1 920 457 5544",
    "sg:postcode":"53081",
    "sg:province":"WI",
    "sg:tags":[
        "corrugated",
        "solid",
        "fiber",
        "box"
    ],
    "sg:website":"www.gp.com",
    "wof:name":"Georgia-Pacific Corp",
    "wof:placetype":"venue"
},
  "geometry": {"coordinates":[-87.73088199999999,43.75624],"type":"Point"}
}