{
  "type": "Feature",
  "properties": {
    "iso:country":"US",
    "sg:address":"4605 Lilac Ave",
    "sg:city":"Wausau",
    "sg:classifiers":[
        {
            "category":"Banks & Credit Unions",
            "subcategory":"Bank",
            "type":"Services"
        }
    ],
    "sg:phone":"+1 715 355 7336",
    "sg:postcode":"54401",
    "sg:province":"WI",
    "sg:tags":[
        "loan",
        "real estate"
    ],
    "wof:name":"Harrison Mortgage LLC",
    "wof:placetype":"venue"
},
  "geometry": {"coordinates":[-89.647356,44.914849],"type":"Point"}
}