{
  "type": "Feature",
  "properties": {
    "iso:country":"US",
    "sg:address":"3345 Edgington Rd",
    "sg:city":"Cobb",
    "sg:classifiers":[
        {
            "category":"Farming",
            "subcategory":"Dairy Farm",
            "type":"Manufacturing & Wholesale Goods"
        }
    ],
    "sg:phone":"+1 608 623 3603",
    "sg:postcode":"53526",
    "sg:province":"WI",
    "wof:name":"Edgington Dairy",
    "wof:placetype":"venue"
},
  "geometry": {"coordinates":[-90.359482,42.968263],"type":"Point"}
}