{
  "type": "Feature",
  "properties": {
    "iso:country":"US",
    "sg:address":"1212 W Lincoln Ave",
    "sg:city":"Milwaukee",
    "sg:classifiers":[
        {
            "category":"Real Estate",
            "subcategory":"Real Estate Agent",
            "type":"Services"
        }
    ],
    "sg:phone":"+1 414 431 2966",
    "sg:postcode":"53215",
    "sg:province":"WI",
    "wof:name":"Complete Realty",
    "wof:placetype":"venue"
},
  "geometry": {"coordinates":[-87.928363,43.002929],"type":"Point"}
}