{
  "type": "Feature",
  "properties": {
    "iso:country":"US",
    "sg:address":"210 Martin Luther King Jr Blvd",
    "sg:city":"Madison",
    "sg:classifiers":[
        {
            "category":"Government",
            "subcategory":"Office",
            "type":"Public Place"
        }
    ],
    "sg:phone":"+1 608 267 8630",
    "sg:postcode":"53709",
    "sg:province":"WI",
    "sg:tags":[
        "village"
    ],
    "wof:name":"Ambulance Billings",
    "wof:placetype":"venue"
},
  "geometry": {"coordinates":[-89.381456,43.072555],"type":"Point"}
}