{
  "type": "Feature",
  "properties": {
    "iso:country":"US",
    "sg:address":"5907 Hilgemann St",
    "sg:city":"Schofield",
    "sg:classifiers":[
        {
            "category":"Shopping",
            "subcategory":"Discount & Variety Stores",
            "type":"Retail Goods"
        }
    ],
    "sg:phone":"+1 715 359 5052",
    "sg:postcode":"54476",
    "sg:province":"WI",
    "sg:tags":[
        "furniture"
    ],
    "wof:name":"Smith Don Sales Inc",
    "wof:placetype":"venue"
},
  "geometry": {"coordinates":[-89.554243,44.903907],"type":"Point"}
}