{
  "type": "Feature",
  "properties": {
    "iso:country":"US",
    "sg:address":"2410 Roosevelt Rd",
    "sg:city":"Marinette",
    "sg:classifiers":[
        {
            "category":"Restaurant",
            "type":"Food & Drink"
        }
    ],
    "sg:phone":"+1 715 732 1023",
    "sg:postcode":"54143",
    "sg:province":"WI",
    "wof:name":"Applebee's Neighborhood Grill",
    "wof:placetype":"venue"
},
  "geometry": {"coordinates":[-87.65803,45.054576],"type":"Point"}
}