{
  "type": "Feature",
  "properties": {
    "iso:country":"US",
    "sg:address":"6323 61st Ave",
    "sg:city":"Kenosha",
    "sg:classifiers":[
        {
            "category":"Autos & Motor Vehicles",
            "subcategory":"Automobile Sales",
            "type":"Retail Goods"
        }
    ],
    "sg:phone":"+1 262 652 8275",
    "sg:postcode":"53142",
    "sg:province":"IL",
    "sg:tags":[
        "used"
    ],
    "wof:name":"Benning Motors",
    "wof:placetype":"venue"
},
  "geometry": {"coordinates":[-87.880663,42.57679],"type":"Point"}
}