{
  "type": "Feature",
  "properties": {
    "iso:country":"US",
    "sg:address":"206 Gifford St",
    "sg:city":"Orfordville",
    "sg:classifiers":[
        {
            "category":"Personal",
            "subcategory":"Beauty Salon",
            "type":"Services"
        }
    ],
    "sg:phone":"+1 608 879 9494",
    "sg:postcode":"53576",
    "sg:province":"WI",
    "sg:tags":[
        "shop"
    ],
    "wof:name":"Reflections",
    "wof:placetype":"venue"
},
  "geometry": {"coordinates":[-89.25139900000001,42.625721],"type":"Point"}
}