{
  "type": "Feature",
  "properties": {
    "iso:country":"US",
    "sg:address":"7775 Hackett Rd",
    "sg:city":"Whitewater",
    "sg:classifiers":[
        {
            "category":"Building & Trades",
            "subcategory":"Construction",
            "type":"Services"
        }
    ],
    "sg:phone":"+1 262 472 8995",
    "sg:postcode":"53190",
    "sg:province":"WI",
    "sg:tags":[
        "house"
    ],
    "wof:name":"Kluczynski Construction LLC",
    "wof:placetype":"venue"
},
  "geometry": {"coordinates":[-88.684265,42.765389],"type":"Point"}
}