{
  "type": "Feature",
  "properties": {
    "iso:country":"US",
    "sg:address":"626 Main St",
    "sg:city":"Darlington",
    "sg:classifiers":[
        {
            "category":"Government",
            "subcategory":"Office",
            "type":"Public Place"
        }
    ],
    "sg:phone":"+1 608 776 4862",
    "sg:postcode":"53530",
    "sg:province":"WI",
    "sg:tags":[
        "county",
        "taxation"
    ],
    "wof:name":"Lafayette County Treasurer",
    "wof:placetype":"venue"
},
  "geometry": {"coordinates":[-90.117794,42.682623],"type":"Point"}
}