{
  "type": "Feature",
  "properties": {
    "addr:full":"14316 US Hwy 45 Tigerton WI 54486",
    "addr:housenumber":"14316",
    "addr:postcode":"54486",
    "addr:street":"Us Hwy 45",
    "iso:country":"US",
    "sg:address":"14316 US Hwy 45",
    "sg:city":"Tigerton",
    "sg:classifiers":[
        {
            "category":"Building & Trades",
            "subcategory":"Construction",
            "type":"Services"
        }
    ],
    "sg:phone":"+1 715 754 4848",
    "sg:postcode":"54486",
    "sg:province":"WI",
    "sg:tags":[
        "painter"
    ],
    "wof:name":"Sexton's Remodeling Exteriors",
    "wof:placetype":"venue"
},
  "geometry": {"coordinates":[-88.978773,44.708739],"type":"Point"}
}