{
  "type": "Feature",
  "properties": {
    "iso:country":"US",
    "sg:address":"7659 Co Rd C",
    "sg:city":"Eldorado",
    "sg:classifiers":[
        {
            "category":"Building & Trades",
            "subcategory":"Construction",
            "type":"Services"
        }
    ],
    "sg:phone":"+1 920 872 5161",
    "sg:postcode":"54932",
    "sg:province":"WI",
    "sg:tags":[
        "silo"
    ],
    "wof:name":"Falls Silo Repair-Central Wi",
    "wof:placetype":"venue"
},
  "geometry": {"coordinates":[-88.623017,43.823637],"type":"Point"}
}