{
  "type": "Feature",
  "properties": {
    "iso:country":"US",
    "sg:address":"8347 Rocky Rd",
    "sg:city":"Portage",
    "sg:classifiers":[
        {
            "category":"Professional",
            "subcategory":"Accounting & Tax Preparation",
            "type":"Services"
        }
    ],
    "sg:phone":"+1 608 742 5694",
    "sg:postcode":"53901",
    "sg:province":"WI",
    "wof:name":"Fenske & Associates",
    "wof:placetype":"venue"
},
  "geometry": {"coordinates":[-89.41809,43.554047],"type":"Point"}
}