{
  "type": "Feature",
  "properties": {
    "addr:full":"121 W 7th St Monroe WI 53566",
    "addr:housenumber":"121",
    "addr:postcode":"53566",
    "addr:street":"W 7Th St",
    "iso:country":"US",
    "sg:address":"121 W 7th St",
    "sg:city":"Monroe",
    "sg:classifiers":[
        {
            "category":"Manufacturing",
            "subcategory":"Chemicals & Compounds",
            "type":"Manufacturing & Wholesale Goods"
        }
    ],
    "sg:phone":"+1 608 325 6033",
    "sg:postcode":"53566",
    "sg:province":"WI",
    "sg:tags":[
        "putty"
    ],
    "sg:website":"www.colorputty.com",
    "wof:name":"Color Putty Co",
    "wof:placetype":"venue"
},
  "geometry": {"coordinates":[-89.66117199999999,42.605446],"type":"Point"}
}