{
  "type": "Feature",
  "properties": {
    "iso:country":"US",
    "sg:address":"107 E 5th St",
    "sg:city":"Marshfield",
    "sg:classifiers":[
        {
            "category":"Retail",
            "subcategory":"Laundry & Dry Cleaning",
            "type":"Services"
        }
    ],
    "sg:phone":"+1 715 389 2898",
    "sg:postcode":"54449",
    "sg:province":"WI",
    "wof:name":"Junes Alterations",
    "wof:placetype":"venue"
},
  "geometry": {"coordinates":[-90.17598599999999,44.663233],"type":"Point"}
}