{
  "type": "Feature",
  "properties": {
    "iso:country":"US",
    "sg:address":"123 N 27th St",
    "sg:city":"Milwaukee",
    "sg:phone":"+1 414 933 1526",
    "sg:postcode":"53208",
    "sg:province":"WI",
    "sg:tags":[
        "leather",
        "tanner",
        "tanning"
    ],
    "wof:name":"Thiele Tanning Company",
    "wof:placetype":"venue"
},
  "geometry": {"coordinates":[-87.94776299999999,43.031445],"type":"Point"}
}