{
  "type": "Feature",
  "properties": {
    "iso:country":"US",
    "sg:address":"19212 Spring St",
    "sg:city":"Union Grove",
    "sg:classifiers":[
        {
            "category":"Autos & Motor Vehicles",
            "subcategory":"Automobile Sales",
            "type":"Retail Goods"
        }
    ],
    "sg:phone":"+1 262 878 2463",
    "sg:postcode":"53182",
    "sg:province":"WI",
    "sg:tags":[
        "car",
        "dealer"
    ],
    "sg:website":"www.rogerpalmen.com",
    "wof:name":"Roger Palmen",
    "wof:placetype":"venue"
},
  "geometry": {"coordinates":[-88.048341,42.704454],"type":"Point"}
}