{
  "type": "Feature",
  "properties": {
    "iso:country":"US",
    "sg:address":"7213 Branford Ln E",
    "sg:city":"Madison",
    "sg:classifiers":[
        {
            "category":"Organizations",
            "subcategory":"Non-profit Organization",
            "type":"Services"
        }
    ],
    "sg:phone":"+1 608 831 3373",
    "sg:postcode":"53717",
    "sg:province":"WI",
    "sg:tags":[
        "fund",
        "counselor",
        "raising"
    ],
    "wof:name":"Designs In Planned Giving",
    "wof:placetype":"venue"
},
  "geometry": {"coordinates":[-89.508708,43.078608],"type":"Point"}
}