{
  "type": "Feature",
  "properties": {
    "iso:country":"US",
    "sg:address":"505 S Dewey St",
    "sg:city":"Eau Claire",
    "sg:classifiers":[
        {
            "category":"Wholesale",
            "subcategory":"Farm Supplies",
            "type":"Manufacturing & Wholesale Goods"
        }
    ],
    "sg:phone":"+1 715 831 8324",
    "sg:postcode":"54701",
    "sg:province":"WI",
    "wof:name":"Mikagen Seeds",
    "wof:placetype":"venue"
},
  "geometry": {"coordinates":[-91.495142,44.809688],"type":"Point"}
}