{
  "type": "Feature",
  "properties": {
    "iso:country":"US",
    "sg:address":"2400 Industrial St",
    "sg:city":"Wisconsin Rapids",
    "sg:classifiers":[
        {
            "category":"Retail",
            "subcategory":"Laundry & Dry Cleaning",
            "type":"Services"
        }
    ],
    "sg:phone":"+1 715 423 4640",
    "sg:postcode":"54495",
    "sg:province":"WI",
    "sg:tags":[
        "garment",
        "industrial",
        "supply"
    ],
    "wof:name":"Unifirst",
    "wof:placetype":"venue"
},
  "geometry": {"coordinates":[-89.853283,44.402071],"type":"Point"}
}