{
  "type": "Feature",
  "properties": {
    "iso:country":"US",
    "sg:address":"2660 Co Rd D",
    "sg:city":"Woodville",
    "sg:classifiers":[
        {
            "category":"Manufacturing",
            "subcategory":"Electronics",
            "type":"Manufacturing & Wholesale Goods"
        }
    ],
    "sg:phone":"+1 715 698 3253",
    "sg:postcode":"54028",
    "sg:province":"WI",
    "sg:tags":[
        "audio"
    ],
    "wof:name":"Stillpoints LLC",
    "wof:placetype":"venue"
},
  "geometry": {"coordinates":[-92.266357,44.974219],"type":"Point"}
}