{
  "type": "Feature",
  "properties": {
    "iso:country":"US",
    "sg:address":"7165 Bighorn Ln",
    "sg:city":"Wautoma",
    "sg:classifiers":[
        {
            "category":"Professional",
            "type":"Services"
        }
    ],
    "sg:phone":"+1 920 787 3243",
    "sg:postcode":"54982",
    "sg:province":"WI",
    "wof:name":"David J Belfeuil",
    "wof:placetype":"venue"
},
  "geometry": {"coordinates":[-89.23580800000001,44.115701],"type":"Point"}
}