{
  "type": "Feature",
  "properties": {
    "iso:country":"US",
    "sg:address":"4021 N 90th St",
    "sg:city":"Milwaukee",
    "sg:classifiers":[
        {
            "category":"Organizations",
            "subcategory":"Religious Organization",
            "type":"Services"
        }
    ],
    "sg:phone":"+1 414 463 8330",
    "sg:postcode":"53222",
    "sg:province":"WI",
    "wof:name":"Saint Timothys Episcpal Church",
    "wof:placetype":"venue"
},
  "geometry": {"coordinates":[-88.025192,43.091262],"type":"Point"}
}