{
  "type": "Feature",
  "properties": {
    "addr:full":"3210 Elmira Ave Superior WI 54880",
    "addr:housenumber":"3210",
    "addr:postcode":"54880",
    "addr:street":"Elmira Ave",
    "iso:country":"US",
    "sg:address":"3210 Elmira Ave",
    "sg:city":"Superior",
    "sg:classifiers":[
        {
            "category":"Building & Trades",
            "subcategory":"Equipment Rental",
            "type":"Services"
        }
    ],
    "sg:phone":"+1 715 394 6088",
    "sg:postcode":"54880",
    "sg:province":"WI",
    "sg:tags":[
        "leasing"
    ],
    "wof:name":"Fur Sher Leasing",
    "wof:placetype":"venue"
},
  "geometry": {"coordinates":[-92.11486600000001,46.701843],"type":"Point"}
}