{
  "type": "Feature",
  "properties": {
    "iso:country":"US",
    "sg:address":"425 Packerland Dr",
    "sg:city":"Green Bay",
    "sg:classifiers":[
        {
            "category":"Professional",
            "subcategory":"Management & Consulting",
            "type":"Services"
        }
    ],
    "sg:phone":"+1 920 884 6479",
    "sg:postcode":"54303",
    "sg:province":"WI",
    "sg:tags":[
        "medical"
    ],
    "wof:name":"Midwest Medical Consulting PC",
    "wof:placetype":"venue"
},
  "geometry": {"coordinates":[-88.094358,44.531965],"type":"Point"}
}