{
  "type": "Feature",
  "properties": {
    "iso:country":"US",
    "sg:address":"2555 N Lake Dr",
    "sg:city":"Milwaukee",
    "sg:classifiers":[
        {
            "category":"Real Estate",
            "subcategory":"Real Estate Operator",
            "type":"Services"
        }
    ],
    "sg:phone":"+1 414 962 4560",
    "sg:postcode":"53211",
    "sg:province":"WI",
    "sg:tags":[
        "building",
        "nonresidential"
    ],
    "wof:name":"Zepezauer & Norman Properties",
    "wof:placetype":"venue"
},
  "geometry": {"coordinates":[-87.877324,43.063285],"type":"Point"}
}