{
  "type": "Feature",
  "properties": {
    "iso:country":"US",
    "sg:address":"1403 Washington Rd",
    "sg:city":"Kenosha",
    "sg:classifiers":[
        {
            "category":"Utilities",
            "subcategory":"Cable",
            "type":"Services"
        }
    ],
    "sg:phone":"+1 262 656 8460",
    "sg:postcode":"53140",
    "sg:province":"WI",
    "sg:tags":[
        "television"
    ],
    "wof:name":"Time Warner Cable",
    "wof:placetype":"venue"
},
  "geometry": {"coordinates":[-87.82858299999999,42.598966],"type":"Point"}
}