{
  "type": "Feature",
  "properties": {
    "iso:country":"US",
    "sg:address":"5015 Lansing High Pt",
    "sg:city":"Oshkosh",
    "sg:classifiers":[
        {
            "category":"Retail",
            "subcategory":"Portrait Studio",
            "type":"Services"
        }
    ],
    "sg:phone":"+1 920 233 3261",
    "sg:postcode":"54904",
    "sg:province":"WI",
    "sg:tags":[
        "photographer"
    ],
    "wof:name":"Creative Imagery",
    "wof:placetype":"venue"
},
  "geometry": {"coordinates":[-88.65114800000001,44.054131],"type":"Point"}
}