{
  "type": "Feature",
  "properties": {
    "iso:country":"US",
    "sg:address":"6663 US Hwy 8",
    "sg:city":"Rhinelander",
    "sg:classifiers":[
        {
            "category":"Retail",
            "subcategory":"Auto Rental",
            "type":"Services"
        }
    ],
    "sg:phone":"+1 715 282 7676",
    "sg:postcode":"54501",
    "sg:province":"WI",
    "sg:tags":[
        "truck"
    ],
    "wof:name":"Ryder Truck Rental One Way",
    "wof:placetype":"venue"
},
  "geometry": {"coordinates":[-89.515461,45.616917],"type":"Point"}
}