{
  "type": "Feature",
  "properties": {
    "iso:country":"US",
    "sg:address":"625 S Market St",
    "sg:city":"Westfield",
    "sg:classifiers":[
        {
            "category":"Building & Trades",
            "subcategory":"Construction",
            "type":"Services"
        }
    ],
    "sg:phone":"+1 608 296 2440",
    "sg:postcode":"53964",
    "sg:province":"WI",
    "sg:tags":[
        "roofing",
        "contractor"
    ],
    "wof:name":"Arnie Singles Roofing Co",
    "wof:placetype":"venue"
},
  "geometry": {"coordinates":[-89.49855,43.88072],"type":"Point"}
}