{
  "type": "Feature",
  "properties": {
    "iso:country":"US",
    "sg:address":"1710 N McCarthy Rd",
    "sg:city":"Appleton",
    "sg:classifiers":[
        {
            "category":"Professional",
            "subcategory":"Accounting & Tax Preparation",
            "type":"Services"
        }
    ],
    "sg:phone":"+1 262 681 1404",
    "sg:postcode":"54913",
    "sg:province":"WI",
    "sg:tags":[
        "accountant"
    ],
    "wof:name":"Accounting & Consulting Svc",
    "wof:placetype":"venue"
},
  "geometry": {"coordinates":[-88.486446,44.27677],"type":"Point"}
}