{
  "type": "Feature",
  "properties": {
    "addr:full":"6529 Valley Ln Plymouth WI 53073",
    "addr:housenumber":"6529",
    "addr:postcode":"53073",
    "addr:street":"Valley Ln",
    "iso:country":"US",
    "sg:address":"6529 Valley Ln",
    "sg:city":"Plymouth",
    "sg:classifiers":[
        {
            "category":"Real Estate",
            "subcategory":"Real Estate Agent",
            "type":"Services"
        }
    ],
    "sg:phone":"+1 920 892 2196",
    "sg:postcode":"53073",
    "sg:province":"WI",
    "sg:tags":[
        "appraiser"
    ],
    "wof:name":"Joe Michalowitz Appraisals",
    "wof:placetype":"venue"
},
  "geometry": {"coordinates":[-88.02200000000001,43.764761],"type":"Point"}
}