{
  "type": "Feature",
  "properties": {
    "addr:full":"506 E Mill St Plymouth WI 53073",
    "addr:housenumber":"506",
    "addr:postcode":"53073",
    "addr:street":"E Mill St",
    "iso:country":"US",
    "sg:address":"506 E Mill St",
    "sg:city":"Plymouth",
    "sg:classifiers":[
        {
            "category":"Banks & Credit Unions",
            "subcategory":"Investment Brokerage",
            "type":"Services"
        }
    ],
    "sg:phone":"+1 920 893 5262",
    "sg:postcode":"53073",
    "sg:province":"WI",
    "sg:tags":[
        "advisory",
        "financial"
    ],
    "wof:name":"Veritas Financial Svc LLC",
    "wof:placetype":"venue"
},
  "geometry": {"coordinates":[-87.975122,43.74769],"type":"Point"}
}