{
  "type": "Feature",
  "properties": {
    "iso:country":"US",
    "sg:address":"37383 State Hwy 121",
    "sg:city":"Whitehall",
    "sg:classifiers":[
        {
            "category":"Farming",
            "subcategory":"Farm",
            "type":"Manufacturing & Wholesale Goods"
        }
    ],
    "sg:phone":"+1 715 538 2006",
    "sg:postcode":"54773",
    "sg:province":"WI",
    "sg:tags":[
        "crop",
        "general"
    ],
    "wof:name":"David McRae",
    "wof:placetype":"venue"
},
  "geometry": {"coordinates":[-91.261741,44.389288],"type":"Point"}
}