{
  "type": "Feature",
  "properties": {
    "addr:full":"1501 W Zellman Ct Milwaukee WI 53221",
    "addr:housenumber":"1501",
    "addr:postcode":"53221",
    "addr:street":"W Zellman Ct",
    "iso:country":"US",
    "sg:address":"1501 W Zellman Ct",
    "sg:city":"Milwaukee",
    "sg:classifiers":[
        {
            "category":"Shopping",
            "subcategory":"Clothing, Apparel, & Fashions",
            "type":"Retail Goods"
        },
        {
            "category":"Personal",
            "type":"Services"
        }
    ],
    "sg:phone":"+1 414 324 1273",
    "sg:postcode":"53221",
    "sg:province":"WI",
    "sg:tags":[
        "tailoring",
        "alterations-clothing",
        "alteration",
        "tailor",
        "wedding"
    ],
    "sg:website":"http://www.twomotherssewing.net",
    "wof:name":"Two Mothers Sewing And Tailoring",
    "wof:placetype":"venue"
},
  "geometry": {"coordinates":[-87.932204,42.925197],"type":"Point"}
}