{
  "type": "Feature",
  "properties": {
    "addr:full":"3365 S Johnson Rd New Berlin WI 53146",
    "addr:housenumber":"3365",
    "addr:postcode":"53146",
    "addr:street":"S Johnson Rd",
    "iso:country":"US",
    "sg:address":"3365 S Johnson Rd",
    "sg:city":"New Berlin",
    "sg:classifiers":[
        {
            "category":"Retail",
            "subcategory":"Auto Repair",
            "type":"Services"
        }
    ],
    "sg:phone":"+1 262 547 0589",
    "sg:postcode":"53146",
    "sg:province":"WI",
    "sg:tags":[
        "general"
    ],
    "wof:name":"Martys Auto Repair",
    "wof:placetype":"venue"
},
  "geometry": {"coordinates":[-88.167314,42.982753],"type":"Point"}
}