{
  "type": "Feature",
  "properties": {
    "iso:country":"US",
    "sg:address":"3620 9th Ave",
    "sg:city":"Wisconsin Dells",
    "sg:classifiers":[
        {
            "category":"Building & Trades",
            "subcategory":"Construction",
            "type":"Services"
        }
    ],
    "sg:phone":"+1 608 254 8086",
    "sg:postcode":"53965",
    "sg:province":"WI",
    "sg:tags":[
        "house"
    ],
    "wof:name":"Stroede Bros Construction Co",
    "wof:placetype":"venue"
},
  "geometry": {"coordinates":[-89.757706,43.721478],"type":"Point"}
}