{
  "type": "Feature",
  "properties": {
    "iso:country":"US",
    "sg:address":"1831 Linden St",
    "sg:city":"Grafton",
    "sg:classifiers":[
        {
            "category":"Building & Trades",
            "subcategory":"Construction",
            "type":"Services"
        }
    ],
    "sg:phone":"+1 262 375 7014",
    "sg:postcode":"53024",
    "sg:province":"WI",
    "sg:tags":[
        "insulation",
        "mechanical"
    ],
    "wof:name":"Insulation Systems Inc",
    "wof:placetype":"venue"
},
  "geometry": {"coordinates":[-87.94236600000001,43.310171],"type":"Point"}
}