{
  "type": "Feature",
  "properties": {
    "addr:full":"315 W Wisconsin Ave Tomahawk WI 54487",
    "addr:housenumber":"315",
    "addr:postcode":"54487",
    "addr:street":"W Wisconsin Ave",
    "iso:country":"US",
    "sg:address":"315 W Wisconsin Ave",
    "sg:city":"Tomahawk",
    "sg:classifiers":[
        {
            "category":"Manufacturing",
            "subcategory":"Printing",
            "type":"Manufacturing & Wholesale Goods"
        }
    ],
    "sg:phone":"+1 715 453 2151",
    "sg:postcode":"54487",
    "sg:province":"WI",
    "sg:tags":[
        "newspaper"
    ],
    "sg:website":"www.tomahawkleader.com",
    "wof:name":"Tomahawk Leader",
    "wof:placetype":"venue"
},
  "geometry": {"coordinates":[-89.73493499999999,45.470955],"type":"Point"}
}