{
  "type": "Feature",
  "properties": {
    "iso:country":"US",
    "sg:address":"114 E Maple St",
    "sg:city":"Spooner",
    "sg:classifiers":[
        {
            "category":"Retail",
            "subcategory":"Auto Repair",
            "type":"Services"
        }
    ],
    "sg:phone":"+1 715 635 2881",
    "sg:postcode":"54801",
    "sg:province":"WI",
    "sg:tags":[
        "body",
        "automobile",
        "painting"
    ],
    "wof:name":"C & J Body Shop Inc",
    "wof:placetype":"venue"
},
  "geometry": {"coordinates":[-91.887607,45.821944],"type":"Point"}
}