{
  "type": "Feature",
  "properties": {
    "addr:full":"6123 Green Bay Rd Kenosha WI 53142",
    "addr:housenumber":"6123",
    "addr:postcode":"53142",
    "addr:street":"Green Bay Rd",
    "iso:country":"US",
    "sg:address":"6123 Green Bay Rd",
    "sg:city":"Kenosha",
    "sg:classifiers":[
        {
            "category":"Professional",
            "subcategory":"Lawyer & Legal Services",
            "type":"Services"
        }
    ],
    "sg:phone":"+1 262 697 1236",
    "sg:postcode":"53142",
    "sg:province":"WI",
    "sg:tags":[
        "attorney"
    ],
    "wof:name":"Thomas Van Beckum Law Office",
    "wof:placetype":"venue"
},
  "geometry": {"coordinates":[-87.885031,42.578867],"type":"Point"}
}