{
  "type": "Feature",
  "properties": {
    "iso:country":"US",
    "sg:address":"604 Lewellen St",
    "sg:city":"Marshall",
    "sg:classifiers":[
        {
            "category":"Health Services",
            "subcategory":"Nursing And Care Facility",
            "type":"Services"
        }
    ],
    "sg:phone":"+1 608 655 3507",
    "sg:postcode":"53559",
    "sg:province":"WI",
    "sg:tags":[
        "skilled"
    ],
    "wof:name":"Sienna Crest",
    "wof:placetype":"venue"
},
  "geometry": {"coordinates":[-89.058263,43.174449],"type":"Point"}
}