{
  "type": "Feature",
  "properties": {
    "iso:country":"US",
    "sg:address":"1393 Thrush St",
    "sg:city":"Green Bay",
    "sg:classifiers":[
        {
            "category":"Freight",
            "type":"Transportation"
        }
    ],
    "sg:phone":"+1 920 491 2375",
    "sg:postcode":"54303",
    "sg:province":"WI",
    "wof:name":"AOJ Transportation Inc",
    "wof:placetype":"venue"
},
  "geometry": {"coordinates":[-88.037659,44.543782],"type":"Point"}
}