{
  "type": "Feature",
  "properties": {
    "iso:country":"US",
    "sg:address":"324 4th Ave",
    "sg:city":"Baraboo",
    "sg:classifiers":[
        {
            "category":"Real Estate",
            "subcategory":"Real Estate Operator",
            "type":"Services"
        }
    ],
    "sg:phone":"+1 608 355 9438",
    "sg:postcode":"53913",
    "sg:province":"WI",
    "sg:tags":[
        "building",
        "nonresidential"
    ],
    "wof:name":"Thunderbird Properties LLC",
    "wof:placetype":"venue"
},
  "geometry": {"coordinates":[-89.74747,43.47101],"type":"Point"}
}