{
  "type": "Feature",
  "properties": {
    "addr:full":"7907 Co Rd C De Forest WI 53532",
    "addr:housenumber":"7907",
    "addr:postcode":"53532",
    "addr:street":"Co Rd",
    "iso:country":"US",
    "sg:address":"7907 Co Rd C",
    "sg:city":"De Forest",
    "sg:classifiers":[
        {
            "category":"Freight",
            "type":"Transportation"
        }
    ],
    "sg:phone":"+1 608 846 7840",
    "sg:postcode":"53532",
    "sg:province":"WI",
    "sg:tags":[
        "grain",
        "elevator"
    ],
    "wof:name":"Peavey Co",
    "wof:placetype":"venue"
},
  "geometry": {"coordinates":[-89.254895,43.278229],"type":"Point"}
}