{
  "type": "Feature",
  "properties": {
    "iso:country":"US",
    "sg:address":"733 Linden St",
    "sg:city":"Waukesha",
    "sg:classifiers":[
        {
            "category":"Education",
            "subcategory":"School",
            "type":"Public Place"
        }
    ],
    "sg:phone":"+1 262 970 1500",
    "sg:postcode":"53186",
    "sg:province":"WI",
    "wof:name":"Hadfield Elementary School",
    "wof:placetype":"venue"
},
  "geometry": {"coordinates":[-88.216736,43.009762],"type":"Point"}
}