{
  "type": "Feature",
  "properties": {
    "iso:country":"US",
    "sg:address":"120 Abbey Ave",
    "sg:city":"Neenah",
    "sg:classifiers":[
        {
            "category":"Manufacturing",
            "subcategory":"Soap",
            "type":"Manufacturing & Wholesale Goods"
        }
    ],
    "sg:phone":"+1 920 720 0046",
    "sg:postcode":"54956",
    "sg:province":"WI",
    "wof:name":"Sweet Scents Soap Company",
    "wof:placetype":"venue"
},
  "geometry": {"coordinates":[-88.459036,44.193787],"type":"Point"}
}