{
  "type": "Feature",
  "properties": {
    "iso:country":"US",
    "sg:address":"130 Warren St",
    "sg:city":"Beaver Dam",
    "sg:classifiers":[
        {
            "category":"Health Services",
            "subcategory":"Doctor",
            "type":"Services"
        }
    ],
    "sg:phone":"+1 920 887 0379",
    "sg:postcode":"53916",
    "sg:province":"WI",
    "sg:tags":[
        "physician",
        "surgeon"
    ],
    "wof:name":"Militello & Haberman",
    "wof:placetype":"venue"
},
  "geometry": {"coordinates":[-88.824625,43.448781],"type":"Point"}
}