{
  "type": "Feature",
  "properties": {
    "iso:country":"US",
    "sg:address":"81955 Co Hwy A",
    "sg:city":"Iron River",
    "sg:classifiers":[
        {
            "category":"Professional",
            "subcategory":"Research",
            "type":"Services"
        }
    ],
    "sg:phone":"+1 715 372 6158",
    "sg:postcode":"54847",
    "sg:province":"WI",
    "sg:tags":[
        "development",
        "laboratory"
    ],
    "wof:name":"Bio Medical Resources Inc",
    "wof:placetype":"venue"
},
  "geometry": {"coordinates":[-91.384068,46.760036],"type":"Point"}
}