{
  "type": "Feature",
  "properties": {
    "iso:country":"US",
    "sg:address":"625 Main St",
    "sg:city":"Onalaska",
    "sg:classifiers":[
        {
            "category":"Retail",
            "subcategory":"Auto Rental",
            "type":"Services"
        }
    ],
    "sg:phone":"+1 608 779 2400",
    "sg:postcode":"54650",
    "sg:province":"WI",
    "sg:tags":[
        "passenger",
        "leasing",
        "car"
    ],
    "wof:name":"Newvascu",
    "wof:placetype":"venue"
},
  "geometry": {"coordinates":[-91.22886800000001,43.884158],"type":"Point"}
}