{
  "type": "Feature",
  "properties": {
    "iso:country":"US",
    "sg:address":"2040 N Main St",
    "sg:city":"West Bend",
    "sg:classifiers":[
        {
            "category":"Building & Trades",
            "subcategory":"Electrical",
            "type":"Services"
        }
    ],
    "sg:phone":"+1 262 334 2474",
    "sg:postcode":"53090",
    "sg:province":"WI",
    "sg:tags":[
        "contractor",
        "electrical",
        "electric",
        "general"
    ],
    "wof:name":"Kirchner Electric Inc",
    "wof:placetype":"venue"
},
  "geometry": {"coordinates":[-88.19027,43.446084],"type":"Point"}
}