{
  "type": "Feature",
  "properties": {
    "addr:full":"630 E Washington Ave Madison WI 53703",
    "addr:housenumber":"630",
    "addr:postcode":"53703",
    "addr:street":"E Washington Ave",
    "iso:country":"US",
    "sg:address":"630 E Washington Ave",
    "sg:city":"Madison",
    "sg:classifiers":[
        {
            "category":"Social Services",
            "type":"Services"
        }
    ],
    "sg:phone":"+1 608 256 2321",
    "sg:postcode":"53703",
    "sg:province":"WI",
    "sg:tags":[
        "organization",
        "welfare"
    ],
    "wof:name":"Salvation Army",
    "wof:placetype":"venue"
},
  "geometry": {"coordinates":[-89.377517,43.079457],"type":"Point"}
}