{
  "type": "Feature",
  "properties": {
    "iso:country":"US",
    "sg:address":"6161 N 64th St",
    "sg:city":"Milwaukee",
    "sg:classifiers":[
        {
            "category":"Manufacturing",
            "subcategory":"Paper Products",
            "type":"Manufacturing & Wholesale Goods"
        }
    ],
    "sg:phone":"+1 414 431 2267",
    "sg:postcode":"53218",
    "sg:province":"WI",
    "sg:tags":[
        "packaging",
        "materials-wholesale",
        "manufacturer"
    ],
    "wof:name":"Amcor Flexibles Inc.",
    "wof:placetype":"venue"
},
  "geometry": {"coordinates":[-87.990898,43.129501],"type":"Point"}
}