{
  "type": "Feature",
  "properties": {
    "iso:country":"US",
    "sg:address":"3253 150th Ave",
    "sg:city":"Glenwood City",
    "sg:classifiers":[
        {
            "category":"Farming",
            "subcategory":"Dairy Farm",
            "type":"Manufacturing & Wholesale Goods"
        }
    ],
    "sg:phone":"+1 715 265 4631",
    "sg:postcode":"54013",
    "sg:province":"WI",
    "wof:name":"B Drinkman",
    "wof:placetype":"venue"
},
  "geometry": {"coordinates":[-92.14613900000001,45.075426],"type":"Point"}
}