{
  "type": "Feature",
  "properties": {
    "iso:country":"US",
    "sg:address":"704 N Center Ave",
    "sg:city":"Merrill",
    "sg:classifiers":[
        {
            "category":"Retail",
            "subcategory":"Auto Repair",
            "type":"Services"
        }
    ],
    "sg:phone":"+1 715 536 5794",
    "sg:postcode":"54452",
    "sg:province":"WI",
    "sg:tags":[
        "repairing",
        "automobile",
        "general"
    ],
    "wof:name":"Mike's Garage",
    "wof:placetype":"venue"
},
  "geometry": {"coordinates":[-89.68320799999999,45.186877],"type":"Point"}
}