{
  "type": "Feature",
  "properties": {
    "iso:country":"US",
    "sg:address":"313 Madison Ave",
    "sg:city":"Fort Atkinson",
    "sg:classifiers":[
        {
            "category":"Food & Beverages",
            "subcategory":"Groceries & Convenience Stores",
            "type":"Retail Goods"
        }
    ],
    "sg:phone":"+1 920 563 8204",
    "sg:postcode":"53538",
    "sg:province":"WI",
    "sg:tags":[
        "grocer"
    ],
    "wof:name":"Stop N Go",
    "wof:placetype":"venue"
},
  "geometry": {"coordinates":[-88.842053,42.93242],"type":"Point"}
}