{
  "type": "Feature",
  "properties": {
    "iso:country":"US",
    "sg:address":"2740 State Hwy 17",
    "sg:city":"Rhinelander",
    "sg:classifiers":[
        {
            "category":"Building & Trades",
            "subcategory":"Construction",
            "type":"Services"
        }
    ],
    "sg:phone":"+1 715 362 1838",
    "sg:postcode":"54501",
    "sg:province":"WI",
    "sg:tags":[
        "hanging",
        "co",
        "painter",
        "contractor"
    ],
    "wof:name":"Autumn Painting & Drywall",
    "wof:placetype":"venue"
},
  "geometry": {"coordinates":[-89.448748,45.596732],"type":"Point"}
}