{
  "type": "Feature",
  "properties": {
    "addr:full":"770 Brookwood Cir Oneida WI 54155",
    "addr:housenumber":"770",
    "addr:postcode":"54155",
    "addr:street":"Brookwood Cir",
    "iso:country":"US",
    "sg:address":"770 Brookwood Cir",
    "sg:city":"Oneida",
    "sg:classifiers":[
        {
            "category":"Building & Trades",
            "subcategory":"Construction",
            "type":"Services"
        }
    ],
    "sg:phone":"+1 920 405 1924",
    "sg:postcode":"54155",
    "sg:province":"WI",
    "sg:tags":[
        "resurfacing",
        "laying",
        "refinishing",
        "floor"
    ],
    "wof:name":"KOH Woodflooring",
    "wof:placetype":"venue"
},
  "geometry": {"coordinates":[-88.15517800000001,44.544555],"type":"Point"}
}