{
  "type": "Feature",
  "properties": {
    "iso:country":"US",
    "sg:address":"5018 Milward Dr",
    "sg:city":"Madison",
    "sg:classifiers":[
        {
            "category":"Banks & Credit Unions",
            "subcategory":"Investment Brokerage",
            "type":"Services"
        }
    ],
    "sg:phone":"+1 608 277 0200",
    "sg:postcode":"53711",
    "sg:province":"WI",
    "sg:tags":[
        "consultant",
        "planning",
        "financial"
    ],
    "wof:name":"Change Unlimited LTD",
    "wof:placetype":"venue"
},
  "geometry": {"coordinates":[-89.467622,43.047722],"type":"Point"}
}