{
  "type": "Feature",
  "properties": {
    "iso:country":"US",
    "sg:address":"3008 S 26th St",
    "sg:city":"Manitowoc",
    "sg:classifiers":[
        {
            "category":"Freight",
            "type":"Transportation"
        }
    ],
    "sg:phone":"+1 920 684 1605",
    "sg:postcode":"54220",
    "sg:province":"WI",
    "sg:tags":[
        "commercial",
        "storage",
        "special"
    ],
    "wof:name":"A & R Mini Storage",
    "wof:placetype":"venue"
},
  "geometry": {"coordinates":[-87.68092300000001,44.061616],"type":"Point"}
}