{
  "type": "Feature",
  "properties": {
    "iso:country":"US",
    "sg:address":"500 Merritt Ave",
    "sg:city":"Oshkosh",
    "sg:classifiers":[
        {
            "category":"Bars & Pubs",
            "type":"Food & Drink"
        }
    ],
    "sg:phone":"+1 920 235 6550",
    "sg:postcode":"54901",
    "sg:province":"WI",
    "wof:name":"Trail's End",
    "wof:placetype":"venue"
},
  "geometry": {"coordinates":[-88.529893,44.019653],"type":"Point"}
}