{
  "type": "Feature",
  "properties": {
    "iso:country":"US",
    "sg:address":"501 S Military Ave",
    "sg:city":"Green Bay",
    "sg:classifiers":[
        {
            "category":"Insurance",
            "subcategory":"Insurance Agent",
            "type":"Services"
        }
    ],
    "sg:phone":"+1 920 499 0821",
    "sg:postcode":"54303",
    "sg:province":"WI",
    "wof:name":"Mongin Insurance",
    "wof:placetype":"venue"
},
  "geometry": {"coordinates":[-88.06353900000001,44.524513],"type":"Point"}
}