{
  "type": "Feature",
  "properties": {
    "iso:country":"US",
    "sg:address":"533 E Main St",
    "sg:city":"Campbellsport",
    "sg:classifiers":[
        {
            "category":"Bars & Pubs",
            "type":"Food & Drink"
        }
    ],
    "sg:phone":"+1 920 533 5730",
    "sg:postcode":"53010",
    "sg:province":"WI",
    "wof:name":"Woody's On The Pond",
    "wof:placetype":"venue"
},
  "geometry": {"coordinates":[-88.272338,43.597945],"type":"Point"}
}