{
  "type": "Feature",
  "properties": {
    "iso:country":"US",
    "sg:address":"215 Main St",
    "sg:city":"Oconto",
    "sg:classifiers":[
        {
            "category":"Wholesale",
            "subcategory":"Auto Parts",
            "type":"Manufacturing & Wholesale Goods"
        }
    ],
    "sg:phone":"+1 920 834 2741",
    "sg:postcode":"54153",
    "sg:province":"WI",
    "sg:tags":[
        "supply"
    ],
    "wof:name":"Carquest of Oconto",
    "wof:placetype":"venue"
},
  "geometry": {"coordinates":[-87.884038,44.893246],"type":"Point"}
}