{
  "type": "Feature",
  "properties": {
    "iso:country":"US",
    "sg:address":"3104 S Business Dr",
    "sg:city":"Sheboygan",
    "sg:classifiers":[
        {
            "category":"Insurance",
            "subcategory":"Insurance Agent",
            "type":"Services"
        }
    ],
    "sg:phone":"+1 920 208 8900",
    "sg:postcode":"53081",
    "sg:province":"WI",
    "wof:name":"AAA Insurance",
    "wof:placetype":"venue"
},
  "geometry": {"coordinates":[-87.73708600000001,43.721372],"type":"Point"}
}