{
  "type": "Feature",
  "properties": {
    "iso:country":"US",
    "sg:address":"21 E Division Ave",
    "sg:city":"Barron",
    "sg:classifiers":[
        {
            "category":"Shopping",
            "type":"Retail Goods"
        }
    ],
    "sg:phone":"+1 715 537 3394",
    "sg:postcode":"54812",
    "sg:province":"WI",
    "sg:tags":[
        "monument"
    ],
    "wof:name":"Harlo Schultz Monuments",
    "wof:placetype":"venue"
},
  "geometry": {"coordinates":[-91.85788,45.4015],"type":"Point"}
}