{
  "type": "Feature",
  "properties": {
    "iso:country":"US",
    "sg:address":"4843 Escarpement Ter",
    "sg:city":"Sherwood",
    "sg:classifiers":[
        {
            "category":"Building & Trades",
            "subcategory":"Landscaping Services",
            "type":"Services"
        }
    ],
    "sg:phone":"+1 920 989 4333",
    "sg:postcode":"54169",
    "sg:province":"WI",
    "sg:tags":[
        "landscape",
        "contractor"
    ],
    "wof:name":"Jack's Lawn & Landscape Inc",
    "wof:placetype":"venue"
},
  "geometry": {"coordinates":[-88.279611,44.171623],"type":"Point"}
}