{
  "type": "Feature",
  "properties": {
    "addr:full":"1113 Stinson Ave Superior WI 54880",
    "addr:housenumber":"1113",
    "addr:postcode":"54880",
    "addr:street":"Stinson Ave",
    "iso:country":"US",
    "sg:address":"1113 Stinson Ave",
    "sg:city":"Superior",
    "sg:classifiers":[
        {
            "category":"Building & Trades",
            "subcategory":"Cleaning & Sanitation",
            "type":"Services"
        }
    ],
    "sg:phone":"+1 715 394 2826",
    "sg:postcode":"54880",
    "sg:province":"WI",
    "sg:tags":[
        "fireplace",
        "chimney"
    ],
    "wof:name":"Chimney & Stove Specialists",
    "wof:placetype":"venue"
},
  "geometry": {"coordinates":[-92.05463,46.698481],"type":"Point"}
}