{
  "type": "Feature",
  "properties": {
    "iso:country":"US",
    "sg:address":"1127 Pedee Rd",
    "sg:city":"Brodhead",
    "sg:classifiers":[
        {
            "category":"Retail",
            "subcategory":"Animal Services",
            "type":"Services"
        }
    ],
    "sg:phone":"+1 608 897 4122",
    "sg:postcode":"53520",
    "sg:province":"WI",
    "sg:tags":[
        "pet",
        "grooming",
        "washing"
    ],
    "wof:name":"Grooming Room",
    "wof:placetype":"venue"
},
  "geometry": {"coordinates":[-89.4195,42.529539],"type":"Point"}
}