{
  "type": "Feature",
  "properties": {
    "iso:country":"US",
    "sg:address":"703 Grignon St",
    "sg:city":"Kaukauna",
    "sg:classifiers":[
        {
            "category":"Autos & Motor Vehicles",
            "subcategory":"Auto Supplies",
            "type":"Retail Goods"
        }
    ],
    "sg:phone":"+1 920 766 2081",
    "sg:postcode":"54130",
    "sg:province":"WI",
    "wof:name":"T & A Tires LLC",
    "wof:placetype":"venue"
},
  "geometry": {"coordinates":[-88.261581,44.283969],"type":"Point"}
}