{
  "type": "Feature",
  "properties": {
    "iso:country":"US",
    "sg:address":"1919 Mead St",
    "sg:city":"Racine",
    "sg:classifiers":[
        {
            "category":"Restaurant",
            "type":"Food & Drink"
        }
    ],
    "sg:phone":"+1 262 898 1478",
    "sg:postcode":"53403",
    "sg:province":"WI",
    "wof:name":"Mama's Fish & Chicken",
    "wof:placetype":"venue"
},
  "geometry": {"coordinates":[-87.792471,42.706311],"type":"Point"}
}