{
  "type": "Feature",
  "properties": {
    "iso:country":"US",
    "sg:address":"1014 S Read Rd",
    "sg:city":"Janesville",
    "sg:classifiers":[
        {
            "category":"Manufacturing",
            "subcategory":"Glass & Minerals",
            "type":"Manufacturing & Wholesale Goods"
        }
    ],
    "sg:phone":"+1 608 754 8956",
    "sg:postcode":"53546",
    "sg:province":"WI",
    "sg:tags":[
        "ready",
        "concrete",
        "mfg"
    ],
    "wof:name":"Churchill Concrete & Stone",
    "wof:placetype":"venue"
},
  "geometry": {"coordinates":[-88.992758,42.665588],"type":"Point"}
}