{
  "type": "Feature",
  "properties": {
    "iso:country":"US",
    "sg:address":"123 Elm St",
    "sg:city":"Mauston",
    "sg:classifiers":[
        {
            "category":"Retail",
            "subcategory":"Funeral Services",
            "type":"Services"
        }
    ],
    "sg:phone":"+1 608 847 5894",
    "sg:postcode":"53948",
    "sg:province":"WI",
    "sg:tags":[
        "director",
        "home"
    ],
    "wof:name":"Crandall Funeral Home Inc",
    "wof:placetype":"venue"
},
  "geometry": {"coordinates":[-90.077772,43.797669],"type":"Point"}
}