{
  "type": "Feature",
  "properties": {
    "iso:country":"US",
    "sg:address":"660 S Hawley Rd",
    "sg:city":"Milwaukee",
    "sg:classifiers":[
        {
            "category":"Manufacturing",
            "subcategory":"Food",
            "type":"Manufacturing & Wholesale Goods"
        }
    ],
    "sg:phone":"+1 414 975 7827",
    "sg:postcode":"53214",
    "sg:province":"WI",
    "sg:tags":[
        "product",
        "dairy",
        "mfg"
    ],
    "wof:name":"Supplement Discountcom LLC",
    "wof:placetype":"venue"
},
  "geometry": {"coordinates":[-87.985985,43.025317],"type":"Point"}
}