{
  "type": "Feature",
  "properties": {
    "iso:country":"US",
    "sg:address":"4675 Cree Ct",
    "sg:city":"La Valle",
    "sg:classifiers":[
        {
            "category":"Professional",
            "subcategory":"Management & Consulting",
            "type":"Services"
        }
    ],
    "sg:phone":"+1 608 985 8244",
    "sg:postcode":"53941",
    "sg:province":"WI",
    "sg:tags":[
        "medical",
        "administration",
        "business"
    ],
    "wof:name":"Edcon Inc",
    "wof:placetype":"venue"
},
  "geometry": {"coordinates":[-90.084186,43.610703],"type":"Point"}
}