{
  "type": "Feature",
  "properties": {
    "iso:country":"US",
    "sg:address":"12285 Reynolds Rd",
    "sg:city":"Lodi",
    "sg:classifiers":[
        {
            "category":"Farming",
            "subcategory":"Dairy Farm",
            "type":"Manufacturing & Wholesale Goods"
        }
    ],
    "sg:phone":"+1 608 592 3761",
    "sg:postcode":"53555",
    "sg:province":"WI",
    "wof:name":"James Ballweg",
    "wof:placetype":"venue"
},
  "geometry": {"coordinates":[-89.60909599999999,43.304268],"type":"Point"}
}