{
  "type": "Feature",
  "properties": {
    "iso:country":"US",
    "sg:address":"6193 State Rd 108",
    "sg:city":"West Salem",
    "sg:classifiers":[
        {
            "category":"Shopping",
            "type":"Retail Goods"
        }
    ],
    "sg:phone":"+1 608 786 4638",
    "sg:postcode":"54669",
    "sg:province":"WI",
    "sg:tags":[
        "picture",
        "frame"
    ],
    "wof:name":"J & R Custom Framing",
    "wof:placetype":"venue"
},
  "geometry": {"coordinates":[-91.08184799999999,43.944745],"type":"Point"}
}