{
  "type": "Feature",
  "properties": {
    "iso:country":"US",
    "sg:address":"1175 Greenridge Ter",
    "sg:city":"Brookfield",
    "sg:classifiers":[
        {
            "category":"Building & Trades",
            "subcategory":"Landscaping Services",
            "type":"Services"
        }
    ],
    "sg:phone":"+1 262 785 1161",
    "sg:postcode":"53045",
    "sg:province":"WI",
    "wof:name":"R T S Landscapes",
    "wof:placetype":"venue"
},
  "geometry": {"coordinates":[-88.17534999999999,43.045761],"type":"Point"}
}