{
  "type": "Feature",
  "properties": {
    "addr:full":"925 23rd St Chetek WI 54728",
    "addr:housenumber":"925",
    "addr:postcode":"54728",
    "addr:street":"23Rd St",
    "iso:country":"US",
    "sg:address":"925 23rd St",
    "sg:city":"Chetek",
    "sg:classifiers":[
        {
            "category":"Retail",
            "subcategory":"Auto Repair",
            "type":"Services"
        }
    ],
    "sg:phone":"+1 715 924 3359",
    "sg:postcode":"54728",
    "sg:province":"WI",
    "sg:tags":[
        "body",
        "automobile",
        "painting"
    ],
    "wof:name":"Country Auto Crafts",
    "wof:placetype":"venue"
},
  "geometry": {"coordinates":[-91.684737,45.339186],"type":"Point"}
}