{
  "type": "Feature",
  "properties": {
    "iso:country":"US",
    "sg:address":"100 Sunnyside Dr",
    "sg:city":"Kansasville",
    "sg:classifiers":[
        {
            "category":"Real Estate",
            "subcategory":"Real Estate Operator",
            "type":"Services"
        }
    ],
    "sg:phone":"+1 262 534 3750",
    "sg:postcode":"53139",
    "sg:province":"WI",
    "sg:tags":[
        "property",
        "lessor"
    ],
    "wof:name":"Mary Alice Greil Living Trust",
    "wof:placetype":"venue"
},
  "geometry": {"coordinates":[-88.15002800000001,42.721198],"type":"Point"}
}