{
  "type": "Feature",
  "properties": {
    "iso:country":"US",
    "sg:address":"1155 S Springdale Rd",
    "sg:city":"Waukesha",
    "sg:classifiers":[
        {
            "category":"Professional",
            "subcategory":"Management & Consulting",
            "type":"Services"
        }
    ],
    "sg:phone":"+1 262 574 0828",
    "sg:postcode":"53186",
    "sg:province":"WI",
    "wof:name":"Kuehn Consulting LLC",
    "wof:placetype":"venue"
},
  "geometry": {"coordinates":[-88.18651699999999,43.020398],"type":"Point"}
}