{
  "type": "Feature",
  "properties": {
    "iso:country":"US",
    "sg:address":"7021 Nicolai Rd",
    "sg:city":"Manawa",
    "sg:classifiers":[
        {
            "category":"Freight",
            "type":"Transportation"
        }
    ],
    "sg:phone":"+1 920 596 2866",
    "sg:postcode":"54949",
    "sg:province":"WI",
    "wof:name":"Grant Scheller",
    "wof:placetype":"venue"
},
  "geometry": {"coordinates":[-88.868602,44.468116],"type":"Point"}
}