{
  "type": "Feature",
  "properties": {
    "iso:country":"US",
    "sg:address":"139 E Kilbourn Ave",
    "sg:city":"Milwaukee",
    "sg:classifiers":[
        {
            "category":"Shopping",
            "subcategory":"Gifts & Souvenirs",
            "type":"Retail Goods"
        }
    ],
    "sg:phone":"+1 414 223 0272",
    "sg:postcode":"53202",
    "sg:province":"WI",
    "sg:tags":[
        "shop"
    ],
    "wof:name":"Living Rainbow",
    "wof:placetype":"venue"
},
  "geometry": {"coordinates":[-87.910668,43.04209],"type":"Point"}
}