{
  "type": "Feature",
  "properties": {
    "iso:country":"US",
    "sg:address":"150 S Maple St",
    "sg:city":"Oconomowoc",
    "sg:classifiers":[
        {
            "category":"Shopping",
            "subcategory":"Gifts & Souvenirs",
            "type":"Retail Goods"
        }
    ],
    "sg:phone":"+1 262 567 0573",
    "sg:postcode":"53066",
    "sg:province":"WI",
    "wof:name":"Yours Truly Gifts",
    "wof:placetype":"venue"
},
  "geometry": {"coordinates":[-88.511821,43.111417],"type":"Point"}
}