{
  "type": "Feature",
  "properties": {
    "iso:country":"US",
    "sg:address":"404 Kane Rd",
    "sg:city":"Eau Claire",
    "sg:classifiers":[
        {
            "category":"Shopping",
            "subcategory":"Computers & Home Electronics",
            "type":"Retail Goods"
        }
    ],
    "sg:phone":"+1 715 552 3212",
    "sg:postcode":"54703",
    "sg:province":"WI",
    "wof:name":"Kingdom Sound & Lighting",
    "wof:placetype":"venue"
},
  "geometry": {"coordinates":[-91.569079,44.804077],"type":"Point"}
}