{
  "type": "Feature",
  "properties": {
    "addr:full":"796 Milwaukee Ave Burlington WI 53105",
    "addr:housenumber":"796",
    "addr:postcode":"53105",
    "addr:street":"Milwaukee Ave",
    "iso:country":"US",
    "sg:address":"796 Milwaukee Ave",
    "sg:city":"Burlington",
    "sg:classifiers":[
        {
            "category":"Banks & Credit Unions",
            "subcategory":"Financial Services",
            "type":"Services"
        }
    ],
    "sg:phone":"+1 262 763 3200",
    "sg:postcode":"53105",
    "sg:province":"WI",
    "sg:tags":[
        "broker",
        "mortgage"
    ],
    "sg:website":"www.thinkfirstoption.com",
    "wof:name":"First Option Home Loans",
    "wof:placetype":"venue"
},
  "geometry": {"coordinates":[-88.271236,42.68682],"type":"Point"}
}