{
  "type": "Feature",
  "properties": {
    "addr:full":"86715 Island View Rd Bayfield WI 54814",
    "addr:housenumber":"86715",
    "addr:postcode":"54814",
    "addr:street":"Island View Rd",
    "iso:country":"US",
    "sg:address":"86715 Island View Rd",
    "sg:city":"Bayfield",
    "sg:classifiers":[
        {
            "category":"Bars & Pubs",
            "type":"Food & Drink"
        }
    ],
    "sg:phone":"+1 715 779 3325",
    "sg:postcode":"54814",
    "sg:province":"WI",
    "sg:tags":[
        "drinking"
    ],
    "wof:name":"Island View Inn LLC",
    "wof:placetype":"venue"
},
  "geometry": {"coordinates":[-90.798242,46.828072],"type":"Point"}
}