{
  "type": "Feature",
  "properties": {
    "iso:country":"US",
    "sg:address":"87560 Bark Point Rd",
    "sg:city":"Herbster",
    "sg:classifiers":[
        {
            "category":"Building & Trades",
            "subcategory":"Electrical",
            "type":"Services"
        }
    ],
    "sg:phone":"+1 715 774 3421",
    "sg:postcode":"54844",
    "sg:province":"WI",
    "sg:tags":[
        "electrical",
        "contractor"
    ],
    "wof:name":"Paradise Electric",
    "wof:placetype":"venue"
},
  "geometry": {"coordinates":[-91.25022199999999,46.84104],"type":"Point"}
}