{
  "type": "Feature",
  "properties": {
    "iso:country":"US",
    "sg:address":"17430 W Bluemound Rd",
    "sg:city":"Brookfield",
    "sg:classifiers":[
        {
            "category":"Restaurant",
            "type":"Food & Drink"
        }
    ],
    "sg:phone":"+1 262 641 9215",
    "sg:postcode":"53045",
    "sg:province":"WI",
    "wof:name":"Friday's",
    "wof:placetype":"venue"
},
  "geometry": {"coordinates":[-88.133303,43.036362],"type":"Point"}
}