{
  "type": "Feature",
  "properties": {
    "iso:country":"US",
    "sg:address":"2510 Ruger Ave",
    "sg:city":"Janesville",
    "sg:classifiers":[
        {
            "category":"Building & Trades",
            "subcategory":"Landscaping Services",
            "type":"Services"
        }
    ],
    "sg:phone":"+1 608 758 8142",
    "sg:postcode":"53545",
    "sg:province":"WI",
    "sg:tags":[
        "landscape",
        "contractor"
    ],
    "wof:name":"Links Land",
    "wof:placetype":"venue"
},
  "geometry": {"coordinates":[-88.987368,42.685601],"type":"Point"}
}