{
  "type": "Feature",
  "properties": {
    "addr:full":"1325 Pearl St Waukesha WI 53186",
    "addr:housenumber":"1325",
    "addr:postcode":"53186",
    "addr:street":"Pearl St",
    "iso:country":"US",
    "sg:address":"1325 Pearl St",
    "sg:city":"Waukesha",
    "sg:classifiers":[
        {
            "category":"Wholesale",
            "subcategory":"Computers",
            "type":"Manufacturing & Wholesale Goods"
        },
        {
            "category":"Shopping",
            "subcategory":"Computers & Home Electronics",
            "type":"Retail Goods"
        }
    ],
    "sg:phone":"+1 262 524 9363",
    "sg:postcode":"53186",
    "sg:province":"WI",
    "sg:tags":[
        "equipment",
        "dealer"
    ],
    "sg:website":"www.digitalintelligence.com",
    "wof:name":"Digital Intelligence Inc",
    "wof:placetype":"venue"
},
  "geometry": {"coordinates":[-88.201887,43.007788],"type":"Point"}
}