{
  "type": "Feature",
  "properties": {
    "iso:country":"US",
    "sg:address":"7996 Inglehart Rd",
    "sg:city":"Cambria",
    "sg:classifiers":[
        {
            "category":"Farming",
            "subcategory":"Dairy Farm",
            "type":"Manufacturing & Wholesale Goods"
        }
    ],
    "sg:phone":"+1 920 348 5381",
    "sg:postcode":"53923",
    "sg:province":"WI",
    "wof:name":"Robert Wiersma",
    "wof:placetype":"venue"
},
  "geometry": {"coordinates":[-89.127541,43.563795],"type":"Point"}
}