{
  "type": "Feature",
  "properties": {
    "iso:country":"US",
    "sg:address":"19680 W Bluemound Rd",
    "sg:city":"Brookfield",
    "sg:classifiers":[
        {
            "category":"Personal",
            "subcategory":"Beauty Salon",
            "type":"Services"
        }
    ],
    "sg:phone":"+1 262 641 6411",
    "sg:postcode":"53045",
    "sg:province":"WI",
    "sg:tags":[
        "shop",
        "manicuring"
    ],
    "wof:name":"Kerry's Nails",
    "wof:placetype":"venue"
},
  "geometry": {"coordinates":[-88.15876299999999,43.036016],"type":"Point"}
}