{
  "type": "Feature",
  "properties": {
    "iso:country":"US",
    "sg:address":"3524 W National Ave",
    "sg:city":"Milwaukee",
    "sg:classifiers":[
        {
            "category":"Retail",
            "subcategory":"Repair Shop",
            "type":"Services"
        }
    ],
    "sg:phone":"+1 414 671 0533",
    "sg:postcode":"53215",
    "sg:province":"WI",
    "sg:tags":[
        "outboard",
        "motor"
    ],
    "wof:name":"Engine Blade & Prop Outboard",
    "wof:placetype":"venue"
},
  "geometry": {"coordinates":[-87.95862099999999,43.021623],"type":"Point"}
}