{
  "type": "Feature",
  "properties": {
    "iso:country":"US",
    "sg:address":"1625 N Ullman St",
    "sg:city":"Appleton",
    "sg:classifiers":[
        {
            "category":"Retail",
            "subcategory":"Laundry & Dry Cleaning",
            "type":"Services"
        }
    ],
    "sg:phone":"+1 920 954 5888",
    "sg:postcode":"54911",
    "sg:province":"WI",
    "sg:tags":[
        "cleaners",
        "rug",
        "carpet"
    ],
    "wof:name":"Fibertech Carpet Upholstery",
    "wof:placetype":"venue"
},
  "geometry": {"coordinates":[-88.382507,44.277296],"type":"Point"}
}