{
  "type": "Feature",
  "properties": {
    "iso:country":"US",
    "sg:address":"2071 Swallow Dr",
    "sg:city":"Sheboygan",
    "sg:classifiers":[
        {
            "category":"Building & Trades",
            "subcategory":"Construction",
            "type":"Services"
        }
    ],
    "sg:phone":"+1 920 467 0495",
    "sg:postcode":"53083",
    "sg:province":"WI",
    "sg:tags":[
        "hanging",
        "contractor"
    ],
    "wof:name":"Gerhartz Decorating",
    "wof:placetype":"venue"
},
  "geometry": {"coordinates":[-87.798435,43.786701],"type":"Point"}
}