{
  "type": "Feature",
  "properties": {
    "addr:full":"423 E Main St Chilton WI 53010",
    "addr:housenumber":"423",
    "addr:postcode":"53010",
    "addr:street":"E Main St",
    "iso:country":"US",
    "sg:address":"423 E Main St",
    "sg:city":"Chilton",
    "sg:classifiers":[
        {
            "category":"Autos & Motor Vehicles",
            "subcategory":"Automobile Sales",
            "type":"Retail Goods"
        }
    ],
    "sg:phone":"+1 920 849 9955",
    "sg:postcode":"53010",
    "sg:province":"WI",
    "sg:tags":[
        "car",
        "dealer"
    ],
    "wof:name":"Crazy Brys Auto LLP",
    "wof:placetype":"venue"
},
  "geometry": {"coordinates":[-88.276397,43.598012],"type":"Point"}
}