{
  "type": "Feature",
  "properties": {
    "iso:country":"US",
    "sg:address":"123 Grand Ave",
    "sg:city":"Wausau",
    "sg:classifiers":[
        {
            "category":"Professional",
            "subcategory":"Lawyer & Legal Services",
            "type":"Services"
        }
    ],
    "sg:phone":"+1 715 845 9621",
    "sg:postcode":"54403",
    "sg:province":"WI",
    "sg:tags":[
        "attorney"
    ],
    "wof:name":"Schmidt & Schmidt",
    "wof:placetype":"venue"
},
  "geometry": {"coordinates":[-89.62451,44.956258],"type":"Point"}
}