{
  "type": "Feature",
  "properties": {
    "addr:full":"13051 Featherly Dr Minong WI 54859",
    "addr:housenumber":"13051",
    "addr:postcode":"54859",
    "addr:street":"Featherly Dr",
    "iso:country":"US",
    "sg:address":"13051 Featherly Dr",
    "sg:city":"Minong",
    "sg:classifiers":[
        {
            "category":"Real Estate",
            "subcategory":"Real Estate Agent",
            "type":"Services"
        }
    ],
    "sg:phone":"+1 715 466 5502",
    "sg:postcode":"54859",
    "sg:province":"WI",
    "sg:tags":[
        "authorities",
        "housing"
    ],
    "wof:name":"Edgewood Apartments",
    "wof:placetype":"venue"
},
  "geometry": {"coordinates":[-91.83701000000001,46.103676],"type":"Point"}
}