{
  "type": "Feature",
  "properties": {
    "iso:country":"US",
    "sg:address":"102 E Clark St",
    "sg:city":"Alma Center",
    "sg:classifiers":[
        {
            "category":"Wholesale",
            "subcategory":"Farm Supplies",
            "type":"Manufacturing & Wholesale Goods"
        }
    ],
    "sg:phone":"+1 715 964 1119",
    "sg:postcode":"54611",
    "sg:province":"WI",
    "sg:tags":[
        "feed",
        "fertilizer",
        "oil",
        "fuel"
    ],
    "wof:name":"Melrose Farm Service Inc",
    "wof:placetype":"venue"
},
  "geometry": {"coordinates":[-90.912725,44.437815],"type":"Point"}
}