{
  "type": "Feature",
  "properties": {
    "addr:full":"1218 W Main St Whitewater WI 53190",
    "addr:housenumber":"1218",
    "addr:postcode":"53190",
    "addr:street":"W Main St",
    "iso:country":"US",
    "sg:address":"1218 W Main St",
    "sg:city":"Whitewater",
    "sg:classifiers":[
        {
            "category":"Health Services",
            "subcategory":"Doctor",
            "type":"Services"
        }
    ],
    "sg:phone":"+1 262 473 5464",
    "sg:postcode":"53190",
    "sg:province":"WI",
    "sg:tags":[
        "dentist"
    ],
    "wof:name":"R A Nosek DDS",
    "wof:placetype":"venue"
},
  "geometry": {"coordinates":[-88.754071,42.834772],"type":"Point"}
}