{
  "type": "Feature",
  "properties": {
    "iso:country":"US",
    "sg:address":"3280 S Clement Ave",
    "sg:city":"Milwaukee",
    "sg:classifiers":[
        {
            "category":"Freight",
            "type":"Transportation"
        }
    ],
    "sg:phone":"+1 414 747 2202",
    "sg:postcode":"53207",
    "sg:province":"WI",
    "sg:tags":[
        "auto",
        "general"
    ],
    "wof:name":"Mopar Parts",
    "wof:placetype":"venue"
},
  "geometry": {"coordinates":[-87.894228,42.986378],"type":"Point"}
}