{
  "type": "Feature",
  "properties": {
    "addr:full":"5768 Deer Rd Hartford WI 53027",
    "addr:housenumber":"5768",
    "addr:postcode":"53027",
    "addr:street":"Deer Rd",
    "iso:country":"US",
    "sg:address":"5768 Deer Rd",
    "sg:city":"Hartford",
    "sg:classifiers":[
        {
            "category":"Building & Trades",
            "subcategory":"Electrical",
            "type":"Services"
        }
    ],
    "sg:phone":"+1 262 644 8940",
    "sg:postcode":"53027",
    "sg:province":"WI",
    "sg:tags":[
        "electrical",
        "contractor"
    ],
    "wof:name":"Tennies Electric",
    "wof:placetype":"venue"
},
  "geometry": {"coordinates":[-88.32123199999999,43.384198],"type":"Point"}
}