{
  "type": "Feature",
  "properties": {
    "iso:country":"US",
    "sg:address":"23327 Co Hwy Aa",
    "sg:city":"Richland Center",
    "sg:classifiers":[
        {
            "category":"Building & Trades",
            "subcategory":"Construction",
            "type":"Services"
        }
    ],
    "sg:phone":"+1 608 647 4036",
    "sg:postcode":"53581",
    "sg:province":"WI",
    "sg:tags":[
        "house"
    ],
    "wof:name":"Fry & Fry Bldg Cont",
    "wof:placetype":"venue"
},
  "geometry": {"coordinates":[-90.379965,43.360662],"type":"Point"}
}