{
  "type": "Feature",
  "properties": {
    "iso:country":"US",
    "sg:address":"316 E Silver Spring Dr",
    "sg:city":"Milwaukee",
    "sg:classifiers":[
        {
            "category":"Health Services",
            "subcategory":"Doctor",
            "type":"Services"
        }
    ],
    "sg:phone":"+1 414 962 9244",
    "sg:postcode":"53217",
    "sg:province":"WI",
    "sg:tags":[
        "dentist"
    ],
    "wof:name":"Richard J Krainz DDS",
    "wof:placetype":"venue"
},
  "geometry": {"coordinates":[-87.905551,43.118582],"type":"Point"}
}