{
  "type": "Feature",
  "properties": {
    "iso:country":"US",
    "sg:address":"448 W Washington Ave",
    "sg:city":"Madison",
    "sg:classifiers":[
        {
            "category":"Professional",
            "subcategory":"Lawyer & Legal Services",
            "type":"Services"
        }
    ],
    "sg:phone":"+1 608 255 2773",
    "sg:postcode":"53703",
    "sg:province":"WI",
    "sg:tags":[
        "attorney"
    ],
    "wof:name":"Karpe Law Office",
    "wof:placetype":"venue"
},
  "geometry": {"coordinates":[-89.389984,43.070773],"type":"Point"}
}