{
  "type": "Feature",
  "properties": {
    "iso:country":"US",
    "sg:address":"14165 Lindsay Dr",
    "sg:city":"Brookfield",
    "sg:classifiers":[
        {
            "category":"Real Estate",
            "subcategory":"Real Estate Agent",
            "type":"Services"
        }
    ],
    "sg:phone":"+1 262 783 5595",
    "sg:postcode":"53005",
    "sg:province":"WI",
    "wof:name":"Wiesners Real Estate",
    "wof:placetype":"venue"
},
  "geometry": {"coordinates":[-88.089087,43.082922],"type":"Point"}
}