{
  "type": "Feature",
  "properties": {
    "addr:full":"1001 Schuster Rd Sun Prairie WI 53590",
    "addr:housenumber":"1001",
    "addr:postcode":"53590",
    "addr:street":"Schuster Rd",
    "iso:country":"US",
    "sg:address":"1001 Schuster Rd",
    "sg:city":"Sun Prairie",
    "sg:classifiers":[
        {
            "category":"Building & Trades",
            "subcategory":"Plumbing",
            "type":"Services"
        }
    ],
    "sg:phone":"+1 608 216 0787",
    "sg:postcode":"53590",
    "sg:province":"WI",
    "sg:tags":[
        "plumbing",
        "contractor"
    ],
    "wof:name":"Advantage Plumbing",
    "wof:placetype":"venue"
},
  "geometry": {"coordinates":[-89.190448,43.191853],"type":"Point"}
}