{
  "type": "Feature",
  "properties": {
    "iso:country":"US",
    "sg:address":"2390 S 179 St",
    "sg:city":"New Berlin",
    "sg:classifiers":[
        {
            "category":"Wholesale",
            "subcategory":"Hardware",
            "type":"Manufacturing & Wholesale Goods"
        }
    ],
    "sg:phone":"+1 262 782 1975",
    "sg:postcode":"53146",
    "sg:province":"WI",
    "sg:tags":[
        "installs",
        "automotive",
        "air",
        "conditioner"
    ],
    "wof:name":"Advance Auto Air Conditioning",
    "wof:placetype":"venue"
},
  "geometry": {"coordinates":[-88.13461,42.999353],"type":"Point"}
}