{
  "type": "Feature",
  "properties": {
    "iso:country":"US",
    "sg:address":"558 Eisenhower Dr",
    "sg:city":"Kimberly",
    "sg:classifiers":[
        {
            "category":"Arts & Performance",
            "subcategory":"Theater",
            "type":"Entertainment"
        }
    ],
    "sg:phone":"+1 920 734 7742",
    "sg:postcode":"54136",
    "sg:province":"WI",
    "sg:tags":[
        "bureau"
    ],
    "wof:name":"Vic Ferrari Band",
    "wof:placetype":"venue"
},
  "geometry": {"coordinates":[-88.347011,44.262986],"type":"Point"}
}