{
  "type": "Feature",
  "properties": {
    "iso:country":"US",
    "sg:address":"2074 N Commerce St",
    "sg:city":"Milwaukee",
    "sg:classifiers":[
        {
            "category":"Restaurant",
            "type":"Food & Drink"
        }
    ],
    "sg:phone":"+1 414 403 7555",
    "sg:postcode":"53212",
    "sg:province":"WI",
    "sg:tags":[
        "eating"
    ],
    "wof:name":"Soup Kitchen",
    "wof:placetype":"venue"
},
  "geometry": {"coordinates":[-87.89834,43.057844],"type":"Point"}
}