{
  "type": "Feature",
  "properties": {
    "iso:country":"US",
    "sg:address":"111 N Main St",
    "sg:city":"Fond Du Lac",
    "sg:classifiers":[
        {
            "category":"Bars & Pubs",
            "type":"Food & Drink"
        }
    ],
    "sg:phone":"+1 920 921 6588",
    "sg:postcode":"54935",
    "sg:province":"WI",
    "wof:name":"Three Aces North",
    "wof:placetype":"venue"
},
  "geometry": {"coordinates":[-88.447,43.782284],"type":"Point"}
}