{
  "type": "Feature",
  "properties": {
    "iso:country":"US",
    "sg:address":"103 Cimmaron Ct",
    "sg:city":"Oshkosh",
    "sg:classifiers":[
        {
            "category":"Real Estate",
            "subcategory":"Real Estate Agent",
            "type":"Services"
        }
    ],
    "sg:phone":"+1 920 303 0816",
    "sg:postcode":"54902",
    "sg:province":"WI",
    "sg:tags":[
        "management"
    ],
    "wof:name":"Hunt Realty & Management",
    "wof:placetype":"venue"
},
  "geometry": {"coordinates":[-88.538561,43.99017],"type":"Point"}
}