{
  "type": "Feature",
  "properties": {
    "iso:country":"US",
    "sg:address":"370 Vine St",
    "sg:city":"Reedsburg",
    "sg:classifiers":[
        {
            "category":"Communications",
            "subcategory":"Television Station",
            "type":"Services"
        }
    ],
    "sg:phone":"+1 608 524 7777",
    "sg:postcode":"53959",
    "sg:province":"WI",
    "sg:tags":[
        "broadcasting",
        "co"
    ],
    "wof:name":"W K O W Television Inc",
    "wof:placetype":"venue"
},
  "geometry": {"coordinates":[-90.00582,43.531474],"type":"Point"}
}