{
  "type": "Feature",
  "properties": {
    "iso:country":"US",
    "sg:address":"721 Field Ave",
    "sg:city":"Hillsboro",
    "sg:classifiers":[
        {
            "category":"Building & Trades",
            "subcategory":"Construction",
            "type":"Services"
        }
    ],
    "sg:phone":"+1 608 489 3299",
    "sg:postcode":"54634",
    "sg:province":"WI",
    "sg:tags":[
        "floor",
        "laying",
        "contractor"
    ],
    "wof:name":"Knutson Hardwood Floors",
    "wof:placetype":"venue"
},
  "geometry": {"coordinates":[-90.344433,43.65252],"type":"Point"}
}