{
  "type": "Feature",
  "properties": {
    "iso:country":"US",
    "sg:address":"725 Kaufman Rd",
    "sg:city":"Augusta",
    "sg:classifiers":[
        {
            "category":"Manufacturing",
            "subcategory":"Furniture",
            "type":"Manufacturing & Wholesale Goods"
        }
    ],
    "sg:phone":"+1 715 667 5129",
    "sg:postcode":"54722",
    "sg:province":"WI",
    "wof:name":"M & W Oak Dining Furniture",
    "wof:placetype":"venue"
},
  "geometry": {"coordinates":[-91.054012,44.828692],"type":"Point"}
}