{
  "type": "Feature",
  "properties": {
    "addr:full":"5412 79th St Kenosha WI 53142",
    "addr:housenumber":"5412",
    "addr:postcode":"53142",
    "addr:street":"79Th St",
    "iso:country":"US",
    "sg:address":"5412 79th St",
    "sg:city":"Kenosha",
    "sg:classifiers":[
        {
            "category":"Manufacturing",
            "subcategory":"Tools & Machinery",
            "type":"Manufacturing & Wholesale Goods"
        }
    ],
    "sg:phone":"+1 262 694 4457",
    "sg:postcode":"53142",
    "sg:province":"WI",
    "sg:tags":[
        "industrial",
        "mfg"
    ],
    "wof:name":"Milos Machining",
    "wof:placetype":"venue"
},
  "geometry": {"coordinates":[-87.871154,42.560059],"type":"Point"}
}