{
  "type": "Feature",
  "properties": {
    "addr:full":"15420 W Capitol Dr Brookfield WI 53005",
    "addr:housenumber":"15420",
    "addr:postcode":"53005",
    "addr:street":"W Capitol Dr",
    "iso:country":"US",
    "sg:address":"15420 W Capitol Dr",
    "sg:city":"Brookfield",
    "sg:classifiers":[
        {
            "category":"Professional",
            "subcategory":"Accounting & Tax Preparation",
            "type":"Services"
        }
    ],
    "sg:phone":"+1 262 784 6210",
    "sg:postcode":"53005",
    "sg:province":"WI",
    "sg:tags":[
        "firm"
    ],
    "wof:name":"Ashland Freyburg Hinkle",
    "wof:placetype":"venue"
},
  "geometry": {"coordinates":[-88.104992,43.0895],"type":"Point"}
}