{
  "type": "Feature",
  "properties": {
    "iso:country":"US",
    "sg:address":"18339 Melby St",
    "sg:city":"Whitehall",
    "sg:classifiers":[
        {
            "category":"Farming",
            "subcategory":"Farm",
            "type":"Manufacturing & Wholesale Goods"
        }
    ],
    "sg:phone":"+1 715 538 2258",
    "sg:postcode":"54773",
    "sg:province":"WI",
    "sg:tags":[
        "crop",
        "general"
    ],
    "wof:name":"Emily L Filla",
    "wof:placetype":"venue"
},
  "geometry": {"coordinates":[-91.31421899999999,44.365387],"type":"Point"}
}