{
  "type": "Feature",
  "properties": {
    "iso:country":"US",
    "sg:address":"1802 Roosevelt Ave",
    "sg:city":"New Holstein",
    "sg:classifiers":[
        {
            "category":"Wholesale",
            "subcategory":"Scrap",
            "type":"Manufacturing & Wholesale Goods"
        }
    ],
    "sg:phone":"+1 920 898 5498",
    "sg:postcode":"53061",
    "sg:province":"WI",
    "sg:tags":[
        "metal",
        "iron"
    ],
    "wof:name":"Mid-Shores Disposal Inc",
    "wof:placetype":"venue"
},
  "geometry": {"coordinates":[-88.090538,43.953507],"type":"Point"}
}