{
  "type": "Feature",
  "properties": {
    "addr:full":"2024 Northpoint St Oshkosh WI 54901",
    "addr:housenumber":"2024",
    "addr:postcode":"54901",
    "addr:street":"Northpoint St",
    "iso:country":"US",
    "sg:address":"2024 Northpoint St",
    "sg:city":"Oshkosh",
    "sg:classifiers":[
        {
            "category":"Building & Trades",
            "subcategory":"Pest Control",
            "type":"Services"
        }
    ],
    "sg:phone":"+1 920 232 1383",
    "sg:postcode":"54901",
    "sg:province":"WI",
    "sg:tags":[
        "trapper",
        "animal"
    ],
    "wof:name":"Geffers Nuisance Animal Rmvl",
    "wof:placetype":"venue"
},
  "geometry": {"coordinates":[-88.51824499999999,44.041604],"type":"Point"}
}