{
  "type": "Feature",
  "properties": {
    "iso:country":"US",
    "sg:address":"3620 Mall Dr",
    "sg:city":"Eau Claire",
    "sg:classifiers":[
        {
            "category":"Autos & Motor Vehicles",
            "subcategory":"Motorcycle Sales",
            "type":"Retail Goods"
        }
    ],
    "sg:phone":"+1 715 835 1442",
    "sg:postcode":"54701",
    "sg:province":"WI",
    "sg:tags":[
        "dealer"
    ],
    "wof:name":"Eau Claire Cycle",
    "wof:placetype":"venue"
},
  "geometry": {"coordinates":[-91.460813,44.779586],"type":"Point"}
}