{
  "type": "Feature",
  "properties": {
    "iso:country":"US",
    "sg:address":"946 S Waukechon St",
    "sg:city":"Shawano",
    "sg:classifiers":[
        {
            "category":"Freight",
            "type":"Transportation"
        }
    ],
    "sg:phone":"+1 715 524 6542",
    "sg:postcode":"54166",
    "sg:province":"WI",
    "sg:tags":[
        "commercial",
        "storage"
    ],
    "wof:name":"Burris Storage",
    "wof:placetype":"venue"
},
  "geometry": {"coordinates":[-88.588559,44.773815],"type":"Point"}
}