{
  "type": "Feature",
  "properties": {
    "iso:country":"US",
    "sg:address":"4128 Lakeshore Dr",
    "sg:city":"Rhinelander",
    "sg:classifiers":[
        {
            "category":"Travel",
            "subcategory":"Hotels & Motels",
            "type":"Entertainment"
        }
    ],
    "sg:phone":"+1 715 369 0404",
    "sg:postcode":"54501",
    "sg:province":"WI",
    "sg:tags":[
        "operation"
    ],
    "wof:name":"R and R Resort",
    "wof:placetype":"venue"
},
  "geometry": {"coordinates":[-89.32364699999999,45.659396],"type":"Point"}
}