{
  "type": "Feature",
  "properties": {
    "addr:full":"7630 W Mill Rd Milwaukee WI 53218",
    "addr:housenumber":"7630",
    "addr:postcode":"53218",
    "addr:street":"W Mill Rd",
    "iso:country":"US",
    "sg:address":"7630 W Mill Rd",
    "sg:city":"Milwaukee",
    "sg:classifiers":[
        {
            "category":"Health Services",
            "subcategory":"Clinic",
            "type":"Services"
        }
    ],
    "sg:phone":"+1 414 286 8830",
    "sg:postcode":"53218",
    "sg:province":"WI",
    "sg:tags":[
        "outpatient",
        "specialty"
    ],
    "sg:website":"http://www.ci.mil.wi.us",
    "wof:name":"Northwest Health Ctr",
    "wof:placetype":"venue"
},
  "geometry": {"coordinates":[-88.006311,43.134209],"type":"Point"}
}