{
  "type": "Feature",
  "properties": {
    "iso:country":"US",
    "sg:address":"6448 Wolf Lake Rd",
    "sg:city":"Wausaukee",
    "sg:classifiers":[
        {
            "category":"Professional",
            "subcategory":"Art Services",
            "type":"Services"
        }
    ],
    "sg:phone":"+1 715 856 6777",
    "sg:postcode":"54177",
    "sg:province":"WI",
    "sg:tags":[
        "photography",
        "commercial"
    ],
    "wof:name":"Little Wolf Photograph",
    "wof:placetype":"venue"
},
  "geometry": {"coordinates":[-87.912214,45.422987],"type":"Point"}
}