{
  "type": "Feature",
  "properties": {
    "iso:country":"US",
    "sg:address":"4126 52nd St",
    "sg:city":"Kenosha",
    "sg:classifiers":[
        {
            "category":"Shopping",
            "subcategory":"Computers & Home Electronics",
            "type":"Retail Goods"
        }
    ],
    "sg:phone":"+1 262 652 3900",
    "sg:postcode":"53144",
    "sg:province":"WI",
    "wof:name":"Radio Shack",
    "wof:placetype":"venue"
},
  "geometry": {"coordinates":[-87.859549,42.588472],"type":"Point"}
}