{
  "type": "Feature",
  "properties": {
    "iso:country":"US",
    "sg:address":"303 S Main St",
    "sg:city":"Amherst",
    "sg:classifiers":[
        {
            "category":"Travel",
            "subcategory":"Hotels & Motels",
            "type":"Entertainment"
        }
    ],
    "sg:phone":"+1 715 824 2326",
    "sg:postcode":"54406",
    "sg:province":"WI",
    "sg:tags":[
        "breakfast",
        "accommodation",
        "bed"
    ],
    "wof:name":"Amherst Inn",
    "wof:placetype":"venue"
},
  "geometry": {"coordinates":[-89.28590699999999,44.449034],"type":"Point"}
}