{
  "type": "Feature",
  "properties": {
    "iso:country":"US",
    "sg:address":"2030 E Mason St",
    "sg:city":"Green Bay",
    "sg:classifiers":[
        {
            "category":"Ice Cream",
            "type":"Food & Drink"
        }
    ],
    "sg:menulink":"http://www.allmenus.com/wi/green-bay/192604-dairy-queen/menu/",
    "sg:phone":"+1 920 465 6404",
    "sg:postcode":"54302",
    "sg:province":"WI",
    "sg:tags":[
        "burger",
        "american"
    ],
    "wof:name":"Dairy Queen",
    "wof:placetype":"venue"
},
  "geometry": {"coordinates":[-87.97456200000001,44.490061],"type":"Point"}
}