{
  "type": "Feature",
  "properties": {
    "addr:full":"1235 E Howard Ave Milwaukee WI 53207",
    "addr:housenumber":"1235",
    "addr:postcode":"53207",
    "addr:street":"E Howard Ave",
    "iso:country":"US",
    "sg:address":"1235 E Howard Ave",
    "sg:city":"Milwaukee",
    "sg:classifiers":[
        {
            "category":"Organizations",
            "subcategory":"Community Association",
            "type":"Services"
        }
    ],
    "sg:phone":"+1 414 744 4609",
    "sg:postcode":"53207",
    "sg:province":"WI",
    "sg:tags":[
        "fraternal"
    ],
    "wof:name":"Masonic Lodge",
    "wof:placetype":"venue"
},
  "geometry": {"coordinates":[-87.89315000000001,42.973654],"type":"Point"}
}