{
  "type": "Feature",
  "properties": {
    "iso:country":"US",
    "sg:address":"201 S Main St",
    "sg:city":"Chaseburg",
    "sg:classifiers":[
        {
            "category":"Professional",
            "subcategory":"Lawyer & Legal Services",
            "type":"Services"
        }
    ],
    "sg:phone":"+1 608 483 2105",
    "sg:postcode":"54621",
    "sg:province":"WI",
    "wof:name":"Papenfuss Francis D",
    "wof:placetype":"venue"
},
  "geometry": {"coordinates":[-91.09960100000001,43.652826],"type":"Point"}
}