{
  "type": "Feature",
  "properties": {
    "iso:country":"US",
    "sg:address":"306 Schofield St",
    "sg:city":"Chetek",
    "sg:classifiers":[
        {
            "category":"Organizations",
            "subcategory":"Religious Organization",
            "type":"Services"
        }
    ],
    "sg:phone":"+1 715 924 3804",
    "sg:postcode":"54728",
    "sg:province":"WI",
    "wof:name":"Red Cedar Presbyterian Church",
    "wof:placetype":"venue"
},
  "geometry": {"coordinates":[-91.653644,45.322724],"type":"Point"}
}