{
  "type": "Feature",
  "properties": {
    "addr:full":"2045 32nd St S La Crosse WI 54601",
    "addr:housenumber":"2045",
    "addr:postcode":"54601",
    "addr:street":"32Nd St S",
    "iso:country":"US",
    "sg:address":"2045 32nd St S",
    "sg:city":"La Crosse",
    "sg:classifiers":[
        {
            "category":"Health Services",
            "subcategory":"Chiropractor",
            "type":"Services"
        }
    ],
    "sg:phone":"+1 608 788 7118",
    "sg:postcode":"54601",
    "sg:province":"WI",
    "wof:name":"Barge & Barge Chiropractic Ctr",
    "wof:placetype":"venue"
},
  "geometry": {"coordinates":[-91.209253,43.790503],"type":"Point"}
}