{
  "type": "Feature",
  "properties": {
    "iso:country":"US",
    "sg:address":"2234 Co Rd K",
    "sg:city":"Durand",
    "sg:phone":"+1 715 673 4953",
    "sg:postcode":"54736",
    "sg:province":"WI",
    "sg:tags":[
        "farm",
        "field",
        "grain",
        "cash",
        "crop"
    ],
    "wof:name":"Terry Sobottka",
    "wof:placetype":"venue"
},
  "geometry": {"coordinates":[-91.979197,44.506005],"type":"Point"}
}