{
  "type": "Feature",
  "properties": {
    "addr:full":"5840 N 60th St Milwaukee WI 53218",
    "addr:housenumber":"5840",
    "addr:postcode":"53218",
    "addr:street":"N 60Th St",
    "iso:country":"US",
    "sg:address":"5840 N 60th St",
    "sg:city":"Milwaukee",
    "sg:classifiers":[
        {
            "category":"Manufacturing",
            "subcategory":"Rubber & Plastics",
            "type":"Manufacturing & Wholesale Goods"
        }
    ],
    "sg:phone":"+1 414 463 1000",
    "sg:postcode":"53218",
    "sg:province":"WI",
    "sg:tags":[
        "product",
        "mfg",
        "molded",
        "precision"
    ],
    "sg:website":"www.pereles.com",
    "wof:name":"Pereles Brothers Inc",
    "wof:placetype":"venue"
},
  "geometry": {"coordinates":[-87.985821,43.126293],"type":"Point"}
}