{
  "type": "Feature",
  "properties": {
    "addr:full":"1009 W Glen Oaks Ln Ste 201 Mequon WI 53092",
    "addr:housenumber":"1009",
    "addr:postcode":"53092",
    "addr:street":"W Glen Oaks Ln Ste 201",
    "iso:country":"US",
    "sg:address":"1009 W Glen Oaks Ln Ste 201",
    "sg:city":"Mequon",
    "sg:classifiers":[
        {
            "category":"Real Estate",
            "subcategory":"Real Estate Services",
            "type":"Services"
        }
    ],
    "sg:phone":"+1 262 240 9678",
    "sg:postcode":"53092",
    "sg:province":"WI",
    "sg:website":"www.ferrici.com",
    "wof:name":"Ferrici & Associates",
    "wof:placetype":"venue"
},
  "geometry": {"coordinates":[-87.920648,43.235714],"type":"Point"}
}