{
  "type": "Feature",
  "properties": {
    "iso:country":"US",
    "sg:address":"1313 Conde St",
    "sg:city":"Janesville",
    "sg:classifiers":[
        {
            "category":"Shopping",
            "subcategory":"Hobbies, Toys, & Games",
            "type":"Retail Goods"
        }
    ],
    "sg:phone":"+1 608 757 2321",
    "sg:postcode":"53546",
    "sg:province":"WI",
    "wof:name":"Smart Stick Co LLC",
    "wof:placetype":"venue"
},
  "geometry": {"coordinates":[-89.03605,42.652918],"type":"Point"}
}