{
  "type": "Feature",
  "properties": {
    "iso:country":"US",
    "sg:address":"2664 Wildflower Rd",
    "sg:city":"Sheldon",
    "sg:classifiers":[
        {
            "category":"Farming",
            "subcategory":"Livestock Farm",
            "type":"Manufacturing & Wholesale Goods"
        }
    ],
    "sg:phone":"+1 715 668 5574",
    "sg:postcode":"54766",
    "sg:province":"WI",
    "sg:tags":[
        "beef",
        "feedlot",
        "cattle"
    ],
    "wof:name":"Fran Holm Inc",
    "wof:placetype":"venue"
},
  "geometry": {"coordinates":[-90.813011,45.407185],"type":"Point"}
}