{
  "type": "Feature",
  "properties": {
    "iso:country":"US",
    "sg:address":"630 Jensen Dr",
    "sg:city":"Medford",
    "sg:classifiers":[
        {
            "category":"Government",
            "subcategory":"Office",
            "type":"Public Place"
        }
    ],
    "sg:phone":"+1 715 748 2546",
    "sg:postcode":"54451",
    "sg:province":"WI",
    "sg:tags":[
        "federal",
        "security"
    ],
    "wof:name":"US National Guard Armory",
    "wof:placetype":"venue"
},
  "geometry": {"coordinates":[-90.355484,45.125214],"type":"Point"}
}