{
  "type": "Feature",
  "properties": {
    "addr:full":"3731 Gateway Dr Eau Claire WI 54701",
    "addr:housenumber":"3731",
    "addr:postcode":"54701",
    "addr:street":"Gateway Dr",
    "iso:country":"US",
    "sg:address":"3731 Gateway Dr",
    "sg:city":"Eau Claire",
    "sg:classifiers":[
        {
            "category":"Retail",
            "subcategory":"Animal Services",
            "type":"Services"
        }
    ],
    "sg:phone":"+1 715 832 6633",
    "sg:postcode":"54701",
    "sg:province":"WI",
    "wof:name":"Pet Grooming Food Warehouse",
    "wof:placetype":"venue"
},
  "geometry": {"coordinates":[-91.43151899999999,44.77808],"type":"Point"}
}