{
  "type": "Feature",
  "properties": {
    "iso:country":"US",
    "sg:address":"3025 Fear St",
    "sg:city":"Eau Claire",
    "sg:classifiers":[
        {
            "category":"Personal",
            "type":"Services"
        }
    ],
    "sg:phone":"+1 715 552 1441",
    "sg:postcode":"54701",
    "sg:province":"WI",
    "wof:name":"Body Essentials Massage",
    "wof:placetype":"venue"
},
  "geometry": {"coordinates":[-91.47674600000001,44.786514],"type":"Point"}
}