{
  "type": "Feature",
  "properties": {
    "iso:country":"US",
    "sg:address":"22600 Sobye Ln",
    "sg:city":"Galesville",
    "sg:classifiers":[
        {
            "category":"Real Estate",
            "subcategory":"Real Estate Operator",
            "type":"Services"
        }
    ],
    "sg:phone":"+1 608 539 2810",
    "sg:postcode":"54630",
    "sg:province":"WI",
    "sg:tags":[
        "building",
        "nonresidential"
    ],
    "wof:name":"Brush Properties LLC",
    "wof:placetype":"venue"
},
  "geometry": {"coordinates":[-91.403116,44.129511],"type":"Point"}
}