{
  "type": "Feature",
  "properties": {
    "iso:country":"US",
    "sg:address":"15350 W Howard Ave",
    "sg:city":"New Berlin",
    "sg:classifiers":[
        {
            "category":"Banks & Credit Unions",
            "subcategory":"Bank",
            "type":"Services"
        }
    ],
    "sg:phone":"+1 262 641 2082",
    "sg:postcode":"53151",
    "sg:province":"WI",
    "wof:name":"M & I Bank",
    "wof:placetype":"venue"
},
  "geometry": {"coordinates":[-88.08983499999999,42.973597],"type":"Point"}
}