{
  "type": "Feature",
  "properties": {
    "addr:full":"631 N Mayfair Rd Milwaukee WI 53226",
    "addr:housenumber":"631",
    "addr:postcode":"53226",
    "addr:street":"N Mayfair Rd",
    "iso:country":"US",
    "sg:address":"631 N Mayfair Rd",
    "sg:city":"Milwaukee",
    "sg:classifiers":[
        {
            "category":"Building & Trades",
            "subcategory":"Construction",
            "type":"Services"
        }
    ],
    "sg:phone":"+1 414 774 1720",
    "sg:postcode":"53226",
    "sg:province":"WI",
    "sg:tags":[
        "house"
    ],
    "wof:name":"Craftsman Homes LLC",
    "wof:placetype":"venue"
},
  "geometry": {"coordinates":[-88.047089,43.035341],"type":"Point"}
}