{
  "type": "Feature",
  "properties": {
    "iso:country":"US",
    "sg:address":"6329 Co Rd B",
    "sg:city":"Jefferson",
    "sg:classifiers":[
        {
            "category":"Professional",
            "subcategory":"Business Services",
            "type":"Services"
        }
    ],
    "sg:phone":"+1 920 648 6160",
    "sg:postcode":"53549",
    "sg:province":"WI",
    "wof:name":"Deltech Engineering Inc",
    "wof:placetype":"venue"
},
  "geometry": {"coordinates":[-88.85825199999999,43.072784],"type":"Point"}
}