{
  "type": "Feature",
  "properties": {
    "iso:country":"US",
    "sg:address":"8081 Freedom Rd",
    "sg:city":"North Freedom",
    "sg:classifiers":[
        {
            "category":"Farming",
            "subcategory":"Livestock Farm",
            "type":"Manufacturing & Wholesale Goods"
        }
    ],
    "sg:phone":"+1 608 544 3783",
    "sg:postcode":"53951",
    "sg:province":"WI",
    "sg:tags":[
        "beef",
        "feedlot",
        "cattle"
    ],
    "wof:name":"Donald Jaedike",
    "wof:placetype":"venue"
},
  "geometry": {"coordinates":[-89.86169700000001,43.367101],"type":"Point"}
}