{
  "type": "Feature",
  "properties": {
    "iso:country":"US",
    "sg:address":"418 N 8th St",
    "sg:city":"River Falls",
    "sg:classifiers":[
        {
            "category":"Education",
            "subcategory":"School",
            "type":"Public Place"
        }
    ],
    "sg:phone":"+1 715 425 1810",
    "sg:postcode":"54022",
    "sg:province":"WI",
    "wof:name":"Greenwood Elementary School",
    "wof:placetype":"venue"
},
  "geometry": {"coordinates":[-92.616536,44.861162],"type":"Point"}
}