{
  "type": "Feature",
  "properties": {
    "iso:country":"US",
    "sg:address":"1061 Proctor Dr",
    "sg:city":"Elkhorn",
    "sg:classifiers":[
        {
            "category":"Manufacturing",
            "subcategory":"Metals",
            "type":"Manufacturing & Wholesale Goods"
        }
    ],
    "sg:phone":"+1 262 723 3344",
    "sg:postcode":"53121",
    "sg:province":"WI",
    "sg:tags":[
        "stampings",
        "stamping",
        "wire",
        "form",
        "mfg"
    ],
    "wof:name":"Jeninga Bros Metal Forming Inc",
    "wof:placetype":"venue"
},
  "geometry": {"coordinates":[-88.524867,42.659114],"type":"Point"}
}