{
  "type": "Feature",
  "properties": {
    "iso:country":"US",
    "sg:address":"4304 W Forest Home Ave",
    "sg:city":"Milwaukee",
    "sg:classifiers":[
        {
            "category":"Education",
            "subcategory":"Music School",
            "type":"Public Place"
        }
    ],
    "sg:phone":"+1 414 329 7820",
    "sg:postcode":"53219",
    "sg:province":"WI",
    "sg:tags":[
        "instruction-instrumental"
    ],
    "wof:name":"Irene Stanczyk",
    "wof:placetype":"venue"
},
  "geometry": {"coordinates":[-87.967901,42.989156],"type":"Point"}
}