{
  "type": "Feature",
  "properties": {
    "iso:country":"US",
    "sg:address":"1303 Evans St",
    "sg:city":"Oshkosh",
    "sg:classifiers":[
        {
            "category":"Organizations",
            "subcategory":"Religious Organization",
            "type":"Services"
        }
    ],
    "sg:phone":"+1 920 235 8834",
    "sg:postcode":"54901",
    "sg:province":"WI",
    "wof:name":"Shining Truth",
    "wof:placetype":"venue"
},
  "geometry": {"coordinates":[-88.526433,44.034621],"type":"Point"}
}