{
  "type": "Feature",
  "properties": {
    "addr:full":"6422 Monona Dr Monona WI 53716",
    "addr:housenumber":"6422",
    "addr:postcode":"53716",
    "addr:street":"Monona Dr",
    "iso:country":"US",
    "sg:address":"6422 Monona Dr",
    "sg:city":"Monona",
    "sg:classifiers":[
        {
            "category":"Shopping",
            "subcategory":"Tobacco",
            "type":"Retail Goods"
        }
    ],
    "sg:phone":"+1 608 221 3005",
    "sg:postcode":"53716",
    "sg:province":"WI",
    "sg:tags":[
        "cigarette",
        "cigar",
        "dealer"
    ],
    "wof:name":"Tobacco Outlet Plus",
    "wof:placetype":"venue"
},
  "geometry": {"coordinates":[-89.32473,43.048635],"type":"Point"}
}