{
  "type": "Feature",
  "properties": {
    "iso:country":"US",
    "sg:address":"3485 E Hamilton Ave",
    "sg:city":"Eau Claire",
    "sg:classifiers":[
        {
            "category":"Social Services",
            "type":"Services"
        }
    ],
    "sg:phone":"+1 715 835 4020",
    "sg:postcode":"54701",
    "sg:province":"WI",
    "sg:tags":[
        "organization",
        "welfare"
    ],
    "wof:name":"American Red Cross",
    "wof:placetype":"venue"
},
  "geometry": {"coordinates":[-91.454536,44.78574],"type":"Point"}
}