{
  "type": "Feature",
  "properties": {
    "iso:country":"US",
    "sg:address":"6485 Shefelbine Rd",
    "sg:city":"Holmen",
    "sg:classifiers":[
        {
            "category":"Farming",
            "subcategory":"Orchard",
            "type":"Manufacturing & Wholesale Goods"
        },
        {
            "category":"Food & Beverages",
            "subcategory":"Fruits & Vegetables",
            "type":"Retail Goods"
        }
    ],
    "sg:phone":"+1 608 526 3495",
    "sg:postcode":"54636",
    "sg:province":"WI",
    "sg:tags":[
        "produce",
        "tree"
    ],
    "wof:name":"Shefelbine Orchards Berry Frm",
    "wof:placetype":"venue"
},
  "geometry": {"coordinates":[-91.15273999999999,43.9578],"type":"Point"}
}