{
  "type": "Feature",
  "properties": {
    "iso:country":"US",
    "sg:address":"1303 Landon St",
    "sg:city":"Schofield",
    "sg:classifiers":[
        {
            "category":"Manufacturing",
            "subcategory":"Tools & Machinery",
            "type":"Manufacturing & Wholesale Goods"
        }
    ],
    "sg:phone":"+1 715 359 3111",
    "sg:postcode":"54476",
    "sg:province":"WI",
    "sg:tags":[
        "piston",
        "carburetor"
    ],
    "sg:website":"www.federal-mogul.com",
    "wof:name":"Federal-Mogul Powertrain Systs",
    "wof:placetype":"venue"
},
  "geometry": {"coordinates":[-89.60806599999999,44.914155],"type":"Point"}
}