{
  "type": "Feature",
  "properties": {
    "iso:country":"US",
    "sg:address":"1697 Hilltop Rd",
    "sg:city":"Ixonia",
    "sg:classifiers":[
        {
            "category":"Farming",
            "subcategory":"Livestock Farm",
            "type":"Manufacturing & Wholesale Goods"
        }
    ],
    "sg:phone":"+1 920 261 4723",
    "sg:postcode":"53036",
    "sg:province":"WI",
    "sg:tags":[
        "beef",
        "feedlot",
        "cattle"
    ],
    "wof:name":"Joseph Heinecke Farm",
    "wof:placetype":"venue"
},
  "geometry": {"coordinates":[-88.618544,43.152427],"type":"Point"}
}