{
  "type": "Feature",
  "properties": {
    "iso:country":"US",
    "sg:address":"5402 Pierce Dr",
    "sg:city":"Manitowoc",
    "sg:classifiers":[
        {
            "category":"Shopping",
            "subcategory":"Catalog Store",
            "type":"Retail Goods"
        }
    ],
    "sg:phone":"+1 920 682 0497",
    "sg:postcode":"54220",
    "sg:province":"WI",
    "sg:tags":[
        "mail",
        "order"
    ],
    "wof:name":"Total Marketing",
    "wof:placetype":"venue"
},
  "geometry": {"coordinates":[-87.717518,44.110683],"type":"Point"}
}