{
  "type": "Feature",
  "properties": {
    "addr:full":"7765 Chelen Ridge Van Dyne WI 54979",
    "addr:housenumber":"7765",
    "addr:postcode":"54979",
    "addr:street":"Chelen Ridge Van",
    "iso:country":"US",
    "sg:address":"7765 Chelen Ridge",
    "sg:city":"Van Dyne",
    "sg:classifiers":[
        {
            "category":"Manufacturing",
            "subcategory":"Toys & Sporting Goods",
            "type":"Manufacturing & Wholesale Goods"
        }
    ],
    "sg:phone":"+1 920 922 5950",
    "sg:postcode":"54979",
    "sg:province":"WI",
    "sg:tags":[
        "athletic"
    ],
    "wof:name":"Mertens' Tackle",
    "wof:placetype":"venue"
},
  "geometry": {"coordinates":[-88.547506,43.842498],"type":"Point"}
}