{
  "type": "Feature",
  "properties": {
    "addr:full":"1015 W Main St Sun Prairie WI 53590",
    "addr:housenumber":"1015",
    "addr:postcode":"53590",
    "addr:street":"W Main St",
    "iso:country":"US",
    "sg:address":"1015 W Main St",
    "sg:city":"Sun Prairie",
    "sg:classifiers":[
        {
            "category":"Professional",
            "subcategory":"Accounting & Tax Preparation",
            "type":"Services"
        }
    ],
    "sg:phone":"+1 608 837 2584",
    "sg:postcode":"53590",
    "sg:province":"WI",
    "sg:tags":[
        "accountant"
    ],
    "wof:name":"Comprehensive Accounting Svc",
    "wof:placetype":"venue"
},
  "geometry": {"coordinates":[-89.23018500000001,43.180846],"type":"Point"}
}