{
  "type": "Feature",
  "properties": {
    "addr:full":"6835 Sunrise Rd Loganville WI 53943",
    "addr:housenumber":"6835",
    "addr:postcode":"53943",
    "addr:street":"Sunrise Rd",
    "iso:country":"US",
    "sg:address":"6835 Sunrise Rd",
    "sg:city":"Loganville",
    "sg:phone":"+1 608 727 2894",
    "sg:postcode":"53943",
    "sg:province":"WI",
    "sg:tags":[
        "farm",
        "corn"
    ],
    "wof:name":"Ed Schuck",
    "wof:placetype":"venue"
},
  "geometry": {"coordinates":[-89.993605,43.399428],"type":"Point"}
}