{
  "type": "Feature",
  "properties": {
    "iso:country":"US",
    "sg:address":"161 W Main St",
    "sg:city":"Stoughton",
    "sg:classifiers":[
        {
            "category":"Social Services",
            "type":"Services"
        }
    ],
    "sg:phone":"+1 608 873 6562",
    "sg:postcode":"53589",
    "sg:province":"WI",
    "wof:name":"Stoughton YMCA Center",
    "wof:placetype":"venue"
},
  "geometry": {"coordinates":[-89.220947,42.916693],"type":"Point"}
}