{
  "type": "Feature",
  "properties": {
    "iso:country":"US",
    "sg:address":"12132 220th Ave",
    "sg:city":"Bristol",
    "sg:classifiers":[
        {
            "category":"Banks & Credit Unions",
            "subcategory":"Investment Brokerage",
            "type":"Services"
        }
    ],
    "sg:phone":"+1 262 862 7281",
    "sg:postcode":"53104",
    "sg:province":"WI",
    "wof:name":"M J Investments",
    "wof:placetype":"venue"
},
  "geometry": {"coordinates":[-88.074274,42.503662],"type":"Point"}
}