{
  "type": "Feature",
  "properties": {
    "iso:country":"US",
    "sg:address":"1111 8th St",
    "sg:city":"Baraboo",
    "sg:classifiers":[
        {
            "category":"Health Services",
            "subcategory":"Doctor",
            "type":"Services"
        }
    ],
    "sg:phone":"+1 608 356 9585",
    "sg:postcode":"53913",
    "sg:province":"WI",
    "sg:tags":[
        "physician",
        "surgeon"
    ],
    "wof:name":"Wenzel Chiropractic Office",
    "wof:placetype":"venue"
},
  "geometry": {"coordinates":[-89.723705,43.474761],"type":"Point"}
}