{
  "type": "Feature",
  "properties": {
    "iso:country":"US",
    "sg:address":"301 Main St W",
    "sg:city":"Ashland",
    "sg:classifiers":[
        {
            "category":"Shopping",
            "subcategory":"Books",
            "type":"Retail Goods"
        }
    ],
    "sg:phone":"+1 715 685 9998",
    "sg:postcode":"54806",
    "sg:province":"WI",
    "sg:tags":[
        "dealer"
    ],
    "wof:name":"Book World",
    "wof:placetype":"venue"
},
  "geometry": {"coordinates":[-90.88567999999999,46.590379],"type":"Point"}
}