{
  "type": "Feature",
  "properties": {
    "iso:country":"US",
    "sg:address":"1800 Plover Rd",
    "sg:city":"Plover",
    "sg:classifiers":[
        {
            "category":"Shopping",
            "subcategory":"Pharmacy",
            "type":"Retail Goods"
        }
    ],
    "sg:phone":"+1 715 342 8974",
    "sg:postcode":"54467",
    "sg:province":"WI",
    "sg:tags":[
        "department",
        "discount",
        "optical",
        "center",
        "store"
    ],
    "wof:name":"Shopko",
    "wof:placetype":"venue"
},
  "geometry": {"coordinates":[-89.52429,44.454055],"type":"Point"}
}