{
  "type": "Feature",
  "properties": {
    "addr:full":"6259 W Leon Ter Milwaukee WI 53218",
    "addr:housenumber":"6259",
    "addr:postcode":"53218",
    "addr:street":"W Leon Ter",
    "iso:country":"US",
    "sg:address":"6259 W Leon Ter",
    "sg:city":"Milwaukee",
    "sg:classifiers":[
        {
            "category":"Building & Trades",
            "subcategory":"Cleaning & Sanitation",
            "type":"Services"
        }
    ],
    "sg:phone":"+1 414 464 1606",
    "sg:postcode":"53218",
    "sg:province":"WI",
    "sg:tags":[
        "window"
    ],
    "wof:name":"Cain Window Cleaning Service",
    "wof:placetype":"venue"
},
  "geometry": {"coordinates":[-87.99010199999999,43.102205],"type":"Point"}
}