{
  "type": "Feature",
  "properties": {
    "iso:country":"US",
    "sg:address":"7388 Ireland Dr",
    "sg:city":"Hartford",
    "sg:classifiers":[
        {
            "category":"Manufacturing",
            "subcategory":"Textiles",
            "type":"Manufacturing & Wholesale Goods"
        }
    ],
    "sg:phone":"+1 262 673 5375",
    "sg:postcode":"53027",
    "sg:province":"WI",
    "sg:tags":[
        "spinning",
        "mill",
        "yarn"
    ],
    "wof:name":"Uniquely Yours Embroidery",
    "wof:placetype":"venue"
},
  "geometry": {"coordinates":[-88.409723,43.256853],"type":"Point"}
}