{
  "type": "Feature",
  "properties": {
    "iso:country":"US",
    "sg:address":"404 N Main St",
    "sg:city":"Oshkosh",
    "sg:classifiers":[
        {
            "category":"Professional",
            "subcategory":"Employment Agencies",
            "type":"Services"
        }
    ],
    "sg:phone":"+1 920 232 3653",
    "sg:postcode":"54901",
    "sg:province":"WI",
    "sg:tags":[
        "opportunity"
    ],
    "wof:name":"Midwest Labor",
    "wof:placetype":"venue"
},
  "geometry": {"coordinates":[-88.537437,44.018252],"type":"Point"}
}