{
  "type": "Feature",
  "properties": {
    "addr:full":"619 River St Belleville WI 53508",
    "addr:housenumber":"619",
    "addr:postcode":"53508",
    "addr:street":"River St",
    "iso:country":"US",
    "sg:address":"619 River St",
    "sg:city":"Belleville",
    "sg:classifiers":[
        {
            "category":"Social Services",
            "type":"Services"
        }
    ],
    "sg:phone":"+1 608 424 9100",
    "sg:postcode":"53508",
    "sg:province":"WI",
    "sg:tags":[
        "counseling"
    ],
    "wof:name":"Foundations Counseling Center",
    "wof:placetype":"venue"
},
  "geometry": {"coordinates":[-89.533126,42.870051],"type":"Point"}
}