{
  "type": "Feature",
  "properties": {
    "addr:full":"3454 E Main St Merrill WI 54452",
    "addr:housenumber":"3454",
    "addr:postcode":"54452",
    "addr:street":"E Main St",
    "iso:country":"US",
    "sg:address":"3454 E Main St",
    "sg:city":"Merrill",
    "sg:classifiers":[
        {
            "category":"Utilities",
            "subcategory":"Mobile Phone",
            "type":"Services"
        }
    ],
    "sg:phone":"+1 715 536 2419",
    "sg:postcode":"54452",
    "sg:province":"WI",
    "sg:tags":[
        "pager"
    ],
    "wof:name":"B P Communications",
    "wof:placetype":"venue"
},
  "geometry": {"coordinates":[-89.65568,45.178023],"type":"Point"}
}