{
  "type": "Feature",
  "properties": {
    "iso:country":"US",
    "sg:address":"9630 State Hwy 13 S",
    "sg:city":"Wisconsin Rapids",
    "sg:classifiers":[
        {
            "category":"Bars & Pubs",
            "type":"Food & Drink"
        }
    ],
    "sg:phone":"+1 715 325 3552",
    "sg:postcode":"54494",
    "sg:province":"WI",
    "wof:name":"Pelot's Inn",
    "wof:placetype":"venue"
},
  "geometry": {"coordinates":[-89.810158,44.31066],"type":"Point"}
}