{
  "type": "Feature",
  "properties": {
    "iso:country":"US",
    "sg:address":"1609 Franklin St",
    "sg:city":"Little Chute",
    "sg:classifiers":[
        {
            "category":"Professional",
            "type":"Services"
        }
    ],
    "sg:phone":"+1 920 788 4862",
    "sg:postcode":"54140",
    "sg:province":"WI",
    "wof:name":"Hattons Fine Finish",
    "wof:placetype":"venue"
},
  "geometry": {"coordinates":[-88.306791,44.293803],"type":"Point"}
}