{
  "type": "Feature",
  "properties": {
    "iso:country":"US",
    "sg:address":"7106 W North Ave",
    "sg:city":"Milwaukee",
    "sg:classifiers":[
        {
            "category":"Health Services",
            "subcategory":"Doctor",
            "type":"Services"
        }
    ],
    "sg:phone":"+1 414 259 0665",
    "sg:postcode":"53213",
    "sg:province":"WI",
    "wof:name":"David R Laste DDS SC",
    "wof:placetype":"venue"
},
  "geometry": {"coordinates":[-88.002044,43.060817],"type":"Point"}
}