{
  "type": "Feature",
  "properties": {
    "addr:full":"5501 Clairemont Dr Appleton WI 54913",
    "addr:housenumber":"5501",
    "addr:postcode":"54913",
    "addr:street":"Clairemont Dr",
    "iso:country":"US",
    "sg:address":"5501 Clairemont Dr",
    "sg:city":"Appleton",
    "sg:classifiers":[
        {
            "category":"Wholesale",
            "subcategory":"Construction Materials",
            "type":"Manufacturing & Wholesale Goods"
        }
    ],
    "sg:phone":"+1 920 757 9150",
    "sg:postcode":"54913",
    "sg:province":"WI",
    "wof:name":"Norandex Reynolds",
    "wof:placetype":"venue"
},
  "geometry": {"coordinates":[-88.49182500000001,44.285283],"type":"Point"}
}