{
  "type": "Feature",
  "properties": {
    "iso:country":"US",
    "sg:address":"27095 120th Ave",
    "sg:city":"Cadott",
    "sg:classifiers":[
        {
            "category":"Organizations",
            "subcategory":"Religious Organization",
            "type":"Services"
        }
    ],
    "sg:phone":"+1 715 289 3608",
    "sg:postcode":"54727",
    "sg:province":"WI",
    "wof:name":"Big Drywood Lutheran Church",
    "wof:placetype":"venue"
},
  "geometry": {"coordinates":[-91.125365,45.016588],"type":"Point"}
}