{
  "type": "Feature",
  "properties": {
    "addr:full":"50669 Charles St Osseo WI 54758",
    "addr:housenumber":"50669",
    "addr:postcode":"54758",
    "addr:street":"Charles St",
    "iso:country":"US",
    "sg:address":"50669 Charles St",
    "sg:city":"Osseo",
    "sg:classifiers":[
        {
            "category":"Retail",
            "subcategory":"Laundry & Dry Cleaning",
            "type":"Services"
        }
    ],
    "sg:phone":"+1 715 597 2170",
    "sg:postcode":"54758",
    "sg:province":"WI",
    "wof:name":"Sdi Services",
    "wof:placetype":"venue"
},
  "geometry": {"coordinates":[-91.22289499999999,44.577915],"type":"Point"}
}