{
  "type": "Feature",
  "properties": {
    "iso:country":"US",
    "sg:address":"260 Co Rd D",
    "sg:city":"Eau Galle",
    "sg:classifiers":[
        {
            "category":"Building & Trades",
            "subcategory":"Plumbing",
            "type":"Services"
        }
    ],
    "sg:phone":"+1 715 283 4851",
    "sg:postcode":"54737",
    "sg:province":"WI",
    "sg:tags":[
        "plumbing",
        "contractor"
    ],
    "wof:name":"J & R's Eau Galle Plumbing Inc",
    "wof:placetype":"venue"
},
  "geometry": {"coordinates":[-92.010018,44.691347],"type":"Point"}
}