{
  "type": "Feature",
  "properties": {
    "addr:full":"333 Washington Dr West Bend WI 53095",
    "addr:housenumber":"333",
    "addr:postcode":"53095",
    "addr:street":"Washington Dr",
    "iso:country":"US",
    "sg:address":"333 Washington Dr",
    "sg:city":"West Bend",
    "sg:classifiers":[
        {
            "category":"Government",
            "subcategory":"Office",
            "type":"Public Place"
        }
    ],
    "sg:phone":"+1 262 335 4497",
    "sg:postcode":"53095",
    "sg:province":"WI",
    "sg:tags":[
        "county",
        "resource"
    ],
    "wof:name":"Washington County Aging Prgrm",
    "wof:placetype":"venue"
},
  "geometry": {"coordinates":[-88.048602,43.374387],"type":"Point"}
}