{
  "type": "Feature",
  "properties": {
    "iso:country":"US",
    "sg:address":"10546 Main St",
    "sg:city":"Hayward",
    "sg:classifiers":[
        {
            "category":"Restaurant",
            "type":"Food & Drink"
        }
    ],
    "sg:phone":"+1 715 638 2271",
    "sg:postcode":"54843",
    "sg:province":"WI",
    "sg:tags":[
        "eating"
    ],
    "wof:name":"Dog Stop",
    "wof:placetype":"venue"
},
  "geometry": {"coordinates":[-91.48452399999999,46.014461],"type":"Point"}
}