{
  "type": "Feature",
  "properties": {
    "iso:country":"US",
    "sg:address":"13855 Reed Rd",
    "sg:city":"Gillett",
    "sg:classifiers":[
        {
            "category":"Building & Trades",
            "subcategory":"Construction",
            "type":"Services"
        }
    ],
    "sg:phone":"+1 920 855 6431",
    "sg:postcode":"54124",
    "sg:province":"WI",
    "sg:tags":[
        "nonresidential"
    ],
    "wof:name":"Kahler Construction",
    "wof:placetype":"venue"
},
  "geometry": {"coordinates":[-88.467628,44.931001],"type":"Point"}
}