{
  "type": "Feature",
  "properties": {
    "iso:country":"US",
    "sg:address":"2196 State Hwy 64",
    "sg:city":"Bloomer",
    "sg:classifiers":[
        {
            "category":"Farming",
            "subcategory":"Dairy Farm",
            "type":"Manufacturing & Wholesale Goods"
        }
    ],
    "sg:phone":"+1 715 568 4118",
    "sg:postcode":"54724",
    "sg:province":"WI",
    "wof:name":"Stuckert Farm",
    "wof:placetype":"venue"
},
  "geometry": {"coordinates":[-91.640696,45.143093],"type":"Point"}
}