{
  "type": "Feature",
  "properties": {
    "addr:full":"1813 14th St Eau Claire WI 54703",
    "addr:housenumber":"1813",
    "addr:postcode":"54703",
    "addr:street":"14Th St",
    "iso:country":"US",
    "sg:address":"1813 14th St",
    "sg:city":"Eau Claire",
    "sg:classifiers":[
        {
            "category":"Insurance",
            "subcategory":"Insurance Agent",
            "type":"Services"
        }
    ],
    "sg:phone":"+1 715 723 7672",
    "sg:postcode":"54703",
    "sg:province":"WI",
    "wof:name":"AFLAC",
    "wof:placetype":"venue"
},
  "geometry": {"coordinates":[-91.528403,44.816832],"type":"Point"}
}