{
  "type": "Feature",
  "properties": {
    "iso:country":"US",
    "sg:address":"10702 W Burleigh St",
    "sg:city":"Milwaukee",
    "sg:classifiers":[
        {
            "category":"Health Services",
            "subcategory":"Hospital",
            "type":"Services"
        }
    ],
    "sg:phone":"+1 414 777 0740",
    "sg:postcode":"53222",
    "sg:province":"WI",
    "sg:tags":[
        "mental"
    ],
    "wof:name":"Solutions Behavioral Health",
    "wof:placetype":"venue"
},
  "geometry": {"coordinates":[-88.047004,43.074846],"type":"Point"}
}