{
  "type": "Feature",
  "properties": {
    "iso:country":"US",
    "sg:address":"7196 170th Ave",
    "sg:city":"Bay City",
    "sg:classifiers":[
        {
            "category":"Farming",
            "subcategory":"Farm",
            "type":"Manufacturing & Wholesale Goods"
        }
    ],
    "sg:phone":"+1 715 594 3912",
    "sg:postcode":"54723",
    "sg:province":"WI",
    "sg:tags":[
        "crop",
        "general"
    ],
    "wof:name":"Larry Swanson",
    "wof:placetype":"venue"
},
  "geometry": {"coordinates":[-92.49059800000001,44.601483],"type":"Point"}
}