{
  "type": "Feature",
  "properties": {
    "addr:full":"1949 Chickadee Ln Alma WI 54610",
    "addr:housenumber":"1949",
    "addr:postcode":"54610",
    "addr:street":"Chickadee Ln",
    "iso:country":"US",
    "sg:address":"1949 Chickadee Ln",
    "sg:city":"Alma",
    "sg:phone":"+1 608 685 3670",
    "sg:postcode":"54610",
    "sg:province":"WI",
    "sg:tags":[
        "beef",
        "farm",
        "crop",
        "field",
        "cattle",
        "feedlot"
    ],
    "wof:name":"Carrol Iberg",
    "wof:placetype":"venue"
},
  "geometry": {"coordinates":[-91.865154,44.318987],"type":"Point"}
}