{
  "type": "Feature",
  "properties": {
    "addr:full":"790 W Moreland Blvd Waukesha WI 53188",
    "addr:housenumber":"790",
    "addr:postcode":"53188",
    "addr:street":"W Moreland Blvd",
    "iso:country":"US",
    "sg:address":"790 W Moreland Blvd",
    "sg:city":"Waukesha",
    "sg:classifiers":[
        {
            "category":"Real Estate",
            "subcategory":"Real Estate Operator",
            "type":"Services"
        }
    ],
    "sg:phone":"+1 262 549 2400",
    "sg:postcode":"53188",
    "sg:province":"WI",
    "sg:tags":[
        "apartment"
    ],
    "wof:name":"Moreland Grove Apartments",
    "wof:placetype":"venue"
},
  "geometry": {"coordinates":[-88.239532,43.025088],"type":"Point"}
}