{
  "type": "Feature",
  "properties": {
    "iso:country":"US",
    "sg:address":"1975 State Hwy 64",
    "sg:city":"Marinette",
    "sg:classifiers":[
        {
            "category":"Wholesale",
            "subcategory":"Machinery & Supplies",
            "type":"Manufacturing & Wholesale Goods"
        }
    ],
    "sg:phone":"+1 715 735 0390",
    "sg:postcode":"54143",
    "sg:province":"WI",
    "sg:tags":[
        "equipment",
        "used",
        "establishment"
    ],
    "wof:name":"A To Z Bar & Rest Sups & Eqp",
    "wof:placetype":"venue"
},
  "geometry": {"coordinates":[-87.63305200000001,45.099713],"type":"Point"}
}