{
  "type": "Feature",
  "properties": {
    "iso:country":"US",
    "sg:address":"2021 Greenway Cross",
    "sg:city":"Fitchburg",
    "sg:classifiers":[
        {
            "category":"Social Services",
            "subcategory":"Child Care",
            "type":"Services"
        }
    ],
    "sg:phone":"+1 608 278 1491",
    "sg:postcode":"53713",
    "sg:province":"WI",
    "wof:name":"Toya's Tikes",
    "wof:placetype":"venue"
},
  "geometry": {"coordinates":[-89.415845,43.030863],"type":"Point"}
}