{
  "type": "Feature",
  "properties": {
    "iso:country":"US",
    "sg:address":"751 Overview Ct",
    "sg:city":"Prairie Du Chien",
    "sg:classifiers":[
        {
            "category":"Professional",
            "type":"Services"
        }
    ],
    "sg:phone":"+1 608 326 7100",
    "sg:postcode":"53821",
    "sg:province":"WI",
    "wof:name":"Saint Feriole Island Memorial",
    "wof:placetype":"venue"
},
  "geometry": {"coordinates":[-91.147406,43.04216],"type":"Point"}
}