{
  "type": "Feature",
  "properties": {
    "iso:country":"US",
    "sg:address":"5859 Co Hwy P",
    "sg:city":"Monroe",
    "sg:classifiers":[
        {
            "category":"Home & Garden",
            "subcategory":"Building Materials",
            "type":"Retail Goods"
        }
    ],
    "sg:phone":"+1 608 325 9421",
    "sg:postcode":"53566",
    "sg:province":"WI",
    "sg:tags":[
        "farm",
        "lumber",
        "supply"
    ],
    "wof:name":"Clarno Lumber & Supply Co Inc",
    "wof:placetype":"venue"
},
  "geometry": {"coordinates":[-89.649958,42.519166],"type":"Point"}
}