{
  "type": "Feature",
  "properties": {
    "iso:country":"US",
    "sg:address":"2833 W Layton Ave",
    "sg:city":"Milwaukee",
    "sg:classifiers":[
        {
            "category":"Banks & Credit Unions",
            "subcategory":"Bank",
            "type":"Services"
        }
    ],
    "sg:phone":"+1 414 431 1980",
    "sg:postcode":"53221",
    "sg:province":"WI",
    "sg:tags":[
        "broker",
        "mortgage"
    ],
    "wof:name":"Wisconsin Wholesale Mrtg LLC",
    "wof:placetype":"venue"
},
  "geometry": {"coordinates":[-87.950075,42.95933],"type":"Point"}
}