{
  "type": "Feature",
  "properties": {
    "iso:country":"US",
    "sg:address":"2628 Oakridge Rd",
    "sg:city":"Neenah",
    "sg:classifiers":[
        {
            "category":"Building & Trades",
            "subcategory":"Construction",
            "type":"Services"
        }
    ],
    "sg:phone":"+1 920 725 7457",
    "sg:postcode":"54956",
    "sg:province":"WI",
    "sg:tags":[
        "house"
    ],
    "wof:name":"Homes For Wisconsin",
    "wof:placetype":"venue"
},
  "geometry": {"coordinates":[-88.535456,44.170744],"type":"Point"}
}