{
  "type": "Feature",
  "properties": {
    "iso:country":"US",
    "sg:address":"3272 Co Rd Ss",
    "sg:city":"Tigerton",
    "sg:classifiers":[
        {
            "category":"Government",
            "subcategory":"Office",
            "type":"Public Place"
        }
    ],
    "sg:phone":"+1 715 535 2655",
    "sg:postcode":"54486",
    "sg:province":"WI",
    "sg:tags":[
        "city"
    ],
    "wof:name":"Town Hall",
    "wof:placetype":"venue"
},
  "geometry": {"coordinates":[-89.022464,44.708166],"type":"Point"}
}