{
  "type": "Feature",
  "properties": {
    "iso:country":"US",
    "sg:address":"211 S Grand Ave",
    "sg:city":"Embarrass",
    "sg:classifiers":[
        {
            "category":"Wholesale",
            "subcategory":"Farm Supplies",
            "type":"Manufacturing & Wholesale Goods"
        }
    ],
    "sg:phone":"+1 715 823 2435",
    "sg:postcode":"54933",
    "sg:province":"WI",
    "sg:tags":[
        "feed"
    ],
    "wof:name":"Magee Feeds",
    "wof:placetype":"venue"
},
  "geometry": {"coordinates":[-88.70778,44.664466],"type":"Point"}
}