{
  "type": "Feature",
  "properties": {
    "iso:country":"US",
    "sg:address":"8973 Co Rd Y",
    "sg:city":"Gordon",
    "sg:classifiers":[
        {
            "category":"Home & Garden",
            "subcategory":"Home Furnishings",
            "type":"Retail Goods"
        }
    ],
    "sg:phone":"+1 715 376 4222",
    "sg:postcode":"54838",
    "sg:province":"WI",
    "wof:name":"Shady Land Creations",
    "wof:placetype":"venue"
},
  "geometry": {"coordinates":[-91.829435,46.242275],"type":"Point"}
}