{
  "type": "Feature",
  "properties": {
    "iso:country":"US",
    "sg:address":"17010 State Hwy 171",
    "sg:city":"Richland Center",
    "sg:classifiers":[
        {
            "category":"Organizations",
            "subcategory":"Membership Organization",
            "type":"Services"
        },
        {
            "category":"Organizations",
            "subcategory":"Community Association",
            "type":"Services"
        }
    ],
    "sg:phone":"+1 608 536 3466",
    "sg:postcode":"53581",
    "sg:province":"WI",
    "sg:tags":[
        "club"
    ],
    "wof:name":"Boaz Community Center",
    "wof:placetype":"venue"
},
  "geometry": {"coordinates":[-90.530025,43.328808],"type":"Point"}
}