{
  "type": "Feature",
  "properties": {
    "iso:country":"US",
    "sg:address":"5800 6th Ave",
    "sg:city":"Kenosha",
    "sg:classifiers":[
        {
            "category":"Restaurant",
            "type":"Food & Drink"
        }
    ],
    "sg:phone":"+1 262 652 8111",
    "sg:postcode":"53140",
    "sg:province":"WI",
    "wof:name":"Three Coins Restaurant Inc",
    "wof:placetype":"venue"
},
  "geometry": {"coordinates":[-87.818288,42.58235],"type":"Point"}
}