{
  "type": "Feature",
  "properties": {
    "iso:country":"US",
    "sg:address":"5036 Mueller Rd",
    "sg:city":"Sheboygan",
    "sg:classifiers":[
        {
            "category":"Building & Trades",
            "subcategory":"Construction",
            "type":"Services"
        }
    ],
    "sg:phone":"+1 920 458 8639",
    "sg:postcode":"53083",
    "sg:province":"WI",
    "sg:tags":[
        "hanging",
        "contractor"
    ],
    "wof:name":"Dahmer Decorating Co",
    "wof:placetype":"venue"
},
  "geometry": {"coordinates":[-87.772768,43.782825],"type":"Point"}
}