{
  "type": "Feature",
  "properties": {
    "iso:country":"US",
    "sg:address":"4881 Langes Corners Rd",
    "sg:city":"Denmark",
    "sg:classifiers":[
        {
            "category":"Real Estate",
            "subcategory":"Real Estate Agent",
            "type":"Services"
        }
    ],
    "sg:phone":"+1 920 863 6332",
    "sg:postcode":"54208",
    "sg:province":"WI",
    "wof:name":"Kafka Realty",
    "wof:placetype":"venue"
},
  "geometry": {"coordinates":[-87.882761,44.38578],"type":"Point"}
}