{
  "type": "Feature",
  "properties": {
    "iso:country":"US",
    "sg:address":"343 E Greenfield St",
    "sg:city":"Appleton",
    "sg:classifiers":[
        {
            "category":"Government",
            "subcategory":"Office",
            "type":"Public Place"
        }
    ],
    "sg:phone":"+1 920 733 4891",
    "sg:postcode":"54911",
    "sg:province":"WI",
    "sg:tags":[
        "program",
        "administrative"
    ],
    "wof:name":"Agape House Inc",
    "wof:placetype":"venue"
},
  "geometry": {"coordinates":[-88.39840700000001,44.285624],"type":"Point"}
}