{
  "type": "Feature",
  "properties": {
    "iso:country":"US",
    "sg:address":"2405 35th St",
    "sg:city":"Kenosha",
    "sg:classifiers":[
        {
            "category":"Building & Trades",
            "subcategory":"Landscaping Services",
            "type":"Services"
        }
    ],
    "sg:phone":"+1 262 652 9300",
    "sg:postcode":"53140",
    "sg:province":"WI",
    "sg:tags":[
        "landscape",
        "contractor"
    ],
    "wof:name":"Grasscape",
    "wof:placetype":"venue"
},
  "geometry": {"coordinates":[-87.845536,42.606142],"type":"Point"}
}