{
  "type": "Feature",
  "properties": {
    "iso:country":"US",
    "sg:address":"2102 16th St",
    "sg:city":"Monroe",
    "sg:classifiers":[
        {
            "category":"Building & Trades",
            "subcategory":"Construction",
            "type":"Services"
        }
    ],
    "sg:phone":"+1 608 329 3966",
    "sg:postcode":"53566",
    "sg:province":"WI",
    "sg:tags":[
        "general",
        "contractor"
    ],
    "wof:name":"Kundert Construction",
    "wof:placetype":"venue"
},
  "geometry": {"coordinates":[-89.63379999999999,42.596577],"type":"Point"}
}