{
  "type": "Feature",
  "properties": {
    "addr:full":"1835 W Pointe Dr Oshkosh WI 54902",
    "addr:housenumber":"1835",
    "addr:postcode":"54902",
    "addr:street":"W Pointe Dr",
    "iso:country":"US",
    "sg:address":"1835 W Pointe Dr",
    "sg:city":"Oshkosh",
    "sg:classifiers":[
        {
            "category":"Health Services",
            "subcategory":"Doctor",
            "type":"Services"
        }
    ],
    "sg:phone":"+1 920 231 3140",
    "sg:postcode":"54902",
    "sg:province":"WI",
    "sg:tags":[
        "dentist"
    ],
    "wof:name":"Jack R Willert DDS",
    "wof:placetype":"venue"
},
  "geometry": {"coordinates":[-88.579318,44.01871],"type":"Point"}
}