{
  "type": "Feature",
  "properties": {
    "addr:full":"1922 Parmenter St Middleton WI 53562",
    "addr:housenumber":"1922",
    "addr:postcode":"53562",
    "addr:street":"Parmenter St",
    "iso:country":"US",
    "sg:address":"1922 Parmenter St",
    "sg:city":"Middleton",
    "sg:classifiers":[
        {
            "category":"Personal",
            "subcategory":"Beauty Salon",
            "type":"Services"
        }
    ],
    "sg:phone":"+1 608 827 6245",
    "sg:postcode":"53562",
    "sg:province":"WI",
    "sg:tags":[
        "shop"
    ],
    "wof:name":"Magic Nails By Bic",
    "wof:placetype":"venue"
},
  "geometry": {"coordinates":[-89.51161,43.09666],"type":"Point"}
}