{
  "type": "Feature",
  "properties": {
    "iso:country":"US",
    "sg:address":"413 W Kilbourn Ave",
    "sg:city":"West Bend",
    "sg:classifiers":[
        {
            "category":"Manufacturing",
            "subcategory":"Food",
            "type":"Manufacturing & Wholesale Goods"
        },
        {
            "category":"Wholesale",
            "subcategory":"Groceries",
            "type":"Manufacturing & Wholesale Goods"
        }
    ],
    "sg:phone":"+1 262 334 2633",
    "sg:postcode":"53095",
    "sg:province":"WI",
    "sg:tags":[
        "juice",
        "drink",
        "soft",
        "fruit",
        "mfg"
    ],
    "wof:name":"Seven Up Bottling Co",
    "wof:placetype":"venue"
},
  "geometry": {"coordinates":[-88.178386,43.418623],"type":"Point"}
}