{
  "type": "Feature",
  "properties": {
    "iso:country":"US",
    "sg:address":"3530 145th St",
    "sg:city":"Siren",
    "sg:classifiers":[
        {
            "category":"Farming",
            "subcategory":"Dairy Farm",
            "type":"Manufacturing & Wholesale Goods"
        }
    ],
    "sg:phone":"+1 715 327 4829",
    "sg:postcode":"54872",
    "sg:province":"WI",
    "wof:name":"Hedlund Dairy",
    "wof:placetype":"venue"
},
  "geometry": {"coordinates":[-92.458006,45.713267],"type":"Point"}
}