{
  "type": "Feature",
  "properties": {
    "iso:country":"US",
    "sg:address":"2724 Post Rd",
    "sg:city":"Stevens Point",
    "sg:classifiers":[
        {
            "category":"Shopping",
            "subcategory":"Books",
            "type":"Retail Goods"
        }
    ],
    "sg:phone":"+1 715 341 2665",
    "sg:postcode":"54481",
    "sg:province":"WI",
    "wof:name":"Book Look",
    "wof:placetype":"venue"
},
  "geometry": {"coordinates":[-89.550855,44.487386],"type":"Point"}
}