{
  "type": "Feature",
  "properties": {
    "addr:full":"2421 E Johnson St Madison WI 53704",
    "addr:housenumber":"2421",
    "addr:postcode":"53704",
    "addr:street":"E Johnson St",
    "iso:country":"US",
    "sg:address":"2421 E Johnson St",
    "sg:city":"Madison",
    "sg:classifiers":[
        {
            "category":"Education",
            "subcategory":"School",
            "type":"Public Place"
        }
    ],
    "sg:phone":"+1 608 204 2000",
    "sg:postcode":"53704",
    "sg:province":"WI",
    "sg:website":"www.madison.k12.wi.us",
    "wof:name":"Emerson Elementary School",
    "wof:placetype":"venue"
},
  "geometry": {"coordinates":[-89.35265200000001,43.101342],"type":"Point"}
}