{
  "type": "Feature",
  "properties": {
    "addr:full":"380 Progress Dr Cottage Grove WI 53527",
    "addr:housenumber":"380",
    "addr:postcode":"53527",
    "addr:street":"Progress Dr",
    "iso:country":"US",
    "sg:address":"380 Progress Dr",
    "sg:city":"Cottage Grove",
    "sg:classifiers":[
        {
            "category":"Wholesale",
            "subcategory":"Hardware",
            "type":"Manufacturing & Wholesale Goods"
        }
    ],
    "sg:phone":"+1 608 839 8489",
    "sg:postcode":"53527",
    "sg:province":"WI",
    "sg:tags":[
        "gas",
        "burner"
    ],
    "wof:name":"PBBS Equipment Corp",
    "wof:placetype":"venue"
},
  "geometry": {"coordinates":[-89.20622400000001,43.077082],"type":"Point"}
}