{
  "type": "Feature",
  "properties": {
    "iso:country":"US",
    "sg:address":"1715 Plymouth St",
    "sg:city":"New Holstein",
    "sg:classifiers":[
        {
            "category":"Government",
            "subcategory":"Office",
            "type":"Public Place"
        }
    ],
    "sg:phone":"+1 920 898 5115",
    "sg:postcode":"53061",
    "sg:province":"WI",
    "sg:tags":[
        "educational",
        "program",
        "administrative"
    ],
    "wof:name":"New Holstein School District",
    "wof:placetype":"venue"
},
  "geometry": {"coordinates":[-88.102565,43.94537],"type":"Point"}
}