{
  "type": "Feature",
  "properties": {
    "iso:country":"US",
    "sg:address":"10590 W Fountain Ave",
    "sg:city":"Milwaukee",
    "sg:classifiers":[
        {
            "category":"Government",
            "subcategory":"Office",
            "type":"Public Place"
        }
    ],
    "sg:phone":"+1 414 357 7807",
    "sg:postcode":"53224",
    "sg:province":"WI",
    "sg:tags":[
        "government-united",
        "state"
    ],
    "wof:name":"Corp Housing",
    "wof:placetype":"venue"
},
  "geometry": {"coordinates":[-88.042613,43.158582],"type":"Point"}
}