{
  "type": "Feature",
  "properties": {
    "iso:country":"US",
    "sg:address":"4249 Argosy Ct",
    "sg:city":"Madison",
    "sg:classifiers":[
        {
            "category":"Professional",
            "type":"Services"
        }
    ],
    "sg:phone":"+1 608 223 1380",
    "sg:postcode":"53714",
    "sg:province":"WI",
    "sg:tags":[
        "establishment"
    ],
    "wof:name":"Advanced Grieg Laminators Inc",
    "wof:placetype":"venue"
},
  "geometry": {"coordinates":[-89.31025099999999,43.088237],"type":"Point"}
}