{
  "type": "Feature",
  "properties": {
    "iso:country":"US",
    "sg:address":"4003 80th St",
    "sg:city":"Kenosha",
    "sg:classifiers":[
        {
            "category":"Government",
            "subcategory":"Jail",
            "type":"Public Place"
        }
    ],
    "sg:phone":"+1 262 697 2500",
    "sg:postcode":"53142",
    "sg:province":"IL",
    "sg:tags":[
        "govt",
        "state",
        "institution"
    ],
    "wof:name":"Corrections Dept",
    "wof:placetype":"venue"
},
  "geometry": {"coordinates":[-87.857553,42.558916],"type":"Point"}
}