{
  "type": "Feature",
  "properties": {
    "iso:country":"US",
    "sg:address":"802 E 1st St",
    "sg:city":"Merrill",
    "sg:classifiers":[
        {
            "category":"Shopping",
            "subcategory":"Clothing, Apparel, & Fashions",
            "type":"Retail Goods"
        }
    ],
    "sg:phone":"+1 715 536 1036",
    "sg:postcode":"54452",
    "sg:province":"WI",
    "sg:tags":[
        "shop",
        "tuxedo",
        "bridal",
        "rental"
    ],
    "wof:name":"Satins Plus Silks By Janelle",
    "wof:placetype":"venue"
},
  "geometry": {"coordinates":[-89.687546,45.180783],"type":"Point"}
}