{
  "type": "Feature",
  "properties": {
    "iso:country":"US",
    "sg:address":"12450 W Colfax Pl",
    "sg:city":"Butler",
    "sg:classifiers":[
        {
            "category":"Building & Trades",
            "subcategory":"Plumbing",
            "type":"Services"
        }
    ],
    "sg:phone":"+1 262 781 4950",
    "sg:postcode":"53007",
    "sg:province":"WI",
    "sg:tags":[
        "refrigeration",
        "contractor"
    ],
    "wof:name":"Anderson Bros Rfrgn Svc",
    "wof:placetype":"venue"
},
  "geometry": {"coordinates":[-88.06588499999999,43.108984],"type":"Point"}
}