{
  "type": "Feature",
  "properties": {
    "iso:country":"US",
    "sg:address":"2911 58th",
    "sg:city":"Wisconsin Rapids",
    "sg:classifiers":[
        {
            "category":"Building & Trades",
            "subcategory":"Construction",
            "type":"Services"
        }
    ],
    "sg:phone":"+1 715 421 3665",
    "sg:postcode":"54494",
    "sg:province":"WI",
    "sg:tags":[
        "painter"
    ],
    "wof:name":"Don's Quality Home Improvement",
    "wof:placetype":"venue"
},
  "geometry": {"coordinates":[-89.752611,44.36874],"type":"Point"}
}