{
  "type": "Feature",
  "properties": {
    "iso:country":"US",
    "sg:address":"301 S Bedford St",
    "sg:city":"Madison",
    "sg:classifiers":[
        {
            "category":"Real Estate",
            "subcategory":"Real Estate Agent",
            "type":"Services"
        }
    ],
    "sg:phone":"+1 608 251 8783",
    "sg:postcode":"53703",
    "sg:province":"WI",
    "sg:website":"www.robertcoxrealty.com",
    "wof:name":"Robert Cox Realty",
    "wof:placetype":"venue"
},
  "geometry": {"coordinates":[-89.388616,43.065943],"type":"Point"}
}