{
  "type": "Feature",
  "properties": {
    "iso:country":"US",
    "sg:address":"314 S Jefferson St",
    "sg:city":"Verona",
    "sg:phone":"+1 608 845 7334",
    "sg:postcode":"53593",
    "sg:province":"WI",
    "sg:tags":[
        "product",
        "petroleum"
    ],
    "wof:name":"Amsoil Synthetic Lubricants",
    "wof:placetype":"venue"
},
  "geometry": {"coordinates":[-89.53085900000001,42.986315],"type":"Point"}
}