{
  "type": "Feature",
  "properties": {
    "iso:country":"US",
    "sg:address":"5444 O'Konski Rd",
    "sg:city":"Mercer",
    "sg:classifiers":[
        {
            "category":"Professional",
            "type":"Services"
        }
    ],
    "sg:phone":"+1 715 476 7849",
    "sg:postcode":"54547",
    "sg:province":"WI",
    "wof:name":"Dan & Neil & Yuki Inc",
    "wof:placetype":"venue"
},
  "geometry": {"coordinates":[-90.01349500000001,46.133004],"type":"Point"}
}