{
  "type": "Feature",
  "properties": {
    "addr:full":"1777 Elk Ln Kaukauna WI 54130",
    "addr:housenumber":"1777",
    "addr:postcode":"54130",
    "addr:street":"Elk Ln",
    "iso:country":"US",
    "sg:address":"1777 Elk Ln",
    "sg:city":"Kaukauna",
    "sg:classifiers":[
        {
            "category":"Organizations",
            "subcategory":"Labor Organization",
            "type":"Services"
        }
    ],
    "sg:phone":"+1 920 788 3648",
    "sg:postcode":"54130",
    "sg:province":"WI",
    "wof:name":"Pace International Union",
    "wof:placetype":"venue"
},
  "geometry": {"coordinates":[-88.275496,44.396126],"type":"Point"}
}