{
  "type": "Feature",
  "properties": {
    "iso:country":"US",
    "sg:address":"2478 N Murray Ave",
    "sg:city":"Milwaukee",
    "sg:classifiers":[
        {
            "category":"Building & Trades",
            "subcategory":"Plumbing",
            "type":"Services"
        }
    ],
    "sg:phone":"+1 414 964 4950",
    "sg:postcode":"53211",
    "sg:province":"WI",
    "sg:tags":[
        "plumbing",
        "air",
        "heating",
        "conditioning",
        "contractor"
    ],
    "wof:name":"Knauer Plumbing Htg & Coolg",
    "wof:placetype":"venue"
},
  "geometry": {"coordinates":[-87.88548,43.062988],"type":"Point"}
}