{
  "type": "Feature",
  "properties": {
    "iso:country":"US",
    "sg:address":"1418 S 12th St",
    "sg:city":"Manitowoc",
    "sg:classifiers":[
        {
            "category":"Building & Trades",
            "subcategory":"Construction",
            "type":"Services"
        }
    ],
    "sg:phone":"+1 920 686 1474",
    "sg:postcode":"54220",
    "sg:province":"WI",
    "sg:tags":[
        "contractor"
    ],
    "wof:name":"Brooks Building",
    "wof:placetype":"venue"
},
  "geometry": {"coordinates":[-87.663518,44.081139],"type":"Point"}
}