{
  "type": "Feature",
  "properties": {
    "addr:full":"6601 Northway Greendale WI 53129",
    "addr:housenumber":"6601",
    "addr:postcode":"53129",
    "addr:street":"Northway",
    "iso:country":"US",
    "sg:address":"6601 Northway",
    "sg:city":"Greendale",
    "sg:classifiers":[
        {
            "category":"Organizations",
            "subcategory":"Non-profit Organization",
            "type":"Services"
        }
    ],
    "sg:phone":"+1 414 423 1210",
    "sg:postcode":"53129",
    "sg:province":"WI",
    "wof:name":"Wisconsin Parks & Recreation",
    "wof:placetype":"venue"
},
  "geometry": {"coordinates":[-87.997336,42.942333],"type":"Point"}
}