{
  "type": "Feature",
  "properties": {
    "iso:country":"US",
    "sg:address":"8828 W North Ave",
    "sg:city":"Milwaukee",
    "sg:classifiers":[
        {
            "category":"Bars & Pubs",
            "type":"Food & Drink"
        }
    ],
    "sg:phone":"+1 414 257 4142",
    "sg:postcode":"53226",
    "sg:province":"WI",
    "wof:name":"Club Tap Cocktail Lounge",
    "wof:placetype":"venue"
},
  "geometry": {"coordinates":[-88.023433,43.060578],"type":"Point"}
}