{
  "type": "Feature",
  "properties": {
    "iso:country":"US",
    "sg:address":"7665 US Hwy 151",
    "sg:city":"Fond Du Lac",
    "sg:classifiers":[
        {
            "category":"Autos & Motor Vehicles",
            "subcategory":"Motorcycle Sales",
            "type":"Retail Goods"
        }
    ],
    "sg:phone":"+1 920 921 7071",
    "sg:postcode":"54935",
    "sg:province":"WI",
    "sg:tags":[
        "all",
        "terrain"
    ],
    "wof:name":"Fred's Fastrac Sales & Svc",
    "wof:placetype":"venue"
},
  "geometry": {"coordinates":[-88.379856,43.817215],"type":"Point"}
}