{
  "type": "Feature",
  "properties": {
    "addr:full":"1639 N Spring St Beaver Dam WI 53916",
    "addr:housenumber":"1639",
    "addr:postcode":"53916",
    "addr:street":"N Spring St",
    "iso:country":"US",
    "sg:address":"1639 N Spring St",
    "sg:city":"Beaver Dam",
    "sg:classifiers":[
        {
            "category":"Restaurant",
            "type":"Food & Drink"
        }
    ],
    "sg:phone":"+1 920 885 3104",
    "sg:postcode":"53916",
    "sg:province":"WI",
    "sg:tags":[
        "eating"
    ],
    "wof:name":"McDonalds",
    "wof:placetype":"venue"
},
  "geometry": {"coordinates":[-88.823902,43.475152],"type":"Point"}
}