{
  "type": "Feature",
  "properties": {
    "addr:full":"1120 W Burleigh St Milwaukee WI 53206",
    "addr:housenumber":"1120",
    "addr:postcode":"53206",
    "addr:street":"W Burleigh St",
    "iso:country":"US",
    "sg:address":"1120 W Burleigh St",
    "sg:city":"Milwaukee",
    "sg:classifiers":[
        {
            "category":"Food & Beverages",
            "subcategory":"Liquor & Beverages",
            "type":"Retail Goods"
        }
    ],
    "sg:phone":"+1 414 562 2793",
    "sg:postcode":"53206",
    "sg:province":"WI",
    "sg:tags":[
        "alcoholic"
    ],
    "wof:name":"Burleigh Beer Depot",
    "wof:placetype":"venue"
},
  "geometry": {"coordinates":[-87.92514799999999,43.074971],"type":"Point"}
}