{
  "type": "Feature",
  "properties": {
    "iso:country":"US",
    "sg:address":"200 Tower St",
    "sg:city":"Sparta",
    "sg:classifiers":[
        {
            "category":"Banks & Credit Unions",
            "subcategory":"Financial Services",
            "type":"Services"
        }
    ],
    "sg:phone":"+1 608 269 7065",
    "sg:postcode":"54656",
    "sg:province":"WI",
    "sg:tags":[
        "investor"
    ],
    "wof:name":"Capaul Realty Investments LLC",
    "wof:placetype":"venue"
},
  "geometry": {"coordinates":[-90.828974,43.946085],"type":"Point"}
}