{
  "type": "Feature",
  "properties": {
    "addr:full":"1110 W Kennedy Ave Kimberly WI 54136",
    "addr:housenumber":"1110",
    "addr:postcode":"54136",
    "addr:street":"W Kennedy Ave",
    "iso:country":"US",
    "sg:address":"1110 W Kennedy Ave",
    "sg:city":"Kimberly",
    "sg:classifiers":[
        {
            "category":"Wholesale",
            "subcategory":"Construction Materials",
            "type":"Manufacturing & Wholesale Goods"
        }
    ],
    "sg:phone":"+1 920 830 0800",
    "sg:postcode":"54136",
    "sg:province":"WI",
    "sg:tags":[
        "sand",
        "gravel"
    ],
    "wof:name":"Cloverleaf Sand & Gravel",
    "wof:placetype":"venue"
},
  "geometry": {"coordinates":[-88.353343,44.261608],"type":"Point"}
}