{
  "type": "Feature",
  "properties": {
    "iso:country":"US",
    "sg:address":"831 Stewart St",
    "sg:city":"Madison",
    "sg:classifiers":[
        {
            "category":"Professional",
            "subcategory":"Business Services",
            "type":"Services"
        }
    ],
    "sg:phone":"+1 608 271 3223",
    "sg:postcode":"53713",
    "sg:province":"WI",
    "sg:tags":[
        "painting",
        "sign"
    ],
    "wof:name":"Muldowney Cy Signs Inc",
    "wof:placetype":"venue"
},
  "geometry": {"coordinates":[-89.396071,43.029958],"type":"Point"}
}