{
  "type": "Feature",
  "properties": {
    "iso:country":"US",
    "sg:address":"7492 Co Rd F",
    "sg:city":"Phillips",
    "sg:classifiers":[
        {
            "category":"Banks & Credit Unions",
            "subcategory":"Bank",
            "type":"Services"
        }
    ],
    "sg:phone":"+1 715 339 4809",
    "sg:postcode":"54555",
    "sg:province":"WI",
    "sg:tags":[
        "loan",
        "real estate"
    ],
    "wof:name":"Fairway Independent Mortgage",
    "wof:placetype":"venue"
},
  "geometry": {"coordinates":[-90.440892,45.70131],"type":"Point"}
}