{
  "type": "Feature",
  "properties": {
    "iso:country":"US",
    "sg:address":"21975 Hess Rd",
    "sg:city":"Galesville",
    "sg:classifiers":[
        {
            "category":"Shopping",
            "type":"Retail Goods"
        }
    ],
    "sg:phone":"+1 608 582 2368",
    "sg:postcode":"54630",
    "sg:province":"WI",
    "sg:tags":[
        "equipment",
        "telephone",
        "supply"
    ],
    "wof:name":"Knappen & Knappen",
    "wof:placetype":"venue"
},
  "geometry": {"coordinates":[-91.38753699999999,44.041934],"type":"Point"}
}