{
  "type": "Feature",
  "properties": {
    "iso:country":"US",
    "sg:address":"21105 Flag Ave",
    "sg:city":"Tomah",
    "sg:classifiers":[
        {
            "category":"Building & Trades",
            "subcategory":"Construction",
            "type":"Services"
        }
    ],
    "sg:phone":"+1 608 372 6064",
    "sg:postcode":"54660",
    "sg:province":"WI",
    "sg:tags":[
        "contractor"
    ],
    "wof:name":"Meincke Construction",
    "wof:placetype":"venue"
},
  "geometry": {"coordinates":[-90.587356,44.007564],"type":"Point"}
}