{
  "type": "Feature",
  "properties": {
    "iso:country":"US",
    "sg:address":"2106 S 83rd St",
    "sg:city":"Milwaukee",
    "sg:classifiers":[
        {
            "category":"Professional",
            "subcategory":"Business Services",
            "type":"Services"
        }
    ],
    "sg:phone":"+1 414 727 8912",
    "sg:postcode":"53219",
    "sg:province":"WI",
    "wof:name":"Emerging Technologies Spc",
    "wof:placetype":"venue"
},
  "geometry": {"coordinates":[-88.016086,43.004094],"type":"Point"}
}