{
  "type": "Feature",
  "properties": {
    "iso:country":"US",
    "sg:address":"1203 State Hwy 175",
    "sg:city":"Hubertus",
    "sg:classifiers":[
        {
            "category":"Retail",
            "subcategory":"Auto Repair",
            "type":"Services"
        }
    ],
    "sg:phone":"+1 262 628 4342",
    "sg:postcode":"53033",
    "sg:province":"WI",
    "sg:tags":[
        "trailer"
    ],
    "wof:name":"Richfield Trailer Inc",
    "wof:placetype":"venue"
},
  "geometry": {"coordinates":[-88.182844,43.229524],"type":"Point"}
}