{
  "type": "Feature",
  "properties": {
    "iso:country":"US",
    "sg:address":"8281 3rd Ln",
    "sg:city":"Marathon",
    "sg:classifiers":[
        {
            "category":"Manufacturing",
            "subcategory":"Food",
            "type":"Manufacturing & Wholesale Goods"
        }
    ],
    "sg:phone":"+1 715 443 2526",
    "sg:postcode":"54448",
    "sg:province":"WI",
    "sg:tags":[
        "cheese",
        "mfg"
    ],
    "wof:name":"Bletsoes Honeybee Cheese Fctry",
    "wof:placetype":"venue"
},
  "geometry": {"coordinates":[-89.864891,45.054576],"type":"Point"}
}