{
  "type": "Feature",
  "properties": {
    "iso:country":"US",
    "sg:address":"1419 100th Ave",
    "sg:city":"Amery",
    "sg:classifiers":[
        {
            "category":"Building & Trades",
            "subcategory":"Construction",
            "type":"Services"
        }
    ],
    "sg:phone":"+1 715 268 2541",
    "sg:postcode":"54001",
    "sg:province":"WI",
    "sg:tags":[
        "contractor"
    ],
    "wof:name":"Ryans Custom Tile",
    "wof:placetype":"venue"
},
  "geometry": {"coordinates":[-92.451892,45.353555],"type":"Point"}
}