{
  "type": "Feature",
  "properties": {
    "iso:country":"US",
    "sg:address":"2693 Jordan Rd",
    "sg:city":"Juda",
    "sg:classifiers":[
        {
            "category":"Farming",
            "subcategory":"Dairy Farm",
            "type":"Manufacturing & Wholesale Goods"
        }
    ],
    "sg:phone":"+1 608 934 1565",
    "sg:postcode":"53550",
    "sg:province":"WI",
    "wof:name":"Hosto Registerd Holstein Farm",
    "wof:placetype":"venue"
},
  "geometry": {"coordinates":[-89.486813,42.537912],"type":"Point"}
}