{
  "type": "Feature",
  "properties": {
    "iso:country":"US",
    "sg:address":"3101 N 20th St",
    "sg:city":"Milwaukee",
    "sg:classifiers":[
        {
            "category":"Professional",
            "subcategory":"Business Services",
            "type":"Services"
        }
    ],
    "sg:phone":"+1 414 873 6423",
    "sg:postcode":"53206",
    "sg:province":"WI",
    "sg:tags":[
        "interior",
        "consultant",
        "design",
        "decorator"
    ],
    "wof:name":"X Cel",
    "wof:placetype":"venue"
},
  "geometry": {"coordinates":[-87.937354,43.075767],"type":"Point"}
}