{
  "type": "Feature",
  "properties": {
    "iso:country":"US",
    "sg:address":"122 S Main St",
    "sg:city":"Elmwood",
    "sg:classifiers":[
        {
            "category":"Personal",
            "subcategory":"Beauty Salon",
            "type":"Services"
        }
    ],
    "sg:phone":"+1 715 639 4351",
    "sg:postcode":"54740",
    "sg:province":"WI",
    "wof:name":"Nancy's Beauty Salon",
    "wof:placetype":"venue"
},
  "geometry": {"coordinates":[-92.151348,44.779298],"type":"Point"}
}