{
  "type": "Feature",
  "properties": {
    "iso:country":"US",
    "sg:address":"517 State St",
    "sg:city":"Madison",
    "sg:classifiers":[
        {
            "category":"Shopping",
            "subcategory":"Gifts & Souvenirs",
            "type":"Retail Goods"
        }
    ],
    "sg:phone":"+1 608 257 2400",
    "sg:postcode":"53703",
    "sg:province":"WI",
    "sg:tags":[
        "poster"
    ],
    "wof:name":"Pipefitter Ltd",
    "wof:placetype":"venue"
},
  "geometry": {"coordinates":[-89.394884,43.07477],"type":"Point"}
}