{
  "type": "Feature",
  "properties": {
    "iso:country":"US",
    "sg:address":"1409 Travis St",
    "sg:city":"La Crosse",
    "sg:classifiers":[
        {
            "category":"Building & Trades",
            "subcategory":"Plumbing",
            "type":"Services"
        }
    ],
    "sg:phone":"+1 608 787 7663",
    "sg:postcode":"54601",
    "sg:province":"WI",
    "sg:tags":[
        "contractor"
    ],
    "wof:name":"Dd Plumbing",
    "wof:placetype":"venue"
},
  "geometry": {"coordinates":[-91.234856,43.792443],"type":"Point"}
}