{
  "type": "Feature",
  "properties": {
    "iso:country":"US",
    "sg:address":"909 Front St",
    "sg:city":"Cashton",
    "sg:classifiers":[
        {
            "category":"Restaurant",
            "type":"Food & Drink"
        }
    ],
    "sg:phone":"+1 608 654 5706",
    "sg:postcode":"54619",
    "sg:province":"WI",
    "sg:tags":[
        "eating"
    ],
    "wof:name":"Badger Crossing Pub & Eatery",
    "wof:placetype":"venue"
},
  "geometry": {"coordinates":[-90.777807,43.744436],"type":"Point"}
}