{
  "type": "Feature",
  "properties": {
    "iso:country":"US",
    "sg:address":"4330 Brusse Rd",
    "sg:city":"Sheboygan Falls",
    "sg:classifiers":[
        {
            "category":"Farming",
            "subcategory":"Livestock Farm",
            "type":"Manufacturing & Wholesale Goods"
        }
    ],
    "sg:phone":"+1 920 467 8546",
    "sg:postcode":"53085",
    "sg:province":"WI",
    "sg:tags":[
        "equine"
    ],
    "wof:name":"Philip Muehlberger",
    "wof:placetype":"venue"
},
  "geometry": {"coordinates":[-87.840435,43.69772],"type":"Point"}
}