{
  "type": "Feature",
  "properties": {
    "iso:country":"US",
    "sg:address":"1804 14th St",
    "sg:city":"Two Rivers",
    "sg:classifiers":[
        {
            "category":"Restaurant",
            "type":"Food & Drink"
        }
    ],
    "sg:phone":"+1 920 794 7001",
    "sg:postcode":"54241",
    "sg:province":"WI",
    "sg:tags":[
        "drinking",
        "eating"
    ],
    "wof:name":"Joyseann Pizza",
    "wof:placetype":"venue"
},
  "geometry": {"coordinates":[-87.574448,44.146243],"type":"Point"}
}