{
  "type": "Feature",
  "properties": {
    "iso:country":"US",
    "sg:address":"786 Harvard Dr",
    "sg:city":"Neenah",
    "sg:classifiers":[
        {
            "category":"Professional",
            "subcategory":"Employment Agencies",
            "type":"Services"
        }
    ],
    "sg:phone":"+1 920 722 0259",
    "sg:postcode":"54956",
    "sg:province":"WI",
    "wof:name":"T M S I",
    "wof:placetype":"venue"
},
  "geometry": {"coordinates":[-88.519252,44.177645],"type":"Point"}
}