{
  "type": "Feature",
  "properties": {
    "iso:country":"US",
    "sg:address":"3979 Lakeview Rd",
    "sg:city":"Markesan",
    "sg:classifiers":[
        {
            "category":"Professional",
            "type":"Services"
        }
    ],
    "sg:phone":"+1 920 398 2247",
    "sg:postcode":"53946",
    "sg:province":"WI",
    "wof:name":"Bremer Dairy LLC",
    "wof:placetype":"venue"
},
  "geometry": {"coordinates":[-88.986323,43.784439],"type":"Point"}
}