{
  "type": "Feature",
  "properties": {
    "addr:full":"1356 Wild Rose Ln Neenah WI 54956",
    "addr:housenumber":"1356",
    "addr:postcode":"54956",
    "addr:street":"Wild Rose Ln",
    "iso:country":"US",
    "sg:address":"1356 Wild Rose Ln",
    "sg:city":"Neenah",
    "sg:classifiers":[
        {
            "category":"Wholesale",
            "subcategory":"Groceries",
            "type":"Manufacturing & Wholesale Goods"
        }
    ],
    "sg:phone":"+1 920 886 9969",
    "sg:postcode":"54956",
    "sg:province":"WI",
    "sg:tags":[
        "food",
        "product"
    ],
    "wof:name":"Pyramid Foods",
    "wof:placetype":"venue"
},
  "geometry": {"coordinates":[-88.493802,44.158972],"type":"Point"}
}