{
  "type": "Feature",
  "properties": {
    "addr:full":"844 Willard Dr Green Bay WI 54304",
    "addr:housenumber":"844",
    "addr:postcode":"54304",
    "addr:street":"Willard Dr",
    "iso:country":"US",
    "sg:address":"844 Willard Dr",
    "sg:city":"Green Bay",
    "sg:classifiers":[
        {
            "category":"Professional",
            "subcategory":"Employment Agencies",
            "type":"Services"
        }
    ],
    "sg:phone":"+1 920 498 9090",
    "sg:postcode":"54304",
    "sg:province":"WI",
    "sg:tags":[
        "opportunity"
    ],
    "wof:name":"Trillium Staffing Solutions",
    "wof:placetype":"venue"
},
  "geometry": {"coordinates":[-88.06337499999999,44.485849],"type":"Point"}
}