{
  "type": "Feature",
  "properties": {
    "addr:full":"268 Reid St Fontana WI 53125",
    "addr:housenumber":"268",
    "addr:postcode":"53125",
    "addr:street":"Reid St",
    "iso:country":"US",
    "sg:address":"268 Reid St",
    "sg:city":"Fontana",
    "sg:classifiers":[
        {
            "category":"Bars & Pubs",
            "type":"Food & Drink"
        }
    ],
    "sg:phone":"+1 262 275 6848",
    "sg:postcode":"53125",
    "sg:province":"WI",
    "wof:name":"Who's On Third",
    "wof:placetype":"venue"
},
  "geometry": {"coordinates":[-88.574928,42.5509],"type":"Point"}
}