{
  "type": "Feature",
  "properties": {
    "iso:country":"US",
    "sg:address":"202 Calumet Dr",
    "sg:city":"Valders",
    "sg:classifiers":[
        {
            "category":"Wholesale",
            "subcategory":"Meat",
            "type":"Manufacturing & Wholesale Goods"
        }
    ],
    "sg:phone":"+1 920 775 4323",
    "sg:postcode":"54245",
    "sg:province":"WI",
    "sg:tags":[
        "packer"
    ],
    "wof:name":"Tuschel's Country Meats",
    "wof:placetype":"venue"
},
  "geometry": {"coordinates":[-87.883758,44.067028],"type":"Point"}
}