{
  "type": "Feature",
  "properties": {
    "addr:full":"1623 Durand Ave Racine WI 53403",
    "addr:housenumber":"1623",
    "addr:postcode":"53403",
    "addr:street":"Durand Ave",
    "iso:country":"US",
    "sg:address":"1623 Durand Ave",
    "sg:city":"Racine",
    "sg:classifiers":[
        {
            "category":"Retail",
            "subcategory":"Auto Repair",
            "type":"Services"
        }
    ],
    "sg:phone":"+1 262 635 0874",
    "sg:postcode":"53403",
    "sg:province":"WI",
    "sg:tags":[
        "repairing",
        "automobile"
    ],
    "wof:name":"Amc Automotive Ctr",
    "wof:placetype":"venue"
},
  "geometry": {"coordinates":[-87.79912,42.696943],"type":"Point"}
}