{
  "type": "Feature",
  "properties": {
    "iso:country":"US",
    "sg:address":"2152 Colladay Point Dr",
    "sg:city":"Stoughton",
    "sg:classifiers":[
        {
            "category":"Freight",
            "type":"Transportation"
        }
    ],
    "sg:phone":"+1 608 873 3036",
    "sg:postcode":"53589",
    "sg:province":"WI",
    "sg:tags":[
        "operator",
        "local",
        "trucking"
    ],
    "wof:name":"Steven Linnerud",
    "wof:placetype":"venue"
},
  "geometry": {"coordinates":[-89.275559,42.963316],"type":"Point"}
}