{
  "type": "Feature",
  "properties": {
    "iso:country":"US",
    "sg:address":"8053 Stump Ridge Rd",
    "sg:city":"Viroqua",
    "sg:classifiers":[
        {
            "category":"Building & Trades",
            "subcategory":"Electrical",
            "type":"Services"
        }
    ],
    "sg:phone":"+1 608 624 5959",
    "sg:postcode":"54665",
    "sg:province":"WI",
    "sg:tags":[
        "electric",
        "contractor"
    ],
    "wof:name":"G & S Electric",
    "wof:placetype":"venue"
},
  "geometry": {"coordinates":[-90.869068,43.446907],"type":"Point"}
}