{
  "type": "Feature",
  "properties": {
    "iso:country":"US",
    "sg:address":"807 S Main St",
    "sg:city":"Viroqua",
    "sg:classifiers":[
        {
            "category":"Food & Beverages",
            "subcategory":"Bakery",
            "type":"Retail Goods"
        }
    ],
    "sg:phone":"+1 608 637 8579",
    "sg:postcode":"54665",
    "sg:province":"WI",
    "sg:tags":[
        "baker"
    ],
    "wof:name":"Cakery & Bake Shop LLC",
    "wof:placetype":"venue"
},
  "geometry": {"coordinates":[-90.88864100000001,43.547812],"type":"Point"}
}