{
  "type": "Feature",
  "properties": {
    "iso:country":"US",
    "sg:address":"1000 Ihm St",
    "sg:city":"Lancaster",
    "sg:classifiers":[
        {
            "category":"Banks & Credit Unions",
            "subcategory":"Bank",
            "type":"Services"
        }
    ],
    "sg:phone":"+1 608 723 7470",
    "sg:postcode":"53813",
    "sg:province":"WI",
    "sg:tags":[
        "federal"
    ],
    "wof:name":"Heartland Credit Union",
    "wof:placetype":"venue"
},
  "geometry": {"coordinates":[-90.707258,42.862389],"type":"Point"}
}