{
  "type": "Feature",
  "properties": {
    "addr:full":"5728 Easy St Waunakee WI 53597",
    "addr:housenumber":"5728",
    "addr:postcode":"53597",
    "addr:street":"Easy St",
    "iso:country":"US",
    "sg:address":"5728 Easy St",
    "sg:city":"Waunakee",
    "sg:classifiers":[
        {
            "category":"Farming",
            "subcategory":"Dairy Farm",
            "type":"Manufacturing & Wholesale Goods"
        }
    ],
    "sg:phone":"+1 608 849 9281",
    "sg:postcode":"53597",
    "sg:province":"WI",
    "wof:name":"Meffert Homested",
    "wof:placetype":"venue"
},
  "geometry": {"coordinates":[-89.432743,43.206578],"type":"Point"}
}