{
  "type": "Feature",
  "properties": {
    "addr:full":"1113 Spleas Skoney Rd East Troy WI 53120",
    "addr:housenumber":"1113",
    "addr:postcode":"53120",
    "addr:street":"Spleas Skoney Rd",
    "iso:country":"US",
    "sg:address":"1113 Spleas Skoney Rd",
    "sg:city":"East Troy",
    "sg:classifiers":[
        {
            "category":"Building & Trades",
            "subcategory":"Landscaping Services",
            "type":"Services"
        }
    ],
    "sg:phone":"+1 262 642 9590",
    "sg:postcode":"53120",
    "sg:province":"WI",
    "wof:name":"Brautigam Environmental Svcs",
    "wof:placetype":"venue"
},
  "geometry": {"coordinates":[-88.360466,42.817551],"type":"Point"}
}