{
  "type": "Feature",
  "properties": {
    "addr:full":"7915 Shorewood Dr Salem WI 53168",
    "addr:housenumber":"7915",
    "addr:postcode":"53168",
    "addr:street":"Shorewood Dr",
    "iso:country":"US",
    "sg:address":"7915 Shorewood Dr",
    "sg:city":"Salem",
    "sg:classifiers":[
        {
            "category":"Bars & Pubs",
            "type":"Food & Drink"
        }
    ],
    "sg:phone":"+1 262 877 8517",
    "sg:postcode":"53168",
    "sg:province":"WI",
    "sg:tags":[
        "drinking"
    ],
    "wof:name":"Lakeside Skybox",
    "wof:placetype":"venue"
},
  "geometry": {"coordinates":[-88.17990899999999,42.561911],"type":"Point"}
}