{
  "type": "Feature",
  "properties": {
    "iso:country":"US",
    "sg:address":"2775 Ledge Rd",
    "sg:city":"Mount Calvary",
    "sg:classifiers":[
        {
            "category":"Farming",
            "subcategory":"Farm",
            "type":"Manufacturing & Wholesale Goods"
        }
    ],
    "sg:phone":"+1 920 922 7593",
    "sg:postcode":"53057",
    "sg:province":"WI",
    "sg:tags":[
        "crop",
        "general"
    ],
    "wof:name":"Keith J Birschbach",
    "wof:placetype":"venue"
},
  "geometry": {"coordinates":[-88.29454699999999,43.819228],"type":"Point"}
}