{
  "type": "Feature",
  "properties": {
    "iso:country":"US",
    "sg:address":"1042 Pembrook Dr",
    "sg:city":"Neenah",
    "sg:classifiers":[
        {
            "category":"Home & Garden",
            "subcategory":"Home Furnishings",
            "type":"Retail Goods"
        }
    ],
    "sg:phone":"+1 920 751 0734",
    "sg:postcode":"54956",
    "sg:province":"WI",
    "wof:name":"Bayfeild Inn LLC",
    "wof:placetype":"venue"
},
  "geometry": {"coordinates":[-88.452699,44.16761],"type":"Point"}
}