{
  "type": "Feature",
  "properties": {
    "iso:country":"US",
    "sg:address":"310 N Brown St",
    "sg:city":"Rhinelander",
    "sg:classifiers":[
        {
            "category":"Building & Trades",
            "subcategory":"Plumbing",
            "type":"Services"
        }
    ],
    "sg:phone":"+1 715 369 1234",
    "sg:postcode":"54501",
    "sg:province":"WI",
    "sg:tags":[
        "plumbing",
        "contractor"
    ],
    "wof:name":"Frasier's Plumbing Heat & Cool",
    "wof:placetype":"venue"
},
  "geometry": {"coordinates":[-89.412673,45.642314],"type":"Point"}
}