{
  "type": "Feature",
  "properties": {
    "iso:country":"US",
    "sg:address":"214 Belmont Cir",
    "sg:city":"Madison",
    "sg:classifiers":[
        {
            "category":"Food & Beverages",
            "subcategory":"Candy",
            "type":"Retail Goods"
        }
    ],
    "sg:phone":"+1 608 244 1988",
    "sg:postcode":"53714",
    "sg:province":"WI",
    "sg:tags":[
        "eating"
    ],
    "wof:name":"Ashard Concessions Inc",
    "wof:placetype":"venue"
},
  "geometry": {"coordinates":[-89.307131,43.095468],"type":"Point"}
}