{
  "type": "Feature",
  "properties": {
    "iso:country":"US",
    "sg:address":"4650 Stagecoach Rd",
    "sg:city":"Green Bay",
    "sg:classifiers":[
        {
            "category":"Bars & Pubs",
            "type":"Food & Drink"
        }
    ],
    "sg:phone":"+1 920 863 3710",
    "sg:postcode":"54311",
    "sg:province":"WI",
    "sg:tags":[
        "drinking"
    ],
    "wof:name":"Terry's Pine Grove Pub",
    "wof:placetype":"venue"
},
  "geometry": {"coordinates":[-87.887872,44.415013],"type":"Point"}
}