{
  "type": "Feature",
  "properties": {
    "addr:full":"214 N Main St River Falls WI 54022",
    "addr:housenumber":"214",
    "addr:postcode":"54022",
    "addr:street":"N Main St",
    "iso:country":"US",
    "sg:address":"214 N Main St",
    "sg:city":"River Falls",
    "sg:classifiers":[
        {
            "category":"Professional",
            "type":"Services"
        }
    ],
    "sg:phone":"+1 715 426 2557",
    "sg:postcode":"54022",
    "sg:province":"WI",
    "sg:tags":[
        "establishment"
    ],
    "wof:name":"Friends Of Sheila Harsdorf",
    "wof:placetype":"venue"
},
  "geometry": {"coordinates":[-92.624932,44.860462],"type":"Point"}
}