{
  "type": "Feature",
  "properties": {
    "addr:full":"231 Woodland Dr Waupun WI 53963",
    "addr:housenumber":"231",
    "addr:postcode":"53963",
    "addr:street":"Woodland Dr",
    "iso:country":"US",
    "sg:address":"231 Woodland Dr",
    "sg:city":"Waupun",
    "sg:classifiers":[
        {
            "category":"Wholesale",
            "subcategory":"Construction Materials",
            "type":"Manufacturing & Wholesale Goods"
        }
    ],
    "sg:phone":"+1 920 324 5115",
    "sg:postcode":"53963",
    "sg:province":"WI",
    "wof:name":"Larson Trucking",
    "wof:placetype":"venue"
},
  "geometry": {"coordinates":[-88.730897,43.641738],"type":"Point"}
}