{
  "type": "Feature",
  "properties": {
    "iso:country":"US",
    "sg:address":"630 1st St",
    "sg:city":"Wausau",
    "sg:classifiers":[
        {
            "category":"Health Services",
            "subcategory":"Doctor",
            "type":"Services"
        }
    ],
    "sg:phone":"+1 715 842 0314",
    "sg:postcode":"54403",
    "sg:province":"WI",
    "wof:name":"Thomas J Nick DDS",
    "wof:placetype":"venue"
},
  "geometry": {"coordinates":[-89.630045,44.96222],"type":"Point"}
}