{
  "type": "Feature",
  "properties": {
    "iso:country":"US",
    "sg:address":"316 W Allerton Ave",
    "sg:city":"Milwaukee",
    "sg:classifiers":[
        {
            "category":"Building & Trades",
            "subcategory":"Landscaping Services",
            "type":"Services"
        }
    ],
    "sg:phone":"+1 414 744 2037",
    "sg:postcode":"53207",
    "sg:province":"WI",
    "sg:tags":[
        "tree"
    ],
    "wof:name":"Jays Stump Grinding Svc",
    "wof:placetype":"venue"
},
  "geometry": {"coordinates":[-87.916839,42.963485],"type":"Point"}
}