{
  "type": "Feature",
  "properties": {
    "addr:full":"5750 W Grande Market Dr Appleton WI 54913",
    "addr:housenumber":"5750",
    "addr:postcode":"54913",
    "addr:street":"W Grande Market Dr",
    "iso:country":"US",
    "sg:address":"5750 W Grande Market Dr",
    "sg:city":"Appleton",
    "sg:classifiers":[
        {
            "category":"Banks & Credit Unions",
            "subcategory":"Investment Brokerage",
            "type":"Services"
        }
    ],
    "sg:phone":"+1 920 993 1526",
    "sg:postcode":"54913",
    "sg:province":"WI",
    "sg:tags":[
        "consultant",
        "security",
        "planning",
        "financial"
    ],
    "wof:name":"Raymond James Financial Svcs",
    "wof:placetype":"venue"
},
  "geometry": {"coordinates":[-88.49417099999999,44.263747],"type":"Point"}
}