{
  "type": "Feature",
  "properties": {
    "iso:country":"US",
    "sg:address":"419 E Main St",
    "sg:city":"Stoughton",
    "sg:classifiers":[
        {
            "category":"Restaurant",
            "type":"Food & Drink"
        }
    ],
    "sg:phone":"+1 608 873 3808",
    "sg:postcode":"53589",
    "sg:province":"WI",
    "wof:name":"Laz Bistro & Bar",
    "wof:placetype":"venue"
},
  "geometry": {"coordinates":[-89.214039,42.917908],"type":"Point"}
}