{
  "type": "Feature",
  "properties": {
    "iso:country":"US",
    "sg:address":"5475 Co Rd T",
    "sg:city":"New London",
    "sg:classifiers":[
        {
            "category":"Organizations",
            "subcategory":"Religious Organization",
            "type":"Services"
        }
    ],
    "sg:phone":"+1 920 982 5475",
    "sg:postcode":"54961",
    "sg:province":"WI",
    "sg:tags":[
        "church"
    ],
    "wof:name":"St Patrick Parish",
    "wof:placetype":"venue"
},
  "geometry": {"coordinates":[-88.732714,44.381077],"type":"Point"}
}