{
  "type": "Feature",
  "properties": {
    "iso:country":"US",
    "sg:address":"1837 Ludden Dr",
    "sg:city":"Cross Plains",
    "sg:classifiers":[
        {
            "category":"Social Services",
            "subcategory":"Child Care",
            "type":"Services"
        }
    ],
    "sg:phone":"+1 608 798 4041",
    "sg:postcode":"53528",
    "sg:province":"WI",
    "sg:tags":[
        "day"
    ],
    "wof:name":"Raggedy Ann & Andy Pre-School",
    "wof:placetype":"venue"
},
  "geometry": {"coordinates":[-89.657373,43.10808],"type":"Point"}
}