{
  "type": "Feature",
  "properties": {
    "addr:full":"4601 S 27th St Milwaukee WI 53221",
    "addr:housenumber":"4601",
    "addr:postcode":"53221",
    "addr:street":"S 27Th St",
    "iso:country":"US",
    "sg:address":"4601 S 27th St",
    "sg:city":"Milwaukee",
    "sg:classifiers":[
        {
            "category":"Shopping",
            "subcategory":"Department Store",
            "type":"Retail Goods"
        }
    ],
    "sg:phone":"+1 414 282 1020",
    "sg:postcode":"53221",
    "sg:province":"WI",
    "sg:website":"www.mykmart.com",
    "wof:name":"Kmart",
    "wof:placetype":"venue"
},
  "geometry": {"coordinates":[-87.948683,42.961596],"type":"Point"}
}