{
  "type": "Feature",
  "properties": {
    "addr:full":"401 Ridge St Madison WI 53705",
    "addr:housenumber":"401",
    "addr:postcode":"53705",
    "addr:street":"Ridge St",
    "iso:country":"US",
    "sg:address":"401 Ridge St",
    "sg:city":"Madison",
    "sg:classifiers":[
        {
            "category":"Professional",
            "type":"Services"
        }
    ],
    "sg:phone":"+1 608 231 6839",
    "sg:postcode":"53705",
    "sg:province":"WI",
    "sg:tags":[
        "establishment"
    ],
    "wof:name":"Schubert & Schubert",
    "wof:placetype":"venue"
},
  "geometry": {"coordinates":[-89.43885899999999,43.071754],"type":"Point"}
}