{
  "type": "Feature",
  "properties": {
    "addr:full":"1332 Traders Rd Menasha WI 54952",
    "addr:housenumber":"1332",
    "addr:postcode":"54952",
    "addr:street":"Traders Rd",
    "iso:country":"US",
    "sg:address":"1332 Traders Rd",
    "sg:city":"Menasha",
    "sg:classifiers":[
        {
            "category":"Real Estate",
            "subcategory":"Real Estate Operator",
            "type":"Services"
        }
    ],
    "sg:phone":"+1 920 725 0497",
    "sg:postcode":"54952",
    "sg:province":"WI",
    "sg:tags":[
        "building",
        "apartment"
    ],
    "wof:name":"Cottonwood Creek",
    "wof:placetype":"venue"
},
  "geometry": {"coordinates":[-88.421767,44.212082],"type":"Point"}
}