{
  "type": "Feature",
  "properties": {
    "iso:country":"US",
    "sg:address":"911 W Exchange St",
    "sg:city":"Brodhead",
    "sg:classifiers":[
        {
            "category":"Insurance",
            "subcategory":"Insurance Agent",
            "type":"Services"
        }
    ],
    "sg:phone":"+1 608 897 5009",
    "sg:postcode":"53520",
    "sg:province":"WI",
    "wof:name":"Rural Insurance Co",
    "wof:placetype":"venue"
},
  "geometry": {"coordinates":[-89.377952,42.619828],"type":"Point"}
}