{
  "type": "Feature",
  "properties": {
    "iso:country":"US",
    "sg:address":"1412 W Kamps Ave",
    "sg:city":"Appleton",
    "sg:classifiers":[
        {
            "category":"Building & Trades",
            "subcategory":"Construction",
            "type":"Services"
        }
    ],
    "sg:phone":"+1 920 734 7116",
    "sg:postcode":"54914",
    "sg:province":"WI",
    "sg:tags":[
        "contractor"
    ],
    "wof:name":"Riehl Construction & Masonry I",
    "wof:placetype":"venue"
},
  "geometry": {"coordinates":[-88.42943,44.274094],"type":"Point"}
}