{
  "type": "Feature",
  "properties": {
    "addr:full":"2026 Rose Ct La Crosse WI 54603",
    "addr:housenumber":"2026",
    "addr:postcode":"54603",
    "addr:street":"Rose Ct",
    "iso:country":"US",
    "sg:address":"2026 Rose Ct",
    "sg:city":"La Crosse",
    "sg:classifiers":[
        {
            "category":"Sports & Exercise",
            "subcategory":"Gym",
            "type":"Entertainment"
        }
    ],
    "sg:phone":"+1 608 779 5004",
    "sg:postcode":"54603",
    "sg:province":"WI",
    "sg:tags":[
        "fitness",
        "physical",
        "facility"
    ],
    "sg:website":"www.curves.com",
    "wof:name":"Curves For Women",
    "wof:placetype":"venue"
},
  "geometry": {"coordinates":[-91.24734599999999,43.852386],"type":"Point"}
}