{
  "type": "Feature",
  "properties": {
    "addr:full":"5642 Mohawk Rd Rhinelander WI 54501",
    "addr:housenumber":"5642",
    "addr:postcode":"54501",
    "addr:street":"Mohawk Rd",
    "iso:country":"US",
    "sg:address":"5642 Mohawk Rd",
    "sg:city":"Rhinelander",
    "sg:classifiers":[
        {
            "category":"Government",
            "subcategory":"Office",
            "type":"Public Place"
        }
    ],
    "sg:phone":"+1 715 362 5655",
    "sg:postcode":"54501",
    "sg:province":"WI",
    "wof:name":"4-H Youth Dept",
    "wof:placetype":"venue"
},
  "geometry": {"coordinates":[-89.437371,45.65843],"type":"Point"}
}