{
  "type": "Feature",
  "properties": {
    "addr:full":"929 Greenfield Ave Sheboygan WI 53081",
    "addr:housenumber":"929",
    "addr:postcode":"53081",
    "addr:street":"Greenfield Ave",
    "iso:country":"US",
    "sg:address":"929 Greenfield Ave",
    "sg:city":"Sheboygan",
    "sg:classifiers":[
        {
            "category":"Organizations",
            "subcategory":"Religious Organization",
            "type":"Services"
        }
    ],
    "sg:phone":"+1 920 208 9605",
    "sg:postcode":"53081",
    "sg:province":"WI",
    "wof:name":"Fresh Rain Worship Center",
    "wof:placetype":"venue"
},
  "geometry": {"coordinates":[-87.717005,43.717583],"type":"Point"}
}