{
  "type": "Feature",
  "properties": {
    "addr:full":"30355 Durand Ave Burlington WI 53105",
    "addr:housenumber":"30355",
    "addr:postcode":"53105",
    "addr:street":"Durand Ave",
    "iso:country":"US",
    "sg:address":"30355 Durand Ave",
    "sg:city":"Burlington",
    "sg:classifiers":[
        {
            "category":"Wholesale",
            "subcategory":"Non-durable Goods",
            "type":"Manufacturing & Wholesale Goods"
        }
    ],
    "sg:phone":"+1 262 767 2855",
    "sg:postcode":"53105",
    "sg:province":"WI",
    "sg:tags":[
        "promotional",
        "advertising",
        "specialty"
    ],
    "wof:name":"Worldwide",
    "wof:placetype":"venue"
},
  "geometry": {"coordinates":[-88.23209300000001,42.68203],"type":"Point"}
}