{
  "type": "Feature",
  "properties": {
    "addr:full":"500 Rainbow Dr Peshtigo WI 54157",
    "addr:housenumber":"500",
    "addr:postcode":"54157",
    "addr:street":"Rainbow Dr",
    "iso:country":"US",
    "sg:address":"500 Rainbow Dr",
    "sg:city":"Peshtigo",
    "sg:classifiers":[
        {
            "category":"Restaurant",
            "type":"Food & Drink"
        }
    ],
    "sg:phone":"+1 715 735 8973",
    "sg:postcode":"54157",
    "sg:province":"WI",
    "wof:name":"Burger King",
    "wof:placetype":"venue"
},
  "geometry": {"coordinates":[-87.737568,45.046886],"type":"Point"}
}