{
  "type": "Feature",
  "properties": {
    "iso:country":"US",
    "sg:address":"6485 State Hwy 95",
    "sg:city":"Neillsville",
    "sg:classifiers":[
        {
            "category":"Professional",
            "subcategory":"Management & Consulting",
            "type":"Services"
        }
    ],
    "sg:phone":"+1 715 743 3037",
    "sg:postcode":"54456",
    "sg:province":"WI",
    "sg:tags":[
        "consultant",
        "safety"
    ],
    "wof:name":"Zeigle Consulting Associates",
    "wof:placetype":"venue"
},
  "geometry": {"coordinates":[-90.634778,44.479786],"type":"Point"}
}