{
  "type": "Feature",
  "properties": {
    "iso:country":"US",
    "sg:address":"5138 N Mayflower Dr",
    "sg:city":"Appleton",
    "sg:classifiers":[
        {
            "category":"Farming",
            "subcategory":"Farm",
            "type":"Manufacturing & Wholesale Goods"
        }
    ],
    "sg:phone":"+1 920 757 5047",
    "sg:postcode":"54913",
    "sg:province":"WI",
    "sg:tags":[
        "crop",
        "general"
    ],
    "wof:name":"Neubert Farm S Gary",
    "wof:placetype":"venue"
},
  "geometry": {"coordinates":[-88.496349,44.316503],"type":"Point"}
}