{
  "type": "Feature",
  "properties": {
    "iso:country":"US",
    "sg:address":"2688 S Stevenson Pier Rd",
    "sg:city":"Brussels",
    "sg:classifiers":[
        {
            "category":"Building & Trades",
            "subcategory":"Cleaning & Sanitation",
            "type":"Services"
        }
    ],
    "sg:phone":"+1 920 866 2800",
    "sg:postcode":"54204",
    "sg:province":"WI",
    "sg:tags":[
        "maintenance"
    ],
    "wof:name":"Wexel Industrial Supply",
    "wof:placetype":"venue"
},
  "geometry": {"coordinates":[-87.548947,44.79141],"type":"Point"}
}