{
  "type": "Feature",
  "properties": {
    "iso:country":"US",
    "sg:address":"2434 N 9th St",
    "sg:city":"Milwaukee",
    "sg:classifiers":[
        {
            "category":"Professional",
            "subcategory":"Accounting & Tax Preparation",
            "type":"Services"
        }
    ],
    "sg:phone":"+1 414 475 6418",
    "sg:postcode":"53206",
    "sg:province":"WI",
    "sg:tags":[
        "accountant"
    ],
    "wof:name":"Edward J O'Keefe CPA",
    "wof:placetype":"venue"
},
  "geometry": {"coordinates":[-87.922621,43.063337],"type":"Point"}
}