{
  "type": "Feature",
  "properties": {
    "iso:country":"US",
    "sg:address":"2 Dunraven Ct",
    "sg:city":"Madison",
    "sg:classifiers":[
        {
            "category":"Building & Trades",
            "subcategory":"Electrical",
            "type":"Services"
        }
    ],
    "sg:phone":"+1 608 821 0801",
    "sg:postcode":"53705",
    "sg:province":"WI",
    "sg:tags":[
        "electrical",
        "contractor"
    ],
    "wof:name":"Ic Cards Inc",
    "wof:placetype":"venue"
},
  "geometry": {"coordinates":[-89.49368699999999,43.062019],"type":"Point"}
}