{
  "type": "Feature",
  "properties": {
    "iso:country":"US",
    "sg:address":"2612 E Shorewood Blvd",
    "sg:city":"Milwaukee",
    "sg:classifiers":[
        {
            "category":"Banks & Credit Unions",
            "subcategory":"Financial Services",
            "type":"Services"
        }
    ],
    "sg:phone":"+1 414 962 2385",
    "sg:postcode":"53211",
    "sg:province":"WI",
    "sg:tags":[
        "investment",
        "closed"
    ],
    "wof:name":"Thornburg Investment Mgt Co",
    "wof:placetype":"venue"
},
  "geometry": {"coordinates":[-87.87361799999999,43.087155],"type":"Point"}
}