{
  "type": "Feature",
  "properties": {
    "iso:country":"US",
    "sg:address":"826 E Meinecke Ave",
    "sg:city":"Milwaukee",
    "sg:classifiers":[
        {
            "category":"Personal",
            "subcategory":"Barber",
            "type":"Services"
        }
    ],
    "sg:phone":"+1 414 263 2711",
    "sg:postcode":"53212",
    "sg:province":"WI",
    "sg:tags":[
        "shop"
    ],
    "wof:name":"Peter's Barber Shop",
    "wof:placetype":"venue"
},
  "geometry": {"coordinates":[-87.900723,43.062094],"type":"Point"}
}