{
  "type": "Feature",
  "properties": {
    "iso:country":"US",
    "sg:address":"750 N Union St",
    "sg:city":"Mauston",
    "sg:classifiers":[
        {
            "category":"Food & Beverages",
            "subcategory":"Groceries & Convenience Stores",
            "type":"Retail Goods"
        }
    ],
    "sg:phone":"+1 608 847 4331",
    "sg:postcode":"53948",
    "sg:province":"WI",
    "sg:tags":[
        "grocer"
    ],
    "wof:name":"Pick n Save",
    "wof:placetype":"venue"
},
  "geometry": {"coordinates":[-90.069891,43.804703],"type":"Point"}
}