{
  "type": "Feature",
  "properties": {
    "iso:country":"US",
    "sg:address":"11345 Cedarburg Rd",
    "sg:city":"Mequon",
    "sg:classifiers":[
        {
            "category":"Education",
            "subcategory":"Library",
            "type":"Public Place"
        }
    ],
    "sg:phone":"+1 262 242 2593",
    "sg:postcode":"53092",
    "sg:province":"WI",
    "sg:website":"www.flwlib.org",
    "wof:name":"Frank L Weyenberg Library",
    "wof:placetype":"venue"
},
  "geometry": {"coordinates":[-87.983377,43.222662],"type":"Point"}
}