{
  "type": "Feature",
  "properties": {
    "iso:country":"US",
    "sg:address":"2593 Pine Tree Rd",
    "sg:city":"Monroe",
    "sg:classifiers":[
        {
            "category":"Wholesale",
            "subcategory":"Chemicals & Plastics",
            "type":"Manufacturing & Wholesale Goods"
        }
    ],
    "sg:phone":"+1 608 966 1119",
    "sg:postcode":"53566",
    "sg:province":"WI",
    "wof:name":"Sharp Machine Works",
    "wof:placetype":"venue"
},
  "geometry": {"coordinates":[-89.780765,42.60679],"type":"Point"}
}