{
  "type": "Feature",
  "properties": {
    "iso:country":"US",
    "sg:address":"2685 W Mason St",
    "sg:city":"Green Bay",
    "sg:classifiers":[
        {
            "category":"Food & Beverages",
            "subcategory":"Specialty",
            "type":"Retail Goods"
        }
    ],
    "sg:phone":"+1 920 405 9110",
    "sg:postcode":"54303",
    "sg:province":"WI",
    "sg:tags":[
        "herb"
    ],
    "wof:name":"Judy's Herbs",
    "wof:placetype":"venue"
},
  "geometry": {"coordinates":[-88.10952899999999,44.523944],"type":"Point"}
}