{
  "type": "Feature",
  "properties": {
    "iso:country":"US",
    "sg:address":"11005 State Hwy 60",
    "sg:city":"Sauk City",
    "sg:classifiers":[
        {
            "category":"Real Estate",
            "subcategory":"Real Estate Operator",
            "type":"Services"
        }
    ],
    "sg:phone":"+1 608 643 6041",
    "sg:postcode":"53583",
    "sg:province":"WI",
    "sg:tags":[
        "property",
        "lessor"
    ],
    "wof:name":"James Mack Farm",
    "wof:placetype":"venue"
},
  "geometry": {"coordinates":[-89.773488,43.270881],"type":"Point"}
}