{
  "type": "Feature",
  "properties": {
    "addr:full":"2912 S 13th St Milwaukee WI 53215",
    "addr:housenumber":"2912",
    "addr:postcode":"53215",
    "addr:street":"S 13Th St",
    "iso:country":"US",
    "sg:address":"2912 S 13th St",
    "sg:city":"Milwaukee",
    "sg:classifiers":[
        {
            "category":"Restaurant",
            "type":"Food & Drink"
        }
    ],
    "sg:phone":"+1 414 383 9876",
    "sg:postcode":"53215",
    "sg:province":"WI",
    "sg:tags":[
        "eating"
    ],
    "wof:name":"Eggs N Stuff",
    "wof:placetype":"venue"
},
  "geometry": {"coordinates":[-87.928676,42.990343],"type":"Point"}
}