{
  "type": "Feature",
  "properties": {
    "iso:country":"US",
    "sg:address":"10734 Schmoldt Rd",
    "sg:city":"Rosendale",
    "sg:classifiers":[
        {
            "category":"Farming",
            "subcategory":"Dairy Farm",
            "type":"Manufacturing & Wholesale Goods"
        }
    ],
    "sg:phone":"+1 920 872 2003",
    "sg:postcode":"54974",
    "sg:province":"WI",
    "wof:name":"Madigan Farms Inc",
    "wof:placetype":"venue"
},
  "geometry": {"coordinates":[-88.70581,43.792704],"type":"Point"}
}