{
  "type": "Feature",
  "properties": {
    "iso:country":"US",
    "sg:address":"13519 State Hwy 70",
    "sg:city":"Minocqua",
    "sg:classifiers":[
        {
            "category":"Professional",
            "subcategory":"Business Services",
            "type":"Services"
        }
    ],
    "sg:phone":"+1 715 358 7970",
    "sg:postcode":"54548",
    "sg:province":"WI",
    "wof:name":"Ai Partners LLC",
    "wof:placetype":"venue"
},
  "geometry": {"coordinates":[-89.860028,45.900155],"type":"Point"}
}