{
  "type": "Feature",
  "properties": {
    "addr:full":"2601 S Business Dr Sheboygan WI 53081",
    "addr:housenumber":"2601",
    "addr:postcode":"53081",
    "addr:street":"S Business Dr",
    "iso:country":"US",
    "sg:address":"2601 S Business Dr",
    "sg:city":"Sheboygan",
    "sg:classifiers":[
        {
            "category":"Shopping",
            "subcategory":"Optical Goods",
            "type":"Retail Goods"
        }
    ],
    "sg:phone":"+1 920 452 3252",
    "sg:postcode":"53081",
    "sg:province":"WI",
    "wof:name":"Pearle Vision Center 950123",
    "wof:placetype":"venue"
},
  "geometry": {"coordinates":[-87.73559,43.723864],"type":"Point"}
}