{
  "type": "Feature",
  "properties": {
    "iso:country":"US",
    "sg:address":"4884 W Brewery Rd",
    "sg:city":"Cross Plains",
    "sg:classifiers":[
        {
            "category":"Building & Trades",
            "subcategory":"Construction",
            "type":"Services"
        }
    ],
    "sg:phone":"+1 608 798 4114",
    "sg:postcode":"53528",
    "sg:province":"WI",
    "sg:tags":[
        "home",
        "improvement"
    ],
    "wof:name":"Dan Laufenberg & Sons",
    "wof:placetype":"venue"
},
  "geometry": {"coordinates":[-89.64224,43.129753],"type":"Point"}
}