{
  "type": "Feature",
  "properties": {
    "addr:full":"211 State St Madison WI 53703",
    "addr:housenumber":"211",
    "addr:postcode":"53703",
    "addr:street":"State St",
    "iso:country":"US",
    "sg:address":"211 State St",
    "sg:city":"Madison",
    "sg:classifiers":[
        {
            "category":"Food & Beverages",
            "subcategory":"Groceries & Convenience Stores",
            "type":"Retail Goods"
        }
    ],
    "sg:phone":"+1 608 251 4510",
    "sg:postcode":"53703",
    "sg:province":"WI",
    "sg:tags":[
        "product"
    ],
    "wof:name":"Consolidated Foods Of Dane Cou",
    "wof:placetype":"venue"
},
  "geometry": {"coordinates":[-89.38978400000001,43.074683],"type":"Point"}
}