{
  "type": "Feature",
  "properties": {
    "iso:country":"US",
    "sg:address":"329 E Milwaukee St",
    "sg:city":"Argyle",
    "sg:classifiers":[
        {
            "category":"Government",
            "subcategory":"Post Office",
            "type":"Public Place"
        }
    ],
    "sg:phone":"+1 608 543 3521",
    "sg:postcode":"53504",
    "sg:province":"WI",
    "wof:name":"US Post Office",
    "wof:placetype":"venue"
},
  "geometry": {"coordinates":[-89.866827,42.701285],"type":"Point"}
}