{
  "type": "Feature",
  "properties": {
    "iso:country":"US",
    "sg:address":"325 N Star Rd",
    "sg:city":"Holmen",
    "sg:classifiers":[
        {
            "category":"Home & Garden",
            "subcategory":"Garden Supply",
            "type":"Retail Goods"
        },
        {
            "category":"Building & Trades",
            "subcategory":"Landscaping Services",
            "type":"Services"
        }
    ],
    "sg:phone":"+1 608 526 4932",
    "sg:postcode":"54636",
    "sg:province":"WI",
    "sg:tags":[
        "landscape",
        "contractor"
    ],
    "wof:name":"Holmen Lawn & Garden Inc",
    "wof:placetype":"venue"
},
  "geometry": {"coordinates":[-91.264895,43.963417],"type":"Point"}
}