{
  "type": "Feature",
  "properties": {
    "iso:country":"US",
    "sg:address":"3840 W Helena Ave",
    "sg:city":"Milwaukee",
    "sg:classifiers":[
        {
            "category":"Professional",
            "subcategory":"Computer Services",
            "type":"Services"
        }
    ],
    "sg:phone":"+1 414 540 9423",
    "sg:postcode":"53209",
    "sg:province":"WI",
    "wof:name":"A C M Cubed",
    "wof:placetype":"venue"
},
  "geometry": {"coordinates":[-87.959413,43.145791],"type":"Point"}
}