{
  "type": "Feature",
  "properties": {
    "addr:full":"1855 Co Rd G Conrath WI 54731",
    "addr:housenumber":"1855",
    "addr:postcode":"54731",
    "addr:street":"Co Rd",
    "iso:country":"US",
    "sg:address":"1855 Co Rd G",
    "sg:city":"Conrath",
    "sg:classifiers":[
        {
            "category":"Farming",
            "subcategory":"Dairy Farm",
            "type":"Manufacturing & Wholesale Goods"
        }
    ],
    "sg:phone":"+1 715 532 5792",
    "sg:postcode":"54731",
    "sg:province":"WI",
    "wof:name":"Lynn Farley",
    "wof:placetype":"venue"
},
  "geometry": {"coordinates":[-91.028496,45.360188],"type":"Point"}
}