{
  "type": "Feature",
  "properties": {
    "iso:country":"US",
    "sg:address":"919 Hood St",
    "sg:city":"La Crosse",
    "sg:classifiers":[
        {
            "category":"Social Services",
            "type":"Services"
        }
    ],
    "sg:phone":"+1 608 782 6224",
    "sg:postcode":"54601",
    "sg:province":"WI",
    "wof:name":"Place Of Grace",
    "wof:placetype":"venue"
},
  "geometry": {"coordinates":[-91.242697,43.798521],"type":"Point"}
}