{
  "type": "Feature",
  "properties": {
    "iso:country":"US",
    "sg:address":"824 2nd St",
    "sg:city":"Stevens Point",
    "sg:classifiers":[
        {
            "category":"Health Services",
            "subcategory":"Doctor",
            "type":"Services"
        }
    ],
    "sg:phone":"+1 715 342 7775",
    "sg:postcode":"54481",
    "sg:province":"WI",
    "sg:tags":[
        "medical"
    ],
    "wof:name":"Karl E Shewmake MD",
    "wof:placetype":"venue"
},
  "geometry": {"coordinates":[-89.585826,44.527746],"type":"Point"}
}