{
  "type": "Feature",
  "properties": {
    "addr:full":"4924 W North Ave Milwaukee WI 53208",
    "addr:housenumber":"4924",
    "addr:postcode":"53208",
    "addr:street":"W North Ave",
    "iso:country":"US",
    "sg:address":"4924 W North Ave",
    "sg:city":"Milwaukee",
    "sg:classifiers":[
        {
            "category":"Personal",
            "subcategory":"Beauty Salon",
            "type":"Services"
        }
    ],
    "sg:phone":"+1 414 342 8520",
    "sg:postcode":"53208",
    "sg:province":"WI",
    "sg:tags":[
        "manicuring"
    ],
    "wof:name":"Sky Nails",
    "wof:placetype":"venue"
},
  "geometry": {"coordinates":[-87.975786,43.060724],"type":"Point"}
}