{
  "type": "Feature",
  "properties": {
    "iso:country":"US",
    "sg:address":"11955 182nd Ave",
    "sg:city":"Bristol",
    "sg:classifiers":[
        {
            "category":"Manufacturing",
            "subcategory":"Building Materials",
            "type":"Manufacturing & Wholesale Goods"
        }
    ],
    "sg:phone":"+1 262 857 4244",
    "sg:postcode":"53104",
    "sg:province":"WI",
    "sg:tags":[
        "mfg"
    ],
    "wof:name":"Swan Woodworks LLC",
    "wof:placetype":"venue"
},
  "geometry": {"coordinates":[-88.02782500000001,42.505552],"type":"Point"}
}