{
  "type": "Feature",
  "properties": {
    "iso:country":"US",
    "sg:address":"5235 Bluff Ct",
    "sg:city":"Sturgeon Bay",
    "sg:classifiers":[
        {
            "category":"Building & Trades",
            "subcategory":"Construction",
            "type":"Services"
        }
    ],
    "sg:phone":"+1 920 743 3618",
    "sg:postcode":"54235",
    "sg:province":"WI",
    "sg:tags":[
        "cherry",
        "well",
        "drilling",
        "orchard"
    ],
    "wof:name":"Jorns Harvey & David Well Drlg",
    "wof:placetype":"venue"
},
  "geometry": {"coordinates":[-87.394047,44.923199],"type":"Point"}
}