{
  "type": "Feature",
  "properties": {
    "iso:country":"US",
    "sg:address":"702 S 1st Ave",
    "sg:city":"Wausau",
    "sg:classifiers":[
        {
            "category":"Professional",
            "subcategory":"Advertising",
            "type":"Services"
        }
    ],
    "sg:phone":"+1 715 845 8815",
    "sg:postcode":"54401",
    "sg:province":"WI",
    "sg:tags":[
        "counselor",
        "agency"
    ],
    "wof:name":"Van De Yacht & Associates",
    "wof:placetype":"venue"
},
  "geometry": {"coordinates":[-89.63823600000001,44.953824],"type":"Point"}
}