{
  "type": "Feature",
  "properties": {
    "iso:country":"US",
    "sg:address":"1510 Division St",
    "sg:city":"Manitowoc",
    "sg:classifiers":[
        {
            "category":"Food & Beverages",
            "subcategory":"Candy",
            "type":"Retail Goods"
        }
    ],
    "sg:phone":"+1 920 684 3731",
    "sg:postcode":"54220",
    "sg:province":"WI",
    "sg:tags":[
        "confectionery"
    ],
    "wof:name":"Candy Division",
    "wof:placetype":"venue"
},
  "geometry": {"coordinates":[-87.668933,44.081063],"type":"Point"}
}