{
  "type": "Feature",
  "properties": {
    "addr:full":"2325 Bluemound Rd Waukesha WI 53186",
    "addr:housenumber":"2325",
    "addr:postcode":"53186",
    "addr:street":"Bluemound Rd",
    "iso:country":"US",
    "sg:address":"2325 Bluemound Rd",
    "sg:city":"Waukesha",
    "sg:classifiers":[
        {
            "category":"Wholesale",
            "subcategory":"Home Furnishings",
            "type":"Manufacturing & Wholesale Goods"
        }
    ],
    "sg:phone":"+1 262 754 8867",
    "sg:postcode":"53186",
    "sg:province":"WI",
    "sg:tags":[
        "closet",
        "accessory"
    ],
    "wof:name":"Garage Tek",
    "wof:placetype":"venue"
},
  "geometry": {"coordinates":[-88.181517,43.036227],"type":"Point"}
}