{
  "type": "Feature",
  "properties": {
    "iso:country":"US",
    "sg:address":"1902 Tennyson Ln",
    "sg:city":"Madison",
    "sg:classifiers":[
        {
            "category":"Professional",
            "subcategory":"Research",
            "type":"Services"
        }
    ],
    "sg:phone":"+1 608 241 7558",
    "sg:postcode":"53704",
    "sg:province":"WI",
    "sg:tags":[
        "product",
        "for",
        "developing",
        "science",
        "health",
        "marketing"
    ],
    "wof:name":"Fugent LLC",
    "wof:placetype":"venue"
},
  "geometry": {"coordinates":[-89.356736,43.134787],"type":"Point"}
}