{
  "type": "Feature",
  "properties": {
    "iso:country":"US",
    "sg:address":"4192 Bedford Rd",
    "sg:city":"Sparta",
    "sg:classifiers":[
        {
            "category":"Professional",
            "subcategory":"Management & Consulting",
            "type":"Services"
        }
    ],
    "sg:phone":"+1 608 272 3231",
    "sg:postcode":"54656",
    "sg:province":"WI",
    "sg:tags":[
        "business"
    ],
    "wof:name":"Deer Path Farm Guest House",
    "wof:placetype":"venue"
},
  "geometry": {"coordinates":[-90.830736,44.121378],"type":"Point"}
}