{
  "type": "Feature",
  "properties": {
    "iso:country":"US",
    "sg:address":"4982 State Hwy 52",
    "sg:city":"Bryant",
    "sg:classifiers":[
        {
            "category":"Bars & Pubs",
            "type":"Food & Drink"
        }
    ],
    "sg:phone":"+1 715 627 4414",
    "sg:postcode":"54418",
    "sg:province":"WI",
    "wof:name":"Check Point Bar",
    "wof:placetype":"venue"
},
  "geometry": {"coordinates":[-89.02459500000001,45.207769],"type":"Point"}
}