{
  "type": "Feature",
  "properties": {
    "iso:country":"US",
    "sg:address":"3379 N 26th St",
    "sg:city":"Milwaukee",
    "sg:classifiers":[
        {
            "category":"Personal",
            "subcategory":"Beauty Salon",
            "type":"Services"
        }
    ],
    "sg:phone":"+1 414 875 8834",
    "sg:postcode":"53206",
    "sg:province":"WI",
    "wof:name":"Carla's Hair Shop",
    "wof:placetype":"venue"
},
  "geometry": {"coordinates":[-87.946012,43.079533],"type":"Point"}
}