{
  "type": "Feature",
  "properties": {
    "iso:country":"US",
    "sg:address":"250 N Sunnyslope Rd",
    "sg:city":"Brookfield",
    "sg:classifiers":[
        {
            "category":"Professional",
            "subcategory":"Management & Consulting",
            "type":"Services"
        }
    ],
    "sg:phone":"+1 262 789 1816",
    "sg:postcode":"53005",
    "sg:province":"WI",
    "sg:tags":[
        "consultant"
    ],
    "wof:name":"Halvorsen & Assoc",
    "wof:placetype":"venue"
},
  "geometry": {"coordinates":[-88.086804,43.033939],"type":"Point"}
}