{
  "type": "Feature",
  "properties": {
    "iso:country":"US",
    "sg:address":"626 23rd St N",
    "sg:city":"La Crosse",
    "sg:classifiers":[
        {
            "category":"Manufacturing",
            "subcategory":"Tools & Machinery",
            "type":"Manufacturing & Wholesale Goods"
        }
    ],
    "sg:phone":"+1 608 782 6827",
    "sg:postcode":"54601",
    "sg:province":"WI",
    "sg:tags":[
        "water",
        "mfg",
        "system",
        "purification"
    ],
    "wof:name":"Puraq Water Solutions Inc",
    "wof:placetype":"venue"
},
  "geometry": {"coordinates":[-91.22206,43.818302],"type":"Point"}
}