{
  "type": "Feature",
  "properties": {
    "iso:country":"US",
    "sg:address":"6433 Nesbitt Rd",
    "sg:city":"Madison",
    "sg:classifiers":[
        {
            "category":"Building & Trades",
            "subcategory":"Landscaping Services",
            "type":"Services"
        }
    ],
    "sg:phone":"+1 608 845 3230",
    "sg:postcode":"53719",
    "sg:province":"WI",
    "sg:tags":[
        "landscape",
        "contractor"
    ],
    "wof:name":"Barnes Inc",
    "wof:placetype":"venue"
},
  "geometry": {"coordinates":[-89.494991,43.002129],"type":"Point"}
}