{
  "type": "Feature",
  "properties": {
    "iso:country":"US",
    "sg:address":"5 Ridgway St",
    "sg:city":"Elkhorn",
    "sg:classifiers":[
        {
            "category":"Organizations",
            "subcategory":"Non-profit Organization",
            "type":"Services"
        }
    ],
    "sg:phone":"+1 262 723 2908",
    "sg:postcode":"53121",
    "sg:province":"WI",
    "sg:website":"www.lakelandba.com",
    "wof:name":"Lakeland Builders Assn",
    "wof:placetype":"venue"
},
  "geometry": {"coordinates":[-88.55669399999999,42.671322],"type":"Point"}
}