{
  "type": "Feature",
  "properties": {
    "addr:full":"5171 S 108th St Hales Corners WI 53130",
    "addr:housenumber":"5171",
    "addr:postcode":"53130",
    "addr:street":"S 108Th St",
    "iso:country":"US",
    "sg:address":"5171 S 108th St",
    "sg:city":"Hales Corners",
    "sg:classifiers":[
        {
            "category":"Restaurant",
            "type":"Food & Drink"
        }
    ],
    "sg:phone":"+1 414 529 1102",
    "sg:postcode":"53130",
    "sg:province":"WI",
    "wof:name":"Charcoal Grill & Rotisserie",
    "wof:placetype":"venue"
},
  "geometry": {"coordinates":[-88.048239,42.950646],"type":"Point"}
}