{
  "type": "Feature",
  "properties": {
    "iso:country":"US",
    "sg:address":"129 E Main St",
    "sg:city":"Little Chute",
    "sg:classifiers":[
        {
            "category":"Personal",
            "subcategory":"Barber",
            "type":"Services"
        }
    ],
    "sg:phone":"+1 920 788 1151",
    "sg:postcode":"54140",
    "sg:province":"WI",
    "wof:name":"Carl's Barber Stylists",
    "wof:placetype":"venue"
},
  "geometry": {"coordinates":[-88.315166,44.279879],"type":"Point"}
}