{
  "type": "Feature",
  "properties": {
    "addr:full":"144 S Depot St Hixton WI 54635",
    "addr:housenumber":"144",
    "addr:postcode":"54635",
    "addr:street":"S Depot St",
    "iso:country":"US",
    "sg:address":"144 S Depot St",
    "sg:city":"Hixton",
    "sg:classifiers":[
        {
            "category":"Wholesale",
            "subcategory":"Farm Supplies",
            "type":"Manufacturing & Wholesale Goods"
        }
    ],
    "sg:phone":"+1 715 963 2041",
    "sg:postcode":"54635",
    "sg:province":"WI",
    "sg:tags":[
        "p",
        "station",
        "gas"
    ],
    "wof:name":"Farmers Cooperative Oil Co",
    "wof:placetype":"venue"
},
  "geometry": {"coordinates":[-91.010442,44.382214],"type":"Point"}
}