{
  "type": "Feature",
  "properties": {
    "iso:country":"US",
    "sg:address":"15 Plymouth St",
    "sg:city":"Plymouth",
    "sg:classifiers":[
        {
            "category":"Organizations",
            "subcategory":"Religious Organization",
            "type":"Services"
        }
    ],
    "sg:phone":"+1 920 892 4006",
    "sg:postcode":"53073",
    "sg:province":"WI",
    "sg:tags":[
        "church"
    ],
    "wof:name":"St John The Baptist Catholic",
    "wof:placetype":"venue"
},
  "geometry": {"coordinates":[-87.98493499999999,43.748573],"type":"Point"}
}