{
  "type": "Feature",
  "properties": {
    "iso:country":"US",
    "sg:address":"125 S Jefferson St",
    "sg:city":"Green Bay",
    "sg:classifiers":[
        {
            "category":"Professional",
            "type":"Services"
        }
    ],
    "sg:phone":"+1 920 435 8751",
    "sg:postcode":"54301",
    "sg:province":"WI",
    "wof:name":"Pje Inc",
    "wof:placetype":"venue"
},
  "geometry": {"coordinates":[-88.01393400000001,44.512344],"type":"Point"}
}