{
  "type": "Feature",
  "properties": {
    "iso:country":"US",
    "sg:address":"7727 Co Hwy P",
    "sg:city":"Browntown",
    "sg:classifiers":[
        {
            "category":"Farming",
            "subcategory":"Dairy Farm",
            "type":"Manufacturing & Wholesale Goods"
        }
    ],
    "sg:phone":"+1 608 325 2951",
    "sg:postcode":"53522",
    "sg:province":"WI",
    "wof:name":"Donald Brennan",
    "wof:placetype":"venue"
},
  "geometry": {"coordinates":[-89.749755,42.51987],"type":"Point"}
}