{
  "type": "Feature",
  "properties": {
    "addr:full":"3607 52nd St Kenosha WI 53144",
    "addr:housenumber":"3607",
    "addr:postcode":"53144",
    "addr:street":"52Nd St",
    "iso:country":"US",
    "sg:address":"3607 52nd St",
    "sg:city":"Kenosha",
    "sg:classifiers":[
        {
            "category":"Insurance",
            "subcategory":"Insurance Agent",
            "type":"Services"
        }
    ],
    "sg:phone":"+1 262 652 9039",
    "sg:postcode":"53144",
    "sg:province":"WI",
    "sg:tags":[
        "agency"
    ],
    "wof:name":"Allstate",
    "wof:placetype":"venue"
},
  "geometry": {"coordinates":[-87.853404,42.588212],"type":"Point"}
}