{
  "type": "Feature",
  "properties": {
    "addr:full":"10401 N Port Washington Rd Mequon WI 53092",
    "addr:housenumber":"10401",
    "addr:postcode":"53092",
    "addr:street":"N Port Washington Rd",
    "iso:country":"US",
    "sg:address":"10401 N Port Washington Rd",
    "sg:city":"Mequon",
    "sg:classifiers":[
        {
            "category":"Professional",
            "type":"Services"
        }
    ],
    "sg:phone":"+1 262 240 1099",
    "sg:postcode":"53092",
    "sg:province":"WI",
    "sg:tags":[
        "establishment"
    ],
    "wof:name":"Teiahc Corp",
    "wof:placetype":"venue"
},
  "geometry": {"coordinates":[-87.924176,43.21028],"type":"Point"}
}