{
  "type": "Feature",
  "properties": {
    "iso:country":"US",
    "sg:address":"3121 Nagle Ave",
    "sg:city":"Manitowoc",
    "sg:classifiers":[
        {
            "category":"Organizations",
            "subcategory":"Religious Organization",
            "type":"Services"
        }
    ],
    "sg:phone":"+1 920 682 7037",
    "sg:postcode":"54220",
    "sg:province":"WI",
    "sg:website":"www.trinityalliancemanitowoc.org",
    "wof:name":"Trinity Alliance Church",
    "wof:placetype":"venue"
},
  "geometry": {"coordinates":[-87.673743,44.135892],"type":"Point"}
}