{
  "type": "Feature",
  "properties": {
    "addr:full":"115 E Main St Omro WI 54963",
    "addr:housenumber":"115",
    "addr:postcode":"54963",
    "addr:street":"E Main St",
    "iso:country":"US",
    "sg:address":"115 E Main St",
    "sg:city":"Omro",
    "sg:classifiers":[
        {
            "category":"Retail",
            "subcategory":"Portrait Studio",
            "type":"Services"
        }
    ],
    "sg:phone":"+1 920 685 5787",
    "sg:postcode":"54963",
    "sg:province":"WI",
    "sg:tags":[
        "photo"
    ],
    "wof:name":"Omro Gallery",
    "wof:placetype":"venue"
},
  "geometry": {"coordinates":[-88.744379,44.039499],"type":"Point"}
}