{
  "type": "Feature",
  "properties": {
    "addr:full":"981 State Rd 80 and 133 Avoca WI 53506",
    "addr:housenumber":"981;80 and 133",
    "addr:postcode":"53506",
    "addr:street":"State Rd",
    "iso:country":"US",
    "sg:address":"981 State Rd 80 and 133",
    "sg:city":"Avoca",
    "sg:phone":"+1 608 532 6376",
    "sg:postcode":"53506",
    "sg:province":"WI",
    "sg:tags":[
        "farm",
        "corn",
        "soybean"
    ],
    "wof:name":"Bomkamp Farms LLC",
    "wof:placetype":"venue"
},
  "geometry": {"coordinates":[-90.38024299999999,43.183343],"type":"Point"}
}