{
  "type": "Feature",
  "properties": {
    "iso:country":"US",
    "sg:address":"12605 W North Ave",
    "sg:city":"Brookfield",
    "sg:classifiers":[
        {
            "category":"Building & Trades",
            "subcategory":"Landscaping Services",
            "type":"Services"
        }
    ],
    "sg:phone":"+1 414 873 9956",
    "sg:postcode":"53005",
    "sg:province":"WI",
    "sg:tags":[
        "lawn",
        "maintenance",
        "grounds"
    ],
    "wof:name":"Clean-Cut Maintenance & Lawn",
    "wof:placetype":"venue"
},
  "geometry": {"coordinates":[-88.069126,43.059835],"type":"Point"}
}