{
  "type": "Feature",
  "properties": {
    "iso:country":"US",
    "sg:address":"1609 Lake Kegonsa Rd",
    "sg:city":"Stoughton",
    "sg:classifiers":[
        {
            "category":"Retail",
            "subcategory":"Repair Shop",
            "type":"Services"
        }
    ],
    "sg:phone":"+1 608 873 7236",
    "sg:postcode":"53589",
    "sg:province":"WI",
    "wof:name":"Onsrud Upholstery Company",
    "wof:placetype":"venue"
},
  "geometry": {"coordinates":[-89.279797,42.941562],"type":"Point"}
}