{
  "type": "Feature",
  "properties": {
    "addr:full":"1000 Ashwaubenon St Green Bay WI 54304",
    "addr:housenumber":"1000",
    "addr:postcode":"54304",
    "addr:street":"Ashwaubenon St",
    "iso:country":"US",
    "sg:address":"1000 Ashwaubenon St",
    "sg:city":"Green Bay",
    "sg:classifiers":[
        {
            "category":"Manufacturing",
            "subcategory":"Motor Vehicles & Parts",
            "type":"Manufacturing & Wholesale Goods"
        }
    ],
    "sg:phone":"+1 920 339 3000",
    "sg:postcode":"54304",
    "sg:province":"WI",
    "sg:tags":[
        "automobile",
        "supply"
    ],
    "sg:website":"www.machineservice.com",
    "wof:name":"Machine Service Inc",
    "wof:placetype":"venue"
},
  "geometry": {"coordinates":[-88.089564,44.464051],"type":"Point"}
}