{
  "type": "Feature",
  "properties": {
    "addr:full":"2083 Blackhawk Island Rd Fort Atkinson WI 53538",
    "addr:housenumber":"2083",
    "addr:postcode":"53538",
    "addr:street":"Blackhawk Island Rd",
    "iso:country":"US",
    "sg:address":"2083 Blackhawk Island Rd",
    "sg:city":"Fort Atkinson",
    "sg:classifiers":[
        {
            "category":"Building & Trades",
            "subcategory":"Plumbing",
            "type":"Services"
        }
    ],
    "sg:phone":"+1 920 563 7517",
    "sg:postcode":"53538",
    "sg:province":"WI",
    "sg:tags":[
        "plumbing",
        "contractor"
    ],
    "wof:name":"Hachtel Plumbing",
    "wof:placetype":"venue"
},
  "geometry": {"coordinates":[-88.873425,42.91672],"type":"Point"}
}