{
  "type": "Feature",
  "properties": {
    "iso:country":"US",
    "sg:address":"5155 Granville Ct",
    "sg:city":"Elkhorn",
    "sg:classifiers":[
        {
            "category":"Professional",
            "subcategory":"Business Services",
            "type":"Services"
        }
    ],
    "sg:phone":"+1 262 723 4778",
    "sg:postcode":"53121",
    "sg:province":"WI",
    "wof:name":"Nikcor Enterprises LLC",
    "wof:placetype":"venue"
},
  "geometry": {"coordinates":[-88.586789,42.679264],"type":"Point"}
}