{
  "type": "Feature",
  "properties": {
    "iso:country":"US",
    "sg:address":"8535 48th Ave",
    "sg:city":"Kenosha",
    "sg:classifiers":[
        {
            "category":"Autos & Motor Vehicles",
            "subcategory":"Auto Supplies",
            "type":"Retail Goods"
        }
    ],
    "sg:phone":"+1 262 697 9931",
    "sg:postcode":"53142",
    "sg:province":"IL",
    "wof:name":"Stein Gerald K Authorized",
    "wof:placetype":"venue"
},
  "geometry": {"coordinates":[-87.866056,42.550333],"type":"Point"}
}