{
  "type": "Feature",
  "properties": {
    "iso:country":"US",
    "sg:address":"444 Scott St",
    "sg:city":"Green Lake",
    "sg:classifiers":[
        {
            "category":"Social Services",
            "subcategory":"Child Care",
            "type":"Services"
        }
    ],
    "sg:phone":"+1 920 294 6099",
    "sg:postcode":"54941",
    "sg:province":"WI",
    "wof:name":"Community Options Inc",
    "wof:placetype":"venue"
},
  "geometry": {"coordinates":[-88.96409800000001,43.849924],"type":"Point"}
}