{
  "type": "Feature",
  "properties": {
    "iso:country":"US",
    "sg:address":"5721 N 94th St",
    "sg:city":"Milwaukee",
    "sg:classifiers":[
        {
            "category":"Professional",
            "type":"Services"
        }
    ],
    "sg:phone":"+1 414 536 1592",
    "sg:postcode":"53225",
    "sg:province":"WI",
    "wof:name":"WI State Choir",
    "wof:placetype":"venue"
},
  "geometry": {"coordinates":[-88.029546,43.122783],"type":"Point"}
}