{
  "type": "Feature",
  "properties": {
    "addr:full":"418 State Road 50 Delavan WI 53115",
    "addr:housenumber":"418",
    "addr:postcode":"53115",
    "addr:street":"State Road 50",
    "iso:country":"US",
    "sg:address":"418 State Road 50",
    "sg:city":"Delavan",
    "sg:classifiers":[
        {
            "category":"Real Estate",
            "subcategory":"Real Estate Services",
            "type":"Services"
        },
        {
            "category":"Real Estate",
            "subcategory":"Real Estate Agent",
            "type":"Services"
        }
    ],
    "sg:phone":"+1 262 725 6368",
    "sg:postcode":"53115",
    "sg:province":"WI",
    "sg:tags":[
        "buyer",
        "broker"
    ],
    "wof:name":"Town & Lakes Real Estate",
    "wof:placetype":"venue"
},
  "geometry": {"coordinates":[-88.58737499999999,42.62539],"type":"Point"}
}