{
  "type": "Feature",
  "properties": {
    "iso:country":"US",
    "sg:address":"5640 Parking St",
    "sg:city":"Greendale",
    "sg:classifiers":[
        {
            "category":"Shopping",
            "subcategory":"Gifts & Souvenirs",
            "type":"Retail Goods"
        }
    ],
    "sg:phone":"+1 414 421 3370",
    "sg:postcode":"53129",
    "sg:province":"WI",
    "sg:tags":[
        "shop"
    ],
    "wof:name":"Shoppe Around The Corner",
    "wof:placetype":"venue"
},
  "geometry": {"coordinates":[-87.996805,42.941751],"type":"Point"}
}