{
  "type": "Feature",
  "properties": {
    "iso:country":"US",
    "sg:address":"680 S Whitney Way",
    "sg:city":"Madison",
    "sg:classifiers":[
        {
            "category":"Shopping",
            "subcategory":"Bicycles & Sporting Goods",
            "type":"Retail Goods"
        }
    ],
    "sg:phone":"+1 608 278 9000",
    "sg:postcode":"53711",
    "sg:province":"WI",
    "sg:tags":[
        "repair"
    ],
    "sg:website":"www.eriksbikeshop.com",
    "wof:name":"Erik's Bike Shop",
    "wof:placetype":"venue"
},
  "geometry": {"coordinates":[-89.473583,43.053377],"type":"Point"}
}