{
  "type": "Feature",
  "properties": {
    "iso:country":"US",
    "sg:address":"205 S University Ave",
    "sg:city":"Beaver Dam",
    "sg:classifiers":[
        {
            "category":"Health Services",
            "subcategory":"Doctor",
            "type":"Services"
        }
    ],
    "sg:phone":"+1 920 887 1292",
    "sg:postcode":"53916",
    "sg:province":"WI",
    "sg:tags":[
        "dentist"
    ],
    "wof:name":"D H Sommer DDS",
    "wof:placetype":"venue"
},
  "geometry": {"coordinates":[-88.828817,43.455191],"type":"Point"}
}