{
  "type": "Feature",
  "properties": {
    "iso:country":"US",
    "sg:address":"8619 Frontage Rd",
    "sg:city":"Caledonia",
    "sg:classifiers":[
        {
            "category":"Bars & Pubs",
            "type":"Food & Drink"
        }
    ],
    "sg:phone":"+1 262 835 2917",
    "sg:postcode":"53108",
    "sg:province":"WI",
    "wof:name":"Dead End Saloon",
    "wof:placetype":"venue"
},
  "geometry": {"coordinates":[-87.95203100000001,42.839035],"type":"Point"}
}