{
  "type": "Feature",
  "properties": {
    "addr:full":"512 Redbird Cir De Pere WI 54115",
    "addr:housenumber":"512",
    "addr:postcode":"54115",
    "addr:street":"Redbird Cir",
    "iso:country":"US",
    "sg:address":"512 Redbird Cir",
    "sg:city":"De Pere",
    "sg:classifiers":[
        {
            "category":"Insurance",
            "subcategory":"Insurance Agent",
            "type":"Services"
        }
    ],
    "sg:phone":"+1 920 337 9229",
    "sg:postcode":"54115",
    "sg:province":"WI",
    "wof:name":"State Farm Insurance",
    "wof:placetype":"venue"
},
  "geometry": {"coordinates":[-88.037649,44.439476],"type":"Point"}
}