{
  "type": "Feature",
  "properties": {
    "iso:country":"US",
    "sg:address":"3938 Co Rd F",
    "sg:city":"Brodhead",
    "sg:classifiers":[
        {
            "category":"Building & Trades",
            "subcategory":"Construction",
            "type":"Services"
        }
    ],
    "sg:phone":"+1 608 897 2300",
    "sg:postcode":"53520",
    "sg:province":"WI",
    "sg:tags":[
        "residential",
        "commercial",
        "contract",
        "general"
    ],
    "wof:name":"Goodman Construction",
    "wof:placetype":"venue"
},
  "geometry": {"coordinates":[-89.446534,42.661706],"type":"Point"}
}