{
  "type": "Feature",
  "properties": {
    "addr:full":"711 W Adams St Black River Fls WI 54615",
    "addr:housenumber":"711",
    "addr:postcode":"54615",
    "addr:street":"W Adams St",
    "iso:country":"US",
    "sg:address":"711 W Adams St",
    "sg:city":"Black River Fls",
    "sg:classifiers":[
        {
            "category":"Health Services",
            "subcategory":"Hospital",
            "type":"Services"
        }
    ],
    "sg:phone":"+1 715 284 5361",
    "sg:postcode":"54615",
    "sg:province":"WI",
    "sg:website":"www.blackriverhospital.com",
    "wof:name":"Black River Memorial Hospital",
    "wof:placetype":"venue"
},
  "geometry": {"coordinates":[-90.855936,44.302405],"type":"Point"}
}