{
  "type": "Feature",
  "properties": {
    "addr:full":"5475 N Hopkins St Milwaukee WI 53209",
    "addr:housenumber":"5475",
    "addr:postcode":"53209",
    "addr:street":"N Hopkins St",
    "iso:country":"US",
    "sg:address":"5475 N Hopkins St",
    "sg:city":"Milwaukee",
    "sg:classifiers":[
        {
            "category":"Building & Trades",
            "subcategory":"Construction",
            "type":"Services"
        }
    ],
    "sg:phone":"+1 414 466 9030",
    "sg:postcode":"53209",
    "sg:province":"WI",
    "sg:tags":[
        "concrete",
        "contractor"
    ],
    "wof:name":"Brobac Development Corp",
    "wof:placetype":"venue"
},
  "geometry": {"coordinates":[-87.965155,43.116044],"type":"Point"}
}