{
  "type": "Feature",
  "properties": {
    "iso:country":"US",
    "sg:address":"419 N Center St",
    "sg:city":"Beaver Dam",
    "sg:classifiers":[
        {
            "category":"Manufacturing",
            "subcategory":"Food",
            "type":"Manufacturing & Wholesale Goods"
        }
    ],
    "sg:phone":"+1 920 885 4411",
    "sg:postcode":"53916",
    "sg:province":"WI",
    "sg:tags":[
        "cheese",
        "mfg"
    ],
    "wof:name":"Kraft Foods",
    "wof:placetype":"venue"
},
  "geometry": {"coordinates":[-88.839406,43.460409],"type":"Point"}
}