{
  "type": "Feature",
  "properties": {
    "addr:full":"1819 N 12th St Milwaukee WI 53205",
    "addr:housenumber":"1819",
    "addr:postcode":"53205",
    "addr:street":"N 12Th St",
    "iso:country":"US",
    "sg:address":"1819 N 12th St",
    "sg:city":"Milwaukee",
    "sg:phone":"+1 414 264 8553",
    "sg:postcode":"53205",
    "sg:province":"WI",
    "wof:name":"12th Street Liquor Store",
    "wof:placetype":"venue"
},
  "geometry": {"coordinates":[-87.927008,43.054113],"type":"Point"}
}