{
  "type": "Feature",
  "properties": {
    "iso:country":"US",
    "sg:address":"12261 Anderson Ln",
    "sg:city":"Bagley",
    "sg:phone":"+1 608 996 2664",
    "sg:postcode":"53801",
    "sg:province":"WI",
    "sg:tags":[
        "farm",
        "corn"
    ],
    "wof:name":"Larry Reynolds",
    "wof:placetype":"venue"
},
  "geometry": {"coordinates":[-91.056757,42.94658],"type":"Point"}
}