{
  "type": "Feature",
  "properties": {
    "iso:country":"US",
    "sg:address":"14029 W Greenfield Ave",
    "sg:city":"New Berlin",
    "sg:classifiers":[
        {
            "category":"Shopping",
            "subcategory":"Stationery & Office Supplies",
            "type":"Retail Goods"
        }
    ],
    "sg:phone":"+1 262 754 8839",
    "sg:postcode":"53151",
    "sg:province":"WI",
    "sg:tags":[
        "album",
        "scrapbook"
    ],
    "sg:website":"www.scrapnnook.com",
    "wof:name":"Scrap'n Nook",
    "wof:placetype":"venue"
},
  "geometry": {"coordinates":[-88.088423,43.016445],"type":"Point"}
}