{
  "type": "Feature",
  "properties": {
    "iso:country":"US",
    "sg:address":"1100 W Anderson Rd",
    "sg:city":"Oak Creek",
    "sg:classifiers":[
        {
            "category":"Building & Trades",
            "subcategory":"Plumbing",
            "type":"Services"
        }
    ],
    "sg:phone":"+1 414 216 6900",
    "sg:postcode":"53154",
    "sg:province":"WI",
    "sg:tags":[
        "mechanical",
        "contractor"
    ],
    "sg:website":"www.grunau.com",
    "wof:name":"Grunau Company Inc",
    "wof:placetype":"venue"
},
  "geometry": {"coordinates":[-87.928921,42.922953],"type":"Point"}
}