{
  "type": "Feature",
  "properties": {
    "iso:country":"US",
    "sg:address":"825 Urbandale Ave",
    "sg:city":"De Pere",
    "sg:classifiers":[
        {
            "category":"Manufacturing",
            "subcategory":"Printing",
            "type":"Manufacturing & Wholesale Goods"
        }
    ],
    "sg:phone":"+1 920 336 6123",
    "sg:postcode":"54115",
    "sg:province":"WI",
    "sg:tags":[
        "publisher"
    ],
    "wof:name":"Bon Vivant Group",
    "wof:placetype":"venue"
},
  "geometry": {"coordinates":[-88.049582,44.454823],"type":"Point"}
}