{
  "type": "Feature",
  "properties": {
    "addr:full":"700 S River St Spooner WI 54801",
    "addr:housenumber":"700",
    "addr:postcode":"54801",
    "addr:street":"S River St",
    "iso:country":"US",
    "sg:address":"700 S River St",
    "sg:city":"Spooner",
    "sg:classifiers":[
        {
            "category":"Banks & Credit Unions",
            "subcategory":"Bank",
            "type":"Services"
        }
    ],
    "sg:phone":"+1 715 635 3837",
    "sg:postcode":"54801",
    "sg:province":"WI",
    "wof:name":"Bank Of The West",
    "wof:placetype":"venue"
},
  "geometry": {"coordinates":[-91.89496200000001,45.817696],"type":"Point"}
}