{
  "type": "Feature",
  "properties": {
    "addr:full":"3011 Co Rd Bb Appleton WI 54914",
    "addr:housenumber":"3011",
    "addr:postcode":"54914",
    "addr:street":"Co Rd",
    "iso:country":"US",
    "sg:address":"3011 Co Rd Bb",
    "sg:city":"Appleton",
    "sg:classifiers":[
        {
            "category":"Utilities",
            "subcategory":"Fuel Oil & Lpg",
            "type":"Services"
        }
    ],
    "sg:phone":"+1 920 730 9393",
    "sg:postcode":"54914",
    "sg:province":"WI",
    "sg:tags":[
        "liquefied",
        "gas",
        "petroleum"
    ],
    "wof:name":"Ferrellgas 4741-5",
    "wof:placetype":"venue"
},
  "geometry": {"coordinates":[-88.5538,44.243646],"type":"Point"}
}