{
  "type": "Feature",
  "properties": {
    "iso:country":"US",
    "sg:address":"4130 N 24th Pl",
    "sg:city":"Milwaukee",
    "sg:classifiers":[
        {
            "category":"Health Services",
            "subcategory":"Nursing And Care Facility",
            "type":"Services"
        },
        {
            "category":"Social Services",
            "subcategory":"Retirement Home",
            "type":"Services"
        },
        {
            "category":"Social Services",
            "subcategory":"Adult Care",
            "type":"Services"
        }
    ],
    "sg:phone":"+1 414 449 8940",
    "sg:postcode":"53209",
    "sg:province":"WI",
    "sg:tags":[
        "living",
        "people",
        "assisted",
        "elder",
        "convalescent",
        "homes-elderly"
    ],
    "wof:name":"Live With Hope Inc",
    "wof:placetype":"venue"
},
  "geometry": {"coordinates":[-87.943449,43.091733],"type":"Point"}
}