{
  "type": "Feature",
  "properties": {
    "iso:country":"US",
    "sg:address":"620 N Lynndale Dr",
    "sg:city":"Appleton",
    "sg:classifiers":[
        {
            "category":"Wholesale",
            "subcategory":"Office Equipment",
            "type":"Manufacturing & Wholesale Goods"
        }
    ],
    "sg:phone":"+1 920 499 9600",
    "sg:postcode":"54914",
    "sg:province":"WI",
    "sg:tags":[
        "machine",
        "duplicating",
        "copying"
    ],
    "sg:website":"www.mbm-idt.com",
    "wof:name":"Modern Business Machines",
    "wof:placetype":"venue"
},
  "geometry": {"coordinates":[-88.44582,44.262443],"type":"Point"}
}