{
  "type": "Feature",
  "properties": {
    "iso:country":"US",
    "sg:address":"1503 1st Center Ave",
    "sg:city":"Brodhead",
    "sg:classifiers":[
        {
            "category":"Food & Beverages",
            "subcategory":"Liquor & Beverages",
            "type":"Retail Goods"
        }
    ],
    "sg:phone":"+1 608 897 4633",
    "sg:postcode":"53520",
    "sg:province":"WI",
    "sg:tags":[
        "store"
    ],
    "wof:name":"Southside Beverage",
    "wof:placetype":"venue"
},
  "geometry": {"coordinates":[-89.376862,42.615377],"type":"Point"}
}