{
  "type": "Feature",
  "properties": {
    "iso:country":"US",
    "sg:address":"244 N Main St",
    "sg:city":"Fort Atkinson",
    "sg:classifiers":[
        {
            "category":"Organizations",
            "subcategory":"Professional Association",
            "type":"Services"
        }
    ],
    "sg:phone":"+1 920 563 3210",
    "sg:postcode":"53538",
    "sg:province":"WI",
    "sg:tags":[
        "business"
    ],
    "wof:name":"Fort Atknsn Area Chmbr of Cmmr",
    "wof:placetype":"venue"
},
  "geometry": {"coordinates":[-88.837026,42.92989],"type":"Point"}
}