{
  "type": "Feature",
  "properties": {
    "iso:country":"US",
    "sg:address":"875 US Hwy 12",
    "sg:city":"Baraboo",
    "sg:classifiers":[
        {
            "category":"Home & Garden",
            "subcategory":"Mobile Homes",
            "type":"Retail Goods"
        }
    ],
    "sg:phone":"+1 608 356 3618",
    "sg:postcode":"53913",
    "sg:province":"WI",
    "wof:name":"Blackhawk Mobile Homes Sales",
    "wof:placetype":"venue"
},
  "geometry": {"coordinates":[-89.770533,43.481295],"type":"Point"}
}