{
  "type": "Feature",
  "properties": {
    "iso:country":"US",
    "sg:address":"3037 S 41st St",
    "sg:city":"Milwaukee",
    "sg:classifiers":[
        {
            "category":"Organizations",
            "subcategory":"Non-profit Organization",
            "type":"Services"
        }
    ],
    "sg:phone":"+1 414 384 0431",
    "sg:postcode":"53215",
    "sg:province":"WI",
    "sg:tags":[
        "information",
        "alcoholism",
        "treatment"
    ],
    "wof:name":"Manitoba House",
    "wof:placetype":"venue"
},
  "geometry": {"coordinates":[-87.965489,42.988684],"type":"Point"}
}