{
  "type": "Feature",
  "properties": {
    "iso:country":"US",
    "sg:address":"9733 W Greenfield Ave",
    "sg:city":"Milwaukee",
    "sg:classifiers":[
        {
            "category":"Insurance",
            "subcategory":"Insurance Agent",
            "type":"Services"
        }
    ],
    "sg:phone":"+1 414 431 2814",
    "sg:postcode":"53214",
    "sg:province":"WI",
    "wof:name":"Fish & Schulkamp",
    "wof:placetype":"venue"
},
  "geometry": {"coordinates":[-88.03383599999999,43.016392],"type":"Point"}
}