{
  "type": "Feature",
  "properties": {
    "iso:country":"US",
    "sg:address":"301 S Prairie Ave",
    "sg:city":"Waukesha",
    "sg:classifiers":[
        {
            "category":"Government",
            "subcategory":"Office",
            "type":"Public Place"
        }
    ],
    "sg:phone":"+1 262 524 3725",
    "sg:postcode":"53186",
    "sg:province":"WI",
    "sg:tags":[
        "village"
    ],
    "wof:name":"Saratoga Softball Complex",
    "wof:placetype":"venue"
},
  "geometry": {"coordinates":[-88.24363099999999,43.002533],"type":"Point"}
}