{
  "type": "Feature",
  "properties": {
    "iso:country":"US",
    "sg:address":"6054 410th Ave",
    "sg:city":"Ellsworth",
    "sg:classifiers":[
        {
            "category":"Farming",
            "subcategory":"Dairy Farm",
            "type":"Manufacturing & Wholesale Goods"
        }
    ],
    "sg:phone":"+1 715 273 6111",
    "sg:postcode":"54011",
    "sg:province":"WI",
    "wof:name":"Grams Dairy Farm",
    "wof:placetype":"venue"
},
  "geometry": {"coordinates":[-92.436085,44.688792],"type":"Point"}
}