{
  "type": "Feature",
  "properties": {
    "addr:full":"5530 Park Ave Merrill WI 54452",
    "addr:housenumber":"5530",
    "addr:postcode":"54452",
    "addr:street":"Park Ave",
    "iso:country":"US",
    "sg:address":"5530 Park Ave",
    "sg:city":"Merrill",
    "sg:classifiers":[
        {
            "category":"Freight",
            "type":"Transportation"
        }
    ],
    "sg:phone":"+1 715 536 3041",
    "sg:postcode":"54452",
    "sg:province":"WI",
    "sg:tags":[
        "commercial",
        "storage",
        "general"
    ],
    "wof:name":"Park-N-Store Self Storage",
    "wof:placetype":"venue"
},
  "geometry": {"coordinates":[-89.69421199999999,45.145223],"type":"Point"}
}