{
  "type": "Feature",
  "properties": {
    "iso:country":"US",
    "sg:address":"1407 S 1st St",
    "sg:city":"Milwaukee",
    "sg:classifiers":[
        {
            "category":"Professional",
            "subcategory":"Computer Services",
            "type":"Services"
        }
    ],
    "sg:phone":"+1 414 643 5623",
    "sg:postcode":"53204",
    "sg:province":"WI",
    "sg:tags":[
        "design",
        "system"
    ],
    "wof:name":"A Webtech Master",
    "wof:placetype":"venue"
},
  "geometry": {"coordinates":[-87.91127,43.016105],"type":"Point"}
}