{
  "type": "Feature",
  "properties": {
    "iso:country":"US",
    "sg:address":"2152 US Hwy 63",
    "sg:city":"Deer Park",
    "sg:classifiers":[
        {
            "category":"Professional",
            "subcategory":"Accounting & Tax Preparation",
            "type":"Services"
        }
    ],
    "sg:phone":"+1 715 263 2435",
    "sg:postcode":"54007",
    "sg:province":"WI",
    "sg:tags":[
        "return"
    ],
    "wof:name":"Schones Tax Service LLC",
    "wof:placetype":"venue"
},
  "geometry": {"coordinates":[-92.283716,45.172883],"type":"Point"}
}