{
  "type": "Feature",
  "properties": {
    "addr:full":"17511 Ideal Rd Sparta WI 54656",
    "addr:housenumber":"17511",
    "addr:postcode":"54656",
    "addr:street":"Ideal Rd",
    "iso:country":"US",
    "sg:address":"17511 Ideal Rd",
    "sg:city":"Sparta",
    "sg:phone":"+1 608 269 5584",
    "sg:postcode":"54656",
    "sg:province":"WI",
    "sg:tags":[
        "building",
        "industrial",
        "farm",
        "cash",
        "construction",
        "grain"
    ],
    "wof:name":"Larry L Revels",
    "wof:placetype":"venue"
},
  "geometry": {"coordinates":[-90.810334,43.920526],"type":"Point"}
}