{
  "type": "Feature",
  "properties": {
    "iso:country":"US",
    "sg:address":"4749 N 22nd St",
    "sg:city":"Milwaukee",
    "sg:classifiers":[
        {
            "category":"Professional",
            "type":"Services"
        }
    ],
    "sg:phone":"+1 414 449 2241",
    "sg:postcode":"53209",
    "sg:province":"WI",
    "wof:name":"Andre J Smith",
    "wof:placetype":"venue"
},
  "geometry": {"coordinates":[-87.939412,43.103434],"type":"Point"}
}