{
  "type": "Feature",
  "properties": {
    "iso:country":"US",
    "sg:address":"8259 Prahl Rd",
    "sg:city":"New London",
    "sg:classifiers":[
        {
            "category":"Building & Trades",
            "subcategory":"Landscaping Services",
            "type":"Services"
        }
    ],
    "sg:phone":"+1 920 982 3658",
    "sg:postcode":"54961",
    "sg:province":"WI",
    "wof:name":"Griffin Landscaping",
    "wof:placetype":"venue"
},
  "geometry": {"coordinates":[-88.809946,44.416714],"type":"Point"}
}