{
  "type": "Feature",
  "properties": {
    "iso:country":"US",
    "sg:address":"1446 Jenifer St",
    "sg:city":"Madison",
    "sg:classifiers":[
        {
            "category":"Building & Trades",
            "subcategory":"Landscaping Services",
            "type":"Services"
        }
    ],
    "sg:phone":"+1 608 280 9699",
    "sg:postcode":"53703",
    "sg:province":"WI",
    "sg:tags":[
        "designer",
        "landscape"
    ],
    "wof:name":"Fertile Earth",
    "wof:placetype":"venue"
},
  "geometry": {"coordinates":[-89.358919,43.085821],"type":"Point"}
}