{
  "type": "Feature",
  "properties": {
    "iso:country":"US",
    "sg:address":"5317 Old Middleton Rd",
    "sg:city":"Madison",
    "sg:classifiers":[
        {
            "category":"Professional",
            "subcategory":"Computer Services",
            "type":"Services"
        }
    ],
    "sg:phone":"+1 608 238 7311",
    "sg:postcode":"53705",
    "sg:province":"WI",
    "sg:tags":[
        "processing",
        "datum"
    ],
    "wof:name":"Comdata Corp",
    "wof:placetype":"venue"
},
  "geometry": {"coordinates":[-89.47202799999999,43.074124],"type":"Point"}
}