{
  "type": "Feature",
  "properties": {
    "addr:full":"625 N Broadway St Milwaukee WI 53202",
    "addr:housenumber":"625",
    "addr:postcode":"53202",
    "addr:street":"N Broadway St",
    "iso:country":"US",
    "sg:address":"625 N Broadway St",
    "sg:city":"Milwaukee",
    "sg:classifiers":[
        {
            "category":"Professional",
            "subcategory":"Management & Consulting",
            "type":"Services"
        },
        {
            "category":"Professional",
            "subcategory":"Employment Agencies",
            "type":"Services"
        }
    ],
    "sg:phone":"+1 414 283 9533",
    "sg:postcode":"53202",
    "sg:province":"WI",
    "sg:tags":[
        "opportunity"
    ],
    "wof:name":"Spano Pratt",
    "wof:placetype":"venue"
},
  "geometry": {"coordinates":[-87.907867,43.038345],"type":"Point"}
}