{
  "type": "Feature",
  "properties": {
    "iso:country":"US",
    "sg:address":"615 State Hwy 136",
    "sg:city":"Baraboo",
    "sg:classifiers":[
        {
            "category":"Utilities",
            "subcategory":"Mobile Phone",
            "type":"Services"
        }
    ],
    "sg:phone":"+1 608 355 9624",
    "sg:postcode":"53913",
    "sg:province":"WI",
    "sg:tags":[
        "telephone",
        "cellular"
    ],
    "wof:name":"Us Cellular Inc",
    "wof:placetype":"venue"
},
  "geometry": {"coordinates":[-89.774899,43.474699],"type":"Point"}
}