{
  "type": "Feature",
  "properties": {
    "iso:country":"US",
    "sg:address":"300 W 2nd St",
    "sg:city":"Reedsburg",
    "sg:classifiers":[
        {
            "category":"Recreation",
            "type":"Entertainment"
        }
    ],
    "sg:phone":"+1 608 524 9781",
    "sg:postcode":"53959",
    "sg:province":"WI",
    "sg:tags":[
        "parks"
    ],
    "wof:name":"Annna Stone Park",
    "wof:placetype":"venue"
},
  "geometry": {"coordinates":[-90.018576,43.533407],"type":"Point"}
}