{
  "type": "Feature",
  "properties": {
    "addr:full":"7426 Co Rd G Somers WI 53126",
    "addr:housenumber":"7426",
    "addr:postcode":"53126",
    "addr:street":"Co Rd",
    "iso:country":"US",
    "sg:address":"7426 Co Rd G",
    "sg:city":"Somers",
    "sg:classifiers":[
        {
            "category":"Building & Trades",
            "subcategory":"Construction",
            "type":"Services"
        }
    ],
    "sg:phone":"+1 262 859 3094",
    "sg:postcode":"53126",
    "sg:province":"WI",
    "sg:tags":[
        "siding",
        "contractor"
    ],
    "wof:name":"Southway Supply Co",
    "wof:placetype":"venue"
},
  "geometry": {"coordinates":[-88.00561500000001,42.81552],"type":"Point"}
}