{
  "type": "Feature",
  "properties": {
    "iso:country":"US",
    "sg:address":"835 N 14th Ave",
    "sg:city":"Sturgeon Bay",
    "sg:classifiers":[
        {
            "category":"Utilities",
            "subcategory":"Refuse",
            "type":"Services"
        }
    ],
    "sg:phone":"+1 920 746 2912",
    "sg:postcode":"54235",
    "sg:province":"WI",
    "sg:tags":[
        "executive",
        "system"
    ],
    "wof:name":"City of Sturgeon Bay",
    "wof:placetype":"venue"
},
  "geometry": {"coordinates":[-87.361754,44.846931],"type":"Point"}
}