{
  "type": "Feature",
  "properties": {
    "addr:full":"11779 State Hwy 70 Minocqua WI 54548",
    "addr:housenumber":"11779",
    "addr:postcode":"54548",
    "addr:street":"State Hwy 70",
    "iso:country":"US",
    "sg:address":"11779 State Hwy 70",
    "sg:city":"Minocqua",
    "sg:classifiers":[
        {
            "category":"Autos & Motor Vehicles",
            "subcategory":"Boat Sales",
            "type":"Retail Goods"
        }
    ],
    "sg:phone":"+1 715 356 3049",
    "sg:postcode":"54548",
    "sg:province":"WI",
    "sg:tags":[
        "small",
        "engine",
        "outboard",
        "repair"
    ],
    "wof:name":"Smylies Northland Marine Inc",
    "wof:placetype":"venue"
},
  "geometry": {"coordinates":[-89.85242700000001,45.893252],"type":"Point"}
}