{
  "type": "Feature",
  "properties": {
    "iso:country":"US",
    "sg:address":"850 Schuster Rd",
    "sg:city":"Sun Prairie",
    "sg:classifiers":[
        {
            "category":"Social Services",
            "type":"Services"
        }
    ],
    "sg:phone":"+1 608 834 6400",
    "sg:postcode":"53590",
    "sg:province":"WI",
    "sg:tags":[
        "counseling"
    ],
    "wof:name":"Behrend Counseling",
    "wof:placetype":"venue"
},
  "geometry": {"coordinates":[-89.19236100000001,43.191844],"type":"Point"}
}