{
  "type": "Feature",
  "properties": {
    "addr:full":"1810 Wolf Rd Richfield WI 53076",
    "addr:housenumber":"1810",
    "addr:postcode":"53076",
    "addr:street":"Wolf Rd",
    "iso:country":"US",
    "sg:address":"1810 Wolf Rd",
    "sg:city":"Richfield",
    "sg:classifiers":[
        {
            "category":"Retail",
            "subcategory":"Auto Repair",
            "type":"Services"
        }
    ],
    "sg:phone":"+1 262 628 1932",
    "sg:postcode":"53076",
    "sg:province":"WI",
    "sg:tags":[
        "truck",
        "sales"
    ],
    "wof:name":"Richfield Service Inc",
    "wof:placetype":"venue"
},
  "geometry": {"coordinates":[-88.191992,43.254354],"type":"Point"}
}