{
  "type": "Feature",
  "properties": {
    "iso:country":"US",
    "sg:address":"2161 Zeier Rd",
    "sg:city":"Madison",
    "sg:classifiers":[
        {
            "category":"Shopping",
            "subcategory":"Hobbies, Toys, & Games",
            "type":"Retail Goods"
        }
    ],
    "sg:phone":"+1 608 246 0555",
    "sg:postcode":"53704",
    "sg:province":"WI",
    "wof:name":"Toys R Us",
    "wof:placetype":"venue"
},
  "geometry": {"coordinates":[-89.300282,43.12583],"type":"Point"}
}