{
  "type": "Feature",
  "properties": {
    "iso:country":"US",
    "sg:address":"324 Wisconsin Ave",
    "sg:city":"Madison",
    "sg:classifiers":[
        {
            "category":"Building & Trades",
            "subcategory":"Equipment Rental",
            "type":"Services"
        }
    ],
    "sg:phone":"+1 608 222 2500",
    "sg:postcode":"53703",
    "sg:province":"WI",
    "sg:tags":[
        "leasing"
    ],
    "sg:website":"www.advantageleasing.com",
    "wof:name":"Advantage Leasing Corp",
    "wof:placetype":"venue"
},
  "geometry": {"coordinates":[-89.38774100000001,43.077281],"type":"Point"}
}