{
  "type": "Feature",
  "properties": {
    "addr:full":"2745 N Brookfield Rd Brookfield WI 53045",
    "addr:housenumber":"2745",
    "addr:postcode":"53045",
    "addr:street":"N Brookfield Rd",
    "iso:country":"US",
    "sg:address":"2745 N Brookfield Rd",
    "sg:city":"Brookfield",
    "sg:classifiers":[
        {
            "category":"Professional",
            "type":"Services"
        }
    ],
    "sg:phone":"+1 262 827 1219",
    "sg:postcode":"53045",
    "sg:province":"WI",
    "wof:name":"Gohr Creative Services LLC",
    "wof:placetype":"venue"
},
  "geometry": {"coordinates":[-88.145973,43.069283],"type":"Point"}
}