{
  "type": "Feature",
  "properties": {
    "iso:country":"US",
    "sg:address":"1907 American Dr",
    "sg:city":"Neenah",
    "sg:classifiers":[
        {
            "category":"Insurance",
            "subcategory":"Insurance Agent",
            "type":"Services"
        }
    ],
    "sg:phone":"+1 920 722 6609",
    "sg:postcode":"54956",
    "sg:province":"WI",
    "wof:name":"Farmers Insurance Group",
    "wof:placetype":"venue"
},
  "geometry": {"coordinates":[-88.469537,44.226991],"type":"Point"}
}