{
  "type": "Feature",
  "properties": {
    "addr:full":"5602 W Burleigh St Milwaukee WI 53210",
    "addr:housenumber":"5602",
    "addr:postcode":"53210",
    "addr:street":"W Burleigh St",
    "iso:country":"US",
    "sg:address":"5602 W Burleigh St",
    "sg:city":"Milwaukee",
    "sg:classifiers":[
        {
            "category":"Food & Beverages",
            "subcategory":"Groceries & Convenience Stores",
            "type":"Retail Goods"
        }
    ],
    "sg:phone":"+1 414 444 3335",
    "sg:postcode":"53210",
    "sg:province":"WI",
    "wof:name":"Hen Pantry",
    "wof:placetype":"venue"
},
  "geometry": {"coordinates":[-87.984111,43.075404],"type":"Point"}
}