{
  "type": "Feature",
  "properties": {
    "addr:full":"1631 US Hwy 8 Barron WI 54812",
    "addr:housenumber":"1631",
    "addr:postcode":"54812",
    "addr:street":"Us Hwy 8",
    "iso:country":"US",
    "sg:address":"1631 US Hwy 8",
    "sg:city":"Barron",
    "sg:classifiers":[
        {
            "category":"Wholesale",
            "subcategory":"Auto Parts",
            "type":"Manufacturing & Wholesale Goods"
        }
    ],
    "sg:phone":"+1 715 537 3157",
    "sg:postcode":"54812",
    "sg:province":"WI",
    "sg:tags":[
        "automobile",
        "rebuilt"
    ],
    "wof:name":"Kadinger's II",
    "wof:placetype":"venue"
},
  "geometry": {"coordinates":[-91.821584,45.401101],"type":"Point"}
}