{
  "type": "Feature",
  "properties": {
    "iso:country":"US",
    "sg:address":"6662 Co Rd X",
    "sg:city":"Weyauwega",
    "sg:classifiers":[
        {
            "category":"Retail",
            "subcategory":"Auto Repair",
            "type":"Services"
        }
    ],
    "sg:phone":"+1 920 867 4159",
    "sg:postcode":"54983",
    "sg:province":"WI",
    "sg:tags":[
        "general"
    ],
    "wof:name":"Jerrys Auto & Truck",
    "wof:placetype":"venue"
},
  "geometry": {"coordinates":[-88.88032699999999,44.355875],"type":"Point"}
}