{
  "type": "Feature",
  "properties": {
    "iso:country":"US",
    "sg:address":"9442 Konkol Ln",
    "sg:city":"Amherst Junction",
    "sg:classifiers":[
        {
            "category":"Health Services",
            "subcategory":"Clinic",
            "type":"Services"
        }
    ],
    "sg:phone":"+1 715 824 2632",
    "sg:postcode":"54407",
    "sg:province":"WI",
    "wof:name":"Amherst First Responders",
    "wof:placetype":"venue"
},
  "geometry": {"coordinates":[-89.312383,44.475272],"type":"Point"}
}