{
  "type": "Feature",
  "properties": {
    "addr:full":"346 Huntington Ct Nekoosa WI 54457",
    "addr:housenumber":"346",
    "addr:postcode":"54457",
    "addr:street":"Huntington Ct",
    "iso:country":"US",
    "sg:address":"346 Huntington Ct",
    "sg:city":"Nekoosa",
    "sg:classifiers":[
        {
            "category":"Building & Trades",
            "subcategory":"Electrical",
            "type":"Services"
        }
    ],
    "sg:phone":"+1 715 325 2686",
    "sg:postcode":"54457",
    "sg:province":"WI",
    "sg:tags":[
        "electric",
        "contractor"
    ],
    "wof:name":"Four Lakes Electric Co",
    "wof:placetype":"venue"
},
  "geometry": {"coordinates":[-89.790122,44.210876],"type":"Point"}
}