{
  "type": "Feature",
  "properties": {
    "iso:country":"US",
    "sg:address":"4751 Elm Grove Ln",
    "sg:city":"Kewaunee",
    "sg:classifiers":[
        {
            "category":"Farming",
            "subcategory":"Dairy Farm",
            "type":"Manufacturing & Wholesale Goods"
        }
    ],
    "sg:phone":"+1 920 388 3256",
    "sg:postcode":"54216",
    "sg:province":"WI",
    "wof:name":"Elm Grove Dairy Inc",
    "wof:placetype":"venue"
},
  "geometry": {"coordinates":[-87.608316,44.497],"type":"Point"}
}