{
  "type": "Feature",
  "properties": {
    "iso:country":"US",
    "sg:address":"311 N Hancock St",
    "sg:city":"Madison",
    "sg:classifiers":[
        {
            "category":"Real Estate",
            "subcategory":"Real Estate Operator",
            "type":"Services"
        }
    ],
    "sg:phone":"+1 608 255 3040",
    "sg:postcode":"53703",
    "sg:province":"WI",
    "sg:tags":[
        "building",
        "apartment"
    ],
    "wof:name":"Nichols Station II Ltd Partnr",
    "wof:placetype":"venue"
},
  "geometry": {"coordinates":[-89.38388999999999,43.080188],"type":"Point"}
}