{
  "type": "Feature",
  "properties": {
    "addr:full":"920 Alpine Cir Fontana WI 53125",
    "addr:housenumber":"920",
    "addr:postcode":"53125",
    "addr:street":"Alpine Cir",
    "iso:country":"US",
    "sg:address":"920 Alpine Cir",
    "sg:city":"Fontana",
    "sg:classifiers":[
        {
            "category":"Professional",
            "subcategory":"Management & Consulting",
            "type":"Services"
        }
    ],
    "sg:phone":"+1 262 275 8030",
    "sg:postcode":"53125",
    "sg:province":"WI",
    "wof:name":"Daniels Marketing Corp 2",
    "wof:placetype":"venue"
},
  "geometry": {"coordinates":[-88.587889,42.538709],"type":"Point"}
}