{
  "type": "Feature",
  "properties": {
    "addr:full":"628 2nd Ave S Onalaska WI 54650",
    "addr:housenumber":"628",
    "addr:postcode":"54650",
    "addr:street":"2Nd Ave S",
    "iso:country":"US",
    "sg:address":"628 2nd Ave S",
    "sg:city":"Onalaska",
    "sg:classifiers":[
        {
            "category":"Insurance",
            "subcategory":"Insurance Agent",
            "type":"Services"
        }
    ],
    "sg:phone":"+1 608 783 1800",
    "sg:postcode":"54650",
    "sg:province":"WI",
    "wof:name":"Wenberg Insurance Assoc",
    "wof:placetype":"venue"
},
  "geometry": {"coordinates":[-91.23191,43.877929],"type":"Point"}
}