{
  "type": "Feature",
  "properties": {
    "iso:country":"US",
    "sg:address":"515 Oak St",
    "sg:city":"Baraboo",
    "sg:classifiers":[
        {
            "category":"Banks & Credit Unions",
            "subcategory":"Bank",
            "type":"Services"
        }
    ],
    "sg:phone":"+1 608 356 5581",
    "sg:postcode":"53913",
    "sg:province":"WI",
    "wof:name":"Sauk County Employee Cu",
    "wof:placetype":"venue"
},
  "geometry": {"coordinates":[-89.742555,43.470758],"type":"Point"}
}