{
  "type": "Feature",
  "properties": {
    "iso:country":"US",
    "sg:address":"2435 N 89th St",
    "sg:city":"Milwaukee",
    "sg:classifiers":[
        {
            "category":"Education",
            "subcategory":"School",
            "type":"Public Place"
        }
    ],
    "sg:phone":"+1 414 773 1500",
    "sg:postcode":"53226",
    "sg:province":"WI",
    "sg:tags":[
        "elementary"
    ],
    "wof:name":"Mc Kinley Elementary School",
    "wof:placetype":"venue"
},
  "geometry": {"coordinates":[-88.02381,43.063514],"type":"Point"}
}