{
  "type": "Feature",
  "properties": {
    "iso:country":"US",
    "sg:address":"12735 S White Potato Lake Rd",
    "sg:city":"Pound",
    "sg:classifiers":[
        {
            "category":"Real Estate",
            "subcategory":"Real Estate Operator",
            "type":"Services"
        }
    ],
    "sg:phone":"+1 920 897 3713",
    "sg:postcode":"54161",
    "sg:province":"WI",
    "sg:tags":[
        "mobile",
        "home",
        "site"
    ],
    "wof:name":"Kobus Sheve Manufactor Home Pk",
    "wof:placetype":"venue"
},
  "geometry": {"coordinates":[-88.208127,45.136219],"type":"Point"}
}