{
  "type": "Feature",
  "properties": {
    "iso:country":"US",
    "sg:address":"10576 Kansas Ave",
    "sg:city":"Hayward",
    "sg:classifiers":[
        {
            "category":"Shopping",
            "subcategory":"Discount & Variety Stores",
            "type":"Retail Goods"
        }
    ],
    "sg:phone":"+1 715 634 8625",
    "sg:postcode":"54843",
    "sg:province":"WI",
    "sg:tags":[
        "merchandise",
        "general"
    ],
    "wof:name":"Nationwide Supply Co Inc",
    "wof:placetype":"venue"
},
  "geometry": {"coordinates":[-91.482878,46.014809],"type":"Point"}
}