{
  "type": "Feature",
  "properties": {
    "addr:full":"12798 US Hwy 63 Hayward WI 54843",
    "addr:housenumber":"12798",
    "addr:postcode":"54843",
    "addr:street":"Us Hwy 63",
    "iso:country":"US",
    "sg:address":"12798 US Hwy 63",
    "sg:city":"Hayward",
    "sg:classifiers":[
        {
            "category":"Freight",
            "type":"Transportation"
        }
    ],
    "sg:phone":"+1 715 634 5704",
    "sg:postcode":"54843",
    "sg:province":"WI",
    "sg:tags":[
        "commercial",
        "storage"
    ],
    "wof:name":"A & M Storage",
    "wof:placetype":"venue"
},
  "geometry": {"coordinates":[-91.390235,46.090309],"type":"Point"}
}