{
  "type": "Feature",
  "properties": {
    "iso:country":"US",
    "sg:address":"8200 W Denver Ave",
    "sg:city":"Milwaukee",
    "sg:classifiers":[
        {
            "category":"Organizations",
            "subcategory":"Religious Organization",
            "type":"Services"
        }
    ],
    "sg:phone":"+1 414 358 4600",
    "sg:postcode":"53223",
    "sg:province":"WI",
    "sg:tags":[
        "catholic",
        "school",
        "church"
    ],
    "wof:name":"St Bernadette Church & School",
    "wof:placetype":"venue"
},
  "geometry": {"coordinates":[-88.016508,43.141373],"type":"Point"}
}