{
  "type": "Feature",
  "properties": {
    "iso:country":"US",
    "sg:address":"21 Broadway St",
    "sg:city":"Edgerton",
    "sg:classifiers":[
        {
            "category":"Building & Trades",
            "subcategory":"Plumbing",
            "type":"Services"
        }
    ],
    "sg:phone":"+1 608 884 3529",
    "sg:postcode":"53534",
    "sg:province":"WI",
    "sg:tags":[
        "contractor"
    ],
    "wof:name":"Rucker & Sons Heating",
    "wof:placetype":"venue"
},
  "geometry": {"coordinates":[-89.065889,42.83346],"type":"Point"}
}