{
  "type": "Feature",
  "properties": {
    "iso:country":"US",
    "sg:address":"639 Brakke Dr",
    "sg:city":"Hudson",
    "sg:classifiers":[
        {
            "category":"Home & Garden",
            "subcategory":"Household Appliances",
            "type":"Retail Goods"
        },
        {
            "category":"Wholesale",
            "subcategory":"Construction Materials",
            "type":"Manufacturing & Wholesale Goods"
        },
        {
            "category":"Home & Garden",
            "subcategory":"Building Materials",
            "type":"Retail Goods"
        },
        {
            "category":"Wholesale",
            "subcategory":"Home Furnishings",
            "type":"Manufacturing & Wholesale Goods"
        }
    ],
    "sg:phone":"+1 715 386 5525",
    "sg:postcode":"54016",
    "sg:province":"WI",
    "sg:tags":[
        "bathroom",
        "supply",
        "fixture",
        "major",
        "cabinet",
        "part",
        "plumbing",
        "fixtures",
        "accessory",
        "supplies-wholesale",
        "manufacturer"
    ],
    "sg:website":"http://www-ferguson-com.netsolads.com/homeowner.shtml?_nsag=39485",
    "wof:name":"Ferguson Bath & Kitchen Gallery",
    "wof:placetype":"venue"
},
  "geometry": {"coordinates":[-92.67130299999999,44.968401],"type":"Point"}
}