{
  "type": "Feature",
  "properties": {
    "iso:country":"US",
    "sg:address":"1098 340th Ave",
    "sg:city":"Frederic",
    "sg:classifiers":[
        {
            "category":"Travel",
            "subcategory":"Hotels & Motels",
            "type":"Entertainment"
        }
    ],
    "sg:phone":"+1 715 653 2323",
    "sg:postcode":"54837",
    "sg:province":"WI",
    "sg:tags":[
        "operation"
    ],
    "sg:website":"www.sevenpineslodge.com",
    "wof:name":"Seven Pines Lodge",
    "wof:placetype":"venue"
},
  "geometry": {"coordinates":[-92.380372,45.698006],"type":"Point"}
}