{
  "type": "Feature",
  "properties": {
    "iso:country":"US",
    "sg:address":"500 S 116th St",
    "sg:city":"Milwaukee",
    "sg:classifiers":[
        {
            "category":"Utilities",
            "subcategory":"Electric",
            "type":"Services"
        }
    ],
    "sg:phone":"+1 414 944 5663",
    "sg:postcode":"53214",
    "sg:province":"WI",
    "sg:tags":[
        "station",
        "headquarters",
        "maintenance"
    ],
    "wof:name":"West Allis Operations Center",
    "wof:placetype":"venue"
},
  "geometry": {"coordinates":[-88.057044,43.027902],"type":"Point"}
}