{
  "type": "Feature",
  "properties": {
    "iso:country":"US",
    "sg:address":"7240 US Hwy 45",
    "sg:city":"Wittenberg",
    "sg:classifiers":[
        {
            "category":"Organizations",
            "subcategory":"Religious Organization",
            "type":"Services"
        }
    ],
    "sg:phone":"+1 715 253 3222",
    "sg:postcode":"54499",
    "sg:province":"WI",
    "sg:tags":[
        "church"
    ],
    "wof:name":"Native American Church",
    "wof:placetype":"venue"
},
  "geometry": {"coordinates":[-89.16869,44.852199],"type":"Point"}
}