{
  "type": "Feature",
  "properties": {
    "iso:country":"US",
    "sg:address":"7485 State Hwy 65",
    "sg:city":"Beldenville",
    "sg:classifiers":[
        {
            "category":"Bars & Pubs",
            "type":"Food & Drink"
        }
    ],
    "sg:phone":"+1 715 273 4951",
    "sg:postcode":"54003",
    "sg:province":"WI",
    "wof:name":"Bighorn",
    "wof:placetype":"venue"
},
  "geometry": {"coordinates":[-92.504319,44.773005],"type":"Point"}
}