{
  "type": "Feature",
  "properties": {
    "iso:country":"US",
    "sg:address":"4054 Hillside Rd",
    "sg:city":"Slinger",
    "sg:classifiers":[
        {
            "category":"Farming",
            "subcategory":"Farm",
            "type":"Manufacturing & Wholesale Goods"
        }
    ],
    "sg:phone":"+1 262 644 5358",
    "sg:postcode":"53086",
    "sg:province":"WI",
    "sg:tags":[
        "crop",
        "general"
    ],
    "wof:name":"Merten Farms",
    "wof:placetype":"venue"
},
  "geometry": {"coordinates":[-88.241013,43.329733],"type":"Point"}
}