{
  "type": "Feature",
  "properties": {
    "iso:country":"US",
    "sg:address":"908 Shamrock Ct",
    "sg:city":"Kaukauna",
    "sg:classifiers":[
        {
            "category":"Building & Trades",
            "subcategory":"Construction",
            "type":"Services"
        }
    ],
    "sg:phone":"+1 920 766 9310",
    "sg:postcode":"54130",
    "sg:province":"WI",
    "sg:tags":[
        "house"
    ],
    "wof:name":"Van Dyn Hoven Jeff Cnstr",
    "wof:placetype":"venue"
},
  "geometry": {"coordinates":[-88.288754,44.273576],"type":"Point"}
}