{
  "type": "Feature",
  "properties": {
    "iso:country":"US",
    "sg:address":"4791 State Hwy 25",
    "sg:city":"Menomonie",
    "sg:classifiers":[
        {
            "category":"Home & Garden",
            "subcategory":"Mobile Homes",
            "type":"Retail Goods"
        },
        {
            "category":"Manufacturing",
            "subcategory":"Buildings",
            "type":"Manufacturing & Wholesale Goods"
        }
    ],
    "sg:phone":"+1 715 235 7020",
    "sg:postcode":"54751",
    "sg:province":"WI",
    "sg:tags":[
        "prefab"
    ],
    "wof:name":"Home Source One",
    "wof:placetype":"venue"
},
  "geometry": {"coordinates":[-91.926111,44.85528],"type":"Point"}
}