{
  "type": "Feature",
  "properties": {
    "iso:country":"US",
    "sg:address":"1630 S 35th St",
    "sg:city":"Milwaukee",
    "sg:classifiers":[
        {
            "category":"Organizations",
            "subcategory":"Religious Organization",
            "type":"Services"
        }
    ],
    "sg:phone":"+1 414 384 8570",
    "sg:postcode":"53215",
    "sg:province":"WI",
    "wof:name":"Higher Heights Ministries",
    "wof:placetype":"venue"
},
  "geometry": {"coordinates":[-87.95755,43.012952],"type":"Point"}
}