{
  "type": "Feature",
  "properties": {
    "iso:country":"US",
    "sg:address":"1805 N 16th St",
    "sg:city":"Superior",
    "sg:classifiers":[
        {
            "category":"Government",
            "subcategory":"Office",
            "type":"Public Place"
        }
    ],
    "sg:phone":"+1 715 395 0541",
    "sg:postcode":"54880",
    "sg:province":"WI",
    "wof:name":"Douglas County Info & Referral",
    "wof:placetype":"venue"
},
  "geometry": {"coordinates":[-92.105428,46.719395],"type":"Point"}
}