{
  "type": "Feature",
  "properties": {
    "addr:full":"27234 Concord Ave Warrens WI 54666",
    "addr:housenumber":"27234",
    "addr:postcode":"54666",
    "addr:street":"Concord Ave",
    "iso:country":"US",
    "sg:address":"27234 Concord Ave",
    "sg:city":"Warrens",
    "sg:phone":"+1 608 378 4629",
    "sg:postcode":"54666",
    "sg:province":"WI",
    "sg:tags":[
        "farm",
        "field",
        "corn",
        "crop"
    ],
    "wof:name":"Johnson Brothers Farms",
    "wof:placetype":"venue"
},
  "geometry": {"coordinates":[-90.455212,44.097229],"type":"Point"}
}