{
  "type": "Feature",
  "properties": {
    "iso:country":"US",
    "sg:address":"1 Eastridge Ct",
    "sg:city":"Madison",
    "sg:classifiers":[
        {
            "category":"Professional",
            "subcategory":"Business Services",
            "type":"Services"
        }
    ],
    "sg:phone":"+1 608 216 0420",
    "sg:postcode":"53716",
    "sg:province":"WI",
    "wof:name":"Act Enterprises",
    "wof:placetype":"venue"
},
  "geometry": {"coordinates":[-89.28191,43.075272],"type":"Point"}
}