{
  "type": "Feature",
  "properties": {
    "addr:full":"4257 S Rutland Ave Milwaukee WI 53235",
    "addr:housenumber":"4257",
    "addr:postcode":"53235",
    "addr:street":"S Rutland Ave",
    "iso:country":"US",
    "sg:address":"4257 S Rutland Ave",
    "sg:city":"Milwaukee",
    "sg:classifiers":[
        {
            "category":"Organizations",
            "subcategory":"Religious Organization",
            "type":"Services"
        }
    ],
    "sg:phone":"+1 414 483 9982",
    "sg:postcode":"53235",
    "sg:province":"WI",
    "sg:tags":[
        "monastery",
        "convent"
    ],
    "wof:name":"Sisters Of St Francis-Assisi",
    "wof:placetype":"venue"
},
  "geometry": {"coordinates":[-87.883591,42.967107],"type":"Point"}
}