{
  "type": "Feature",
  "properties": {
    "addr:full":"509 E Wausau Ave Wausau WI 54403",
    "addr:housenumber":"509",
    "addr:postcode":"54403",
    "addr:street":"E Wausau Ave",
    "iso:country":"US",
    "sg:address":"509 E Wausau Ave",
    "sg:city":"Wausau",
    "sg:classifiers":[
        {
            "category":"Professional",
            "type":"Services"
        }
    ],
    "sg:phone":"+1 715 858 0997",
    "sg:postcode":"54403",
    "sg:province":"WI",
    "wof:name":"Christopher L Kulesa",
    "wof:placetype":"venue"
},
  "geometry": {"coordinates":[-89.623963,44.973752],"type":"Point"}
}