{
  "type": "Feature",
  "properties": {
    "iso:country":"US",
    "sg:address":"435 State St",
    "sg:city":"Madison",
    "sg:classifiers":[
        {
            "category":"Shopping",
            "subcategory":"Luggage & Leather Goods",
            "type":"Retail Goods"
        }
    ],
    "sg:phone":"+1 608 258 9962",
    "sg:postcode":"53703",
    "sg:province":"WI",
    "sg:tags":[
        "sales"
    ],
    "wof:name":"Village Bag Shop",
    "wof:placetype":"venue"
},
  "geometry": {"coordinates":[-89.39294,43.074738],"type":"Point"}
}