{
  "type": "Feature",
  "properties": {
    "addr:full":"1813 E Kenilworth Pl Milwaukee WI 53202",
    "addr:housenumber":"1813",
    "addr:postcode":"53202",
    "addr:street":"E Kenilworth Pl",
    "iso:country":"US",
    "sg:address":"1813 E Kenilworth Pl",
    "sg:city":"Milwaukee",
    "sg:classifiers":[
        {
            "category":"Restaurant",
            "type":"Food & Drink"
        }
    ],
    "sg:menulink":"http://www.allmenus.com/wi/milwaukee/141302-hotch-a-do/menu/",
    "sg:phone":"+1 414 727 2122",
    "sg:postcode":"53202",
    "sg:province":"WI",
    "sg:tags":[
        "american"
    ],
    "wof:name":"Hotch-a-do",
    "wof:placetype":"venue"
},
  "geometry": {"coordinates":[-87.887491,43.059956],"type":"Point"}
}