{
  "type": "Feature",
  "properties": {
    "iso:country":"US",
    "sg:address":"4503 W Ramsey Ave",
    "sg:city":"Greendale",
    "sg:classifiers":[
        {
            "category":"Real Estate",
            "subcategory":"Real Estate Operator",
            "type":"Services"
        }
    ],
    "sg:phone":"+1 414 421 2610",
    "sg:postcode":"53129",
    "sg:province":"WI",
    "sg:tags":[
        "apartment"
    ],
    "wof:name":"Applewood Village",
    "wof:placetype":"venue"
},
  "geometry": {"coordinates":[-87.97371,42.937563],"type":"Point"}
}