{
  "type": "Feature",
  "properties": {
    "iso:country":"US",
    "sg:address":"805 Milwaukee St",
    "sg:city":"Delafield",
    "sg:classifiers":[
        {
            "category":"Food & Beverages",
            "subcategory":"Bakery",
            "type":"Retail Goods"
        }
    ],
    "sg:phone":"+1 262 784 5670",
    "sg:postcode":"53018",
    "sg:province":"WI",
    "wof:name":"Mrs Millers Strawberry Pies",
    "wof:placetype":"venue"
},
  "geometry": {"coordinates":[-88.399492,43.061898],"type":"Point"}
}