{
  "type": "Feature",
  "properties": {
    "iso:country":"US",
    "sg:address":"5101 Division Rd",
    "sg:city":"Waterford",
    "sg:classifiers":[
        {
            "category":"Building & Trades",
            "subcategory":"Construction",
            "type":"Services"
        }
    ],
    "sg:phone":"+1 262 895 6847",
    "sg:postcode":"53185",
    "sg:province":"WI",
    "sg:tags":[
        "concrete",
        "contractor"
    ],
    "wof:name":"Walls Are Us Inc",
    "wof:placetype":"venue"
},
  "geometry": {"coordinates":[-88.17688099999999,42.792507],"type":"Point"}
}