{
  "type": "Feature",
  "properties": {
    "iso:country":"US",
    "sg:address":"4111 Kauth Dr",
    "sg:city":"Wisconsin Rapids",
    "sg:classifiers":[
        {
            "category":"Freight",
            "type":"Transportation"
        }
    ],
    "sg:phone":"+1 715 424 0990",
    "sg:postcode":"54494",
    "sg:province":"WI",
    "wof:name":"Rs Transport LLC",
    "wof:placetype":"venue"
},
  "geometry": {"coordinates":[-89.774747,44.36192],"type":"Point"}
}