{
  "type": "Feature",
  "properties": {
    "iso:country":"US",
    "sg:address":"4327 Musser Dr",
    "sg:city":"Phillips",
    "sg:classifiers":[
        {
            "category":"Retail",
            "subcategory":"Animal Services",
            "type":"Services"
        }
    ],
    "sg:phone":"+1 715 339 6239",
    "sg:postcode":"54555",
    "sg:province":"WI",
    "wof:name":"Norphlandpier Cabin",
    "wof:placetype":"venue"
},
  "geometry": {"coordinates":[-90.260347,45.725056],"type":"Point"}
}