{
  "type": "Feature",
  "properties": {
    "iso:country":"US",
    "sg:address":"1760 Milwaukee St",
    "sg:city":"Delafield",
    "sg:classifiers":[
        {
            "category":"Wholesale",
            "subcategory":"Electrical",
            "type":"Manufacturing & Wholesale Goods"
        }
    ],
    "sg:phone":"+1 262 646 5420",
    "sg:postcode":"53018",
    "sg:province":"WI",
    "sg:tags":[
        "electronic"
    ],
    "wof:name":"Janus Inc",
    "wof:placetype":"venue"
},
  "geometry": {"coordinates":[-88.385025,43.05792],"type":"Point"}
}