{
  "type": "Feature",
  "properties": {
    "iso:country":"US",
    "sg:address":"5031 W Howard Ave",
    "sg:city":"Milwaukee",
    "sg:classifiers":[
        {
            "category":"Retail",
            "subcategory":"Repair Shop",
            "type":"Services"
        }
    ],
    "sg:phone":"+1 414 321 4909",
    "sg:postcode":"53220",
    "sg:province":"WI",
    "sg:tags":[
        "appliance",
        "household",
        "electrical"
    ],
    "wof:name":"Vac Hut Plus",
    "wof:placetype":"venue"
},
  "geometry": {"coordinates":[-87.97775799999999,42.973836],"type":"Point"}
}