{
  "type": "Feature",
  "properties": {
    "iso:country":"US",
    "sg:address":"47 Park Pl",
    "sg:city":"Appleton",
    "sg:classifiers":[
        {
            "category":"Insurance",
            "subcategory":"Insurance Agent",
            "type":"Services"
        }
    ],
    "sg:phone":"+1 920 731 7730",
    "sg:postcode":"54914",
    "sg:province":"WI",
    "wof:name":"Pekin Insurance",
    "wof:placetype":"venue"
},
  "geometry": {"coordinates":[-88.467069,44.257281],"type":"Point"}
}