{
  "type": "Feature",
  "properties": {
    "iso:country":"US",
    "sg:address":"1600 Miller Park Way",
    "sg:city":"Milwaukee",
    "sg:classifiers":[
        {
            "category":"Professional",
            "type":"Services"
        }
    ],
    "sg:phone":"+1 414 672 1533",
    "sg:postcode":"53214",
    "sg:province":"WI",
    "sg:tags":[
        "establishment"
    ],
    "wof:name":"Inland Companies",
    "wof:placetype":"venue"
},
  "geometry": {"coordinates":[-87.967434,43.014384],"type":"Point"}
}