{
  "type": "Feature",
  "properties": {
    "iso:country":"US",
    "sg:address":"10125 W North Ave",
    "sg:city":"Milwaukee",
    "sg:classifiers":[
        {
            "category":"Building & Trades",
            "subcategory":"Construction",
            "type":"Services"
        }
    ],
    "sg:phone":"+1 262 238 2900",
    "sg:postcode":"53226",
    "sg:province":"WI",
    "sg:tags":[
        "roofing",
        "contractor"
    ],
    "wof:name":"Impressive Roofing & Siding",
    "wof:placetype":"venue"
},
  "geometry": {"coordinates":[-88.039731,43.060232],"type":"Point"}
}