{
  "type": "Feature",
  "properties": {
    "iso:country":"US",
    "sg:address":"19263 Elm Rd",
    "sg:city":"Eland",
    "sg:classifiers":[
        {
            "category":"Building & Trades",
            "subcategory":"Construction",
            "type":"Services"
        }
    ],
    "sg:phone":"+1 715 253 3350",
    "sg:postcode":"54427",
    "sg:province":"WI",
    "sg:tags":[
        "contractor"
    ],
    "wof:name":"Cz Drywall",
    "wof:placetype":"venue"
},
  "geometry": {"coordinates":[-89.224214,44.802812],"type":"Point"}
}