{
  "type": "Feature",
  "properties": {
    "iso:country":"US",
    "sg:address":"15 Guindon Blvd",
    "sg:city":"Fond Du Lac",
    "sg:classifiers":[
        {
            "category":"Wholesale",
            "subcategory":"Chemicals & Plastics",
            "type":"Manufacturing & Wholesale Goods"
        }
    ],
    "sg:phone":"+1 920 923 5377",
    "sg:postcode":"54935",
    "sg:province":"WI",
    "sg:tags":[
        "oxygen"
    ],
    "wof:name":"Home Tech Oxygen",
    "wof:placetype":"venue"
},
  "geometry": {"coordinates":[-88.445692,43.758127],"type":"Point"}
}