{
  "type": "Feature",
  "properties": {
    "iso:country":"US",
    "sg:address":"415 Bel Aire Dr",
    "sg:city":"Thiensville",
    "sg:classifiers":[
        {
            "category":"Professional",
            "subcategory":"Business Services",
            "type":"Services"
        }
    ],
    "sg:phone":"+1 262 242 5033",
    "sg:postcode":"53092",
    "sg:province":"WI",
    "wof:name":"D Boese & Sons Enterprises",
    "wof:placetype":"venue"
},
  "geometry": {"coordinates":[-87.972015,43.238916],"type":"Point"}
}