{
  "type": "Feature",
  "properties": {
    "addr:full":"4552 Iroquois Ct La Valle WI 53941",
    "addr:housenumber":"4552",
    "addr:postcode":"53941",
    "addr:street":"Iroquois Ct",
    "iso:country":"US",
    "sg:address":"4552 Iroquois Ct",
    "sg:city":"La Valle",
    "sg:classifiers":[
        {
            "category":"Shopping",
            "type":"Retail Goods"
        }
    ],
    "sg:phone":"+1 608 985 8113",
    "sg:postcode":"53941",
    "sg:province":"WI",
    "sg:tags":[
        "miscellaneous",
        "store"
    ],
    "wof:name":"Adelman's Cottage",
    "wof:placetype":"venue"
},
  "geometry": {"coordinates":[-90.08998699999999,43.604931],"type":"Point"}
}