{
  "type": "Feature",
  "properties": {
    "iso:country":"US",
    "sg:address":"2037 Winnebago St",
    "sg:city":"Madison",
    "sg:classifiers":[
        {
            "category":"Health Services",
            "subcategory":"Chiropractor",
            "type":"Services"
        }
    ],
    "sg:phone":"+1 608 249 2188",
    "sg:postcode":"53704",
    "sg:province":"WI",
    "wof:name":"Rose Chiropractic",
    "wof:placetype":"venue"
},
  "geometry": {"coordinates":[-89.354665,43.092483],"type":"Point"}
}