{
  "type": "Feature",
  "properties": {
    "iso:country":"US",
    "sg:address":"215 N Main St",
    "sg:city":"Alma",
    "sg:classifiers":[
        {
            "category":"Restaurant",
            "type":"Food & Drink"
        }
    ],
    "sg:phone":"+1 608 685 4505",
    "sg:postcode":"54610",
    "sg:province":"WI",
    "wof:name":"Kate Graceys",
    "wof:placetype":"venue"
},
  "geometry": {"coordinates":[-91.91665,44.32352],"type":"Point"}
}