{
  "type": "Feature",
  "properties": {
    "iso:country":"US",
    "sg:address":"19400 38th St",
    "sg:city":"Bristol",
    "sg:classifiers":[
        {
            "category":"Building & Trades",
            "subcategory":"Construction",
            "type":"Services"
        }
    ],
    "sg:phone":"+1 262 857 2728",
    "sg:postcode":"53104",
    "sg:province":"WI",
    "sg:tags":[
        "water",
        "well",
        "drilling"
    ],
    "wof:name":"Gohlke Well Drilling",
    "wof:placetype":"venue"
},
  "geometry": {"coordinates":[-88.031821,42.604586],"type":"Point"}
}