{
  "type": "Feature",
  "properties": {
    "iso:country":"US",
    "sg:address":"4314 39th Ave",
    "sg:city":"Kenosha",
    "sg:classifiers":[
        {
            "category":"Freight",
            "type":"Transportation"
        }
    ],
    "sg:phone":"+1 262 564 5232",
    "sg:postcode":"53144",
    "sg:province":"WI",
    "sg:tags":[
        "truck",
        "trucking"
    ],
    "sg:website":"www.activetransport.com",
    "wof:name":"Active Transportation Co LLC",
    "wof:placetype":"venue"
},
  "geometry": {"coordinates":[-87.855817,42.597896],"type":"Point"}
}