{
  "type": "Feature",
  "properties": {
    "iso:country":"US",
    "sg:address":"7427 Brereton Rd",
    "sg:city":"Dane",
    "sg:classifiers":[
        {
            "category":"Farming",
            "subcategory":"Dairy Farm",
            "type":"Manufacturing & Wholesale Goods"
        }
    ],
    "sg:phone":"+1 608 849 5359",
    "sg:postcode":"53529",
    "sg:province":"WI",
    "wof:name":"Neil Maly",
    "wof:placetype":"venue"
},
  "geometry": {"coordinates":[-89.569233,43.219602],"type":"Point"}
}