{
  "type": "Feature",
  "properties": {
    "addr:full":"W156s7985 Audrey Ct Muskego WI 53150",
    "addr:postcode":"53150",
    "addr:street":"W156S7985 Audrey Ct",
    "iso:country":"US",
    "sg:address":"W156s7985 Audrey Ct",
    "sg:city":"Muskego",
    "sg:classifiers":[
        {
            "category":"Shopping",
            "subcategory":"Crafts & Fabrics",
            "type":"Retail Goods"
        },
        {
            "category":"Professional",
            "subcategory":"Art Services",
            "type":"Services"
        }
    ],
    "sg:phone":"+1 262 253 1118",
    "sg:postcode":"53150",
    "sg:province":"WI",
    "sg:tags":[
        "punching",
        "design",
        "embroidery"
    ],
    "wof:name":"Lambrecht Embroidery",
    "wof:placetype":"venue"
},
  "geometry": {"coordinates":[-88.110168,42.900311],"type":"Point"}
}