{
  "type": "Feature",
  "properties": {
    "addr:full":"3002 Manitowoc Rd Green Bay WI 54311",
    "addr:housenumber":"3002",
    "addr:postcode":"54311",
    "addr:street":"Manitowoc Rd",
    "iso:country":"US",
    "sg:address":"3002 Manitowoc Rd",
    "sg:city":"Green Bay",
    "sg:classifiers":[
        {
            "category":"Bars & Pubs",
            "type":"Food & Drink"
        }
    ],
    "sg:phone":"+1 920 468 9973",
    "sg:postcode":"54311",
    "sg:province":"WI",
    "wof:name":"Bourgies Bar",
    "wof:placetype":"venue"
},
  "geometry": {"coordinates":[-87.93699100000001,44.454912],"type":"Point"}
}