{
  "type": "Feature",
  "properties": {
    "iso:country":"US",
    "sg:address":"12735 W Stark St",
    "sg:city":"Butler",
    "sg:classifiers":[
        {
            "category":"Professional",
            "type":"Services"
        }
    ],
    "sg:phone":"+1 262 783 7107",
    "sg:postcode":"53007",
    "sg:province":"WI",
    "sg:tags":[
        "establishment"
    ],
    "wof:name":"Applewood Design",
    "wof:placetype":"venue"
},
  "geometry": {"coordinates":[-88.070983,43.10577],"type":"Point"}
}