{
  "type": "Feature",
  "properties": {
    "iso:country":"US",
    "sg:address":"6050 Industrial Ct",
    "sg:city":"Greendale",
    "sg:classifiers":[
        {
            "category":"Manufacturing",
            "subcategory":"Furniture",
            "type":"Manufacturing & Wholesale Goods"
        },
        {
            "category":"Wholesale",
            "subcategory":"Furniture",
            "type":"Manufacturing & Wholesale Goods"
        }
    ],
    "sg:phone":"+1 414 421 2960",
    "sg:postcode":"53129",
    "sg:province":"WI",
    "sg:tags":[
        "bleachers",
        "outdoor",
        "grandstand",
        "mfg"
    ],
    "wof:name":"Midwest Bleachers Inc",
    "wof:placetype":"venue"
},
  "geometry": {"coordinates":[-87.994965,42.93121],"type":"Point"}
}