{
  "type": "Feature",
  "properties": {
    "iso:country":"US",
    "sg:address":"5273 Co Rd Mm",
    "sg:city":"Shawano",
    "sg:classifiers":[
        {
            "category":"Building & Trades",
            "subcategory":"Electrical",
            "type":"Services"
        }
    ],
    "sg:phone":"+1 715 524 4033",
    "sg:postcode":"54166",
    "sg:province":"WI",
    "sg:tags":[
        "electrical",
        "contractor"
    ],
    "wof:name":"M J Electric",
    "wof:placetype":"venue"
},
  "geometry": {"coordinates":[-88.624575,44.777922],"type":"Point"}
}