{
  "type": "Feature",
  "properties": {
    "iso:country":"US",
    "sg:address":"130 E Main St",
    "sg:city":"Coleman",
    "sg:classifiers":[
        {
            "category":"Bars & Pubs",
            "type":"Food & Drink"
        }
    ],
    "sg:phone":"+1 920 897 3949",
    "sg:postcode":"54112",
    "sg:province":"WI",
    "sg:tags":[
        "drinking"
    ],
    "wof:name":"Fortiers Bar",
    "wof:placetype":"venue"
},
  "geometry": {"coordinates":[-88.033479,45.065254],"type":"Point"}
}