{
  "type": "Feature",
  "properties": {
    "iso:country":"US",
    "sg:address":"8401 W Capitol Dr",
    "sg:city":"Milwaukee",
    "sg:classifiers":[
        {
            "category":"Home & Garden",
            "subcategory":"Furniture",
            "type":"Retail Goods"
        },
        {
            "category":"Home & Garden",
            "subcategory":"Carpets & Floor Coverings",
            "type":"Retail Goods"
        }
    ],
    "sg:phone":"+1 414 463 5000",
    "sg:postcode":"53222",
    "sg:province":"WI",
    "sg:tags":[
        "rug",
        "store",
        "mattress"
    ],
    "sg:website":"http://www.steinhafels.com",
    "wof:name":"Steinhafels, Inc.",
    "wof:placetype":"venue"
},
  "geometry": {"coordinates":[-88.01754800000001,43.089771],"type":"Point"}
}