{
  "type": "Feature",
  "properties": {
    "addr:full":"107 Scott St Wausau WI 54403",
    "addr:housenumber":"107",
    "addr:postcode":"54403",
    "addr:street":"Scott St",
    "iso:country":"US",
    "sg:address":"107 Scott St",
    "sg:city":"Wausau",
    "sg:classifiers":[
        {
            "category":"Banks & Credit Unions",
            "subcategory":"Investment Brokerage",
            "type":"Services"
        }
    ],
    "sg:phone":"+1 715 849 9040",
    "sg:postcode":"54403",
    "sg:province":"WI",
    "sg:tags":[
        "consultant",
        "planning",
        "financial"
    ],
    "wof:name":"American Express Financial Adv",
    "wof:placetype":"venue"
},
  "geometry": {"coordinates":[-89.62904899999999,44.960649],"type":"Point"}
}