{
  "type": "Feature",
  "properties": {
    "iso:country":"US",
    "sg:address":"713 Superior Ave",
    "sg:city":"Tomah",
    "sg:classifiers":[
        {
            "category":"Retail",
            "subcategory":"Auto Repair",
            "type":"Services"
        }
    ],
    "sg:phone":"+1 608 374 3800",
    "sg:postcode":"54660",
    "sg:province":"WI",
    "sg:tags":[
        "repairing",
        "automobile",
        "radiator"
    ],
    "wof:name":"Rick's Radiator & Repair",
    "wof:placetype":"venue"
},
  "geometry": {"coordinates":[-90.504839,43.98041],"type":"Point"}
}