{
  "type": "Feature",
  "properties": {
    "iso:country":"US",
    "sg:address":"4421 Memory Ln",
    "sg:city":"Eau Claire",
    "sg:classifiers":[
        {
            "category":"Banks & Credit Unions",
            "subcategory":"Financial Services",
            "type":"Services"
        }
    ],
    "sg:phone":"+1 715 832 4322",
    "sg:postcode":"54701",
    "sg:province":"WI",
    "sg:tags":[
        "management",
        "open",
        "investment"
    ],
    "wof:name":"C D B C H B LLC",
    "wof:placetype":"venue"
},
  "geometry": {"coordinates":[-91.445509,44.77094],"type":"Point"}
}