{
  "type": "Feature",
  "properties": {
    "iso:country":"US",
    "sg:address":"1220 Dewey Ave # 414",
    "sg:city":"Milwaukee",
    "sg:classifiers":[
        {
            "category":"Health Services",
            "subcategory":"Doctor",
            "type":"Services"
        },
        {
            "category":"Health Services",
            "subcategory":"Clinic",
            "type":"Services"
        }
    ],
    "sg:phone":"+1 414 454 6600",
    "sg:postcode":"53213",
    "sg:province":"WI",
    "sg:tags":[
        "psychological",
        "psychologist"
    ],
    "wof:name":"Mendelberg Hava E DR Psycholgst",
    "wof:placetype":"venue"
},
  "geometry": {"coordinates":[-88.00949900000001,43.046611],"type":"Point"}
}