{
  "type": "Feature",
  "properties": {
    "iso:country":"US",
    "sg:address":"2913 Roosevelt Rd",
    "sg:city":"Kenosha",
    "sg:classifiers":[
        {
            "category":"Shopping",
            "subcategory":"Florist",
            "type":"Retail Goods"
        }
    ],
    "sg:phone":"+1 262 657 3448",
    "sg:postcode":"53143",
    "sg:province":"WI",
    "wof:name":"Strobbe's Flower Cart",
    "wof:placetype":"venue"
},
  "geometry": {"coordinates":[-87.84520999999999,42.571811],"type":"Point"}
}