{
  "type": "Feature",
  "properties": {
    "addr:full":"110 S Harris Ave Waupun WI 53963",
    "addr:housenumber":"110",
    "addr:postcode":"53963",
    "addr:street":"S Harris Ave",
    "iso:country":"US",
    "sg:address":"110 S Harris Ave",
    "sg:city":"Waupun",
    "sg:classifiers":[
        {
            "category":"Government",
            "subcategory":"Office",
            "type":"Public Place"
        }
    ],
    "sg:phone":"+1 920 324 3035",
    "sg:postcode":"53963",
    "sg:province":"WI",
    "sg:tags":[
        "county"
    ],
    "wof:name":"Dodge County Authority",
    "wof:placetype":"venue"
},
  "geometry": {"coordinates":[-88.756152,43.63179],"type":"Point"}
}