{
  "type": "Feature",
  "properties": {
    "addr:full":"7012 State Rd 49 Fremont WI 54940",
    "addr:housenumber":"7012;49",
    "addr:postcode":"54940",
    "addr:street":"State Rd",
    "iso:country":"US",
    "sg:address":"7012 State Rd 49",
    "sg:city":"Fremont",
    "sg:classifiers":[
        {
            "category":"Building & Trades",
            "subcategory":"Plumbing",
            "type":"Services"
        }
    ],
    "sg:phone":"+1 920 867 5051",
    "sg:postcode":"54940",
    "sg:province":"WI",
    "sg:tags":[
        "plumbing"
    ],
    "wof:name":"Lc Plumbing",
    "wof:placetype":"venue"
},
  "geometry": {"coordinates":[-88.92945400000001,44.233664],"type":"Point"}
}