{
  "type": "Feature",
  "properties": {
    "addr:full":"1713 Dunlap Ave Marinette WI 54143",
    "addr:housenumber":"1713",
    "addr:postcode":"54143",
    "addr:street":"Dunlap Ave",
    "iso:country":"US",
    "sg:address":"1713 Dunlap Ave",
    "sg:city":"Marinette",
    "sg:classifiers":[
        {
            "category":"Retail",
            "subcategory":"Repair Shop",
            "type":"Services"
        }
    ],
    "sg:phone":"+1 715 574 3400",
    "sg:postcode":"54143",
    "sg:province":"WI",
    "wof:name":"Lake Air LLC",
    "wof:placetype":"venue"
},
  "geometry": {"coordinates":[-87.631109,45.09959],"type":"Point"}
}