{
  "type": "Feature",
  "properties": {
    "iso:country":"US",
    "sg:address":"1600 Shawano Ave",
    "sg:city":"Green Bay",
    "sg:classifiers":[
        {
            "category":"Banks & Credit Unions",
            "subcategory":"Bank",
            "type":"Services"
        }
    ],
    "sg:phone":"+1 920 265 4799",
    "sg:postcode":"54303",
    "sg:province":"WI",
    "sg:tags":[
        "loan",
        "broker"
    ],
    "wof:name":"Best Equity Lending",
    "wof:placetype":"venue"
},
  "geometry": {"coordinates":[-88.06321,44.53106],"type":"Point"}
}