{
  "type": "Feature",
  "properties": {
    "iso:country":"US",
    "sg:address":"4650 N Schopen Rd",
    "sg:city":"Jefferson",
    "sg:classifiers":[
        {
            "category":"Travel",
            "subcategory":"Hotels & Motels",
            "type":"Entertainment"
        }
    ],
    "sg:phone":"+1 920 674 3553",
    "sg:postcode":"53549",
    "sg:province":"WI",
    "sg:tags":[
        "operation"
    ],
    "wof:name":"Deegs Outdoor Cabin Rentals",
    "wof:placetype":"venue"
},
  "geometry": {"coordinates":[-88.773944,43.011414],"type":"Point"}
}