{
  "type": "Feature",
  "properties": {
    "iso:country":"US",
    "sg:address":"19700 W Lincoln Ave",
    "sg:city":"New Berlin",
    "sg:classifiers":[
        {
            "category":"Freight",
            "type":"Transportation"
        },
        {
            "category":"Home & Garden",
            "subcategory":"Garden Supply",
            "type":"Retail Goods"
        }
    ],
    "sg:phone":"+1 262 547 1400",
    "sg:postcode":"53146",
    "sg:province":"WI",
    "sg:tags":[
        "operator",
        "local",
        "trucking"
    ],
    "wof:name":"Fredricks Bros Trucking Inc",
    "wof:placetype":"venue"
},
  "geometry": {"coordinates":[-88.15486900000001,43.002655],"type":"Point"}
}