{
  "type": "Feature",
  "properties": {
    "iso:country":"US",
    "sg:address":"3098 Mercedes Dr",
    "sg:city":"Green Bay",
    "sg:classifiers":[
        {
            "category":"Wholesale",
            "subcategory":"Machinery & Supplies",
            "type":"Manufacturing & Wholesale Goods"
        }
    ],
    "sg:phone":"+1 920 434 6435",
    "sg:postcode":"54313",
    "sg:province":"WI",
    "sg:tags":[
        "equipment",
        "industrial"
    ],
    "wof:name":"Ingersoll Cutting Tools",
    "wof:placetype":"venue"
},
  "geometry": {"coordinates":[-88.10317499999999,44.579106],"type":"Point"}
}