{
  "type": "Feature",
  "properties": {
    "iso:country":"US",
    "sg:address":"999 State Hwy 82",
    "sg:city":"Wisconsin Dells",
    "sg:classifiers":[
        {
            "category":"Bars & Pubs",
            "type":"Food & Drink"
        }
    ],
    "sg:phone":"+1 608 253 6888",
    "sg:postcode":"53965",
    "sg:province":"WI",
    "sg:tags":[
        "drinking"
    ],
    "wof:name":"Getaway Lodge",
    "wof:placetype":"venue"
},
  "geometry": {"coordinates":[-89.777434,43.774425],"type":"Point"}
}