{
  "type": "Feature",
  "properties": {
    "addr:full":"632 Adams St Fort Atkinson WI 53538",
    "addr:housenumber":"632",
    "addr:postcode":"53538",
    "addr:street":"Adams St",
    "iso:country":"US",
    "sg:address":"632 Adams St",
    "sg:city":"Fort Atkinson",
    "sg:classifiers":[
        {
            "category":"Professional",
            "subcategory":"Management & Consulting",
            "type":"Services"
        }
    ],
    "sg:phone":"+1 920 563 9471",
    "sg:postcode":"53538",
    "sg:province":"WI",
    "sg:tags":[
        "business"
    ],
    "wof:name":"Ldf Consulting",
    "wof:placetype":"venue"
},
  "geometry": {"coordinates":[-88.840536,42.936516],"type":"Point"}
}