{
  "type": "Feature",
  "properties": {
    "iso:country":"US",
    "sg:address":"10135 Rick Rd",
    "sg:city":"Wonewoc",
    "sg:classifiers":[
        {
            "category":"Professional",
            "type":"Services"
        }
    ],
    "sg:phone":"+1 608 464 7266",
    "sg:postcode":"53968",
    "sg:province":"WI",
    "wof:name":"Richard Rick",
    "wof:placetype":"venue"
},
  "geometry": {"coordinates":[-90.270996,43.653243],"type":"Point"}
}