{
  "type": "Feature",
  "properties": {
    "addr:full":"902 N River St Spooner WI 54801",
    "addr:housenumber":"902",
    "addr:postcode":"54801",
    "addr:street":"N River St",
    "iso:country":"US",
    "sg:address":"902 N River St",
    "sg:city":"Spooner",
    "sg:classifiers":[
        {
            "category":"Real Estate",
            "subcategory":"Real Estate Services",
            "type":"Services"
        }
    ],
    "sg:phone":"+1 715 635 3672",
    "sg:postcode":"54801",
    "sg:province":"WI",
    "wof:name":"Banana Abstract",
    "wof:placetype":"venue"
},
  "geometry": {"coordinates":[-91.884891,45.831452],"type":"Point"}
}