{
  "type": "Feature",
  "properties": {
    "iso:country":"US",
    "sg:address":"21480 Astolat Dr",
    "sg:city":"Brookfield",
    "sg:classifiers":[
        {
            "category":"Professional",
            "subcategory":"Business Services",
            "type":"Services"
        }
    ],
    "sg:phone":"+1 262 786 4634",
    "sg:postcode":"53045",
    "sg:province":"WI",
    "sg:tags":[
        "merchandising"
    ],
    "wof:name":"Wolfe Retail Svc Inc",
    "wof:placetype":"venue"
},
  "geometry": {"coordinates":[-88.179818,43.062452],"type":"Point"}
}