{
  "type": "Feature",
  "properties": {
    "iso:country":"US",
    "sg:address":"6506 W Warnimont Ave",
    "sg:city":"Milwaukee",
    "sg:classifiers":[
        {
            "category":"Education",
            "subcategory":"School",
            "type":"Public Place"
        }
    ],
    "sg:phone":"+1 414 604 7800",
    "sg:postcode":"53220",
    "sg:province":"WI",
    "sg:tags":[
        "middle"
    ],
    "wof:name":"Bell Middle School",
    "wof:placetype":"venue"
},
  "geometry": {"coordinates":[-87.994932,42.978884],"type":"Point"}
}