{
  "type": "Feature",
  "properties": {
    "iso:country":"US",
    "sg:address":"506 N Main St",
    "sg:city":"Lake Mills",
    "sg:classifiers":[
        {
            "category":"Shopping",
            "subcategory":"Computers & Home Electronics",
            "type":"Retail Goods"
        }
    ],
    "sg:phone":"+1 920 648 5408",
    "sg:postcode":"53551",
    "sg:province":"WI",
    "sg:tags":[
        "software"
    ],
    "sg:website":"www.stationerycentral.com",
    "wof:name":"STATIONERYCENTRAL.COM",
    "wof:placetype":"venue"
},
  "geometry": {"coordinates":[-88.90996699999999,43.084765],"type":"Point"}
}