{
  "type": "Feature",
  "properties": {
    "addr:full":"116 W Sumner St Hartford WI 53027",
    "addr:housenumber":"116",
    "addr:postcode":"53027",
    "addr:street":"W Sumner St",
    "iso:country":"US",
    "sg:address":"116 W Sumner St",
    "sg:city":"Hartford",
    "sg:classifiers":[
        {
            "category":"Banks & Credit Unions",
            "subcategory":"Bank",
            "type":"Services"
        }
    ],
    "sg:phone":"+1 262 673 5800",
    "sg:postcode":"53027",
    "sg:province":"WI",
    "sg:website":"www.fnb-hartford.com",
    "wof:name":"First National Bank",
    "wof:placetype":"venue"
},
  "geometry": {"coordinates":[-88.380414,43.317648],"type":"Point"}
}