{
  "type": "Feature",
  "properties": {
    "iso:country":"US",
    "sg:address":"565 Cemetery Ave",
    "sg:city":"Turtle Lake",
    "sg:classifiers":[
        {
            "category":"Recreation",
            "type":"Entertainment"
        }
    ],
    "sg:phone":"+1 715 986 2510",
    "sg:postcode":"54889",
    "sg:province":"WI",
    "sg:tags":[
        "hall",
        "auditorium"
    ],
    "wof:name":"Fire Hall",
    "wof:placetype":"venue"
},
  "geometry": {"coordinates":[-92.150971,45.388121],"type":"Point"}
}