{
  "type": "Feature",
  "properties": {
    "iso:country":"US",
    "sg:address":"1570 N Port Washington Rd",
    "sg:city":"Grafton",
    "sg:classifiers":[
        {
            "category":"Building & Trades",
            "subcategory":"Construction",
            "type":"Services"
        }
    ],
    "sg:phone":"+1 262 375 2021",
    "sg:postcode":"53024",
    "sg:province":"WI",
    "sg:tags":[
        "house"
    ],
    "wof:name":"Shell Homes Inc",
    "wof:placetype":"venue"
},
  "geometry": {"coordinates":[-87.925338,43.331414],"type":"Point"}
}