{
  "type": "Feature",
  "properties": {
    "addr:full":"3531 17th St Racine WI 53405",
    "addr:housenumber":"3531",
    "addr:postcode":"53405",
    "addr:street":"17Th St",
    "iso:country":"US",
    "sg:address":"3531 17th St",
    "sg:city":"Racine",
    "sg:classifiers":[
        {
            "category":"Restaurant",
            "type":"Food & Drink"
        }
    ],
    "sg:phone":"+1 262 551 7202",
    "sg:postcode":"53405",
    "sg:province":"WI",
    "sg:tags":[
        "eating"
    ],
    "wof:name":"Donnas Diner",
    "wof:placetype":"venue"
},
  "geometry": {"coordinates":[-87.821789,42.710272],"type":"Point"}
}