{
  "type": "Feature",
  "properties": {
    "iso:country":"US",
    "sg:address":"5729 Garden Cir",
    "sg:city":"Monona",
    "sg:classifiers":[
        {
            "category":"Social Services",
            "subcategory":"Child Care",
            "type":"Services"
        },
        {
            "category":"Social Services",
            "type":"Services"
        }
    ],
    "sg:phone":"+1 608 223 1410",
    "sg:postcode":"53716",
    "sg:province":"WI",
    "wof:name":"Jesye's Day Care",
    "wof:placetype":"venue"
},
  "geometry": {"coordinates":[-89.32706399999999,43.057184],"type":"Point"}
}