{
  "type": "Feature",
  "properties": {
    "iso:country":"US",
    "sg:address":"1221 la Grange Ave",
    "sg:city":"Tomah",
    "sg:classifiers":[
        {
            "category":"Organizations",
            "subcategory":"Religious Organization",
            "type":"Services"
        }
    ],
    "sg:phone":"+1 608 374 2444",
    "sg:postcode":"54660",
    "sg:province":"WI",
    "wof:name":"Good Shepherd Lutheran Church",
    "wof:placetype":"venue"
},
  "geometry": {"coordinates":[-90.41235399999999,44.053297],"type":"Point"}
}