{
  "type": "Feature",
  "properties": {
    "addr:full":"3224 Wright Ave Racine WI 53405",
    "addr:housenumber":"3224",
    "addr:postcode":"53405",
    "addr:street":"Wright Ave",
    "iso:country":"US",
    "sg:address":"3224 Wright Ave",
    "sg:city":"Racine",
    "sg:classifiers":[
        {
            "category":"Organizations",
            "subcategory":"Religious Organization",
            "type":"Services"
        }
    ],
    "sg:phone":"+1 262 633 9200",
    "sg:postcode":"53405",
    "sg:province":"WI",
    "wof:name":"Lakeview Church Of Christ",
    "wof:placetype":"venue"
},
  "geometry": {"coordinates":[-87.818302,42.715249],"type":"Point"}
}