{
  "type": "Feature",
  "properties": {
    "iso:country":"US",
    "sg:address":"9408 State Hwy 16",
    "sg:city":"Onalaska",
    "sg:classifiers":[
        {
            "category":"Shopping",
            "subcategory":"Hobbies, Toys, & Games",
            "type":"Retail Goods"
        }
    ],
    "sg:phone":"+1 608 779 5087",
    "sg:postcode":"54650",
    "sg:province":"WI",
    "sg:tags":[
        "craft",
        "supply"
    ],
    "sg:website":"www.hobbylobby.com",
    "wof:name":"Hobby Lobby Creative Center",
    "wof:placetype":"venue"
},
  "geometry": {"coordinates":[-91.194653,43.871431],"type":"Point"}
}