{
  "type": "Feature",
  "properties": {
    "addr:full":"1050 Legion Dr Elm Grove WI 53122",
    "addr:housenumber":"1050",
    "addr:postcode":"53122",
    "addr:street":"Legion Dr",
    "iso:country":"US",
    "sg:address":"1050 Legion Dr",
    "sg:city":"Elm Grove",
    "sg:classifiers":[
        {
            "category":"Personal",
            "subcategory":"Beauty Salon",
            "type":"Services"
        }
    ],
    "sg:phone":"+1 262 827 9600",
    "sg:postcode":"53122",
    "sg:province":"WI",
    "wof:name":"Henry Steven's Salon LTD",
    "wof:placetype":"venue"
},
  "geometry": {"coordinates":[-88.08018,43.044969],"type":"Point"}
}