{
  "type": "Feature",
  "properties": {
    "iso:country":"US",
    "sg:address":"4951 Baldwin Rd",
    "sg:city":"Manawa",
    "sg:classifiers":[
        {
            "category":"Manufacturing",
            "subcategory":"Metals",
            "type":"Manufacturing & Wholesale Goods"
        }
    ],
    "sg:phone":"+1 920 596 2237",
    "sg:postcode":"54949",
    "sg:province":"WI",
    "sg:tags":[
        "fabrication",
        "structural"
    ],
    "wof:name":"Abrahamson Body & Eqp Svc",
    "wof:placetype":"venue"
},
  "geometry": {"coordinates":[-88.94748199999999,44.415046],"type":"Point"}
}