{
  "type": "Feature",
  "properties": {
    "iso:country":"US",
    "sg:address":"2873 N 39th St",
    "sg:city":"Milwaukee",
    "sg:classifiers":[
        {
            "category":"Social Services",
            "subcategory":"Child Care",
            "type":"Services"
        }
    ],
    "sg:phone":"+1 414 444 5648",
    "sg:postcode":"53210",
    "sg:province":"WI",
    "wof:name":"Anita's Daycare",
    "wof:placetype":"venue"
},
  "geometry": {"coordinates":[-87.962231,43.070204],"type":"Point"}
}