{
  "type": "Feature",
  "properties": {
    "iso:country":"US",
    "sg:address":"451 E Grand Ave",
    "sg:city":"Wisconsin Rapids",
    "sg:classifiers":[
        {
            "category":"Restaurant",
            "type":"Food & Drink"
        }
    ],
    "sg:phone":"+1 715 422 7000",
    "sg:postcode":"54494",
    "sg:province":"WI",
    "sg:tags":[
        "eating"
    ],
    "wof:name":"Cafe Mulino",
    "wof:placetype":"venue"
},
  "geometry": {"coordinates":[-89.822375,44.389369],"type":"Point"}
}