{
  "type": "Feature",
  "properties": {
    "iso:country":"US",
    "sg:address":"2207 N Farwell Ave",
    "sg:city":"Milwaukee",
    "sg:classifiers":[
        {
            "category":"Manufacturing",
            "subcategory":"Jewelry",
            "type":"Manufacturing & Wholesale Goods"
        },
        {
            "category":"Shopping",
            "subcategory":"Jewelry",
            "type":"Retail Goods"
        }
    ],
    "sg:phone":"+1 414 270 0157",
    "sg:postcode":"53202",
    "sg:province":"WI",
    "sg:tags":[
        "precious",
        "designer",
        "metal",
        "mfg"
    ],
    "wof:name":"Artist's Friends",
    "wof:placetype":"venue"
},
  "geometry": {"coordinates":[-87.88560200000001,43.060105],"type":"Point"}
}