{
  "type": "Feature",
  "properties": {
    "addr:full":"3518 86th St Kenosha WI 53142",
    "addr:housenumber":"3518",
    "addr:postcode":"53142",
    "addr:street":"86Th St",
    "iso:country":"US",
    "sg:address":"3518 86th St",
    "sg:city":"Kenosha",
    "sg:classifiers":[
        {
            "category":"Real Estate",
            "subcategory":"Real Estate Agent",
            "type":"Services"
        }
    ],
    "sg:phone":"+1 262 697 6190",
    "sg:postcode":"53142",
    "sg:province":"WI",
    "sg:tags":[
        "inspection"
    ],
    "wof:name":"Inspect Your Home Inc",
    "wof:placetype":"venue"
},
  "geometry": {"coordinates":[-87.849058,42.549444],"type":"Point"}
}