{
  "type": "Feature",
  "properties": {
    "iso:country":"US",
    "sg:address":"124 2nd St",
    "sg:city":"Baraboo",
    "sg:classifiers":[
        {
            "category":"Government",
            "subcategory":"Office",
            "type":"Public Place"
        }
    ],
    "sg:phone":"+1 608 356 3326",
    "sg:postcode":"53913",
    "sg:province":"WI",
    "sg:tags":[
        "state",
        "program"
    ],
    "wof:name":"Transportation Dept",
    "wof:placetype":"venue"
},
  "geometry": {"coordinates":[-89.742198,43.468868],"type":"Point"}
}