{
  "type": "Feature",
  "properties": {
    "iso:country":"US",
    "sg:address":"202 Main St",
    "sg:city":"Oconto",
    "sg:classifiers":[
        {
            "category":"Shopping",
            "subcategory":"Bicycles & Sporting Goods",
            "type":"Retail Goods"
        }
    ],
    "sg:phone":"+1 920 834 4910",
    "sg:postcode":"54153",
    "sg:province":"WI",
    "wof:name":"Willow Bay Sporting Goods",
    "wof:placetype":"venue"
},
  "geometry": {"coordinates":[-87.884197,44.893046],"type":"Point"}
}