{
  "type": "Feature",
  "properties": {
    "iso:country":"US",
    "sg:address":"5900 N Port Washington Rd",
    "sg:city":"Milwaukee",
    "sg:classifiers":[
        {
            "category":"Government",
            "subcategory":"Office",
            "type":"Public Place"
        }
    ],
    "sg:phone":"+1 414 527 1800",
    "sg:postcode":"53217",
    "sg:province":"WI",
    "sg:tags":[
        "state",
        "program",
        "health"
    ],
    "wof:name":"Covenant Behavioral Health",
    "wof:placetype":"venue"
},
  "geometry": {"coordinates":[-87.91653100000001,43.118908],"type":"Point"}
}