{
  "type": "Feature",
  "properties": {
    "iso:country":"US",
    "sg:address":"670 Glover Rd",
    "sg:city":"River Falls",
    "sg:classifiers":[
        {
            "category":"Professional",
            "type":"Services"
        }
    ],
    "sg:phone":"+1 715 426 3507",
    "sg:postcode":"54022",
    "sg:province":"WI",
    "wof:name":"Wisdot D T D 6",
    "wof:placetype":"venue"
},
  "geometry": {"coordinates":[-92.66649700000001,44.913019],"type":"Point"}
}