{
  "type": "Feature",
  "properties": {
    "iso:country":"US",
    "sg:address":"1318 N 122nd St",
    "sg:city":"Milwaukee",
    "sg:classifiers":[
        {
            "category":"Autos & Motor Vehicles",
            "subcategory":"Auto Supplies",
            "type":"Retail Goods"
        },
        {
            "category":"Wholesale",
            "subcategory":"Auto Parts",
            "type":"Manufacturing & Wholesale Goods"
        }
    ],
    "sg:phone":"+1 414 771 4790",
    "sg:postcode":"53226",
    "sg:province":"WI",
    "sg:tags":[
        "wheel",
        "vehicles-supplies",
        "drive",
        "four",
        "equipment",
        "truck"
    ],
    "wof:name":"Tectran",
    "wof:placetype":"venue"
},
  "geometry": {"coordinates":[-88.06446800000001,43.047396],"type":"Point"}
}