{
  "type": "Feature",
  "properties": {
    "iso:country":"US",
    "sg:address":"376 Lakken Rd",
    "sg:city":"Sarona",
    "sg:classifiers":[
        {
            "category":"Travel",
            "subcategory":"Hotels & Motels",
            "type":"Entertainment"
        }
    ],
    "sg:phone":"+1 715 354 3515",
    "sg:postcode":"54870",
    "sg:province":"WI",
    "sg:tags":[
        "resort"
    ],
    "wof:name":"Spring Waters Inn & Resort",
    "wof:placetype":"venue"
},
  "geometry": {"coordinates":[-91.72349800000001,45.643122],"type":"Point"}
}