{
  "type": "Feature",
  "properties": {
    "iso:country":"US",
    "sg:address":"5909 N Milwaukee River Pkwy",
    "sg:city":"Milwaukee",
    "sg:classifiers":[
        {
            "category":"Government",
            "subcategory":"Office",
            "type":"Public Place"
        }
    ],
    "sg:phone":"+1 414 228 1710",
    "sg:postcode":"53209",
    "sg:province":"WI",
    "sg:tags":[
        "village"
    ],
    "wof:name":"Building Inspection Dept",
    "wof:placetype":"venue"
},
  "geometry": {"coordinates":[-87.927362,43.122888],"type":"Point"}
}