{
  "type": "Feature",
  "properties": {
    "addr:full":"2627 Eastern Ave Plymouth WI 53073",
    "addr:housenumber":"2627",
    "addr:postcode":"53073",
    "addr:street":"Eastern Ave",
    "iso:country":"US",
    "sg:address":"2627 Eastern Ave",
    "sg:city":"Plymouth",
    "sg:classifiers":[
        {
            "category":"Shopping",
            "subcategory":"Clothing, Apparel, & Fashions",
            "type":"Retail Goods"
        }
    ],
    "sg:phone":"+1 920 892 6062",
    "sg:postcode":"53073",
    "sg:province":"WI",
    "wof:name":"Fashion Bug",
    "wof:placetype":"venue"
},
  "geometry": {"coordinates":[-87.950422,43.747044],"type":"Point"}
}