{
  "type": "Feature",
  "properties": {
    "iso:country":"US",
    "sg:address":"2104 Valley Rd",
    "sg:city":"La Crosse",
    "sg:classifiers":[
        {
            "category":"Professional",
            "type":"Services"
        }
    ],
    "sg:phone":"+1 608 788 7432",
    "sg:postcode":"54601",
    "sg:province":"WI",
    "wof:name":"Wiltay LLC",
    "wof:placetype":"venue"
},
  "geometry": {"coordinates":[-91.194301,43.79899],"type":"Point"}
}