{
  "type": "Feature",
  "properties": {
    "iso:country":"US",
    "sg:address":"338 E Park Ave",
    "sg:city":"Chippewa Falls",
    "sg:classifiers":[
        {
            "category":"Manufacturing",
            "subcategory":"Wood Products",
            "type":"Manufacturing & Wholesale Goods"
        }
    ],
    "sg:phone":"+1 715 726 2220",
    "sg:postcode":"54729",
    "sg:province":"WI",
    "sg:tags":[
        "mfg"
    ],
    "wof:name":"Elm Grove Woodworks",
    "wof:placetype":"venue"
},
  "geometry": {"coordinates":[-91.387868,44.925939],"type":"Point"}
}