{
  "type": "Feature",
  "properties": {
    "addr:full":"3700 Durand Ave Racine WI 53405",
    "addr:housenumber":"3700",
    "addr:postcode":"53405",
    "addr:street":"Durand Ave",
    "iso:country":"US",
    "sg:address":"3700 Durand Ave",
    "sg:city":"Racine",
    "sg:classifiers":[
        {
            "category":"Banks & Credit Unions",
            "subcategory":"Bank",
            "type":"Services"
        }
    ],
    "sg:phone":"+1 262 637 1354",
    "sg:postcode":"53405",
    "sg:province":"WI",
    "sg:tags":[
        "depository",
        "banking"
    ],
    "wof:name":"Cash Advance of Wisconsin Inc",
    "wof:placetype":"venue"
},
  "geometry": {"coordinates":[-87.82463799999999,42.696867],"type":"Point"}
}