{
  "type": "Feature",
  "properties": {
    "iso:country":"US",
    "sg:address":"210 Gould St",
    "sg:city":"Beaver Dam",
    "sg:classifiers":[
        {
            "category":"Education",
            "subcategory":"School",
            "type":"Public Place"
        }
    ],
    "sg:phone":"+1 920 885 7396",
    "sg:postcode":"53916",
    "sg:province":"WI",
    "wof:name":"Lincoln Elementary School",
    "wof:placetype":"venue"
},
  "geometry": {"coordinates":[-88.82458,43.461395],"type":"Point"}
}