{
  "type": "Feature",
  "properties": {
    "iso:country":"US",
    "sg:address":"941 Perkins Ave",
    "sg:city":"Waukesha",
    "sg:classifiers":[
        {
            "category":"Shopping",
            "subcategory":"Discount & Variety Stores",
            "type":"Retail Goods"
        }
    ],
    "sg:phone":"+1 262 560 9420",
    "sg:postcode":"53186",
    "sg:province":"WI",
    "wof:name":"Katlynn's Dollar Palace",
    "wof:placetype":"venue"
},
  "geometry": {"coordinates":[-88.212726,43.014874],"type":"Point"}
}