{
  "type": "Feature",
  "properties": {
    "iso:country":"US",
    "sg:address":"109 Grove St",
    "sg:city":"Beaver Dam",
    "sg:classifiers":[
        {
            "category":"Building & Trades",
            "subcategory":"Electrical",
            "type":"Services"
        }
    ],
    "sg:phone":"+1 920 887 8391",
    "sg:postcode":"53916",
    "sg:province":"WI",
    "sg:tags":[
        "electrical",
        "contractor"
    ],
    "wof:name":"Quality Electric",
    "wof:placetype":"venue"
},
  "geometry": {"coordinates":[-88.837771,43.461716],"type":"Point"}
}