{
  "type": "Feature",
  "properties": {
    "addr:full":"3945 Lone Elm Dr Brookfield WI 53005",
    "addr:housenumber":"3945",
    "addr:postcode":"53005",
    "addr:street":"Lone Elm Dr",
    "iso:country":"US",
    "sg:address":"3945 Lone Elm Dr",
    "sg:city":"Brookfield",
    "sg:classifiers":[
        {
            "category":"Education",
            "subcategory":"School",
            "type":"Public Place"
        }
    ],
    "sg:phone":"+1 262 790 8804",
    "sg:postcode":"53005",
    "sg:province":"WI",
    "wof:name":"Nml Agent Jeffrey Reibow",
    "wof:placetype":"venue"
},
  "geometry": {"coordinates":[-88.11164599999999,43.087383],"type":"Point"}
}