{
  "type": "Feature",
  "properties": {
    "iso:country":"US",
    "sg:address":"1823 Grove St",
    "sg:city":"Oshkosh",
    "sg:classifiers":[
        {
            "category":"Sports & Exercise",
            "subcategory":"Bowling",
            "type":"Entertainment"
        }
    ],
    "sg:phone":"+1 920 235 4640",
    "sg:postcode":"54901",
    "sg:province":"WI",
    "sg:tags":[
        "tavern",
        "center",
        "alley"
    ],
    "wof:name":"Shore View Bowling Lanes",
    "wof:placetype":"venue"
},
  "geometry": {"coordinates":[-88.52522999999999,44.042828],"type":"Point"}
}