{
  "type": "Feature",
  "properties": {
    "addr:full":"3650 S Wollmer Rd Milwaukee WI 53228",
    "addr:housenumber":"3650",
    "addr:postcode":"53228",
    "addr:street":"S Wollmer Rd",
    "iso:country":"US",
    "sg:address":"3650 S Wollmer Rd",
    "sg:city":"Milwaukee",
    "sg:classifiers":[
        {
            "category":"Professional",
            "subcategory":"Business Services",
            "type":"Services"
        }
    ],
    "sg:phone":"+1 414 541 4755",
    "sg:postcode":"53228",
    "sg:province":"WI",
    "sg:tags":[
        "hair",
        "salon"
    ],
    "wof:name":"New Creations Hair Studio",
    "wof:placetype":"venue"
},
  "geometry": {"coordinates":[-88.045435,42.977684],"type":"Point"}
}