{
  "type": "Feature",
  "properties": {
    "iso:country":"US",
    "sg:address":"5529 Ray Wood Ter",
    "sg:city":"Fond Du Lac",
    "sg:classifiers":[
        {
            "category":"Insurance",
            "subcategory":"Insurance Agent",
            "type":"Services"
        }
    ],
    "sg:phone":"+1 920 923 0068",
    "sg:postcode":"54937",
    "sg:province":"WI",
    "wof:name":"Baccus Insurance Service",
    "wof:placetype":"venue"
},
  "geometry": {"coordinates":[-88.483092,43.742044],"type":"Point"}
}