{
  "type": "Feature",
  "properties": {
    "iso:country":"US",
    "sg:address":"511 N Spring St",
    "sg:city":"Sparta",
    "sg:classifiers":[
        {
            "category":"Professional",
            "subcategory":"Business Services",
            "type":"Services"
        }
    ],
    "sg:phone":"+1 608 269 3321",
    "sg:postcode":"54656",
    "sg:province":"WI",
    "sg:tags":[
        "interior",
        "design"
    ],
    "wof:name":"Mary Armbruster Associates",
    "wof:placetype":"venue"
},
  "geometry": {"coordinates":[-90.809326,43.949311],"type":"Point"}
}