{
  "type": "Feature",
  "properties": {
    "addr:full":"1691 State Hwy 49 Wittenberg WI 54499",
    "addr:housenumber":"1691",
    "addr:postcode":"54499",
    "addr:street":"State Hwy 49",
    "iso:country":"US",
    "sg:address":"1691 State Hwy 49",
    "sg:city":"Wittenberg",
    "sg:classifiers":[
        {
            "category":"Wholesale",
            "subcategory":"Fruits & Vegetables",
            "type":"Manufacturing & Wholesale Goods"
        }
    ],
    "sg:phone":"+1 715 677 4793",
    "sg:postcode":"54499",
    "sg:province":"WI",
    "wof:name":"Liberty Packing Inc",
    "wof:placetype":"venue"
},
  "geometry": {"coordinates":[-89.26434500000001,44.710516],"type":"Point"}
}