{
  "type": "Feature",
  "properties": {
    "iso:country":"US",
    "sg:address":"2401 S Oneida St",
    "sg:city":"Green Bay",
    "sg:classifiers":[
        {
            "category":"Shopping",
            "subcategory":"Music",
            "type":"Retail Goods"
        }
    ],
    "sg:phone":"+1 920 499 0570",
    "sg:postcode":"54304",
    "sg:province":"WI",
    "sg:tags":[
        "compact",
        "record",
        "disc",
        "tape"
    ],
    "wof:name":"Sam Goody",
    "wof:placetype":"venue"
},
  "geometry": {"coordinates":[-88.067645,44.485974],"type":"Point"}
}