{
  "type": "Feature",
  "properties": {
    "iso:country":"US",
    "sg:address":"1520 Conservation Rd",
    "sg:city":"Brillion",
    "sg:classifiers":[
        {
            "category":"Farming",
            "subcategory":"Dairy Farm",
            "type":"Manufacturing & Wholesale Goods"
        }
    ],
    "sg:phone":"+1 920 756 2367",
    "sg:postcode":"54110",
    "sg:province":"WI",
    "wof:name":"Wayne Maile",
    "wof:placetype":"venue"
},
  "geometry": {"coordinates":[-88.114502,44.178147],"type":"Point"}
}