{
  "type": "Feature",
  "properties": {
    "iso:country":"US",
    "sg:address":"581 224th Ave",
    "sg:city":"Kansasville",
    "sg:classifiers":[
        {
            "category":"Farming",
            "subcategory":"Farm",
            "type":"Manufacturing & Wholesale Goods"
        }
    ],
    "sg:phone":"+1 262 878 1480",
    "sg:postcode":"53139",
    "sg:province":"WI",
    "sg:tags":[
        "crop",
        "general"
    ],
    "wof:name":"Bart Ament",
    "wof:placetype":"venue"
},
  "geometry": {"coordinates":[-88.080742,42.669437],"type":"Point"}
}