{
  "type": "Feature",
  "properties": {
    "iso:country":"US",
    "sg:address":"3919 6th Ave",
    "sg:city":"Kenosha",
    "sg:classifiers":[
        {
            "category":"Professional",
            "subcategory":"Computer Services",
            "type":"Services"
        }
    ],
    "sg:phone":"+1 262 909 7264",
    "sg:postcode":"53140",
    "sg:province":"WI",
    "sg:tags":[
        "repair"
    ],
    "wof:name":"Computer Doctor",
    "wof:placetype":"venue"
},
  "geometry": {"coordinates":[-87.81918400000001,42.600884],"type":"Point"}
}