{
  "type": "Feature",
  "properties": {
    "iso:country":"US",
    "sg:address":"11104 N Port Washington Rd",
    "sg:city":"Mequon",
    "sg:classifiers":[
        {
            "category":"Food & Beverages",
            "subcategory":"Specialty",
            "type":"Retail Goods"
        }
    ],
    "sg:phone":"+1 262 240 0213",
    "sg:postcode":"53092",
    "sg:province":"WI",
    "sg:tags":[
        "tea",
        "coffee"
    ],
    "wof:name":"Caribou Coffee Co",
    "wof:placetype":"venue"
},
  "geometry": {"coordinates":[-87.923891,43.218227],"type":"Point"}
}