{
  "type": "Feature",
  "properties": {
    "iso:country":"US",
    "sg:address":"2671 Libal St",
    "sg:city":"Green Bay",
    "sg:classifiers":[
        {
            "category":"Shopping",
            "subcategory":"Used Merchandise",
            "type":"Retail Goods"
        }
    ],
    "sg:phone":"+1 920 437 0789",
    "sg:postcode":"54301",
    "sg:province":"WI",
    "sg:tags":[
        "furniture"
    ],
    "wof:name":"Frugal Classics",
    "wof:placetype":"venue"
},
  "geometry": {"coordinates":[-88.021726,44.469742],"type":"Point"}
}