{
  "type": "Feature",
  "properties": {
    "addr:full":"3035 Aspen Ter Danbury WI 54830",
    "addr:housenumber":"3035",
    "addr:postcode":"54830",
    "addr:street":"Aspen Ter",
    "iso:country":"US",
    "sg:address":"3035 Aspen Ter",
    "sg:city":"Danbury",
    "sg:classifiers":[
        {
            "category":"Manufacturing",
            "subcategory":"Jewelry",
            "type":"Manufacturing & Wholesale Goods"
        }
    ],
    "sg:phone":"+1 715 259 3632",
    "sg:postcode":"54830",
    "sg:province":"WI",
    "wof:name":"Sandbay Jewelry",
    "wof:placetype":"venue"
},
  "geometry": {"coordinates":[-92.137469,45.970276],"type":"Point"}
}