{
  "type": "Feature",
  "properties": {
    "iso:country":"US",
    "sg:address":"8772 Porcupine Ln",
    "sg:city":"Arkansaw",
    "sg:classifiers":[
        {
            "category":"Farming",
            "subcategory":"Livestock Farm",
            "type":"Manufacturing & Wholesale Goods"
        }
    ],
    "sg:phone":"+1 715 285 5648",
    "sg:postcode":"54721",
    "sg:province":"WI",
    "sg:tags":[
        "corn",
        "beef",
        "feedlot",
        "cattle"
    ],
    "wof:name":"Trent Gates",
    "wof:placetype":"venue"
},
  "geometry": {"coordinates":[-92.093504,44.57579],"type":"Point"}
}