{
  "type": "Feature",
  "properties": {
    "addr:full":"844 E Silver Spring Dr Milwaukee WI 53217",
    "addr:housenumber":"844",
    "addr:postcode":"53217",
    "addr:street":"E Silver Spring Dr",
    "iso:country":"US",
    "sg:address":"844 E Silver Spring Dr",
    "sg:city":"Milwaukee",
    "sg:classifiers":[
        {
            "category":"Social Services",
            "subcategory":"Child Care",
            "type":"Services"
        }
    ],
    "sg:phone":"+1 414 906 9720",
    "sg:postcode":"53217",
    "sg:province":"WI",
    "sg:tags":[
        "day"
    ],
    "wof:name":"Winnies Wndrland Fmly Day Care",
    "wof:placetype":"venue"
},
  "geometry": {"coordinates":[-87.89928999999999,43.118488],"type":"Point"}
}