{
  "type": "Feature",
  "properties": {
    "iso:country":"US",
    "sg:address":"2361 W Birchwood Ave",
    "sg:city":"Milwaukee",
    "sg:classifiers":[
        {
            "category":"Restaurant",
            "type":"Food & Drink"
        }
    ],
    "sg:phone":"+1 414 282 9466",
    "sg:postcode":"53221",
    "sg:province":"WI",
    "sg:tags":[
        "eating"
    ],
    "wof:name":"Travlin Jo LLC",
    "wof:placetype":"venue"
},
  "geometry": {"coordinates":[-87.945141,42.939744],"type":"Point"}
}