{
  "type": "Feature",
  "properties": {
    "addr:full":"803 Hyland Ave Kaukauna WI 54130",
    "addr:housenumber":"803",
    "addr:postcode":"54130",
    "addr:street":"Hyland Ave",
    "iso:country":"US",
    "sg:address":"803 Hyland Ave",
    "sg:city":"Kaukauna",
    "sg:classifiers":[
        {
            "category":"Autos & Motor Vehicles",
            "subcategory":"Automobile Sales",
            "type":"Retail Goods"
        }
    ],
    "sg:phone":"+1 920 766 1599",
    "sg:postcode":"54130",
    "sg:province":"WI",
    "sg:tags":[
        "used"
    ],
    "wof:name":"Smokeys Auto Sales & Detailing",
    "wof:placetype":"venue"
},
  "geometry": {"coordinates":[-88.27090200000001,44.289835],"type":"Point"}
}