{
  "type": "Feature",
  "properties": {
    "iso:country":"US",
    "sg:address":"714 W Hamilton Ave",
    "sg:city":"Eau Claire",
    "sg:classifiers":[
        {
            "category":"Health Services",
            "subcategory":"Doctor",
            "type":"Services"
        }
    ],
    "sg:phone":"+1 715 830 9990",
    "sg:postcode":"54701",
    "sg:province":"WI",
    "sg:tags":[
        "medicine",
        "internal",
        "pediatrics"
    ],
    "wof:name":"Higgins Janet MD",
    "wof:placetype":"venue"
},
  "geometry": {"coordinates":[-91.507491,44.785746],"type":"Point"}
}