{
  "type": "Feature",
  "properties": {
    "iso:country":"US",
    "sg:address":"502 N Lawn Ave",
    "sg:city":"Madison",
    "sg:classifiers":[
        {
            "category":"Real Estate",
            "subcategory":"Real Estate Agent",
            "type":"Services"
        }
    ],
    "sg:phone":"+1 608 442 0006",
    "sg:postcode":"53704",
    "sg:province":"WI",
    "sg:tags":[
        "consultant"
    ],
    "wof:name":"Perry Holland Group",
    "wof:placetype":"venue"
},
  "geometry": {"coordinates":[-89.345433,43.106768],"type":"Point"}
}