{
  "type": "Feature",
  "properties": {
    "iso:country":"US",
    "sg:address":"1001 Countryside Dr",
    "sg:city":"De Pere",
    "sg:classifiers":[
        {
            "category":"Building & Trades",
            "subcategory":"Cleaning & Sanitation",
            "type":"Services"
        }
    ],
    "sg:phone":"+1 920 336 8750",
    "sg:postcode":"54115",
    "sg:province":"WI",
    "sg:tags":[
        "maintenance"
    ],
    "wof:name":"Cleaner Solutions",
    "wof:placetype":"venue"
},
  "geometry": {"coordinates":[-88.086283,44.431546],"type":"Point"}
}