{
  "type": "Feature",
  "properties": {
    "iso:country":"US",
    "sg:address":"410 N River St",
    "sg:city":"Spooner",
    "sg:classifiers":[
        {
            "category":"Professional",
            "subcategory":"Employment Agencies",
            "type":"Services"
        }
    ],
    "sg:phone":"+1 715 635 4361",
    "sg:postcode":"54801",
    "sg:province":"WI",
    "wof:name":"Specialty Nurses Inc",
    "wof:placetype":"venue"
},
  "geometry": {"coordinates":[-91.88851099999999,45.826086],"type":"Point"}
}