{
  "type": "Feature",
  "properties": {
    "iso:country":"US",
    "sg:address":"6443 906th St",
    "sg:city":"Elk Mound",
    "sg:classifiers":[
        {
            "category":"Building & Trades",
            "subcategory":"Construction",
            "type":"Services"
        }
    ],
    "sg:phone":"+1 715 879 5766",
    "sg:postcode":"54739",
    "sg:province":"WI",
    "sg:tags":[
        "house",
        "residential"
    ],
    "wof:name":"Varpness Farm",
    "wof:placetype":"venue"
},
  "geometry": {"coordinates":[-91.722786,44.923595],"type":"Point"}
}