{
  "type": "Feature",
  "properties": {
    "addr:full":"2801 Crossroads Dr Madison WI 53718",
    "addr:housenumber":"2801",
    "addr:postcode":"53718",
    "addr:street":"Crossroads Dr",
    "iso:country":"US",
    "sg:address":"2801 Crossroads Dr",
    "sg:city":"Madison",
    "sg:classifiers":[
        {
            "category":"Wholesale",
            "subcategory":"Non-durable Goods",
            "type":"Manufacturing & Wholesale Goods"
        }
    ],
    "sg:phone":"+1 608 241 9887",
    "sg:postcode":"53718",
    "sg:province":"WI",
    "sg:tags":[
        "advertising",
        "merchandise",
        "promotional"
    ],
    "sg:website":"www.cms-4you.com",
    "wof:name":"Creative Marketing Specialists",
    "wof:placetype":"venue"
},
  "geometry": {"coordinates":[-89.29024699999999,43.13436],"type":"Point"}
}