{
  "type": "Feature",
  "properties": {
    "addr:full":"4415 Valley Ct Rhinelander WI 54501",
    "addr:housenumber":"4415",
    "addr:postcode":"54501",
    "addr:street":"Valley Ct",
    "iso:country":"US",
    "sg:address":"4415 Valley Ct",
    "sg:city":"Rhinelander",
    "sg:classifiers":[
        {
            "category":"Real Estate",
            "subcategory":"Real Estate Agent",
            "type":"Services"
        }
    ],
    "sg:phone":"+1 715 362 1789",
    "sg:postcode":"54501",
    "sg:province":"WI",
    "wof:name":"Progressive Property Inc",
    "wof:placetype":"venue"
},
  "geometry": {"coordinates":[-89.459997,45.677181],"type":"Point"}
}