{
  "type": "Feature",
  "properties": {
    "addr:full":"9913 Co Rd B B Marshfield WI 54449",
    "addr:housenumber":"9913;b",
    "addr:postcode":"54449",
    "addr:street":"Co Rd",
    "iso:country":"US",
    "sg:address":"9913 Co Rd B B",
    "sg:city":"Marshfield",
    "sg:classifiers":[
        {
            "category":"Retail",
            "subcategory":"Repair Shop",
            "type":"Services"
        }
    ],
    "sg:phone":"+1 715 387 8714",
    "sg:postcode":"54449",
    "sg:province":"WI",
    "wof:name":"Northern Lights Taxidermy",
    "wof:placetype":"venue"
},
  "geometry": {"coordinates":[-90.206678,44.627142],"type":"Point"}
}