{
  "type": "Feature",
  "properties": {
    "iso:country":"US",
    "sg:address":"2857 Fish Hatchery Rd",
    "sg:city":"Madison",
    "sg:classifiers":[
        {
            "category":"Retail",
            "subcategory":"Car Wash",
            "type":"Services"
        }
    ],
    "sg:phone":"+1 608 274 2012",
    "sg:postcode":"53713",
    "sg:province":"WI",
    "sg:tags":[
        "carwash"
    ],
    "wof:name":"Wonder Wash Management Inc",
    "wof:placetype":"venue"
},
  "geometry": {"coordinates":[-89.409554,43.030766],"type":"Point"}
}