{
  "type": "Feature",
  "properties": {
    "iso:country":"US",
    "sg:address":"427 E Main St",
    "sg:city":"Hortonville",
    "sg:classifiers":[
        {
            "category":"Manufacturing",
            "subcategory":"Printing",
            "type":"Manufacturing & Wholesale Goods"
        }
    ],
    "sg:phone":"+1 920 779 4380",
    "sg:postcode":"54944",
    "sg:province":"WI",
    "sg:tags":[
        "commercial",
        "lithographic"
    ],
    "wof:name":"Schillings Qulty Prtg & Design",
    "wof:placetype":"venue"
},
  "geometry": {"coordinates":[-88.622399,44.335076],"type":"Point"}
}