{
  "type": "Feature",
  "properties": {
    "iso:country":"US",
    "sg:address":"303 Golf View Dr",
    "sg:city":"Mount Horeb",
    "sg:classifiers":[
        {
            "category":"Insurance",
            "subcategory":"Hazard Insurance",
            "type":"Services"
        }
    ],
    "sg:phone":"+1 608 437 3664",
    "sg:postcode":"53572",
    "sg:province":"WI",
    "sg:tags":[
        "carrier"
    ],
    "wof:name":"David Becker",
    "wof:placetype":"venue"
},
  "geometry": {"coordinates":[-89.72077899999999,43.003998],"type":"Point"}
}