{
  "type": "Feature",
  "properties": {
    "iso:country":"US",
    "sg:address":"1626 Fond du Lac Ave",
    "sg:city":"Kewaskum",
    "sg:classifiers":[
        {
            "category":"Farming",
            "subcategory":"Dairy Farm",
            "type":"Manufacturing & Wholesale Goods"
        }
    ],
    "sg:phone":"+1 262 626 8008",
    "sg:postcode":"53040",
    "sg:province":"WI",
    "wof:name":"Family Dairies USA",
    "wof:placetype":"venue"
},
  "geometry": {"coordinates":[-88.23157,43.524848],"type":"Point"}
}