{
  "type": "Feature",
  "properties": {
    "iso:country":"US",
    "sg:address":"1440 Horicon St",
    "sg:city":"Mayville",
    "sg:classifiers":[
        {
            "category":"Shopping",
            "subcategory":"Gifts & Souvenirs",
            "type":"Retail Goods"
        }
    ],
    "sg:phone":"+1 920 387 3738",
    "sg:postcode":"53050",
    "sg:province":"WI",
    "sg:tags":[
        "balloon",
        "artist"
    ],
    "wof:name":"Village Flower Shoppe",
    "wof:placetype":"venue"
},
  "geometry": {"coordinates":[-88.563143,43.494579],"type":"Point"}
}