{
  "type": "Feature",
  "properties": {
    "iso:country":"US",
    "sg:address":"4380 Ridge Rd",
    "sg:city":"Neillsville",
    "sg:classifiers":[
        {
            "category":"Farming",
            "subcategory":"Farm",
            "type":"Manufacturing & Wholesale Goods"
        }
    ],
    "sg:phone":"+1 715 743 6795",
    "sg:postcode":"54456",
    "sg:province":"WI",
    "sg:tags":[
        "crop",
        "general"
    ],
    "wof:name":"Boulder Ridge Farms",
    "wof:placetype":"venue"
},
  "geometry": {"coordinates":[-90.53132100000001,44.560046],"type":"Point"}
}