{
  "type": "Feature",
  "properties": {
    "addr:full":"16853 S 1st St Galesville WI 54630",
    "addr:housenumber":"16853",
    "addr:postcode":"54630",
    "addr:street":"S 1St St",
    "iso:country":"US",
    "sg:address":"16853 S 1st St",
    "sg:city":"Galesville",
    "sg:classifiers":[
        {
            "category":"Health Services",
            "subcategory":"Chiropractor",
            "type":"Services"
        }
    ],
    "sg:phone":"+1 608 582 2225",
    "sg:postcode":"54630",
    "sg:province":"WI",
    "sg:tags":[
        "chiropractic"
    ],
    "sg:website":"http://www.bronstonchiropractic.com",
    "wof:name":"Bronston Chiropractic",
    "wof:placetype":"venue"
},
  "geometry": {"coordinates":[-91.35025,44.082259],"type":"Point"}
}