{
  "type": "Feature",
  "properties": {
    "iso:country":"US",
    "sg:address":"6352 N 84th St Apt 8",
    "sg:city":"Milwaukee",
    "sg:classifiers":[
        {
            "category":"Retail",
            "subcategory":"Funeral Services",
            "type":"Services"
        }
    ],
    "sg:phone":"+1 414 446 5582",
    "sg:postcode":"53225",
    "sg:province":"WI",
    "sg:tags":[
        "burial",
        "vault"
    ],
    "wof:name":"Silk Vault Publishing",
    "wof:placetype":"venue"
},
  "geometry": {"coordinates":[-88.015574,43.13322],"type":"Point"}
}