{
  "type": "Feature",
  "properties": {
    "iso:country":"US",
    "sg:address":"300 Grant St",
    "sg:city":"De Pere",
    "sg:classifiers":[
        {
            "category":"Travel",
            "subcategory":"Hotels & Motels",
            "type":"Entertainment"
        }
    ],
    "sg:phone":"+1 920 403 5100",
    "sg:postcode":"54115",
    "sg:province":"WI",
    "sg:website":"www.kressinn.com",
    "wof:name":"Kress Inn",
    "wof:placetype":"venue"
},
  "geometry": {"coordinates":[-88.069824,44.44546],"type":"Point"}
}