{
  "type": "Feature",
  "properties": {
    "iso:country":"US",
    "sg:address":"2638 Marion Ln",
    "sg:city":"Waupaca",
    "sg:classifiers":[
        {
            "category":"Retail",
            "subcategory":"Animal Services",
            "type":"Services"
        }
    ],
    "sg:phone":"+1 715 258 0636",
    "sg:postcode":"54981",
    "sg:province":"WI",
    "sg:tags":[
        "specialty"
    ],
    "wof:name":"Matts Quality Hoof Care",
    "wof:placetype":"venue"
},
  "geometry": {"coordinates":[-89.096555,44.303746],"type":"Point"}
}