{
  "type": "Feature",
  "properties": {
    "iso:country":"US",
    "sg:address":"430 N Koeller St",
    "sg:city":"Oshkosh",
    "sg:classifiers":[
        {
            "category":"Health Services",
            "subcategory":"Doctor",
            "type":"Services"
        }
    ],
    "sg:phone":"+1 920 929 8553",
    "sg:postcode":"54902",
    "sg:province":"WI",
    "sg:tags":[
        "physician",
        "surgeon",
        "medical"
    ],
    "wof:name":"Valley Neurology Clinic",
    "wof:placetype":"venue"
},
  "geometry": {"coordinates":[-88.581429,44.023938],"type":"Point"}
}