{
  "type": "Feature",
  "properties": {
    "iso:country":"US",
    "sg:address":"245 S Executive Dr",
    "sg:city":"Brookfield",
    "sg:classifiers":[
        {
            "category":"Banks & Credit Unions",
            "subcategory":"Bank",
            "type":"Services"
        }
    ],
    "sg:phone":"+1 262 641 0192",
    "sg:postcode":"53005",
    "sg:province":"WI",
    "sg:tags":[
        "loan",
        "real estate"
    ],
    "sg:website":"www.mycountrywide.com",
    "wof:name":"Countrywide Home Loans",
    "wof:placetype":"venue"
},
  "geometry": {"coordinates":[-88.114619,43.026972],"type":"Point"}
}