{
  "type": "Feature",
  "properties": {
    "iso:country":"US",
    "sg:address":"4224 W Ruby Ave",
    "sg:city":"Milwaukee",
    "sg:classifiers":[
        {
            "category":"Education",
            "subcategory":"School",
            "type":"Public Place"
        }
    ],
    "sg:phone":"+1 414 871 1224",
    "sg:postcode":"53209",
    "sg:province":"WI",
    "wof:name":"Atonement Lutheran School",
    "wof:placetype":"venue"
},
  "geometry": {"coordinates":[-87.966502,43.099025],"type":"Point"}
}