{
  "type": "Feature",
  "properties": {
    "iso:country":"US",
    "sg:address":"2119 Co Rd F",
    "sg:city":"Berlin",
    "sg:classifiers":[
        {
            "category":"Home & Garden",
            "subcategory":"Household Appliances",
            "type":"Retail Goods"
        }
    ],
    "sg:phone":"+1 920 361 1789",
    "sg:postcode":"54923",
    "sg:province":"WI",
    "sg:tags":[
        "machine",
        "sewing"
    ],
    "wof:name":"West Side Sewing",
    "wof:placetype":"venue"
},
  "geometry": {"coordinates":[-88.988601,43.968613],"type":"Point"}
}