{
  "type": "Feature",
  "properties": {
    "iso:country":"US",
    "sg:address":"305 N 35th St",
    "sg:city":"Milwaukee",
    "sg:classifiers":[
        {
            "category":"Autos & Motor Vehicles",
            "subcategory":"Automobile Sales",
            "type":"Retail Goods"
        }
    ],
    "sg:phone":"+1 414 933 2257",
    "sg:postcode":"53208",
    "sg:province":"WI",
    "sg:tags":[
        "used"
    ],
    "wof:name":"R P Motors Inc",
    "wof:placetype":"venue"
},
  "geometry": {"coordinates":[-87.957801,43.034743],"type":"Point"}
}