{
  "type": "Feature",
  "properties": {
    "addr:full":"202 Main St Camp Douglas WI 54618",
    "addr:housenumber":"202",
    "addr:postcode":"54618",
    "addr:street":"Main St",
    "iso:country":"US",
    "sg:address":"202 Main St",
    "sg:city":"Camp Douglas",
    "sg:classifiers":[
        {
            "category":"Food & Beverages",
            "subcategory":"Groceries & Convenience Stores",
            "type":"Retail Goods"
        }
    ],
    "sg:phone":"+1 608 427 3144",
    "sg:postcode":"54618",
    "sg:province":"WI",
    "sg:tags":[
        "grocer"
    ],
    "wof:name":"Maggie's Market",
    "wof:placetype":"venue"
},
  "geometry": {"coordinates":[-90.26793000000001,43.918963],"type":"Point"}
}