{
  "type": "Feature",
  "properties": {
    "addr:full":"101 Nob Hill Rd Madison WI 53713",
    "addr:housenumber":"101",
    "addr:postcode":"53713",
    "addr:street":"Nob Hill Rd",
    "iso:country":"US",
    "sg:address":"101 Nob Hill Rd",
    "sg:city":"Madison",
    "sg:classifiers":[
        {
            "category":"Real Estate",
            "subcategory":"Real Estate Agent",
            "type":"Services"
        }
    ],
    "sg:phone":"+1 608 277 5524",
    "sg:postcode":"53713",
    "sg:province":"WI",
    "wof:name":"Michelson Management Inc",
    "wof:placetype":"venue"
},
  "geometry": {"coordinates":[-89.37292600000001,43.041659],"type":"Point"}
}