{
  "type": "Feature",
  "properties": {
    "iso:country":"US",
    "sg:address":"4259 Phillips Rd",
    "sg:city":"Marinette",
    "sg:classifiers":[
        {
            "category":"Farming",
            "subcategory":"Livestock Farm",
            "type":"Manufacturing & Wholesale Goods"
        }
    ],
    "sg:phone":"+1 715 789 2049",
    "sg:postcode":"54143",
    "sg:province":"WI",
    "sg:tags":[
        "beef",
        "feedlot",
        "cattle"
    ],
    "wof:name":"Michael Murphy",
    "wof:placetype":"venue"
},
  "geometry": {"coordinates":[-87.814253,45.120968],"type":"Point"}
}