{
  "type": "Feature",
  "properties": {
    "iso:country":"US",
    "sg:address":"7009 Old 113 Rd",
    "sg:city":"Dane",
    "sg:classifiers":[
        {
            "category":"Freight",
            "type":"Transportation"
        }
    ],
    "sg:phone":"+1 608 850 4342",
    "sg:postcode":"53529",
    "sg:province":"WI",
    "sg:tags":[
        "operator",
        "local",
        "trucking"
    ],
    "wof:name":"Nellen Trucking LLC",
    "wof:placetype":"venue"
},
  "geometry": {"coordinates":[-89.48123200000001,43.237859],"type":"Point"}
}