{
  "type": "Feature",
  "properties": {
    "iso:country":"US",
    "sg:address":"8050 N Port Washington Rd",
    "sg:city":"Milwaukee",
    "sg:classifiers":[
        {
            "category":"Real Estate",
            "subcategory":"Real Estate Operator",
            "type":"Services"
        }
    ],
    "sg:phone":"+1 414 628 1222",
    "sg:postcode":"53217",
    "sg:province":"WI",
    "sg:tags":[
        "mobile",
        "home",
        "community"
    ],
    "wof:name":"Hilltop Highlands",
    "wof:placetype":"venue"
},
  "geometry": {"coordinates":[-87.911525,43.16303],"type":"Point"}
}