{
  "type": "Feature",
  "properties": {
    "addr:full":"50196 Co Rd B Soldiers Grove WI 54655",
    "addr:housenumber":"50196",
    "addr:postcode":"54655",
    "addr:street":"Co Rd B Soldiers Grove",
    "iso:country":"US",
    "sg:address":"50196 Co Rd B",
    "sg:city":"Soldiers Grove",
    "sg:classifiers":[
        {
            "category":"Building & Trades",
            "subcategory":"Construction",
            "type":"Services"
        }
    ],
    "sg:phone":"+1 608 735 4922",
    "sg:postcode":"54655",
    "sg:province":"WI",
    "sg:tags":[
        "general",
        "contractor"
    ],
    "wof:name":"Crooked Creek Construction",
    "wof:placetype":"venue"
},
  "geometry": {"coordinates":[-90.866192,43.372221],"type":"Point"}
}