{
  "type": "Feature",
  "properties": {
    "addr:full":"340 Coyier Ln Madison WI 53713",
    "addr:housenumber":"340",
    "addr:postcode":"53713",
    "addr:street":"Coyier Ln",
    "iso:country":"US",
    "sg:address":"340 Coyier Ln",
    "sg:city":"Madison",
    "sg:classifiers":[
        {
            "category":"Manufacturing",
            "subcategory":"Paper Products",
            "type":"Manufacturing & Wholesale Goods"
        }
    ],
    "sg:phone":"+1 608 223 6040",
    "sg:postcode":"53713",
    "sg:province":"WI",
    "sg:tags":[
        "bag"
    ],
    "sg:website":"www.wppa.com",
    "wof:name":"WPPA-Forward Bag Inc",
    "wof:placetype":"venue"
},
  "geometry": {"coordinates":[-89.372742,43.040687],"type":"Point"}
}