{
  "type": "Feature",
  "properties": {
    "iso:country":"US",
    "sg:address":"712 Main St E",
    "sg:city":"Ashland",
    "sg:classifiers":[
        {
            "category":"Personal",
            "subcategory":"Beauty Salon",
            "type":"Services"
        }
    ],
    "sg:phone":"+1 715 682 8887",
    "sg:postcode":"54806",
    "sg:province":"WI",
    "wof:name":"Holly's Hair-Itage",
    "wof:placetype":"venue"
},
  "geometry": {"coordinates":[-90.874557,46.595186],"type":"Point"}
}