{
  "type": "Feature",
  "properties": {
    "iso:country":"US",
    "sg:address":"211 Staadt Ave N",
    "sg:city":"Marshfield",
    "sg:classifiers":[
        {
            "category":"Wholesale",
            "subcategory":"Meat",
            "type":"Manufacturing & Wholesale Goods"
        }
    ],
    "sg:phone":"+1 715 384 5868",
    "sg:postcode":"54449",
    "sg:province":"WI",
    "sg:tags":[
        "packing",
        "plant",
        "prepared",
        "butchering",
        "mfg"
    ],
    "wof:name":"Northern Meat Processing Plant",
    "wof:placetype":"venue"
},
  "geometry": {"coordinates":[-90.119741,44.701539],"type":"Point"}
}