{
  "type": "Feature",
  "properties": {
    "addr:full":"220 Breckenridge St Mayville WI 53050",
    "addr:housenumber":"220",
    "addr:postcode":"53050",
    "addr:street":"Breckenridge St",
    "iso:country":"US",
    "sg:address":"220 Breckenridge St",
    "sg:city":"Mayville",
    "sg:classifiers":[
        {
            "category":"Retail",
            "subcategory":"Repair Shop",
            "type":"Services"
        }
    ],
    "sg:phone":"+1 920 387 4424",
    "sg:postcode":"53050",
    "sg:province":"WI",
    "sg:tags":[
        "refinishing",
        "furniture"
    ],
    "wof:name":"Willie's Pine Shop",
    "wof:placetype":"venue"
},
  "geometry": {"coordinates":[-88.546797,43.501259],"type":"Point"}
}