{
  "type": "Feature",
  "properties": {
    "addr:full":"4700 Sherman Rd Slinger WI 53086",
    "addr:housenumber":"4700",
    "addr:postcode":"53086",
    "addr:street":"Sherman Rd",
    "iso:country":"US",
    "sg:address":"4700 Sherman Rd",
    "sg:city":"Slinger",
    "sg:classifiers":[
        {
            "category":"Building & Trades",
            "subcategory":"Landscaping Services",
            "type":"Services"
        }
    ],
    "sg:phone":"+1 262 268 0675",
    "sg:postcode":"53086",
    "sg:province":"WI",
    "sg:tags":[
        "designer",
        "landscape"
    ],
    "wof:name":"Scenic Landscaping",
    "wof:placetype":"venue"
},
  "geometry": {"coordinates":[-88.271198,43.311389],"type":"Point"}
}