{
  "type": "Feature",
  "properties": {
    "addr:full":"2517 Prais St Stevens Point WI 54481",
    "addr:housenumber":"2517",
    "addr:postcode":"54481",
    "addr:street":"Prais St",
    "iso:country":"US",
    "sg:address":"2517 Prais St",
    "sg:city":"Stevens Point",
    "sg:classifiers":[
        {
            "category":"Health Services",
            "subcategory":"Medical Lab",
            "type":"Services"
        }
    ],
    "sg:phone":"+1 715 344 7020",
    "sg:postcode":"54481",
    "sg:province":"WI",
    "sg:tags":[
        "laboratory"
    ],
    "wof:name":"Association of Pathology",
    "wof:placetype":"venue"
},
  "geometry": {"coordinates":[-89.563457,44.527076],"type":"Point"}
}