{
  "type": "Feature",
  "properties": {
    "addr:full":"311 David Dr Green Bay WI 54303",
    "addr:housenumber":"311",
    "addr:postcode":"54303",
    "addr:street":"David Dr",
    "iso:country":"US",
    "sg:address":"311 David Dr",
    "sg:city":"Green Bay",
    "sg:classifiers":[
        {
            "category":"Insurance",
            "subcategory":"Insurance Agent",
            "type":"Services"
        }
    ],
    "sg:phone":"+1 920 497 2495",
    "sg:postcode":"54303",
    "sg:province":"WI",
    "wof:name":"J C E Medical Billing & C L A",
    "wof:placetype":"venue"
},
  "geometry": {"coordinates":[-88.06705100000001,44.536657],"type":"Point"}
}