{
  "type": "Feature",
  "properties": {
    "iso:country":"US",
    "sg:address":"1029 250th Ave",
    "sg:city":"Luck",
    "sg:classifiers":[
        {
            "category":"Food & Beverages",
            "subcategory":"Groceries & Convenience Stores",
            "type":"Retail Goods"
        }
    ],
    "sg:phone":"+1 715 472 2945",
    "sg:postcode":"54853",
    "sg:province":"WI",
    "wof:name":"Bone Lake Store",
    "wof:placetype":"venue"
},
  "geometry": {"coordinates":[-92.370181,45.568573],"type":"Point"}
}