{
  "type": "Feature",
  "properties": {
    "iso:country":"US",
    "sg:address":"12666 State Hwy 42",
    "sg:city":"Ellison Bay",
    "sg:classifiers":[
        {
            "category":"Travel",
            "subcategory":"Hotels & Motels",
            "type":"Entertainment"
        }
    ],
    "sg:phone":"+1 920 854 5196",
    "sg:postcode":"54210",
    "sg:province":"WI",
    "sg:tags":[
        "operation"
    ],
    "sg:website":"www.door-county-inn.com",
    "wof:name":"Harbor House Inn",
    "wof:placetype":"venue"
},
  "geometry": {"coordinates":[-87.02073900000001,45.285193],"type":"Point"}
}