{
  "type": "Feature",
  "properties": {
    "addr:full":"18880 W Bluemound Rd Brookfield WI 53045",
    "addr:housenumber":"18880",
    "addr:postcode":"53045",
    "addr:street":"W Bluemound Rd",
    "iso:country":"US",
    "sg:address":"18880 W Bluemound Rd",
    "sg:city":"Brookfield",
    "sg:classifiers":[
        {
            "category":"Restaurant",
            "type":"Food & Drink"
        }
    ],
    "sg:menulink":"http://www.allmenus.com/wi/brookfield/63432-mama-mia/menu/",
    "sg:phone":"+1 262 789 0277",
    "sg:postcode":"53045",
    "sg:province":"WI",
    "sg:tags":[
        "italian"
    ],
    "wof:name":"Mama Mia",
    "wof:placetype":"venue"
},
  "geometry": {"coordinates":[-88.147373,43.036803],"type":"Point"}
}