{
  "type": "Feature",
  "properties": {
    "addr:full":"1424 N Flowage Rd Park Falls WI 54552",
    "addr:housenumber":"1424",
    "addr:postcode":"54552",
    "addr:street":"N Flowage Rd",
    "iso:country":"US",
    "sg:address":"1424 N Flowage Rd",
    "sg:city":"Park Falls",
    "sg:classifiers":[
        {
            "category":"Travel",
            "subcategory":"Hotels & Motels",
            "type":"Entertainment"
        }
    ],
    "sg:phone":"+1 715 583 4414",
    "sg:postcode":"54552",
    "sg:province":"WI",
    "sg:tags":[
        "operation"
    ],
    "wof:name":"French Lake Resort",
    "wof:placetype":"venue"
},
  "geometry": {"coordinates":[-90.15567,46.029309],"type":"Point"}
}