{
  "type": "Feature",
  "properties": {
    "addr:full":"804 Liberty Blvd Sun Prairie WI 53590",
    "addr:housenumber":"804",
    "addr:postcode":"53590",
    "addr:street":"Liberty Blvd",
    "iso:country":"US",
    "sg:address":"804 Liberty Blvd",
    "sg:city":"Sun Prairie",
    "sg:classifiers":[
        {
            "category":"Restaurant",
            "type":"Food & Drink"
        }
    ],
    "sg:menulink":"http://www.allmenus.com/wi/sun-prairie/99414-beef-obradys/menu/",
    "sg:phone":"+1 608 837 3131",
    "sg:postcode":"53590",
    "sg:province":"WI",
    "sg:tags":[
        "burger",
        "american",
        "wing",
        "pub"
    ],
    "wof:name":"Beef O'Brady's",
    "wof:placetype":"venue"
},
  "geometry": {"coordinates":[-89.22579500000001,43.199236],"type":"Point"}
}