{
  "type": "Feature",
  "properties": {
    "iso:country":"US",
    "sg:address":"749 US Hwy 12",
    "sg:city":"Hudson",
    "sg:classifiers":[
        {
            "category":"Real Estate",
            "subcategory":"Surveying",
            "type":"Services"
        }
    ],
    "sg:phone":"+1 715 386 7736",
    "sg:postcode":"54016",
    "sg:province":"WI",
    "sg:tags":[
        "surveyor"
    ],
    "wof:name":"Melchert Walkky Inc",
    "wof:placetype":"venue"
},
  "geometry": {"coordinates":[-92.649379,44.988847],"type":"Point"}
}