{
  "type": "Feature",
  "properties": {
    "iso:country":"US",
    "sg:address":"2355 Sunny Ln",
    "sg:city":"Green Bay",
    "sg:classifiers":[
        {
            "category":"Retail",
            "subcategory":"Auto Repair",
            "type":"Services"
        }
    ],
    "sg:phone":"+1 920 434 6770",
    "sg:postcode":"54313",
    "sg:province":"WI",
    "sg:tags":[
        "body",
        "automobile",
        "painting"
    ],
    "wof:name":"Dent Away",
    "wof:placetype":"venue"
},
  "geometry": {"coordinates":[-88.073126,44.598242],"type":"Point"}
}