{
  "type": "Feature",
  "properties": {
    "iso:country":"US",
    "sg:address":"7910 US Hwy 45",
    "sg:city":"Larsen",
    "sg:classifiers":[
        {
            "category":"Restaurant",
            "type":"Food & Drink"
        }
    ],
    "sg:phone":"+1 920 836 2533",
    "sg:postcode":"54947",
    "sg:province":"WI",
    "wof:name":"Bob & Loie's Yellow Jacket",
    "wof:placetype":"venue"
},
  "geometry": {"coordinates":[-88.66451000000001,44.169638],"type":"Point"}
}