{
  "type": "Feature",
  "properties": {
    "iso:country":"US",
    "sg:address":"6636 870th Ave",
    "sg:city":"Colfax",
    "sg:classifiers":[
        {
            "category":"Building & Trades",
            "subcategory":"Construction",
            "type":"Services"
        }
    ],
    "sg:phone":"+1 715 962 3898",
    "sg:postcode":"54730",
    "sg:province":"WI",
    "sg:tags":[
        "contractor"
    ],
    "wof:name":"Breckner Drywall",
    "wof:placetype":"venue"
},
  "geometry": {"coordinates":[-91.826235,44.994603],"type":"Point"}
}