{
  "type": "Feature",
  "properties": {
    "iso:country":"US",
    "sg:address":"2645 N 84th St",
    "sg:city":"Milwaukee",
    "sg:classifiers":[
        {
            "category":"Professional",
            "subcategory":"Management & Consulting",
            "type":"Services"
        }
    ],
    "sg:phone":"+1 414 453 4030",
    "sg:postcode":"53226",
    "sg:province":"WI",
    "wof:name":"Grede Company",
    "wof:placetype":"venue"
},
  "geometry": {"coordinates":[-88.017529,43.06646],"type":"Point"}
}