{
  "type": "Feature",
  "properties": {
    "iso:country":"US",
    "sg:address":"923 E Layton Ave",
    "sg:city":"Milwaukee",
    "sg:classifiers":[
        {
            "category":"Recreation",
            "type":"Entertainment"
        }
    ],
    "sg:phone":"+1 414 482 0062",
    "sg:postcode":"53110",
    "sg:province":"WI",
    "sg:tags":[
        "club",
        "membership"
    ],
    "wof:name":"Panther Aero Ltd",
    "wof:placetype":"venue"
},
  "geometry": {"coordinates":[-87.899175,42.959086],"type":"Point"}
}