{
  "type": "Feature",
  "properties": {
    "addr:full":"600 Powers St Palmyra WI 53156",
    "addr:housenumber":"600",
    "addr:postcode":"53156",
    "addr:street":"Powers St",
    "iso:country":"US",
    "sg:address":"600 Powers St",
    "sg:city":"Palmyra",
    "sg:classifiers":[
        {
            "category":"Professional",
            "type":"Services"
        }
    ],
    "sg:phone":"+1 262 495 4201",
    "sg:postcode":"53156",
    "sg:province":"WI",
    "wof:name":"Little Miracles LLC",
    "wof:placetype":"venue"
},
  "geometry": {"coordinates":[-88.59358400000001,42.881428],"type":"Point"}
}