{
  "type": "Feature",
  "properties": {
    "iso:country":"US",
    "sg:address":"8931 State Hwy 57",
    "sg:city":"Luxemburg",
    "sg:classifiers":[
        {
            "category":"Travel",
            "subcategory":"Hotels & Motels",
            "type":"Entertainment"
        }
    ],
    "sg:phone":"+1 920 866 2978",
    "sg:postcode":"54217",
    "sg:province":"WI",
    "sg:tags":[
        "operation",
        "condominium"
    ],
    "wof:name":"Sunset Beach Motel & Condos",
    "wof:placetype":"venue"
},
  "geometry": {"coordinates":[-87.755809,44.646918],"type":"Point"}
}