{
  "type": "Feature",
  "properties": {
    "iso:country":"US",
    "sg:address":"207 E Buffalo St",
    "sg:city":"Milwaukee",
    "sg:classifiers":[
        {
            "category":"Shopping",
            "subcategory":"Gifts & Souvenirs",
            "type":"Retail Goods"
        },
        {
            "category":"Shopping",
            "type":"Retail Goods"
        },
        {
            "category":"Manufacturing",
            "subcategory":"Apparel",
            "type":"Manufacturing & Wholesale Goods"
        }
    ],
    "sg:phone":"+1 414 273 8066",
    "sg:postcode":"53202",
    "sg:province":"WI",
    "sg:tags":[
        "shop",
        "items-wholesale",
        "boutique",
        "item",
        "manufacturer"
    ],
    "wof:name":"Grotta & Co",
    "wof:placetype":"venue"
},
  "geometry": {"coordinates":[-87.908902,43.033719],"type":"Point"}
}