{
  "type": "Feature",
  "properties": {
    "iso:country":"US",
    "sg:address":"3099 Wegner Rd",
    "sg:city":"Marion",
    "sg:classifiers":[
        {
            "category":"Building & Trades",
            "subcategory":"Construction",
            "type":"Services"
        }
    ],
    "sg:phone":"+1 715 754 5582",
    "sg:postcode":"54950",
    "sg:province":"WI",
    "sg:tags":[
        "plaster",
        "masonry",
        "contractor"
    ],
    "wof:name":"Stong Wall Systems",
    "wof:placetype":"venue"
},
  "geometry": {"coordinates":[-88.920614,44.696182],"type":"Point"}
}