{
  "type": "Feature",
  "properties": {
    "iso:country":"US",
    "sg:address":"8608 Willis Ray Rd",
    "sg:city":"Whitewater",
    "sg:classifiers":[
        {
            "category":"School Buses",
            "type":"Transportation"
        }
    ],
    "sg:phone":"+1 262 473 6680",
    "sg:postcode":"53190",
    "sg:province":"WI",
    "sg:tags":[
        "charter",
        "au"
    ],
    "wof:name":"Nelsons Bus Service Inc",
    "wof:placetype":"venue"
},
  "geometry": {"coordinates":[-88.71892,42.817104],"type":"Point"}
}