{
  "type": "Feature",
  "properties": {
    "iso:country":"US",
    "sg:address":"160 W Progress Dr",
    "sg:city":"West Bend",
    "sg:classifiers":[
        {
            "category":"Retail",
            "subcategory":"Auto Repair",
            "type":"Services"
        }
    ],
    "sg:phone":"+1 800 800 2727",
    "sg:postcode":"53095",
    "sg:province":"WI",
    "sg:tags":[
        "glass",
        "replacement"
    ],
    "wof:name":"Safelite Autoglass",
    "wof:placetype":"venue"
},
  "geometry": {"coordinates":[-88.174565,43.389785],"type":"Point"}
}