{
  "type": "Feature",
  "properties": {
    "addr:full":"600 Cross St La Crosse WI 54601",
    "addr:housenumber":"600",
    "addr:postcode":"54601",
    "addr:street":"Cross St",
    "iso:country":"US",
    "sg:address":"600 Cross St",
    "sg:city":"La Crosse",
    "sg:classifiers":[
        {
            "category":"Personal",
            "subcategory":"Beauty Salon",
            "type":"Services"
        }
    ],
    "sg:phone":"+1 608 784 6441",
    "sg:postcode":"54601",
    "sg:province":"WI",
    "sg:tags":[
        "nail"
    ],
    "wof:name":"Metropolitan Salon & Day Spa",
    "wof:placetype":"venue"
},
  "geometry": {"coordinates":[-91.255989,43.807705],"type":"Point"}
}