{
  "type": "Feature",
  "properties": {
    "iso:country":"US",
    "sg:address":"1100 Proctor Dr",
    "sg:city":"Elkhorn",
    "sg:classifiers":[
        {
            "category":"Manufacturing",
            "subcategory":"Metals",
            "type":"Manufacturing & Wholesale Goods"
        }
    ],
    "sg:phone":"+1 262 723 6100",
    "sg:postcode":"53121",
    "sg:province":"WI",
    "sg:tags":[
        "machine",
        "screw",
        "product"
    ],
    "wof:name":"Screw Machine Co",
    "wof:placetype":"venue"
},
  "geometry": {"coordinates":[-88.525857,42.659962],"type":"Point"}
}