{
  "type": "Feature",
  "properties": {
    "iso:country":"US",
    "sg:address":"1868 Melody Ln",
    "sg:city":"Waupaca",
    "sg:classifiers":[
        {
            "category":"Building & Trades",
            "subcategory":"Construction",
            "type":"Services"
        }
    ],
    "sg:phone":"+1 715 258 5654",
    "sg:postcode":"54981",
    "sg:province":"WI",
    "sg:tags":[
        "house"
    ],
    "wof:name":"Last Design & Const Services",
    "wof:placetype":"venue"
},
  "geometry": {"coordinates":[-89.130928,44.332581],"type":"Point"}
}