{
  "type": "Feature",
  "properties": {
    "iso:country":"US",
    "sg:address":"1631 13th St",
    "sg:city":"Barron",
    "sg:classifiers":[
        {
            "category":"Retail",
            "subcategory":"Auto Repair",
            "type":"Services"
        }
    ],
    "sg:phone":"+1 715 537 3878",
    "sg:postcode":"54812",
    "sg:province":"WI",
    "sg:tags":[
        "wrecker"
    ],
    "wof:name":"Snively's Towing",
    "wof:placetype":"venue"
},
  "geometry": {"coordinates":[-91.888762,45.44047],"type":"Point"}
}