{
  "type": "Feature",
  "properties": {
    "addr:full":"6145 Michels Dr Fond Du Lac WI 54937",
    "addr:housenumber":"6145",
    "addr:postcode":"54937",
    "addr:street":"Michels Dr",
    "iso:country":"US",
    "sg:address":"6145 Michels Dr",
    "sg:city":"Fond Du Lac",
    "sg:phone":"+1 920 921 8395",
    "sg:postcode":"54937",
    "sg:province":"WI",
    "sg:tags":[
        "farm",
        "field",
        "corn",
        "crop"
    ],
    "wof:name":"Leonard Michels",
    "wof:placetype":"venue"
},
  "geometry": {"coordinates":[-88.583732,43.762037],"type":"Point"}
}