{
  "type": "Feature",
  "properties": {
    "iso:country":"US",
    "sg:address":"617 N 67th St",
    "sg:city":"Milwaukee",
    "sg:classifiers":[
        {
            "category":"Manufacturing",
            "subcategory":"Tools & Machinery",
            "type":"Manufacturing & Wholesale Goods"
        }
    ],
    "sg:phone":"+1 414 257 3630",
    "sg:postcode":"53213",
    "sg:province":"WI",
    "sg:tags":[
        "process",
        "control",
        "mfg",
        "instrument"
    ],
    "wof:name":"Novatronix LLC",
    "wof:placetype":"venue"
},
  "geometry": {"coordinates":[-87.995757,43.037188],"type":"Point"}
}