{
  "type": "Feature",
  "properties": {
    "iso:country":"US",
    "sg:address":"1613 Center St",
    "sg:city":"Kewaunee",
    "sg:classifiers":[
        {
            "category":"Autos & Motor Vehicles",
            "subcategory":"Automobile Sales",
            "type":"Retail Goods"
        }
    ],
    "sg:phone":"+1 920 388 0520",
    "sg:postcode":"54216",
    "sg:province":"WI",
    "sg:tags":[
        "car",
        "dealer"
    ],
    "sg:website":"www.jorns.com",
    "wof:name":"Jorns Chevrolet Pontiac Inc",
    "wof:placetype":"venue"
},
  "geometry": {"coordinates":[-87.525514,44.455632],"type":"Point"}
}