{
  "type": "Feature",
  "properties": {
    "iso:country":"US",
    "sg:address":"1111 Ashwaubenon St",
    "sg:city":"Green Bay",
    "sg:classifiers":[
        {
            "category":"Manufacturing",
            "subcategory":"Tools & Machinery",
            "type":"Manufacturing & Wholesale Goods"
        }
    ],
    "sg:phone":"+1 920 330 9808",
    "sg:postcode":"54304",
    "sg:province":"WI",
    "sg:tags":[
        "mold",
        "special"
    ],
    "wof:name":"KBL Of Wisconsin",
    "wof:placetype":"venue"
},
  "geometry": {"coordinates":[-88.093602,44.465712],"type":"Point"}
}