{
  "type": "Feature",
  "properties": {
    "iso:country":"US",
    "sg:address":"1207 S Main St",
    "sg:city":"River Falls",
    "sg:classifiers":[
        {
            "category":"Organizations",
            "subcategory":"Professional Association",
            "type":"Services"
        }
    ],
    "sg:phone":"+1 715 426 5388",
    "sg:postcode":"54022",
    "sg:province":"WI",
    "wof:name":"Muscular Dystrophy Assn",
    "wof:placetype":"venue"
},
  "geometry": {"coordinates":[-92.629407,44.84485],"type":"Point"}
}