{
  "type": "Feature",
  "properties": {
    "iso:country":"US",
    "sg:address":"4125 N 124th St",
    "sg:city":"Brookfield",
    "sg:classifiers":[
        {
            "category":"Professional",
            "type":"Services"
        }
    ],
    "sg:phone":"+1 262 781 1115",
    "sg:postcode":"53005",
    "sg:province":"WI",
    "wof:name":"Highlands International",
    "wof:placetype":"venue"
},
  "geometry": {"coordinates":[-88.06641399999999,43.088984],"type":"Point"}
}