{
  "type": "Feature",
  "properties": {
    "iso:country":"US",
    "sg:address":"1800 Quintin Ct",
    "sg:city":"Appleton",
    "sg:classifiers":[
        {
            "category":"Real Estate",
            "subcategory":"Real Estate Operator",
            "type":"Services"
        }
    ],
    "sg:phone":"+1 920 954 6078",
    "sg:postcode":"54915",
    "sg:province":"WI",
    "sg:tags":[
        "building",
        "nonresidential"
    ],
    "wof:name":"Mork Properties LLC",
    "wof:placetype":"venue"
},
  "geometry": {"coordinates":[-88.365196,44.245306],"type":"Point"}
}