{
  "type": "Feature",
  "properties": {
    "iso:country":"US",
    "sg:address":"4441 Robertson Rd",
    "sg:city":"Madison",
    "sg:classifiers":[
        {
            "category":"Manufacturing",
            "subcategory":"Printing",
            "type":"Manufacturing & Wholesale Goods"
        }
    ],
    "sg:phone":"+1 608 241 5900",
    "sg:postcode":"53714",
    "sg:province":"WI",
    "sg:tags":[
        "printer",
        "technical",
        "manual",
        "commercial",
        "trade",
        "periodical",
        "print"
    ],
    "wof:name":"On Target Productions LLC",
    "wof:placetype":"venue"
},
  "geometry": {"coordinates":[-89.31041999999999,43.093157],"type":"Point"}
}