{
  "type": "Feature",
  "properties": {
    "iso:country":"US",
    "sg:address":"1313 Fish Hatchery Rd",
    "sg:city":"Madison",
    "sg:classifiers":[
        {
            "category":"Health Services",
            "subcategory":"Clinic",
            "type":"Services"
        },
        {
            "category":"Community Center",
            "type":"Public Place"
        }
    ],
    "sg:phone":"+1 608 252 8226",
    "sg:postcode":"53715",
    "sg:province":"WI",
    "sg:tags":[
        "medical"
    ],
    "wof:name":"Deem Clinic",
    "wof:placetype":"venue"
},
  "geometry": {"coordinates":[-89.399064,43.05225],"type":"Point"}
}