{
  "type": "Feature",
  "properties": {
    "iso:country":"US",
    "sg:address":"2786 S Linebarger Ter",
    "sg:city":"Milwaukee",
    "sg:classifiers":[
        {
            "category":"Professional",
            "subcategory":"Business Services",
            "type":"Services"
        }
    ],
    "sg:phone":"+1 414 483 7319",
    "sg:postcode":"53207",
    "sg:province":"WI",
    "wof:name":"Long Haul Productions",
    "wof:placetype":"venue"
},
  "geometry": {"coordinates":[-87.88896800000001,42.994693],"type":"Point"}
}