{
  "type": "Feature",
  "properties": {
    "iso:country":"US",
    "sg:address":"130 Main St",
    "sg:city":"Menasha",
    "sg:classifiers":[
        {
            "category":"Insurance",
            "subcategory":"Hazard Insurance",
            "type":"Services"
        }
    ],
    "sg:phone":"+1 920 731 5867",
    "sg:postcode":"54952",
    "sg:province":"WI",
    "sg:tags":[
        "employee",
        "benefit",
        "compensation",
        "plan"
    ],
    "wof:name":"BAF Inc",
    "wof:placetype":"venue"
},
  "geometry": {"coordinates":[-88.450778,44.200158],"type":"Point"}
}