{
  "type": "Feature",
  "properties": {
    "iso:country":"US",
    "sg:address":"1505 Tower Ave",
    "sg:city":"Superior",
    "sg:classifiers":[
        {
            "category":"Shopping",
            "subcategory":"Optical Goods",
            "type":"Retail Goods"
        }
    ],
    "sg:phone":"+1 715 394 7339",
    "sg:postcode":"54880",
    "sg:province":"WI",
    "sg:tags":[
        "optician"
    ],
    "wof:name":"Superior Optics Inc",
    "wof:placetype":"venue"
},
  "geometry": {"coordinates":[-92.10399200000001,46.719365],"type":"Point"}
}