{
  "type": "Feature",
  "properties": {
    "iso:country":"US",
    "sg:address":"520 Karla Ct",
    "sg:city":"Portage",
    "sg:classifiers":[
        {
            "category":"Bars & Pubs",
            "type":"Food & Drink"
        }
    ],
    "sg:phone":"+1 608 742 4292",
    "sg:postcode":"53901",
    "sg:province":"WI",
    "sg:tags":[
        "drinking"
    ],
    "wof:name":"Lean-To The",
    "wof:placetype":"venue"
},
  "geometry": {"coordinates":[-89.45662,43.552838],"type":"Point"}
}