{
  "type": "Feature",
  "properties": {
    "iso:country":"US",
    "sg:address":"3372 State Hwy 13 N",
    "sg:city":"Wisconsin Rapids",
    "sg:classifiers":[
        {
            "category":"Restaurant",
            "type":"Food & Drink"
        }
    ],
    "sg:phone":"+1 715 423 7577",
    "sg:postcode":"54495",
    "sg:province":"WI",
    "wof:name":"Homestead Golf Course",
    "wof:placetype":"venue"
},
  "geometry": {"coordinates":[-89.887418,44.411345],"type":"Point"}
}