{
  "type": "Feature",
  "properties": {
    "iso:country":"US",
    "sg:address":"20839 Co Hwy Ee",
    "sg:city":"Cornell",
    "sg:classifiers":[
        {
            "category":"Farming",
            "subcategory":"Dairy Farm",
            "type":"Manufacturing & Wholesale Goods"
        }
    ],
    "sg:phone":"+1 715 239 6112",
    "sg:postcode":"54732",
    "sg:province":"WI",
    "wof:name":"Thompson Arden",
    "wof:placetype":"venue"
},
  "geometry": {"coordinates":[-91.10392,45.14256],"type":"Point"}
}