{
  "type": "Feature",
  "properties": {
    "addr:full":"623 S 2nd St Milwaukee WI 53204",
    "addr:housenumber":"623",
    "addr:postcode":"53204",
    "addr:street":"S 2Nd St",
    "iso:country":"US",
    "sg:address":"623 S 2nd St",
    "sg:city":"Milwaukee",
    "sg:classifiers":[
        {
            "category":"Professional",
            "subcategory":"Art Services",
            "type":"Services"
        }
    ],
    "sg:phone":"+1 414 273 7468",
    "sg:postcode":"53204",
    "sg:province":"WI",
    "sg:tags":[
        "photographer"
    ],
    "wof:name":"Long Shots Photographics",
    "wof:placetype":"venue"
},
  "geometry": {"coordinates":[-87.91270400000001,43.024435],"type":"Point"}
}