{
  "type": "Feature",
  "properties": {
    "addr:full":"1914 Grange Ave Racine WI 53403",
    "addr:housenumber":"1914",
    "addr:postcode":"53403",
    "addr:street":"Grange Ave",
    "iso:country":"US",
    "sg:address":"1914 Grange Ave",
    "sg:city":"Racine",
    "sg:classifiers":[
        {
            "category":"Organizations",
            "subcategory":"Religious Organization",
            "type":"Services"
        }
    ],
    "sg:phone":"+1 262 619 0498",
    "sg:postcode":"53403",
    "sg:province":"WI",
    "sg:tags":[
        "church"
    ],
    "wof:name":"Parkway Church",
    "wof:placetype":"venue"
},
  "geometry": {"coordinates":[-87.811273,42.706537],"type":"Point"}
}