{
  "type": "Feature",
  "properties": {
    "iso:country":"US",
    "sg:address":"6135 S Kirk Rd",
    "sg:city":"Durand",
    "sg:classifiers":[
        {
            "category":"Farming",
            "subcategory":"Dairy Farm",
            "type":"Manufacturing & Wholesale Goods"
        }
    ],
    "sg:phone":"+1 715 285 5853",
    "sg:postcode":"54736",
    "sg:province":"WI",
    "wof:name":"Gerry Dusek",
    "wof:placetype":"venue"
},
  "geometry": {"coordinates":[-92.000398,44.629073],"type":"Point"}
}