{
  "type": "Feature",
  "properties": {
    "iso:country":"US",
    "sg:address":"8210 W Appleton Ave",
    "sg:city":"Milwaukee",
    "sg:classifiers":[
        {
            "category":"Home & Garden",
            "subcategory":"Household Appliances",
            "type":"Retail Goods"
        }
    ],
    "sg:phone":"+1 414 462 8570",
    "sg:postcode":"53218",
    "sg:province":"WI",
    "sg:tags":[
        "washer",
        "dryers-parts"
    ],
    "wof:name":"Whirlpool Washer Service Co",
    "wof:placetype":"venue"
},
  "geometry": {"coordinates":[-88.014561,43.103161],"type":"Point"}
}