{
  "type": "Feature",
  "properties": {
    "iso:country":"US",
    "sg:address":"10363 250th St",
    "sg:city":"Cadott",
    "sg:classifiers":[
        {
            "category":"Professional",
            "type":"Services"
        }
    ],
    "sg:phone":"+1 715 289 3612",
    "sg:postcode":"54727",
    "sg:province":"WI",
    "wof:name":"Thomas J Lewandowski",
    "wof:placetype":"venue"
},
  "geometry": {"coordinates":[-91.16583300000001,44.976981],"type":"Point"}
}