{
  "type": "Feature",
  "properties": {
    "iso:country":"US",
    "sg:address":"316 South Ave",
    "sg:city":"Scales Mound",
    "sg:classifiers":[
        {
            "category":"Retail",
            "subcategory":"Funeral Services",
            "type":"Services"
        }
    ],
    "sg:phone":"+1 815 845 2218",
    "sg:postcode":"61075",
    "sg:province":"WI",
    "sg:tags":[
        "director"
    ],
    "wof:name":"Kitchen Miller Steinke Funeral",
    "wof:placetype":"venue"
},
  "geometry": {"coordinates":[-90.25267599999999,42.476564],"type":"Point"}
}