{
  "type": "Feature",
  "properties": {
    "addr:full":"2700 Newcastle Ct Waukesha WI 53188",
    "addr:housenumber":"2700",
    "addr:postcode":"53188",
    "addr:street":"Newcastle Ct",
    "iso:country":"US",
    "sg:address":"2700 Newcastle Ct",
    "sg:city":"Waukesha",
    "sg:classifiers":[
        {
            "category":"Professional",
            "type":"Services"
        }
    ],
    "sg:phone":"+1 262 549 0826",
    "sg:postcode":"53188",
    "sg:province":"WI",
    "wof:name":"Thos H & Renee R Mihal",
    "wof:placetype":"venue"
},
  "geometry": {"coordinates":[-88.27920899999999,43.043721],"type":"Point"}
}