{
  "type": "Feature",
  "properties": {
    "addr:full":"2408 W Galena St Milwaukee WI 53205",
    "addr:housenumber":"2408",
    "addr:postcode":"53205",
    "addr:street":"W Galena St",
    "iso:country":"US",
    "sg:address":"2408 W Galena St",
    "sg:city":"Milwaukee",
    "sg:classifiers":[
        {
            "category":"Building & Trades",
            "subcategory":"Construction",
            "type":"Services"
        }
    ],
    "sg:phone":"+1 414 933 7416",
    "sg:postcode":"53205",
    "sg:province":"WI",
    "sg:tags":[
        "house"
    ],
    "wof:name":"Luna Construction LLC",
    "wof:placetype":"venue"
},
  "geometry": {"coordinates":[-87.94386,43.051474],"type":"Point"}
}