{
  "type": "Feature",
  "properties": {
    "iso:country":"US",
    "sg:address":"701 W Wisconsin St",
    "sg:city":"Sparta",
    "sg:classifiers":[
        {
            "category":"Bars & Pubs",
            "type":"Food & Drink"
        }
    ],
    "sg:phone":"+1 608 269 9954",
    "sg:postcode":"54656",
    "sg:province":"WI",
    "sg:tags":[
        "drinking"
    ],
    "wof:name":"Wayside Tavern Inc",
    "wof:placetype":"venue"
},
  "geometry": {"coordinates":[-90.820652,43.93914],"type":"Point"}
}