{
  "type": "Feature",
  "properties": {
    "iso:country":"US",
    "sg:address":"833 Water St",
    "sg:city":"Sauk City",
    "sg:classifiers":[
        {
            "category":"Bars & Pubs",
            "type":"Food & Drink"
        }
    ],
    "sg:phone":"+1 608 643 2999",
    "sg:postcode":"53583",
    "sg:province":"WI",
    "sg:tags":[
        "drinking"
    ],
    "wof:name":"Tundra Tap",
    "wof:placetype":"venue"
},
  "geometry": {"coordinates":[-89.721347,43.272064],"type":"Point"}
}