{
  "type": "Feature",
  "properties": {
    "iso:country":"US",
    "sg:address":"2404 State Rd",
    "sg:city":"La Crosse",
    "sg:classifiers":[
        {
            "category":"Travel",
            "subcategory":"Travel Agent",
            "type":"Entertainment"
        }
    ],
    "sg:phone":"+1 608 784 9820",
    "sg:postcode":"54601",
    "sg:province":"WI",
    "sg:tags":[
        "ticket",
        "agency",
        "airline"
    ],
    "sg:website":"www.carlsongolis.com",
    "wof:name":"Carlson Wagonlit Travel",
    "wof:placetype":"venue"
},
  "geometry": {"coordinates":[-91.217265,43.795446],"type":"Point"}
}