{
  "type": "Feature",
  "properties": {
    "addr:full":"1804 Wisconsin Ave New Holstein WI 53061",
    "addr:housenumber":"1804",
    "addr:postcode":"53061",
    "addr:street":"Wisconsin Ave",
    "iso:country":"US",
    "sg:address":"1804 Wisconsin Ave",
    "sg:city":"New Holstein",
    "sg:classifiers":[
        {
            "category":"Retail",
            "subcategory":"Auto Rental",
            "type":"Services"
        }
    ],
    "sg:phone":"+1 920 898 5237",
    "sg:postcode":"53061",
    "sg:province":"WI",
    "sg:tags":[
        "truck",
        "trailer",
        "utility"
    ],
    "wof:name":"U-Haul",
    "wof:placetype":"venue"
},
  "geometry": {"coordinates":[-88.08994,43.949838],"type":"Point"}
}