{
  "type": "Feature",
  "properties": {
    "iso:country":"US",
    "sg:address":"3940 Forshaug Rd",
    "sg:city":"Black Earth",
    "sg:classifiers":[
        {
            "category":"Retail",
            "subcategory":"Veterinary Services",
            "type":"Services"
        }
    ],
    "sg:phone":"+1 608 767 3071",
    "sg:postcode":"53515",
    "sg:province":"WI",
    "sg:tags":[
        "veterinarian"
    ],
    "sg:website":"www.safecapture.com",
    "wof:name":"Safe-Capture Intl",
    "wof:placetype":"venue"
},
  "geometry": {"coordinates":[-89.76582000000001,43.073824],"type":"Point"}
}