{
  "type": "Feature",
  "properties": {
    "addr:full":"711 3rd St Mosinee WI 54455",
    "addr:housenumber":"711",
    "addr:postcode":"54455",
    "addr:street":"3Rd St",
    "iso:country":"US",
    "sg:address":"711 3rd St",
    "sg:city":"Mosinee",
    "sg:classifiers":[
        {
            "category":"Manufacturing",
            "subcategory":"Printing",
            "type":"Manufacturing & Wholesale Goods"
        }
    ],
    "sg:phone":"+1 715 693 2491",
    "sg:postcode":"54455",
    "sg:province":"WI",
    "sg:tags":[
        "lithographic",
        "commercial"
    ],
    "wof:name":"Gold Edge Computers",
    "wof:placetype":"venue"
},
  "geometry": {"coordinates":[-89.70690999999999,44.788823],"type":"Point"}
}