{
  "type": "Feature",
  "properties": {
    "iso:country":"US",
    "sg:address":"1900 N Washington St",
    "sg:city":"Janesville",
    "sg:classifiers":[
        {
            "category":"Real Estate",
            "subcategory":"Real Estate Operator",
            "type":"Services"
        }
    ],
    "sg:phone":"+1 608 758 0421",
    "sg:postcode":"53548",
    "sg:province":"WI",
    "sg:tags":[
        "apartment"
    ],
    "wof:name":"Washington Highlands Apts",
    "wof:placetype":"venue"
},
  "geometry": {"coordinates":[-89.039458,42.701323],"type":"Point"}
}