{
  "type": "Feature",
  "properties": {
    "addr:full":"202 Eau Claire St Eau Claire WI 54701",
    "addr:housenumber":"202",
    "addr:postcode":"54701",
    "addr:street":"Eau Claire St",
    "iso:country":"US",
    "sg:address":"202 Eau Claire St",
    "sg:city":"Eau Claire",
    "sg:classifiers":[
        {
            "category":"Professional",
            "subcategory":"Lawyer & Legal Services",
            "type":"Services"
        }
    ],
    "sg:phone":"+1 715 831 9565",
    "sg:postcode":"54701",
    "sg:province":"WI",
    "sg:tags":[
        "attorney"
    ],
    "wof:name":"White Welter & Schilling",
    "wof:placetype":"venue"
},
  "geometry": {"coordinates":[-91.500676,44.812266],"type":"Point"}
}