{
  "type": "Feature",
  "properties": {
    "addr:full":"5507 22nd Ave Kenosha WI 53140",
    "addr:housenumber":"5507",
    "addr:postcode":"53140",
    "addr:street":"22Nd Ave",
    "iso:country":"US",
    "sg:address":"5507 22nd Ave",
    "sg:city":"Kenosha",
    "sg:classifiers":[
        {
            "category":"Sports & Exercise",
            "subcategory":"Gym",
            "type":"Entertainment"
        }
    ],
    "sg:phone":"+1 262 652 4994",
    "sg:postcode":"53140",
    "sg:province":"WI",
    "sg:tags":[
        "fitness",
        "physical",
        "facility"
    ],
    "wof:name":"Atlas Gym",
    "wof:placetype":"venue"
},
  "geometry": {"coordinates":[-87.835633,42.58373],"type":"Point"}
}