{
  "type": "Feature",
  "properties": {
    "addr:full":"4401 Green Bay Rd Kenosha WI 53144",
    "addr:housenumber":"4401",
    "addr:postcode":"53144",
    "addr:street":"Green Bay Rd",
    "iso:country":"US",
    "sg:address":"4401 Green Bay Rd",
    "sg:city":"Kenosha",
    "sg:classifiers":[
        {
            "category":"Government",
            "subcategory":"Office",
            "type":"Public Place"
        }
    ],
    "sg:phone":"+1 262 653 4308",
    "sg:postcode":"53144",
    "sg:province":"WI",
    "sg:tags":[
        "water",
        "executive",
        "system",
        "supply",
        "sewerage"
    ],
    "wof:name":"Kenosha Water Utility",
    "wof:placetype":"venue"
},
  "geometry": {"coordinates":[-87.880453,42.596553],"type":"Point"}
}