{
  "type": "Feature",
  "properties": {
    "iso:country":"US",
    "sg:address":"151 Green Bay Rd",
    "sg:city":"Thiensville",
    "sg:classifiers":[
        {
            "category":"Personal",
            "subcategory":"Beauty Salon",
            "type":"Services"
        }
    ],
    "sg:phone":"+1 262 238 9963",
    "sg:postcode":"53092",
    "sg:province":"WI",
    "sg:tags":[
        "shop"
    ],
    "wof:name":"Hair Biz",
    "wof:placetype":"venue"
},
  "geometry": {"coordinates":[-87.982771,43.230741],"type":"Point"}
}