{
  "type": "Feature",
  "properties": {
    "addr:full":"648 N Plankinton Ave Ste 250 Milwaukee WI 53203",
    "addr:housenumber":"648",
    "addr:postcode":"53203",
    "addr:street":"N Plankinton Ave Ste 250",
    "iso:country":"US",
    "sg:address":"648 N Plankinton Ave Ste 250",
    "sg:city":"Milwaukee",
    "sg:classifiers":[
        {
            "category":"Internet Cafe",
            "subcategory":"None",
            "type":"Food & Drink"
        },
        {
            "category":"Professional",
            "subcategory":"Computer Services",
            "type":"Services"
        }
    ],
    "sg:phone":"+1 414 755 3900",
    "sg:postcode":"53203",
    "sg:province":"WI",
    "sg:tags":[
        "product",
        "designer",
        "network",
        "consultant",
        "system",
        "design",
        "software"
    ],
    "wof:name":"Smag Media",
    "wof:placetype":"venue"
},
  "geometry": {"coordinates":[-87.911186,43.038139],"type":"Point"}
}