{
  "type": "Feature",
  "properties": {
    "addr:full":"10839 Dove Ln Hayward WI 54843",
    "addr:housenumber":"10839",
    "addr:postcode":"54843",
    "addr:street":"Dove Ln",
    "iso:country":"US",
    "sg:address":"10839 Dove Ln",
    "sg:city":"Hayward",
    "sg:classifiers":[
        {
            "category":"Real Estate",
            "subcategory":"Real Estate Agent",
            "type":"Services"
        }
    ],
    "sg:phone":"+1 715 462 3068",
    "sg:postcode":"54843",
    "sg:province":"WI",
    "wof:name":"Bugel Properties",
    "wof:placetype":"venue"
},
  "geometry": {"coordinates":[-91.282523,46.019614],"type":"Point"}
}