{
  "type": "Feature",
  "properties": {
    "iso:country":"US",
    "sg:address":"1045 N Lynndale Dr",
    "sg:city":"Appleton",
    "sg:classifiers":[
        {
            "category":"Wholesale",
            "subcategory":"Electrical",
            "type":"Manufacturing & Wholesale Goods"
        }
    ],
    "sg:phone":"+1 920 739 1241",
    "sg:postcode":"54914",
    "sg:province":"WI",
    "sg:tags":[
        "supply"
    ],
    "wof:name":"Reliance Electric Indus Co",
    "wof:placetype":"venue"
},
  "geometry": {"coordinates":[-88.44603600000001,44.267275],"type":"Point"}
}