{
  "type": "Feature",
  "properties": {
    "addr:full":"1005 Gilbert Rd Madison WI 53711",
    "addr:housenumber":"1005",
    "addr:postcode":"53711",
    "addr:street":"Gilbert Rd",
    "iso:country":"US",
    "sg:address":"1005 Gilbert Rd",
    "sg:city":"Madison",
    "sg:classifiers":[
        {
            "category":"Real Estate",
            "subcategory":"Real Estate Operator",
            "type":"Services"
        }
    ],
    "sg:phone":"+1 608 274 2319",
    "sg:postcode":"53711",
    "sg:province":"WI",
    "sg:tags":[
        "building",
        "apartment"
    ],
    "wof:name":"Orchard Valley Apartments",
    "wof:placetype":"venue"
},
  "geometry": {"coordinates":[-89.473372,43.041041],"type":"Point"}
}