{
  "type": "Feature",
  "properties": {
    "iso:country":"US",
    "sg:address":"8241 Fairmont Ln",
    "sg:city":"Greendale",
    "sg:classifiers":[
        {
            "category":"Professional",
            "subcategory":"Business Services",
            "type":"Services"
        }
    ],
    "sg:phone":"+1 414 421 7007",
    "sg:postcode":"53129",
    "sg:province":"WI",
    "sg:tags":[
        "inventory"
    ],
    "wof:name":"Store Checks Inc",
    "wof:placetype":"venue"
},
  "geometry": {"coordinates":[-88.015467,42.933245],"type":"Point"}
}