{
  "type": "Feature",
  "properties": {
    "iso:country":"US",
    "sg:address":"900 N Division St",
    "sg:city":"Roberts",
    "sg:classifiers":[
        {
            "category":"Autos & Motor Vehicles",
            "subcategory":"Fuel & Gas Station",
            "type":"Retail Goods"
        }
    ],
    "sg:phone":"+1 715 749 3388",
    "sg:postcode":"54023",
    "sg:province":"WI",
    "sg:tags":[
        "station",
        "gasoline"
    ],
    "wof:name":"S/S/G Corporation",
    "wof:placetype":"venue"
},
  "geometry": {"coordinates":[-92.552948,44.988967],"type":"Point"}
}