{
  "type": "Feature",
  "properties": {
    "iso:country":"US",
    "sg:address":"13133 N Port Washington Rd.",
    "sg:city":"Mequon",
    "sg:classifiers":[
        {
            "category":"Personal",
            "subcategory":"Hair Removal",
            "type":"Services"
        }
    ],
    "sg:phone":"+1 262 243 5302",
    "sg:postcode":"53097",
    "sg:province":"WI",
    "wof:name":"American Laser Centers",
    "wof:placetype":"venue"
},
  "geometry": {"coordinates":[-87.924167,43.256665],"type":"Point"}
}