{
  "type": "Feature",
  "properties": {
    "iso:country":"US",
    "sg:address":"439 E Main St",
    "sg:city":"Mishicot",
    "sg:classifiers":[
        {
            "category":"Professional",
            "type":"Services"
        }
    ],
    "sg:phone":"+1 920 755 3152",
    "sg:postcode":"54228",
    "sg:province":"WI",
    "sg:tags":[
        "establishment"
    ],
    "wof:name":"Behrmanns Na",
    "wof:placetype":"venue"
},
  "geometry": {"coordinates":[-87.640243,44.238462],"type":"Point"}
}