{
  "type": "Feature",
  "properties": {
    "iso:country":"US",
    "sg:address":"333 E Sunset Ct",
    "sg:city":"Madison",
    "sg:classifiers":[
        {
            "category":"Real Estate",
            "subcategory":"Real Estate Operator",
            "type":"Services"
        }
    ],
    "sg:phone":"+1 608 231 1702",
    "sg:postcode":"53705",
    "sg:province":"WI",
    "sg:tags":[
        "property",
        "lessor"
    ],
    "wof:name":"Lawrence Howe",
    "wof:placetype":"venue"
},
  "geometry": {"coordinates":[-89.444811,43.060829],"type":"Point"}
}