{
  "type": "Feature",
  "properties": {
    "iso:country":"US",
    "sg:address":"1010 S Military Ave",
    "sg:city":"Green Bay",
    "sg:classifiers":[
        {
            "category":"Autos & Motor Vehicles",
            "subcategory":"Automobile Sales",
            "type":"Retail Goods"
        }
    ],
    "sg:phone":"+1 920 499 3131",
    "sg:postcode":"54304",
    "sg:province":"WI",
    "sg:tags":[
        "car",
        "dealer"
    ],
    "sg:website":"www.vanboxtelford.com",
    "wof:name":"Van Boxtel Ford Rental",
    "wof:placetype":"venue"
},
  "geometry": {"coordinates":[-88.067601,44.518775],"type":"Point"}
}