{
  "type": "Feature",
  "properties": {
    "iso:country":"US",
    "sg:address":"826 Lucky St",
    "sg:city":"Reedsburg",
    "sg:classifiers":[
        {
            "category":"Manufacturing",
            "subcategory":"Wood Products",
            "type":"Manufacturing & Wholesale Goods"
        },
        {
            "category":"Building & Trades",
            "subcategory":"Construction",
            "type":"Services"
        }
    ],
    "sg:phone":"+1 608 524 2428",
    "sg:postcode":"53959",
    "sg:province":"WI",
    "sg:tags":[
        "mfg",
        "woodworker"
    ],
    "sg:website":"www.stageproductions.com",
    "wof:name":"Stage Productions Inc",
    "wof:placetype":"venue"
},
  "geometry": {"coordinates":[-89.9987,43.528318],"type":"Point"}
}