{
  "type": "Feature",
  "properties": {
    "iso:country":"US",
    "sg:address":"4350 S 13th St",
    "sg:city":"Milwaukee",
    "sg:classifiers":[
        {
            "category":"Manufacturing",
            "subcategory":"Glass & Minerals",
            "type":"Manufacturing & Wholesale Goods"
        }
    ],
    "sg:phone":"+1 414 258 7000",
    "sg:postcode":"53221",
    "sg:province":"WI",
    "sg:tags":[
        "ready"
    ],
    "wof:name":"Central Ready Mixed Concrete",
    "wof:placetype":"venue"
},
  "geometry": {"coordinates":[-87.92916700000001,42.966536],"type":"Point"}
}