{
  "type": "Feature",
  "properties": {
    "iso:country":"US",
    "sg:address":"250 Oak St",
    "sg:city":"Grafton",
    "sg:classifiers":[
        {
            "category":"Shopping",
            "subcategory":"Pharmacy",
            "type":"Retail Goods"
        }
    ],
    "sg:phone":"+1 262 375 0600",
    "sg:postcode":"53024",
    "sg:province":"WI",
    "wof:name":"Ozaukee Apothecary Pharmacy",
    "wof:placetype":"venue"
},
  "geometry": {"coordinates":[-87.96080000000001,43.306509],"type":"Point"}
}