{
  "type": "Feature",
  "properties": {
    "iso:country":"US",
    "sg:address":"655 S 70th St",
    "sg:city":"Milwaukee",
    "sg:classifiers":[
        {
            "category":"Autos & Motor Vehicles",
            "subcategory":"Auto Supplies",
            "type":"Retail Goods"
        },
        {
            "category":"Retail",
            "subcategory":"Auto Repair",
            "type":"Services"
        }
    ],
    "sg:phone":"+1 414 453 2600",
    "sg:postcode":"53214",
    "sg:province":"WI",
    "sg:tags":[
        "body",
        "lettering",
        "automobile",
        "removal",
        "truck",
        "dent",
        "painting",
        "repairing"
    ],
    "wof:name":"Krause Auto Body",
    "wof:placetype":"venue"
},
  "geometry": {"coordinates":[-87.99993600000001,43.025252],"type":"Point"}
}