{
  "type": "Feature",
  "properties": {
    "addr:full":"488 Cledell St Oregon WI 53575",
    "addr:housenumber":"488",
    "addr:postcode":"53575",
    "addr:street":"Cledell St",
    "iso:country":"US",
    "sg:address":"488 Cledell St",
    "sg:city":"Oregon",
    "sg:classifiers":[
        {
            "category":"Building & Trades",
            "subcategory":"Construction",
            "type":"Services"
        }
    ],
    "sg:phone":"+1 608 455 1914",
    "sg:postcode":"53575",
    "sg:province":"WI",
    "sg:tags":[
        "house"
    ],
    "wof:name":"Reliable Home Investments LLC",
    "wof:placetype":"venue"
},
  "geometry": {"coordinates":[-89.37979799999999,42.91767],"type":"Point"}
}