{
  "type": "Feature",
  "properties": {
    "iso:country":"US",
    "sg:address":"8082 Brinkland Dr",
    "sg:city":"Minocqua",
    "sg:classifiers":[
        {
            "category":"Building & Trades",
            "subcategory":"Construction",
            "type":"Services"
        }
    ],
    "sg:phone":"+1 715 358 3145",
    "sg:postcode":"54548",
    "sg:province":"WI",
    "sg:tags":[
        "general",
        "contractor"
    ],
    "wof:name":"Miller/Emil Builders Inc",
    "wof:placetype":"venue"
},
  "geometry": {"coordinates":[-89.692147,45.859008],"type":"Point"}
}