{
  "type": "Feature",
  "properties": {
    "iso:country":"US",
    "sg:address":"900 E Keefe Ave",
    "sg:city":"Milwaukee",
    "sg:classifiers":[
        {
            "category":"Utilities",
            "subcategory":"Electric",
            "type":"Services"
        }
    ],
    "sg:phone":"+1 414 967 6500",
    "sg:postcode":"53212",
    "sg:province":"WI",
    "sg:tags":[
        "transformer"
    ],
    "sg:website":"http://www.mycdtechno.com",
    "wof:name":"C&D Technologies, Inc.",
    "wof:placetype":"venue"
},
  "geometry": {"coordinates":[-87.900002,43.081989],"type":"Point"}
}