{
  "type": "Feature",
  "properties": {
    "iso:country":"US",
    "sg:address":"3906 Cemetery Rd",
    "sg:city":"Reedsburg",
    "sg:classifiers":[
        {
            "category":"Manufacturing",
            "subcategory":"Lumber",
            "type":"Manufacturing & Wholesale Goods"
        }
    ],
    "sg:phone":"+1 608 985 7638",
    "sg:postcode":"53959",
    "sg:province":"WI",
    "sg:tags":[
        "sawmill"
    ],
    "wof:name":"Pearson's Saw Mill",
    "wof:placetype":"venue"
},
  "geometry": {"coordinates":[-90.122942,43.547985],"type":"Point"}
}