{
  "type": "Feature",
  "properties": {
    "iso:country":"US",
    "sg:address":"223 E Green Bay St",
    "sg:city":"Shawano",
    "sg:classifiers":[
        {
            "category":"Professional",
            "type":"Services"
        }
    ],
    "sg:phone":"+1 715 524 5185",
    "sg:postcode":"54166",
    "sg:province":"WI",
    "wof:name":"D & M Winners Circle",
    "wof:placetype":"venue"
},
  "geometry": {"coordinates":[-88.60612999999999,44.782121],"type":"Point"}
}