{
  "type": "Feature",
  "properties": {
    "iso:country":"US",
    "sg:address":"9106 Harvestore Rd",
    "sg:city":"Hilbert",
    "sg:classifiers":[
        {
            "category":"Building & Trades",
            "subcategory":"Construction",
            "type":"Services"
        }
    ],
    "sg:phone":"+1 920 989 2166",
    "sg:postcode":"54129",
    "sg:province":"WI",
    "sg:tags":[
        "masonry",
        "contractor"
    ],
    "wof:name":"Lyle Thiel Masonry",
    "wof:placetype":"venue"
},
  "geometry": {"coordinates":[-88.183694,44.219943],"type":"Point"}
}