{
  "type": "Feature",
  "properties": {
    "iso:country":"US",
    "sg:address":"1208 Oshkosh Ave",
    "sg:city":"Oshkosh",
    "sg:classifiers":[
        {
            "category":"Shopping",
            "type":"Retail Goods"
        }
    ],
    "sg:phone":"+1 920 233 4565",
    "sg:postcode":"54902",
    "sg:province":"WI",
    "sg:tags":[
        "equipment",
        "supply"
    ],
    "wof:name":"TPL Inc Used Restaurant",
    "wof:placetype":"venue"
},
  "geometry": {"coordinates":[-88.566838,44.034455],"type":"Point"}
}