{
  "type": "Feature",
  "properties": {
    "iso:country":"US",
    "sg:address":"4416 29th St",
    "sg:city":"Kenosha",
    "sg:classifiers":[
        {
            "category":"Manufacturing",
            "subcategory":"Retail Goods",
            "type":"Manufacturing & Wholesale Goods"
        }
    ],
    "sg:phone":"+1 262 652 7991",
    "sg:postcode":"53144",
    "sg:province":"WI",
    "sg:tags":[
        "product",
        "mfg"
    ],
    "wof:name":"Chime In",
    "wof:placetype":"venue"
},
  "geometry": {"coordinates":[-87.862664,42.611821],"type":"Point"}
}