{
  "type": "Feature",
  "properties": {
    "iso:country":"US",
    "sg:address":"855 Specialists Ave",
    "sg:city":"Neenah",
    "sg:classifiers":[
        {
            "category":"Freight",
            "type":"Transportation"
        }
    ],
    "sg:phone":"+1 920 969 3943",
    "sg:postcode":"54956",
    "sg:province":"WI",
    "sg:tags":[
        "local",
        "storage",
        "trucking"
    ],
    "wof:name":"Estes Innovative",
    "wof:placetype":"venue"
},
  "geometry": {"coordinates":[-88.522502,44.201083],"type":"Point"}
}