{
  "type": "Feature",
  "properties": {
    "iso:country":"US",
    "sg:address":"720 Hillcrest Hts",
    "sg:city":"Green Bay",
    "sg:classifiers":[
        {
            "category":"Social Services",
            "subcategory":"Child Care",
            "type":"Services"
        }
    ],
    "sg:phone":"+1 920 434 6043",
    "sg:postcode":"54313",
    "sg:province":"WI",
    "wof:name":"Children's World Learning Ctr",
    "wof:placetype":"venue"
},
  "geometry": {"coordinates":[-88.09963,44.5612],"type":"Point"}
}