{
  "type": "Feature",
  "properties": {
    "iso:country":"US",
    "sg:address":"1715 Sundown Ln",
    "sg:city":"Appleton",
    "sg:classifiers":[
        {
            "category":"Building & Trades",
            "subcategory":"Cleaning & Sanitation",
            "type":"Services"
        }
    ],
    "sg:phone":"+1 920 954 8443",
    "sg:postcode":"54915",
    "sg:province":"WI",
    "sg:tags":[
        "janitor"
    ],
    "wof:name":"Accu Clean Svc Of WIS",
    "wof:placetype":"venue"
},
  "geometry": {"coordinates":[-88.362342,44.247558],"type":"Point"}
}