{
  "type": "Feature",
  "properties": {
    "iso:country":"US",
    "sg:address":"3405 Calumet Ave",
    "sg:city":"Manitowoc",
    "sg:classifiers":[
        {
            "category":"Restaurant",
            "type":"Food & Drink"
        }
    ],
    "sg:phone":"+1 920 684 8533",
    "sg:postcode":"54220",
    "sg:province":"WI",
    "sg:tags":[
        "eating"
    ],
    "wof:name":"China Buffet At Manitowoc Inc",
    "wof:placetype":"venue"
},
  "geometry": {"coordinates":[-87.68982699999999,44.084192],"type":"Point"}
}