{
  "type": "Feature",
  "properties": {
    "iso:country":"US",
    "sg:address":"816 W National Ave",
    "sg:city":"Milwaukee",
    "sg:classifiers":[
        {
            "category":"Building & Trades",
            "subcategory":"Construction",
            "type":"Services"
        }
    ],
    "sg:phone":"+1 414 241 4111",
    "sg:postcode":"53204",
    "sg:province":"WI",
    "sg:tags":[
        "house",
        "residential"
    ],
    "sg:website":"www.generonconstruction.com",
    "wof:name":"Generon Construction",
    "wof:placetype":"venue"
},
  "geometry": {"coordinates":[-87.922433,43.023295],"type":"Point"}
}