{
  "type": "Feature",
  "properties": {
    "iso:country":"US",
    "sg:address":"1059 Circle Dr",
    "sg:city":"Highland",
    "sg:classifiers":[
        {
            "category":"Shopping",
            "type":"Retail Goods"
        }
    ],
    "sg:phone":"+1 608 929 7500",
    "sg:postcode":"53543",
    "sg:province":"WI",
    "sg:tags":[
        "merchandise"
    ],
    "wof:name":"McT Inc",
    "wof:placetype":"venue"
},
  "geometry": {"coordinates":[-90.38018700000001,43.053933],"type":"Point"}
}