{
  "type": "Feature",
  "properties": {
    "addr:full":"1110 2nd St Pepin WI 54759",
    "addr:housenumber":"1110",
    "addr:postcode":"54759",
    "addr:street":"2Nd St",
    "iso:country":"US",
    "sg:address":"1110 2nd St",
    "sg:city":"Pepin",
    "sg:classifiers":[
        {
            "category":"Health Services",
            "subcategory":"Nursing And Care Facility",
            "type":"Services"
        }
    ],
    "sg:phone":"+1 715 442 4811",
    "sg:postcode":"54759",
    "sg:province":"WI",
    "sg:tags":[
        "home"
    ],
    "wof:name":"Pepin Manor",
    "wof:placetype":"venue"
},
  "geometry": {"coordinates":[-92.159464,44.442676],"type":"Point"}
}