{
  "type": "Feature",
  "properties": {
    "iso:country":"US",
    "sg:address":"1230 E Scott St",
    "sg:city":"Omro",
    "sg:classifiers":[
        {
            "category":"Social Services",
            "subcategory":"Child Care",
            "type":"Services"
        }
    ],
    "sg:phone":"+1 920 685 6074",
    "sg:postcode":"54963",
    "sg:province":"WI",
    "sg:tags":[
        "day"
    ],
    "wof:name":"Friendship Shop",
    "wof:placetype":"venue"
},
  "geometry": {"coordinates":[-88.72905799999999,44.033265],"type":"Point"}
}