{
  "type": "Feature",
  "properties": {
    "iso:country":"US",
    "sg:address":"201 Soo Ave E",
    "sg:city":"Almena",
    "sg:classifiers":[
        {
            "category":"Restaurant",
            "type":"Food & Drink"
        }
    ],
    "sg:phone":"+1 715 357 3558",
    "sg:postcode":"54805",
    "sg:province":"WI",
    "wof:name":"Veterans Of Foreign Wars",
    "wof:placetype":"venue"
},
  "geometry": {"coordinates":[-92.03530499999999,45.417964],"type":"Point"}
}