{
  "type": "Feature",
  "properties": {
    "iso:country":"US",
    "sg:address":"717 3rd St E",
    "sg:city":"Menomonie",
    "sg:classifiers":[
        {
            "category":"Retail",
            "subcategory":"Repair Shop",
            "type":"Services"
        }
    ],
    "sg:phone":"+1 715 232 8570",
    "sg:postcode":"54751",
    "sg:province":"WI",
    "wof:name":"Mary Kohanek Upholstering",
    "wof:placetype":"venue"
},
  "geometry": {"coordinates":[-91.92732700000001,44.876356],"type":"Point"}
}