{
  "type": "Feature",
  "properties": {
    "iso:country":"US",
    "sg:address":"683 Bay Park Sq",
    "sg:city":"Green Bay",
    "sg:classifiers":[
        {
            "category":"Shopping",
            "subcategory":"Gifts & Souvenirs",
            "type":"Retail Goods"
        }
    ],
    "sg:phone":"+1 920 494 9640",
    "sg:postcode":"54304",
    "sg:province":"WI",
    "wof:name":"Coach House Cards & Gifts",
    "wof:placetype":"venue"
},
  "geometry": {"coordinates":[-88.067868,44.484641],"type":"Point"}
}