{
  "type": "Feature",
  "properties": {
    "addr:full":"555 Lester Ave Onalaska WI 54650",
    "addr:housenumber":"555",
    "addr:postcode":"54650",
    "addr:street":"Lester Ave",
    "iso:country":"US",
    "sg:address":"555 Lester Ave",
    "sg:city":"Onalaska",
    "sg:classifiers":[
        {
            "category":"Professional",
            "type":"Services"
        },
        {
            "category":"Government",
            "subcategory":"Office",
            "type":"Public Place"
        }
    ],
    "sg:phone":"+1 608 783 8405",
    "sg:postcode":"54650",
    "sg:province":"WI",
    "sg:tags":[
        "establishment",
        "fishery",
        "resource"
    ],
    "wof:name":"Upper Mississippi River Nation",
    "wof:placetype":"venue"
},
  "geometry": {"coordinates":[-91.197988,43.874979],"type":"Point"}
}