{
  "type": "Feature",
  "properties": {
    "iso:country":"US",
    "sg:address":"7805 Evergreen Dr",
    "sg:city":"Algoma",
    "sg:classifiers":[
        {
            "category":"Organizations",
            "subcategory":"Religious Organization",
            "type":"Services"
        }
    ],
    "sg:phone":"+1 920 487 5360",
    "sg:postcode":"54201",
    "sg:province":"WI",
    "sg:tags":[
        "church"
    ],
    "wof:name":"Jehovah's Witnesses",
    "wof:placetype":"venue"
},
  "geometry": {"coordinates":[-87.459688,44.606763],"type":"Point"}
}