{
  "type": "Feature",
  "properties": {
    "addr:full":"718 Delaware Ave Grafton WI 53024",
    "addr:housenumber":"718",
    "addr:postcode":"53024",
    "addr:street":"Delaware Ave",
    "iso:country":"US",
    "sg:address":"718 Delaware Ave",
    "sg:city":"Grafton",
    "sg:classifiers":[
        {
            "category":"Organizations",
            "subcategory":"Membership Organization",
            "type":"Services"
        }
    ],
    "sg:phone":"+1 414 442 3572",
    "sg:postcode":"53024",
    "sg:province":"WI",
    "wof:name":"Bridging The Gap CDC",
    "wof:placetype":"venue"
},
  "geometry": {"coordinates":[-87.935345,43.329221],"type":"Point"}
}