{
  "type": "Feature",
  "properties": {
    "iso:country":"US",
    "sg:address":"3163 N River Rd",
    "sg:city":"Rhinelander",
    "sg:classifiers":[
        {
            "category":"Building & Trades",
            "subcategory":"Construction",
            "type":"Services"
        }
    ],
    "sg:phone":"+1 715 369 3070",
    "sg:postcode":"54501",
    "sg:province":"WI",
    "sg:tags":[
        "industrial",
        "supply",
        "wallcoverings-installation",
        "wallpaper",
        "painting",
        "contractor",
        "equipment",
        "contractors-commercial",
        "drywall"
    ],
    "wof:name":"Bob's Painting & Decorating Inc",
    "wof:placetype":"venue"
},
  "geometry": {"coordinates":[-89.448323,45.624109],"type":"Point"}
}