{
  "type": "Feature",
  "properties": {
    "iso:country":"US",
    "sg:address":"1037 E Green Bay St",
    "sg:city":"Shawano",
    "sg:classifiers":[
        {
            "category":"Autos & Motor Vehicles",
            "subcategory":"Fuel & Gas Station",
            "type":"Retail Goods"
        }
    ],
    "sg:phone":"+1 715 524 8101",
    "sg:postcode":"54166",
    "sg:province":"WI",
    "sg:tags":[
        "station",
        "gasoline"
    ],
    "wof:name":"Petro Mart",
    "wof:placetype":"venue"
},
  "geometry": {"coordinates":[-88.590417,44.782225],"type":"Point"}
}