{
  "type": "Feature",
  "properties": {
    "iso:country":"US",
    "sg:address":"1 Chipmunk Hollow",
    "sg:city":"Superior",
    "sg:classifiers":[
        {
            "category":"Travel",
            "subcategory":"Hotels & Motels",
            "type":"Entertainment"
        }
    ],
    "sg:phone":"+1 715 394 7550",
    "sg:postcode":"54880",
    "sg:province":"WI",
    "sg:tags":[
        "operation"
    ],
    "wof:name":"Wildcat Brule Inc",
    "wof:placetype":"venue"
},
  "geometry": {"coordinates":[-92.137227,46.707546],"type":"Point"}
}