{
  "type": "Feature",
  "properties": {
    "iso:country":"US",
    "sg:address":"7320 Old Sauk Rd",
    "sg:city":"Madison",
    "sg:classifiers":[
        {
            "category":"Professional",
            "subcategory":"Business Services",
            "type":"Services"
        }
    ],
    "sg:phone":"+1 608 831 6924",
    "sg:postcode":"53717",
    "sg:province":"WI",
    "sg:tags":[
        "translator",
        "interpreter"
    ],
    "wof:name":"Interlink Helping Cultures",
    "wof:placetype":"venue"
},
  "geometry": {"coordinates":[-89.508556,43.075232],"type":"Point"}
}