{
  "type": "Feature",
  "properties": {
    "iso:country":"US",
    "sg:address":"14460 W Honey Ln",
    "sg:city":"New Berlin",
    "sg:classifiers":[
        {
            "category":"Health Services",
            "subcategory":"Health Practitioner",
            "type":"Services"
        }
    ],
    "sg:phone":"+1 262 796 9876",
    "sg:postcode":"53151",
    "sg:province":"WI",
    "wof:name":"Tender Touch Therapy",
    "wof:placetype":"venue"
},
  "geometry": {"coordinates":[-88.095071,43.009419],"type":"Point"}
}