{
  "type": "Feature",
  "properties": {
    "iso:country":"US",
    "sg:address":"4415 Walker Rd",
    "sg:city":"Sturgeon Bay",
    "sg:classifiers":[
        {
            "category":"Professional",
            "subcategory":"Management & Consulting",
            "type":"Services"
        }
    ],
    "sg:phone":"+1 920 743 2744",
    "sg:postcode":"54235",
    "sg:province":"WI",
    "sg:tags":[
        "business"
    ],
    "wof:name":"Anndee LLC",
    "wof:placetype":"venue"
},
  "geometry": {"coordinates":[-87.366891,44.8847],"type":"Point"}
}