{
  "type": "Feature",
  "properties": {
    "addr:full":"1621 N Clark St Appleton WI 54911",
    "addr:housenumber":"1621",
    "addr:postcode":"54911",
    "addr:street":"N Clark St",
    "iso:country":"US",
    "sg:address":"1621 N Clark St",
    "sg:city":"Appleton",
    "sg:classifiers":[
        {
            "category":"Wholesale",
            "subcategory":"Scrap",
            "type":"Manufacturing & Wholesale Goods"
        }
    ],
    "sg:phone":"+1 920 739 4990",
    "sg:postcode":"54911",
    "sg:province":"WI",
    "sg:tags":[
        "material"
    ],
    "wof:name":"Mickelson Scrap Metal Business",
    "wof:placetype":"venue"
},
  "geometry": {"coordinates":[-88.409734,44.275413],"type":"Point"}
}