{
  "type": "Feature",
  "properties": {
    "iso:country":"US",
    "sg:address":"1435 Co Hwy Nn",
    "sg:city":"West Bend",
    "sg:classifiers":[
        {
            "category":"Farming",
            "subcategory":"Dairy Farm",
            "type":"Manufacturing & Wholesale Goods"
        }
    ],
    "sg:phone":"+1 262 675 6514",
    "sg:postcode":"53095",
    "sg:province":"WI",
    "wof:name":"Alan Reetz",
    "wof:placetype":"venue"
},
  "geometry": {"coordinates":[-88.088988,43.367693],"type":"Point"}
}