{
  "type": "Feature",
  "properties": {
    "addr:full":"4334 7th St Kenosha WI 53144",
    "addr:housenumber":"4334",
    "addr:postcode":"53144",
    "addr:street":"7Th St",
    "iso:country":"US",
    "sg:address":"4334 7th St",
    "sg:city":"Kenosha",
    "sg:classifiers":[
        {
            "category":"Health Services",
            "subcategory":"Doctor",
            "type":"Services"
        }
    ],
    "sg:phone":"+1 262 552 2657",
    "sg:postcode":"53144",
    "sg:province":"WI",
    "sg:tags":[
        "medical"
    ],
    "wof:name":"Gregory J Capelli MD",
    "wof:placetype":"venue"
},
  "geometry": {"coordinates":[-87.860111,42.654146],"type":"Point"}
}