{
  "type": "Feature",
  "properties": {
    "iso:country":"US",
    "sg:address":"107 South St W",
    "sg:city":"Amery",
    "sg:classifiers":[
        {
            "category":"Retail",
            "subcategory":"Self-service Laundry",
            "type":"Services"
        }
    ],
    "sg:phone":"+1 715 246 7189",
    "sg:postcode":"54001",
    "sg:province":"WI",
    "sg:tags":[
        "coin"
    ],
    "wof:name":"Laundry Basket Launderette",
    "wof:placetype":"venue"
},
  "geometry": {"coordinates":[-92.362234,45.305026],"type":"Point"}
}