{
  "type": "Feature",
  "properties": {
    "iso:country":"US",
    "sg:address":"141 Cherry St",
    "sg:city":"Campbellsport",
    "sg:classifiers":[
        {
            "category":"Personal",
            "type":"Services"
        }
    ],
    "sg:phone":"+1 920 533 3456",
    "sg:postcode":"53010",
    "sg:province":"WI",
    "wof:name":"Soothing Enrgy Massage Therapy",
    "wof:placetype":"venue"
},
  "geometry": {"coordinates":[-88.283539,43.596442],"type":"Point"}
}