{
  "type": "Feature",
  "properties": {
    "iso:country":"US",
    "sg:address":"6024 W Mitchell St",
    "sg:city":"Milwaukee",
    "sg:classifiers":[
        {
            "category":"Retail",
            "subcategory":"Auto Repair",
            "type":"Services"
        }
    ],
    "sg:phone":"+1 414 545 9211",
    "sg:postcode":"53214",
    "sg:province":"WI",
    "sg:tags":[
        "body",
        "repairing",
        "shop",
        "automotive",
        "automobile",
        "painting"
    ],
    "sg:website":"http://www.autobodyspecialistsllc.com",
    "wof:name":"Auto Body Specialists Llc",
    "wof:placetype":"venue"
},
  "geometry": {"coordinates":[-87.98769799999999,43.012278],"type":"Point"}
}