{
  "type": "Feature",
  "properties": {
    "iso:country":"US",
    "sg:address":"19 Crowfoot Ct",
    "sg:city":"Fond Du Lac",
    "sg:classifiers":[
        {
            "category":"Professional",
            "subcategory":"Accounting & Tax Preparation",
            "type":"Services"
        }
    ],
    "sg:phone":"+1 920 921 5838",
    "sg:postcode":"54935",
    "sg:province":"WI",
    "sg:tags":[
        "return",
        "filing"
    ],
    "wof:name":"Christenson Business Svc Inc",
    "wof:placetype":"venue"
},
  "geometry": {"coordinates":[-88.408649,43.767686],"type":"Point"}
}