{
  "type": "Feature",
  "properties": {
    "iso:country":"US",
    "sg:address":"219 Schober St",
    "sg:city":"Green Bay",
    "sg:classifiers":[
        {
            "category":"Building & Trades",
            "subcategory":"Construction",
            "type":"Services"
        }
    ],
    "sg:phone":"+1 920 405 6489",
    "sg:postcode":"54302",
    "sg:province":"WI",
    "sg:tags":[
        "roofing",
        "contractor"
    ],
    "wof:name":"All Weather Roofing",
    "wof:placetype":"venue"
},
  "geometry": {"coordinates":[-87.976888,44.499161],"type":"Point"}
}