{
  "type": "Feature",
  "properties": {
    "iso:country":"US",
    "sg:address":"107 S Dousman St",
    "sg:city":"Wauzeka",
    "sg:classifiers":[
        {
            "category":"Organizations",
            "subcategory":"Religious Organization",
            "type":"Services"
        }
    ],
    "sg:phone":"+1 608 875 7701",
    "sg:postcode":"53826",
    "sg:province":"WI",
    "sg:tags":[
        "church"
    ],
    "wof:name":"St Paul Lutheran Church",
    "wof:placetype":"venue"
},
  "geometry": {"coordinates":[-90.880879,43.085901],"type":"Point"}
}