{
  "type": "Feature",
  "properties": {
    "addr:full":"6011 W Bradley Rd Milwaukee WI 53223",
    "addr:housenumber":"6011",
    "addr:postcode":"53223",
    "addr:street":"W Bradley Rd",
    "iso:country":"US",
    "sg:address":"6011 W Bradley Rd",
    "sg:city":"Milwaukee",
    "sg:classifiers":[
        {
            "category":"Food & Beverages",
            "subcategory":"Groceries & Convenience Stores",
            "type":"Retail Goods"
        }
    ],
    "sg:phone":"+1 414 354 4748",
    "sg:postcode":"53223",
    "sg:province":"WI",
    "wof:name":"Citgo East Layton",
    "wof:placetype":"venue"
},
  "geometry": {"coordinates":[-87.989181,43.163063],"type":"Point"}
}