{
  "type": "Feature",
  "properties": {
    "iso:country":"US",
    "sg:address":"7727 W Greenfield Ave",
    "sg:city":"Milwaukee",
    "sg:classifiers":[
        {
            "category":"Restaurant",
            "type":"Food & Drink"
        }
    ],
    "sg:menulink":"http://www.allmenus.com/wi/west-allis/141440-pegasus-restaurant/menu/",
    "sg:phone":"+1 414 774 4828",
    "sg:postcode":"53214",
    "sg:province":"WI",
    "sg:tags":[
        "american"
    ],
    "wof:name":"Pegasus Restaurant",
    "wof:placetype":"venue"
},
  "geometry": {"coordinates":[-88.00884000000001,43.016633],"type":"Point"}
}