{
  "type": "Feature",
  "properties": {
    "addr:full":"212 E Main St Sun Prairie WI 53590",
    "addr:housenumber":"212",
    "addr:postcode":"53590",
    "addr:street":"E Main St",
    "iso:country":"US",
    "sg:address":"212 E Main St",
    "sg:city":"Sun Prairie",
    "sg:classifiers":[
        {
            "category":"Banks & Credit Unions",
            "subcategory":"Investment Brokerage",
            "type":"Services"
        }
    ],
    "sg:phone":"+1 608 837 2700",
    "sg:postcode":"53590",
    "sg:province":"WI",
    "sg:tags":[
        "stock",
        "bond"
    ],
    "wof:name":"Edward Jones Co",
    "wof:placetype":"venue"
},
  "geometry": {"coordinates":[-89.212484,43.183266],"type":"Point"}
}