{
  "type": "Feature",
  "properties": {
    "addr:full":"2030 Yelk Rd Marshall WI 53559",
    "addr:housenumber":"2030",
    "addr:postcode":"53559",
    "addr:street":"Yelk Rd",
    "iso:country":"US",
    "sg:address":"2030 Yelk Rd",
    "sg:city":"Marshall",
    "sg:classifiers":[
        {
            "category":"Real Estate",
            "subcategory":"Developer",
            "type":"Services"
        }
    ],
    "sg:phone":"+1 608 837 4366",
    "sg:postcode":"53559",
    "sg:province":"WI",
    "wof:name":"Cottage Grove Golf Dev Co LLC",
    "wof:placetype":"venue"
},
  "geometry": {"coordinates":[-89.16037,43.166731],"type":"Point"}
}