{
  "type": "Feature",
  "properties": {
    "addr:full":"2414 Grandview Ln Eden WI 53019",
    "addr:housenumber":"2414",
    "addr:postcode":"53019",
    "addr:street":"Grandview Ln",
    "iso:country":"US",
    "sg:address":"2414 Grandview Ln",
    "sg:city":"Eden",
    "sg:classifiers":[
        {
            "category":"Farming",
            "subcategory":"Dairy Farm",
            "type":"Manufacturing & Wholesale Goods"
        }
    ],
    "sg:phone":"+1 920 477 5188",
    "sg:postcode":"53019",
    "sg:province":"WI",
    "wof:name":"Roger Soyk",
    "wof:placetype":"venue"
},
  "geometry": {"coordinates":[-88.27396400000001,43.708128],"type":"Point"}
}