{
  "type": "Feature",
  "properties": {
    "iso:country":"US",
    "sg:address":"4380 S 76th St",
    "sg:city":"Milwaukee",
    "sg:classifiers":[
        {
            "category":"Wholesale",
            "subcategory":"Medical Equipment & Supplies",
            "type":"Manufacturing & Wholesale Goods"
        }
    ],
    "sg:phone":"+1 414 321 1542",
    "sg:postcode":"53220",
    "sg:province":"WI",
    "sg:tags":[
        "physician",
        "surgeon"
    ],
    "wof:name":"Body Jewelry Rescue",
    "wof:placetype":"venue"
},
  "geometry": {"coordinates":[-88.008127,42.964808],"type":"Point"}
}