{
  "type": "Feature",
  "properties": {
    "addr:full":"4421 Marken Rd Valders WI 54245",
    "addr:housenumber":"4421",
    "addr:postcode":"54245",
    "addr:street":"Marken Rd",
    "iso:country":"US",
    "sg:address":"4421 Marken Rd",
    "sg:city":"Valders",
    "sg:classifiers":[
        {
            "category":"Retail",
            "subcategory":"Auto Repair",
            "type":"Services"
        }
    ],
    "sg:phone":"+1 920 775 4959",
    "sg:postcode":"54245",
    "sg:province":"WI",
    "sg:tags":[
        "body"
    ],
    "wof:name":"Liberty Auto Body",
    "wof:placetype":"venue"
},
  "geometry": {"coordinates":[-87.902008,44.045514],"type":"Point"}
}