{
  "type": "Feature",
  "properties": {
    "addr:full":"1040 Parker Dr Mauston WI 53948",
    "addr:housenumber":"1040",
    "addr:postcode":"53948",
    "addr:street":"Parker Dr",
    "iso:country":"US",
    "sg:address":"1040 Parker Dr",
    "sg:city":"Mauston",
    "sg:classifiers":[
        {
            "category":"Manufacturing",
            "subcategory":"Tools & Machinery",
            "type":"Manufacturing & Wholesale Goods"
        }
    ],
    "sg:phone":"+1 608 847 6233",
    "sg:postcode":"53948",
    "sg:province":"WI",
    "sg:tags":[
        "valve",
        "mfg"
    ],
    "wof:name":"Parker Hannifin Corporation",
    "wof:placetype":"venue"
},
  "geometry": {"coordinates":[-90.095208,43.804597],"type":"Point"}
}