{
  "type": "Feature",
  "properties": {
    "iso:country":"US",
    "sg:address":"2110 US Hwy 12",
    "sg:city":"Menomonie",
    "sg:classifiers":[
        {
            "category":"Health Services",
            "subcategory":"Doctor",
            "type":"Services"
        }
    ],
    "sg:phone":"+1 715 233 2020",
    "sg:postcode":"54751",
    "sg:province":"WI",
    "sg:tags":[
        "physician",
        "surgeon"
    ],
    "wof:name":"Wisconsin Vision Correction",
    "wof:placetype":"venue"
},
  "geometry": {"coordinates":[-91.90298,44.881568],"type":"Point"}
}