{
  "type": "Feature",
  "properties": {
    "iso:country":"US",
    "sg:address":"10102 Fairground Ave",
    "sg:city":"Greenwood",
    "sg:classifiers":[
        {
            "category":"Farming",
            "subcategory":"Livestock Farm",
            "type":"Manufacturing & Wholesale Goods"
        }
    ],
    "sg:phone":"+1 715 267 3212",
    "sg:postcode":"54437",
    "sg:province":"WI",
    "sg:tags":[
        "animal",
        "general"
    ],
    "wof:name":"Colby Dennis",
    "wof:placetype":"venue"
},
  "geometry": {"coordinates":[-90.577887,44.781193],"type":"Point"}
}