{
  "type": "Feature",
  "properties": {
    "addr:full":"609 S Park St Madison WI 53715",
    "addr:housenumber":"609",
    "addr:postcode":"53715",
    "addr:street":"S Park St",
    "iso:country":"US",
    "sg:address":"609 S Park St",
    "sg:city":"Madison",
    "sg:classifiers":[
        {
            "category":"Personal",
            "subcategory":"Shoe Repair & Shine",
            "type":"Services"
        }
    ],
    "sg:phone":"+1 608 256 4001",
    "sg:postcode":"53715",
    "sg:province":"WI",
    "sg:tags":[
        "repairing",
        "parlor",
        "boot"
    ],
    "wof:name":"Park Street Shoe Repair",
    "wof:placetype":"venue"
},
  "geometry": {"coordinates":[-89.400678,43.060356],"type":"Point"}
}