{
  "type": "Feature",
  "properties": {
    "iso:country":"US",
    "sg:address":"9086 South Rd",
    "sg:city":"Berlin",
    "sg:classifiers":[
        {
            "category":"Shopping",
            "subcategory":"Bicycles & Sporting Goods",
            "type":"Retail Goods"
        }
    ],
    "sg:phone":"+1 920 361 3514",
    "sg:postcode":"54923",
    "sg:province":"WI",
    "sg:tags":[
        "saddlery",
        "harness"
    ],
    "wof:name":"Sand Box Tack Shop",
    "wof:placetype":"venue"
},
  "geometry": {"coordinates":[-89.125959,43.955484],"type":"Point"}
}