{
  "type": "Feature",
  "properties": {
    "iso:country":"US",
    "sg:address":"14281 W Sterling Rd",
    "sg:city":"Alma Center",
    "sg:classifiers":[
        {
            "category":"Farming",
            "subcategory":"Dairy Farm",
            "type":"Manufacturing & Wholesale Goods"
        }
    ],
    "sg:phone":"+1 715 964 2941",
    "sg:postcode":"54611",
    "sg:province":"WI",
    "wof:name":"J- Lnad Farms",
    "wof:placetype":"venue"
},
  "geometry": {"coordinates":[-91.025206,44.466047],"type":"Point"}
}