{
  "type": "Feature",
  "properties": {
    "addr:full":"940 N 23rd St Milwaukee WI 53233",
    "addr:housenumber":"940",
    "addr:postcode":"53233",
    "addr:street":"N 23Rd St",
    "iso:country":"US",
    "sg:address":"940 N 23rd St",
    "sg:city":"Milwaukee",
    "sg:classifiers":[
        {
            "category":"Organizations",
            "subcategory":"Non-profit Organization",
            "type":"Services"
        }
    ],
    "sg:phone":"+1 414 937 8260",
    "sg:postcode":"53233",
    "sg:province":"WI",
    "wof:name":"Milwaukee Careers Cooperative",
    "wof:placetype":"venue"
},
  "geometry": {"coordinates":[-87.941487,43.042569],"type":"Point"}
}