{
  "type": "Feature",
  "properties": {
    "addr:full":"525 Wright Rd Johnson Creek WI 53038",
    "addr:housenumber":"525",
    "addr:postcode":"53038",
    "addr:street":"Wright Rd",
    "iso:country":"US",
    "sg:address":"525 Wright Rd",
    "sg:city":"Johnson Creek",
    "sg:classifiers":[
        {
            "category":"Restaurant",
            "type":"Food & Drink"
        }
    ],
    "sg:menulink":"http://www.allmenus.com/wi/johnson-creek/145537-subway/menu/",
    "sg:phone":"+1 920 699 2669",
    "sg:postcode":"53038",
    "sg:province":"WI",
    "sg:tags":[
        "american",
        "sandwich"
    ],
    "wof:name":"Subway",
    "wof:placetype":"venue"
},
  "geometry": {"coordinates":[-88.758736,43.085367],"type":"Point"}
}