{
  "type": "Feature",
  "properties": {
    "iso:country":"US",
    "sg:address":"8401 Klappstein Rd",
    "sg:city":"Portage",
    "sg:classifiers":[
        {
            "category":"Building & Trades",
            "subcategory":"Construction",
            "type":"Services"
        }
    ],
    "sg:phone":"+1 608 742 5433",
    "sg:postcode":"53901",
    "sg:province":"WI",
    "sg:tags":[
        "concrete",
        "contractor"
    ],
    "wof:name":"Hurd Masonry LLC",
    "wof:placetype":"venue"
},
  "geometry": {"coordinates":[-89.543825,43.591775],"type":"Point"}
}