{
  "type": "Feature",
  "properties": {
    "addr:full":"1510 E Blodgett St Marshfield WI 54449",
    "addr:housenumber":"1510",
    "addr:postcode":"54449",
    "addr:street":"E Blodgett St",
    "iso:country":"US",
    "sg:address":"1510 E Blodgett St",
    "sg:city":"Marshfield",
    "sg:classifiers":[
        {
            "category":"Professional",
            "subcategory":"Business Services",
            "type":"Services"
        }
    ],
    "sg:phone":"+1 715 387 6740",
    "sg:postcode":"54449",
    "sg:province":"WI",
    "wof:name":"Steve Cox Production",
    "wof:placetype":"venue"
},
  "geometry": {"coordinates":[-90.154659,44.663451],"type":"Point"}
}