{
  "type": "Feature",
  "properties": {
    "iso:country":"US",
    "sg:address":"121 Kleeman Ct",
    "sg:city":"Shawano",
    "sg:classifiers":[
        {
            "category":"Building & Trades",
            "subcategory":"Construction",
            "type":"Services"
        }
    ],
    "sg:phone":"+1 715 526 9837",
    "sg:postcode":"54166",
    "sg:province":"WI",
    "sg:tags":[
        "house"
    ],
    "wof:name":"United Crafts Inc",
    "wof:placetype":"venue"
},
  "geometry": {"coordinates":[-88.607892,44.762997],"type":"Point"}
}