{
  "type": "Feature",
  "properties": {
    "iso:country":"US",
    "sg:address":"9126 W North Ave",
    "sg:city":"Milwaukee",
    "sg:classifiers":[
        {
            "category":"Home & Garden",
            "subcategory":"Building Materials",
            "type":"Retail Goods"
        }
    ],
    "sg:phone":"+1 414 258 8640",
    "sg:postcode":"53226",
    "sg:province":"WI",
    "sg:tags":[
        "blinds-venetian",
        "vertical"
    ],
    "wof:name":"Wallpaper Wallpaper",
    "wof:placetype":"venue"
},
  "geometry": {"coordinates":[-88.026532,43.060475],"type":"Point"}
}