{
  "type": "Feature",
  "properties": {
    "iso:country":"US",
    "sg:address":"3912 Sheridan Rd",
    "sg:city":"Racine",
    "sg:classifiers":[
        {
            "category":"Retail",
            "subcategory":"Laundry & Dry Cleaning",
            "type":"Services"
        }
    ],
    "sg:phone":"+1 262 633 9952",
    "sg:postcode":"53403",
    "sg:province":"WI",
    "sg:tags":[
        "cleaners",
        "rug",
        "carpet"
    ],
    "wof:name":"Funderburg's Pro Carpet Clean",
    "wof:placetype":"venue"
},
  "geometry": {"coordinates":[-87.79710900000001,42.686212],"type":"Point"}
}