{
  "type": "Feature",
  "properties": {
    "addr:full":"100 S Main St Cochrane WI 54622",
    "addr:housenumber":"100",
    "addr:postcode":"54622",
    "addr:street":"S Main St",
    "iso:country":"US",
    "sg:address":"100 S Main St",
    "sg:city":"Cochrane",
    "sg:classifiers":[
        {
            "category":"Professional",
            "subcategory":"Lawyer & Legal Services",
            "type":"Services"
        }
    ],
    "sg:phone":"+1 608 248 2202",
    "sg:postcode":"54622",
    "sg:province":"WI",
    "sg:tags":[
        "attorney"
    ],
    "wof:name":"C Michael Chambers Law Office",
    "wof:placetype":"venue"
},
  "geometry": {"coordinates":[-91.835736,44.227292],"type":"Point"}
}