{
  "type": "Feature",
  "properties": {
    "iso:country":"US",
    "sg:address":"1122 N Astor St",
    "sg:city":"Milwaukee",
    "sg:classifiers":[
        {
            "category":"Place Of Worship",
            "subcategory":"Church",
            "type":"Public Place"
        },
        {
            "category":"Place Of Worship",
            "type":"Public Place"
        }
    ],
    "sg:phone":"+1 414 226 0097",
    "sg:postcode":"53202",
    "sg:province":"WI",
    "sg:tags":[
        "churches-salvation",
        "army"
    ],
    "wof:name":"Proteus",
    "wof:placetype":"venue"
},
  "geometry": {"coordinates":[-87.899688,43.045089],"type":"Point"}
}