{
  "type": "Feature",
  "properties": {
    "iso:country":"US",
    "sg:address":"1970 Rainbow Rd",
    "sg:city":"Spooner",
    "sg:classifiers":[
        {
            "category":"Travel",
            "subcategory":"Hotels & Motels",
            "type":"Entertainment"
        }
    ],
    "sg:phone":"+1 715 635 2390",
    "sg:postcode":"54801",
    "sg:province":"WI",
    "sg:tags":[
        "resort"
    ],
    "wof:name":"Rainbow Bay Resort",
    "wof:placetype":"venue"
},
  "geometry": {"coordinates":[-92.083423,45.898708],"type":"Point"}
}