{
  "type": "Feature",
  "properties": {
    "addr:full":"14405 Doe Ave Colby WI 54421",
    "addr:housenumber":"14405",
    "addr:postcode":"54421",
    "addr:street":"Doe Ave",
    "iso:country":"US",
    "sg:address":"14405 Doe Ave",
    "sg:city":"Colby",
    "sg:classifiers":[
        {
            "category":"Farming",
            "subcategory":"Farm",
            "type":"Manufacturing & Wholesale Goods"
        }
    ],
    "sg:phone":"+1 715 223 6244",
    "sg:postcode":"54421",
    "sg:province":"WI",
    "sg:tags":[
        "crop",
        "general"
    ],
    "wof:name":"Schindler Farms Inc",
    "wof:placetype":"venue"
},
  "geometry": {"coordinates":[-90.387236,44.938445],"type":"Point"}
}