{
  "type": "Feature",
  "properties": {
    "iso:country":"US",
    "sg:address":"819 Service Rd",
    "sg:city":"Kiel",
    "sg:classifiers":[
        {
            "category":"Food & Beverages",
            "subcategory":"Liquor & Beverages",
            "type":"Retail Goods"
        }
    ],
    "sg:phone":"+1 920 894 4855",
    "sg:postcode":"53042",
    "sg:province":"WI",
    "wof:name":"Nigrelli's",
    "wof:placetype":"venue"
},
  "geometry": {"coordinates":[-88.022873,43.917568],"type":"Point"}
}