{
  "type": "Feature",
  "properties": {
    "iso:country":"US",
    "sg:address":"5614 Lake End Rd",
    "sg:city":"Rhinelander",
    "sg:classifiers":[
        {
            "category":"Personal",
            "subcategory":"Beauty Salon",
            "type":"Services"
        }
    ],
    "sg:phone":"+1 715 362 0401",
    "sg:postcode":"54501",
    "sg:province":"WI",
    "wof:name":"Look",
    "wof:placetype":"venue"
},
  "geometry": {"coordinates":[-89.43807700000001,45.618832],"type":"Point"}
}