{
  "type": "Feature",
  "properties": {
    "addr:full":"3008 S 14th St Milwaukee WI 53215",
    "addr:housenumber":"3008",
    "addr:postcode":"53215",
    "addr:street":"S 14Th St",
    "iso:country":"US",
    "sg:address":"3008 S 14th St",
    "sg:city":"Milwaukee",
    "sg:classifiers":[
        {
            "category":"Shopping",
            "type":"Retail Goods"
        }
    ],
    "sg:phone":"+1 414 672 4049",
    "sg:postcode":"53215",
    "sg:province":"WI",
    "sg:tags":[
        "merchandise"
    ],
    "wof:name":"Multi-Pure Drinking Water Syst",
    "wof:placetype":"venue"
},
  "geometry": {"coordinates":[-87.930082,42.988432],"type":"Point"}
}