{
  "type": "Feature",
  "properties": {
    "addr:full":"225 Regency Ct Brookfield WI 53045",
    "addr:housenumber":"225",
    "addr:postcode":"53045",
    "addr:street":"Regency Ct",
    "iso:country":"US",
    "sg:address":"225 Regency Ct",
    "sg:city":"Brookfield",
    "sg:classifiers":[
        {
            "category":"Banks & Credit Unions",
            "subcategory":"Bank",
            "type":"Services"
        }
    ],
    "sg:phone":"+1 262 787 0900",
    "sg:postcode":"53045",
    "sg:province":"WI",
    "sg:tags":[
        "loan",
        "real estate"
    ],
    "wof:name":"DSI",
    "wof:placetype":"venue"
},
  "geometry": {"coordinates":[-88.149698,43.034274],"type":"Point"}
}