{
  "type": "Feature",
  "properties": {
    "iso:country":"US",
    "sg:address":"1119 Hammond Ave",
    "sg:city":"Superior",
    "sg:classifiers":[
        {
            "category":"Shopping",
            "type":"Retail Goods"
        }
    ],
    "sg:phone":"+1 715 395 7723",
    "sg:postcode":"54880",
    "sg:province":"WI",
    "sg:tags":[
        "merchandise"
    ],
    "wof:name":"North Country Pet Sitting",
    "wof:placetype":"venue"
},
  "geometry": {"coordinates":[-92.09793,46.724464],"type":"Point"}
}