{
  "type": "Feature",
  "properties": {
    "iso:country":"US",
    "sg:address":"1610 N Prospect Ave",
    "sg:city":"Milwaukee",
    "sg:classifiers":[
        {
            "category":"Professional",
            "subcategory":"Computer Services",
            "type":"Services"
        }
    ],
    "sg:phone":"+1 414 224 7727",
    "sg:postcode":"53202",
    "sg:province":"WI",
    "sg:tags":[
        "related"
    ],
    "wof:name":"Harmon Ics Inc",
    "wof:placetype":"venue"
},
  "geometry": {"coordinates":[-87.89017,43.053272],"type":"Point"}
}