{
  "type": "Feature",
  "properties": {
    "iso:country":"US",
    "sg:address":"9512 Washington Ave",
    "sg:city":"Racine",
    "sg:classifiers":[
        {
            "category":"Building & Trades",
            "subcategory":"Construction",
            "type":"Services"
        }
    ],
    "sg:phone":"+1 262 886 6419",
    "sg:postcode":"53406",
    "sg:province":"WI",
    "sg:tags":[
        "general",
        "contractor"
    ],
    "wof:name":"Michael Thomas Constr Inc",
    "wof:placetype":"venue"
},
  "geometry": {"coordinates":[-87.904184,42.719859],"type":"Point"}
}