{
  "type": "Feature",
  "properties": {
    "addr:full":"2715 S Slope Ter Eau Claire WI 54703",
    "addr:housenumber":"2715",
    "addr:postcode":"54703",
    "addr:street":"S Slope Ter",
    "iso:country":"US",
    "sg:address":"2715 S Slope Ter",
    "sg:city":"Eau Claire",
    "sg:classifiers":[
        {
            "category":"Arts & Performance",
            "subcategory":"Theater",
            "type":"Entertainment"
        }
    ],
    "sg:phone":"+1 715 834 6412",
    "sg:postcode":"54703",
    "sg:province":"WI",
    "sg:tags":[
        "group"
    ],
    "wof:name":"Chippewa Valley Dance Festival",
    "wof:placetype":"venue"
},
  "geometry": {"coordinates":[-91.470384,44.822324],"type":"Point"}
}