{
  "type": "Feature",
  "properties": {
    "iso:country":"US",
    "sg:address":"2588 Summerville Park Rd",
    "sg:city":"Lodi",
    "sg:classifiers":[
        {
            "category":"Manufacturing",
            "subcategory":"Tools & Machinery",
            "type":"Manufacturing & Wholesale Goods"
        }
    ],
    "sg:phone":"+1 608 592 3838",
    "sg:postcode":"53555",
    "sg:province":"WI",
    "sg:tags":[
        "machine",
        "shop"
    ],
    "wof:name":"Atkinson Engineering",
    "wof:placetype":"venue"
},
  "geometry": {"coordinates":[-89.571381,43.366076],"type":"Point"}
}