{
  "type": "Feature",
  "properties": {
    "iso:country":"US",
    "sg:address":"220 E Racine St",
    "sg:city":"Jefferson",
    "sg:classifiers":[
        {
            "category":"Health Services",
            "subcategory":"Chiropractor",
            "type":"Services"
        }
    ],
    "sg:phone":"+1 920 674 6108",
    "sg:postcode":"53549",
    "sg:province":"WI",
    "wof:name":"Volk Chiropractic",
    "wof:placetype":"venue"
},
  "geometry": {"coordinates":[-88.805035,43.00519],"type":"Point"}
}