{
  "type": "Feature",
  "properties": {
    "addr:full":"3748 Silica Rd Fond Du Lac WI 54935",
    "addr:housenumber":"3748",
    "addr:postcode":"54935",
    "addr:street":"Silica Rd",
    "iso:country":"US",
    "sg:address":"3748 Silica Rd",
    "sg:city":"Fond Du Lac",
    "sg:classifiers":[
        {
            "category":"Building & Trades",
            "subcategory":"Construction",
            "type":"Services"
        }
    ],
    "sg:phone":"+1 920 921 4433",
    "sg:postcode":"54935",
    "sg:province":"WI",
    "sg:tags":[
        "excavation",
        "contractor"
    ],
    "wof:name":"Simon Stone & Excavating",
    "wof:placetype":"venue"
},
  "geometry": {"coordinates":[-88.344347,43.848247],"type":"Point"}
}