{
  "type": "Feature",
  "properties": {
    "iso:country":"US",
    "sg:address":"635 Riverfront Dr",
    "sg:city":"Sheboygan",
    "sg:classifiers":[
        {
            "category":"Shopping",
            "subcategory":"Clothing, Apparel, & Fashions",
            "type":"Retail Goods"
        }
    ],
    "sg:phone":"+1 920 451 3084",
    "sg:postcode":"53081",
    "sg:province":"WI",
    "sg:tags":[
        "store"
    ],
    "wof:name":"T L C Casual",
    "wof:placetype":"venue"
},
  "geometry": {"coordinates":[-87.711147,43.748211],"type":"Point"}
}