{
  "type": "Feature",
  "properties": {
    "iso:country":"US",
    "sg:address":"840 N Grand Ave",
    "sg:city":"Waukesha",
    "sg:classifiers":[
        {
            "category":"Professional",
            "type":"Services"
        }
    ],
    "sg:phone":"+1 262 547 4860",
    "sg:postcode":"53186",
    "sg:province":"WI",
    "wof:name":"Por Ella Tax Svc",
    "wof:placetype":"venue"
},
  "geometry": {"coordinates":[-88.231669,43.01119],"type":"Point"}
}