{
  "type": "Feature",
  "properties": {
    "iso:country":"US",
    "sg:address":"6150 E Buckatabon Rd",
    "sg:city":"Conover",
    "sg:classifiers":[
        {
            "category":"Travel",
            "subcategory":"Campground",
            "type":"Entertainment"
        }
    ],
    "sg:phone":"+1 715 479 4400",
    "sg:postcode":"54519",
    "sg:province":"WI",
    "sg:tags":[
        "camp",
        "trailer"
    ],
    "wof:name":"Camp Ramah",
    "wof:placetype":"venue"
},
  "geometry": {"coordinates":[-89.352362,46.005114],"type":"Point"}
}