{
  "type": "Feature",
  "properties": {
    "iso:country":"US",
    "sg:address":"9810 Ridgeview Dr",
    "sg:city":"Oak Creek",
    "sg:classifiers":[
        {
            "category":"Freight",
            "type":"Transportation"
        }
    ],
    "sg:phone":"+1 414 304 7777",
    "sg:postcode":"53154",
    "sg:province":"WI",
    "sg:tags":[
        "consultant"
    ],
    "wof:name":"Diamond Logistics Inc",
    "wof:placetype":"venue"
},
  "geometry": {"coordinates":[-87.93953399999999,42.86496],"type":"Point"}
}