{
  "type": "Feature",
  "properties": {
    "iso:country":"US",
    "sg:address":"5037 US Hwy 51",
    "sg:city":"Mercer",
    "sg:classifiers":[
        {
            "category":"Shopping",
            "subcategory":"Crafts & Fabrics",
            "type":"Retail Goods"
        }
    ],
    "sg:phone":"+1 715 476 9180",
    "sg:postcode":"54547",
    "sg:province":"WI",
    "sg:tags":[
        "shop",
        "sewing"
    ],
    "wof:name":"Sampler",
    "wof:placetype":"venue"
},
  "geometry": {"coordinates":[-90.05109899999999,46.160039],"type":"Point"}
}