{
  "type": "Feature",
  "properties": {
    "iso:country":"US",
    "sg:address":"1712 W 6th St",
    "sg:city":"Racine",
    "sg:classifiers":[
        {
            "category":"Professional",
            "subcategory":"Lawyer & Legal Services",
            "type":"Services"
        }
    ],
    "sg:phone":"+1 262 633 4557",
    "sg:postcode":"53404",
    "sg:province":"WI",
    "sg:tags":[
        "attorney"
    ],
    "wof:name":"David Saldana",
    "wof:placetype":"venue"
},
  "geometry": {"coordinates":[-87.802655,42.726059],"type":"Point"}
}