{
  "type": "Feature",
  "properties": {
    "iso:country":"US",
    "sg:address":"6136 S 27th St",
    "sg:city":"Milwaukee",
    "sg:classifiers":[
        {
            "category":"Autos & Motor Vehicles",
            "subcategory":"Fuel & Gas Station",
            "type":"Retail Goods"
        }
    ],
    "sg:phone":"+1 414 761 1330",
    "sg:postcode":"53221",
    "sg:province":"WI",
    "sg:tags":[
        "automotive",
        "filling",
        "station",
        "general",
        "repair"
    ],
    "wof:name":"Deinleins Tri City Service",
    "wof:placetype":"venue"
},
  "geometry": {"coordinates":[-87.949253,42.933141],"type":"Point"}
}