{
  "type": "Feature",
  "properties": {
    "iso:country":"US",
    "sg:address":"6521 Co Rd A I",
    "sg:city":"Juneau",
    "sg:classifiers":[
        {
            "category":"Farming",
            "subcategory":"Dairy Farm",
            "type":"Manufacturing & Wholesale Goods"
        }
    ],
    "sg:phone":"+1 920 887 9247",
    "sg:postcode":"53039",
    "sg:province":"WI",
    "wof:name":"Westhoff Farms",
    "wof:placetype":"venue"
},
  "geometry": {"coordinates":[-88.744457,43.423028],"type":"Point"}
}