{
  "type": "Feature",
  "properties": {
    "iso:country":"US",
    "sg:address":"2437 W Bolivar Ave",
    "sg:city":"Milwaukee",
    "sg:classifiers":[
        {
            "category":"Manufacturing",
            "subcategory":"Tools & Machinery",
            "type":"Manufacturing & Wholesale Goods"
        }
    ],
    "sg:phone":"+1 414 281 9198",
    "sg:postcode":"53221",
    "sg:province":"WI",
    "sg:tags":[
        "machine",
        "mfg"
    ],
    "wof:name":"Badger Machinery Svc",
    "wof:placetype":"venue"
},
  "geometry": {"coordinates":[-87.941981,42.966541],"type":"Point"}
}