{
  "type": "Feature",
  "properties": {
    "iso:country":"US",
    "sg:address":"1539 22nd St",
    "sg:city":"Cameron",
    "sg:classifiers":[
        {
            "category":"Organizations",
            "subcategory":"Non-profit Organization",
            "type":"Services"
        }
    ],
    "sg:phone":"+1 715 458 2187",
    "sg:postcode":"54822",
    "sg:province":"WI",
    "sg:tags":[
        "social"
    ],
    "wof:name":"Cameron Area 1st Responder",
    "wof:placetype":"venue"
},
  "geometry": {"coordinates":[-91.703953,45.423109],"type":"Point"}
}