{
  "type": "Feature",
  "properties": {
    "iso:country":"US",
    "sg:address":"9196 Hidden Valley Pl",
    "sg:city":"Cambridge",
    "sg:classifiers":[
        {
            "category":"Professional",
            "subcategory":"Advertising",
            "type":"Services"
        }
    ],
    "sg:phone":"+1 608 423 1500",
    "sg:postcode":"53523",
    "sg:province":"WI",
    "sg:tags":[
        "agency"
    ],
    "wof:name":"Advertising By Design",
    "wof:placetype":"venue"
},
  "geometry": {"coordinates":[-88.986225,43.013583],"type":"Point"}
}