{
  "type": "Feature",
  "properties": {
    "iso:country":"US",
    "sg:address":"3136 Co Rd Qq",
    "sg:city":"Waupaca",
    "sg:classifiers":[
        {
            "category":"Organizations",
            "subcategory":"Religious Organization",
            "type":"Services"
        }
    ],
    "sg:phone":"+1 715 258 8061",
    "sg:postcode":"54981",
    "sg:province":"WI",
    "sg:tags":[
        "church"
    ],
    "wof:name":"Shepherd Of The Lakes Lutheran",
    "wof:placetype":"venue"
},
  "geometry": {"coordinates":[-89.118265,44.356004],"type":"Point"}
}