{
  "type": "Feature",
  "properties": {
    "addr:full":"3274 N 77th St Milwaukee WI 53222",
    "addr:housenumber":"3274",
    "addr:postcode":"53222",
    "addr:street":"N 77Th St",
    "iso:country":"US",
    "sg:address":"3274 N 77th St",
    "sg:city":"Milwaukee",
    "sg:classifiers":[
        {
            "category":"Banks & Credit Unions",
            "subcategory":"Bank",
            "type":"Services"
        }
    ],
    "sg:phone":"+1 414 444 8300",
    "sg:postcode":"53222",
    "sg:province":"WI",
    "sg:tags":[
        "mortgage",
        "loan",
        "broker",
        "real estate"
    ],
    "wof:name":"Mortgage Alternatives Inc",
    "wof:placetype":"venue"
},
  "geometry": {"coordinates":[-88.00852399999999,43.080334],"type":"Point"}
}