{
  "type": "Feature",
  "properties": {
    "iso:country":"US",
    "sg:address":"247 Hillcrest Ln",
    "sg:city":"Fond Du Lac",
    "sg:classifiers":[
        {
            "category":"Building & Trades",
            "subcategory":"Electrical",
            "type":"Services"
        }
    ],
    "sg:phone":"+1 920 921 4877",
    "sg:postcode":"54935",
    "sg:province":"WI",
    "sg:tags":[
        "electrical",
        "electric",
        "contractor"
    ],
    "wof:name":"Jake Schomner Electric Inc",
    "wof:placetype":"venue"
},
  "geometry": {"coordinates":[-88.469295,43.772813],"type":"Point"}
}