{
  "type": "Feature",
  "properties": {
    "iso:country":"US",
    "sg:address":"30954 Vergon Dr",
    "sg:city":"Burlington",
    "sg:classifiers":[
        {
            "category":"Wholesale",
            "subcategory":"Electrical",
            "type":"Manufacturing & Wholesale Goods"
        },
        {
            "category":"Professional",
            "subcategory":"Computer Services",
            "type":"Services"
        }
    ],
    "sg:phone":"+1 262 534 9012",
    "sg:postcode":"53105",
    "sg:province":"WI",
    "sg:tags":[
        "hardware",
        "equipment",
        "support",
        "provides",
        "communications"
    ],
    "wof:name":"Cornerstone Communications Inc",
    "wof:placetype":"venue"
},
  "geometry": {"coordinates":[-88.234863,42.721263],"type":"Point"}
}