{
  "type": "Feature",
  "properties": {
    "iso:country":"US",
    "sg:address":"2331 E Lourdes Dr",
    "sg:city":"Appleton",
    "sg:classifiers":[
        {
            "category":"Education",
            "subcategory":"School",
            "type":"Public Place"
        }
    ],
    "sg:phone":"+1 920 739 5391",
    "sg:postcode":"54915",
    "sg:province":"WI",
    "wof:name":"St Bernadette School",
    "wof:placetype":"venue"
},
  "geometry": {"coordinates":[-88.37079199999999,44.252492],"type":"Point"}
}