{
  "type": "Feature",
  "properties": {
    "iso:country":"US",
    "sg:address":"2179 Fairgrounds Rd",
    "sg:city":"St Croix Falls",
    "sg:classifiers":[
        {
            "category":"Personal",
            "subcategory":"Barber",
            "type":"Services"
        }
    ],
    "sg:phone":"+1 715 483 9327",
    "sg:postcode":"54024",
    "sg:province":"WI",
    "wof:name":"Cathy's Barber Shop",
    "wof:placetype":"venue"
},
  "geometry": {"coordinates":[-92.60884,45.418852],"type":"Point"}
}