{
  "type": "Feature",
  "properties": {
    "iso:country":"US",
    "sg:address":"1323 Co Rd Aa",
    "sg:city":"Nekoosa",
    "sg:classifiers":[
        {
            "category":"Farming",
            "subcategory":"Nursery",
            "type":"Manufacturing & Wholesale Goods"
        }
    ],
    "sg:phone":"+1 715 886 4736",
    "sg:postcode":"54457",
    "sg:province":"WI",
    "sg:tags":[
        "ornamental"
    ],
    "wof:name":"Serenity Gardens",
    "wof:placetype":"venue"
},
  "geometry": {"coordinates":[-89.89277,44.293223],"type":"Point"}
}