{
  "type": "Feature",
  "properties": {
    "iso:country":"US",
    "sg:address":"1772 Chadsworth Dr",
    "sg:city":"Sun Prairie",
    "sg:classifiers":[
        {
            "category":"Professional",
            "subcategory":"Management & Consulting",
            "type":"Services"
        }
    ],
    "sg:phone":"+1 608 837 3316",
    "sg:postcode":"53590",
    "sg:province":"WI",
    "wof:name":"Highley Consulting",
    "wof:placetype":"venue"
},
  "geometry": {"coordinates":[-89.244107,43.197337],"type":"Point"}
}