{
  "type": "Feature",
  "properties": {
    "addr:full":"13907 10th St Osseo WI 54758",
    "addr:housenumber":"13907",
    "addr:postcode":"54758",
    "addr:street":"10Th St",
    "iso:country":"US",
    "sg:address":"13907 10th St",
    "sg:city":"Osseo",
    "sg:classifiers":[
        {
            "category":"Food & Beverages",
            "subcategory":"Groceries & Convenience Stores",
            "type":"Retail Goods"
        }
    ],
    "sg:phone":"+1 715 597 3278",
    "sg:postcode":"54758",
    "sg:province":"WI",
    "wof:name":"KWIK Trip",
    "wof:placetype":"venue"
},
  "geometry": {"coordinates":[-91.224825,44.579297],"type":"Point"}
}