{
  "type": "Feature",
  "properties": {
    "iso:country":"US",
    "sg:address":"9880 Old Hwy 12",
    "sg:city":"Merrillan",
    "sg:classifiers":[
        {
            "category":"Farming",
            "subcategory":"Dairy Farm",
            "type":"Manufacturing & Wholesale Goods"
        }
    ],
    "sg:phone":"+1 715 333 6062",
    "sg:postcode":"54754",
    "sg:province":"WI",
    "wof:name":"Olson Bruce or Gayle",
    "wof:placetype":"venue"
},
  "geometry": {"coordinates":[-90.83213600000001,44.433392],"type":"Point"}
}