{
  "type": "Feature",
  "properties": {
    "addr:full":"967 Armour Rd Oconomowoc WI 53066",
    "addr:housenumber":"967",
    "addr:postcode":"53066",
    "addr:street":"Armour Rd",
    "iso:country":"US",
    "sg:address":"967 Armour Rd",
    "sg:city":"Oconomowoc",
    "sg:classifiers":[
        {
            "category":"Recreation",
            "type":"Entertainment"
        }
    ],
    "sg:phone":"+1 262 569 1147",
    "sg:postcode":"53066",
    "sg:province":"WI",
    "wof:name":"Memmel Gallery LLC",
    "wof:placetype":"venue"
},
  "geometry": {"coordinates":[-88.479258,43.103893],"type":"Point"}
}