{
  "type": "Feature",
  "properties": {
    "iso:country":"US",
    "sg:address":"4768 Bay View Ln",
    "sg:city":"Oshkosh",
    "sg:classifiers":[
        {
            "category":"Real Estate",
            "subcategory":"Real Estate Operator",
            "type":"Services"
        }
    ],
    "sg:phone":"+1 920 235 0376",
    "sg:postcode":"54902",
    "sg:province":"WI",
    "sg:tags":[
        "building",
        "nonresidential"
    ],
    "wof:name":"Nu View Properties LLC",
    "wof:placetype":"venue"
},
  "geometry": {"coordinates":[-88.50980199999999,43.952289],"type":"Point"}
}