{
  "type": "Feature",
  "properties": {
    "iso:country":"US",
    "sg:address":"1610 Birchwood Dr",
    "sg:city":"Saint Germain",
    "sg:classifiers":[
        {
            "category":"Manufacturing",
            "subcategory":"Textiles",
            "type":"Manufacturing & Wholesale Goods"
        }
    ],
    "sg:phone":"+1 715 477 2599",
    "sg:postcode":"54558",
    "sg:province":"WI",
    "sg:tags":[
        "plant",
        "silk",
        "finishing",
        "fiber"
    ],
    "wof:name":"Jr Creations LLC",
    "wof:placetype":"venue"
},
  "geometry": {"coordinates":[-89.424294,45.932544],"type":"Point"}
}