{
  "type": "Feature",
  "properties": {
    "iso:country":"US",
    "sg:address":"12531 N Woodland Dr",
    "sg:city":"Thiensville",
    "sg:classifiers":[
        {
            "category":"Organizations",
            "subcategory":"Professional Association",
            "type":"Services"
        }
    ],
    "sg:phone":"+1 262 238 1499",
    "sg:postcode":"53092",
    "sg:province":"WI",
    "sg:tags":[
        "review",
        "board"
    ],
    "wof:name":"Marsha K Konz",
    "wof:placetype":"venue"
},
  "geometry": {"coordinates":[-87.947257,43.246448],"type":"Point"}
}