{
  "type": "Feature",
  "properties": {
    "addr:full":"937 S Cesar E Chavez Dr Milwaukee WI 53204",
    "addr:housenumber":"937",
    "addr:postcode":"53204",
    "addr:street":"S Cesar E Chavez Dr",
    "iso:country":"US",
    "sg:address":"937 S Cesar E Chavez Dr",
    "sg:city":"Milwaukee",
    "sg:classifiers":[
        {
            "category":"Home & Garden",
            "subcategory":"Furniture",
            "type":"Retail Goods"
        }
    ],
    "sg:phone":"+1 414 645 4500",
    "sg:postcode":"53204",
    "sg:province":"WI",
    "sg:tags":[
        "store"
    ],
    "wof:name":"Best Quality Furniture",
    "wof:placetype":"venue"
},
  "geometry": {"coordinates":[-87.933046,43.021545],"type":"Point"}
}