{
  "type": "Feature",
  "properties": {
    "iso:country":"US",
    "sg:address":"101 S Lake St",
    "sg:city":"Hustisford",
    "sg:classifiers":[
        {
            "category":"Cinema",
            "subcategory":"Movie Rental",
            "type":"Entertainment"
        }
    ],
    "sg:phone":"+1 920 349 8632",
    "sg:postcode":"53034",
    "sg:province":"WI",
    "sg:tags":[
        "leasing",
        "video",
        "disc",
        "tape"
    ],
    "wof:name":"Jb's Video",
    "wof:placetype":"venue"
},
  "geometry": {"coordinates":[-88.600634,43.346134],"type":"Point"}
}