{
  "type": "Feature",
  "properties": {
    "iso:country":"US",
    "sg:address":"808 W Lexington Pkwy",
    "sg:city":"De Forest",
    "sg:classifiers":[
        {
            "category":"Education",
            "subcategory":"Special Training",
            "type":"Public Place"
        },
        {
            "category":"Shopping",
            "subcategory":"Musical Instruments",
            "type":"Retail Goods"
        }
    ],
    "sg:phone":"+1 608 846 9734",
    "sg:postcode":"53532",
    "sg:province":"WI",
    "sg:tags":[
        "instruction",
        "music"
    ],
    "wof:name":"Ten Fingers Guitar LLC",
    "wof:placetype":"venue"
},
  "geometry": {"coordinates":[-89.361327,43.247384],"type":"Point"}
}