{
  "type": "Feature",
  "properties": {
    "addr:full":"108 W 9th St Marshfield WI 54449",
    "addr:housenumber":"108",
    "addr:postcode":"54449",
    "addr:street":"W 9Th St",
    "iso:country":"US",
    "sg:address":"108 W 9th St",
    "sg:city":"Marshfield",
    "sg:phone":"+1 715 389 1868",
    "sg:postcode":"54449",
    "sg:province":"WI",
    "sg:website":"http://www.west14th.com",
    "wof:name":"West 14th",
    "wof:placetype":"venue"
},
  "geometry": {"coordinates":[-90.179047,44.659665],"type":"Point"}
}