{
  "type": "Feature",
  "properties": {
    "iso:country":"US",
    "sg:address":"1501 9th St E",
    "sg:city":"Menomonie",
    "sg:classifiers":[
        {
            "category":"Autos & Motor Vehicles",
            "subcategory":"Fuel & Gas Station",
            "type":"Retail Goods"
        }
    ],
    "sg:phone":"+1 715 235 2222",
    "sg:postcode":"54751",
    "sg:province":"WI",
    "sg:tags":[
        "oil"
    ],
    "wof:name":"Amoco Food Shop",
    "wof:placetype":"venue"
},
  "geometry": {"coordinates":[-91.919541,44.86918],"type":"Point"}
}