{
  "type": "Feature",
  "properties": {
    "iso:country":"US",
    "sg:address":"2230 Loomis St",
    "sg:city":"La Crosse",
    "sg:classifiers":[
        {
            "category":"Travel",
            "subcategory":"Travel Agent",
            "type":"Entertainment"
        }
    ],
    "sg:phone":"+1 608 781 3991",
    "sg:postcode":"54603",
    "sg:province":"WI",
    "sg:tags":[
        "cruise"
    ],
    "wof:name":"Cruises Inc",
    "wof:placetype":"venue"
},
  "geometry": {"coordinates":[-91.236935,43.854947],"type":"Point"}
}