{
  "type": "Feature",
  "properties": {
    "iso:country":"US",
    "sg:address":"515 E Broadway St",
    "sg:city":"Viroqua",
    "sg:classifiers":[
        {
            "category":"Personal",
            "subcategory":"Beauty Salon",
            "type":"Services"
        }
    ],
    "sg:phone":"+1 608 637 6102",
    "sg:postcode":"54665",
    "sg:province":"WI",
    "sg:tags":[
        "shop"
    ],
    "wof:name":"Mary Anns Wee Tots LLC",
    "wof:placetype":"venue"
},
  "geometry": {"coordinates":[-90.883887,43.560725],"type":"Point"}
}