{
  "type": "Feature",
  "properties": {
    "iso:country":"US",
    "sg:address":"9820 N Lamplighter Ln",
    "sg:city":"Thiensville",
    "sg:classifiers":[
        {
            "category":"Farming",
            "subcategory":"Fish & Marine Products",
            "type":"Manufacturing & Wholesale Goods"
        }
    ],
    "sg:phone":"+1 262 241 9432",
    "sg:postcode":"53092",
    "sg:province":"WI",
    "sg:tags":[
        "management"
    ],
    "wof:name":"Lehmann Brokerage Consultants",
    "wof:placetype":"venue"
},
  "geometry": {"coordinates":[-87.950001,43.196089],"type":"Point"}
}