{
  "type": "Feature",
  "properties": {
    "iso:country":"US",
    "sg:address":"325 W Cottage Grove Rd",
    "sg:city":"Cottage Grove",
    "sg:classifiers":[
        {
            "category":"Health Services",
            "subcategory":"Nursing And Care Facility",
            "type":"Services"
        }
    ],
    "sg:phone":"+1 608 839 1555",
    "sg:postcode":"53527",
    "sg:province":"WI",
    "sg:tags":[
        "intermediate"
    ],
    "wof:name":"Harber Sr Concettes",
    "wof:placetype":"venue"
},
  "geometry": {"coordinates":[-89.20530599999999,43.086748],"type":"Point"}
}