{
  "type": "Feature",
  "properties": {
    "addr:full":"819 Superior Ave Tomah WI 54660",
    "addr:housenumber":"819",
    "addr:postcode":"54660",
    "addr:street":"Superior Ave",
    "iso:country":"US",
    "sg:address":"819 Superior Ave",
    "sg:city":"Tomah",
    "sg:classifiers":[
        {
            "category":"Recreation",
            "type":"Entertainment"
        }
    ],
    "sg:phone":"+1 608 374 7445",
    "sg:postcode":"54660",
    "sg:province":"WI",
    "sg:tags":[
        "parks"
    ],
    "wof:name":"Tomah Parks & Recreation Dept",
    "wof:placetype":"venue"
},
  "geometry": {"coordinates":[-90.50484899999999,43.979358],"type":"Point"}
}