{
  "type": "Feature",
  "properties": {
    "iso:country":"US",
    "sg:address":"9524 James Ave",
    "sg:city":"Sparta",
    "sg:classifiers":[
        {
            "category":"Manufacturing",
            "subcategory":"Apparel",
            "type":"Manufacturing & Wholesale Goods"
        }
    ],
    "sg:phone":"+1 608 269 1735",
    "sg:postcode":"54656",
    "sg:province":"WI",
    "sg:tags":[
        "heat",
        "embroidery",
        "mfg"
    ],
    "wof:name":"Sweatshirt Lady",
    "wof:placetype":"venue"
},
  "geometry": {"coordinates":[-90.803097,43.889285],"type":"Point"}
}