{
  "type": "Feature",
  "properties": {
    "iso:country":"US",
    "sg:address":"3832 E 2nd St",
    "sg:city":"Superior",
    "sg:classifiers":[
        {
            "category":"Shopping",
            "subcategory":"Computers & Home Electronics",
            "type":"Retail Goods"
        }
    ],
    "sg:phone":"+1 715 398 6010",
    "sg:postcode":"54880",
    "sg:province":"WI",
    "sg:tags":[
        "tape",
        "video",
        "rental"
    ],
    "wof:name":"2nd Street Video",
    "wof:placetype":"venue"
},
  "geometry": {"coordinates":[-92.025285,46.689372],"type":"Point"}
}