{
  "type": "Feature",
  "properties": {
    "iso:country":"US",
    "sg:address":"111 Atkinson St",
    "sg:city":"Mukwonago",
    "sg:classifiers":[
        {
            "category":"Shopping",
            "subcategory":"Bicycles & Sporting Goods",
            "type":"Retail Goods"
        }
    ],
    "sg:phone":"+1 262 363 4580",
    "sg:postcode":"53149",
    "sg:province":"WI",
    "sg:tags":[
        "equipment",
        "golf",
        "supply"
    ],
    "wof:name":"Geneva Golf LLC",
    "wof:placetype":"venue"
},
  "geometry": {"coordinates":[-88.33121,42.862651],"type":"Point"}
}