{
  "type": "Feature",
  "properties": {
    "iso:country":"US",
    "sg:address":"152 W Wisconsin Ave",
    "sg:city":"Milwaukee",
    "sg:classifiers":[
        {
            "category":"Personal",
            "subcategory":"Beauty Salon",
            "type":"Services"
        }
    ],
    "sg:phone":"+1 414 291 3678",
    "sg:postcode":"53203",
    "sg:province":"WI",
    "sg:tags":[
        "shop"
    ],
    "wof:name":"Mary's Hair In Motion",
    "wof:placetype":"venue"
},
  "geometry": {"coordinates":[-87.912559,43.038803],"type":"Point"}
}