{
  "type": "Feature",
  "properties": {
    "iso:country":"US",
    "sg:address":"63 Means Dr",
    "sg:city":"Platteville",
    "sg:classifiers":[
        {
            "category":"Shopping",
            "type":"Retail Goods"
        }
    ],
    "sg:phone":"+1 608 348 2381",
    "sg:postcode":"53818",
    "sg:province":"WI",
    "sg:tags":[
        "equipment",
        "merchandise"
    ],
    "wof:name":"Bel Aire Tent Rental",
    "wof:placetype":"venue"
},
  "geometry": {"coordinates":[-90.444835,42.730907],"type":"Point"}
}