{
  "type": "Feature",
  "properties": {
    "addr:full":"7307 Vandenheuvel Seymour WI 54165",
    "addr:housenumber":"7307",
    "addr:postcode":"54165",
    "addr:street":"Vandenheuvel",
    "iso:country":"US",
    "sg:address":"7307 Vandenheuvel",
    "sg:city":"Seymour",
    "sg:classifiers":[
        {
            "category":"Manufacturing",
            "subcategory":"Tools & Machinery",
            "type":"Manufacturing & Wholesale Goods"
        }
    ],
    "sg:phone":"+1 920 833 9715",
    "sg:postcode":"54165",
    "sg:province":"WI",
    "sg:tags":[
        "machine",
        "shop"
    ],
    "wof:name":"B C Machine",
    "wof:placetype":"venue"
},
  "geometry": {"coordinates":[-88.31033600000001,44.507438],"type":"Point"}
}