{
  "type": "Feature",
  "properties": {
    "iso:country":"US",
    "sg:address":"880 N Orange St",
    "sg:city":"Richland Center",
    "sg:classifiers":[
        {
            "category":"Building & Trades",
            "subcategory":"Plumbing",
            "type":"Services"
        }
    ],
    "sg:phone":"+1 608 647 3553",
    "sg:postcode":"53581",
    "sg:province":"WI",
    "sg:tags":[
        "plumbing",
        "contractor"
    ],
    "wof:name":"Schneider Plumbing & Heating",
    "wof:placetype":"venue"
},
  "geometry": {"coordinates":[-90.389112,43.342108],"type":"Point"}
}