{
  "type": "Feature",
  "properties": {
    "iso:country":"US",
    "sg:address":"1525 Cowling Bay Rd",
    "sg:city":"Neenah",
    "sg:classifiers":[
        {
            "category":"Building & Trades",
            "subcategory":"Construction",
            "type":"Services"
        }
    ],
    "sg:phone":"+1 920 725 5801",
    "sg:postcode":"54956",
    "sg:province":"WI",
    "sg:tags":[
        "house"
    ],
    "wof:name":"Galt Construction Inc",
    "wof:placetype":"venue"
},
  "geometry": {"coordinates":[-88.48043199999999,44.11389],"type":"Point"}
}