{
  "type": "Feature",
  "properties": {
    "iso:country":"US",
    "sg:address":"5659 Driftwood Ln",
    "sg:city":"Sheboygan",
    "sg:classifiers":[
        {
            "category":"Building & Trades",
            "subcategory":"Plumbing",
            "type":"Services"
        }
    ],
    "sg:phone":"+1 920 452 9465",
    "sg:postcode":"53081",
    "sg:province":"WI",
    "sg:tags":[
        "sheet",
        "work",
        "metal",
        "contractor"
    ],
    "wof:name":"IFM Industrial Sheet Metal",
    "wof:placetype":"venue"
},
  "geometry": {"coordinates":[-87.70437200000001,43.690104],"type":"Point"}
}