{
  "type": "Feature",
  "properties": {
    "addr:full":"4674 Co Rd V Luxemburg WI 54217",
    "addr:housenumber":"4674",
    "addr:postcode":"54217",
    "addr:street":"Co Rd V",
    "iso:country":"US",
    "sg:address":"4674 Co Rd V",
    "sg:city":"Luxemburg",
    "sg:classifiers":[
        {
            "category":"Farming",
            "subcategory":"Dairy Farm",
            "type":"Manufacturing & Wholesale Goods"
        }
    ],
    "sg:phone":"+1 920 845 5174",
    "sg:postcode":"54217",
    "sg:province":"WI",
    "wof:name":"James Dorner",
    "wof:placetype":"venue"
},
  "geometry": {"coordinates":[-87.72471899999999,44.496266],"type":"Point"}
}