{
  "type": "Feature",
  "properties": {
    "iso:country":"US",
    "sg:address":"10635 River Rd",
    "sg:city":"Suring",
    "sg:classifiers":[
        {
            "category":"Real Estate",
            "subcategory":"Real Estate Agent",
            "type":"Services"
        }
    ],
    "sg:phone":"+1 920 842 4778",
    "sg:postcode":"54174",
    "sg:province":"WI",
    "wof:name":"Cramer Realty",
    "wof:placetype":"venue"
},
  "geometry": {"coordinates":[-88.384378,45.059372],"type":"Point"}
}