{
  "type": "Feature",
  "properties": {
    "addr:full":"2585 W 20th Ave Oshkosh WI 54904",
    "addr:housenumber":"2585",
    "addr:postcode":"54904",
    "addr:street":"W 20Th Ave",
    "iso:country":"US",
    "sg:address":"2585 W 20th Ave",
    "sg:city":"Oshkosh",
    "sg:classifiers":[
        {
            "category":"Wholesale",
            "subcategory":"Metals & Minerals",
            "type":"Manufacturing & Wholesale Goods"
        }
    ],
    "sg:phone":"+1 920 233 8502",
    "sg:postcode":"54904",
    "sg:province":"WI",
    "sg:tags":[
        "steel",
        "warehouse"
    ],
    "sg:website":"www.lapham-hickey.com",
    "wof:name":"Lapham-Hickey Steel Corp",
    "wof:placetype":"venue"
},
  "geometry": {"coordinates":[-88.595309,43.996224],"type":"Point"}
}