{
  "type": "Feature",
  "properties": {
    "addr:full":"20914 31st St Bristol WI 53104",
    "addr:housenumber":"20914",
    "addr:postcode":"53104",
    "addr:street":"31St St",
    "iso:country":"US",
    "sg:address":"20914 31st St",
    "sg:city":"Bristol",
    "sg:classifiers":[
        {
            "category":"Organizations",
            "subcategory":"Community Association",
            "type":"Services"
        }
    ],
    "sg:phone":"+1 262 878 2338",
    "sg:postcode":"53104",
    "sg:province":"WI",
    "wof:name":"Gifford Larsen VFW Post 7924",
    "wof:placetype":"venue"
},
  "geometry": {"coordinates":[-88.060096,42.611852],"type":"Point"}
}