{
  "type": "Feature",
  "properties": {
    "iso:country":"US",
    "sg:address":"5453 Co Rd Dd",
    "sg:city":"Mineral Point",
    "sg:phone":"+1 608 987 3004",
    "sg:postcode":"53565",
    "sg:province":"WI",
    "sg:tags":[
        "farm",
        "soybean"
    ],
    "wof:name":"Greenwood Acres",
    "wof:placetype":"venue"
},
  "geometry": {"coordinates":[-90.072973,42.857434],"type":"Point"}
}