{
  "type": "Feature",
  "properties": {
    "iso:country":"US",
    "sg:address":"1902 Pastime Ln",
    "sg:city":"East Troy",
    "sg:classifiers":[
        {
            "category":"Building & Trades",
            "subcategory":"Construction",
            "type":"Services"
        }
    ],
    "sg:phone":"+1 262 642 4383",
    "sg:postcode":"53120",
    "sg:province":"WI",
    "sg:tags":[
        "heavy",
        "house"
    ],
    "wof:name":"Jerrys Pier Service",
    "wof:placetype":"venue"
},
  "geometry": {"coordinates":[-88.395557,42.810216],"type":"Point"}
}