{
  "type": "Feature",
  "properties": {
    "iso:country":"US",
    "sg:address":"825 S Timmers Ln",
    "sg:city":"Appleton",
    "sg:classifiers":[
        {
            "category":"Building & Trades",
            "subcategory":"Construction",
            "type":"Services"
        }
    ],
    "sg:phone":"+1 920 734 6268",
    "sg:postcode":"54914",
    "sg:province":"WI",
    "sg:tags":[
        "house",
        "carpentry",
        "contractor"
    ],
    "wof:name":"Home Imprv Repr & Remodel",
    "wof:placetype":"venue"
},
  "geometry": {"coordinates":[-88.463342,44.255228],"type":"Point"}
}