{
  "type": "Feature",
  "properties": {
    "iso:country":"US",
    "sg:address":"5305 W Clinton Ave",
    "sg:city":"Milwaukee",
    "sg:classifiers":[
        {
            "category":"Home & Garden",
            "subcategory":"Carpets & Floor Coverings",
            "type":"Retail Goods"
        }
    ],
    "sg:phone":"+1 414 355 1559",
    "sg:postcode":"53223",
    "sg:province":"WI",
    "sg:tags":[
        "dealer",
        "rug"
    ],
    "wof:name":"Carpet Service",
    "wof:placetype":"venue"
},
  "geometry": {"coordinates":[-87.980874,43.153198],"type":"Point"}
}