{
  "type": "Feature",
  "properties": {
    "iso:country":"US",
    "sg:address":"704 Oak St",
    "sg:city":"Fort Atkinson",
    "sg:classifiers":[
        {
            "category":"Wholesale",
            "subcategory":"Machinery & Supplies",
            "type":"Manufacturing & Wholesale Goods"
        }
    ],
    "sg:phone":"+1 920 568 1010",
    "sg:postcode":"53538",
    "sg:province":"WI",
    "sg:tags":[
        "fire",
        "department",
        "equipment"
    ],
    "wof:name":"5 Alarm Fire & Safety Inc",
    "wof:placetype":"venue"
},
  "geometry": {"coordinates":[-88.837329,42.937437],"type":"Point"}
}