{
  "type": "Feature",
  "properties": {
    "iso:country":"US",
    "sg:address":"4136 State Hwy 42",
    "sg:city":"Sheboygan",
    "sg:classifiers":[
        {
            "category":"Restaurant",
            "type":"Food & Drink"
        }
    ],
    "sg:phone":"+1 920 457 1898",
    "sg:postcode":"53083",
    "sg:province":"WI",
    "wof:name":"Shuff's Last Resort",
    "wof:placetype":"venue"
},
  "geometry": {"coordinates":[-87.758306,43.788967],"type":"Point"}
}