{
  "type": "Feature",
  "properties": {
    "iso:country":"US",
    "sg:address":"6899 Little Sugar Ln",
    "sg:city":"Monticello",
    "sg:classifiers":[
        {
            "category":"Retail",
            "subcategory":"Animal Services",
            "type":"Services"
        }
    ],
    "sg:phone":"+1 608 938 1017",
    "sg:postcode":"53570",
    "sg:province":"WI",
    "sg:tags":[
        "pet",
        "boarding",
        "sitting"
    ],
    "wof:name":"A C's Pet Boarding",
    "wof:placetype":"venue"
},
  "geometry": {"coordinates":[-89.64683599999999,42.751228],"type":"Point"}
}