{
  "type": "Feature",
  "properties": {
    "iso:country":"US",
    "sg:address":"3486 W Bearskull Rd",
    "sg:city":"Park Falls",
    "sg:classifiers":[
        {
            "category":"Government",
            "subcategory":"Fire Station",
            "type":"Public Place"
        }
    ],
    "sg:phone":"+1 715 583 9979",
    "sg:postcode":"54552",
    "sg:province":"WI",
    "sg:tags":[
        "protection"
    ],
    "wof:name":"Iron County Fire Chiefs Assn",
    "wof:placetype":"venue"
},
  "geometry": {"coordinates":[-90.114521,46.019303],"type":"Point"}
}