{
  "type": "Feature",
  "properties": {
    "iso:country":"US",
    "sg:address":"334 S Chestnut St",
    "sg:city":"Green Bay",
    "sg:classifiers":[
        {
            "category":"Building & Trades",
            "subcategory":"Construction",
            "type":"Services"
        }
    ],
    "sg:phone":"+1 920 430 1196",
    "sg:postcode":"54303",
    "sg:province":"WI",
    "sg:tags":[
        "woodworker"
    ],
    "wof:name":"Wisconsin Woodworks",
    "wof:placetype":"venue"
},
  "geometry": {"coordinates":[-88.025035,44.51379],"type":"Point"}
}