{
  "type": "Feature",
  "properties": {
    "iso:country":"US",
    "sg:address":"302 Main St",
    "sg:city":"Elroy",
    "sg:classifiers":[
        {
            "category":"Building & Trades",
            "subcategory":"Construction",
            "type":"Services"
        }
    ],
    "sg:phone":"+1 608 462 4030",
    "sg:postcode":"53929",
    "sg:province":"WI",
    "sg:tags":[
        "contractor"
    ],
    "wof:name":"J & M Builders",
    "wof:placetype":"venue"
},
  "geometry": {"coordinates":[-90.27077,43.738877],"type":"Point"}
}