{
  "type": "Feature",
  "properties": {
    "addr:full":"11766 497th Ave Prescott WI 54021",
    "addr:housenumber":"11766",
    "addr:postcode":"54021",
    "addr:street":"497Th Ave",
    "iso:country":"US",
    "sg:address":"11766 497th Ave",
    "sg:city":"Prescott",
    "sg:classifiers":[
        {
            "category":"Professional",
            "type":"Services"
        }
    ],
    "sg:phone":"+1 715 262 5908",
    "sg:postcode":"54021",
    "sg:province":"WI",
    "wof:name":"David W Schmidt",
    "wof:placetype":"venue"
},
  "geometry": {"coordinates":[-92.726878,44.720873],"type":"Point"}
}