{
  "type": "Feature",
  "properties": {
    "addr:full":"3349 Co Rd G Cedar Grove WI 53013",
    "addr:housenumber":"3349",
    "addr:postcode":"53013",
    "addr:street":"Co Rd G;Grove",
    "iso:country":"US",
    "sg:address":"3349 Co Rd G",
    "sg:city":"Cedar Grove",
    "sg:classifiers":[
        {
            "category":"Freight",
            "type":"Transportation"
        }
    ],
    "sg:phone":"+1 920 668 8083",
    "sg:postcode":"53013",
    "sg:province":"WI",
    "sg:tags":[
        "operator",
        "trucking"
    ],
    "wof:name":"L & R Shavings",
    "wof:placetype":"venue"
},
  "geometry": {"coordinates":[-87.86187099999999,43.586784],"type":"Point"}
}