{
  "type": "Feature",
  "properties": {
    "iso:country":"US",
    "sg:address":"2275 Main St",
    "sg:city":"Green Bay",
    "sg:classifiers":[
        {
            "category":"Retail",
            "subcategory":"Car Wash",
            "type":"Services"
        }
    ],
    "sg:phone":"+1 920 469 5921",
    "sg:postcode":"54311",
    "sg:province":"WI",
    "sg:tags":[
        "automobile",
        "detail",
        "clean"
    ],
    "wof:name":"Bubba's Auto Detailing",
    "wof:placetype":"venue"
},
  "geometry": {"coordinates":[-87.969168,44.478927],"type":"Point"}
}