{
  "type": "Feature",
  "properties": {
    "addr:full":"21020 W Good Hope Rd Lannon WI 53046",
    "addr:housenumber":"21020",
    "addr:postcode":"53046",
    "addr:street":"W Good Hope Rd",
    "iso:country":"US",
    "sg:address":"21020 W Good Hope Rd",
    "sg:city":"Lannon",
    "sg:classifiers":[
        {
            "category":"Manufacturing",
            "subcategory":"Metals",
            "type":"Manufacturing & Wholesale Goods"
        }
    ],
    "sg:phone":"+1 262 251 8180",
    "sg:postcode":"53046",
    "sg:province":"WI",
    "sg:tags":[
        "casting"
    ],
    "sg:website":"www.afwfdry.com",
    "wof:name":"AFW Foundry Inc",
    "wof:placetype":"venue"
},
  "geometry": {"coordinates":[-88.170601,43.148306],"type":"Point"}
}