{
  "type": "Feature",
  "properties": {
    "iso:country":"US",
    "sg:address":"3321 N Shawnee Ln",
    "sg:city":"Appleton",
    "sg:classifiers":[
        {
            "category":"Building & Trades",
            "subcategory":"Construction",
            "type":"Services"
        }
    ],
    "sg:phone":"+1 920 730 8179",
    "sg:postcode":"54914",
    "sg:province":"WI",
    "sg:tags":[
        "contractor"
    ],
    "wof:name":"Schauland Drywall",
    "wof:placetype":"venue"
},
  "geometry": {"coordinates":[-88.451414,44.295134],"type":"Point"}
}