{
  "type": "Feature",
  "properties": {
    "iso:country":"US",
    "sg:address":"214 S Rochester St",
    "sg:city":"Mukwonago",
    "sg:classifiers":[
        {
            "category":"Shopping",
            "subcategory":"Used Merchandise",
            "type":"Retail Goods"
        }
    ],
    "sg:phone":"+1 262 363 7015",
    "sg:postcode":"53149",
    "sg:province":"WI",
    "sg:tags":[
        "antique"
    ],
    "wof:name":"Indian Creek Antiques",
    "wof:placetype":"venue"
},
  "geometry": {"coordinates":[-88.32923700000001,42.857814],"type":"Point"}
}