{
  "type": "Feature",
  "properties": {
    "iso:country":"US",
    "sg:address":"5181 N 125th St",
    "sg:city":"Butler",
    "sg:classifiers":[
        {
            "category":"Manufacturing",
            "subcategory":"Rubber & Plastics",
            "type":"Manufacturing & Wholesale Goods"
        }
    ],
    "sg:phone":"+1 262 781 4610",
    "sg:postcode":"53007",
    "sg:province":"WI",
    "sg:tags":[
        "tubing",
        "belting",
        "metal"
    ],
    "wof:name":"Midwest Flexible Hose, Inc.",
    "wof:placetype":"venue"
},
  "geometry": {"coordinates":[-88.067024,43.111649],"type":"Point"}
}