{
  "type": "Feature",
  "properties": {
    "iso:country":"US",
    "sg:address":"720 Lincoln Ave",
    "sg:city":"Baraboo",
    "sg:classifiers":[
        {
            "category":"Personal",
            "subcategory":"Beauty Salon",
            "type":"Services"
        }
    ],
    "sg:phone":"+1 608 356 7654",
    "sg:postcode":"53913",
    "sg:province":"WI",
    "wof:name":"Hairloom",
    "wof:placetype":"venue"
},
  "geometry": {"coordinates":[-89.721432,43.473106],"type":"Point"}
}