{
  "type": "Feature",
  "properties": {
    "addr:full":"215 Church St Montello WI 53949",
    "addr:housenumber":"215",
    "addr:postcode":"53949",
    "addr:street":"Church St",
    "iso:country":"US",
    "sg:address":"215 Church St",
    "sg:city":"Montello",
    "sg:classifiers":[
        {
            "category":"Health Services",
            "subcategory":"Doctor",
            "type":"Services"
        }
    ],
    "sg:phone":"+1 608 297 2181",
    "sg:postcode":"53949",
    "sg:province":"WI",
    "sg:tags":[
        "dentist"
    ],
    "wof:name":"Fox River Dental Assoc",
    "wof:placetype":"venue"
},
  "geometry": {"coordinates":[-89.318859,43.793795],"type":"Point"}
}