{
  "type": "Feature",
  "properties": {
    "iso:country":"US",
    "sg:address":"422 W 11th Ave",
    "sg:city":"Oshkosh",
    "sg:classifiers":[
        {
            "category":"Banks & Credit Unions",
            "subcategory":"Bank",
            "type":"Services"
        }
    ],
    "sg:phone":"+1 920 230 8303",
    "sg:postcode":"54902",
    "sg:province":"WI",
    "sg:tags":[
        "loan",
        "broker"
    ],
    "wof:name":"First Wisconsin Lending Inc",
    "wof:placetype":"venue"
},
  "geometry": {"coordinates":[-88.549639,44.008496],"type":"Point"}
}