{
  "type": "Feature",
  "properties": {
    "iso:country":"US",
    "sg:address":"1802 Shepherd Ct",
    "sg:city":"Waukesha",
    "sg:classifiers":[
        {
            "category":"Professional",
            "subcategory":"Engineering",
            "type":"Services"
        }
    ],
    "sg:phone":"+1 262 513 6643",
    "sg:postcode":"53186",
    "sg:province":"WI",
    "wof:name":"CM Solutions LLC",
    "wof:placetype":"venue"
},
  "geometry": {"coordinates":[-88.194225,43.021695],"type":"Point"}
}