{
  "type": "Feature",
  "properties": {
    "iso:country":"US",
    "sg:address":"2545 N 30th St",
    "sg:city":"Milwaukee",
    "sg:classifiers":[
        {
            "category":"Building & Trades",
            "subcategory":"Construction",
            "type":"Services"
        }
    ],
    "sg:phone":"+1 414 264 6673",
    "sg:postcode":"53210",
    "sg:province":"WI",
    "sg:tags":[
        "demolition",
        "wrecking",
        "contractor"
    ],
    "wof:name":"McKinleys Corp",
    "wof:placetype":"venue"
},
  "geometry": {"coordinates":[-87.95121399999999,43.065238],"type":"Point"}
}