{
  "type": "Feature",
  "properties": {
    "iso:country":"US",
    "sg:address":"2014 US Hwy 8",
    "sg:city":"St Croix Falls",
    "sg:classifiers":[
        {
            "category":"Shopping",
            "subcategory":"Used Merchandise",
            "type":"Retail Goods"
        },
        {
            "category":"Retail",
            "subcategory":"Repair Shop",
            "type":"Services"
        }
    ],
    "sg:phone":"+1 715 483 1012",
    "sg:postcode":"54024",
    "sg:province":"WI",
    "sg:tags":[
        "antique",
        "restoring"
    ],
    "wof:name":"Twin Spruce Antique & Furnitur",
    "wof:placetype":"venue"
},
  "geometry": {"coordinates":[-92.571674,45.397472],"type":"Point"}
}