{
  "type": "Feature",
  "properties": {
    "iso:country":"US",
    "sg:address":"12940 W National Ave",
    "sg:city":"New Berlin",
    "sg:classifiers":[
        {
            "category":"Manufacturing",
            "subcategory":"Printing",
            "type":"Manufacturing & Wholesale Goods"
        }
    ],
    "sg:phone":"+1 262 432 3333",
    "sg:postcode":"53151",
    "sg:province":"WI",
    "sg:tags":[
        "commercial"
    ],
    "sg:website":"www.pressandpromo.com",
    "wof:name":"Press & Promo Inc",
    "wof:placetype":"venue"
},
  "geometry": {"coordinates":[-88.07409699999999,42.988289],"type":"Point"}
}