{
  "type": "Feature",
  "properties": {
    "iso:country":"US",
    "sg:address":"214 S 3rd St",
    "sg:city":"Delavan",
    "sg:classifiers":[
        {
            "category":"Insurance",
            "subcategory":"Insurance Agent",
            "type":"Services"
        }
    ],
    "sg:phone":"+1 262 728 2022",
    "sg:postcode":"53115",
    "sg:province":"WI",
    "wof:name":"Allied Senior Services",
    "wof:placetype":"venue"
},
  "geometry": {"coordinates":[-88.64536699999999,42.630984],"type":"Point"}
}