{
  "type": "Feature",
  "properties": {
    "iso:country":"US",
    "sg:address":"4010 Monona Dr",
    "sg:city":"Madison",
    "sg:classifiers":[
        {
            "category":"Shopping",
            "type":"Retail Goods"
        },
        {
            "category":"Shopping",
            "subcategory":"Crafts & Fabrics",
            "type":"Retail Goods"
        }
    ],
    "sg:phone":"+1 608 442 0118",
    "sg:postcode":"53716",
    "sg:province":"WI",
    "sg:tags":[
        "sewing",
        "art",
        "gallery",
        "dealer"
    ],
    "wof:name":"Patchwork Peddler LLC",
    "wof:placetype":"venue"
},
  "geometry": {"coordinates":[-89.323813,43.080209],"type":"Point"}
}