{
  "type": "Feature",
  "properties": {
    "iso:country":"US",
    "sg:address":"5036 N Hopkins St",
    "sg:city":"Milwaukee",
    "sg:classifiers":[
        {
            "category":"Professional",
            "subcategory":"Accounting & Tax Preparation",
            "type":"Services"
        }
    ],
    "sg:phone":"+1 414 438 1414",
    "sg:postcode":"53209",
    "sg:province":"WI",
    "sg:tags":[
        "return",
        "filing"
    ],
    "wof:name":"First Place Income Tax Svc",
    "wof:placetype":"venue"
},
  "geometry": {"coordinates":[-87.96202700000001,43.109292],"type":"Point"}
}