{
  "type": "Feature",
  "properties": {
    "iso:country":"US",
    "sg:address":"777 E Wisconsin Ave # 3500",
    "sg:city":"Milwaukee",
    "sg:classifiers":[
        {
            "category":"Banks & Credit Unions",
            "subcategory":"Investment Brokerage",
            "type":"Services"
        }
    ],
    "sg:phone":"+1 414 225 8970",
    "sg:postcode":"53202",
    "sg:province":"WI",
    "sg:tags":[
        "trust"
    ],
    "wof:name":"Trust Uw Camille A Lonstorf",
    "wof:placetype":"venue"
},
  "geometry": {"coordinates":[-87.901568,43.03899],"type":"Point"}
}