{
  "type": "Feature",
  "properties": {
    "iso:country":"US",
    "sg:address":"111 E Main St",
    "sg:city":"Cazenovia",
    "sg:classifiers":[
        {
            "category":"Retail",
            "subcategory":"Funeral Services",
            "type":"Services"
        }
    ],
    "sg:phone":"+1 608 983 2727",
    "sg:postcode":"53924",
    "sg:province":"WI",
    "wof:name":"Farber Funeral Chapel",
    "wof:placetype":"venue"
},
  "geometry": {"coordinates":[-90.196018,43.523199],"type":"Point"}
}