{
  "type": "Feature",
  "properties": {
    "iso:country":"US",
    "sg:address":"100 15th Ave",
    "sg:city":"South Milwaukee",
    "sg:classifiers":[
        {
            "category":"Health Services",
            "subcategory":"Doctor",
            "type":"Services"
        }
    ],
    "sg:phone":"+1 414 571 6070",
    "sg:postcode":"53172",
    "sg:province":"WI",
    "sg:tags":[
        "medical"
    ],
    "wof:name":"Aurora Pharmacy Inc",
    "wof:placetype":"venue"
},
  "geometry": {"coordinates":[-87.870756,42.926676],"type":"Point"}
}