{
  "type": "Feature",
  "properties": {
    "addr:full":"2829 Glendale Ave Green Bay WI 54313",
    "addr:housenumber":"2829",
    "addr:postcode":"54313",
    "addr:street":"Glendale Ave",
    "iso:country":"US",
    "sg:address":"2829 Glendale Ave",
    "sg:city":"Green Bay",
    "sg:classifiers":[
        {
            "category":"Building & Trades",
            "subcategory":"Construction",
            "type":"Services"
        }
    ],
    "sg:phone":"+1 920 434 0474",
    "sg:postcode":"54313",
    "sg:province":"WI",
    "sg:tags":[
        "contractor"
    ],
    "wof:name":"Arndt Masonry Construction",
    "wof:placetype":"venue"
},
  "geometry": {"coordinates":[-88.095383,44.565456],"type":"Point"}
}