{
  "type": "Feature",
  "properties": {
    "iso:country":"US",
    "sg:address":"307 North St",
    "sg:city":"Sullivan",
    "sg:classifiers":[
        {
            "category":"Professional",
            "subcategory":"Business Services",
            "type":"Services"
        }
    ],
    "sg:phone":"+1 262 593 8508",
    "sg:postcode":"53178",
    "sg:province":"WI",
    "wof:name":"Brayant Enterprises",
    "wof:placetype":"venue"
},
  "geometry": {"coordinates":[-88.581818,43.018637],"type":"Point"}
}