{
  "type": "Feature",
  "properties": {
    "addr:full":"16880 US Hwy 63 Hayward WI 54843",
    "addr:postcode":"16880;54843",
    "addr:street":"Us Hwy 63",
    "iso:country":"US",
    "sg:address":"16880 US Hwy 63",
    "sg:city":"Hayward",
    "sg:classifiers":[
        {
            "category":"Communications",
            "subcategory":"Radio Station",
            "type":"Services"
        }
    ],
    "sg:phone":"+1 715 634 4836",
    "sg:postcode":"54843",
    "sg:province":"WI",
    "sg:tags":[
        "company",
        "broadcasting"
    ],
    "wof:name":"WHSM",
    "wof:placetype":"venue"
},
  "geometry": {"coordinates":[-91.49738000000001,46.00429],"type":"Point"}
}