{
  "type": "Feature",
  "properties": {
    "iso:country":"US",
    "sg:address":"206 W Prospect St",
    "sg:city":"Thorp",
    "sg:classifiers":[
        {
            "category":"Health Services",
            "subcategory":"Nursing And Care Facility",
            "type":"Services"
        }
    ],
    "sg:phone":"+1 715 669 5321",
    "sg:postcode":"54771",
    "sg:province":"WI",
    "sg:tags":[
        "home",
        "skilled"
    ],
    "wof:name":"Oakbrook Manor",
    "wof:placetype":"venue"
},
  "geometry": {"coordinates":[-90.80045699999999,44.958104],"type":"Point"}
}