{
  "type": "Feature",
  "properties": {
    "iso:country":"US",
    "sg:address":"515 Junction Rd",
    "sg:city":"Madison",
    "sg:classifiers":[
        {
            "category":"Professional",
            "subcategory":"Management & Consulting",
            "type":"Services"
        }
    ],
    "sg:phone":"+1 608 662 8220",
    "sg:postcode":"53717",
    "sg:province":"WI",
    "wof:name":"Corvel",
    "wof:placetype":"venue"
},
  "geometry": {"coordinates":[-89.524371,43.068943],"type":"Point"}
}