{
  "type": "Feature",
  "properties": {
    "iso:country":"US",
    "sg:address":"620 1st St",
    "sg:city":"Menasha",
    "sg:classifiers":[
        {
            "category":"Professional",
            "subcategory":"Management & Consulting",
            "type":"Services"
        }
    ],
    "sg:phone":"+1 920 725 6992",
    "sg:postcode":"54952",
    "sg:province":"WI",
    "sg:tags":[
        "business"
    ],
    "wof:name":"John Price & Associates",
    "wof:placetype":"venue"
},
  "geometry": {"coordinates":[-88.44057,44.202974],"type":"Point"}
}