{
  "type": "Feature",
  "properties": {
    "iso:country":"US",
    "sg:address":"4015 Terminal Dr",
    "sg:city":"Mc Farland",
    "sg:classifiers":[
        {
            "category":"Restaurant",
            "type":"Food & Drink"
        }
    ],
    "sg:phone":"+1 608 838 9090",
    "sg:postcode":"53558",
    "sg:province":"WI",
    "wof:name":"Great American Steak Co",
    "wof:placetype":"venue"
},
  "geometry": {"coordinates":[-89.30228,43.040119],"type":"Point"}
}