{
  "type": "Feature",
  "properties": {
    "addr:full":"3707 Campbell Trace Rd Hartland WI 53029",
    "addr:housenumber":"3707",
    "addr:postcode":"53029",
    "addr:street":"Campbell Trace Rd",
    "iso:country":"US",
    "sg:address":"3707 Campbell Trace Rd",
    "sg:city":"Hartland",
    "sg:classifiers":[
        {
            "category":"Wholesale",
            "subcategory":"Plants",
            "type":"Manufacturing & Wholesale Goods"
        }
    ],
    "sg:phone":"+1 262 367 2558",
    "sg:postcode":"53029",
    "sg:province":"WI",
    "sg:tags":[
        "supply"
    ],
    "wof:name":"Gerbers Nursery",
    "wof:placetype":"venue"
},
  "geometry": {"coordinates":[-88.363072,43.091864],"type":"Point"}
}