{
  "type": "Feature",
  "properties": {
    "iso:country":"US",
    "sg:address":"202 W Dolf St",
    "sg:city":"Colby",
    "sg:classifiers":[
        {
            "category":"Education",
            "subcategory":"School",
            "type":"Public Place"
        }
    ],
    "sg:phone":"+1 715 223 3939",
    "sg:postcode":"54421",
    "sg:province":"WI",
    "wof:name":"Colby Elementary School",
    "wof:placetype":"venue"
},
  "geometry": {"coordinates":[-90.31823799999999,44.918055],"type":"Point"}
}