{
  "type": "Feature",
  "properties": {
    "iso:country":"US",
    "sg:address":"3038 Bosshard Dr",
    "sg:city":"Madison",
    "sg:classifiers":[
        {
            "category":"Real Estate",
            "subcategory":"Real Estate Agent",
            "type":"Services"
        }
    ],
    "sg:phone":"+1 608 288 9009",
    "sg:postcode":"53711",
    "sg:province":"WI",
    "wof:name":"Family Magic LLC",
    "wof:placetype":"venue"
},
  "geometry": {"coordinates":[-89.441924,43.017981],"type":"Point"}
}