{
  "type": "Feature",
  "properties": {
    "addr:full":"3726 22nd Ave Kenosha WI 53140",
    "addr:housenumber":"3726",
    "addr:postcode":"53140",
    "addr:street":"22Nd Ave",
    "iso:country":"US",
    "sg:address":"3726 22nd Ave",
    "sg:city":"Kenosha",
    "sg:classifiers":[
        {
            "category":"Shopping",
            "subcategory":"Pharmacy",
            "type":"Retail Goods"
        }
    ],
    "sg:phone":"+1 262 654 6545",
    "sg:postcode":"53140",
    "sg:province":"WI",
    "wof:name":"Osco Drug",
    "wof:placetype":"venue"
},
  "geometry": {"coordinates":[-87.83600800000001,42.601471],"type":"Point"}
}