{
  "type": "Feature",
  "properties": {
    "iso:country":"US",
    "sg:address":"2500 N Mayfair Rd",
    "sg:city":"Milwaukee",
    "sg:classifiers":[
        {
            "category":"Building & Trades",
            "subcategory":"Construction",
            "type":"Services"
        }
    ],
    "sg:phone":"+1 414 476 5117",
    "sg:postcode":"53222",
    "sg:province":"WI",
    "sg:tags":[
        "contractor"
    ],
    "wof:name":"Tri-North Builders",
    "wof:placetype":"venue"
},
  "geometry": {"coordinates":[-88.047678,43.063727],"type":"Point"}
}