{
  "type": "Feature",
  "properties": {
    "iso:country":"US",
    "sg:address":"2126 Colladay Point Dr",
    "sg:city":"Stoughton",
    "sg:classifiers":[
        {
            "category":"Professional",
            "subcategory":"Engineering",
            "type":"Services"
        }
    ],
    "sg:phone":"+1 608 873 7993",
    "sg:postcode":"53589",
    "sg:province":"WI",
    "wof:name":"R S Grant Consulting",
    "wof:placetype":"venue"
},
  "geometry": {"coordinates":[-89.280856,42.962571],"type":"Point"}
}