{
  "type": "Feature",
  "properties": {
    "addr:full":"1600 E Williams Dr Beloit WI 53511",
    "addr:housenumber":"1600",
    "addr:postcode":"53511",
    "addr:street":"E Williams Dr",
    "iso:country":"US",
    "sg:address":"1600 E Williams Dr",
    "sg:city":"Beloit",
    "sg:classifiers":[
        {
            "category":"Restaurant",
            "type":"Food & Drink"
        }
    ],
    "sg:phone":"+1 608 362 3362",
    "sg:postcode":"53511",
    "sg:province":"WI",
    "sg:tags":[
        "eating"
    ],
    "wof:name":"Cartunes Inc",
    "wof:placetype":"venue"
},
  "geometry": {"coordinates":[-89.016341,42.560615],"type":"Point"}
}