{
  "type": "Feature",
  "properties": {
    "iso:country":"US",
    "sg:address":"2201 E Main St",
    "sg:city":"Merrill",
    "sg:classifiers":[
        {
            "category":"Home & Garden",
            "subcategory":"Garden Supply",
            "type":"Retail Goods"
        }
    ],
    "sg:phone":"+1 715 536 2840",
    "sg:postcode":"54452",
    "sg:province":"WI",
    "sg:tags":[
        "farm",
        "implement",
        "lawn",
        "mower"
    ],
    "wof:name":"William Kamke & Sons Inc",
    "wof:placetype":"venue"
},
  "geometry": {"coordinates":[-89.66997499999999,45.180743],"type":"Point"}
}