{
  "type": "Feature",
  "properties": {
    "addr:full":"3233 Church St Stevens Point WI 54481",
    "addr:housenumber":"3233",
    "addr:postcode":"54481",
    "addr:street":"Church St",
    "iso:country":"US",
    "sg:address":"3233 Church St",
    "sg:city":"Stevens Point",
    "sg:classifiers":[
        {
            "category":"Banks & Credit Unions",
            "subcategory":"Bank",
            "type":"Services"
        }
    ],
    "sg:phone":"+1 715 342 1159",
    "sg:postcode":"54481",
    "sg:province":"WI",
    "sg:tags":[
        "loan",
        "real estate"
    ],
    "wof:name":"Beneficial Wisconsin Inc",
    "wof:placetype":"venue"
},
  "geometry": {"coordinates":[-89.56592000000001,44.503497],"type":"Point"}
}