{
  "type": "Feature",
  "properties": {
    "iso:country":"US",
    "sg:address":"1259 Harding Rd",
    "sg:city":"Rubicon",
    "sg:classifiers":[
        {
            "category":"Freight",
            "type":"Transportation"
        }
    ],
    "sg:phone":"+1 920 474 7575",
    "sg:postcode":"53078",
    "sg:province":"WI",
    "sg:tags":[
        "trucking"
    ],
    "wof:name":"Paul's Trucking",
    "wof:placetype":"venue"
},
  "geometry": {"coordinates":[-88.458822,43.253561],"type":"Point"}
}