{
  "type": "Feature",
  "properties": {
    "iso:country":"US",
    "sg:address":"319 S Buchanan St",
    "sg:city":"Prairie Du Chien",
    "sg:classifiers":[
        {
            "category":"Professional",
            "type":"Services"
        }
    ],
    "sg:phone":"+1 608 326 4639",
    "sg:postcode":"53821",
    "sg:province":"WI",
    "wof:name":"Jeff Sjoberg",
    "wof:placetype":"venue"
},
  "geometry": {"coordinates":[-91.135509,43.048946],"type":"Point"}
}