{
  "type": "Feature",
  "properties": {
    "iso:country":"US",
    "sg:address":"8737 W Fond du Lac Ave",
    "sg:city":"Milwaukee",
    "sg:classifiers":[
        {
            "category":"Wholesale",
            "subcategory":"Motor Vehicles",
            "type":"Manufacturing & Wholesale Goods"
        }
    ],
    "sg:phone":"+1 414 464 5147",
    "sg:postcode":"53225",
    "sg:province":"WI",
    "wof:name":"J J R Motor Car Company",
    "wof:placetype":"venue"
},
  "geometry": {"coordinates":[-88.02126800000001,43.125075],"type":"Point"}
}