{
  "type": "Feature",
  "properties": {
    "iso:country":"US",
    "sg:address":"1650 Tri Park Way",
    "sg:city":"Appleton",
    "sg:classifiers":[
        {
            "category":"Professional",
            "subcategory":"Business Services",
            "type":"Services"
        },
        {
            "category":"Professional",
            "subcategory":"Management & Consulting",
            "type":"Services"
        }
    ],
    "sg:phone":"+1 920 730 7000",
    "sg:postcode":"54914",
    "sg:province":"WI",
    "wof:name":"Sycamore Group",
    "wof:placetype":"venue"
},
  "geometry": {"coordinates":[-88.45348,44.276399],"type":"Point"}
}