{
  "type": "Feature",
  "properties": {
    "iso:country":"US",
    "sg:address":"700 Cross St",
    "sg:city":"La Crosse",
    "sg:classifiers":[
        {
            "category":"Shopping",
            "subcategory":"Pharmacy",
            "type":"Retail Goods"
        }
    ],
    "sg:phone":"+1 608 791 9724",
    "sg:postcode":"54601",
    "sg:province":"WI",
    "wof:name":"Home Health Pharmacy",
    "wof:placetype":"venue"
},
  "geometry": {"coordinates":[-91.255992,43.806682],"type":"Point"}
}