{
  "type": "Feature",
  "properties": {
    "iso:country":"US",
    "sg:address":"11015 N Louies Landing Rd",
    "sg:city":"Hayward",
    "sg:classifiers":[
        {
            "category":"Retail",
            "subcategory":"Repair Shop",
            "type":"Services"
        }
    ],
    "sg:phone":"+1 715 462 3860",
    "sg:postcode":"54843",
    "sg:province":"WI",
    "sg:tags":[
        "vehicle"
    ],
    "wof:name":"Performance Parts",
    "wof:placetype":"venue"
},
  "geometry": {"coordinates":[-91.080302,46.027228],"type":"Point"}
}