{
  "type": "Feature",
  "properties": {
    "addr:full":"2139 S 111th St Milwaukee WI 53227",
    "addr:housenumber":"2139",
    "addr:postcode":"53227",
    "addr:street":"S 111Th St",
    "iso:country":"US",
    "sg:address":"2139 S 111th St",
    "sg:city":"Milwaukee",
    "sg:classifiers":[
        {
            "category":"Arts & Performance",
            "subcategory":"Theater",
            "type":"Entertainment"
        }
    ],
    "sg:phone":"+1 414 732 8122",
    "sg:postcode":"53227",
    "sg:province":"WI",
    "sg:tags":[
        "magician"
    ],
    "wof:name":"Aristides Magic",
    "wof:placetype":"venue"
},
  "geometry": {"coordinates":[-88.05061000000001,43.005144],"type":"Point"}
}