{
  "type": "Feature",
  "properties": {
    "addr:full":"1628 N Main St West Bend WI 53090",
    "addr:housenumber":"1628",
    "addr:postcode":"53090",
    "addr:street":"N Main St",
    "iso:country":"US",
    "sg:address":"1628 N Main St",
    "sg:city":"West Bend",
    "sg:classifiers":[
        {
            "category":"Retail",
            "subcategory":"Auto Rental",
            "type":"Services"
        }
    ],
    "sg:phone":"+1 262 306 9202",
    "sg:postcode":"53090",
    "sg:province":"WI",
    "sg:tags":[
        "renting",
        "truck",
        "leasing"
    ],
    "wof:name":"Penske Truck Rental",
    "wof:placetype":"venue"
},
  "geometry": {"coordinates":[-88.18727699999999,43.442324],"type":"Point"}
}