{
  "type": "Feature",
  "properties": {
    "iso:country":"US",
    "sg:address":"8211 W River Rd",
    "sg:city":"Manawa",
    "sg:classifiers":[
        {
            "category":"Farming",
            "subcategory":"Dairy Farm",
            "type":"Manufacturing & Wholesale Goods"
        }
    ],
    "sg:phone":"+1 920 596 3715",
    "sg:postcode":"54949",
    "sg:province":"WI",
    "wof:name":"Pethke Sunnydale Dairy Farm",
    "wof:placetype":"venue"
},
  "geometry": {"coordinates":[-88.910603,44.532063],"type":"Point"}
}