{
  "type": "Feature",
  "properties": {
    "addr:full":"1125 E Mineral St Platteville WI 53818",
    "addr:housenumber":"1125",
    "addr:postcode":"53818",
    "addr:street":"E Mineral St",
    "iso:country":"US",
    "sg:address":"1125 E Mineral St",
    "sg:city":"Platteville",
    "sg:classifiers":[
        {
            "category":"Manufacturing",
            "subcategory":"Tools & Machinery",
            "type":"Manufacturing & Wholesale Goods"
        }
    ],
    "sg:phone":"+1 608 348 2547",
    "sg:postcode":"53818",
    "sg:province":"WI",
    "sg:tags":[
        "machine",
        "shop"
    ],
    "wof:name":"Q & T Machining Inc",
    "wof:placetype":"venue"
},
  "geometry": {"coordinates":[-90.460992,42.732967],"type":"Point"}
}