{
  "type": "Feature",
  "properties": {
    "iso:country":"US",
    "sg:address":"6688 Wright Way Dr",
    "sg:city":"Fond Du Lac",
    "sg:classifiers":[
        {
            "category":"Building & Trades",
            "subcategory":"Construction",
            "type":"Services"
        }
    ],
    "sg:phone":"+1 920 923 0721",
    "sg:postcode":"54937",
    "sg:province":"WI",
    "sg:tags":[
        "siding",
        "contractor"
    ],
    "sg:website":"www.wrightwaysiding.com",
    "wof:name":"Wrightway Inc",
    "wof:placetype":"venue"
},
  "geometry": {"coordinates":[-88.502052,43.785699],"type":"Point"}
}