{
  "type": "Feature",
  "properties": {
    "iso:country":"US",
    "sg:address":"1524 Raveen St",
    "sg:city":"Fort Atkinson",
    "sg:phone":"+1 920 563 3971",
    "sg:postcode":"53538",
    "sg:province":"WI",
    "sg:tags":[
        "real",
        "lessor",
        "farm",
        "corn",
        "soybean",
        "property"
    ],
    "wof:name":"McNally John",
    "wof:placetype":"venue"
},
  "geometry": {"coordinates":[-88.861509,42.937516],"type":"Point"}
}