{
  "type": "Feature",
  "properties": {
    "iso:country":"US",
    "sg:address":"7110 Ashwood Ln",
    "sg:city":"Muskego",
    "sg:classifiers":[
        {
            "category":"Manufacturing",
            "subcategory":"Toys & Sporting Goods",
            "type":"Manufacturing & Wholesale Goods"
        }
    ],
    "sg:phone":"+1 262 895 6981",
    "sg:postcode":"53185",
    "sg:province":"WI",
    "sg:tags":[
        "craft"
    ],
    "wof:name":"J C Quaw Indian Crafts",
    "wof:placetype":"venue"
},
  "geometry": {"coordinates":[-88.160242,42.816876],"type":"Point"}
}