{
  "type": "Feature",
  "properties": {
    "iso:country":"US",
    "sg:address":"117 115th St",
    "sg:city":"Pleasant Prairie",
    "sg:classifiers":[
        {
            "category":"Wholesale",
            "subcategory":"Metals & Minerals",
            "type":"Manufacturing & Wholesale Goods"
        }
    ],
    "sg:phone":"+1 262 942 9559",
    "sg:postcode":"53158",
    "sg:province":"WI",
    "sg:tags":[
        "steel"
    ],
    "wof:name":"Apple Steel Sales Corp",
    "wof:placetype":"venue"
},
  "geometry": {"coordinates":[-87.81225,42.508551],"type":"Point"}
}