{
  "type": "Feature",
  "properties": {
    "addr:full":"124 Carroll St Random Lake WI 53075",
    "addr:housenumber":"124",
    "addr:postcode":"53075",
    "addr:street":"Carroll St",
    "iso:country":"US",
    "sg:address":"124 Carroll St",
    "sg:city":"Random Lake",
    "sg:classifiers":[
        {
            "category":"Bars & Pubs",
            "type":"Food & Drink"
        }
    ],
    "sg:phone":"+1 920 994 4561",
    "sg:postcode":"53075",
    "sg:province":"WI",
    "wof:name":"Booz'In",
    "wof:placetype":"venue"
},
  "geometry": {"coordinates":[-87.96189800000001,43.550293],"type":"Point"}
}