{
  "type": "Feature",
  "properties": {
    "iso:country":"US",
    "sg:address":"1200 Gohres St",
    "sg:city":"La Crosse",
    "sg:classifiers":[
        {
            "category":"Shopping",
            "subcategory":"Gifts & Souvenirs",
            "type":"Retail Goods"
        }
    ],
    "sg:phone":"+1 608 784 4500",
    "sg:postcode":"54603",
    "sg:province":"WI",
    "wof:name":"Gifted Hands",
    "wof:placetype":"venue"
},
  "geometry": {"coordinates":[-91.23835099999999,43.849216],"type":"Point"}
}