{
  "type": "Feature",
  "properties": {
    "addr:full":"121 Roedl Ct Beaver Dam WI 53916",
    "addr:housenumber":"121",
    "addr:postcode":"53916",
    "addr:street":"Roedl Ct",
    "iso:country":"US",
    "sg:address":"121 Roedl Ct",
    "sg:city":"Beaver Dam",
    "sg:classifiers":[
        {
            "category":"Professional",
            "type":"Services"
        }
    ],
    "sg:phone":"+1 920 887 3254",
    "sg:postcode":"53916",
    "sg:province":"WI",
    "wof:name":"Bart M Radtke",
    "wof:placetype":"venue"
},
  "geometry": {"coordinates":[-88.83004800000001,43.450637],"type":"Point"}
}