{
  "type": "Feature",
  "properties": {
    "addr:full":"13912 Pioneer Rd Newton WI 53063",
    "addr:housenumber":"13912",
    "addr:postcode":"53063",
    "addr:street":"Pioneer Rd",
    "iso:country":"US",
    "sg:address":"13912 Pioneer Rd",
    "sg:city":"Newton",
    "sg:classifiers":[
        {
            "category":"Farming",
            "subcategory":"Dairy Farm",
            "type":"Manufacturing & Wholesale Goods"
        }
    ],
    "sg:phone":"+1 920 693 8334",
    "sg:postcode":"53063",
    "sg:province":"WI",
    "wof:name":"Rof Lor Dairy Farm",
    "wof:placetype":"venue"
},
  "geometry": {"coordinates":[-87.838728,43.934161],"type":"Point"}
}