{
  "type": "Feature",
  "properties": {
    "iso:country":"US",
    "sg:address":"1165 Club Cir",
    "sg:city":"Brookfield",
    "sg:classifiers":[
        {
            "category":"Place Of Worship",
            "subcategory":"Church",
            "type":"Public Place"
        },
        {
            "category":"Place Of Worship",
            "type":"Public Place"
        },
        {
            "category":"Health Services",
            "subcategory":"Medical Lab",
            "type":"Services"
        },
        {
            "category":"Organizations",
            "subcategory":"Religious Organization",
            "type":"Services"
        }
    ],
    "sg:phone":"+1 262 785 6789",
    "sg:postcode":"53005",
    "sg:province":"WI",
    "sg:tags":[
        "science",
        "christian",
        "churches-christian",
        "practitioner",
        "churches-religious"
    ],
    "wof:name":"Connie Coddington CSB",
    "wof:placetype":"venue"
},
  "geometry": {"coordinates":[-88.111181,43.019372],"type":"Point"}
}