{
  "type": "Feature",
  "properties": {
    "addr:full":"13615 State Hwy 32 Mountain WI 54149",
    "addr:housenumber":"13615",
    "addr:postcode":"54149",
    "addr:street":"State Hwy 32",
    "iso:country":"US",
    "sg:address":"13615 State Hwy 32",
    "sg:city":"Mountain",
    "sg:classifiers":[
        {
            "category":"Building & Trades",
            "subcategory":"Landscaping Services",
            "type":"Services"
        }
    ],
    "sg:phone":"+1 715 276 1410",
    "sg:postcode":"54149",
    "sg:province":"WI",
    "sg:tags":[
        "landscape",
        "contractor"
    ],
    "wof:name":"Peter Bollenbach Landscape",
    "wof:placetype":"venue"
},
  "geometry": {"coordinates":[-88.466463,45.173001],"type":"Point"}
}