{
  "type": "Feature",
  "properties": {
    "iso:country":"US",
    "sg:address":"9036 School Rd",
    "sg:city":"Brussels",
    "sg:classifiers":[
        {
            "category":"Farming",
            "subcategory":"Dairy Farm",
            "type":"Manufacturing & Wholesale Goods"
        }
    ],
    "sg:phone":"+1 920 825 7814",
    "sg:postcode":"54204",
    "sg:province":"WI",
    "wof:name":"Denil Dairy",
    "wof:placetype":"venue"
},
  "geometry": {"coordinates":[-87.569073,44.733568],"type":"Point"}
}