{
  "type": "Feature",
  "properties": {
    "addr:full":"1602 S Park St Madison WI 53715",
    "addr:housenumber":"1602",
    "addr:postcode":"53715",
    "addr:street":"S Park St",
    "iso:country":"US",
    "sg:address":"1602 S Park St",
    "sg:city":"Madison",
    "sg:classifiers":[
        {
            "category":"Education",
            "subcategory":"College",
            "type":"Public Place"
        }
    ],
    "sg:phone":"+1 608 255 6568",
    "sg:postcode":"53715",
    "sg:province":"WI",
    "sg:tags":[
        "academic",
        "school"
    ],
    "wof:name":"Madison Area Technical College",
    "wof:placetype":"venue"
},
  "geometry": {"coordinates":[-89.394498,43.051048],"type":"Point"}
}