{
  "type": "Feature",
  "properties": {
    "iso:country":"US",
    "sg:address":"13430 W Raddison Dr",
    "sg:city":"New Berlin",
    "sg:classifiers":[
        {
            "category":"Banks & Credit Unions",
            "subcategory":"Bank",
            "type":"Services"
        }
    ],
    "sg:phone":"+1 414 529 9999",
    "sg:postcode":"53151",
    "sg:province":"WI",
    "sg:tags":[
        "loan",
        "real estate"
    ],
    "wof:name":"Lake Country Mortgage",
    "wof:placetype":"venue"
},
  "geometry": {"coordinates":[-88.082605,42.954491],"type":"Point"}
}