{
  "type": "Feature",
  "properties": {
    "addr:full":"9927 N Port Washington Ln Thiensville WI 53092",
    "addr:housenumber":"9927",
    "addr:postcode":"53092",
    "addr:street":"N Port Washington Ln",
    "iso:country":"US",
    "sg:address":"9927 N Port Washington Ln",
    "sg:city":"Thiensville",
    "sg:classifiers":[
        {
            "category":"Banks & Credit Unions",
            "subcategory":"Financial Services",
            "type":"Services"
        }
    ],
    "sg:phone":"+1 262 241 3457",
    "sg:postcode":"53092",
    "sg:province":"WI",
    "sg:tags":[
        "investor"
    ],
    "wof:name":"Samuel Investments LLC",
    "wof:placetype":"venue"
},
  "geometry": {"coordinates":[-87.924448,43.198771],"type":"Point"}
}