{
  "type": "Feature",
  "properties": {
    "iso:country":"US",
    "sg:address":"1926 90th St",
    "sg:city":"New Richmond",
    "sg:classifiers":[
        {
            "category":"Professional",
            "type":"Services"
        }
    ],
    "sg:phone":"+1 715 247 2781",
    "sg:postcode":"54017",
    "sg:province":"WI",
    "wof:name":"D B V LLC",
    "wof:placetype":"venue"
},
  "geometry": {"coordinates":[-92.631314,45.137279],"type":"Point"}
}