{
  "type": "Feature",
  "properties": {
    "iso:country":"US",
    "sg:address":"60 Hollander Ct",
    "sg:city":"Fond Du Lac",
    "sg:classifiers":[
        {
            "category":"Freight",
            "type":"Transportation"
        }
    ],
    "sg:phone":"+1 920 923 7920",
    "sg:postcode":"54937",
    "sg:province":"WI",
    "sg:tags":[
        "mover"
    ],
    "sg:website":"www.dufranemoving.com",
    "wof:name":"Dufrane Moving & Storage Inc",
    "wof:placetype":"venue"
},
  "geometry": {"coordinates":[-88.469556,43.751118],"type":"Point"}
}