{
  "type": "Feature",
  "properties": {
    "iso:country":"US",
    "sg:address":"626 S Main St",
    "sg:city":"Janesville",
    "sg:classifiers":[
        {
            "category":"Professional",
            "subcategory":"Computer Services",
            "type":"Services"
        }
    ],
    "sg:phone":"+1 608 743 0866",
    "sg:postcode":"53545",
    "sg:province":"WI",
    "sg:tags":[
        "datum"
    ],
    "wof:name":"Dots On The Go",
    "wof:placetype":"venue"
},
  "geometry": {"coordinates":[-89.01348,42.674772],"type":"Point"}
}