{
  "type": "Feature",
  "properties": {
    "iso:country":"US",
    "sg:address":"2 Harrison St",
    "sg:city":"N Fond Du Lac",
    "sg:classifiers":[
        {
            "category":"Railroad",
            "type":"Transportation"
        }
    ],
    "sg:phone":"+1 920 929 6080",
    "sg:postcode":"54937",
    "sg:province":"WI",
    "wof:name":"Wisconsin Central LTD",
    "wof:placetype":"venue"
},
  "geometry": {"coordinates":[-88.481012,43.80957],"type":"Point"}
}