{
  "type": "Feature",
  "properties": {
    "iso:country":"US",
    "sg:address":"765 Woodlake Rd",
    "sg:city":"Kohler",
    "sg:classifiers":[
        {
            "category":"Shopping",
            "subcategory":"Gifts & Souvenirs",
            "type":"Retail Goods"
        }
    ],
    "sg:phone":"+1 920 458 5570",
    "sg:postcode":"53044",
    "sg:province":"WI",
    "sg:tags":[
        "shop"
    ],
    "wof:name":"Kohler Gardener",
    "wof:placetype":"venue"
},
  "geometry": {"coordinates":[-87.78282400000001,43.743934],"type":"Point"}
}