{
  "type": "Feature",
  "properties": {
    "iso:country":"US",
    "sg:address":"7261 Marsh Rd",
    "sg:city":"Fremont",
    "sg:classifiers":[
        {
            "category":"Farming",
            "subcategory":"Farm",
            "type":"Manufacturing & Wholesale Goods"
        }
    ],
    "sg:phone":"+1 920 667 4932",
    "sg:postcode":"54940",
    "sg:province":"WI",
    "sg:tags":[
        "crop",
        "general"
    ],
    "wof:name":"A Oberstadt",
    "wof:placetype":"venue"
},
  "geometry": {"coordinates":[-88.76598,44.243291],"type":"Point"}
}