{
  "type": "Feature",
  "properties": {
    "addr:full":"1873 Horseshoe Ln De Pere WI 54115",
    "addr:housenumber":"1873",
    "addr:postcode":"54115",
    "addr:street":"Horseshoe Ln",
    "iso:country":"US",
    "sg:address":"1873 Horseshoe Ln",
    "sg:city":"De Pere",
    "sg:classifiers":[
        {
            "category":"Building & Trades",
            "subcategory":"Construction",
            "type":"Services"
        }
    ],
    "sg:phone":"+1 920 336 3863",
    "sg:postcode":"54115",
    "sg:province":"WI",
    "sg:tags":[
        "residential"
    ],
    "wof:name":"Paul Collette Construction",
    "wof:placetype":"venue"
},
  "geometry": {"coordinates":[-88.041104,44.431586],"type":"Point"}
}