{
  "type": "Feature",
  "properties": {
    "addr:full":"807 S Farwell St Eau Claire WI 54701",
    "addr:housenumber":"807",
    "addr:postcode":"54701",
    "addr:street":"S Farwell St",
    "iso:country":"US",
    "sg:address":"807 S Farwell St",
    "sg:city":"Eau Claire",
    "sg:classifiers":[
        {
            "category":"Health Services",
            "subcategory":"Doctor",
            "type":"Services"
        }
    ],
    "sg:phone":"+1 715 839 5175",
    "sg:postcode":"54701",
    "sg:province":"WI",
    "sg:tags":[
        "medical",
        "hospital",
        "general"
    ],
    "wof:name":"Eau Clire Fmly Medicine Clinic",
    "wof:placetype":"venue"
},
  "geometry": {"coordinates":[-91.494086,44.806934],"type":"Point"}
}