{
  "type": "Feature",
  "properties": {
    "addr:full":"3395 Co Rd B Westby WI 54667",
    "addr:housenumber":"3395",
    "addr:postcode":"54667",
    "addr:street":"Co Rd",
    "iso:country":"US",
    "sg:address":"3395 Co Rd B",
    "sg:city":"Westby",
    "sg:classifiers":[
        {
            "category":"Organizations",
            "subcategory":"Religious Organization",
            "type":"Services"
        }
    ],
    "sg:phone":"+1 608 634 4808",
    "sg:postcode":"54667",
    "sg:province":"WI",
    "sg:tags":[
        "church"
    ],
    "wof:name":"Bethel Lutheran Church",
    "wof:placetype":"venue"
},
  "geometry": {"coordinates":[-90.94951,43.604722],"type":"Point"}
}