{
  "type": "Feature",
  "properties": {
    "iso:country":"US",
    "sg:address":"8018 W Capitol Dr",
    "sg:city":"Milwaukee",
    "sg:classifiers":[
        {
            "category":"Autos & Motor Vehicles",
            "subcategory":"Motorcycle Sales",
            "type":"Retail Goods"
        }
    ],
    "sg:phone":"+1 414 464 7744",
    "sg:postcode":"53222",
    "sg:province":"WI",
    "wof:name":"Milwaukee Harley - Davidson Inc",
    "wof:placetype":"venue"
},
  "geometry": {"coordinates":[-88.012602,43.089936],"type":"Point"}
}