{
  "type": "Feature",
  "properties": {
    "iso:country":"US",
    "sg:address":"2820 W Grand Ave",
    "sg:city":"Wisconsin Rapids",
    "sg:classifiers":[
        {
            "category":"Retail",
            "subcategory":"Auto Rental",
            "type":"Services"
        }
    ],
    "sg:phone":"+1 715 424 1113",
    "sg:postcode":"54495",
    "sg:province":"WI",
    "sg:tags":[
        "renting",
        "leasing",
        "trailer"
    ],
    "wof:name":"U-Haul Co",
    "wof:placetype":"venue"
},
  "geometry": {"coordinates":[-89.858515,44.39742],"type":"Point"}
}