{
  "type": "Feature",
  "properties": {
    "addr:full":"515 W Moreland Blvd Waukesha WI 53188",
    "addr:housenumber":"515",
    "addr:postcode":"53188",
    "addr:street":"W Moreland Blvd",
    "iso:country":"US",
    "sg:address":"515 W Moreland Blvd",
    "sg:city":"Waukesha",
    "sg:classifiers":[
        {
            "category":"Wholesale",
            "subcategory":"Electrical",
            "type":"Manufacturing & Wholesale Goods"
        }
    ],
    "sg:phone":"+1 262 446 0956",
    "sg:postcode":"53188",
    "sg:province":"WI",
    "sg:tags":[
        "television"
    ],
    "wof:name":"Court TV",
    "wof:placetype":"venue"
},
  "geometry": {"coordinates":[-88.22783,43.023215],"type":"Point"}
}