{
  "type": "Feature",
  "properties": {
    "iso:country":"US",
    "sg:address":"9401 W Beloit Rd",
    "sg:city":"Milwaukee",
    "sg:classifiers":[
        {
            "category":"Banks & Credit Unions",
            "subcategory":"Bank",
            "type":"Services"
        }
    ],
    "sg:phone":"+1 414 327 1984",
    "sg:postcode":"53227",
    "sg:province":"WI",
    "sg:tags":[
        "loan",
        "broker",
        "mortgage"
    ],
    "sg:website":"http://www.marine-financial.com",
    "wof:name":"Marine Financial",
    "wof:placetype":"venue"
},
  "geometry": {"coordinates":[-88.029449,42.985359],"type":"Point"}
}