{
  "type": "Feature",
  "properties": {
    "iso:country":"US",
    "sg:address":"2544 Lindee Ln",
    "sg:city":"Waupaca",
    "sg:classifiers":[
        {
            "category":"Freight",
            "type":"Transportation"
        }
    ],
    "sg:phone":"+1 715 258 9700",
    "sg:postcode":"54981",
    "sg:province":"WI",
    "sg:tags":[
        "dock"
    ],
    "wof:name":"Best Built Piers",
    "wof:placetype":"venue"
},
  "geometry": {"coordinates":[-89.100006,44.301925],"type":"Point"}
}