{
  "type": "Feature",
  "properties": {
    "addr:full":"709 Eastern Trl Mukwonago WI 53149",
    "addr:housenumber":"709",
    "addr:postcode":"53149",
    "addr:street":"Eastern Trl",
    "iso:country":"US",
    "sg:address":"709 Eastern Trl",
    "sg:city":"Mukwonago",
    "sg:classifiers":[
        {
            "category":"Freight",
            "type":"Transportation"
        }
    ],
    "sg:phone":"+1 262 363 3001",
    "sg:postcode":"53149",
    "sg:province":"WI",
    "wof:name":"Tri-State Expedited Svc",
    "wof:placetype":"venue"
},
  "geometry": {"coordinates":[-88.31224400000001,42.873039],"type":"Point"}
}