{
  "type": "Feature",
  "properties": {
    "iso:country":"US",
    "sg:address":"4777 Rocky Ln",
    "sg:city":"Bonduel",
    "sg:classifiers":[
        {
            "category":"Farming",
            "subcategory":"Dairy Farm",
            "type":"Manufacturing & Wholesale Goods"
        }
    ],
    "sg:phone":"+1 715 758 6748",
    "sg:postcode":"54107",
    "sg:province":"WI",
    "wof:name":"Allen & Elsie Bontrager",
    "wof:placetype":"venue"
},
  "geometry": {"coordinates":[-88.482767,44.744505],"type":"Point"}
}