{
  "type": "Feature",
  "properties": {
    "iso:country":"US",
    "sg:address":"3667 Flintville Rd",
    "sg:city":"Green Bay",
    "sg:classifiers":[
        {
            "category":"Organizations",
            "subcategory":"Religious Organization",
            "type":"Services"
        }
    ],
    "sg:phone":"+1 920 865 7677",
    "sg:postcode":"54313",
    "sg:province":"WI",
    "sg:tags":[
        "church"
    ],
    "sg:website":"www.stedwardisidore.org",
    "wof:name":"St Edward & Isidore Rectory",
    "wof:placetype":"venue"
},
  "geometry": {"coordinates":[-88.121438,44.638513],"type":"Point"}
}