{
  "type": "Feature",
  "properties": {
    "iso:country":"US",
    "sg:address":"10059 Rose-Eld Rd",
    "sg:city":"Rosendale",
    "sg:classifiers":[
        {
            "category":"Building & Trades",
            "subcategory":"Construction",
            "type":"Services"
        }
    ],
    "sg:phone":"+1 920 872 2712",
    "sg:postcode":"54974",
    "sg:province":"WI",
    "sg:tags":[
        "concrete",
        "contractor"
    ],
    "wof:name":"King's Concrete & Construction",
    "wof:placetype":"venue"
},
  "geometry": {"coordinates":[-88.64991000000001,43.815026],"type":"Point"}
}