{
  "type": "Feature",
  "properties": {
    "iso:country":"US",
    "sg:address":"7200 S 6th St",
    "sg:city":"Oak Creek",
    "sg:classifiers":[
        {
            "category":"Manufacturing",
            "subcategory":"Metals",
            "type":"Manufacturing & Wholesale Goods"
        }
    ],
    "sg:phone":"+1 414 764 0220",
    "sg:postcode":"53154",
    "sg:province":"WI",
    "sg:tags":[
        "steel",
        "mills"
    ],
    "wof:name":"Nucor Cold Finish Wisconsin",
    "wof:placetype":"venue"
},
  "geometry": {"coordinates":[-87.919793,42.915243],"type":"Point"}
}