{
  "type": "Feature",
  "properties": {
    "iso:country":"US",
    "sg:address":"2621 S Green Bay Rd",
    "sg:city":"Racine",
    "sg:classifiers":[
        {
            "category":"Home & Garden",
            "subcategory":"Home Furnishings",
            "type":"Retail Goods"
        }
    ],
    "sg:phone":"+1 262 554 2311",
    "sg:postcode":"53406",
    "sg:province":"WI",
    "wof:name":"Pier 1",
    "wof:placetype":"venue"
},
  "geometry": {"coordinates":[-87.852091,42.704095],"type":"Point"}
}