{
  "type": "Feature",
  "properties": {
    "addr:full":"142 E Main St Twin Lakes WI 53181",
    "addr:housenumber":"142",
    "addr:postcode":"53181",
    "addr:street":"E Main St",
    "iso:country":"US",
    "sg:address":"142 E Main St",
    "sg:city":"Twin Lakes",
    "sg:classifiers":[
        {
            "category":"Home & Garden",
            "subcategory":"Carpets & Floor Coverings",
            "type":"Retail Goods"
        }
    ],
    "sg:phone":"+1 262 877 9402",
    "sg:postcode":"53181",
    "sg:province":"WI",
    "sg:tags":[
        "dealer",
        "rug"
    ],
    "wof:name":"Warehouse Fashion Floors",
    "wof:placetype":"venue"
},
  "geometry": {"coordinates":[-88.254794,42.531146],"type":"Point"}
}