{
  "type": "Feature",
  "properties": {
    "iso:country":"US",
    "sg:address":"334 N Pelham St",
    "sg:city":"Rhinelander",
    "sg:classifiers":[
        {
            "category":"Museum",
            "type":"Entertainment"
        }
    ],
    "sg:phone":"+1 715 369 5004",
    "sg:postcode":"54501",
    "sg:province":"WI",
    "wof:name":"Loging Museum",
    "wof:placetype":"venue"
},
  "geometry": {"coordinates":[-89.409812,45.642021],"type":"Point"}
}