{
  "type": "Feature",
  "properties": {
    "addr:full":"2990 Riverside Dr Green Bay WI 54301",
    "addr:housenumber":"2990",
    "addr:postcode":"54301",
    "addr:street":"Riverside Dr",
    "iso:country":"US",
    "sg:address":"2990 Riverside Dr",
    "sg:city":"Green Bay",
    "sg:classifiers":[
        {
            "category":"Building & Trades",
            "subcategory":"Construction",
            "type":"Services"
        }
    ],
    "sg:phone":"+1 920 430 1699",
    "sg:postcode":"54301",
    "sg:province":"WI",
    "sg:tags":[
        "company"
    ],
    "wof:name":"Vinton Construction",
    "wof:placetype":"venue"
},
  "geometry": {"coordinates":[-88.040029,44.472777],"type":"Point"}
}