{
  "type": "Feature",
  "properties": {
    "iso:country":"US",
    "sg:address":"2031 N 38th St",
    "sg:city":"Milwaukee",
    "sg:classifiers":[
        {
            "category":"Organizations",
            "subcategory":"Religious Organization",
            "type":"Services"
        }
    ],
    "sg:phone":"+1 414 444 3131",
    "sg:postcode":"53208",
    "sg:province":"WI",
    "sg:tags":[
        "churches-lutheran",
        "church"
    ],
    "wof:name":"Bethany Luth. Church",
    "wof:placetype":"venue"
},
  "geometry": {"coordinates":[-87.961144,43.056756],"type":"Point"}
}