{
  "type": "Feature",
  "properties": {
    "addr:full":"24855 National Ave Mukwonago WI 53149",
    "addr:housenumber":"24855",
    "addr:postcode":"53149",
    "addr:street":"National Ave",
    "iso:country":"US",
    "sg:address":"24855 National Ave",
    "sg:city":"Mukwonago",
    "sg:classifiers":[
        {
            "category":"Building & Trades",
            "subcategory":"Construction",
            "type":"Services"
        }
    ],
    "sg:phone":"+1 262 662 5073",
    "sg:postcode":"53149",
    "sg:province":"WI",
    "sg:tags":[
        "house"
    ],
    "wof:name":"Vintage Custom Homes LLC",
    "wof:placetype":"venue"
},
  "geometry": {"coordinates":[-88.245226,42.905108],"type":"Point"}
}