{
  "type": "Feature",
  "properties": {
    "addr:full":"8020 Division St Park Falls WI 54552",
    "addr:housenumber":"8020",
    "addr:postcode":"54552",
    "addr:street":"Division St",
    "iso:country":"US",
    "sg:address":"8020 Division St",
    "sg:city":"Park Falls",
    "sg:classifiers":[
        {
            "category":"Retail",
            "subcategory":"Repair Shop",
            "type":"Services"
        }
    ],
    "sg:phone":"+1 715 762 4930",
    "sg:postcode":"54552",
    "sg:province":"WI",
    "wof:name":"Jakes Deluxe Repair",
    "wof:placetype":"venue"
},
  "geometry": {"coordinates":[-90.464202,45.934764],"type":"Point"}
}