{
  "type": "Feature",
  "properties": {
    "addr:full":"520 N 5th Ave Gilman WI 54433",
    "addr:housenumber":"520",
    "addr:postcode":"54433",
    "addr:street":"N 5Th Ave",
    "iso:country":"US",
    "sg:address":"520 N 5th Ave",
    "sg:city":"Gilman",
    "sg:classifiers":[
        {
            "category":"Professional",
            "subcategory":"Business Services",
            "type":"Services"
        }
    ],
    "sg:phone":"+1 715 447 8564",
    "sg:postcode":"54433",
    "sg:province":"WI",
    "wof:name":"Hickeys Auction Service",
    "wof:placetype":"venue"
},
  "geometry": {"coordinates":[-90.807654,45.169659],"type":"Point"}
}