{
  "type": "Feature",
  "properties": {
    "iso:country":"US",
    "sg:address":"871 W Main St",
    "sg:city":"Brownsville",
    "sg:classifiers":[
        {
            "category":"Organizations",
            "subcategory":"Community Association",
            "type":"Services"
        }
    ],
    "sg:phone":"+1 920 583 4550",
    "sg:postcode":"53006",
    "sg:province":"WI",
    "sg:tags":[
        "club"
    ],
    "wof:name":"Brownsville Community Club",
    "wof:placetype":"venue"
},
  "geometry": {"coordinates":[-88.499864,43.616156],"type":"Point"}
}