{
  "type": "Feature",
  "properties": {
    "iso:country":"US",
    "sg:address":"5605 W Hemlock St",
    "sg:city":"Milwaukee",
    "sg:classifiers":[
        {
            "category":"Manufacturing",
            "subcategory":"Tools & Machinery",
            "type":"Manufacturing & Wholesale Goods"
        }
    ],
    "sg:phone":"+1 414 760 3377",
    "sg:postcode":"53223",
    "sg:province":"WI",
    "sg:tags":[
        "lighting",
        "fixture"
    ],
    "wof:name":"Schumaker Lighting Inc",
    "wof:placetype":"venue"
},
  "geometry": {"coordinates":[-87.985258,43.151594],"type":"Point"}
}