{
  "type": "Feature",
  "properties": {
    "addr:full":"6073 Co Rd C Marion WI 54950",
    "addr:housenumber":"6073",
    "addr:postcode":"54950",
    "addr:street":"Co Rd C",
    "iso:country":"US",
    "sg:address":"6073 Co Rd C",
    "sg:city":"Marion",
    "sg:classifiers":[
        {
            "category":"Organizations",
            "subcategory":"Religious Organization",
            "type":"Services"
        }
    ],
    "sg:phone":"+1 715 754 2690",
    "sg:postcode":"54950",
    "sg:province":"WI",
    "sg:tags":[
        "church"
    ],
    "wof:name":"St Paul's Lutheran Church",
    "wof:placetype":"venue"
},
  "geometry": {"coordinates":[-88.921778,44.604987],"type":"Point"}
}