{
  "type": "Feature",
  "properties": {
    "addr:full":"433 W Saint Paul Ave Milwaukee WI 53203",
    "addr:housenumber":"433",
    "addr:postcode":"53203",
    "addr:street":"W Saint Paul Ave",
    "iso:country":"US",
    "sg:address":"433 W Saint Paul Ave",
    "sg:city":"Milwaukee",
    "sg:classifiers":[
        {
            "category":"Retail",
            "subcategory":"Auto Rental",
            "type":"Services"
        }
    ],
    "sg:phone":"+1 414 224 0050",
    "sg:postcode":"53203",
    "sg:province":"WI",
    "sg:tags":[
        "car"
    ],
    "sg:website":"http://www.hertz.com",
    "wof:name":"Hertz",
    "wof:placetype":"venue"
},
  "geometry": {"coordinates":[-87.916284,43.034662],"type":"Point"}
}