{
  "type": "Feature",
  "properties": {
    "iso:country":"US",
    "sg:address":"4125 S Co Rd P",
    "sg:city":"Denmark",
    "sg:classifiers":[
        {
            "category":"Wholesale",
            "subcategory":"Construction Materials",
            "type":"Manufacturing & Wholesale Goods"
        },
        {
            "category":"Home & Garden",
            "subcategory":"Building Materials",
            "type":"Retail Goods"
        }
    ],
    "sg:phone":"+1 920 863 2847",
    "sg:postcode":"54208",
    "sg:province":"WI",
    "sg:tags":[
        "door"
    ],
    "wof:name":"Lakeland Door & Service Inc",
    "wof:placetype":"venue"
},
  "geometry": {"coordinates":[-87.785844,44.422938],"type":"Point"}
}