{
  "type": "Feature",
  "properties": {
    "iso:country":"US",
    "sg:address":"1217 Madison St",
    "sg:city":"Beaver Dam",
    "sg:classifiers":[
        {
            "category":"Professional",
            "type":"Services"
        }
    ],
    "sg:phone":"+1 920 887 1631",
    "sg:postcode":"53916",
    "sg:province":"WI",
    "sg:tags":[
        "establishment"
    ],
    "wof:name":"South Hills",
    "wof:placetype":"venue"
},
  "geometry": {"coordinates":[-88.857028,43.440888],"type":"Point"}
}