{
  "type": "Feature",
  "properties": {
    "iso:country":"US",
    "sg:address":"170 Division St",
    "sg:city":"Park Falls",
    "sg:classifiers":[
        {
            "category":"Insurance",
            "subcategory":"Insurance Agent",
            "type":"Services"
        }
    ],
    "sg:phone":"+1 715 762 2000",
    "sg:postcode":"54552",
    "sg:province":"WI",
    "wof:name":"First National Ins Agency",
    "wof:placetype":"venue"
},
  "geometry": {"coordinates":[-90.448915,45.935191],"type":"Point"}
}