{
  "type": "Feature",
  "properties": {
    "iso:country":"US",
    "sg:address":"217 N 8th St",
    "sg:city":"Medford",
    "sg:classifiers":[
        {
            "category":"Home & Garden",
            "subcategory":"Building Materials",
            "type":"Retail Goods"
        }
    ],
    "sg:phone":"+1 715 748 3757",
    "sg:postcode":"54451",
    "sg:province":"WI",
    "wof:name":"Glass To Go",
    "wof:placetype":"venue"
},
  "geometry": {"coordinates":[-90.333339,45.141915],"type":"Point"}
}