{
  "type": "Feature",
  "properties": {
    "iso:country":"US",
    "sg:address":"3736 State Hwy 32",
    "sg:city":"Pulaski",
    "sg:classifiers":[
        {
            "category":"Airport",
            "type":"Transportation"
        }
    ],
    "sg:phone":"+1 920 822 3644",
    "sg:postcode":"54162",
    "sg:province":"WI",
    "wof:name":"Blue Skies",
    "wof:placetype":"venue"
},
  "geometry": {"coordinates":[-88.245693,44.718711],"type":"Point"}
}