{
  "type": "Feature",
  "properties": {
    "iso:country":"US",
    "sg:address":"2000 W Pershing St",
    "sg:city":"Appleton",
    "sg:classifiers":[
        {
            "category":"Freight",
            "type":"Transportation"
        }
    ],
    "sg:phone":"+1 920 730 4200",
    "sg:postcode":"54914",
    "sg:province":"WI",
    "sg:tags":[
        "refrigeration",
        "special"
    ],
    "wof:name":"Atlas Cold Storage",
    "wof:placetype":"venue"
},
  "geometry": {"coordinates":[-88.437587,44.284001],"type":"Point"}
}