{
  "type": "Feature",
  "properties": {
    "iso:country":"US",
    "sg:address":"16400 W Lincoln Ave",
    "sg:city":"New Berlin",
    "sg:classifiers":[
        {
            "category":"Manufacturing",
            "subcategory":"Metals",
            "type":"Manufacturing & Wholesale Goods"
        }
    ],
    "sg:phone":"+1 262 784 3838",
    "sg:postcode":"53151",
    "sg:province":"WI",
    "sg:tags":[
        "tool"
    ],
    "sg:website":"www.toolrite.com",
    "wof:name":"Carbide Specialists Inc",
    "wof:placetype":"venue"
},
  "geometry": {"coordinates":[-88.119027,43.002647],"type":"Point"}
}