{
  "type": "Feature",
  "properties": {
    "iso:country":"US",
    "sg:address":"619 du Bay Ave",
    "sg:city":"Stevens Point",
    "sg:classifiers":[
        {
            "category":"Building & Trades",
            "subcategory":"Construction",
            "type":"Services"
        }
    ],
    "sg:phone":"+1 715 344 7934",
    "sg:postcode":"54481",
    "sg:province":"WI",
    "sg:tags":[
        "carpentry",
        "contractor"
    ],
    "wof:name":"Tonys Custom Carpentry",
    "wof:placetype":"venue"
},
  "geometry": {"coordinates":[-89.59429,44.551854],"type":"Point"}
}