{
  "type": "Feature",
  "properties": {
    "addr:full":"13712 Northwestern Ave Franksville WI 53126",
    "addr:housenumber":"13712",
    "addr:postcode":"53126",
    "addr:street":"Northwestern Ave",
    "iso:country":"US",
    "sg:address":"13712 Northwestern Ave",
    "sg:city":"Franksville",
    "sg:classifiers":[
        {
            "category":"Restaurant",
            "type":"Food & Drink"
        }
    ],
    "sg:menulink":"http://www.allmenus.com/wi/caledonia/159417-arbys/menu/",
    "sg:phone":"+1 262 835 2417",
    "sg:postcode":"53126",
    "sg:province":"WI",
    "sg:tags":[
        "burger",
        "american"
    ],
    "wof:name":"Arby's",
    "wof:placetype":"venue"
},
  "geometry": {"coordinates":[-87.951369,42.778334],"type":"Point"}
}