{
  "type": "Feature",
  "properties": {
    "iso:country":"US",
    "sg:address":"1545 Woodmont Way",
    "sg:city":"Green Bay",
    "sg:classifiers":[
        {
            "category":"Building & Trades",
            "subcategory":"Construction",
            "type":"Services"
        }
    ],
    "sg:phone":"+1 920 499 9392",
    "sg:postcode":"54313",
    "sg:province":"WI",
    "sg:tags":[
        "painting",
        "contractor"
    ],
    "wof:name":"Green Bay Paint Professionals",
    "wof:placetype":"venue"
},
  "geometry": {"coordinates":[-88.08689,44.507746],"type":"Point"}
}