{
  "type": "Feature",
  "properties": {
    "iso:country":"US",
    "sg:address":"3123 W North Ave",
    "sg:city":"Milwaukee",
    "sg:classifiers":[
        {
            "category":"Manufacturing",
            "subcategory":"Metals",
            "type":"Manufacturing & Wholesale Goods"
        }
    ],
    "sg:phone":"+1 414 873 4400",
    "sg:postcode":"53208",
    "sg:province":"WI",
    "sg:tags":[
        "trim",
        "frame",
        "door",
        "sash"
    ],
    "wof:name":"Fred's Ornamental Security",
    "wof:placetype":"venue"
},
  "geometry": {"coordinates":[-87.952924,43.060533],"type":"Point"}
}