{
  "type": "Feature",
  "properties": {
    "iso:country":"US",
    "sg:address":"320 E Main St",
    "sg:city":"Wautoma",
    "sg:classifiers":[
        {
            "category":"Retail",
            "subcategory":"Auto Repair",
            "type":"Services"
        }
    ],
    "sg:phone":"+1 920 787 7396",
    "sg:postcode":"54982",
    "sg:province":"WI",
    "sg:tags":[
        "body",
        "automobile",
        "painting"
    ],
    "wof:name":"Pat's Collision Repair/Towing",
    "wof:placetype":"venue"
},
  "geometry": {"coordinates":[-89.283305,44.074118],"type":"Point"}
}