{
  "type": "Feature",
  "properties": {
    "addr:full":"9 E Main St Watertown WI 53094",
    "addr:housenumber":"9",
    "addr:postcode":"53094",
    "addr:street":"E Main St",
    "iso:country":"US",
    "sg:address":"9 E Main St",
    "sg:city":"Watertown",
    "sg:classifiers":[
        {
            "category":"Personal",
            "subcategory":"Beauty Salon",
            "type":"Services"
        }
    ],
    "sg:phone":"+1 920 261 9022",
    "sg:postcode":"53094",
    "sg:province":"WI",
    "sg:tags":[
        "shop"
    ],
    "wof:name":"Shear Xpressions",
    "wof:placetype":"venue"
},
  "geometry": {"coordinates":[-88.724726,43.194302],"type":"Point"}
}