{
  "type": "Feature",
  "properties": {
    "addr:full":"780 N Water St Milwaukee WI 53202",
    "addr:housenumber":"780",
    "addr:postcode":"53202",
    "addr:street":"N Water St",
    "iso:country":"US",
    "sg:address":"780 N Water St",
    "sg:city":"Milwaukee",
    "sg:classifiers":[
        {
            "category":"Professional",
            "subcategory":"Lawyer & Legal Services",
            "type":"Services"
        }
    ],
    "sg:phone":"+1 414 273 3500",
    "sg:postcode":"53202",
    "sg:province":"WI",
    "sg:tags":[
        "firm",
        "attorney",
        "law"
    ],
    "sg:website":"www.gklaw.com",
    "wof:name":"Godfrey & Kahn SC",
    "wof:placetype":"venue"
},
  "geometry": {"coordinates":[-87.909519,43.040711],"type":"Point"}
}