{
  "type": "Feature",
  "properties": {
    "iso:country":"US",
    "sg:address":"5485 N Port Washington Rd",
    "sg:city":"Milwaukee",
    "sg:classifiers":[
        {
            "category":"Travel",
            "subcategory":"Hotels & Motels",
            "type":"Entertainment"
        },
        {
            "category":"Travel",
            "subcategory":"Bed & Breakfast",
            "type":"Entertainment"
        }
    ],
    "sg:phone":"+1 414 961 7272",
    "sg:postcode":"53217",
    "sg:province":"WI",
    "sg:tags":[
        "inn",
        "lodging"
    ],
    "sg:website":"http://www.baymontinns.com/hotel/23875&cid=RASE",
    "wof:name":"Baymont Inn & Suites Glendale-Milwaukee-NE",
    "wof:placetype":"venue"
},
  "geometry": {"coordinates":[-87.91674,43.116687],"type":"Point"}
}