{
  "type": "Feature",
  "properties": {
    "addr:full":"23585 115th Ave Cadott WI 54727",
    "addr:housenumber":"23585",
    "addr:postcode":"54727",
    "addr:street":"115Th Ave",
    "iso:country":"US",
    "sg:address":"23585 115th Ave",
    "sg:city":"Cadott",
    "sg:classifiers":[
        {
            "category":"Building & Trades",
            "subcategory":"Construction",
            "type":"Services"
        }
    ],
    "sg:phone":"+1 715 289 3522",
    "sg:postcode":"54727",
    "sg:province":"WI",
    "sg:tags":[
        "excavation"
    ],
    "wof:name":"Roger Balts",
    "wof:placetype":"venue"
},
  "geometry": {"coordinates":[-91.196579,45.006485],"type":"Point"}
}