{
  "type": "Feature",
  "properties": {
    "iso:country":"US",
    "sg:address":"213 Klein Dr",
    "sg:city":"Waunakee",
    "sg:classifiers":[
        {
            "category":"Shopping",
            "subcategory":"Used Merchandise",
            "type":"Retail Goods"
        },
        {
            "category":"Social Services",
            "type":"Services"
        }
    ],
    "sg:phone":"+1 608 850 6271",
    "sg:postcode":"53597",
    "sg:province":"WI",
    "sg:tags":[
        "shop",
        "thrift"
    ],
    "wof:name":"St Vincent Depaul Stores",
    "wof:placetype":"venue"
},
  "geometry": {"coordinates":[-89.463397,43.191454],"type":"Point"}
}