{
  "type": "Feature",
  "properties": {
    "iso:country":"US",
    "sg:address":"3123 E Washington Ave",
    "sg:city":"Madison",
    "sg:classifiers":[
        {
            "category":"Retail",
            "subcategory":"Repair Shop",
            "type":"Services"
        }
    ],
    "sg:phone":"+1 608 241 5557",
    "sg:postcode":"53704",
    "sg:province":"WI",
    "sg:tags":[
        "scooter",
        "motorcycle",
        "motor"
    ],
    "wof:name":"Mad-City Cycle Svc",
    "wof:placetype":"venue"
},
  "geometry": {"coordinates":[-89.339386,43.106936],"type":"Point"}
}