{
  "type": "Feature",
  "properties": {
    "iso:country":"US",
    "sg:address":"12581 State Hwy 29",
    "sg:city":"Prescott",
    "sg:classifiers":[
        {
            "category":"Wholesale",
            "subcategory":"Farm Supplies",
            "type":"Manufacturing & Wholesale Goods"
        }
    ],
    "sg:phone":"+1 715 262 5799",
    "sg:postcode":"54021",
    "sg:province":"WI",
    "sg:tags":[
        "bean"
    ],
    "wof:name":"Dow Agrosciences LLC",
    "wof:placetype":"venue"
},
  "geometry": {"coordinates":[-92.767849,44.775728],"type":"Point"}
}