{
  "type": "Feature",
  "properties": {
    "iso:country":"US",
    "sg:address":"11520 W Bluemound Rd",
    "sg:city":"Milwaukee",
    "sg:classifiers":[
        {
            "category":"Shopping",
            "subcategory":"Crafts & Fabrics",
            "type":"Retail Goods"
        },
        {
            "category":"Manufacturing",
            "subcategory":"Pottery",
            "type":"Manufacturing & Wholesale Goods"
        }
    ],
    "sg:phone":"+1 414 443 1800",
    "sg:postcode":"53226",
    "sg:province":"WI",
    "sg:tags":[
        "products-decorative",
        "ceramics-equipment",
        "ceramic",
        "supply"
    ],
    "wof:name":"La Terraza",
    "wof:placetype":"venue"
},
  "geometry": {"coordinates":[-88.06547500000001,43.036449],"type":"Point"}
}