{
  "type": "Feature",
  "properties": {
    "iso:country":"US",
    "sg:address":"10671 Old Stage Rd",
    "sg:city":"Sister Bay",
    "sg:classifiers":[
        {
            "category":"Building & Trades",
            "subcategory":"Plumbing",
            "type":"Services"
        }
    ],
    "sg:phone":"+1 920 854 4371",
    "sg:postcode":"54234",
    "sg:province":"WI",
    "sg:tags":[
        "plumbing",
        "contractor"
    ],
    "wof:name":"Voeks Plumbing",
    "wof:placetype":"venue"
},
  "geometry": {"coordinates":[-87.091283,45.186721],"type":"Point"}
}