{
  "type": "Feature",
  "properties": {
    "iso:country":"US",
    "sg:address":"1530 Corner Rd",
    "sg:city":"Wittenberg",
    "sg:classifiers":[
        {
            "category":"Building & Trades",
            "subcategory":"Plumbing",
            "type":"Services"
        }
    ],
    "sg:phone":"+1 715 454 6888",
    "sg:postcode":"54499",
    "sg:province":"WI",
    "sg:tags":[
        "contractor"
    ],
    "wof:name":"Easy Heating & Cooling LLC",
    "wof:placetype":"venue"
},
  "geometry": {"coordinates":[-89.255607,44.717732],"type":"Point"}
}