{
  "type": "Feature",
  "properties": {
    "iso:country":"US",
    "sg:address":"3705 Jennings Rd",
    "sg:city":"New London",
    "sg:classifiers":[
        {
            "category":"Retail",
            "subcategory":"Repair Shop",
            "type":"Services"
        }
    ],
    "sg:phone":"+1 920 982 6372",
    "sg:postcode":"54961",
    "sg:province":"WI",
    "sg:tags":[
        "refrigeration"
    ],
    "wof:name":"Heating & AC Appl & Duct Clg",
    "wof:placetype":"venue"
},
  "geometry": {"coordinates":[-88.777411,44.377136],"type":"Point"}
}