{
  "type": "Feature",
  "properties": {
    "addr:full":"4720 Golf Rd Eau Claire WI 54701",
    "addr:housenumber":"4720",
    "addr:postcode":"54701",
    "addr:street":"Golf Rd",
    "iso:country":"US",
    "sg:address":"4720 Golf Rd",
    "sg:city":"Eau Claire",
    "sg:classifiers":[
        {
            "category":"Professional",
            "subcategory":"Accounting & Tax Preparation",
            "type":"Services"
        }
    ],
    "sg:phone":"+1 715 852 0177",
    "sg:postcode":"54701",
    "sg:province":"WI",
    "sg:tags":[
        "return"
    ],
    "wof:name":"H & R Block",
    "wof:placetype":"venue"
},
  "geometry": {"coordinates":[-91.448609,44.770517],"type":"Point"}
}