{
  "type": "Feature",
  "properties": {
    "iso:country":"US",
    "sg:address":"1554 Gohres St",
    "sg:city":"La Crosse",
    "sg:classifiers":[
        {
            "category":"Retail",
            "subcategory":"Self-service Laundry",
            "type":"Services"
        }
    ],
    "sg:phone":"+1 608 782 9291",
    "sg:postcode":"54603",
    "sg:province":"WI",
    "wof:name":"Giant Wash",
    "wof:placetype":"venue"
},
  "geometry": {"coordinates":[-91.235109,43.849156],"type":"Point"}
}