{
  "type": "Feature",
  "properties": {
    "iso:country":"US",
    "sg:address":"4556 Marty Lake Rd",
    "sg:city":"Park Falls",
    "sg:classifiers":[
        {
            "category":"Airport",
            "type":"Transportation"
        }
    ],
    "sg:phone":"+1 715 583 4533",
    "sg:postcode":"54552",
    "sg:province":"WI",
    "wof:name":"Merrill Flying Services Inc",
    "wof:placetype":"venue"
},
  "geometry": {"coordinates":[-90.165458,45.983645],"type":"Point"}
}