{
  "type": "Feature",
  "properties": {
    "iso:country":"US",
    "sg:address":"9923 E Scenic Dr",
    "sg:city":"Solon Springs",
    "sg:classifiers":[
        {
            "category":"Professional",
            "subcategory":"Engineering",
            "type":"Services"
        }
    ],
    "sg:phone":"+1 715 378 4493",
    "sg:postcode":"54873",
    "sg:province":"WI",
    "sg:tags":[
        "roads",
        "inspection",
        "for",
        "dot"
    ],
    "wof:name":"True North Engineering Inc",
    "wof:placetype":"venue"
},
  "geometry": {"coordinates":[-91.787462,46.372262],"type":"Point"}
}