{
  "type": "Feature",
  "properties": {
    "iso:country":"US",
    "sg:address":"348 2nd St N",
    "sg:city":"Stevens Point",
    "sg:classifiers":[
        {
            "category":"Bars & Pubs",
            "type":"Food & Drink"
        }
    ],
    "sg:phone":"+1 715 341 1999",
    "sg:postcode":"54481",
    "sg:province":"WI",
    "wof:name":"C J's Bar & Grill",
    "wof:placetype":"venue"
},
  "geometry": {"coordinates":[-89.58574900000001,44.539367],"type":"Point"}
}