{
  "type": "Feature",
  "properties": {
    "addr:full":"6925 Wildwood Point Rd Hartland WI 53029",
    "addr:housenumber":"6925",
    "addr:postcode":"53029",
    "addr:street":"Wildwood Point Rd",
    "iso:country":"US",
    "sg:address":"6925 Wildwood Point Rd",
    "sg:city":"Hartland",
    "sg:classifiers":[
        {
            "category":"Professional",
            "subcategory":"Management & Consulting",
            "type":"Services"
        }
    ],
    "sg:phone":"+1 262 966 7691",
    "sg:postcode":"53029",
    "sg:province":"WI",
    "sg:tags":[
        "business"
    ],
    "wof:name":"Merganser Corp",
    "wof:placetype":"venue"
},
  "geometry": {"coordinates":[-88.390933,43.141099],"type":"Point"}
}