{
  "type": "Feature",
  "properties": {
    "iso:country":"US",
    "sg:address":"231 Woodland Beach Rd",
    "sg:city":"Lake Mills",
    "sg:classifiers":[
        {
            "category":"Education",
            "subcategory":"School",
            "type":"Public Place"
        }
    ],
    "sg:phone":"+1 920 648 2321",
    "sg:postcode":"53551",
    "sg:province":"WI",
    "sg:tags":[
        "high"
    ],
    "sg:website":"www.llhs.org",
    "wof:name":"Lakeside Lutheran High School",
    "wof:placetype":"venue"
},
  "geometry": {"coordinates":[-88.917431,43.0676],"type":"Point"}
}