{
  "type": "Feature",
  "properties": {
    "iso:country":"US",
    "sg:address":"3782 Kettle Moraine Rd",
    "sg:city":"Hartford",
    "sg:classifiers":[
        {
            "category":"Professional",
            "subcategory":"Secretarial Services",
            "type":"Services"
        }
    ],
    "sg:phone":"+1 262 644 6590",
    "sg:postcode":"53027",
    "sg:province":"WI",
    "sg:tags":[
        "medical",
        "reporting",
        "court",
        "typing"
    ],
    "wof:name":"Med Express Transcription Svcs",
    "wof:placetype":"venue"
},
  "geometry": {"coordinates":[-88.319176,43.328073],"type":"Point"}
}