{
  "type": "Feature",
  "properties": {
    "iso:country":"US",
    "sg:address":"704 Willow Creek Pkwy",
    "sg:city":"Watertown",
    "sg:classifiers":[
        {
            "category":"Building & Trades",
            "subcategory":"Construction",
            "type":"Services"
        }
    ],
    "sg:phone":"+1 920 262 6310",
    "sg:postcode":"53094",
    "sg:province":"WI",
    "sg:tags":[
        "carpentry",
        "contractor"
    ],
    "wof:name":"Precision Custom Carpentry LLC",
    "wof:placetype":"venue"
},
  "geometry": {"coordinates":[-88.741433,43.186566],"type":"Point"}
}