{
  "type": "Feature",
  "properties": {
    "iso:country":"US",
    "sg:address":"1010 Menasha Ave",
    "sg:city":"Manitowoc",
    "sg:classifiers":[
        {
            "category":"Manufacturing",
            "subcategory":"Building Materials",
            "type":"Manufacturing & Wholesale Goods"
        },
        {
            "category":"Manufacturing",
            "subcategory":"Wood Products",
            "type":"Manufacturing & Wholesale Goods"
        }
    ],
    "sg:phone":"+1 920 684 3734",
    "sg:postcode":"54220",
    "sg:province":"WI",
    "sg:tags":[
        "mfg"
    ],
    "wof:name":"Manitowoc Woodworking Co Inc",
    "wof:placetype":"venue"
},
  "geometry": {"coordinates":[-87.663232,44.107633],"type":"Point"}
}