{
  "type": "Feature",
  "properties": {
    "addr:full":"407 E Madison St Crandon WI 54520",
    "addr:housenumber":"407",
    "addr:postcode":"54520",
    "addr:street":"E Madison St",
    "iso:country":"US",
    "sg:address":"407 E Madison St",
    "sg:city":"Crandon",
    "sg:classifiers":[
        {
            "category":"Banks & Credit Unions",
            "subcategory":"Financial Services",
            "type":"Services"
        }
    ],
    "sg:phone":"+1 715 478 7903",
    "sg:postcode":"54520",
    "sg:province":"WI",
    "sg:tags":[
        "investor"
    ],
    "wof:name":"Rhjsm Investments LLC",
    "wof:placetype":"venue"
},
  "geometry": {"coordinates":[-88.89878400000001,45.569471],"type":"Point"}
}