{
  "type": "Feature",
  "properties": {
    "iso:country":"US",
    "sg:address":"7450 Sunwood Dr",
    "sg:city":"Neenah",
    "sg:classifiers":[
        {
            "category":"Professional",
            "subcategory":"Business Services",
            "type":"Services"
        }
    ],
    "sg:phone":"+1 920 836 1772",
    "sg:postcode":"54956",
    "sg:province":"WI",
    "wof:name":"Mtd Marketing Services",
    "wof:placetype":"venue"
},
  "geometry": {"coordinates":[-88.555835,44.161298],"type":"Point"}
}