{
  "type": "Feature",
  "properties": {
    "addr:full":"740 Phillips Blvd Sauk City WI 53583",
    "addr:housenumber":"740",
    "addr:postcode":"53583",
    "addr:street":"Phillips Blvd",
    "iso:country":"US",
    "sg:address":"740 Phillips Blvd",
    "sg:city":"Sauk City",
    "sg:classifiers":[
        {
            "category":"Food & Beverages",
            "subcategory":"Groceries & Convenience Stores",
            "type":"Retail Goods"
        }
    ],
    "sg:phone":"+1 608 643 8033",
    "sg:postcode":"53583",
    "sg:province":"WI",
    "wof:name":"Cenex Convenience Store",
    "wof:placetype":"venue"
},
  "geometry": {"coordinates":[-89.72601400000001,43.271256],"type":"Point"}
}