{
  "type": "Feature",
  "properties": {
    "iso:country":"US",
    "sg:address":"626 E Wisconsin Ave",
    "sg:city":"Milwaukee",
    "sg:classifiers":[
        {
            "category":"Government",
            "subcategory":"Office",
            "type":"Public Place"
        }
    ],
    "sg:phone":"+1 414 297 4400",
    "sg:postcode":"53202",
    "sg:province":"WI",
    "sg:tags":[
        "management",
        "land"
    ],
    "wof:name":"Milwaukee Field Office",
    "wof:placetype":"venue"
},
  "geometry": {"coordinates":[-87.903081,43.039018],"type":"Point"}
}