{
  "type": "Feature",
  "properties": {
    "iso:country":"US",
    "sg:address":"3338 N 39th St",
    "sg:city":"Milwaukee",
    "sg:classifiers":[
        {
            "category":"Banks & Credit Unions",
            "subcategory":"Financial Services",
            "type":"Services"
        }
    ],
    "sg:phone":"+1 414 444 8737",
    "sg:postcode":"53216",
    "sg:province":"WI",
    "sg:tags":[
        "investor"
    ],
    "wof:name":"Best Friends United Investment",
    "wof:placetype":"venue"
},
  "geometry": {"coordinates":[-87.96218399999999,43.080339],"type":"Point"}
}