{
  "type": "Feature",
  "properties": {
    "iso:country":"US",
    "sg:address":"37899 Gierok Rd",
    "sg:city":"Independence",
    "sg:classifiers":[
        {
            "category":"Farming",
            "subcategory":"Dairy Farm",
            "type":"Manufacturing & Wholesale Goods"
        }
    ],
    "sg:phone":"+1 715 538 4624",
    "sg:postcode":"54747",
    "sg:province":"WI",
    "wof:name":"Dnr Kulig Farm",
    "wof:placetype":"venue"
},
  "geometry": {"coordinates":[-91.382103,44.390765],"type":"Point"}
}