{
  "type": "Feature",
  "properties": {
    "iso:country":"US",
    "sg:address":"609 S Grandview Ave",
    "sg:city":"Crandon",
    "sg:classifiers":[
        {
            "category":"Freight",
            "type":"Transportation"
        }
    ],
    "sg:phone":"+1 715 478 2248",
    "sg:postcode":"54520",
    "sg:province":"WI",
    "sg:tags":[
        "operator",
        "local",
        "trucking"
    ],
    "wof:name":"Carl & Janet Hawks",
    "wof:placetype":"venue"
},
  "geometry": {"coordinates":[-88.889593,45.567204],"type":"Point"}
}