{
  "type": "Feature",
  "properties": {
    "iso:country":"US",
    "sg:address":"3177 S 107th St",
    "sg:city":"Milwaukee",
    "sg:classifiers":[
        {
            "category":"Place Of Worship",
            "subcategory":"Church",
            "type":"Public Place"
        },
        {
            "category":"Place Of Worship",
            "type":"Public Place"
        },
        {
            "category":"Education",
            "subcategory":"Preschool",
            "type":"Public Place"
        }
    ],
    "sg:phone":"+1 414 541 9050",
    "sg:postcode":"53227",
    "sg:province":"WI",
    "sg:tags":[
        "churches-united",
        "kindergarten",
        "methodist",
        "churches-methodist"
    ],
    "sg:website":"http://www.calvary-preschool.org",
    "wof:name":"Calvary United Methodist Church",
    "wof:placetype":"venue"
},
  "geometry": {"coordinates":[-88.045625,42.98625],"type":"Point"}
}