{
  "type": "Feature",
  "properties": {
    "iso:country":"US",
    "sg:address":"9546 E 16 Frontage Rd",
    "sg:city":"Onalaska",
    "sg:classifiers":[
        {
            "category":"Home & Garden",
            "subcategory":"Home Furnishings",
            "type":"Retail Goods"
        }
    ],
    "sg:phone":"+1 608 783 4438",
    "sg:postcode":"54650",
    "sg:province":"WI",
    "sg:tags":[
        "decor",
        "gift"
    ],
    "wof:name":"Treehouse Gift & Home",
    "wof:placetype":"venue"
},
  "geometry": {"coordinates":[-91.17164,43.883647],"type":"Point"}
}