{
  "type": "Feature",
  "properties": {
    "addr:full":"269 W Hoxie St Spring Green WI 53588",
    "addr:housenumber":"269",
    "addr:postcode":"53588",
    "addr:street":"W Hoxie St",
    "iso:country":"US",
    "sg:address":"269 W Hoxie St",
    "sg:city":"Spring Green",
    "sg:classifiers":[
        {
            "category":"Building & Trades",
            "subcategory":"Plumbing",
            "type":"Services"
        }
    ],
    "sg:phone":"+1 608 588 7183",
    "sg:postcode":"53588",
    "sg:province":"WI",
    "sg:tags":[
        "contractor"
    ],
    "wof:name":"Hottmann Plumbing",
    "wof:placetype":"venue"
},
  "geometry": {"coordinates":[-90.071067,43.172385],"type":"Point"}
}