{
  "type": "Feature",
  "properties": {
    "iso:country":"US",
    "sg:address":"2862 Kennedy Rd",
    "sg:city":"Hazel Green",
    "sg:classifiers":[
        {
            "category":"Building & Trades",
            "subcategory":"Construction",
            "type":"Services"
        }
    ],
    "sg:phone":"+1 608 854 2350",
    "sg:postcode":"53811",
    "sg:province":"WI",
    "sg:tags":[
        "general",
        "contractor"
    ],
    "wof:name":"Gateway Development Constr",
    "wof:placetype":"venue"
},
  "geometry": {"coordinates":[-90.407721,42.528858],"type":"Point"}
}