{
  "type": "Feature",
  "properties": {
    "addr:full":"588 Outpost Cir Hudson WI 54016",
    "addr:housenumber":"588",
    "addr:postcode":"54016",
    "addr:street":"Outpost Cir",
    "iso:country":"US",
    "sg:address":"588 Outpost Cir",
    "sg:city":"Hudson",
    "sg:classifiers":[
        {
            "category":"Wholesale",
            "subcategory":"Hardware",
            "type":"Manufacturing & Wholesale Goods"
        },
        {
            "category":"Home & Garden",
            "subcategory":"Garden Supply",
            "type":"Retail Goods"
        },
        {
            "category":"Retail",
            "subcategory":"Repair Shop",
            "type":"Services"
        }
    ],
    "sg:phone":"+1 715 386 2354",
    "sg:postcode":"54016",
    "sg:province":"WI",
    "sg:tags":[
        "renting",
        "lawn",
        "outdoor",
        "power",
        "landscaping",
        "equipment-sales",
        "equipment",
        "saw"
    ],
    "sg:website":"http://www.stihldealer.net/default-dealer-043710.aspx",
    "wof:name":"ALL SEASONS RENTAL EQUIPMENT, LLC.",
    "wof:placetype":"venue"
},
  "geometry": {"coordinates":[-92.68040000000001,44.961114],"type":"Point"}
}