{
  "type": "Feature",
  "properties": {
    "iso:country":"US",
    "sg:address":"9196 Co Rd V",
    "sg:city":"New Auburn",
    "sg:classifiers":[
        {
            "category":"Building & Trades",
            "subcategory":"Construction",
            "type":"Services"
        }
    ],
    "sg:phone":"+1 715 658 1050",
    "sg:postcode":"54757",
    "sg:province":"WI",
    "sg:tags":[
        "contractor"
    ],
    "wof:name":"Djs Remodeling",
    "wof:placetype":"venue"
},
  "geometry": {"coordinates":[-91.687943,45.167415],"type":"Point"}
}