{
  "type": "Feature",
  "properties": {
    "iso:country":"US",
    "sg:address":"13471 Singer Rd",
    "sg:city":"Weyerhaeuser",
    "sg:classifiers":[
        {
            "category":"Farming",
            "subcategory":"Dairy Farm",
            "type":"Manufacturing & Wholesale Goods"
        }
    ],
    "sg:phone":"+1 715 868 1983",
    "sg:postcode":"54895",
    "sg:province":"WI",
    "wof:name":"Pine Row Dairy Farm",
    "wof:placetype":"venue"
},
  "geometry": {"coordinates":[-91.37529499999999,45.479134],"type":"Point"}
}