{
  "type": "Feature",
  "properties": {
    "addr:full":"1227 Corporate Center Dr Oconomowoc WI 53066",
    "addr:housenumber":"1227",
    "addr:postcode":"53066",
    "addr:street":"Corporate Center Dr",
    "iso:country":"US",
    "sg:address":"1227 Corporate Center Dr",
    "sg:city":"Oconomowoc",
    "sg:classifiers":[
        {
            "category":"Banks & Credit Unions",
            "subcategory":"Bank",
            "type":"Services"
        }
    ],
    "sg:phone":"+1 262 567 2800",
    "sg:postcode":"53066",
    "sg:province":"WI",
    "sg:tags":[
        "state",
        "commercial"
    ],
    "wof:name":"Waukesha State Bank",
    "wof:placetype":"venue"
},
  "geometry": {"coordinates":[-88.472489,43.074016],"type":"Point"}
}