{
  "type": "Feature",
  "properties": {
    "iso:country":"US",
    "sg:address":"8083 185th Ave",
    "sg:city":"Hager City",
    "sg:classifiers":[
        {
            "category":"Farming",
            "subcategory":"Farm",
            "type":"Manufacturing & Wholesale Goods"
        }
    ],
    "sg:phone":"+1 715 792 5344",
    "sg:postcode":"54014",
    "sg:province":"WI",
    "sg:tags":[
        "crop",
        "general"
    ],
    "wof:name":"Hague Del",
    "wof:placetype":"venue"
},
  "geometry": {"coordinates":[-92.53332,44.606289],"type":"Point"}
}