{
  "type": "Feature",
  "properties": {
    "iso:country":"US",
    "sg:address":"103 Mound View Cir",
    "sg:city":"Belmont",
    "sg:classifiers":[
        {
            "category":"Bars & Pubs",
            "type":"Food & Drink"
        }
    ],
    "sg:phone":"+1 608 762 6902",
    "sg:postcode":"53572",
    "sg:province":"WI",
    "wof:name":"Crazy Cow Saloon",
    "wof:placetype":"venue"
},
  "geometry": {"coordinates":[-89.749424,43.008774],"type":"Point"}
}