{
  "type": "Feature",
  "properties": {
    "iso:country":"US",
    "sg:address":"2134 Rose St",
    "sg:city":"La Crosse",
    "sg:classifiers":[
        {
            "category":"Retail",
            "subcategory":"Auto Rental",
            "type":"Services"
        }
    ],
    "sg:phone":"+1 608 781 3131",
    "sg:postcode":"54603",
    "sg:province":"WI",
    "sg:tags":[
        "truck",
        "trailer",
        "utility"
    ],
    "wof:name":"U-Haul",
    "wof:placetype":"venue"
},
  "geometry": {"coordinates":[-91.24596200000001,43.855018],"type":"Point"}
}