{
  "type": "Feature",
  "properties": {
    "iso:country":"US",
    "sg:address":"1225 Hockridge St",
    "sg:city":"Marinette",
    "sg:classifiers":[
        {
            "category":"Education",
            "subcategory":"School",
            "type":"Public Place"
        }
    ],
    "sg:phone":"+1 715 732 7913",
    "sg:postcode":"54143",
    "sg:province":"WI",
    "wof:name":"Marinette Elementary School",
    "wof:placetype":"venue"
},
  "geometry": {"coordinates":[-87.648236,45.095372],"type":"Point"}
}