{
  "type": "Feature",
  "properties": {
    "addr:full":"138 N Iowa St Dodgeville WI 53533",
    "addr:housenumber":"138",
    "addr:postcode":"53533",
    "addr:street":"N Iowa St",
    "iso:country":"US",
    "sg:address":"138 N Iowa St",
    "sg:city":"Dodgeville",
    "sg:classifiers":[
        {
            "category":"Restaurant",
            "type":"Food & Drink"
        }
    ],
    "sg:phone":"+1 608 930 2233",
    "sg:postcode":"53533",
    "sg:province":"WI",
    "wof:name":"Grace Cafe",
    "wof:placetype":"venue"
},
  "geometry": {"coordinates":[-90.130465,42.960548],"type":"Point"}
}