{
  "type": "Feature",
  "properties": {
    "iso:country":"US",
    "sg:address":"2150 Maple Dr",
    "sg:city":"Plover",
    "sg:classifiers":[
        {
            "category":"Retail",
            "subcategory":"Self-service Laundry",
            "type":"Services"
        }
    ],
    "sg:phone":"+1 715 343 1769",
    "sg:postcode":"54467",
    "sg:province":"WI",
    "sg:tags":[
        "coin",
        "power"
    ],
    "wof:name":"Hangers",
    "wof:placetype":"venue"
},
  "geometry": {"coordinates":[-89.531707,44.450246],"type":"Point"}
}