{
  "type": "Feature",
  "properties": {
    "addr:full":"9656 School Rd Brussels WI 54204",
    "addr:housenumber":"9656",
    "addr:postcode":"54204",
    "addr:street":"School Rd",
    "iso:country":"US",
    "sg:address":"9656 School Rd",
    "sg:city":"Brussels",
    "sg:classifiers":[
        {
            "category":"Government",
            "subcategory":"Fire Station",
            "type":"Public Place"
        }
    ],
    "sg:phone":"+1 920 825 1339",
    "sg:postcode":"54204",
    "sg:province":"WI",
    "sg:tags":[
        "protection"
    ],
    "wof:name":"Brussels Union Gdnr Fire Dept",
    "wof:placetype":"venue"
},
  "geometry": {"coordinates":[-87.60615799999999,44.73415],"type":"Point"}
}