{
  "type": "Feature",
  "properties": {
    "addr:full":"15534 Arneman Dr South Beloit WI 61080",
    "addr:housenumber":"15534",
    "addr:postcode":"61080",
    "addr:street":"Arneman Dr",
    "iso:country":"US",
    "sg:address":"15534 Arneman Dr",
    "sg:city":"South Beloit",
    "sg:classifiers":[
        {
            "category":"Insurance",
            "subcategory":"Insurance Agent",
            "type":"Services"
        }
    ],
    "sg:phone":"+1 815 389 1359",
    "sg:postcode":"61080",
    "sg:province":"WI",
    "wof:name":"National Aviation Underwriters",
    "wof:placetype":"venue"
},
  "geometry": {"coordinates":[-89.018519,42.487734],"type":"Point"}
}