{
  "type": "Feature",
  "properties": {
    "addr:full":"901 N Center Ave Merrill WI 54452",
    "addr:housenumber":"901",
    "addr:postcode":"54452",
    "addr:street":"N Center Ave",
    "iso:country":"US",
    "sg:address":"901 N Center Ave",
    "sg:city":"Merrill",
    "sg:classifiers":[
        {
            "category":"Restaurant",
            "type":"Food & Drink"
        }
    ],
    "sg:menulink":"http://www.allmenus.com/wi/merrill/79990-pizza-hut/menu/",
    "sg:phone":"+1 715 536 2433",
    "sg:postcode":"54452",
    "sg:province":"WI",
    "sg:tags":[
        "american",
        "pizza"
    ],
    "wof:name":"Pizza Hut",
    "wof:placetype":"venue"
},
  "geometry": {"coordinates":[-89.682897,45.187692],"type":"Point"}
}