{
  "type": "Feature",
  "properties": {
    "addr:full":"5605 190th Ave Menomonie WI 54751",
    "addr:housenumber":"5605",
    "addr:postcode":"54751",
    "addr:street":"190Th Ave",
    "iso:country":"US",
    "sg:address":"5605 190th Ave",
    "sg:city":"Menomonie",
    "sg:phone":"+1 715 664 8303",
    "sg:postcode":"54751",
    "sg:province":"WI",
    "sg:tags":[
        "farm",
        "dairy",
        "corn",
        "grain",
        "cash"
    ],
    "wof:name":"Pleasant Valley Farm",
    "wof:placetype":"venue"
},
  "geometry": {"coordinates":[-91.878782,44.748861],"type":"Point"}
}