{
  "type": "Feature",
  "properties": {
    "iso:country":"US",
    "sg:address":"8532 W Capitol Dr",
    "sg:city":"Milwaukee",
    "sg:classifiers":[
        {
            "category":"Insurance",
            "subcategory":"Insurance Agent",
            "type":"Services"
        }
    ],
    "sg:phone":"+1 414 438 6540",
    "sg:postcode":"53222",
    "sg:province":"WI",
    "wof:name":"One Accord Financial",
    "wof:placetype":"venue"
},
  "geometry": {"coordinates":[-88.01978800000001,43.089876],"type":"Point"}
}