{
  "type": "Feature",
  "properties": {
    "iso:country":"US",
    "sg:address":"1709 Clark St",
    "sg:city":"Stevens Point",
    "sg:classifiers":[
        {
            "category":"Professional",
            "subcategory":"Accounting & Tax Preparation",
            "type":"Services"
        }
    ],
    "sg:phone":"+1 715 344 0637",
    "sg:postcode":"54481",
    "sg:province":"WI",
    "wof:name":"Business Consultants",
    "wof:placetype":"venue"
},
  "geometry": {"coordinates":[-89.574642,44.522313],"type":"Point"}
}