{
  "type": "Feature",
  "properties": {
    "iso:country":"US",
    "sg:address":"501 Lake Ave",
    "sg:city":"Florence",
    "sg:classifiers":[
        {
            "category":"Government",
            "subcategory":"Office",
            "type":"Public Place"
        }
    ],
    "sg:phone":"+1 715 528 4251",
    "sg:postcode":"54121",
    "sg:province":"WI",
    "wof:name":"Florence County JOB Ctr",
    "wof:placetype":"venue"
},
  "geometry": {"coordinates":[-88.24982199999999,45.921459],"type":"Point"}
}