{
  "type": "Feature",
  "properties": {
    "iso:country":"US",
    "sg:address":"126 S Chestnut St",
    "sg:city":"Ellsworth",
    "sg:classifiers":[
        {
            "category":"Manufacturing",
            "subcategory":"Printing",
            "type":"Manufacturing & Wholesale Goods"
        }
    ],
    "sg:phone":"+1 715 273 4334",
    "sg:postcode":"54011",
    "sg:province":"WI",
    "sg:tags":[
        "newspaper",
        "lithographic",
        "commercial"
    ],
    "wof:name":"Divison Rver Town Nwsppr Group",
    "wof:placetype":"venue"
},
  "geometry": {"coordinates":[-92.48304899999999,44.731173],"type":"Point"}
}