{
  "type": "Feature",
  "properties": {
    "iso:country":"US",
    "sg:address":"2833 Milton Ave",
    "sg:city":"Janesville",
    "sg:classifiers":[
        {
            "category":"Retail",
            "subcategory":"Auto Rental",
            "type":"Services"
        }
    ],
    "sg:phone":"+1 608 758 7100",
    "sg:postcode":"53545",
    "sg:province":"WI",
    "sg:tags":[
        "renting",
        "automobile",
        "leasing"
    ],
    "wof:name":"Enterprise Rent-A-Car",
    "wof:placetype":"venue"
},
  "geometry": {"coordinates":[-89.00032400000001,42.714405],"type":"Point"}
}