{
  "type": "Feature",
  "properties": {
    "iso:country":"US",
    "sg:address":"1200 River Rd",
    "sg:city":"Sparta",
    "sg:classifiers":[
        {
            "category":"Real Estate",
            "subcategory":"Real Estate Operator",
            "type":"Services"
        }
    ],
    "sg:phone":"+1 608 269 1957",
    "sg:postcode":"54656",
    "sg:province":"WI",
    "sg:tags":[
        "mobile",
        "home",
        "community"
    ],
    "wof:name":"River Pines Mobile Home Park",
    "wof:placetype":"venue"
},
  "geometry": {"coordinates":[-90.834009,43.932586],"type":"Point"}
}