{
  "type": "Feature",
  "properties": {
    "addr:full":"120 Fritz Ave E Ladysmith WI 54848",
    "addr:housenumber":"120",
    "addr:postcode":"54848",
    "addr:street":"Fritz Ave E",
    "iso:country":"US",
    "sg:address":"120 Fritz Ave E",
    "sg:city":"Ladysmith",
    "sg:classifiers":[
        {
            "category":"Retail",
            "subcategory":"Funeral Services",
            "type":"Services"
        }
    ],
    "sg:phone":"+1 715 532 4881",
    "sg:postcode":"54848",
    "sg:province":"WI",
    "sg:tags":[
        "director"
    ],
    "wof:name":"Nash-Jackan Funeral Homes Inc",
    "wof:placetype":"venue"
},
  "geometry": {"coordinates":[-91.100516,45.462248],"type":"Point"}
}