{
  "type": "Feature",
  "properties": {
    "iso:country":"US",
    "sg:address":"6210 W Douglas Ave",
    "sg:city":"Milwaukee",
    "sg:classifiers":[
        {
            "category":"Wholesale",
            "subcategory":"Non-durable Goods",
            "type":"Manufacturing & Wholesale Goods"
        }
    ],
    "sg:phone":"+1 414 462 9220",
    "sg:postcode":"53218",
    "sg:province":"WI",
    "sg:tags":[
        "sponge",
        "rubber",
        "foam"
    ],
    "wof:name":"Active Foam Products",
    "wof:placetype":"venue"
},
  "geometry": {"coordinates":[-87.98918,43.129477],"type":"Point"}
}