{
  "type": "Feature",
  "properties": {
    "iso:country":"US",
    "sg:address":"1317 31st Ave",
    "sg:city":"Monroe",
    "sg:classifiers":[
        {
            "category":"Organizations",
            "subcategory":"Professional Association",
            "type":"Services"
        }
    ],
    "sg:phone":"+1 608 325 9987",
    "sg:postcode":"53566",
    "sg:province":"WI",
    "wof:name":"Alpine Curling Club",
    "wof:placetype":"venue"
},
  "geometry": {"coordinates":[-89.622085,42.598826],"type":"Point"}
}