{
  "type": "Feature",
  "properties": {
    "addr:full":"6202 Paske Ct Middleton WI 53562",
    "addr:housenumber":"6202",
    "addr:postcode":"53562",
    "addr:street":"Paske Ct",
    "iso:country":"US",
    "sg:address":"6202 Paske Ct",
    "sg:city":"Middleton",
    "sg:classifiers":[
        {
            "category":"Building & Trades",
            "subcategory":"Construction",
            "type":"Services"
        }
    ],
    "sg:phone":"+1 608 831 0047",
    "sg:postcode":"53562",
    "sg:province":"WI",
    "sg:tags":[
        "concrete",
        "contractor"
    ],
    "wof:name":"Chris Foss Contractors Inc",
    "wof:placetype":"venue"
},
  "geometry": {"coordinates":[-89.490548,43.091283],"type":"Point"}
}