{
  "type": "Feature",
  "properties": {
    "addr:full":"464 3rd Ave Clear Lake WI 54005",
    "addr:housenumber":"464",
    "addr:postcode":"54005",
    "addr:street":"3Rd Ave",
    "iso:country":"US",
    "sg:address":"464 3rd Ave",
    "sg:city":"Clear Lake",
    "sg:classifiers":[
        {
            "category":"Home & Garden",
            "subcategory":"Home Furnishings",
            "type":"Retail Goods"
        }
    ],
    "sg:phone":"+1 715 263 2384",
    "sg:postcode":"54005",
    "sg:province":"WI",
    "sg:tags":[
        "quilting"
    ],
    "wof:name":"Sew Country",
    "wof:placetype":"venue"
},
  "geometry": {"coordinates":[-92.27077300000001,45.251482],"type":"Point"}
}