{
  "type": "Feature",
  "properties": {
    "iso:country":"US",
    "sg:address":"13073 State Hwy 32 64",
    "sg:city":"Mountain",
    "sg:classifiers":[
        {
            "category":"Bars & Pubs",
            "type":"Food & Drink"
        }
    ],
    "sg:phone":"+1 715 276 7477",
    "sg:postcode":"54149",
    "sg:province":"WI",
    "sg:tags":[
        "drinking"
    ],
    "wof:name":"Uncle Tom's Barr & Grill",
    "wof:placetype":"venue"
},
  "geometry": {"coordinates":[-88.45107,45.156258],"type":"Point"}
}