{
  "type": "Feature",
  "properties": {
    "addr:full":"7600 Terrace Ave Middleton WI 53562",
    "addr:housenumber":"7600",
    "addr:postcode":"53562",
    "addr:street":"Terrace Ave",
    "iso:country":"US",
    "sg:address":"7600 Terrace Ave",
    "sg:city":"Middleton",
    "sg:classifiers":[
        {
            "category":"Health Services",
            "subcategory":"Chiropractor",
            "type":"Services"
        }
    ],
    "sg:phone":"+1 608 836 8883",
    "sg:postcode":"53562",
    "sg:province":"WI",
    "wof:name":"Fenske Chiropractic",
    "wof:placetype":"venue"
},
  "geometry": {"coordinates":[-89.51602099999999,43.094536],"type":"Point"}
}