{
  "type": "Feature",
  "properties": {
    "addr:full":"5199 Popp Rd Jefferson WI 53549",
    "addr:housenumber":"5199",
    "addr:postcode":"53549",
    "addr:street":"Popp Rd",
    "iso:country":"US",
    "sg:address":"5199 Popp Rd",
    "sg:city":"Jefferson",
    "sg:classifiers":[
        {
            "category":"Building & Trades",
            "subcategory":"Landscaping Services",
            "type":"Services"
        }
    ],
    "sg:phone":"+1 920 674 6296",
    "sg:postcode":"53549",
    "sg:province":"WI",
    "wof:name":"Brauns Garden",
    "wof:placetype":"venue"
},
  "geometry": {"coordinates":[-88.83697100000001,43.03115],"type":"Point"}
}