{
  "type": "Feature",
  "properties": {
    "iso:country":"US",
    "sg:address":"7771 State Hwy 33",
    "sg:city":"Beaver Dam",
    "sg:classifiers":[
        {
            "category":"Bars & Pubs",
            "type":"Food & Drink"
        }
    ],
    "sg:phone":"+1 920 885 4836",
    "sg:postcode":"53916",
    "sg:province":"WI",
    "wof:name":"Scoots",
    "wof:placetype":"venue"
},
  "geometry": {"coordinates":[-88.800566,43.451384],"type":"Point"}
}