{
  "type": "Feature",
  "properties": {
    "iso:country":"US",
    "sg:address":"4720 Pine Ridge Trl",
    "sg:city":"Abrams",
    "sg:classifiers":[
        {
            "category":"Building & Trades",
            "subcategory":"Plumbing",
            "type":"Services"
        }
    ],
    "sg:phone":"+1 920 826 4546",
    "sg:postcode":"54101",
    "sg:province":"WI",
    "sg:tags":[
        "plumbing",
        "contractor"
    ],
    "wof:name":"Triton Plumbing Abrams",
    "wof:placetype":"venue"
},
  "geometry": {"coordinates":[-88.055134,44.841498],"type":"Point"}
}