{
  "type": "Feature",
  "properties": {
    "addr:full":"2003 Merrill Ave Wausau WI 54401",
    "addr:housenumber":"2003",
    "addr:postcode":"54401",
    "addr:street":"Merrill Ave",
    "iso:country":"US",
    "sg:address":"2003 Merrill Ave",
    "sg:city":"Wausau",
    "sg:classifiers":[
        {
            "category":"Retail",
            "subcategory":"Repair Shop",
            "type":"Services"
        }
    ],
    "sg:phone":"+1 715 675 4959",
    "sg:postcode":"54401",
    "sg:province":"WI",
    "sg:tags":[
        "repairing",
        "saw"
    ],
    "wof:name":"Tomahawk Service Company",
    "wof:placetype":"venue"
},
  "geometry": {"coordinates":[-89.661503,44.990216],"type":"Point"}
}