{
  "type": "Feature",
  "properties": {
    "addr:full":"5224 W Center St Milwaukee WI 53210",
    "addr:housenumber":"5224",
    "addr:postcode":"53210",
    "addr:street":"W Center St",
    "iso:country":"US",
    "sg:address":"5224 W Center St",
    "sg:city":"Milwaukee",
    "sg:classifiers":[
        {
            "category":"Shopping",
            "subcategory":"Used Merchandise",
            "type":"Retail Goods"
        }
    ],
    "sg:phone":"+1 414 447 0933",
    "sg:postcode":"53210",
    "sg:province":"WI",
    "sg:tags":[
        "shop",
        "consignment"
    ],
    "wof:name":"Mary's Resale Shop",
    "wof:placetype":"venue"
},
  "geometry": {"coordinates":[-87.97957100000001,43.068058],"type":"Point"}
}