{
  "type": "Feature",
  "properties": {
    "iso:country":"US",
    "sg:address":"211 W 8th St",
    "sg:city":"Neillsville",
    "sg:classifiers":[
        {
            "category":"Real Estate",
            "subcategory":"Real Estate Agent",
            "type":"Services"
        }
    ],
    "sg:phone":"+1 715 743 6202",
    "sg:postcode":"54456",
    "sg:province":"WI",
    "sg:tags":[
        "agency",
        "rental"
    ],
    "wof:name":"Russell's-Neillsville Rental",
    "wof:placetype":"venue"
},
  "geometry": {"coordinates":[-90.598236,44.56217],"type":"Point"}
}