{
  "type": "Feature",
  "properties": {
    "addr:full":"6949 W Hollow Ln Franklin WI 53132",
    "addr:housenumber":"6949",
    "addr:postcode":"53132",
    "addr:street":"W Hollow Ln",
    "iso:country":"US",
    "sg:address":"6949 W Hollow Ln",
    "sg:city":"Franklin",
    "sg:classifiers":[
        {
            "category":"Professional",
            "subcategory":"Computer Services",
            "type":"Services"
        }
    ],
    "sg:phone":"+1 414 765 3723",
    "sg:postcode":"53132",
    "sg:province":"WI",
    "sg:tags":[
        "related"
    ],
    "wof:name":"Novell Consulting",
    "wof:placetype":"venue"
},
  "geometry": {"coordinates":[-88.00133599999999,42.907315],"type":"Point"}
}