{
  "type": "Feature",
  "properties": {
    "iso:country":"US",
    "sg:address":"212 N 31st St",
    "sg:city":"Milwaukee",
    "sg:classifiers":[
        {
            "category":"Retail",
            "subcategory":"Repair Shop",
            "type":"Services"
        }
    ],
    "sg:phone":"+1 414 933 5242",
    "sg:postcode":"53208",
    "sg:province":"WI",
    "sg:tags":[
        "television",
        "radio"
    ],
    "wof:name":"Phil's Television & Radio Svc",
    "wof:placetype":"venue"
},
  "geometry": {"coordinates":[-87.95273299999999,43.033544],"type":"Point"}
}