{
  "type": "Feature",
  "properties": {
    "iso:country":"US",
    "sg:address":"50 Rockwell Ave",
    "sg:city":"Fort Atkinson",
    "sg:classifiers":[
        {
            "category":"Manufacturing",
            "subcategory":"Rubber & Plastics",
            "type":"Manufacturing & Wholesale Goods"
        }
    ],
    "sg:phone":"+1 920 563 6011",
    "sg:postcode":"53538",
    "sg:province":"WI",
    "sg:tags":[
        "product"
    ],
    "wof:name":"Arrowhead Manufacturing",
    "wof:placetype":"venue"
},
  "geometry": {"coordinates":[-88.833652,42.916806],"type":"Point"}
}