{
  "type": "Feature",
  "properties": {
    "iso:country":"US",
    "sg:address":"1227 120th St",
    "sg:city":"Amery",
    "sg:classifiers":[
        {
            "category":"Farming",
            "subcategory":"Dairy Farm",
            "type":"Manufacturing & Wholesale Goods"
        }
    ],
    "sg:phone":"+1 715 268 6246",
    "sg:postcode":"54001",
    "sg:province":"WI",
    "wof:name":"Berglund Scott or Kathlee",
    "wof:placetype":"venue"
},
  "geometry": {"coordinates":[-92.407898,45.38233],"type":"Point"}
}