{
  "type": "Feature",
  "properties": {
    "iso:country":"US",
    "sg:address":"324 E Wisconsin Ave",
    "sg:city":"Milwaukee",
    "sg:classifiers":[
        {
            "category":"Professional",
            "subcategory":"Lawyer & Legal Services",
            "type":"Services"
        }
    ],
    "sg:phone":"+1 414 831 0427",
    "sg:postcode":"53202",
    "sg:province":"WI",
    "sg:tags":[
        "attorney"
    ],
    "wof:name":"Dantzman & Dantzman Law Ofc",
    "wof:placetype":"venue"
},
  "geometry": {"coordinates":[-87.906836,43.038785],"type":"Point"}
}