{
  "type": "Feature",
  "properties": {
    "iso:country":"US",
    "sg:address":"9780 Mallard Ct",
    "sg:city":"Beaver Dam",
    "sg:classifiers":[
        {
            "category":"Building & Trades",
            "subcategory":"Construction",
            "type":"Services"
        }
    ],
    "sg:phone":"+1 920 356 9237",
    "sg:postcode":"53916",
    "sg:province":"WI",
    "sg:tags":[
        "dry wall",
        "contractor"
    ],
    "wof:name":"Pasewald Drywall",
    "wof:placetype":"venue"
},
  "geometry": {"coordinates":[-88.889606,43.507811],"type":"Point"}
}