{
  "type": "Feature",
  "properties": {
    "iso:country":"US",
    "sg:address":"4781 Hayes Rd",
    "sg:city":"Madison",
    "sg:classifiers":[
        {
            "category":"Insurance",
            "subcategory":"Insurance Agent",
            "type":"Services"
        }
    ],
    "sg:phone":"+1 608 244 7336",
    "sg:postcode":"53704",
    "sg:province":"WI",
    "wof:name":"Horace Mann Insurance Co",
    "wof:placetype":"venue"
},
  "geometry": {"coordinates":[-89.29952299999999,43.139034],"type":"Point"}
}