{
  "type": "Feature",
  "properties": {
    "addr:full":"711 Eisenhower Dr Kimberly WI 54136",
    "addr:housenumber":"711",
    "addr:postcode":"54136",
    "addr:street":"Eisenhower Dr",
    "iso:country":"US",
    "sg:address":"711 Eisenhower Dr",
    "sg:city":"Kimberly",
    "sg:classifiers":[
        {
            "category":"Insurance",
            "subcategory":"Insurance Agent",
            "type":"Services"
        }
    ],
    "sg:phone":"+1 920 731 0400",
    "sg:postcode":"54136",
    "sg:province":"WI",
    "sg:website":"www.jabasgroup.com",
    "wof:name":"Jabas Group Inc",
    "wof:placetype":"venue"
},
  "geometry": {"coordinates":[-88.346812,44.259668],"type":"Point"}
}