{
  "type": "Feature",
  "properties": {
    "iso:country":"US",
    "sg:address":"121 W Main St",
    "sg:city":"Port Washington",
    "sg:classifiers":[
        {
            "category":"Government",
            "subcategory":"Office",
            "type":"Public Place"
        }
    ],
    "sg:phone":"+1 262 284 8129",
    "sg:postcode":"53074",
    "sg:province":"WI",
    "sg:website":"www.co.ozaukee.wi.us",
    "wof:name":"Ozaukee County Dev Disability",
    "wof:placetype":"venue"
},
  "geometry": {"coordinates":[-87.872211,43.388423],"type":"Point"}
}