{
  "type": "Feature",
  "properties": {
    "iso:country":"US",
    "sg:address":"6929 Pilgrim Rd",
    "sg:city":"Madison",
    "sg:classifiers":[
        {
            "category":"Professional",
            "subcategory":"Lawyer & Legal Services",
            "type":"Services"
        }
    ],
    "sg:phone":"+1 608 276 6893",
    "sg:postcode":"53711",
    "sg:province":"WI",
    "sg:tags":[
        "attorney"
    ],
    "wof:name":"Winstrom Law Office LLC",
    "wof:placetype":"venue"
},
  "geometry": {"coordinates":[-89.502464,43.028212],"type":"Point"}
}