{
  "type": "Feature",
  "properties": {
    "addr:full":"4183 Shawano Ave Green Bay WI 54313",
    "addr:housenumber":"4183",
    "addr:postcode":"54313",
    "addr:street":"Shawano Ave",
    "iso:country":"US",
    "sg:address":"4183 Shawano Ave",
    "sg:city":"Green Bay",
    "sg:classifiers":[
        {
            "category":"Freight",
            "type":"Transportation"
        }
    ],
    "sg:phone":"+1 920 865 6015",
    "sg:postcode":"54313",
    "sg:province":"WI",
    "sg:tags":[
        "general"
    ],
    "wof:name":"All Size Self Storage",
    "wof:placetype":"venue"
},
  "geometry": {"coordinates":[-88.14399,44.576889],"type":"Point"}
}