{
  "type": "Feature",
  "properties": {
    "iso:country":"US",
    "sg:address":"1017 W Lincoln Ave",
    "sg:city":"Milwaukee",
    "sg:classifiers":[
        {
            "category":"Recreation",
            "subcategory":"Arcade",
            "type":"Entertainment"
        }
    ],
    "sg:phone":"+1 414 643 6174",
    "sg:postcode":"53215",
    "sg:province":"WI",
    "sg:tags":[
        "device",
        "operator",
        "amusement"
    ],
    "wof:name":"Lincoln Novelty Limited",
    "wof:placetype":"venue"
},
  "geometry": {"coordinates":[-87.92498399999999,43.002767],"type":"Point"}
}