{
  "type": "Feature",
  "properties": {
    "addr:full":"5440 Willow Rd Waunakee WI 53597",
    "addr:housenumber":"5440",
    "addr:postcode":"53597",
    "addr:street":"Willow Rd",
    "iso:country":"US",
    "sg:address":"5440 Willow Rd",
    "sg:city":"Waunakee",
    "sg:classifiers":[
        {
            "category":"Manufacturing",
            "subcategory":"Metals",
            "type":"Manufacturing & Wholesale Goods"
        }
    ],
    "sg:phone":"+1 608 442 3045",
    "sg:postcode":"53597",
    "sg:province":"WI",
    "sg:tags":[
        "fabrication",
        "structural"
    ],
    "wof:name":"Suncor North Inc",
    "wof:placetype":"venue"
},
  "geometry": {"coordinates":[-89.41373,43.15154],"type":"Point"}
}