{
  "type": "Feature",
  "properties": {
    "iso:country":"US",
    "sg:address":"1360 9th Ave",
    "sg:city":"Baldwin",
    "sg:classifiers":[
        {
            "category":"Farming",
            "subcategory":"Dairy Farm",
            "type":"Manufacturing & Wholesale Goods"
        }
    ],
    "sg:phone":"+1 715 684 2041",
    "sg:postcode":"54002",
    "sg:province":"WI",
    "wof:name":"Woodside Dairy Part",
    "wof:placetype":"venue"
},
  "geometry": {"coordinates":[-92.373869,44.963505],"type":"Point"}
}