{
  "type": "Feature",
  "properties": {
    "iso:country":"US",
    "sg:address":"12120 N Maryhill Ct 42W",
    "sg:city":"Mequon",
    "sg:classifiers":[
        {
            "category":"Professional",
            "type":"Services"
        }
    ],
    "sg:phone":"+1 262 236 0110",
    "sg:postcode":"53092",
    "sg:province":"WI",
    "sg:tags":[
        "literary",
        "writer",
        "agent"
    ],
    "sg:website":"http://www.orfieldcommunications.com",
    "wof:name":"Orfield Communication",
    "wof:placetype":"venue"
},
  "geometry": {"coordinates":[-87.96259000000001,43.237637],"type":"Point"}
}