{
  "type": "Feature",
  "properties": {
    "iso:country":"US",
    "sg:address":"4717 Deep Lake Rd",
    "sg:city":"Sarona",
    "sg:classifiers":[
        {
            "category":"Personal",
            "subcategory":"Beauty Salon",
            "type":"Services"
        }
    ],
    "sg:phone":"+1 715 469 3267",
    "sg:postcode":"54870",
    "sg:province":"WI",
    "sg:tags":[
        "shop"
    ],
    "wof:name":"Donna's Hair Design",
    "wof:placetype":"venue"
},
  "geometry": {"coordinates":[-91.782285,45.767456],"type":"Point"}
}