{
  "type": "Feature",
  "properties": {
    "iso:country":"US",
    "sg:address":"1335 Creston Park Dr",
    "sg:city":"Janesville",
    "sg:classifiers":[
        {
            "category":"Real Estate",
            "subcategory":"Real Estate Operator",
            "type":"Services"
        }
    ],
    "sg:phone":"+1 608 752 0332",
    "sg:postcode":"53545",
    "sg:province":"WI",
    "sg:tags":[
        "building",
        "nonresidential"
    ],
    "wof:name":"Odana Management",
    "wof:placetype":"venue"
},
  "geometry": {"coordinates":[-89.005956,42.701729],"type":"Point"}
}