{
  "type": "Feature",
  "properties": {
    "iso:country":"US",
    "sg:address":"5029 Nelson Ln",
    "sg:city":"Sturgeon Bay",
    "sg:classifiers":[
        {
            "category":"Building & Trades",
            "subcategory":"Landscaping Services",
            "type":"Services"
        }
    ],
    "sg:phone":"+1 920 743 4872",
    "sg:postcode":"54235",
    "sg:province":"WI",
    "wof:name":"Birnscheins Yard Service",
    "wof:placetype":"venue"
},
  "geometry": {"coordinates":[-87.22869,44.912877],"type":"Point"}
}