{
  "type": "Feature",
  "properties": {
    "iso:country":"US",
    "sg:address":"4359 463rd Ave",
    "sg:city":"Menomonie",
    "sg:classifiers":[
        {
            "category":"Building & Trades",
            "subcategory":"Construction",
            "type":"Services"
        }
    ],
    "sg:phone":"+1 715 235 1223",
    "sg:postcode":"54751",
    "sg:province":"WI",
    "sg:tags":[
        "residential",
        "general",
        "family",
        "contractor"
    ],
    "wof:name":"Red Cedar Construction Inc",
    "wof:placetype":"venue"
},
  "geometry": {"coordinates":[-91.941597,44.848433],"type":"Point"}
}