{
  "type": "Feature",
  "properties": {
    "iso:country":"US",
    "sg:address":"900 Silvernail Rd",
    "sg:city":"Pewaukee",
    "sg:classifiers":[
        {
            "category":"Real Estate",
            "subcategory":"Real Estate Agent",
            "type":"Services"
        }
    ],
    "sg:phone":"+1 262 542 8833",
    "sg:postcode":"53072",
    "sg:province":"WI",
    "wof:name":"Silvernail Development",
    "wof:placetype":"venue"
},
  "geometry": {"coordinates":[-88.25330200000001,43.043092],"type":"Point"}
}