{
  "type": "Feature",
  "properties": {
    "addr:full":"6320 Monona Dr Madison WI 53716",
    "addr:housenumber":"6320",
    "addr:postcode":"53716",
    "addr:street":"Monona Dr",
    "iso:country":"US",
    "sg:address":"6320 Monona Dr",
    "sg:city":"Madison",
    "sg:classifiers":[
        {
            "category":"Insurance",
            "subcategory":"Insurance Agent",
            "type":"Services"
        }
    ],
    "sg:phone":"+1 608 221 0420",
    "sg:postcode":"53716",
    "sg:province":"WI",
    "wof:name":"Parkview Title RES Assoc LLC",
    "wof:placetype":"venue"
},
  "geometry": {"coordinates":[-89.325183,43.053057],"type":"Point"}
}