{
  "type": "Feature",
  "properties": {
    "addr:full":"2604 Merganser Way Wausau WI 54401",
    "addr:housenumber":"2604",
    "addr:postcode":"54401",
    "addr:street":"Merganser Way",
    "iso:country":"US",
    "sg:address":"2604 Merganser Way",
    "sg:city":"Wausau",
    "sg:classifiers":[
        {
            "category":"Manufacturing",
            "subcategory":"Motor Vehicles & Parts",
            "type":"Manufacturing & Wholesale Goods"
        }
    ],
    "sg:phone":"+1 715 848 8800",
    "sg:postcode":"54401",
    "sg:province":"WI",
    "sg:tags":[
        "equipment",
        "transportation",
        "mfg"
    ],
    "wof:name":"Bombardier Motor Corp Of AME",
    "wof:placetype":"venue"
},
  "geometry": {"coordinates":[-89.69001,44.933622],"type":"Point"}
}