{
  "type": "Feature",
  "properties": {
    "iso:country":"US",
    "sg:address":"1035 W Canal St",
    "sg:city":"Milwaukee",
    "sg:classifiers":[
        {
            "category":"Utilities",
            "subcategory":"Electric",
            "type":"Services"
        }
    ],
    "sg:phone":"+1 414 221 3880",
    "sg:postcode":"53233",
    "sg:province":"WI",
    "sg:website":"http://www.powerthefuture.com",
    "wof:name":"Valley Power Plant",
    "wof:placetype":"venue"
},
  "geometry": {"coordinates":[-87.922774,43.031391],"type":"Point"}
}