{
  "type": "Feature",
  "properties": {
    "addr:full":"130 E Juneau Ave Milwaukee WI 53202",
    "addr:housenumber":"130",
    "addr:postcode":"53202",
    "addr:street":"E Juneau Ave",
    "iso:country":"US",
    "sg:address":"130 E Juneau Ave",
    "sg:city":"Milwaukee",
    "sg:classifiers":[
        {
            "category":"Place Of Worship",
            "subcategory":"Church",
            "type":"Public Place"
        },
        {
            "category":"Place Of Worship",
            "type":"Public Place"
        }
    ],
    "sg:phone":"+1 414 273 7617",
    "sg:postcode":"53202",
    "sg:province":"WI",
    "sg:tags":[
        "lutheran",
        "christ",
        "christ-new",
        "churches-lutheran-evangelical",
        "testament",
        "churches-church",
        "america",
        "churches-lutheran"
    ],
    "wof:name":"The Village Church",
    "wof:placetype":"venue"
},
  "geometry": {"coordinates":[-87.911992,43.045764],"type":"Point"}
}