{
  "type": "Feature",
  "properties": {
    "iso:country":"US",
    "sg:address":"12148 State Hwy 60",
    "sg:city":"Lodi",
    "sg:phone":"+1 608 592 3764",
    "sg:postcode":"53555",
    "sg:province":"WI",
    "sg:tags":[
        "farm",
        "grain",
        "cash"
    ],
    "wof:name":"Gordon Hartmann",
    "wof:placetype":"venue"
},
  "geometry": {"coordinates":[-89.59786200000001,43.301369],"type":"Point"}
}