{
  "type": "Feature",
  "properties": {
    "iso:country":"US",
    "sg:address":"202 N Main St",
    "sg:city":"Walworth",
    "sg:classifiers":[
        {
            "category":"Wholesale",
            "subcategory":"Machinery & Supplies",
            "type":"Manufacturing & Wholesale Goods"
        }
    ],
    "sg:phone":"+1 262 275 8900",
    "sg:postcode":"53184",
    "sg:province":"WI",
    "sg:tags":[
        "equipment",
        "printing",
        "industrial"
    ],
    "wof:name":"Xeric Web Drying Systems",
    "wof:placetype":"venue"
},
  "geometry": {"coordinates":[-88.59951599999999,42.532656],"type":"Point"}
}