{
  "type": "Feature",
  "properties": {
    "iso:country":"US",
    "sg:address":"126 E Main St",
    "sg:city":"Hixton",
    "sg:classifiers":[
        {
            "category":"Personal",
            "subcategory":"Beauty Salon",
            "type":"Services"
        }
    ],
    "sg:phone":"+1 715 963 2211",
    "sg:postcode":"54635",
    "sg:province":"WI",
    "wof:name":"Candy's Styling & Tanning",
    "wof:placetype":"venue"
},
  "geometry": {"coordinates":[-91.012873,44.386697],"type":"Point"}
}