{
  "type": "Feature",
  "properties": {
    "addr:full":"430 State Hwy 70 E St Germain WI 54558",
    "addr:housenumber":"430",
    "addr:postcode":"54558",
    "addr:street":"State Hwy 70 E",
    "iso:country":"US",
    "sg:address":"430 State Hwy 70 E",
    "sg:city":"St Germain",
    "sg:classifiers":[
        {
            "category":"Autos & Motor Vehicles",
            "subcategory":"Boat Sales",
            "type":"Retail Goods"
        }
    ],
    "sg:phone":"+1 715 479 4930",
    "sg:postcode":"54558",
    "sg:province":"WI",
    "sg:tags":[
        "dealer",
        "sales"
    ],
    "sg:website":"www.stgermainsportmarine.com",
    "wof:name":"St Germain Sport Marine",
    "wof:placetype":"venue"
},
  "geometry": {"coordinates":[-89.48744499999999,45.911333],"type":"Point"}
}