{
  "type": "Feature",
  "properties": {
    "iso:country":"US",
    "sg:address":"2575 S Main St",
    "sg:city":"Rice Lake",
    "sg:classifiers":[
        {
            "category":"Shopping",
            "subcategory":"Shoes",
            "type":"Retail Goods"
        }
    ],
    "sg:phone":"+1 715 234 7703",
    "sg:postcode":"54868",
    "sg:province":"WI",
    "wof:name":"Payless Shoe Source",
    "wof:placetype":"venue"
},
  "geometry": {"coordinates":[-91.73515500000001,45.474914],"type":"Point"}
}