{
  "type": "Feature",
  "properties": {
    "iso:country":"US",
    "sg:address":"314 E Quincy St",
    "sg:city":"New London",
    "sg:classifiers":[
        {
            "category":"Manufacturing",
            "subcategory":"Glass & Minerals",
            "type":"Manufacturing & Wholesale Goods"
        }
    ],
    "sg:phone":"+1 920 982 1674",
    "sg:postcode":"54961",
    "sg:province":"WI",
    "sg:tags":[
        "concrete",
        "brick",
        "prod",
        "block"
    ],
    "wof:name":"Cool Crete",
    "wof:placetype":"venue"
},
  "geometry": {"coordinates":[-88.73663999999999,44.385768],"type":"Point"}
}