{
  "type": "Feature",
  "properties": {
    "iso:country":"US",
    "sg:address":"2927 Oneida Lake Rd",
    "sg:city":"Harshaw",
    "sg:classifiers":[
        {
            "category":"Building & Trades",
            "subcategory":"Construction",
            "type":"Services"
        }
    ],
    "sg:phone":"+1 715 282 7082",
    "sg:postcode":"54529",
    "sg:province":"WI",
    "sg:tags":[
        "general",
        "contractor"
    ],
    "wof:name":"Durkee Construction",
    "wof:placetype":"venue"
},
  "geometry": {"coordinates":[-89.632491,45.601892],"type":"Point"}
}