{
  "type": "Feature",
  "properties": {
    "iso:country":"US",
    "sg:address":"106 Soo Ave E",
    "sg:city":"Almena",
    "sg:classifiers":[
        {
            "category":"Building & Trades",
            "subcategory":"Construction",
            "type":"Services"
        }
    ],
    "sg:phone":"+1 715 357 3047",
    "sg:postcode":"54805",
    "sg:province":"WI",
    "sg:tags":[
        "stone",
        "pointing"
    ],
    "wof:name":"Boedeker Restoration",
    "wof:placetype":"venue"
},
  "geometry": {"coordinates":[-92.037951,45.417901],"type":"Point"}
}