{
  "type": "Feature",
  "properties": {
    "iso:country":"US",
    "sg:address":"12446 State Hwy 81",
    "sg:city":"Beloit",
    "sg:classifiers":[
        {
            "category":"Professional",
            "subcategory":"Computer Services",
            "type":"Services"
        }
    ],
    "sg:phone":"+1 608 879 9897",
    "sg:postcode":"53511",
    "sg:province":"IL",
    "sg:tags":[
        "website",
        "design"
    ],
    "wof:name":"E-Net-Webs",
    "wof:placetype":"venue"
},
  "geometry": {"coordinates":[-89.247886,42.536958],"type":"Point"}
}