{
  "type": "Feature",
  "properties": {
    "addr:full":"4305 S 108th St Milwaukee WI 53228",
    "addr:housenumber":"4305",
    "addr:postcode":"53228",
    "addr:street":"S 108Th St",
    "iso:country":"US",
    "sg:address":"4305 S 108th St",
    "sg:city":"Milwaukee",
    "sg:classifiers":[
        {
            "category":"Retail",
            "subcategory":"Auto Rental",
            "type":"Services"
        }
    ],
    "sg:phone":"+1 414 425 0566",
    "sg:postcode":"53228",
    "sg:province":"WI",
    "sg:tags":[
        "renting",
        "truck",
        "leasing"
    ],
    "wof:name":"U-Haul Co",
    "wof:placetype":"venue"
},
  "geometry": {"coordinates":[-88.04795799999999,42.961641],"type":"Point"}
}