{
  "type": "Feature",
  "properties": {
    "addr:full":"6271 Stage Rd Potosi WI 53820",
    "addr:housenumber":"6271",
    "addr:postcode":"53820",
    "addr:street":"Stage Rd",
    "iso:country":"US",
    "sg:address":"6271 Stage Rd",
    "sg:city":"Potosi",
    "sg:classifiers":[
        {
            "category":"Farming",
            "subcategory":"Farm",
            "type":"Manufacturing & Wholesale Goods"
        }
    ],
    "sg:phone":"+1 608 763 2314",
    "sg:postcode":"53820",
    "sg:province":"WI",
    "wof:name":"Rudies Farm",
    "wof:placetype":"venue"
},
  "geometry": {"coordinates":[-90.701702,42.727769],"type":"Point"}
}