{
  "type": "Feature",
  "properties": {
    "iso:country":"US",
    "sg:address":"440 S Executive Dr # 200",
    "sg:city":"Brookfield",
    "sg:classifiers":[
        {
            "category":"Shopping",
            "subcategory":"Stationery & Office Supplies",
            "type":"Retail Goods"
        },
        {
            "category":"Wholesale",
            "subcategory":"Office Equipment",
            "type":"Manufacturing & Wholesale Goods"
        },
        {
            "category":"Retail",
            "subcategory":"Repair Shop",
            "type":"Services"
        },
        {
            "category":"Manufacturing",
            "subcategory":"Printing",
            "type":"Manufacturing & Wholesale Goods"
        },
        {
            "category":"Professional",
            "subcategory":"Computer Services",
            "type":"Services"
        }
    ],
    "sg:phone":"+1 262 784 8726",
    "sg:postcode":"53005",
    "sg:province":"WI",
    "sg:tags":[
        "refinish",
        "copier",
        "machine",
        "equipment-repair",
        "equipment-service",
        "copy",
        "supplies-wholesale",
        "manufacturer",
        "furniture"
    ],
    "sg:website":"http://www.xerox.com",
    "wof:name":"Xerox",
    "wof:placetype":"venue"
},
  "geometry": {"coordinates":[-88.11454500000001,43.026873],"type":"Point"}
}