{
  "type": "Feature",
  "properties": {
    "addr:full":"2503 Norwood Ct Racine WI 53403",
    "addr:housenumber":"2503",
    "addr:postcode":"53403",
    "addr:street":"Norwood Ct",
    "iso:country":"US",
    "sg:address":"2503 Norwood Ct",
    "sg:city":"Racine",
    "sg:classifiers":[
        {
            "category":"Wholesale",
            "subcategory":"Vending Machines",
            "type":"Manufacturing & Wholesale Goods"
        }
    ],
    "sg:phone":"+1 262 554 9111",
    "sg:postcode":"53403",
    "sg:province":"WI",
    "sg:tags":[
        "operator"
    ],
    "wof:name":"Davies Triple M Vending",
    "wof:placetype":"venue"
},
  "geometry": {"coordinates":[-87.80861299999999,42.684904],"type":"Point"}
}