{
  "type": "Feature",
  "properties": {
    "iso:country":"US",
    "sg:address":"9746 Fox River Rd",
    "sg:city":"Portage",
    "sg:phone":"+1 608 742 2469",
    "sg:postcode":"53901",
    "sg:province":"WI",
    "sg:tags":[
        "farm",
        "corn"
    ],
    "wof:name":"Wilcox John",
    "wof:placetype":"venue"
},
  "geometry": {"coordinates":[-89.422847,43.635249],"type":"Point"}
}