{
  "type": "Feature",
  "properties": {
    "iso:country":"US",
    "sg:address":"1486 Co Rd G",
    "sg:city":"Junction City",
    "sg:classifiers":[
        {
            "category":"Farming",
            "subcategory":"Dairy Farm",
            "type":"Manufacturing & Wholesale Goods"
        }
    ],
    "sg:phone":"+1 715 457 2691",
    "sg:postcode":"54443",
    "sg:province":"WI",
    "wof:name":"Maple Mills Dairy",
    "wof:placetype":"venue"
},
  "geometry": {"coordinates":[-89.77780799999999,44.567687],"type":"Point"}
}