{
  "type": "Feature",
  "properties": {
    "iso:country":"US",
    "sg:address":"2900 W Oklahoma Ave",
    "sg:city":"Milwaukee",
    "sg:classifiers":[
        {
            "category":"Health Services",
            "subcategory":"Doctor",
            "type":"Services"
        }
    ],
    "sg:phone":"+1 414 385 8600",
    "sg:postcode":"53215",
    "sg:province":"WI",
    "sg:tags":[
        "physician",
        "surgeon"
    ],
    "wof:name":"Peter W Messer MD",
    "wof:placetype":"venue"
},
  "geometry": {"coordinates":[-87.951788,42.988527],"type":"Point"}
}