{
  "type": "Feature",
  "properties": {
    "iso:country":"US",
    "sg:address":"1206 N Bequette St",
    "sg:city":"Dodgeville",
    "sg:classifiers":[
        {
            "category":"Restaurant",
            "type":"Food & Drink"
        }
    ],
    "sg:phone":"+1 608 935 5310",
    "sg:postcode":"53533",
    "sg:province":"WI",
    "wof:name":"Narvey's Restaurant",
    "wof:placetype":"venue"
},
  "geometry": {"coordinates":[-90.13280399999999,42.974437],"type":"Point"}
}