{
  "type": "Feature",
  "properties": {
    "iso:country":"US",
    "sg:address":"5813 S New York Ave",
    "sg:city":"Cudahy",
    "sg:classifiers":[
        {
            "category":"Retail",
            "subcategory":"Car Wash",
            "type":"Services"
        }
    ],
    "sg:phone":"+1 414 687 1213",
    "sg:postcode":"53110",
    "sg:province":"WI",
    "wof:name":"Western Auto Detailing And Hand Wash",
    "wof:placetype":"venue"
},
  "geometry": {"coordinates":[-87.87857,42.93847],"type":"Point"}
}