{
  "type": "Feature",
  "properties": {
    "iso:country":"US",
    "sg:address":"17830 W Westward Dr",
    "sg:city":"New Berlin",
    "sg:classifiers":[
        {
            "category":"Building & Trades",
            "subcategory":"Construction",
            "type":"Services"
        }
    ],
    "sg:phone":"+1 262 785 0836",
    "sg:postcode":"53146",
    "sg:province":"WI",
    "sg:tags":[
        "house"
    ],
    "wof:name":"Aliota Bros Contracting Inc",
    "wof:placetype":"venue"
},
  "geometry": {"coordinates":[-88.13446,43.006541],"type":"Point"}
}