{
  "type": "Feature",
  "properties": {
    "iso:country":"US",
    "sg:address":"476 S Argyle Ave",
    "sg:city":"Phillips",
    "sg:classifiers":[
        {
            "category":"Professional",
            "subcategory":"Management & Consulting",
            "type":"Services"
        },
        {
            "category":"Professional",
            "subcategory":"Computer Services",
            "type":"Services"
        }
    ],
    "sg:phone":"+1 715 339 6010",
    "sg:postcode":"54555",
    "sg:province":"WI",
    "sg:tags":[
        "consultant",
        "programing",
        "business",
        "custom"
    ],
    "wof:name":"J A Huycke Consulting",
    "wof:placetype":"venue"
},
  "geometry": {"coordinates":[-90.393157,45.683395],"type":"Point"}
}