{
  "type": "Feature",
  "properties": {
    "addr:full":"3810 Bass Ln Cottage Grove WI 53527",
    "addr:housenumber":"3810",
    "addr:postcode":"53527",
    "addr:street":"Bass Ln",
    "iso:country":"US",
    "sg:address":"3810 Bass Ln",
    "sg:city":"Cottage Grove",
    "sg:classifiers":[
        {
            "category":"Real Estate",
            "subcategory":"Real Estate Agent",
            "type":"Services"
        }
    ],
    "sg:phone":"+1 608 764 2800",
    "sg:postcode":"53527",
    "sg:province":"WI",
    "wof:name":"Amacher Realty",
    "wof:placetype":"venue"
},
  "geometry": {"coordinates":[-89.207286,43.056608],"type":"Point"}
}