{
  "type": "Feature",
  "properties": {
    "addr:full":"5696 Fairview Rd Fond Du Lac WI 54937",
    "addr:housenumber":"5696",
    "addr:postcode":"54937",
    "addr:street":"Fairview Rd",
    "iso:country":"US",
    "sg:address":"5696 Fairview Rd",
    "sg:city":"Fond Du Lac",
    "sg:classifiers":[
        {
            "category":"Building & Trades",
            "subcategory":"Construction",
            "type":"Services"
        }
    ],
    "sg:phone":"+1 920 923 1554",
    "sg:postcode":"54937",
    "sg:province":"WI",
    "sg:tags":[
        "contractor"
    ],
    "wof:name":"Potratz Roofing & Construction",
    "wof:placetype":"venue"
},
  "geometry": {"coordinates":[-88.59886,43.736699],"type":"Point"}
}