{
  "type": "Feature",
  "properties": {
    "addr:full":"28 Main St Black River Falls WI 54615",
    "addr:housenumber":"28",
    "addr:postcode":"54615",
    "addr:street":"Main St",
    "iso:country":"US",
    "sg:address":"28 Main St",
    "sg:city":"Black River Falls",
    "sg:classifiers":[
        {
            "category":"Manufacturing",
            "subcategory":"Printing",
            "type":"Manufacturing & Wholesale Goods"
        }
    ],
    "sg:phone":"+1 715 284 2222",
    "sg:postcode":"54615",
    "sg:province":"WI",
    "sg:tags":[
        "commercial",
        "lithographic"
    ],
    "wof:name":"Litho Specialists Inc",
    "wof:placetype":"venue"
},
  "geometry": {"coordinates":[-90.848552,44.294895],"type":"Point"}
}