{
  "type": "Feature",
  "properties": {
    "iso:country":"US",
    "sg:address":"1100 Cranston Rd",
    "sg:city":"Beloit",
    "sg:classifiers":[
        {
            "category":"Insurance",
            "subcategory":"Insurance Agent",
            "type":"Services"
        }
    ],
    "sg:phone":"+1 608 362 8877",
    "sg:postcode":"53511",
    "sg:province":"IL",
    "wof:name":"Seitz Insurance",
    "wof:placetype":"venue"
},
  "geometry": {"coordinates":[-89.02308,42.532264],"type":"Point"}
}