{
  "type": "Feature",
  "properties": {
    "addr:full":"2323 Eastern Ave Plymouth WI 53073",
    "addr:housenumber":"2323",
    "addr:postcode":"53073",
    "addr:street":"Eastern Ave",
    "iso:country":"US",
    "sg:address":"2323 Eastern Ave",
    "sg:city":"Plymouth",
    "sg:classifiers":[
        {
            "category":"Banks & Credit Unions",
            "subcategory":"Bank",
            "type":"Services"
        }
    ],
    "sg:phone":"+1 920 893 1611",
    "sg:postcode":"53073",
    "sg:province":"WI",
    "sg:website":"www.bankfirstnational.com",
    "wof:name":"First National Bank",
    "wof:placetype":"venue"
},
  "geometry": {"coordinates":[-87.954925,43.74704],"type":"Point"}
}