{
  "type": "Feature",
  "properties": {
    "iso:country":"US",
    "sg:address":"4340 S Regal Ct",
    "sg:city":"New Berlin",
    "sg:classifiers":[
        {
            "category":"Building & Trades",
            "subcategory":"Construction",
            "type":"Services"
        }
    ],
    "sg:phone":"+1 262 784 8909",
    "sg:postcode":"53151",
    "sg:province":"WI",
    "sg:tags":[
        "floor",
        "laying",
        "contractor"
    ],
    "wof:name":"Ribish Floor Sanding Co",
    "wof:placetype":"venue"
},
  "geometry": {"coordinates":[-88.098861,42.965103],"type":"Point"}
}