{
  "type": "Feature",
  "properties": {
    "addr:full":"2108 Kohler Memorial Dr Sheboygan WI 53081",
    "addr:housenumber":"2108",
    "addr:postcode":"53081",
    "addr:street":"Memorial Dr",
    "iso:country":"US",
    "sg:address":"2108 Kohler Memorial Dr",
    "sg:city":"Sheboygan",
    "sg:classifiers":[
        {
            "category":"Health Services",
            "subcategory":"Clinic",
            "type":"Services"
        }
    ],
    "sg:phone":"+1 920 803 0188",
    "sg:postcode":"53081",
    "sg:province":"WI",
    "wof:name":"Home Instead Senior Care",
    "wof:placetype":"venue"
},
  "geometry": {"coordinates":[-87.736923,43.756494],"type":"Point"}
}