{
  "type": "Feature",
  "properties": {
    "iso:country":"US",
    "sg:address":"4155 N Newhall St",
    "sg:city":"Milwaukee",
    "sg:classifiers":[
        {
            "category":"Manufacturing",
            "subcategory":"Printing",
            "type":"Manufacturing & Wholesale Goods"
        }
    ],
    "sg:phone":"+1 414 962 0844",
    "sg:postcode":"53211",
    "sg:province":"WI",
    "sg:tags":[
        "typesetting"
    ],
    "wof:name":"City Desktop Productions LLC",
    "wof:placetype":"venue"
},
  "geometry": {"coordinates":[-87.88996400000001,43.093103],"type":"Point"}
}