{
  "type": "Feature",
  "properties": {
    "iso:country":"US",
    "sg:address":"224 Monroe St",
    "sg:city":"Sheboygan Falls",
    "sg:classifiers":[
        {
            "category":"Retail",
            "subcategory":"Veterinary Services",
            "type":"Services"
        }
    ],
    "sg:phone":"+1 920 467 3114",
    "sg:postcode":"53085",
    "sg:province":"WI",
    "sg:tags":[
        "veterinarian"
    ],
    "wof:name":"Sheboygan Falls Veterinary Svc",
    "wof:placetype":"venue"
},
  "geometry": {"coordinates":[-87.803673,43.72915],"type":"Point"}
}