{
  "type": "Feature",
  "properties": {
    "addr:full":"1952 Knob Rd Burlington WI 53105",
    "addr:housenumber":"1952",
    "addr:postcode":"53105",
    "addr:street":"Knob Rd",
    "iso:country":"US",
    "sg:address":"1952 Knob Rd",
    "sg:city":"Burlington",
    "sg:classifiers":[
        {
            "category":"Wholesale",
            "subcategory":"Chemicals & Plastics",
            "type":"Manufacturing & Wholesale Goods"
        }
    ],
    "sg:phone":"+1 262 763 8687",
    "sg:postcode":"53105",
    "sg:province":"WI",
    "wof:name":"Ms Moly",
    "wof:placetype":"venue"
},
  "geometry": {"coordinates":[-88.32567299999999,42.630761],"type":"Point"}
}