{
  "type": "Feature",
  "properties": {
    "iso:country":"US",
    "sg:address":"7287 Forest Ave",
    "sg:city":"Fond Du Lac",
    "sg:classifiers":[
        {
            "category":"Professional",
            "subcategory":"Engineering",
            "type":"Services"
        }
    ],
    "sg:phone":"+1 920 922 9892",
    "sg:postcode":"54937",
    "sg:province":"WI",
    "wof:name":"Advantage Engineerng Co",
    "wof:placetype":"venue"
},
  "geometry": {"coordinates":[-88.523152,43.77743],"type":"Point"}
}