{
  "type": "Feature",
  "properties": {
    "addr:full":"5253 S Howell Ave Milwaukee WI 53207",
    "addr:housenumber":"5253",
    "addr:postcode":"53207",
    "addr:street":"S Howell Ave",
    "iso:country":"US",
    "sg:address":"5253 S Howell Ave",
    "sg:city":"Milwaukee",
    "sg:classifiers":[
        {
            "category":"Travel",
            "subcategory":"Hotels & Motels",
            "type":"Entertainment"
        }
    ],
    "sg:phone":"+1 414 481 8488",
    "sg:postcode":"53207",
    "sg:province":"WI",
    "sg:website":"http://www.the.super8.com/milwaukee03384",
    "wof:name":"Super 8 Milwaukee Airport",
    "wof:placetype":"venue"
},
  "geometry": {"coordinates":[-87.909828,42.949141],"type":"Point"}
}