{
  "type": "Feature",
  "properties": {
    "iso:country":"US",
    "sg:address":"11978 Pleasant Rd",
    "sg:city":"Marshfield",
    "sg:classifiers":[
        {
            "category":"Building & Trades",
            "subcategory":"Plumbing",
            "type":"Services"
        }
    ],
    "sg:phone":"+1 715 387 3674",
    "sg:postcode":"54449",
    "sg:province":"WI",
    "sg:tags":[
        "plumbing",
        "contractor"
    ],
    "wof:name":"Cal's Plumbing Svc LLC",
    "wof:placetype":"venue"
},
  "geometry": {"coordinates":[-90.238336,44.678318],"type":"Point"}
}