{
  "type": "Feature",
  "properties": {
    "iso:country":"US",
    "sg:address":"4309 53rd Ave",
    "sg:city":"Kenosha",
    "sg:classifiers":[
        {
            "category":"Real Estate",
            "subcategory":"Real Estate Agent",
            "type":"Services"
        }
    ],
    "sg:phone":"+1 262 654 5432",
    "sg:postcode":"53144",
    "sg:province":"WI",
    "wof:name":"Roger Schultz Realty",
    "wof:placetype":"venue"
},
  "geometry": {"coordinates":[-87.871153,42.597466],"type":"Point"}
}