{
  "type": "Feature",
  "properties": {
    "addr:full":"131 Carmichael Rd Hudson WI 54016",
    "addr:housenumber":"131",
    "addr:postcode":"54016",
    "addr:street":"Carmichael Rd",
    "iso:country":"US",
    "sg:address":"131 Carmichael Rd",
    "sg:city":"Hudson",
    "sg:classifiers":[
        {
            "category":"Coffee & Tea",
            "type":"Food & Drink"
        },
        {
            "category":"Bagels",
            "type":"Food & Drink"
        }
    ],
    "sg:menulink":"http://www.allmenus.com/wi/hudson/114789-brueggers/menu/",
    "sg:phone":"+1 715 381 3510",
    "sg:postcode":"54016",
    "sg:province":"WI",
    "sg:tags":[
        "wrap",
        "soup",
        "american",
        "sandwich",
        "salad"
    ],
    "wof:name":"Bruegger's",
    "wof:placetype":"venue"
},
  "geometry": {"coordinates":[-92.72121199999999,44.966263],"type":"Point"}
}