{
  "type": "Feature",
  "properties": {
    "iso:country":"US",
    "sg:address":"811 Harding St",
    "sg:city":"Waupaca",
    "sg:classifiers":[
        {
            "category":"Government",
            "subcategory":"Office",
            "type":"Public Place"
        }
    ],
    "sg:phone":"+1 715 258 6230",
    "sg:postcode":"54981",
    "sg:province":"WI",
    "wof:name":"Waupaca County Extension Ofc",
    "wof:placetype":"venue"
},
  "geometry": {"coordinates":[-89.06773200000001,44.350383],"type":"Point"}
}