{
  "type": "Feature",
  "properties": {
    "addr:full":"25 S Main St Mayville WI 53050",
    "addr:housenumber":"25",
    "addr:postcode":"53050",
    "addr:street":"S Main St",
    "iso:country":"US",
    "sg:address":"25 S Main St",
    "sg:city":"Mayville",
    "sg:classifiers":[
        {
            "category":"Sports & Exercise",
            "subcategory":"Bowling",
            "type":"Entertainment"
        }
    ],
    "sg:phone":"+1 920 387 5870",
    "sg:postcode":"53050",
    "sg:province":"WI",
    "sg:tags":[
        "drinking",
        "center"
    ],
    "wof:name":"Spare Time Bowl Inc",
    "wof:placetype":"venue"
},
  "geometry": {"coordinates":[-88.544156,43.495411],"type":"Point"}
}