{
  "type": "Feature",
  "properties": {
    "iso:country":"US",
    "sg:address":"346 King Ln",
    "sg:city":"Oneida",
    "sg:classifiers":[
        {
            "category":"Building & Trades",
            "subcategory":"Cleaning & Sanitation",
            "type":"Services"
        }
    ],
    "sg:phone":"+1 920 869 2166",
    "sg:postcode":"54155",
    "sg:province":"WI",
    "sg:tags":[
        "maintenance"
    ],
    "wof:name":"Sherry Cleaning Service",
    "wof:placetype":"venue"
},
  "geometry": {"coordinates":[-88.200783,44.491299],"type":"Point"}
}