{
  "type": "Feature",
  "properties": {
    "iso:country":"US",
    "sg:address":"711 McClellan St",
    "sg:city":"Wausau",
    "sg:classifiers":[
        {
            "category":"Organizations",
            "subcategory":"Community Association",
            "type":"Services"
        }
    ],
    "sg:phone":"+1 715 845 9914",
    "sg:postcode":"54403",
    "sg:province":"WI",
    "sg:tags":[
        "club"
    ],
    "wof:name":"Alano Club Of Wausau Inc",
    "wof:placetype":"venue"
},
  "geometry": {"coordinates":[-89.620212,44.960955],"type":"Point"}
}