{
  "type": "Feature",
  "properties": {
    "iso:country":"US",
    "sg:address":"3310 Church St",
    "sg:city":"Stevens Point",
    "sg:classifiers":[
        {
            "category":"Shopping",
            "subcategory":"Bicycles & Sporting Goods",
            "type":"Retail Goods"
        }
    ],
    "sg:phone":"+1 715 342 0580",
    "sg:postcode":"54481",
    "sg:province":"WI",
    "wof:name":"Sportsmans Choice",
    "wof:placetype":"venue"
},
  "geometry": {"coordinates":[-89.562899,44.499284],"type":"Point"}
}