{
  "type": "Feature",
  "properties": {
    "iso:country":"US",
    "sg:address":"8952 Co Rd C",
    "sg:city":"Plain",
    "sg:classifiers":[
        {
            "category":"Wholesale",
            "subcategory":"Non-durable Goods",
            "type":"Manufacturing & Wholesale Goods"
        }
    ],
    "sg:phone":"+1 608 643 4401",
    "sg:postcode":"53577",
    "sg:province":"WI",
    "sg:tags":[
        "advertising"
    ],
    "wof:name":"Neumark 1",
    "wof:placetype":"venue"
},
  "geometry": {"coordinates":[-89.95195699999999,43.318089],"type":"Point"}
}