{
  "type": "Feature",
  "properties": {
    "iso:country":"US",
    "sg:address":"2550 Hillcrest Rd",
    "sg:city":"Port Washington",
    "sg:classifiers":[
        {
            "category":"Building & Trades",
            "subcategory":"Landscaping Services",
            "type":"Services"
        }
    ],
    "sg:phone":"+1 262 284 9131",
    "sg:postcode":"53074",
    "sg:province":"WI",
    "sg:tags":[
        "landscape",
        "contractor"
    ],
    "wof:name":"Gantner's Landscape Svc",
    "wof:placetype":"venue"
},
  "geometry": {"coordinates":[-87.910481,43.397661],"type":"Point"}
}