{
  "type": "Feature",
  "properties": {
    "iso:country":"US",
    "sg:address":"11731 52nd St",
    "sg:city":"Colfax",
    "sg:classifiers":[
        {
            "category":"Wholesale",
            "subcategory":"Machinery & Supplies",
            "type":"Manufacturing & Wholesale Goods"
        }
    ],
    "sg:phone":"+1 715 568 4747",
    "sg:postcode":"54730",
    "sg:province":"WI",
    "sg:tags":[
        "repair",
        "industrial",
        "miscellaneous"
    ],
    "wof:name":"Sikora Jeff Equipment Supply",
    "wof:placetype":"venue"
},
  "geometry": {"coordinates":[-91.565328,45.013206],"type":"Point"}
}