{
  "type": "Feature",
  "properties": {
    "iso:country":"US",
    "sg:address":"1206 3rd St S",
    "sg:city":"La Crosse",
    "sg:classifiers":[
        {
            "category":"Real Estate",
            "subcategory":"Surveying",
            "type":"Services"
        }
    ],
    "sg:phone":"+1 608 782 3433",
    "sg:postcode":"54601",
    "sg:province":"WI",
    "sg:tags":[
        "surveyor"
    ],
    "wof:name":"LA Crosse Engineering",
    "wof:placetype":"venue"
},
  "geometry": {"coordinates":[-91.253492,43.800544],"type":"Point"}
}