{
  "type": "Feature",
  "properties": {
    "addr:full":"8052 N 76th St Milwaukee WI 53223",
    "addr:housenumber":"8052",
    "addr:postcode":"53223",
    "addr:street":"N 76Th St",
    "iso:country":"US",
    "sg:address":"8052 N 76th St",
    "sg:city":"Milwaukee",
    "sg:classifiers":[
        {
            "category":"Retail",
            "subcategory":"Veterinary Services",
            "type":"Services"
        }
    ],
    "sg:phone":"+1 414 365 5200",
    "sg:postcode":"53223",
    "sg:province":"WI",
    "sg:tags":[
        "veterinarian"
    ],
    "wof:name":"Advance Veterinary Care",
    "wof:placetype":"venue"
},
  "geometry": {"coordinates":[-88.004581,43.164179],"type":"Point"}
}