{
  "type": "Feature",
  "properties": {
    "iso:country":"US",
    "sg:address":"12873 State Hwy 27",
    "sg:city":"Cadott",
    "sg:classifiers":[
        {
            "category":"Banks & Credit Unions",
            "subcategory":"Investment Brokerage",
            "type":"Services"
        }
    ],
    "sg:phone":"+1 715 289 3676",
    "sg:postcode":"54727",
    "sg:province":"WI",
    "sg:tags":[
        "security"
    ],
    "wof:name":"WPRE LTD",
    "wof:placetype":"venue"
},
  "geometry": {"coordinates":[-91.14645899999999,45.023736],"type":"Point"}
}