{
  "type": "Feature",
  "properties": {
    "iso:country":"US",
    "sg:address":"682 S Whitney Way",
    "sg:city":"Madison",
    "sg:classifiers":[
        {
            "category":"Wholesale",
            "subcategory":"Machinery & Supplies",
            "type":"Manufacturing & Wholesale Goods"
        }
    ],
    "sg:phone":"+1 608 288 8580",
    "sg:postcode":"53711",
    "sg:province":"WI",
    "sg:tags":[
        "salon",
        "beauty"
    ],
    "wof:name":"Victory Beauty Systems",
    "wof:placetype":"venue"
},
  "geometry": {"coordinates":[-89.4735,43.053621],"type":"Point"}
}