{
  "type": "Feature",
  "properties": {
    "addr:full":"6939 S 27th St Franklin WI 53132",
    "addr:housenumber":"6939",
    "addr:postcode":"53132",
    "addr:street":"S 27Th St",
    "iso:country":"US",
    "sg:address":"6939 S 27th St",
    "sg:city":"Franklin",
    "sg:classifiers":[
        {
            "category":"Shopping",
            "subcategory":"Bicycles & Sporting Goods",
            "type":"Retail Goods"
        }
    ],
    "sg:phone":"+1 414 761 1500",
    "sg:postcode":"53132",
    "sg:province":"WI",
    "wof:name":"Gander Mountain",
    "wof:placetype":"venue"
},
  "geometry": {"coordinates":[-87.949729,42.923766],"type":"Point"}
}