{
  "type": "Feature",
  "properties": {
    "iso:country":"US",
    "sg:address":"4402 N 27th St",
    "sg:city":"Milwaukee",
    "sg:classifiers":[
        {
            "category":"Food & Beverages",
            "subcategory":"Groceries & Convenience Stores",
            "type":"Retail Goods"
        }
    ],
    "sg:phone":"+1 414 873 5525",
    "sg:postcode":"53209",
    "sg:province":"WI",
    "sg:tags":[
        "grocer"
    ],
    "wof:name":"North Town Super-Market",
    "wof:placetype":"venue"
},
  "geometry": {"coordinates":[-87.946775,43.097404],"type":"Point"}
}