{
  "type": "Feature",
  "properties": {
    "iso:country":"US",
    "sg:address":"3093 Market St",
    "sg:city":"Green Bay",
    "sg:classifiers":[
        {
            "category":"Wholesale",
            "subcategory":"Durable Goods & Equipment",
            "type":"Manufacturing & Wholesale Goods"
        }
    ],
    "sg:phone":"+1 920 339 0158",
    "sg:postcode":"54304",
    "sg:province":"WI",
    "sg:tags":[
        "representative",
        "manufacturer"
    ],
    "wof:name":"Burton Anderson & Assoc",
    "wof:placetype":"venue"
},
  "geometry": {"coordinates":[-88.084737,44.464469],"type":"Point"}
}