{
  "type": "Feature",
  "properties": {
    "iso:country":"US",
    "sg:address":"127 S Washington St",
    "sg:city":"Green Bay",
    "sg:classifiers":[
        {
            "category":"Real Estate",
            "subcategory":"Real Estate Agent",
            "type":"Services"
        }
    ],
    "sg:phone":"+1 920 435 7000",
    "sg:postcode":"54301",
    "sg:province":"WI",
    "sg:tags":[
        "appraiser"
    ],
    "wof:name":"Dean Reich Appraisers Inc",
    "wof:placetype":"venue"
},
  "geometry": {"coordinates":[-88.01674800000001,44.513373],"type":"Point"}
}