{
  "type": "Feature",
  "properties": {
    "iso:country":"US",
    "sg:address":"925 Madison Ave",
    "sg:city":"South Milwaukee",
    "sg:classifiers":[
        {
            "category":"Restaurant",
            "type":"Food & Drink"
        }
    ],
    "sg:phone":"+1 414 762 0131",
    "sg:postcode":"53172",
    "sg:province":"WI",
    "sg:tags":[
        "eating"
    ],
    "wof:name":"Lloyd's Lunch",
    "wof:placetype":"venue"
},
  "geometry": {"coordinates":[-87.860308,42.909683],"type":"Point"}
}