{
  "type": "Feature",
  "properties": {
    "iso:country":"US",
    "sg:address":"2926 S Mabbett Ave",
    "sg:city":"Milwaukee",
    "sg:classifiers":[
        {
            "category":"Retail",
            "subcategory":"Laundry & Dry Cleaning",
            "type":"Services"
        }
    ],
    "sg:phone":"+1 414 744 4604",
    "sg:postcode":"53207",
    "sg:province":"WI",
    "sg:tags":[
        "cleaners",
        "rug",
        "carpet"
    ],
    "wof:name":"Excellence Carpet",
    "wof:placetype":"venue"
},
  "geometry": {"coordinates":[-87.882148,42.989823],"type":"Point"}
}