{
  "type": "Feature",
  "properties": {
    "addr:full":"2080 Shopiere Rd Beloit WI 53511",
    "addr:housenumber":"2080",
    "addr:postcode":"53511",
    "addr:street":"Shopiere Rd",
    "iso:country":"US",
    "sg:address":"2080 Shopiere Rd",
    "sg:city":"Beloit",
    "sg:classifiers":[
        {
            "category":"Real Estate",
            "subcategory":"Real Estate Operator",
            "type":"Services"
        }
    ],
    "sg:phone":"+1 608 362 8235",
    "sg:postcode":"53511",
    "sg:province":"WI",
    "sg:tags":[
        "building",
        "apartment"
    ],
    "wof:name":"Arrowhead Pointe Apartments",
    "wof:placetype":"venue"
},
  "geometry": {"coordinates":[-89.006828,42.528265],"type":"Point"}
}