{
  "type": "Feature",
  "properties": {
    "addr:full":"8032 238th Ave Salem WI 53168",
    "addr:housenumber":"8032",
    "addr:postcode":"53168",
    "addr:street":"238Th Ave",
    "iso:country":"US",
    "sg:address":"8032 238th Ave",
    "sg:city":"Salem",
    "sg:classifiers":[
        {
            "category":"Freight",
            "type":"Transportation"
        }
    ],
    "sg:phone":"+1 262 843 2042",
    "sg:postcode":"53168",
    "sg:province":"WI",
    "sg:tags":[
        "operator",
        "trucking"
    ],
    "wof:name":"Harris Motor Express",
    "wof:placetype":"venue"
},
  "geometry": {"coordinates":[-88.09556499999999,42.560412],"type":"Point"}
}