{
  "type": "Feature",
  "properties": {
    "iso:country":"US",
    "sg:address":"254 S Chestnut St",
    "sg:city":"Ellsworth",
    "sg:classifiers":[
        {
            "category":"Real Estate",
            "subcategory":"Real Estate Operator",
            "type":"Services"
        }
    ],
    "sg:phone":"+1 715 273 6448",
    "sg:postcode":"54011",
    "sg:province":"WI",
    "sg:tags":[
        "building",
        "parks"
    ],
    "wof:name":"Ames Business Ctr",
    "wof:placetype":"venue"
},
  "geometry": {"coordinates":[-92.482978,44.729072],"type":"Point"}
}