{
  "type": "Feature",
  "properties": {
    "iso:country":"US",
    "sg:address":"1103 17th St",
    "sg:city":"Brodhead",
    "sg:classifiers":[
        {
            "category":"Manufacturing",
            "subcategory":"Metals",
            "type":"Manufacturing & Wholesale Goods"
        }
    ],
    "sg:phone":"+1 608 897 4484",
    "sg:postcode":"53520",
    "sg:province":"WI",
    "sg:tags":[
        "windows",
        "door",
        "storm"
    ],
    "wof:name":"Therma-Vue Window Co",
    "wof:placetype":"venue"
},
  "geometry": {"coordinates":[-89.380433,42.613664],"type":"Point"}
}