{
  "type": "Feature",
  "properties": {
    "addr:full":"1225 E Main St Arcadia WI 54612",
    "addr:housenumber":"1225",
    "addr:postcode":"54612",
    "addr:street":"E Main St",
    "iso:country":"US",
    "sg:address":"1225 E Main St",
    "sg:city":"Arcadia",
    "sg:classifiers":[
        {
            "category":"Utilities",
            "subcategory":"Electric",
            "type":"Services"
        }
    ],
    "sg:phone":"+1 608 685 4415",
    "sg:postcode":"54612",
    "sg:province":"WI",
    "wof:name":"Riverland Energy Cooperative",
    "wof:placetype":"venue"
},
  "geometry": {"coordinates":[-91.50032,44.252523],"type":"Point"}
}