{
  "type": "Feature",
  "properties": {
    "iso:country":"US",
    "sg:address":"739 S Main St",
    "sg:city":"Jefferson",
    "sg:classifiers":[
        {
            "category":"Manufacturing",
            "subcategory":"Metals",
            "type":"Manufacturing & Wholesale Goods"
        }
    ],
    "sg:phone":"+1 920 674 2000",
    "sg:postcode":"53549",
    "sg:province":"WI",
    "sg:tags":[
        "steel"
    ],
    "wof:name":"Arrow Co",
    "wof:placetype":"venue"
},
  "geometry": {"coordinates":[-88.807629,42.998994],"type":"Point"}
}