{
  "type": "Feature",
  "properties": {
    "addr:full":"309 Main St Darlington WI 53530",
    "addr:housenumber":"309",
    "addr:postcode":"53530",
    "addr:street":"Main St",
    "iso:country":"US",
    "sg:address":"309 Main St",
    "sg:city":"Darlington",
    "sg:classifiers":[
        {
            "category":"Personal",
            "subcategory":"Tanning Parlor",
            "type":"Services"
        },
        {
            "category":"Personal",
            "type":"Services"
        }
    ],
    "sg:phone":"+1 608 776 8267",
    "sg:postcode":"53530",
    "sg:province":"WI",
    "sg:tags":[
        "salon"
    ],
    "wof:name":"Cooper Glow Tanning",
    "wof:placetype":"venue"
},
  "geometry": {"coordinates":[-90.117693,42.6798],"type":"Point"}
}