{
  "type": "Feature",
  "properties": {
    "iso:country":"US",
    "sg:address":"1210 Draper St",
    "sg:city":"Baraboo",
    "sg:classifiers":[
        {
            "category":"Health Services",
            "subcategory":"Doctor",
            "type":"Services"
        }
    ],
    "sg:phone":"+1 608 356 2151",
    "sg:postcode":"53913",
    "sg:province":"WI",
    "sg:tags":[
        "dentist"
    ],
    "wof:name":"Orthodontic Specialists",
    "wof:placetype":"venue"
},
  "geometry": {"coordinates":[-89.754468,43.477862],"type":"Point"}
}