{
  "type": "Feature",
  "properties": {
    "iso:country":"US",
    "sg:address":"126 W Newhall Ave",
    "sg:city":"Waukesha",
    "sg:classifiers":[
        {
            "category":"Professional",
            "type":"Services"
        }
    ],
    "sg:phone":"+1 262 650 7966",
    "sg:postcode":"53186",
    "sg:province":"WI",
    "wof:name":"Grand Chapter of Wisconsi",
    "wof:placetype":"venue"
},
  "geometry": {"coordinates":[-88.22960399999999,42.999711],"type":"Point"}
}