{
  "type": "Feature",
  "properties": {
    "iso:country":"US",
    "sg:address":"3521 W Lincoln Ave",
    "sg:city":"Milwaukee",
    "sg:classifiers":[
        {
            "category":"Wholesale",
            "subcategory":"Meat",
            "type":"Manufacturing & Wholesale Goods"
        }
    ],
    "sg:phone":"+1 414 645 1756",
    "sg:postcode":"53215",
    "sg:province":"WI",
    "wof:name":"Badger Boiled Ham Co Inc",
    "wof:placetype":"venue"
},
  "geometry": {"coordinates":[-87.959007,43.002942],"type":"Point"}
}