{
  "type": "Feature",
  "properties": {
    "iso:country":"US",
    "sg:address":"310 Industrial Blvd",
    "sg:city":"New Richmond",
    "sg:classifiers":[
        {
            "category":"Wholesale",
            "subcategory":"Machinery & Supplies",
            "type":"Manufacturing & Wholesale Goods"
        }
    ],
    "sg:phone":"+1 715 246 6414",
    "sg:postcode":"54017",
    "sg:province":"WI",
    "sg:tags":[
        "packaging"
    ],
    "wof:name":"Eclipse Packaging Machine",
    "wof:placetype":"venue"
},
  "geometry": {"coordinates":[-92.539055,45.133961],"type":"Point"}
}