{
  "type": "Feature",
  "properties": {
    "iso:country":"US",
    "sg:address":"1880 N Casaloma Dr",
    "sg:city":"Appleton",
    "sg:classifiers":[
        {
            "category":"Wholesale",
            "subcategory":"Hardware",
            "type":"Manufacturing & Wholesale Goods"
        }
    ],
    "sg:phone":"+1 920 380 0303",
    "sg:postcode":"54913",
    "sg:province":"WI",
    "sg:tags":[
        "plumbing",
        "fixture"
    ],
    "wof:name":"Bath Tech of Appleton LLC",
    "wof:placetype":"venue"
},
  "geometry": {"coordinates":[-88.476412,44.277457],"type":"Point"}
}