{
  "type": "Feature",
  "properties": {
    "iso:country":"US",
    "sg:address":"2035 Walker Rd",
    "sg:city":"Mosinee",
    "sg:classifiers":[
        {
            "category":"Building & Trades",
            "subcategory":"Construction",
            "type":"Services"
        }
    ],
    "sg:phone":"+1 715 241 8621",
    "sg:postcode":"54455",
    "sg:province":"WI",
    "sg:tags":[
        "contractor"
    ],
    "wof:name":"Tim Koch Builders Inc",
    "wof:placetype":"venue"
},
  "geometry": {"coordinates":[-89.613094,44.843418],"type":"Point"}
}