{
  "type": "Feature",
  "properties": {
    "iso:country":"US",
    "sg:address":"4276 State Hwy 35",
    "sg:city":"Superior",
    "sg:classifiers":[
        {
            "category":"Building & Trades",
            "subcategory":"Construction",
            "type":"Services"
        }
    ],
    "sg:phone":"+1 715 399 8546",
    "sg:postcode":"54880",
    "sg:province":"WI",
    "sg:tags":[
        "contractor"
    ],
    "wof:name":"Roger Pettit Construction",
    "wof:placetype":"venue"
},
  "geometry": {"coordinates":[-92.104101,46.68591],"type":"Point"}
}