{
  "type": "Feature",
  "properties": {
    "iso:country":"US",
    "sg:address":"214 Olivet St",
    "sg:city":"La Crosse",
    "sg:classifiers":[
        {
            "category":"Freight",
            "type":"Transportation"
        }
    ],
    "sg:phone":"+1 608 796 1325",
    "sg:postcode":"54603",
    "sg:province":"WI",
    "sg:tags":[
        "operator",
        "local",
        "trucking"
    ],
    "wof:name":"CT Delivery Service Inc",
    "wof:placetype":"venue"
},
  "geometry": {"coordinates":[-91.264391,43.857686],"type":"Point"}
}