{
  "type": "Feature",
  "properties": {
    "iso:country":"US",
    "sg:address":"560 Westlawn Ave",
    "sg:city":"Elkhorn",
    "sg:classifiers":[
        {
            "category":"Freight",
            "type":"Transportation"
        }
    ],
    "sg:phone":"+1 262 723 1920",
    "sg:postcode":"53121",
    "sg:province":"WI",
    "sg:tags":[
        "logistics",
        "arrangement"
    ],
    "wof:name":"Cornerstone Systems Inc",
    "wof:placetype":"venue"
},
  "geometry": {"coordinates":[-88.552195,42.679466],"type":"Point"}
}