{
  "type": "Feature",
  "properties": {
    "iso:country":"US",
    "sg:address":"7761 Pine Rd",
    "sg:city":"Lake Tomahawk",
    "sg:classifiers":[
        {
            "category":"Building & Trades",
            "subcategory":"Construction",
            "type":"Services"
        }
    ],
    "sg:phone":"+1 715 277 2519",
    "sg:postcode":"54539",
    "sg:province":"WI",
    "sg:tags":[
        "home",
        "general",
        "family",
        "contractor"
    ],
    "wof:name":"Kuckkahn Construction Inc",
    "wof:placetype":"venue"
},
  "geometry": {"coordinates":[-89.58205100000001,45.808086],"type":"Point"}
}