{
  "type": "Feature",
  "properties": {
    "iso:country":"US",
    "sg:address":"1218 W Kilbourn Ave",
    "sg:city":"Milwaukee",
    "sg:classifiers":[
        {
            "category":"Health Services",
            "subcategory":"Health Practitioner",
            "type":"Services"
        }
    ],
    "sg:phone":"+1 414 219 7769",
    "sg:postcode":"53233",
    "sg:province":"WI",
    "sg:tags":[
        "psychologist"
    ],
    "wof:name":"Kerry Hamsher PHD",
    "wof:placetype":"venue"
},
  "geometry": {"coordinates":[-87.92850900000001,43.04167],"type":"Point"}
}