{
  "type": "Feature",
  "properties": {
    "addr:full":"1239 Bellevue Ave Eau Claire WI 54703",
    "addr:housenumber":"1239",
    "addr:postcode":"54703",
    "addr:street":"Bellevue Ave",
    "iso:country":"US",
    "sg:address":"1239 Bellevue Ave",
    "sg:city":"Eau Claire",
    "sg:classifiers":[
        {
            "category":"Building & Trades",
            "subcategory":"Construction",
            "type":"Services"
        }
    ],
    "sg:phone":"+1 715 834 6211",
    "sg:postcode":"54703",
    "sg:province":"WI",
    "sg:tags":[
        "roofing",
        "contractor"
    ],
    "wof:name":"TEK Roofing Inc",
    "wof:placetype":"venue"
},
  "geometry": {"coordinates":[-91.490945,44.817118],"type":"Point"}
}