{
  "type": "Feature",
  "properties": {
    "iso:country":"US",
    "sg:address":"4223 Expo Dr",
    "sg:city":"Manitowoc",
    "sg:classifiers":[
        {
            "category":"Building & Trades",
            "subcategory":"Construction",
            "type":"Services"
        }
    ],
    "sg:phone":"+1 920 684 4564",
    "sg:postcode":"54220",
    "sg:province":"WI",
    "sg:tags":[
        "general",
        "contractor"
    ],
    "wof:name":"Jos Schmitt & Sons Constr Co",
    "wof:placetype":"venue"
},
  "geometry": {"coordinates":[-87.69956500000001,44.080609],"type":"Point"}
}