{
  "type": "Feature",
  "properties": {
    "iso:country":"US",
    "sg:address":"1206 Declark St",
    "sg:city":"Beaver Dam",
    "sg:classifiers":[
        {
            "category":"Retail",
            "subcategory":"Veterinary Services",
            "type":"Services"
        }
    ],
    "sg:phone":"+1 920 885 4148",
    "sg:postcode":"53916",
    "sg:province":"WI",
    "wof:name":"Wyllow Pet Hospital",
    "wof:placetype":"venue"
},
  "geometry": {"coordinates":[-88.834841,43.479881],"type":"Point"}
}