{
  "type": "Feature",
  "properties": {
    "iso:country":"US",
    "sg:address":"191 Memorial Dr",
    "sg:city":"Berlin",
    "sg:classifiers":[
        {
            "category":"Health Services",
            "subcategory":"Doctor",
            "type":"Services"
        }
    ],
    "sg:phone":"+1 920 361 4949",
    "sg:postcode":"54923",
    "sg:province":"WI",
    "sg:tags":[
        "physician",
        "surgeon"
    ],
    "wof:name":"Clarke Laser Vision",
    "wof:placetype":"venue"
},
  "geometry": {"coordinates":[-88.945116,43.977736],"type":"Point"}
}