{
  "type": "Feature",
  "properties": {
    "iso:country":"US",
    "sg:address":"9036 W Schlinger Ave",
    "sg:city":"Milwaukee",
    "sg:classifiers":[
        {
            "category":"Real Estate",
            "subcategory":"Real Estate Operator",
            "type":"Services"
        },
        {
            "category":"Autos & Motor Vehicles",
            "subcategory":"Auto Supplies",
            "type":"Retail Goods"
        }
    ],
    "sg:phone":"+1 414 453 2440",
    "sg:postcode":"53214",
    "sg:province":"WI",
    "sg:tags":[
        "automobile",
        "racing",
        "dwelling",
        "car",
        "equipment"
    ],
    "wof:name":"Yard Racing",
    "wof:placetype":"venue"
},
  "geometry": {"coordinates":[-88.025644,43.023892],"type":"Point"}
}