{
  "type": "Feature",
  "properties": {
    "iso:country":"US",
    "sg:address":"5534 State Rd 50",
    "sg:city":"Delavan",
    "sg:classifiers":[
        {
            "category":"Personal",
            "subcategory":"Tanning Parlor",
            "type":"Services"
        },
        {
            "category":"Personal",
            "subcategory":"Beauty Salon",
            "type":"Services"
        }
    ],
    "sg:phone":"+1 262 728 8267",
    "sg:postcode":"53115",
    "sg:province":"WI",
    "sg:tags":[
        "shop"
    ],
    "wof:name":"Hands 'n Tans",
    "wof:placetype":"venue"
},
  "geometry": {"coordinates":[-88.594798,42.627971],"type":"Point"}
}