{
  "type": "Feature",
  "properties": {
    "iso:country":"US",
    "sg:address":"924 E Main St",
    "sg:city":"Madison",
    "sg:classifiers":[
        {
            "category":"Home & Garden",
            "subcategory":"Building Materials",
            "type":"Retail Goods"
        }
    ],
    "sg:phone":"+1 608 260 9129",
    "sg:postcode":"53703",
    "sg:province":"WI",
    "wof:name":"Altschuler Wallpaper",
    "wof:placetype":"venue"
},
  "geometry": {"coordinates":[-89.370842,43.082454],"type":"Point"}
}