{
  "type": "Feature",
  "properties": {
    "addr:full":"4340 Basswood Dr Lake Geneva WI 53147",
    "addr:housenumber":"4340",
    "addr:postcode":"53147",
    "addr:street":"Basswood Dr",
    "iso:country":"US",
    "sg:address":"4340 Basswood Dr",
    "sg:city":"Lake Geneva",
    "sg:classifiers":[
        {
            "category":"Recreation",
            "subcategory":"Marina",
            "type":"Entertainment"
        }
    ],
    "sg:phone":"+1 262 248 6128",
    "sg:postcode":"53147",
    "sg:province":"WI",
    "sg:tags":[
        "marine",
        "storage",
        "repair"
    ],
    "wof:name":"Majestic Marine Inc",
    "wof:placetype":"venue"
},
  "geometry": {"coordinates":[-88.514143,42.551033],"type":"Point"}
}