{
  "type": "Feature",
  "properties": {
    "iso:country":"US",
    "sg:address":"6419 W Leon Ter",
    "sg:city":"Milwaukee",
    "sg:classifiers":[
        {
            "category":"Organizations",
            "subcategory":"Religious Organization",
            "type":"Services"
        }
    ],
    "sg:phone":"+1 414 342 9974",
    "sg:postcode":"53218",
    "sg:province":"WI",
    "wof:name":"Greater New Bethel Full Gospel",
    "wof:placetype":"venue"
},
  "geometry": {"coordinates":[-87.991902,43.103351],"type":"Point"}
}