{
  "type": "Feature",
  "properties": {
    "iso:country":"US",
    "sg:address":"2623 W Lake Vista Ct",
    "sg:city":"Thiensville",
    "sg:classifiers":[
        {
            "category":"Professional",
            "subcategory":"Business Services",
            "type":"Services"
        }
    ],
    "sg:phone":"+1 262 236 0168",
    "sg:postcode":"53092",
    "sg:province":"WI",
    "wof:name":"Cft Enterprises Inc",
    "wof:placetype":"venue"
},
  "geometry": {"coordinates":[-87.943184,43.245813],"type":"Point"}
}