{
  "type": "Feature",
  "properties": {
    "iso:country":"US",
    "sg:address":"5040 W Fond du Lac Ave",
    "sg:city":"Milwaukee",
    "sg:classifiers":[
        {
            "category":"Shopping",
            "type":"Retail Goods"
        }
    ],
    "sg:phone":"+1 414 466 0300",
    "sg:postcode":"53216",
    "sg:province":"WI",
    "sg:tags":[
        "merchandise"
    ],
    "wof:name":"Mister Stereo",
    "wof:placetype":"venue"
},
  "geometry": {"coordinates":[-87.97675,43.090305],"type":"Point"}
}