{
  "type": "Feature",
  "properties": {
    "iso:country":"US",
    "sg:address":"117 E Canal St",
    "sg:city":"Chippewa Falls",
    "sg:classifiers":[
        {
            "category":"Shopping",
            "subcategory":"Hobbies, Toys, & Games",
            "type":"Retail Goods"
        }
    ],
    "sg:phone":"+1 715 726 9219",
    "sg:postcode":"54729",
    "sg:province":"WI",
    "wof:name":"D & R Diecast",
    "wof:placetype":"venue"
},
  "geometry": {"coordinates":[-91.39061,44.928662],"type":"Point"}
}