{
  "type": "Feature",
  "properties": {
    "iso:country":"US",
    "sg:address":"7002 Shanty Rd",
    "sg:city":"Greenleaf",
    "sg:classifiers":[
        {
            "category":"Farming",
            "subcategory":"Dairy Farm",
            "type":"Manufacturing & Wholesale Goods"
        }
    ],
    "sg:phone":"+1 920 532 4082",
    "sg:postcode":"54126",
    "sg:province":"WI",
    "wof:name":"Van Dehey Paul",
    "wof:placetype":"venue"
},
  "geometry": {"coordinates":[-88.152292,44.299576],"type":"Point"}
}