{
  "type": "Feature",
  "properties": {
    "iso:country":"US",
    "sg:address":"6400 Firelane 8",
    "sg:city":"Menasha",
    "sg:classifiers":[
        {
            "category":"Professional",
            "subcategory":"Computer Services",
            "type":"Services"
        }
    ],
    "sg:phone":"+1 920 733 6863",
    "sg:postcode":"54952",
    "sg:province":"WI",
    "sg:tags":[
        "programing",
        "custom"
    ],
    "wof:name":"Digital Expressions",
    "wof:placetype":"venue"
},
  "geometry": {"coordinates":[-88.36355,44.205148],"type":"Point"}
}