{
  "type": "Feature",
  "properties": {
    "iso:country":"US",
    "sg:address":"199 Baldwin St",
    "sg:city":"Sharon",
    "sg:classifiers":[
        {
            "category":"Food & Beverages",
            "subcategory":"Specialty",
            "type":"Retail Goods"
        },
        {
            "category":"Restaurant",
            "type":"Food & Drink"
        }
    ],
    "sg:phone":"+1 262 736 2400",
    "sg:postcode":"53585",
    "sg:province":"WI",
    "sg:tags":[
        "shop",
        "coffee",
        "eating"
    ],
    "wof:name":"A Norther Cup Coffee & Tea",
    "wof:placetype":"venue"
},
  "geometry": {"coordinates":[-88.729133,42.502168],"type":"Point"}
}