{
  "type": "Feature",
  "properties": {
    "iso:country":"US",
    "sg:address":"18797 Apollo Dr",
    "sg:city":"Muskego",
    "sg:classifiers":[
        {
            "category":"Manufacturing",
            "subcategory":"Metals",
            "type":"Manufacturing & Wholesale Goods"
        }
    ],
    "sg:phone":"+1 262 679 2820",
    "sg:postcode":"53150",
    "sg:province":"WI",
    "sg:tags":[
        "die",
        "tool",
        "stampings",
        "mfg"
    ],
    "wof:name":"Accu Tool & Die",
    "wof:placetype":"venue"
},
  "geometry": {"coordinates":[-88.148549,42.898397],"type":"Point"}
}