{
  "type": "Feature",
  "properties": {
    "iso:country":"US",
    "sg:address":"1530 W Atkinson Ave",
    "sg:city":"Milwaukee",
    "sg:classifiers":[
        {
            "category":"Organizations",
            "subcategory":"Religious Organization",
            "type":"Services"
        }
    ],
    "sg:phone":"+1 414 562 6776",
    "sg:postcode":"53206",
    "sg:province":"WI",
    "sg:tags":[
        "church"
    ],
    "wof:name":"Lovell Johnson Quality Of Life",
    "wof:placetype":"venue"
},
  "geometry": {"coordinates":[-87.930469,43.087058],"type":"Point"}
}