{
  "type": "Feature",
  "properties": {
    "addr:full":"225 N Janacek Rd Brookfield WI 53045",
    "addr:housenumber":"225",
    "addr:postcode":"53045",
    "addr:street":"N Janacek Rd",
    "iso:country":"US",
    "sg:address":"225 N Janacek Rd",
    "sg:city":"Brookfield",
    "sg:classifiers":[
        {
            "category":"Manufacturing",
            "subcategory":"Metals",
            "type":"Manufacturing & Wholesale Goods"
        }
    ],
    "sg:phone":"+1 262 789 7370",
    "sg:postcode":"53045",
    "sg:province":"WI",
    "sg:tags":[
        "fabricator",
        "sheet"
    ],
    "sg:website":"www.fabri-tech.net",
    "wof:name":"Fabri-Tech Inc",
    "wof:placetype":"venue"
},
  "geometry": {"coordinates":[-88.15684899999999,43.033531],"type":"Point"}
}