{
  "type": "Feature",
  "properties": {
    "iso:country":"US",
    "sg:address":"1905 Hall Ave",
    "sg:city":"Marinette",
    "sg:classifiers":[
        {
            "category":"Government",
            "subcategory":"Office",
            "type":"Public Place"
        }
    ],
    "sg:phone":"+1 715 732 5134",
    "sg:postcode":"54143",
    "sg:province":"WI",
    "sg:tags":[
        "city",
        "planning",
        "dev"
    ],
    "wof:name":"Marinette Redevelopment Auth",
    "wof:placetype":"venue"
},
  "geometry": {"coordinates":[-87.632121,45.099758],"type":"Point"}
}