{
  "type": "Feature",
  "properties": {
    "iso:country":"US",
    "sg:address":"430 S Christine St",
    "sg:city":"Appleton",
    "sg:classifiers":[
        {
            "category":"Professional",
            "type":"Services"
        }
    ],
    "sg:phone":"+1 920 739 9680",
    "sg:postcode":"54915",
    "sg:province":"WI",
    "wof:name":"Jacksons Nursery",
    "wof:placetype":"venue"
},
  "geometry": {"coordinates":[-88.373846,44.257388],"type":"Point"}
}