{
  "type": "Feature",
  "properties": {
    "iso:country":"US",
    "sg:address":"2056 Main St",
    "sg:city":"Green Bay",
    "sg:classifiers":[
        {
            "category":"Retail",
            "subcategory":"Self-service Laundry",
            "type":"Services"
        }
    ],
    "sg:phone":"+1 920 468 9996",
    "sg:postcode":"54302",
    "sg:province":"WI",
    "sg:tags":[
        "coin"
    ],
    "wof:name":"Clean Machine Laundry East & W",
    "wof:placetype":"venue"
},
  "geometry": {"coordinates":[-87.973613,44.489713],"type":"Point"}
}