{
  "type": "Feature",
  "properties": {
    "addr:full":"3289 Co Rd A Columbus WI 53925",
    "addr:housenumber":"3289",
    "addr:postcode":"53925",
    "addr:street":"Co Rd A",
    "iso:country":"US",
    "sg:address":"3289 Co Rd A",
    "sg:city":"Columbus",
    "sg:phone":"+1 920 992 3541",
    "sg:postcode":"53925",
    "sg:province":"WI",
    "sg:tags":[
        "farm",
        "corn"
    ],
    "wof:name":"Ss Farms",
    "wof:placetype":"venue"
},
  "geometry": {"coordinates":[-89.16616500000001,43.324211],"type":"Point"}
}