{
  "type": "Feature",
  "properties": {
    "iso:country":"US",
    "sg:address":"6702 Venture Cir",
    "sg:city":"Schofield",
    "sg:classifiers":[
        {
            "category":"Manufacturing",
            "subcategory":"Apparel",
            "type":"Manufacturing & Wholesale Goods"
        }
    ],
    "sg:phone":"+1 715 241 7676",
    "sg:postcode":"54476",
    "sg:province":"WI",
    "sg:tags":[
        "sewing",
        "contractor"
    ],
    "wof:name":"Midwest Industrial Sewing Corp",
    "wof:placetype":"venue"
},
  "geometry": {"coordinates":[-89.514106,44.896406],"type":"Point"}
}