{
  "type": "Feature",
  "properties": {
    "iso:country":"US",
    "sg:address":"511 Partridge Dr",
    "sg:city":"New London",
    "sg:classifiers":[
        {
            "category":"Real Estate",
            "subcategory":"Real Estate Operator",
            "type":"Services"
        }
    ],
    "sg:phone":"+1 920 982 4404",
    "sg:postcode":"54961",
    "sg:province":"WI",
    "wof:name":"Gateway Village Apartments",
    "wof:placetype":"venue"
},
  "geometry": {"coordinates":[-88.748106,44.413701],"type":"Point"}
}