{
  "type": "Feature",
  "properties": {
    "iso:country":"US",
    "sg:address":"1111 State Hwy 11",
    "sg:city":"Brodhead",
    "sg:classifiers":[
        {
            "category":"Wholesale",
            "subcategory":"Farm Supplies",
            "type":"Manufacturing & Wholesale Goods"
        }
    ],
    "sg:phone":"+1 608 897 2001",
    "sg:postcode":"53520",
    "sg:province":"WI",
    "sg:tags":[
        "corn"
    ],
    "wof:name":"Jacksons Farm Store Inc",
    "wof:placetype":"venue"
},
  "geometry": {"coordinates":[-89.376879,42.619445],"type":"Point"}
}