{
  "type": "Feature",
  "properties": {
    "iso:country":"US",
    "sg:address":"316 Freeman St",
    "sg:city":"Genoa City",
    "sg:classifiers":[
        {
            "category":"Manufacturing",
            "subcategory":"Tools & Machinery",
            "type":"Manufacturing & Wholesale Goods"
        }
    ],
    "sg:phone":"+1 262 279 6533",
    "sg:postcode":"53125",
    "sg:province":"WI",
    "sg:tags":[
        "designed",
        "built"
    ],
    "sg:website":"www.ktmautomation.com",
    "wof:name":"Knolls Tool & Mfg Inc",
    "wof:placetype":"venue"
},
  "geometry": {"coordinates":[-88.329911,42.501847],"type":"Point"}
}