{
  "type": "Feature",
  "properties": {
    "iso:country":"US",
    "sg:address":"801 E Decker St",
    "sg:city":"Viroqua",
    "sg:classifiers":[
        {
            "category":"Real Estate",
            "subcategory":"Real Estate Agent",
            "type":"Services"
        }
    ],
    "sg:phone":"+1 608 637 7051",
    "sg:postcode":"54665",
    "sg:province":"WI",
    "sg:tags":[
        "business"
    ],
    "sg:website":"www.viroquarealty.com",
    "wof:name":"Viroqua Realty",
    "wof:placetype":"venue"
},
  "geometry": {"coordinates":[-90.878287,43.557833],"type":"Point"}
}