{
  "type": "Feature",
  "properties": {
    "iso:country":"US",
    "sg:address":"1623 N 37th St",
    "sg:city":"Sheboygan",
    "sg:classifiers":[
        {
            "category":"Building & Trades",
            "subcategory":"Equipment Rental",
            "type":"Services"
        }
    ],
    "sg:phone":"+1 920 452 1074",
    "sg:postcode":"53081",
    "sg:province":"WI",
    "sg:tags":[
        "operator",
        "dwelling"
    ],
    "wof:name":"Loesing Rentals",
    "wof:placetype":"venue"
},
  "geometry": {"coordinates":[-87.755848,43.763152],"type":"Point"}
}