{
  "type": "Feature",
  "properties": {
    "addr:full":"940 Wisconsin Dells Pkwy Wisconsin Dells WI 53965",
    "addr:housenumber":"940",
    "addr:postcode":"53965",
    "addr:street":"Wisconsin Dells Pkwy",
    "iso:country":"US",
    "sg:address":"940 Wisconsin Dells Pkwy",
    "sg:city":"Wisconsin Dells",
    "sg:classifiers":[
        {
            "category":"Restaurant",
            "type":"Food & Drink"
        }
    ],
    "sg:menulink":"http://www.allmenus.com/wi/lake-delton/214698-ponderosa-steak-house/menu/",
    "sg:phone":"+1 608 253 3705",
    "sg:postcode":"53965",
    "sg:province":"WI",
    "sg:tags":[
        "american",
        "steakhouse"
    ],
    "wof:name":"Ponderosa Steak House",
    "wof:placetype":"venue"
},
  "geometry": {"coordinates":[-89.79353500000001,43.600237],"type":"Point"}
}