{
  "type": "Feature",
  "properties": {
    "iso:country":"US",
    "sg:address":"106 N L St",
    "sg:city":"Sparta",
    "sg:classifiers":[
        {
            "category":"Food & Beverages",
            "subcategory":"Specialty",
            "type":"Retail Goods"
        }
    ],
    "sg:phone":"+1 608 269 5036",
    "sg:postcode":"54656",
    "sg:province":"WI",
    "sg:tags":[
        "vitamin"
    ],
    "wof:name":"Shaklee Distributor",
    "wof:placetype":"venue"
},
  "geometry": {"coordinates":[-90.815257,43.945386],"type":"Point"}
}