{
  "type": "Feature",
  "properties": {
    "iso:country":"US",
    "sg:address":"10033 W Ruby Ave",
    "sg:city":"Milwaukee",
    "sg:classifiers":[
        {
            "category":"Professional",
            "subcategory":"Computer Services",
            "type":"Services"
        }
    ],
    "sg:phone":"+1 414 535 0161",
    "sg:postcode":"53225",
    "sg:province":"WI",
    "sg:tags":[
        "datum",
        "g"
    ],
    "wof:name":"Jazz Review",
    "wof:placetype":"venue"
},
  "geometry": {"coordinates":[-88.038909,43.098718],"type":"Point"}
}