{
  "type": "Feature",
  "properties": {
    "iso:country":"US",
    "sg:address":"1744 Riggert Rd",
    "sg:city":"Fort Atkinson",
    "sg:classifiers":[
        {
            "category":"Building & Trades",
            "subcategory":"Construction",
            "type":"Services"
        }
    ],
    "sg:phone":"+1 920 568 0963",
    "sg:postcode":"53538",
    "sg:province":"WI",
    "sg:tags":[
        "house"
    ],
    "wof:name":"M&H Builders",
    "wof:placetype":"venue"
},
  "geometry": {"coordinates":[-88.834377,42.903152],"type":"Point"}
}