{
  "type": "Feature",
  "properties": {
    "iso:country":"US",
    "sg:address":"3085 51st St",
    "sg:city":"Mauston",
    "sg:classifiers":[
        {
            "category":"Farming",
            "subcategory":"Livestock Farm",
            "type":"Manufacturing & Wholesale Goods"
        }
    ],
    "sg:phone":"+1 608 847 5574",
    "sg:postcode":"53948",
    "sg:province":"WI",
    "sg:tags":[
        "beef",
        "feedlot",
        "cattle"
    ],
    "wof:name":"Bluff View Farms",
    "wof:placetype":"venue"
},
  "geometry": {"coordinates":[-89.926362,43.782086],"type":"Point"}
}