{
  "type": "Feature",
  "properties": {
    "iso:country":"US",
    "sg:address":"139 Main St",
    "sg:city":"Camp Douglas",
    "sg:classifiers":[
        {
            "category":"Insurance",
            "subcategory":"Insurance Agent",
            "type":"Services"
        }
    ],
    "sg:phone":"+1 608 562 6015",
    "sg:postcode":"54618",
    "sg:province":"WI",
    "wof:name":"Rick Bean Agency",
    "wof:placetype":"venue"
},
  "geometry": {"coordinates":[-90.268022,43.919229],"type":"Point"}
}