{
  "type": "Feature",
  "properties": {
    "iso:country":"US",
    "sg:address":"1580 10th Ave",
    "sg:city":"Baldwin",
    "sg:classifiers":[
        {
            "category":"Government",
            "subcategory":"Office",
            "type":"Public Place"
        }
    ],
    "sg:phone":"+1 715 684 2535",
    "sg:postcode":"54002",
    "sg:province":"WI",
    "sg:tags":[
        "management"
    ],
    "wof:name":"Village Baldwin Public Works",
    "wof:placetype":"venue"
},
  "geometry": {"coordinates":[-92.375031,44.958383],"type":"Point"}
}