{
  "type": "Feature",
  "properties": {
    "addr:full":"3200 S 3rd St Milwaukee WI 53207",
    "addr:housenumber":"3200",
    "addr:postcode":"53207",
    "addr:street":"S 3Rd St",
    "iso:country":"US",
    "sg:address":"3200 S 3rd St",
    "sg:city":"Milwaukee",
    "sg:classifiers":[
        {
            "category":"Professional",
            "subcategory":"Art Services",
            "type":"Services"
        }
    ],
    "sg:phone":"+1 414 482 4114",
    "sg:postcode":"53207",
    "sg:province":"WI",
    "sg:tags":[
        "photography",
        "commercial"
    ],
    "wof:name":"Lanza Advertising Photography",
    "wof:placetype":"venue"
},
  "geometry": {"coordinates":[-87.914402,42.985253],"type":"Point"}
}