{
  "type": "Feature",
  "properties": {
    "iso:country":"US",
    "sg:address":"420 Riverside Blvd",
    "sg:city":"Amery",
    "sg:classifiers":[
        {
            "category":"Professional",
            "subcategory":"Art Services",
            "type":"Services"
        }
    ],
    "sg:phone":"+1 715 268 2996",
    "sg:postcode":"54001",
    "sg:province":"WI",
    "sg:tags":[
        "commercial",
        "design"
    ],
    "wof:name":"Isakson Design Limited Inc",
    "wof:placetype":"venue"
},
  "geometry": {"coordinates":[-92.358315,45.316084],"type":"Point"}
}