{
  "type": "Feature",
  "properties": {
    "addr:full":"12438 W National Ave New Berlin WI 53151",
    "addr:housenumber":"12438",
    "addr:postcode":"53151",
    "addr:street":"W National Ave",
    "iso:country":"US",
    "sg:address":"12438 W National Ave",
    "sg:city":"New Berlin",
    "sg:classifiers":[
        {
            "category":"Personal",
            "subcategory":"Beauty Salon",
            "type":"Services"
        }
    ],
    "sg:phone":"+1 262 797 9710",
    "sg:postcode":"53151",
    "sg:province":"WI",
    "sg:tags":[
        "shop"
    ],
    "wof:name":"Hair Decisions",
    "wof:placetype":"venue"
},
  "geometry": {"coordinates":[-88.069745,42.988249],"type":"Point"}
}