{
  "type": "Feature",
  "properties": {
    "iso:country":"US",
    "sg:address":"8418 Oakmont Dr",
    "sg:city":"Madison",
    "sg:classifiers":[
        {
            "category":"Autos & Motor Vehicles",
            "subcategory":"Fuel & Gas Station",
            "type":"Retail Goods"
        }
    ],
    "sg:phone":"+1 608 833 1242",
    "sg:postcode":"53717",
    "sg:province":"WI",
    "sg:tags":[
        "station",
        "gasoline"
    ],
    "wof:name":"S & K Petroleum LLC",
    "wof:placetype":"venue"
},
  "geometry": {"coordinates":[-89.527851,43.069203],"type":"Point"}
}