{
  "type": "Feature",
  "properties": {
    "iso:country":"US",
    "sg:address":"220 E Union St",
    "sg:city":"Waupaca",
    "sg:classifiers":[
        {
            "category":"Real Estate",
            "subcategory":"Real Estate Operator",
            "type":"Services"
        }
    ],
    "sg:phone":"+1 715 258 2525",
    "sg:postcode":"54981",
    "sg:province":"WI",
    "sg:tags":[
        "building",
        "operation",
        "apartment"
    ],
    "wof:name":"Hotel Waupaca",
    "wof:placetype":"venue"
},
  "geometry": {"coordinates":[-89.082835,44.357022],"type":"Point"}
}