{
  "type": "Feature",
  "properties": {
    "iso:country":"US",
    "sg:address":"504 Main St",
    "sg:city":"Wilton",
    "sg:classifiers":[
        {
            "category":"Bars & Pubs",
            "type":"Food & Drink"
        }
    ],
    "sg:phone":"+1 608 435 6552",
    "sg:postcode":"54670",
    "sg:province":"WI",
    "wof:name":"Lone Star Bar & Grill",
    "wof:placetype":"venue"
},
  "geometry": {"coordinates":[-90.528144,43.814961],"type":"Point"}
}