{
  "type": "Feature",
  "properties": {
    "iso:country":"US",
    "sg:address":"14350 Badger Ave",
    "sg:city":"Abbotsford",
    "sg:classifiers":[
        {
            "category":"Farming",
            "subcategory":"Dairy Farm",
            "type":"Manufacturing & Wholesale Goods"
        }
    ],
    "sg:phone":"+1 715 223 2555",
    "sg:postcode":"54405",
    "sg:province":"WI",
    "wof:name":"L Mader Farm",
    "wof:placetype":"venue"
},
  "geometry": {"coordinates":[-90.357023,44.934669],"type":"Point"}
}