{
  "type": "Feature",
  "properties": {
    "iso:country":"US",
    "sg:address":"18520 Scranton St",
    "sg:city":"Whitehall",
    "sg:classifiers":[
        {
            "category":"Health Services",
            "subcategory":"Doctor",
            "type":"Services"
        }
    ],
    "sg:phone":"+1 715 538 2306",
    "sg:postcode":"54773",
    "sg:province":"WI",
    "sg:tags":[
        "clinic"
    ],
    "wof:name":"Western Dairyland Family Plng",
    "wof:placetype":"venue"
},
  "geometry": {"coordinates":[-91.317598,44.36948],"type":"Point"}
}