{
  "type": "Feature",
  "properties": {
    "iso:country":"US",
    "sg:address":"5792 Courtland",
    "sg:city":"Oconomowoc",
    "sg:classifiers":[
        {
            "category":"Professional",
            "subcategory":"Management & Consulting",
            "type":"Services"
        }
    ],
    "sg:phone":"+1 262 567 7605",
    "sg:postcode":"53066",
    "sg:province":"WI",
    "wof:name":"Uhlmann Assoc",
    "wof:placetype":"venue"
},
  "geometry": {"coordinates":[-88.529005,43.125846],"type":"Point"}
}