{
  "type": "Feature",
  "properties": {
    "iso:country":"US",
    "sg:address":"4525 N Branch St",
    "sg:city":"Wabeno",
    "sg:classifiers":[
        {
            "category":"Shopping",
            "subcategory":"Hobbies, Toys, & Games",
            "type":"Retail Goods"
        }
    ],
    "sg:phone":"+1 715 473 6404",
    "sg:postcode":"54566",
    "sg:province":"WI",
    "wof:name":"Wagon Wheel",
    "wof:placetype":"venue"
},
  "geometry": {"coordinates":[-88.659927,45.43899],"type":"Point"}
}