{
  "type": "Feature",
  "properties": {
    "addr:full":"120 N Crosby Ave Janesville WI 53548",
    "addr:housenumber":"120",
    "addr:postcode":"53548",
    "addr:street":"N Crosby Ave",
    "iso:country":"US",
    "sg:address":"120 N Crosby Ave",
    "sg:city":"Janesville",
    "sg:classifiers":[
        {
            "category":"Freight",
            "type":"Transportation"
        },
        {
            "category":"Social Services",
            "type":"Services"
        }
    ],
    "sg:phone":"+1 608 757 0909",
    "sg:postcode":"53548",
    "sg:province":"WI",
    "sg:tags":[
        "post",
        "assembly",
        "parcel",
        "business"
    ],
    "wof:name":"Riverfront Inc",
    "wof:placetype":"venue"
},
  "geometry": {"coordinates":[-89.05165599999999,42.679199],"type":"Point"}
}