{
  "type": "Feature",
  "properties": {
    "iso:country":"US",
    "sg:address":"832 Goldfinch Ct",
    "sg:city":"La Valle",
    "sg:classifiers":[
        {
            "category":"Building & Trades",
            "subcategory":"Construction",
            "type":"Services"
        }
    ],
    "sg:phone":"+1 608 985 8141",
    "sg:postcode":"53941",
    "sg:province":"WI",
    "sg:tags":[
        "house"
    ],
    "wof:name":"Hahn Builders",
    "wof:placetype":"venue"
},
  "geometry": {"coordinates":[-90.094154,43.616796],"type":"Point"}
}