{
  "type": "Feature",
  "properties": {
    "iso:country":"US",
    "sg:address":"600 High St",
    "sg:city":"Wrightstown",
    "sg:classifiers":[
        {
            "category":"Education",
            "subcategory":"School",
            "type":"Public Place"
        }
    ],
    "sg:phone":"+1 920 532 0525",
    "sg:postcode":"54180",
    "sg:province":"WI",
    "sg:website":"www.wrightstown.k12.wi.us",
    "wof:name":"Wrightstown High School",
    "wof:placetype":"venue"
},
  "geometry": {"coordinates":[-88.151467,44.317094],"type":"Point"}
}