{
  "type": "Feature",
  "properties": {
    "iso:country":"US",
    "sg:address":"140 W Center St",
    "sg:city":"Whitewater",
    "sg:classifiers":[
        {
            "category":"Bars & Pubs",
            "type":"Food & Drink"
        }
    ],
    "sg:phone":"+1 262 473 4455",
    "sg:postcode":"53190",
    "sg:province":"WI",
    "sg:tags":[
        "drinking"
    ],
    "wof:name":"Hammers Hometown Tap",
    "wof:placetype":"venue"
},
  "geometry": {"coordinates":[-88.732355,42.833587],"type":"Point"}
}