{
  "type": "Feature",
  "properties": {
    "iso:country":"US",
    "sg:address":"2015 N 58th St",
    "sg:city":"Milwaukee",
    "sg:classifiers":[
        {
            "category":"Professional",
            "type":"Services"
        }
    ],
    "sg:phone":"+1 414 479 1826",
    "sg:postcode":"53208",
    "sg:province":"WI",
    "wof:name":"Davinci",
    "wof:placetype":"venue"
},
  "geometry": {"coordinates":[-87.985377,43.05615],"type":"Point"}
}