{
  "type": "Feature",
  "properties": {
    "addr:full":"3306 Rosewood Ln Racine WI 53404",
    "addr:housenumber":"3306",
    "addr:postcode":"53404",
    "addr:street":"Rosewood Ln",
    "iso:country":"US",
    "sg:address":"3306 Rosewood Ln",
    "sg:city":"Racine",
    "sg:classifiers":[
        {
            "category":"Professional",
            "subcategory":"Engineering",
            "type":"Services"
        }
    ],
    "sg:phone":"+1 262 639 4475",
    "sg:postcode":"53404",
    "sg:province":"WI",
    "sg:tags":[
        "engineer"
    ],
    "wof:name":"Redmon Engineering Company",
    "wof:placetype":"venue"
},
  "geometry": {"coordinates":[-87.823773,42.760084],"type":"Point"}
}