{
  "type": "Feature",
  "properties": {
    "iso:country":"US",
    "sg:address":"105 E Tyranena Park Rd",
    "sg:city":"Lake Mills",
    "sg:classifiers":[
        {
            "category":"Food & Beverages",
            "subcategory":"Groceries & Convenience Stores",
            "type":"Retail Goods"
        }
    ],
    "sg:phone":"+1 920 648 3033",
    "sg:postcode":"53551",
    "sg:province":"WI",
    "wof:name":"KWIK Trip",
    "wof:placetype":"venue"
},
  "geometry": {"coordinates":[-88.90633800000001,43.089575],"type":"Point"}
}