{
  "type": "Feature",
  "properties": {
    "addr:full":"5919 Oncken Rd Waunakee WI 53597",
    "addr:housenumber":"5919",
    "addr:postcode":"53597",
    "addr:street":"Oncken Rd",
    "iso:country":"US",
    "sg:address":"5919 Oncken Rd",
    "sg:city":"Waunakee",
    "sg:classifiers":[
        {
            "category":"Professional",
            "subcategory":"Engineering",
            "type":"Services"
        },
        {
            "category":"Manufacturing",
            "subcategory":"Tools & Machinery",
            "type":"Manufacturing & Wholesale Goods"
        }
    ],
    "sg:phone":"+1 608 836 1101",
    "sg:postcode":"53597",
    "sg:province":"WI",
    "sg:tags":[
        "mfg",
        "fountain",
        "beverage",
        "design",
        "engineer"
    ],
    "sg:website":"www.engrworkshop.com",
    "wof:name":"Protoco Engineering Inc",
    "wof:placetype":"venue"
},
  "geometry": {"coordinates":[-89.450661,43.137263],"type":"Point"}
}