{
  "type": "Feature",
  "properties": {
    "iso:country":"US",
    "sg:address":"2340 Rose St",
    "sg:city":"La Crosse",
    "sg:classifiers":[
        {
            "category":"Professional",
            "subcategory":"Accounting & Tax Preparation",
            "type":"Services"
        }
    ],
    "sg:phone":"+1 608 781 7505",
    "sg:postcode":"54603",
    "sg:province":"WI",
    "sg:tags":[
        "return",
        "filing"
    ],
    "sg:website":"www.hrblock.com",
    "wof:name":"H & R Block Tax Svc",
    "wof:placetype":"venue"
},
  "geometry": {"coordinates":[-91.242732,43.858187],"type":"Point"}
}