{
  "type": "Feature",
  "properties": {
    "iso:country":"US",
    "sg:address":"781 Tower Dr",
    "sg:city":"Fredonia",
    "sg:classifiers":[
        {
            "category":"Home & Garden",
            "subcategory":"Furniture",
            "type":"Retail Goods"
        }
    ],
    "sg:phone":"+1 262 692 2214",
    "sg:postcode":"53021",
    "sg:province":"WI",
    "sg:tags":[
        "equipment",
        "kitchen",
        "cabinet"
    ],
    "wof:name":"Uhlig Custom Counters",
    "wof:placetype":"venue"
},
  "geometry": {"coordinates":[-87.94766199999999,43.461604],"type":"Point"}
}