{
  "type": "Feature",
  "properties": {
    "addr:full":"1025 S Main St River Falls WI 54022",
    "addr:housenumber":"1025",
    "addr:postcode":"54022",
    "addr:street":"S Main St",
    "iso:country":"US",
    "sg:address":"1025 S Main St",
    "sg:city":"River Falls",
    "sg:classifiers":[
        {
            "category":"Restaurant",
            "type":"Food & Drink"
        }
    ],
    "sg:phone":"+1 715 425 9161",
    "sg:postcode":"54022",
    "sg:province":"WI",
    "sg:tags":[
        "eating"
    ],
    "wof:name":"Pizza Man",
    "wof:placetype":"venue"
},
  "geometry": {"coordinates":[-92.629417,44.847701],"type":"Point"}
}