{
  "type": "Feature",
  "properties": {
    "iso:country":"US",
    "sg:address":"626 Main St",
    "sg:city":"Darlington",
    "sg:classifiers":[
        {
            "category":"Real Estate",
            "subcategory":"Real Estate Agent",
            "type":"Services"
        }
    ],
    "sg:phone":"+1 608 776 4880",
    "sg:postcode":"53530",
    "sg:province":"WI",
    "sg:tags":[
        "housing",
        "authority"
    ],
    "wof:name":"Lafayette County Housing Auth",
    "wof:placetype":"venue"
},
  "geometry": {"coordinates":[-90.117794,42.682623],"type":"Point"}
}