{
  "type": "Feature",
  "properties": {
    "iso:country":"US",
    "sg:address":"4285 Porter Rd",
    "sg:city":"Bonduel",
    "sg:classifiers":[
        {
            "category":"Building & Trades",
            "subcategory":"Construction",
            "type":"Services"
        }
    ],
    "sg:phone":"+1 715 758 6213",
    "sg:postcode":"54107",
    "sg:province":"WI",
    "sg:tags":[
        "contractor"
    ],
    "wof:name":"Yoder Builders Leland",
    "wof:placetype":"venue"
},
  "geometry": {"coordinates":[-88.452343,44.734648],"type":"Point"}
}