{
  "type": "Feature",
  "properties": {
    "addr:full":"3595 S Mulberry Cir New Berlin WI 53146",
    "addr:housenumber":"3595",
    "addr:postcode":"53146",
    "addr:street":"S Mulberry Cir",
    "iso:country":"US",
    "sg:address":"3595 S Mulberry Cir",
    "sg:city":"New Berlin",
    "sg:classifiers":[
        {
            "category":"Building & Trades",
            "subcategory":"Construction",
            "type":"Services"
        }
    ],
    "sg:phone":"+1 414 587 4209",
    "sg:postcode":"53146",
    "sg:province":"WI",
    "sg:tags":[
        "carpentry",
        "contractor"
    ],
    "wof:name":"Gmh Construction Inc",
    "wof:placetype":"venue"
},
  "geometry": {"coordinates":[-88.16426,42.980353],"type":"Point"}
}