{
  "type": "Feature",
  "properties": {
    "iso:country":"US",
    "sg:address":"500 Windwood Cir",
    "sg:city":"Edgerton",
    "sg:classifiers":[
        {
            "category":"Building & Trades",
            "subcategory":"Construction",
            "type":"Services"
        }
    ],
    "sg:phone":"+1 608 884 3783",
    "sg:postcode":"53534",
    "sg:province":"WI",
    "sg:tags":[
        "house"
    ],
    "wof:name":"H & R Renovations LLC",
    "wof:placetype":"venue"
},
  "geometry": {"coordinates":[-89.067615,42.870833],"type":"Point"}
}