{
  "type": "Feature",
  "properties": {
    "iso:country":"US",
    "sg:address":"93 State Hwy 35",
    "sg:city":"Osceola",
    "sg:classifiers":[
        {
            "category":"Professional",
            "type":"Services"
        }
    ],
    "sg:phone":"+1 715 755 4888",
    "sg:postcode":"54020",
    "sg:province":"WI",
    "wof:name":"Raska Sewer Service",
    "wof:placetype":"venue"
},
  "geometry": {"coordinates":[-92.705735,45.31917],"type":"Point"}
}