{
  "type": "Feature",
  "properties": {
    "addr:full":"115 Lincoln Ave Rio WI 53960",
    "addr:housenumber":"115",
    "addr:postcode":"53960",
    "addr:street":"Lincoln Ave Rio",
    "iso:country":"US",
    "sg:address":"115 Lincoln Ave",
    "sg:city":"Rio",
    "sg:classifiers":[
        {
            "category":"Personal",
            "subcategory":"Barber",
            "type":"Services"
        }
    ],
    "sg:phone":"+1 920 992 3324",
    "sg:postcode":"53960",
    "sg:province":"WI",
    "wof:name":"Malibu's Barber Shop",
    "wof:placetype":"venue"
},
  "geometry": {"coordinates":[-89.239282,43.449236],"type":"Point"}
}