{
  "type": "Feature",
  "properties": {
    "iso:country":"US",
    "sg:address":"301 Nicolet Blvd",
    "sg:city":"Neenah",
    "sg:classifiers":[
        {
            "category":"Professional",
            "subcategory":"Lawyer & Legal Services",
            "type":"Services"
        }
    ],
    "sg:phone":"+1 920 725 8401",
    "sg:postcode":"54956",
    "sg:province":"WI",
    "sg:tags":[
        "attorney"
    ],
    "wof:name":"Adams & Woodrow SC",
    "wof:placetype":"venue"
},
  "geometry": {"coordinates":[-88.452404,44.193604],"type":"Point"}
}