{
  "type": "Feature",
  "properties": {
    "iso:country":"US",
    "sg:address":"1003 6th Ave",
    "sg:city":"Monroe",
    "sg:classifiers":[
        {
            "category":"Insurance",
            "subcategory":"Insurance Agent",
            "type":"Services"
        }
    ],
    "sg:phone":"+1 608 325 3416",
    "sg:postcode":"53566",
    "sg:province":"WI",
    "wof:name":"Green County Mutual Insurance",
    "wof:placetype":"venue"
},
  "geometry": {"coordinates":[-89.652748,42.601467],"type":"Point"}
}