{
  "type": "Feature",
  "properties": {
    "iso:country":"US",
    "sg:address":"1202 Ann St",
    "sg:city":"Madison",
    "sg:classifiers":[
        {
            "category":"Health Services",
            "subcategory":"Medical Lab",
            "type":"Services"
        }
    ],
    "sg:phone":"+1 608 258 1565",
    "sg:postcode":"53713",
    "sg:province":"WI",
    "sg:tags":[
        "prepackaged",
        "laboratory",
        "software"
    ],
    "sg:website":"www.kendricklabs.com",
    "wof:name":"Kendrick Laboratories Inc",
    "wof:placetype":"venue"
},
  "geometry": {"coordinates":[-89.404865,43.036477],"type":"Point"}
}