{
  "type": "Feature",
  "properties": {
    "iso:country":"US",
    "sg:address":"446 S Main St",
    "sg:city":"West Bend",
    "sg:classifiers":[
        {
            "category":"Personal",
            "subcategory":"Beauty Salon",
            "type":"Services"
        }
    ],
    "sg:phone":"+1 262 338 0033",
    "sg:postcode":"53095",
    "sg:province":"WI",
    "wof:name":"B J & Co",
    "wof:placetype":"venue"
},
  "geometry": {"coordinates":[-88.18113,43.418857],"type":"Point"}
}