{
  "type": "Feature",
  "properties": {
    "addr:full":"7930 N Eagle Rd Janesville WI 53548",
    "addr:housenumber":"7930",
    "addr:postcode":"53548",
    "addr:street":"N Eagle Rd",
    "iso:country":"US",
    "sg:address":"7930 N Eagle Rd",
    "sg:city":"Janesville",
    "sg:classifiers":[
        {
            "category":"Farming",
            "subcategory":"Dairy Farm",
            "type":"Manufacturing & Wholesale Goods"
        }
    ],
    "sg:phone":"+1 608 884 6681",
    "sg:postcode":"53548",
    "sg:province":"WI",
    "wof:name":"Towns Farms Inc",
    "wof:placetype":"venue"
},
  "geometry": {"coordinates":[-89.17104999999999,42.774367],"type":"Point"}
}