{
  "type": "Feature",
  "properties": {
    "addr:full":"3620 Wilgus Ave Sheboygan WI 53081",
    "addr:housenumber":"3620",
    "addr:postcode":"53081",
    "addr:street":"Wilgus Ave",
    "iso:country":"US",
    "sg:address":"3620 Wilgus Ave",
    "sg:city":"Sheboygan",
    "sg:classifiers":[
        {
            "category":"Education",
            "subcategory":"College",
            "type":"Public Place"
        }
    ],
    "sg:phone":"+1 920 208 5888",
    "sg:postcode":"53081",
    "sg:province":"WI",
    "sg:tags":[
        "academic",
        "school"
    ],
    "sg:website":"www.gotoltc.edu",
    "wof:name":"Lakeshore Technical College",
    "wof:placetype":"venue"
},
  "geometry": {"coordinates":[-87.757212,43.76015],"type":"Point"}
}