{
  "type": "Feature",
  "properties": {
    "iso:country":"US",
    "sg:address":"112 Front St",
    "sg:city":"Beaver Dam",
    "sg:classifiers":[
        {
            "category":"Banks & Credit Unions",
            "subcategory":"Bank",
            "type":"Services"
        }
    ],
    "sg:phone":"+1 920 356 1200",
    "sg:postcode":"53916",
    "sg:province":"WI",
    "sg:tags":[
        "cashing",
        "check"
    ],
    "wof:name":"Speedy Loan",
    "wof:placetype":"venue"
},
  "geometry": {"coordinates":[-88.837108,43.456319],"type":"Point"}
}