{
  "type": "Feature",
  "properties": {
    "addr:full":"3603 W Oklahoma Ave Milwaukee WI 53215",
    "addr:housenumber":"3603",
    "addr:postcode":"53215",
    "addr:street":"W Oklahoma Ave",
    "iso:country":"US",
    "sg:address":"3603 W Oklahoma Ave",
    "sg:city":"Milwaukee",
    "sg:classifiers":[
        {
            "category":"Wholesale",
            "subcategory":"Durable Goods & Equipment",
            "type":"Manufacturing & Wholesale Goods"
        }
    ],
    "sg:phone":"+1 414 384 4448",
    "sg:postcode":"53215",
    "sg:province":"WI",
    "sg:tags":[
        "representative",
        "manufacturer"
    ],
    "wof:name":"Donald A Loss & Assoc",
    "wof:placetype":"venue"
},
  "geometry": {"coordinates":[-87.960509,42.988356],"type":"Point"}
}