{
  "type": "Feature",
  "properties": {
    "iso:country":"US",
    "sg:address":"681 Baeten Rd",
    "sg:city":"Green Bay",
    "sg:classifiers":[
        {
            "category":"Professional",
            "subcategory":"Research",
            "type":"Services"
        },
        {
            "category":"Professional",
            "subcategory":"Management & Consulting",
            "type":"Services"
        }
    ],
    "sg:phone":"+1 920 496 1960",
    "sg:postcode":"54304",
    "sg:province":"WI",
    "sg:tags":[
        "consultant",
        "market",
        "analysis",
        "business"
    ],
    "sg:website":"www.venturegb.com",
    "wof:name":"Venture Research Corporation",
    "wof:placetype":"venue"
},
  "geometry": {"coordinates":[-88.06876800000001,44.466604],"type":"Point"}
}