{
  "type": "Feature",
  "properties": {
    "iso:country":"US",
    "sg:address":"947 la Salle St",
    "sg:city":"Racine",
    "sg:classifiers":[
        {
            "category":"Social Services",
            "subcategory":"Child Care",
            "type":"Services"
        }
    ],
    "sg:phone":"+1 262 632 0879",
    "sg:postcode":"53404",
    "sg:province":"WI",
    "wof:name":"Silly Kids Day Care",
    "wof:placetype":"venue"
},
  "geometry": {"coordinates":[-87.835078,42.815574],"type":"Point"}
}