{
  "type": "Feature",
  "properties": {
    "iso:country":"US",
    "sg:address":"3322 Valley Creek Cir",
    "sg:city":"Middleton",
    "sg:classifiers":[
        {
            "category":"Real Estate",
            "subcategory":"Architect",
            "type":"Services"
        }
    ],
    "sg:phone":"+1 608 836 7479",
    "sg:postcode":"53562",
    "sg:province":"WI",
    "sg:tags":[
        "architectural"
    ],
    "wof:name":"Donald J Richards Architect",
    "wof:placetype":"venue"
},
  "geometry": {"coordinates":[-89.481934,43.111085],"type":"Point"}
}