{
  "type": "Feature",
  "properties": {
    "iso:country":"US",
    "sg:address":"2662 Co Rd D",
    "sg:city":"Clintonville",
    "sg:classifiers":[
        {
            "category":"Farming",
            "subcategory":"Dairy Farm",
            "type":"Manufacturing & Wholesale Goods"
        }
    ],
    "sg:phone":"+1 715 823 7931",
    "sg:postcode":"54929",
    "sg:province":"WI",
    "wof:name":"Schmidt Dairy",
    "wof:placetype":"venue"
},
  "geometry": {"coordinates":[-88.751874,44.688936],"type":"Point"}
}