{
  "type": "Feature",
  "properties": {
    "iso:country":"US",
    "sg:address":"208 W South St",
    "sg:city":"Beaver Dam",
    "sg:classifiers":[
        {
            "category":"Retail",
            "subcategory":"Auto Repair",
            "type":"Services"
        }
    ],
    "sg:phone":"+1 920 885 5010",
    "sg:postcode":"53916",
    "sg:province":"WI",
    "sg:tags":[
        "automotive"
    ],
    "wof:name":"Park Avenue Towing",
    "wof:placetype":"venue"
},
  "geometry": {"coordinates":[-88.841928,43.45102],"type":"Point"}
}