{
  "type": "Feature",
  "properties": {
    "addr:full":"4701 Weeden Creek Rd Sheboygan WI 53081",
    "addr:postcode":"4701;53081",
    "addr:street":"Weeden Creek Rd",
    "iso:country":"US",
    "sg:address":"4701 Weeden Creek Rd",
    "sg:city":"Sheboygan",
    "sg:classifiers":[
        {
            "category":"Building & Trades",
            "subcategory":"Construction",
            "type":"Services"
        }
    ],
    "sg:phone":"+1 920 458 1857",
    "sg:postcode":"53081",
    "sg:province":"WI",
    "sg:tags":[
        "contractor"
    ],
    "wof:name":"Cw Construction Inc",
    "wof:placetype":"venue"
},
  "geometry": {"coordinates":[-87.775221,43.703171],"type":"Point"}
}