{
  "type": "Feature",
  "properties": {
    "addr:full":"5730 W Capitol Dr Milwaukee WI 53216",
    "addr:housenumber":"5730",
    "addr:postcode":"53216",
    "addr:street":"W Capitol Dr",
    "iso:country":"US",
    "sg:address":"5730 W Capitol Dr",
    "sg:city":"Milwaukee",
    "sg:classifiers":[
        {
            "category":"Professional",
            "type":"Services"
        }
    ],
    "sg:phone":"+1 414 444 3689",
    "sg:postcode":"53216",
    "sg:province":"WI",
    "wof:name":"Aj Wright",
    "wof:placetype":"venue"
},
  "geometry": {"coordinates":[-87.98482799999999,43.090025],"type":"Point"}
}