{
  "type": "Feature",
  "properties": {
    "addr:full":"1037 Truman St Kimberly WI 54136",
    "addr:housenumber":"1037",
    "addr:postcode":"54136",
    "addr:street":"Truman St",
    "iso:country":"US",
    "sg:address":"1037 Truman St",
    "sg:city":"Kimberly",
    "sg:classifiers":[
        {
            "category":"Building & Trades",
            "subcategory":"Construction",
            "type":"Services"
        }
    ],
    "sg:phone":"+1 920 882 1116",
    "sg:postcode":"54136",
    "sg:province":"WI",
    "sg:tags":[
        "house",
        "builder",
        "home"
    ],
    "wof:name":"Royalty Homes LLC",
    "wof:placetype":"venue"
},
  "geometry": {"coordinates":[-88.350579,44.259411],"type":"Point"}
}