{
  "type": "Feature",
  "properties": {
    "iso:country":"US",
    "sg:address":"6009 Tower Ave",
    "sg:city":"Superior",
    "sg:classifiers":[
        {
            "category":"Building & Trades",
            "subcategory":"Equipment Rental",
            "type":"Services"
        }
    ],
    "sg:phone":"+1 715 392 5202",
    "sg:postcode":"54880",
    "sg:province":"WI",
    "sg:tags":[
        "yard"
    ],
    "wof:name":"Thompson Rental Inc",
    "wof:placetype":"venue"
},
  "geometry": {"coordinates":[-92.104364,46.665872],"type":"Point"}
}