{
  "type": "Feature",
  "properties": {
    "addr:full":"160 Milltown Ave W Milltown WI 54858",
    "addr:housenumber":"160",
    "addr:postcode":"54858",
    "addr:street":"Milltown Ave W",
    "iso:country":"US",
    "sg:address":"160 Milltown Ave W",
    "sg:city":"Milltown",
    "sg:classifiers":[
        {
            "category":"Recreation",
            "type":"Entertainment"
        }
    ],
    "sg:phone":"+1 715 825 3598",
    "sg:postcode":"54858",
    "sg:province":"WI",
    "sg:tags":[
        "amusement"
    ],
    "wof:name":"Milltown Ballpark",
    "wof:placetype":"venue"
},
  "geometry": {"coordinates":[-92.505703,45.524351],"type":"Point"}
}