{
  "type": "Feature",
  "properties": {
    "iso:country":"US",
    "sg:address":"115 Madison St",
    "sg:city":"Sauk City",
    "sg:classifiers":[
        {
            "category":"Organizations",
            "subcategory":"Religious Organization",
            "type":"Services"
        }
    ],
    "sg:phone":"+1 608 643 2449",
    "sg:postcode":"53583",
    "sg:province":"WI",
    "sg:tags":[
        "church"
    ],
    "wof:name":"Saint Aloysius Catholic Church",
    "wof:placetype":"venue"
},
  "geometry": {"coordinates":[-89.725131,43.281818],"type":"Point"}
}