{
  "type": "Feature",
  "properties": {
    "addr:full":"9120 W Hampton Ave Milwaukee WI 53225",
    "addr:housenumber":"9120",
    "addr:postcode":"53225",
    "addr:street":"W Hampton Ave",
    "iso:country":"US",
    "sg:address":"9120 W Hampton Ave",
    "sg:city":"Milwaukee",
    "sg:classifiers":[
        {
            "category":"Health Services",
            "subcategory":"Health Practitioner",
            "type":"Services"
        }
    ],
    "sg:phone":"+1 262 783 7778",
    "sg:postcode":"53225",
    "sg:province":"WI",
    "wof:name":"Academic & Family Services LLC",
    "wof:placetype":"venue"
},
  "geometry": {"coordinates":[-88.027213,43.105032],"type":"Point"}
}