{
  "type": "Feature",
  "properties": {
    "iso:country":"US",
    "sg:address":"8101 W Bottsford Ave",
    "sg:city":"Milwaukee",
    "sg:classifiers":[
        {
            "category":"Wholesale",
            "subcategory":"Computers",
            "type":"Manufacturing & Wholesale Goods"
        }
    ],
    "sg:phone":"+1 414 541 3317",
    "sg:postcode":"53220",
    "sg:province":"WI",
    "wof:name":"As & E Inc",
    "wof:placetype":"venue"
},
  "geometry": {"coordinates":[-88.015513,42.964233],"type":"Point"}
}