{
  "type": "Feature",
  "properties": {
    "iso:country":"US",
    "sg:address":"268 W 12th St",
    "sg:city":"Fond Du Lac",
    "sg:classifiers":[
        {
            "category":"Manufacturing",
            "subcategory":"Tobacco Products",
            "type":"Manufacturing & Wholesale Goods"
        }
    ],
    "sg:phone":"+1 920 907 8431",
    "sg:postcode":"54935",
    "sg:province":"WI",
    "sg:tags":[
        "cigarette",
        "cigar"
    ],
    "wof:name":"R J Reynolds Tobacco Co",
    "wof:placetype":"venue"
},
  "geometry": {"coordinates":[-88.457381,43.765366],"type":"Point"}
}