{
  "type": "Feature",
  "properties": {
    "iso:country":"US",
    "sg:address":"5910 US Hwy 51",
    "sg:city":"Mc Farland",
    "sg:classifiers":[
        {
            "category":"Personal",
            "subcategory":"Beauty Salon",
            "type":"Services"
        }
    ],
    "sg:phone":"+1 608 838 4106",
    "sg:postcode":"53558",
    "sg:province":"WI",
    "sg:tags":[
        "shop"
    ],
    "wof:name":"Todays Hair",
    "wof:placetype":"venue"
},
  "geometry": {"coordinates":[-89.302965,43.01348],"type":"Point"}
}