{
  "type": "Feature",
  "properties": {
    "iso:country":"US",
    "sg:address":"17787 Hammond Ln",
    "sg:city":"Galesville",
    "sg:classifiers":[
        {
            "category":"Farming",
            "subcategory":"Dairy Farm",
            "type":"Manufacturing & Wholesale Goods"
        }
    ],
    "sg:phone":"+1 608 539 3243",
    "sg:postcode":"54630",
    "sg:province":"WI",
    "wof:name":"Leland Wier",
    "wof:placetype":"venue"
},
  "geometry": {"coordinates":[-91.411636,44.09368],"type":"Point"}
}