{
  "type": "Feature",
  "properties": {
    "iso:country":"US",
    "sg:address":"5591 Co Rd Ff",
    "sg:city":"Merrill",
    "sg:classifiers":[
        {
            "category":"Real Estate",
            "subcategory":"Real Estate Agent",
            "type":"Services"
        }
    ],
    "sg:phone":"+1 715 536 6199",
    "sg:postcode":"54452",
    "sg:province":"WI",
    "sg:tags":[
        "appraiser",
        "business"
    ],
    "wof:name":"Schield Appraisal Service",
    "wof:placetype":"venue"
},
  "geometry": {"coordinates":[-89.699014,45.127114],"type":"Point"}
}