{
  "type": "Feature",
  "properties": {
    "addr:full":"1228 W South Park Ave Oshkosh WI 54902",
    "addr:housenumber":"1228",
    "addr:postcode":"54902",
    "addr:street":"W South Park Ave",
    "iso:country":"US",
    "sg:address":"1228 W South Park Ave",
    "sg:city":"Oshkosh",
    "sg:classifiers":[
        {
            "category":"Manufacturing",
            "subcategory":"Metals",
            "type":"Manufacturing & Wholesale Goods"
        }
    ],
    "sg:phone":"+1 920 233 4522",
    "sg:postcode":"54902",
    "sg:province":"WI",
    "sg:tags":[
        "plating"
    ],
    "wof:name":"Oshkosh Plating Inc",
    "wof:placetype":"venue"
},
  "geometry": {"coordinates":[-88.56255,44.004427],"type":"Point"}
}