{
  "type": "Feature",
  "properties": {
    "addr:full":"600 W Walnut St Milwaukee WI 53205",
    "addr:housenumber":"600",
    "addr:postcode":"53205",
    "addr:street":"W Walnut St",
    "iso:country":"US",
    "sg:address":"600 W Walnut St",
    "sg:city":"Milwaukee",
    "sg:classifiers":[
        {
            "category":"Education",
            "subcategory":"School",
            "type":"Public Place"
        }
    ],
    "sg:phone":"+1 414 562 1797",
    "sg:postcode":"53205",
    "sg:province":"WI",
    "sg:tags":[
        "high"
    ],
    "wof:name":"Cornerstone Achievement Inst",
    "wof:placetype":"venue"
},
  "geometry": {"coordinates":[-87.92009899999999,43.052561],"type":"Point"}
}