{
  "type": "Feature",
  "properties": {
    "addr:full":"919 Main St Bloomer WI 54724",
    "addr:housenumber":"919",
    "addr:postcode":"54724",
    "addr:street":"Main St",
    "iso:country":"US",
    "sg:address":"919 Main St",
    "sg:city":"Bloomer",
    "sg:classifiers":[
        {
            "category":"Wholesale",
            "subcategory":"Machinery & Supplies",
            "type":"Manufacturing & Wholesale Goods"
        }
    ],
    "sg:phone":"+1 715 568 2140",
    "sg:postcode":"54724",
    "sg:province":"WI",
    "sg:tags":[
        "farm",
        "equipment"
    ],
    "wof:name":"Swoboda Implement Inc",
    "wof:placetype":"venue"
},
  "geometry": {"coordinates":[-91.48894,45.106662],"type":"Point"}
}