{
  "type": "Feature",
  "properties": {
    "iso:country":"US",
    "sg:address":"6909 W North Ave",
    "sg:city":"Milwaukee",
    "sg:classifiers":[
        {
            "category":"Organizations",
            "subcategory":"Membership Organization",
            "type":"Services"
        }
    ],
    "sg:phone":"+1 414 771 9400",
    "sg:postcode":"53213",
    "sg:province":"WI",
    "wof:name":"A L S Assoc",
    "wof:placetype":"venue"
},
  "geometry": {"coordinates":[-87.999681,43.060664],"type":"Point"}
}