{
  "type": "Feature",
  "properties": {
    "iso:country":"US",
    "sg:address":"1375 Carrington Ln",
    "sg:city":"De Pere",
    "sg:classifiers":[
        {
            "category":"Building & Trades",
            "subcategory":"Electrical",
            "type":"Services"
        }
    ],
    "sg:phone":"+1 920 819 4084",
    "sg:postcode":"54115",
    "sg:province":"WI",
    "sg:tags":[
        "electrical",
        "contractor"
    ],
    "wof:name":"J & M Electric",
    "wof:placetype":"venue"
},
  "geometry": {"coordinates":[-88.096327,44.43158],"type":"Point"}
}