{
  "type": "Feature",
  "properties": {
    "addr:full":"9696 Evergreen Ln Merrillan WI 54754",
    "addr:housenumber":"9696",
    "addr:postcode":"54754",
    "addr:street":"Evergreen Ln",
    "iso:country":"US",
    "sg:address":"9696 Evergreen Ln",
    "sg:city":"Merrillan",
    "sg:classifiers":[
        {
            "category":"Retail",
            "subcategory":"Auto Repair",
            "type":"Services"
        }
    ],
    "sg:phone":"+1 715 333 7250",
    "sg:postcode":"54754",
    "sg:province":"WI",
    "sg:tags":[
        "automotive"
    ],
    "wof:name":"Staz Works",
    "wof:placetype":"venue"
},
  "geometry": {"coordinates":[-90.799627,44.410855],"type":"Point"}
}