{
  "type": "Feature",
  "properties": {
    "addr:full":"205 Pine St Pepin WI 54759",
    "addr:housenumber":"205",
    "addr:postcode":"54759",
    "addr:street":"Pine St",
    "iso:country":"US",
    "sg:address":"205 Pine St",
    "sg:city":"Pepin",
    "sg:classifiers":[
        {
            "category":"Place Of Worship",
            "subcategory":"Church",
            "type":"Public Place"
        },
        {
            "category":"Place Of Worship",
            "type":"Public Place"
        }
    ],
    "sg:phone":"+1 715 442 3213",
    "sg:postcode":"54759",
    "sg:province":"WI",
    "sg:tags":[
        "covenant",
        "lutheran",
        "churches-covenant",
        "churches-evangelical",
        "churches-lutheran-evangelical",
        "america",
        "churches-lutheran"
    ],
    "wof:name":"Immanuel Evangelical Lutheran Church",
    "wof:placetype":"venue"
},
  "geometry": {"coordinates":[-92.14952599999999,44.44041],"type":"Point"}
}