{
  "type": "Feature",
  "properties": {
    "iso:country":"US",
    "sg:address":"4509 White Aspen Rd",
    "sg:city":"Madison",
    "sg:classifiers":[
        {
            "category":"Building & Trades",
            "subcategory":"Construction",
            "type":"Services"
        }
    ],
    "sg:phone":"+1 608 241 3048",
    "sg:postcode":"53704",
    "sg:province":"WI",
    "sg:tags":[
        "house"
    ],
    "wof:name":"S&S Home Repair LLC",
    "wof:placetype":"venue"
},
  "geometry": {"coordinates":[-89.392139,43.143627],"type":"Point"}
}