{
  "type": "Feature",
  "properties": {
    "addr:full":"3027 Walden Cir Waukesha WI 53188",
    "addr:housenumber":"3027",
    "addr:postcode":"53188",
    "addr:street":"Walden Cir",
    "iso:country":"US",
    "sg:address":"3027 Walden Cir",
    "sg:city":"Waukesha",
    "sg:classifiers":[
        {
            "category":"Real Estate",
            "subcategory":"Real Estate Agent",
            "type":"Services"
        }
    ],
    "sg:phone":"+1 262 544 9675",
    "sg:postcode":"53188",
    "sg:province":"WI",
    "wof:name":"Crestwood Homes Wisconsin LLC",
    "wof:placetype":"venue"
},
  "geometry": {"coordinates":[-88.280868,43.0129],"type":"Point"}
}