{
  "type": "Feature",
  "properties": {
    "iso:country":"US",
    "sg:address":"1343 S Lincoln St",
    "sg:city":"Shawano",
    "sg:classifiers":[
        {
            "category":"Retail",
            "subcategory":"Repair Shop",
            "type":"Services"
        }
    ],
    "sg:phone":"+1 715 524 3858",
    "sg:postcode":"54166",
    "sg:province":"WI",
    "sg:tags":[
        "taxidermist"
    ],
    "wof:name":"Tim's Taxidermy",
    "wof:placetype":"venue"
},
  "geometry": {"coordinates":[-88.603759,44.765077],"type":"Point"}
}