{
  "type": "Feature",
  "properties": {
    "addr:full":"19544 103rd St Bristol WI 53104",
    "addr:housenumber":"19544",
    "addr:postcode":"53104",
    "addr:street":"103Rd St",
    "iso:country":"US",
    "sg:address":"19544 103rd St",
    "sg:city":"Bristol",
    "sg:classifiers":[
        {
            "category":"Wholesale",
            "subcategory":"Machinery & Supplies",
            "type":"Manufacturing & Wholesale Goods"
        }
    ],
    "sg:phone":"+1 262 857 2924",
    "sg:postcode":"53104",
    "sg:province":"WI",
    "sg:tags":[
        "equipment",
        "ride",
        "park",
        "amusement"
    ],
    "wof:name":"ATON",
    "wof:placetype":"venue"
},
  "geometry": {"coordinates":[-88.043453,42.525943],"type":"Point"}
}