{
  "type": "Feature",
  "properties": {
    "iso:country":"US",
    "sg:address":"1818 230th Ave",
    "sg:city":"Luck",
    "sg:classifiers":[
        {
            "category":"Building & Trades",
            "subcategory":"Construction",
            "type":"Services"
        }
    ],
    "sg:phone":"+1 715 825 4442",
    "sg:postcode":"54853",
    "sg:province":"WI",
    "sg:tags":[
        "house"
    ],
    "wof:name":"Hoverman Construction",
    "wof:placetype":"venue"
},
  "geometry": {"coordinates":[-92.532645,45.541142],"type":"Point"}
}