{
  "type": "Feature",
  "properties": {
    "iso:country":"US",
    "sg:address":"600 N Adams St",
    "sg:city":"Green Bay",
    "sg:classifiers":[
        {
            "category":"Banks & Credit Unions",
            "subcategory":"Bank",
            "type":"Services"
        }
    ],
    "sg:phone":"+1 920 433 1784",
    "sg:postcode":"54301",
    "sg:province":"WI",
    "wof:name":"Service Credit Union",
    "wof:placetype":"venue"
},
  "geometry": {"coordinates":[-88.011529,44.518112],"type":"Point"}
}