{
  "type": "Feature",
  "properties": {
    "addr:full":"2187 W J St Sparta WI 54656",
    "addr:housenumber":"2187",
    "addr:postcode":"54656",
    "addr:street":"W J St",
    "iso:country":"US",
    "sg:address":"2187 W J St",
    "sg:city":"Sparta",
    "sg:classifiers":[
        {
            "category":"Government",
            "subcategory":"Office",
            "type":"Public Place"
        }
    ],
    "sg:phone":"+1 608 388 5527",
    "sg:postcode":"54656",
    "sg:province":"WI",
    "sg:tags":[
        "recreational",
        "activity"
    ],
    "wof:name":"Army and Air Force Exch Svc",
    "wof:placetype":"venue"
},
  "geometry": {"coordinates":[-90.700664,44.029014],"type":"Point"}
}