{
  "type": "Feature",
  "properties": {
    "iso:country":"US",
    "sg:address":"191 Vincent Cir",
    "sg:city":"Beaver Dam",
    "sg:classifiers":[
        {
            "category":"Retail",
            "subcategory":"Laundry & Dry Cleaning",
            "type":"Services"
        }
    ],
    "sg:phone":"+1 920 887 0074",
    "sg:postcode":"53916",
    "sg:province":"WI",
    "wof:name":"Aok Carpet Cleaning & Dye LLC",
    "wof:placetype":"venue"
},
  "geometry": {"coordinates":[-88.83739,43.442959],"type":"Point"}
}