{
  "type": "Feature",
  "properties": {
    "iso:country":"US",
    "sg:address":"2616 E Lexington Blvd",
    "sg:city":"Eau Claire",
    "sg:classifiers":[
        {
            "category":"Building & Trades",
            "subcategory":"Construction",
            "type":"Services"
        }
    ],
    "sg:phone":"+1 715 832 2319",
    "sg:postcode":"54701",
    "sg:province":"WI",
    "sg:tags":[
        "ope",
        "nonresidential"
    ],
    "wof:name":"Pathos Properties",
    "wof:placetype":"venue"
},
  "geometry": {"coordinates":[-91.46335999999999,44.792808],"type":"Point"}
}