{
  "type": "Feature",
  "properties": {
    "addr:full":"431 Union St River Falls WI 54022",
    "addr:housenumber":"431",
    "addr:postcode":"54022",
    "addr:street":"Union St",
    "iso:country":"US",
    "sg:address":"431 Union St",
    "sg:city":"River Falls",
    "sg:classifiers":[
        {
            "category":"Building & Trades",
            "subcategory":"Cleaning & Sanitation",
            "type":"Services"
        }
    ],
    "sg:phone":"+1 715 425 6360",
    "sg:postcode":"54022",
    "sg:province":"WI",
    "sg:tags":[
        "maintenance"
    ],
    "wof:name":"ServiceMaster",
    "wof:placetype":"venue"
},
  "geometry": {"coordinates":[-92.619046,44.864237],"type":"Point"}
}