{
  "type": "Feature",
  "properties": {
    "iso:country":"US",
    "sg:address":"4941 Bakertown Dr",
    "sg:city":"Sullivan",
    "sg:classifiers":[
        {
            "category":"Farming",
            "subcategory":"Farm",
            "type":"Manufacturing & Wholesale Goods"
        }
    ],
    "sg:phone":"+1 262 593 2623",
    "sg:postcode":"53178",
    "sg:province":"WI",
    "sg:tags":[
        "crop",
        "general"
    ],
    "wof:name":"Duesterbeck Farms LLC",
    "wof:placetype":"venue"
},
  "geometry": {"coordinates":[-88.602675,43.023405],"type":"Point"}
}