{
  "type": "Feature",
  "properties": {
    "iso:country":"US",
    "sg:address":"2195 255th St",
    "sg:city":"St Croix Falls",
    "sg:classifiers":[
        {
            "category":"Home & Garden",
            "subcategory":"Household Appliances",
            "type":"Retail Goods"
        }
    ],
    "sg:phone":"+1 715 483 1020",
    "sg:postcode":"54024",
    "sg:province":"WI",
    "sg:tags":[
        "cleaners",
        "vacuum"
    ],
    "wof:name":"Rainbow Vacuum Cleaners",
    "wof:placetype":"venue"
},
  "geometry": {"coordinates":[-92.68257,45.521726],"type":"Point"}
}