{
  "type": "Feature",
  "properties": {
    "iso:country":"US",
    "sg:address":"318 Main St",
    "sg:city":"Luxemburg",
    "sg:classifiers":[
        {
            "category":"Education",
            "subcategory":"School",
            "type":"Public Place"
        }
    ],
    "sg:phone":"+1 920 845 2371",
    "sg:postcode":"54217",
    "sg:province":"WI",
    "wof:name":"Luxemburg-Casco Elementary",
    "wof:placetype":"venue"
},
  "geometry": {"coordinates":[-87.703333,44.543025],"type":"Point"}
}