{
  "type": "Feature",
  "properties": {
    "iso:country":"US",
    "sg:address":"8539 N Reedsburg Rd",
    "sg:city":"Reedsburg",
    "sg:classifiers":[
        {
            "category":"Freight",
            "type":"Transportation"
        }
    ],
    "sg:phone":"+1 608 524 4611",
    "sg:postcode":"53959",
    "sg:province":"WI",
    "sg:tags":[
        "hauling",
        "trucking"
    ],
    "wof:name":"LBS Expediting Svc",
    "wof:placetype":"venue"
},
  "geometry": {"coordinates":[-89.89478099999999,43.540136],"type":"Point"}
}