{
  "type": "Feature",
  "properties": {
    "addr:full":"804 26th St Chetek WI 54728",
    "addr:housenumber":"804",
    "addr:postcode":"54728",
    "addr:street":"26Th St",
    "iso:country":"US",
    "sg:address":"804 26th St",
    "sg:city":"Chetek",
    "sg:classifiers":[
        {
            "category":"Travel",
            "subcategory":"Hotels & Motels",
            "type":"Entertainment"
        }
    ],
    "sg:phone":"+1 715 924 4515",
    "sg:postcode":"54728",
    "sg:province":"WI",
    "sg:tags":[
        "resort"
    ],
    "wof:name":"Crimson Hue Resort",
    "wof:placetype":"venue"
},
  "geometry": {"coordinates":[-91.622005,45.321704],"type":"Point"}
}