{
  "type": "Feature",
  "properties": {
    "iso:country":"US",
    "sg:address":"2333 Jourdain Ln",
    "sg:city":"Green Bay",
    "sg:classifiers":[
        {
            "category":"Professional",
            "subcategory":"Management & Consulting",
            "type":"Services"
        }
    ],
    "sg:phone":"+1 920 436 0542",
    "sg:postcode":"54301",
    "sg:province":"WI",
    "sg:tags":[
        "business"
    ],
    "wof:name":"Total Quality Systems LLC",
    "wof:placetype":"venue"
},
  "geometry": {"coordinates":[-88.022815,44.477853],"type":"Point"}
}