{
  "type": "Feature",
  "properties": {
    "iso:country":"US",
    "sg:address":"5332 Servais Rd",
    "sg:city":"New Franken",
    "sg:classifiers":[
        {
            "category":"Building & Trades",
            "subcategory":"Construction",
            "type":"Services"
        }
    ],
    "sg:phone":"+1 920 866 3137",
    "sg:postcode":"54229",
    "sg:province":"WI",
    "sg:tags":[
        "hanging",
        "contractor"
    ],
    "wof:name":"Basten Painting Service",
    "wof:placetype":"venue"
},
  "geometry": {"coordinates":[-87.81366300000001,44.603612],"type":"Point"}
}