{
  "type": "Feature",
  "properties": {
    "addr:full":"1305 Rutledge St Madison WI 53703",
    "addr:housenumber":"1305",
    "addr:postcode":"53703",
    "addr:street":"Rutledge St",
    "iso:country":"US",
    "sg:address":"1305 Rutledge St",
    "sg:city":"Madison",
    "sg:classifiers":[
        {
            "category":"Professional",
            "subcategory":"Engineering",
            "type":"Services"
        }
    ],
    "sg:phone":"+1 608 255 5517",
    "sg:postcode":"53703",
    "sg:province":"WI",
    "sg:tags":[
        "consulting",
        "computer"
    ],
    "wof:name":"S A Technology",
    "wof:placetype":"venue"
},
  "geometry": {"coordinates":[-89.358197,43.083703],"type":"Point"}
}