{
  "type": "Feature",
  "properties": {
    "iso:country":"US",
    "sg:address":"505 S Green Bay Rd",
    "sg:city":"Neenah",
    "sg:classifiers":[
        {
            "category":"Retail",
            "subcategory":"Car Wash",
            "type":"Services"
        }
    ],
    "sg:phone":"+1 920 727 9991",
    "sg:postcode":"54956",
    "sg:province":"WI",
    "sg:tags":[
        "polishing",
        "washing"
    ],
    "wof:name":"Best Wash Of Neenah",
    "wof:placetype":"venue"
},
  "geometry": {"coordinates":[-88.485156,44.179732],"type":"Point"}
}