{
  "type": "Feature",
  "properties": {
    "addr:full":"321 Barney St Waukesha WI 53186",
    "addr:housenumber":"321",
    "addr:postcode":"53186",
    "addr:street":"Barney St",
    "iso:country":"US",
    "sg:address":"321 Barney St",
    "sg:city":"Waukesha",
    "sg:classifiers":[
        {
            "category":"Professional",
            "subcategory":"Management & Consulting",
            "type":"Services"
        }
    ],
    "sg:phone":"+1 262 574 1225",
    "sg:postcode":"53186",
    "sg:province":"WI",
    "sg:tags":[
        "environmental",
        "planning",
        "education"
    ],
    "wof:name":"International Envmtl MGT Svcs",
    "wof:placetype":"venue"
},
  "geometry": {"coordinates":[-88.224853,43.006595],"type":"Point"}
}