{
  "type": "Feature",
  "properties": {
    "iso:country":"US",
    "sg:address":"125 17th St S",
    "sg:city":"La Crosse",
    "sg:classifiers":[
        {
            "category":"Travel",
            "subcategory":"Travel Agent",
            "type":"Entertainment"
        }
    ],
    "sg:phone":"+1 608 785 0095",
    "sg:postcode":"54601",
    "sg:province":"WI",
    "sg:tags":[
        "agency"
    ],
    "wof:name":"Lakeshore Travel Agency",
    "wof:placetype":"venue"
},
  "geometry": {"coordinates":[-91.230909,43.810499],"type":"Point"}
}