{
  "type": "Feature",
  "properties": {
    "iso:country":"US",
    "sg:address":"115 W Park St",
    "sg:city":"New Lisbon",
    "sg:classifiers":[
        {
            "category":"Education",
            "subcategory":"Library",
            "type":"Public Place"
        }
    ],
    "sg:phone":"+1 608 562 3213",
    "sg:postcode":"53950",
    "sg:province":"WI",
    "wof:name":"New Lisbon Public Library",
    "wof:placetype":"venue"
},
  "geometry": {"coordinates":[-90.167283,43.877263],"type":"Point"}
}