{
  "type": "Feature",
  "properties": {
    "iso:country":"US",
    "sg:address":"822 4th St",
    "sg:city":"Beloit",
    "sg:classifiers":[
        {
            "category":"Autos & Motor Vehicles",
            "subcategory":"Auto Supplies",
            "type":"Retail Goods"
        }
    ],
    "sg:phone":"+1 608 365 7747",
    "sg:postcode":"53511",
    "sg:province":"WI",
    "wof:name":"Big A Auto Parts",
    "wof:placetype":"venue"
},
  "geometry": {"coordinates":[-89.037986,42.505538],"type":"Point"}
}