{
  "type": "Feature",
  "properties": {
    "iso:country":"US",
    "sg:address":"5168 N Hollywood Ave",
    "sg:city":"Milwaukee",
    "sg:classifiers":[
        {
            "category":"Personal",
            "subcategory":"Barber",
            "type":"Services"
        }
    ],
    "sg:phone":"+1 414 964 4080",
    "sg:postcode":"53217",
    "sg:province":"WI",
    "sg:tags":[
        "shop",
        "beauty"
    ],
    "wof:name":"Haases Hair Imporium",
    "wof:placetype":"venue"
},
  "geometry": {"coordinates":[-87.903217,43.109979],"type":"Point"}
}