{
  "type": "Feature",
  "properties": {
    "iso:country":"US",
    "sg:address":"322 Fremont St",
    "sg:city":"Fond Du Lac",
    "sg:classifiers":[
        {
            "category":"Home & Garden",
            "subcategory":"Garden Supply",
            "type":"Retail Goods"
        }
    ],
    "sg:phone":"+1 920 922 3222",
    "sg:postcode":"54935",
    "sg:province":"WI",
    "sg:tags":[
        "fertilizer"
    ],
    "wof:name":"Norm's Ag Svc",
    "wof:placetype":"venue"
},
  "geometry": {"coordinates":[-88.458287,43.764168],"type":"Point"}
}