{
  "type": "Feature",
  "properties": {
    "iso:country":"US",
    "sg:address":"190 Gardner Ave",
    "sg:city":"Burlington",
    "sg:classifiers":[
        {
            "category":"Health Services",
            "subcategory":"Doctor",
            "type":"Services"
        }
    ],
    "sg:phone":"+1 262 763 3012",
    "sg:postcode":"53105",
    "sg:province":"WI",
    "sg:tags":[
        "dental"
    ],
    "wof:name":"Anthony J Rio DDS SC",
    "wof:placetype":"venue"
},
  "geometry": {"coordinates":[-88.278914,42.670541],"type":"Point"}
}