{
  "type": "Feature",
  "properties": {
    "iso:country":"US",
    "sg:address":"910 Augusta St",
    "sg:city":"Linden",
    "sg:classifiers":[
        {
            "category":"Shopping",
            "type":"Retail Goods"
        }
    ],
    "sg:phone":"+1 608 623 2284",
    "sg:postcode":"53553",
    "sg:province":"WI",
    "sg:tags":[
        "merchandise"
    ],
    "wof:name":"Peddler Creek General Store LL",
    "wof:placetype":"venue"
},
  "geometry": {"coordinates":[-90.277001,42.921598],"type":"Point"}
}