{
  "type": "Feature",
  "properties": {
    "iso:country":"US",
    "sg:address":"222 N Bell St",
    "sg:city":"Fond Du Lac",
    "sg:classifiers":[
        {
            "category":"Shopping",
            "subcategory":"Bicycles & Sporting Goods",
            "type":"Retail Goods"
        }
    ],
    "sg:phone":"+1 920 923 6411",
    "sg:postcode":"54935",
    "sg:province":"WI",
    "wof:name":"Sticks & Strings Archery",
    "wof:placetype":"venue"
},
  "geometry": {"coordinates":[-88.465861,43.785483],"type":"Point"}
}