{
  "type": "Feature",
  "properties": {
    "iso:country":"US",
    "sg:address":"637 Perkins Dr",
    "sg:city":"Mukwonago",
    "sg:classifiers":[
        {
            "category":"Retail",
            "subcategory":"Repair Shop",
            "type":"Services"
        }
    ],
    "sg:phone":"+1 262 363 2919",
    "sg:postcode":"53149",
    "sg:province":"WI",
    "sg:tags":[
        "truck"
    ],
    "wof:name":"Industrial Truck Repair Inc",
    "wof:placetype":"venue"
},
  "geometry": {"coordinates":[-88.321923,42.865376],"type":"Point"}
}