{
  "type": "Feature",
  "properties": {
    "iso:country":"US",
    "sg:address":"21875 Doral Rd",
    "sg:city":"Waukesha",
    "sg:classifiers":[
        {
            "category":"Manufacturing",
            "subcategory":"Printing",
            "type":"Manufacturing & Wholesale Goods"
        }
    ],
    "sg:phone":"+1 262 782 1470",
    "sg:postcode":"53186",
    "sg:province":"WI",
    "sg:tags":[
        "commercial"
    ],
    "sg:website":"www.lang.com",
    "wof:name":"Miller-O'Connell Corp",
    "wof:placetype":"venue"
},
  "geometry": {"coordinates":[-88.179361,43.041885],"type":"Point"}
}