{
  "type": "Feature",
  "properties": {
    "iso:country":"US",
    "sg:address":"1927 Main St",
    "sg:city":"Green Bay",
    "sg:classifiers":[
        {
            "category":"Home & Garden",
            "subcategory":"Household Appliances",
            "type":"Retail Goods"
        }
    ],
    "sg:phone":"+1 920 465 9333",
    "sg:postcode":"54302",
    "sg:province":"WI",
    "sg:tags":[
        "cleaners",
        "vacuum"
    ],
    "sg:website":"www.a1vacuumcenter.com",
    "wof:name":"A-1 Vacuum Cleaner Inc",
    "wof:placetype":"venue"
},
  "geometry": {"coordinates":[-87.974399,44.490831],"type":"Point"}
}