{
  "type": "Feature",
  "properties": {
    "addr:full":"1302 Stieber Ave Marathon WI 54448",
    "addr:housenumber":"1302",
    "addr:postcode":"54448",
    "addr:street":"Stieber Ave",
    "iso:country":"US",
    "sg:address":"1302 Stieber Ave",
    "sg:city":"Marathon",
    "sg:classifiers":[
        {
            "category":"Professional",
            "type":"Services"
        }
    ],
    "sg:phone":"+1 715 443 2027",
    "sg:postcode":"54448",
    "sg:province":"WI",
    "wof:name":"Lorton F Stieber",
    "wof:placetype":"venue"
},
  "geometry": {"coordinates":[-89.86608200000001,44.944666],"type":"Point"}
}