{
  "type": "Feature",
  "properties": {
    "addr:full":"1922 S 59th St Milwaukee WI 53219",
    "addr:housenumber":"1922",
    "addr:postcode":"53219",
    "addr:street":"S 59Th St",
    "iso:country":"US",
    "sg:address":"1922 S 59th St",
    "sg:city":"Milwaukee",
    "sg:classifiers":[
        {
            "category":"Organizations",
            "subcategory":"Labor Organization",
            "type":"Services"
        }
    ],
    "sg:phone":"+1 414 321 1527",
    "sg:postcode":"53219",
    "sg:province":"WI",
    "sg:website":"http://www.uswa.org",
    "wof:name":"United Steel Workers of America Local 1527",
    "wof:placetype":"venue"
},
  "geometry": {"coordinates":[-87.98620699999999,43.009682],"type":"Point"}
}