{
  "type": "Feature",
  "properties": {
    "addr:full":"5154 Elm St Medford WI 54451",
    "addr:housenumber":"5154",
    "addr:postcode":"54451",
    "addr:street":"Elm St",
    "iso:country":"US",
    "sg:address":"5154 Elm St",
    "sg:city":"Medford",
    "sg:classifiers":[
        {
            "category":"Manufacturing",
            "subcategory":"Tools & Machinery",
            "type":"Manufacturing & Wholesale Goods"
        }
    ],
    "sg:phone":"+1 715 748 5799",
    "sg:postcode":"54451",
    "sg:province":"WI",
    "sg:tags":[
        "machine",
        "mfg"
    ],
    "wof:name":"Speciality Tool Machine",
    "wof:placetype":"venue"
},
  "geometry": {"coordinates":[-90.31001999999999,45.290455],"type":"Point"}
}