{
  "type": "Feature",
  "properties": {
    "iso:country":"US",
    "sg:address":"1805 9th Ave W",
    "sg:city":"Brodhead",
    "sg:classifiers":[
        {
            "category":"Manufacturing",
            "subcategory":"Tools & Machinery",
            "type":"Manufacturing & Wholesale Goods"
        }
    ],
    "sg:phone":"+1 608 897 8575",
    "sg:postcode":"53520",
    "sg:province":"WI",
    "sg:tags":[
        "machine",
        "shop"
    ],
    "wof:name":"Production Grinding & Mchng",
    "wof:placetype":"venue"
},
  "geometry": {"coordinates":[-89.38655900000001,42.61576],"type":"Point"}
}