{
  "type": "Feature",
  "properties": {
    "addr:full":"415 Co Rd A Marathon WI 54448",
    "addr:housenumber":"415",
    "addr:postcode":"54448",
    "addr:street":"Co Rd A",
    "iso:country":"US",
    "sg:address":"415 Co Rd A",
    "sg:city":"Marathon",
    "sg:classifiers":[
        {
            "category":"Farming",
            "subcategory":"Farm",
            "type":"Manufacturing & Wholesale Goods"
        }
    ],
    "sg:phone":"+1 715 257 7924",
    "sg:postcode":"54448",
    "sg:province":"WI",
    "wof:name":"Albrecht Family Farms",
    "wof:placetype":"venue"
},
  "geometry": {"coordinates":[-89.871078,45.047208],"type":"Point"}
}