{
  "type": "Feature",
  "properties": {
    "iso:country":"US",
    "sg:address":"1319 24th Ave",
    "sg:city":"Rice Lake",
    "sg:phone":"+1 715 822 2679",
    "sg:postcode":"54868",
    "sg:province":"WI",
    "sg:tags":[
        "farm",
        "corn",
        "grain",
        "cash"
    ],
    "wof:name":"Madison Acres",
    "wof:placetype":"venue"
},
  "geometry": {"coordinates":[-91.88574800000001,45.553111],"type":"Point"}
}