{
  "type": "Feature",
  "properties": {
    "addr:full":"5712 US Hwy 51 Mc Farland WI 53558",
    "addr:housenumber":"5712",
    "addr:postcode":"53558",
    "addr:street":"Us Hwy 51 Mc Farland",
    "iso:country":"US",
    "sg:address":"5712 US Hwy 51",
    "sg:city":"Mc Farland",
    "sg:classifiers":[
        {
            "category":"Home & Garden",
            "subcategory":"Carpets & Floor Coverings",
            "type":"Retail Goods"
        }
    ],
    "sg:phone":"+1 608 838 3000",
    "sg:postcode":"53558",
    "sg:province":"WI",
    "sg:tags":[
        "dealer",
        "rug"
    ],
    "wof:name":"Bisbee's Carpets",
    "wof:placetype":"venue"
},
  "geometry": {"coordinates":[-89.302143,43.015208],"type":"Point"}
}