{
  "type": "Feature",
  "properties": {
    "addr:full":"1525 Wisconsin Ave Grafton WI 53024",
    "addr:housenumber":"1525",
    "addr:postcode":"53024",
    "addr:street":"Wisconsin Ave",
    "iso:country":"US",
    "sg:address":"1525 Wisconsin Ave",
    "sg:city":"Grafton",
    "sg:classifiers":[
        {
            "category":"Shopping",
            "type":"Retail Goods"
        }
    ],
    "sg:phone":"+1 262 376 0729",
    "sg:postcode":"53024",
    "sg:province":"WI",
    "sg:tags":[
        "merchandise"
    ],
    "wof:name":"Weg Electric Motors Corp",
    "wof:placetype":"venue"
},
  "geometry": {"coordinates":[-87.952946,43.31681],"type":"Point"}
}