{
  "type": "Feature",
  "properties": {
    "iso:country":"US",
    "sg:address":"701 Somerset Dr",
    "sg:city":"Janesville",
    "sg:classifiers":[
        {
            "category":"Professional",
            "subcategory":"Business Services",
            "type":"Services"
        }
    ],
    "sg:phone":"+1 608 756 2671",
    "sg:postcode":"53546",
    "sg:province":"WI",
    "wof:name":"Mark Daniel Wittman",
    "wof:placetype":"venue"
},
  "geometry": {"coordinates":[-88.981927,42.692636],"type":"Point"}
}