{
  "type": "Feature",
  "properties": {
    "iso:country":"US",
    "sg:address":"4758 State Hwy 54",
    "sg:city":"Algoma",
    "sg:classifiers":[
        {
            "category":"Farming",
            "subcategory":"Dairy Farm",
            "type":"Manufacturing & Wholesale Goods"
        }
    ],
    "sg:phone":"+1 920 487 3652",
    "sg:postcode":"54201",
    "sg:province":"WI",
    "wof:name":"John Zeitler Dairy Farm",
    "wof:placetype":"venue"
},
  "geometry": {"coordinates":[-87.531869,44.590403],"type":"Point"}
}