{
  "type": "Feature",
  "properties": {
    "iso:country":"US",
    "sg:address":"710 E Mifflin St",
    "sg:city":"Madison",
    "sg:classifiers":[
        {
            "category":"Professional",
            "subcategory":"Computer Services",
            "type":"Services"
        }
    ],
    "sg:phone":"+1 608 268 3282",
    "sg:postcode":"53703",
    "sg:province":"WI",
    "sg:tags":[
        "related"
    ],
    "wof:name":"Stone & Najem Consulting Inc",
    "wof:placetype":"venue"
},
  "geometry": {"coordinates":[-89.37647,43.081817],"type":"Point"}
}