{
  "type": "Feature",
  "properties": {
    "iso:country":"US",
    "sg:address":"2911 Rapids Dr",
    "sg:city":"Racine",
    "sg:classifiers":[
        {
            "category":"Retail",
            "subcategory":"Veterinary Services",
            "type":"Services"
        }
    ],
    "sg:phone":"+1 262 634 3130",
    "sg:postcode":"53404",
    "sg:province":"WI",
    "wof:name":"Beechwood Veterinary Clinic",
    "wof:placetype":"venue"
},
  "geometry": {"coordinates":[-87.815641,42.750148],"type":"Point"}
}