{
  "type": "Feature",
  "properties": {
    "iso:country":"US",
    "sg:address":"844 Somerset Dr",
    "sg:city":"Janesville",
    "sg:classifiers":[
        {
            "category":"Retail",
            "subcategory":"Laundry & Dry Cleaning",
            "type":"Services"
        }
    ],
    "sg:phone":"+1 608 752 8347",
    "sg:postcode":"53546",
    "sg:province":"WI",
    "sg:tags":[
        "cleaners",
        "rug",
        "carpet"
    ],
    "wof:name":"Forster's Professional Clean",
    "wof:placetype":"venue"
},
  "geometry": {"coordinates":[-88.982578,42.696448],"type":"Point"}
}