{
  "type": "Feature",
  "properties": {
    "iso:country":"US",
    "sg:address":"219 N Washington St",
    "sg:city":"Green Bay",
    "sg:classifiers":[
        {
            "category":"Bars & Pubs",
            "type":"Food & Drink"
        }
    ],
    "sg:phone":"+1 920 433 0299",
    "sg:postcode":"54301",
    "sg:province":"WI",
    "sg:tags":[
        "drinking"
    ],
    "wof:name":"Maloney's Pub",
    "wof:placetype":"venue"
},
  "geometry": {"coordinates":[-88.014938,44.516097],"type":"Point"}
}