{
  "type": "Feature",
  "properties": {
    "iso:country":"US",
    "sg:address":"2205 Woodview Ct",
    "sg:city":"Madison",
    "sg:classifiers":[
        {
            "category":"Real Estate",
            "subcategory":"Real Estate Operator",
            "type":"Services"
        }
    ],
    "sg:phone":"+1 608 257 8926",
    "sg:postcode":"53713",
    "sg:province":"WI",
    "sg:tags":[
        "apartment"
    ],
    "wof:name":"Park Village Apartments",
    "wof:placetype":"venue"
},
  "geometry": {"coordinates":[-89.39275499999999,43.040186],"type":"Point"}
}