{
  "type": "Feature",
  "properties": {
    "iso:country":"US",
    "sg:address":"3712 50th St",
    "sg:city":"Kenosha",
    "sg:classifiers":[
        {
            "category":"Social Services",
            "type":"Services"
        }
    ],
    "sg:phone":"+1 262 657 6373",
    "sg:postcode":"53144",
    "sg:province":"WI",
    "sg:tags":[
        "youth",
        "organization",
        "center"
    ],
    "wof:name":"Boys & Girls Club Of Kenosha",
    "wof:placetype":"venue"
},
  "geometry": {"coordinates":[-87.85453,42.591264],"type":"Point"}
}