{
  "type": "Feature",
  "properties": {
    "iso:country":"US",
    "sg:address":"350 E Hiawatha Dr",
    "sg:city":"Wisconsin Dells",
    "sg:classifiers":[
        {
            "category":"Building & Trades",
            "subcategory":"Construction",
            "type":"Services"
        },
        {
            "category":"Travel",
            "subcategory":"Hotels & Motels",
            "type":"Entertainment"
        }
    ],
    "sg:phone":"+1 608 254 5253",
    "sg:postcode":"53965",
    "sg:province":"WI",
    "sg:tags":[
        "residential"
    ],
    "wof:name":"Wilderness On The Lake",
    "wof:placetype":"venue"
},
  "geometry": {"coordinates":[-89.787408,43.598731],"type":"Point"}
}