{
  "type": "Feature",
  "properties": {
    "iso:country":"US",
    "sg:address":"11408 US Hwy 12",
    "sg:city":"Sauk City",
    "sg:classifiers":[
        {
            "category":"Home & Garden",
            "subcategory":"Building Materials",
            "type":"Retail Goods"
        }
    ],
    "sg:phone":"+1 608 643 8007",
    "sg:postcode":"53583",
    "sg:province":"WI",
    "wof:name":"United Building Centers",
    "wof:placetype":"venue"
},
  "geometry": {"coordinates":[-89.740484,43.270996],"type":"Point"}
}