{
  "type": "Feature",
  "properties": {
    "iso:country":"US",
    "sg:address":"5285 N 124th St",
    "sg:city":"Butler",
    "sg:classifiers":[
        {
            "category":"Manufacturing",
            "subcategory":"Metals",
            "type":"Manufacturing & Wholesale Goods"
        }
    ],
    "sg:phone":"+1 262 781 8550",
    "sg:postcode":"53007",
    "sg:province":"WI",
    "sg:tags":[
        "machine",
        "screw",
        "product",
        "mfg"
    ],
    "wof:name":"A-Plus Machine Products Inc",
    "wof:placetype":"venue"
},
  "geometry": {"coordinates":[-88.06591,43.111971],"type":"Point"}
}