{
  "type": "Feature",
  "properties": {
    "iso:country":"US",
    "sg:address":"6041 US Hwy 18",
    "sg:city":"Jefferson",
    "sg:classifiers":[
        {
            "category":"Wholesale",
            "subcategory":"Machinery & Supplies",
            "type":"Manufacturing & Wholesale Goods"
        }
    ],
    "sg:phone":"+1 920 674 3464",
    "sg:postcode":"53549",
    "sg:province":"WI",
    "sg:tags":[
        "farm",
        "equipment",
        "implement",
        "repair"
    ],
    "wof:name":"Voeltz Implement Co",
    "wof:placetype":"venue"
},
  "geometry": {"coordinates":[-88.832859,43.006357],"type":"Point"}
}