{
  "type": "Feature",
  "properties": {
    "iso:country":"US",
    "sg:address":"5067 Clausen Rd",
    "sg:city":"Burlington",
    "sg:classifiers":[
        {
            "category":"Freight",
            "type":"Transportation"
        }
    ],
    "sg:phone":"+1 262 763 3471",
    "sg:postcode":"53105",
    "sg:province":"WI",
    "sg:tags":[
        "operator",
        "local",
        "trucking"
    ],
    "wof:name":"Jensen Trucking",
    "wof:placetype":"venue"
},
  "geometry": {"coordinates":[-88.374792,42.672447],"type":"Point"}
}