{
  "type": "Feature",
  "properties": {
    "addr:full":"216 S Main St Eagle River WI 54521",
    "addr:housenumber":"216",
    "addr:postcode":"54521",
    "addr:street":"S Main St",
    "iso:country":"US",
    "sg:address":"216 S Main St",
    "sg:city":"Eagle River",
    "sg:classifiers":[
        {
            "category":"Shopping",
            "type":"Retail Goods"
        }
    ],
    "sg:phone":"+1 715 479 6383",
    "sg:postcode":"54521",
    "sg:province":"WI",
    "sg:tags":[
        "art",
        "gallery",
        "dealer"
    ],
    "wof:name":"River Woods Gallery",
    "wof:placetype":"venue"
},
  "geometry": {"coordinates":[-89.250922,45.915198],"type":"Point"}
}