{
  "type": "Feature",
  "properties": {
    "addr:full":"6220 University Ave Middleton WI 53562",
    "addr:housenumber":"6220",
    "addr:postcode":"53562",
    "addr:street":"University Ave",
    "iso:country":"US",
    "sg:address":"6220 University Ave",
    "sg:city":"Middleton",
    "sg:classifiers":[
        {
            "category":"Professional",
            "type":"Services"
        },
        {
            "category":"Recreation",
            "type":"Entertainment"
        }
    ],
    "sg:phone":"+1 608 233 5425",
    "sg:postcode":"53562",
    "sg:province":"WI",
    "sg:tags":[
        "martial",
        "arts",
        "instruction"
    ],
    "wof:name":"Kicks Unlimited LLLLC",
    "wof:placetype":"venue"
},
  "geometry": {"coordinates":[-89.48662899999999,43.09009],"type":"Point"}
}