{
  "type": "Feature",
  "properties": {
    "iso:country":"US",
    "sg:address":"310 E Madison St",
    "sg:city":"Eau Claire",
    "sg:classifiers":[
        {
            "category":"Social Services",
            "type":"Services"
        }
    ],
    "sg:phone":"+1 715 833 0533",
    "sg:postcode":"54703",
    "sg:province":"WI",
    "sg:tags":[
        "youth",
        "organization",
        "center"
    ],
    "wof:name":"Lighthouse Youth Ctr & Mini",
    "wof:placetype":"venue"
},
  "geometry": {"coordinates":[-91.501979,44.816468],"type":"Point"}
}