{
  "type": "Feature",
  "properties": {
    "iso:country":"US",
    "sg:address":"11051 N Towne Square Rd",
    "sg:city":"Mequon",
    "sg:classifiers":[
        {
            "category":"Professional",
            "subcategory":"Management & Consulting",
            "type":"Services"
        }
    ],
    "sg:phone":"+1 262 241 5727",
    "sg:postcode":"53092",
    "sg:province":"WI",
    "sg:tags":[
        "consultant",
        "business"
    ],
    "wof:name":"CME Resources",
    "wof:placetype":"venue"
},
  "geometry": {"coordinates":[-87.925505,43.21935],"type":"Point"}
}