{
  "type": "Feature",
  "properties": {
    "iso:country":"US",
    "sg:address":"8758 W Fond du Lac Ave",
    "sg:city":"Milwaukee",
    "sg:classifiers":[
        {
            "category":"Retail",
            "subcategory":"Veterinary Services",
            "type":"Services"
        }
    ],
    "sg:phone":"+1 414 463 0323",
    "sg:postcode":"53225",
    "sg:province":"WI",
    "wof:name":"C J Gurneau",
    "wof:placetype":"venue"
},
  "geometry": {"coordinates":[-88.021113,43.125128],"type":"Point"}
}