{
  "type": "Feature",
  "properties": {
    "iso:country":"US",
    "sg:address":"2042 N Booth St",
    "sg:city":"Milwaukee",
    "sg:classifiers":[
        {
            "category":"Government",
            "subcategory":"Office",
            "type":"Public Place"
        }
    ],
    "sg:phone":"+1 414 350 7688",
    "sg:postcode":"53212",
    "sg:province":"WI",
    "sg:tags":[
        "car",
        "loading",
        "transportation",
        "unloading"
    ],
    "wof:name":"Baer Transport",
    "wof:placetype":"venue"
},
  "geometry": {"coordinates":[-87.904078,43.056942],"type":"Point"}
}