{
  "type": "Feature",
  "properties": {
    "addr:full":"5713 Piping Rock Rd Madison WI 53711",
    "addr:housenumber":"5713",
    "addr:postcode":"53711",
    "addr:street":"Piping Rock Rd",
    "iso:country":"US",
    "sg:address":"5713 Piping Rock Rd",
    "sg:city":"Madison",
    "sg:classifiers":[
        {
            "category":"Recreation",
            "type":"Entertainment"
        }
    ],
    "sg:phone":"+1 608 271 4614",
    "sg:postcode":"53711",
    "sg:province":"WI",
    "sg:tags":[
        "pool",
        "swimming"
    ],
    "wof:name":"Www Ridgewoodpool Com",
    "wof:placetype":"venue"
},
  "geometry": {"coordinates":[-89.479519,43.041421],"type":"Point"}
}