{
  "type": "Feature",
  "properties": {
    "addr:full":"5106 Academy Dr Madison WI 53716",
    "addr:housenumber":"5106",
    "addr:postcode":"53716",
    "addr:street":"Academy Dr",
    "iso:country":"US",
    "sg:address":"5106 Academy Dr",
    "sg:city":"Madison",
    "sg:classifiers":[
        {
            "category":"Education",
            "subcategory":"School",
            "type":"Public Place"
        }
    ],
    "sg:phone":"+1 608 204 1400",
    "sg:postcode":"53716",
    "sg:province":"WI",
    "wof:name":"Conrad Elvehjem Elementary",
    "wof:placetype":"venue"
},
  "geometry": {"coordinates":[-89.293488,43.078022],"type":"Point"}
}