{
  "type": "Feature",
  "properties": {
    "iso:country":"US",
    "sg:address":"4750 N 74th St",
    "sg:city":"Milwaukee",
    "sg:classifiers":[
        {
            "category":"Retail",
            "subcategory":"Auto Repair",
            "type":"Services"
        }
    ],
    "sg:phone":"+1 414 578 3355",
    "sg:postcode":"53218",
    "sg:province":"WI",
    "sg:tags":[
        "glass",
        "coating",
        "tinting"
    ],
    "wof:name":"Matt Krause Window Tinting",
    "wof:placetype":"venue"
},
  "geometry": {"coordinates":[-88.00461799999999,43.104973],"type":"Point"}
}