{
  "type": "Feature",
  "properties": {
    "iso:country":"US",
    "sg:address":"3220 Basler Ln",
    "sg:city":"Oshkosh",
    "sg:classifiers":[
        {
            "category":"Building & Trades",
            "subcategory":"Plumbing",
            "type":"Services"
        }
    ],
    "sg:phone":"+1 920 235 6951",
    "sg:postcode":"54901",
    "sg:province":"WI",
    "sg:tags":[
        "heating",
        "contractor"
    ],
    "wof:name":"Wesley Heating & Cooling",
    "wof:placetype":"venue"
},
  "geometry": {"coordinates":[-88.570499,44.058269],"type":"Point"}
}