{
  "type": "Feature",
  "properties": {
    "iso:country":"US",
    "sg:address":"1759 6th St",
    "sg:city":"Comstock",
    "sg:classifiers":[
        {
            "category":"Farming",
            "subcategory":"Dairy Farm",
            "type":"Manufacturing & Wholesale Goods"
        }
    ],
    "sg:phone":"+1 715 357 6391",
    "sg:postcode":"54826",
    "sg:province":"WI",
    "wof:name":"Daniel Neby",
    "wof:placetype":"venue"
},
  "geometry": {"coordinates":[-92.032405,45.45836],"type":"Point"}
}