{
  "type": "Feature",
  "properties": {
    "iso:country":"US",
    "sg:address":"613 N Randolph St",
    "sg:city":"Cuba City",
    "sg:classifiers":[
        {
            "category":"Wholesale",
            "subcategory":"Farm Supplies",
            "type":"Manufacturing & Wholesale Goods"
        }
    ],
    "sg:phone":"+1 608 744 7333",
    "sg:postcode":"53807",
    "sg:province":"WI",
    "sg:tags":[
        "bulb",
        "seed"
    ],
    "sg:website":"www.northgro.com",
    "wof:name":"North-Gro Seeds Inc",
    "wof:placetype":"venue"
},
  "geometry": {"coordinates":[-90.43436,42.612253],"type":"Point"}
}