{
  "type": "Feature",
  "properties": {
    "iso:country":"US",
    "sg:address":"7330 Botting Rd",
    "sg:city":"Racine",
    "sg:classifiers":[
        {
            "category":"Recreation",
            "type":"Entertainment"
        }
    ],
    "sg:phone":"+1 262 639 8500",
    "sg:postcode":"53402",
    "sg:province":"WI",
    "wof:name":"Lane Arbor Farm",
    "wof:placetype":"venue"
},
  "geometry": {"coordinates":[-87.85024,42.81988],"type":"Point"}
}