{
  "type": "Feature",
  "properties": {
    "iso:country":"US",
    "sg:address":"7610 Mineral Point Rd",
    "sg:city":"Madison",
    "sg:classifiers":[
        {
            "category":"Shopping",
            "subcategory":"Computers & Home Electronics",
            "type":"Retail Goods"
        }
    ],
    "sg:phone":"+1 608 833 4097",
    "sg:postcode":"53717",
    "sg:province":"WI",
    "sg:tags":[
        "game",
        "video"
    ],
    "wof:name":"Preplayed",
    "wof:placetype":"venue"
},
  "geometry": {"coordinates":[-89.514014,43.060654],"type":"Point"}
}