{
  "type": "Feature",
  "properties": {
    "iso:country":"US",
    "sg:address":"14810 Tannery Rd",
    "sg:city":"Mishicot",
    "sg:classifiers":[
        {
            "category":"Retail",
            "subcategory":"Repair Shop",
            "type":"Services"
        }
    ],
    "sg:phone":"+1 920 755 2953",
    "sg:postcode":"54228",
    "sg:province":"WI",
    "wof:name":"Roys Radio TV",
    "wof:placetype":"venue"
},
  "geometry": {"coordinates":[-87.583628,44.271579],"type":"Point"}
}