{
  "type": "Feature",
  "properties": {
    "addr:full":"333 S 108th St Milwaukee WI 53214",
    "addr:housenumber":"333",
    "addr:postcode":"53214",
    "addr:street":"S 108Th St",
    "iso:country":"US",
    "sg:address":"333 S 108th St",
    "sg:city":"Milwaukee",
    "sg:classifiers":[
        {
            "category":"Home & Garden",
            "subcategory":"Household Appliances",
            "type":"Retail Goods"
        },
        {
            "category":"Home & Garden",
            "subcategory":"Carpets & Floor Coverings",
            "type":"Retail Goods"
        },
        {
            "category":"Shopping",
            "subcategory":"Computers & Home Electronics",
            "type":"Retail Goods"
        },
        {
            "category":"Professional",
            "type":"Services"
        },
        {
            "category":"Home & Garden",
            "subcategory":"Furniture",
            "type":"Retail Goods"
        }
    ],
    "sg:phone":"+1 414 476 1574",
    "sg:postcode":"53214",
    "sg:province":"WI",
    "sg:tags":[
        "major",
        "theater",
        "material",
        "system",
        "mattress",
        "moving",
        "services-labor",
        "store"
    ],
    "sg:website":"http://www.colders.com",
    "wof:name":"Colder's",
    "wof:placetype":"venue"
},
  "geometry": {"coordinates":[-88.04779499999999,43.026098],"type":"Point"}
}