{
  "type": "Feature",
  "properties": {
    "iso:country":"US",
    "sg:address":"2017 Lathrop Ave",
    "sg:city":"Racine",
    "sg:classifiers":[
        {
            "category":"Manufacturing",
            "subcategory":"Printing",
            "type":"Manufacturing & Wholesale Goods"
        }
    ],
    "sg:phone":"+1 262 632 8855",
    "sg:postcode":"53405",
    "sg:province":"WI",
    "sg:tags":[
        "publisher"
    ],
    "sg:website":"www.naso.org",
    "wof:name":"Referee Enterprises Inc",
    "wof:placetype":"venue"
},
  "geometry": {"coordinates":[-87.825899,42.70447],"type":"Point"}
}