{
  "type": "Feature",
  "properties": {
    "iso:country":"US",
    "sg:address":"915 E Oklahoma Ave",
    "sg:city":"Milwaukee",
    "sg:classifiers":[
        {
            "category":"Organizations",
            "subcategory":"Religious Organization",
            "type":"Services"
        }
    ],
    "sg:phone":"+1 414 481 3530",
    "sg:postcode":"53207",
    "sg:province":"WI",
    "sg:tags":[
        "church"
    ],
    "sg:website":"www.ucc.org",
    "wof:name":"Christ Church",
    "wof:placetype":"venue"
},
  "geometry": {"coordinates":[-87.89705,42.988217],"type":"Point"}
}