{
  "type": "Feature",
  "properties": {
    "iso:country":"US",
    "sg:address":"3329 Sunset Rd",
    "sg:city":"Sheboygan",
    "sg:classifiers":[
        {
            "category":"Manufacturing",
            "subcategory":"Glass & Minerals",
            "type":"Manufacturing & Wholesale Goods"
        }
    ],
    "sg:phone":"+1 920 467 1605",
    "sg:postcode":"53085",
    "sg:province":"WI",
    "sg:tags":[
        "concrete",
        "brick",
        "prod",
        "block"
    ],
    "wof:name":"East Central Foundations",
    "wof:placetype":"venue"
},
  "geometry": {"coordinates":[-87.870449,43.754942],"type":"Point"}
}