{
  "type": "Feature",
  "properties": {
    "addr:full":"152 W Wisconsin Ave Milwaukee WI 53203",
    "addr:housenumber":"152",
    "addr:postcode":"53203",
    "addr:street":"W Wisconsin Ave",
    "iso:country":"US",
    "sg:address":"152 W Wisconsin Ave",
    "sg:city":"Milwaukee",
    "sg:classifiers":[
        {
            "category":"Restaurant",
            "type":"Food & Drink"
        }
    ],
    "sg:phone":"+1 414 287 0900",
    "sg:postcode":"53203",
    "sg:province":"WI",
    "sg:tags":[
        "management"
    ],
    "wof:name":"Global Restaurant Systems",
    "wof:placetype":"venue"
},
  "geometry": {"coordinates":[-87.912559,43.038803],"type":"Point"}
}