{
  "type": "Feature",
  "properties": {
    "iso:country":"US",
    "sg:address":"6838 Smock Valley Rd",
    "sg:city":"Monroe",
    "sg:classifiers":[
        {
            "category":"Farming",
            "subcategory":"Dairy Farm",
            "type":"Manufacturing & Wholesale Goods"
        }
    ],
    "sg:phone":"+1 608 328 2811",
    "sg:postcode":"53566",
    "sg:province":"WI",
    "wof:name":"Ronald Nipple",
    "wof:placetype":"venue"
},
  "geometry": {"coordinates":[-89.698724,42.608489],"type":"Point"}
}