{
  "type": "Feature",
  "properties": {
    "iso:country":"US",
    "sg:address":"643 N Main St",
    "sg:city":"Viola",
    "sg:classifiers":[
        {
            "category":"Building & Trades",
            "subcategory":"Electrical",
            "type":"Services"
        }
    ],
    "sg:phone":"+1 608 627 1423",
    "sg:postcode":"54664",
    "sg:province":"WI",
    "sg:tags":[
        "electric",
        "contractor"
    ],
    "wof:name":"Geary Electric",
    "wof:placetype":"venue"
},
  "geometry": {"coordinates":[-90.66862,43.511772],"type":"Point"}
}