{
  "type": "Feature",
  "properties": {
    "iso:country":"US",
    "sg:address":"610 W Main St",
    "sg:city":"Princeton",
    "sg:classifiers":[
        {
            "category":"Insurance",
            "subcategory":"Insurance Agent",
            "type":"Services"
        }
    ],
    "sg:phone":"+1 920 295 6119",
    "sg:postcode":"54968",
    "sg:province":"WI",
    "wof:name":"Norb Wianecki Agency",
    "wof:placetype":"venue"
},
  "geometry": {"coordinates":[-89.13191,43.851301],"type":"Point"}
}