{
  "type": "Feature",
  "properties": {
    "addr:full":"1234 E Juneau Ave Milwaukee WI 53202",
    "addr:housenumber":"1234",
    "addr:postcode":"53202",
    "addr:street":"E Juneau Ave",
    "iso:country":"US",
    "sg:address":"1234 E Juneau Ave",
    "sg:city":"Milwaukee",
    "sg:classifiers":[
        {
            "category":"Banks & Credit Unions",
            "subcategory":"Investment Brokerage",
            "type":"Services"
        }
    ],
    "sg:phone":"+1 414 431 1401",
    "sg:postcode":"53202",
    "sg:province":"WI",
    "sg:tags":[
        "advisory"
    ],
    "wof:name":"Biomedical Renaissance LLC",
    "wof:placetype":"venue"
},
  "geometry": {"coordinates":[-87.89686,43.045747],"type":"Point"}
}