{
  "type": "Feature",
  "properties": {
    "iso:country":"US",
    "sg:address":"3900 Creekview Rd",
    "sg:city":"De Pere",
    "sg:classifiers":[
        {
            "category":"Recreation",
            "type":"Entertainment"
        }
    ],
    "sg:phone":"+1 920 339 3098",
    "sg:postcode":"54115",
    "sg:province":"WI",
    "sg:tags":[
        "animal"
    ],
    "wof:name":"Creekview Riding Center Inc",
    "wof:placetype":"venue"
},
  "geometry": {"coordinates":[-87.929391,44.400514],"type":"Point"}
}