{
  "type": "Feature",
  "properties": {
    "iso:country":"US",
    "sg:address":"225 W North St",
    "sg:city":"De Forest",
    "sg:classifiers":[
        {
            "category":"Building & Trades",
            "subcategory":"Construction",
            "type":"Services"
        }
    ],
    "sg:phone":"+1 608 846 1816",
    "sg:postcode":"53532",
    "sg:province":"WI",
    "sg:tags":[
        "roofing",
        "contractor"
    ],
    "wof:name":"Suburban Roofing Systems",
    "wof:placetype":"venue"
},
  "geometry": {"coordinates":[-89.34791800000001,43.252591],"type":"Point"}
}