{
  "type": "Feature",
  "properties": {
    "iso:country":"US",
    "sg:address":"113 Kettle Moraine Dr S",
    "sg:city":"Slinger",
    "sg:classifiers":[
        {
            "category":"Personal",
            "subcategory":"Barber",
            "type":"Services"
        }
    ],
    "sg:phone":"+1 262 644 8411",
    "sg:postcode":"53086",
    "sg:province":"WI",
    "sg:tags":[
        "shop"
    ],
    "wof:name":"Joe's Barber Shop",
    "wof:placetype":"venue"
},
  "geometry": {"coordinates":[-88.285702,43.33397],"type":"Point"}
}