{
  "type": "Feature",
  "properties": {
    "iso:country":"US",
    "sg:address":"1173 Arboleda Ln",
    "sg:city":"Sheboygan",
    "sg:classifiers":[
        {
            "category":"Professional",
            "subcategory":"Management & Consulting",
            "type":"Services"
        }
    ],
    "sg:phone":"+1 920 451 7084",
    "sg:postcode":"53081",
    "sg:province":"WI",
    "wof:name":"International Marketing Assoc",
    "wof:placetype":"venue"
},
  "geometry": {"coordinates":[-87.720043,43.688481],"type":"Point"}
}