{
  "type": "Feature",
  "properties": {
    "iso:country":"US",
    "sg:address":"2722 Cedar Ave",
    "sg:city":"Sayner",
    "sg:classifiers":[
        {
            "category":"Manufacturing",
            "subcategory":"Lumber",
            "type":"Manufacturing & Wholesale Goods"
        }
    ],
    "sg:phone":"+1 715 542 4452",
    "sg:postcode":"54560",
    "sg:province":"WI",
    "sg:tags":[
        "forester"
    ],
    "wof:name":"Park Fals Hardwoods",
    "wof:placetype":"venue"
},
  "geometry": {"coordinates":[-89.519341,45.98136],"type":"Point"}
}