{
  "type": "Feature",
  "properties": {
    "addr:full":"165 N Main St Richland Center WI 53581",
    "addr:housenumber":"165",
    "addr:postcode":"53581",
    "addr:street":"N Main St",
    "iso:country":"US",
    "sg:address":"165 N Main St",
    "sg:city":"Richland Center",
    "sg:classifiers":[
        {
            "category":"Personal",
            "subcategory":"Beauty Salon",
            "type":"Services"
        }
    ],
    "sg:phone":"+1 608 647 9052",
    "sg:postcode":"53581",
    "sg:province":"WI",
    "wof:name":"Pampered Pleasures",
    "wof:placetype":"venue"
},
  "geometry": {"coordinates":[-90.38661399999999,43.335522],"type":"Point"}
}