{
  "type": "Feature",
  "properties": {
    "iso:country":"US",
    "sg:address":"4168 Capitol Dr",
    "sg:city":"Shawano",
    "sg:classifiers":[
        {
            "category":"Manufacturing",
            "subcategory":"Tools & Machinery",
            "type":"Manufacturing & Wholesale Goods"
        }
    ],
    "sg:phone":"+1 715 524 5171",
    "sg:postcode":"54166",
    "sg:province":"WI",
    "sg:tags":[
        "machine",
        "shop"
    ],
    "wof:name":"Capitol Manufacturing",
    "wof:placetype":"venue"
},
  "geometry": {"coordinates":[-88.685436,44.736393],"type":"Point"}
}