{
  "type": "Feature",
  "properties": {
    "iso:country":"US",
    "sg:address":"3895 14th Ct",
    "sg:city":"Montello",
    "sg:classifiers":[
        {
            "category":"Manufacturing",
            "subcategory":"Tools & Machinery",
            "type":"Manufacturing & Wholesale Goods"
        }
    ],
    "sg:phone":"+1 608 297 9880",
    "sg:postcode":"53949",
    "sg:province":"WI",
    "sg:tags":[
        "industry",
        "mfg"
    ],
    "wof:name":"C A E Service & E P M",
    "wof:placetype":"venue"
},
  "geometry": {"coordinates":[-89.34411,43.78234],"type":"Point"}
}