{
  "type": "Feature",
  "properties": {
    "iso:country":"US",
    "sg:address":"825 E Prospect St",
    "sg:city":"Durand",
    "sg:classifiers":[
        {
            "category":"Shopping",
            "subcategory":"Discount & Variety Stores",
            "type":"Retail Goods"
        },
        {
            "category":"Professional",
            "subcategory":"Business Services",
            "type":"Services"
        }
    ],
    "sg:phone":"+1 715 672 5884",
    "sg:postcode":"54736",
    "sg:province":"WI",
    "sg:tags":[
        "merchandise",
        "liquidator",
        "general"
    ],
    "wof:name":"C & M Liquidators Inc",
    "wof:placetype":"venue"
},
  "geometry": {"coordinates":[-91.956967,44.631747],"type":"Point"}
}