{
  "type": "Feature",
  "properties": {
    "addr:full":"4475 N 124th St Brookfield WI 53005",
    "addr:housenumber":"4475",
    "addr:postcode":"53005",
    "addr:street":"N 124Th St",
    "iso:country":"US",
    "sg:address":"4475 N 124th St",
    "sg:city":"Brookfield",
    "sg:classifiers":[
        {
            "category":"Shopping",
            "subcategory":"Stationery & Office Supplies",
            "type":"Retail Goods"
        },
        {
            "category":"Wholesale",
            "subcategory":"Office Equipment",
            "type":"Manufacturing & Wholesale Goods"
        },
        {
            "category":"Professional",
            "subcategory":"Printing & Photocopies",
            "type":"Services"
        },
        {
            "category":"Banks & Credit Unions",
            "subcategory":"Bureau De Change",
            "type":"Services"
        }
    ],
    "sg:phone":"+1 262 781 6040",
    "sg:postcode":"53005",
    "sg:province":"WI",
    "sg:tags":[
        "form",
        "business",
        "register",
        "autographic",
        "printers-business",
        "card"
    ],
    "sg:website":"http://www.bcaaonline.com",
    "wof:name":"Business Cards Across America",
    "wof:placetype":"venue"
},
  "geometry": {"coordinates":[-88.066152,43.09787],"type":"Point"}
}