{
  "type": "Feature",
  "properties": {
    "iso:country":"US",
    "sg:address":"814 Superior Ave",
    "sg:city":"Sheboygan",
    "sg:classifiers":[
        {
            "category":"Organizations",
            "subcategory":"Religious Organization",
            "type":"Services"
        }
    ],
    "sg:phone":"+1 920 452 0129",
    "sg:postcode":"53081",
    "sg:province":"WI",
    "wof:name":"Holy Name Parish Religious Ed",
    "wof:placetype":"venue"
},
  "geometry": {"coordinates":[-87.71444,43.760796],"type":"Point"}
}