{
  "type": "Feature",
  "properties": {
    "addr:full":"1511 3rd St Wausau WI 54403",
    "addr:housenumber":"1511",
    "addr:postcode":"54403",
    "addr:street":"3Rd St",
    "iso:country":"US",
    "sg:address":"1511 3rd St",
    "sg:city":"Wausau",
    "sg:classifiers":[
        {
            "category":"Autos & Motor Vehicles",
            "subcategory":"Fuel & Gas Station",
            "type":"Retail Goods"
        },
        {
            "category":"Food & Beverages",
            "subcategory":"Groceries & Convenience Stores",
            "type":"Retail Goods"
        }
    ],
    "sg:phone":"+1 715 842 0347",
    "sg:postcode":"54403",
    "sg:province":"WI",
    "sg:website":"http://www.riiser.com",
    "wof:name":"Wausau Third & Bridge R-Store",
    "wof:placetype":"venue"
},
  "geometry": {"coordinates":[-89.62719300000001,44.96875],"type":"Point"}
}