{
  "type": "Feature",
  "properties": {
    "iso:country":"US",
    "sg:address":"1415 Lawrence Dr",
    "sg:city":"De Pere",
    "sg:classifiers":[
        {
            "category":"Restaurant",
            "type":"Food & Drink"
        }
    ],
    "sg:menulink":"http://www.allmenus.com/wi/de-pere/145436-subway/menu/",
    "sg:phone":"+1 920 351 0076",
    "sg:postcode":"54115",
    "sg:province":"WI",
    "sg:tags":[
        "american",
        "sandwich"
    ],
    "wof:name":"Subway",
    "wof:placetype":"venue"
},
  "geometry": {"coordinates":[-88.100532,44.437465],"type":"Point"}
}