{
  "type": "Feature",
  "properties": {
    "iso:country":"US",
    "sg:address":"1808 W Thomas St",
    "sg:city":"Wausau",
    "sg:classifiers":[
        {
            "category":"Professional",
            "subcategory":"Business Services",
            "type":"Services"
        }
    ],
    "sg:phone":"+1 715 848 1538",
    "sg:postcode":"54401",
    "sg:province":"WI",
    "wof:name":"Markka Group Inc",
    "wof:placetype":"venue"
},
  "geometry": {"coordinates":[-89.65791,44.948371],"type":"Point"}
}