{
  "type": "Feature",
  "properties": {
    "iso:country":"US",
    "sg:address":"222 N Main St",
    "sg:city":"Fond Du Lac",
    "sg:classifiers":[
        {
            "category":"Retail",
            "subcategory":"Animal Services",
            "type":"Services"
        }
    ],
    "sg:phone":"+1 920 926 0554",
    "sg:postcode":"54935",
    "sg:province":"WI",
    "wof:name":"Affordable Family Pet Grooming",
    "wof:placetype":"venue"
},
  "geometry": {"coordinates":[-88.446963,43.7862],"type":"Point"}
}