{
  "type": "Feature",
  "properties": {
    "iso:country":"US",
    "sg:address":"9622 274th Ave",
    "sg:city":"Trevor",
    "sg:classifiers":[
        {
            "category":"Building & Trades",
            "subcategory":"Construction",
            "type":"Services"
        }
    ],
    "sg:phone":"+1 262 889 4932",
    "sg:postcode":"53179",
    "sg:province":"WI",
    "sg:tags":[
        "general",
        "contractor"
    ],
    "wof:name":"H & H Custom Builders",
    "wof:placetype":"venue"
},
  "geometry": {"coordinates":[-88.141793,42.536123],"type":"Point"}
}