{
  "type": "Feature",
  "properties": {
    "iso:country":"US",
    "sg:address":"1800 Jackson St",
    "sg:city":"Oshkosh",
    "sg:classifiers":[
        {
            "category":"Restaurant",
            "type":"Food & Drink"
        }
    ],
    "sg:menulink":"http://www.allmenus.com/wi/oshkosh/204851-taco-bell/menu/",
    "sg:phone":"+1 920 233 4133",
    "sg:postcode":"54901",
    "sg:province":"WI",
    "sg:tags":[
        "mexican"
    ],
    "wof:name":"Taco Bell",
    "wof:placetype":"venue"
},
  "geometry": {"coordinates":[-88.542469,44.039605],"type":"Point"}
}