{
  "type": "Feature",
  "properties": {
    "addr:full":"148 N Eau Claire St Mondovi WI 54755",
    "addr:housenumber":"148",
    "addr:postcode":"54755",
    "addr:street":"N Eau Claire St",
    "iso:country":"US",
    "sg:address":"148 N Eau Claire St",
    "sg:city":"Mondovi",
    "sg:classifiers":[
        {
            "category":"Professional",
            "subcategory":"Lawyer & Legal Services",
            "type":"Services"
        }
    ],
    "sg:phone":"+1 715 926 3854",
    "sg:postcode":"54755",
    "sg:province":"WI",
    "sg:tags":[
        "attorney"
    ],
    "wof:name":"Hagness Law Office",
    "wof:placetype":"venue"
},
  "geometry": {"coordinates":[-91.67053199999999,44.56833],"type":"Point"}
}