{
  "type": "Feature",
  "properties": {
    "iso:country":"US",
    "sg:address":"2012 Melody Ln",
    "sg:city":"Waukesha",
    "sg:classifiers":[
        {
            "category":"Professional",
            "subcategory":"Secretarial Services",
            "type":"Services"
        }
    ],
    "sg:phone":"+1 262 524 9282",
    "sg:postcode":"53186",
    "sg:province":"WI",
    "sg:tags":[
        "transcription",
        "medical",
        "reporting"
    ],
    "wof:name":"Midwest Transcription Svcs LLC",
    "wof:placetype":"venue"
},
  "geometry": {"coordinates":[-88.195998,43.030796],"type":"Point"}
}