{
  "type": "Feature",
  "properties": {
    "iso:country":"US",
    "sg:address":"38134 Delafield Rd",
    "sg:city":"Oconomowoc",
    "sg:classifiers":[
        {
            "category":"Farming",
            "subcategory":"Farm",
            "type":"Manufacturing & Wholesale Goods"
        }
    ],
    "sg:phone":"+1 262 593 8347",
    "sg:postcode":"53066",
    "sg:province":"WI",
    "sg:tags":[
        "crop",
        "animal",
        "general"
    ],
    "wof:name":"Arnold Schlender",
    "wof:placetype":"venue"
},
  "geometry": {"coordinates":[-88.501979,43.060876],"type":"Point"}
}