{
  "type": "Feature",
  "properties": {
    "iso:country":"US",
    "sg:address":"8861 S 27th St",
    "sg:city":"Franklin",
    "sg:classifiers":[
        {
            "category":"Building & Trades",
            "subcategory":"Construction",
            "type":"Services"
        }
    ],
    "sg:phone":"+1 414 761 9690",
    "sg:postcode":"53132",
    "sg:province":"WI",
    "sg:tags":[
        "company"
    ],
    "wof:name":"Larkman Construction Inc",
    "wof:placetype":"venue"
},
  "geometry": {"coordinates":[-87.951021,42.884412],"type":"Point"}
}