{
  "type": "Feature",
  "properties": {
    "iso:country":"US",
    "sg:address":"2467 Schuman Rd",
    "sg:city":"Woodruff",
    "sg:classifiers":[
        {
            "category":"Manufacturing",
            "subcategory":"Buildings",
            "type":"Manufacturing & Wholesale Goods"
        }
    ],
    "sg:phone":"+1 715 356 4404",
    "sg:postcode":"54568",
    "sg:province":"WI",
    "sg:tags":[
        "prefabricated",
        "wood",
        "mfg"
    ],
    "wof:name":"Old Timer Log Homes",
    "wof:placetype":"venue"
},
  "geometry": {"coordinates":[-89.704061,45.963525],"type":"Point"}
}