{
  "type": "Feature",
  "properties": {
    "addr:full":"1907 American Dr Neenah WI 54956",
    "addr:housenumber":"1907",
    "addr:postcode":"54956",
    "addr:street":"American Dr",
    "iso:country":"US",
    "sg:address":"1907 American Dr",
    "sg:city":"Neenah",
    "sg:classifiers":[
        {
            "category":"Professional",
            "subcategory":"Printing & Photocopies",
            "type":"Services"
        }
    ],
    "sg:phone":"+1 920 969 1785",
    "sg:postcode":"54956",
    "sg:province":"WI",
    "sg:tags":[
        "duplicating",
        "copying"
    ],
    "wof:name":"Specialty Prep Svc",
    "wof:placetype":"venue"
},
  "geometry": {"coordinates":[-88.469537,44.226991],"type":"Point"}
}