{
  "type": "Feature",
  "properties": {
    "iso:country":"US",
    "sg:address":"1401 E Brady St",
    "sg:city":"Milwaukee",
    "sg:classifiers":[
        {
            "category":"Bars & Pubs",
            "type":"Food & Drink"
        }
    ],
    "sg:phone":"+1 414 224 8111",
    "sg:postcode":"53202",
    "sg:province":"WI",
    "sg:tags":[
        "lounge",
        "drinking",
        "cocktail"
    ],
    "sg:website":"http://www.nomadpub.com",
    "wof:name":"Nomad World Pub",
    "wof:placetype":"venue"
},
  "geometry": {"coordinates":[-87.89376799999999,43.052959],"type":"Point"}
}