{
  "type": "Feature",
  "properties": {
    "addr:full":"3630 N 50th St Milwaukee WI 53216",
    "addr:housenumber":"3630",
    "addr:postcode":"53216",
    "addr:street":"N 50Th St",
    "iso:country":"US",
    "sg:address":"3630 N 50th St",
    "sg:city":"Milwaukee",
    "sg:classifiers":[
        {
            "category":"Professional",
            "subcategory":"Business Services",
            "type":"Services"
        }
    ],
    "sg:phone":"+1 414 442 8692",
    "sg:postcode":"53216",
    "sg:province":"WI",
    "wof:name":"Finishin Touches Unlimited LLC",
    "wof:placetype":"venue"
},
  "geometry": {"coordinates":[-87.97584000000001,43.083183],"type":"Point"}
}