{
  "type": "Feature",
  "properties": {
    "iso:country":"US",
    "sg:address":"2643 N 53rd St",
    "sg:city":"Milwaukee",
    "sg:classifiers":[
        {
            "category":"Shopping",
            "subcategory":"Hobbies, Toys, & Games",
            "type":"Retail Goods"
        },
        {
            "category":"Professional",
            "subcategory":"Business Services",
            "type":"Services"
        }
    ],
    "sg:phone":"+1 414 871 3889",
    "sg:postcode":"53210",
    "sg:province":"WI",
    "sg:tags":[
        "supply"
    ],
    "wof:name":"Perahera Imports LLC",
    "wof:placetype":"venue"
},
  "geometry": {"coordinates":[-87.979928,43.067192],"type":"Point"}
}