{
  "type": "Feature",
  "properties": {
    "iso:country":"US",
    "sg:address":"8877 Woodbridge Dr",
    "sg:city":"Greendale",
    "sg:classifiers":[
        {
            "category":"Social Services",
            "subcategory":"Job Training",
            "type":"Services"
        },
        {
            "category":"Education",
            "subcategory":"Special Training",
            "type":"Public Place"
        }
    ],
    "sg:phone":"+1 414 427 0945",
    "sg:postcode":"53129",
    "sg:province":"WI",
    "sg:tags":[
        "career",
        "employment",
        "vocational",
        "counseling"
    ],
    "wof:name":"Vocational Opportunities",
    "wof:placetype":"venue"
},
  "geometry": {"coordinates":[-88.025004,42.946625],"type":"Point"}
}