{
  "type": "Feature",
  "properties": {
    "iso:country":"US",
    "sg:address":"1715 E Cumberland Blvd",
    "sg:city":"Milwaukee",
    "sg:classifiers":[
        {
            "category":"Manufacturing",
            "subcategory":"Printing",
            "type":"Manufacturing & Wholesale Goods"
        }
    ],
    "sg:phone":"+1 414 332 6775",
    "sg:postcode":"53211",
    "sg:province":"WI",
    "sg:tags":[
        "publisher"
    ],
    "wof:name":"Ageless Dominion Publishing",
    "wof:placetype":"venue"
},
  "geometry": {"coordinates":[-87.88752100000001,43.101148],"type":"Point"}
}