{
  "type": "Feature",
  "properties": {
    "iso:country":"US",
    "sg:address":"2749 Alpine Rd",
    "sg:city":"Eau Claire",
    "sg:classifiers":[
        {
            "category":"Retail",
            "subcategory":"Auto Repair",
            "type":"Services"
        }
    ],
    "sg:phone":"+1 715 834 6044",
    "sg:postcode":"54703",
    "sg:province":"WI",
    "sg:tags":[
        "body",
        "automobile",
        "painting"
    ],
    "wof:name":"Mark's Auto Body",
    "wof:placetype":"venue"
},
  "geometry": {"coordinates":[-91.55034499999999,44.843188],"type":"Point"}
}