{
  "type": "Feature",
  "properties": {
    "iso:country":"US",
    "sg:address":"600 N Plankinton Ave",
    "sg:city":"Milwaukee",
    "sg:classifiers":[
        {
            "category":"Organizations",
            "subcategory":"Professional Association",
            "type":"Services"
        }
    ],
    "sg:phone":"+1 414 272 8575",
    "sg:postcode":"53203",
    "sg:province":"WI",
    "wof:name":"ASQ",
    "wof:placetype":"venue"
},
  "geometry": {"coordinates":[-87.911251,43.038712],"type":"Point"}
}