{
  "type": "Feature",
  "properties": {
    "iso:country":"US",
    "sg:address":"905 S Walden Ave",
    "sg:city":"Appleton",
    "sg:classifiers":[
        {
            "category":"Building & Trades",
            "subcategory":"Electrical",
            "type":"Services"
        }
    ],
    "sg:phone":"+1 920 735 1297",
    "sg:postcode":"54915",
    "sg:province":"WI",
    "sg:tags":[
        "electrical",
        "contractor"
    ],
    "wof:name":"AB Electric of Appleton",
    "wof:placetype":"venue"
},
  "geometry": {"coordinates":[-88.381958,44.25428],"type":"Point"}
}