{
  "type": "Feature",
  "properties": {
    "addr:full":"3725 Roosevelt Rd Kenosha WI 53142",
    "addr:housenumber":"3725",
    "addr:postcode":"53142",
    "addr:street":"Roosevelt Rd",
    "iso:country":"US",
    "sg:address":"3725 Roosevelt Rd",
    "sg:city":"Kenosha",
    "sg:classifiers":[
        {
            "category":"Shopping",
            "subcategory":"Optical Goods",
            "type":"Retail Goods"
        }
    ],
    "sg:phone":"+1 262 654 7991",
    "sg:postcode":"53142",
    "sg:province":"WI",
    "sg:tags":[
        "optician"
    ],
    "wof:name":"Salem Vision Ctr",
    "wof:placetype":"venue"
},
  "geometry": {"coordinates":[-87.853711,42.567153],"type":"Point"}
}