{
  "type": "Feature",
  "properties": {
    "iso:country":"US",
    "sg:address":"412 N Main St",
    "sg:city":"Holmen",
    "sg:classifiers":[
        {
            "category":"Wholesale",
            "subcategory":"Meat",
            "type":"Manufacturing & Wholesale Goods"
        }
    ],
    "sg:phone":"+1 608 526 3112",
    "sg:postcode":"54636",
    "sg:province":"WI",
    "sg:tags":[
        "butchering"
    ],
    "wof:name":"Holmen Locker & Meat Market",
    "wof:placetype":"venue"
},
  "geometry": {"coordinates":[-91.260103,43.966876],"type":"Point"}
}