{
  "type": "Feature",
  "properties": {
    "iso:country":"US",
    "sg:address":"870 Larkspur Dr",
    "sg:city":"Brookfield",
    "sg:classifiers":[
        {
            "category":"Organizations",
            "subcategory":"Non-profit Organization",
            "type":"Services"
        }
    ],
    "sg:phone":"+1 262 641 5639",
    "sg:postcode":"53045",
    "sg:province":"WI",
    "wof:name":"Bright Brain Injury Group Hope",
    "wof:placetype":"venue"
},
  "geometry": {"coordinates":[-88.16403,43.042865],"type":"Point"}
}