{
  "type": "Feature",
  "properties": {
    "iso:country":"US",
    "sg:address":"10945 N Port Washington Rd",
    "sg:city":"Mequon",
    "sg:classifiers":[
        {
            "category":"Health Services",
            "subcategory":"Doctor",
            "type":"Services"
        }
    ],
    "sg:phone":"+1 414 963 1700",
    "sg:postcode":"53092",
    "sg:province":"WI",
    "sg:tags":[
        "physician",
        "surgeon"
    ],
    "wof:name":"Plastic Cosmetic & Hand Surgry",
    "wof:placetype":"venue"
},
  "geometry": {"coordinates":[-87.92407799999999,43.213854],"type":"Point"}
}