{
  "type": "Feature",
  "properties": {
    "iso:country":"US",
    "sg:address":"280 Washington St",
    "sg:city":"Prairie Du Sac",
    "sg:classifiers":[
        {
            "category":"Utilities",
            "subcategory":"Electric",
            "type":"Services"
        }
    ],
    "sg:phone":"+1 608 643 3133",
    "sg:postcode":"53578",
    "sg:province":"WI",
    "sg:tags":[
        "company"
    ],
    "wof:name":"Prairie Du Sac City Govt",
    "wof:placetype":"venue"
},
  "geometry": {"coordinates":[-89.72235999999999,43.290735],"type":"Point"}
}