{
  "type": "Feature",
  "properties": {
    "iso:country":"US",
    "sg:address":"4333 N 83rd St",
    "sg:city":"Milwaukee",
    "sg:classifiers":[
        {
            "category":"Building & Trades",
            "subcategory":"Construction",
            "type":"Services"
        }
    ],
    "sg:phone":"+1 414 578 3983",
    "sg:postcode":"53222",
    "sg:province":"WI",
    "sg:tags":[
        "contractor"
    ],
    "wof:name":"Fashion Builders",
    "wof:placetype":"venue"
},
  "geometry": {"coordinates":[-88.016175,43.096513],"type":"Point"}
}