{
  "type": "Feature",
  "properties": {
    "iso:country":"US",
    "sg:address":"2702 Calumet Ave",
    "sg:city":"Manitowoc",
    "sg:classifiers":[
        {
            "category":"Shopping",
            "subcategory":"Pharmacy",
            "type":"Retail Goods"
        }
    ],
    "sg:phone":"+1 920 683 8881",
    "sg:postcode":"54220",
    "sg:province":"WI",
    "sg:tags":[
        "photofinishing",
        "laboratory"
    ],
    "wof:name":"Walgreens",
    "wof:placetype":"venue"
},
  "geometry": {"coordinates":[-87.682085,44.087111],"type":"Point"}
}