{
  "type": "Feature",
  "properties": {
    "iso:country":"US",
    "sg:address":"787 N Main St",
    "sg:city":"Oregon",
    "sg:classifiers":[
        {
            "category":"Shopping",
            "subcategory":"Clothing, Apparel, & Fashions",
            "type":"Retail Goods"
        }
    ],
    "sg:phone":"+1 608 835 3632",
    "sg:postcode":"53575",
    "sg:province":"WI",
    "sg:tags":[
        "alteration"
    ],
    "wof:name":"Best Way Cleaners",
    "wof:placetype":"venue"
},
  "geometry": {"coordinates":[-89.383466,42.937653],"type":"Point"}
}