{
  "type": "Feature",
  "properties": {
    "iso:country":"US",
    "sg:address":"15444 State Hwy 32",
    "sg:city":"Lakewood",
    "sg:classifiers":[
        {
            "category":"Building & Trades",
            "subcategory":"Construction",
            "type":"Services"
        }
    ],
    "sg:phone":"+1 715 276 1900",
    "sg:postcode":"54138",
    "sg:province":"WI",
    "sg:tags":[
        "house"
    ],
    "wof:name":"BOHM Builders Inc",
    "wof:placetype":"venue"
},
  "geometry": {"coordinates":[-88.532414,45.30129],"type":"Point"}
}