{
  "type": "Feature",
  "properties": {
    "addr:full":"280 Haberdale Dr Footville WI 53548",
    "addr:housenumber":"280",
    "addr:postcode":"53548",
    "addr:street":"Haberdale Dr",
    "iso:country":"US",
    "sg:address":"280 Haberdale Dr",
    "sg:city":"Footville",
    "sg:classifiers":[
        {
            "category":"Organizations",
            "subcategory":"Religious Organization",
            "type":"Services"
        }
    ],
    "sg:phone":"+1 608 876 6252",
    "sg:postcode":"53548",
    "sg:province":"WI",
    "sg:tags":[
        "church"
    ],
    "wof:name":"St Augustine's Church",
    "wof:placetype":"venue"
},
  "geometry": {"coordinates":[-89.204599,42.673669],"type":"Point"}
}