{
  "type": "Feature",
  "properties": {
    "iso:country":"US",
    "sg:address":"4164 N New Franken Rd",
    "sg:city":"New Franken",
    "sg:classifiers":[
        {
            "category":"Restaurant",
            "type":"Food & Drink"
        }
    ],
    "sg:phone":"+1 920 866 9506",
    "sg:postcode":"54229",
    "sg:province":"WI",
    "sg:tags":[
        "eating"
    ],
    "wof:name":"Trackside Steakhouse",
    "wof:placetype":"venue"
},
  "geometry": {"coordinates":[-87.824639,44.599271],"type":"Point"}
}