{
  "type": "Feature",
  "properties": {
    "iso:country":"US",
    "sg:address":"10460 S 4th Ave",
    "sg:city":"Oak Creek",
    "sg:classifiers":[
        {
            "category":"Professional",
            "type":"Services"
        }
    ],
    "sg:phone":"+1 414 571 7066",
    "sg:postcode":"53154",
    "sg:province":"WI",
    "wof:name":"GTM Services Inc",
    "wof:placetype":"venue"
},
  "geometry": {"coordinates":[-87.850998,42.854006],"type":"Point"}
}