{
  "type": "Feature",
  "properties": {
    "addr:full":"2100 Riverside Dr Green Bay WI 54301",
    "addr:housenumber":"2100",
    "addr:postcode":"54301",
    "addr:street":"Riverside Dr",
    "iso:country":"US",
    "sg:address":"2100 Riverside Dr",
    "sg:city":"Green Bay",
    "sg:classifiers":[
        {
            "category":"Health Services",
            "subcategory":"Clinic",
            "type":"Services"
        }
    ],
    "sg:phone":"+1 920 448 7187",
    "sg:postcode":"54301",
    "sg:province":"WI",
    "sg:website":"www.stvincenthospital.org/wholeh",
    "wof:name":"Wholehealth",
    "wof:placetype":"venue"
},
  "geometry": {"coordinates":[-88.028441,44.486327],"type":"Point"}
}