{
  "type": "Feature",
  "properties": {
    "iso:country":"US",
    "sg:address":"7950 Highland Rd",
    "sg:city":"Loganville",
    "sg:classifiers":[
        {
            "category":"Building & Trades",
            "subcategory":"Construction",
            "type":"Services"
        }
    ],
    "sg:phone":"+1 608 727 2406",
    "sg:postcode":"53943",
    "sg:province":"WI",
    "sg:tags":[
        "house"
    ],
    "wof:name":"Triple J Remodeling LLC",
    "wof:placetype":"venue"
},
  "geometry": {"coordinates":[-90.040114,43.360524],"type":"Point"}
}