{
  "type": "Feature",
  "properties": {
    "iso:country":"US",
    "sg:address":"120 Bishops Way Ste 100",
    "sg:city":"Brookfield",
    "sg:classifiers":[
        {
            "category":"Health Services",
            "subcategory":"Doctor",
            "type":"Services"
        },
        {
            "category":"Health Services",
            "subcategory":"Hospital",
            "type":"Services"
        }
    ],
    "sg:phone":"+1 262 784 1156",
    "sg:postcode":"53005",
    "sg:province":"WI",
    "sg:tags":[
        "nursing",
        "consultant",
        "medical",
        "practice",
        "home"
    ],
    "wof:name":"Gibraltar Consultants Ltd",
    "wof:placetype":"venue"
},
  "geometry": {"coordinates":[-88.079177,43.029717],"type":"Point"}
}