{
  "type": "Feature",
  "properties": {
    "iso:country":"US",
    "sg:address":"1232 Carpenter St",
    "sg:city":"Madison",
    "sg:classifiers":[
        {
            "category":"Professional",
            "type":"Services"
        }
    ],
    "sg:phone":"+1 608 240 9512",
    "sg:postcode":"53704",
    "sg:province":"WI",
    "wof:name":"Allen Wilson",
    "wof:placetype":"venue"
},
  "geometry": {"coordinates":[-89.334857,43.113605],"type":"Point"}
}