{
  "type": "Feature",
  "properties": {
    "iso:country":"US",
    "sg:address":"20507 Sunny Slope Rd",
    "sg:city":"Reedsville",
    "sg:classifiers":[
        {
            "category":"Farming",
            "subcategory":"Dairy Farm",
            "type":"Manufacturing & Wholesale Goods"
        }
    ],
    "sg:phone":"+1 920 754 4560",
    "sg:postcode":"54230",
    "sg:province":"WI",
    "wof:name":"Sunny Slope Dairy",
    "wof:placetype":"venue"
},
  "geometry": {"coordinates":[-87.975551,44.167907],"type":"Point"}
}