{
  "type": "Feature",
  "properties": {
    "iso:country":"US",
    "sg:address":"4606 Pflaum Rd",
    "sg:city":"Madison",
    "sg:classifiers":[
        {
            "category":"Building & Trades",
            "subcategory":"Construction",
            "type":"Services"
        }
    ],
    "sg:phone":"+1 608 222 2122",
    "sg:postcode":"53718",
    "sg:province":"WI",
    "sg:tags":[
        "home",
        "contractor",
        "general",
        "family",
        "new"
    ],
    "wof:name":"Homestead Builders",
    "wof:placetype":"venue"
},
  "geometry": {"coordinates":[-89.30317599999999,43.062385],"type":"Point"}
}