{
  "type": "Feature",
  "properties": {
    "iso:country":"US",
    "sg:address":"411 Washington St",
    "sg:city":"Wausau",
    "sg:classifiers":[
        {
            "category":"Shopping",
            "subcategory":"Gifts & Souvenirs",
            "type":"Retail Goods"
        }
    ],
    "sg:phone":"+1 715 842 3880",
    "sg:postcode":"54403",
    "sg:province":"WI",
    "wof:name":"Spencer Gifts Inc",
    "wof:placetype":"venue"
},
  "geometry": {"coordinates":[-89.625795,44.95876],"type":"Point"}
}