{
  "type": "Feature",
  "properties": {
    "iso:country":"US",
    "sg:address":"450 US Hwy 8",
    "sg:city":"Turtle Lake",
    "sg:classifiers":[
        {
            "category":"Professional",
            "type":"Services"
        }
    ],
    "sg:phone":"+1 715 234 8333",
    "sg:postcode":"54889",
    "sg:province":"WI",
    "sg:tags":[
        "establishment"
    ],
    "wof:name":"Servicemaster Cleaning & Resto",
    "wof:placetype":"venue"
},
  "geometry": {"coordinates":[-92.249605,45.395757],"type":"Point"}
}