{
  "type": "Feature",
  "properties": {
    "iso:country":"US",
    "sg:address":"427 N University Dr",
    "sg:city":"Waukesha",
    "sg:classifiers":[
        {
            "category":"Social Services",
            "subcategory":"Adult Care",
            "type":"Services"
        }
    ],
    "sg:phone":"+1 262 524 1180",
    "sg:postcode":"53188",
    "sg:province":"WI",
    "sg:tags":[
        "home",
        "residential"
    ],
    "sg:website":"www.lindengrove.org",
    "wof:name":"Linden Heights",
    "wof:placetype":"venue"
},
  "geometry": {"coordinates":[-88.268539,43.018424],"type":"Point"}
}