{
  "type": "Feature",
  "properties": {
    "iso:country":"US",
    "sg:address":"2449 Blotz Rd",
    "sg:city":"Dodgeville",
    "sg:classifiers":[
        {
            "category":"Farming",
            "subcategory":"Dairy Farm",
            "type":"Manufacturing & Wholesale Goods"
        }
    ],
    "sg:phone":"+1 608 935 2636",
    "sg:postcode":"53533",
    "sg:province":"WI",
    "sg:tags":[
        "beef",
        "feedlot",
        "cattle"
    ],
    "wof:name":"Timothy Blotz",
    "wof:placetype":"venue"
},
  "geometry": {"coordinates":[-90.08773600000001,42.935838],"type":"Point"}
}