{
  "type": "Feature",
  "properties": {
    "iso:country":"US",
    "sg:address":"5887 Buchanan Rd",
    "sg:city":"Hartford",
    "sg:classifiers":[
        {
            "category":"Manufacturing",
            "subcategory":"Buildings",
            "type":"Manufacturing & Wholesale Goods"
        }
    ],
    "sg:phone":"+1 920 387 5676",
    "sg:postcode":"53027",
    "sg:province":"WI",
    "sg:tags":[
        "prefabricated",
        "wood",
        "mfg"
    ],
    "wof:name":"Plus Logs",
    "wof:placetype":"venue"
},
  "geometry": {"coordinates":[-88.4504,43.399293],"type":"Point"}
}