{
  "type": "Feature",
  "properties": {
    "addr:full":"635 W Hwy 16 West Salem WI 54669",
    "addr:housenumber":"635",
    "addr:postcode":"54669",
    "addr:street":"W Hwy 16",
    "iso:country":"US",
    "sg:address":"635 W Hwy 16",
    "sg:city":"West Salem",
    "sg:classifiers":[
        {
            "category":"Food & Beverages",
            "subcategory":"Meat & Fish",
            "type":"Retail Goods"
        }
    ],
    "sg:phone":"+1 608 786 1730",
    "sg:postcode":"54669",
    "sg:province":"WI",
    "sg:tags":[
        "grocery"
    ],
    "wof:name":"Hansens IGA Inc",
    "wof:placetype":"venue"
},
  "geometry": {"coordinates":[-91.092314,43.899232],"type":"Point"}
}