{
  "type": "Feature",
  "properties": {
    "addr:full":"27751 Nutmeg Rd Kendall WI 54638",
    "addr:housenumber":"27751",
    "addr:postcode":"54638",
    "addr:street":"Nutmeg Rd",
    "iso:country":"US",
    "sg:address":"27751 Nutmeg Rd",
    "sg:city":"Kendall",
    "sg:classifiers":[
        {
            "category":"Travel",
            "subcategory":"Hotels & Motels",
            "type":"Entertainment"
        }
    ],
    "sg:phone":"+1 608 463 8268",
    "sg:postcode":"54638",
    "sg:province":"WI",
    "sg:tags":[
        "breakfast",
        "accommodation",
        "bed"
    ],
    "wof:name":"Sunburst Haus",
    "wof:placetype":"venue"
},
  "geometry": {"coordinates":[-90.329481,43.77777],"type":"Point"}
}