{
  "type": "Feature",
  "properties": {
    "addr:full":"1290 Poeppel Rd Fort Atkinson WI 53538",
    "addr:housenumber":"1290",
    "addr:postcode":"53538",
    "addr:street":"Poeppel Rd",
    "iso:country":"US",
    "sg:address":"1290 Poeppel Rd",
    "sg:city":"Fort Atkinson",
    "sg:classifiers":[
        {
            "category":"Retail",
            "subcategory":"Auto Repair",
            "type":"Services"
        }
    ],
    "sg:phone":"+1 920 563 6363",
    "sg:postcode":"53538",
    "sg:province":"WI",
    "sg:tags":[
        "repairing",
        "automobile",
        "general"
    ],
    "wof:name":"Shilt's Auto Repair",
    "wof:placetype":"venue"
},
  "geometry": {"coordinates":[-88.85153,42.888713],"type":"Point"}
}