{
  "type": "Feature",
  "properties": {
    "iso:country":"US",
    "sg:address":"319 E Lloyd St",
    "sg:city":"Milwaukee",
    "sg:classifiers":[
        {
            "category":"Real Estate",
            "subcategory":"Real Estate Agent",
            "type":"Services"
        }
    ],
    "sg:phone":"+1 414 372 9663",
    "sg:postcode":"53212",
    "sg:province":"WI",
    "wof:name":"Bill Wood Realtor",
    "wof:placetype":"venue"
},
  "geometry": {"coordinates":[-87.908263,43.057683],"type":"Point"}
}