{
  "type": "Feature",
  "properties": {
    "iso:country":"US",
    "sg:address":"909 State Hwy 120",
    "sg:city":"Lake Geneva",
    "sg:classifiers":[
        {
            "category":"Retail",
            "subcategory":"Repair Shop",
            "type":"Services"
        }
    ],
    "sg:phone":"+1 262 248 1968",
    "sg:postcode":"53147",
    "sg:province":"WI",
    "sg:tags":[
        "upholsterer"
    ],
    "wof:name":"Recht Upholstery",
    "wof:placetype":"venue"
},
  "geometry": {"coordinates":[-88.432551,42.58081],"type":"Point"}
}