{
  "type": "Feature",
  "properties": {
    "addr:full":"2845 Co Rd D Birchwood WI 54817",
    "addr:housenumber":"2845",
    "addr:postcode":"54817",
    "addr:street":"Co Rd D",
    "iso:country":"US",
    "sg:address":"2845 Co Rd D",
    "sg:city":"Birchwood",
    "sg:classifiers":[
        {
            "category":"Real Estate",
            "subcategory":"Real Estate Agent",
            "type":"Services"
        }
    ],
    "sg:phone":"+1 715 354 3395",
    "sg:postcode":"54817",
    "sg:province":"WI",
    "wof:name":"American Timber Homes",
    "wof:placetype":"venue"
},
  "geometry": {"coordinates":[-91.680803,45.667151],"type":"Point"}
}