{
  "type": "Feature",
  "properties": {
    "iso:country":"US",
    "sg:address":"4001 Triangle St",
    "sg:city":"Mc Farland",
    "sg:classifiers":[
        {
            "category":"Professional",
            "type":"Services"
        }
    ],
    "sg:phone":"+1 608 838 0233",
    "sg:postcode":"53558",
    "sg:province":"WI",
    "sg:tags":[
        "establishment"
    ],
    "sg:website":"www.ahtwindows.com",
    "wof:name":"Advanced Home Technologies",
    "wof:placetype":"venue"
},
  "geometry": {"coordinates":[-89.29982699999999,43.039355],"type":"Point"}
}