{
  "type": "Feature",
  "properties": {
    "iso:country":"US",
    "sg:address":"306 S Main St",
    "sg:city":"Delavan",
    "sg:classifiers":[
        {
            "category":"Government",
            "subcategory":"Office",
            "type":"Public Place"
        }
    ],
    "sg:phone":"+1 262 728 0086",
    "sg:postcode":"53115",
    "sg:province":"WI",
    "sg:tags":[
        "national",
        "security"
    ],
    "wof:name":"Civil Air Patrol Inc",
    "wof:placetype":"venue"
},
  "geometry": {"coordinates":[-88.648465,42.62966],"type":"Point"}
}