{
  "type": "Feature",
  "properties": {
    "iso:country":"US",
    "sg:address":"7916 Co Rd U",
    "sg:city":"Beetown",
    "sg:classifiers":[
        {
            "category":"Restaurant",
            "type":"Food & Drink"
        }
    ],
    "sg:phone":"+1 608 794 2341",
    "sg:postcode":"53820",
    "sg:province":"WI",
    "wof:name":"Homestretch",
    "wof:placetype":"venue"
},
  "geometry": {"coordinates":[-90.807196,42.748025],"type":"Point"}
}