{
  "type": "Feature",
  "properties": {
    "iso:country":"US",
    "sg:address":"1650 S 38th St",
    "sg:city":"Milwaukee",
    "sg:classifiers":[
        {
            "category":"Organizations",
            "subcategory":"Labor Organization",
            "type":"Services"
        }
    ],
    "sg:phone":"+1 414 383 3330",
    "sg:postcode":"53215",
    "sg:province":"WI",
    "sg:tags":[
        "union"
    ],
    "wof:name":"Cream City Lodge 1061 IA M",
    "wof:placetype":"venue"
},
  "geometry": {"coordinates":[-87.961886,43.013207],"type":"Point"}
}