{
  "type": "Feature",
  "properties": {
    "iso:country":"US",
    "sg:address":"115 S 84th St",
    "sg:city":"Milwaukee",
    "sg:classifiers":[
        {
            "category":"Utilities",
            "subcategory":"Mobile Phone",
            "type":"Services"
        }
    ],
    "sg:phone":"+1 414 453 9577",
    "sg:postcode":"53214",
    "sg:province":"WI",
    "sg:tags":[
        "communication",
        "datum",
        "telephone",
        "cellular"
    ],
    "sg:website":"http://www.cingular.com",
    "wof:name":"Cingular Wireless",
    "wof:placetype":"venue"
},
  "geometry": {"coordinates":[-88.01730999999999,43.031126],"type":"Point"}
}