{
  "type": "Feature",
  "properties": {
    "iso:country":"US",
    "sg:address":"7401 W Towne Way",
    "sg:city":"Madison",
    "sg:classifiers":[
        {
            "category":"Shopping",
            "subcategory":"Department Store",
            "type":"Retail Goods"
        }
    ],
    "sg:phone":"+1 608 833 9293",
    "sg:postcode":"53719",
    "sg:province":"WI",
    "sg:website":"www.kohls.com",
    "wof:name":"Kohl's",
    "wof:placetype":"venue"
},
  "geometry": {"coordinates":[-89.51321299999999,43.057434],"type":"Point"}
}