{
  "type": "Feature",
  "properties": {
    "iso:country":"US",
    "sg:address":"8224 State Hwy 83",
    "sg:city":"Mukwonago",
    "sg:classifiers":[
        {
            "category":"Professional",
            "subcategory":"Management & Consulting",
            "type":"Services"
        }
    ],
    "sg:phone":"+1 262 642 9610",
    "sg:postcode":"53149",
    "sg:province":"WI",
    "sg:tags":[
        "training"
    ],
    "wof:name":"Impact Sales",
    "wof:placetype":"venue"
},
  "geometry": {"coordinates":[-88.299291,42.827045],"type":"Point"}
}