{
  "type": "Feature",
  "properties": {
    "addr:full":"121 N 120th St Milwaukee WI 53226",
    "addr:housenumber":"121",
    "addr:postcode":"53226",
    "addr:street":"N 120Th St",
    "iso:country":"US",
    "sg:address":"121 N 120th St",
    "sg:city":"Milwaukee",
    "sg:classifiers":[
        {
            "category":"Manufacturing",
            "subcategory":"Rubber & Plastics",
            "type":"Manufacturing & Wholesale Goods"
        }
    ],
    "sg:phone":"+1 414 475 1880",
    "sg:postcode":"53226",
    "sg:province":"WI",
    "sg:tags":[
        "product",
        "mfg"
    ],
    "wof:name":"Creative Plastics Inc",
    "wof:placetype":"venue"
},
  "geometry": {"coordinates":[-88.061682,43.031959],"type":"Point"}
}