{
  "type": "Feature",
  "properties": {
    "addr:full":"3127 Purintun Rd Albany WI 53502",
    "addr:postcode":"3127;53502",
    "addr:street":"Purintun Rd",
    "iso:country":"US",
    "sg:address":"3127 Purintun Rd",
    "sg:city":"Albany",
    "sg:classifiers":[
        {
            "category":"Farming",
            "subcategory":"Dairy Farm",
            "type":"Manufacturing & Wholesale Goods"
        }
    ],
    "sg:phone":"+1 608 862 3588",
    "sg:postcode":"53502",
    "sg:province":"WI",
    "wof:name":"Miktim Dairy",
    "wof:placetype":"venue"
},
  "geometry": {"coordinates":[-89.515216,42.711769],"type":"Point"}
}