{
  "type": "Feature",
  "properties": {
    "addr:full":"1605 Co Rd F Sullivan WI 53178",
    "addr:housenumber":"1605",
    "addr:postcode":"53178",
    "addr:street":"Co Rd",
    "iso:country":"US",
    "sg:address":"1605 Co Rd F",
    "sg:city":"Sullivan",
    "sg:classifiers":[
        {
            "category":"Bars & Pubs",
            "type":"Food & Drink"
        }
    ],
    "sg:phone":"+1 262 593 8614",
    "sg:postcode":"53178",
    "sg:province":"WI",
    "sg:tags":[
        "drinking"
    ],
    "wof:name":"C W Riverboat",
    "wof:placetype":"venue"
},
  "geometry": {"coordinates":[-88.606667,42.992864],"type":"Point"}
}