{
  "type": "Feature",
  "properties": {
    "addr:full":"2810 N Calhoun Rd Brookfield WI 53005",
    "addr:housenumber":"2810",
    "addr:postcode":"53005",
    "addr:street":"N Calhoun Rd",
    "iso:country":"US",
    "sg:address":"2810 N Calhoun Rd",
    "sg:city":"Brookfield",
    "sg:classifiers":[
        {
            "category":"Real Estate",
            "subcategory":"Real Estate Services",
            "type":"Services"
        },
        {
            "category":"Real Estate",
            "subcategory":"Real Estate Agent",
            "type":"Services"
        }
    ],
    "sg:phone":"+1 262 641 1000",
    "sg:postcode":"53005",
    "sg:province":"WI",
    "sg:tags":[
        "management"
    ],
    "wof:name":"Cap Management",
    "wof:placetype":"venue"
},
  "geometry": {"coordinates":[-88.125905,43.070062],"type":"Point"}
}