{
  "type": "Feature",
  "properties": {
    "iso:country":"US",
    "sg:address":"2876 Shore Dr",
    "sg:city":"Marinette",
    "sg:classifiers":[
        {
            "category":"Real Estate",
            "subcategory":"Real Estate Agent",
            "type":"Services"
        }
    ],
    "sg:phone":"+1 715 735 3221",
    "sg:postcode":"54143",
    "sg:province":"WI",
    "sg:tags":[
        "appraiser"
    ],
    "wof:name":"Boneham Appraisal Svc",
    "wof:placetype":"venue"
},
  "geometry": {"coordinates":[-87.61925599999999,45.067046],"type":"Point"}
}