{
  "type": "Feature",
  "properties": {
    "iso:country":"US",
    "sg:address":"6530 W Fond Du Lac Ave",
    "sg:city":"Milwaukee",
    "sg:classifiers":[
        {
            "category":"Autos & Motor Vehicles",
            "subcategory":"Fuel & Gas Station",
            "type":"Retail Goods"
        },
        {
            "category":"Retail",
            "subcategory":"Car Wash",
            "type":"Services"
        }
    ],
    "sg:phone":"+1 414 616 0340",
    "sg:postcode":"53218",
    "sg:province":"WI",
    "sg:website":"http://www.localshell.com",
    "wof:name":"Hampton Shell",
    "wof:placetype":"venue"
},
  "geometry": {"coordinates":[-87.993103,43.103298],"type":"Point"}
}