{
  "type": "Feature",
  "properties": {
    "iso:country":"US",
    "sg:address":"501 N 4th St",
    "sg:city":"Watertown",
    "sg:classifiers":[
        {
            "category":"Bars & Pubs",
            "type":"Food & Drink"
        }
    ],
    "sg:phone":"+1 920 206 7777",
    "sg:postcode":"53094",
    "sg:province":"WI",
    "sg:tags":[
        "drinking"
    ],
    "wof:name":"Sidelines",
    "wof:placetype":"venue"
},
  "geometry": {"coordinates":[-88.72041299999999,43.19748],"type":"Point"}
}