{
  "type": "Feature",
  "properties": {
    "addr:full":"2756 State Hwy 17 Rhinelander WI 54501",
    "addr:housenumber":"2756",
    "addr:postcode":"54501",
    "addr:street":"State Hwy 17",
    "iso:country":"US",
    "sg:address":"2756 State Hwy 17",
    "sg:city":"Rhinelander",
    "sg:classifiers":[
        {
            "category":"Professional",
            "type":"Services"
        }
    ],
    "sg:phone":"+1 715 362 2568",
    "sg:postcode":"54501",
    "sg:province":"WI",
    "wof:name":"Sheahan Kitchen and Bath L L C",
    "wof:placetype":"venue"
},
  "geometry": {"coordinates":[-89.44887199999999,45.595762],"type":"Point"}
}