{
  "type": "Feature",
  "properties": {
    "iso:country":"US",
    "sg:address":"508 S Foster St",
    "sg:city":"Merrill",
    "sg:classifiers":[
        {
            "category":"Building & Trades",
            "subcategory":"Plumbing",
            "type":"Services"
        }
    ],
    "sg:phone":"+1 715 536 9017",
    "sg:postcode":"54452",
    "sg:province":"WI",
    "sg:tags":[
        "contractor"
    ],
    "wof:name":"J J Refrigration and Heating",
    "wof:placetype":"venue"
},
  "geometry": {"coordinates":[-89.719051,45.174508],"type":"Point"}
}