{
  "type": "Feature",
  "properties": {
    "iso:country":"US",
    "sg:address":"1691 E Mason St",
    "sg:city":"Green Bay",
    "sg:classifiers":[
        {
            "category":"Building & Trades",
            "subcategory":"Construction",
            "type":"Services"
        }
    ],
    "sg:phone":"+1 920 468 5384",
    "sg:postcode":"54302",
    "sg:province":"WI",
    "sg:tags":[
        "water",
        "contractor",
        "main",
        "sewer"
    ],
    "wof:name":"Knaus Construction Co Inc",
    "wof:placetype":"venue"
},
  "geometry": {"coordinates":[-87.985209,44.494132],"type":"Point"}
}