{
  "type": "Feature",
  "properties": {
    "iso:country":"US",
    "sg:address":"2300 N Mayfair Rd",
    "sg:city":"Milwaukee",
    "sg:classifiers":[
        {
            "category":"Retail",
            "subcategory":"Funeral Services",
            "type":"Services"
        }
    ],
    "sg:phone":"+1 414 453 3060",
    "sg:postcode":"53226",
    "sg:province":"WI",
    "sg:tags":[
        "director",
        "plans-pre-arranged"
    ],
    "sg:website":"http://www.wfda.org/",
    "wof:name":"Wisconsin Funeral Directors Association",
    "wof:placetype":"venue"
},
  "geometry": {"coordinates":[-88.047546,43.06004],"type":"Point"}
}