{
  "type": "Feature",
  "properties": {
    "iso:country":"US",
    "sg:address":"510 K St",
    "sg:city":"Reedsburg",
    "sg:classifiers":[
        {
            "category":"Insurance",
            "subcategory":"Insurance Agent",
            "type":"Services"
        }
    ],
    "sg:phone":"+1 608 524 3350",
    "sg:postcode":"53959",
    "sg:province":"WI",
    "wof:name":"Allstate Insurance",
    "wof:placetype":"venue"
},
  "geometry": {"coordinates":[-90.017029,43.525224],"type":"Point"}
}