{
  "type": "Feature",
  "properties": {
    "addr:full":"133 Park Ave Beaver Dam WI 53916",
    "addr:housenumber":"133",
    "addr:postcode":"53916",
    "addr:street":"Park Ave",
    "iso:country":"US",
    "sg:address":"133 Park Ave",
    "sg:city":"Beaver Dam",
    "sg:classifiers":[
        {
            "category":"Retail",
            "subcategory":"Auto Repair",
            "type":"Services"
        }
    ],
    "sg:phone":"+1 920 887 9404",
    "sg:postcode":"53916",
    "sg:province":"WI",
    "sg:tags":[
        "repairing",
        "automobile"
    ],
    "wof:name":"TTS Auto Repair",
    "wof:placetype":"venue"
},
  "geometry": {"coordinates":[-88.834862,43.456189],"type":"Point"}
}