{
  "type": "Feature",
  "properties": {
    "iso:country":"US",
    "sg:address":"1310 S Walnut St",
    "sg:city":"Janesville",
    "sg:classifiers":[
        {
            "category":"Shopping",
            "type":"Retail Goods"
        }
    ],
    "sg:phone":"+1 608 758 4546",
    "sg:postcode":"53546",
    "sg:province":"WI",
    "sg:tags":[
        "merchandise"
    ],
    "wof:name":"Machine Knittery",
    "wof:placetype":"venue"
},
  "geometry": {"coordinates":[-89.040092,42.662006],"type":"Point"}
}