{
  "type": "Feature",
  "properties": {
    "iso:country":"US",
    "sg:address":"2218 Hilltop Dr",
    "sg:city":"Green Bay",
    "sg:classifiers":[
        {
            "category":"Arts & Performance",
            "subcategory":"Theater",
            "type":"Entertainment"
        }
    ],
    "sg:phone":"+1 920 405 0961",
    "sg:postcode":"54313",
    "sg:province":"WI",
    "sg:tags":[
        "group"
    ],
    "wof:name":"Lahti Entertainment LLC",
    "wof:placetype":"venue"
},
  "geometry": {"coordinates":[-88.08793,44.499981],"type":"Point"}
}