{
  "type": "Feature",
  "properties": {
    "addr:full":"259 N Fond du Lac Ave Campbellsport WI 53010",
    "addr:housenumber":"259",
    "addr:postcode":"53010",
    "addr:street":"N Fond Du Lac Ave",
    "iso:country":"US",
    "sg:address":"259 N Fond du Lac Ave",
    "sg:city":"Campbellsport",
    "sg:classifiers":[
        {
            "category":"Food & Beverages",
            "subcategory":"Groceries & Convenience Stores",
            "type":"Retail Goods"
        }
    ],
    "sg:phone":"+1 920 533 5544",
    "sg:postcode":"53010",
    "sg:province":"WI",
    "wof:name":"Fredon Holdings",
    "wof:placetype":"venue"
},
  "geometry": {"coordinates":[-88.286337,43.600158],"type":"Point"}
}