{
  "type": "Feature",
  "properties": {
    "iso:country":"US",
    "sg:address":"1417 Northport Dr",
    "sg:city":"Madison",
    "sg:classifiers":[
        {
            "category":"Retail",
            "subcategory":"Laundry & Dry Cleaning",
            "type":"Services"
        }
    ],
    "sg:phone":"+1 608 831 7274",
    "sg:postcode":"53704",
    "sg:province":"WI",
    "wof:name":"Northport Laundry",
    "wof:placetype":"venue"
},
  "geometry": {"coordinates":[-89.37299899999999,43.134587],"type":"Point"}
}