{
  "type": "Feature",
  "properties": {
    "iso:country":"US",
    "sg:address":"3124 Parkway Rd",
    "sg:city":"Antigo",
    "sg:classifiers":[
        {
            "category":"Real Estate",
            "subcategory":"Real Estate Agent",
            "type":"Services"
        }
    ],
    "sg:phone":"+1 715 623 3805",
    "sg:postcode":"54409",
    "sg:province":"WI",
    "wof:name":"A & K Investments V LLC",
    "wof:placetype":"venue"
},
  "geometry": {"coordinates":[-89.114797,45.142002],"type":"Point"}
}