{
  "type": "Feature",
  "properties": {
    "iso:country":"US",
    "sg:address":"11110 N Reedsburg Rd",
    "sg:city":"Baraboo",
    "sg:classifiers":[
        {
            "category":"Manufacturing",
            "subcategory":"Tools & Machinery",
            "type":"Manufacturing & Wholesale Goods"
        }
    ],
    "sg:phone":"+1 608 356 7969",
    "sg:postcode":"53913",
    "sg:province":"WI",
    "sg:tags":[
        "pattern",
        "industrial",
        "mfg"
    ],
    "wof:name":"Precision Pattern Works",
    "wof:placetype":"venue"
},
  "geometry": {"coordinates":[-89.768196,43.532504],"type":"Point"}
}