{
  "type": "Feature",
  "properties": {
    "iso:country":"US",
    "sg:address":"3035 River Birch Dr",
    "sg:city":"Brookfield",
    "sg:classifiers":[
        {
            "category":"Wholesale",
            "subcategory":"Medical Equipment & Supplies",
            "type":"Manufacturing & Wholesale Goods"
        }
    ],
    "sg:phone":"+1 262 789 7355",
    "sg:postcode":"53045",
    "sg:province":"WI",
    "wof:name":"Ziegler John",
    "wof:placetype":"venue"
},
  "geometry": {"coordinates":[-88.128658,43.075354],"type":"Point"}
}