{
  "type": "Feature",
  "properties": {
    "iso:country":"US",
    "sg:address":"3621 E Mallory Ave",
    "sg:city":"Cudahy",
    "sg:classifiers":[
        {
            "category":"Autos & Motor Vehicles",
            "subcategory":"Automobile Sales",
            "type":"Retail Goods"
        }
    ],
    "sg:phone":"+1 414 481 4235",
    "sg:postcode":"53110",
    "sg:province":"WI",
    "sg:tags":[
        "car",
        "dealer"
    ],
    "wof:name":"Vision Auto",
    "wof:placetype":"venue"
},
  "geometry": {"coordinates":[-87.85799799999999,42.946477],"type":"Point"}
}