{
  "type": "Feature",
  "properties": {
    "addr:full":"1020 Prospect Ln Kaukauna WI 54130",
    "addr:housenumber":"1020",
    "addr:postcode":"54130",
    "addr:street":"Prospect Ln",
    "iso:country":"US",
    "sg:address":"1020 Prospect Ln",
    "sg:city":"Kaukauna",
    "sg:classifiers":[
        {
            "category":"Building & Trades",
            "subcategory":"Construction",
            "type":"Services"
        }
    ],
    "sg:phone":"+1 920 766 1721",
    "sg:postcode":"54130",
    "sg:province":"WI",
    "sg:tags":[
        "concrete",
        "cutting",
        "breaking",
        "sawing"
    ],
    "wof:name":"Concrete Cutters Inc",
    "wof:placetype":"venue"
},
  "geometry": {"coordinates":[-88.26694999999999,44.299326],"type":"Point"}
}