{
  "type": "Feature",
  "properties": {
    "iso:country":"US",
    "sg:address":"523 US Hwy 51",
    "sg:city":"Poynette",
    "sg:classifiers":[
        {
            "category":"Restaurant",
            "type":"Food & Drink"
        }
    ],
    "sg:phone":"+1 608 635 7002",
    "sg:postcode":"53955",
    "sg:province":"WI",
    "sg:tags":[
        "grocery",
        "eating"
    ],
    "wof:name":"Poynette Town Mart",
    "wof:placetype":"venue"
},
  "geometry": {"coordinates":[-89.39532800000001,43.395282],"type":"Point"}
}