{
  "type": "Feature",
  "properties": {
    "iso:country":"US",
    "sg:address":"3915 Lovers Rd",
    "sg:city":"Loyal",
    "sg:classifiers":[
        {
            "category":"Retail",
            "subcategory":"Repair Shop",
            "type":"Services"
        }
    ],
    "sg:phone":"+1 715 255 8715",
    "sg:postcode":"54479",
    "sg:province":"WI",
    "wof:name":"Dd Repair",
    "wof:placetype":"venue"
},
  "geometry": {"coordinates":[-90.510435,44.806287],"type":"Point"}
}