{
  "type": "Feature",
  "properties": {
    "iso:country":"US",
    "sg:address":"13321 Co Hwy B",
    "sg:city":"Sparta",
    "sg:classifiers":[
        {
            "category":"Building & Trades",
            "subcategory":"Electrical",
            "type":"Services"
        }
    ],
    "sg:phone":"+1 608 269 4105",
    "sg:postcode":"54656",
    "sg:province":"WI",
    "sg:tags":[
        "electrical",
        "contractor"
    ],
    "wof:name":"Johns Electric",
    "wof:placetype":"venue"
},
  "geometry": {"coordinates":[-90.815023,43.996581],"type":"Point"}
}