{
  "type": "Feature",
  "properties": {
    "addr:full":"432 State Rd 33 E West Bend WI 53095",
    "addr:housenumber":"432;33 e",
    "addr:postcode":"53095",
    "addr:street":"State Rd",
    "iso:country":"US",
    "sg:address":"432 State Rd 33 E",
    "sg:city":"West Bend",
    "sg:classifiers":[
        {
            "category":"Autos & Motor Vehicles",
            "subcategory":"Fuel & Gas Station",
            "type":"Retail Goods"
        }
    ],
    "sg:phone":"+1 262 675 6649",
    "sg:postcode":"53095",
    "sg:province":"WI",
    "sg:tags":[
        "station",
        "gasoline"
    ],
    "wof:name":"Tripar Oil Co Incorporated",
    "wof:placetype":"venue"
},
  "geometry": {"coordinates":[-88.17609299999999,43.426752],"type":"Point"}
}