{
  "type": "Feature",
  "properties": {
    "addr:full":"515 Keyes St Menasha WI 54952",
    "addr:housenumber":"515",
    "addr:postcode":"54952",
    "addr:street":"Keyes St",
    "iso:country":"US",
    "sg:address":"515 Keyes St",
    "sg:city":"Menasha",
    "sg:classifiers":[
        {
            "category":"Building & Trades",
            "subcategory":"Construction",
            "type":"Services"
        }
    ],
    "sg:phone":"+1 920 725 7288",
    "sg:postcode":"54952",
    "sg:province":"WI",
    "sg:tags":[
        "house"
    ],
    "wof:name":"Brooks Builders",
    "wof:placetype":"venue"
},
  "geometry": {"coordinates":[-88.44329,44.198329],"type":"Point"}
}