{
  "type": "Feature",
  "properties": {
    "addr:full":"171 N Wells St Lake Geneva WI 53147",
    "addr:housenumber":"171",
    "addr:postcode":"53147",
    "addr:street":"N Wells St",
    "iso:country":"US",
    "sg:address":"171 N Wells St",
    "sg:city":"Lake Geneva",
    "sg:classifiers":[
        {
            "category":"Restaurant",
            "type":"Food & Drink"
        }
    ],
    "sg:menulink":"http://www.allmenus.com/wi/lake-geneva/181512-kfc---kentucky-fried-chicken/menu/",
    "sg:phone":"+1 262 248 2860",
    "sg:postcode":"53147",
    "sg:province":"WI",
    "sg:tags":[
        "american",
        "chicken"
    ],
    "wof:name":"KFC - Kentucky Fried Chicken",
    "wof:placetype":"venue"
},
  "geometry": {"coordinates":[-88.42899199999999,42.589975],"type":"Point"}
}