{
  "type": "Feature",
  "properties": {
    "iso:country":"US",
    "sg:address":"1346 Gem Ct",
    "sg:city":"Wisconsin Dells",
    "sg:classifiers":[
        {
            "category":"Professional",
            "subcategory":"Management & Consulting",
            "type":"Services"
        }
    ],
    "sg:phone":"+1 608 253 6617",
    "sg:postcode":"53965",
    "sg:province":"WI",
    "wof:name":"D/F Electronics",
    "wof:placetype":"venue"
},
  "geometry": {"coordinates":[-89.814414,43.711281],"type":"Point"}
}