{
  "type": "Feature",
  "properties": {
    "iso:country":"US",
    "sg:address":"345 W Wisconsin Ave",
    "sg:city":"Appleton",
    "sg:classifiers":[
        {
            "category":"Shopping",
            "subcategory":"Clothing, Apparel, & Fashions",
            "type":"Retail Goods"
        }
    ],
    "sg:phone":"+1 920 731 5948",
    "sg:postcode":"54911",
    "sg:province":"WI",
    "sg:tags":[
        "personal"
    ],
    "wof:name":"Brides The",
    "wof:placetype":"venue"
},
  "geometry": {"coordinates":[-88.410527,44.272862],"type":"Point"}
}