{
  "type": "Feature",
  "properties": {
    "addr:full":"3817 610th St Ellsworth WI 54011",
    "addr:housenumber":"3817",
    "addr:postcode":"54011",
    "addr:street":"610Th St",
    "iso:country":"US",
    "sg:address":"3817 610th St",
    "sg:city":"Ellsworth",
    "sg:classifiers":[
        {
            "category":"Professional",
            "subcategory":"Business Services",
            "type":"Services"
        }
    ],
    "sg:phone":"+1 715 273 3888",
    "sg:postcode":"54011",
    "sg:province":"WI",
    "wof:name":"Henry Bartel Auction Service",
    "wof:placetype":"venue"
},
  "geometry": {"coordinates":[-92.443376,44.676278],"type":"Point"}
}