{
  "type": "Feature",
  "properties": {
    "iso:country":"US",
    "sg:address":"1602 Robin Ln",
    "sg:city":"Wausau",
    "sg:classifiers":[
        {
            "category":"Professional",
            "subcategory":"Business Services",
            "type":"Services"
        }
    ],
    "sg:phone":"+1 715 843 9579",
    "sg:postcode":"54401",
    "sg:province":"WI",
    "sg:tags":[
        "liquidator"
    ],
    "wof:name":"J & P Liquidators",
    "wof:placetype":"venue"
},
  "geometry": {"coordinates":[-89.654985,44.930683],"type":"Point"}
}