{
  "type": "Feature",
  "properties": {
    "iso:country":"US",
    "sg:address":"167 W Grand Ave",
    "sg:city":"Beloit",
    "sg:classifiers":[
        {
            "category":"Shopping",
            "subcategory":"Clothing, Apparel, & Fashions",
            "type":"Retail Goods"
        }
    ],
    "sg:phone":"+1 608 313 3200",
    "sg:postcode":"53511",
    "sg:province":"IL",
    "sg:tags":[
        "item",
        "boutique"
    ],
    "wof:name":"Willie Etta's Boutique",
    "wof:placetype":"venue"
},
  "geometry": {"coordinates":[-89.038567,42.501678],"type":"Point"}
}