{
  "type": "Feature",
  "properties": {
    "addr:full":"1212 Charles St De Pere WI 54115",
    "addr:housenumber":"1212",
    "addr:postcode":"54115",
    "addr:street":"Charles St",
    "iso:country":"US",
    "sg:address":"1212 Charles St",
    "sg:city":"De Pere",
    "sg:classifiers":[
        {
            "category":"Recreation",
            "type":"Entertainment"
        }
    ],
    "sg:phone":"+1 920 339 4069",
    "sg:postcode":"54115",
    "sg:province":"WI",
    "sg:tags":[
        "pool",
        "swimming"
    ],
    "wof:name":"Legion Swimming Pool",
    "wof:placetype":"venue"
},
  "geometry": {"coordinates":[-88.049723,44.447617],"type":"Point"}
}