{
  "type": "Feature",
  "properties": {
    "addr:full":"3094 Lost Dauphin Rd De Pere WI 54115",
    "addr:housenumber":"3094",
    "addr:postcode":"54115",
    "addr:street":"Lost Dauphin Rd De",
    "iso:country":"US",
    "sg:address":"3094 Lost Dauphin Rd",
    "sg:city":"De Pere",
    "sg:phone":"+1 920 336 9623",
    "sg:postcode":"54115",
    "sg:province":"WI",
    "sg:tags":[
        "farm",
        "grain",
        "cash"
    ],
    "wof:name":"Huth Farms",
    "wof:placetype":"venue"
},
  "geometry": {"coordinates":[-88.125049,44.383467],"type":"Point"}
}