{
  "type": "Feature",
  "properties": {
    "addr:full":"8717 State Hwy 51 Rothschild WI 54474",
    "addr:housenumber":"8717",
    "addr:postcode":"54474",
    "addr:street":"State Hwy 51",
    "iso:country":"US",
    "sg:address":"8717 State Hwy 51",
    "sg:city":"Rothschild",
    "sg:classifiers":[
        {
            "category":"Bars & Pubs",
            "type":"Food & Drink"
        }
    ],
    "sg:phone":"+1 715 359 2381",
    "sg:postcode":"54474",
    "sg:province":"WI",
    "sg:tags":[
        "drinking"
    ],
    "wof:name":"Robin's Nest",
    "wof:placetype":"venue"
},
  "geometry": {"coordinates":[-89.633088,44.877424],"type":"Point"}
}