{
  "type": "Feature",
  "properties": {
    "iso:country":"US",
    "sg:address":"3975 N Teutonia Ave",
    "sg:city":"Milwaukee",
    "sg:classifiers":[
        {
            "category":"Banks & Credit Unions",
            "subcategory":"Bank",
            "type":"Services"
        }
    ],
    "sg:phone":"+1 414 449 3434",
    "sg:postcode":"53206",
    "sg:province":"WI",
    "sg:tags":[
        "cashing",
        "check"
    ],
    "wof:name":"Milwaukee Check Cashers",
    "wof:placetype":"venue"
},
  "geometry": {"coordinates":[-87.938624,43.088989],"type":"Point"}
}