{
  "type": "Feature",
  "properties": {
    "iso:country":"US",
    "sg:address":"1743 N Dr Martin Luther King Dr",
    "sg:city":"Milwaukee",
    "sg:classifiers":[
        {
            "category":"Shopping",
            "subcategory":"Used Merchandise",
            "type":"Retail Goods"
        }
    ],
    "sg:phone":"+1 414 265 0217",
    "sg:postcode":"53212",
    "sg:province":"WI",
    "sg:tags":[
        "shop",
        "consignment"
    ],
    "wof:name":"Deja Vu",
    "wof:placetype":"venue"
},
  "geometry": {"coordinates":[-87.914357,43.053292],"type":"Point"}
}