{
  "type": "Feature",
  "properties": {
    "addr:full":"1771 Allouez Ave Green Bay WI 54311",
    "addr:housenumber":"1771",
    "addr:postcode":"54311",
    "addr:street":"Allouez Ave",
    "iso:country":"US",
    "sg:address":"1771 Allouez Ave",
    "sg:city":"Green Bay",
    "sg:classifiers":[
        {
            "category":"Health Services",
            "subcategory":"Podiatrist",
            "type":"Services"
        }
    ],
    "sg:phone":"+1 920 469 5522",
    "sg:postcode":"54311",
    "sg:province":"WI",
    "wof:name":"Allouez Avenue Foot Clinic",
    "wof:placetype":"venue"
},
  "geometry": {"coordinates":[-87.99579900000001,44.470388],"type":"Point"}
}