{
  "type": "Feature",
  "properties": {
    "iso:country":"US",
    "sg:address":"1280 S Van Dyke Rd",
    "sg:city":"Appleton",
    "sg:classifiers":[
        {
            "category":"Retail",
            "subcategory":"Portrait Studio",
            "type":"Services"
        }
    ],
    "sg:phone":"+1 920 733 3089",
    "sg:postcode":"54914",
    "sg:province":"WI",
    "sg:tags":[
        "photographer",
        "photo"
    ],
    "sg:website":"www.lifetouch.com",
    "wof:name":"Lifetouch",
    "wof:placetype":"venue"
},
  "geometry": {"coordinates":[-88.468042,44.246069],"type":"Point"}
}