{
  "type": "Feature",
  "properties": {
    "iso:country":"US",
    "sg:address":"W62N248 Washington Ave Rear",
    "sg:city":"Cedarburg",
    "sg:classifiers":[
        {
            "category":"Banks & Credit Unions",
            "subcategory":"Bank",
            "type":"Services"
        },
        {
            "category":"Banks & Credit Unions",
            "subcategory":"Financial Services",
            "type":"Services"
        }
    ],
    "sg:phone":"+1 262 377 9222",
    "sg:postcode":"53012",
    "sg:province":"WI",
    "sg:tags":[
        "broker",
        "mortgage"
    ],
    "sg:website":"bankmutual.com",
    "wof:name":"Bank Mutual",
    "wof:placetype":"venue"
},
  "geometry": {"coordinates":[-87.986801,43.284599],"type":"Point"}
}