{
  "type": "Feature",
  "properties": {
    "iso:country":"US",
    "sg:address":"729 6th St S",
    "sg:city":"La Crosse",
    "sg:classifiers":[
        {
            "category":"Shopping",
            "subcategory":"Used Merchandise",
            "type":"Retail Goods"
        }
    ],
    "sg:phone":"+1 608 784 6973",
    "sg:postcode":"54601",
    "sg:province":"WI",
    "sg:tags":[
        "shop",
        "consignment"
    ],
    "wof:name":"Friendship Tree Too",
    "wof:placetype":"venue"
},
  "geometry": {"coordinates":[-91.248678,43.803933],"type":"Point"}
}