{
  "type": "Feature",
  "properties": {
    "addr:full":"1509 Rapids Dr Racine WI 53404",
    "addr:housenumber":"1509",
    "addr:postcode":"53404",
    "addr:street":"Rapids Dr",
    "iso:country":"US",
    "sg:address":"1509 Rapids Dr",
    "sg:city":"Racine",
    "sg:classifiers":[
        {
            "category":"Manufacturing",
            "subcategory":"Tools & Machinery",
            "type":"Manufacturing & Wholesale Goods"
        }
    ],
    "sg:phone":"+1 262 632 1229",
    "sg:postcode":"53404",
    "sg:province":"WI",
    "sg:tags":[
        "control",
        "environmental",
        "mfg"
    ],
    "wof:name":"Lake Air International Inc",
    "wof:placetype":"venue"
},
  "geometry": {"coordinates":[-87.800246,42.744603],"type":"Point"}
}