{
  "type": "Feature",
  "properties": {
    "iso:country":"US",
    "sg:address":"1461 Western Ave",
    "sg:city":"Jackson",
    "sg:classifiers":[
        {
            "category":"Farming",
            "subcategory":"Dairy Farm",
            "type":"Manufacturing & Wholesale Goods"
        }
    ],
    "sg:phone":"+1 262 677 3243",
    "sg:postcode":"53037",
    "sg:province":"WI",
    "wof:name":"Gerald Groth",
    "wof:placetype":"venue"
},
  "geometry": {"coordinates":[-88.111886,43.294188],"type":"Point"}
}