{
  "type": "Feature",
  "properties": {
    "iso:country":"US",
    "sg:address":"522 N Bay Shore Dr",
    "sg:city":"Sister Bay",
    "sg:classifiers":[
        {
            "category":"Home & Garden",
            "subcategory":"Building Materials",
            "type":"Retail Goods"
        }
    ],
    "sg:phone":"+1 920 854 4825",
    "sg:postcode":"54234",
    "sg:province":"WI",
    "sg:tags":[
        "glass",
        "leaded"
    ],
    "wof:name":"Eight Of Pentacles",
    "wof:placetype":"venue"
},
  "geometry": {"coordinates":[-87.122227,45.187871],"type":"Point"}
}