{
  "type": "Feature",
  "properties": {
    "iso:country":"US",
    "sg:address":"6560 S Lovers Lane Rd",
    "sg:city":"Franklin",
    "sg:classifiers":[
        {
            "category":"Home & Garden",
            "subcategory":"Household Appliances",
            "type":"Retail Goods"
        }
    ],
    "sg:phone":"+1 414 529 1907",
    "sg:postcode":"53132",
    "sg:province":"WI",
    "sg:tags":[
        "refrigerator",
        "freezer"
    ],
    "wof:name":"Freeze Aire Refrigeration",
    "wof:placetype":"venue"
},
  "geometry": {"coordinates":[-88.047079,42.924898],"type":"Point"}
}