{
  "type": "Feature",
  "properties": {
    "addr:full":"1184 W Main St Whitewater WI 53190",
    "addr:housenumber":"1184",
    "addr:postcode":"53190",
    "addr:street":"W Main St",
    "iso:country":"US",
    "sg:address":"1184 W Main St",
    "sg:city":"Whitewater",
    "sg:classifiers":[
        {
            "category":"Food & Beverages",
            "subcategory":"Groceries & Convenience Stores",
            "type":"Retail Goods"
        }
    ],
    "sg:phone":"+1 262 473 7770",
    "sg:postcode":"53190",
    "sg:province":"WI",
    "wof:name":"Speedway 4189",
    "wof:placetype":"venue"
},
  "geometry": {"coordinates":[-88.751802,42.834904],"type":"Point"}
}