{
  "type": "Feature",
  "properties": {
    "addr:full":"10201 W Innovation Dr Wauwatosa WI 53226",
    "addr:housenumber":"10201",
    "addr:postcode":"53226",
    "addr:street":"W Innovation Dr",
    "iso:country":"US",
    "sg:address":"10201 W Innovation Dr",
    "sg:city":"Wauwatosa",
    "sg:classifiers":[
        {
            "category":"Shopping",
            "subcategory":"Computers & Home Electronics",
            "type":"Retail Goods"
        }
    ],
    "sg:phone":"+1 414 266 9600",
    "sg:postcode":"53226",
    "sg:province":"WI",
    "sg:tags":[
        "software"
    ],
    "wof:name":"Computer Aided Technology",
    "wof:placetype":"venue"
},
  "geometry": {"coordinates":[-88.043351,43.044393],"type":"Point"}
}