{
  "type": "Feature",
  "properties": {
    "iso:country":"US",
    "sg:address":"822 York St",
    "sg:city":"Manitowoc",
    "sg:classifiers":[
        {
            "category":"Personal",
            "subcategory":"Beauty Salon",
            "type":"Services"
        }
    ],
    "sg:phone":"+1 920 686 1190",
    "sg:postcode":"54220",
    "sg:province":"WI",
    "sg:tags":[
        "shop"
    ],
    "wof:name":"Ambiance Salon",
    "wof:placetype":"venue"
},
  "geometry": {"coordinates":[-87.658979,44.09385],"type":"Point"}
}