{
  "type": "Feature",
  "properties": {
    "addr:full":"1245 Cheyenne Ave Grafton WI 53024",
    "addr:housenumber":"1245",
    "addr:postcode":"53024",
    "addr:street":"Cheyenne Ave",
    "iso:country":"US",
    "sg:address":"1245 Cheyenne Ave",
    "sg:city":"Grafton",
    "sg:classifiers":[
        {
            "category":"Real Estate",
            "subcategory":"Real Estate Agent",
            "type":"Services"
        }
    ],
    "sg:phone":"+1 262 284 6054",
    "sg:postcode":"53024",
    "sg:province":"WI",
    "wof:name":"Shore West",
    "wof:placetype":"venue"
},
  "geometry": {"coordinates":[-87.935242,43.31956],"type":"Point"}
}