{
  "type": "Feature",
  "properties": {
    "iso:country":"US",
    "sg:address":"7 S 1st St",
    "sg:city":"Barron",
    "sg:classifiers":[
        {
            "category":"Freight",
            "type":"Transportation"
        }
    ],
    "sg:phone":"+1 715 837 1584",
    "sg:postcode":"54812",
    "sg:province":"WI",
    "sg:tags":[
        "trucking"
    ],
    "wof:name":"Mizer Trucking Inc",
    "wof:placetype":"venue"
},
  "geometry": {"coordinates":[-91.85667599999999,45.401388],"type":"Point"}
}