{
  "type": "Feature",
  "properties": {
    "iso:country":"US",
    "sg:address":"900 W Lake St",
    "sg:city":"Horicon",
    "sg:classifiers":[
        {
            "category":"Wholesale",
            "subcategory":"Metals & Minerals",
            "type":"Manufacturing & Wholesale Goods"
        }
    ],
    "sg:phone":"+1 920 485 3133",
    "sg:postcode":"53032",
    "sg:province":"WI",
    "sg:tags":[
        "center"
    ],
    "wof:name":"J Rubin & Co",
    "wof:placetype":"venue"
},
  "geometry": {"coordinates":[-88.647685,43.453313],"type":"Point"}
}