{
  "type": "Feature",
  "properties": {
    "iso:country":"US",
    "sg:address":"6237 W National Ave",
    "sg:city":"Milwaukee",
    "sg:classifiers":[
        {
            "category":"Shopping",
            "type":"Retail Goods"
        }
    ],
    "sg:phone":"+1 414 607 6542",
    "sg:postcode":"53214",
    "sg:province":"WI",
    "sg:tags":[
        "candle"
    ],
    "wof:name":"Candle Shop",
    "wof:placetype":"venue"
},
  "geometry": {"coordinates":[-87.99063700000001,43.016357],"type":"Point"}
}