{
  "type": "Feature",
  "properties": {
    "iso:country":"US",
    "sg:address":"1930 8th St S",
    "sg:city":"Wisconsin Rapids",
    "sg:classifiers":[
        {
            "category":"Banks & Credit Unions",
            "subcategory":"Bank",
            "type":"Services"
        }
    ],
    "sg:phone":"+1 715 423 2650",
    "sg:postcode":"54494",
    "sg:province":"WI",
    "sg:tags":[
        "loan",
        "real estate"
    ],
    "sg:website":"www.becu.net",
    "wof:name":"Bull's Eye Credit Union",
    "wof:placetype":"venue"
},
  "geometry": {"coordinates":[-89.817097,44.377213],"type":"Point"}
}