{
  "type": "Feature",
  "properties": {
    "iso:country":"US",
    "sg:address":"2041 N 107th St",
    "sg:city":"Milwaukee",
    "sg:classifiers":[
        {
            "category":"Health Services",
            "subcategory":"Doctor",
            "type":"Services"
        }
    ],
    "sg:phone":"+1 414 257 9499",
    "sg:postcode":"53226",
    "sg:province":"WI",
    "sg:tags":[
        "medical"
    ],
    "wof:name":"Huntingtons Disease Society",
    "wof:placetype":"venue"
},
  "geometry": {"coordinates":[-88.046199,43.057836],"type":"Point"}
}