{
  "type": "Feature",
  "properties": {
    "iso:country":"US",
    "sg:address":"3746 S Kansas Ave",
    "sg:city":"Milwaukee",
    "sg:classifiers":[
        {
            "category":"Organizations",
            "subcategory":"Religious Organization",
            "type":"Services"
        }
    ],
    "sg:phone":"+1 414 483 3809",
    "sg:postcode":"53207",
    "sg:province":"WI",
    "sg:tags":[
        "monastery",
        "convent"
    ],
    "wof:name":"Sisters Of St Francis",
    "wof:placetype":"venue"
},
  "geometry": {"coordinates":[-87.887046,42.974657],"type":"Point"}
}