{
  "type": "Feature",
  "properties": {
    "iso:country":"US",
    "sg:address":"5703 8th Ave",
    "sg:city":"Kenosha",
    "sg:classifiers":[
        {
            "category":"Professional",
            "subcategory":"Computer Services",
            "type":"Services"
        }
    ],
    "sg:phone":"+1 262 657 7351",
    "sg:postcode":"53140",
    "sg:province":"WI",
    "wof:name":"Computer Wiz",
    "wof:placetype":"venue"
},
  "geometry": {"coordinates":[-87.820569,42.582984],"type":"Point"}
}