{
  "type": "Feature",
  "properties": {
    "iso:country":"US",
    "sg:address":"2301 S Oneida St",
    "sg:city":"Green Bay",
    "sg:classifiers":[
        {
            "category":"Organizations",
            "subcategory":"Labor Organization",
            "type":"Services"
        }
    ],
    "sg:phone":"+1 920 498 1102",
    "sg:postcode":"54304",
    "sg:province":"WI",
    "wof:name":"Uaw Local 1102",
    "wof:placetype":"venue"
},
  "geometry": {"coordinates":[-88.066446,44.487445],"type":"Point"}
}