{
  "type": "Feature",
  "properties": {
    "iso:country":"US",
    "sg:address":"322 Broadway St",
    "sg:city":"Berlin",
    "sg:classifiers":[
        {
            "category":"Shopping",
            "type":"Retail Goods"
        }
    ],
    "sg:phone":"+1 920 361 0485",
    "sg:postcode":"54923",
    "sg:province":"WI",
    "sg:tags":[
        "hearing",
        "equipment",
        "supply",
        "impaired"
    ],
    "wof:name":"Hearing Aids",
    "wof:placetype":"venue"
},
  "geometry": {"coordinates":[-88.95607699999999,43.968267],"type":"Point"}
}