{
  "type": "Feature",
  "properties": {
    "iso:country":"US",
    "sg:address":"8054 US Hwy 151",
    "sg:city":"Fond Du Lac",
    "sg:classifiers":[
        {
            "category":"Farming",
            "subcategory":"Livestock Farm",
            "type":"Manufacturing & Wholesale Goods"
        }
    ],
    "sg:phone":"+1 920 921 9842",
    "sg:postcode":"54935",
    "sg:province":"WI",
    "sg:tags":[
        "sporting",
        "equine"
    ],
    "wof:name":"Horseshoe Springs Tack Shop",
    "wof:placetype":"venue"
},
  "geometry": {"coordinates":[-88.37552,43.831609],"type":"Point"}
}