{
  "type": "Feature",
  "properties": {
    "iso:country":"US",
    "sg:address":"443 Grant St",
    "sg:city":"Hartford",
    "sg:classifiers":[
        {
            "category":"Manufacturing",
            "subcategory":"Signs",
            "type":"Manufacturing & Wholesale Goods"
        }
    ],
    "sg:phone":"+1 262 673 5248",
    "sg:postcode":"53027",
    "sg:province":"WI",
    "wof:name":"Brush Works Plus LLC",
    "wof:placetype":"venue"
},
  "geometry": {"coordinates":[-88.384692,43.323233],"type":"Point"}
}