{
  "type": "Feature",
  "properties": {
    "addr:full":"1755 N Calhoun Rd Brookfield WI 53005",
    "addr:housenumber":"1755",
    "addr:postcode":"53005",
    "addr:street":"N Calhoun Rd",
    "iso:country":"US",
    "sg:address":"1755 N Calhoun Rd",
    "sg:city":"Brookfield",
    "sg:classifiers":[
        {
            "category":"Organizations",
            "subcategory":"Religious Organization",
            "type":"Services"
        }
    ],
    "sg:phone":"+1 262 796 3940",
    "sg:postcode":"53005",
    "sg:province":"WI",
    "sg:tags":[
        "church"
    ],
    "sg:website":"www.stjohnv.org",
    "wof:name":"St John Vianney Parish",
    "wof:placetype":"venue"
},
  "geometry": {"coordinates":[-88.12639799999999,43.056923],"type":"Point"}
}