{
  "type": "Feature",
  "properties": {
    "iso:country":"US",
    "sg:address":"4000 Olson Dr",
    "sg:city":"Viroqua",
    "sg:classifiers":[
        {
            "category":"Professional",
            "subcategory":"Engineering",
            "type":"Services"
        }
    ],
    "sg:phone":"+1 608 634 4564",
    "sg:postcode":"54665",
    "sg:province":"WI",
    "wof:name":"Welch Engineering Inc",
    "wof:placetype":"venue"
},
  "geometry": {"coordinates":[-90.974038,43.584182],"type":"Point"}
}