{
  "type": "Feature",
  "properties": {
    "iso:country":"US",
    "sg:address":"250 E Main St",
    "sg:city":"Waukesha",
    "sg:classifiers":[
        {
            "category":"Shopping",
            "subcategory":"Used Merchandise",
            "type":"Retail Goods"
        }
    ],
    "sg:phone":"+1 262 549 4404",
    "sg:postcode":"53186",
    "sg:province":"WI",
    "wof:name":"Fox Riverwalk Antique Mall LLC",
    "wof:placetype":"venue"
},
  "geometry": {"coordinates":[-88.225544,43.013258],"type":"Point"}
}