{
  "type": "Feature",
  "properties": {
    "iso:country":"US",
    "sg:address":"116 W Main St",
    "sg:city":"Mt Hope",
    "sg:classifiers":[
        {
            "category":"Banks & Credit Unions",
            "subcategory":"Bank",
            "type":"Services"
        }
    ],
    "sg:phone":"+1 608 988 4512",
    "sg:postcode":"53816",
    "sg:province":"WI",
    "wof:name":"Peoples State Bank",
    "wof:placetype":"venue"
},
  "geometry": {"coordinates":[-90.86017099999999,42.966972],"type":"Point"}
}