{
  "type": "Feature",
  "properties": {
    "iso:country":"US",
    "sg:address":"5807 Aspen Ct",
    "sg:city":"Mc Farland",
    "sg:classifiers":[
        {
            "category":"Manufacturing",
            "subcategory":"Printing",
            "type":"Manufacturing & Wholesale Goods"
        }
    ],
    "sg:phone":"+1 608 838 0096",
    "sg:postcode":"53558",
    "sg:province":"WI",
    "sg:tags":[
        "laser"
    ],
    "wof:name":"North American Peripherals",
    "wof:placetype":"venue"
},
  "geometry": {"coordinates":[-89.280096,43.020172],"type":"Point"}
}