{
  "type": "Feature",
  "properties": {
    "addr:full":"20100 W Greenfield Ave Brookfield WI 53045",
    "addr:housenumber":"20100",
    "addr:postcode":"53045",
    "addr:street":"W Greenfield Ave",
    "iso:country":"US",
    "sg:address":"20100 W Greenfield Ave",
    "sg:city":"Brookfield",
    "sg:classifiers":[
        {
            "category":"Health Services",
            "subcategory":"Doctor",
            "type":"Services"
        }
    ],
    "sg:phone":"+1 262 786 4819",
    "sg:postcode":"53045",
    "sg:province":"WI",
    "sg:tags":[
        "dentist"
    ],
    "wof:name":"Thomas J Mc Carthy & Assoc",
    "wof:placetype":"venue"
},
  "geometry": {"coordinates":[-88.16469600000001,43.017229],"type":"Point"}
}