{
  "type": "Feature",
  "properties": {
    "addr:full":"3235 Brook Dr Medford WI 54451",
    "addr:housenumber":"3235",
    "addr:postcode":"54451",
    "addr:street":"Brook Dr",
    "iso:country":"US",
    "sg:address":"3235 Brook Dr",
    "sg:city":"Medford",
    "sg:classifiers":[
        {
            "category":"Building & Trades",
            "subcategory":"Construction",
            "type":"Services"
        }
    ],
    "sg:phone":"+1 715 748 3269",
    "sg:postcode":"54451",
    "sg:province":"WI",
    "sg:tags":[
        "remodeling",
        "gen"
    ],
    "wof:name":"Russ Thums Construction",
    "wof:placetype":"venue"
},
  "geometry": {"coordinates":[-90.443442,45.146692],"type":"Point"}
}