{
  "type": "Feature",
  "properties": {
    "addr:full":"6635 McKee Rd Madison WI 53593",
    "addr:housenumber":"6635",
    "addr:postcode":"53593",
    "addr:street":"Mckee Rd",
    "iso:country":"US",
    "sg:address":"6635 McKee Rd",
    "sg:city":"Madison",
    "sg:classifiers":[
        {
            "category":"Retail",
            "subcategory":"Laundry & Dry Cleaning",
            "type":"Services"
        }
    ],
    "sg:phone":"+1 608 848 9971",
    "sg:postcode":"53593",
    "sg:province":"WI",
    "sg:tags":[
        "cleaners"
    ],
    "wof:name":"TLC Dry Cleaning",
    "wof:placetype":"venue"
},
  "geometry": {"coordinates":[-89.491843,43.015635],"type":"Point"}
}