{
  "type": "Feature",
  "properties": {
    "iso:country":"US",
    "sg:address":"1067 25th St",
    "sg:city":"Cameron",
    "sg:classifiers":[
        {
            "category":"Health Services",
            "subcategory":"Doctor",
            "type":"Services"
        }
    ],
    "sg:phone":"+1 715 859 6204",
    "sg:postcode":"54822",
    "sg:province":"WI",
    "wof:name":"Kevin L Masters DDS",
    "wof:placetype":"venue"
},
  "geometry": {"coordinates":[-91.641729,45.359543],"type":"Point"}
}