{
  "type": "Feature",
  "properties": {
    "iso:country":"US",
    "sg:address":"2800 Cleveland Ave",
    "sg:city":"Stevens Point",
    "sg:classifiers":[
        {
            "category":"Personal",
            "subcategory":"Beauty Salon",
            "type":"Services"
        }
    ],
    "sg:phone":"+1 715 341 8212",
    "sg:postcode":"54481",
    "sg:province":"WI",
    "sg:tags":[
        "shop"
    ],
    "wof:name":"Salon Ultimate",
    "wof:placetype":"venue"
},
  "geometry": {"coordinates":[-89.566882,44.509598],"type":"Point"}
}