{
  "type": "Feature",
  "properties": {
    "iso:country":"US",
    "sg:address":"840 E Hancock St",
    "sg:city":"Appleton",
    "sg:classifiers":[
        {
            "category":"Shopping",
            "type":"Retail Goods"
        }
    ],
    "sg:phone":"+1 920 468 0700",
    "sg:postcode":"54911",
    "sg:province":"WI",
    "sg:tags":[
        "merchandise"
    ],
    "wof:name":"Green Bay Aquarium Society",
    "wof:placetype":"venue"
},
  "geometry": {"coordinates":[-88.39353800000001,44.268885],"type":"Point"}
}