{
  "type": "Feature",
  "properties": {
    "iso:country":"US",
    "sg:address":"936 E Side Rd",
    "sg:city":"Birchwood",
    "sg:classifiers":[
        {
            "category":"Building & Trades",
            "subcategory":"Construction",
            "type":"Services"
        }
    ],
    "sg:phone":"+1 715 354 7994",
    "sg:postcode":"54817",
    "sg:province":"WI",
    "sg:tags":[
        "excavation",
        "contractor"
    ],
    "wof:name":"Dig This Excavating",
    "wof:placetype":"venue"
},
  "geometry": {"coordinates":[-91.679613,45.668522],"type":"Point"}
}