{
  "type": "Feature",
  "properties": {
    "addr:full":"1598 State Hwy 49 Wittenberg WI 54499",
    "addr:housenumber":"1598",
    "addr:postcode":"54499",
    "addr:street":"State Hwy 49",
    "iso:country":"US",
    "sg:address":"1598 State Hwy 49",
    "sg:city":"Wittenberg",
    "sg:classifiers":[
        {
            "category":"Farming",
            "subcategory":"Livestock Farm",
            "type":"Manufacturing & Wholesale Goods"
        }
    ],
    "sg:phone":"+1 715 454 6649",
    "sg:postcode":"54499",
    "sg:province":"WI",
    "sg:tags":[
        "animal",
        "general"
    ],
    "wof:name":"Bushmans Riverside Ranch Inc",
    "wof:placetype":"venue"
},
  "geometry": {"coordinates":[-89.263233,44.713809],"type":"Point"}
}