{
  "type": "Feature",
  "properties": {
    "iso:country":"US",
    "sg:address":"301 Harbour Town Dr",
    "sg:city":"Madison",
    "sg:classifiers":[
        {
            "category":"Professional",
            "subcategory":"Business Services",
            "type":"Services"
        }
    ],
    "sg:phone":"+1 608 829 0309",
    "sg:postcode":"53717",
    "sg:province":"WI",
    "wof:name":"Ruffin Technologies",
    "wof:placetype":"venue"
},
  "geometry": {"coordinates":[-89.52563,43.067782],"type":"Point"}
}