{
  "type": "Feature",
  "properties": {
    "iso:country":"US",
    "sg:address":"310 W Main St",
    "sg:city":"Sparta",
    "sg:classifiers":[
        {
            "category":"Health Services",
            "subcategory":"Hospital",
            "type":"Services"
        }
    ],
    "sg:phone":"+1 608 269 4132",
    "sg:postcode":"54656",
    "sg:province":"WI",
    "sg:tags":[
        "clinic",
        "alcohol"
    ],
    "wof:name":"Alcohol & Drug Abuse Treatment",
    "wof:placetype":"venue"
},
  "geometry": {"coordinates":[-90.815062,43.944445],"type":"Point"}
}