{
  "type": "Feature",
  "properties": {
    "iso:country":"US",
    "sg:address":"1170 W Windlake Ave",
    "sg:city":"Milwaukee",
    "sg:classifiers":[
        {
            "category":"Education",
            "subcategory":"School",
            "type":"Public Place"
        }
    ],
    "sg:phone":"+1 414 643 6943",
    "sg:postcode":"53215",
    "sg:province":"WI",
    "wof:name":"Badger State Baptist School",
    "wof:placetype":"venue"
},
  "geometry": {"coordinates":[-87.92766,43.005273],"type":"Point"}
}