{
  "type": "Feature",
  "properties": {
    "addr:full":"675 Industrial Ct Hartland WI 53029",
    "addr:housenumber":"675",
    "addr:postcode":"53029",
    "addr:street":"Industrial Ct",
    "iso:country":"US",
    "sg:address":"675 Industrial Ct",
    "sg:city":"Hartland",
    "sg:classifiers":[
        {
            "category":"Wholesale",
            "subcategory":"Chemicals & Plastics",
            "type":"Manufacturing & Wholesale Goods"
        }
    ],
    "sg:phone":"+1 262 369 9820",
    "sg:postcode":"53029",
    "sg:province":"WI",
    "wof:name":"Todd & Assoc",
    "wof:placetype":"venue"
},
  "geometry": {"coordinates":[-88.359866,43.093421],"type":"Point"}
}