{
  "type": "Feature",
  "properties": {
    "iso:country":"US",
    "sg:address":"1045 Oak St",
    "sg:city":"Wisconsin Dells",
    "sg:classifiers":[
        {
            "category":"Shopping",
            "subcategory":"Computers & Home Electronics",
            "type":"Retail Goods"
        }
    ],
    "sg:phone":"+1 608 253 2720",
    "sg:postcode":"53965",
    "sg:province":"WI",
    "wof:name":"P C Xtreme",
    "wof:placetype":"venue"
},
  "geometry": {"coordinates":[-89.772497,43.631555],"type":"Point"}
}