{
  "type": "Feature",
  "properties": {
    "iso:country":"US",
    "sg:address":"13 Dutch Harbor Ests",
    "sg:city":"Little Chute",
    "sg:classifiers":[
        {
            "category":"Wholesale",
            "subcategory":"Machinery & Supplies",
            "type":"Manufacturing & Wholesale Goods"
        }
    ],
    "sg:phone":"+1 920 968 2430",
    "sg:postcode":"54140",
    "sg:province":"WI",
    "sg:tags":[
        "equipment",
        "industrial"
    ],
    "wof:name":"Industrial Tech Serv",
    "wof:placetype":"venue"
},
  "geometry": {"coordinates":[-88.32720399999999,44.288187],"type":"Point"}
}