{
  "type": "Feature",
  "properties": {
    "iso:country":"US",
    "sg:address":"2220 American Dr",
    "sg:city":"Neenah",
    "sg:classifiers":[
        {
            "category":"Manufacturing",
            "subcategory":"Tools & Machinery",
            "type":"Manufacturing & Wholesale Goods"
        }
    ],
    "sg:phone":"+1 920 830 8247",
    "sg:postcode":"54956",
    "sg:province":"WI",
    "sg:tags":[
        "machine",
        "shop"
    ],
    "wof:name":"Munishing Corp",
    "wof:placetype":"venue"
},
  "geometry": {"coordinates":[-88.469367,44.233167],"type":"Point"}
}