{
  "type": "Feature",
  "properties": {
    "iso:country":"US",
    "sg:address":"115 Alpine Ct",
    "sg:city":"Shawano",
    "sg:classifiers":[
        {
            "category":"Health Services",
            "subcategory":"Doctor",
            "type":"Services"
        }
    ],
    "sg:phone":"+1 715 526 2544",
    "sg:postcode":"54166",
    "sg:province":"WI",
    "sg:tags":[
        "dentist"
    ],
    "wof:name":"William P Swetlik DDS",
    "wof:placetype":"venue"
},
  "geometry": {"coordinates":[-88.608841,44.788862],"type":"Point"}
}