{
  "type": "Feature",
  "properties": {
    "addr:full":"231 N 114th St Milwaukee WI 53226",
    "addr:housenumber":"231",
    "addr:postcode":"53226",
    "addr:street":"N 114Th St",
    "iso:country":"US",
    "sg:address":"231 N 114th St",
    "sg:city":"Milwaukee",
    "sg:classifiers":[
        {
            "category":"Health Services",
            "subcategory":"Clinic",
            "type":"Services"
        }
    ],
    "sg:phone":"+1 414 803 5624",
    "sg:postcode":"53226",
    "sg:province":"WI",
    "wof:name":"Professional Medical Screening",
    "wof:placetype":"venue"
},
  "geometry": {"coordinates":[-88.055122,43.033461],"type":"Point"}
}