{
  "type": "Feature",
  "properties": {
    "addr:full":"4575 Moore St Wabeno WI 54566",
    "addr:housenumber":"4575",
    "addr:postcode":"54566",
    "addr:street":"Moore St",
    "iso:country":"US",
    "sg:address":"4575 Moore St",
    "sg:city":"Wabeno",
    "sg:classifiers":[
        {
            "category":"Government",
            "subcategory":"Office",
            "type":"Public Place"
        }
    ],
    "sg:phone":"+1 715 473 4608",
    "sg:postcode":"54566",
    "sg:province":"WI",
    "sg:tags":[
        "village"
    ],
    "wof:name":"Wabeno Town Shop",
    "wof:placetype":"venue"
},
  "geometry": {"coordinates":[-88.65544800000001,45.440191],"type":"Point"}
}