{
  "type": "Feature",
  "properties": {
    "iso:country":"US",
    "sg:address":"10605 W North Ave",
    "sg:city":"Wauwatosa",
    "sg:classifiers":[
        {
            "category":"Banks & Credit Unions",
            "subcategory":"Bank",
            "type":"Services"
        }
    ],
    "sg:phone":"+1 414 486 4500",
    "sg:postcode":"53226",
    "sg:province":"WI",
    "wof:name":"Milwaukee Metropolitan CU",
    "wof:placetype":"venue"
},
  "geometry": {"coordinates":[-88.046118,43.060041],"type":"Point"}
}