{
  "type": "Feature",
  "properties": {
    "iso:country":"US",
    "sg:address":"622 State Hwy 54",
    "sg:city":"Black River Fls",
    "sg:classifiers":[
        {
            "category":"Restaurant",
            "type":"Food & Drink"
        }
    ],
    "sg:phone":"+1 715 284 8325",
    "sg:postcode":"54615",
    "sg:province":"WI",
    "sg:tags":[
        "eating"
    ],
    "wof:name":"Oriental Kitchen",
    "wof:placetype":"venue"
},
  "geometry": {"coordinates":[-90.855557,44.294609],"type":"Point"}
}