{
  "type": "Feature",
  "properties": {
    "iso:country":"US",
    "sg:address":"231 Michigan St",
    "sg:city":"Sturgeon Bay",
    "sg:classifiers":[
        {
            "category":"Shopping",
            "subcategory":"Gifts & Souvenirs",
            "type":"Retail Goods"
        }
    ],
    "sg:phone":"+1 920 743 5695",
    "sg:postcode":"54235",
    "sg:province":"WI",
    "sg:tags":[
        "shop"
    ],
    "wof:name":"Great Bakes & Gifts",
    "wof:placetype":"venue"
},
  "geometry": {"coordinates":[-87.37653,44.834022],"type":"Point"}
}