{
  "type": "Feature",
  "properties": {
    "addr:full":"260 S Tyler St Lancaster WI 53813",
    "addr:housenumber":"260",
    "addr:postcode":"53813",
    "addr:street":"S Tyler St",
    "iso:country":"US",
    "sg:address":"260 S Tyler St",
    "sg:city":"Lancaster",
    "sg:classifiers":[
        {
            "category":"Insurance",
            "subcategory":"Insurance Agent",
            "type":"Services"
        }
    ],
    "sg:phone":"+1 608 723 7755",
    "sg:postcode":"53813",
    "sg:province":"WI",
    "wof:name":"Carl R Thiede",
    "wof:placetype":"venue"
},
  "geometry": {"coordinates":[-90.715306,42.846325],"type":"Point"}
}