{
  "type": "Feature",
  "properties": {
    "iso:country":"US",
    "sg:address":"402 E Fremont St",
    "sg:city":"Appleton",
    "sg:classifiers":[
        {
            "category":"Professional",
            "subcategory":"Employment Agencies",
            "type":"Services"
        }
    ],
    "sg:phone":"+1 920 831 4141",
    "sg:postcode":"54915",
    "sg:province":"WI",
    "sg:tags":[
        "help",
        "supply"
    ],
    "wof:name":"Personal Touch Cleaning Servic",
    "wof:placetype":"venue"
},
  "geometry": {"coordinates":[-88.398143,44.249923],"type":"Point"}
}