{
  "type": "Feature",
  "properties": {
    "iso:country":"US",
    "sg:address":"1221 Menomonie St",
    "sg:city":"Eau Claire",
    "sg:classifiers":[
        {
            "category":"Wholesale",
            "subcategory":"Stationery",
            "type":"Manufacturing & Wholesale Goods"
        }
    ],
    "sg:phone":"+1 715 878 9414",
    "sg:postcode":"54703",
    "sg:province":"WI",
    "wof:name":"Galaxy Paper Products West",
    "wof:placetype":"venue"
},
  "geometry": {"coordinates":[-91.528522,44.799963],"type":"Point"}
}