{
  "type": "Feature",
  "properties": {
    "addr:full":"103 Hi Corners Rd Scandinavia WI 54977",
    "addr:housenumber":"103",
    "addr:postcode":"54977",
    "addr:street":"Hi Corners Rd",
    "iso:country":"US",
    "sg:address":"103 Hi Corners Rd",
    "sg:city":"Scandinavia",
    "sg:classifiers":[
        {
            "category":"Home & Garden",
            "subcategory":"Garden Supply",
            "type":"Retail Goods"
        }
    ],
    "sg:phone":"+1 715 467 2682",
    "sg:postcode":"54977",
    "sg:province":"WI",
    "sg:tags":[
        "nurseryman"
    ],
    "wof:name":"Vandaalwyk Tree Farm",
    "wof:placetype":"venue"
},
  "geometry": {"coordinates":[-89.210943,44.45942],"type":"Point"}
}