{
  "type": "Feature",
  "properties": {
    "addr:full":"1030 N High Point Rd Madison WI 53717",
    "addr:housenumber":"1030",
    "addr:postcode":"53717",
    "addr:street":"N High Point Rd",
    "iso:country":"US",
    "sg:address":"1030 N High Point Rd",
    "sg:city":"Madison",
    "sg:classifiers":[
        {
            "category":"Building & Trades",
            "subcategory":"Electrical",
            "type":"Services"
        }
    ],
    "sg:phone":"+1 608 827 6526",
    "sg:postcode":"53717",
    "sg:province":"WI",
    "sg:tags":[
        "electrical",
        "contractor"
    ],
    "wof:name":"Network Cabling Solutions LLC",
    "wof:placetype":"venue"
},
  "geometry": {"coordinates":[-89.51916799999999,43.079313],"type":"Point"}
}