{
  "type": "Feature",
  "properties": {
    "iso:country":"US",
    "sg:address":"7935 Harwood Ave",
    "sg:city":"Milwaukee",
    "sg:classifiers":[
        {
            "category":"Real Estate",
            "subcategory":"Real Estate Agent",
            "type":"Services"
        }
    ],
    "sg:phone":"+1 414 475 1775",
    "sg:postcode":"53213",
    "sg:province":"WI",
    "wof:name":"Lexington Realty Group",
    "wof:placetype":"venue"
},
  "geometry": {"coordinates":[-88.01266,43.047196],"type":"Point"}
}