{
  "type": "Feature",
  "properties": {
    "iso:country":"US",
    "sg:address":"200 N Harbor Dr",
    "sg:city":"Milwaukee",
    "sg:classifiers":[
        {
            "category":"Professional",
            "type":"Services"
        }
    ],
    "sg:phone":"+1 414 289 9301",
    "sg:postcode":"53202",
    "sg:province":"WI",
    "wof:name":"North Earth",
    "wof:placetype":"venue"
},
  "geometry": {"coordinates":[-87.899658,43.033091],"type":"Point"}
}