{
  "type": "Feature",
  "properties": {
    "iso:country":"US",
    "sg:address":"9081 Fox Rd",
    "sg:city":"Spooner",
    "sg:classifiers":[
        {
            "category":"Manufacturing",
            "subcategory":"Tools & Machinery",
            "type":"Manufacturing & Wholesale Goods"
        }
    ],
    "sg:phone":"+1 715 455 1328",
    "sg:postcode":"54801",
    "sg:province":"WI",
    "sg:tags":[
        "industrial",
        "mfg"
    ],
    "wof:name":"Schulz Machine Inc",
    "wof:placetype":"venue"
},
  "geometry": {"coordinates":[-91.98992200000001,45.886251],"type":"Point"}
}