{
  "type": "Feature",
  "properties": {
    "iso:country":"US",
    "sg:address":"1142 E Crane Lake Ln",
    "sg:city":"Pickerel",
    "sg:classifiers":[
        {
            "category":"Freight",
            "type":"Transportation"
        }
    ],
    "sg:phone":"+1 715 484 7192",
    "sg:postcode":"54465",
    "sg:province":"WI",
    "sg:tags":[
        "operator",
        "local",
        "trucking"
    ],
    "wof:name":"Torgerson Trucking",
    "wof:placetype":"venue"
},
  "geometry": {"coordinates":[-88.884264,45.415335],"type":"Point"}
}