{
  "type": "Feature",
  "properties": {
    "iso:country":"US",
    "sg:address":"7123 W Greenfield Ave",
    "sg:city":"West Allis",
    "sg:classifiers":[
        {
            "category":"Shopping",
            "subcategory":"Used Merchandise",
            "type":"Retail Goods"
        }
    ],
    "sg:phone":"+1 414 257 1212",
    "sg:postcode":"53214",
    "sg:province":"WI",
    "sg:tags":[
        "antique"
    ],
    "wof:name":"Antique Oasis",
    "wof:placetype":"venue"
},
  "geometry": {"coordinates":[-88.002232,43.016585],"type":"Point"}
}