{
  "type": "Feature",
  "properties": {
    "iso:country":"US",
    "sg:address":"1717 10th St",
    "sg:city":"Monroe",
    "sg:classifiers":[
        {
            "category":"Banks & Credit Unions",
            "subcategory":"Bank",
            "type":"Services"
        }
    ],
    "sg:phone":"+1 608 328 4000",
    "sg:postcode":"53566",
    "sg:province":"WI",
    "sg:tags":[
        "commercial",
        "saving"
    ],
    "sg:website":"http://www.wisconsincommunity.com",
    "wof:name":"Wisconsin Community Bank",
    "wof:placetype":"venue"
},
  "geometry": {"coordinates":[-89.638373,42.602112],"type":"Point"}
}