{
  "type": "Feature",
  "properties": {
    "iso:country":"US",
    "sg:address":"305 S 7th Ave",
    "sg:city":"West Bend",
    "sg:classifiers":[
        {
            "category":"Banks & Credit Unions",
            "subcategory":"Investment Brokerage",
            "type":"Services"
        }
    ],
    "sg:phone":"+1 262 335 1700",
    "sg:postcode":"53095",
    "sg:province":"WI",
    "sg:tags":[
        "consultant",
        "financing"
    ],
    "wof:name":"Sheehy Financial LLC",
    "wof:placetype":"venue"
},
  "geometry": {"coordinates":[-88.184832,43.4195],"type":"Point"}
}