{
  "type": "Feature",
  "properties": {
    "iso:country":"US",
    "sg:address":"2304 N Grandview Blvd",
    "sg:city":"Waukesha",
    "sg:classifiers":[
        {
            "category":"Professional",
            "subcategory":"Lawyer & Legal Services",
            "type":"Services"
        }
    ],
    "sg:phone":"+1 262 549 3600",
    "sg:postcode":"53188",
    "sg:province":"WI",
    "sg:tags":[
        "attorney"
    ],
    "wof:name":"Hans A Buehler Law Office",
    "wof:placetype":"venue"
},
  "geometry": {"coordinates":[-88.256084,43.033007],"type":"Point"}
}