{
  "type": "Feature",
  "properties": {
    "iso:country":"US",
    "sg:address":"410 Water Tower Ct",
    "sg:city":"Watertown",
    "sg:classifiers":[
        {
            "category":"Building & Trades",
            "subcategory":"Construction",
            "type":"Services"
        }
    ],
    "sg:phone":"+1 920 261 1682",
    "sg:postcode":"53094",
    "sg:province":"WI",
    "sg:tags":[
        "general",
        "contractor"
    ],
    "sg:website":"www.maasbros.com",
    "wof:name":"Maas Brothers Construction Co",
    "wof:placetype":"venue"
},
  "geometry": {"coordinates":[-88.753623,43.193498],"type":"Point"}
}