{
  "type": "Feature",
  "properties": {
    "iso:country":"US",
    "sg:address":"506 Summit Ave",
    "sg:city":"Waukesha",
    "sg:classifiers":[
        {
            "category":"Retail",
            "subcategory":"Laundry & Dry Cleaning",
            "type":"Services"
        }
    ],
    "sg:phone":"+1 262 549 2122",
    "sg:postcode":"53188",
    "sg:province":"WI",
    "wof:name":"Magic Stitch LLC",
    "wof:placetype":"venue"
},
  "geometry": {"coordinates":[-88.241098,43.018973],"type":"Point"}
}