{
  "type": "Feature",
  "properties": {
    "addr:full":"900 S Clara St Appleton WI 54915",
    "addr:housenumber":"900",
    "addr:postcode":"54915",
    "addr:street":"S Clara St",
    "iso:country":"US",
    "sg:address":"900 S Clara St",
    "sg:city":"Appleton",
    "sg:classifiers":[
        {
            "category":"Professional",
            "subcategory":"Secretarial Services",
            "type":"Services"
        }
    ],
    "sg:phone":"+1 920 585 8200",
    "sg:postcode":"54915",
    "sg:province":"WI",
    "sg:tags":[
        "transcription",
        "medical"
    ],
    "wof:name":"Appleton Transcription",
    "wof:placetype":"venue"
},
  "geometry": {"coordinates":[-88.365025,44.253569],"type":"Point"}
}