{
  "type": "Feature",
  "properties": {
    "addr:full":"816 College Ave Racine WI 53403",
    "addr:housenumber":"816",
    "addr:postcode":"53403",
    "addr:street":"College Ave",
    "iso:country":"US",
    "sg:address":"816 College Ave",
    "sg:city":"Racine",
    "sg:classifiers":[
        {
            "category":"Social Services",
            "subcategory":"Child Care",
            "type":"Services"
        }
    ],
    "sg:phone":"+1 262 632 5196",
    "sg:postcode":"53403",
    "sg:province":"WI",
    "wof:name":"Robin & Lafiya's Daycare",
    "wof:placetype":"venue"
},
  "geometry": {"coordinates":[-87.784931,42.723221],"type":"Point"}
}