{
  "type": "Feature",
  "properties": {
    "addr:full":"116 W Grant Ave Eau Claire WI 54701",
    "addr:housenumber":"116",
    "addr:postcode":"54701",
    "addr:street":"W Grant Ave",
    "iso:country":"US",
    "sg:address":"116 W Grant Ave",
    "sg:city":"Eau Claire",
    "sg:classifiers":[
        {
            "category":"Wholesale",
            "subcategory":"Stationery",
            "type":"Manufacturing & Wholesale Goods"
        }
    ],
    "sg:phone":"+1 715 833 1129",
    "sg:postcode":"54701",
    "sg:province":"WI",
    "sg:tags":[
        "supply"
    ],
    "wof:name":"Mike Fischer School Products",
    "wof:placetype":"venue"
},
  "geometry": {"coordinates":[-91.49968800000001,44.788428],"type":"Point"}
}