{
  "type": "Feature",
  "properties": {
    "iso:country":"US",
    "sg:address":"373 Milwaukee Rd",
    "sg:city":"Hudson",
    "sg:classifiers":[
        {
            "category":"Health Services",
            "subcategory":"Doctor",
            "type":"Services"
        }
    ],
    "sg:phone":"+1 715 425 8326",
    "sg:postcode":"54016",
    "sg:province":"WI",
    "sg:tags":[
        "physician",
        "surgeon",
        "anesthesiology",
        "surgeons"
    ],
    "wof:name":"Valley Anestesia Inc",
    "wof:placetype":"venue"
},
  "geometry": {"coordinates":[-92.688023,44.916512],"type":"Point"}
}