{
  "type": "Feature",
  "properties": {
    "iso:country":"US",
    "sg:address":"1526 Indiana Ave",
    "sg:city":"Sheboygan",
    "sg:classifiers":[
        {
            "category":"Autos & Motor Vehicles",
            "subcategory":"Auto Supplies",
            "type":"Retail Goods"
        }
    ],
    "sg:phone":"+1 920 459 8887",
    "sg:postcode":"53081",
    "sg:province":"WI",
    "sg:tags":[
        "automobile",
        "parts"
    ],
    "wof:name":"Car Quest Auto Parts",
    "wof:placetype":"venue"
},
  "geometry": {"coordinates":[-87.725953,43.743289],"type":"Point"}
}