{
  "type": "Feature",
  "properties": {
    "iso:country":"US",
    "sg:address":"731 N Jackson St Ste 900",
    "sg:city":"Milwaukee",
    "sg:classifiers":[
        {
            "category":"Structure",
            "subcategory":"Office Building",
            "type":"Public Place"
        }
    ],
    "sg:phone":"+1 414 271 2424",
    "sg:postcode":"53202",
    "sg:province":"WI",
    "sg:tags":[
        "park"
    ],
    "wof:name":"Tlm Properties",
    "wof:placetype":"venue"
},
  "geometry": {"coordinates":[-87.904082,43.039651],"type":"Point"}
}