{
  "type": "Feature",
  "properties": {
    "addr:full":"436 Connie St Cottage Grove WI 53527",
    "addr:housenumber":"436",
    "addr:postcode":"53527",
    "addr:street":"Connie St",
    "iso:country":"US",
    "sg:address":"436 Connie St",
    "sg:city":"Cottage Grove",
    "sg:phone":"+1 608 839 4057",
    "sg:postcode":"53527",
    "sg:province":"WI",
    "sg:tags":[
        "farm",
        "corn"
    ],
    "wof:name":"Swalheim Farms",
    "wof:placetype":"venue"
},
  "geometry": {"coordinates":[-89.202416,43.083877],"type":"Point"}
}