{
  "type": "Feature",
  "properties": {
    "iso:country":"US",
    "sg:address":"595 S Ira St",
    "sg:city":"Richland Center",
    "sg:classifiers":[
        {
            "category":"Professional",
            "subcategory":"Business Services",
            "type":"Services"
        }
    ],
    "sg:phone":"+1 608 647 2363",
    "sg:postcode":"53581",
    "sg:province":"WI",
    "wof:name":"Richland County Voiture 1268",
    "wof:placetype":"venue"
},
  "geometry": {"coordinates":[-90.379244,43.330916],"type":"Point"}
}