{
  "type": "Feature",
  "properties": {
    "addr:full":"706 Ogden Ave Superior WI 54880",
    "addr:housenumber":"706",
    "addr:postcode":"54880",
    "addr:street":"Ogden Ave",
    "iso:country":"US",
    "sg:address":"706 Ogden Ave",
    "sg:city":"Superior",
    "sg:classifiers":[
        {
            "category":"Manufacturing",
            "subcategory":"Tools & Machinery",
            "type":"Manufacturing & Wholesale Goods"
        }
    ],
    "sg:phone":"+1 715 394 5262",
    "sg:postcode":"54880",
    "sg:province":"WI",
    "wof:name":"Ogden Machine & Welding Svc",
    "wof:placetype":"venue"
},
  "geometry": {"coordinates":[-92.102261,46.729169],"type":"Point"}
}