{
  "type": "Feature",
  "properties": {
    "iso:country":"US",
    "sg:address":"2024 N Dr Martin Luther King Dr",
    "sg:city":"Milwaukee",
    "sg:classifiers":[
        {
            "category":"Organizations",
            "subcategory":"Religious Organization",
            "type":"Services"
        }
    ],
    "sg:phone":"+1 414 265 0103",
    "sg:postcode":"53212",
    "sg:province":"WI",
    "sg:tags":[
        "clergy"
    ],
    "wof:name":"J L Holmes",
    "wof:placetype":"venue"
},
  "geometry": {"coordinates":[-87.914129,43.057468],"type":"Point"}
}