{
  "type": "Feature",
  "properties": {
    "addr:full":"2860 Co Rd A Sheboygan Falls WI 53085",
    "addr:housenumber":"2860",
    "addr:postcode":"53085",
    "addr:street":"Co Rd A",
    "iso:country":"US",
    "sg:address":"2860 Co Rd A",
    "sg:city":"Sheboygan Falls",
    "sg:classifiers":[
        {
            "category":"Farming",
            "subcategory":"Dairy Farm",
            "type":"Manufacturing & Wholesale Goods"
        }
    ],
    "sg:phone":"+1 920 565 2585",
    "sg:postcode":"53085",
    "sg:province":"WI",
    "wof:name":"Roulette Ltd",
    "wof:placetype":"venue"
},
  "geometry": {"coordinates":[-87.838447,43.833845],"type":"Point"}
}