{
  "type": "Feature",
  "properties": {
    "iso:country":"US",
    "sg:address":"325 E Silver Spring Dr",
    "sg:city":"Milwaukee",
    "sg:classifiers":[
        {
            "category":"Shopping",
            "subcategory":"Clothing, Apparel, & Fashions",
            "type":"Retail Goods"
        }
    ],
    "sg:phone":"+1 414 962 6488",
    "sg:postcode":"53217",
    "sg:province":"WI",
    "wof:name":"Talbots 143",
    "wof:placetype":"venue"
},
  "geometry": {"coordinates":[-87.905709,43.118434],"type":"Point"}
}