{
  "type": "Feature",
  "properties": {
    "iso:country":"US",
    "sg:address":"957 Ruby Dr",
    "sg:city":"Stetsonville",
    "sg:classifiers":[
        {
            "category":"Social Services",
            "subcategory":"Child Care",
            "type":"Services"
        }
    ],
    "sg:phone":"+1 715 678 2349",
    "sg:postcode":"54480",
    "sg:province":"WI",
    "sg:tags":[
        "day"
    ],
    "wof:name":"Focus On Family Daycare",
    "wof:placetype":"venue"
},
  "geometry": {"coordinates":[-90.258436,45.06984],"type":"Point"}
}