{
  "type": "Feature",
  "properties": {
    "iso:country":"US",
    "sg:address":"2470 N 50th St",
    "sg:city":"Milwaukee",
    "sg:classifiers":[
        {
            "category":"Social Services",
            "subcategory":"Child Care",
            "type":"Services"
        }
    ],
    "sg:phone":"+1 414 873 6387",
    "sg:postcode":"53210",
    "sg:province":"WI",
    "sg:tags":[
        "day"
    ],
    "wof:name":"Wings Wonder Children Center",
    "wof:placetype":"venue"
},
  "geometry": {"coordinates":[-87.976194,43.062999],"type":"Point"}
}