{
  "type": "Feature",
  "properties": {
    "iso:country":"US",
    "sg:address":"27919 Whistle Pass Rd",
    "sg:city":"Trempealeau",
    "sg:classifiers":[
        {
            "category":"Farming",
            "subcategory":"Farm",
            "type":"Manufacturing & Wholesale Goods"
        }
    ],
    "sg:phone":"+1 608 539 2881",
    "sg:postcode":"54661",
    "sg:province":"WI",
    "sg:tags":[
        "crop",
        "general"
    ],
    "wof:name":"Joseph Wener",
    "wof:placetype":"venue"
},
  "geometry": {"coordinates":[-91.498953,44.102505],"type":"Point"}
}