{
  "type": "Feature",
  "properties": {
    "addr:full":"551 S Northview Rd Green Bay WI 54311",
    "addr:housenumber":"551",
    "addr:postcode":"54311",
    "addr:street":"S Northview Rd",
    "iso:country":"US",
    "sg:address":"551 S Northview Rd",
    "sg:city":"Green Bay",
    "sg:classifiers":[
        {
            "category":"Building & Trades",
            "subcategory":"Construction",
            "type":"Services"
        }
    ],
    "sg:phone":"+1 920 469 9383",
    "sg:postcode":"54311",
    "sg:province":"WI",
    "sg:tags":[
        "siding",
        "contractor"
    ],
    "wof:name":"AMZ Roofing & Siding",
    "wof:placetype":"venue"
},
  "geometry": {"coordinates":[-87.88713799999999,44.491596],"type":"Point"}
}