{
  "type": "Feature",
  "properties": {
    "iso:country":"US",
    "sg:address":"13 Atlas Ct",
    "sg:city":"Madison",
    "sg:classifiers":[
        {
            "category":"Sports & Exercise",
            "subcategory":"Bowling",
            "type":"Entertainment"
        }
    ],
    "sg:phone":"+1 608 221 3596",
    "sg:postcode":"53714",
    "sg:province":"WI",
    "sg:tags":[
        "center"
    ],
    "sg:website":"www.dreamlanes.com",
    "wof:name":"Dream Lanes",
    "wof:placetype":"venue"
},
  "geometry": {"coordinates":[-89.30726799999999,43.086277],"type":"Point"}
}