{
  "type": "Feature",
  "properties": {
    "iso:country":"US",
    "sg:address":"866 McDiarmid Cir",
    "sg:city":"Hudson",
    "sg:classifiers":[
        {
            "category":"Professional",
            "type":"Services"
        }
    ],
    "sg:phone":"+1 715 381 0315",
    "sg:postcode":"54016",
    "sg:province":"WI",
    "wof:name":"Windridge Designs Ltd",
    "wof:placetype":"venue"
},
  "geometry": {"coordinates":[-92.635596,44.988224],"type":"Point"}
}