{
  "type": "Feature",
  "properties": {
    "iso:country":"US",
    "sg:address":"1025 S 17th Ave",
    "sg:city":"Wausau",
    "sg:classifiers":[
        {
            "category":"Retail",
            "subcategory":"Veterinary Services",
            "type":"Services"
        }
    ],
    "sg:phone":"+1 715 845 1919",
    "sg:postcode":"54401",
    "sg:province":"WI",
    "sg:tags":[
        "veterinarian"
    ],
    "wof:name":"Marathon Animal Hospital SC",
    "wof:placetype":"venue"
},
  "geometry": {"coordinates":[-89.655374,44.949596],"type":"Point"}
}