{
  "type": "Feature",
  "properties": {
    "iso:country":"US",
    "sg:address":"2125 N Richmond St",
    "sg:city":"Appleton",
    "sg:classifiers":[
        {
            "category":"Food & Beverages",
            "subcategory":"Groceries & Convenience Stores",
            "type":"Retail Goods"
        }
    ],
    "sg:phone":"+1 920 830 3311",
    "sg:postcode":"54911",
    "sg:province":"WI",
    "sg:tags":[
        "grocer"
    ],
    "sg:website":"www.cathysbulkfoods.com",
    "wof:name":"Cathy's Country Store Inc",
    "wof:placetype":"venue"
},
  "geometry": {"coordinates":[-88.415871,44.281857],"type":"Point"}
}