{
  "type": "Feature",
  "properties": {
    "iso:country":"US",
    "sg:address":"7270 529th St",
    "sg:city":"Menomonie",
    "sg:classifiers":[
        {
            "category":"Home & Garden",
            "subcategory":"Home Furnishings",
            "type":"Retail Goods"
        }
    ],
    "sg:phone":"+1 715 235 8714",
    "sg:postcode":"54751",
    "sg:province":"WI",
    "wof:name":"Tada LLC",
    "wof:placetype":"venue"
},
  "geometry": {"coordinates":[-91.894091,44.937857],"type":"Point"}
}