{
  "type": "Feature",
  "properties": {
    "iso:country":"US",
    "sg:address":"615 Gohres St",
    "sg:city":"La Crosse",
    "sg:classifiers":[
        {
            "category":"Manufacturing",
            "subcategory":"Printing",
            "type":"Manufacturing & Wholesale Goods"
        }
    ],
    "sg:phone":"+1 608 784 2684",
    "sg:postcode":"54603",
    "sg:province":"WI",
    "sg:tags":[
        "commercial",
        "lithographic",
        "ty"
    ],
    "wof:name":"Curtis Printing Co Inc",
    "wof:placetype":"venue"
},
  "geometry": {"coordinates":[-91.24697,43.849496],"type":"Point"}
}