{
  "type": "Feature",
  "properties": {
    "addr:full":"310 Lance Dr Twin Lakes WI 53181",
    "addr:housenumber":"310",
    "addr:postcode":"53181",
    "addr:street":"Lance Dr",
    "iso:country":"US",
    "sg:address":"310 Lance Dr",
    "sg:city":"Twin Lakes",
    "sg:classifiers":[
        {
            "category":"Building & Trades",
            "subcategory":"Construction",
            "type":"Services"
        }
    ],
    "sg:phone":"+1 262 877 8030",
    "sg:postcode":"53181",
    "sg:province":"WI",
    "sg:tags":[
        "contractor"
    ],
    "wof:name":"M K Drywall",
    "wof:placetype":"venue"
},
  "geometry": {"coordinates":[-88.25886,42.529762],"type":"Point"}
}