{
  "type": "Feature",
  "properties": {
    "iso:country":"US",
    "sg:address":"1124 N 11th St",
    "sg:city":"Sheboygan",
    "sg:classifiers":[
        {
            "category":"Social Services",
            "subcategory":"Child Care",
            "type":"Services"
        }
    ],
    "sg:phone":"+1 920 451 1104",
    "sg:postcode":"53081",
    "sg:province":"WI",
    "sg:tags":[
        "day"
    ],
    "wof:name":"Bears Den Daycare LLC",
    "wof:placetype":"venue"
},
  "geometry": {"coordinates":[-87.718019,43.757186],"type":"Point"}
}