{
  "type": "Feature",
  "properties": {
    "iso:country":"US",
    "sg:address":"12536 Co Rd Q",
    "sg:city":"Two Rivers",
    "sg:classifiers":[
        {
            "category":"Building & Trades",
            "subcategory":"Landscaping Services",
            "type":"Services"
        }
    ],
    "sg:phone":"+1 920 755 4319",
    "sg:postcode":"54241",
    "sg:province":"WI",
    "wof:name":"Cretton Enterprises Inc",
    "wof:placetype":"venue"
},
  "geometry": {"coordinates":[-87.705879,44.245596],"type":"Point"}
}