{
  "type": "Feature",
  "properties": {
    "iso:country":"US",
    "sg:address":"4901 Regal Ct",
    "sg:city":"Racine",
    "sg:classifiers":[
        {
            "category":"Real Estate",
            "subcategory":"Real Estate Agent",
            "type":"Services"
        }
    ],
    "sg:phone":"+1 262 554 1847",
    "sg:postcode":"53406",
    "sg:province":"WI",
    "wof:name":"Sale By Owner Assistance Inc",
    "wof:placetype":"venue"
},
  "geometry": {"coordinates":[-87.83893999999999,42.69238],"type":"Point"}
}