{
  "type": "Feature",
  "properties": {
    "iso:country":"US",
    "sg:address":"1819 52nd St",
    "sg:city":"Kenosha",
    "sg:classifiers":[
        {
            "category":"Travel",
            "subcategory":"Hotels & Motels",
            "type":"Entertainment"
        },
        {
            "category":"Bars & Pubs",
            "type":"Food & Drink"
        }
    ],
    "sg:phone":"+1 262 653 0911",
    "sg:postcode":"53140",
    "sg:province":"WI",
    "sg:tags":[
        "operation"
    ],
    "wof:name":"Norm S So Seldom Inn",
    "wof:placetype":"venue"
},
  "geometry": {"coordinates":[-87.831947,42.587894],"type":"Point"}
}