{
  "type": "Feature",
  "properties": {
    "iso:country":"US",
    "sg:address":"4502 Oak Springs Cir",
    "sg:city":"De Forest",
    "sg:classifiers":[
        {
            "category":"Professional",
            "subcategory":"Management & Consulting",
            "type":"Services"
        }
    ],
    "sg:phone":"+1 608 846 4899",
    "sg:postcode":"53532",
    "sg:province":"WI",
    "sg:tags":[
        "business"
    ],
    "wof:name":"Drk Consulting Inc",
    "wof:placetype":"venue"
},
  "geometry": {"coordinates":[-89.343637,43.234525],"type":"Point"}
}