{
  "type": "Feature",
  "properties": {
    "iso:country":"US",
    "sg:address":"8130 US Hwy 8",
    "sg:city":"Pembine",
    "sg:classifiers":[
        {
            "category":"Food & Beverages",
            "subcategory":"Groceries & Convenience Stores",
            "type":"Retail Goods"
        }
    ],
    "sg:phone":"+1 715 324 6905",
    "sg:postcode":"54156",
    "sg:province":"WI",
    "wof:name":"Pembine Marathon LLC",
    "wof:placetype":"venue"
},
  "geometry": {"coordinates":[-87.998352,45.622942],"type":"Point"}
}