{
  "type": "Feature",
  "properties": {
    "iso:country":"US",
    "sg:address":"809 Burton Blvd",
    "sg:city":"De Forest",
    "sg:classifiers":[
        {
            "category":"Building & Trades",
            "subcategory":"Construction",
            "type":"Services"
        },
        {
            "category":"Wholesale",
            "subcategory":"Durable Goods & Equipment",
            "type":"Manufacturing & Wholesale Goods"
        }
    ],
    "sg:phone":"+1 608 846 0970",
    "sg:postcode":"53532",
    "sg:province":"WI",
    "sg:tags":[
        "hanging",
        "manufacturer",
        "representative",
        "contractor"
    ],
    "wof:name":"Industrial Custom Finishing WI",
    "wof:placetype":"venue"
},
  "geometry": {"coordinates":[-89.327628,43.25761],"type":"Point"}
}