{
  "type": "Feature",
  "properties": {
    "iso:country":"US",
    "sg:address":"416 S Madison St",
    "sg:city":"Green Bay",
    "sg:classifiers":[
        {
            "category":"Professional",
            "subcategory":"Business Services",
            "type":"Services"
        }
    ],
    "sg:phone":"+1 920 437 0000",
    "sg:postcode":"54301",
    "sg:province":"WI",
    "sg:tags":[
        "appraiser"
    ],
    "wof:name":"Progressive Appraisers Group",
    "wof:placetype":"venue"
},
  "geometry": {"coordinates":[-88.014956,44.508627],"type":"Point"}
}