{
  "type": "Feature",
  "properties": {
    "iso:country":"US",
    "sg:address":"1327 Milwaukee Dr",
    "sg:city":"New Holstein",
    "sg:classifiers":[
        {
            "category":"Retail",
            "subcategory":"Auto Repair",
            "type":"Services"
        }
    ],
    "sg:phone":"+1 920 898 4433",
    "sg:postcode":"53061",
    "sg:province":"WI",
    "sg:tags":[
        "repairing",
        "automobile"
    ],
    "wof:name":"Depies Firestone",
    "wof:placetype":"venue"
},
  "geometry": {"coordinates":[-88.081525,43.947587],"type":"Point"}
}