{
  "type": "Feature",
  "properties": {
    "addr:full":"712 Douglas Trl Madison WI 53716",
    "addr:housenumber":"712",
    "addr:postcode":"53716",
    "addr:street":"Douglas Trl",
    "iso:country":"US",
    "sg:address":"712 Douglas Trl",
    "sg:city":"Madison",
    "sg:classifiers":[
        {
            "category":"Professional",
            "subcategory":"Engineering",
            "type":"Services"
        }
    ],
    "sg:phone":"+1 608 222 8737",
    "sg:postcode":"53716",
    "sg:province":"WI",
    "wof:name":"Falcorp LLC",
    "wof:placetype":"venue"
},
  "geometry": {"coordinates":[-89.31653799999999,43.060998],"type":"Point"}
}