{
  "type": "Feature",
  "properties": {
    "iso:country":"US",
    "sg:address":"9051 N 85th St",
    "sg:city":"Milwaukee",
    "sg:classifiers":[
        {
            "category":"Arts & Performance",
            "subcategory":"Theater",
            "type":"Entertainment"
        }
    ],
    "sg:phone":"+1 414 365 2937",
    "sg:postcode":"53224",
    "sg:province":"WI",
    "sg:tags":[
        "bureau"
    ],
    "wof:name":"Your Choice Entertainment",
    "wof:placetype":"venue"
},
  "geometry": {"coordinates":[-88.015738,43.180873],"type":"Point"}
}