{
  "type": "Feature",
  "properties": {
    "iso:country":"US",
    "sg:address":"805 N Main St",
    "sg:city":"Lodi",
    "sg:classifiers":[
        {
            "category":"Food & Beverages",
            "subcategory":"Groceries & Convenience Stores",
            "type":"Retail Goods"
        }
    ],
    "sg:phone":"+1 608 592 7570",
    "sg:postcode":"53555",
    "sg:province":"WI",
    "sg:tags":[
        "grocer"
    ],
    "wof:name":"D & D Piggly Wiggly",
    "wof:placetype":"venue"
},
  "geometry": {"coordinates":[-89.531803,43.318461],"type":"Point"}
}