{
  "type": "Feature",
  "properties": {
    "addr:full":"1 S Pinckney St Madison WI 53703",
    "addr:housenumber":"1",
    "addr:postcode":"53703",
    "addr:street":"S Pinckney St",
    "iso:country":"US",
    "sg:address":"1 S Pinckney St",
    "sg:city":"Madison",
    "sg:classifiers":[
        {
            "category":"Personal",
            "subcategory":"Beauty Salon",
            "type":"Services"
        }
    ],
    "sg:phone":"+1 608 257 0604",
    "sg:postcode":"53703",
    "sg:province":"WI",
    "wof:name":"William Jon Salon",
    "wof:placetype":"venue"
},
  "geometry": {"coordinates":[-89.382136,43.074669],"type":"Point"}
}