{
  "type": "Feature",
  "properties": {
    "iso:country":"US",
    "sg:address":"2010 Velp Ave",
    "sg:city":"Green Bay",
    "sg:classifiers":[
        {
            "category":"Banks & Credit Unions",
            "subcategory":"Investment Brokerage",
            "type":"Services"
        }
    ],
    "sg:phone":"+1 920 661 9000",
    "sg:postcode":"54303",
    "sg:province":"WI",
    "sg:tags":[
        "consultant",
        "planning",
        "financial"
    ],
    "wof:name":"Chambers Financial Group",
    "wof:placetype":"venue"
},
  "geometry": {"coordinates":[-88.06684,44.559513],"type":"Point"}
}