{
  "type": "Feature",
  "properties": {
    "addr:full":"244 Blaine Ave Racine WI 53405",
    "addr:housenumber":"244",
    "addr:postcode":"53405",
    "addr:street":"Blaine Ave",
    "iso:country":"US",
    "sg:address":"244 Blaine Ave",
    "sg:city":"Racine",
    "sg:classifiers":[
        {
            "category":"Retail",
            "subcategory":"Auto Repair",
            "type":"Services"
        }
    ],
    "sg:phone":"+1 262 635 8822",
    "sg:postcode":"53405",
    "sg:province":"WI",
    "sg:tags":[
        "body"
    ],
    "wof:name":"Penys Detailing & Custom Shop",
    "wof:placetype":"venue"
},
  "geometry": {"coordinates":[-87.821264,42.731044],"type":"Point"}
}