{
  "type": "Feature",
  "properties": {
    "iso:country":"US",
    "sg:address":"6236 8th Ct",
    "sg:city":"Westfield",
    "sg:classifiers":[
        {
            "category":"Real Estate",
            "subcategory":"Real Estate Operator",
            "type":"Services"
        }
    ],
    "sg:phone":"+1 608 296 2367",
    "sg:postcode":"53964",
    "sg:province":"WI",
    "sg:tags":[
        "property",
        "lessor"
    ],
    "wof:name":"Marvin Ahlstrom",
    "wof:placetype":"venue"
},
  "geometry": {"coordinates":[-89.46011799999999,43.865802],"type":"Point"}
}