{
  "type": "Feature",
  "properties": {
    "iso:country":"US",
    "sg:address":"303 Columbia Dr",
    "sg:city":"Poynette",
    "sg:classifiers":[
        {
            "category":"Manufacturing",
            "subcategory":"Retail Goods",
            "type":"Manufacturing & Wholesale Goods"
        }
    ],
    "sg:phone":"+1 608 635 8938",
    "sg:postcode":"53955",
    "sg:province":"WI",
    "sg:tags":[
        "product",
        "mfg"
    ],
    "wof:name":"Gbn Industries Inc",
    "wof:placetype":"venue"
},
  "geometry": {"coordinates":[-89.394831,43.397652],"type":"Point"}
}