{
  "type": "Feature",
  "properties": {
    "iso:country":"US",
    "sg:address":"744 W Bender Rd",
    "sg:city":"Milwaukee",
    "sg:classifiers":[
        {
            "category":"Professional",
            "type":"Services"
        }
    ],
    "sg:phone":"+1 414 906 1459",
    "sg:postcode":"53217",
    "sg:province":"WI",
    "wof:name":"J2 Vision Services SC",
    "wof:placetype":"venue"
},
  "geometry": {"coordinates":[-87.91859100000001,43.129655],"type":"Point"}
}