{
  "type": "Feature",
  "properties": {
    "iso:country":"US",
    "sg:address":"1380 Industrial Park Dr",
    "sg:city":"Union Grove",
    "sg:classifiers":[
        {
            "category":"Building & Trades",
            "subcategory":"Plumbing",
            "type":"Services"
        }
    ],
    "sg:phone":"+1 262 878 3348",
    "sg:postcode":"53182",
    "sg:province":"WI",
    "sg:tags":[
        "contractor"
    ],
    "wof:name":"Bigelow Rfrgn Sls & Svc",
    "wof:placetype":"venue"
},
  "geometry": {"coordinates":[-88.064347,42.682384],"type":"Point"}
}