{
  "type": "Feature",
  "properties": {
    "iso:country":"US",
    "sg:address":"5335 State Hwy 29",
    "sg:city":"Denmark",
    "sg:classifiers":[
        {
            "category":"Home & Garden",
            "subcategory":"Building Materials",
            "type":"Retail Goods"
        }
    ],
    "sg:phone":"+1 920 863 1146",
    "sg:postcode":"54208",
    "sg:province":"WI",
    "sg:tags":[
        "trade",
        "contractor",
        "mfg"
    ],
    "wof:name":"Bayland Fence Company",
    "wof:placetype":"venue"
},
  "geometry": {"coordinates":[-87.819761,44.443866],"type":"Point"}
}