{
  "type": "Feature",
  "properties": {
    "iso:country":"US",
    "sg:address":"1401 S Webster Ave",
    "sg:city":"Green Bay",
    "sg:classifiers":[
        {
            "category":"Professional",
            "subcategory":"Employment Agencies",
            "type":"Services"
        }
    ],
    "sg:phone":"+1 920 436 9990",
    "sg:postcode":"54301",
    "sg:province":"WI",
    "sg:tags":[
        "temp",
        "labor"
    ],
    "wof:name":"Labor Ready",
    "wof:placetype":"venue"
},
  "geometry": {"coordinates":[-88.01612799999999,44.493387],"type":"Point"}
}