{
  "type": "Feature",
  "properties": {
    "iso:country":"US",
    "sg:address":"989 Kimball Ave",
    "sg:city":"Nekoosa",
    "sg:classifiers":[
        {
            "category":"Freight",
            "type":"Transportation"
        }
    ],
    "sg:phone":"+1 715 886 4212",
    "sg:postcode":"54457",
    "sg:province":"WI",
    "sg:tags":[
        "operator",
        "local",
        "trucking"
    ],
    "wof:name":"David Korntved Trucking",
    "wof:placetype":"venue"
},
  "geometry": {"coordinates":[-89.944587,44.281646],"type":"Point"}
}