{
  "type": "Feature",
  "properties": {
    "iso:country":"US",
    "sg:address":"3606 10th Ave",
    "sg:city":"Kenosha",
    "sg:classifiers":[
        {
            "category":"Organizations",
            "subcategory":"Community Association",
            "type":"Services"
        }
    ],
    "sg:phone":"+1 262 657 6279",
    "sg:postcode":"53140",
    "sg:province":"WI",
    "wof:name":"Marine Corps League",
    "wof:placetype":"venue"
},
  "geometry": {"coordinates":[-87.824462,42.603867],"type":"Point"}
}