{
  "type": "Feature",
  "properties": {
    "iso:country":"US",
    "sg:address":"208 S 4th Ave",
    "sg:city":"Sturgeon Bay",
    "sg:classifiers":[
        {
            "category":"Real Estate",
            "subcategory":"Surveying",
            "type":"Services"
        }
    ],
    "sg:phone":"+1 920 743 6963",
    "sg:postcode":"54235",
    "sg:province":"WI",
    "sg:tags":[
        "surveyor"
    ],
    "wof:name":"Brey Stuewe and Braun Surveys",
    "wof:placetype":"venue"
},
  "geometry": {"coordinates":[-87.37348299999999,44.833144],"type":"Point"}
}