{
  "type": "Feature",
  "properties": {
    "iso:country":"US",
    "sg:address":"1823 15th St",
    "sg:city":"Rice Lake",
    "sg:classifiers":[
        {
            "category":"Manufacturing",
            "subcategory":"Building Materials",
            "type":"Manufacturing & Wholesale Goods"
        }
    ],
    "sg:phone":"+1 715 537 3556",
    "sg:postcode":"54868",
    "sg:province":"WI",
    "wof:name":"Kuhrt Lumber Co",
    "wof:placetype":"venue"
},
  "geometry": {"coordinates":[-91.847408,45.466186],"type":"Point"}
}