{
  "type": "Feature",
  "properties": {
    "iso:country":"US",
    "sg:address":"920 Co Rd H",
    "sg:city":"Elkhorn",
    "sg:classifiers":[
        {
            "category":"Organizations",
            "subcategory":"Religious Organization",
            "type":"Services"
        }
    ],
    "sg:phone":"+1 262 723 4387",
    "sg:postcode":"53121",
    "sg:province":"WI",
    "sg:tags":[
        "church"
    ],
    "wof:name":"Emmanuel Baptist Church",
    "wof:placetype":"venue"
},
  "geometry": {"coordinates":[-88.523444,42.670054],"type":"Point"}
}