{
  "type": "Feature",
  "properties": {
    "iso:country":"US",
    "sg:address":"531 E Grand Ave",
    "sg:city":"Beloit",
    "sg:classifiers":[
        {
            "category":"Banks & Credit Unions",
            "subcategory":"Bank",
            "type":"Services"
        }
    ],
    "sg:phone":"+1 608 364 9044",
    "sg:postcode":"53511",
    "sg:province":"WI",
    "wof:name":"Associated Bank",
    "wof:placetype":"venue"
},
  "geometry": {"coordinates":[-89.031513,42.499699],"type":"Point"}
}