{
  "type": "Feature",
  "properties": {
    "addr:full":"3730 N 28th St Milwaukee WI 53216",
    "addr:housenumber":"3730",
    "addr:postcode":"53216",
    "addr:street":"N 28Th St",
    "iso:country":"US",
    "sg:address":"3730 N 28th St",
    "sg:city":"Milwaukee",
    "sg:classifiers":[
        {
            "category":"Building & Trades",
            "subcategory":"Construction",
            "type":"Services"
        }
    ],
    "sg:phone":"+1 414 871 2668",
    "sg:postcode":"53216",
    "sg:province":"WI",
    "sg:tags":[
        "repairing",
        "remodeling",
        "contractor"
    ],
    "wof:name":"D B Remodeling",
    "wof:placetype":"venue"
},
  "geometry": {"coordinates":[-87.948277,43.085728],"type":"Point"}
}