{
  "type": "Feature",
  "properties": {
    "iso:country":"US",
    "sg:address":"8950 S River Edge Dr",
    "sg:city":"Oak Creek",
    "sg:classifiers":[
        {
            "category":"Building & Trades",
            "subcategory":"Construction",
            "type":"Services"
        }
    ],
    "sg:phone":"+1 414 764 0709",
    "sg:postcode":"53154",
    "sg:province":"WI",
    "sg:tags":[
        "roofing",
        "contractor"
    ],
    "wof:name":"J & J Contractors LLC",
    "wof:placetype":"venue"
},
  "geometry": {"coordinates":[-87.926011,42.882806],"type":"Point"}
}