{
  "type": "Feature",
  "properties": {
    "iso:country":"US",
    "sg:address":"1126 S 70th St",
    "sg:city":"Milwaukee",
    "sg:classifiers":[
        {
            "category":"Professional",
            "type":"Services"
        }
    ],
    "sg:phone":"+1 414 607 7477",
    "sg:postcode":"53214",
    "sg:province":"WI",
    "sg:tags":[
        "establishment"
    ],
    "wof:name":"Max Staff",
    "wof:placetype":"venue"
},
  "geometry": {"coordinates":[-87.99993499999999,43.019398],"type":"Point"}
}