{
  "type": "Feature",
  "properties": {
    "addr:full":"6753 Manitowoc Rd Menasha WI 54952",
    "addr:postcode":"6753;54952",
    "addr:street":"Manitowoc Rd",
    "iso:country":"US",
    "sg:address":"6753 Manitowoc Rd",
    "sg:city":"Menasha",
    "sg:phone":"+1 920 733 5247",
    "sg:postcode":"54952",
    "sg:province":"WI",
    "sg:tags":[
        "farm",
        "corn"
    ],
    "wof:name":"Bartlein John",
    "wof:placetype":"venue"
},
  "geometry": {"coordinates":[-88.37615,44.221713],"type":"Point"}
}