{
  "type": "Feature",
  "properties": {
    "iso:country":"US",
    "sg:address":"141 N Washington St",
    "sg:city":"St Croix Falls",
    "sg:classifiers":[
        {
            "category":"Home & Garden",
            "subcategory":"Building Materials",
            "type":"Retail Goods"
        }
    ],
    "sg:phone":"+1 715 483 5454",
    "sg:postcode":"54024",
    "sg:province":"WI",
    "sg:tags":[
        "glass",
        "window",
        "plate"
    ],
    "sg:website":"www.indianheadglass.com",
    "wof:name":"Indianhead Glass Inc",
    "wof:placetype":"venue"
},
  "geometry": {"coordinates":[-92.644915,45.411481],"type":"Point"}
}