{
  "type": "Feature",
  "properties": {
    "iso:country":"US",
    "sg:address":"208 W Water St",
    "sg:city":"Shullsburg",
    "sg:classifiers":[
        {
            "category":"Manufacturing",
            "subcategory":"Food",
            "type":"Manufacturing & Wholesale Goods"
        }
    ],
    "sg:phone":"+1 608 965 4485",
    "sg:postcode":"53586",
    "sg:province":"WI",
    "sg:tags":[
        "cheese",
        "processor"
    ],
    "wof:name":"Shullsburg Creamery",
    "wof:placetype":"venue"
},
  "geometry": {"coordinates":[-90.234055,42.573011],"type":"Point"}
}