{
  "type": "Feature",
  "properties": {
    "iso:country":"US",
    "sg:address":"501 W Rolling Meadows Dr",
    "sg:city":"Fond Du Lac",
    "sg:classifiers":[
        {
            "category":"Retail",
            "subcategory":"Auto Repair",
            "type":"Services"
        }
    ],
    "sg:phone":"+1 800 800 2727",
    "sg:postcode":"54937",
    "sg:province":"WI",
    "sg:tags":[
        "glass",
        "replacement"
    ],
    "wof:name":"Safelite Autoglass",
    "wof:placetype":"venue"
},
  "geometry": {"coordinates":[-88.476112,43.754678],"type":"Point"}
}