{
  "type": "Feature",
  "properties": {
    "iso:country":"US",
    "sg:address":"200 Wisconsin St",
    "sg:city":"Fredonia",
    "sg:classifiers":[
        {
            "category":"Manufacturing",
            "subcategory":"Tools & Machinery",
            "type":"Manufacturing & Wholesale Goods"
        }
    ],
    "sg:phone":"+1 262 692 2427",
    "sg:postcode":"53021",
    "sg:province":"WI",
    "wof:name":"Milwaukee N/C Machining",
    "wof:placetype":"venue"
},
  "geometry": {"coordinates":[-87.954835,43.468696],"type":"Point"}
}