{
  "type": "Feature",
  "properties": {
    "addr:full":"923 N 3rd Ave Wausau WI 54401",
    "addr:housenumber":"923",
    "addr:postcode":"54401",
    "addr:street":"N 3Rd Ave",
    "iso:country":"US",
    "sg:address":"923 N 3rd Ave",
    "sg:city":"Wausau",
    "sg:classifiers":[
        {
            "category":"Retail",
            "subcategory":"Laundry & Dry Cleaning",
            "type":"Services"
        }
    ],
    "sg:phone":"+1 715 675 2918",
    "sg:postcode":"54401",
    "sg:province":"WI",
    "sg:tags":[
        "coin",
        "power"
    ],
    "wof:name":"Northway Coin Laundry",
    "wof:placetype":"venue"
},
  "geometry": {"coordinates":[-89.639312,44.974591],"type":"Point"}
}