{
  "type": "Feature",
  "properties": {
    "iso:country":"US",
    "sg:address":"2304 18th St",
    "sg:city":"Kenosha",
    "sg:classifiers":[
        {
            "category":"Restaurant",
            "type":"Food & Drink"
        }
    ],
    "sg:menulink":"http://www.allmenus.com/wi/kenosha/63977-papa-johns-pizza/menu/",
    "sg:phone":"+1 262 551 7573",
    "sg:postcode":"53140",
    "sg:province":"WI",
    "sg:tags":[
        "american",
        "pizza"
    ],
    "wof:name":"Papa John's Pizza",
    "wof:placetype":"venue"
},
  "geometry": {"coordinates":[-87.837256,42.624642],"type":"Point"}
}