{
  "type": "Feature",
  "properties": {
    "iso:country":"US",
    "sg:address":"332 7th Ave",
    "sg:city":"Baraboo",
    "sg:classifiers":[
        {
            "category":"Building & Trades",
            "subcategory":"Construction",
            "type":"Services"
        }
    ],
    "sg:phone":"+1 608 355 0053",
    "sg:postcode":"53913",
    "sg:province":"WI",
    "sg:tags":[
        "contractor"
    ],
    "wof:name":"Bottom Line Tile Floor MA",
    "wof:placetype":"venue"
},
  "geometry": {"coordinates":[-89.747317,43.473891],"type":"Point"}
}