{
  "type": "Feature",
  "properties": {
    "iso:country":"US",
    "sg:address":"1803 Monroe St",
    "sg:city":"Madison",
    "sg:classifiers":[
        {
            "category":"Building & Trades",
            "subcategory":"Construction",
            "type":"Services"
        }
    ],
    "sg:phone":"+1 608 255 8453",
    "sg:postcode":"53711",
    "sg:province":"WI",
    "sg:tags":[
        "contractor"
    ],
    "wof:name":"Tile Art Design Speclsts",
    "wof:placetype":"venue"
},
  "geometry": {"coordinates":[-89.417444,43.064586],"type":"Point"}
}