{
  "type": "Feature",
  "properties": {
    "iso:country":"US",
    "sg:address":"3422 W National Ave",
    "sg:city":"Milwaukee",
    "sg:classifiers":[
        {
            "category":"Wholesale",
            "subcategory":"Groceries",
            "type":"Manufacturing & Wholesale Goods"
        }
    ],
    "sg:phone":"+1 414 672 8440",
    "sg:postcode":"53215",
    "sg:province":"WI",
    "sg:tags":[
        "food",
        "broker"
    ],
    "wof:name":"Vientiane Food Dealer",
    "wof:placetype":"venue"
},
  "geometry": {"coordinates":[-87.95742,43.021703],"type":"Point"}
}