{
  "type": "Feature",
  "properties": {
    "iso:country":"US",
    "sg:address":"4230 Rosin Rd",
    "sg:city":"De Pere",
    "sg:classifiers":[
        {
            "category":"Farming",
            "subcategory":"Dairy Farm",
            "type":"Manufacturing & Wholesale Goods"
        }
    ],
    "sg:phone":"+1 920 532 3848",
    "sg:postcode":"54115",
    "sg:province":"WI",
    "wof:name":"New Horizons Dairy LLC",
    "wof:placetype":"venue"
},
  "geometry": {"coordinates":[-88.161302,44.348109],"type":"Point"}
}