{
  "type": "Feature",
  "properties": {
    "iso:country":"US",
    "sg:address":"8697 US Hwy 8 E",
    "sg:city":"Crandon",
    "sg:classifiers":[
        {
            "category":"Food & Beverages",
            "subcategory":"Liquor & Beverages",
            "type":"Retail Goods"
        }
    ],
    "sg:phone":"+1 715 478 3554",
    "sg:postcode":"54520",
    "sg:province":"WI",
    "sg:tags":[
        "alcoholic"
    ],
    "wof:name":"Double Top Pizza & Liquor",
    "wof:placetype":"venue"
},
  "geometry": {"coordinates":[-88.924425,45.571791],"type":"Point"}
}