{
  "type": "Feature",
  "properties": {
    "addr:full":"100 S Broadway De Pere WI 54115",
    "addr:housenumber":"100",
    "addr:postcode":"54115",
    "addr:street":"S Broadway",
    "iso:country":"US",
    "sg:address":"100 S Broadway",
    "sg:city":"De Pere",
    "sg:classifiers":[
        {
            "category":"Shopping",
            "subcategory":"Clothing, Apparel, & Fashions",
            "type":"Retail Goods"
        }
    ],
    "sg:phone":"+1 920 336 3371",
    "sg:postcode":"54115",
    "sg:province":"WI",
    "sg:tags":[
        "boutique"
    ],
    "wof:name":"Ergo",
    "wof:placetype":"venue"
},
  "geometry": {"coordinates":[-88.060491,44.447762],"type":"Point"}
}