{
  "type": "Feature",
  "properties": {
    "iso:country":"US",
    "sg:address":"3230 Larry Dr",
    "sg:city":"Plover",
    "sg:classifiers":[
        {
            "category":"Freight",
            "type":"Transportation"
        }
    ],
    "sg:phone":"+1 715 342 9947",
    "sg:postcode":"54467",
    "sg:province":"WI",
    "sg:tags":[
        "operator",
        "local",
        "trucking"
    ],
    "wof:name":"Kp Trucking LLC",
    "wof:placetype":"venue"
},
  "geometry": {"coordinates":[-89.55427400000001,44.452223],"type":"Point"}
}