{
  "type": "Feature",
  "properties": {
    "iso:country":"US",
    "sg:address":"4105 Dixie Ave",
    "sg:city":"Wausau",
    "sg:classifiers":[
        {
            "category":"Professional",
            "subcategory":"Accounting & Tax Preparation",
            "type":"Services"
        }
    ],
    "sg:phone":"+1 715 675 9000",
    "sg:postcode":"54401",
    "sg:province":"WI",
    "wof:name":"Koenig & Lundin Sc Inc",
    "wof:placetype":"venue"
},
  "geometry": {"coordinates":[-89.673815,45.009297],"type":"Point"}
}