{
  "type": "Feature",
  "properties": {
    "iso:country":"US",
    "sg:address":"6823 W Two Lakes Rd",
    "sg:city":"Lake Tomahawk",
    "sg:classifiers":[
        {
            "category":"Building & Trades",
            "subcategory":"Construction",
            "type":"Services"
        }
    ],
    "sg:phone":"+1 715 277 3275",
    "sg:postcode":"54539",
    "sg:province":"WI",
    "sg:tags":[
        "excavating",
        "contractor"
    ],
    "wof:name":"Dunbar Excavating & Septic",
    "wof:placetype":"venue"
},
  "geometry": {"coordinates":[-89.600617,45.797457],"type":"Point"}
}