{
  "type": "Feature",
  "properties": {
    "iso:country":"US",
    "sg:address":"1220 Mound Ave",
    "sg:city":"Racine",
    "sg:classifiers":[
        {
            "category":"Social Services",
            "subcategory":"Child Care",
            "type":"Services"
        }
    ],
    "sg:phone":"+1 262 635 1920",
    "sg:postcode":"53404",
    "sg:province":"WI",
    "sg:tags":[
        "support",
        "family"
    ],
    "wof:name":"Next Generation Now Inc",
    "wof:placetype":"venue"
},
  "geometry": {"coordinates":[-87.79532,42.728887],"type":"Point"}
}