{
  "type": "Feature",
  "properties": {
    "addr:full":"800 N Lynndale Dr Appleton WI 54914",
    "addr:housenumber":"800",
    "addr:postcode":"54914",
    "addr:street":"N Lynndale Dr",
    "iso:country":"US",
    "sg:address":"800 N Lynndale Dr",
    "sg:city":"Appleton",
    "sg:classifiers":[
        {
            "category":"Professional",
            "subcategory":"Lawyer & Legal Services",
            "type":"Services"
        }
    ],
    "sg:phone":"+1 920 468 7366",
    "sg:postcode":"54914",
    "sg:province":"WI",
    "sg:tags":[
        "attorney"
    ],
    "wof:name":"Herrling Clark Hartzhelm LTD",
    "wof:placetype":"venue"
},
  "geometry": {"coordinates":[-88.44601900000001,44.270953],"type":"Point"}
}