{
  "type": "Feature",
  "properties": {
    "iso:country":"US",
    "sg:address":"1201 Droster Rd",
    "sg:city":"Madison",
    "sg:classifiers":[
        {
            "category":"Organizations",
            "subcategory":"Religious Organization",
            "type":"Services"
        }
    ],
    "sg:phone":"+1 608 222 5151",
    "sg:postcode":"53716",
    "sg:province":"WI",
    "wof:name":"Our Saviours Luth Chrch Mdsn",
    "wof:placetype":"venue"
},
  "geometry": {"coordinates":[-89.286611,43.081556],"type":"Point"}
}