{
  "type": "Feature",
  "properties": {
    "addr:full":"1226 Oregon St Oshkosh WI 54902",
    "addr:housenumber":"1226",
    "addr:postcode":"54902",
    "addr:street":"Oregon St",
    "iso:country":"US",
    "sg:address":"1226 Oregon St",
    "sg:city":"Oshkosh",
    "sg:classifiers":[
        {
            "category":"Food & Beverages",
            "subcategory":"Specialty",
            "type":"Retail Goods"
        }
    ],
    "sg:phone":"+1 920 235 1351",
    "sg:postcode":"54902",
    "sg:province":"WI",
    "wof:name":"Nutrition Supply Co",
    "wof:placetype":"venue"
},
  "geometry": {"coordinates":[-88.54241500000001,44.006718],"type":"Point"}
}