{
  "type": "Feature",
  "properties": {
    "iso:country":"US",
    "sg:address":"1226 Oregon St",
    "sg:city":"Oshkosh",
    "sg:classifiers":[
        {
            "category":"Food & Beverages",
            "subcategory":"Specialty",
            "type":"Retail Goods"
        }
    ],
    "sg:phone":"+1 920 235 1351",
    "sg:postcode":"54902",
    "sg:province":"WI",
    "wof:name":"Nutrition Supply Co",
    "wof:placetype":"venue"
},
  "geometry": {"coordinates":[-88.542415,44.006718],"type":"Point"}
}