{
  "type": "Feature",
  "properties": {
    "iso:country":"US",
    "sg:address":"2546 Blackberry Dr",
    "sg:city":"Mount Calvary",
    "sg:classifiers":[
        {
            "category":"Professional",
            "subcategory":"Business Services",
            "type":"Services"
        }
    ],
    "sg:phone":"+1 920 924 4069",
    "sg:postcode":"53057",
    "sg:province":"WI",
    "wof:name":"Potential Enterprise LLC",
    "wof:placetype":"venue"
},
  "geometry": {"coordinates":[-88.283997,43.798185],"type":"Point"}
}