{
  "type": "Feature",
  "properties": {
    "iso:country":"US",
    "sg:address":"3673 Co Rd P",
    "sg:city":"Cross Plains",
    "sg:classifiers":[
        {
            "category":"Organizations",
            "subcategory":"Religious Organization",
            "type":"Services"
        }
    ],
    "sg:phone":"+1 608 798 2111",
    "sg:postcode":"53528",
    "sg:province":"WI",
    "sg:tags":[
        "church"
    ],
    "wof:name":"St Mary's Of Pine Bluff Cath",
    "wof:placetype":"venue"
},
  "geometry": {"coordinates":[-89.631226,43.120933],"type":"Point"}
}