{
  "type": "Feature",
  "properties": {
    "iso:country":"US",
    "sg:address":"2355 Clark Rd",
    "sg:city":"Dresser",
    "sg:classifiers":[
        {
            "category":"Organizations",
            "subcategory":"Religious Organization",
            "type":"Services"
        }
    ],
    "sg:phone":"+1 715 755 2515",
    "sg:postcode":"54009",
    "sg:province":"WI",
    "sg:tags":[
        "church"
    ],
    "sg:website":"www.centurytel.net/peace",
    "wof:name":"Peace Lutheran Church ELCA",
    "wof:placetype":"venue"
},
  "geometry": {"coordinates":[-92.636812,45.365202],"type":"Point"}
}