{
  "type": "Feature",
  "properties": {
    "addr:full":"839 Stewart St Madison WI 53713",
    "addr:housenumber":"839",
    "addr:postcode":"53713",
    "addr:street":"Stewart St",
    "iso:country":"US",
    "sg:address":"839 Stewart St",
    "sg:city":"Madison",
    "sg:classifiers":[
        {
            "category":"Retail",
            "subcategory":"Auto Repair",
            "type":"Services"
        }
    ],
    "sg:phone":"+1 608 274 5545",
    "sg:postcode":"53713",
    "sg:province":"WI",
    "sg:tags":[
        "repairing",
        "automobile"
    ],
    "wof:name":"R H Automotive",
    "wof:placetype":"venue"
},
  "geometry": {"coordinates":[-89.39578899999999,43.029955],"type":"Point"}
}