{
  "type": "Feature",
  "properties": {
    "iso:country":"US",
    "sg:address":"1828 Tower Ave",
    "sg:city":"Superior",
    "sg:classifiers":[
        {
            "category":"Food & Beverages",
            "subcategory":"Specialty",
            "type":"Retail Goods"
        }
    ],
    "sg:phone":"+1 715 392 3303",
    "sg:postcode":"54880",
    "sg:province":"WI",
    "wof:name":"Superior Design & Coffees",
    "wof:placetype":"venue"
},
  "geometry": {"coordinates":[-92.10387799999999,46.716192],"type":"Point"}
}