{
  "type": "Feature",
  "properties": {
    "iso:country":"US",
    "sg:address":"7824 Fielding Ln",
    "sg:city":"Greendale",
    "sg:classifiers":[
        {
            "category":"Professional",
            "subcategory":"Management & Consulting",
            "type":"Services"
        }
    ],
    "sg:phone":"+1 414 421 1505",
    "sg:postcode":"53129",
    "sg:province":"WI",
    "wof:name":"Hillside Management LLC",
    "wof:placetype":"venue"
},
  "geometry": {"coordinates":[-88.013648,42.935017],"type":"Point"}
}