{
  "type": "Feature",
  "properties": {
    "iso:country":"US",
    "sg:address":"731 N Jackson St Ste 100",
    "sg:city":"Milwaukee",
    "sg:classifiers":[
        {
            "category":"Insurance",
            "subcategory":"Hazard Insurance",
            "type":"Services"
        },
        {
            "category":"Insurance",
            "subcategory":"Life Insurance",
            "type":"Services"
        },
        {
            "category":"Banks & Credit Unions",
            "subcategory":"Financial Services",
            "type":"Services"
        }
    ],
    "sg:phone":"+1 414 203 6044",
    "sg:postcode":"53202",
    "sg:province":"WI",
    "sg:website":"http://www.mikeslutzky.com/?src=yellow&DCMP=AFL-yellow",
    "wof:name":"Northwestern Mutual - Michael Slutzky",
    "wof:placetype":"venue"
},
  "geometry": {"coordinates":[-87.904082,43.039651],"type":"Point"}
}