{
  "type": "Feature",
  "properties": {
    "iso:country":"US",
    "sg:address":"2711 Pleasant St",
    "sg:city":"Eau Claire",
    "sg:classifiers":[
        {
            "category":"Professional",
            "subcategory":"Credit Reporting & Collection",
            "type":"Services"
        }
    ],
    "sg:phone":"+1 715 832 7151",
    "sg:postcode":"54701",
    "sg:province":"WI",
    "sg:tags":[
        "agency"
    ],
    "wof:name":"National Recovery Systems Corp",
    "wof:placetype":"venue"
},
  "geometry": {"coordinates":[-91.463155,44.799243],"type":"Point"}
}