{
  "type": "Feature",
  "properties": {
    "addr:full":"131 N Main St Lake Mills WI 53551",
    "addr:housenumber":"131",
    "addr:postcode":"53551",
    "addr:street":"N Main St",
    "iso:country":"US",
    "sg:address":"131 N Main St",
    "sg:city":"Lake Mills",
    "sg:classifiers":[
        {
            "category":"Restaurant",
            "type":"Food & Drink"
        }
    ],
    "sg:phone":"+1 920 648 2915",
    "sg:postcode":"53551",
    "sg:province":"WI",
    "wof:name":"Cafe On The Park",
    "wof:placetype":"venue"
},
  "geometry": {"coordinates":[-88.911885,43.080983],"type":"Point"}
}