{
  "type": "Feature",
  "properties": {
    "iso:country":"US",
    "sg:address":"25 S Stevens St",
    "sg:city":"Rhinelander",
    "sg:classifiers":[
        {
            "category":"Restaurant",
            "type":"Food & Drink"
        }
    ],
    "sg:phone":"+1 715 369 1775",
    "sg:postcode":"54501",
    "sg:province":"WI",
    "sg:tags":[
        "eating"
    ],
    "wof:name":"McDonalds",
    "wof:placetype":"venue"
},
  "geometry": {"coordinates":[-89.411242,45.63761],"type":"Point"}
}