{
  "type": "Feature",
  "properties": {
    "iso:country":"US",
    "sg:address":"4969 N 48th St",
    "sg:city":"Milwaukee",
    "sg:classifiers":[
        {
            "category":"Professional",
            "subcategory":"Management & Consulting",
            "type":"Services"
        }
    ],
    "sg:phone":"+1 414 852 7461",
    "sg:postcode":"53218",
    "sg:province":"WI",
    "sg:tags":[
        "business"
    ],
    "wof:name":"Buveck Consultants",
    "wof:placetype":"venue"
},
  "geometry": {"coordinates":[-87.97275500000001,43.105971],"type":"Point"}
}