{
  "type": "Feature",
  "properties": {
    "iso:country":"US",
    "sg:address":"8223 W Becher St",
    "sg:city":"Milwaukee",
    "sg:classifiers":[
        {
            "category":"Restaurant",
            "type":"Food & Drink"
        }
    ],
    "sg:phone":"+1 414 545 0700",
    "sg:postcode":"53219",
    "sg:province":"WI",
    "sg:tags":[
        "caterer"
    ],
    "wof:name":"Eci",
    "wof:placetype":"venue"
},
  "geometry": {"coordinates":[-88.01588,43.006236],"type":"Point"}
}