{
  "type": "Feature",
  "properties": {
    "iso:country":"US",
    "sg:address":"4525 W Dean Rd",
    "sg:city":"Milwaukee",
    "sg:classifiers":[
        {
            "category":"Wholesale",
            "subcategory":"Hardware",
            "type":"Manufacturing & Wholesale Goods"
        }
    ],
    "sg:phone":"+1 414 354 5910",
    "sg:postcode":"53223",
    "sg:province":"WI",
    "sg:tags":[
        "equipment",
        "heating",
        "system"
    ],
    "wof:name":"Acclaim Heating & Air Cond",
    "wof:placetype":"venue"
},
  "geometry": {"coordinates":[-87.967465,43.170332],"type":"Point"}
}