{
  "type": "Feature",
  "properties": {
    "iso:country":"US",
    "sg:address":"21772 Country Club Rd",
    "sg:city":"Shullsburg",
    "sg:classifiers":[
        {
            "category":"Farming",
            "subcategory":"Livestock Farm",
            "type":"Manufacturing & Wholesale Goods"
        }
    ],
    "sg:phone":"+1 608 776 2958",
    "sg:postcode":"53586",
    "sg:province":"WI",
    "sg:tags":[
        "feedlot",
        "corn",
        "soybean",
        "beef",
        "cattle"
    ],
    "wof:name":"Patrick McComish",
    "wof:placetype":"venue"
},
  "geometry": {"coordinates":[-90.249404,42.660525],"type":"Point"}
}