{
  "type": "Feature",
  "properties": {
    "addr:full":"2322 W Vliet St Milwaukee WI 53205",
    "addr:housenumber":"2322",
    "addr:postcode":"53205",
    "addr:street":"W Vliet St",
    "iso:country":"US",
    "sg:address":"2322 W Vliet St",
    "sg:city":"Milwaukee",
    "sg:classifiers":[
        {
            "category":"Professional",
            "type":"Services"
        }
    ],
    "sg:phone":"+1 414 933 1029",
    "sg:postcode":"53205",
    "sg:province":"WI",
    "wof:name":"Designed Details By Charisse",
    "wof:placetype":"venue"
},
  "geometry": {"coordinates":[-87.942682,43.0487],"type":"Point"}
}