{
  "type": "Feature",
  "properties": {
    "iso:country":"US",
    "sg:address":"1503 S 9th St",
    "sg:city":"Sheboygan",
    "sg:classifiers":[
        {
            "category":"Professional",
            "subcategory":"Business Services",
            "type":"Services"
        }
    ],
    "sg:phone":"+1 920 458 3575",
    "sg:postcode":"53081",
    "sg:province":"WI",
    "sg:tags":[
        "program",
        "incentive"
    ],
    "sg:website":"www.wschwartz.com",
    "wof:name":"Marketing Methods-Div Of Sello",
    "wof:placetype":"venue"
},
  "geometry": {"coordinates":[-87.714551,43.736929],"type":"Point"}
}