{
  "type": "Feature",
  "properties": {
    "iso:country":"US",
    "sg:address":"12341 N Dandelion Ct",
    "sg:city":"Mequon",
    "sg:classifiers":[
        {
            "category":"Local Transit",
            "type":"Transportation"
        }
    ],
    "sg:phone":"+1 262 243 9959",
    "sg:postcode":"53092",
    "sg:province":"WI",
    "sg:tags":[
        "handicapped"
    ],
    "wof:name":"L & W Transportation",
    "wof:placetype":"venue"
},
  "geometry": {"coordinates":[-87.918077,43.242095],"type":"Point"}
}