{
  "type": "Feature",
  "properties": {
    "iso:country":"US",
    "sg:address":"222 W Washington Ave",
    "sg:city":"Madison",
    "sg:classifiers":[
        {
            "category":"Shopping",
            "subcategory":"Computers & Home Electronics",
            "type":"Retail Goods"
        }
    ],
    "sg:phone":"+1 608 310 6012",
    "sg:postcode":"53703",
    "sg:province":"WI",
    "sg:tags":[
        "software"
    ],
    "wof:name":"3D Readers The Neuron Farm",
    "wof:placetype":"venue"
},
  "geometry": {"coordinates":[-89.387017,43.072806],"type":"Point"}
}