{
  "type": "Feature",
  "properties": {
    "iso:country":"US",
    "sg:address":"365 Cottonwood Ave",
    "sg:city":"Hartland",
    "sg:classifiers":[
        {
            "category":"Sports & Exercise",
            "subcategory":"Gym",
            "type":"Entertainment"
        }
    ],
    "sg:phone":"+1 262 369 9588",
    "sg:postcode":"53029",
    "sg:province":"WI",
    "sg:tags":[
        "club",
        "health"
    ],
    "wof:name":"Curves For Women",
    "wof:placetype":"venue"
},
  "geometry": {"coordinates":[-88.348243,43.102422],"type":"Point"}
}