{
  "type": "Feature",
  "properties": {
    "iso:country":"US",
    "sg:address":"8920 Durand Ave",
    "sg:city":"Sturtevant",
    "sg:classifiers":[
        {
            "category":"Autos & Motor Vehicles",
            "subcategory":"Fuel & Gas Station",
            "type":"Retail Goods"
        }
    ],
    "sg:phone":"+1 262 886 1409",
    "sg:postcode":"53177",
    "sg:province":"WI",
    "sg:tags":[
        "grocery",
        "station",
        "gasoline"
    ],
    "wof:name":"Speedway Superamerica LLC",
    "wof:placetype":"venue"
},
  "geometry": {"coordinates":[-87.892866,42.697993],"type":"Point"}
}