{
  "type": "Feature",
  "properties": {
    "addr:full":"8844 Oneida Rd Menasha WI 54952",
    "addr:housenumber":"8844",
    "addr:postcode":"54952",
    "addr:street":"Oneida Rd",
    "iso:country":"US",
    "sg:address":"8844 Oneida Rd",
    "sg:city":"Menasha",
    "sg:classifiers":[
        {
            "category":"Building & Trades",
            "subcategory":"Construction",
            "type":"Services"
        }
    ],
    "sg:phone":"+1 920 915 0184",
    "sg:postcode":"54952",
    "sg:province":"WI",
    "sg:tags":[
        "hanging",
        "contractor"
    ],
    "wof:name":"Advanced Services",
    "wof:placetype":"venue"
},
  "geometry": {"coordinates":[-88.404173,44.21514],"type":"Point"}
}