{
  "type": "Feature",
  "properties": {
    "iso:country":"US",
    "sg:address":"11231 W Forest Home Ave",
    "sg:city":"Franklin",
    "sg:classifiers":[
        {
            "category":"Sports & Exercise",
            "subcategory":"Bowling",
            "type":"Entertainment"
        }
    ],
    "sg:phone":"+1 414 425 3050",
    "sg:postcode":"53132",
    "sg:province":"WI",
    "sg:tags":[
        "alley"
    ],
    "wof:name":"Skylark Lanes",
    "wof:placetype":"venue"
},
  "geometry": {"coordinates":[-88.057163,42.916537],"type":"Point"}
}