{
  "type": "Feature",
  "properties": {
    "iso:country":"US",
    "sg:address":"1299 Garlick Rd",
    "sg:city":"Westby",
    "sg:classifiers":[
        {
            "category":"Farming",
            "subcategory":"Dairy Farm",
            "type":"Manufacturing & Wholesale Goods"
        }
    ],
    "sg:phone":"+1 608 634 4431",
    "sg:postcode":"54667",
    "sg:province":"WI",
    "wof:name":"Arnold Meyer",
    "wof:placetype":"venue"
},
  "geometry": {"coordinates":[-90.860556,43.682576],"type":"Point"}
}