{
  "type": "Feature",
  "properties": {
    "iso:country":"US",
    "sg:address":"706 55th St",
    "sg:city":"Kenosha",
    "sg:classifiers":[
        {
            "category":"Professional",
            "subcategory":"Detective & Security Services",
            "type":"Services"
        }
    ],
    "sg:phone":"+1 262 652 6831",
    "sg:postcode":"53140",
    "sg:province":"WI",
    "sg:tags":[
        "car"
    ],
    "wof:name":"Schmitt Protective Corporation",
    "wof:placetype":"venue"
},
  "geometry": {"coordinates":[-87.821183,42.585752],"type":"Point"}
}