{
  "type": "Feature",
  "properties": {
    "iso:country":"US",
    "sg:address":"2387 Cloverleaf Rd",
    "sg:city":"Sturgeon Bay",
    "sg:classifiers":[
        {
            "category":"Farming",
            "subcategory":"Farm",
            "type":"Manufacturing & Wholesale Goods"
        }
    ],
    "sg:phone":"+1 920 825 7029",
    "sg:postcode":"54235",
    "sg:province":"WI",
    "sg:tags":[
        "crop",
        "general"
    ],
    "wof:name":"L Jeanquart Farm",
    "wof:placetype":"venue"
},
  "geometry": {"coordinates":[-87.50948200000001,44.782038],"type":"Point"}
}