{
  "type": "Feature",
  "properties": {
    "iso:country":"US",
    "sg:address":"5073 Pioneer Rd",
    "sg:city":"Athens",
    "sg:phone":"+1 715 257 7841",
    "sg:postcode":"54411",
    "sg:province":"WI",
    "sg:tags":[
        "farm",
        "corn",
        "wheat"
    ],
    "wof:name":"Frank Omelian",
    "wof:placetype":"venue"
},
  "geometry": {"coordinates":[-90.065472,44.946494],"type":"Point"}
}