{
  "type": "Feature",
  "properties": {
    "iso:country":"US",
    "sg:address":"1300 E Main St",
    "sg:city":"Merrill",
    "sg:classifiers":[
        {
            "category":"Bars & Pubs",
            "type":"Food & Drink"
        }
    ],
    "sg:phone":"+1 715 536 8262",
    "sg:postcode":"54452",
    "sg:province":"WI",
    "sg:tags":[
        "drinking"
    ],
    "wof:name":"Gesundheit Bar & Grill",
    "wof:placetype":"venue"
},
  "geometry": {"coordinates":[-89.681725,45.180828],"type":"Point"}
}