{
  "type": "Feature",
  "properties": {
    "iso:country":"US",
    "sg:address":"6713 Co Rd X",
    "sg:city":"Webster",
    "sg:classifiers":[
        {
            "category":"Shopping",
            "type":"Retail Goods"
        }
    ],
    "sg:phone":"+1 715 866 4646",
    "sg:postcode":"54893",
    "sg:province":"WI",
    "sg:tags":[
        "merchandise",
        "monument"
    ],
    "wof:name":"Swedberg Monuments",
    "wof:placetype":"venue"
},
  "geometry": {"coordinates":[-92.33399799999999,45.871199],"type":"Point"}
}