{
  "type": "Feature",
  "properties": {
    "iso:country":"US",
    "sg:address":"16016 W Dorner Rd",
    "sg:city":"Brodhead",
    "sg:phone":"+1 608 879 2232",
    "sg:postcode":"53520",
    "sg:province":"WI",
    "sg:tags":[
        "farm",
        "field",
        "corn",
        "crop",
        "soybean"
    ],
    "wof:name":"Richard Massen",
    "wof:placetype":"venue"
},
  "geometry": {"coordinates":[-89.320187,42.672225],"type":"Point"}
}