{
  "type": "Feature",
  "properties": {
    "iso:country":"US",
    "sg:address":"5434 Dahlen Dr",
    "sg:city":"Madison",
    "sg:classifiers":[
        {
            "category":"Building & Trades",
            "subcategory":"Landscaping Services",
            "type":"Services"
        }
    ],
    "sg:phone":"+1 608 233 4215",
    "sg:postcode":"53705",
    "sg:province":"WI",
    "sg:tags":[
        "landscape",
        "contractor"
    ],
    "wof:name":"Landscape Designs Inc",
    "wof:placetype":"venue"
},
  "geometry": {"coordinates":[-89.477988,43.078912],"type":"Point"}
}