{
  "type": "Feature",
  "properties": {
    "iso:country":"US",
    "sg:address":"1224 Weeden Creek Rd",
    "sg:city":"Sheboygan",
    "sg:classifiers":[
        {
            "category":"Personal",
            "type":"Services"
        }
    ],
    "sg:phone":"+1 920 457 9555",
    "sg:postcode":"53081",
    "sg:province":"WI",
    "wof:name":"Sundance Tan",
    "wof:placetype":"venue"
},
  "geometry": {"coordinates":[-87.72292,43.701969],"type":"Point"}
}