{
  "type": "Feature",
  "properties": {
    "iso:country":"US",
    "sg:address":"6440 Bollard Ln",
    "sg:city":"Fennimore",
    "sg:phone":"+1 608 988 4642",
    "sg:postcode":"53809",
    "sg:province":"WI",
    "sg:tags":[
        "farm",
        "corn"
    ],
    "wof:name":"Robert Nelson Farm",
    "wof:placetype":"venue"
},
  "geometry": {"coordinates":[-90.736868,42.959488],"type":"Point"}
}