{
  "type": "Feature",
  "properties": {
    "iso:country":"US",
    "sg:address":"2404 Main St",
    "sg:city":"Cross Plains",
    "sg:classifiers":[
        {
            "category":"Autos & Motor Vehicles",
            "subcategory":"Automobile Sales",
            "type":"Retail Goods"
        }
    ],
    "sg:phone":"+1 608 798 3541",
    "sg:postcode":"53528",
    "sg:province":"WI",
    "sg:tags":[
        "car",
        "dealer"
    ],
    "wof:name":"Kalscheur Garage Inc",
    "wof:placetype":"venue"
},
  "geometry": {"coordinates":[-89.645661,43.111565],"type":"Point"}
}