{
  "type": "Feature",
  "properties": {
    "addr:full":"1146 Elizabeth St Madison WI 53703",
    "addr:housenumber":"1146",
    "addr:postcode":"53703",
    "addr:street":"Elizabeth St",
    "iso:country":"US",
    "sg:address":"1146 Elizabeth St",
    "sg:city":"Madison",
    "sg:classifiers":[
        {
            "category":"Building & Trades",
            "subcategory":"Landscaping Services",
            "type":"Services"
        }
    ],
    "sg:phone":"+1 608 698 1146",
    "sg:postcode":"53703",
    "sg:province":"WI",
    "sg:tags":[
        "lawn",
        "maintenance",
        "grounds"
    ],
    "wof:name":"Bando Lawn & Landscape",
    "wof:placetype":"venue"
},
  "geometry": {"coordinates":[-89.37259,43.089323],"type":"Point"}
}