{
  "type": "Feature",
  "properties": {
    "iso:country":"US",
    "sg:address":"1017 Park St",
    "sg:city":"Cross Plains",
    "sg:classifiers":[
        {
            "category":"Manufacturing",
            "subcategory":"Rubber & Plastics",
            "type":"Manufacturing & Wholesale Goods"
        }
    ],
    "sg:phone":"+1 608 798 3071",
    "sg:postcode":"53528",
    "sg:province":"WI",
    "sg:tags":[
        "packaging",
        "mfg"
    ],
    "sg:website":"www.plasticingenuity.com",
    "wof:name":"Plastic Ingenuity Inc",
    "wof:placetype":"venue"
},
  "geometry": {"coordinates":[-89.660766,43.11546],"type":"Point"}
}