{
  "type": "Feature",
  "properties": {
    "iso:country":"US",
    "sg:address":"180 Main St",
    "sg:city":"Menasha",
    "sg:classifiers":[
        {
            "category":"Building & Trades",
            "subcategory":"Construction",
            "type":"Services"
        }
    ],
    "sg:phone":"+1 920 235 1555",
    "sg:postcode":"54952",
    "sg:province":"WI",
    "sg:tags":[
        "garage",
        "builder"
    ],
    "wof:name":"Best Built Garage Builders Inc",
    "wof:placetype":"venue"
},
  "geometry": {"coordinates":[-88.44905199999999,44.200964],"type":"Point"}
}