{
  "type": "Feature",
  "properties": {
    "addr:full":"700 13th Ave Union Grove WI 53182",
    "addr:housenumber":"700",
    "addr:postcode":"53182",
    "addr:street":"13Th Ave",
    "iso:country":"US",
    "sg:address":"700 13th Ave",
    "sg:city":"Union Grove",
    "sg:classifiers":[
        {
            "category":"Building & Trades",
            "subcategory":"Construction",
            "type":"Services"
        }
    ],
    "sg:phone":"+1 262 878 3434",
    "sg:postcode":"53182",
    "sg:province":"WI",
    "sg:tags":[
        "residential"
    ],
    "wof:name":"Darrey Construction Inc",
    "wof:placetype":"venue"
},
  "geometry": {"coordinates":[-88.04848699999999,42.684253],"type":"Point"}
}