{
  "type": "Feature",
  "properties": {
    "iso:country":"US",
    "sg:address":"11600 W Center St",
    "sg:city":"Milwaukee",
    "sg:classifiers":[
        {
            "category":"Education",
            "subcategory":"School",
            "type":"Public Place"
        }
    ],
    "sg:phone":"+1 414 773 1100",
    "sg:postcode":"53222",
    "sg:province":"WI",
    "wof:name":"Eisenhower Elementary School",
    "wof:placetype":"venue"
},
  "geometry": {"coordinates":[-88.05698,43.067402],"type":"Point"}
}