{
  "type": "Feature",
  "properties": {
    "iso:country":"US",
    "sg:address":"2839 Harrison St",
    "sg:city":"Oshkosh",
    "sg:classifiers":[
        {
            "category":"Bars & Pubs",
            "type":"Food & Drink"
        }
    ],
    "sg:phone":"+1 920 231 5089",
    "sg:postcode":"54901",
    "sg:province":"WI",
    "sg:tags":[
        "drinking"
    ],
    "wof:name":"Cheatin Heart",
    "wof:placetype":"venue"
},
  "geometry": {"coordinates":[-88.528886,44.053408],"type":"Point"}
}