{
  "type": "Feature",
  "properties": {
    "iso:country":"US",
    "sg:address":"706 Post Rd",
    "sg:city":"Madison",
    "sg:classifiers":[
        {
            "category":"Personal",
            "subcategory":"Beauty Salon",
            "type":"Services"
        }
    ],
    "sg:phone":"+1 608 712 3825",
    "sg:postcode":"53713",
    "sg:province":"WI",
    "wof:name":"Aviance' Hair Studio",
    "wof:placetype":"venue"
},
  "geometry": {"coordinates":[-89.39294599999999,43.027128],"type":"Point"}
}