{
  "type": "Feature",
  "properties": {
    "iso:country":"US",
    "sg:address":"712 Milwaukee Ave",
    "sg:city":"South Milwaukee",
    "sg:classifiers":[
        {
            "category":"Organizations",
            "subcategory":"Labor Organization",
            "type":"Services"
        }
    ],
    "sg:phone":"+1 414 762 3738",
    "sg:postcode":"53172",
    "sg:province":"WI",
    "wof:name":"United Steelworkers Of America",
    "wof:placetype":"venue"
},
  "geometry": {"coordinates":[-87.85665899999999,42.910666],"type":"Point"}
}