{
  "type": "Feature",
  "properties": {
    "iso:country":"US",
    "sg:address":"3135 Delhi Rd",
    "sg:city":"Omro",
    "sg:classifiers":[
        {
            "category":"Autos & Motor Vehicles",
            "subcategory":"Motorcycle Sales",
            "type":"Retail Goods"
        }
    ],
    "sg:phone":"+1 920 685 2196",
    "sg:postcode":"54963",
    "sg:province":"WI",
    "wof:name":"DC Parts & Supply",
    "wof:placetype":"venue"
},
  "geometry": {"coordinates":[-88.785527,44.006333],"type":"Point"}
}