{
  "type": "Feature",
  "properties": {
    "iso:country":"US",
    "sg:address":"4679 Spaulding Rd",
    "sg:city":"Marion",
    "sg:classifiers":[
        {
            "category":"Professional",
            "subcategory":"Business Services",
            "type":"Services"
        }
    ],
    "sg:phone":"+1 715 754 2355",
    "sg:postcode":"54950",
    "sg:province":"WI",
    "wof:name":"Home Interior",
    "wof:placetype":"venue"
},
  "geometry": {"coordinates":[-88.992164,44.63366],"type":"Point"}
}