{
  "type": "Feature",
  "properties": {
    "iso:country":"US",
    "sg:address":"3333 Express Ct",
    "sg:city":"Appleton",
    "sg:classifiers":[
        {
            "category":"Retail",
            "subcategory":"Auto Repair",
            "type":"Services"
        }
    ],
    "sg:phone":"+1 920 585 2886",
    "sg:postcode":"54915",
    "sg:province":"WI",
    "sg:tags":[
        "repairing",
        "automobile",
        "automotive"
    ],
    "wof:name":"Automotive Services",
    "wof:placetype":"venue"
},
  "geometry": {"coordinates":[-88.359276,44.259659],"type":"Point"}
}