{
  "type": "Feature",
  "properties": {
    "iso:country":"US",
    "sg:address":"928 E Clairemont Ave",
    "sg:city":"Eau Claire",
    "sg:classifiers":[
        {
            "category":"Wholesale",
            "subcategory":"Farm Supplies",
            "type":"Manufacturing & Wholesale Goods"
        }
    ],
    "sg:phone":"+1 715 835 1558",
    "sg:postcode":"54701",
    "sg:province":"WI",
    "wof:name":"Lincoln Sales",
    "wof:placetype":"venue"
},
  "geometry": {"coordinates":[-91.490274,44.793196],"type":"Point"}
}