{
  "type": "Feature",
  "properties": {
    "iso:country":"US",
    "sg:address":"2717 3rd St",
    "sg:city":"Monroe",
    "sg:classifiers":[
        {
            "category":"Freight",
            "type":"Transportation"
        }
    ],
    "sg:phone":"+1 608 325 6242",
    "sg:postcode":"53566",
    "sg:province":"WI",
    "sg:tags":[
        "operator",
        "local",
        "trucking"
    ],
    "wof:name":"William J McGuire Trucking LLC",
    "wof:placetype":"venue"
},
  "geometry": {"coordinates":[-89.626373,42.609907],"type":"Point"}
}