{
  "type": "Feature",
  "properties": {
    "iso:country":"US",
    "sg:address":"32785 Co Rd K",
    "sg:city":"Prairie Du Chien",
    "sg:classifiers":[
        {
            "category":"Restaurant",
            "type":"Food & Drink"
        }
    ],
    "sg:phone":"+1 608 326 2888",
    "sg:postcode":"53821",
    "sg:province":"WI",
    "wof:name":"Winneshiek Marina",
    "wof:placetype":"venue"
},
  "geometry": {"coordinates":[-91.147471,43.087913],"type":"Point"}
}