{
  "type": "Feature",
  "properties": {
    "iso:country":"US",
    "sg:address":"8559 N Granville Rd Apt 208",
    "sg:city":"Milwaukee",
    "sg:classifiers":[
        {
            "category":"Taxi",
            "type":"Transportation"
        }
    ],
    "sg:phone":"+1 414 397 5654",
    "sg:postcode":"53224",
    "sg:province":"WI",
    "wof:name":"Cj Taxi",
    "wof:placetype":"venue"
},
  "geometry": {"coordinates":[-88.0398,43.172672],"type":"Point"}
}