{
  "type": "Feature",
  "properties": {
    "iso:country":"US",
    "sg:address":"7403 US Hwy 14",
    "sg:city":"Arena",
    "sg:classifiers":[
        {
            "category":"Retail",
            "subcategory":"Auto Repair",
            "type":"Services"
        }
    ],
    "sg:phone":"+1 608 753 2929",
    "sg:postcode":"53503",
    "sg:province":"WI",
    "sg:tags":[
        "automotive"
    ],
    "wof:name":"Quality Quick Lube & Detail",
    "wof:placetype":"venue"
},
  "geometry": {"coordinates":[-89.943712,43.161449],"type":"Point"}
}