{
  "type": "Feature",
  "properties": {
    "addr:full":"2515 S 30th St Milwaukee WI 53215",
    "addr:housenumber":"2515",
    "addr:postcode":"53215",
    "addr:street":"S 30Th St",
    "iso:country":"US",
    "sg:address":"2515 S 30th St",
    "sg:city":"Milwaukee",
    "sg:classifiers":[
        {
            "category":"Organizations",
            "subcategory":"Religious Organization",
            "type":"Services"
        }
    ],
    "sg:phone":"+1 414 671 5819",
    "sg:postcode":"53215",
    "sg:province":"WI",
    "sg:tags":[
        "place",
        "worship",
        "church"
    ],
    "sg:website":"http://achurchforallpeople.org",
    "wof:name":"Saint Cyril & Methodius Church",
    "wof:placetype":"venue"
},
  "geometry": {"coordinates":[-87.951778,42.999079],"type":"Point"}
}