{
  "type": "Feature",
  "properties": {
    "iso:country":"US",
    "sg:address":"4001 Peterson Rd",
    "sg:city":"Sturgeon Bay",
    "sg:classifiers":[
        {
            "category":"Utilities",
            "subcategory":"Refuse",
            "type":"Services"
        }
    ],
    "sg:phone":"+1 920 746 7434",
    "sg:postcode":"54235",
    "sg:province":"WI",
    "sg:tags":[
        "sanitary",
        "industrial",
        "system"
    ],
    "wof:name":"Little Hoppers",
    "wof:placetype":"venue"
},
  "geometry": {"coordinates":[-87.361683,44.862242],"type":"Point"}
}