{
  "type": "Feature",
  "properties": {
    "iso:country":"US",
    "sg:address":"29013 Co Rd H",
    "sg:city":"Cuba City",
    "sg:classifiers":[
        {
            "category":"Farming",
            "subcategory":"Dairy Farm",
            "type":"Manufacturing & Wholesale Goods"
        }
    ],
    "sg:phone":"+1 608 744 8709",
    "sg:postcode":"53807",
    "sg:province":"WI",
    "wof:name":"Bumble B Dairy Inc",
    "wof:placetype":"venue"
},
  "geometry": {"coordinates":[-90.38638,42.623685],"type":"Point"}
}