{
  "type": "Feature",
  "properties": {
    "iso:country":"US",
    "sg:address":"405 E Forest St",
    "sg:city":"Oconomowoc",
    "sg:classifiers":[
        {
            "category":"Professional",
            "subcategory":"Business Services",
            "type":"Services"
        }
    ],
    "sg:phone":"+1 262 569 3730",
    "sg:postcode":"53066",
    "sg:province":"WI",
    "wof:name":"Rosen & Rupnow Ltd",
    "wof:placetype":"venue"
},
  "geometry": {"coordinates":[-88.493011,43.102299],"type":"Point"}
}