{
  "type": "Feature",
  "properties": {
    "iso:country":"US",
    "sg:address":"126 W 2nd St",
    "sg:city":"Oconomowoc",
    "sg:classifiers":[
        {
            "category":"Personal",
            "subcategory":"Tanning Parlor",
            "type":"Services"
        },
        {
            "category":"Personal",
            "type":"Services"
        }
    ],
    "sg:phone":"+1 262 569 8499",
    "sg:postcode":"53066",
    "sg:province":"WI",
    "sg:tags":[
        "salon"
    ],
    "wof:name":"Tropical Island Tanning",
    "wof:placetype":"venue"
},
  "geometry": {"coordinates":[-88.501133,43.109449],"type":"Point"}
}