{
  "type": "Feature",
  "properties": {
    "addr:full":"2201 W Hampton Ave Milwaukee WI 53209",
    "addr:housenumber":"2201",
    "addr:postcode":"53209",
    "addr:street":"W Hampton Ave",
    "iso:country":"US",
    "sg:address":"2201 W Hampton Ave",
    "sg:city":"Milwaukee",
    "sg:classifiers":[
        {
            "category":"Freight",
            "type":"Transportation"
        },
        {
            "category":"Local Transit",
            "type":"Transportation"
        }
    ],
    "sg:phone":"+1 414 447 0347",
    "sg:postcode":"53209",
    "sg:province":"WI",
    "sg:tags":[
        "provider",
        "broker",
        "trucking"
    ],
    "wof:name":"D V Trans Inc",
    "wof:placetype":"venue"
},
  "geometry": {"coordinates":[-87.939278,43.104382],"type":"Point"}
}