{
  "type": "Feature",
  "properties": {
    "iso:country":"US",
    "sg:address":"15665 W Brentwood Dr",
    "sg:city":"Brookfield",
    "sg:classifiers":[
        {
            "category":"Building & Trades",
            "subcategory":"Construction",
            "type":"Services"
        }
    ],
    "sg:phone":"+1 262 783 9901",
    "sg:postcode":"53005",
    "sg:province":"WI",
    "sg:tags":[
        "house"
    ],
    "wof:name":"House Doctor",
    "wof:placetype":"venue"
},
  "geometry": {"coordinates":[-88.108234,43.097452],"type":"Point"}
}