{
  "type": "Feature",
  "properties": {
    "iso:country":"US",
    "sg:address":"10244 Jason Ave",
    "sg:city":"Sparta",
    "sg:classifiers":[
        {
            "category":"Organizations",
            "subcategory":"Non-profit Organization",
            "type":"Services"
        }
    ],
    "sg:phone":"+1 608 343 7794",
    "sg:postcode":"54656",
    "sg:province":"WI",
    "sg:tags":[
        "health"
    ],
    "wof:name":"That Special Touch",
    "wof:placetype":"venue"
},
  "geometry": {"coordinates":[-90.779985,43.878811],"type":"Point"}
}