{
  "type": "Feature",
  "properties": {
    "iso:country":"US",
    "sg:address":"411 E Fond du Lac St",
    "sg:city":"Ripon",
    "sg:classifiers":[
        {
            "category":"Organizations",
            "subcategory":"Religious Organization",
            "type":"Services"
        }
    ],
    "sg:phone":"+1 920 748 2325",
    "sg:postcode":"54971",
    "sg:province":"WI",
    "wof:name":"St Wenceslaus Church",
    "wof:placetype":"venue"
},
  "geometry": {"coordinates":[-88.83301899999999,43.840512],"type":"Point"}
}