{
  "type": "Feature",
  "properties": {
    "addr:full":"16381 W Boylan Rd Stone Lake WI 54876",
    "addr:housenumber":"16381",
    "addr:postcode":"54876",
    "addr:street":"W Boylan Rd",
    "iso:country":"US",
    "sg:address":"16381 W Boylan Rd",
    "sg:city":"Stone Lake",
    "sg:classifiers":[
        {
            "category":"Manufacturing",
            "subcategory":"Tools & Machinery",
            "type":"Manufacturing & Wholesale Goods"
        }
    ],
    "sg:phone":"+1 715 865 6204",
    "sg:postcode":"54876",
    "sg:province":"WI",
    "sg:tags":[
        "machine",
        "shop"
    ],
    "wof:name":"Tri-Tech Enterprises",
    "wof:placetype":"venue"
},
  "geometry": {"coordinates":[-91.51969,45.8704],"type":"Point"}
}