{
  "type": "Feature",
  "properties": {
    "iso:country":"US",
    "sg:address":"720 25th Ave",
    "sg:city":"Monroe",
    "sg:classifiers":[
        {
            "category":"Freight",
            "type":"Transportation"
        }
    ],
    "sg:phone":"+1 608 325 6646",
    "sg:postcode":"53566",
    "sg:province":"WI",
    "sg:tags":[
        "local",
        "storage",
        "trucking"
    ],
    "wof:name":"Scherer Moving & Storage",
    "wof:placetype":"venue"
},
  "geometry": {"coordinates":[-89.629836,42.6049],"type":"Point"}
}