{
  "type": "Feature",
  "properties": {
    "iso:country":"US",
    "sg:address":"1320 Scenic Dr",
    "sg:city":"Kewaskum",
    "sg:classifiers":[
        {
            "category":"Building & Trades",
            "subcategory":"Electrical",
            "type":"Services"
        }
    ],
    "sg:phone":"+1 262 692 2607",
    "sg:postcode":"53040",
    "sg:province":"WI",
    "sg:tags":[
        "electrical",
        "contractor"
    ],
    "wof:name":"Enright Electric",
    "wof:placetype":"venue"
},
  "geometry": {"coordinates":[-88.10556200000001,43.527291],"type":"Point"}
}