{
  "type": "Feature",
  "properties": {
    "addr:full":"5211 W Lisbon Ave Milwaukee WI 53210",
    "addr:housenumber":"5211",
    "addr:postcode":"53210",
    "addr:street":"W Lisbon Ave",
    "iso:country":"US",
    "sg:address":"5211 W Lisbon Ave",
    "sg:city":"Milwaukee",
    "sg:classifiers":[
        {
            "category":"Autos & Motor Vehicles",
            "subcategory":"Automobile Sales",
            "type":"Retail Goods"
        }
    ],
    "sg:phone":"+1 414 447 1366",
    "sg:postcode":"53210",
    "sg:province":"WI",
    "sg:tags":[
        "used"
    ],
    "wof:name":"Stevie GS Used Cars",
    "wof:placetype":"venue"
},
  "geometry": {"coordinates":[-87.979845,43.064035],"type":"Point"}
}