{
  "type": "Feature",
  "properties": {
    "iso:country":"US",
    "sg:address":"9630 Lee Rd",
    "sg:city":"Minocqua",
    "sg:classifiers":[
        {
            "category":"Building & Trades",
            "subcategory":"Construction",
            "type":"Services"
        }
    ],
    "sg:phone":"+1 715 358 4044",
    "sg:postcode":"54548",
    "sg:province":"WI",
    "sg:tags":[
        "siding",
        "contractor"
    ],
    "wof:name":"Northwoods Siding & Windows",
    "wof:placetype":"venue"
},
  "geometry": {"coordinates":[-89.715675,45.825102],"type":"Point"}
}