{
  "type": "Feature",
  "properties": {
    "iso:country":"US",
    "sg:address":"1447 10th St",
    "sg:city":"Turtle Lake",
    "sg:classifiers":[
        {
            "category":"Retail",
            "subcategory":"Auto Repair",
            "type":"Services"
        }
    ],
    "sg:phone":"+1 715 986 2739",
    "sg:postcode":"54889",
    "sg:province":"WI",
    "sg:tags":[
        "general"
    ],
    "wof:name":"Turtle Lake Motor Sports & Mar",
    "wof:placetype":"venue"
},
  "geometry": {"coordinates":[-92.17668,45.419128],"type":"Point"}
}