{
  "type": "Feature",
  "properties": {
    "iso:country":"US",
    "sg:address":"2945 Windswept Way",
    "sg:city":"Verona",
    "sg:classifiers":[
        {
            "category":"Building & Trades",
            "subcategory":"Construction",
            "type":"Services"
        }
    ],
    "sg:phone":"+1 608 848 6677",
    "sg:postcode":"53593",
    "sg:province":"WI",
    "sg:tags":[
        "hanging",
        "painter",
        "contractor"
    ],
    "wof:name":"Humboldt's Painting Inc",
    "wof:placetype":"venue"
},
  "geometry": {"coordinates":[-89.549389,43.015573],"type":"Point"}
}