{
  "type": "Feature",
  "properties": {
    "iso:country":"US",
    "sg:address":"912 S Central Ave",
    "sg:city":"Marshfield",
    "sg:classifiers":[
        {
            "category":"Insurance",
            "subcategory":"Insurance Agent",
            "type":"Services"
        }
    ],
    "sg:phone":"+1 715 387 6677",
    "sg:postcode":"54449",
    "sg:province":"WI",
    "wof:name":"Service Central Financial Svcs",
    "wof:placetype":"venue"
},
  "geometry": {"coordinates":[-90.178721,44.659537],"type":"Point"}
}