{
  "type": "Feature",
  "properties": {
    "iso:country":"US",
    "sg:address":"161 W Chestnut St",
    "sg:city":"Burlington",
    "sg:classifiers":[
        {
            "category":"Government",
            "subcategory":"Office",
            "type":"Public Place"
        }
    ],
    "sg:phone":"+1 262 763 7896",
    "sg:postcode":"53105",
    "sg:province":"WI",
    "sg:tags":[
        "armed",
        "force",
        "recruiting"
    ],
    "wof:name":"US Naval Recruiting",
    "wof:placetype":"venue"
},
  "geometry": {"coordinates":[-88.278038,42.680268],"type":"Point"}
}