{
  "type": "Feature",
  "properties": {
    "iso:country":"US",
    "sg:address":"1120 Main St",
    "sg:city":"Union Grove",
    "sg:classifiers":[
        {
            "category":"Health Services",
            "subcategory":"Doctor",
            "type":"Services"
        }
    ],
    "sg:phone":"+1 262 687 2606",
    "sg:postcode":"53182",
    "sg:province":"WI",
    "sg:tags":[
        "clinic"
    ],
    "wof:name":"All Saints Medical Group",
    "wof:placetype":"venue"
},
  "geometry": {"coordinates":[-88.051944,42.686225],"type":"Point"}
}