{
  "type": "Feature",
  "properties": {
    "addr:full":"2007 Pleasant St Milwaukee WI 53213",
    "addr:housenumber":"2007",
    "addr:postcode":"53213",
    "addr:street":"Pleasant St",
    "iso:country":"US",
    "sg:address":"2007 Pleasant St",
    "sg:city":"Milwaukee",
    "sg:classifiers":[
        {
            "category":"Professional",
            "subcategory":"Management & Consulting",
            "type":"Services"
        }
    ],
    "sg:phone":"+1 414 257 3593",
    "sg:postcode":"53213",
    "sg:province":"WI",
    "sg:tags":[
        "retail",
        "direct",
        "sales"
    ],
    "wof:name":"Julie Lucey",
    "wof:placetype":"venue"
},
  "geometry": {"coordinates":[-88.012325,43.05744],"type":"Point"}
}