{
  "type": "Feature",
  "properties": {
    "iso:country":"US",
    "sg:address":"1839 Thiry Daems Rd",
    "sg:city":"Luxemburg",
    "sg:classifiers":[
        {
            "category":"Freight",
            "type":"Transportation"
        }
    ],
    "sg:phone":"+1 920 845 2634",
    "sg:postcode":"54217",
    "sg:province":"WI",
    "sg:tags":[
        "local",
        "trucking"
    ],
    "wof:name":"Jadin James Trucking",
    "wof:placetype":"venue"
},
  "geometry": {"coordinates":[-87.676637,44.603209],"type":"Point"}
}