{
  "type": "Feature",
  "properties": {
    "iso:country":"US",
    "sg:address":"5300 S 76th St",
    "sg:city":"Greendale",
    "sg:classifiers":[
        {
            "category":"Shopping",
            "subcategory":"Jewelry",
            "type":"Retail Goods"
        }
    ],
    "sg:phone":"+1 414 421 8555",
    "sg:postcode":"53129",
    "sg:province":"WI",
    "wof:name":"B & B Stores",
    "wof:placetype":"venue"
},
  "geometry": {"coordinates":[-88.008476,42.946837],"type":"Point"}
}