{
  "type": "Feature",
  "properties": {
    "iso:country":"US",
    "sg:address":"3177 Hamilton Rd",
    "sg:city":"Springbrook",
    "sg:classifiers":[
        {
            "category":"Sports & Exercise",
            "subcategory":"Gym",
            "type":"Entertainment"
        }
    ],
    "sg:phone":"+1 715 766 2045",
    "sg:postcode":"54875",
    "sg:province":"WI",
    "sg:tags":[
        "fitness",
        "physical",
        "facility"
    ],
    "wof:name":"Damian Vraniak",
    "wof:placetype":"venue"
},
  "geometry": {"coordinates":[-91.70032999999999,45.957377],"type":"Point"}
}