{
  "type": "Feature",
  "properties": {
    "iso:country":"US",
    "sg:address":"413 Fremont St",
    "sg:city":"Kiel",
    "sg:classifiers":[
        {
            "category":"Organizations",
            "subcategory":"Religious Organization",
            "type":"Services"
        }
    ],
    "sg:phone":"+1 920 894 3553",
    "sg:postcode":"53042",
    "sg:province":"WI",
    "sg:tags":[
        "church"
    ],
    "sg:website":"www.spps.pvt.k12.wi.us",
    "wof:name":"St Peter & Paul",
    "wof:placetype":"venue"
},
  "geometry": {"coordinates":[-88.035732,43.912588],"type":"Point"}
}