{
  "type": "Feature",
  "properties": {
    "iso:country":"US",
    "sg:address":"339 W North Ave",
    "sg:city":"Milwaukee",
    "sg:classifiers":[
        {
            "category":"Shopping",
            "subcategory":"Shoes",
            "type":"Retail Goods"
        }
    ],
    "sg:phone":"+1 414 264 2356",
    "sg:postcode":"53212",
    "sg:province":"WI",
    "wof:name":"Foot Locker",
    "wof:placetype":"venue"
},
  "geometry": {"coordinates":[-87.915128,43.060209],"type":"Point"}
}