{
  "type": "Feature",
  "properties": {
    "iso:country":"US",
    "sg:address":"300 Seward St",
    "sg:city":"Ripon",
    "sg:classifiers":[
        {
            "category":"Education",
            "subcategory":"College",
            "type":"Public Place"
        }
    ],
    "sg:phone":"+1 920 748 8115",
    "sg:postcode":"54971",
    "sg:province":"WI",
    "sg:tags":[
        "academic",
        "school"
    ],
    "sg:website":"www.ripon.edu",
    "wof:name":"Ripon College",
    "wof:placetype":"venue"
},
  "geometry": {"coordinates":[-88.834648,43.842951],"type":"Point"}
}