{
  "type": "Feature",
  "properties": {
    "iso:country":"US",
    "sg:address":"200 S Main St",
    "sg:city":"Alma",
    "sg:classifiers":[
        {
            "category":"Shopping",
            "subcategory":"Gifts & Souvenirs",
            "type":"Retail Goods"
        }
    ],
    "sg:phone":"+1 608 685 4555",
    "sg:postcode":"54610",
    "sg:province":"WI",
    "sg:tags":[
        "shop"
    ],
    "wof:name":"Beef Slough Store",
    "wof:placetype":"venue"
},
  "geometry": {"coordinates":[-91.914551,44.319127],"type":"Point"}
}