{
  "type": "Feature",
  "properties": {
    "iso:country":"US",
    "sg:address":"1425 Summit Ave",
    "sg:city":"Waukesha",
    "sg:classifiers":[
        {
            "category":"Health Services",
            "subcategory":"Health Practitioner",
            "type":"Services"
        }
    ],
    "sg:phone":"+1 262 970 9630",
    "sg:postcode":"53188",
    "sg:province":"WI",
    "sg:tags":[
        "acupuncture"
    ],
    "wof:name":"Waukesha Wellness Clinic",
    "wof:placetype":"venue"
},
  "geometry": {"coordinates":[-88.25093699999999,43.021453],"type":"Point"}
}