{
  "type": "Feature",
  "properties": {
    "addr:full":"2321 State Hwy 25 Menomonie WI 54751",
    "addr:housenumber":"2321",
    "addr:postcode":"54751",
    "addr:street":"State Hwy 25",
    "iso:country":"US",
    "sg:address":"2321 State Hwy 25",
    "sg:city":"Menomonie",
    "sg:classifiers":[
        {
            "category":"Food & Beverages",
            "subcategory":"Specialty",
            "type":"Retail Goods"
        }
    ],
    "sg:phone":"+1 715 235 5866",
    "sg:postcode":"54751",
    "sg:province":"WI",
    "sg:tags":[
        "health",
        "diet"
    ],
    "wof:name":"GNC",
    "wof:placetype":"venue"
},
  "geometry": {"coordinates":[-91.936168,44.766203],"type":"Point"}
}