{
  "type": "Feature",
  "properties": {
    "iso:country":"US",
    "sg:address":"838 Cardinal Dr",
    "sg:city":"Cedarburg",
    "sg:classifiers":[
        {
            "category":"Shopping",
            "subcategory":"Computers & Home Electronics",
            "type":"Retail Goods"
        }
    ],
    "sg:phone":"+1 262 376 9000",
    "sg:postcode":"53012",
    "sg:province":"WI",
    "wof:name":"Computer Software Liquidations",
    "wof:placetype":"venue"
},
  "geometry": {"coordinates":[-88.081084,43.280023],"type":"Point"}
}