{
  "type": "Feature",
  "properties": {
    "iso:country":"US",
    "sg:address":"801 Milwaukee Ave",
    "sg:city":"South Milwaukee",
    "sg:classifiers":[
        {
            "category":"Health Services",
            "subcategory":"Doctor",
            "type":"Services"
        }
    ],
    "sg:phone":"+1 414 762 2300",
    "sg:postcode":"53172",
    "sg:province":"WI",
    "sg:tags":[
        "dentist"
    ],
    "wof:name":"Melvyn F Foley DDS",
    "wof:placetype":"venue"
},
  "geometry": {"coordinates":[-87.85875900000001,42.91064],"type":"Point"}
}