{
  "type": "Feature",
  "properties": {
    "iso:country":"US",
    "sg:address":"332 Sugar Bush Ln",
    "sg:city":"Elkhart Lake",
    "sg:classifiers":[
        {
            "category":"Professional",
            "subcategory":"Management & Consulting",
            "type":"Services"
        }
    ],
    "sg:phone":"+1 920 876 2528",
    "sg:postcode":"53020",
    "sg:province":"WI",
    "wof:name":"Braninger Tommy Sports",
    "wof:placetype":"venue"
},
  "geometry": {"coordinates":[-88.01287499999999,43.821362],"type":"Point"}
}