{
  "type": "Feature",
  "properties": {
    "iso:country":"US",
    "sg:address":"124 W Main St",
    "sg:city":"Winneconne",
    "sg:classifiers":[
        {
            "category":"Banks & Credit Unions",
            "subcategory":"Bank",
            "type":"Services"
        }
    ],
    "sg:phone":"+1 920 582 4351",
    "sg:postcode":"54986",
    "sg:province":"WI",
    "wof:name":"Citizens Bank",
    "wof:placetype":"venue"
},
  "geometry": {"coordinates":[-88.711871,44.110925],"type":"Point"}
}