{
  "type": "Feature",
  "properties": {
    "iso:country":"US",
    "sg:address":"1019 Madison St",
    "sg:city":"Waukesha",
    "sg:classifiers":[
        {
            "category":"Organizations",
            "subcategory":"Professional Association",
            "type":"Services"
        }
    ],
    "sg:phone":"+1 262 544 4415",
    "sg:postcode":"53188",
    "sg:province":"WI",
    "sg:tags":[
        "business"
    ],
    "wof:name":"Spec Products Inc",
    "wof:placetype":"venue"
},
  "geometry": {"coordinates":[-88.246023,43.013239],"type":"Point"}
}