{
  "type": "Feature",
  "properties": {
    "iso:country":"US",
    "sg:address":"2815 Ramada Way",
    "sg:city":"Green Bay",
    "sg:classifiers":[
        {
            "category":"Travel",
            "subcategory":"Hotels & Motels",
            "type":"Entertainment"
        }
    ],
    "sg:phone":"+1 920 494 8790",
    "sg:postcode":"54304",
    "sg:province":"WI",
    "wof:name":"Best Western",
    "wof:placetype":"venue"
},
  "geometry": {"coordinates":[-88.077766,44.473221],"type":"Point"}
}