{
  "type": "Feature",
  "properties": {
    "iso:country":"US",
    "sg:address":"11028 W 18th Rd",
    "sg:city":"Pound",
    "sg:classifiers":[
        {
            "category":"Building & Trades",
            "subcategory":"Landscaping Services",
            "type":"Services"
        }
    ],
    "sg:phone":"+1 920 897 2846",
    "sg:postcode":"54161",
    "sg:province":"WI",
    "wof:name":"Marios Custom Stump Removal",
    "wof:placetype":"venue"
},
  "geometry": {"coordinates":[-88.15052900000001,45.153285],"type":"Point"}
}