{
  "type": "Feature",
  "properties": {
    "addr:full":"626 Monroe St Fort Atkinson WI 53538",
    "addr:housenumber":"626",
    "addr:postcode":"53538",
    "addr:street":"Monroe St",
    "iso:country":"US",
    "sg:address":"626 Monroe St",
    "sg:city":"Fort Atkinson",
    "sg:classifiers":[
        {
            "category":"Food & Beverages",
            "subcategory":"Specialty",
            "type":"Retail Goods"
        }
    ],
    "sg:phone":"+1 920 563 6877",
    "sg:postcode":"53538",
    "sg:province":"WI",
    "sg:tags":[
        "health",
        "diet"
    ],
    "wof:name":"Shaklee Distributor",
    "wof:placetype":"venue"
},
  "geometry": {"coordinates":[-88.844506,42.936253],"type":"Point"}
}