{
  "type": "Feature",
  "properties": {
    "addr:full":"3701 Rib Mountain Dr Wausau WI 54401",
    "addr:housenumber":"3701",
    "addr:postcode":"54401",
    "addr:street":"Rib Mountain Dr",
    "iso:country":"US",
    "sg:address":"3701 Rib Mountain Dr",
    "sg:city":"Wausau",
    "sg:classifiers":[
        {
            "category":"Shopping",
            "subcategory":"Department Store",
            "type":"Retail Goods"
        }
    ],
    "sg:phone":"+1 715 241 7959",
    "sg:postcode":"54401",
    "sg:province":"WI",
    "wof:name":"Gordmans",
    "wof:placetype":"venue"
},
  "geometry": {"coordinates":[-89.653187,44.925347],"type":"Point"}
}