{
  "type": "Feature",
  "properties": {
    "iso:country":"US",
    "sg:address":"2602 Hughitt Ave",
    "sg:city":"Superior",
    "sg:classifiers":[
        {
            "category":"Retail",
            "subcategory":"Auto Rental",
            "type":"Services"
        }
    ],
    "sg:phone":"+1 218 391 2706",
    "sg:postcode":"54880",
    "sg:province":"WI",
    "sg:tags":[
        "limousine"
    ],
    "wof:name":"Five Star Limo Service Inc",
    "wof:placetype":"venue"
},
  "geometry": {"coordinates":[-92.09953299999999,46.707725],"type":"Point"}
}