{
  "type": "Feature",
  "properties": {
    "addr:full":"11003 17th Ave Necedah WI 54646",
    "addr:housenumber":"11003",
    "addr:postcode":"54646",
    "addr:street":"17Th Ave",
    "iso:country":"US",
    "sg:address":"11003 17th Ave",
    "sg:city":"Necedah",
    "sg:classifiers":[
        {
            "category":"Education",
            "subcategory":"School",
            "type":"Public Place"
        }
    ],
    "sg:phone":"+1 608 565 4660",
    "sg:postcode":"54646",
    "sg:province":"WI",
    "sg:tags":[
        "academic",
        "special"
    ],
    "wof:name":"Juneau County Adolescent Needs",
    "wof:placetype":"venue"
},
  "geometry": {"coordinates":[-90.035326,44.044301],"type":"Point"}
}