{
  "type": "Feature",
  "properties": {
    "iso:country":"US",
    "sg:address":"144 E Oak St",
    "sg:city":"Juneau",
    "sg:classifiers":[
        {
            "category":"Government",
            "subcategory":"Court House",
            "type":"Public Place"
        }
    ],
    "sg:phone":"+1 920 386 5577",
    "sg:postcode":"53039",
    "sg:province":"WI",
    "sg:tags":[
        "state",
        "counsel"
    ],
    "wof:name":"Public Defender",
    "wof:placetype":"venue"
},
  "geometry": {"coordinates":[-88.70352800000001,43.406882],"type":"Point"}
}