{
  "type": "Feature",
  "properties": {
    "addr:full":"2450 Hoftiezer Rd Oostburg WI 53070",
    "addr:housenumber":"2450",
    "addr:postcode":"53070",
    "addr:street":"Hoftiezer Rd",
    "iso:country":"US",
    "sg:address":"2450 Hoftiezer Rd",
    "sg:city":"Oostburg",
    "sg:classifiers":[
        {
            "category":"Building & Trades",
            "subcategory":"Construction",
            "type":"Services"
        }
    ],
    "sg:phone":"+1 920 564 2058",
    "sg:postcode":"53070",
    "sg:province":"WI",
    "sg:tags":[
        "excavation",
        "contractor"
    ],
    "wof:name":"Brills Excavating",
    "wof:placetype":"venue"
},
  "geometry": {"coordinates":[-87.81661699999999,43.604908],"type":"Point"}
}