{
  "type": "Feature",
  "properties": {
    "iso:country":"US",
    "sg:address":"7852 Freedom Rd",
    "sg:city":"North Freedom",
    "sg:classifiers":[
        {
            "category":"Professional",
            "type":"Services"
        }
    ],
    "sg:phone":"+1 608 643 6527",
    "sg:postcode":"53951",
    "sg:province":"WI",
    "wof:name":"Richard Stone",
    "wof:placetype":"venue"
},
  "geometry": {"coordinates":[-89.86197,43.368515],"type":"Point"}
}