{
  "type": "Feature",
  "properties": {
    "iso:country":"US",
    "sg:address":"1707 Freedom Rd",
    "sg:city":"Little Chute",
    "sg:classifiers":[
        {
            "category":"Professional",
            "subcategory":"Computer Services",
            "type":"Services"
        }
    ],
    "sg:phone":"+1 920 687 2972",
    "sg:postcode":"54140",
    "sg:province":"WI",
    "sg:tags":[
        "website",
        "design"
    ],
    "sg:website":"www.imccentral.com",
    "wof:name":"Innovative Media Corp",
    "wof:placetype":"venue"
},
  "geometry": {"coordinates":[-88.313073,44.291154],"type":"Point"}
}