{
  "type": "Feature",
  "properties": {
    "iso:country":"US",
    "sg:address":"932 Co Rd A",
    "sg:city":"Prentice",
    "sg:classifiers":[
        {
            "category":"Manufacturing",
            "subcategory":"Tools & Machinery",
            "type":"Manufacturing & Wholesale Goods"
        }
    ],
    "sg:phone":"+1 715 428 2919",
    "sg:postcode":"54556",
    "sg:province":"WI",
    "sg:tags":[
        "machine",
        "shop"
    ],
    "wof:name":"Balczewski Custom Mach & Fab",
    "wof:placetype":"venue"
},
  "geometry": {"coordinates":[-90.28830499999999,45.542058],"type":"Point"}
}