{
  "type": "Feature",
  "properties": {
    "addr:full":"3817 S 108th St Milwaukee WI 53228",
    "addr:housenumber":"3817",
    "addr:postcode":"53228",
    "addr:street":"S 108Th St",
    "iso:country":"US",
    "sg:address":"3817 S 108th St",
    "sg:city":"Milwaukee",
    "sg:classifiers":[
        {
            "category":"Recreation",
            "subcategory":"Arcade",
            "type":"Entertainment"
        }
    ],
    "sg:phone":"+1 414 545 9123",
    "sg:postcode":"53228",
    "sg:province":"WI",
    "sg:tags":[
        "game",
        "video"
    ],
    "wof:name":"Video Game Exchange",
    "wof:placetype":"venue"
},
  "geometry": {"coordinates":[-88.047659,42.97418],"type":"Point"}
}