{
  "type": "Feature",
  "properties": {
    "addr:full":"1027 Riders Club Rd Onalaska WI 54650",
    "addr:housenumber":"1027",
    "addr:postcode":"54650",
    "addr:street":"Riders Club Rd",
    "iso:country":"US",
    "sg:address":"1027 Riders Club Rd",
    "sg:city":"Onalaska",
    "sg:classifiers":[
        {
            "category":"Insurance",
            "subcategory":"Insurance Agent",
            "type":"Services"
        }
    ],
    "sg:phone":"+1 608 781 3323",
    "sg:postcode":"54650",
    "sg:province":"WI",
    "sg:tags":[
        "administrator"
    ],
    "wof:name":"Greater Insurance Service",
    "wof:placetype":"venue"
},
  "geometry": {"coordinates":[-91.22276599999999,43.905599],"type":"Point"}
}