{
  "type": "Feature",
  "properties": {
    "iso:country":"US",
    "sg:address":"14601 Braun Rd",
    "sg:city":"Sturtevant",
    "sg:classifiers":[
        {
            "category":"Manufacturing",
            "subcategory":"Metals",
            "type":"Manufacturing & Wholesale Goods"
        }
    ],
    "sg:phone":"+1 262 878 1700",
    "sg:postcode":"53177",
    "sg:province":"WI",
    "sg:tags":[
        "steel",
        "industrial",
        "mfg",
        "tool",
        "foundry",
        "machine",
        "machinery"
    ],
    "wof:name":"E & R Mfg",
    "wof:placetype":"venue"
},
  "geometry": {"coordinates":[-87.96613600000001,42.684156],"type":"Point"}
}