{
  "type": "Feature",
  "properties": {
    "iso:country":"US",
    "sg:address":"13725 State Hwy 64",
    "sg:city":"Bloomer",
    "sg:classifiers":[
        {
            "category":"Building & Trades",
            "subcategory":"Construction",
            "type":"Services"
        }
    ],
    "sg:phone":"+1 715 288 6395",
    "sg:postcode":"54724",
    "sg:province":"WI",
    "sg:tags":[
        "home",
        "house",
        "carpentry",
        "improvement",
        "contractor"
    ],
    "wof:name":"Kerckhove Home Improvements",
    "wof:placetype":"venue"
},
  "geometry": {"coordinates":[-91.38914200000001,45.120259],"type":"Point"}
}