{
  "type": "Feature",
  "properties": {
    "iso:country":"US",
    "sg:address":"1196 Co Rd T",
    "sg:city":"Marshall",
    "sg:phone":"+1 608 655 3056",
    "sg:postcode":"53559",
    "sg:province":"WI",
    "sg:tags":[
        "farm",
        "corn",
        "soybean"
    ],
    "wof:name":"Caroline Langer",
    "wof:placetype":"venue"
},
  "geometry": {"coordinates":[-89.099845,43.160904],"type":"Point"}
}