{
  "type": "Feature",
  "properties": {
    "iso:country":"US",
    "sg:address":"208 Industrial Dr",
    "sg:city":"Verona",
    "sg:classifiers":[
        {
            "category":"Professional",
            "subcategory":"Computer Services",
            "type":"Services"
        }
    ],
    "sg:phone":"+1 608 845 8883",
    "sg:postcode":"53593",
    "sg:province":"WI",
    "sg:tags":[
        "repair"
    ],
    "wof:name":"Service Electronics Corp",
    "wof:placetype":"venue"
},
  "geometry": {"coordinates":[-89.538503,42.985838],"type":"Point"}
}