{
  "type": "Feature",
  "properties": {
    "iso:country":"US",
    "sg:address":"3260 Co Rd R",
    "sg:city":"Durand",
    "sg:classifiers":[
        {
            "category":"Farming",
            "subcategory":"Farm",
            "type":"Manufacturing & Wholesale Goods"
        }
    ],
    "sg:phone":"+1 715 672 5740",
    "sg:postcode":"54736",
    "sg:province":"WI",
    "sg:tags":[
        "crop",
        "general"
    ],
    "wof:name":"Berg Orlin Farm",
    "wof:placetype":"venue"
},
  "geometry": {"coordinates":[-91.815995,44.654225],"type":"Point"}
}