{
  "type": "Feature",
  "properties": {
    "iso:country":"US",
    "sg:address":"10562 Shady Lane Rd",
    "sg:city":"Baraboo",
    "sg:classifiers":[
        {
            "category":"Travel",
            "subcategory":"Campground",
            "type":"Entertainment"
        }
    ],
    "sg:phone":"+1 608 356 5898",
    "sg:postcode":"53913",
    "sg:province":"WI",
    "sg:website":"www.dellboo.com",
    "wof:name":"Dell Boo Campground",
    "wof:placetype":"venue"
},
  "geometry": {"coordinates":[-89.794939,43.54713],"type":"Point"}
}