{
  "type": "Feature",
  "properties": {
    "iso:country":"US",
    "sg:address":"9625 S 20th St",
    "sg:city":"Oak Creek",
    "sg:classifiers":[
        {
            "category":"Retail",
            "subcategory":"Car Wash",
            "type":"Services"
        }
    ],
    "sg:phone":"+1 414 761 1099",
    "sg:postcode":"53154",
    "sg:province":"WI",
    "sg:tags":[
        "truck"
    ],
    "wof:name":"Blue Beacon of Milwaukee",
    "wof:placetype":"venue"
},
  "geometry": {"coordinates":[-87.94237699999999,42.871929],"type":"Point"}
}