{
  "type": "Feature",
  "properties": {
    "addr:full":"6787 Co Rd Pp Ripon WI 54971",
    "addr:housenumber":"6787",
    "addr:postcode":"54971",
    "addr:street":"Co Rd Pp",
    "iso:country":"US",
    "sg:address":"6787 Co Rd Pp",
    "sg:city":"Ripon",
    "sg:classifiers":[
        {
            "category":"Farming",
            "subcategory":"Farm",
            "type":"Manufacturing & Wholesale Goods"
        }
    ],
    "sg:phone":"+1 920 748 3051",
    "sg:postcode":"54971",
    "sg:province":"WI",
    "sg:tags":[
        "crop",
        "general"
    ],
    "wof:name":"Richard Stellmacher",
    "wof:placetype":"venue"
},
  "geometry": {"coordinates":[-88.90485700000001,43.872887],"type":"Point"}
}