{
  "type": "Feature",
  "properties": {
    "iso:country":"US",
    "sg:address":"1710 Avon St",
    "sg:city":"La Crosse",
    "sg:classifiers":[
        {
            "category":"Manufacturing",
            "subcategory":"Printing",
            "type":"Manufacturing & Wholesale Goods"
        }
    ],
    "sg:phone":"+1 608 781 4037",
    "sg:postcode":"54603",
    "sg:province":"WI",
    "sg:tags":[
        "publishing"
    ],
    "wof:name":"Bills Publishing",
    "wof:placetype":"venue"
},
  "geometry": {"coordinates":[-91.245336,43.849048],"type":"Point"}
}