{
  "type": "Feature",
  "properties": {
    "iso:country":"US",
    "sg:address":"2217 Oakridge Ave",
    "sg:city":"Madison",
    "sg:classifiers":[
        {
            "category":"Professional",
            "subcategory":"Art Services",
            "type":"Services"
        }
    ],
    "sg:phone":"+1 608 241 7774",
    "sg:postcode":"53704",
    "sg:province":"WI",
    "sg:tags":[
        "graphic",
        "designer"
    ],
    "wof:name":"KARI Hamann Design",
    "wof:placetype":"venue"
},
  "geometry": {"coordinates":[-89.348751,43.090415],"type":"Point"}
}