{
  "type": "Feature",
  "properties": {
    "iso:country":"US",
    "sg:address":"11316 D'Nera Vista Ct",
    "sg:city":"Baraboo",
    "sg:classifiers":[
        {
            "category":"Professional",
            "type":"Services"
        }
    ],
    "sg:phone":"+1 608 356 7579",
    "sg:postcode":"53913",
    "sg:province":"WI",
    "wof:name":"Laura Rossiter & Assoc",
    "wof:placetype":"venue"
},
  "geometry": {"coordinates":[-89.75725799999999,43.486257],"type":"Point"}
}