{
  "type": "Feature",
  "properties": {
    "addr:full":"2372 S Oneida St Green Bay WI 54304",
    "addr:housenumber":"2372",
    "addr:postcode":"54304",
    "addr:street":"S Oneida St",
    "iso:country":"US",
    "sg:address":"2372 S Oneida St",
    "sg:city":"Green Bay",
    "sg:classifiers":[
        {
            "category":"Real Estate",
            "subcategory":"Real Estate Agent",
            "type":"Services"
        }
    ],
    "sg:phone":"+1 920 499 4835",
    "sg:postcode":"54304",
    "sg:province":"WI",
    "wof:name":"Gilson Real Estate",
    "wof:placetype":"venue"
},
  "geometry": {"coordinates":[-88.068195,44.485206],"type":"Point"}
}