{
  "type": "Feature",
  "properties": {
    "iso:country":"US",
    "sg:address":"5440 Old B Rd",
    "sg:city":"Rio",
    "sg:classifiers":[
        {
            "category":"Insurance",
            "subcategory":"Insurance Agent",
            "type":"Services"
        }
    ],
    "sg:phone":"+1 920 992 3066",
    "sg:postcode":"53960",
    "sg:province":"WI",
    "wof:name":"West Bend Mutual Insurance",
    "wof:placetype":"venue"
},
  "geometry": {"coordinates":[-89.21608000000001,43.476186],"type":"Point"}
}