{
  "type": "Feature",
  "properties": {
    "iso:country":"US",
    "sg:address":"2190 S Ashland Ave",
    "sg:city":"Green Bay",
    "sg:classifiers":[
        {
            "category":"Shopping",
            "subcategory":"Bicycles & Sporting Goods",
            "type":"Retail Goods"
        }
    ],
    "sg:phone":"+1 920 499 2784",
    "sg:postcode":"54304",
    "sg:province":"WI",
    "sg:tags":[
        "sport",
        "merchandise"
    ],
    "wof:name":"Packerland Pools Spas & Billd",
    "wof:placetype":"venue"
},
  "geometry": {"coordinates":[-88.051414,44.487811],"type":"Point"}
}