{
  "type": "Feature",
  "properties": {
    "iso:country":"US",
    "sg:address":"547 17th Ave",
    "sg:city":"Almena",
    "sg:classifiers":[
        {
            "category":"Farming",
            "subcategory":"Farm & Veterinary Services",
            "type":"Manufacturing & Wholesale Goods"
        }
    ],
    "sg:phone":"+1 715 357 3795",
    "sg:postcode":"54805",
    "sg:province":"WI",
    "sg:tags":[
        "crop",
        "harvesting"
    ],
    "wof:name":"Sellent Bruce",
    "wof:placetype":"venue"
},
  "geometry": {"coordinates":[-92.043965,45.452804],"type":"Point"}
}