{
  "type": "Feature",
  "properties": {
    "iso:country":"US",
    "sg:address":"403 Blue View Dr",
    "sg:city":"Mt Horeb",
    "sg:classifiers":[
        {
            "category":"Personal",
            "subcategory":"Beauty Salon",
            "type":"Services"
        }
    ],
    "sg:phone":"+1 608 437 5744",
    "sg:postcode":"53572",
    "sg:province":"WI",
    "sg:tags":[
        "shop",
        "merchandise"
    ],
    "wof:name":"Hair Designs",
    "wof:placetype":"venue"
},
  "geometry": {"coordinates":[-89.73318999999999,43.017133],"type":"Point"}
}