{
  "type": "Feature",
  "properties": {
    "iso:country":"US",
    "sg:address":"59205 Pease Rd",
    "sg:city":"Ferryville",
    "sg:classifiers":[
        {
            "category":"Personal",
            "subcategory":"Beauty Salon",
            "type":"Services"
        }
    ],
    "sg:phone":"+1 608 734 3216",
    "sg:postcode":"54628",
    "sg:province":"WI",
    "sg:tags":[
        "shop"
    ],
    "wof:name":"Puttin On The Ritz",
    "wof:placetype":"venue"
},
  "geometry": {"coordinates":[-91.048022,43.293158],"type":"Point"}
}