{
  "type": "Feature",
  "properties": {
    "iso:country":"US",
    "sg:address":"404 Central Ave",
    "sg:city":"Coon Valley",
    "sg:classifiers":[
        {
            "category":"Bars & Pubs",
            "type":"Food & Drink"
        }
    ],
    "sg:phone":"+1 608 452 9178",
    "sg:postcode":"54623",
    "sg:province":"WI",
    "wof:name":"Fjord Bar",
    "wof:placetype":"venue"
},
  "geometry": {"coordinates":[-91.014466,43.702465],"type":"Point"}
}