{
  "type": "Feature",
  "properties": {
    "iso:country":"US",
    "sg:address":"7276 N Teutonia Ave",
    "sg:city":"Milwaukee",
    "sg:classifiers":[
        {
            "category":"Restaurant",
            "type":"Food & Drink"
        }
    ],
    "sg:phone":"+1 414 352 4650",
    "sg:postcode":"53209",
    "sg:province":"WI",
    "wof:name":"Pikmar Restaurant",
    "wof:placetype":"venue"
},
  "geometry": {"coordinates":[-87.957099,43.150099],"type":"Point"}
}