{
  "type": "Feature",
  "properties": {
    "iso:country":"US",
    "sg:address":"6506 Normandy Ln",
    "sg:city":"Madison",
    "sg:classifiers":[
        {
            "category":"Health Services",
            "subcategory":"Health Practitioner",
            "type":"Services"
        }
    ],
    "sg:phone":"+1 608 833 2225",
    "sg:postcode":"53719",
    "sg:province":"WI",
    "sg:tags":[
        "therapist",
        "physical"
    ],
    "wof:name":"A Mpt Advanced Manual Physical",
    "wof:placetype":"venue"
},
  "geometry": {"coordinates":[-89.49434100000001,43.057497],"type":"Point"}
}