{
  "type": "Feature",
  "properties": {
    "addr:full":"5507 Lilac Ave Wausau WI 54401",
    "addr:housenumber":"5507",
    "addr:postcode":"54401",
    "addr:street":"Lilac Ave",
    "iso:country":"US",
    "sg:address":"5507 Lilac Ave",
    "sg:city":"Wausau",
    "sg:classifiers":[
        {
            "category":"Autos & Motor Vehicles",
            "subcategory":"Recreational Vehicle Sales",
            "type":"Retail Goods"
        }
    ],
    "sg:phone":"+1 715 355 5556",
    "sg:postcode":"54401",
    "sg:province":"WI",
    "sg:tags":[
        "accessory"
    ],
    "sg:website":"www.kingscampers.com",
    "wof:name":"Kings Campers",
    "wof:placetype":"venue"
},
  "geometry": {"coordinates":[-89.644458,44.903985],"type":"Point"}
}