{
  "type": "Feature",
  "properties": {
    "iso:country":"US",
    "sg:address":"566 Pine St",
    "sg:city":"Hartford",
    "sg:classifiers":[
        {
            "category":"Shopping",
            "subcategory":"Florist",
            "type":"Retail Goods"
        }
    ],
    "sg:phone":"+1 262 673 3860",
    "sg:postcode":"53027",
    "sg:province":"WI",
    "wof:name":"Black's Flower Shop",
    "wof:placetype":"venue"
},
  "geometry": {"coordinates":[-88.389578,43.325147],"type":"Point"}
}