{
  "type": "Feature",
  "properties": {
    "iso:country":"US",
    "sg:address":"11700 W Lake Park Dr",
    "sg:city":"Milwaukee",
    "sg:classifiers":[
        {
            "category":"Manufacturing",
            "subcategory":"Printing",
            "type":"Manufacturing & Wholesale Goods"
        }
    ],
    "sg:phone":"+1 414 359 1040",
    "sg:postcode":"53224",
    "sg:province":"WI",
    "sg:tags":[
        "publishing",
        "periodical"
    ],
    "wof:name":"Families International Inc",
    "wof:placetype":"venue"
},
  "geometry": {"coordinates":[-88.057726,43.159113],"type":"Point"}
}