{
  "type": "Feature",
  "properties": {
    "iso:country":"US",
    "sg:address":"2440 S 179 St",
    "sg:city":"New Berlin",
    "sg:classifiers":[
        {
            "category":"Wholesale",
            "subcategory":"Drugs",
            "type":"Manufacturing & Wholesale Goods"
        }
    ],
    "sg:phone":"+1 262 821 9182",
    "sg:postcode":"53146",
    "sg:province":"WI",
    "sg:tags":[
        "instrument",
        "mfg"
    ],
    "wof:name":"Escalon Medical Corp",
    "wof:placetype":"venue"
},
  "geometry": {"coordinates":[-88.134647,42.999485],"type":"Point"}
}