{
  "type": "Feature",
  "properties": {
    "iso:country":"US",
    "sg:address":"4355 N Richards St",
    "sg:city":"Milwaukee",
    "sg:classifiers":[
        {
            "category":"Professional",
            "subcategory":"Computer Services",
            "type":"Services"
        }
    ],
    "sg:phone":"+1 262 573 3982",
    "sg:postcode":"53212",
    "sg:province":"WI",
    "sg:tags":[
        "technology"
    ],
    "wof:name":"Technology Advantage",
    "wof:placetype":"venue"
},
  "geometry": {"coordinates":[-87.907218,43.096326],"type":"Point"}
}