{
  "type": "Feature",
  "properties": {
    "iso:country":"US",
    "sg:address":"4699 Jordan Center Rd",
    "sg:city":"Argyle",
    "sg:classifiers":[
        {
            "category":"Freight",
            "type":"Transportation"
        }
    ],
    "sg:phone":"+1 608 325 3407",
    "sg:postcode":"53504",
    "sg:province":"WI",
    "sg:tags":[
        "operator",
        "trucking"
    ],
    "wof:name":"Free Bird Express Inc",
    "wof:placetype":"venue"
},
  "geometry": {"coordinates":[-89.759331,42.680413],"type":"Point"}
}