{
  "type": "Feature",
  "properties": {
    "addr:full":"2609 Seiferth Rd Madison WI 53716",
    "addr:postcode":"2609;53716",
    "addr:street":"Seiferth Rd",
    "iso:country":"US",
    "sg:address":"2609 Seiferth Rd",
    "sg:city":"Madison",
    "sg:classifiers":[
        {
            "category":"Recreation",
            "type":"Entertainment"
        }
    ],
    "sg:phone":"+1 608 224 1223",
    "sg:postcode":"53716",
    "sg:province":"WI",
    "sg:tags":[
        "instruction",
        "gymnastic"
    ],
    "wof:name":"Spirit Athletics Inc",
    "wof:placetype":"venue"
},
  "geometry": {"coordinates":[-89.307461,43.062041],"type":"Point"}
}