{
  "type": "Feature",
  "properties": {
    "iso:country":"US",
    "sg:address":"4790 N Hopkins St",
    "sg:city":"Milwaukee",
    "sg:classifiers":[
        {
            "category":"Food & Beverages",
            "subcategory":"Groceries & Convenience Stores",
            "type":"Retail Goods"
        }
    ],
    "sg:phone":"+1 414 535 1666",
    "sg:postcode":"53209",
    "sg:province":"WI",
    "wof:name":"S & J Food Market",
    "wof:placetype":"venue"
},
  "geometry": {"coordinates":[-87.959343,43.102752],"type":"Point"}
}