{
  "type": "Feature",
  "properties": {
    "iso:country":"US",
    "sg:address":"5810 W Fond du Lac Ave",
    "sg:city":"Milwaukee",
    "sg:classifiers":[
        {
            "category":"Social Services",
            "subcategory":"Child Care",
            "type":"Services"
        }
    ],
    "sg:phone":"+1 414 438 0430",
    "sg:postcode":"53218",
    "sg:province":"WI",
    "sg:tags":[
        "day"
    ],
    "wof:name":"Westbrooks Child Dev Ctr",
    "wof:placetype":"venue"
},
  "geometry": {"coordinates":[-87.986661,43.098138],"type":"Point"}
}