{
  "type": "Feature",
  "properties": {
    "iso:country":"US",
    "sg:address":"806 Waters Edge Rd",
    "sg:city":"Racine",
    "sg:classifiers":[
        {
            "category":"Real Estate",
            "subcategory":"Architect",
            "type":"Services"
        }
    ],
    "sg:phone":"+1 262 639 2416",
    "sg:postcode":"53402",
    "sg:province":"WI",
    "wof:name":"Mark Zinni Architects LTD",
    "wof:placetype":"venue"
},
  "geometry": {"coordinates":[-87.790634,42.802581],"type":"Point"}
}