{
  "type": "Feature",
  "properties": {
    "iso:country":"US",
    "sg:address":"720 Association Dr",
    "sg:city":"Appleton",
    "sg:classifiers":[
        {
            "category":"Organizations",
            "subcategory":"Non-profit Organization",
            "type":"Services"
        }
    ],
    "sg:phone":"+1 920 749 1040",
    "sg:postcode":"54914",
    "sg:province":"WI",
    "sg:website":"www.natptax.com",
    "wof:name":"National Assn Of Tax Prctnrs",
    "wof:placetype":"venue"
},
  "geometry": {"coordinates":[-88.41643000000001,44.297167],"type":"Point"}
}