{
  "type": "Feature",
  "properties": {
    "iso:country":"US",
    "sg:address":"900 E Lincoln St",
    "sg:city":"Mount Horeb",
    "sg:classifiers":[
        {
            "category":"Social Services",
            "subcategory":"Child Care",
            "type":"Services"
        }
    ],
    "sg:phone":"+1 608 437 3948",
    "sg:postcode":"53572",
    "sg:province":"WI",
    "sg:tags":[
        "day"
    ],
    "wof:name":"Kiddie Kampus",
    "wof:placetype":"venue"
},
  "geometry": {"coordinates":[-89.73045500000001,43.007248],"type":"Point"}
}