{
  "type": "Feature",
  "properties": {
    "addr:full":"123 E Wisconsin Ave Oconomowoc WI 53066",
    "addr:housenumber":"123",
    "addr:postcode":"53066",
    "addr:street":"E Wisconsin Ave",
    "iso:country":"US",
    "sg:address":"123 E Wisconsin Ave",
    "sg:city":"Oconomowoc",
    "sg:classifiers":[
        {
            "category":"Wholesale",
            "subcategory":"Non-durable Goods",
            "type":"Manufacturing & Wholesale Goods"
        }
    ],
    "sg:phone":"+1 262 560 9420",
    "sg:postcode":"53066",
    "sg:province":"WI",
    "wof:name":"Katlynns Dollar Palace",
    "wof:placetype":"venue"
},
  "geometry": {"coordinates":[-88.49754900000001,43.110611],"type":"Point"}
}