{
  "type": "Feature",
  "properties": {
    "iso:country":"US",
    "sg:address":"8535 W Capitol Dr",
    "sg:city":"Milwaukee",
    "sg:classifiers":[
        {
            "category":"Shopping",
            "subcategory":"Optical Goods",
            "type":"Retail Goods"
        }
    ],
    "sg:phone":"+1 414 461 6573",
    "sg:postcode":"53222",
    "sg:province":"WI",
    "wof:name":"Ollie Optical",
    "wof:placetype":"venue"
},
  "geometry": {"coordinates":[-88.019766,43.089726],"type":"Point"}
}