{
  "type": "Feature",
  "properties": {
    "addr:full":"260 Eastridge Rd Portage WI 53901",
    "addr:housenumber":"260",
    "addr:postcode":"53901",
    "addr:street":"Eastridge Rd",
    "iso:country":"US",
    "sg:address":"260 Eastridge Rd",
    "sg:city":"Portage",
    "sg:classifiers":[
        {
            "category":"Government",
            "subcategory":"Office",
            "type":"Public Place"
        }
    ],
    "sg:phone":"+1 608 742 8087",
    "sg:postcode":"53901",
    "sg:province":"WI",
    "sg:tags":[
        "state",
        "program"
    ],
    "wof:name":"Transportation Dept",
    "wof:placetype":"venue"
},
  "geometry": {"coordinates":[-89.464743,43.568039],"type":"Point"}
}