{
  "type": "Feature",
  "properties": {
    "iso:country":"US",
    "sg:address":"591 Grandview Dr",
    "sg:city":"Fredonia",
    "sg:classifiers":[
        {
            "category":"Real Estate",
            "subcategory":"Developer",
            "type":"Services"
        }
    ],
    "sg:phone":"+1 262 692 2197",
    "sg:postcode":"53021",
    "sg:province":"WI",
    "wof:name":"Danal Land Management",
    "wof:placetype":"venue"
},
  "geometry": {"coordinates":[-88.061302,43.488908],"type":"Point"}
}