{
  "type": "Feature",
  "properties": {
    "iso:country":"US",
    "sg:address":"1270 Scheuring Rd",
    "sg:city":"De Pere",
    "sg:classifiers":[
        {
            "category":"Insurance",
            "subcategory":"Insurance Agent",
            "type":"Services"
        }
    ],
    "sg:phone":"+1 920 430 1543",
    "sg:postcode":"54115",
    "sg:province":"WI",
    "wof:name":"Bradley Burdette Insurance",
    "wof:placetype":"venue"
},
  "geometry": {"coordinates":[-88.092932,44.430723],"type":"Point"}
}