{
  "type": "Feature",
  "properties": {
    "addr:full":"229 N 28th St Superior WI 54880",
    "addr:housenumber":"229",
    "addr:postcode":"54880",
    "addr:street":"N 28Th St",
    "iso:country":"US",
    "sg:address":"229 N 28th St",
    "sg:city":"Superior",
    "sg:classifiers":[
        {
            "category":"Organizations",
            "subcategory":"Religious Organization",
            "type":"Services"
        }
    ],
    "sg:phone":"+1 715 392 4751",
    "sg:postcode":"54880",
    "sg:province":"WI",
    "sg:tags":[
        "church"
    ],
    "sg:website":"www.superiorunitedpres.com",
    "wof:name":"United Presbyterian Church",
    "wof:placetype":"venue"
},
  "geometry": {"coordinates":[-92.08207299999999,46.706235],"type":"Point"}
}