{
  "type": "Feature",
  "properties": {
    "addr:full":"225 Pierce St Randolph WI 53956",
    "addr:housenumber":"225",
    "addr:postcode":"53956",
    "addr:street":"Pierce St",
    "iso:country":"US",
    "sg:address":"225 Pierce St",
    "sg:city":"Randolph",
    "sg:classifiers":[
        {
            "category":"Organizations",
            "subcategory":"Religious Organization",
            "type":"Services"
        }
    ],
    "sg:phone":"+1 920 326 5642",
    "sg:postcode":"53956",
    "sg:province":"WI",
    "sg:tags":[
        "church"
    ],
    "wof:name":"Protestant Reformed Church",
    "wof:placetype":"venue"
},
  "geometry": {"coordinates":[-89.00336900000001,43.543095],"type":"Point"}
}