{
  "type": "Feature",
  "properties": {
    "iso:country":"US",
    "sg:address":"2710 N Avondale Blvd",
    "sg:city":"Milwaukee",
    "sg:classifiers":[
        {
            "category":"Shopping",
            "subcategory":"Hobbies, Toys, & Games",
            "type":"Retail Goods"
        }
    ],
    "sg:phone":"+1 414 442 0470",
    "sg:postcode":"53210",
    "sg:province":"WI",
    "wof:name":"Discovery Toys",
    "wof:placetype":"venue"
},
  "geometry": {"coordinates":[-87.992095,43.070303],"type":"Point"}
}