{
  "type": "Feature",
  "properties": {
    "iso:country":"US",
    "sg:address":"4435 Jewell Ln",
    "sg:city":"Platteville",
    "sg:classifiers":[
        {
            "category":"Manufacturing",
            "subcategory":"Motor Vehicles & Parts",
            "type":"Manufacturing & Wholesale Goods"
        }
    ],
    "sg:phone":"+1 608 568 7261",
    "sg:postcode":"53818",
    "sg:province":"WI",
    "sg:tags":[
        "mfg"
    ],
    "wof:name":"1 Up U S A",
    "wof:placetype":"venue"
},
  "geometry": {"coordinates":[-90.54288699999999,42.666639],"type":"Point"}
}