{
  "type": "Feature",
  "properties": {
    "iso:country":"US",
    "sg:address":"10315 N Port Washington Rd",
    "sg:city":"Mequon",
    "sg:classifiers":[
        {
            "category":"Retail",
            "subcategory":"Auto Repair",
            "type":"Services"
        }
    ],
    "sg:phone":"+1 262 241 4636",
    "sg:postcode":"53092",
    "sg:province":"WI",
    "sg:tags":[
        "repairing",
        "automobile",
        "general"
    ],
    "wof:name":"Zinecker's Auto Repair",
    "wof:placetype":"venue"
},
  "geometry": {"coordinates":[-87.92436600000001,43.206421],"type":"Point"}
}