{
  "type": "Feature",
  "properties": {
    "iso:country":"US",
    "sg:address":"6560 Alpine Dr",
    "sg:city":"West Bend",
    "sg:classifiers":[
        {
            "category":"Professional",
            "type":"Services"
        }
    ],
    "sg:phone":"+1 262 629 4072",
    "sg:postcode":"53090",
    "sg:province":"WI",
    "wof:name":"Randy Neuman",
    "wof:placetype":"venue"
},
  "geometry": {"coordinates":[-88.291758,43.434993],"type":"Point"}
}