{
  "type": "Feature",
  "properties": {
    "iso:country":"US",
    "sg:address":"1106 N 17th St",
    "sg:city":"Superior",
    "sg:classifiers":[
        {
            "category":"Retail",
            "subcategory":"Laundry & Dry Cleaning",
            "type":"Services"
        }
    ],
    "sg:phone":"+1 715 394 3113",
    "sg:postcode":"54880",
    "sg:province":"WI",
    "wof:name":"Whistle Carpet Cleaners",
    "wof:placetype":"venue"
},
  "geometry": {"coordinates":[-92.094867,46.717815],"type":"Point"}
}