{
  "type": "Feature",
  "properties": {
    "iso:country":"US",
    "sg:address":"246 W Ottawa Ave",
    "sg:city":"Dousman",
    "sg:classifiers":[
        {
            "category":"Education",
            "subcategory":"School",
            "type":"Public Place"
        }
    ],
    "sg:phone":"+1 262 965 2291",
    "sg:postcode":"53118",
    "sg:province":"WI",
    "wof:name":"St Bruno Parish School",
    "wof:placetype":"venue"
},
  "geometry": {"coordinates":[-88.47457799999999,43.010622],"type":"Point"}
}