{
  "type": "Feature",
  "properties": {
    "iso:country":"US",
    "sg:address":"2832 N 68th St",
    "sg:city":"Milwaukee",
    "sg:classifiers":[
        {
            "category":"Organizations",
            "subcategory":"Community Association",
            "type":"Services"
        }
    ],
    "sg:phone":"+1 414 771 0522",
    "sg:postcode":"53210",
    "sg:province":"WI",
    "wof:name":"Swiss Singing Society",
    "wof:placetype":"venue"
},
  "geometry": {"coordinates":[-87.997318,43.069747],"type":"Point"}
}