{
  "type": "Feature",
  "properties": {
    "iso:country":"US",
    "sg:address":"1019 N Kelly St",
    "sg:city":"Cadott",
    "sg:classifiers":[
        {
            "category":"Real Estate",
            "subcategory":"Real Estate Operator",
            "type":"Services"
        }
    ],
    "sg:phone":"+1 715 289 4755",
    "sg:postcode":"54727",
    "sg:province":"WI",
    "sg:tags":[
        "apartment"
    ],
    "wof:name":"Cadott Country Apartments",
    "wof:placetype":"venue"
},
  "geometry": {"coordinates":[-91.145844,44.958456],"type":"Point"}
}