{
  "type": "Feature",
  "properties": {
    "addr:full":"1661 N Water St Milwaukee WI 53202",
    "addr:housenumber":"1661",
    "addr:postcode":"53202",
    "addr:street":"N Water St",
    "iso:country":"US",
    "sg:address":"1661 N Water St",
    "sg:city":"Milwaukee",
    "sg:classifiers":[
        {
            "category":"Health Services",
            "subcategory":"Hospital",
            "type":"Services"
        }
    ],
    "sg:phone":"+1 414 270 1981",
    "sg:postcode":"53202",
    "sg:province":"WI",
    "sg:tags":[
        "mental"
    ],
    "wof:name":"Christine Harness",
    "wof:placetype":"venue"
},
  "geometry": {"coordinates":[-87.905995,43.051914],"type":"Point"}
}