{
  "type": "Feature",
  "properties": {
    "iso:country":"US",
    "sg:address":"420 E Verona Ave",
    "sg:city":"Verona",
    "sg:classifiers":[
        {
            "category":"Professional",
            "type":"Services"
        }
    ],
    "sg:phone":"+1 608 845 3852",
    "sg:postcode":"53593",
    "sg:province":"WI",
    "sg:tags":[
        "establishment"
    ],
    "wof:name":"Anchorbank Fsb",
    "wof:placetype":"venue"
},
  "geometry": {"coordinates":[-89.52969299999999,42.991867],"type":"Point"}
}