{
  "type": "Feature",
  "properties": {
    "iso:country":"US",
    "sg:address":"1191 Huntington Ave",
    "sg:city":"Wisconsin Rapids",
    "sg:classifiers":[
        {
            "category":"Food & Beverages",
            "subcategory":"Candy",
            "type":"Retail Goods"
        }
    ],
    "sg:phone":"+1 715 424 6220",
    "sg:postcode":"54494",
    "sg:province":"WI",
    "sg:tags":[
        "confectionery"
    ],
    "wof:name":"Trapistine Quality Candy",
    "wof:placetype":"venue"
},
  "geometry": {"coordinates":[-89.812065,44.372232],"type":"Point"}
}