{
  "type": "Feature",
  "properties": {
    "addr:full":"6616 Mineral Point Rd Madison WI 53705",
    "addr:housenumber":"6616",
    "addr:postcode":"53705",
    "addr:street":"Mineral Point Rd",
    "iso:country":"US",
    "sg:address":"6616 Mineral Point Rd",
    "sg:city":"Madison",
    "sg:classifiers":[
        {
            "category":"Personal",
            "subcategory":"Beauty Salon",
            "type":"Services"
        }
    ],
    "sg:phone":"+1 608 829 3884",
    "sg:postcode":"53705",
    "sg:province":"WI",
    "sg:tags":[
        "shop",
        "manicuring"
    ],
    "wof:name":"Ultimate Touch Nail Studio",
    "wof:placetype":"venue"
},
  "geometry": {"coordinates":[-89.496916,43.060829],"type":"Point"}
}