{
  "type": "Feature",
  "properties": {
    "iso:country":"US",
    "sg:address":"2220 W National Ave",
    "sg:city":"Milwaukee",
    "sg:classifiers":[
        {
            "category":"Social Services",
            "subcategory":"Child Care",
            "type":"Services"
        }
    ],
    "sg:phone":"+1 414 385 2255",
    "sg:postcode":"53204",
    "sg:province":"WI",
    "sg:tags":[
        "day"
    ],
    "wof:name":"Little Playmates Child Learnin",
    "wof:placetype":"venue"
},
  "geometry": {"coordinates":[-87.941965,43.022603],"type":"Point"}
}