{
  "type": "Feature",
  "properties": {
    "iso:country":"US",
    "sg:address":"6110 N Sunny Point Rd",
    "sg:city":"Milwaukee",
    "sg:classifiers":[
        {
            "category":"Real Estate",
            "subcategory":"Real Estate Agent",
            "type":"Services"
        }
    ],
    "sg:phone":"+1 414 228 9949",
    "sg:postcode":"53209",
    "sg:province":"WI",
    "wof:name":"Wais Appraisals LLC",
    "wof:placetype":"venue"
},
  "geometry": {"coordinates":[-87.926208,43.125815],"type":"Point"}
}