{
  "type": "Feature",
  "properties": {
    "addr:full":"1040 Pilgrim Way Green Bay WI 54304",
    "addr:housenumber":"1040",
    "addr:postcode":"54304",
    "addr:street":"Pilgrim Way",
    "iso:country":"US",
    "sg:address":"1040 Pilgrim Way",
    "sg:city":"Green Bay",
    "sg:classifiers":[
        {
            "category":"Health Services",
            "subcategory":"Nursing And Care Facility",
            "type":"Services"
        }
    ],
    "sg:phone":"+1 920 499 1481",
    "sg:postcode":"54304",
    "sg:province":"WI",
    "sg:tags":[
        "residential",
        "skilled",
        "elderly",
        "home"
    ],
    "wof:name":"Woodside Lutheran Home",
    "wof:placetype":"venue"
},
  "geometry": {"coordinates":[-88.07347300000001,44.483891],"type":"Point"}
}