{
  "type": "Feature",
  "properties": {
    "iso:country":"US",
    "sg:address":"121 Williams St",
    "sg:city":"Randolph",
    "sg:classifiers":[
        {
            "category":"Insurance",
            "subcategory":"Insurance Agent",
            "type":"Services"
        }
    ],
    "sg:phone":"+1 920 326 5545",
    "sg:postcode":"53956",
    "sg:province":"WI",
    "wof:name":"Weinberger Roger",
    "wof:placetype":"venue"
},
  "geometry": {"coordinates":[-89.005071,43.538545],"type":"Point"}
}