{
  "type": "Feature",
  "properties": {
    "addr:full":"4768 N Wigwam Rd Rosholt WI 54473",
    "addr:housenumber":"4768",
    "addr:postcode":"54473",
    "addr:street":"N Wigwam Rd",
    "iso:country":"US",
    "sg:address":"4768 N Wigwam Rd",
    "sg:city":"Rosholt",
    "sg:classifiers":[
        {
            "category":"Home & Garden",
            "subcategory":"Building Materials",
            "type":"Retail Goods"
        }
    ],
    "sg:phone":"+1 715 677 3800",
    "sg:postcode":"54473",
    "sg:province":"WI",
    "wof:name":"Age Of Glass",
    "wof:placetype":"venue"
},
  "geometry": {"coordinates":[-89.244095,44.676369],"type":"Point"}
}