{
  "type": "Feature",
  "properties": {
    "addr:full":"3324 Wagon Wheel Rd Manitowoc WI 54220",
    "addr:housenumber":"3324",
    "addr:postcode":"54220",
    "addr:street":"Wagon Wheel Rd",
    "iso:country":"US",
    "sg:address":"3324 Wagon Wheel Rd",
    "sg:city":"Manitowoc",
    "sg:classifiers":[
        {
            "category":"Building & Trades",
            "subcategory":"Construction",
            "type":"Services"
        }
    ],
    "sg:phone":"+1 920 686 8868",
    "sg:postcode":"54220",
    "sg:province":"WI",
    "sg:tags":[
        "fabricator",
        "metal"
    ],
    "wof:name":"Anger Guy Streetfighters",
    "wof:placetype":"venue"
},
  "geometry": {"coordinates":[-87.720979,44.140705],"type":"Point"}
}