{
  "type": "Feature",
  "properties": {
    "addr:full":"821 W Prospect Ave Appleton WI 54914",
    "addr:housenumber":"821",
    "addr:postcode":"54914",
    "addr:street":"W Prospect Ave",
    "iso:country":"US",
    "sg:address":"821 W Prospect Ave",
    "sg:city":"Appleton",
    "sg:classifiers":[
        {
            "category":"Real Estate",
            "subcategory":"Real Estate Operator",
            "type":"Services"
        }
    ],
    "sg:phone":"+1 920 954 1683",
    "sg:postcode":"54914",
    "sg:province":"WI",
    "sg:tags":[
        "building",
        "apartment"
    ],
    "wof:name":"Capital Prospects LLC",
    "wof:placetype":"venue"
},
  "geometry": {"coordinates":[-88.419077,44.2546],"type":"Point"}
}