{
  "type": "Feature",
  "properties": {
    "addr:full":"14145 W Kostner Ln New Berlin WI 53151",
    "addr:housenumber":"14145",
    "addr:postcode":"53151",
    "addr:street":"W Kostner Ln",
    "iso:country":"US",
    "sg:address":"14145 W Kostner Ln",
    "sg:city":"New Berlin",
    "sg:classifiers":[
        {
            "category":"Freight",
            "type":"Transportation"
        }
    ],
    "sg:phone":"+1 262 797 0599",
    "sg:postcode":"53151",
    "sg:province":"WI",
    "sg:tags":[
        "general"
    ],
    "wof:name":"Advance Insulation Warehouse",
    "wof:placetype":"venue"
},
  "geometry": {"coordinates":[-88.089994,43.011411],"type":"Point"}
}