{
  "type": "Feature",
  "properties": {
    "iso:country":"US",
    "sg:address":"127 Front St",
    "sg:city":"Beaver Dam",
    "sg:classifiers":[
        {
            "category":"Shopping",
            "subcategory":"Musical Instruments",
            "type":"Retail Goods"
        }
    ],
    "sg:phone":"+1 920 885 3281",
    "sg:postcode":"53916",
    "sg:province":"WI",
    "wof:name":"L&W Music Center",
    "wof:placetype":"venue"
},
  "geometry": {"coordinates":[-88.837365,43.456166],"type":"Point"}
}