{
  "type": "Feature",
  "properties": {
    "iso:country":"US",
    "sg:address":"306 Nautical Dr",
    "sg:city":"Sturgeon Bay",
    "sg:classifiers":[
        {
            "category":"Recreation",
            "type":"Entertainment"
        }
    ],
    "sg:phone":"+1 920 746 0087",
    "sg:postcode":"54235",
    "sg:province":"WI",
    "sg:tags":[
        "amusement"
    ],
    "wof:name":"Mr Outboards Watersports",
    "wof:placetype":"venue"
},
  "geometry": {"coordinates":[-87.377949,44.824042],"type":"Point"}
}