{
  "type": "Feature",
  "properties": {
    "iso:country":"US",
    "sg:address":"4331 8th St S",
    "sg:city":"Wisconsin Rapids",
    "sg:classifiers":[
        {
            "category":"Personal",
            "subcategory":"Beauty Salon",
            "type":"Services"
        }
    ],
    "sg:phone":"+1 715 421 2411",
    "sg:postcode":"54494",
    "sg:province":"WI",
    "wof:name":"Smart Style Family Hair Salon",
    "wof:placetype":"venue"
},
  "geometry": {"coordinates":[-89.81671,44.354565],"type":"Point"}
}