{
  "type": "Feature",
  "properties": {
    "iso:country":"US",
    "sg:address":"187 Beth Ct",
    "sg:city":"Burlington",
    "sg:classifiers":[
        {
            "category":"Shopping",
            "subcategory":"Clothing, Apparel, & Fashions",
            "type":"Retail Goods"
        }
    ],
    "sg:phone":"+1 262 248 1355",
    "sg:postcode":"53105",
    "sg:province":"WI",
    "wof:name":"Riviera Beach Shop",
    "wof:placetype":"venue"
},
  "geometry": {"coordinates":[-88.295666,42.675567],"type":"Point"}
}