{
  "type": "Feature",
  "properties": {
    "iso:country":"US",
    "sg:address":"3810 W National Ave",
    "sg:city":"Milwaukee",
    "sg:classifiers":[
        {
            "category":"Restaurant",
            "type":"Food & Drink"
        }
    ],
    "sg:phone":"+1 414 384 3160",
    "sg:postcode":"53215",
    "sg:province":"WI",
    "wof:name":"Golden Chicken Franchise",
    "wof:placetype":"venue"
},
  "geometry": {"coordinates":[-87.9616,43.021446],"type":"Point"}
}