{
  "type": "Feature",
  "properties": {
    "addr:full":"9220 6 Mile Rd Caledonia WI 53108",
    "addr:housenumber":"9220",
    "addr:postcode":"53108",
    "addr:street":"6 Mile Rd",
    "iso:country":"US",
    "sg:address":"9220 6 Mile Rd",
    "sg:city":"Caledonia",
    "sg:classifiers":[
        {
            "category":"Shopping",
            "subcategory":"Stationery & Office Supplies",
            "type":"Retail Goods"
        },
        {
            "category":"Professional",
            "subcategory":"Printing & Photocopies",
            "type":"Services"
        }
    ],
    "sg:phone":"+1 262 835 0020",
    "sg:postcode":"53108",
    "sg:province":"WI",
    "sg:tags":[
        "announcement",
        "invitation"
    ],
    "sg:website":"http://www.schnabelprinting.com",
    "wof:name":"Schnabel Karl H Co",
    "wof:placetype":"venue"
},
  "geometry": {"coordinates":[-87.89657099999999,42.814237],"type":"Point"}
}