{
  "type": "Feature",
  "properties": {
    "addr:full":"1682 Apache Ln Nekoosa WI 54457",
    "addr:housenumber":"1682",
    "addr:postcode":"54457",
    "addr:street":"Apache Ln",
    "iso:country":"US",
    "sg:address":"1682 Apache Ln",
    "sg:city":"Nekoosa",
    "sg:classifiers":[
        {
            "category":"Restaurant",
            "type":"Food & Drink"
        }
    ],
    "sg:phone":"+1 715 325 6550",
    "sg:postcode":"54457",
    "sg:province":"WI",
    "sg:tags":[
        "eating"
    ],
    "wof:name":"Hide-A-Way Supper Club The",
    "wof:placetype":"venue"
},
  "geometry": {"coordinates":[-89.891211,44.188869],"type":"Point"}
}