{
  "type": "Feature",
  "properties": {
    "iso:country":"US",
    "sg:address":"17800 W Bluemound Rd",
    "sg:city":"Brookfield",
    "sg:classifiers":[
        {
            "category":"Banks & Credit Unions",
            "subcategory":"Investment Brokerage",
            "type":"Services"
        },
        {
            "category":"Professional",
            "subcategory":"Business Services",
            "type":"Services"
        }
    ],
    "sg:phone":"+1 262 780 0369",
    "sg:postcode":"53045",
    "sg:province":"WI",
    "sg:tags":[
        "advisory",
        "financial"
    ],
    "wof:name":"Primerica",
    "wof:placetype":"venue"
},
  "geometry": {"coordinates":[-88.13656,43.03658],"type":"Point"}
}