{
  "type": "Feature",
  "properties": {
    "addr:full":"1505 Albany D W Mondovi WI 54755",
    "addr:housenumber":"1505",
    "addr:postcode":"54755",
    "addr:street":"Albany D W",
    "iso:country":"US",
    "sg:address":"1505 Albany D W",
    "sg:city":"Mondovi",
    "sg:classifiers":[
        {
            "category":"Bars & Pubs",
            "type":"Food & Drink"
        }
    ],
    "sg:phone":"+1 715 875 4541",
    "sg:postcode":"54755",
    "sg:province":"WI",
    "sg:tags":[
        "drinking"
    ],
    "wof:name":"Hide A While Bar",
    "wof:placetype":"venue"
},
  "geometry": {"coordinates":[-91.74116600000001,44.683699],"type":"Point"}
}