{
  "type": "Feature",
  "properties": {
    "addr:full":"128 E Lake St Lake Mills WI 53551",
    "addr:housenumber":"128",
    "addr:postcode":"53551",
    "addr:street":"E Lake St",
    "iso:country":"US",
    "sg:address":"128 E Lake St",
    "sg:city":"Lake Mills",
    "sg:classifiers":[
        {
            "category":"Real Estate",
            "subcategory":"Real Estate Agent",
            "type":"Services"
        }
    ],
    "sg:phone":"+1 920 648 5228",
    "sg:postcode":"53551",
    "sg:province":"WI",
    "sg:tags":[
        "trade",
        "contractor"
    ],
    "wof:name":"Century 21",
    "wof:placetype":"venue"
},
  "geometry": {"coordinates":[-88.91217899999999,43.079653],"type":"Point"}
}