{
  "type": "Feature",
  "properties": {
    "iso:country":"US",
    "sg:address":"937 Co Rd H",
    "sg:city":"Cuba City",
    "sg:classifiers":[
        {
            "category":"Building & Trades",
            "subcategory":"Plumbing",
            "type":"Services"
        }
    ],
    "sg:phone":"+1 608 744 8445",
    "sg:postcode":"53807",
    "sg:province":"WI",
    "sg:tags":[
        "plumbing",
        "contractor"
    ],
    "wof:name":"Baus Plumbing & Heating",
    "wof:placetype":"venue"
},
  "geometry": {"coordinates":[-90.466478,42.609544],"type":"Point"}
}