{
  "type": "Feature",
  "properties": {
    "iso:country":"US",
    "sg:address":"902 8th St",
    "sg:city":"Baraboo",
    "sg:classifiers":[
        {
            "category":"Building & Trades",
            "subcategory":"Equipment Rental",
            "type":"Services"
        }
    ],
    "sg:phone":"+1 608 356 7859",
    "sg:postcode":"53913",
    "sg:province":"WI",
    "wof:name":"Gypsy Johns Inc",
    "wof:placetype":"venue"
},
  "geometry": {"coordinates":[-89.728363,43.474624],"type":"Point"}
}