{
  "type": "Feature",
  "properties": {
    "iso:country":"US",
    "sg:address":"5515 Byrd Ave",
    "sg:city":"Racine",
    "sg:classifiers":[
        {
            "category":"Organizations",
            "subcategory":"Religious Organization",
            "type":"Services"
        }
    ],
    "sg:phone":"+1 262 635 0162",
    "sg:postcode":"53406",
    "sg:province":"WI",
    "wof:name":"Higher Ground Ministries",
    "wof:placetype":"venue"
},
  "geometry": {"coordinates":[-87.845928,42.709472],"type":"Point"}
}