{
  "type": "Feature",
  "properties": {
    "iso:country":"US",
    "sg:address":"187 N Main St",
    "sg:city":"Rosholt",
    "sg:classifiers":[
        {
            "category":"Organizations",
            "subcategory":"Religious Organization",
            "type":"Services"
        }
    ],
    "sg:phone":"+1 715 677 4642",
    "sg:postcode":"54473",
    "sg:province":"WI",
    "wof:name":"Village Church",
    "wof:placetype":"venue"
},
  "geometry": {"coordinates":[-89.308943,44.62801],"type":"Point"}
}