{
  "type": "Feature",
  "properties": {
    "iso:country":"US",
    "sg:address":"3025 Tower Ave",
    "sg:city":"Superior",
    "sg:classifiers":[
        {
            "category":"Education",
            "subcategory":"School",
            "type":"Public Place"
        }
    ],
    "sg:phone":"+1 715 394 8700",
    "sg:postcode":"54880",
    "sg:province":"WI",
    "sg:tags":[
        "educational",
        "district"
    ],
    "sg:website":"http://www.superior.k12.wi.us",
    "wof:name":"School District Of Superior",
    "wof:placetype":"venue"
},
  "geometry": {"coordinates":[-92.104055,46.704312],"type":"Point"}
}