{
  "type": "Feature",
  "properties": {
    "iso:country":"US",
    "sg:address":"43555 Big Brook Rd",
    "sg:city":"Cable",
    "sg:classifiers":[
        {
            "category":"Farming",
            "subcategory":"Nursery",
            "type":"Manufacturing & Wholesale Goods"
        }
    ],
    "sg:phone":"+1 715 798 3191",
    "sg:postcode":"54821",
    "sg:province":"WI",
    "sg:tags":[
        "plant",
        "perennial",
        "greenhouse",
        "potted"
    ],
    "wof:name":"Big Brook Greenhouses",
    "wof:placetype":"venue"
},
  "geometry": {"coordinates":[-91.329972,46.213331],"type":"Point"}
}