{
  "type": "Feature",
  "properties": {
    "iso:country":"US",
    "sg:address":"505 Commerce St",
    "sg:city":"West Bend",
    "sg:classifiers":[
        {
            "category":"Shopping",
            "type":"Retail Goods"
        }
    ],
    "sg:phone":"+1 262 338 0676",
    "sg:postcode":"53090",
    "sg:province":"WI",
    "sg:tags":[
        "equipment",
        "supply"
    ],
    "sg:website":"www.miesproducts.com",
    "wof:name":"Mies Products Inc",
    "wof:placetype":"venue"
},
  "geometry": {"coordinates":[-88.181554,43.443089],"type":"Point"}
}