{
  "type": "Feature",
  "properties": {
    "iso:country":"US",
    "sg:address":"1017 Waube Ln",
    "sg:city":"Green Bay",
    "sg:classifiers":[
        {
            "category":"Retail",
            "subcategory":"Laundry & Dry Cleaning",
            "type":"Services"
        }
    ],
    "sg:phone":"+1 920 339 3157",
    "sg:postcode":"54304",
    "sg:province":"WI",
    "sg:tags":[
        "drycleaning",
        "plant"
    ],
    "wof:name":"Neighborhood Cleaners",
    "wof:placetype":"venue"
},
  "geometry": {"coordinates":[-88.087129,44.468945],"type":"Point"}
}