{
  "type": "Feature",
  "properties": {
    "iso:country":"US",
    "sg:address":"530 N 22nd St",
    "sg:city":"Milwaukee",
    "sg:classifiers":[
        {
            "category":"Manufacturing",
            "subcategory":"Printing",
            "type":"Manufacturing & Wholesale Goods"
        }
    ],
    "sg:phone":"+1 414 342 5050",
    "sg:postcode":"53233",
    "sg:province":"WI",
    "sg:tags":[
        "lithographer",
        "commercial",
        "lithographic"
    ],
    "sg:website":"http://www.amerlitho.com",
    "wof:name":"American Litho",
    "wof:placetype":"venue"
},
  "geometry": {"coordinates":[-87.94063,43.036535],"type":"Point"}
}