{
  "type": "Feature",
  "properties": {
    "iso:country":"US",
    "sg:address":"500 N Western Ave",
    "sg:city":"Platteville",
    "sg:classifiers":[
        {
            "category":"Farming",
            "subcategory":"Dairy Farm",
            "type":"Manufacturing & Wholesale Goods"
        }
    ],
    "sg:phone":"+1 608 348 3750",
    "sg:postcode":"53818",
    "sg:province":"WI",
    "sg:tags":[
        "corn",
        "soybean"
    ],
    "wof:name":"Glenn Balbach",
    "wof:placetype":"venue"
},
  "geometry": {"coordinates":[-90.49552799999999,42.740359],"type":"Point"}
}