{
  "type": "Feature",
  "properties": {
    "iso:country":"US",
    "sg:address":"2803 Banks Ave",
    "sg:city":"Superior",
    "sg:classifiers":[
        {
            "category":"Building & Trades",
            "subcategory":"Plumbing",
            "type":"Services"
        }
    ],
    "sg:phone":"+1 715 394 3651",
    "sg:postcode":"54880",
    "sg:province":"WI",
    "sg:tags":[
        "plumbing",
        "contractor"
    ],
    "wof:name":"Tower Plumbing & Heating",
    "wof:placetype":"venue"
},
  "geometry": {"coordinates":[-92.105559,46.704905],"type":"Point"}
}