{
  "type": "Feature",
  "properties": {
    "addr:full":"1110 N Old World 3rd St Milwaukee WI 53203",
    "addr:housenumber":"1110",
    "addr:postcode":"53203",
    "addr:street":"N Old World 3Rd St",
    "iso:country":"US",
    "sg:address":"1110 N Old World 3rd St",
    "sg:city":"Milwaukee",
    "sg:classifiers":[
        {
            "category":"Restaurant",
            "type":"Food & Drink"
        }
    ],
    "sg:menulink":"http://www.allmenus.com/wi/milwaukee/269775-kincaids---milwaukee/menu/",
    "sg:phone":"+1 414 227 1111",
    "sg:postcode":"53203",
    "sg:province":"WI",
    "sg:tags":[
        "american"
    ],
    "wof:name":"Kincaid's - Milwaukee",
    "wof:placetype":"venue"
},
  "geometry": {"coordinates":[-87.91443099999999,43.044469],"type":"Point"}
}