{
  "type": "Feature",
  "properties": {
    "iso:country":"US",
    "sg:address":"2397 Co Rd Z",
    "sg:city":"Friendship",
    "sg:classifiers":[
        {
            "category":"Travel",
            "subcategory":"Campground",
            "type":"Entertainment"
        }
    ],
    "sg:phone":"+1 608 339 7713",
    "sg:postcode":"53934",
    "sg:province":"WI",
    "sg:tags":[
        "camp"
    ],
    "wof:name":"Adams County Castle Rock Park",
    "wof:placetype":"venue"
},
  "geometry": {"coordinates":[-89.937741,43.908477],"type":"Point"}
}