{
  "type": "Feature",
  "properties": {
    "addr:full":"4500 W Wisconsin Ave Milwaukee WI 53208",
    "addr:housenumber":"4500",
    "addr:postcode":"53208",
    "addr:street":"W Wisconsin Ave",
    "iso:country":"US",
    "sg:address":"4500 W Wisconsin Ave",
    "sg:city":"Milwaukee",
    "sg:classifiers":[
        {
            "category":"Retail",
            "subcategory":"Animal Services",
            "type":"Services"
        }
    ],
    "sg:phone":"+1 414 431 6222",
    "sg:postcode":"53208",
    "sg:province":"WI",
    "sg:tags":[
        "shelter",
        "cat",
        "furnishing",
        "dog",
        "supply"
    ],
    "sg:website":"http://www.wihumane.org",
    "wof:name":"Animal Antics",
    "wof:placetype":"venue"
},
  "geometry": {"coordinates":[-87.970004,43.038838],"type":"Point"}
}