{
  "type": "Feature",
  "properties": {
    "iso:country":"US",
    "sg:address":"735 S Main St",
    "sg:city":"West Bend",
    "sg:classifiers":[
        {
            "category":"Education",
            "subcategory":"Vocational School",
            "type":"Public Place"
        }
    ],
    "sg:phone":"+1 262 335 5656",
    "sg:postcode":"53095",
    "sg:province":"WI",
    "wof:name":"West Bend School District",
    "wof:placetype":"venue"
},
  "geometry": {"coordinates":[-88.180959,43.413726],"type":"Point"}
}