{
  "type": "Feature",
  "properties": {
    "iso:country":"US",
    "sg:address":"109 S Pioneer Pkwy",
    "sg:city":"Fond Du Lac",
    "sg:classifiers":[
        {
            "category":"Manufacturing",
            "subcategory":"Printing",
            "type":"Manufacturing & Wholesale Goods"
        }
    ],
    "sg:phone":"+1 920 922 8886",
    "sg:postcode":"54935",
    "sg:province":"WI",
    "sg:tags":[
        "commercial"
    ],
    "wof:name":"Dynamic Decals",
    "wof:placetype":"venue"
},
  "geometry": {"coordinates":[-88.478658,43.775604],"type":"Point"}
}