{
  "type": "Feature",
  "properties": {
    "iso:country":"US",
    "sg:address":"250 6th Ave",
    "sg:city":"Clear Lake",
    "sg:classifiers":[
        {
            "category":"Retail",
            "subcategory":"Auto Repair",
            "type":"Services"
        }
    ],
    "sg:phone":"+1 715 263 2857",
    "sg:postcode":"54005",
    "sg:province":"WI",
    "sg:tags":[
        "body",
        "automobile",
        "painting"
    ],
    "wof:name":"Jim's Body Shop",
    "wof:placetype":"venue"
},
  "geometry": {"coordinates":[-92.269931,45.248499],"type":"Point"}
}