{
  "type": "Feature",
  "properties": {
    "iso:country":"US",
    "sg:address":"10701 W North Ave",
    "sg:city":"Milwaukee",
    "sg:classifiers":[
        {
            "category":"Professional",
            "subcategory":"Management & Consulting",
            "type":"Services"
        }
    ],
    "sg:phone":"+1 262 522 6868",
    "sg:postcode":"53226",
    "sg:province":"WI",
    "wof:name":"CJ Marketing",
    "wof:placetype":"venue"
},
  "geometry": {"coordinates":[-88.047659,43.059927],"type":"Point"}
}