{
  "type": "Feature",
  "properties": {
    "iso:country":"US",
    "sg:address":"11548 N River Rd",
    "sg:city":"Mequon",
    "sg:classifiers":[
        {
            "category":"Animal Shelter",
            "type":"Public Place"
        },
        {
            "category":"Shopping",
            "subcategory":"Pets & Pet Supplies",
            "type":"Retail Goods"
        }
    ],
    "sg:phone":"+1 262 242 3824",
    "sg:postcode":"53092",
    "sg:province":"WI",
    "sg:tags":[
        "store"
    ],
    "wof:name":"Wi Society For the Prevention of Cruelty To Animls",
    "wof:placetype":"venue"
},
  "geometry": {"coordinates":[-87.96369900000001,43.227798],"type":"Point"}
}