{
  "type": "Feature",
  "properties": {
    "iso:country":"US",
    "sg:address":"408 N 8th St",
    "sg:city":"Hilbert",
    "sg:classifiers":[
        {
            "category":"Bars & Pubs",
            "type":"Food & Drink"
        }
    ],
    "sg:phone":"+1 920 853 7131",
    "sg:postcode":"54129",
    "sg:province":"WI",
    "wof:name":"Hilbert Lanes",
    "wof:placetype":"venue"
},
  "geometry": {"coordinates":[-88.163943,44.144126],"type":"Point"}
}