{
  "type": "Feature",
  "properties": {
    "addr:full":"555 Braund St Onalaska WI 54650",
    "addr:housenumber":"555",
    "addr:postcode":"54650",
    "addr:street":"Braund St",
    "iso:country":"US",
    "sg:address":"555 Braund St",
    "sg:city":"Onalaska",
    "sg:classifiers":[
        {
            "category":"Building & Trades",
            "subcategory":"Construction",
            "type":"Services"
        }
    ],
    "sg:phone":"+1 608 779 5010",
    "sg:postcode":"54650",
    "sg:province":"WI",
    "sg:tags":[
        "installation",
        "terrazzo",
        "floor"
    ],
    "sg:website":"www.wisconsinterrazzo.com",
    "wof:name":"Wisconsin Terrazzo & Tile Inc",
    "wof:placetype":"venue"
},
  "geometry": {"coordinates":[-91.199592,43.875494],"type":"Point"}
}