{
  "type": "Feature",
  "properties": {
    "iso:country":"US",
    "sg:address":"2743 N 59th St",
    "sg:city":"Milwaukee",
    "sg:classifiers":[
        {
            "category":"Bars & Pubs",
            "type":"Food & Drink"
        }
    ],
    "sg:phone":"+1 414 447 8462",
    "sg:postcode":"53210",
    "sg:province":"WI",
    "sg:tags":[
        "drinking"
    ],
    "wof:name":"Hard Ride Saloon",
    "wof:placetype":"venue"
},
  "geometry": {"coordinates":[-87.986402,43.068604],"type":"Point"}
}