{
  "type": "Feature",
  "properties": {
    "iso:country":"US",
    "sg:address":"920 61st St",
    "sg:city":"Kenosha",
    "sg:classifiers":[
        {
            "category":"Professional",
            "subcategory":"Lawyer & Legal Services",
            "type":"Services"
        }
    ],
    "sg:phone":"+1 262 654 3091",
    "sg:postcode":"53143",
    "sg:province":"WI",
    "sg:tags":[
        "attorney"
    ],
    "wof:name":"Lisa Danielson LLC",
    "wof:placetype":"venue"
},
  "geometry": {"coordinates":[-87.822422,42.579591],"type":"Point"}
}