{
  "type": "Feature",
  "properties": {
    "iso:country":"US",
    "sg:address":"2909 Bongey Dr",
    "sg:city":"Menomonie",
    "sg:classifiers":[
        {
            "category":"Bars & Pubs",
            "type":"Food & Drink"
        }
    ],
    "sg:phone":"+1 715 235 3472",
    "sg:postcode":"54751",
    "sg:province":"WI",
    "wof:name":"Veterans Of Foreign Wars",
    "wof:placetype":"venue"
},
  "geometry": {"coordinates":[-91.94002399999999,44.857022],"type":"Point"}
}