{
  "type": "Feature",
  "properties": {
    "iso:country":"US",
    "sg:address":"6405 Banks Ave",
    "sg:city":"Superior",
    "sg:classifiers":[
        {
            "category":"Freight",
            "type":"Transportation"
        }
    ],
    "sg:phone":"+1 715 392 5268",
    "sg:postcode":"54880",
    "sg:province":"WI",
    "sg:tags":[
        "operator",
        "local",
        "trucking"
    ],
    "wof:name":"M & M Cartage",
    "wof:placetype":"venue"
},
  "geometry": {"coordinates":[-92.10597199999999,46.660915],"type":"Point"}
}