{
  "type": "Feature",
  "properties": {
    "iso:country":"US",
    "sg:address":"5138 N 57th St",
    "sg:city":"Milwaukee",
    "sg:classifiers":[
        {
            "category":"Professional",
            "subcategory":"Lawyer & Legal Services",
            "type":"Services"
        }
    ],
    "sg:phone":"+1 414 438 9757",
    "sg:postcode":"53218",
    "sg:province":"WI",
    "sg:tags":[
        "attorney"
    ],
    "wof:name":"Dennis Law Office",
    "wof:placetype":"venue"
},
  "geometry": {"coordinates":[-87.983676,43.109423],"type":"Point"}
}