{
  "type": "Feature",
  "properties": {
    "iso:country":"US",
    "sg:address":"4646 Hill Rd",
    "sg:city":"Bryant",
    "sg:classifiers":[
        {
            "category":"Farming",
            "subcategory":"Farm",
            "type":"Manufacturing & Wholesale Goods"
        }
    ],
    "sg:phone":"+1 715 623 6623",
    "sg:postcode":"54418",
    "sg:province":"WI",
    "sg:tags":[
        "general",
        "milk",
        "fluid",
        "crop",
        "mfg"
    ],
    "wof:name":"Spring Brook Farm",
    "wof:placetype":"venue"
},
  "geometry": {"coordinates":[-89.029699,45.198504],"type":"Point"}
}