{
  "type": "Feature",
  "properties": {
    "iso:country":"US",
    "sg:address":"519 Christel Dr",
    "sg:city":"Valders",
    "sg:classifiers":[
        {
            "category":"Health Services",
            "subcategory":"Doctor",
            "type":"Services"
        }
    ],
    "sg:phone":"+1 920 775 4531",
    "sg:postcode":"54245",
    "sg:province":"WI",
    "sg:tags":[
        "dentist"
    ],
    "wof:name":"Valders Dental Assoc",
    "wof:placetype":"venue"
},
  "geometry": {"coordinates":[-87.885458,44.062886],"type":"Point"}
}