{
  "type": "Feature",
  "properties": {
    "iso:country":"US",
    "sg:address":"126 E Milwaukee St",
    "sg:city":"Jefferson",
    "sg:classifiers":[
        {
            "category":"Organizations",
            "subcategory":"Labor Organization",
            "type":"Services"
        }
    ],
    "sg:phone":"+1 920 674 5558",
    "sg:postcode":"53549",
    "sg:province":"WI",
    "sg:tags":[
        "plant",
        "packing",
        "meat"
    ],
    "wof:name":"United Fd Coml Wkrs Local 538",
    "wof:placetype":"venue"
},
  "geometry": {"coordinates":[-88.80697600000001,43.004318],"type":"Point"}
}