{
  "type": "Feature",
  "properties": {
    "iso:country":"US",
    "sg:address":"8654 Pine St",
    "sg:city":"Bancroft",
    "sg:classifiers":[
        {
            "category":"Building & Trades",
            "subcategory":"Plumbing",
            "type":"Services"
        }
    ],
    "sg:phone":"+1 715 335 6163",
    "sg:postcode":"54921",
    "sg:province":"WI",
    "sg:tags":[
        "contractor"
    ],
    "wof:name":"Premium Plumbing & Heating",
    "wof:placetype":"venue"
},
  "geometry": {"coordinates":[-89.51112999999999,44.299754],"type":"Point"}
}