{
  "type": "Feature",
  "properties": {
    "iso:country":"US",
    "sg:address":"19275 W Capitol Dr",
    "sg:city":"Brookfield",
    "sg:classifiers":[
        {
            "category":"Professional",
            "subcategory":"Lawyer & Legal Services",
            "type":"Services"
        },
        {
            "category":"Professional",
            "subcategory":"Management & Consulting",
            "type":"Services"
        }
    ],
    "sg:phone":"+1 262 790 9870",
    "sg:postcode":"53045",
    "sg:province":"WI",
    "sg:tags":[
        "attorney"
    ],
    "wof:name":"Ludwig Law Firm",
    "wof:placetype":"venue"
},
  "geometry": {"coordinates":[-88.155507,43.090221],"type":"Point"}
}