{
  "type": "Feature",
  "properties": {
    "iso:country":"US",
    "sg:address":"6607 Wayside Dr",
    "sg:city":"Merrill",
    "sg:classifiers":[
        {
            "category":"Health Services",
            "subcategory":"Chiropractor",
            "type":"Services"
        }
    ],
    "sg:phone":"+1 715 536 9668",
    "sg:postcode":"54452",
    "sg:province":"WI",
    "wof:name":"Apprill Family Chiropractic SC",
    "wof:placetype":"venue"
},
  "geometry": {"coordinates":[-89.75829,45.21246],"type":"Point"}
}