{
  "type": "Feature",
  "properties": {
    "iso:country":"US",
    "sg:address":"605 S River St",
    "sg:city":"Shawano",
    "sg:classifiers":[
        {
            "category":"Health Services",
            "subcategory":"Doctor",
            "type":"Services"
        }
    ],
    "sg:phone":"+1 715 526 5862",
    "sg:postcode":"54166",
    "sg:province":"WI",
    "sg:tags":[
        "medical"
    ],
    "wof:name":"John D Scharine Crna SC",
    "wof:placetype":"venue"
},
  "geometry": {"coordinates":[-88.618122,44.776557],"type":"Point"}
}