{
  "type": "Feature",
  "properties": {
    "iso:country":"US",
    "sg:address":"4222 W Capitol Dr",
    "sg:city":"Milwaukee",
    "sg:classifiers":[
        {
            "category":"Insurance",
            "subcategory":"Insurance Agent",
            "type":"Services"
        }
    ],
    "sg:phone":"+1 414 444 3233",
    "sg:postcode":"53216",
    "sg:province":"WI",
    "wof:name":"Luster Agency",
    "wof:placetype":"venue"
},
  "geometry": {"coordinates":[-87.966724,43.089883],"type":"Point"}
}