{
  "type": "Feature",
  "properties": {
    "iso:country":"US",
    "sg:address":"1312 Sterling Ct",
    "sg:city":"West Bend",
    "sg:classifiers":[
        {
            "category":"Recreation",
            "type":"Entertainment"
        }
    ],
    "sg:phone":"+1 262 338 3570",
    "sg:postcode":"53095",
    "sg:province":"WI",
    "sg:tags":[
        "range",
        "golf",
        "driving"
    ],
    "wof:name":"Blue Dog Golf",
    "wof:placetype":"venue"
},
  "geometry": {"coordinates":[-88.19372,43.414619],"type":"Point"}
}