{
  "type": "Feature",
  "properties": {
    "iso:country":"US",
    "sg:address":"7311 S 13th St",
    "sg:city":"Oak Creek",
    "sg:classifiers":[
        {
            "category":"Organizations",
            "subcategory":"Religious Organization",
            "type":"Services"
        }
    ],
    "sg:phone":"+1 414 762 2010",
    "sg:postcode":"53154",
    "sg:province":"WI",
    "sg:website":"www.oakcreekag.org",
    "wof:name":"Oak Creek Assembly Of God",
    "wof:placetype":"venue"
},
  "geometry": {"coordinates":[-87.931224,42.905503],"type":"Point"}
}