{
  "type": "Feature",
  "properties": {
    "iso:country":"US",
    "sg:address":"960 Jefferson St",
    "sg:city":"Fennimore",
    "sg:classifiers":[
        {
            "category":"Organizations",
            "subcategory":"Religious Organization",
            "type":"Services"
        }
    ],
    "sg:phone":"+1 608 822 6735",
    "sg:postcode":"53809",
    "sg:province":"WI",
    "sg:tags":[
        "church"
    ],
    "wof:name":"St Mary's Church Hall",
    "wof:placetype":"venue"
},
  "geometry": {"coordinates":[-90.654532,42.983104],"type":"Point"}
}