{
  "type": "Feature",
  "properties": {
    "iso:country":"US",
    "sg:address":"4899 Linwood Ln",
    "sg:city":"Sheboygan Falls",
    "sg:classifiers":[
        {
            "category":"Building & Trades",
            "subcategory":"Construction",
            "type":"Services"
        }
    ],
    "sg:phone":"+1 920 467 0329",
    "sg:postcode":"53085",
    "sg:province":"WI",
    "sg:tags":[
        "builder",
        "general"
    ],
    "wof:name":"Cornerstone Builders",
    "wof:placetype":"venue"
},
  "geometry": {"coordinates":[-87.86549,43.718544],"type":"Point"}
}