{
  "type": "Feature",
  "properties": {
    "iso:country":"US",
    "sg:address":"1501 Union Ave",
    "sg:city":"Sheboygan",
    "sg:classifiers":[
        {
            "category":"Bars & Pubs",
            "type":"Food & Drink"
        }
    ],
    "sg:phone":"+1 920 458 1026",
    "sg:postcode":"53081",
    "sg:province":"WI",
    "sg:tags":[
        "drinking"
    ],
    "wof:name":"Mueller's Bar",
    "wof:placetype":"venue"
},
  "geometry": {"coordinates":[-87.726227,43.732082],"type":"Point"}
}