{
  "type": "Feature",
  "properties": {
    "iso:country":"US",
    "sg:address":"4581 Hillcrest Dr",
    "sg:city":"West Bend",
    "sg:classifiers":[
        {
            "category":"Professional",
            "subcategory":"Business Services",
            "type":"Services"
        }
    ],
    "sg:phone":"+1 262 629 5195",
    "sg:postcode":"53095",
    "sg:province":"WI",
    "wof:name":"Krause Home Inspections",
    "wof:placetype":"venue"
},
  "geometry": {"coordinates":[-88.264526,43.412935],"type":"Point"}
}