{
  "type": "Feature",
  "properties": {
    "iso:country":"US",
    "sg:address":"2607 Eaton Ln",
    "sg:city":"Racine",
    "sg:classifiers":[
        {
            "category":"Manufacturing",
            "subcategory":"Metals",
            "type":"Manufacturing & Wholesale Goods"
        }
    ],
    "sg:phone":"+1 262 632 2232",
    "sg:postcode":"53404",
    "sg:province":"WI",
    "sg:tags":[
        "stampings",
        "mfg"
    ],
    "sg:website":"www.pinnacleprecisioninc.com",
    "wof:name":"Pinnacle Precision Inc",
    "wof:placetype":"venue"
},
  "geometry": {"coordinates":[-87.81292999999999,42.7532],"type":"Point"}
}