{
  "type": "Feature",
  "properties": {
    "iso:country":"US",
    "sg:address":"8232 Springer Rd",
    "sg:city":"Lake Mills",
    "sg:classifiers":[
        {
            "category":"Retail",
            "subcategory":"Animal Services",
            "type":"Services"
        }
    ],
    "sg:phone":"+1 920 648 5574",
    "sg:postcode":"53551",
    "sg:province":"WI",
    "wof:name":"Dj Rockin Stables",
    "wof:placetype":"venue"
},
  "geometry": {"coordinates":[-88.910564,43.1431],"type":"Point"}
}