{
  "type": "Feature",
  "properties": {
    "iso:country":"US",
    "sg:address":"6921 Mariner Dr",
    "sg:city":"Racine",
    "sg:classifiers":[
        {
            "category":"Professional",
            "subcategory":"Accounting & Tax Preparation",
            "type":"Services"
        }
    ],
    "sg:phone":"+1 262 884 8990",
    "sg:postcode":"53406",
    "sg:province":"WI",
    "sg:tags":[
        "accountant"
    ],
    "wof:name":"Erdman & Hoyt",
    "wof:placetype":"venue"
},
  "geometry": {"coordinates":[-87.864937,42.722626],"type":"Point"}
}