{
  "type": "Feature",
  "properties": {
    "iso:country":"US",
    "sg:address":"28683 Clary Ln",
    "sg:city":"Richland Center",
    "sg:classifiers":[
        {
            "category":"Real Estate",
            "subcategory":"Real Estate Operator",
            "type":"Services"
        }
    ],
    "sg:phone":"+1 608 647 7131",
    "sg:postcode":"53581",
    "sg:province":"WI",
    "sg:tags":[
        "apartment"
    ],
    "wof:name":"Meridian Group",
    "wof:placetype":"venue"
},
  "geometry": {"coordinates":[-90.295384,43.287408],"type":"Point"}
}