{
  "type": "Feature",
  "properties": {
    "addr:full":"313 Main St Friendship WI 53934",
    "addr:housenumber":"313",
    "addr:postcode":"53934",
    "addr:street":"Main St",
    "iso:country":"US",
    "sg:address":"313 Main St",
    "sg:city":"Friendship",
    "sg:classifiers":[
        {
            "category":"Real Estate",
            "subcategory":"Real Estate Agent",
            "type":"Services"
        }
    ],
    "sg:phone":"+1 608 339 3342",
    "sg:postcode":"53934",
    "sg:province":"WI",
    "wof:name":"Adams County Realty Inc",
    "wof:placetype":"venue"
},
  "geometry": {"coordinates":[-89.816256,43.972074],"type":"Point"}
}