{
  "type": "Feature",
  "properties": {
    "iso:country":"US",
    "sg:address":"140 N Brown St",
    "sg:city":"Rhinelander",
    "sg:classifiers":[
        {
            "category":"Health Services",
            "subcategory":"Doctor",
            "type":"Services"
        }
    ],
    "sg:phone":"+1 715 362 4247",
    "sg:postcode":"54501",
    "sg:province":"WI",
    "wof:name":"Randall L Natrop DDS",
    "wof:placetype":"venue"
},
  "geometry": {"coordinates":[-89.412682,45.639662],"type":"Point"}
}