{
  "type": "Feature",
  "properties": {
    "iso:country":"US",
    "sg:address":"765 Woodlake Rd",
    "sg:city":"Kohler",
    "sg:classifiers":[
        {
            "category":"Shopping",
            "subcategory":"Hobbies, Toys, & Games",
            "type":"Retail Goods"
        }
    ],
    "sg:phone":"+1 920 457 8807",
    "sg:postcode":"53044",
    "sg:province":"WI",
    "sg:tags":[
        "doll"
    ],
    "wof:name":"Nursery Window Ltd",
    "wof:placetype":"venue"
},
  "geometry": {"coordinates":[-87.782824,43.743934],"type":"Point"}
}