{
  "type": "Feature",
  "properties": {
    "iso:country":"US",
    "sg:address":"460 N Beaumont Ave",
    "sg:city":"Brookfield",
    "sg:classifiers":[
        {
            "category":"Building & Trades",
            "subcategory":"Construction",
            "type":"Services"
        }
    ],
    "sg:phone":"+1 262 780 9746",
    "sg:postcode":"53005",
    "sg:province":"WI",
    "sg:tags":[
        "house"
    ],
    "wof:name":"Westbrook Handyman Services",
    "wof:placetype":"venue"
},
  "geometry": {"coordinates":[-88.09302,43.035004],"type":"Point"}
}