{
  "type": "Feature",
  "properties": {
    "iso:country":"US",
    "sg:address":"10819 Co Rd V",
    "sg:city":"Marshfield",
    "sg:classifiers":[
        {
            "category":"Retail",
            "subcategory":"Repair Shop",
            "type":"Services"
        }
    ],
    "sg:phone":"+1 715 676 2462",
    "sg:postcode":"54449",
    "sg:province":"WI",
    "wof:name":"Lucas Mobile Home Service",
    "wof:placetype":"venue"
},
  "geometry": {"coordinates":[-90.29925900000001,44.638854],"type":"Point"}
}