{
  "type": "Feature",
  "properties": {
    "iso:country":"US",
    "sg:address":"5851 Douglas Ave",
    "sg:city":"Racine",
    "sg:classifiers":[
        {
            "category":"Building & Trades",
            "subcategory":"Construction",
            "type":"Services"
        }
    ],
    "sg:phone":"+1 262 681 2478",
    "sg:postcode":"53402",
    "sg:province":"WI",
    "sg:tags":[
        "sewer",
        "contractor"
    ],
    "wof:name":"Danbar Construction",
    "wof:placetype":"venue"
},
  "geometry": {"coordinates":[-87.821036,42.796983],"type":"Point"}
}