{
  "type": "Feature",
  "properties": {
    "addr:full":"4505 Pine Ln Green Bay WI 54313",
    "addr:housenumber":"4505",
    "addr:postcode":"54313",
    "addr:street":"Pine Ln",
    "iso:country":"US",
    "sg:address":"4505 Pine Ln",
    "sg:city":"Green Bay",
    "sg:classifiers":[
        {
            "category":"Shopping",
            "subcategory":"Crafts & Fabrics",
            "type":"Retail Goods"
        }
    ],
    "sg:phone":"+1 920 434 6648",
    "sg:postcode":"54313",
    "sg:province":"WI",
    "sg:tags":[
        "material",
        "quilting",
        "sewing",
        "supply"
    ],
    "wof:name":"A Quilter's Dream",
    "wof:placetype":"venue"
},
  "geometry": {"coordinates":[-88.110878,44.660449],"type":"Point"}
}