{
  "type": "Feature",
  "properties": {
    "addr:full":"245 Paperjack Dr New Richmond WI 54017",
    "addr:housenumber":"245",
    "addr:postcode":"54017",
    "addr:street":"Paperjack Dr",
    "iso:country":"US",
    "sg:address":"245 Paperjack Dr",
    "sg:city":"New Richmond",
    "sg:classifiers":[
        {
            "category":"Social Services",
            "subcategory":"Child Care",
            "type":"Services"
        }
    ],
    "sg:phone":"+1 715 246 7600",
    "sg:postcode":"54017",
    "sg:province":"WI",
    "sg:tags":[
        "kindergarten",
        "academic",
        "school"
    ],
    "wof:name":"Learning Station Preschool",
    "wof:placetype":"venue"
},
  "geometry": {"coordinates":[-92.535473,45.104502],"type":"Point"}
}