{
  "type": "Feature",
  "properties": {
    "addr:full":"6832 W Becher St West Allis WI 53219",
    "addr:housenumber":"6832",
    "addr:postcode":"53219",
    "addr:street":"W Becher St",
    "iso:country":"US",
    "sg:address":"6832 W Becher St",
    "sg:city":"West Allis",
    "sg:classifiers":[
        {
            "category":"Shopping",
            "subcategory":"Gifts & Souvenirs",
            "type":"Retail Goods"
        }
    ],
    "sg:phone":"+1 414 543 4230",
    "sg:postcode":"53219",
    "sg:province":"WI",
    "sg:tags":[
        "shop"
    ],
    "sg:website":"www.wacheese-gifts.com",
    "wof:name":"West Allis Cheese & Sausage",
    "wof:placetype":"venue"
},
  "geometry": {"coordinates":[-87.998808,43.006463],"type":"Point"}
}