{
  "type": "Feature",
  "properties": {
    "iso:country":"US",
    "sg:address":"2587 Lawrence Dr",
    "sg:city":"De Pere",
    "sg:classifiers":[
        {
            "category":"Retail",
            "subcategory":"Auto Repair",
            "type":"Services"
        }
    ],
    "sg:phone":"+1 920 336 8261",
    "sg:postcode":"54115",
    "sg:province":"WI",
    "sg:tags":[
        "supply",
        "general"
    ],
    "wof:name":"Bay Speed Center",
    "wof:placetype":"venue"
},
  "geometry": {"coordinates":[-88.13589399999999,44.397088],"type":"Point"}
}