{
  "type": "Feature",
  "properties": {
    "addr:full":"1401 Marks Rd Oconomowoc WI 53066",
    "addr:housenumber":"1401",
    "addr:postcode":"53066",
    "addr:street":"Marks Rd",
    "iso:country":"US",
    "sg:address":"1401 Marks Rd",
    "sg:city":"Oconomowoc",
    "sg:classifiers":[
        {
            "category":"Personal",
            "subcategory":"Beauty Salon",
            "type":"Services"
        }
    ],
    "sg:phone":"+1 262 567 5390",
    "sg:postcode":"53066",
    "sg:province":"WI",
    "wof:name":"Julie's Hair By Design",
    "wof:placetype":"venue"
},
  "geometry": {"coordinates":[-88.52452599999999,43.121893],"type":"Point"}
}