{
  "type": "Feature",
  "properties": {
    "iso:country":"US",
    "sg:address":"140 W Bell St",
    "sg:city":"Neenah",
    "sg:classifiers":[
        {
            "category":"Organizations",
            "subcategory":"Religious Organization",
            "type":"Services"
        }
    ],
    "sg:phone":"+1 920 722 3343",
    "sg:postcode":"54956",
    "sg:province":"WI",
    "sg:tags":[
        "church"
    ],
    "wof:name":"Victory Bible Assembly Of God",
    "wof:placetype":"venue"
},
  "geometry": {"coordinates":[-88.463712,44.156611],"type":"Point"}
}