{
  "type": "Feature",
  "properties": {
    "iso:country":"US",
    "sg:address":"10206 N Port Washington Rd",
    "sg:city":"Thiensville",
    "sg:classifiers":[
        {
            "category":"Freight",
            "type":"Transportation"
        }
    ],
    "sg:phone":"+1 262 241 1500",
    "sg:postcode":"53092",
    "sg:province":"WI",
    "sg:tags":[
        "warehouse",
        "storage"
    ],
    "wof:name":"Instant Mini Storage Inc",
    "wof:placetype":"venue"
},
  "geometry": {"coordinates":[-87.924206,43.204682],"type":"Point"}
}