{
  "type": "Feature",
  "properties": {
    "iso:country":"US",
    "sg:address":"830 Virginia Ave",
    "sg:city":"Sheboygan",
    "sg:classifiers":[
        {
            "category":"Education",
            "subcategory":"School",
            "type":"Public Place"
        }
    ],
    "sg:phone":"+1 920 459 3500",
    "sg:postcode":"53081",
    "sg:province":"WI",
    "sg:tags":[
        "management",
        "sch"
    ],
    "sg:website":"www.sheboygan.k12.wi.us",
    "wof:name":"Sheboygan Area School District",
    "wof:placetype":"venue"
},
  "geometry": {"coordinates":[-87.714474,43.747678],"type":"Point"}
}