{
  "type": "Feature",
  "properties": {
    "addr:full":"7544 Co Rd G Hillpoint WI 53937",
    "addr:housenumber":"7544",
    "addr:postcode":"53937",
    "addr:street":"Co Rd",
    "iso:country":"US",
    "sg:address":"7544 Co Rd G",
    "sg:city":"Hillpoint",
    "sg:classifiers":[
        {
            "category":"Farming",
            "subcategory":"Dairy Farm",
            "type":"Manufacturing & Wholesale Goods"
        }
    ],
    "sg:phone":"+1 608 986 3623",
    "sg:postcode":"53937",
    "sg:province":"WI",
    "wof:name":"McCluskey Bros",
    "wof:placetype":"venue"
},
  "geometry": {"coordinates":[-90.120563,43.372382],"type":"Point"}
}