{
  "type": "Feature",
  "properties": {
    "addr:full":"4335 N 104th St Milwaukee WI 53222",
    "addr:housenumber":"4335",
    "addr:postcode":"53222",
    "addr:street":"N 104Th St",
    "iso:country":"US",
    "sg:address":"4335 N 104th St",
    "sg:city":"Milwaukee",
    "sg:classifiers":[
        {
            "category":"Real Estate",
            "subcategory":"Real Estate Services",
            "type":"Services"
        }
    ],
    "sg:phone":"+1 888 509 6645",
    "sg:postcode":"53222",
    "sg:province":"WI",
    "sg:tags":[
        "apartment",
        "management",
        "rental",
        "finder"
    ],
    "sg:website":"http://milwaukee.citysearch.com/profile/external/44854723/milwaukee_wi/grantosa_crossing.html?publisher=yellowpages&reference_id=1&placement=ypwebsitemip",
    "wof:name":"Grantosa Crossing",
    "wof:placetype":"venue"
},
  "geometry": {"coordinates":[-88.041839,43.094025],"type":"Point"}
}