{
  "type": "Feature",
  "properties": {
    "iso:country":"US",
    "sg:address":"1104 E 3rd St",
    "sg:city":"Merrill",
    "sg:classifiers":[
        {
            "category":"Education",
            "subcategory":"School",
            "type":"Public Place"
        }
    ],
    "sg:phone":"+1 715 536 7264",
    "sg:postcode":"54452",
    "sg:province":"WI",
    "wof:name":"St John's Lutheran School",
    "wof:placetype":"venue"
},
  "geometry": {"coordinates":[-89.684284,45.183475],"type":"Point"}
}