{
  "type": "Feature",
  "properties": {
    "iso:country":"US",
    "sg:address":"916 S Union St",
    "sg:city":"Shawano",
    "sg:classifiers":[
        {
            "category":"Shopping",
            "subcategory":"Gifts & Souvenirs",
            "type":"Retail Goods"
        }
    ],
    "sg:phone":"+1 715 524 2308",
    "sg:postcode":"54166",
    "sg:province":"WI",
    "wof:name":"Longeberger Co",
    "wof:placetype":"venue"
},
  "geometry": {"coordinates":[-88.602519,44.772491],"type":"Point"}
}