{
  "type": "Feature",
  "properties": {
    "iso:country":"US",
    "sg:address":"1006 Highland Springs Ct",
    "sg:city":"Oneida",
    "sg:classifiers":[
        {
            "category":"Insurance",
            "subcategory":"Insurance Agent",
            "type":"Services"
        }
    ],
    "sg:phone":"+1 920 494 9004",
    "sg:postcode":"54155",
    "sg:province":"WI",
    "wof:name":"AFLAC",
    "wof:placetype":"venue"
},
  "geometry": {"coordinates":[-88.144942,44.546008],"type":"Point"}
}