{
  "type": "Feature",
  "properties": {
    "iso:country":"US",
    "sg:address":"4913 Jones Rd",
    "sg:city":"Spring Green",
    "sg:classifiers":[
        {
            "category":"Banks & Credit Unions",
            "subcategory":"Investment Brokerage",
            "type":"Services"
        }
    ],
    "sg:phone":"+1 608 588 7590",
    "sg:postcode":"53588",
    "sg:province":"WI",
    "sg:tags":[
        "security"
    ],
    "wof:name":"Bill Oberg Trading",
    "wof:placetype":"venue"
},
  "geometry": {"coordinates":[-90.064401,43.197022],"type":"Point"}
}