{
  "type": "Feature",
  "properties": {
    "iso:country":"US",
    "sg:address":"3220 N 90th St",
    "sg:city":"Milwaukee",
    "sg:classifiers":[
        {
            "category":"Health Services",
            "subcategory":"Medical Lab",
            "type":"Services"
        }
    ],
    "sg:phone":"+1 414 873 3067",
    "sg:postcode":"53222",
    "sg:province":"WI",
    "sg:tags":[
        "laboratory"
    ],
    "wof:name":"Phillips Health Care Products",
    "wof:placetype":"venue"
},
  "geometry": {"coordinates":[-88.025003,43.078337],"type":"Point"}
}