{
  "type": "Feature",
  "properties": {
    "addr:full":"3872 N 8th St Milwaukee WI 53206",
    "addr:housenumber":"3872",
    "addr:postcode":"53206",
    "addr:street":"N 8Th St",
    "iso:country":"US",
    "sg:address":"3872 N 8th St",
    "sg:city":"Milwaukee",
    "sg:classifiers":[
        {
            "category":"Education",
            "subcategory":"School",
            "type":"Public Place"
        }
    ],
    "sg:phone":"+1 414 267 4600",
    "sg:postcode":"53206",
    "sg:province":"WI",
    "sg:tags":[
        "elementary"
    ],
    "wof:name":"Green Bay Avenue Public School",
    "wof:placetype":"venue"
},
  "geometry": {"coordinates":[-87.92095500000001,43.086923],"type":"Point"}
}