{
  "type": "Feature",
  "properties": {
    "iso:country":"US",
    "sg:address":"717 Arthur St",
    "sg:city":"Menasha",
    "sg:classifiers":[
        {
            "category":"Autos & Motor Vehicles",
            "subcategory":"Automobile Sales",
            "type":"Retail Goods"
        }
    ],
    "sg:phone":"+1 920 725 6375",
    "sg:postcode":"54952",
    "sg:province":"WI",
    "wof:name":"Auto One LLC",
    "wof:placetype":"venue"
},
  "geometry": {"coordinates":[-88.425434,44.212486],"type":"Point"}
}