{
  "type": "Feature",
  "properties": {
    "iso:country":"US",
    "sg:address":"420 2nd St",
    "sg:city":"Taylor",
    "sg:classifiers":[
        {
            "category":"Education",
            "subcategory":"Library",
            "type":"Public Place"
        }
    ],
    "sg:phone":"+1 715 662 2310",
    "sg:postcode":"54659",
    "sg:province":"WI",
    "wof:name":"Village Of Taylor Library",
    "wof:placetype":"venue"
},
  "geometry": {"coordinates":[-91.120569,44.321592],"type":"Point"}
}