{
  "type": "Feature",
  "properties": {
    "iso:country":"US",
    "sg:address":"5225 N Chipmunk Rd",
    "sg:city":"Stoddard",
    "sg:classifiers":[
        {
            "category":"Recreation",
            "type":"Entertainment"
        }
    ],
    "sg:phone":"+1 608 788 5458",
    "sg:postcode":"54658",
    "sg:province":"WI",
    "sg:tags":[
        "club",
        "membership"
    ],
    "wof:name":"Coulee Rock Club Inc",
    "wof:placetype":"venue"
},
  "geometry": {"coordinates":[-91.166737,43.725357],"type":"Point"}
}