{
  "type": "Feature",
  "properties": {
    "addr:full":"1380 State Hwy 164 Hubertus WI 53033",
    "addr:housenumber":"1380",
    "addr:postcode":"53033",
    "addr:street":"State Hwy 164",
    "iso:country":"US",
    "sg:address":"1380 State Hwy 164",
    "sg:city":"Hubertus",
    "sg:classifiers":[
        {
            "category":"Retail",
            "subcategory":"Repair Shop",
            "type":"Services"
        }
    ],
    "sg:phone":"+1 262 628 4047",
    "sg:postcode":"53033",
    "sg:province":"WI",
    "sg:tags":[
        "taxidermist"
    ],
    "wof:name":"Scenic Hill Taxidermy",
    "wof:placetype":"venue"
},
  "geometry": {"coordinates":[-88.261707,43.243078],"type":"Point"}
}