{
  "type": "Feature",
  "properties": {
    "addr:full":"8105 W Wisconsin Ave Milwaukee WI 53213",
    "addr:housenumber":"8105",
    "addr:postcode":"53213",
    "addr:street":"W Wisconsin Ave",
    "iso:country":"US",
    "sg:address":"8105 W Wisconsin Ave",
    "sg:city":"Milwaukee",
    "sg:classifiers":[
        {
            "category":"Real Estate",
            "subcategory":"Real Estate Agent",
            "type":"Services"
        }
    ],
    "sg:phone":"+1 414 258 7582",
    "sg:postcode":"53213",
    "sg:province":"WI",
    "wof:name":"Kathleen Callan Brady LLC",
    "wof:placetype":"venue"
},
  "geometry": {"coordinates":[-88.014335,43.038612],"type":"Point"}
}