{
  "type": "Feature",
  "properties": {
    "iso:country":"US",
    "sg:address":"326 W Juneau St",
    "sg:city":"Hustisford",
    "sg:classifiers":[
        {
            "category":"Food & Beverages",
            "subcategory":"Groceries & Convenience Stores",
            "type":"Retail Goods"
        }
    ],
    "sg:phone":"+1 920 349 3989",
    "sg:postcode":"53034",
    "sg:province":"WI",
    "wof:name":"United Cooperative",
    "wof:placetype":"venue"
},
  "geometry": {"coordinates":[-88.609029,43.346154],"type":"Point"}
}