{
  "type": "Feature",
  "properties": {
    "iso:country":"US",
    "sg:address":"1614 Main St",
    "sg:city":"Marinette",
    "sg:classifiers":[
        {
            "category":"Shopping",
            "subcategory":"Musical Instruments",
            "type":"Retail Goods"
        }
    ],
    "sg:phone":"+1 715 735 7111",
    "sg:postcode":"54143",
    "sg:province":"WI",
    "wof:name":"Paul's Music",
    "wof:placetype":"venue"
},
  "geometry": {"coordinates":[-87.629205,45.098808],"type":"Point"}
}