{
  "type": "Feature",
  "properties": {
    "iso:country":"US",
    "sg:address":"6418 Normandy Ln",
    "sg:city":"Madison",
    "sg:classifiers":[
        {
            "category":"Building & Trades",
            "subcategory":"Construction",
            "type":"Services"
        }
    ],
    "sg:phone":"+1 608 819 0055",
    "sg:postcode":"53719",
    "sg:province":"WI",
    "sg:tags":[
        "house"
    ],
    "wof:name":"Vulcan Construction LLC",
    "wof:placetype":"venue"
},
  "geometry": {"coordinates":[-89.49030999999999,43.05642],"type":"Point"}
}