{
  "type": "Feature",
  "properties": {
    "iso:country":"US",
    "sg:address":"1810 Kellogg Ave",
    "sg:city":"Janesville",
    "sg:classifiers":[
        {
            "category":"Organizations",
            "subcategory":"Religious Organization",
            "type":"Services"
        }
    ],
    "sg:phone":"+1 608 752 7961",
    "sg:postcode":"53546",
    "sg:province":"WI",
    "sg:tags":[
        "church"
    ],
    "wof:name":"Asbury United Methodist Church",
    "wof:placetype":"venue"
},
  "geometry": {"coordinates":[-89.045985,42.649922],"type":"Point"}
}