{
  "type": "Feature",
  "properties": {
    "iso:country":"US",
    "sg:address":"2050 Riverside Dr",
    "sg:city":"Green Bay",
    "sg:classifiers":[
        {
            "category":"Professional",
            "subcategory":"Management & Consulting",
            "type":"Services"
        }
    ],
    "sg:phone":"+1 920 432 1963",
    "sg:postcode":"54301",
    "sg:province":"WI",
    "sg:tags":[
        "consultant",
        "business"
    ],
    "wof:name":"Planning Management Assoc",
    "wof:placetype":"venue"
},
  "geometry": {"coordinates":[-88.02872499999999,44.485788],"type":"Point"}
}