{
  "type": "Feature",
  "properties": {
    "addr:full":"920 17th Ave E Superior WI 54880",
    "addr:housenumber":"920",
    "addr:postcode":"54880",
    "addr:street":"17Th Ave E",
    "iso:country":"US",
    "sg:address":"920 17th Ave E",
    "sg:city":"Superior",
    "sg:classifiers":[
        {
            "category":"Health Services",
            "subcategory":"Health Practitioner",
            "type":"Services"
        }
    ],
    "sg:phone":"+1 715 398 3745",
    "sg:postcode":"54880",
    "sg:province":"WI",
    "wof:name":"Terry C Ross",
    "wof:placetype":"venue"
},
  "geometry": {"coordinates":[-92.061054,46.70755],"type":"Point"}
}