{
  "type": "Feature",
  "properties": {
    "iso:country":"US",
    "sg:address":"2945 N 89th St",
    "sg:city":"Milwaukee",
    "sg:classifiers":[
        {
            "category":"Wholesale",
            "subcategory":"Machinery & Supplies",
            "type":"Manufacturing & Wholesale Goods"
        }
    ],
    "sg:phone":"+1 414 771 0975",
    "sg:postcode":"53222",
    "sg:province":"WI",
    "sg:tags":[
        "equipment",
        "industrial"
    ],
    "wof:name":"W C Distribution",
    "wof:placetype":"venue"
},
  "geometry": {"coordinates":[-88.023852,43.072464],"type":"Point"}
}