{
  "type": "Feature",
  "properties": {
    "iso:country":"US",
    "sg:address":"1225 Fond du Lac Ave",
    "sg:city":"Kewaskum",
    "sg:classifiers":[
        {
            "category":"Professional",
            "subcategory":"Lawyer & Legal Services",
            "type":"Services"
        }
    ],
    "sg:phone":"+1 262 626 8432",
    "sg:postcode":"53040",
    "sg:province":"WI",
    "sg:tags":[
        "attorney"
    ],
    "wof:name":"Kiefer Law Office",
    "wof:placetype":"venue"
},
  "geometry": {"coordinates":[-88.228955,43.521032],"type":"Point"}
}