{
  "type": "Feature",
  "properties": {
    "iso:country":"US",
    "sg:address":"8698 Firelane 6",
    "sg:city":"Menasha",
    "sg:classifiers":[
        {
            "category":"Manufacturing",
            "subcategory":"Building Materials",
            "type":"Manufacturing & Wholesale Goods"
        }
    ],
    "sg:phone":"+1 920 954 9694",
    "sg:postcode":"54952",
    "sg:province":"WI",
    "sg:tags":[
        "mfg",
        "wood",
        "kitchen",
        "cabinet"
    ],
    "wof:name":"McClintock Cabinets",
    "wof:placetype":"venue"
},
  "geometry": {"coordinates":[-88.37216600000001,44.208432],"type":"Point"}
}