{
  "type": "Feature",
  "properties": {
    "addr:full":"242 W Capitol Dr Hartland WI 53029",
    "addr:housenumber":"242",
    "addr:postcode":"53029",
    "addr:street":"W Capitol Dr",
    "iso:country":"US",
    "sg:address":"242 W Capitol Dr",
    "sg:city":"Hartland",
    "sg:classifiers":[
        {
            "category":"Wholesale",
            "subcategory":"Auto Parts",
            "type":"Manufacturing & Wholesale Goods"
        }
    ],
    "sg:phone":"+1 262 367 1179",
    "sg:postcode":"53029",
    "sg:province":"WI",
    "wof:name":"Johnny Box LLC",
    "wof:placetype":"venue"
},
  "geometry": {"coordinates":[-88.34882899999999,43.103803],"type":"Point"}
}