{
  "type": "Feature",
  "properties": {
    "iso:country":"US",
    "sg:address":"148 McHenry St",
    "sg:city":"Burlington",
    "sg:classifiers":[
        {
            "category":"Education",
            "subcategory":"School",
            "type":"Public Place"
        }
    ],
    "sg:phone":"+1 262 763 1510",
    "sg:postcode":"53105",
    "sg:province":"WI",
    "sg:tags":[
        "elementary",
        "secondary"
    ],
    "sg:website":"www.cchsnet.org",
    "wof:name":"Catholic Central High School",
    "wof:placetype":"venue"
},
  "geometry": {"coordinates":[-88.28209699999999,42.675499],"type":"Point"}
}