{
  "type": "Feature",
  "properties": {
    "addr:full":"13531 Griffith Ave Wisconsin Rapids WI 54494",
    "addr:housenumber":"13531",
    "addr:postcode":"54494",
    "addr:street":"Griffith Ave",
    "iso:country":"US",
    "sg:address":"13531 Griffith Ave",
    "sg:city":"Wisconsin Rapids",
    "sg:classifiers":[
        {
            "category":"Farming",
            "subcategory":"Dairy Farm",
            "type":"Manufacturing & Wholesale Goods"
        }
    ],
    "sg:phone":"+1 715 424 4538",
    "sg:postcode":"54494",
    "sg:province":"WI",
    "wof:name":"Knipple Phil & Cheryl Beichel",
    "wof:placetype":"venue"
},
  "geometry": {"coordinates":[-89.610432,44.352032],"type":"Point"}
}