{
  "type": "Feature",
  "properties": {
    "iso:country":"US",
    "sg:address":"2920 Superior Ave",
    "sg:city":"Sheboygan",
    "sg:classifiers":[
        {
            "category":"Health Services",
            "subcategory":"Doctor",
            "type":"Services"
        }
    ],
    "sg:phone":"+1 920 458 0705",
    "sg:postcode":"53081",
    "sg:province":"WI",
    "sg:tags":[
        "medical"
    ],
    "wof:name":"Medical Arts",
    "wof:placetype":"venue"
},
  "geometry": {"coordinates":[-87.745702,43.761207],"type":"Point"}
}