{
  "type": "Feature",
  "properties": {
    "iso:country":"US",
    "sg:address":"306 Oneida St",
    "sg:city":"Minocqua",
    "sg:classifiers":[
        {
            "category":"Utilities",
            "subcategory":"Mobile Phone",
            "type":"Services"
        }
    ],
    "sg:phone":"+1 715 356 2330",
    "sg:postcode":"54548",
    "sg:province":"WI",
    "sg:tags":[
        "telephone",
        "cellular"
    ],
    "wof:name":"B P Cellular",
    "wof:placetype":"venue"
},
  "geometry": {"coordinates":[-89.709707,45.869727],"type":"Point"}
}