{
  "type": "Feature",
  "properties": {
    "iso:country":"US",
    "sg:address":"17465 Now Rd",
    "sg:city":"Birnamwood",
    "sg:classifiers":[
        {
            "category":"Wholesale",
            "subcategory":"Farm Supplies",
            "type":"Manufacturing & Wholesale Goods"
        }
    ],
    "sg:phone":"+1 715 623 2940",
    "sg:postcode":"54414",
    "sg:province":"WI",
    "sg:tags":[
        "buyer",
        "livestock"
    ],
    "wof:name":"Brian Lenzner Livestock",
    "wof:placetype":"venue"
},
  "geometry": {"coordinates":[-89.130599,45.029386],"type":"Point"}
}