{
  "type": "Feature",
  "properties": {
    "iso:country":"US",
    "sg:address":"642 Oconto Rd",
    "sg:city":"Mosinee",
    "sg:classifiers":[
        {
            "category":"Real Estate",
            "subcategory":"Real Estate Agent",
            "type":"Services"
        }
    ],
    "sg:phone":"+1 715 845 5208",
    "sg:postcode":"54455",
    "sg:province":"WI",
    "wof:name":"Blossom Creek LLP",
    "wof:placetype":"venue"
},
  "geometry": {"coordinates":[-89.682965,44.807892],"type":"Point"}
}