{
  "type": "Feature",
  "properties": {
    "addr:full":"2312 Jefferson St New Holstein WI 53061",
    "addr:housenumber":"2312",
    "addr:postcode":"53061",
    "addr:street":"Jefferson St",
    "iso:country":"US",
    "sg:address":"2312 Jefferson St",
    "sg:city":"New Holstein",
    "sg:classifiers":[
        {
            "category":"Wholesale",
            "subcategory":"Stationery",
            "type":"Manufacturing & Wholesale Goods"
        }
    ],
    "sg:phone":"+1 920 898 4246",
    "sg:postcode":"53061",
    "sg:province":"WI",
    "sg:tags":[
        "paper"
    ],
    "wof:name":"International Paper",
    "wof:placetype":"venue"
},
  "geometry": {"coordinates":[-88.084637,43.955254],"type":"Point"}
}