{
  "type": "Feature",
  "properties": {
    "iso:country":"US",
    "sg:address":"702 N Midvale Blvd",
    "sg:city":"Madison",
    "sg:classifiers":[
        {
            "category":"Personal",
            "subcategory":"Beauty Salon",
            "type":"Services"
        }
    ],
    "sg:phone":"+1 608 238 7154",
    "sg:postcode":"53705",
    "sg:province":"WI",
    "wof:name":"Edward's Of Hilldale",
    "wof:placetype":"venue"
},
  "geometry": {"coordinates":[-89.451208,43.074606],"type":"Point"}
}