{
  "type": "Feature",
  "properties": {
    "iso:country":"US",
    "sg:address":"1826 Harrison St",
    "sg:city":"Oshkosh",
    "sg:classifiers":[
        {
            "category":"Wholesale",
            "subcategory":"Auto Parts",
            "type":"Manufacturing & Wholesale Goods"
        }
    ],
    "sg:phone":"+1 920 235 8365",
    "sg:postcode":"54901",
    "sg:province":"WI",
    "wof:name":"Classic Engine Co",
    "wof:placetype":"venue"
},
  "geometry": {"coordinates":[-88.532581,44.040828],"type":"Point"}
}