{
  "type": "Feature",
  "properties": {
    "iso:country":"US",
    "sg:address":"112 16th Ave",
    "sg:city":"South Milwaukee",
    "sg:classifiers":[
        {
            "category":"Professional",
            "subcategory":"Computer Services",
            "type":"Services"
        }
    ],
    "sg:phone":"+1 800 257 3424",
    "sg:postcode":"53172",
    "sg:province":"WI",
    "sg:tags":[
        "related"
    ],
    "wof:name":"Network Diagnostic Clinic Inc",
    "wof:placetype":"venue"
},
  "geometry": {"coordinates":[-87.872413,42.927878],"type":"Point"}
}