{
  "type": "Feature",
  "properties": {
    "iso:country":"US",
    "sg:address":"4725 Farwell St",
    "sg:city":"Mc Farland",
    "sg:classifiers":[
        {
            "category":"Home & Garden",
            "subcategory":"Hardware",
            "type":"Retail Goods"
        }
    ],
    "sg:phone":"+1 608 838 4285",
    "sg:postcode":"53558",
    "sg:province":"WI",
    "wof:name":"Mc Farland Truevalue",
    "wof:placetype":"venue"
},
  "geometry": {"coordinates":[-89.298743,43.013122],"type":"Point"}
}