{
  "type": "Feature",
  "properties": {
    "iso:country":"US",
    "sg:address":"29816 Wilmot Rd",
    "sg:city":"Trevor",
    "sg:classifiers":[
        {
            "category":"Manufacturing",
            "subcategory":"Metals",
            "type":"Manufacturing & Wholesale Goods"
        }
    ],
    "sg:phone":"+1 262 862 7152",
    "sg:postcode":"53179",
    "sg:province":"WI",
    "sg:tags":[
        "copper",
        "foundry"
    ],
    "wof:name":"Angel Impressions",
    "wof:placetype":"venue"
},
  "geometry": {"coordinates":[-88.169816,42.510516],"type":"Point"}
}