{
  "type": "Feature",
  "properties": {
    "iso:country":"US",
    "sg:address":"1314 W Olive St",
    "sg:city":"Milwaukee",
    "sg:classifiers":[
        {
            "category":"Food & Beverages",
            "subcategory":"Groceries & Convenience Stores",
            "type":"Retail Goods"
        }
    ],
    "sg:phone":"+1 414 264 1655",
    "sg:postcode":"53209",
    "sg:province":"WI",
    "sg:tags":[
        "grocer"
    ],
    "wof:name":"Richardson S Grocery",
    "wof:placetype":"venue"
},
  "geometry": {"coordinates":[-87.925285,43.093712],"type":"Point"}
}