{
  "type": "Feature",
  "properties": {
    "addr:full":"1416 Liberty Ln Janesville WI 53545",
    "addr:housenumber":"1416",
    "addr:postcode":"53545",
    "addr:street":"Liberty Ln",
    "iso:country":"US",
    "sg:address":"1416 Liberty Ln",
    "sg:city":"Janesville",
    "sg:classifiers":[
        {
            "category":"Shopping",
            "subcategory":"Gifts & Souvenirs",
            "type":"Retail Goods"
        }
    ],
    "sg:phone":"+1 608 757 8085",
    "sg:postcode":"53545",
    "sg:province":"WI",
    "wof:name":"Millies House of Gifts",
    "wof:placetype":"venue"
},
  "geometry": {"coordinates":[-88.996286,42.702051],"type":"Point"}
}