{
  "type": "Feature",
  "properties": {
    "iso:country":"US",
    "sg:address":"125 W Maple St",
    "sg:city":"Lancaster",
    "sg:classifiers":[
        {
            "category":"Shopping",
            "subcategory":"Clothing, Apparel, & Fashions",
            "type":"Retail Goods"
        }
    ],
    "sg:phone":"+1 608 723 4700",
    "sg:postcode":"53813",
    "sg:province":"WI",
    "sg:tags":[
        "alteration"
    ],
    "sg:website":"www.walkersclothingandshoes.com",
    "wof:name":"Walker's Clothing & Shoes",
    "wof:placetype":"venue"
},
  "geometry": {"coordinates":[-90.710557,42.848033],"type":"Point"}
}