{
  "type": "Feature",
  "properties": {
    "iso:country":"US",
    "sg:address":"934 Shiloh Rd",
    "sg:city":"Sturgeon Bay",
    "sg:classifiers":[
        {
            "category":"Building & Trades",
            "subcategory":"Construction",
            "type":"Services"
        },
        {
            "category":"Mining & Drilling",
            "type":"Manufacturing & Wholesale Goods"
        }
    ],
    "sg:phone":"+1 920 743 2904",
    "sg:postcode":"54235",
    "sg:province":"WI",
    "sg:tags":[
        "product",
        "asphalt",
        "contractor",
        "sand",
        "paving",
        "blacktop",
        "gravel",
        "pit"
    ],
    "wof:name":"Bissen Blacktop Inc",
    "wof:placetype":"venue"
},
  "geometry": {"coordinates":[-87.37663999999999,44.711821],"type":"Point"}
}