{
  "type": "Feature",
  "properties": {
    "iso:country":"US",
    "sg:address":"10625 W North Ave",
    "sg:city":"Milwaukee",
    "sg:classifiers":[
        {
            "category":"Health Services",
            "subcategory":"Health Practitioner",
            "type":"Services"
        }
    ],
    "sg:phone":"+1 414 453 8800",
    "sg:postcode":"53226",
    "sg:province":"WI",
    "sg:tags":[
        "nurse",
        "registry"
    ],
    "sg:website":"www.bestnurseusa.com",
    "wof:name":"Bestnurse USA",
    "wof:placetype":"venue"
},
  "geometry": {"coordinates":[-88.045869,43.060071],"type":"Point"}
}