{
  "type": "Feature",
  "properties": {
    "iso:country":"US",
    "sg:address":"126 N Main St",
    "sg:city":"Fond Du Lac",
    "sg:classifiers":[
        {
            "category":"Government",
            "subcategory":"Office",
            "type":"Public Place"
        }
    ],
    "sg:phone":"+1 920 929 3223",
    "sg:postcode":"54935",
    "sg:province":"WI",
    "sg:tags":[
        "executive"
    ],
    "wof:name":"Investigating Follow Up",
    "wof:placetype":"venue"
},
  "geometry": {"coordinates":[-88.446987,43.783567],"type":"Point"}
}