{
  "type": "Feature",
  "properties": {
    "addr:full":"161 W Wisconsin Ave Milwaukee WI 53233",
    "addr:housenumber":"161",
    "addr:postcode":"53233",
    "addr:street":"W Wisconsin Ave",
    "iso:country":"US",
    "sg:address":"161 W Wisconsin Ave",
    "sg:city":"Milwaukee",
    "sg:classifiers":[
        {
            "category":"Museum",
            "type":"Entertainment"
        }
    ],
    "sg:phone":"+1 414 319 0848",
    "sg:postcode":"53233",
    "sg:province":"WI",
    "sg:website":"www.clownmuseum.org",
    "wof:name":"Intl Clown Hall Of Fame",
    "wof:placetype":"venue"
},
  "geometry": {"coordinates":[-87.912379,43.038649],"type":"Point"}
}