{
  "type": "Feature",
  "properties": {
    "iso:country":"US",
    "sg:address":"7609 Airport Rd",
    "sg:city":"Waterloo",
    "sg:classifiers":[
        {
            "category":"Shopping",
            "subcategory":"Books",
            "type":"Retail Goods"
        }
    ],
    "sg:phone":"+1 920 478 3644",
    "sg:postcode":"53594",
    "sg:province":"WI",
    "wof:name":"James Hyer Bookseller",
    "wof:placetype":"venue"
},
  "geometry": {"coordinates":[-88.985379,43.116763],"type":"Point"}
}