{
  "type": "Feature",
  "properties": {
    "addr:full":"2202 W Mequon Rd Mequon WI 53092",
    "addr:housenumber":"2202",
    "addr:postcode":"53092",
    "addr:street":"W Mequon Rd",
    "iso:country":"US",
    "sg:address":"2202 W Mequon Rd",
    "sg:city":"Mequon",
    "sg:classifiers":[
        {
            "category":"Autos & Motor Vehicles",
            "subcategory":"Automobile Sales",
            "type":"Retail Goods"
        }
    ],
    "sg:phone":"+1 262 242 2213",
    "sg:postcode":"53092",
    "sg:province":"WI",
    "sg:tags":[
        "car",
        "dealer"
    ],
    "wof:name":"Fasco AC Motors",
    "wof:placetype":"venue"
},
  "geometry": {"coordinates":[-87.934394,43.221395],"type":"Point"}
}