{
  "type": "Feature",
  "properties": {
    "addr:full":"4808 N Hopkins St Milwaukee WI 53209",
    "addr:housenumber":"4808",
    "addr:postcode":"53209",
    "addr:street":"N Hopkins St",
    "iso:country":"US",
    "sg:address":"4808 N Hopkins St",
    "sg:city":"Milwaukee",
    "sg:classifiers":[
        {
            "category":"Shopping",
            "subcategory":"Pharmacy",
            "type":"Retail Goods"
        }
    ],
    "sg:phone":"+1 414 462 4601",
    "sg:postcode":"53209",
    "sg:province":"WI",
    "wof:name":"Walgreens",
    "wof:placetype":"venue"
},
  "geometry": {"coordinates":[-87.960626,43.106307],"type":"Point"}
}