{
  "type": "Feature",
  "properties": {
    "iso:country":"US",
    "sg:address":"1365 W Pleasant Valley Rd",
    "sg:city":"West Bend",
    "sg:classifiers":[
        {
            "category":"Shopping",
            "subcategory":"Bicycles & Sporting Goods",
            "type":"Retail Goods"
        }
    ],
    "sg:phone":"+1 262 675 6442",
    "sg:postcode":"53095",
    "sg:province":"WI",
    "wof:name":"Sundown View Ranch",
    "wof:placetype":"venue"
},
  "geometry": {"coordinates":[-88.107867,43.351846],"type":"Point"}
}