{
  "type": "Feature",
  "properties": {
    "iso:country":"US",
    "sg:address":"121 Green St",
    "sg:city":"Belleville",
    "sg:classifiers":[
        {
            "category":"Building & Trades",
            "subcategory":"Electrical",
            "type":"Services"
        }
    ],
    "sg:phone":"+1 608 424 3030",
    "sg:postcode":"53508",
    "sg:province":"WI",
    "sg:tags":[
        "electric",
        "contractor"
    ],
    "wof:name":"Short Electric",
    "wof:placetype":"venue"
},
  "geometry": {"coordinates":[-89.53532300000001,42.858557],"type":"Point"}
}