{
  "type": "Feature",
  "properties": {
    "addr:full":"4433 S 27th St Milwaukee WI 53221",
    "addr:housenumber":"4433",
    "addr:postcode":"53221",
    "addr:street":"S 27Th St",
    "iso:country":"US",
    "sg:address":"4433 S 27th St",
    "sg:city":"Milwaukee",
    "sg:classifiers":[
        {
            "category":"Insurance",
            "subcategory":"Hazard Insurance",
            "type":"Services"
        },
        {
            "category":"Insurance",
            "subcategory":"Insurance Agent",
            "type":"Services"
        },
        {
            "category":"Insurance",
            "subcategory":"Title Insurance",
            "type":"Services"
        },
        {
            "category":"Insurance",
            "subcategory":"Life Insurance",
            "type":"Services"
        },
        {
            "category":"Banks & Credit Unions",
            "subcategory":"Financial Services",
            "type":"Services"
        }
    ],
    "sg:phone":"+1 414 423 2180",
    "sg:postcode":"53221",
    "sg:province":"WI",
    "sg:tags":[
        "auto",
        "retirement",
        "plan",
        "annuity",
        "homeowner"
    ],
    "sg:website":"http://www.autoclubgroup.com/wisconsin/index.aspx?campaign=local_wi_yellow",
    "wof:name":"AAA",
    "wof:placetype":"venue"
},
  "geometry": {"coordinates":[-87.948786,42.964371],"type":"Point"}
}