{
  "type": "Feature",
  "properties": {
    "iso:country":"US",
    "sg:address":"216 W Water St",
    "sg:city":"Shullsburg",
    "sg:classifiers":[
        {
            "category":"Insurance",
            "subcategory":"Insurance Agent",
            "type":"Services"
        }
    ],
    "sg:phone":"+1 608 965 3031",
    "sg:postcode":"53586",
    "sg:province":"WI",
    "wof:name":"Woodworth Insurance Group",
    "wof:placetype":"venue"
},
  "geometry": {"coordinates":[-90.23357799999999,42.572748],"type":"Point"}
}