{
  "type": "Feature",
  "properties": {
    "iso:country":"US",
    "sg:address":"12501 W Bluemound Rd",
    "sg:city":"Brookfield",
    "sg:classifiers":[
        {
            "category":"Shopping",
            "subcategory":"Used Merchandise",
            "type":"Retail Goods"
        }
    ],
    "sg:phone":"+1 262 784 7836",
    "sg:postcode":"53005",
    "sg:province":"WI",
    "sg:tags":[
        "antique"
    ],
    "wof:name":"Great Finds Consignments",
    "wof:placetype":"venue"
},
  "geometry": {"coordinates":[-88.06931400000001,43.036226],"type":"Point"}
}