{
  "type": "Feature",
  "properties": {
    "iso:country":"US",
    "sg:address":"5261 Hillcrest Dr",
    "sg:city":"Plymouth",
    "sg:classifiers":[
        {
            "category":"Building & Trades",
            "subcategory":"Plumbing",
            "type":"Services"
        }
    ],
    "sg:phone":"+1 920 892 2880",
    "sg:postcode":"53073",
    "sg:province":"WI",
    "sg:tags":[
        "septic"
    ],
    "wof:name":"Den-Bec Inc",
    "wof:placetype":"venue"
},
  "geometry": {"coordinates":[-88.060819,43.729521],"type":"Point"}
}