{
  "type": "Feature",
  "properties": {
    "iso:country":"US",
    "sg:address":"2717 60th St",
    "sg:city":"Kenosha",
    "sg:classifiers":[
        {
            "category":"Bars & Pubs",
            "type":"Food & Drink"
        }
    ],
    "sg:phone":"+1 262 654 8837",
    "sg:postcode":"53140",
    "sg:province":"WI",
    "wof:name":"Mc Fibber's Pub",
    "wof:placetype":"venue"
},
  "geometry": {"coordinates":[-87.841632,42.580708],"type":"Point"}
}