{
  "type": "Feature",
  "properties": {
    "iso:country":"US",
    "sg:address":"2608 E Racine St",
    "sg:city":"Janesville",
    "sg:classifiers":[
        {
            "category":"Real Estate",
            "subcategory":"Real Estate Operator",
            "type":"Services"
        }
    ],
    "sg:phone":"+1 608 758 9362",
    "sg:postcode":"53545",
    "sg:province":"WI",
    "sg:tags":[
        "building",
        "apartment"
    ],
    "wof:name":"Arrowhead Point Apartments",
    "wof:placetype":"venue"
},
  "geometry": {"coordinates":[-88.987963,42.671884],"type":"Point"}
}