{
  "type": "Feature",
  "properties": {
    "addr:full":"23 Springbrook Circle Dr Appleton WI 54914",
    "addr:housenumber":"23",
    "addr:postcode":"54914",
    "addr:street":"Springbrook Circle Dr",
    "iso:country":"US",
    "sg:address":"23 Springbrook Circle Dr",
    "sg:city":"Appleton",
    "sg:classifiers":[
        {
            "category":"Professional",
            "subcategory":"Computer Services",
            "type":"Services"
        }
    ],
    "sg:phone":"+1 920 997 0003",
    "sg:postcode":"54914",
    "sg:province":"WI",
    "sg:tags":[
        "information",
        "consulting",
        "technology"
    ],
    "wof:name":"Ciber Inc",
    "wof:placetype":"venue"
},
  "geometry": {"coordinates":[-88.47126799999999,44.256752],"type":"Point"}
}