{
  "type": "Feature",
  "properties": {
    "iso:country":"US",
    "sg:address":"7376 Hospital Rd",
    "sg:city":"Elkhorn",
    "sg:classifiers":[
        {
            "category":"Farming",
            "subcategory":"Dairy Farm",
            "type":"Manufacturing & Wholesale Goods"
        }
    ],
    "sg:phone":"+1 262 723 3165",
    "sg:postcode":"53121",
    "sg:province":"WI",
    "wof:name":"Richard A Finster",
    "wof:placetype":"venue"
},
  "geometry": {"coordinates":[-88.418419,42.654812],"type":"Point"}
}