{
  "type": "Feature",
  "properties": {
    "iso:country":"US",
    "sg:address":"6205 241st Ave",
    "sg:city":"Salem",
    "sg:classifiers":[
        {
            "category":"Building & Trades",
            "subcategory":"Construction",
            "type":"Services"
        }
    ],
    "sg:phone":"+1 262 843 3501",
    "sg:postcode":"53168",
    "sg:province":"WI",
    "sg:tags":[
        "concrete",
        "contractor"
    ],
    "wof:name":"Westosha Concrete",
    "wof:placetype":"venue"
},
  "geometry": {"coordinates":[-88.100943,42.580083],"type":"Point"}
}