{
  "type": "Feature",
  "properties": {
    "iso:country":"US",
    "sg:address":"5850 Schudy Rd",
    "sg:city":"Wisconsin Rapids",
    "sg:classifiers":[
        {
            "category":"Farming",
            "subcategory":"Farm",
            "type":"Manufacturing & Wholesale Goods"
        }
    ],
    "sg:phone":"+1 715 421 0121",
    "sg:postcode":"54495",
    "sg:province":"WI",
    "sg:tags":[
        "crop",
        "general"
    ],
    "wof:name":"Kimmet Farms",
    "wof:placetype":"venue"
},
  "geometry": {"coordinates":[-89.877719,44.453347],"type":"Point"}
}