{
  "type": "Feature",
  "properties": {
    "iso:country":"US",
    "sg:address":"6060 N Ironwood Ln",
    "sg:city":"Milwaukee",
    "sg:classifiers":[
        {
            "category":"Shopping",
            "subcategory":"Pharmacy",
            "type":"Retail Goods"
        }
    ],
    "sg:phone":"+1 414 961 8899",
    "sg:postcode":"53217",
    "sg:province":"WI",
    "wof:name":"Crestwood Pharmacy Inc",
    "wof:placetype":"venue"
},
  "geometry": {"coordinates":[-87.918194,43.126204],"type":"Point"}
}