{
  "type": "Feature",
  "properties": {
    "iso:country":"US",
    "sg:address":"409 Technology Dr W",
    "sg:city":"Menomonie",
    "sg:classifiers":[
        {
            "category":"Manufacturing",
            "subcategory":"Rubber & Plastics",
            "type":"Manufacturing & Wholesale Goods"
        }
    ],
    "sg:phone":"+1 715 232 4800",
    "sg:postcode":"54751",
    "sg:province":"WI",
    "sg:tags":[
        "product",
        "mfg"
    ],
    "wof:name":"Medical Molding Building 1",
    "wof:placetype":"venue"
},
  "geometry": {"coordinates":[-91.89900299999999,44.880767],"type":"Point"}
}