{
  "type": "Feature",
  "properties": {
    "iso:country":"US",
    "sg:address":"129 E Chestnut St",
    "sg:city":"Burlington",
    "sg:classifiers":[
        {
            "category":"Shopping",
            "subcategory":"Antiques",
            "type":"Retail Goods"
        }
    ],
    "sg:phone":"+1 262 767 9390",
    "sg:postcode":"53105",
    "sg:province":"WI",
    "wof:name":"Shy Violet Antiques & Collectibles",
    "wof:placetype":"venue"
},
  "geometry": {"coordinates":[-88.277199,42.680099],"type":"Point"}
}