{
  "type": "Feature",
  "properties": {
    "addr:full":"2796 Florann Dr Fitchburg WI 53711",
    "addr:housenumber":"2796",
    "addr:postcode":"53711",
    "addr:street":"Florann Dr",
    "iso:country":"US",
    "sg:address":"2796 Florann Dr",
    "sg:city":"Fitchburg",
    "sg:classifiers":[
        {
            "category":"Wholesale",
            "subcategory":"Machinery & Supplies",
            "type":"Manufacturing & Wholesale Goods"
        }
    ],
    "sg:phone":"+1 608 274 6585",
    "sg:postcode":"53711",
    "sg:province":"WI",
    "wof:name":"Bacon & Bacon",
    "wof:placetype":"venue"
},
  "geometry": {"coordinates":[-89.430538,43.00603],"type":"Point"}
}