{
  "type": "Feature",
  "properties": {
    "iso:country":"US",
    "sg:address":"4225 W Peck Pl",
    "sg:city":"Milwaukee",
    "sg:classifiers":[
        {
            "category":"Social Services",
            "subcategory":"Child Care",
            "type":"Services"
        }
    ],
    "sg:phone":"+1 414 540 6569",
    "sg:postcode":"53209",
    "sg:province":"WI",
    "sg:tags":[
        "day"
    ],
    "wof:name":"Stones In Home Day Care",
    "wof:placetype":"venue"
},
  "geometry": {"coordinates":[-87.96643400000001,43.10159],"type":"Point"}
}