{
  "type": "Feature",
  "properties": {
    "iso:country":"US",
    "sg:address":"217 S Hamilton St",
    "sg:city":"Madison",
    "sg:classifiers":[
        {
            "category":"Professional",
            "subcategory":"Management & Consulting",
            "type":"Services"
        }
    ],
    "sg:phone":"+1 608 255 7211",
    "sg:postcode":"53703",
    "sg:province":"WI",
    "sg:tags":[
        "counselor",
        "public",
        "relations"
    ],
    "wof:name":"Alice O'Connor Co",
    "wof:placetype":"venue"
},
  "geometry": {"coordinates":[-89.384203,43.070692],"type":"Point"}
}