{
  "type": "Feature",
  "properties": {
    "addr:full":"6414 Copps Ave Monona WI 53716",
    "addr:housenumber":"6414",
    "addr:postcode":"53716",
    "addr:street":"Copps Ave",
    "iso:country":"US",
    "sg:address":"6414 Copps Ave",
    "sg:city":"Monona",
    "sg:classifiers":[
        {
            "category":"Wholesale",
            "subcategory":"Electrical",
            "type":"Manufacturing & Wholesale Goods"
        }
    ],
    "sg:phone":"+1 608 661 5555",
    "sg:postcode":"53716",
    "sg:province":"WI",
    "sg:tags":[
        "lighting",
        "fixture"
    ],
    "wof:name":"Energy Performance Specilaists",
    "wof:placetype":"venue"
},
  "geometry": {"coordinates":[-89.310653,43.048365],"type":"Point"}
}