{
  "type": "Feature",
  "properties": {
    "iso:country":"US",
    "sg:address":"1121 11th St S",
    "sg:city":"Wisconsin Rapids",
    "sg:classifiers":[
        {
            "category":"Retail",
            "subcategory":"Animal Services",
            "type":"Services"
        }
    ],
    "sg:phone":"+1 715 421 4404",
    "sg:postcode":"54494",
    "sg:province":"WI",
    "wof:name":"Heathers Best Care Pet Sittin",
    "wof:placetype":"venue"
},
  "geometry": {"coordinates":[-89.813185,44.381628],"type":"Point"}
}