{
  "type": "Feature",
  "properties": {
    "addr:full":"307 N Court St Sparta WI 54656",
    "addr:housenumber":"307",
    "addr:postcode":"54656",
    "addr:street":"N Court St",
    "iso:country":"US",
    "sg:address":"307 N Court St",
    "sg:city":"Sparta",
    "sg:classifiers":[
        {
            "category":"Real Estate",
            "subcategory":"Real Estate Operator",
            "type":"Services"
        }
    ],
    "sg:phone":"+1 608 269 2188",
    "sg:postcode":"54656",
    "sg:province":"WI",
    "sg:tags":[
        "apartment"
    ],
    "wof:name":"Brookside Apts",
    "wof:placetype":"venue"
},
  "geometry": {"coordinates":[-90.814403,43.949786],"type":"Point"}
}