{
  "type": "Feature",
  "properties": {
    "addr:full":"14425 Watertown Plank Rd Elm Grove WI 53122",
    "addr:housenumber":"14425",
    "addr:postcode":"53122",
    "addr:street":"Watertown Plank Rd",
    "iso:country":"US",
    "sg:address":"14425 Watertown Plank Rd",
    "sg:city":"Elm Grove",
    "sg:classifiers":[
        {
            "category":"Wholesale",
            "subcategory":"Computers",
            "type":"Manufacturing & Wholesale Goods"
        }
    ],
    "sg:phone":"+1 262 786 1438",
    "sg:postcode":"53122",
    "sg:province":"WI",
    "wof:name":"Tim R Wroblewski",
    "wof:placetype":"venue"
},
  "geometry": {"coordinates":[-88.09371400000001,43.039529],"type":"Point"}
}