{
  "type": "Feature",
  "properties": {
    "addr:full":"2742 Hillside Dr Delafield WI 53018",
    "addr:housenumber":"2742",
    "addr:postcode":"53018",
    "addr:street":"Hillside Dr",
    "iso:country":"US",
    "sg:address":"2742 Hillside Dr",
    "sg:city":"Delafield",
    "sg:classifiers":[
        {
            "category":"Restaurant",
            "type":"Food & Drink"
        },
        {
            "category":"Ice Cream",
            "type":"Food & Drink"
        }
    ],
    "sg:menulink":"http://www.allmenus.com/wi/delafield/184491-cold-stone-creamery/menu/",
    "sg:phone":"+1 262 646 5759",
    "sg:postcode":"53018",
    "sg:province":"WI",
    "sg:tags":[
        "smoothy",
        "juice",
        "american",
        "ice",
        "cream"
    ],
    "wof:name":"Cold Stone Creamery",
    "wof:placetype":"venue"
},
  "geometry": {"coordinates":[-88.37295399999999,43.047381],"type":"Point"}
}