{
  "type": "Feature",
  "properties": {
    "iso:country":"US",
    "sg:address":"11707 W North Ave",
    "sg:city":"Milwaukee",
    "sg:classifiers":[
        {
            "category":"Professional",
            "subcategory":"Accounting & Tax Preparation",
            "type":"Services"
        }
    ],
    "sg:phone":"+1 414 771 9611",
    "sg:postcode":"53226",
    "sg:province":"WI",
    "sg:tags":[
        "public",
        "accountants-certified"
    ],
    "sg:website":"http://www.brayco.com",
    "wof:name":"Bray & Company Cpas",
    "wof:placetype":"venue"
},
  "geometry": {"coordinates":[-88.058903,43.059959],"type":"Point"}
}