{
  "type": "Feature",
  "properties": {
    "iso:country":"US",
    "sg:address":"1846 State Rd 83",
    "sg:city":"Hartford",
    "sg:classifiers":[
        {
            "category":"Government",
            "subcategory":"Office",
            "type":"Public Place"
        }
    ],
    "sg:phone":"+1 262 673 0970",
    "sg:postcode":"53027",
    "sg:province":"WI",
    "sg:tags":[
        "village"
    ],
    "wof:name":"Erin Building Inspector",
    "wof:placetype":"venue"
},
  "geometry": {"coordinates":[-88.370833,43.253326],"type":"Point"}
}