{
  "type": "Feature",
  "properties": {
    "iso:country":"US",
    "sg:address":"6203 Sauk Trail Rd",
    "sg:city":"Belgium",
    "sg:classifiers":[
        {
            "category":"Farming",
            "subcategory":"Farm",
            "type":"Manufacturing & Wholesale Goods"
        }
    ],
    "sg:phone":"+1 262 285 3836",
    "sg:postcode":"53004",
    "sg:province":"WI",
    "sg:tags":[
        "crop",
        "general"
    ],
    "wof:name":"Lakeshore Farms LLC",
    "wof:placetype":"venue"
},
  "geometry": {"coordinates":[-87.801066,43.501335],"type":"Point"}
}