{
  "type": "Feature",
  "properties": {
    "iso:country":"US",
    "sg:address":"7404 Co Rd Z",
    "sg:city":"Custer",
    "sg:classifiers":[
        {
            "category":"Food & Beverages",
            "subcategory":"Groceries & Convenience Stores",
            "type":"Retail Goods"
        }
    ],
    "sg:phone":"+1 715 592 4242",
    "sg:postcode":"54423",
    "sg:province":"WI",
    "sg:tags":[
        "drinking"
    ],
    "wof:name":"Ernie & Irene Star & Tavern",
    "wof:placetype":"venue"
},
  "geometry": {"coordinates":[-89.415446,44.569839],"type":"Point"}
}