{
  "type": "Feature",
  "properties": {
    "iso:country":"US",
    "sg:address":"1852 Grace St",
    "sg:city":"De Pere",
    "sg:classifiers":[
        {
            "category":"Organizations",
            "subcategory":"Religious Organization",
            "type":"Services"
        }
    ],
    "sg:phone":"+1 920 338 9622",
    "sg:postcode":"54115",
    "sg:province":"WI",
    "sg:tags":[
        "church"
    ],
    "wof:name":"Powerlink Ministries Inc",
    "wof:placetype":"venue"
},
  "geometry": {"coordinates":[-88.044677,44.437698],"type":"Point"}
}