{
  "type": "Feature",
  "properties": {
    "iso:country":"US",
    "sg:address":"2050 Knob Rd",
    "sg:city":"Burlington",
    "sg:classifiers":[
        {
            "category":"Manufacturing",
            "subcategory":"Tools & Machinery",
            "type":"Manufacturing & Wholesale Goods"
        }
    ],
    "sg:phone":"+1 262 763 4306",
    "sg:postcode":"53105",
    "sg:province":"WI",
    "sg:tags":[
        "equipment",
        "lighting",
        "mfg"
    ],
    "wof:name":"Mediahouse Productions",
    "wof:placetype":"venue"
},
  "geometry": {"coordinates":[-88.325689,42.625112],"type":"Point"}
}