{
  "type": "Feature",
  "properties": {
    "iso:country":"US",
    "sg:address":"485 Lienke Rd",
    "sg:city":"Columbus",
    "sg:classifiers":[
        {
            "category":"Building & Trades",
            "subcategory":"Construction",
            "type":"Services"
        }
    ],
    "sg:phone":"+1 920 484 3849",
    "sg:postcode":"53925",
    "sg:province":"WI",
    "sg:tags":[
        "house"
    ],
    "wof:name":"Timberstone LLC",
    "wof:placetype":"venue"
},
  "geometry": {"coordinates":[-89.028917,43.392977],"type":"Point"}
}