{
  "type": "Feature",
  "properties": {
    "addr:full":"1898 Cypress Dr Grafton WI 53024",
    "addr:housenumber":"1898",
    "addr:postcode":"53024",
    "addr:street":"Cypress Dr",
    "iso:country":"US",
    "sg:address":"1898 Cypress Dr",
    "sg:city":"Grafton",
    "sg:classifiers":[
        {
            "category":"Education",
            "subcategory":"Library",
            "type":"Public Place"
        }
    ],
    "sg:phone":"+1 262 375 2604",
    "sg:postcode":"53024",
    "sg:province":"WI",
    "wof:name":"Library Duplex LLC",
    "wof:placetype":"venue"
},
  "geometry": {"coordinates":[-87.94049099999999,43.311402],"type":"Point"}
}