{
  "type": "Feature",
  "properties": {
    "addr:full":"13215 38th St Kenosha WI 53144",
    "addr:housenumber":"13215",
    "addr:postcode":"53144",
    "addr:street":"38Th St",
    "iso:country":"US",
    "sg:address":"13215 38th St",
    "sg:city":"Kenosha",
    "sg:phone":"+1 262 859 2583",
    "sg:postcode":"53144",
    "sg:province":"WI",
    "sg:tags":[
        "farm",
        "corn",
        "soybean"
    ],
    "wof:name":"Joe Kolnik",
    "wof:placetype":"venue"
},
  "geometry": {"coordinates":[-87.968503,42.604146],"type":"Point"}
}