{
  "type": "Feature",
  "properties": {
    "addr:full":"1241 S 54th St Milwaukee WI 53214",
    "addr:housenumber":"1241",
    "addr:postcode":"53214",
    "addr:street":"S 54Th St",
    "iso:country":"US",
    "sg:address":"1241 S 54th St",
    "sg:city":"Milwaukee",
    "sg:classifiers":[
        {
            "category":"Professional",
            "type":"Services"
        }
    ],
    "sg:phone":"+1 414 672 1262",
    "sg:postcode":"53214",
    "sg:province":"WI",
    "wof:name":"Df III LLC",
    "wof:placetype":"venue"
},
  "geometry": {"coordinates":[-87.980344,43.017192],"type":"Point"}
}