{
  "type": "Feature",
  "properties": {
    "addr:full":"148 East Ln Belgium WI 53004",
    "addr:housenumber":"148",
    "addr:postcode":"53004",
    "addr:street":"East Ln",
    "iso:country":"US",
    "sg:address":"148 East Ln",
    "sg:city":"Belgium",
    "sg:classifiers":[
        {
            "category":"Personal",
            "subcategory":"Beauty Salon",
            "type":"Services"
        }
    ],
    "sg:phone":"+1 262 285 3933",
    "sg:postcode":"53004",
    "sg:province":"WI",
    "sg:tags":[
        "shop"
    ],
    "wof:name":"Shear Design Styling Salon",
    "wof:placetype":"venue"
},
  "geometry": {"coordinates":[-87.84137200000001,43.500942],"type":"Point"}
}