{
  "type": "Feature",
  "properties": {
    "iso:country":"US",
    "sg:address":"607 E 2nd St",
    "sg:city":"Owen",
    "sg:classifiers":[
        {
            "category":"Shopping",
            "subcategory":"Computers & Home Electronics",
            "type":"Retail Goods"
        }
    ],
    "sg:phone":"+1 715 229 9696",
    "sg:postcode":"54460",
    "sg:province":"WI",
    "wof:name":"Computer Works Central",
    "wof:placetype":"venue"
},
  "geometry": {"coordinates":[-90.556922,44.946824],"type":"Point"}
}