{
  "type": "Feature",
  "properties": {
    "addr:full":"11940 W Ripley Ave Milwaukee WI 53226",
    "addr:housenumber":"11940",
    "addr:postcode":"53226",
    "addr:street":"W Ripley Ave",
    "iso:country":"US",
    "sg:address":"11940 W Ripley Ave",
    "sg:city":"Milwaukee",
    "sg:classifiers":[
        {
            "category":"Building & Trades",
            "subcategory":"Construction",
            "type":"Services"
        },
        {
            "category":"Building & Trades",
            "subcategory":"Electrical",
            "type":"Services"
        }
    ],
    "sg:phone":"+1 414 771 0685",
    "sg:postcode":"53226",
    "sg:province":"WI",
    "sg:tags":[
        "flameproofing",
        "fireproofing"
    ],
    "wof:name":"Milwaukee Office",
    "wof:placetype":"venue"
},
  "geometry": {"coordinates":[-88.06177,43.032272],"type":"Point"}
}