{
  "type": "Feature",
  "properties": {
    "iso:country":"US",
    "sg:address":"1500 Highland Ave",
    "sg:city":"Madison",
    "sg:classifiers":[
        {
            "category":"Health Services",
            "subcategory":"Doctor",
            "type":"Services"
        }
    ],
    "sg:phone":"+1 608 263 2522",
    "sg:postcode":"53792",
    "sg:province":"WI",
    "sg:tags":[
        "clinic"
    ],
    "wof:name":"Communication Aids & Systems",
    "wof:placetype":"venue"
},
  "geometry": {"coordinates":[-89.431922,43.078764],"type":"Point"}
}