{
  "type": "Feature",
  "properties": {
    "addr:full":"4203 Shady Rd Black Creek WI 54106",
    "addr:housenumber":"4203",
    "addr:postcode":"54106",
    "addr:street":"Shady Rd",
    "iso:country":"US",
    "sg:address":"4203 Shady Rd",
    "sg:city":"Black Creek",
    "sg:classifiers":[
        {
            "category":"Farming",
            "subcategory":"Dairy Farm",
            "type":"Manufacturing & Wholesale Goods"
        }
    ],
    "sg:phone":"+1 920 833 7507",
    "sg:postcode":"54106",
    "sg:province":"WI",
    "wof:name":"Craig Krohlow",
    "wof:placetype":"venue"
},
  "geometry": {"coordinates":[-88.40410900000001,44.588547],"type":"Point"}
}