{
  "type": "Feature",
  "properties": {
    "addr:full":"1411 Hacienda Ln Cedarburg WI 53012",
    "addr:housenumber":"1411",
    "addr:postcode":"53012",
    "addr:street":"Hacienda Ln",
    "iso:country":"US",
    "sg:address":"1411 Hacienda Ln",
    "sg:city":"Cedarburg",
    "sg:classifiers":[
        {
            "category":"Building & Trades",
            "subcategory":"Construction",
            "type":"Services"
        }
    ],
    "sg:phone":"+1 262 677 0770",
    "sg:postcode":"53012",
    "sg:province":"WI",
    "sg:tags":[
        "carpentry",
        "contractor"
    ],
    "wof:name":"M H Carpentry",
    "wof:placetype":"venue"
},
  "geometry": {"coordinates":[-88.107303,43.296494],"type":"Point"}
}