{
  "type": "Feature",
  "properties": {
    "iso:country":"US",
    "sg:address":"996 Tarrant Dr",
    "sg:city":"Fontana",
    "sg:classifiers":[
        {
            "category":"Professional",
            "subcategory":"Engineering",
            "type":"Services"
        }
    ],
    "sg:phone":"+1 262 275 5572",
    "sg:postcode":"53125",
    "sg:province":"WI",
    "sg:tags":[
        "engineer"
    ],
    "wof:name":"Scire Corp",
    "wof:placetype":"venue"
},
  "geometry": {"coordinates":[-88.578412,42.537467],"type":"Point"}
}