{
  "type": "Feature",
  "properties": {
    "iso:country":"US",
    "sg:address":"3913 W Prospect Ave",
    "sg:city":"Appleton",
    "sg:classifiers":[
        {
            "category":"Travel",
            "subcategory":"Hotels & Motels",
            "type":"Entertainment"
        }
    ],
    "sg:phone":"+1 920 969 1369",
    "sg:postcode":"54914",
    "sg:province":"WI",
    "sg:tags":[
        "operation"
    ],
    "wof:name":"Ganesh LLC",
    "wof:placetype":"venue"
},
  "geometry": {"coordinates":[-88.46509,44.243726],"type":"Point"}
}