{
  "type": "Feature",
  "properties": {
    "addr:full":"204 Highland St Mount Horeb WI 53572",
    "addr:housenumber":"204",
    "addr:postcode":"53572",
    "addr:street":"Highland St",
    "iso:country":"US",
    "sg:address":"204 Highland St",
    "sg:city":"Mount Horeb",
    "sg:classifiers":[
        {
            "category":"Freight",
            "type":"Transportation"
        }
    ],
    "sg:phone":"+1 608 437 6391",
    "sg:postcode":"53572",
    "sg:province":"WI",
    "sg:tags":[
        "operator",
        "local",
        "trucking"
    ],
    "wof:name":"Edseth Trucking",
    "wof:placetype":"venue"
},
  "geometry": {"coordinates":[-89.74416100000001,43.012014],"type":"Point"}
}