{
  "type": "Feature",
  "properties": {
    "iso:country":"US",
    "sg:address":"1721 3rd St W",
    "sg:city":"Ashland",
    "sg:classifiers":[
        {
            "category":"Building & Trades",
            "subcategory":"Construction",
            "type":"Services"
        }
    ],
    "sg:phone":"+1 715 682 4884",
    "sg:postcode":"54806",
    "sg:province":"WI",
    "sg:tags":[
        "excavating",
        "contractor"
    ],
    "wof:name":"Ashland Construction Co",
    "wof:placetype":"venue"
},
  "geometry": {"coordinates":[-90.90247599999999,46.581892],"type":"Point"}
}