{
  "type": "Feature",
  "properties": {
    "iso:country":"US",
    "sg:address":"7640 W Forest Home Ave",
    "sg:city":"Milwaukee",
    "sg:classifiers":[
        {
            "category":"Personal",
            "type":"Services"
        }
    ],
    "sg:phone":"+1 414 543 7744",
    "sg:postcode":"53220",
    "sg:province":"WI",
    "sg:tags":[
        "banquet",
        "hall",
        "catering"
    ],
    "wof:name":"Barbeques & Catrg By Rakovich",
    "wof:placetype":"venue"
},
  "geometry": {"coordinates":[-88.010498,42.962313],"type":"Point"}
}