{
  "type": "Feature",
  "properties": {
    "iso:country":"US",
    "sg:address":"4902 Co Rd Hh",
    "sg:city":"Mauston",
    "sg:classifiers":[
        {
            "category":"Bars & Pubs",
            "type":"Food & Drink"
        }
    ],
    "sg:phone":"+1 608 847 5209",
    "sg:postcode":"53948",
    "sg:province":"WI",
    "sg:tags":[
        "drinking"
    ],
    "wof:name":"Way Station",
    "wof:placetype":"venue"
},
  "geometry": {"coordinates":[-89.937709,43.814297],"type":"Point"}
}