{
  "type": "Feature",
  "properties": {
    "iso:country":"US",
    "sg:address":"4606 Golf Rd",
    "sg:city":"Eau Claire",
    "sg:classifiers":[
        {
            "category":"Shopping",
            "subcategory":"Department Store",
            "type":"Retail Goods"
        }
    ],
    "sg:phone":"+1 715 833 5000",
    "sg:postcode":"54701",
    "sg:province":"WI",
    "wof:name":"Marshall Field's",
    "wof:placetype":"venue"
},
  "geometry": {"coordinates":[-91.447989,44.77081],"type":"Point"}
}