{
  "type": "Feature",
  "properties": {
    "iso:country":"US",
    "sg:address":"304 S Main St",
    "sg:city":"Viroqua",
    "sg:classifiers":[
        {
            "category":"Insurance",
            "subcategory":"Insurance Agent",
            "type":"Services"
        }
    ],
    "sg:phone":"+1 608 637 2170",
    "sg:postcode":"54665",
    "sg:province":"WI",
    "wof:name":"State Farm Insurance",
    "wof:placetype":"venue"
},
  "geometry": {"coordinates":[-90.889383,43.553985],"type":"Point"}
}