{
  "type": "Feature",
  "properties": {
    "iso:country":"US",
    "sg:address":"2006 N 117th St",
    "sg:city":"Milwaukee",
    "sg:classifiers":[
        {
            "category":"Professional",
            "subcategory":"Lawyer & Legal Services",
            "type":"Services"
        }
    ],
    "sg:phone":"+1 414 443 1957",
    "sg:postcode":"53226",
    "sg:province":"WI",
    "sg:tags":[
        "attorney"
    ],
    "wof:name":"Margaret A Mc Kenna",
    "wof:placetype":"venue"
},
  "geometry": {"coordinates":[-88.058818,43.058237],"type":"Point"}
}