{
  "type": "Feature",
  "properties": {
    "iso:country":"US",
    "sg:address":"115 5th Ave S",
    "sg:city":"Onalaska",
    "sg:classifiers":[
        {
            "category":"Professional",
            "subcategory":"Lawyer & Legal Services",
            "type":"Services"
        }
    ],
    "sg:phone":"+1 608 784 7243",
    "sg:postcode":"54650",
    "sg:province":"WI",
    "sg:tags":[
        "plan"
    ],
    "wof:name":"Pre-Paid Legal Svc Inc",
    "wof:placetype":"venue"
},
  "geometry": {"coordinates":[-91.230214,43.882799],"type":"Point"}
}