{
  "type": "Feature",
  "properties": {
    "iso:country":"US",
    "sg:address":"3930 N 1st St",
    "sg:city":"Milwaukee",
    "sg:classifiers":[
        {
            "category":"Manufacturing",
            "subcategory":"Metals",
            "type":"Manufacturing & Wholesale Goods"
        }
    ],
    "sg:phone":"+1 414 962 6896",
    "sg:postcode":"53212",
    "sg:province":"WI",
    "sg:tags":[
        "die",
        "nonferrous",
        "foundry",
        "mfg"
    ],
    "sg:website":"www.mwdcc.com",
    "wof:name":"Midwest Die Casting Corp",
    "wof:placetype":"venue"
},
  "geometry": {"coordinates":[-87.91072699999999,43.08895],"type":"Point"}
}