{
  "type": "Feature",
  "properties": {
    "iso:country":"US",
    "sg:address":"3117 Buena Vista St",
    "sg:city":"Madison",
    "sg:classifiers":[
        {
            "category":"Health Services",
            "subcategory":"Clinic",
            "type":"Services"
        }
    ],
    "sg:phone":"+1 608 249 3580",
    "sg:postcode":"53704",
    "sg:province":"WI",
    "wof:name":"Sound Experience",
    "wof:placetype":"venue"
},
  "geometry": {"coordinates":[-89.33829,43.093594],"type":"Point"}
}