{
  "type": "Feature",
  "properties": {
    "iso:country":"US",
    "sg:address":"1501 Pierce Ave",
    "sg:city":"Marinette",
    "sg:classifiers":[
        {
            "category":"Insurance",
            "subcategory":"Insurance Agent",
            "type":"Services"
        }
    ],
    "sg:phone":"+1 715 735 9521",
    "sg:postcode":"54143",
    "sg:province":"WI",
    "wof:name":"Reiswitz Insurance Inc",
    "wof:placetype":"venue"
},
  "geometry": {"coordinates":[-87.629482,45.090795],"type":"Point"}
}