{
  "type": "Feature",
  "properties": {
    "iso:country":"US",
    "sg:address":"402 S George St",
    "sg:city":"Iron River",
    "sg:classifiers":[
        {
            "category":"Social Services",
            "type":"Services"
        }
    ],
    "sg:phone":"+1 715 372 5433",
    "sg:postcode":"54847",
    "sg:province":"WI",
    "sg:tags":[
        "organization",
        "welfare"
    ],
    "wof:name":"Children's Service Society-Wi",
    "wof:placetype":"venue"
},
  "geometry": {"coordinates":[-91.415272,46.565046],"type":"Point"}
}