{
  "type": "Feature",
  "properties": {
    "iso:country":"US",
    "sg:address":"9052 E Baldwin Ave",
    "sg:city":"Solon Springs",
    "sg:classifiers":[
        {
            "category":"Social Services",
            "subcategory":"Child Care",
            "type":"Services"
        }
    ],
    "sg:phone":"+1 715 378 2693",
    "sg:postcode":"54873",
    "sg:province":"WI",
    "wof:name":"Mary's Care Bear Ctr",
    "wof:placetype":"venue"
},
  "geometry": {"coordinates":[-91.82883,46.345493],"type":"Point"}
}