{
  "type": "Feature",
  "properties": {
    "addr:full":"503 Sommers Landing Rd N Hudson WI 54016",
    "addr:housenumber":"503",
    "addr:postcode":"54016",
    "addr:street":"Sommers Landing Rd N",
    "iso:country":"US",
    "sg:address":"503 Sommers Landing Rd N",
    "sg:city":"Hudson",
    "sg:classifiers":[
        {
            "category":"Building & Trades",
            "subcategory":"Construction",
            "type":"Services"
        }
    ],
    "sg:phone":"+1 715 386 3432",
    "sg:postcode":"54016",
    "sg:province":"WI",
    "sg:tags":[
        "finisher",
        "metal"
    ],
    "wof:name":"Polishing Inc",
    "wof:placetype":"venue"
},
  "geometry": {"coordinates":[-92.760549,45.004592],"type":"Point"}
}