{
  "type": "Feature",
  "properties": {
    "iso:country":"US",
    "sg:address":"110 E Main St",
    "sg:city":"Madison",
    "sg:classifiers":[
        {
            "category":"Government",
            "subcategory":"Office",
            "type":"Public Place"
        }
    ],
    "sg:phone":"+1 608 266 7711",
    "sg:postcode":"53703",
    "sg:province":"WI",
    "sg:tags":[
        "state",
        "inspection"
    ],
    "wof:name":"Medical Mediation Panels",
    "wof:placetype":"venue"
},
  "geometry": {"coordinates":[-89.381112,43.075279],"type":"Point"}
}