{
  "type": "Feature",
  "properties": {
    "iso:country":"US",
    "sg:address":"910 S Main St",
    "sg:city":"Fort Atkinson",
    "sg:classifiers":[
        {
            "category":"Banks & Credit Unions",
            "subcategory":"Bank",
            "type":"Services"
        }
    ],
    "sg:phone":"+1 920 563 6616",
    "sg:postcode":"53538",
    "sg:province":"WI",
    "wof:name":"Premier Bank",
    "wof:placetype":"venue"
},
  "geometry": {"coordinates":[-88.836873,42.91675],"type":"Point"}
}