{
  "type": "Feature",
  "properties": {
    "iso:country":"US",
    "sg:address":"110 Busch Rd",
    "sg:city":"Muscoda",
    "sg:classifiers":[
        {
            "category":"Farming",
            "subcategory":"Livestock Farm",
            "type":"Manufacturing & Wholesale Goods"
        }
    ],
    "sg:phone":"+1 608 739 3748",
    "sg:postcode":"53573",
    "sg:province":"WI",
    "sg:tags":[
        "beef",
        "feedlot",
        "cattle"
    ],
    "wof:name":"David Drews",
    "wof:placetype":"venue"
},
  "geometry": {"coordinates":[-90.428918,43.114923],"type":"Point"}
}