{
  "type": "Feature",
  "properties": {
    "iso:country":"US",
    "sg:address":"280 N Main St",
    "sg:city":"Clintonville",
    "sg:classifiers":[
        {
            "category":"Restaurant",
            "type":"Food & Drink"
        }
    ],
    "sg:phone":"+1 715 823 3492",
    "sg:postcode":"54929",
    "sg:province":"WI",
    "sg:tags":[
        "drinking",
        "eating"
    ],
    "wof:name":"Wagon Wheel Inc",
    "wof:placetype":"venue"
},
  "geometry": {"coordinates":[-88.752842,44.632208],"type":"Point"}
}