{
  "type": "Feature",
  "properties": {
    "iso:country":"US",
    "sg:address":"2736 830th St",
    "sg:city":"Hager City",
    "sg:classifiers":[
        {
            "category":"Freight",
            "type":"Transportation"
        }
    ],
    "sg:phone":"+1 715 792 2313",
    "sg:postcode":"54014",
    "sg:province":"WI",
    "sg:tags":[
        "operator",
        "local",
        "trucking"
    ],
    "wof:name":"R & D Express Inc",
    "wof:placetype":"venue"
},
  "geometry": {"coordinates":[-92.545417,44.636082],"type":"Point"}
}