{
  "type": "Feature",
  "properties": {
    "iso:country":"US",
    "sg:address":"106 Elm St E",
    "sg:city":"Amery",
    "sg:classifiers":[
        {
            "category":"Travel",
            "subcategory":"Travel Agent",
            "type":"Entertainment"
        }
    ],
    "sg:phone":"+1 715 268 9283",
    "sg:postcode":"54001",
    "sg:province":"WI",
    "sg:tags":[
        "passenger",
        "agency",
        "transportation",
        "arrangement"
    ],
    "wof:name":"Amery Travel Service",
    "wof:placetype":"venue"
},
  "geometry": {"coordinates":[-92.36126,45.309107],"type":"Point"}
}