{
  "type": "Feature",
  "properties": {
    "iso:country":"US",
    "sg:address":"1808 E Main St",
    "sg:city":"Onalaska",
    "sg:classifiers":[
        {
            "category":"Insurance",
            "subcategory":"Insurance Agent",
            "type":"Services"
        }
    ],
    "sg:phone":"+1 608 781 9692",
    "sg:postcode":"54650",
    "sg:province":"WI",
    "sg:website":"www.healthtradition.com",
    "wof:name":"Health Tradition Health Plan",
    "wof:placetype":"venue"
},
  "geometry": {"coordinates":[-91.209943,43.884034],"type":"Point"}
}