{
  "type": "Feature",
  "properties": {
    "iso:country":"US",
    "sg:address":"721 Oxford Ave",
    "sg:city":"Eau Claire",
    "sg:classifiers":[
        {
            "category":"Real Estate",
            "subcategory":"Real Estate Agent",
            "type":"Services"
        }
    ],
    "sg:phone":"+1 715 839 6230",
    "sg:postcode":"54703",
    "sg:province":"WI",
    "sg:tags":[
        "manager"
    ],
    "wof:name":"Eau Claire County Housing Auth",
    "wof:placetype":"venue"
},
  "geometry": {"coordinates":[-91.504845,44.808377],"type":"Point"}
}