{
  "type": "Feature",
  "properties": {
    "addr:full":"221 Main St Black River Fls WI 54615",
    "addr:housenumber":"221",
    "addr:postcode":"54615",
    "addr:street":"Main St",
    "iso:country":"US",
    "sg:address":"221 Main St",
    "sg:city":"Black River Fls",
    "sg:classifiers":[
        {
            "category":"Insurance",
            "subcategory":"Hazard Insurance",
            "type":"Services"
        },
        {
            "category":"Insurance",
            "subcategory":"Insurance Agent",
            "type":"Services"
        }
    ],
    "sg:phone":"+1 715 284 7773",
    "sg:postcode":"54615",
    "sg:province":"WI",
    "sg:tags":[
        "agency"
    ],
    "wof:name":"Timberland Insurance Agency",
    "wof:placetype":"venue"
},
  "geometry": {"coordinates":[-90.850224,44.295053],"type":"Point"}
}