{
  "type": "Feature",
  "properties": {
    "iso:country":"US",
    "sg:address":"20023 Rebel Ridge Dr",
    "sg:city":"Richland Center",
    "sg:classifiers":[
        {
            "category":"Farming",
            "subcategory":"Dairy Farm",
            "type":"Manufacturing & Wholesale Goods"
        }
    ],
    "sg:phone":"+1 608 538 3838",
    "sg:postcode":"53581",
    "sg:province":"WI",
    "wof:name":"Michael & Pam Green",
    "wof:placetype":"venue"
},
  "geometry": {"coordinates":[-90.598024,43.406823],"type":"Point"}
}