{
  "type": "Feature",
  "properties": {
    "addr:full":"3813 Rock St Manitowoc WI 54220",
    "addr:housenumber":"3813",
    "addr:postcode":"54220",
    "addr:street":"Rock St",
    "iso:country":"US",
    "sg:address":"3813 Rock St",
    "sg:city":"Manitowoc",
    "sg:classifiers":[
        {
            "category":"Building & Trades",
            "subcategory":"Construction",
            "type":"Services"
        }
    ],
    "sg:phone":"+1 920 683 3467",
    "sg:postcode":"54220",
    "sg:province":"WI",
    "sg:tags":[
        "house",
        "residential"
    ],
    "wof:name":"Bobs Home Improvement",
    "wof:placetype":"venue"
},
  "geometry": {"coordinates":[-87.69590100000001,44.088942],"type":"Point"}
}