{
  "type": "Feature",
  "properties": {
    "iso:country":"US",
    "sg:address":"2001 Bellevue St",
    "sg:city":"Green Bay",
    "sg:classifiers":[
        {
            "category":"Autos & Motor Vehicles",
            "subcategory":"Motorcycle Sales",
            "type":"Retail Goods"
        }
    ],
    "sg:phone":"+1 920 432 1577",
    "sg:postcode":"54311",
    "sg:province":"WI",
    "sg:tags":[
        "scooter"
    ],
    "wof:name":"Full Throttle Cycle",
    "wof:placetype":"venue"
},
  "geometry": {"coordinates":[-88.001171,44.471454],"type":"Point"}
}