{
  "type": "Feature",
  "properties": {
    "addr:full":"2735 Swanson Rd Nekoosa WI 54457",
    "addr:housenumber":"2735",
    "addr:postcode":"54457",
    "addr:street":"Swanson Rd",
    "iso:country":"US",
    "sg:address":"2735 Swanson Rd",
    "sg:city":"Nekoosa",
    "sg:classifiers":[
        {
            "category":"Retail",
            "subcategory":"Auto Repair",
            "type":"Services"
        }
    ],
    "sg:phone":"+1 715 887 3200",
    "sg:postcode":"54457",
    "sg:province":"WI",
    "sg:tags":[
        "body",
        "automobile",
        "painting"
    ],
    "wof:name":"Ebert's Classic Chevy Parts",
    "wof:placetype":"venue"
},
  "geometry": {"coordinates":[-89.90531900000001,44.349795],"type":"Point"}
}