{
  "type": "Feature",
  "properties": {
    "iso:country":"US",
    "sg:address":"1696 Oconnor Rd",
    "sg:city":"Lodi",
    "sg:classifiers":[
        {
            "category":"Government",
            "subcategory":"Office",
            "type":"Public Place"
        }
    ],
    "sg:phone":"+1 608 592 7059",
    "sg:postcode":"53555",
    "sg:province":"WI",
    "sg:tags":[
        "village"
    ],
    "wof:name":"Town Of West Point",
    "wof:placetype":"venue"
},
  "geometry": {"coordinates":[-89.64322199999999,43.322803],"type":"Point"}
}