{
  "type": "Feature",
  "properties": {
    "iso:country":"US",
    "sg:address":"5244 W Forest Home Ave",
    "sg:city":"Milwaukee",
    "sg:classifiers":[
        {
            "category":"Shopping",
            "subcategory":"Music",
            "type":"Retail Goods"
        }
    ],
    "sg:phone":"+1 414 321 7746",
    "sg:postcode":"53219",
    "sg:province":"WI",
    "sg:tags":[
        "compact",
        "record",
        "disc",
        "tape"
    ],
    "wof:name":"Spin Dizzy Records & Compact",
    "wof:placetype":"venue"
},
  "geometry": {"coordinates":[-87.97981,42.981957],"type":"Point"}
}