{
  "type": "Feature",
  "properties": {
    "iso:country":"US",
    "sg:address":"7212 Co Rd Z",
    "sg:city":"Wisconsin Rapids",
    "sg:classifiers":[
        {
            "category":"Wholesale",
            "subcategory":"Construction Materials",
            "type":"Manufacturing & Wholesale Goods"
        }
    ],
    "sg:phone":"+1 715 887 4444",
    "sg:postcode":"54494",
    "sg:province":"WI",
    "sg:tags":[
        "timberland",
        "company",
        "timber"
    ],
    "wof:name":"Plum Creek Timber",
    "wof:placetype":"venue"
},
  "geometry": {"coordinates":[-89.746292,44.351587],"type":"Point"}
}