{
  "type": "Feature",
  "properties": {
    "iso:country":"US",
    "sg:address":"830 Williams St",
    "sg:city":"Lake Geneva",
    "sg:classifiers":[
        {
            "category":"Personal",
            "subcategory":"Beauty Salon",
            "type":"Services"
        }
    ],
    "sg:phone":"+1 262 249 7675",
    "sg:postcode":"53147",
    "sg:province":"WI",
    "sg:tags":[
        "shop"
    ],
    "wof:name":"Cutting Zone",
    "wof:placetype":"venue"
},
  "geometry": {"coordinates":[-88.435744,42.598873],"type":"Point"}
}