{
  "type": "Feature",
  "properties": {
    "addr:full":"5133 S 108th St Hales Corners WI 53130",
    "addr:housenumber":"5133",
    "addr:postcode":"53130",
    "addr:street":"S 108Th St",
    "iso:country":"US",
    "sg:address":"5133 S 108th St",
    "sg:city":"Hales Corners",
    "sg:classifiers":[
        {
            "category":"Restaurant",
            "type":"Food & Drink"
        }
    ],
    "sg:phone":"+1 414 425 1010",
    "sg:postcode":"53130",
    "sg:province":"WI",
    "sg:tags":[
        "eating"
    ],
    "wof:name":"A&W Restaurant",
    "wof:placetype":"venue"
},
  "geometry": {"coordinates":[-88.048295,42.949833],"type":"Point"}
}