{
  "type": "Feature",
  "properties": {
    "iso:country":"US",
    "sg:address":"5110 W Ryan Rd",
    "sg:city":"Franklin",
    "sg:classifiers":[
        {
            "category":"Freight",
            "type":"Transportation"
        }
    ],
    "sg:phone":"+1 414 423 8903",
    "sg:postcode":"53132",
    "sg:province":"WI",
    "wof:name":"Blue Moon Trucking & Freight",
    "wof:placetype":"venue"
},
  "geometry": {"coordinates":[-87.98481200000001,42.87268],"type":"Point"}
}