{
  "type": "Feature",
  "properties": {
    "iso:country":"US",
    "sg:address":"7610 Pershing Blvd",
    "sg:city":"Kenosha",
    "sg:classifiers":[
        {
            "category":"Shopping",
            "subcategory":"Books",
            "type":"Retail Goods"
        }
    ],
    "sg:phone":"+1 262 694 4055",
    "sg:postcode":"53142",
    "sg:province":"WI",
    "sg:tags":[
        "cards",
        "magazine",
        "greeting"
    ],
    "wof:name":"R K News Inc",
    "wof:placetype":"venue"
},
  "geometry": {"coordinates":[-87.85769,42.563891],"type":"Point"}
}