{
  "type": "Feature",
  "properties": {
    "iso:country":"US",
    "sg:address":"816 Porter Ave",
    "sg:city":"Eau Claire",
    "sg:classifiers":[
        {
            "category":"Health Services",
            "subcategory":"Nursing And Care Facility",
            "type":"Services"
        },
        {
            "category":"Social Services",
            "subcategory":"Adult Care",
            "type":"Services"
        }
    ],
    "sg:phone":"+1 715 832 1644",
    "sg:postcode":"54701",
    "sg:province":"WI",
    "sg:tags":[
        "home",
        "intermediate",
        "residential"
    ],
    "wof:name":"Syverson Lutheran Home Aux",
    "wof:placetype":"venue"
},
  "geometry": {"coordinates":[-91.496064,44.804918],"type":"Point"}
}