{
  "type": "Feature",
  "properties": {
    "addr:full":"3943 Lindberg Rd Conover WI 54519",
    "addr:housenumber":"3943",
    "addr:postcode":"54519",
    "addr:street":"Lindberg Rd",
    "iso:country":"US",
    "sg:address":"3943 Lindberg Rd",
    "sg:city":"Conover",
    "sg:classifiers":[
        {
            "category":"Retail",
            "subcategory":"Laundry & Dry Cleaning",
            "type":"Services"
        }
    ],
    "sg:phone":"+1 715 479 8732",
    "sg:postcode":"54519",
    "sg:province":"WI",
    "wof:name":"Excel Cleaning & Restoration",
    "wof:placetype":"venue"
},
  "geometry": {"coordinates":[-89.196451,46.034989],"type":"Point"}
}