{
  "type": "Feature",
  "properties": {
    "iso:country":"US",
    "sg:address":"715 Ackley St",
    "sg:city":"Antigo",
    "sg:classifiers":[
        {
            "category":"Health Services",
            "subcategory":"Nursing And Care Facility",
            "type":"Services"
        }
    ],
    "sg:phone":"+1 715 623 0423",
    "sg:postcode":"54409",
    "sg:province":"WI",
    "sg:tags":[
        "home",
        "skilled",
        "convalescent"
    ],
    "wof:name":"Evergreen Terrace LLC",
    "wof:placetype":"venue"
},
  "geometry": {"coordinates":[-89.154809,45.159207],"type":"Point"}
}