{
  "type": "Feature",
  "properties": {
    "iso:country":"US",
    "sg:address":"330 E Kilbourn Ave",
    "sg:city":"Milwaukee",
    "sg:classifiers":[
        {
            "category":"Professional",
            "subcategory":"Lawyer & Legal Services",
            "type":"Services"
        }
    ],
    "sg:phone":"+1 414 271 1440",
    "sg:postcode":"53202",
    "sg:province":"WI",
    "sg:tags":[
        "attorney"
    ],
    "sg:website":"www.grgblaw.com",
    "wof:name":"Gimbel Reilly Guerin & Brown",
    "wof:placetype":"venue"
},
  "geometry": {"coordinates":[-87.907285,43.042515],"type":"Point"}
}