{
  "type": "Feature",
  "properties": {
    "iso:country":"US",
    "sg:address":"1606 Royal Crown Ct",
    "sg:city":"Green Bay",
    "sg:classifiers":[
        {
            "category":"Professional",
            "type":"Services"
        }
    ],
    "sg:phone":"+1 920 494 5646",
    "sg:postcode":"54313",
    "sg:province":"WI",
    "wof:name":"Logo-Motion",
    "wof:placetype":"venue"
},
  "geometry": {"coordinates":[-88.128307,44.515662],"type":"Point"}
}