{
  "type": "Feature",
  "properties": {
    "addr:full":"107 Oak St E Frederic WI 54837",
    "addr:housenumber":"107",
    "addr:postcode":"54837",
    "addr:street":"Oak St E",
    "iso:country":"US",
    "sg:address":"107 Oak St E",
    "sg:city":"Frederic",
    "sg:classifiers":[
        {
            "category":"Health Services",
            "subcategory":"Clinic",
            "type":"Services"
        }
    ],
    "sg:phone":"+1 715 327 4246",
    "sg:postcode":"54837",
    "sg:province":"WI",
    "sg:tags":[
        "home"
    ],
    "wof:name":"Lakeview Homecare & Hospice",
    "wof:placetype":"venue"
},
  "geometry": {"coordinates":[-92.464681,45.659319],"type":"Point"}
}