{
  "type": "Feature",
  "properties": {
    "iso:country":"US",
    "sg:address":"424 S Main St",
    "sg:city":"Holmen",
    "sg:classifiers":[
        {
            "category":"Restaurant",
            "type":"Food & Drink"
        }
    ],
    "sg:phone":"+1 608 526 6177",
    "sg:postcode":"54636",
    "sg:province":"WI",
    "sg:tags":[
        "eating"
    ],
    "wof:name":"Blue Cup Coffee House",
    "wof:placetype":"venue"
},
  "geometry": {"coordinates":[-91.256441,43.963108],"type":"Point"}
}