{
  "type": "Feature",
  "properties": {
    "addr:full":"1602 Church Rd Cecil WI 54111",
    "addr:housenumber":"1602",
    "addr:postcode":"54111",
    "addr:street":"Church Rd",
    "iso:country":"US",
    "sg:address":"1602 Church Rd",
    "sg:city":"Cecil",
    "sg:classifiers":[
        {
            "category":"Building & Trades",
            "subcategory":"Construction",
            "type":"Services"
        }
    ],
    "sg:phone":"+1 715 745 6392",
    "sg:postcode":"54111",
    "sg:province":"WI",
    "sg:tags":[
        "contractor"
    ],
    "wof:name":"S & D Exteriors",
    "wof:placetype":"venue"
},
  "geometry": {"coordinates":[-88.325367,44.837949],"type":"Point"}
}