{
  "type": "Feature",
  "properties": {
    "iso:country":"US",
    "sg:address":"800 Riverside Dr",
    "sg:city":"Waupaca",
    "sg:classifiers":[
        {
            "category":"Health Services",
            "subcategory":"Doctor",
            "type":"Services"
        }
    ],
    "sg:phone":"+1 715 258 1119",
    "sg:postcode":"54981",
    "sg:province":"WI",
    "sg:tags":[
        "physician",
        "surgeon"
    ],
    "wof:name":"Fox Valley Hematology",
    "wof:placetype":"venue"
},
  "geometry": {"coordinates":[-89.075958,44.345251],"type":"Point"}
}