{
  "type": "Feature",
  "properties": {
    "iso:country":"US",
    "sg:address":"6991 S Lovers Lane Rd",
    "sg:city":"Franklin",
    "sg:classifiers":[
        {
            "category":"Travel",
            "subcategory":"Hotels & Motels",
            "type":"Entertainment"
        }
    ],
    "sg:phone":"+1 414 425 4370",
    "sg:postcode":"53132",
    "sg:province":"WI",
    "sg:tags":[
        "operation"
    ],
    "wof:name":"Whitnall View Motel",
    "wof:placetype":"venue"
},
  "geometry": {"coordinates":[-88.046336,42.918621],"type":"Point"}
}