{
  "type": "Feature",
  "properties": {
    "addr:full":"634 Muttart Rd Neenah WI 54956",
    "addr:housenumber":"634",
    "addr:postcode":"54956",
    "addr:street":"Muttart Rd",
    "iso:country":"US",
    "sg:address":"634 Muttart Rd",
    "sg:city":"Neenah",
    "sg:classifiers":[
        {
            "category":"Freight",
            "type":"Transportation"
        }
    ],
    "sg:phone":"+1 920 729 4343",
    "sg:postcode":"54956",
    "sg:province":"WI",
    "sg:tags":[
        "trucking"
    ],
    "sg:website":"www.wpg.org",
    "wof:name":"Wisconsin Paper Group",
    "wof:placetype":"venue"
},
  "geometry": {"coordinates":[-88.48678700000001,44.134539],"type":"Point"}
}