{
  "type": "Feature",
  "properties": {
    "iso:country":"US",
    "sg:address":"400 Bayview Rd",
    "sg:city":"Mukwonago",
    "sg:classifiers":[
        {
            "category":"Shopping",
            "subcategory":"Optical Goods",
            "type":"Retail Goods"
        }
    ],
    "sg:phone":"+1 262 363 4040",
    "sg:postcode":"53149",
    "sg:province":"WI",
    "wof:name":"Herslof Opticians",
    "wof:placetype":"venue"
},
  "geometry": {"coordinates":[-88.336507,42.85192],"type":"Point"}
}