{
  "type": "Feature",
  "properties": {
    "iso:country":"US",
    "sg:address":"318 N Water St",
    "sg:city":"Milwaukee",
    "sg:classifiers":[
        {
            "category":"Banks & Credit Unions",
            "subcategory":"Bank",
            "type":"Services"
        }
    ],
    "sg:phone":"+1 414 238 2957",
    "sg:postcode":"53202",
    "sg:province":"WI",
    "wof:name":"Pyramax Bank",
    "wof:placetype":"venue"
},
  "geometry": {"coordinates":[-87.90872,43.034713],"type":"Point"}
}