{
  "type": "Feature",
  "properties": {
    "iso:country":"US",
    "sg:address":"1604 9th St",
    "sg:city":"Green Bay",
    "sg:classifiers":[
        {
            "category":"Building & Trades",
            "subcategory":"Electrical",
            "type":"Services"
        }
    ],
    "sg:phone":"+1 920 494 3155",
    "sg:postcode":"54304",
    "sg:province":"WI",
    "sg:tags":[
        "electrical",
        "contractor"
    ],
    "wof:name":"Vander Leest Incorporated",
    "wof:placetype":"venue"
},
  "geometry": {"coordinates":[-88.071051,44.516664],"type":"Point"}
}