{
  "type": "Feature",
  "properties": {
    "iso:country":"US",
    "sg:address":"1715 52nd St",
    "sg:city":"Kenosha",
    "sg:classifiers":[
        {
            "category":"Social Services",
            "type":"Services"
        }
    ],
    "sg:phone":"+1 262 652 9543",
    "sg:postcode":"53140",
    "sg:province":"WI",
    "sg:tags":[
        "youth",
        "organization",
        "center"
    ],
    "wof:name":"Christian Youth Ctr",
    "wof:placetype":"venue"
},
  "geometry": {"coordinates":[-87.83098099999999,42.587902],"type":"Point"}
}