{
  "type": "Feature",
  "properties": {
    "iso:country":"US",
    "sg:address":"5316 Lighthouse Bay Dr",
    "sg:city":"Madison",
    "sg:classifiers":[
        {
            "category":"Social Services",
            "type":"Services"
        }
    ],
    "sg:phone":"+1 608 246 8766",
    "sg:postcode":"53704",
    "sg:province":"WI",
    "wof:name":"Segues LLC",
    "wof:placetype":"venue"
},
  "geometry": {"coordinates":[-89.405413,43.148646],"type":"Point"}
}