{
  "type": "Feature",
  "properties": {
    "iso:country":"US",
    "sg:address":"9930 S Franklin Dr",
    "sg:city":"Franklin",
    "sg:classifiers":[
        {
            "category":"Manufacturing",
            "subcategory":"Metals",
            "type":"Manufacturing & Wholesale Goods"
        },
        {
            "category":"Manufacturing",
            "subcategory":"Tools & Machinery",
            "type":"Manufacturing & Wholesale Goods"
        }
    ],
    "sg:phone":"+1 414 421 8890",
    "sg:postcode":"53132",
    "sg:province":"WI",
    "sg:tags":[
        "screw",
        "product",
        "apparatus",
        "mfg",
        "supply",
        "machine",
        "equipment",
        "welding"
    ],
    "sg:website":"http://www.hinzcompany.com",
    "wof:name":"The Howard G Hinz Company Inc",
    "wof:placetype":"venue"
},
  "geometry": {"coordinates":[-87.97821,42.865549],"type":"Point"}
}