{
  "type": "Feature",
  "properties": {
    "addr:full":"5819 Forest Ln Rhinelander WI 54501",
    "addr:housenumber":"5819",
    "addr:postcode":"54501",
    "addr:street":"Forest Ln",
    "iso:country":"US",
    "sg:address":"5819 Forest Ln",
    "sg:city":"Rhinelander",
    "sg:classifiers":[
        {
            "category":"Wholesale",
            "subcategory":"Non-durable Goods",
            "type":"Manufacturing & Wholesale Goods"
        }
    ],
    "sg:phone":"+1 715 362 8562",
    "sg:postcode":"54501",
    "sg:province":"WI",
    "wof:name":"Gauthier Distributor",
    "wof:placetype":"venue"
},
  "geometry": {"coordinates":[-89.45376899999999,45.652229],"type":"Point"}
}