{
  "type": "Feature",
  "properties": {
    "iso:country":"US",
    "sg:address":"2420 Milwaukee St",
    "sg:city":"Delafield",
    "sg:classifiers":[
        {
            "category":"Shopping",
            "type":"Retail Goods"
        }
    ],
    "sg:phone":"+1 262 646 4886",
    "sg:postcode":"53018",
    "sg:province":"WI",
    "sg:tags":[
        "art",
        "gallery",
        "dealer"
    ],
    "wof:name":"94 83 Gallery",
    "wof:placetype":"venue"
},
  "geometry": {"coordinates":[-88.371754,43.051927],"type":"Point"}
}