{
  "type": "Feature",
  "properties": {
    "iso:country":"US",
    "sg:address":"161 East St",
    "sg:city":"Boyceville",
    "sg:classifiers":[
        {
            "category":"Education",
            "subcategory":"School",
            "type":"Public Place"
        }
    ],
    "sg:phone":"+1 715 643 4331",
    "sg:postcode":"54725",
    "sg:province":"WI",
    "sg:website":"www.boyceville.k12.wi.us",
    "wof:name":"Tiffany Creek Elementary Schl",
    "wof:placetype":"venue"
},
  "geometry": {"coordinates":[-92.03573299999999,45.049724],"type":"Point"}
}