{
  "type": "Feature",
  "properties": {
    "iso:country":"US",
    "sg:address":"611 N Barker Rd",
    "sg:city":"Brookfield",
    "sg:classifiers":[
        {
            "category":"Professional",
            "type":"Services"
        },
        {
            "category":"Professional",
            "subcategory":"Lawyer & Legal Services",
            "type":"Services"
        }
    ],
    "sg:phone":"+1 414 476 5700",
    "sg:postcode":"53045",
    "sg:province":"WI",
    "sg:tags":[
        "attorney",
        "criminal",
        "estate",
        "divorce",
        "wills",
        "mediation",
        "planning",
        "trust",
        "law",
        "bankruptcy"
    ],
    "sg:website":"http://www.horizonslaw.com",
    "wof:name":"Horizons Law Group LLC",
    "wof:placetype":"venue"
},
  "geometry": {"coordinates":[-88.16687,43.037386],"type":"Point"}
}