{
  "type": "Feature",
  "properties": {
    "addr:full":"5587 E Waterford Rd Hartford WI 53027",
    "addr:housenumber":"5587",
    "addr:postcode":"53027",
    "addr:street":"E Waterford Rd",
    "iso:country":"US",
    "sg:address":"5587 E Waterford Rd",
    "sg:city":"Hartford",
    "sg:classifiers":[
        {
            "category":"Farming",
            "subcategory":"Farm & Veterinary Services",
            "type":"Manufacturing & Wholesale Goods"
        }
    ],
    "sg:phone":"+1 262 670 4933",
    "sg:postcode":"53027",
    "sg:province":"WI",
    "sg:tags":[
        "breeder",
        "livestock"
    ],
    "wof:name":"Kettle Hills Alpaca Farm",
    "wof:placetype":"venue"
},
  "geometry": {"coordinates":[-88.310925,43.281304],"type":"Point"}
}