{
  "type": "Feature",
  "properties": {
    "iso:country":"US",
    "sg:address":"2516 Biehl Rd",
    "sg:city":"Marinette",
    "sg:classifiers":[
        {
            "category":"Wholesale",
            "subcategory":"Hardware",
            "type":"Manufacturing & Wholesale Goods"
        }
    ],
    "sg:phone":"+1 715 732 9115",
    "sg:postcode":"54143",
    "sg:province":"WI",
    "sg:tags":[
        "fastener"
    ],
    "wof:name":"Fastenal Co",
    "wof:placetype":"venue"
},
  "geometry": {"coordinates":[-87.64203999999999,45.083684],"type":"Point"}
}