{
  "type": "Feature",
  "properties": {
    "iso:country":"US",
    "sg:address":"4021 Hiawatha Dr",
    "sg:city":"Madison",
    "sg:classifiers":[
        {
            "category":"Shopping",
            "subcategory":"Used Merchandise",
            "type":"Retail Goods"
        }
    ],
    "sg:phone":"+1 608 233 9700",
    "sg:postcode":"53711",
    "sg:province":"WI",
    "wof:name":"Easy Street Antiques",
    "wof:placetype":"venue"
},
  "geometry": {"coordinates":[-89.445732,43.04566],"type":"Point"}
}