{
  "type": "Feature",
  "properties": {
    "addr:full":"1238 Melody Dr Green Bay WI 54303",
    "addr:housenumber":"1238",
    "addr:postcode":"54303",
    "addr:street":"Melody Dr",
    "iso:country":"US",
    "sg:address":"1238 Melody Dr",
    "sg:city":"Green Bay",
    "sg:classifiers":[
        {
            "category":"Building & Trades",
            "subcategory":"Construction",
            "type":"Services"
        }
    ],
    "sg:phone":"+1 920 494 5323",
    "sg:postcode":"54303",
    "sg:province":"WI",
    "sg:tags":[
        "downspouts",
        "gutter"
    ],
    "wof:name":"Advance Leaf Protection",
    "wof:placetype":"venue"
},
  "geometry": {"coordinates":[-88.05648100000001,44.551118],"type":"Point"}
}