{
  "type": "Feature",
  "properties": {
    "iso:country":"US",
    "sg:address":"611 N Frontage Rd",
    "sg:city":"Wisconsin Dells",
    "sg:classifiers":[
        {
            "category":"Local Transit",
            "type":"Transportation"
        }
    ],
    "sg:phone":"+1 608 254 2081",
    "sg:postcode":"53965",
    "sg:province":"WI",
    "sg:tags":[
        "bus",
        "line"
    ],
    "wof:name":"Greyhound Bus Lines",
    "wof:placetype":"venue"
},
  "geometry": {"coordinates":[-89.79384400000001,43.622883],"type":"Point"}
}