{
  "type": "Feature",
  "properties": {
    "addr:full":"9035 Blumenstein Rd Woodruff WI 54568",
    "addr:housenumber":"9035",
    "addr:postcode":"54568",
    "addr:street":"Blumenstein Rd",
    "iso:country":"US",
    "sg:address":"9035 Blumenstein Rd",
    "sg:city":"Woodruff",
    "sg:classifiers":[
        {
            "category":"Organizations",
            "subcategory":"Religious Organization",
            "type":"Services"
        }
    ],
    "sg:phone":"+1 715 356 4311",
    "sg:postcode":"54568",
    "sg:province":"WI",
    "sg:tags":[
        "church"
    ],
    "wof:name":"Faith Evangelical Free Church",
    "wof:placetype":"venue"
},
  "geometry": {"coordinates":[-89.715332,45.896585],"type":"Point"}
}