{
  "type": "Feature",
  "properties": {
    "iso:country":"US",
    "sg:address":"5237 W Electric Ave",
    "sg:city":"Milwaukee",
    "sg:classifiers":[
        {
            "category":"Building & Trades",
            "subcategory":"Construction",
            "type":"Services"
        }
    ],
    "sg:phone":"+1 414 543 5215",
    "sg:postcode":"53219",
    "sg:province":"WI",
    "sg:tags":[
        "contractor"
    ],
    "wof:name":"MB Restorations",
    "wof:placetype":"venue"
},
  "geometry": {"coordinates":[-87.978565,43.003828],"type":"Point"}
}