{
  "type": "Feature",
  "properties": {
    "iso:country":"US",
    "sg:address":"7717 Eagle St",
    "sg:city":"Milwaukee",
    "sg:classifiers":[
        {
            "category":"Building & Trades",
            "subcategory":"Plumbing",
            "type":"Services"
        }
    ],
    "sg:phone":"+1 414 305 6466",
    "sg:postcode":"53213",
    "sg:province":"WI",
    "sg:tags":[
        "plumbing",
        "contractor"
    ],
    "wof:name":"Drain Surgeon",
    "wof:placetype":"venue"
},
  "geometry": {"coordinates":[-88.00872699999999,43.067036],"type":"Point"}
}