{
  "type": "Feature",
  "properties": {
    "addr:full":"3185 Finger Rd Green Bay WI 54311",
    "addr:housenumber":"3185",
    "addr:postcode":"54311",
    "addr:street":"Finger Rd",
    "iso:country":"US",
    "sg:address":"3185 Finger Rd",
    "sg:city":"Green Bay",
    "sg:classifiers":[
        {
            "category":"Wholesale",
            "subcategory":"Electrical",
            "type":"Manufacturing & Wholesale Goods"
        }
    ],
    "sg:phone":"+1 920 884 0806",
    "sg:postcode":"54311",
    "sg:province":"WI",
    "wof:name":"Kennys Appliance Service",
    "wof:placetype":"venue"
},
  "geometry": {"coordinates":[-87.9254,44.488175],"type":"Point"}
}