{
  "type": "Feature",
  "properties": {
    "iso:country":"US",
    "sg:address":"12143 W Oakwood Rd",
    "sg:city":"Franklin",
    "sg:classifiers":[
        {
            "category":"Wholesale",
            "subcategory":"Electrical",
            "type":"Manufacturing & Wholesale Goods"
        }
    ],
    "sg:phone":"+1 414 858 9393",
    "sg:postcode":"53132",
    "sg:province":"WI",
    "sg:tags":[
        "electronic"
    ],
    "wof:name":"Key Industries",
    "wof:placetype":"venue"
},
  "geometry": {"coordinates":[-88.06040400000001,42.85796],"type":"Point"}
}