{
  "type": "Feature",
  "properties": {
    "iso:country":"US",
    "sg:address":"519 Milwaukee Ave",
    "sg:city":"South Milwaukee",
    "sg:classifiers":[
        {
            "category":"Health Services",
            "subcategory":"Doctor",
            "type":"Services"
        }
    ],
    "sg:phone":"+1 414 764 5960",
    "sg:postcode":"53172",
    "sg:province":"WI",
    "sg:tags":[
        "dentist"
    ],
    "wof:name":"Darrell A Francis DDS",
    "wof:placetype":"venue"
},
  "geometry": {"coordinates":[-87.852799,42.910428],"type":"Point"}
}