{
  "type": "Feature",
  "properties": {
    "iso:country":"US",
    "sg:address":"985 Ehlers Rd",
    "sg:city":"Neenah",
    "sg:classifiers":[
        {
            "category":"Building & Trades",
            "subcategory":"Electrical",
            "type":"Services"
        }
    ],
    "sg:phone":"+1 920 729 1400",
    "sg:postcode":"54956",
    "sg:province":"WI",
    "sg:tags":[
        "electrical",
        "contractor"
    ],
    "wof:name":"Endeavor Electric Inc",
    "wof:placetype":"venue"
},
  "geometry": {"coordinates":[-88.47924999999999,44.208076],"type":"Point"}
}