{
  "type": "Feature",
  "properties": {
    "iso:country":"US",
    "sg:address":"9326 Union Valley Rd",
    "sg:city":"Black Earth",
    "sg:classifiers":[
        {
            "category":"Farming",
            "subcategory":"Dairy Farm",
            "type":"Manufacturing & Wholesale Goods"
        }
    ],
    "sg:phone":"+1 608 767 3660",
    "sg:postcode":"53515",
    "sg:province":"WI",
    "wof:name":"Parrell Bros",
    "wof:placetype":"venue"
},
  "geometry": {"coordinates":[-89.709706,43.101043],"type":"Point"}
}