{
  "type": "Feature",
  "properties": {
    "iso:country":"US",
    "sg:address":"465 S Jossart Rd",
    "sg:city":"Luxemburg",
    "sg:classifiers":[
        {
            "category":"Restaurant",
            "type":"Food & Drink"
        }
    ],
    "sg:phone":"+1 920 845 9947",
    "sg:postcode":"54217",
    "sg:province":"WI",
    "sg:tags":[
        "eating"
    ],
    "wof:name":"Electro Subs Inc",
    "wof:placetype":"venue"
},
  "geometry": {"coordinates":[-87.775363,44.49329],"type":"Point"}
}