{
  "type": "Feature",
  "properties": {
    "iso:country":"US",
    "sg:address":"111 Jefferson St",
    "sg:city":"Waupaca",
    "sg:classifiers":[
        {
            "category":"Banks & Credit Unions",
            "subcategory":"Financial Services",
            "type":"Services"
        }
    ],
    "sg:phone":"+1 715 258 5511",
    "sg:postcode":"54981",
    "sg:province":"WI",
    "sg:tags":[
        "company",
        "holding"
    ],
    "wof:name":"Waupaca Bancorp Inc",
    "wof:placetype":"venue"
},
  "geometry": {"coordinates":[-89.083606,44.357853],"type":"Point"}
}