{
  "type": "Feature",
  "properties": {
    "iso:country":"US",
    "sg:address":"300 Travis Ln",
    "sg:city":"Waukesha",
    "sg:classifiers":[
        {
            "category":"Home & Garden",
            "subcategory":"Home Furnishings",
            "type":"Retail Goods"
        }
    ],
    "sg:phone":"+1 262 574 1453",
    "sg:postcode":"53189",
    "sg:province":"WI",
    "sg:tags":[
        "venetian",
        "blind",
        "window",
        "treatment"
    ],
    "wof:name":"Wisconsin's Window Concepts",
    "wof:placetype":"venue"
},
  "geometry": {"coordinates":[-88.23084799999999,42.975966],"type":"Point"}
}