{
  "type": "Feature",
  "properties": {
    "iso:country":"US",
    "sg:address":"1001 S 75th St",
    "sg:city":"Milwaukee",
    "sg:classifiers":[
        {
            "category":"Professional",
            "subcategory":"Computer Services",
            "type":"Services"
        }
    ],
    "sg:phone":"+1 414 476 8641",
    "sg:postcode":"53214",
    "sg:province":"WI",
    "sg:tags":[
        "internet"
    ],
    "sg:website":"www.tcg24x7.com",
    "wof:name":"Computer Guys",
    "wof:placetype":"venue"
},
  "geometry": {"coordinates":[-88.006062,43.02138],"type":"Point"}
}