{
  "type": "Feature",
  "properties": {
    "addr:full":"510 Orchard Dr Madison WI 53711",
    "addr:housenumber":"510",
    "addr:postcode":"53711",
    "addr:street":"Orchard Dr",
    "iso:country":"US",
    "sg:address":"510 Orchard Dr",
    "sg:city":"Madison",
    "sg:classifiers":[
        {
            "category":"Recreation",
            "type":"Entertainment"
        }
    ],
    "sg:phone":"+1 608 273 9153",
    "sg:postcode":"53711",
    "sg:province":"WI",
    "wof:name":"Planet Trout Enterprises",
    "wof:placetype":"venue"
},
  "geometry": {"coordinates":[-89.456191,43.053877],"type":"Point"}
}