{
  "type": "Feature",
  "properties": {
    "iso:country":"US",
    "sg:address":"2850 N 2nd St",
    "sg:city":"Milwaukee",
    "sg:classifiers":[
        {
            "category":"Professional",
            "subcategory":"Detective & Security Services",
            "type":"Services"
        }
    ],
    "sg:phone":"+1 414 372 8518",
    "sg:postcode":"53212",
    "sg:province":"WI",
    "sg:tags":[
        "information",
        "bureau"
    ],
    "wof:name":"Intrans Language Services",
    "wof:placetype":"venue"
},
  "geometry": {"coordinates":[-87.912525,43.070232],"type":"Point"}
}