{
  "type": "Feature",
  "properties": {
    "iso:country":"US",
    "sg:address":"112 N Water St",
    "sg:city":"Watertown",
    "sg:classifiers":[
        {
            "category":"Professional",
            "subcategory":"Business Services",
            "type":"Services"
        }
    ],
    "sg:phone":"+1 920 262 8966",
    "sg:postcode":"53094",
    "sg:province":"WI",
    "sg:tags":[
        "notary"
    ],
    "wof:name":"Diamond Financial Corp",
    "wof:placetype":"venue"
},
  "geometry": {"coordinates":[-88.72601299999999,43.195561],"type":"Point"}
}