{
  "type": "Feature",
  "properties": {
    "addr:full":"413 E Main St Watertown WI 53094",
    "addr:housenumber":"413",
    "addr:postcode":"53094",
    "addr:street":"E Main St",
    "iso:country":"US",
    "sg:address":"413 E Main St",
    "sg:city":"Watertown",
    "sg:classifiers":[
        {
            "category":"Shopping",
            "subcategory":"Gifts & Souvenirs",
            "type":"Retail Goods"
        }
    ],
    "sg:phone":"+1 920 261 2908",
    "sg:postcode":"53094",
    "sg:province":"WI",
    "sg:tags":[
        "shop"
    ],
    "wof:name":"Far Horizons Imports",
    "wof:placetype":"venue"
},
  "geometry": {"coordinates":[-88.72113299999999,43.193879],"type":"Point"}
}