{
  "type": "Feature",
  "properties": {
    "iso:country":"US",
    "sg:address":"1962 N Prospect Ave",
    "sg:city":"Milwaukee",
    "sg:classifiers":[
        {
            "category":"Building & Trades",
            "subcategory":"Construction",
            "type":"Services"
        }
    ],
    "sg:phone":"+1 414 221 9433",
    "sg:postcode":"53202",
    "sg:province":"WI",
    "sg:tags":[
        "tile",
        "dealer"
    ],
    "wof:name":"Grout Medic",
    "wof:placetype":"venue"
},
  "geometry": {"coordinates":[-87.887576,43.056],"type":"Point"}
}