{
  "type": "Feature",
  "properties": {
    "iso:country":"US",
    "sg:address":"5055 N 124th St",
    "sg:city":"Butler",
    "sg:classifiers":[
        {
            "category":"Autos & Motor Vehicles",
            "subcategory":"Auto Supplies",
            "type":"Retail Goods"
        },
        {
            "category":"Retail",
            "subcategory":"Auto Repair",
            "type":"Services"
        }
    ],
    "sg:phone":"+1 262 781 6840",
    "sg:postcode":"53007",
    "sg:province":"WI",
    "sg:tags":[
        "body",
        "repairing",
        "classic",
        "automobile",
        "part",
        "painting",
        "restoration-antique"
    ],
    "sg:website":"http://www.kandylandautobody.com",
    "wof:name":"Kandyland Auto",
    "wof:placetype":"venue"
},
  "geometry": {"coordinates":[-88.065853,43.109211],"type":"Point"}
}