{
  "type": "Feature",
  "properties": {
    "iso:country":"US",
    "sg:address":"706 Pearl St",
    "sg:city":"Tomah",
    "sg:classifiers":[
        {
            "category":"Professional",
            "type":"Services"
        }
    ],
    "sg:phone":"+1 608 372 3556",
    "sg:postcode":"54660",
    "sg:province":"WI",
    "wof:name":"Walterville LLC",
    "wof:placetype":"venue"
},
  "geometry": {"coordinates":[-90.51220499999999,43.983002],"type":"Point"}
}