{
  "type": "Feature",
  "properties": {
    "iso:country":"US",
    "sg:address":"5810 Lincoln Village Dr",
    "sg:city":"Racine",
    "sg:classifiers":[
        {
            "category":"Professional",
            "type":"Services"
        }
    ],
    "sg:phone":"+1 262 633 6630",
    "sg:postcode":"53406",
    "sg:province":"WI",
    "sg:tags":[
        "establishment"
    ],
    "wof:name":"Lincoln Villas Kitchen",
    "wof:placetype":"venue"
},
  "geometry": {"coordinates":[-87.850533,42.711087],"type":"Point"}
}