{
  "type": "Feature",
  "properties": {
    "iso:country":"US",
    "sg:address":"1732 Co Rd F",
    "sg:city":"Athens",
    "sg:classifiers":[
        {
            "category":"Farming",
            "subcategory":"Dairy Farm",
            "type":"Manufacturing & Wholesale Goods"
        }
    ],
    "sg:phone":"+1 715 257 9143",
    "sg:postcode":"54411",
    "sg:province":"WI",
    "wof:name":"Bernard Weiler",
    "wof:placetype":"venue"
},
  "geometry": {"coordinates":[-90.122324,45.076717],"type":"Point"}
}