{
  "type": "Feature",
  "properties": {
    "iso:country":"US",
    "sg:address":"5323 N 118th Ct",
    "sg:city":"Milwaukee",
    "sg:classifiers":[
        {
            "category":"Wholesale",
            "subcategory":"Metals & Minerals",
            "type":"Manufacturing & Wholesale Goods"
        }
    ],
    "sg:phone":"+1 414 760 6300",
    "sg:postcode":"53225",
    "sg:province":"WI",
    "sg:tags":[
        "steel",
        "warehouse",
        "center"
    ],
    "wof:name":"Castle Metals",
    "wof:placetype":"venue"
},
  "geometry": {"coordinates":[-88.059437,43.114196],"type":"Point"}
}