{
  "type": "Feature",
  "properties": {
    "addr:full":"320 S Main St Adams WI 53910",
    "addr:housenumber":"320",
    "addr:postcode":"53910",
    "addr:street":"S Main St",
    "iso:country":"US",
    "sg:address":"320 S Main St",
    "sg:city":"Adams",
    "sg:classifiers":[
        {
            "category":"Restaurant",
            "type":"Food & Drink"
        }
    ],
    "sg:phone":"+1 608 339 4919",
    "sg:postcode":"53910",
    "sg:province":"WI",
    "wof:name":"Wildwood Cafe",
    "wof:placetype":"venue"
},
  "geometry": {"coordinates":[-89.817463,43.954282],"type":"Point"}
}