{
  "type": "Feature",
  "properties": {
    "iso:country":"US",
    "sg:address":"500 W Silver Spring Dr",
    "sg:city":"Milwaukee",
    "sg:classifiers":[
        {
            "category":"Structure",
            "subcategory":"Office Building",
            "type":"Public Place"
        }
    ],
    "sg:phone":"+1 414 847 6200",
    "sg:postcode":"53217",
    "sg:province":"WI",
    "sg:tags":[
        "desk",
        "rental",
        "space"
    ],
    "wof:name":"Regus Center",
    "wof:placetype":"venue"
},
  "geometry": {"coordinates":[-87.915222,43.118698],"type":"Point"}
}