{
  "type": "Feature",
  "properties": {
    "iso:country":"US",
    "sg:address":"18650 W Corporate Dr",
    "sg:city":"Brookfield",
    "sg:classifiers":[
        {
            "category":"Insurance",
            "subcategory":"Insurance Agent",
            "type":"Services"
        }
    ],
    "sg:phone":"+1 262 792 1242",
    "sg:postcode":"53045",
    "sg:province":"WI",
    "wof:name":"Westberg Insurance",
    "wof:placetype":"venue"
},
  "geometry": {"coordinates":[-88.145285,43.029728],"type":"Point"}
}