{
  "type": "Feature",
  "properties": {
    "addr:full":"101 N Main St Oconto Falls WI 54154",
    "addr:housenumber":"101",
    "addr:postcode":"54154",
    "addr:street":"N Main St",
    "iso:country":"US",
    "sg:address":"101 N Main St",
    "sg:city":"Oconto Falls",
    "sg:classifiers":[
        {
            "category":"Recreation",
            "type":"Entertainment"
        }
    ],
    "sg:phone":"+1 920 846 4804",
    "sg:postcode":"54154",
    "sg:province":"WI",
    "wof:name":"Falls Flying Dragons",
    "wof:placetype":"venue"
},
  "geometry": {"coordinates":[-88.14401599999999,44.875579],"type":"Point"}
}