{
  "type": "Feature",
  "properties": {
    "iso:country":"US",
    "sg:address":"458 E Bradley Ave",
    "sg:city":"Milwaukee",
    "sg:classifiers":[
        {
            "category":"Building & Trades",
            "subcategory":"Landscaping Services",
            "type":"Services"
        }
    ],
    "sg:phone":"+1 414 744 9066",
    "sg:postcode":"53207",
    "sg:province":"WI",
    "sg:tags":[
        "lawn",
        "garden"
    ],
    "wof:name":"Liebl John Jr & Son Ldscpg",
    "wof:placetype":"venue"
},
  "geometry": {"coordinates":[-87.905567,42.977471],"type":"Point"}
}