{
  "type": "Feature",
  "properties": {
    "iso:country":"US",
    "sg:address":"13 Hollybrook Ct",
    "sg:city":"Madison",
    "sg:classifiers":[
        {
            "category":"Professional",
            "subcategory":"Computer Services",
            "type":"Services"
        }
    ],
    "sg:phone":"+1 608 513 8159",
    "sg:postcode":"53716",
    "sg:province":"WI",
    "sg:tags":[
        "datum"
    ],
    "wof:name":"R S M Promotions LLC",
    "wof:placetype":"venue"
},
  "geometry": {"coordinates":[-89.292631,43.068397],"type":"Point"}
}