{
  "type": "Feature",
  "properties": {
    "iso:country":"US",
    "sg:address":"611 E Blackhawk Ave",
    "sg:city":"Prairie Du Chien",
    "sg:classifiers":[
        {
            "category":"Real Estate",
            "subcategory":"Real Estate Agent",
            "type":"Services"
        }
    ],
    "sg:phone":"+1 608 326 5130",
    "sg:postcode":"53821",
    "sg:province":"WI",
    "sg:tags":[
        "appraiser"
    ],
    "wof:name":"Morrissey Appraisal Service",
    "wof:placetype":"venue"
},
  "geometry": {"coordinates":[-91.13824099999999,43.052079],"type":"Point"}
}