{
  "type": "Feature",
  "properties": {
    "iso:country":"US",
    "sg:address":"11425 Co Rd C",
    "sg:city":"Black River Falls",
    "sg:classifiers":[
        {
            "category":"Professional",
            "subcategory":"Management & Consulting",
            "type":"Services"
        }
    ],
    "sg:phone":"+1 715 284 9633",
    "sg:postcode":"54615",
    "sg:province":"WI",
    "wof:name":"Motivational Marketing Svcs",
    "wof:placetype":"venue"
},
  "geometry": {"coordinates":[-90.876404,44.284194],"type":"Point"}
}