{
  "type": "Feature",
  "properties": {
    "iso:country":"US",
    "sg:address":"1255 Marietta Ave",
    "sg:city":"Ixonia",
    "sg:phone":"+1 262 567 6509",
    "sg:postcode":"53036",
    "sg:province":"WI",
    "sg:tags":[
        "oil"
    ],
    "wof:name":"Frontier FS Coop",
    "wof:placetype":"venue"
},
  "geometry": {"coordinates":[-88.595128,43.143333],"type":"Point"}
}