{
  "type": "Feature",
  "properties": {
    "addr:full":"405 S Arch St Janesville WI 53548",
    "addr:housenumber":"405",
    "addr:postcode":"53548",
    "addr:street":"S Arch St",
    "iso:country":"US",
    "sg:address":"405 S Arch St",
    "sg:city":"Janesville",
    "sg:classifiers":[
        {
            "category":"Manufacturing",
            "subcategory":"Glass & Minerals",
            "type":"Manufacturing & Wholesale Goods"
        }
    ],
    "sg:phone":"+1 608 752 6507",
    "sg:postcode":"53548",
    "sg:province":"WI",
    "sg:tags":[
        "farm",
        "concrete",
        "product",
        "arch",
        "mfg"
    ],
    "wof:name":"AG Pre Cast",
    "wof:placetype":"venue"
},
  "geometry": {"coordinates":[-89.044742,42.672008],"type":"Point"}
}