{
  "type": "Feature",
  "properties": {
    "addr:full":"260 E Highland Ave Milwaukee WI 53202",
    "addr:housenumber":"260",
    "addr:postcode":"53202",
    "addr:street":"E Highland Ave",
    "iso:country":"US",
    "sg:address":"260 E Highland Ave",
    "sg:city":"Milwaukee",
    "sg:classifiers":[
        {
            "category":"Professional",
            "subcategory":"Business Services",
            "type":"Services"
        }
    ],
    "sg:phone":"+1 414 291 9397",
    "sg:postcode":"53202",
    "sg:province":"WI",
    "sg:tags":[
        "recording",
        "studio"
    ],
    "wof:name":"Laboratory",
    "wof:placetype":"venue"
},
  "geometry": {"coordinates":[-87.908738,43.04479],"type":"Point"}
}