{
  "type": "Feature",
  "properties": {
    "addr:full":"811 N Lynndale St Appleton WI 54914",
    "addr:housenumber":"811",
    "addr:postcode":"54914",
    "addr:street":"N Lynndale St",
    "iso:country":"US",
    "sg:address":"811 N Lynndale St",
    "sg:city":"Appleton",
    "sg:classifiers":[
        {
            "category":"Insurance",
            "subcategory":"Insurance Agent",
            "type":"Services"
        }
    ],
    "sg:phone":"+1 920 830 6500",
    "sg:postcode":"54914",
    "sg:province":"WI",
    "sg:tags":[
        "advisory",
        "investment"
    ],
    "wof:name":"David Kuhn Insur & Investments",
    "wof:placetype":"venue"
},
  "geometry": {"coordinates":[-88.446093,44.270802],"type":"Point"}
}