{
  "type": "Feature",
  "properties": {
    "iso:country":"US",
    "sg:address":"10 Pluim Dr",
    "sg:city":"Waupun",
    "sg:classifiers":[
        {
            "category":"Health Services",
            "subcategory":"Nursing And Care Facility",
            "type":"Services"
        }
    ],
    "sg:phone":"+1 920 324 9755",
    "sg:postcode":"53963",
    "sg:province":"WI",
    "sg:tags":[
        "residential"
    ],
    "wof:name":"Friendship Haven",
    "wof:placetype":"venue"
},
  "geometry": {"coordinates":[-88.718282,43.634221],"type":"Point"}
}