{
  "type": "Feature",
  "properties": {
    "addr:full":"11 Karl Ave Belleville WI 53508",
    "addr:housenumber":"11",
    "addr:postcode":"53508",
    "addr:street":"Karl Ave",
    "iso:country":"US",
    "sg:address":"11 Karl Ave",
    "sg:city":"Belleville",
    "sg:classifiers":[
        {
            "category":"Social Services",
            "subcategory":"Child Care",
            "type":"Services"
        }
    ],
    "sg:phone":"+1 608 424 6482",
    "sg:postcode":"53508",
    "sg:province":"WI",
    "sg:tags":[
        "kindergarten",
        "academic",
        "school"
    ],
    "wof:name":"Early Childhood-Adventure",
    "wof:placetype":"venue"
},
  "geometry": {"coordinates":[-89.53318899999999,42.871239],"type":"Point"}
}