{
  "type": "Feature",
  "properties": {
    "iso:country":"US",
    "sg:address":"147 Bartlain Dr",
    "sg:city":"Ixonia",
    "sg:classifiers":[
        {
            "category":"Building & Trades",
            "subcategory":"Construction",
            "type":"Services"
        }
    ],
    "sg:phone":"+1 262 567 1789",
    "sg:postcode":"53036",
    "sg:province":"WI",
    "sg:tags":[
        "general",
        "contractor"
    ],
    "wof:name":"David E Otto Carpentry & Gnrl",
    "wof:placetype":"venue"
},
  "geometry": {"coordinates":[-88.539117,43.177434],"type":"Point"}
}