{
  "type": "Feature",
  "properties": {
    "iso:country":"US",
    "sg:address":"1969 Roosevelt Ave",
    "sg:city":"Two Rivers",
    "sg:classifiers":[
        {
            "category":"Organizations",
            "subcategory":"Religious Organization",
            "type":"Services"
        }
    ],
    "sg:phone":"+1 920 793 1576",
    "sg:postcode":"54241",
    "sg:province":"WI",
    "sg:tags":[
        "church"
    ],
    "wof:name":"Abundant Life Church",
    "wof:placetype":"venue"
},
  "geometry": {"coordinates":[-87.576223,44.14306],"type":"Point"}
}