{
  "type": "Feature",
  "properties": {
    "addr:full":"25 E Main St Waupun WI 53963",
    "addr:housenumber":"25",
    "addr:postcode":"53963",
    "addr:street":"E Main St",
    "iso:country":"US",
    "sg:address":"25 E Main St",
    "sg:city":"Waupun",
    "sg:classifiers":[
        {
            "category":"Autos & Motor Vehicles",
            "subcategory":"Fuel & Gas Station",
            "type":"Retail Goods"
        }
    ],
    "sg:phone":"+1 920 324 9962",
    "sg:postcode":"53963",
    "sg:province":"WI",
    "sg:tags":[
        "automotive",
        "station",
        "gasoline",
        "repair"
    ],
    "wof:name":"Shell",
    "wof:placetype":"venue"
},
  "geometry": {"coordinates":[-88.734505,43.633079],"type":"Point"}
}