{
  "type": "Feature",
  "properties": {
    "iso:country":"US",
    "sg:address":"230 N Francis St",
    "sg:city":"Shullsburg",
    "sg:classifiers":[
        {
            "category":"Shopping",
            "subcategory":"Computers & Home Electronics",
            "type":"Retail Goods"
        }
    ],
    "sg:phone":"+1 608 965 3035",
    "sg:postcode":"53586",
    "sg:province":"WI",
    "sg:tags":[
        "equipment",
        "dealer"
    ],
    "wof:name":"Computer Essentials",
    "wof:placetype":"venue"
},
  "geometry": {"coordinates":[-90.232335,42.577414],"type":"Point"}
}