{
  "type": "Feature",
  "properties": {
    "addr:full":"4551 N 107th St Milwaukee WI 53225",
    "addr:housenumber":"4551",
    "addr:postcode":"53225",
    "addr:street":"N 107Th St",
    "iso:country":"US",
    "sg:address":"4551 N 107th St",
    "sg:city":"Milwaukee",
    "sg:classifiers":[
        {
            "category":"Professional",
            "subcategory":"Computer Services",
            "type":"Services"
        }
    ],
    "sg:phone":"+1 414 527 4794",
    "sg:postcode":"53225",
    "sg:province":"WI",
    "sg:tags":[
        "related"
    ],
    "wof:name":"Che Computer Consultants",
    "wof:placetype":"venue"
},
  "geometry": {"coordinates":[-88.045923,43.097952],"type":"Point"}
}