{
  "type": "Feature",
  "properties": {
    "iso:country":"US",
    "sg:address":"8430 W Silver Spring Dr",
    "sg:city":"Milwaukee",
    "sg:classifiers":[
        {
            "category":"Shopping",
            "subcategory":"Gifts & Souvenirs",
            "type":"Retail Goods"
        }
    ],
    "sg:phone":"+1 414 463 1892",
    "sg:postcode":"53225",
    "sg:province":"WI",
    "sg:tags":[
        "shop"
    ],
    "wof:name":"Char's Hallmark",
    "wof:placetype":"venue"
},
  "geometry": {"coordinates":[-88.014043,43.119562],"type":"Point"}
}