{
  "type": "Feature",
  "properties": {
    "addr:full":"130 Vine St Belleville WI 53508",
    "addr:housenumber":"130",
    "addr:postcode":"53508",
    "addr:street":"Vine St",
    "iso:country":"US",
    "sg:address":"130 Vine St",
    "sg:city":"Belleville",
    "sg:classifiers":[
        {
            "category":"Education",
            "subcategory":"Library",
            "type":"Public Place"
        }
    ],
    "sg:phone":"+1 608 424 1812",
    "sg:postcode":"53508",
    "sg:province":"WI",
    "wof:name":"Belleville Public Library",
    "wof:placetype":"venue"
},
  "geometry": {"coordinates":[-89.53394,42.858465],"type":"Point"}
}