{
  "type": "Feature",
  "properties": {
    "addr:full":"61382 Limery Rd Prairie Du Chien WI 53821",
    "addr:housenumber":"61382",
    "addr:postcode":"53821",
    "addr:street":"Limery Rd",
    "iso:country":"US",
    "sg:address":"61382 Limery Rd",
    "sg:city":"Prairie Du Chien",
    "sg:classifiers":[
        {
            "category":"Wholesale",
            "subcategory":"Machinery & Supplies",
            "type":"Manufacturing & Wholesale Goods"
        }
    ],
    "sg:phone":"+1 608 326 6119",
    "sg:postcode":"53821",
    "sg:province":"WI",
    "sg:tags":[
        "engine",
        "parts",
        "air"
    ],
    "wof:name":"Valley Small Engine Service",
    "wof:placetype":"venue"
},
  "geometry": {"coordinates":[-91.122176,43.089282],"type":"Point"}
}