{
  "type": "Feature",
  "properties": {
    "iso:country":"US",
    "sg:address":"3527 State Hwy 35",
    "sg:city":"Maiden Rock",
    "sg:classifiers":[
        {
            "category":"Bars & Pubs",
            "type":"Food & Drink"
        }
    ],
    "sg:phone":"+1 715 448 4121",
    "sg:postcode":"54750",
    "sg:province":"WI",
    "wof:name":"Lakeside Bar",
    "wof:placetype":"venue"
},
  "geometry": {"coordinates":[-92.299427,44.549212],"type":"Point"}
}