{
  "type": "Feature",
  "properties": {
    "iso:country":"US",
    "sg:address":"3826 Crosstown Rd",
    "sg:city":"Hilbert",
    "sg:classifiers":[
        {
            "category":"Building & Trades",
            "subcategory":"Landscaping Services",
            "type":"Services"
        }
    ],
    "sg:phone":"+1 920 989 5500",
    "sg:postcode":"54129",
    "sg:province":"WI",
    "sg:tags":[
        "landscape"
    ],
    "wof:name":"Cornerstone Hardscapes Inc",
    "wof:placetype":"venue"
},
  "geometry": {"coordinates":[-88.235048,44.155203],"type":"Point"}
}