{
  "type": "Feature",
  "properties": {
    "iso:country":"US",
    "sg:address":"5400 Stewart Ave",
    "sg:city":"Wausau",
    "sg:classifiers":[
        {
            "category":"Home & Garden",
            "subcategory":"Carpets & Floor Coverings",
            "type":"Retail Goods"
        }
    ],
    "sg:phone":"+1 715 842 2332",
    "sg:postcode":"54401",
    "sg:province":"WI",
    "sg:tags":[
        "material"
    ],
    "wof:name":"Contract Carpets Of Wausau",
    "wof:placetype":"venue"
},
  "geometry": {"coordinates":[-89.701583,44.955254],"type":"Point"}
}