{
  "type": "Feature",
  "properties": {
    "iso:country":"US",
    "sg:address":"136 E 12th St",
    "sg:city":"Fond Du Lac",
    "sg:classifiers":[
        {
            "category":"Building & Trades",
            "subcategory":"Cleaning & Sanitation",
            "type":"Services"
        }
    ],
    "sg:phone":"+1 920 923 4085",
    "sg:postcode":"54935",
    "sg:province":"WI",
    "sg:tags":[
        "maintenance"
    ],
    "wof:name":"All Clean Residential S",
    "wof:placetype":"venue"
},
  "geometry": {"coordinates":[-88.442911,43.765595],"type":"Point"}
}