{
  "type": "Feature",
  "properties": {
    "iso:country":"US",
    "sg:address":"4234 S Circle Dr",
    "sg:city":"Racine",
    "sg:classifiers":[
        {
            "category":"Real Estate",
            "subcategory":"Real Estate Operator",
            "type":"Services"
        }
    ],
    "sg:phone":"+1 262 637 3263",
    "sg:postcode":"53406",
    "sg:province":"WI",
    "sg:tags":[
        "condominium"
    ],
    "wof:name":"Hidden Creek Venture Inc",
    "wof:placetype":"venue"
},
  "geometry": {"coordinates":[-87.83090199999999,42.747957],"type":"Point"}
}