{
  "type": "Feature",
  "properties": {
    "iso:country":"US",
    "sg:address":"3001 Progress Rd",
    "sg:city":"Madison",
    "sg:classifiers":[
        {
            "category":"Retail",
            "subcategory":"Auto Repair",
            "type":"Services"
        }
    ],
    "sg:phone":"+1 608 224 2524",
    "sg:postcode":"53716",
    "sg:province":"WI",
    "sg:tags":[
        "repairing",
        "cylinder"
    ],
    "sg:website":"www.maxpower-engines.com",
    "wof:name":"Max Power Cylinders Inc",
    "wof:placetype":"venue"
},
  "geometry": {"coordinates":[-89.303878,43.057208],"type":"Point"}
}