{
  "type": "Feature",
  "properties": {
    "iso:country":"US",
    "sg:address":"6908 N Santa Monica Blvd",
    "sg:city":"Milwaukee",
    "sg:classifiers":[
        {
            "category":"Health Services",
            "subcategory":"Health Practitioner",
            "type":"Services"
        }
    ],
    "sg:phone":"+1 414 352 4196",
    "sg:postcode":"53217",
    "sg:province":"WI",
    "wof:name":"Golf For Life",
    "wof:placetype":"venue"
},
  "geometry": {"coordinates":[-87.90233000000001,43.143769],"type":"Point"}
}