{
  "type": "Feature",
  "properties": {
    "iso:country":"US",
    "sg:address":"17800 W Bluemound Rd",
    "sg:city":"Brookfield",
    "sg:classifiers":[
        {
            "category":"Shopping",
            "subcategory":"Photographic Equipment",
            "type":"Retail Goods"
        }
    ],
    "sg:phone":"+1 262 821 1199",
    "sg:postcode":"53045",
    "sg:province":"WI",
    "sg:tags":[
        "photography",
        "store"
    ],
    "wof:name":"Moto Photo & Portrait Studio",
    "wof:placetype":"venue"
},
  "geometry": {"coordinates":[-88.13656,43.03658],"type":"Point"}
}