{
  "type": "Feature",
  "properties": {
    "iso:country":"US",
    "sg:address":"1380 Heritage Dr",
    "sg:city":"New Richmond",
    "sg:classifiers":[
        {
            "category":"Real Estate",
            "subcategory":"Real Estate Operator",
            "type":"Services"
        }
    ],
    "sg:phone":"+1 715 246 6558",
    "sg:postcode":"54017",
    "sg:province":"WI",
    "sg:tags":[
        "apartment"
    ],
    "wof:name":"Heritage Apartments",
    "wof:placetype":"venue"
},
  "geometry": {"coordinates":[-92.536285,45.107103],"type":"Point"}
}