{
  "type": "Feature",
  "properties": {
    "iso:country":"US",
    "sg:address":"1654 20th St",
    "sg:city":"Turtle Lake",
    "sg:classifiers":[
        {
            "category":"Building & Trades",
            "subcategory":"Construction",
            "type":"Services"
        }
    ],
    "sg:phone":"+1 715 986 4482",
    "sg:postcode":"54889",
    "sg:province":"WI",
    "sg:tags":[
        "excavation",
        "contractor"
    ],
    "wof:name":"Evenson Excavating Inc",
    "wof:placetype":"venue"
},
  "geometry": {"coordinates":[-92.197176,45.446963],"type":"Point"}
}