{
  "type": "Feature",
  "properties": {
    "iso:country":"US",
    "sg:address":"2123 N 15th St",
    "sg:city":"Sheboygan",
    "sg:classifiers":[
        {
            "category":"Bars & Pubs",
            "type":"Food & Drink"
        }
    ],
    "sg:phone":"+1 920 452 6910",
    "sg:postcode":"53081",
    "sg:province":"WI",
    "sg:tags":[
        "drinking"
    ],
    "wof:name":"Jacquealine Paradise",
    "wof:placetype":"venue"
},
  "geometry": {"coordinates":[-87.724441,43.768257],"type":"Point"}
}