{
  "type": "Feature",
  "properties": {
    "addr:full":"7809 W Burleigh St Milwaukee WI 53222",
    "addr:housenumber":"7809",
    "addr:postcode":"53222",
    "addr:street":"W Burleigh St",
    "iso:country":"US",
    "sg:address":"7809 W Burleigh St",
    "sg:city":"Milwaukee",
    "sg:classifiers":[
        {
            "category":"Shopping",
            "subcategory":"Clothing, Apparel, & Fashions",
            "type":"Retail Goods"
        }
    ],
    "sg:phone":"+1 414 447 1637",
    "sg:postcode":"53222",
    "sg:province":"WI",
    "wof:name":"Purseusion LLC",
    "wof:placetype":"venue"
},
  "geometry": {"coordinates":[-88.011037,43.075204],"type":"Point"}
}