{
  "type": "Feature",
  "properties": {
    "iso:country":"US",
    "sg:address":"2449 State Hwy 44",
    "sg:city":"Oshkosh",
    "sg:classifiers":[
        {
            "category":"Freight",
            "type":"Transportation"
        }
    ],
    "sg:phone":"+1 920 233 8150",
    "sg:postcode":"54904",
    "sg:province":"WI",
    "sg:tags":[
        "operator",
        "local",
        "trucking"
    ],
    "wof:name":"Roadway Express",
    "wof:placetype":"venue"
},
  "geometry": {"coordinates":[-88.587664,43.987504],"type":"Point"}
}