{
  "type": "Feature",
  "properties": {
    "addr:full":"2645 Richardson St Madison WI 53711",
    "addr:housenumber":"2645",
    "addr:postcode":"53711",
    "addr:street":"Richardson St",
    "iso:country":"US",
    "sg:address":"2645 Richardson St",
    "sg:city":"Madison",
    "sg:classifiers":[
        {
            "category":"Social Services",
            "subcategory":"Job Training",
            "type":"Services"
        }
    ],
    "sg:phone":"+1 920 693 1347",
    "sg:postcode":"53711",
    "sg:province":"WI",
    "wof:name":"Huber Larry E Efo Cem",
    "wof:placetype":"venue"
},
  "geometry": {"coordinates":[-89.437192,42.998355],"type":"Point"}
}