{
  "type": "Feature",
  "properties": {
    "iso:country":"US",
    "sg:address":"305 W 4th St",
    "sg:city":"Washburn",
    "sg:classifiers":[
        {
            "category":"Education",
            "subcategory":"School",
            "type":"Public Place"
        }
    ],
    "sg:phone":"+1 715 373 2616",
    "sg:postcode":"54891",
    "sg:province":"WI",
    "wof:name":"Washburn School District",
    "wof:placetype":"venue"
},
  "geometry": {"coordinates":[-90.895906,46.673537],"type":"Point"}
}