{
  "type": "Feature",
  "properties": {
    "addr:full":"3910 85th St Kenosha WI 53142",
    "addr:housenumber":"3910",
    "addr:postcode":"53142",
    "addr:street":"85Th St",
    "iso:country":"US",
    "sg:address":"3910 85th St",
    "sg:city":"Kenosha",
    "sg:classifiers":[
        {
            "category":"Health Services",
            "subcategory":"Doctor",
            "type":"Services"
        }
    ],
    "sg:phone":"+1 262 694 6800",
    "sg:postcode":"53142",
    "sg:province":"WI",
    "sg:website":"www.wedellortho.com",
    "wof:name":"George B Wedell DDS",
    "wof:placetype":"venue"
},
  "geometry": {"coordinates":[-87.85823000000001,42.551793],"type":"Point"}
}