{
  "type": "Feature",
  "properties": {
    "iso:country":"US",
    "sg:address":"208 Anderson St",
    "sg:city":"Coon Valley",
    "sg:classifiers":[
        {
            "category":"Professional",
            "type":"Services"
        }
    ],
    "sg:phone":"+1 608 452 3759",
    "sg:postcode":"54623",
    "sg:province":"WI",
    "wof:name":"Dennis and Daniel Neriso",
    "wof:placetype":"venue"
},
  "geometry": {"coordinates":[-91.017278,43.701026],"type":"Point"}
}