{
  "type": "Feature",
  "properties": {
    "iso:country":"US",
    "sg:address":"531 W Wisconsin Ave",
    "sg:city":"Appleton",
    "sg:classifiers":[
        {
            "category":"Real Estate",
            "subcategory":"Real Estate Agent",
            "type":"Services"
        }
    ],
    "sg:phone":"+1 920 734 9055",
    "sg:postcode":"54911",
    "sg:province":"WI",
    "wof:name":"Help U Sale Valley Homes LLC",
    "wof:placetype":"venue"
},
  "geometry": {"coordinates":[-88.412744,44.272853],"type":"Point"}
}