{
  "type": "Feature",
  "properties": {
    "addr:full":"1355 S West Ave Waukesha WI 53186",
    "addr:housenumber":"1355",
    "addr:postcode":"53186",
    "addr:street":"S West Ave",
    "iso:country":"US",
    "sg:address":"1355 S West Ave",
    "sg:city":"Waukesha",
    "sg:classifiers":[
        {
            "category":"Sports & Exercise",
            "subcategory":"Gym",
            "type":"Entertainment"
        }
    ],
    "sg:phone":"+1 262 446 1881",
    "sg:postcode":"53186",
    "sg:province":"WI",
    "sg:tags":[
        "fitness",
        "physical",
        "facility"
    ],
    "wof:name":"Curves For Women",
    "wof:placetype":"venue"
},
  "geometry": {"coordinates":[-88.23705099999999,42.990007],"type":"Point"}
}