{
  "type": "Feature",
  "properties": {
    "iso:country":"US",
    "sg:address":"4785 State Hwy 175",
    "sg:city":"Hartford",
    "sg:classifiers":[
        {
            "category":"Building & Trades",
            "subcategory":"Construction",
            "type":"Services"
        }
    ],
    "sg:phone":"+1 262 644 8737",
    "sg:postcode":"53027",
    "sg:province":"WI",
    "sg:tags":[
        "carpentry",
        "contractor"
    ],
    "wof:name":"Making Sawdust LLC",
    "wof:placetype":"venue"
},
  "geometry": {"coordinates":[-88.328677,43.364275],"type":"Point"}
}