{
  "type": "Feature",
  "properties": {
    "iso:country":"US",
    "sg:address":"11752 Co Rd Z",
    "sg:city":"Prairie Du Sac",
    "sg:classifiers":[
        {
            "category":"Wholesale",
            "subcategory":"Farm Supplies",
            "type":"Manufacturing & Wholesale Goods"
        }
    ],
    "sg:phone":"+1 608 643 2348",
    "sg:postcode":"53578",
    "sg:province":"WI",
    "wof:name":"Agronimy Center",
    "wof:placetype":"venue"
},
  "geometry": {"coordinates":[-89.736423,43.314861],"type":"Point"}
}