{
  "type": "Feature",
  "properties": {
    "iso:country":"US",
    "sg:address":"215 South St W",
    "sg:city":"Deer Park",
    "sg:classifiers":[
        {
            "category":"Building & Trades",
            "subcategory":"Construction",
            "type":"Services"
        }
    ],
    "sg:phone":"+1 715 269 5590",
    "sg:postcode":"54007",
    "sg:province":"WI",
    "sg:tags":[
        "grading",
        "contractor"
    ],
    "wof:name":"St Croix County Highway Dept",
    "wof:placetype":"venue"
},
  "geometry": {"coordinates":[-92.400268,45.187288],"type":"Point"}
}