{
  "type": "Feature",
  "properties": {
    "iso:country":"US",
    "sg:address":"478 E Huron St",
    "sg:city":"Berlin",
    "sg:classifiers":[
        {
            "category":"Wholesale",
            "subcategory":"Scrap",
            "type":"Manufacturing & Wholesale Goods"
        }
    ],
    "sg:phone":"+1 920 361 1450",
    "sg:postcode":"54923",
    "sg:province":"WI",
    "sg:tags":[
        "metal",
        "iron"
    ],
    "wof:name":"Lawent Iron & Metal",
    "wof:placetype":"venue"
},
  "geometry": {"coordinates":[-88.931976,43.968247],"type":"Point"}
}