{
  "type": "Feature",
  "properties": {
    "iso:country":"US",
    "sg:address":"9672 US Hwy 12",
    "sg:city":"Cambridge",
    "sg:classifiers":[
        {
            "category":"Professional",
            "subcategory":"Accounting & Tax Preparation",
            "type":"Services"
        }
    ],
    "sg:phone":"+1 608 423 3737",
    "sg:postcode":"53523",
    "sg:province":"WI",
    "sg:tags":[
        "return",
        "filing"
    ],
    "wof:name":"Drews Tax Plus",
    "wof:placetype":"venue"
},
  "geometry": {"coordinates":[-89.006652,43.000161],"type":"Point"}
}