{
  "type": "Feature",
  "properties": {
    "addr:full":"103 State St Holmen WI 54636",
    "addr:housenumber":"103",
    "addr:postcode":"54636",
    "addr:street":"State St",
    "iso:country":"US",
    "sg:address":"103 State St",
    "sg:city":"Holmen",
    "sg:classifiers":[
        {
            "category":"Education",
            "subcategory":"Library",
            "type":"Public Place"
        }
    ],
    "sg:phone":"+1 608 526 9600",
    "sg:postcode":"54636",
    "sg:province":"WI",
    "sg:website":"www.lacrossecounty.com",
    "wof:name":"LA Crosse County Library",
    "wof:placetype":"venue"
},
  "geometry": {"coordinates":[-91.254396,43.963206],"type":"Point"}
}