{
  "type": "Feature",
  "properties": {
    "iso:country":"US",
    "sg:address":"3315 Milton Ave",
    "sg:city":"Janesville",
    "sg:classifiers":[
        {
            "category":"Bakery",
            "type":"Food & Drink"
        }
    ],
    "sg:menulink":"http://www.allmenus.com/wi/janesville/102354-perkins-restaurant--bakery/menu/",
    "sg:phone":"+1 608 755 1464",
    "sg:postcode":"53545",
    "sg:province":"WI",
    "sg:tags":[
        "sandwich",
        "salad",
        "soup",
        "american",
        "pastry",
        "wrap"
    ],
    "wof:name":"Perkins Restaurant & Bakery",
    "wof:placetype":"venue"
},
  "geometry": {"coordinates":[-88.99636099999999,42.720782],"type":"Point"}
}