{
  "type": "Feature",
  "properties": {
    "iso:country":"US",
    "sg:address":"4746 Co Rd Z",
    "sg:city":"Dodgeville",
    "sg:classifiers":[
        {
            "category":"Building & Trades",
            "subcategory":"Landscaping Services",
            "type":"Services"
        }
    ],
    "sg:phone":"+1 608 935 5031",
    "sg:postcode":"53533",
    "sg:province":"WI",
    "sg:tags":[
        "lawn",
        "maintenance",
        "grounds"
    ],
    "wof:name":"New Horizon Supply Co-Op",
    "wof:placetype":"venue"
},
  "geometry": {"coordinates":[-90.073131,43.053188],"type":"Point"}
}