{
  "type": "Feature",
  "properties": {
    "addr:full":"170 Bennett St Clintonville WI 54929",
    "addr:housenumber":"170",
    "addr:postcode":"54929",
    "addr:street":"Bennett St",
    "iso:country":"US",
    "sg:address":"170 Bennett St",
    "sg:city":"Clintonville",
    "sg:classifiers":[
        {
            "category":"Autos & Motor Vehicles",
            "subcategory":"Auto Supplies",
            "type":"Retail Goods"
        }
    ],
    "sg:phone":"+1 715 823 2430",
    "sg:postcode":"54929",
    "sg:province":"WI",
    "sg:tags":[
        "tire"
    ],
    "wof:name":"Pomps Tire Service Inc",
    "wof:placetype":"venue"
},
  "geometry": {"coordinates":[-88.763966,44.616385],"type":"Point"}
}