{
  "type": "Feature",
  "properties": {
    "iso:country":"US",
    "sg:address":"3091 Co Rd B",
    "sg:city":"Hancock",
    "sg:classifiers":[
        {
            "category":"Shopping",
            "subcategory":"Computers & Home Electronics",
            "type":"Retail Goods"
        }
    ],
    "sg:phone":"+1 715 572 1845",
    "sg:postcode":"54943",
    "sg:province":"WI",
    "wof:name":"Deerfield Detectors",
    "wof:placetype":"venue"
},
  "geometry": {"coordinates":[-89.415341,44.084787],"type":"Point"}
}