{
  "type": "Feature",
  "properties": {
    "iso:country":"US",
    "sg:address":"13723 W Capitol Dr",
    "sg:city":"Brookfield",
    "sg:classifiers":[
        {
            "category":"Personal",
            "subcategory":"Beauty Salon",
            "type":"Services"
        }
    ],
    "sg:phone":"+1 262 783 6900",
    "sg:postcode":"53005",
    "sg:province":"WI",
    "sg:tags":[
        "wig",
        "hair",
        "piece"
    ],
    "sg:website":"http://www.sharonswigs.com",
    "wof:name":"Sharons Wig Salon",
    "wof:placetype":"venue"
},
  "geometry": {"coordinates":[-88.082409,43.089457],"type":"Point"}
}