{
  "type": "Feature",
  "properties": {
    "iso:country":"US",
    "sg:address":"9330 N Creek Ln",
    "sg:city":"Lena",
    "sg:classifiers":[
        {
            "category":"Building & Trades",
            "subcategory":"Electrical",
            "type":"Services"
        }
    ],
    "sg:phone":"+1 920 829 5422",
    "sg:postcode":"54139",
    "sg:province":"WI",
    "sg:tags":[
        "electrical",
        "electric",
        "contractor"
    ],
    "wof:name":"Hosking Electrical",
    "wof:placetype":"venue"
},
  "geometry": {"coordinates":[-87.974002,45.002515],"type":"Point"}
}