{
  "type": "Feature",
  "properties": {
    "addr:full":"4010 Airport Ave Wisconsin Rapids WI 54494",
    "addr:housenumber":"4010",
    "addr:postcode":"54494",
    "addr:street":"Airport Ave",
    "iso:country":"US",
    "sg:address":"4010 Airport Ave",
    "sg:city":"Wisconsin Rapids",
    "sg:classifiers":[
        {
            "category":"Professional",
            "subcategory":"Business Services",
            "type":"Services"
        },
        {
            "category":"Shopping",
            "subcategory":"Clothing, Apparel, & Fashions",
            "type":"Retail Goods"
        }
    ],
    "sg:phone":"+1 715 423 2769",
    "sg:postcode":"54494",
    "sg:province":"WI",
    "sg:tags":[
        "military",
        "embroidery",
        "uniform"
    ],
    "wof:name":"Let's Play Tag",
    "wof:placetype":"venue"
},
  "geometry": {"coordinates":[-89.77583199999999,44.36583],"type":"Point"}
}