{
  "type": "Feature",
  "properties": {
    "iso:country":"US",
    "sg:address":"20410 Co Rd H",
    "sg:city":"Barronett",
    "sg:classifiers":[
        {
            "category":"Building & Trades",
            "subcategory":"Construction",
            "type":"Services"
        }
    ],
    "sg:phone":"+1 715 468 4202",
    "sg:postcode":"54813",
    "sg:province":"WI",
    "sg:tags":[
        "excavation",
        "contractor"
    ],
    "wof:name":"Madison Construction",
    "wof:placetype":"venue"
},
  "geometry": {"coordinates":[-92.10311900000001,45.656695],"type":"Point"}
}