{
  "type": "Feature",
  "properties": {
    "iso:country":"US",
    "sg:address":"3314 Geele Ave",
    "sg:city":"Sheboygan",
    "sg:classifiers":[
        {
            "category":"Building & Trades",
            "subcategory":"Construction",
            "type":"Services"
        }
    ],
    "sg:phone":"+1 920 458 9918",
    "sg:postcode":"53083",
    "sg:province":"WI",
    "sg:tags":[
        "excavation",
        "contractor"
    ],
    "wof:name":"Steffs Excavating Inc",
    "wof:placetype":"venue"
},
  "geometry": {"coordinates":[-87.75100399999999,43.76835],"type":"Point"}
}