{
  "type": "Feature",
  "properties": {
    "iso:country":"US",
    "sg:address":"1918 State Hwy 88",
    "sg:city":"Alma",
    "sg:classifiers":[
        {
            "category":"Building & Trades",
            "subcategory":"Construction",
            "type":"Services"
        }
    ],
    "sg:phone":"+1 608 626 2231",
    "sg:postcode":"54610",
    "sg:province":"WI",
    "sg:tags":[
        "excavation",
        "contractor"
    ],
    "wof:name":"Reglin & Hesch Construction",
    "wof:placetype":"venue"
},
  "geometry": {"coordinates":[-91.770489,44.314422],"type":"Point"}
}