{
  "type": "Feature",
  "properties": {
    "iso:country":"US",
    "sg:address":"2422 Winnebago St",
    "sg:city":"Madison",
    "sg:classifiers":[
        {
            "category":"Restaurant",
            "type":"Food & Drink"
        }
    ],
    "sg:phone":"+1 608 442 6454",
    "sg:postcode":"53704",
    "sg:province":"WI",
    "wof:name":"Trudy's Cafe",
    "wof:placetype":"venue"
},
  "geometry": {"coordinates":[-89.350395,43.098055],"type":"Point"}
}