{
  "type": "Feature",
  "properties": {
    "addr:full":"6917 W Oklahoma Ave Milwaukee WI 53219",
    "addr:housenumber":"6917",
    "addr:postcode":"53219",
    "addr:street":"W Oklahoma Ave",
    "iso:country":"US",
    "sg:address":"6917 W Oklahoma Ave",
    "sg:city":"Milwaukee",
    "sg:classifiers":[
        {
            "category":"Shopping",
            "subcategory":"Pharmacy",
            "type":"Retail Goods"
        }
    ],
    "sg:phone":"+1 414 224 7844",
    "sg:postcode":"53219",
    "sg:province":"WI",
    "wof:name":"Aurora Pharmacy",
    "wof:placetype":"venue"
},
  "geometry": {"coordinates":[-87.99884900000001,42.988269],"type":"Point"}
}