{
  "type": "Feature",
  "properties": {
    "iso:country":"US",
    "sg:address":"220 14th St N",
    "sg:city":"Wisconsin Rapids",
    "sg:classifiers":[
        {
            "category":"Health Services",
            "subcategory":"Clinic",
            "type":"Services"
        }
    ],
    "sg:phone":"+1 715 424 3423",
    "sg:postcode":"54494",
    "sg:province":"WI",
    "sg:tags":[
        "childbirth",
        "education"
    ],
    "wof:name":"Central Wisconsin Birthing",
    "wof:placetype":"venue"
},
  "geometry": {"coordinates":[-89.809302,44.390888],"type":"Point"}
}