{
  "type": "Feature",
  "properties": {
    "iso:country":"US",
    "sg:address":"5821 Hat Rapids Rd",
    "sg:city":"Rhinelander",
    "sg:classifiers":[
        {
            "category":"Retail",
            "subcategory":"Auto Repair",
            "type":"Services"
        }
    ],
    "sg:phone":"+1 715 362 9660",
    "sg:postcode":"54501",
    "sg:province":"WI",
    "sg:tags":[
        "general"
    ],
    "wof:name":"Glimmer Auto",
    "wof:placetype":"venue"
},
  "geometry": {"coordinates":[-89.47144299999999,45.569913],"type":"Point"}
}