{
  "type": "Feature",
  "properties": {
    "iso:country":"US",
    "sg:address":"W16751 Pow Wow Ln",
    "sg:city":"Galesville",
    "sg:phone":"+1 608 582 2995",
    "sg:postcode":"54630",
    "sg:province":"WI",
    "sg:website":"http://www.riversedgecampgroundgalesville.com",
    "wof:name":"River's Edge Campground & Resort",
    "wof:placetype":"venue"
},
  "geometry": {"coordinates":[-91.280418,44.06402],"type":"Point"}
}