{
  "type": "Feature",
  "properties": {
    "iso:country":"US",
    "sg:address":"920 Greenwald Ct",
    "sg:city":"Mukwonago",
    "sg:classifiers":[
        {
            "category":"Banks & Credit Unions",
            "subcategory":"Bank",
            "type":"Services"
        }
    ],
    "sg:phone":"+1 262 363 1340",
    "sg:postcode":"53149",
    "sg:province":"WI",
    "sg:tags":[
        "institution",
        "business"
    ],
    "wof:name":"Cash Works LLC",
    "wof:placetype":"venue"
},
  "geometry": {"coordinates":[-88.32523500000001,42.850834],"type":"Point"}
}