{
  "type": "Feature",
  "properties": {
    "iso:country":"US",
    "sg:address":"7835 S Loomis Rd",
    "sg:city":"Wind Lake",
    "sg:classifiers":[
        {
            "category":"Retail",
            "subcategory":"Veterinary Services",
            "type":"Services"
        }
    ],
    "sg:phone":"+1 262 895 2600",
    "sg:postcode":"53185",
    "sg:province":"WI",
    "sg:tags":[
        "veterinarian"
    ],
    "wof:name":"Wind Lake Animal Hospital",
    "wof:placetype":"venue"
},
  "geometry": {"coordinates":[-88.15977599999999,42.826915],"type":"Point"}
}