{
  "type": "Feature",
  "properties": {
    "iso:country":"US",
    "sg:address":"8948 W Watertown Plank Rd",
    "sg:city":"Milwaukee",
    "sg:classifiers":[
        {
            "category":"Social Services",
            "type":"Services"
        }
    ],
    "sg:phone":"+1 414 475 5333",
    "sg:postcode":"53226",
    "sg:province":"WI",
    "sg:tags":[
        "organization",
        "welfare"
    ],
    "wof:name":"Ronald Mc Donald House",
    "wof:placetype":"venue"
},
  "geometry": {"coordinates":[-88.022442,43.045698],"type":"Point"}
}