{
  "type": "Feature",
  "properties": {
    "addr:full":"15285 Watertown Plank Rd Elm Grove WI 53122",
    "addr:postcode":"15285;53122",
    "addr:street":"Plank Rd",
    "iso:country":"US",
    "sg:address":"15285 Watertown Plank Rd",
    "sg:city":"Elm Grove",
    "sg:classifiers":[
        {
            "category":"Wholesale",
            "subcategory":"Electrical",
            "type":"Manufacturing & Wholesale Goods"
        }
    ],
    "sg:phone":"+1 262 786 2355",
    "sg:postcode":"53122",
    "sg:province":"WI",
    "sg:tags":[
        "alarm",
        "burglar",
        "system"
    ],
    "wof:name":"Statewide Security Systems Inc",
    "wof:placetype":"venue"
},
  "geometry": {"coordinates":[-88.102031,43.037895],"type":"Point"}
}