{
  "type": "Feature",
  "properties": {
    "addr:full":"18915 W Capitol Dr Brookfield WI 53045",
    "addr:housenumber":"18915",
    "addr:postcode":"53045",
    "addr:street":"W Capitol Dr",
    "iso:country":"US",
    "sg:address":"18915 W Capitol Dr",
    "sg:city":"Brookfield",
    "sg:classifiers":[
        {
            "category":"Shopping",
            "subcategory":"Clothing, Apparel, & Fashions",
            "type":"Retail Goods"
        }
    ],
    "sg:phone":"+1 262 783 5146",
    "sg:postcode":"53045",
    "sg:province":"WI",
    "wof:name":"Detour Clothing Store",
    "wof:placetype":"venue"
},
  "geometry": {"coordinates":[-88.14634100000001,43.090385],"type":"Point"}
}