{
  "type": "Feature",
  "properties": {
    "iso:country":"US",
    "sg:address":"1189 Main Rd",
    "sg:city":"Washington Isle",
    "sg:classifiers":[
        {
            "category":"Recreation",
            "subcategory":"Marina",
            "type":"Entertainment"
        }
    ],
    "sg:phone":"+1 920 847 2503",
    "sg:postcode":"54246",
    "sg:province":"WI",
    "sg:tags":[
        "repairing",
        "boat"
    ],
    "wof:name":"Marine Diesel Specialist",
    "wof:placetype":"venue"
},
  "geometry": {"coordinates":[-86.930647,45.373096],"type":"Point"}
}