{
  "type": "Feature",
  "properties": {
    "addr:full":"3944 Anderson Dr Eau Claire WI 54703",
    "addr:housenumber":"3944",
    "addr:postcode":"54703",
    "addr:street":"Anderson Dr",
    "iso:country":"US",
    "sg:address":"3944 Anderson Dr",
    "sg:city":"Eau Claire",
    "sg:classifiers":[
        {
            "category":"Personal",
            "subcategory":"Barber",
            "type":"Services"
        }
    ],
    "sg:phone":"+1 715 832 9402",
    "sg:postcode":"54703",
    "sg:province":"WI",
    "sg:tags":[
        "shop"
    ],
    "wof:name":"Tom's Barber Shop",
    "wof:placetype":"venue"
},
  "geometry": {"coordinates":[-91.45840099999999,44.862874],"type":"Point"}
}