{
  "type": "Feature",
  "properties": {
    "iso:country":"US",
    "sg:address":"7425 Maple Ter",
    "sg:city":"Milwaukee",
    "sg:classifiers":[
        {
            "category":"Health Services",
            "subcategory":"Health Practitioner",
            "type":"Services"
        }
    ],
    "sg:phone":"+1 414 475 5815",
    "sg:postcode":"53213",
    "sg:province":"WI",
    "wof:name":"Maple Psychotherapy",
    "wof:placetype":"venue"
},
  "geometry": {"coordinates":[-88.003439,43.042253],"type":"Point"}
}