{
  "type": "Feature",
  "properties": {
    "iso:country":"US",
    "sg:address":"940 Ontario Rd",
    "sg:city":"Green Bay",
    "sg:classifiers":[
        {
            "category":"Manufacturing",
            "subcategory":"Tools & Machinery",
            "type":"Manufacturing & Wholesale Goods"
        }
    ],
    "sg:phone":"+1 920 468 4947",
    "sg:postcode":"54311",
    "sg:province":"WI",
    "sg:tags":[
        "blow",
        "die",
        "mfg"
    ],
    "wof:name":"V S Machine Co Inc",
    "wof:placetype":"venue"
},
  "geometry": {"coordinates":[-87.927804,44.483334],"type":"Point"}
}