{
  "type": "Feature",
  "properties": {
    "iso:country":"US",
    "sg:address":"616 State Hwy 32",
    "sg:city":"Wabeno",
    "sg:classifiers":[
        {
            "category":"Recreation",
            "type":"Entertainment"
        }
    ],
    "sg:phone":"+1 715 473 2021",
    "sg:postcode":"54566",
    "sg:province":"WI",
    "sg:tags":[
        "bingo",
        "game"
    ],
    "sg:website":"www.cartercasino.com",
    "wof:name":"Potawatomi Bingo Northern",
    "wof:placetype":"venue"
},
  "geometry": {"coordinates":[-88.632837,45.400536],"type":"Point"}
}