{
  "type": "Feature",
  "properties": {
    "addr:full":"319 W Main St Princeton WI 54968",
    "addr:housenumber":"319",
    "addr:postcode":"54968",
    "addr:street":"W Main St",
    "iso:country":"US",
    "sg:address":"319 W Main St",
    "sg:city":"Princeton",
    "sg:classifiers":[
        {
            "category":"Shopping",
            "subcategory":"Gifts & Souvenirs",
            "type":"Retail Goods"
        }
    ],
    "sg:phone":"+1 920 295 4331",
    "sg:postcode":"54968",
    "sg:province":"WI",
    "wof:name":"Wooden Hobby",
    "wof:placetype":"venue"
},
  "geometry": {"coordinates":[-89.12667399999999,43.850977],"type":"Point"}
}