{
  "type": "Feature",
  "properties": {
    "iso:country":"US",
    "sg:address":"3265 Gateway Rd",
    "sg:city":"Brookfield",
    "sg:classifiers":[
        {
            "category":"Professional",
            "subcategory":"Business Services",
            "type":"Services"
        }
    ],
    "sg:phone":"+1 262 790 1888",
    "sg:postcode":"53045",
    "sg:province":"WI",
    "sg:tags":[
        "packaging"
    ],
    "wof:name":"Chenequa Packaging",
    "wof:placetype":"venue"
},
  "geometry": {"coordinates":[-88.180735,43.078839],"type":"Point"}
}