{
  "type": "Feature",
  "properties": {
    "iso:country":"US",
    "sg:address":"4464 Gateway Dr",
    "sg:city":"Sheboygan",
    "sg:classifiers":[
        {
            "category":"Professional",
            "type":"Services"
        }
    ],
    "sg:phone":"+1 920 208 8220",
    "sg:postcode":"53081",
    "sg:province":"WI",
    "sg:tags":[
        "establishment"
    ],
    "wof:name":"Rockline",
    "wof:placetype":"venue"
},
  "geometry": {"coordinates":[-87.751981,43.705005],"type":"Point"}
}