{
  "type": "Feature",
  "properties": {
    "iso:country":"US",
    "sg:address":"5425 Otto Kerl Rd",
    "sg:city":"Cross Plains",
    "sg:classifiers":[
        {
            "category":"Retail",
            "subcategory":"Animal Services",
            "type":"Services"
        }
    ],
    "sg:phone":"+1 608 798 0452",
    "sg:postcode":"53528",
    "sg:province":"WI",
    "sg:tags":[
        "breeder",
        "horse"
    ],
    "wof:name":"Hillside Horse Farms",
    "wof:placetype":"venue"
},
  "geometry": {"coordinates":[-89.64217600000001,43.151848],"type":"Point"}
}