{
  "type": "Feature",
  "properties": {
    "iso:country":"US",
    "sg:address":"362 E Four Mile Rd",
    "sg:city":"Racine",
    "sg:classifiers":[
        {
            "category":"Professional",
            "subcategory":"Computer Services",
            "type":"Services"
        }
    ],
    "sg:phone":"+1 262 898 7142",
    "sg:postcode":"53402",
    "sg:province":"WI",
    "sg:tags":[
        "related"
    ],
    "wof:name":"Wsi Internet Consulting",
    "wof:placetype":"venue"
},
  "geometry": {"coordinates":[-87.764656,42.784553],"type":"Point"}
}