{
  "type": "Feature",
  "properties": {
    "addr:full":"229 N Washington St Green Bay WI 54301",
    "addr:housenumber":"229",
    "addr:postcode":"54301",
    "addr:street":"N Washington St",
    "iso:country":"US",
    "sg:address":"229 N Washington St",
    "sg:city":"Green Bay",
    "sg:classifiers":[
        {
            "category":"Social Services",
            "type":"Services"
        }
    ],
    "sg:phone":"+1 920 499 8714",
    "sg:postcode":"54301",
    "sg:province":"WI",
    "wof:name":"Wwwbigcityfuncom",
    "wof:placetype":"venue"
},
  "geometry": {"coordinates":[-88.01498599999999,44.515999],"type":"Point"}
}