{
  "type": "Feature",
  "properties": {
    "addr:full":"372 Hoover St Sun Prairie WI 53590",
    "addr:housenumber":"372",
    "addr:postcode":"53590",
    "addr:street":"Hoover St",
    "iso:country":"US",
    "sg:address":"372 Hoover St",
    "sg:city":"Sun Prairie",
    "sg:classifiers":[
        {
            "category":"Organizations",
            "subcategory":"Community Association",
            "type":"Services"
        }
    ],
    "sg:phone":"+1 608 837 2116",
    "sg:postcode":"53590",
    "sg:province":"WI",
    "wof:name":"Madison East Rotary Found",
    "wof:placetype":"venue"
},
  "geometry": {"coordinates":[-89.20624599999999,43.194862],"type":"Point"}
}