{
  "type": "Feature",
  "properties": {
    "iso:country":"US",
    "sg:address":"16 Sibley St",
    "sg:city":"Fond Du Lac",
    "sg:classifiers":[
        {
            "category":"Wholesale",
            "subcategory":"Auto Parts",
            "type":"Manufacturing & Wholesale Goods"
        }
    ],
    "sg:phone":"+1 920 922 3390",
    "sg:postcode":"54935",
    "sg:province":"WI",
    "sg:tags":[
        "automobile"
    ],
    "wof:name":"Anders Auto Parts Inc",
    "wof:placetype":"venue"
},
  "geometry": {"coordinates":[-88.44836599999999,43.789657],"type":"Point"}
}