{
  "type": "Feature",
  "properties": {
    "iso:country":"US",
    "sg:address":"22 Milo Ln",
    "sg:city":"Madison",
    "sg:classifiers":[
        {
            "category":"Health Services",
            "subcategory":"Clinic",
            "type":"Services"
        }
    ],
    "sg:phone":"+1 608 241 3431",
    "sg:postcode":"53714",
    "sg:province":"WI",
    "sg:tags":[
        "home",
        "care"
    ],
    "wof:name":"Chamolmile Ltd",
    "wof:placetype":"venue"
},
  "geometry": {"coordinates":[-89.304677,43.100665],"type":"Point"}
}