{
  "type": "Feature",
  "properties": {
    "iso:country":"US",
    "sg:address":"51 S River St",
    "sg:city":"Janesville",
    "sg:classifiers":[
        {
            "category":"Professional",
            "subcategory":"Lawyer & Legal Services",
            "type":"Services"
        }
    ],
    "sg:phone":"+1 608 758 5454",
    "sg:postcode":"53548",
    "sg:province":"WI",
    "sg:tags":[
        "attorney"
    ],
    "wof:name":"Greenhalgh & Krueger",
    "wof:placetype":"venue"
},
  "geometry": {"coordinates":[-89.023595,42.680586],"type":"Point"}
}