{
  "type": "Feature",
  "properties": {
    "addr:full":"420 Locust St Baraboo WI 53913",
    "addr:housenumber":"420",
    "addr:postcode":"53913",
    "addr:street":"Locust St",
    "iso:country":"US",
    "sg:address":"420 Locust St",
    "sg:city":"Baraboo",
    "sg:classifiers":[
        {
            "category":"Building & Trades",
            "subcategory":"Construction",
            "type":"Services"
        }
    ],
    "sg:phone":"+1 608 356 3988",
    "sg:postcode":"53913",
    "sg:province":"WI",
    "sg:tags":[
        "siding",
        "contractor"
    ],
    "wof:name":"Clary Buildign & Siding",
    "wof:placetype":"venue"
},
  "geometry": {"coordinates":[-89.76678699999999,43.472023],"type":"Point"}
}