{
  "type": "Feature",
  "properties": {
    "iso:country":"US",
    "sg:address":"3150 S 46th St",
    "sg:city":"Milwaukee",
    "sg:classifiers":[
        {
            "category":"Personal",
            "subcategory":"Barber",
            "type":"Services"
        }
    ],
    "sg:phone":"+1 414 541 1010",
    "sg:postcode":"53219",
    "sg:province":"WI",
    "sg:tags":[
        "shop"
    ],
    "wof:name":"Chuck Blanchard's Barber Shop",
    "wof:placetype":"venue"
},
  "geometry": {"coordinates":[-87.971755,42.987119],"type":"Point"}
}