{
  "type": "Feature",
  "properties": {
    "iso:country":"US",
    "sg:address":"3498 Oneida Lake Dr",
    "sg:city":"Harshaw",
    "sg:classifiers":[
        {
            "category":"Travel",
            "subcategory":"Hotels & Motels",
            "type":"Entertainment"
        }
    ],
    "sg:phone":"+1 715 282 5417",
    "sg:postcode":"54529",
    "sg:province":"WI",
    "sg:tags":[
        "operation"
    ],
    "wof:name":"Eds White Birch Resort",
    "wof:placetype":"venue"
},
  "geometry": {"coordinates":[-89.622785,45.637114],"type":"Point"}
}