{
  "type": "Feature",
  "properties": {
    "iso:country":"US",
    "sg:address":"5935 Emstan Hills Rd",
    "sg:city":"Racine",
    "sg:classifiers":[
        {
            "category":"Insurance",
            "subcategory":"Hazard Insurance",
            "type":"Services"
        }
    ],
    "sg:phone":"+1 262 554 1300",
    "sg:postcode":"53406",
    "sg:province":"WI",
    "sg:tags":[
        "carrier"
    ],
    "wof:name":"Sentry Insurance",
    "wof:placetype":"venue"
},
  "geometry": {"coordinates":[-87.85336,42.690355],"type":"Point"}
}