{
  "type": "Feature",
  "properties": {
    "iso:country":"US",
    "sg:address":"555 E Wells St",
    "sg:city":"Milwaukee",
    "sg:classifiers":[
        {
            "category":"Organizations",
            "subcategory":"Non-profit Organization",
            "type":"Services"
        }
    ],
    "sg:phone":"+1 414 276 9339",
    "sg:postcode":"53202",
    "sg:province":"WI",
    "sg:tags":[
        "charity",
        "foundations-educational",
        "philanthropic",
        "research"
    ],
    "wof:name":"Society For Advance Of Blood",
    "wof:placetype":"venue"
},
  "geometry": {"coordinates":[-87.90482799999999,43.041341],"type":"Point"}
}