{
  "type": "Feature",
  "properties": {
    "iso:country":"US",
    "sg:address":"2319 Bay Beach Ct",
    "sg:city":"Green Bay",
    "sg:classifiers":[
        {
            "category":"Professional",
            "subcategory":"Management & Consulting",
            "type":"Services"
        }
    ],
    "sg:phone":"+1 920 469 7222",
    "sg:postcode":"54302",
    "sg:province":"WI",
    "sg:tags":[
        "business"
    ],
    "wof:name":"AK Enterprises",
    "wof:placetype":"venue"
},
  "geometry": {"coordinates":[-87.939402,44.53061],"type":"Point"}
}