{
  "type": "Feature",
  "properties": {
    "iso:country":"US",
    "sg:address":"1693 County Line Rd",
    "sg:city":"Cambria",
    "sg:classifiers":[
        {
            "category":"Manufacturing",
            "subcategory":"Apparel",
            "type":"Manufacturing & Wholesale Goods"
        }
    ],
    "sg:phone":"+1 920 348 5553",
    "sg:postcode":"53923",
    "sg:province":"WI",
    "wof:name":"Design Solutions",
    "wof:placetype":"venue"
},
  "geometry": {"coordinates":[-89.086568,43.631894],"type":"Point"}
}