{
  "type": "Feature",
  "properties": {
    "iso:country":"US",
    "sg:address":"4828 Vorpahl Rd",
    "sg:city":"Random Lake",
    "sg:classifiers":[
        {
            "category":"Building & Trades",
            "subcategory":"Plumbing",
            "type":"Services"
        }
    ],
    "sg:phone":"+1 920 994 2250",
    "sg:postcode":"53075",
    "sg:province":"WI",
    "sg:tags":[
        "contractor"
    ],
    "wof:name":"Country Aire Heating & Cooling",
    "wof:placetype":"venue"
},
  "geometry": {"coordinates":[-87.936998,43.575955],"type":"Point"}
}