{
  "type": "Feature",
  "properties": {
    "addr:full":"316 E Main St Mt Horeb WI 53572",
    "addr:housenumber":"316",
    "addr:postcode":"53572",
    "addr:street":"E Main St",
    "iso:country":"US",
    "sg:address":"316 E Main St",
    "sg:city":"Mt Horeb",
    "sg:classifiers":[
        {
            "category":"Real Estate",
            "subcategory":"Real Estate Agent",
            "type":"Services"
        }
    ],
    "sg:phone":"+1 608 437 6820",
    "sg:postcode":"53572",
    "sg:province":"WI",
    "sg:website":"www.benderrealestate.com",
    "wof:name":"Bender & Assoc Realty",
    "wof:placetype":"venue"
},
  "geometry": {"coordinates":[-89.736519,43.008741],"type":"Point"}
}