{
  "type": "Feature",
  "properties": {
    "addr:full":"2411 S Root River Pkwy Milwaukee WI 53227",
    "addr:housenumber":"2411",
    "addr:postcode":"53227",
    "addr:street":"S Root River Pkwy",
    "iso:country":"US",
    "sg:address":"2411 S Root River Pkwy",
    "sg:city":"Milwaukee",
    "sg:classifiers":[
        {
            "category":"Professional",
            "type":"Services"
        }
    ],
    "sg:phone":"+1 414 327 3491",
    "sg:postcode":"53227",
    "sg:province":"WI",
    "wof:name":"Sues Springfresh Service",
    "wof:placetype":"venue"
},
  "geometry": {"coordinates":[-88.067043,42.999698],"type":"Point"}
}