{
  "type": "Feature",
  "properties": {
    "addr:full":"24 E Gruenwald Ave Oshkosh WI 54901",
    "addr:housenumber":"24",
    "addr:postcode":"54901",
    "addr:street":"E Gruenwald Ave",
    "iso:country":"US",
    "sg:address":"24 E Gruenwald Ave",
    "sg:city":"Oshkosh",
    "sg:classifiers":[
        {
            "category":"Bars & Pubs",
            "type":"Food & Drink"
        }
    ],
    "sg:phone":"+1 920 231 7944",
    "sg:postcode":"54901",
    "sg:province":"WI",
    "sg:tags":[
        "drinking"
    ],
    "wof:name":"Jockey Club Inc",
    "wof:placetype":"venue"
},
  "geometry": {"coordinates":[-88.53662199999999,44.041351],"type":"Point"}
}