{
  "type": "Feature",
  "properties": {
    "iso:country":"US",
    "sg:address":"2332 Misty Ln",
    "sg:city":"Waukesha",
    "sg:classifiers":[
        {
            "category":"Shopping",
            "subcategory":"Florist",
            "type":"Retail Goods"
        }
    ],
    "sg:phone":"+1 262 542 0512",
    "sg:postcode":"53186",
    "sg:province":"WI",
    "wof:name":"Rosas Floral Creations",
    "wof:placetype":"venue"
},
  "geometry": {"coordinates":[-88.19517,43.033916],"type":"Point"}
}