{
  "type": "Feature",
  "properties": {
    "addr:full":"8851 Greenhill Ln Greendale WI 53129",
    "addr:housenumber":"8851",
    "addr:postcode":"53129",
    "addr:street":"Greenhill Ln",
    "iso:country":"US",
    "sg:address":"8851 Greenhill Ln",
    "sg:city":"Greendale",
    "sg:classifiers":[
        {
            "category":"Professional",
            "subcategory":"Management & Consulting",
            "type":"Services"
        }
    ],
    "sg:phone":"+1 414 529 8460",
    "sg:postcode":"53129",
    "sg:province":"WI",
    "sg:tags":[
        "consultant",
        "business"
    ],
    "sg:website":"www.roaringforkcondo.com",
    "wof:name":"Fisher/Evans Intl Inc",
    "wof:placetype":"venue"
},
  "geometry": {"coordinates":[-88.023146,42.939431],"type":"Point"}
}