{
  "type": "Feature",
  "properties": {
    "iso:country":"US",
    "sg:address":"7663 State Hwy 146",
    "sg:city":"Cambria",
    "sg:classifiers":[
        {
            "category":"Farming",
            "subcategory":"Farm",
            "type":"Manufacturing & Wholesale Goods"
        }
    ],
    "sg:phone":"+1 920 348 5795",
    "sg:postcode":"53923",
    "sg:province":"WI",
    "sg:tags":[
        "crop",
        "general"
    ],
    "wof:name":"Gene Steinich",
    "wof:placetype":"venue"
},
  "geometry": {"coordinates":[-89.102357,43.555698],"type":"Point"}
}