{
  "type": "Feature",
  "properties": {
    "iso:country":"US",
    "sg:address":"1108 56th St",
    "sg:city":"Kenosha",
    "sg:classifiers":[
        {
            "category":"Real Estate",
            "subcategory":"Real Estate Agent",
            "type":"Services"
        }
    ],
    "sg:phone":"+1 262 552 7833",
    "sg:postcode":"53140",
    "sg:province":"WI",
    "sg:tags":[
        "management"
    ],
    "wof:name":"Twin Cities",
    "wof:placetype":"venue"
},
  "geometry": {"coordinates":[-87.825809,42.584302],"type":"Point"}
}