{
  "type": "Feature",
  "properties": {
    "iso:country":"US",
    "sg:address":"616 Rubicon St",
    "sg:city":"Neosho",
    "sg:classifiers":[
        {
            "category":"Building & Trades",
            "subcategory":"Construction",
            "type":"Services"
        }
    ],
    "sg:phone":"+1 920 625 3648",
    "sg:postcode":"53059",
    "sg:province":"WI",
    "sg:tags":[
        "carpentry",
        "contractor"
    ],
    "wof:name":"D B Builders",
    "wof:placetype":"venue"
},
  "geometry": {"coordinates":[-88.516531,43.303933],"type":"Point"}
}