{
  "type": "Feature",
  "properties": {
    "iso:country":"US",
    "sg:address":"5932 N Green Bay Ave",
    "sg:city":"Milwaukee",
    "sg:classifiers":[
        {
            "category":"Restaurant",
            "type":"Food & Drink"
        }
    ],
    "sg:phone":"+1 414 228 1911",
    "sg:postcode":"53209",
    "sg:province":"WI",
    "sg:website":"www.whgonline.com",
    "wof:name":"Dos Bandidos",
    "wof:placetype":"venue"
},
  "geometry": {"coordinates":[-87.93518,43.124667],"type":"Point"}
}