{
  "type": "Feature",
  "properties": {
    "iso:country":"US",
    "sg:address":"2500 W Capitol Dr",
    "sg:city":"Milwaukee",
    "sg:classifiers":[
        {
            "category":"Retail",
            "subcategory":"Repair Shop",
            "type":"Services"
        },
        {
            "category":"Building & Trades",
            "subcategory":"Equipment Rental",
            "type":"Services"
        }
    ],
    "sg:phone":"+1 414 449 0705",
    "sg:postcode":"53206",
    "sg:province":"WI",
    "sg:tags":[
        "tools-renting",
        "saw"
    ],
    "wof:name":"Housing Resources Inc.",
    "wof:placetype":"venue"
},
  "geometry": {"coordinates":[-87.944672,43.089821],"type":"Point"}
}