{
  "type": "Feature",
  "properties": {
    "iso:country":"US",
    "sg:address":"2115 S Taylor Dr",
    "sg:city":"Sheboygan",
    "sg:classifiers":[
        {
            "category":"Professional",
            "subcategory":"Lawyer & Legal Services",
            "type":"Services"
        }
    ],
    "sg:phone":"+1 920 458 0331",
    "sg:postcode":"53081",
    "sg:province":"WI",
    "wof:name":"Buesing Carl K",
    "wof:placetype":"venue"
},
  "geometry": {"coordinates":[-87.75078,43.731906],"type":"Point"}
}