{
  "type": "Feature",
  "properties": {
    "iso:country":"US",
    "sg:address":"207 S 6th St",
    "sg:city":"Colby",
    "sg:classifiers":[
        {
            "category":"Retail",
            "subcategory":"Repair Shop",
            "type":"Services"
        }
    ],
    "sg:phone":"+1 715 223 2470",
    "sg:postcode":"54421",
    "sg:province":"WI",
    "sg:tags":[
        "television",
        "radio",
        "stereo"
    ],
    "wof:name":"Jerrys TV Sales and Service",
    "wof:placetype":"venue"
},
  "geometry": {"coordinates":[-90.323473,44.903951],"type":"Point"}
}