{
  "type": "Feature",
  "properties": {
    "iso:country":"US",
    "sg:address":"169 N Water St",
    "sg:city":"Neenah",
    "sg:classifiers":[
        {
            "category":"Health Services",
            "subcategory":"Doctor",
            "type":"Services"
        }
    ],
    "sg:phone":"+1 920 969 1493",
    "sg:postcode":"54956",
    "sg:province":"WI",
    "sg:tags":[
        "physician",
        "surgeon"
    ],
    "wof:name":"Theda Clark Remote Office",
    "wof:placetype":"venue"
},
  "geometry": {"coordinates":[-88.455331,44.189274],"type":"Point"}
}