{
  "type": "Feature",
  "properties": {
    "iso:country":"US",
    "sg:address":"24 N Henry St",
    "sg:city":"Edgerton",
    "sg:classifiers":[
        {
            "category":"Professional",
            "subcategory":"Lawyer & Legal Services",
            "type":"Services"
        }
    ],
    "sg:phone":"+1 608 884 3391",
    "sg:postcode":"53534",
    "sg:province":"WI",
    "sg:tags":[
        "attorney"
    ],
    "wof:name":"Roethe Krohn Pope Mc Carthy",
    "wof:placetype":"venue"
},
  "geometry": {"coordinates":[-89.069969,42.834584],"type":"Point"}
}