{
  "type": "Feature",
  "properties": {
    "addr:full":"211 W Main St Sun Prairie WI 53590",
    "addr:housenumber":"211",
    "addr:postcode":"53590",
    "addr:street":"W Main St",
    "iso:country":"US",
    "sg:address":"211 W Main St",
    "sg:city":"Sun Prairie",
    "sg:classifiers":[
        {
            "category":"Shopping",
            "subcategory":"Gifts & Souvenirs",
            "type":"Retail Goods"
        }
    ],
    "sg:phone":"+1 608 837 5051",
    "sg:postcode":"53590",
    "sg:province":"WI",
    "sg:tags":[
        "shop"
    ],
    "wof:name":"Prairie House",
    "wof:placetype":"venue"
},
  "geometry": {"coordinates":[-89.21525699999999,43.183225],"type":"Point"}
}