{
  "type": "Feature",
  "properties": {
    "iso:country":"US",
    "sg:address":"3243 Whiting Rd",
    "sg:city":"Stevens Point",
    "sg:classifiers":[
        {
            "category":"Manufacturing",
            "subcategory":"Paper Products",
            "type":"Manufacturing & Wholesale Goods"
        }
    ],
    "sg:phone":"+1 715 345 5046",
    "sg:postcode":"54481",
    "sg:province":"WI",
    "sg:tags":[
        "mill"
    ],
    "wof:name":"Whiting Mill of Kimberly",
    "wof:placetype":"venue"
},
  "geometry": {"coordinates":[-89.568367,44.482205],"type":"Point"}
}