{
  "type": "Feature",
  "properties": {
    "iso:country":"US",
    "sg:address":"604 Main Ave",
    "sg:city":"Crivitz",
    "sg:classifiers":[
        {
            "category":"Personal",
            "subcategory":"Barber",
            "type":"Services"
        }
    ],
    "sg:phone":"+1 715 854 2418",
    "sg:postcode":"54114",
    "sg:province":"WI",
    "sg:tags":[
        "shop"
    ],
    "wof:name":"Jerry The Barber",
    "wof:placetype":"venue"
},
  "geometry": {"coordinates":[-88.004213,45.232337],"type":"Point"}
}