{
  "type": "Feature",
  "properties": {
    "iso:country":"US",
    "sg:address":"634 US Hwy 141",
    "sg:city":"Little Suamico",
    "sg:classifiers":[
        {
            "category":"Freight",
            "type":"Transportation"
        }
    ],
    "sg:phone":"+1 920 826 2629",
    "sg:postcode":"54141",
    "sg:province":"WI",
    "sg:tags":[
        "hauling",
        "trucking"
    ],
    "wof:name":"Alpha Omega Enterprises Inc",
    "wof:placetype":"venue"
},
  "geometry": {"coordinates":[-88.050734,44.696769],"type":"Point"}
}