{
  "type": "Feature",
  "properties": {
    "iso:country":"US",
    "sg:address":"614 S Green Bay Rd",
    "sg:city":"Neenah",
    "sg:classifiers":[
        {
            "category":"Retail",
            "subcategory":"Auto Repair",
            "type":"Services"
        }
    ],
    "sg:phone":"+1 920 729 5433",
    "sg:postcode":"54956",
    "sg:province":"WI",
    "sg:tags":[
        "automobile",
        "lubrication"
    ],
    "wof:name":"Lubepro's 10 Minute Oil Change",
    "wof:placetype":"venue"
},
  "geometry": {"coordinates":[-88.485028,44.181395],"type":"Point"}
}