{
  "type": "Feature",
  "properties": {
    "addr:full":"6206 W Main St Burnett WI 53922",
    "addr:housenumber":"6206",
    "addr:postcode":"53922",
    "addr:street":"W Main St",
    "iso:country":"US",
    "sg:address":"6206 W Main St",
    "sg:city":"Burnett",
    "sg:classifiers":[
        {
            "category":"Manufacturing",
            "subcategory":"Tools & Machinery",
            "type":"Manufacturing & Wholesale Goods"
        }
    ],
    "sg:phone":"+1 920 689 2344",
    "sg:postcode":"53922",
    "sg:province":"WI",
    "sg:tags":[
        "die",
        "maker"
    ],
    "wof:name":"TNT Tool & Machine",
    "wof:placetype":"venue"
},
  "geometry": {"coordinates":[-88.71008500000001,43.504798],"type":"Point"}
}