{
  "type": "Feature",
  "properties": {
    "iso:country":"US",
    "sg:address":"750 Gregory Ct",
    "sg:city":"Walworth",
    "sg:classifiers":[
        {
            "category":"Organizations",
            "subcategory":"Religious Organization",
            "type":"Services"
        }
    ],
    "sg:phone":"+1 262 275 2193",
    "sg:postcode":"53184",
    "sg:province":"WI",
    "sg:tags":[
        "church"
    ],
    "wof:name":"Friendship Baptist Church",
    "wof:placetype":"venue"
},
  "geometry": {"coordinates":[-88.58333,42.526412],"type":"Point"}
}