{
  "type": "Feature",
  "properties": {
    "iso:country":"US",
    "sg:address":"405 Water St",
    "sg:city":"Iola",
    "sg:classifiers":[
        {
            "category":"Government",
            "subcategory":"Office",
            "type":"Public Place"
        }
    ],
    "sg:phone":"+1 715 445 3387",
    "sg:postcode":"54945",
    "sg:province":"WI",
    "sg:tags":[
        "village"
    ],
    "wof:name":"Taylor Field",
    "wof:placetype":"venue"
},
  "geometry": {"coordinates":[-89.124218,44.509822],"type":"Point"}
}