{
  "type": "Feature",
  "properties": {
    "iso:country":"US",
    "sg:address":"853 State Hwy 46",
    "sg:city":"Amery",
    "sg:classifiers":[
        {
            "category":"Freight",
            "type":"Transportation"
        }
    ],
    "sg:phone":"+1 715 268 4000",
    "sg:postcode":"54001",
    "sg:province":"WI",
    "sg:tags":[
        "commercial",
        "storage"
    ],
    "wof:name":"AAAA Amery Storage",
    "wof:placetype":"venue"
},
  "geometry": {"coordinates":[-92.36718500000001,45.297026],"type":"Point"}
}