{
  "type": "Feature",
  "properties": {
    "iso:country":"US",
    "sg:address":"107 S Broadway",
    "sg:city":"De Pere",
    "sg:classifiers":[
        {
            "category":"Shopping",
            "subcategory":"Stationery & Office Supplies",
            "type":"Retail Goods"
        }
    ],
    "sg:phone":"+1 920 336 1616",
    "sg:postcode":"54115",
    "sg:province":"WI",
    "sg:website":"www.frv.com",
    "wof:name":"FRV Inc",
    "wof:placetype":"venue"
},
  "geometry": {"coordinates":[-88.060415,44.447835],"type":"Point"}
}