{
  "type": "Feature",
  "properties": {
    "iso:country":"US",
    "sg:address":"25289 Co Hwy T",
    "sg:city":"Richland Center",
    "sg:classifiers":[
        {
            "category":"Farming",
            "subcategory":"Berry Farm",
            "type":"Manufacturing & Wholesale Goods"
        }
    ],
    "sg:phone":"+1 608 585 2194",
    "sg:postcode":"53581",
    "sg:province":"WI",
    "sg:tags":[
        "crop",
        "general"
    ],
    "wof:name":"Durst Hollow Farms",
    "wof:placetype":"venue"
},
  "geometry": {"coordinates":[-90.22041299999999,43.331403],"type":"Point"}
}