{
  "type": "Feature",
  "properties": {
    "iso:country":"US",
    "sg:address":"488 South St",
    "sg:city":"Green Lake",
    "sg:classifiers":[
        {
            "category":"Travel",
            "subcategory":"Hotels & Motels",
            "type":"Entertainment"
        }
    ],
    "sg:phone":"+1 920 294 3318",
    "sg:postcode":"54941",
    "sg:province":"WI",
    "wof:name":"Lakeside Motel",
    "wof:placetype":"venue"
},
  "geometry": {"coordinates":[-88.96096799999999,43.844382],"type":"Point"}
}