{
  "type": "Feature",
  "properties": {
    "iso:country":"US",
    "sg:address":"1929 N Main St",
    "sg:city":"Racine",
    "sg:classifiers":[
        {
            "category":"Recreation",
            "type":"Entertainment"
        }
    ],
    "sg:phone":"+1 262 634 3062",
    "sg:postcode":"53402",
    "sg:province":"WI",
    "sg:tags":[
        "goo",
        "mfg"
    ],
    "wof:name":"Mandys Charters",
    "wof:placetype":"venue"
},
  "geometry": {"coordinates":[-87.78480500000001,42.74552],"type":"Point"}
}