{
  "type": "Feature",
  "properties": {
    "iso:country":"US",
    "sg:address":"2818 Glendale Ave",
    "sg:city":"Wausau",
    "sg:classifiers":[
        {
            "category":"Professional",
            "subcategory":"Engineering",
            "type":"Services"
        }
    ],
    "sg:phone":"+1 715 845 2782",
    "sg:postcode":"54401",
    "sg:province":"WI",
    "wof:name":"JRW Enterprises",
    "wof:placetype":"venue"
},
  "geometry": {"coordinates":[-89.672948,44.961937],"type":"Point"}
}