{
  "type": "Feature",
  "properties": {
    "iso:country":"US",
    "sg:address":"7833 W Becher St",
    "sg:city":"Milwaukee",
    "sg:classifiers":[
        {
            "category":"Shopping",
            "subcategory":"Jewelry",
            "type":"Retail Goods"
        }
    ],
    "sg:phone":"+1 414 543 4653",
    "sg:postcode":"53219",
    "sg:province":"WI",
    "wof:name":"Custom Bridal Jewelry Inc",
    "wof:placetype":"venue"
},
  "geometry": {"coordinates":[-88.011212,43.006244],"type":"Point"}
}