{
  "type": "Feature",
  "properties": {
    "iso:country":"US",
    "sg:address":"7001 Dakota Rd",
    "sg:city":"Mayville",
    "sg:classifiers":[
        {
            "category":"Government",
            "subcategory":"Office",
            "type":"Public Place"
        }
    ],
    "sg:phone":"+1 920 387 5200",
    "sg:postcode":"53050",
    "sg:province":"WI",
    "sg:tags":[
        "executive"
    ],
    "wof:name":"Federal Aviation ADM Systems",
    "wof:placetype":"venue"
},
  "geometry": {"coordinates":[-88.489946,43.447705],"type":"Point"}
}