{
  "type": "Feature",
  "properties": {
    "addr:full":"4223 88th Pl Kenosha WI 53142",
    "addr:housenumber":"4223",
    "addr:postcode":"53142",
    "addr:street":"88Th Pl",
    "iso:country":"US",
    "sg:address":"4223 88th Pl",
    "sg:city":"Kenosha",
    "sg:classifiers":[
        {
            "category":"Professional",
            "subcategory":"Computer Services",
            "type":"Services"
        }
    ],
    "sg:phone":"+1 262 620 2734",
    "sg:postcode":"53142",
    "sg:province":"WI",
    "sg:tags":[
        "design",
        "system",
        "network"
    ],
    "wof:name":"Midwest Medical Technologies Of America",
    "wof:placetype":"venue"
},
  "geometry": {"coordinates":[-87.859253,42.545763],"type":"Point"}
}