{
  "type": "Feature",
  "properties": {
    "iso:country":"US",
    "sg:address":"10 E Doty St",
    "sg:city":"Madison",
    "sg:classifiers":[
        {
            "category":"Utilities",
            "subcategory":"Natural Gas",
            "type":"Services"
        }
    ],
    "sg:phone":"+1 608 280 7350",
    "sg:postcode":"53703",
    "sg:province":"WI",
    "sg:tags":[
        "distribution"
    ],
    "wof:name":"XCEL Energy",
    "wof:placetype":"venue"
},
  "geometry": {"coordinates":[-89.381142,43.073995],"type":"Point"}
}