{
  "type": "Feature",
  "properties": {
    "iso:country":"US",
    "sg:address":"1021 Green Acres Ln",
    "sg:city":"Neenah",
    "sg:classifiers":[
        {
            "category":"Health Services",
            "subcategory":"Nursing And Care Facility",
            "type":"Services"
        }
    ],
    "sg:phone":"+1 920 722 0375",
    "sg:postcode":"54956",
    "sg:province":"WI",
    "wof:name":"Family Services",
    "wof:placetype":"venue"
},
  "geometry": {"coordinates":[-88.492886,44.169545],"type":"Point"}
}