{
  "type": "Feature",
  "properties": {
    "iso:country":"US",
    "sg:address":"450 Interchange N",
    "sg:city":"Lake Geneva",
    "sg:classifiers":[
        {
            "category":"Manufacturing",
            "subcategory":"Metals",
            "type":"Manufacturing & Wholesale Goods"
        }
    ],
    "sg:phone":"+1 262 248 6157",
    "sg:postcode":"53147",
    "sg:province":"WI",
    "sg:tags":[
        "stamping"
    ],
    "wof:name":"Hay Manufacturing Inc",
    "wof:placetype":"venue"
},
  "geometry": {"coordinates":[-88.428748,42.605384],"type":"Point"}
}