{
  "type": "Feature",
  "properties": {
    "iso:country":"US",
    "sg:address":"4430 S Green Ridge Cir",
    "sg:city":"Milwaukee",
    "sg:classifiers":[
        {
            "category":"Professional",
            "type":"Services"
        }
    ],
    "sg:phone":"+1 414 329 7214",
    "sg:postcode":"53220",
    "sg:province":"WI",
    "wof:name":"Enjayo Inc",
    "wof:placetype":"venue"
},
  "geometry": {"coordinates":[-88.005532,42.964734],"type":"Point"}
}