{
  "type": "Feature",
  "properties": {
    "iso:country":"US",
    "sg:address":"10395 26th Ave",
    "sg:city":"Eau Claire",
    "sg:classifiers":[
        {
            "category":"Autos & Motor Vehicles",
            "subcategory":"Automobile Sales",
            "type":"Retail Goods"
        }
    ],
    "sg:phone":"+1 715 723 1581",
    "sg:postcode":"54703",
    "sg:province":"WI",
    "sg:tags":[
        "body",
        "use",
        "used"
    ],
    "wof:name":"Nicks Auto Sales",
    "wof:placetype":"venue"
},
  "geometry": {"coordinates":[-91.459221,44.881203],"type":"Point"}
}