{
  "type": "Feature",
  "properties": {
    "iso:country":"US",
    "sg:address":"1941 Ashland Ave",
    "sg:city":"Sheboygan",
    "sg:classifiers":[
        {
            "category":"Building & Trades",
            "subcategory":"Construction",
            "type":"Services"
        }
    ],
    "sg:phone":"+1 920 458 8188",
    "sg:postcode":"53081",
    "sg:province":"WI",
    "sg:tags":[
        "drywall",
        "contractor"
    ],
    "wof:name":"A & B Drywall",
    "wof:placetype":"venue"
},
  "geometry": {"coordinates":[-87.732482,43.729791],"type":"Point"}
}