{
  "type": "Feature",
  "properties": {
    "iso:country":"US",
    "sg:address":"301 Spring St",
    "sg:city":"Kendall",
    "sg:classifiers":[
        {
            "category":"Organizations",
            "subcategory":"Religious Organization",
            "type":"Services"
        }
    ],
    "sg:phone":"+1 608 463 7166",
    "sg:postcode":"54638",
    "sg:province":"WI",
    "sg:tags":[
        "church"
    ],
    "wof:name":"St Joseph's Church",
    "wof:placetype":"venue"
},
  "geometry": {"coordinates":[-90.369721,43.796883],"type":"Point"}
}