{
  "type": "Feature",
  "properties": {
    "addr:full":"5400 W Washington Blvd Milwaukee WI 53208",
    "addr:housenumber":"5400",
    "addr:postcode":"53208",
    "addr:street":"W Washington Blvd",
    "iso:country":"US",
    "sg:address":"5400 W Washington Blvd",
    "sg:city":"Milwaukee",
    "sg:classifiers":[
        {
            "category":"Organizations",
            "subcategory":"Religious Organization",
            "type":"Services"
        }
    ],
    "sg:phone":"+1 414 453 1928",
    "sg:postcode":"53208",
    "sg:province":"WI",
    "sg:tags":[
        "church"
    ],
    "wof:name":"St Sebastian Congregation",
    "wof:placetype":"venue"
},
  "geometry": {"coordinates":[-87.982078,43.052945],"type":"Point"}
}