{
  "type": "Feature",
  "properties": {
    "iso:country":"US",
    "sg:address":"35936 Osseo Rd",
    "sg:city":"Independence",
    "sg:classifiers":[
        {
            "category":"Autos & Motor Vehicles",
            "subcategory":"Automobile Sales",
            "type":"Retail Goods"
        }
    ],
    "sg:phone":"+1 715 985 2122",
    "sg:postcode":"54747",
    "sg:province":"WI",
    "sg:tags":[
        "dealers-used",
        "car",
        "used",
        "cars-wholesale",
        "new"
    ],
    "wof:name":"Kb Auto Sales",
    "wof:placetype":"venue"
},
  "geometry": {"coordinates":[-91.42351600000001,44.365301],"type":"Point"}
}