{
  "type": "Feature",
  "properties": {
    "iso:country":"US",
    "sg:address":"1105 E Keefe Ave",
    "sg:city":"Milwaukee",
    "sg:classifiers":[
        {
            "category":"Social Services",
            "subcategory":"Job Training",
            "type":"Services"
        },
        {
            "category":"Education",
            "subcategory":"Vocational School",
            "type":"Public Place"
        }
    ],
    "sg:phone":"+1 414 964 5119",
    "sg:postcode":"53212",
    "sg:province":"WI",
    "sg:tags":[
        "consultant",
        "business"
    ],
    "wof:name":"Lestarge & Associates",
    "wof:placetype":"venue"
},
  "geometry": {"coordinates":[-87.897442,43.081988],"type":"Point"}
}