{
  "type": "Feature",
  "properties": {
    "iso:country":"US",
    "sg:address":"325 W Roberta Ave",
    "sg:city":"Waukesha",
    "sg:classifiers":[
        {
            "category":"Building & Trades",
            "subcategory":"Construction",
            "type":"Services"
        }
    ],
    "sg:phone":"+1 262 549 5197",
    "sg:postcode":"53186",
    "sg:province":"WI",
    "sg:tags":[
        "home",
        "improvement"
    ],
    "wof:name":"Plehn Plastering Co Inc",
    "wof:placetype":"venue"
},
  "geometry": {"coordinates":[-88.232273,42.99345],"type":"Point"}
}