{
  "type": "Feature",
  "properties": {
    "iso:country":"US",
    "sg:address":"1551 S 169th St",
    "sg:city":"New Berlin",
    "sg:classifiers":[
        {
            "category":"Real Estate",
            "subcategory":"Real Estate Agent",
            "type":"Services"
        }
    ],
    "sg:phone":"+1 262 782 2110",
    "sg:postcode":"53151",
    "sg:province":"WI",
    "sg:tags":[
        "inspection"
    ],
    "wof:name":"A To Z Home Inspection Svc",
    "wof:placetype":"venue"
},
  "geometry": {"coordinates":[-88.12346599999999,43.014129],"type":"Point"}
}