{
  "type": "Feature",
  "properties": {
    "iso:country":"US",
    "sg:address":"1189 Quarter Rd",
    "sg:city":"Merrill",
    "sg:classifiers":[
        {
            "category":"Farming",
            "subcategory":"Orchard",
            "type":"Manufacturing & Wholesale Goods"
        }
    ],
    "sg:phone":"+1 715 536 1207",
    "sg:postcode":"54452",
    "sg:province":"WI",
    "sg:tags":[
        "grove",
        "management"
    ],
    "wof:name":"Pagoria & Pagoria",
    "wof:placetype":"venue"
},
  "geometry": {"coordinates":[-89.7238,45.160117],"type":"Point"}
}