{
  "type": "Feature",
  "properties": {
    "iso:country":"US",
    "sg:address":"8619 S Market Pl",
    "sg:city":"Oak Creek",
    "sg:classifiers":[
        {
            "category":"Shopping",
            "subcategory":"Gifts & Souvenirs",
            "type":"Retail Goods"
        }
    ],
    "sg:phone":"+1 414 570 7579",
    "sg:postcode":"53154",
    "sg:province":"WI",
    "sg:tags":[
        "collectible"
    ],
    "wof:name":"Touch Down Sports",
    "wof:placetype":"venue"
},
  "geometry": {"coordinates":[-87.86371699999999,42.886129],"type":"Point"}
}