{
  "type": "Feature",
  "properties": {
    "iso:country":"US",
    "sg:address":"6701 Seybold Rd",
    "sg:city":"Madison",
    "sg:classifiers":[
        {
            "category":"Shopping",
            "subcategory":"Bicycles & Sporting Goods",
            "type":"Retail Goods"
        }
    ],
    "sg:phone":"+1 608 274 0223",
    "sg:postcode":"53719",
    "sg:province":"WI",
    "sg:tags":[
        "equipment",
        "playground"
    ],
    "wof:name":"Park & Recreation Products Inc",
    "wof:placetype":"venue"
},
  "geometry": {"coordinates":[-89.501615,43.051661],"type":"Point"}
}