{
  "type": "Feature",
  "properties": {
    "addr:full":"215 Spring St Kendall WI 54638",
    "addr:housenumber":"215",
    "addr:postcode":"54638",
    "addr:street":"Spring St",
    "iso:country":"US",
    "sg:address":"215 Spring St",
    "sg:city":"Kendall",
    "sg:classifiers":[
        {
            "category":"Government",
            "subcategory":"Office",
            "type":"Public Place"
        }
    ],
    "sg:phone":"+1 608 463 7559",
    "sg:postcode":"54638",
    "sg:province":"WI",
    "sg:tags":[
        "village"
    ],
    "wof:name":"Town Shop",
    "wof:placetype":"venue"
},
  "geometry": {"coordinates":[-90.370041,43.796891],"type":"Point"}
}