{
  "type": "Feature",
  "properties": {
    "addr:full":"4421 S Kansas Ave Milwaukee WI 53235",
    "addr:housenumber":"4421",
    "addr:postcode":"53235",
    "addr:street":"S Kansas Ave",
    "iso:country":"US",
    "sg:address":"4421 S Kansas Ave",
    "sg:city":"Milwaukee",
    "sg:classifiers":[
        {
            "category":"Utilities",
            "subcategory":"Telephone",
            "type":"Services"
        }
    ],
    "sg:phone":"+1 414 489 1000",
    "sg:postcode":"53235",
    "sg:province":"WI",
    "sg:tags":[
        "communications"
    ],
    "wof:name":"On-Line Cable Services Inc",
    "wof:placetype":"venue"
},
  "geometry": {"coordinates":[-87.88688399999999,42.965166],"type":"Point"}
}