{
  "type": "Feature",
  "properties": {
    "iso:country":"US",
    "sg:address":"400 S 2nd St",
    "sg:city":"Alma",
    "sg:classifiers":[
        {
            "category":"Real Estate",
            "subcategory":"Real Estate Services",
            "type":"Services"
        }
    ],
    "sg:phone":"+1 608 685 3895",
    "sg:postcode":"54610",
    "sg:province":"WI",
    "sg:tags":[
        "company",
        "title"
    ],
    "wof:name":"Jensen Abstracting & Title",
    "wof:placetype":"venue"
},
  "geometry": {"coordinates":[-91.912555,44.317709],"type":"Point"}
}