{
  "type": "Feature",
  "properties": {
    "addr:full":"2040 Winnebago St Madison WI 53704",
    "addr:housenumber":"2040",
    "addr:postcode":"53704",
    "addr:street":"Winnebago St",
    "iso:country":"US",
    "sg:address":"2040 Winnebago St",
    "sg:city":"Madison",
    "sg:classifiers":[
        {
            "category":"Real Estate",
            "subcategory":"Architect",
            "type":"Services"
        }
    ],
    "sg:phone":"+1 608 271 0140",
    "sg:postcode":"53704",
    "sg:province":"WI",
    "wof:name":"Knapp Schmidt Architects Inc",
    "wof:placetype":"venue"
},
  "geometry": {"coordinates":[-89.354848,43.092468],"type":"Point"}
}