{
  "type": "Feature",
  "properties": {
    "iso:country":"US",
    "sg:address":"11120 Newton Lake Rd",
    "sg:city":"Athelstane",
    "sg:classifiers":[
        {
            "category":"Travel",
            "subcategory":"Hotels & Motels",
            "type":"Entertainment"
        }
    ],
    "sg:phone":"+1 715 757 2122",
    "sg:postcode":"54104",
    "sg:province":"WI",
    "sg:tags":[
        "operation"
    ],
    "wof:name":"Bayer Newton Lake Lodge",
    "wof:placetype":"venue"
},
  "geometry": {"coordinates":[-88.120718,45.366762],"type":"Point"}
}