{
  "type": "Feature",
  "properties": {
    "iso:country":"US",
    "sg:address":"403 Grand Ave",
    "sg:city":"Merrill",
    "sg:classifiers":[
        {
            "category":"Insurance",
            "subcategory":"Insurance Agent",
            "type":"Services"
        }
    ],
    "sg:phone":"+1 715 536 2551",
    "sg:postcode":"54452",
    "sg:province":"WI",
    "wof:name":"Thrivent Financial-Lutherans",
    "wof:placetype":"venue"
},
  "geometry": {"coordinates":[-89.705713,45.180298],"type":"Point"}
}