{
  "type": "Feature",
  "properties": {
    "iso:country":"US",
    "sg:address":"1145 Clyde Hanson Dr",
    "sg:city":"Hammond",
    "sg:classifiers":[
        {
            "category":"Manufacturing",
            "subcategory":"Tools & Machinery",
            "type":"Manufacturing & Wholesale Goods"
        }
    ],
    "sg:phone":"+1 715 796 2200",
    "sg:postcode":"54015",
    "sg:province":"WI",
    "sg:tags":[
        "pattern",
        "industrial",
        "mfg"
    ],
    "wof:name":"Star Pattern Works Inc",
    "wof:placetype":"venue"
},
  "geometry": {"coordinates":[-92.43773299999999,44.968411],"type":"Point"}
}