{
  "type": "Feature",
  "properties": {
    "iso:country":"US",
    "sg:address":"9254 Woodside School Rd",
    "sg:city":"Cambridge",
    "sg:phone":"+1 608 423 3537",
    "sg:postcode":"53523",
    "sg:province":"WI",
    "sg:tags":[
        "farm",
        "corn"
    ],
    "wof:name":"John Bakes Farm",
    "wof:placetype":"venue"
},
  "geometry": {"coordinates":[-88.991007,42.932777],"type":"Point"}
}