{
  "type": "Feature",
  "properties": {
    "iso:country":"US",
    "sg:address":"2292 Ridgewood Rd",
    "sg:city":"Grafton",
    "sg:classifiers":[
        {
            "category":"Organizations",
            "subcategory":"Community Association",
            "type":"Services"
        }
    ],
    "sg:phone":"+1 262 375 2239",
    "sg:postcode":"53024",
    "sg:province":"WI",
    "wof:name":"Northern Cross Scnce Fundation",
    "wof:placetype":"venue"
},
  "geometry": {"coordinates":[-87.91851200000001,43.361743],"type":"Point"}
}