{
  "type": "Feature",
  "properties": {
    "iso:country":"US",
    "sg:address":"603 N 4th St",
    "sg:city":"Milwaukee",
    "sg:classifiers":[
        {
            "category":"Autos & Motor Vehicles",
            "subcategory":"Automobile Sales",
            "type":"Retail Goods"
        },
        {
            "category":"Retail",
            "subcategory":"Auto Rental",
            "type":"Services"
        }
    ],
    "sg:phone":"+1 414 276 1634",
    "sg:postcode":"53203",
    "sg:province":"WI",
    "sg:tags":[
        "car",
        "leasing",
        "truck"
    ],
    "sg:website":"http://budget.com/IYP_tl",
    "wof:name":"Budget Rent A Car",
    "wof:placetype":"venue"
},
  "geometry": {"coordinates":[-87.916061,43.037409],"type":"Point"}
}