{
  "type": "Feature",
  "properties": {
    "iso:country":"US",
    "sg:address":"451 W North St",
    "sg:city":"Juneau",
    "sg:classifiers":[
        {
            "category":"Government",
            "subcategory":"Office",
            "type":"Public Place"
        }
    ],
    "sg:phone":"+1 920 386 9999",
    "sg:postcode":"53039",
    "sg:province":"WI",
    "sg:tags":[
        "farm",
        "agency"
    ],
    "wof:name":"Farm Service Agency",
    "wof:placetype":"venue"
},
  "geometry": {"coordinates":[-88.712851,43.410167],"type":"Point"}
}