{
  "type": "Feature",
  "properties": {
    "addr:full":"700 N Water St Milwaukee WI 53202",
    "addr:housenumber":"700",
    "addr:postcode":"53202",
    "addr:street":"N Water St",
    "iso:country":"US",
    "sg:address":"700 N Water St",
    "sg:city":"Milwaukee",
    "sg:classifiers":[
        {
            "category":"Travel",
            "subcategory":"Travel Agent",
            "type":"Entertainment"
        }
    ],
    "sg:phone":"+1 414 225 4431",
    "sg:postcode":"53202",
    "sg:province":"WI",
    "sg:tags":[
        "ticket",
        "airline"
    ],
    "wof:name":"Northwest Airlines",
    "wof:placetype":"venue"
},
  "geometry": {"coordinates":[-87.909235,43.039808],"type":"Point"}
}