{
  "type": "Feature",
  "properties": {
    "iso:country":"US",
    "sg:address":"685 McNally Ln",
    "sg:city":"Brookfield",
    "sg:classifiers":[
        {
            "category":"Home & Garden",
            "subcategory":"Carpets & Floor Coverings",
            "type":"Retail Goods"
        }
    ],
    "sg:phone":"+1 262 879 9915",
    "sg:postcode":"53045",
    "sg:province":"WI",
    "wof:name":"Don & Kays Carpet Service",
    "wof:placetype":"venue"
},
  "geometry": {"coordinates":[-88.150767,43.025487],"type":"Point"}
}