{
  "type": "Feature",
  "properties": {
    "iso:country":"US",
    "sg:address":"13400 Highwood Dr",
    "sg:city":"Elm Grove",
    "sg:classifiers":[
        {
            "category":"Health Services",
            "subcategory":"Doctor",
            "type":"Services"
        }
    ],
    "sg:phone":"+1 262 821 5586",
    "sg:postcode":"53122",
    "sg:province":"WI",
    "sg:tags":[
        "medical"
    ],
    "wof:name":"Dennis G Vincent MD",
    "wof:placetype":"venue"
},
  "geometry": {"coordinates":[-88.079892,43.039432],"type":"Point"}
}