{
  "type": "Feature",
  "properties": {
    "iso:country":"US",
    "sg:address":"820 S 8th Ave",
    "sg:city":"Wausau",
    "sg:classifiers":[
        {
            "category":"Organizations",
            "subcategory":"Religious Organization",
            "type":"Services"
        }
    ],
    "sg:phone":"+1 715 842 0477",
    "sg:postcode":"54401",
    "sg:province":"WI",
    "sg:tags":[
        "church"
    ],
    "wof:name":"Freedom By The Word Church",
    "wof:placetype":"venue"
},
  "geometry": {"coordinates":[-89.64543999999999,44.953776],"type":"Point"}
}