{
  "type": "Feature",
  "properties": {
    "addr:full":"414 Beardsley St Kewaunee WI 54216",
    "addr:housenumber":"414",
    "addr:postcode":"54216",
    "addr:street":"Beardsley St",
    "iso:country":"US",
    "sg:address":"414 Beardsley St",
    "sg:city":"Kewaunee",
    "sg:classifiers":[
        {
            "category":"Freight",
            "type":"Transportation"
        }
    ],
    "sg:phone":"+1 920 388 4633",
    "sg:postcode":"54216",
    "sg:province":"WI",
    "sg:tags":[
        "operator",
        "local",
        "trucking"
    ],
    "wof:name":"Pam Wagner Trucking",
    "wof:placetype":"venue"
},
  "geometry": {"coordinates":[-87.50724200000001,44.45845],"type":"Point"}
}