{
  "type": "Feature",
  "properties": {
    "iso:country":"US",
    "sg:address":"425 N Westfield Rd",
    "sg:city":"Madison",
    "sg:classifiers":[
        {
            "category":"Communications",
            "type":"Services"
        }
    ],
    "sg:phone":"+1 608 833 2050",
    "sg:postcode":"53717",
    "sg:province":"WI",
    "wof:name":"Qcomm",
    "wof:placetype":"venue"
},
  "geometry": {"coordinates":[-89.51023000000001,43.072622],"type":"Point"}
}