{
  "type": "Feature",
  "properties": {
    "iso:country":"US",
    "sg:address":"2627 Jacato Dr",
    "sg:city":"Racine",
    "sg:classifiers":[
        {
            "category":"Real Estate",
            "subcategory":"Real Estate Operator",
            "type":"Services"
        }
    ],
    "sg:phone":"+1 262 633 1625",
    "sg:postcode":"53404",
    "sg:province":"WI",
    "sg:tags":[
        "apartment"
    ],
    "wof:name":"Parrish Properties",
    "wof:placetype":"venue"
},
  "geometry": {"coordinates":[-87.81166399999999,42.752714],"type":"Point"}
}