{
  "type": "Feature",
  "properties": {
    "addr:full":"4905 Doris Rd New Franken WI 54229",
    "addr:housenumber":"4905",
    "addr:postcode":"54229",
    "addr:street":"Doris Rd",
    "iso:country":"US",
    "sg:address":"4905 Doris Rd",
    "sg:city":"New Franken",
    "sg:classifiers":[
        {
            "category":"Retail",
            "subcategory":"Auto Repair",
            "type":"Services"
        }
    ],
    "sg:phone":"+1 920 866 1137",
    "sg:postcode":"54229",
    "sg:province":"WI",
    "sg:tags":[
        "body"
    ],
    "wof:name":"Body By Doug",
    "wof:placetype":"venue"
},
  "geometry": {"coordinates":[-87.832994,44.589327],"type":"Point"}
}