{
  "type": "Feature",
  "properties": {
    "iso:country":"US",
    "sg:address":"6356 Stonefield Rd",
    "sg:city":"Middleton",
    "sg:classifiers":[
        {
            "category":"Shopping",
            "type":"Retail Goods"
        }
    ],
    "sg:phone":"+1 608 836 5967",
    "sg:postcode":"53562",
    "sg:province":"WI",
    "sg:tags":[
        "wedding",
        "supply"
    ],
    "wof:name":"Forget Me Not Wi",
    "wof:placetype":"venue"
},
  "geometry": {"coordinates":[-89.49433999999999,43.085323],"type":"Point"}
}