{
  "type": "Feature",
  "properties": {
    "iso:country":"US",
    "sg:address":"4514 N Oakland Ave",
    "sg:city":"Milwaukee",
    "sg:classifiers":[
        {
            "category":"Autos & Motor Vehicles",
            "subcategory":"Fuel & Gas Station",
            "type":"Retail Goods"
        }
    ],
    "sg:phone":"+1 414 962 7950",
    "sg:postcode":"53211",
    "sg:province":"WI",
    "sg:tags":[
        "repair",
        "grocer",
        "station",
        "gasoline",
        "general"
    ],
    "wof:name":"Matt Rech Service Inc",
    "wof:placetype":"venue"
},
  "geometry": {"coordinates":[-87.887332,43.099719],"type":"Point"}
}