{
  "type": "Feature",
  "properties": {
    "addr:full":"3529 Grawe Ln Fountain City WI 54629",
    "addr:housenumber":"3529",
    "addr:postcode":"54629",
    "addr:street":"Grawe Ln",
    "iso:country":"US",
    "sg:address":"3529 Grawe Ln",
    "sg:city":"Fountain City",
    "sg:classifiers":[
        {
            "category":"Building & Trades",
            "subcategory":"Plumbing",
            "type":"Services"
        }
    ],
    "sg:phone":"+1 507 450 7993",
    "sg:postcode":"54629",
    "sg:province":"WI",
    "sg:tags":[
        "contractor"
    ],
    "wof:name":"Reisdorf Heating LLC",
    "wof:placetype":"venue"
},
  "geometry": {"coordinates":[-91.60677200000001,44.08269],"type":"Point"}
}