{
  "type": "Feature",
  "properties": {
    "addr:full":"3063 Townline Rd Kewaunee WI 54216",
    "addr:housenumber":"3063",
    "addr:postcode":"54216",
    "addr:street":"Townline Rd",
    "iso:country":"US",
    "sg:address":"3063 Townline Rd",
    "sg:city":"Kewaunee",
    "sg:classifiers":[
        {
            "category":"Autos & Motor Vehicles",
            "subcategory":"Motorcycle Sales",
            "type":"Retail Goods"
        }
    ],
    "sg:phone":"+1 920 388 4192",
    "sg:postcode":"54216",
    "sg:province":"WI",
    "wof:name":"Rohr Custom Cycle",
    "wof:placetype":"venue"
},
  "geometry": {"coordinates":[-87.614002,44.414305],"type":"Point"}
}