{
  "type": "Feature",
  "properties": {
    "iso:country":"US",
    "sg:address":"2103 State Rd",
    "sg:city":"La Crosse",
    "sg:classifiers":[
        {
            "category":"Building & Trades",
            "subcategory":"Construction",
            "type":"Services"
        }
    ],
    "sg:phone":"+1 608 788 5115",
    "sg:postcode":"54601",
    "sg:province":"WI",
    "sg:tags":[
        "house"
    ],
    "wof:name":"Wolfe Construction Inc",
    "wof:placetype":"venue"
},
  "geometry": {"coordinates":[-91.224831,43.799562],"type":"Point"}
}