{
  "type": "Feature",
  "properties": {
    "iso:country":"US",
    "sg:address":"1050 Legion Dr",
    "sg:city":"Elm Grove",
    "sg:classifiers":[
        {
            "category":"Professional",
            "subcategory":"Management & Consulting",
            "type":"Services"
        }
    ],
    "sg:phone":"+1 262 796 1444",
    "sg:postcode":"53122",
    "sg:province":"WI",
    "sg:tags":[
        "marketing",
        "company",
        "promotional"
    ],
    "wof:name":"Salessmith Inc",
    "wof:placetype":"venue"
},
  "geometry": {"coordinates":[-88.08018,43.044969],"type":"Point"}
}