{
  "type": "Feature",
  "properties": {
    "iso:country":"US",
    "sg:address":"1031 E Grand Ave",
    "sg:city":"Eau Claire",
    "sg:classifiers":[
        {
            "category":"Building & Trades",
            "subcategory":"Construction",
            "type":"Services"
        }
    ],
    "sg:phone":"+1 715 855 7970",
    "sg:postcode":"54701",
    "sg:province":"WI",
    "sg:tags":[
        "contractor"
    ],
    "wof:name":"Dutch Construction",
    "wof:placetype":"venue"
},
  "geometry": {"coordinates":[-91.487357,44.813037],"type":"Point"}
}