{
  "type": "Feature",
  "properties": {
    "addr:full":"155 E Silver Spring Dr Milwaukee WI 53217",
    "addr:housenumber":"155",
    "addr:postcode":"53217",
    "addr:street":"E Silver Spring Dr",
    "iso:country":"US",
    "sg:address":"155 E Silver Spring Dr",
    "sg:city":"Milwaukee",
    "sg:classifiers":[
        {
            "category":"Social Services",
            "type":"Services"
        }
    ],
    "sg:phone":"+1 414 332 4114",
    "sg:postcode":"53217",
    "sg:province":"WI",
    "wof:name":"Silver Sprng Psychothrpy Assoc",
    "wof:placetype":"venue"
},
  "geometry": {"coordinates":[-87.908055,43.118467],"type":"Point"}
}