{
  "type": "Feature",
  "properties": {
    "iso:country":"US",
    "sg:address":"1712 S 8th St",
    "sg:city":"Sheboygan",
    "sg:classifiers":[
        {
            "category":"Retail",
            "subcategory":"Auto Repair",
            "type":"Services"
        }
    ],
    "sg:phone":"+1 920 459 7484",
    "sg:postcode":"53081",
    "sg:province":"WI",
    "sg:tags":[
        "tv",
        "stereo"
    ],
    "wof:name":"Jims Auto Stereo & T V",
    "wof:placetype":"venue"
},
  "geometry": {"coordinates":[-87.713035,43.734881],"type":"Point"}
}