{
  "type": "Feature",
  "properties": {
    "iso:country":"US",
    "sg:address":"177 S Main St",
    "sg:city":"Lodi",
    "sg:classifiers":[
        {
            "category":"Professional",
            "subcategory":"Accounting & Tax Preparation",
            "type":"Services"
        }
    ],
    "sg:phone":"+1 608 592 7441",
    "sg:postcode":"53555",
    "sg:province":"WI",
    "wof:name":"Brokish Stephen D",
    "wof:placetype":"venue"
},
  "geometry": {"coordinates":[-89.526368,43.313613],"type":"Point"}
}