{
  "type": "Feature",
  "properties": {
    "iso:country":"US",
    "sg:address":"1090 Arnett Rd",
    "sg:city":"Woodruff",
    "sg:classifiers":[
        {
            "category":"Real Estate",
            "subcategory":"Real Estate Agent",
            "type":"Services"
        }
    ],
    "sg:phone":"+1 715 358 6556",
    "sg:postcode":"54568",
    "sg:province":"WI",
    "wof:name":"Town & Country Realty",
    "wof:placetype":"venue"
},
  "geometry": {"coordinates":[-89.746405,45.9027],"type":"Point"}
}