{
  "type": "Feature",
  "properties": {
    "addr:full":"8917 W Brown Deer Rd Milwaukee WI 53224",
    "addr:housenumber":"8917",
    "addr:postcode":"53224",
    "addr:street":"W Brown Deer Rd",
    "iso:country":"US",
    "sg:address":"8917 W Brown Deer Rd",
    "sg:city":"Milwaukee",
    "sg:classifiers":[
        {
            "category":"Shopping",
            "subcategory":"Department Store",
            "type":"Retail Goods"
        }
    ],
    "sg:phone":"+1 414 357 7723",
    "sg:postcode":"53224",
    "sg:province":"WI",
    "sg:tags":[
        "shop"
    ],
    "wof:name":"Family Dollar Store",
    "wof:placetype":"venue"
},
  "geometry": {"coordinates":[-88.019538,43.177692],"type":"Point"}
}