{
  "type": "Feature",
  "properties": {
    "iso:country":"US",
    "sg:address":"7220 W Ryan Rd",
    "sg:city":"Franklin",
    "sg:classifiers":[
        {
            "category":"Professional",
            "subcategory":"Accounting & Tax Preparation",
            "type":"Services"
        }
    ],
    "sg:phone":"+1 414 529 4520",
    "sg:postcode":"53132",
    "sg:province":"WI",
    "sg:tags":[
        "accountant"
    ],
    "wof:name":"Dunn's Accounting Svc",
    "wof:placetype":"venue"
},
  "geometry": {"coordinates":[-88.005861,42.872678],"type":"Point"}
}