{
  "type": "Feature",
  "properties": {
    "iso:country":"US",
    "sg:address":"15 9th St",
    "sg:city":"Clintonville",
    "sg:classifiers":[
        {
            "category":"Education",
            "subcategory":"Special Training",
            "type":"Public Place"
        }
    ],
    "sg:phone":"+1 715 823 5660",
    "sg:postcode":"54929",
    "sg:province":"WI",
    "sg:tags":[
        "instruction",
        "driving"
    ],
    "wof:name":"A J's Driving School",
    "wof:placetype":"venue"
},
  "geometry": {"coordinates":[-88.763211,44.621717],"type":"Point"}
}