{
  "type": "Feature",
  "properties": {
    "iso:country":"US",
    "sg:address":"4976 State Hwy 26",
    "sg:city":"Jefferson",
    "sg:classifiers":[
        {
            "category":"Autos & Motor Vehicles",
            "subcategory":"Automobile Sales",
            "type":"Retail Goods"
        }
    ],
    "sg:phone":"+1 920 674 6565",
    "sg:postcode":"53549",
    "sg:province":"WI",
    "sg:tags":[
        "car",
        "dealer"
    ],
    "wof:name":"N 26 Motor Sales",
    "wof:placetype":"venue"
},
  "geometry": {"coordinates":[-88.8077,43.029213],"type":"Point"}
}