{
  "type": "Feature",
  "properties": {
    "iso:country":"US",
    "sg:address":"3890 S Harmony Rd",
    "sg:city":"Peshtigo",
    "sg:classifiers":[
        {
            "category":"Government",
            "subcategory":"Fire Station",
            "type":"Public Place"
        }
    ],
    "sg:phone":"+1 715 789 2220",
    "sg:postcode":"54157",
    "sg:province":"WI",
    "sg:tags":[
        "department"
    ],
    "wof:name":"Grover-Porterfield Fire Dept",
    "wof:placetype":"venue"
},
  "geometry": {"coordinates":[-87.819804,45.092446],"type":"Point"}
}