{
  "type": "Feature",
  "properties": {
    "addr:full":"5455 Reddin Rd Wisconsin Rapids WI 54495",
    "addr:postcode":"5455;54495",
    "addr:street":"Reddin Rd",
    "iso:country":"US",
    "sg:address":"5455 Reddin Rd",
    "sg:city":"Wisconsin Rapids",
    "sg:classifiers":[
        {
            "category":"Home & Garden",
            "subcategory":"Building Materials",
            "type":"Retail Goods"
        }
    ],
    "sg:phone":"+1 715 424 5569",
    "sg:postcode":"54495",
    "sg:province":"WI",
    "wof:name":"Don Joosten Custom Millwork",
    "wof:placetype":"venue"
},
  "geometry": {"coordinates":[-89.814779,44.444813],"type":"Point"}
}