{
  "type": "Feature",
  "properties": {
    "addr:full":"3 E Spirit Ave Tomahawk WI 54487",
    "addr:housenumber":"3",
    "addr:postcode":"54487",
    "addr:street":"E Spirit Ave",
    "iso:country":"US",
    "sg:address":"3 E Spirit Ave",
    "sg:city":"Tomahawk",
    "sg:classifiers":[
        {
            "category":"Shopping",
            "subcategory":"Used Merchandise",
            "type":"Retail Goods"
        }
    ],
    "sg:phone":"+1 715 453 4085",
    "sg:postcode":"54487",
    "sg:province":"WI",
    "wof:name":"Antiques On Spirit",
    "wof:placetype":"venue"
},
  "geometry": {"coordinates":[-89.729254,45.470029],"type":"Point"}
}