{
  "type": "Feature",
  "properties": {
    "iso:country":"US",
    "sg:address":"4035 Hayes Rd",
    "sg:city":"Stratford",
    "sg:classifiers":[
        {
            "category":"Building & Trades",
            "subcategory":"Construction",
            "type":"Services"
        }
    ],
    "sg:phone":"+1 715 687 4254",
    "sg:postcode":"54484",
    "sg:province":"WI",
    "sg:tags":[
        "carpentry",
        "contractor"
    ],
    "wof:name":"Carpentry Plus",
    "wof:placetype":"venue"
},
  "geometry": {"coordinates":[-90.029928,44.799325],"type":"Point"}
}