{
  "type": "Feature",
  "properties": {
    "iso:country":"US",
    "sg:address":"1836 Industrial Dr",
    "sg:city":"Green Bay",
    "sg:classifiers":[
        {
            "category":"Autos & Motor Vehicles",
            "subcategory":"Motorcycle Sales",
            "type":"Retail Goods"
        }
    ],
    "sg:phone":"+1 920 468 5056",
    "sg:postcode":"54302",
    "sg:province":"WI",
    "wof:name":"Pecard Chemical Co",
    "wof:placetype":"venue"
},
  "geometry": {"coordinates":[-87.993016,44.485111],"type":"Point"}
}