{
  "type": "Feature",
  "properties": {
    "iso:country":"US",
    "sg:address":"5634 Polworth St",
    "sg:city":"Madison",
    "sg:classifiers":[
        {
            "category":"Retail",
            "subcategory":"Repair Shop",
            "type":"Services"
        }
    ],
    "sg:phone":"+1 608 271 8188",
    "sg:postcode":"53711",
    "sg:province":"WI",
    "sg:tags":[
        "electrical"
    ],
    "wof:name":"Neumann Communications",
    "wof:placetype":"venue"
},
  "geometry": {"coordinates":[-89.432664,42.993572],"type":"Point"}
}