{
  "type": "Feature",
  "properties": {
    "iso:country":"US",
    "sg:address":"11324 Burr Oak Rd",
    "sg:city":"Waterloo",
    "sg:classifiers":[
        {
            "category":"Farming",
            "subcategory":"Livestock Farm",
            "type":"Manufacturing & Wholesale Goods"
        }
    ],
    "sg:phone":"+1 920 623 4431",
    "sg:postcode":"53594",
    "sg:province":"WI",
    "sg:tags":[
        "hog",
        "or",
        "feedlot"
    ],
    "wof:name":"Richard Klubertanz",
    "wof:placetype":"venue"
},
  "geometry": {"coordinates":[-88.959912,43.28515],"type":"Point"}
}