{
  "type": "Feature",
  "properties": {
    "addr:full":"9 Horse Shoe Bend Madison WI 53705",
    "addr:housenumber":"9",
    "addr:postcode":"53705",
    "addr:street":"Horse Shoe Bend",
    "iso:country":"US",
    "sg:address":"9 Horse Shoe Bend",
    "sg:city":"Madison",
    "sg:classifiers":[
        {
            "category":"Professional",
            "subcategory":"Management & Consulting",
            "type":"Services"
        }
    ],
    "sg:phone":"+1 608 827 0827",
    "sg:postcode":"53705",
    "sg:province":"WI",
    "wof:name":"Paker Technical Consulting",
    "wof:placetype":"venue"
},
  "geometry": {"coordinates":[-89.49608000000001,43.068362],"type":"Point"}
}