{
  "type": "Feature",
  "properties": {
    "iso:country":"US",
    "sg:address":"20687 Bonniwell Rd",
    "sg:city":"Richfield",
    "sg:classifiers":[
        {
            "category":"Freight",
            "type":"Transportation"
        }
    ],
    "sg:phone":"+1 262 993 3384",
    "sg:postcode":"53076",
    "sg:province":"WI",
    "sg:tags":[
        "operator",
        "trucking"
    ],
    "wof:name":"Adventure Transportation LLC",
    "wof:placetype":"venue"
},
  "geometry": {"coordinates":[-88.166414,43.264776],"type":"Point"}
}