{
  "type": "Feature",
  "properties": {
    "iso:country":"US",
    "sg:address":"1837 Lafayette St",
    "sg:city":"Janesville",
    "sg:classifiers":[
        {
            "category":"Shopping",
            "subcategory":"Optical Goods",
            "type":"Retail Goods"
        }
    ],
    "sg:phone":"+1 608 756 0728",
    "sg:postcode":"53546",
    "sg:province":"WI",
    "wof:name":"Wisconsin Vision",
    "wof:placetype":"venue"
},
  "geometry": {"coordinates":[-89.029172,42.650294],"type":"Point"}
}