{
  "type": "Feature",
  "properties": {
    "addr:full":"1511 Wheelihan Ave Necedah WI 54646",
    "addr:housenumber":"1511",
    "addr:postcode":"54646",
    "addr:street":"Wheelihan Ave",
    "iso:country":"US",
    "sg:address":"1511 Wheelihan Ave",
    "sg:city":"Necedah",
    "sg:classifiers":[
        {
            "category":"Building & Trades",
            "subcategory":"Pest Control",
            "type":"Services"
        }
    ],
    "sg:phone":"+1 608 565 7234",
    "sg:postcode":"54646",
    "sg:province":"WI",
    "wof:name":"Paul Lewandoski",
    "wof:placetype":"venue"
},
  "geometry": {"coordinates":[-90.069577,44.009819],"type":"Point"}
}