{
  "type": "Feature",
  "properties": {
    "addr:full":"6200 S Ace Industrial Dr Cudahy WI 53110",
    "addr:housenumber":"6200",
    "addr:postcode":"53110",
    "addr:street":"S Ace Industrial Dr",
    "iso:country":"US",
    "sg:address":"6200 S Ace Industrial Dr",
    "sg:city":"Cudahy",
    "sg:classifiers":[
        {
            "category":"Airline",
            "type":"Transportation"
        }
    ],
    "sg:phone":"+1 414 762 3372",
    "sg:postcode":"53110",
    "sg:province":"WI",
    "sg:tags":[
        "courier",
        "air"
    ],
    "wof:name":"D H L Worldwide Express",
    "wof:placetype":"venue"
},
  "geometry": {"coordinates":[-87.883257,42.932362],"type":"Point"}
}