{
  "type": "Feature",
  "properties": {
    "iso:country":"US",
    "sg:address":"544 Main St",
    "sg:city":"Highland",
    "sg:classifiers":[
        {
            "category":"Retail",
            "subcategory":"Funeral Services",
            "type":"Services"
        }
    ],
    "sg:phone":"+1 608 929 4815",
    "sg:postcode":"53543",
    "sg:province":"WI",
    "sg:tags":[
        "director"
    ],
    "wof:name":"McGuire-Peterson-Houck Fnrl HM",
    "wof:placetype":"venue"
},
  "geometry": {"coordinates":[-90.380289,43.046318],"type":"Point"}
}