{
  "type": "Feature",
  "properties": {
    "iso:country":"US",
    "sg:address":"813 Gohres St",
    "sg:city":"La Crosse",
    "sg:classifiers":[
        {
            "category":"Building & Trades",
            "subcategory":"Construction",
            "type":"Services"
        }
    ],
    "sg:phone":"+1 608 784 5776",
    "sg:postcode":"54603",
    "sg:province":"WI",
    "sg:tags":[
        "house"
    ],
    "wof:name":"Storlie Construction",
    "wof:placetype":"venue"
},
  "geometry": {"coordinates":[-91.244075,43.849247],"type":"Point"}
}