{
  "type": "Feature",
  "properties": {
    "iso:country":"US",
    "sg:address":"821 Mc Comb Ave",
    "sg:city":"Rib Lake",
    "sg:classifiers":[
        {
            "category":"Personal",
            "subcategory":"Barber",
            "type":"Services"
        }
    ],
    "sg:phone":"+1 715 427 3707",
    "sg:postcode":"54470",
    "sg:province":"WI",
    "wof:name":"Georges Barber Shop",
    "wof:placetype":"venue"
},
  "geometry": {"coordinates":[-90.204161,45.319984],"type":"Point"}
}