{
  "type": "Feature",
  "properties": {
    "iso:country":"US",
    "sg:address":"1701 W Marquette St",
    "sg:city":"Appleton",
    "sg:classifiers":[
        {
            "category":"Organizations",
            "subcategory":"Religious Organization",
            "type":"Services"
        }
    ],
    "sg:phone":"+1 920 993 9289",
    "sg:postcode":"54914",
    "sg:province":"WI",
    "wof:name":"Faith Chariton-Mueller",
    "wof:placetype":"venue"
},
  "geometry": {"coordinates":[-88.43343299999999,44.282243],"type":"Point"}
}