{
  "type": "Feature",
  "properties": {
    "iso:country":"US",
    "sg:address":"25635 Grain Ave",
    "sg:city":"Tomah",
    "sg:classifiers":[
        {
            "category":"Freight",
            "type":"Transportation"
        }
    ],
    "sg:phone":"+1 608 372 2568",
    "sg:postcode":"54660",
    "sg:province":"WI",
    "sg:tags":[
        "trucking"
    ],
    "wof:name":"Badgerland Freight Service LLC",
    "wof:placetype":"venue"
},
  "geometry": {"coordinates":[-90.493571,43.968684],"type":"Point"}
}