{
  "type": "Feature",
  "properties": {
    "iso:country":"US",
    "sg:address":"11303 Co Rd B",
    "sg:city":"Lake Nebagamon",
    "sg:classifiers":[
        {
            "category":"Professional",
            "subcategory":"Computer Services",
            "type":"Services"
        }
    ],
    "sg:phone":"+1 715 398 7030",
    "sg:postcode":"54849",
    "sg:province":"WI",
    "sg:tags":[
        "consultant",
        "designer"
    ],
    "sg:website":"www.micro-tech-design.com",
    "wof:name":"Micro-Tech Corp",
    "wof:placetype":"venue"
},
  "geometry": {"coordinates":[-91.716342,46.515537],"type":"Point"}
}