{
  "type": "Feature",
  "properties": {
    "iso:country":"US",
    "sg:address":"4291 Oak Hill Rd",
    "sg:city":"Oregon",
    "sg:classifiers":[
        {
            "category":"Building & Trades",
            "subcategory":"Construction",
            "type":"Services"
        }
    ],
    "sg:phone":"+1 608 835 8579",
    "sg:postcode":"53575",
    "sg:province":"WI",
    "sg:tags":[
        "downspouts",
        "gutter",
        "contractor"
    ],
    "wof:name":"Precision Seamless Gutters & D",
    "wof:placetype":"venue"
},
  "geometry": {"coordinates":[-89.327831,42.903915],"type":"Point"}
}