{
  "type": "Feature",
  "properties": {
    "iso:country":"US",
    "sg:address":"2100 Edgewood Ct",
    "sg:city":"Kaukauna",
    "sg:classifiers":[
        {
            "category":"Manufacturing",
            "subcategory":"Retail Goods",
            "type":"Manufacturing & Wholesale Goods"
        }
    ],
    "sg:phone":"+1 920 766 1129",
    "sg:postcode":"54130",
    "sg:province":"WI",
    "sg:tags":[
        "product",
        "mfg"
    ],
    "wof:name":"After Hours Candles LLC",
    "wof:placetype":"venue"
},
  "geometry": {"coordinates":[-88.290663,44.279635],"type":"Point"}
}