{
  "type": "Feature",
  "properties": {
    "iso:country":"US",
    "sg:address":"6253 W Pierner Pl",
    "sg:city":"Milwaukee",
    "sg:classifiers":[
        {
            "category":"Autos & Motor Vehicles",
            "subcategory":"Auto Supplies",
            "type":"Retail Goods"
        }
    ],
    "sg:phone":"+1 414 354 6065",
    "sg:postcode":"53223",
    "sg:province":"WI",
    "sg:tags":[
        "repair"
    ],
    "wof:name":"Joes Auto Top",
    "wof:placetype":"venue"
},
  "geometry": {"coordinates":[-87.991857,43.185743],"type":"Point"}
}