{
  "type": "Feature",
  "properties": {
    "iso:country":"US",
    "sg:address":"2420 E Mason St",
    "sg:city":"Green Bay",
    "sg:classifiers":[
        {
            "category":"Restaurant",
            "type":"Food & Drink"
        }
    ],
    "sg:phone":"+1 920 406 8140",
    "sg:postcode":"54302",
    "sg:province":"WI",
    "wof:name":"Applebee's Neighborhood Grill",
    "wof:placetype":"venue"
},
  "geometry": {"coordinates":[-87.960905,44.487404],"type":"Point"}
}