{
  "type": "Feature",
  "properties": {
    "addr:full":"2846 Plantation Rd Pelican Lake WI 54463",
    "addr:housenumber":"2846",
    "addr:postcode":"54463",
    "addr:street":"Plantation Rd",
    "iso:country":"US",
    "sg:address":"2846 Plantation Rd",
    "sg:city":"Pelican Lake",
    "sg:classifiers":[
        {
            "category":"Professional",
            "type":"Services"
        }
    ],
    "sg:phone":"+1 715 487 6148",
    "sg:postcode":"54463",
    "sg:province":"WI",
    "wof:name":"Tracy J Guth",
    "wof:placetype":"venue"
},
  "geometry": {"coordinates":[-89.2392,45.490085],"type":"Point"}
}