{
  "type": "Feature",
  "properties": {
    "iso:country":"US",
    "sg:address":"920 Co Rd B",
    "sg:city":"Pulaski",
    "sg:classifiers":[
        {
            "category":"Restaurant",
            "type":"Food & Drink"
        }
    ],
    "sg:phone":"+1 920 822 5900",
    "sg:postcode":"54162",
    "sg:province":"WI",
    "wof:name":"Mc Donald's",
    "wof:placetype":"venue"
},
  "geometry": {"coordinates":[-88.218899,44.657297],"type":"Point"}
}