{
  "type": "Feature",
  "properties": {
    "addr:full":"8888 Kelly Rd Augusta WI 54722",
    "addr:housenumber":"8888",
    "addr:postcode":"54722",
    "addr:street":"Kelly Rd",
    "iso:country":"US",
    "sg:address":"8888 Kelly Rd",
    "sg:city":"Augusta",
    "sg:classifiers":[
        {
            "category":"Farming",
            "subcategory":"Dairy Farm",
            "type":"Manufacturing & Wholesale Goods"
        }
    ],
    "sg:phone":"+1 715 286 2139",
    "sg:postcode":"54722",
    "sg:province":"WI",
    "wof:name":"Kurt Schulz Farm",
    "wof:placetype":"venue"
},
  "geometry": {"coordinates":[-91.07405300000001,44.723485],"type":"Point"}
}