{
  "type": "Feature",
  "properties": {
    "iso:country":"US",
    "sg:address":"21488 295th St",
    "sg:city":"Cornell",
    "sg:classifiers":[
        {
            "category":"Retail",
            "subcategory":"Repair Shop",
            "type":"Services"
        }
    ],
    "sg:phone":"+1 715 239 6099",
    "sg:postcode":"54732",
    "sg:province":"WI",
    "sg:tags":[
        "welding"
    ],
    "wof:name":"Grambow Welding & Farm Repair",
    "wof:placetype":"venue"
},
  "geometry": {"coordinates":[-91.08031,45.1421],"type":"Point"}
}