{
  "type": "Feature",
  "properties": {
    "addr:full":"986 Lakeview Dr Green Bay WI 54313",
    "addr:housenumber":"986",
    "addr:postcode":"54313",
    "addr:street":"Lakeview Dr",
    "iso:country":"US",
    "sg:address":"986 Lakeview Dr",
    "sg:city":"Green Bay",
    "sg:classifiers":[
        {
            "category":"Social Services",
            "subcategory":"Child Care",
            "type":"Services"
        }
    ],
    "sg:phone":"+1 920 434 4222",
    "sg:postcode":"54313",
    "sg:province":"WI",
    "wof:name":"Children's World Learning Ctr",
    "wof:placetype":"venue"
},
  "geometry": {"coordinates":[-88.064638,44.565983],"type":"Point"}
}