{
  "type": "Feature",
  "properties": {
    "iso:country":"US",
    "sg:address":"5850 State Hwy 76",
    "sg:city":"Oshkosh",
    "sg:classifiers":[
        {
            "category":"Bars & Pubs",
            "type":"Food & Drink"
        }
    ],
    "sg:phone":"+1 920 232 9000",
    "sg:postcode":"54904",
    "sg:province":"WI",
    "sg:tags":[
        "drinking",
        "eating"
    ],
    "wof:name":"Wingers West & Jurassic Valley",
    "wof:placetype":"venue"
},
  "geometry": {"coordinates":[-88.543466,44.107829],"type":"Point"}
}