{
  "type": "Feature",
  "properties": {
    "iso:country":"US",
    "sg:address":"333 S Erie St",
    "sg:city":"De Pere",
    "sg:classifiers":[
        {
            "category":"Manufacturing",
            "subcategory":"Wood Products",
            "type":"Manufacturing & Wholesale Goods"
        }
    ],
    "sg:phone":"+1 920 337 9920",
    "sg:postcode":"54115",
    "sg:province":"WI",
    "sg:tags":[
        "container",
        "mfg"
    ],
    "wof:name":"Statewide Pallet Recycling",
    "wof:placetype":"venue"
},
  "geometry": {"coordinates":[-88.054391,44.44568],"type":"Point"}
}