{
  "type": "Feature",
  "properties": {
    "addr:full":"3562 Co Rd U Merrimac WI 53561",
    "addr:housenumber":"3562",
    "addr:postcode":"53561",
    "addr:street":"Co Rd",
    "iso:country":"US",
    "sg:address":"3562 Co Rd U",
    "sg:city":"Merrimac",
    "sg:classifiers":[
        {
            "category":"Local Transit",
            "type":"Transportation"
        }
    ],
    "sg:phone":"+1 608 493 9481",
    "sg:postcode":"53561",
    "sg:province":"WI",
    "wof:name":"Proconsul Inc",
    "wof:placetype":"venue"
},
  "geometry": {"coordinates":[-89.581503,43.408389],"type":"Point"}
}