{
  "type": "Feature",
  "properties": {
    "iso:country":"US",
    "sg:address":"10906 N Port Washington Rd",
    "sg:city":"Mequon",
    "sg:classifiers":[
        {
            "category":"Shopping",
            "subcategory":"Musical Instruments",
            "type":"Retail Goods"
        }
    ],
    "sg:phone":"+1 262 240 5397",
    "sg:postcode":"53092",
    "sg:province":"WI",
    "wof:name":"Bradford Stineway Showcase",
    "wof:placetype":"venue"
},
  "geometry": {"coordinates":[-87.923917,43.215869],"type":"Point"}
}