{
  "type": "Feature",
  "properties": {
    "iso:country":"US",
    "sg:address":"1271 Minnie Ln",
    "sg:city":"Campbellsport",
    "sg:classifiers":[
        {
            "category":"Organizations",
            "subcategory":"Religious Organization",
            "type":"Services"
        }
    ],
    "sg:phone":"+1 920 533 8644",
    "sg:postcode":"53010",
    "sg:province":"WI",
    "sg:tags":[
        "clergy"
    ],
    "wof:name":"Wayne J Barta",
    "wof:placetype":"venue"
},
  "geometry": {"coordinates":[-88.374512,43.586238],"type":"Point"}
}