{
  "type": "Feature",
  "properties": {
    "iso:country":"US",
    "sg:address":"9085 Colby Rd",
    "sg:city":"Mount Horeb",
    "sg:classifiers":[
        {
            "category":"Professional",
            "type":"Services"
        }
    ],
    "sg:phone":"+1 608 832 6307",
    "sg:postcode":"53572",
    "sg:province":"WI",
    "wof:name":"L Richard Chancellor",
    "wof:placetype":"venue"
},
  "geometry": {"coordinates":[-89.685485,42.944506],"type":"Point"}
}