{
  "type": "Feature",
  "properties": {
    "addr:full":"10980 W 2nd St Hewitt WI 54441",
    "addr:housenumber":"10980",
    "addr:postcode":"54441",
    "addr:street":"W 2Nd St",
    "iso:country":"US",
    "sg:address":"10980 W 2nd St",
    "sg:city":"Hewitt",
    "sg:classifiers":[
        {
            "category":"Retail",
            "subcategory":"Laundry & Dry Cleaning",
            "type":"Services"
        }
    ],
    "sg:phone":"+1 715 387 3800",
    "sg:postcode":"54441",
    "sg:province":"WI",
    "wof:name":"Modern Janitorial Service",
    "wof:placetype":"venue"
},
  "geometry": {"coordinates":[-90.10233700000001,44.641913],"type":"Point"}
}