{
  "type": "Feature",
  "properties": {
    "addr:full":"3654 Nursery Rd Rhinelander WI 54501",
    "addr:housenumber":"3654",
    "addr:postcode":"54501",
    "addr:street":"Nursery Rd",
    "iso:country":"US",
    "sg:address":"3654 Nursery Rd",
    "sg:city":"Rhinelander",
    "sg:classifiers":[
        {
            "category":"Government",
            "subcategory":"Office",
            "type":"Public Place"
        }
    ],
    "sg:phone":"+1 715 369 5221",
    "sg:postcode":"54501",
    "sg:province":"WI",
    "sg:tags":[
        "federal",
        "program"
    ],
    "wof:name":"US Agricultural Dept",
    "wof:placetype":"venue"
},
  "geometry": {"coordinates":[-89.467947,45.641095],"type":"Point"}
}