{
  "type": "Feature",
  "properties": {
    "addr:full":"1826 W Center St Milwaukee WI 53206",
    "addr:housenumber":"1826",
    "addr:postcode":"53206",
    "addr:street":"W Center St",
    "iso:country":"US",
    "sg:address":"1826 W Center St",
    "sg:city":"Milwaukee",
    "sg:classifiers":[
        {
            "category":"Organizations",
            "subcategory":"Religious Organization",
            "type":"Services"
        }
    ],
    "sg:phone":"+1 414 431 0744",
    "sg:postcode":"53206",
    "sg:province":"WI",
    "sg:tags":[
        "church"
    ],
    "wof:name":"New Convenant Gospel Ministry",
    "wof:placetype":"venue"
},
  "geometry": {"coordinates":[-87.936807,43.067865],"type":"Point"}
}