{
  "type": "Feature",
  "properties": {
    "iso:country":"US",
    "sg:address":"104 Elm St",
    "sg:city":"Sheboygan Falls",
    "sg:classifiers":[
        {
            "category":"Organizations",
            "subcategory":"Religious Organization",
            "type":"Services"
        }
    ],
    "sg:phone":"+1 920 467 6639",
    "sg:postcode":"53085",
    "sg:province":"WI",
    "sg:tags":[
        "church"
    ],
    "wof:name":"Saint Peters Episcopal Church",
    "wof:placetype":"venue"
},
  "geometry": {"coordinates":[-87.81161,43.727092],"type":"Point"}
}