{
  "type": "Feature",
  "properties": {
    "iso:country":"US",
    "sg:address":"3879 N Richards St",
    "sg:city":"Milwaukee",
    "sg:classifiers":[
        {
            "category":"Manufacturing",
            "subcategory":"Tools & Machinery",
            "type":"Manufacturing & Wholesale Goods"
        }
    ],
    "sg:phone":"+1 414 964 3668",
    "sg:postcode":"53212",
    "sg:province":"WI",
    "sg:tags":[
        "machine",
        "shop"
    ],
    "sg:website":"www.barefootinternational.com",
    "wof:name":"Barefoot Int/Fly High",
    "wof:placetype":"venue"
},
  "geometry": {"coordinates":[-87.907372,43.088749],"type":"Point"}
}