{
  "type": "Feature",
  "properties": {
    "addr:full":"9024 State Hwy 89 Whitewater WI 53190",
    "addr:housenumber":"9024",
    "addr:postcode":"53190",
    "addr:street":"State Hwy 89",
    "iso:country":"US",
    "sg:address":"9024 State Hwy 89",
    "sg:city":"Whitewater",
    "sg:classifiers":[
        {
            "category":"Food & Beverages",
            "subcategory":"Bakery",
            "type":"Retail Goods"
        }
    ],
    "sg:phone":"+1 262 473 6176",
    "sg:postcode":"53190",
    "sg:province":"WI",
    "wof:name":"Cookies Spice Everything Nice",
    "wof:placetype":"venue"
},
  "geometry": {"coordinates":[-88.744696,42.819219],"type":"Point"}
}