{
  "type": "Feature",
  "properties": {
    "addr:full":"7451 Co Rd B Oconto Falls WI 54154",
    "addr:housenumber":"7451",
    "addr:postcode":"54154",
    "addr:street":"Co Rd B",
    "iso:country":"US",
    "sg:address":"7451 Co Rd B",
    "sg:city":"Oconto Falls",
    "sg:phone":"+1 920 846 8401",
    "sg:postcode":"54154",
    "sg:province":"WI",
    "sg:tags":[
        "farm",
        "corn",
        "beef",
        "feedlot",
        "cattle"
    ],
    "wof:name":"David Brehmer Farm",
    "wof:placetype":"venue"
},
  "geometry": {"coordinates":[-88.16470200000001,44.938422],"type":"Point"}
}