{
  "type": "Feature",
  "properties": {
    "iso:country":"US",
    "sg:address":"2610 US Hwy 14",
    "sg:city":"Janesville",
    "sg:classifiers":[
        {
            "category":"Professional",
            "subcategory":"Business Services",
            "type":"Services"
        }
    ],
    "sg:phone":"+1 608 758 7894",
    "sg:postcode":"53545",
    "sg:province":"WI",
    "wof:name":"J Rose Sewing Studio",
    "wof:placetype":"venue"
},
  "geometry": {"coordinates":[-88.99190400000001,42.718868],"type":"Point"}
}