{
  "type": "Feature",
  "properties": {
    "addr:full":"330 W Pine St Eagle River WI 54521",
    "addr:housenumber":"330",
    "addr:postcode":"54521",
    "addr:street":"W Pine St",
    "iso:country":"US",
    "sg:address":"330 W Pine St",
    "sg:city":"Eagle River",
    "sg:classifiers":[
        {
            "category":"Professional",
            "subcategory":"Accounting & Tax Preparation",
            "type":"Services"
        }
    ],
    "sg:phone":"+1 715 479 6148",
    "sg:postcode":"54521",
    "sg:province":"WI",
    "sg:tags":[
        "return",
        "filing"
    ],
    "wof:name":"H & R Block Tax Svc",
    "wof:placetype":"venue"
},
  "geometry": {"coordinates":[-89.25579399999999,45.914111],"type":"Point"}
}