{
  "type": "Feature",
  "properties": {
    "iso:country":"US",
    "sg:address":"2213 Manor Green Dr",
    "sg:city":"Madison",
    "sg:classifiers":[
        {
            "category":"Health Services",
            "subcategory":"Clinic",
            "type":"Services"
        }
    ],
    "sg:phone":"+1 608 298 0273",
    "sg:postcode":"53711",
    "sg:province":"WI",
    "sg:tags":[
        "organization",
        "medical",
        "surgical"
    ],
    "wof:name":"Wi Physician Svc",
    "wof:placetype":"venue"
},
  "geometry": {"coordinates":[-89.474307,43.028845],"type":"Point"}
}