{
  "type": "Feature",
  "properties": {
    "iso:country":"US",
    "sg:address":"1349 Topel St",
    "sg:city":"Lake Mills",
    "sg:classifiers":[
        {
            "category":"Recreation",
            "type":"Entertainment"
        }
    ],
    "sg:phone":"+1 920 648 4959",
    "sg:postcode":"53551",
    "sg:province":"WI",
    "wof:name":"Topels Tee Box",
    "wof:placetype":"venue"
},
  "geometry": {"coordinates":[-88.916566,43.06125],"type":"Point"}
}