{
  "type": "Feature",
  "properties": {
    "iso:country":"US",
    "sg:address":"3823 N 87th St",
    "sg:city":"Milwaukee",
    "sg:classifiers":[
        {
            "category":"Building & Trades",
            "subcategory":"Plumbing",
            "type":"Services"
        }
    ],
    "sg:phone":"+1 414 463 0450",
    "sg:postcode":"53222",
    "sg:province":"WI",
    "sg:tags":[
        "mechanical",
        "contractor"
    ],
    "wof:name":"CSL Mechanical Systems",
    "wof:placetype":"venue"
},
  "geometry": {"coordinates":[-88.021452,43.088323],"type":"Point"}
}