{
  "type": "Feature",
  "properties": {
    "iso:country":"US",
    "sg:address":"989 Park St",
    "sg:city":"Oregon",
    "sg:classifiers":[
        {
            "category":"Social Services",
            "subcategory":"Adult Care",
            "type":"Services"
        }
    ],
    "sg:phone":"+1 608 835 0000",
    "sg:postcode":"53575",
    "sg:province":"WI",
    "sg:tags":[
        "residential",
        "intermediate",
        "facility"
    ],
    "wof:name":"Sienna Meadows",
    "wof:placetype":"venue"
},
  "geometry": {"coordinates":[-89.370961,42.919194],"type":"Point"}
}