{
  "type": "Feature",
  "properties": {
    "iso:country":"US",
    "sg:address":"4540 Hearthridge Dr",
    "sg:city":"Janesville",
    "sg:classifiers":[
        {
            "category":"Shopping",
            "type":"Retail Goods"
        }
    ],
    "sg:phone":"+1 608 757 1116",
    "sg:postcode":"53546",
    "sg:province":"WI",
    "sg:tags":[
        "cosmetic",
        "perfume"
    ],
    "wof:name":"Mary Kay Cosmetics",
    "wof:placetype":"venue"
},
  "geometry": {"coordinates":[-88.959839,42.684084],"type":"Point"}
}