{
  "type": "Feature",
  "properties": {
    "iso:country":"US",
    "sg:address":"4219 51st Ave",
    "sg:city":"Kenosha",
    "sg:classifiers":[
        {
            "category":"Real Estate",
            "subcategory":"Real Estate Operator",
            "type":"Services"
        }
    ],
    "sg:phone":"+1 262 652 4745",
    "sg:postcode":"53144",
    "sg:province":"WI",
    "sg:tags":[
        "property",
        "lessor"
    ],
    "wof:name":"Saints Properties LLC",
    "wof:placetype":"venue"
},
  "geometry": {"coordinates":[-87.86995400000001,42.598503],"type":"Point"}
}