{
  "type": "Feature",
  "properties": {
    "iso:country":"US",
    "sg:address":"738 W Washington St",
    "sg:city":"Milwaukee",
    "sg:classifiers":[
        {
            "category":"Travel",
            "subcategory":"Travel Agent",
            "type":"Entertainment"
        }
    ],
    "sg:phone":"+1 414 672 0929",
    "sg:postcode":"53204",
    "sg:province":"WI",
    "sg:tags":[
        "agency",
        "bureau"
    ],
    "wof:name":"Spanish Time Inc",
    "wof:placetype":"venue"
},
  "geometry": {"coordinates":[-87.918533,43.020194],"type":"Point"}
}