{
  "type": "Feature",
  "properties": {
    "iso:country":"US",
    "sg:address":"110 Linden Rd",
    "sg:city":"Prescott",
    "sg:classifiers":[
        {
            "category":"Manufacturing",
            "subcategory":"Tools & Machinery",
            "type":"Manufacturing & Wholesale Goods"
        }
    ],
    "sg:phone":"+1 715 262 4818",
    "sg:postcode":"54021",
    "sg:province":"WI",
    "sg:tags":[
        "construction",
        "mfg"
    ],
    "wof:name":"Flatworks LLC",
    "wof:placetype":"venue"
},
  "geometry": {"coordinates":[-92.784436,44.754845],"type":"Point"}
}