{
  "type": "Feature",
  "properties": {
    "addr:full":"770 N Milwaukee St Milwaukee WI 53202",
    "addr:housenumber":"770",
    "addr:postcode":"53202",
    "addr:street":"N Milwaukee St",
    "iso:country":"US",
    "sg:address":"770 N Milwaukee St",
    "sg:city":"Milwaukee",
    "sg:classifiers":[
        {
            "category":"Bars & Pubs",
            "type":"Food & Drink"
        }
    ],
    "sg:menulink":"http://www.allmenus.com/wi/milwaukee/143597-zims-bar/menu/",
    "sg:phone":"+1 414 727 9447",
    "sg:postcode":"53202",
    "sg:province":"WI",
    "sg:tags":[
        "american"
    ],
    "wof:name":"Zim's Bar",
    "wof:placetype":"venue"
},
  "geometry": {"coordinates":[-87.906347,43.04064],"type":"Point"}
}