{
  "type": "Feature",
  "properties": {
    "iso:country":"US",
    "sg:address":"565 E South Ave",
    "sg:city":"Chippewa Falls",
    "sg:classifiers":[
        {
            "category":"Education",
            "subcategory":"School",
            "type":"Public Place"
        }
    ],
    "sg:phone":"+1 715 726 2415",
    "sg:postcode":"54729",
    "sg:province":"WI",
    "sg:tags":[
        "elementary"
    ],
    "sg:website":"www.chippewafallsschooldistrict.com",
    "wof:name":"Halmstad Elementary School",
    "wof:placetype":"venue"
},
  "geometry": {"coordinates":[-91.379875,44.91532],"type":"Point"}
}