{
  "type": "Feature",
  "properties": {
    "iso:country":"US",
    "sg:address":"3142 N 24th Pl",
    "sg:city":"Milwaukee",
    "sg:classifiers":[
        {
            "category":"Recreation",
            "type":"Entertainment"
        }
    ],
    "sg:phone":"+1 414 449 9624",
    "sg:postcode":"53206",
    "sg:province":"WI",
    "sg:tags":[
        "amusement"
    ],
    "wof:name":"Kim's Playland",
    "wof:placetype":"venue"
},
  "geometry": {"coordinates":[-87.94345,43.07619],"type":"Point"}
}