{
  "type": "Feature",
  "properties": {
    "iso:country":"US",
    "sg:address":"5206 Pleasant Valley Rd",
    "sg:city":"Platteville",
    "sg:classifiers":[
        {
            "category":"Home & Garden",
            "subcategory":"Building Materials",
            "type":"Retail Goods"
        }
    ],
    "sg:phone":"+1 608 348 3330",
    "sg:postcode":"53818",
    "sg:province":"WI",
    "sg:tags":[
        "type",
        "door"
    ],
    "wof:name":"Long Grove Overhead Doors",
    "wof:placetype":"venue"
},
  "geometry": {"coordinates":[-90.46127,42.694314],"type":"Point"}
}