{
  "type": "Feature",
  "properties": {
    "iso:country":"US",
    "sg:address":"130 E 1st St",
    "sg:city":"New Richmond",
    "sg:classifiers":[
        {
            "category":"Retail",
            "subcategory":"Auto Repair",
            "type":"Services"
        }
    ],
    "sg:phone":"+1 715 246 4448",
    "sg:postcode":"54017",
    "sg:province":"WI",
    "sg:tags":[
        "glass",
        "replacement"
    ],
    "wof:name":"Indianhead Glass Inc",
    "wof:placetype":"venue"
},
  "geometry": {"coordinates":[-92.53704,45.122709],"type":"Point"}
}