{
  "type": "Feature",
  "properties": {
    "iso:country":"US",
    "sg:address":"1415 Indianhead Dr E",
    "sg:city":"Menomonie",
    "sg:classifiers":[
        {
            "category":"Freight",
            "type":"Transportation"
        }
    ],
    "sg:phone":"+1 715 235 5121",
    "sg:postcode":"54751",
    "sg:province":"WI",
    "sg:tags":[
        "trucking"
    ],
    "sg:website":"www.trac-inc.com",
    "wof:name":"TRAC Inc",
    "wof:placetype":"venue"
},
  "geometry": {"coordinates":[-91.872479,44.896111],"type":"Point"}
}