{
  "type": "Feature",
  "properties": {
    "iso:country":"US",
    "sg:address":"5811 Camp Phillips Rd",
    "sg:city":"Schofield",
    "sg:classifiers":[
        {
            "category":"Retail",
            "subcategory":"Auto Repair",
            "type":"Services"
        }
    ],
    "sg:phone":"+1 715 359 2670",
    "sg:postcode":"54476",
    "sg:province":"WI",
    "sg:tags":[
        "body",
        "automobile",
        "painting"
    ],
    "wof:name":"Sanders Collision Svc",
    "wof:placetype":"venue"
},
  "geometry": {"coordinates":[-89.572828,44.906782],"type":"Point"}
}