{
  "type": "Feature",
  "properties": {
    "iso:country":"US",
    "sg:address":"15602 Arneman Dr",
    "sg:city":"South Beloit",
    "sg:classifiers":[
        {
            "category":"Real Estate",
            "subcategory":"Real Estate Operator",
            "type":"Services"
        }
    ],
    "sg:phone":"+1 815 389 3899",
    "sg:postcode":"61080",
    "sg:province":"WI",
    "sg:tags":[
        "apartment"
    ],
    "wof:name":"Foxwood Hills Apartments",
    "wof:placetype":"venue"
},
  "geometry": {"coordinates":[-89.01850399999999,42.486386],"type":"Point"}
}