{
  "type": "Feature",
  "properties": {
    "iso:country":"US",
    "sg:address":"3807 S Riverside Dr",
    "sg:city":"Beloit",
    "sg:classifiers":[
        {
            "category":"Bars & Pubs",
            "type":"Food & Drink"
        },
        {
            "category":"Restaurant",
            "type":"Food & Drink"
        },
        {
            "category":"Retail",
            "subcategory":"Event Space",
            "type":"Services"
        }
    ],
    "sg:phone":"+1 608 362 5249",
    "sg:postcode":"53511",
    "sg:province":"WI",
    "sg:tags":[
        "facility",
        "banquet",
        "american",
        "reception",
        "brew",
        "hall"
    ],
    "wof:name":"Marine Corps League",
    "wof:placetype":"venue"
},
  "geometry": {"coordinates":[-89.029534,42.573985],"type":"Point"}
}