{
  "type": "Feature",
  "properties": {
    "iso:country":"US",
    "sg:address":"3008 75th St",
    "sg:city":"Kenosha",
    "sg:classifiers":[
        {
            "category":"Building & Trades",
            "subcategory":"Construction",
            "type":"Services"
        }
    ],
    "sg:phone":"+1 262 654 6644",
    "sg:postcode":"53142",
    "sg:province":"WI",
    "sg:tags":[
        "roofing",
        "contractor"
    ],
    "wof:name":"Dick's Roof Repair Svc",
    "wof:placetype":"venue"
},
  "geometry": {"coordinates":[-87.846251,42.566135],"type":"Point"}
}