{
  "type": "Feature",
  "properties": {
    "iso:country":"US",
    "sg:address":"19880 W Main St",
    "sg:city":"Lannon",
    "sg:classifiers":[
        {
            "category":"Bus Charters",
            "type":"Transportation"
        },
        {
            "category":"Retail",
            "subcategory":"Auto Rental",
            "type":"Services"
        },
        {
            "category":"School Buses",
            "type":"Transportation"
        },
        {
            "category":"Retail",
            "subcategory":"Storage",
            "type":"Services"
        },
        {
            "category":"Local Transit",
            "type":"Transportation"
        }
    ],
    "sg:phone":"+1 262 253 4060",
    "sg:postcode":"53046",
    "sg:province":"WI",
    "sg:tags":[
        "buses-charter",
        "moving-self",
        "truck",
        "line"
    ],
    "wof:name":"Dairyland Hamilton Inc",
    "wof:placetype":"venue"
},
  "geometry": {"coordinates":[-88.15696,43.155226],"type":"Point"}
}