{
  "type": "Feature",
  "properties": {
    "addr:full":"1551 la Salle Ct Janesville WI 53546",
    "addr:housenumber":"1551",
    "addr:postcode":"53546",
    "addr:street":"La Salle Ct",
    "iso:country":"US",
    "sg:address":"1551 la Salle Ct",
    "sg:city":"Janesville",
    "sg:classifiers":[
        {
            "category":"Retail",
            "subcategory":"Laundry & Dry Cleaning",
            "type":"Services"
        },
        {
            "category":"Building & Trades",
            "subcategory":"Cleaning & Sanitation",
            "type":"Services"
        }
    ],
    "sg:phone":"+1 608 754 4587",
    "sg:postcode":"53546",
    "sg:province":"WI",
    "sg:tags":[
        "cleaner",
        "house"
    ],
    "wof:name":"Like New Pressure Cleaning",
    "wof:placetype":"venue"
},
  "geometry": {"coordinates":[-89.026904,42.657742],"type":"Point"}
}