{
  "type": "Feature",
  "properties": {
    "addr:full":"24 N 3rd Ave Sturgeon Bay WI 54235",
    "addr:housenumber":"24",
    "addr:postcode":"54235",
    "addr:street":"N 3Rd Ave",
    "iso:country":"US",
    "sg:address":"24 N 3rd Ave",
    "sg:city":"Sturgeon Bay",
    "sg:classifiers":[
        {
            "category":"Food & Beverages",
            "subcategory":"Candy",
            "type":"Retail Goods"
        }
    ],
    "sg:phone":"+1 920 746 0924",
    "sg:postcode":"54235",
    "sg:province":"WI",
    "wof:name":"Copper Kettle Confections",
    "wof:placetype":"venue"
},
  "geometry": {"coordinates":[-87.37689399999999,44.834931],"type":"Point"}
}