{
  "type": "Feature",
  "properties": {
    "iso:country":"US",
    "sg:address":"2426 23rd Ave",
    "sg:city":"Kenosha",
    "sg:classifiers":[
        {
            "category":"Building & Trades",
            "subcategory":"Construction",
            "type":"Services"
        }
    ],
    "sg:phone":"+1 262 657 1535",
    "sg:postcode":"53140",
    "sg:province":"WI",
    "sg:tags":[
        "home",
        "improvement"
    ],
    "wof:name":"R & S Home Improvements",
    "wof:placetype":"venue"
},
  "geometry": {"coordinates":[-87.837087,42.61445],"type":"Point"}
}