{
  "type": "Feature",
  "properties": {
    "addr:full":"837 Broadway St Eau Claire WI 54703",
    "addr:housenumber":"837",
    "addr:postcode":"54703",
    "addr:street":"Broadway St",
    "iso:country":"US",
    "sg:address":"837 Broadway St",
    "sg:city":"Eau Claire",
    "sg:classifiers":[
        {
            "category":"Retail",
            "subcategory":"Repair Shop",
            "type":"Services"
        }
    ],
    "sg:phone":"+1 715 832 1122",
    "sg:postcode":"54703",
    "sg:province":"WI",
    "wof:name":"Rips",
    "wof:placetype":"venue"
},
  "geometry": {"coordinates":[-91.51767599999999,44.804967],"type":"Point"}
}