{
  "type": "Feature",
  "properties": {
    "iso:country":"US",
    "sg:address":"3639 Patton St",
    "sg:city":"Eau Claire",
    "sg:classifiers":[
        {
            "category":"Professional",
            "subcategory":"Management & Consulting",
            "type":"Services"
        }
    ],
    "sg:phone":"+1 715 834 4814",
    "sg:postcode":"54701",
    "sg:province":"WI",
    "sg:tags":[
        "retail",
        "direct",
        "sales"
    ],
    "wof:name":"Linda Wood",
    "wof:placetype":"venue"
},
  "geometry": {"coordinates":[-91.493444,44.779911],"type":"Point"}
}