{
  "type": "Feature",
  "properties": {
    "iso:country":"US",
    "sg:address":"8193 Waschbisch Rd",
    "sg:city":"Oconto Falls",
    "sg:classifiers":[
        {
            "category":"Building & Trades",
            "subcategory":"Construction",
            "type":"Services"
        }
    ],
    "sg:phone":"+1 920 846 8756",
    "sg:postcode":"54154",
    "sg:province":"WI",
    "sg:tags":[
        "a",
        "residential",
        "sp",
        "operates",
        "as",
        "contractor"
    ],
    "wof:name":"Bear Built Construction",
    "wof:placetype":"venue"
},
  "geometry": {"coordinates":[-88.160856,44.8898],"type":"Point"}
}