{
  "type": "Feature",
  "properties": {
    "iso:country":"US",
    "sg:address":"670 Kington Rd",
    "sg:city":"Unity",
    "sg:classifiers":[
        {
            "category":"Farming",
            "subcategory":"Dairy Farm",
            "type":"Manufacturing & Wholesale Goods"
        }
    ],
    "sg:phone":"+1 715 223 4478",
    "sg:postcode":"54488",
    "sg:province":"WI",
    "wof:name":"Wayne Westrich",
    "wof:placetype":"venue"
},
  "geometry": {"coordinates":[-90.344763,44.829336],"type":"Point"}
}