{
  "type": "Feature",
  "properties": {
    "iso:country":"US",
    "sg:address":"2353 Geneva St",
    "sg:city":"Oshkosh",
    "sg:classifiers":[
        {
            "category":"Utilities",
            "type":"Services"
        }
    ],
    "sg:phone":"+1 920 235 8667",
    "sg:postcode":"54901",
    "sg:province":"WI",
    "sg:tags":[
        "sanitary"
    ],
    "wof:name":"Wissink Dave Landscape Svcs",
    "wof:placetype":"venue"
},
  "geometry": {"coordinates":[-88.540199,44.04663],"type":"Point"}
}