{
  "type": "Feature",
  "properties": {
    "addr:full":"5300 S Howell Ave Milwaukee WI 53207",
    "addr:housenumber":"5300",
    "addr:postcode":"53207",
    "addr:street":"S Howell Ave",
    "iso:country":"US",
    "sg:address":"5300 S Howell Ave",
    "sg:city":"Milwaukee",
    "sg:classifiers":[
        {
            "category":"Restaurant",
            "type":"Food & Drink"
        },
        {
            "category":"Wholesale",
            "subcategory":"Dairy",
            "type":"Manufacturing & Wholesale Goods"
        }
    ],
    "sg:phone":"+1 414 481 1990",
    "sg:postcode":"53207",
    "sg:province":"WI",
    "sg:tags":[
        "frozen",
        "dessert",
        "eating",
        "ice",
        "cream"
    ],
    "wof:name":"Airport Ice Cream Shop Inc",
    "wof:placetype":"venue"
},
  "geometry": {"coordinates":[-87.909716,42.947265],"type":"Point"}
}