{
  "type": "Feature",
  "properties": {
    "iso:country":"US",
    "sg:address":"419 Prospect Ave",
    "sg:city":"Sheboygan Falls",
    "sg:classifiers":[
        {
            "category":"Insurance",
            "subcategory":"Hazard Insurance",
            "type":"Services"
        }
    ],
    "sg:phone":"+1 920 467 4836",
    "sg:postcode":"53085",
    "sg:province":"WI",
    "sg:tags":[
        "carrier"
    ],
    "wof:name":"Senior Care Svcs",
    "wof:placetype":"venue"
},
  "geometry": {"coordinates":[-87.80779,43.733191],"type":"Point"}
}