{
  "type": "Feature",
  "properties": {
    "iso:country":"US",
    "sg:address":"24 S Main St",
    "sg:city":"Oconomowoc",
    "sg:classifiers":[
        {
            "category":"Banks & Credit Unions",
            "subcategory":"Investment Brokerage",
            "type":"Services"
        }
    ],
    "sg:phone":"+1 262 560 0585",
    "sg:postcode":"53066",
    "sg:province":"WI",
    "sg:tags":[
        "consultant",
        "financing"
    ],
    "wof:name":"First Wisconsin Lending",
    "wof:placetype":"venue"
},
  "geometry": {"coordinates":[-88.49951799999999,43.111166],"type":"Point"}
}