{
  "type": "Feature",
  "properties": {
    "iso:country":"US",
    "sg:address":"1281 Racine Dr",
    "sg:city":"Spooner",
    "sg:classifiers":[
        {
            "category":"Utilities",
            "type":"Services"
        }
    ],
    "sg:phone":"+1 715 635 7760",
    "sg:postcode":"54801",
    "sg:province":"WI",
    "sg:tags":[
        "sanitary"
    ],
    "wof:name":"Lakes & Pines Sno Trails",
    "wof:placetype":"venue"
},
  "geometry": {"coordinates":[-92.050254,45.948143],"type":"Point"}
}