{
  "type": "Feature",
  "properties": {
    "addr:full":"9960 Ridgewood Dr Minocqua WI 54548",
    "addr:housenumber":"9960",
    "addr:postcode":"54548",
    "addr:street":"Ridgewood Dr",
    "iso:country":"US",
    "sg:address":"9960 Ridgewood Dr",
    "sg:city":"Minocqua",
    "sg:classifiers":[
        {
            "category":"Professional",
            "subcategory":"Business Services",
            "type":"Services"
        }
    ],
    "sg:phone":"+1 715 356 2683",
    "sg:postcode":"54548",
    "sg:province":"WI",
    "wof:name":"1st Group of Minocqua LLC",
    "wof:placetype":"venue"
},
  "geometry": {"coordinates":[-89.73347699999999,45.821335],"type":"Point"}
}