{
  "type": "Feature",
  "properties": {
    "iso:country":"US",
    "sg:address":"1202 Whitewater Ave",
    "sg:city":"Fort Atkinson",
    "sg:classifiers":[
        {
            "category":"Retail",
            "subcategory":"Repair Shop",
            "type":"Services"
        },
        {
            "category":"Shopping",
            "subcategory":"Computers & Home Electronics",
            "type":"Retail Goods"
        }
    ],
    "sg:phone":"+1 920 563 9684",
    "sg:postcode":"53538",
    "sg:province":"WI",
    "sg:tags":[
        "radio",
        "television",
        "electrical",
        "trade"
    ],
    "wof:name":"Paske T V & Stereo",
    "wof:placetype":"venue"
},
  "geometry": {"coordinates":[-88.831852,42.913295],"type":"Point"}
}