{
  "type": "Feature",
  "properties": {
    "iso:country":"US",
    "sg:address":"2958 E Washington Ave",
    "sg:city":"Madison",
    "sg:classifiers":[
        {
            "category":"Restaurant",
            "type":"Food & Drink"
        }
    ],
    "sg:menulink":"http://www.allmenus.com/wi/madison/181474-kfc---kentucky-fried-chicken/menu/",
    "sg:phone":"+1 608 249 5664",
    "sg:postcode":"53704",
    "sg:province":"WI",
    "sg:tags":[
        "american",
        "chicken"
    ],
    "wof:name":"KFC - Kentucky Fried Chicken",
    "wof:placetype":"venue"
},
  "geometry": {"coordinates":[-89.343757,43.103508],"type":"Point"}
}