{
  "type": "Feature",
  "properties": {
    "iso:country":"US",
    "sg:address":"54 Commerce St",
    "sg:city":"Holmen",
    "sg:classifiers":[
        {
            "category":"Real Estate",
            "subcategory":"Real Estate Operator",
            "type":"Services"
        }
    ],
    "sg:phone":"+1 608 526 3032",
    "sg:postcode":"54636",
    "sg:province":"WI",
    "sg:tags":[
        "mobile",
        "home",
        "site"
    ],
    "wof:name":"Kingsfeld Estates Condo MBL Ho",
    "wof:placetype":"venue"
},
  "geometry": {"coordinates":[-91.275091,43.961824],"type":"Point"}
}