{
  "type": "Feature",
  "properties": {
    "addr:full":"902 Centennial Pkwy Waunakee WI 53597",
    "addr:housenumber":"902",
    "addr:postcode":"53597",
    "addr:street":"Centennial Pkwy",
    "iso:country":"US",
    "sg:address":"902 Centennial Pkwy",
    "sg:city":"Waunakee",
    "sg:classifiers":[
        {
            "category":"Professional",
            "subcategory":"Engineering",
            "type":"Services"
        }
    ],
    "sg:phone":"+1 608 849 5554",
    "sg:postcode":"53597",
    "sg:province":"WI",
    "wof:name":"Larke LLC",
    "wof:placetype":"venue"
},
  "geometry": {"coordinates":[-89.4661,43.181527],"type":"Point"}
}