{
  "type": "Feature",
  "properties": {
    "iso:country":"US",
    "sg:address":"222 Madison St",
    "sg:city":"Beaver Dam",
    "sg:classifiers":[
        {
            "category":"Manufacturing",
            "subcategory":"Leather Goods",
            "type":"Manufacturing & Wholesale Goods"
        }
    ],
    "sg:phone":"+1 920 887 1723",
    "sg:postcode":"53916",
    "sg:province":"WI",
    "sg:tags":[
        "footwear",
        "mfg"
    ],
    "wof:name":"Weyco Group Inc",
    "wof:placetype":"venue"
},
  "geometry": {"coordinates":[-88.841152,43.45517],"type":"Point"}
}