{
  "type": "Feature",
  "properties": {
    "iso:country":"US",
    "sg:address":"2710 E Sharon Dr",
    "sg:city":"Oak Creek",
    "sg:classifiers":[
        {
            "category":"Autos & Motor Vehicles",
            "subcategory":"Auto Supplies",
            "type":"Retail Goods"
        }
    ],
    "sg:phone":"+1 414 764 4586",
    "sg:postcode":"53154",
    "sg:province":"WI",
    "wof:name":"Kayenel Machine",
    "wof:placetype":"venue"
},
  "geometry": {"coordinates":[-87.878091,42.887191],"type":"Point"}
}