{
  "type": "Feature",
  "properties": {
    "iso:country":"US",
    "sg:address":"1531 E Moreland Blvd",
    "sg:city":"Waukesha",
    "sg:classifiers":[
        {
            "category":"Banks & Credit Unions",
            "subcategory":"Bank",
            "type":"Services"
        }
    ],
    "sg:phone":"+1 262 574 4131",
    "sg:postcode":"53186",
    "sg:province":"WI",
    "wof:name":"Waukesha State Bank",
    "wof:placetype":"venue"
},
  "geometry": {"coordinates":[-88.204293,43.024997],"type":"Point"}
}