{
  "type": "Feature",
  "properties": {
    "addr:full":"3710 392nd Ave Burlington WI 53105",
    "addr:housenumber":"3710",
    "addr:postcode":"53105",
    "addr:street":"392Nd Ave",
    "iso:country":"US",
    "sg:address":"3710 392nd Ave",
    "sg:city":"Burlington",
    "sg:classifiers":[
        {
            "category":"Farming",
            "subcategory":"Farm",
            "type":"Manufacturing & Wholesale Goods"
        }
    ],
    "sg:phone":"+1 262 539 2986",
    "sg:postcode":"53105",
    "sg:province":"WI",
    "wof:name":"Dyer Lake Farm",
    "wof:placetype":"venue"
},
  "geometry": {"coordinates":[-88.286327,42.604909],"type":"Point"}
}