{
  "type": "Feature",
  "properties": {
    "iso:country":"US",
    "sg:address":"511 Broadway St",
    "sg:city":"Sheboygan Falls",
    "sg:classifiers":[
        {
            "category":"Wholesale",
            "subcategory":"Hardware",
            "type":"Manufacturing & Wholesale Goods"
        }
    ],
    "sg:phone":"+1 920 625 2131",
    "sg:postcode":"53085",
    "sg:province":"WI",
    "sg:tags":[
        "machine",
        "making",
        "ice",
        "equipment"
    ],
    "wof:name":"William Mannhardt & Son",
    "wof:placetype":"venue"
},
  "geometry": {"coordinates":[-87.81126,43.728401],"type":"Point"}
}