{
  "type": "Feature",
  "properties": {
    "iso:country":"US",
    "sg:address":"122 N Pioneer Park Rd",
    "sg:city":"Westfield",
    "sg:classifiers":[
        {
            "category":"Recreation",
            "type":"Entertainment"
        }
    ],
    "sg:phone":"+1 608 296 3996",
    "sg:postcode":"53964",
    "sg:province":"WI",
    "wof:name":"Pioneer Mini Golf",
    "wof:placetype":"venue"
},
  "geometry": {"coordinates":[-89.485706,43.889855],"type":"Point"}
}