{
  "type": "Feature",
  "properties": {
    "iso:country":"US",
    "sg:address":"3141 S 77th St",
    "sg:city":"Milwaukee",
    "sg:classifiers":[
        {
            "category":"Social Services",
            "subcategory":"Adult Care",
            "type":"Services"
        }
    ],
    "sg:phone":"+1 414 541 3472",
    "sg:postcode":"53219",
    "sg:province":"WI",
    "sg:tags":[
        "residential"
    ],
    "wof:name":"Evergreen Square I 06737",
    "wof:placetype":"venue"
},
  "geometry": {"coordinates":[-88.00926800000001,42.987684],"type":"Point"}
}