{
  "type": "Feature",
  "properties": {
    "addr:full":"3869 Bray Rd Elkhorn WI 53121",
    "addr:housenumber":"3869",
    "addr:postcode":"53121",
    "addr:street":"Bray Rd",
    "iso:country":"US",
    "sg:address":"3869 Bray Rd",
    "sg:city":"Elkhorn",
    "sg:phone":"+1 262 723 2597",
    "sg:postcode":"53121",
    "sg:province":"WI",
    "sg:tags":[
        "farm",
        "corn",
        "soybean"
    ],
    "wof:name":"Smage Farms",
    "wof:placetype":"venue"
},
  "geometry": {"coordinates":[-88.491298,42.67908],"type":"Point"}
}