{
  "type": "Feature",
  "properties": {
    "iso:country":"US",
    "sg:address":"1216 American Way",
    "sg:city":"Watertown",
    "sg:classifiers":[
        {
            "category":"Wholesale",
            "subcategory":"Groceries",
            "type":"Manufacturing & Wholesale Goods"
        }
    ],
    "sg:phone":"+1 920 261 8094",
    "sg:postcode":"53094",
    "sg:province":"WI",
    "sg:tags":[
        "confectionery",
        "candy"
    ],
    "wof:name":"Deb Wholesale & Distributing",
    "wof:placetype":"venue"
},
  "geometry": {"coordinates":[-88.75901399999999,43.178037],"type":"Point"}
}