{
  "type": "Feature",
  "properties": {
    "addr:full":"800 4th Ave Stevens Point WI 54481",
    "addr:housenumber":"800",
    "addr:postcode":"54481",
    "addr:street":"4Th Ave",
    "iso:country":"US",
    "sg:address":"800 4th Ave",
    "sg:city":"Stevens Point",
    "sg:classifiers":[
        {
            "category":"Organizations",
            "subcategory":"Religious Organization",
            "type":"Services"
        }
    ],
    "sg:phone":"+1 715 344 6115",
    "sg:postcode":"54481",
    "sg:province":"WI",
    "sg:tags":[
        "church"
    ],
    "wof:name":"St Peter's Church",
    "wof:placetype":"venue"
},
  "geometry": {"coordinates":[-89.58671099999999,44.528824],"type":"Point"}
}