{
  "type": "Feature",
  "properties": {
    "addr:full":"430 S Main St Shawano WI 54166",
    "addr:housenumber":"430",
    "addr:postcode":"54166",
    "addr:street":"S Main St",
    "iso:country":"US",
    "sg:address":"430 S Main St",
    "sg:city":"Shawano",
    "sg:classifiers":[
        {
            "category":"Professional",
            "subcategory":"Business Services",
            "type":"Services"
        }
    ],
    "sg:phone":"+1 715 526 2220",
    "sg:postcode":"54166",
    "sg:province":"WI",
    "sg:tags":[
        "water",
        "softener"
    ],
    "wof:name":"Culligan",
    "wof:placetype":"venue"
},
  "geometry": {"coordinates":[-88.609099,44.776476],"type":"Point"}
}