{
  "type": "Feature",
  "properties": {
    "addr:full":"5810 W Oklahoma Ave Milwaukee WI 53219",
    "addr:housenumber":"5810",
    "addr:postcode":"53219",
    "addr:street":"W Oklahoma Ave",
    "iso:country":"US",
    "sg:address":"5810 W Oklahoma Ave",
    "sg:city":"Milwaukee",
    "sg:classifiers":[
        {
            "category":"Personal",
            "subcategory":"Beauty Salon",
            "type":"Services"
        }
    ],
    "sg:phone":"+1 414 545 2102",
    "sg:postcode":"53219",
    "sg:province":"WI",
    "sg:tags":[
        "shop"
    ],
    "wof:name":"Olga's Hair Fair",
    "wof:placetype":"venue"
},
  "geometry": {"coordinates":[-87.98747299999999,42.988489],"type":"Point"}
}