{
  "type": "Feature",
  "properties": {
    "iso:country":"US",
    "sg:address":"3701 W Burnham St",
    "sg:city":"Milwaukee",
    "sg:phone":"+1 414 476 0757",
    "sg:postcode":"53215",
    "sg:province":"WI",
    "sg:website":"http://www.redanvil.net",
    "wof:name":"Red Anvil",
    "wof:placetype":"venue"
},
  "geometry": {"coordinates":[-87.960373,43.010231],"type":"Point"}
}