{
  "type": "Feature",
  "properties": {
    "iso:country":"US",
    "sg:address":"9203 W Bluemound Rd",
    "sg:city":"Milwaukee",
    "sg:classifiers":[
        {
            "category":"Home & Garden",
            "subcategory":"Home Furnishings",
            "type":"Retail Goods"
        }
    ],
    "sg:phone":"+1 414 774 0993",
    "sg:postcode":"53226",
    "sg:province":"WI",
    "sg:tags":[
        "housewares"
    ],
    "wof:name":"Royal Prestige Of Wi Inc",
    "wof:placetype":"venue"
},
  "geometry": {"coordinates":[-88.029025,43.035688],"type":"Point"}
}