{
  "type": "Feature",
  "properties": {
    "iso:country":"US",
    "sg:address":"127 S Spring St",
    "sg:city":"Beaver Dam",
    "sg:classifiers":[
        {
            "category":"Organizations",
            "subcategory":"Professional Association",
            "type":"Services"
        }
    ],
    "sg:phone":"+1 920 887 8879",
    "sg:postcode":"53916",
    "sg:province":"WI",
    "sg:tags":[
        "chambers",
        "commerce"
    ],
    "sg:website":"www.beaverdamchamber.com",
    "wof:name":"Beaver Dam Area Chamber-Cmmrc",
    "wof:placetype":"venue"
},
  "geometry": {"coordinates":[-88.836815,43.455957],"type":"Point"}
}