{
  "type": "Feature",
  "properties": {
    "iso:country":"US",
    "sg:address":"621 E Glencoe Pl",
    "sg:city":"Milwaukee",
    "sg:classifiers":[
        {
            "category":"Manufacturing",
            "subcategory":"Printing",
            "type":"Manufacturing & Wholesale Goods"
        }
    ],
    "sg:phone":"+1 414 352 4466",
    "sg:postcode":"53217",
    "sg:province":"WI",
    "sg:tags":[
        "commercial"
    ],
    "wof:name":"Meisenheimer Associates",
    "wof:placetype":"venue"
},
  "geometry": {"coordinates":[-87.901816,43.177726],"type":"Point"}
}