{
  "type": "Feature",
  "properties": {
    "iso:country":"US",
    "sg:address":"2207 255th St",
    "sg:city":"Saint Croix Falls",
    "sg:classifiers":[
        {
            "category":"Building & Trades",
            "subcategory":"Construction",
            "type":"Services"
        }
    ],
    "sg:phone":"+1 715 483 1313",
    "sg:postcode":"54024",
    "sg:province":"WI",
    "sg:tags":[
        "house"
    ],
    "wof:name":"Double O Construction LLC",
    "wof:placetype":"venue"
},
  "geometry": {"coordinates":[-92.682605,45.519915],"type":"Point"}
}