{
  "type": "Feature",
  "properties": {
    "addr:full":"3535 W State St Milwaukee WI 53208",
    "addr:housenumber":"3535",
    "addr:postcode":"53208",
    "addr:street":"W State St",
    "iso:country":"US",
    "sg:address":"3535 W State St",
    "sg:city":"Milwaukee",
    "sg:classifiers":[
        {
            "category":"Manufacturing",
            "subcategory":"Wood Products",
            "type":"Manufacturing & Wholesale Goods"
        }
    ],
    "sg:phone":"+1 414 342 0531",
    "sg:postcode":"53208",
    "sg:province":"WI",
    "sg:tags":[
        "millwork-wholesale",
        "millwork",
        "manufacturer"
    ],
    "sg:website":"http://www.ajpeach.com",
    "wof:name":"A.J. Pietsch Co., Inc.",
    "wof:placetype":"venue"
},
  "geometry": {"coordinates":[-87.958556,43.043566],"type":"Point"}
}