{
  "type": "Feature",
  "properties": {
    "iso:country":"US",
    "sg:address":"5678 704th Ave",
    "sg:city":"Menomonie",
    "sg:classifiers":[
        {
            "category":"Building & Trades",
            "subcategory":"Plumbing",
            "type":"Services"
        }
    ],
    "sg:phone":"+1 715 235 5790",
    "sg:postcode":"54751",
    "sg:province":"WI",
    "sg:tags":[
        "plumbing",
        "contractor"
    ],
    "wof:name":"Koehler Septic & Plumbing",
    "wof:placetype":"venue"
},
  "geometry": {"coordinates":[-91.877479,44.934895],"type":"Point"}
}