{
  "type": "Feature",
  "properties": {
    "iso:country":"US",
    "sg:address":"99 E Towne Mall",
    "sg:city":"Madison",
    "sg:classifiers":[
        {
            "category":"Restaurant",
            "type":"Food & Drink"
        }
    ],
    "sg:menulink":"http://www.allmenus.com/wi/madison/233466-pretzel-maker/menu/",
    "sg:phone":"+1 608 249 3020",
    "sg:postcode":"53704",
    "sg:province":"WI",
    "sg:tags":[
        "new",
        "american"
    ],
    "wof:name":"Pretzel Maker",
    "wof:placetype":"venue"
},
  "geometry": {"coordinates":[-89.302018,43.124352],"type":"Point"}
}