{
  "type": "Feature",
  "properties": {
    "iso:country":"US",
    "sg:address":"307 N Washington St",
    "sg:city":"Thorp",
    "sg:classifiers":[
        {
            "category":"Bars & Pubs",
            "type":"Food & Drink"
        }
    ],
    "sg:phone":"+1 715 669 5801",
    "sg:postcode":"54771",
    "sg:province":"WI",
    "wof:name":"Cindy's",
    "wof:placetype":"venue"
},
  "geometry": {"coordinates":[-90.800371,44.961735],"type":"Point"}
}