{
  "type": "Feature",
  "properties": {
    "iso:country":"US",
    "sg:address":"626 E Kilbourn Ave",
    "sg:city":"Milwaukee",
    "sg:classifiers":[
        {
            "category":"Professional",
            "type":"Services"
        }
    ],
    "sg:phone":"+1 414 225 9390",
    "sg:postcode":"53202",
    "sg:province":"WI",
    "wof:name":"Krazy Wake Shack",
    "wof:placetype":"venue"
},
  "geometry": {"coordinates":[-87.903475,43.042766],"type":"Point"}
}