{
  "type": "Feature",
  "properties": {
    "iso:country":"US",
    "sg:address":"1763 Audubon Ave",
    "sg:city":"Grafton",
    "sg:classifiers":[
        {
            "category":"Professional",
            "subcategory":"Computer Services",
            "type":"Services"
        }
    ],
    "sg:phone":"+1 262 375 0667",
    "sg:postcode":"53024",
    "sg:province":"WI",
    "sg:tags":[
        "programing",
        "custom"
    ],
    "wof:name":"Dennis Knutson",
    "wof:placetype":"venue"
},
  "geometry": {"coordinates":[-87.96703599999999,43.310696],"type":"Point"}
}