{
  "type": "Feature",
  "properties": {
    "iso:country":"US",
    "sg:address":"9419 W Mineral Point Rd",
    "sg:city":"Janesville",
    "sg:classifiers":[
        {
            "category":"Farming",
            "subcategory":"Dairy Farm",
            "type":"Manufacturing & Wholesale Goods"
        }
    ],
    "sg:phone":"+1 608 876 6773",
    "sg:postcode":"53548",
    "sg:province":"WI",
    "wof:name":"Ballmerland Farms",
    "wof:placetype":"venue"
},
  "geometry": {"coordinates":[-89.17660600000001,42.687118],"type":"Point"}
}