{
  "type": "Feature",
  "properties": {
    "iso:country":"US",
    "sg:address":"306 Mill St",
    "sg:city":"Clinton",
    "sg:classifiers":[
        {
            "category":"Building & Trades",
            "subcategory":"Construction",
            "type":"Services"
        }
    ],
    "sg:phone":"+1 608 676 1100",
    "sg:postcode":"53525",
    "sg:province":"WI",
    "sg:tags":[
        "hanging",
        "contractor"
    ],
    "wof:name":"Van Egmond Painting",
    "wof:placetype":"venue"
},
  "geometry": {"coordinates":[-88.861445,42.557313],"type":"Point"}
}