{
  "type": "Feature",
  "properties": {
    "iso:country":"US",
    "sg:address":"1116 N Claremont Dr",
    "sg:city":"Janesville",
    "sg:classifiers":[
        {
            "category":"Education",
            "subcategory":"Special Training",
            "type":"Public Place"
        }
    ],
    "sg:phone":"+1 608 754 5316",
    "sg:postcode":"53545",
    "sg:province":"WI",
    "sg:tags":[
        "instruction",
        "flight"
    ],
    "wof:name":"A V I W A C R",
    "wof:placetype":"venue"
},
  "geometry": {"coordinates":[-88.991332,42.699159],"type":"Point"}
}