{
  "type": "Feature",
  "properties": {
    "iso:country":"US",
    "sg:address":"7919 N Lake Dr",
    "sg:city":"Milwaukee",
    "sg:classifiers":[
        {
            "category":"Professional",
            "subcategory":"Accounting & Tax Preparation",
            "type":"Services"
        }
    ],
    "sg:phone":"+1 414 351 3600",
    "sg:postcode":"53217",
    "sg:province":"WI",
    "wof:name":"Kenneth F Schelong CPA",
    "wof:placetype":"venue"
},
  "geometry": {"coordinates":[-87.896918,43.160126],"type":"Point"}
}