{
  "type": "Feature",
  "properties": {
    "addr:full":"13894 Willow Rd Suring WI 54174",
    "addr:housenumber":"13894",
    "addr:postcode":"54174",
    "addr:street":"Willow Rd",
    "iso:country":"US",
    "sg:address":"13894 Willow Rd",
    "sg:city":"Suring",
    "sg:classifiers":[
        {
            "category":"Farming",
            "subcategory":"Dairy Farm",
            "type":"Manufacturing & Wholesale Goods"
        }
    ],
    "sg:phone":"+1 920 842 2248",
    "sg:postcode":"54174",
    "sg:province":"WI",
    "sg:tags":[
        "corn",
        "grain",
        "cash"
    ],
    "wof:name":"Gardebrecht Donald",
    "wof:placetype":"venue"
},
  "geometry": {"coordinates":[-88.4568,45.015394],"type":"Point"}
}