{
  "type": "Feature",
  "properties": {
    "iso:country":"US",
    "sg:address":"8831 W Herbert Ave",
    "sg:city":"Milwaukee",
    "sg:classifiers":[
        {
            "category":"Building & Trades",
            "subcategory":"Cleaning & Sanitation",
            "type":"Services"
        }
    ],
    "sg:phone":"+1 414 393 0548",
    "sg:postcode":"53225",
    "sg:province":"WI",
    "sg:tags":[
        "janitor"
    ],
    "wof:name":"Fresh & Clean",
    "wof:placetype":"venue"
},
  "geometry": {"coordinates":[-88.022469,43.102978],"type":"Point"}
}