{
  "type": "Feature",
  "properties": {
    "iso:country":"US",
    "sg:address":"803 Klaus St",
    "sg:city":"Green Bay",
    "sg:classifiers":[
        {
            "category":"Restaurant",
            "type":"Food & Drink"
        }
    ],
    "sg:phone":"+1 920 437 9595",
    "sg:postcode":"54302",
    "sg:province":"WI",
    "sg:tags":[
        "eating",
        "out"
    ],
    "wof:name":"Mill Town Cafe",
    "wof:placetype":"venue"
},
  "geometry": {"coordinates":[-87.99827500000001,44.524136],"type":"Point"}
}