{
  "type": "Feature",
  "properties": {
    "addr:full":"15600 W National Ave New Berlin WI 53151",
    "addr:housenumber":"15600",
    "addr:postcode":"53151",
    "addr:street":"W National Ave",
    "iso:country":"US",
    "sg:address":"15600 W National Ave",
    "sg:city":"New Berlin",
    "sg:classifiers":[
        {
            "category":"Coffee & Tea",
            "type":"Food & Drink"
        }
    ],
    "sg:menulink":"http://www.allmenus.com/wi/new-berlin/117975-starbucks-coffee/menu/",
    "sg:phone":"+1 262 938 9117",
    "sg:postcode":"53151",
    "sg:province":"WI",
    "sg:tags":[
        "american"
    ],
    "wof:name":"Starbucks Coffee",
    "wof:placetype":"venue"
},
  "geometry": {"coordinates":[-88.10903,42.976481],"type":"Point"}
}