{
  "type": "Feature",
  "properties": {
    "iso:country":"US",
    "sg:address":"9726 W Whitmore Rd",
    "sg:city":"Evansville",
    "sg:classifiers":[
        {
            "category":"Freight",
            "type":"Transportation"
        }
    ],
    "sg:phone":"+1 608 876 6056",
    "sg:postcode":"53536",
    "sg:province":"WI",
    "sg:tags":[
        "operator",
        "local",
        "trucking"
    ],
    "wof:name":"Hulbert Trking",
    "wof:placetype":"venue"
},
  "geometry": {"coordinates":[-89.174019,42.718571],"type":"Point"}
}