{
  "type": "Feature",
  "properties": {
    "iso:country":"US",
    "sg:address":"2534 Steffens Ct",
    "sg:city":"Green Bay",
    "sg:classifiers":[
        {
            "category":"Food & Beverages",
            "subcategory":"Groceries & Convenience Stores",
            "type":"Retail Goods"
        }
    ],
    "sg:phone":"+1 920 465 3800",
    "sg:postcode":"54311",
    "sg:province":"WI",
    "sg:tags":[
        "grocer"
    ],
    "sg:website":"www.festfoods.com",
    "wof:name":"Festival Foods",
    "wof:placetype":"venue"
},
  "geometry": {"coordinates":[-87.955566,44.468368],"type":"Point"}
}