{
  "type": "Feature",
  "properties": {
    "iso:country":"US",
    "sg:address":"2310 E Main St",
    "sg:city":"Merrill",
    "sg:classifiers":[
        {
            "category":"Shopping",
            "type":"Retail Goods"
        }
    ],
    "sg:phone":"+1 715 536 8300",
    "sg:postcode":"54452",
    "sg:province":"WI",
    "sg:tags":[
        "merchandise",
        "animal"
    ],
    "wof:name":"Pet-I-Cure Grooming Salon",
    "wof:placetype":"venue"
},
  "geometry": {"coordinates":[-89.668324,45.180838],"type":"Point"}
}