{
  "type": "Feature",
  "properties": {
    "iso:country":"US",
    "sg:address":"1400 Milwaukee Ave",
    "sg:city":"South Milwaukee",
    "sg:classifiers":[
        {
            "category":"Bars & Pubs",
            "type":"Food & Drink"
        }
    ],
    "sg:phone":"+1 414 762 7140",
    "sg:postcode":"53172",
    "sg:province":"WI",
    "sg:tags":[
        "drinking"
    ],
    "wof:name":"Kutchki's Bar",
    "wof:placetype":"venue"
},
  "geometry": {"coordinates":[-87.871011,42.910917],"type":"Point"}
}