{
  "type": "Feature",
  "properties": {
    "iso:country":"US",
    "sg:address":"1121 S Broadway",
    "sg:city":"Green Bay",
    "sg:classifiers":[
        {
            "category":"Manufacturing",
            "subcategory":"Apparel",
            "type":"Manufacturing & Wholesale Goods"
        }
    ],
    "sg:phone":"+1 920 437 6061",
    "sg:postcode":"54304",
    "sg:province":"WI",
    "sg:tags":[
        "upholstery",
        "boat",
        "mfg"
    ],
    "wof:name":"Allie Entps Mar Canvas Uphols",
    "wof:placetype":"venue"
},
  "geometry": {"coordinates":[-88.029495,44.504308],"type":"Point"}
}