{
  "type": "Feature",
  "properties": {
    "addr:full":"15718 Cemetery Rd Kiel WI 53042",
    "addr:housenumber":"15718",
    "addr:postcode":"53042",
    "addr:street":"Cemetery Rd",
    "iso:country":"US",
    "sg:address":"15718 Cemetery Rd",
    "sg:city":"Kiel",
    "sg:classifiers":[
        {
            "category":"Retail",
            "subcategory":"Animal Services",
            "type":"Services"
        }
    ],
    "sg:phone":"+1 920 894 2996",
    "sg:postcode":"53042",
    "sg:province":"WI",
    "wof:name":"Schubert Kennels Pet Resort",
    "wof:placetype":"venue"
},
  "geometry": {"coordinates":[-88.002307,43.91807],"type":"Point"}
}