{
  "type": "Feature",
  "properties": {
    "addr:full":"502 N 8th St Manitowoc WI 54220",
    "addr:housenumber":"502",
    "addr:postcode":"54220",
    "addr:street":"N 8Th St",
    "iso:country":"US",
    "sg:address":"502 N 8th St",
    "sg:city":"Manitowoc",
    "sg:classifiers":[
        {
            "category":"Organizations",
            "subcategory":"Religious Organization",
            "type":"Services"
        }
    ],
    "sg:phone":"+1 920 682 4688",
    "sg:postcode":"54220",
    "sg:province":"WI",
    "wof:name":"First Presbyterian Church",
    "wof:placetype":"venue"
},
  "geometry": {"coordinates":[-87.65777199999999,44.098794],"type":"Point"}
}