{
  "type": "Feature",
  "properties": {
    "iso:country":"US",
    "sg:address":"7642 US Hwy 61",
    "sg:city":"Lancaster",
    "sg:classifiers":[
        {
            "category":"Airport",
            "type":"Transportation"
        }
    ],
    "sg:phone":"+1 608 723 4366",
    "sg:postcode":"53813",
    "sg:province":"WI",
    "wof:name":"Lancaster Municipal Airport",
    "wof:placetype":"venue"
},
  "geometry": {"coordinates":[-90.682389,42.779331],"type":"Point"}
}