{
  "type": "Feature",
  "properties": {
    "iso:country":"US",
    "sg:address":"7980 Beaver Rd",
    "sg:city":"Bear Creek",
    "sg:classifiers":[
        {
            "category":"Restaurant",
            "type":"Food & Drink"
        }
    ],
    "sg:phone":"+1 715 823 5675",
    "sg:postcode":"54922",
    "sg:province":"WI",
    "sg:tags":[
        "eating"
    ],
    "wof:name":"Last Chance Cafe",
    "wof:placetype":"venue"
},
  "geometry": {"coordinates":[-88.87775600000001,44.524518],"type":"Point"}
}