{
  "type": "Feature",
  "properties": {
    "iso:country":"US",
    "sg:address":"4602 Speros Ln",
    "sg:city":"Eau Claire",
    "sg:classifiers":[
        {
            "category":"Shopping",
            "subcategory":"Bicycles & Sporting Goods",
            "type":"Retail Goods"
        }
    ],
    "sg:phone":"+1 715 839 8967",
    "sg:postcode":"54701",
    "sg:province":"WI",
    "wof:name":"Cnr Tackle & Supply",
    "wof:placetype":"venue"
},
  "geometry": {"coordinates":[-91.466987,44.76994],"type":"Point"}
}