{
  "type": "Feature",
  "properties": {
    "iso:country":"US",
    "sg:address":"5 S Henry St",
    "sg:city":"Edgerton",
    "sg:classifiers":[
        {
            "category":"Professional",
            "type":"Services"
        }
    ],
    "sg:phone":"+1 608 884 9691",
    "sg:postcode":"53534",
    "sg:province":"WI",
    "sg:tags":[
        "establishment"
    ],
    "wof:name":"Draconian",
    "wof:placetype":"venue"
},
  "geometry": {"coordinates":[-89.070721,42.833598],"type":"Point"}
}