{
  "type": "Feature",
  "properties": {
    "iso:country":"US",
    "sg:address":"4623 Clover Valley Rd",
    "sg:city":"Harshaw",
    "sg:classifiers":[
        {
            "category":"Food & Beverages",
            "subcategory":"Groceries & Convenience Stores",
            "type":"Retail Goods"
        }
    ],
    "sg:phone":"+1 715 282 5600",
    "sg:postcode":"54529",
    "sg:province":"WI",
    "wof:name":"Hermans Clover Valley Farm LL",
    "wof:placetype":"venue"
},
  "geometry": {"coordinates":[-89.642287,45.688443],"type":"Point"}
}