{
  "type": "Feature",
  "properties": {
    "addr:full":"1759 S 83rd St Milwaukee WI 53214",
    "addr:housenumber":"1759",
    "addr:postcode":"53214",
    "addr:street":"S 83Rd St",
    "iso:country":"US",
    "sg:address":"1759 S 83rd St",
    "sg:city":"Milwaukee",
    "sg:classifiers":[
        {
            "category":"Professional",
            "subcategory":"Lawyer & Legal Services",
            "type":"Services"
        }
    ],
    "sg:phone":"+1 414 476 0340",
    "sg:postcode":"53214",
    "sg:province":"WI",
    "wof:name":"Attorney At Law",
    "wof:placetype":"venue"
},
  "geometry": {"coordinates":[-88.015815,43.012405],"type":"Point"}
}