{
  "type": "Feature",
  "properties": {
    "iso:country":"US",
    "sg:address":"19801 83rd St",
    "sg:city":"Bristol",
    "sg:classifiers":[
        {
            "category":"Government",
            "subcategory":"City Hall",
            "type":"Public Place"
        },
        {
            "category":"Government",
            "subcategory":"Office",
            "type":"Public Place"
        }
    ],
    "sg:phone":"+1 262 857 2368",
    "sg:postcode":"53104",
    "sg:province":"WI",
    "sg:tags":[
        "town",
        "township",
        "planner",
        "government-city",
        "village"
    ],
    "wof:name":"Bristol Township",
    "wof:placetype":"venue"
},
  "geometry": {"coordinates":[-88.048027,42.55743],"type":"Point"}
}