{
  "type": "Feature",
  "properties": {
    "iso:country":"US",
    "sg:address":"516 Wilson Ave",
    "sg:city":"Sheboygan",
    "sg:classifiers":[
        {
            "category":"Professional",
            "subcategory":"Computer Services",
            "type":"Services"
        }
    ],
    "sg:phone":"+1 920 458 8025",
    "sg:postcode":"53081",
    "sg:province":"WI",
    "sg:tags":[
        "related"
    ],
    "wof:name":"Neese Microsystems",
    "wof:placetype":"venue"
},
  "geometry": {"coordinates":[-87.710126,43.723049],"type":"Point"}
}