{
  "type": "Feature",
  "properties": {
    "iso:country":"US",
    "sg:address":"4195 Cemetery Rd",
    "sg:city":"Reedsburg",
    "sg:classifiers":[
        {
            "category":"Farming",
            "subcategory":"Dairy Farm",
            "type":"Manufacturing & Wholesale Goods"
        }
    ],
    "sg:phone":"+1 608 985 7071",
    "sg:postcode":"53959",
    "sg:province":"WI",
    "wof:name":"Michael Cummings",
    "wof:placetype":"venue"
},
  "geometry": {"coordinates":[-90.108407,43.549017],"type":"Point"}
}