{
  "type": "Feature",
  "properties": {
    "addr:full":"2050 Winchester Ave Oshkosh WI 54901",
    "addr:housenumber":"2050",
    "addr:postcode":"54901",
    "addr:street":"Winchester Ave",
    "iso:country":"US",
    "sg:address":"2050 Winchester Ave",
    "sg:city":"Oshkosh",
    "sg:classifiers":[
        {
            "category":"Building & Trades",
            "subcategory":"Construction",
            "type":"Services"
        }
    ],
    "sg:phone":"+1 920 233 5309",
    "sg:postcode":"54901",
    "sg:province":"WI",
    "sg:tags":[
        "company"
    ],
    "wof:name":"Litjen Construction",
    "wof:placetype":"venue"
},
  "geometry": {"coordinates":[-88.56174900000001,44.04507],"type":"Point"}
}