{
  "type": "Feature",
  "properties": {
    "addr:full":"460 Main St Wild Rose WI 54984",
    "addr:housenumber":"460",
    "addr:postcode":"54984",
    "addr:street":"Main St",
    "iso:country":"US",
    "sg:address":"460 Main St",
    "sg:city":"Wild Rose",
    "sg:classifiers":[
        {
            "category":"Banks & Credit Unions",
            "subcategory":"Bank",
            "type":"Services"
        }
    ],
    "sg:phone":"+1 920 622 3264",
    "sg:postcode":"54984",
    "sg:province":"WI",
    "wof:name":"F & M Bank",
    "wof:placetype":"venue"
},
  "geometry": {"coordinates":[-89.247018,44.181783],"type":"Point"}
}