{
  "type": "Feature",
  "properties": {
    "iso:country":"US",
    "sg:address":"9450 Dellwood Rd",
    "sg:city":"Reedsburg",
    "sg:classifiers":[
        {
            "category":"Real Estate",
            "subcategory":"Real Estate Operator",
            "type":"Services"
        }
    ],
    "sg:phone":"+1 608 254 6363",
    "sg:postcode":"53959",
    "sg:province":"WI",
    "sg:tags":[
        "mobile",
        "home",
        "site",
        "community"
    ],
    "wof:name":"Dellwood Mobile Home Court",
    "wof:placetype":"venue"
},
  "geometry": {"coordinates":[-89.852245,43.561825],"type":"Point"}
}