{
  "type": "Feature",
  "properties": {
    "addr:full":"505 King St Onalaska WI 54650",
    "addr:housenumber":"505",
    "addr:postcode":"54650",
    "addr:street":"King St",
    "iso:country":"US",
    "sg:address":"505 King St",
    "sg:city":"Onalaska",
    "sg:classifiers":[
        {
            "category":"Parking",
            "type":"Transportation"
        }
    ],
    "sg:phone":"+1 608 784 4050",
    "sg:postcode":"54650",
    "sg:province":"WI",
    "sg:tags":[
        "garage"
    ],
    "wof:name":"King On 5th",
    "wof:placetype":"venue"
},
  "geometry": {"coordinates":[-91.230206,43.884897],"type":"Point"}
}