{
  "type": "Feature",
  "properties": {
    "iso:country":"US",
    "sg:address":"5801 W Saint Lawrence Ave",
    "sg:city":"Beloit",
    "sg:classifiers":[
        {
            "category":"Personal",
            "subcategory":"Shoe Repair & Shine",
            "type":"Services"
        }
    ],
    "sg:phone":"+1 608 362 3541",
    "sg:postcode":"53511",
    "sg:province":"IL",
    "sg:tags":[
        "parlor"
    ],
    "wof:name":"Family Luggage Repair",
    "wof:placetype":"venue"
},
  "geometry": {"coordinates":[-89.119337,42.504228],"type":"Point"}
}