{
  "type": "Feature",
  "properties": {
    "iso:country":"US",
    "sg:address":"7845 Harwood Ave",
    "sg:city":"Milwaukee",
    "sg:classifiers":[
        {
            "category":"Professional",
            "subcategory":"Advertising",
            "type":"Services"
        }
    ],
    "sg:phone":"+1 414 443 0850",
    "sg:postcode":"53213",
    "sg:province":"WI",
    "sg:tags":[
        "public",
        "relations"
    ],
    "wof:name":"Leum Roberts Inc",
    "wof:placetype":"venue"
},
  "geometry": {"coordinates":[-88.011105,43.047873],"type":"Point"}
}