{
  "type": "Feature",
  "properties": {
    "iso:country":"US",
    "sg:address":"2077 200th St",
    "sg:city":"Centuria",
    "sg:classifiers":[
        {
            "category":"Farming",
            "subcategory":"Dairy Farm",
            "type":"Manufacturing & Wholesale Goods"
        }
    ],
    "sg:phone":"+1 715 825 4441",
    "sg:postcode":"54824",
    "sg:province":"WI",
    "wof:name":"Roger Fisk",
    "wof:placetype":"venue"
},
  "geometry": {"coordinates":[-92.569562,45.50113],"type":"Point"}
}