{
  "type": "Feature",
  "properties": {
    "iso:country":"US",
    "sg:address":"600 52nd St",
    "sg:city":"Kenosha",
    "sg:classifiers":[
        {
            "category":"Professional",
            "subcategory":"Lawyer & Legal Services",
            "type":"Services"
        }
    ],
    "sg:phone":"+1 262 658 4800",
    "sg:postcode":"53140",
    "sg:province":"WI",
    "sg:tags":[
        "firm",
        "attorney",
        "law"
    ],
    "sg:website":"www.kenoshalawyers.com",
    "wof:name":"Guttormsen Hartley & Guttormse",
    "wof:placetype":"venue"
},
  "geometry": {"coordinates":[-87.820454,42.588108],"type":"Point"}
}