{
  "type": "Feature",
  "properties": {
    "iso:country":"US",
    "sg:address":"7436 Mineral Point Rd",
    "sg:city":"Madison",
    "sg:classifiers":[
        {
            "category":"Restaurant",
            "type":"Food & Drink"
        },
        {
            "category":"Bars & Pubs",
            "type":"Food & Drink"
        }
    ],
    "sg:phone":"+1 608 833 4262",
    "sg:postcode":"53717",
    "sg:province":"WI",
    "sg:tags":[
        "drinking"
    ],
    "wof:name":"Martin O'Grady Irish Pub",
    "wof:placetype":"venue"
},
  "geometry": {"coordinates":[-89.512274,43.060655],"type":"Point"}
}