{
  "type": "Feature",
  "properties": {
    "iso:country":"US",
    "sg:address":"8951 Enterprise Way",
    "sg:city":"Schofield",
    "sg:classifiers":[
        {
            "category":"Manufacturing",
            "subcategory":"Metals",
            "type":"Manufacturing & Wholesale Goods"
        }
    ],
    "sg:phone":"+1 715 359 2073",
    "sg:postcode":"54476",
    "sg:province":"WI",
    "sg:tags":[
        "tube",
        "fabricating"
    ],
    "wof:name":"J & D Tube Benders Inc",
    "wof:placetype":"venue"
},
  "geometry": {"coordinates":[-89.51475499999999,44.897823],"type":"Point"}
}