{
  "type": "Feature",
  "properties": {
    "addr:full":"6174 Eagle Ln Wittenberg WI 54499",
    "addr:housenumber":"6174",
    "addr:postcode":"54499",
    "addr:street":"Eagle Ln",
    "iso:country":"US",
    "sg:address":"6174 Eagle Ln",
    "sg:city":"Wittenberg",
    "sg:classifiers":[
        {
            "category":"Manufacturing",
            "subcategory":"Lumber",
            "type":"Manufacturing & Wholesale Goods"
        }
    ],
    "sg:phone":"+1 715 253 2399",
    "sg:postcode":"54499",
    "sg:province":"WI",
    "sg:tags":[
        "logging"
    ],
    "wof:name":"Hoekstra Logging & Forestry",
    "wof:placetype":"venue"
},
  "geometry": {"coordinates":[-89.18373699999999,44.8197],"type":"Point"}
}