{
  "type": "Feature",
  "properties": {
    "iso:country":"US",
    "sg:address":"1218 Oshkosh Ave",
    "sg:city":"Oshkosh",
    "sg:classifiers":[
        {
            "category":"Organizations",
            "subcategory":"Labor Organization",
            "type":"Services"
        }
    ],
    "sg:phone":"+1 920 235 8884",
    "sg:postcode":"54902",
    "sg:province":"WI",
    "wof:name":"MCI Telecommunications",
    "wof:placetype":"venue"
},
  "geometry": {"coordinates":[-88.56727,44.034333],"type":"Point"}
}