{
  "type": "Feature",
  "properties": {
    "iso:country":"US",
    "sg:address":"3737 Blueberry Rd",
    "sg:city":"Warrens",
    "sg:classifiers":[
        {
            "category":"Social Services",
            "subcategory":"Adult Care",
            "type":"Services"
        }
    ],
    "sg:phone":"+1 608 378 4054",
    "sg:postcode":"54666",
    "sg:province":"WI",
    "sg:tags":[
        "residential"
    ],
    "wof:name":"Agape Acres Supportive Living",
    "wof:placetype":"venue"
},
  "geometry": {"coordinates":[-90.588092,44.119304],"type":"Point"}
}