{
  "type": "Feature",
  "properties": {
    "iso:country":"US",
    "sg:address":"2267 Manley Dr",
    "sg:city":"Sun Prairie",
    "sg:classifiers":[
        {
            "category":"Shopping",
            "type":"Retail Goods"
        }
    ],
    "sg:phone":"+1 608 825 2777",
    "sg:postcode":"53590",
    "sg:province":"WI",
    "sg:tags":[
        "merchandise"
    ],
    "wof:name":"Thunder Bay Gifts",
    "wof:placetype":"venue"
},
  "geometry": {"coordinates":[-89.178982,43.180223],"type":"Point"}
}