{
  "type": "Feature",
  "properties": {
    "addr:full":"6370 N Green Bay Ave Milwaukee WI 53209",
    "addr:housenumber":"6370",
    "addr:postcode":"53209",
    "addr:street":"N Green Bay Ave",
    "iso:country":"US",
    "sg:address":"6370 N Green Bay Ave",
    "sg:city":"Milwaukee",
    "sg:classifiers":[
        {
            "category":"Social Services",
            "subcategory":"Adult Care",
            "type":"Services"
        }
    ],
    "sg:phone":"+1 414 228 1880",
    "sg:postcode":"53209",
    "sg:province":"WI",
    "sg:tags":[
        "home",
        "residential"
    ],
    "wof:name":"New Living Concepts",
    "wof:placetype":"venue"
},
  "geometry": {"coordinates":[-87.93231,43.133067],"type":"Point"}
}