{
  "type": "Feature",
  "properties": {
    "iso:country":"US",
    "sg:address":"1559 State Rd 49",
    "sg:city":"Berlin",
    "sg:classifiers":[
        {
            "category":"Building & Trades",
            "subcategory":"Construction",
            "type":"Services"
        }
    ],
    "sg:phone":"+1 920 361 0749",
    "sg:postcode":"54923",
    "sg:province":"WI",
    "sg:tags":[
        "house"
    ],
    "wof:name":"Greening Construction",
    "wof:placetype":"venue"
},
  "geometry": {"coordinates":[-88.971133,44.032413],"type":"Point"}
}