{
  "type": "Feature",
  "properties": {
    "addr:full":"716 S Hill Rd Beloit WI 53511",
    "addr:housenumber":"716",
    "addr:postcode":"53511",
    "addr:street":"S Hill Rd",
    "iso:country":"US",
    "sg:address":"716 S Hill Rd",
    "sg:city":"Beloit",
    "sg:classifiers":[
        {
            "category":"Farming",
            "subcategory":"Farm",
            "type":"Manufacturing & Wholesale Goods"
        }
    ],
    "sg:phone":"+1 608 362 1214",
    "sg:postcode":"53511",
    "sg:province":"WI",
    "sg:tags":[
        "crop",
        "general"
    ],
    "wof:name":"Louise Junig",
    "wof:placetype":"venue"
},
  "geometry": {"coordinates":[-89.03379200000001,42.542947],"type":"Point"}
}