{
  "type": "Feature",
  "properties": {
    "iso:country":"US",
    "sg:address":"3940 S Woodhill Ln",
    "sg:city":"New Berlin",
    "sg:classifiers":[
        {
            "category":"Wholesale",
            "subcategory":"Non-durable Goods",
            "type":"Manufacturing & Wholesale Goods"
        }
    ],
    "sg:phone":"+1 262 827 1339",
    "sg:postcode":"53151",
    "sg:province":"WI",
    "wof:name":"DK Imports LLC",
    "wof:placetype":"venue"
},
  "geometry": {"coordinates":[-88.073269,42.970341],"type":"Point"}
}