{
  "type": "Feature",
  "properties": {
    "iso:country":"US",
    "sg:address":"304 Broadway St",
    "sg:city":"Baraboo",
    "sg:classifiers":[
        {
            "category":"Banks & Credit Unions",
            "subcategory":"Bank",
            "type":"Services"
        }
    ],
    "sg:phone":"+1 608 355 0532",
    "sg:postcode":"53913",
    "sg:province":"WI",
    "sg:tags":[
        "depository",
        "banking"
    ],
    "wof:name":"Efmark",
    "wof:placetype":"venue"
},
  "geometry": {"coordinates":[-89.744203,43.468936],"type":"Point"}
}