{
  "type": "Feature",
  "properties": {
    "iso:country":"US",
    "sg:address":"430 Clarmar Dr",
    "sg:city":"Sun Prairie",
    "sg:classifiers":[
        {
            "category":"Sports & Exercise",
            "subcategory":"Bowling",
            "type":"Entertainment"
        }
    ],
    "sg:phone":"+1 608 837 2586",
    "sg:postcode":"53590",
    "sg:province":"WI",
    "sg:tags":[
        "center"
    ],
    "sg:website":"www.prairielanes.com",
    "wof:name":"Prairie Lanes",
    "wof:placetype":"venue"
},
  "geometry": {"coordinates":[-89.241776,43.175686],"type":"Point"}
}