{
  "type": "Feature",
  "properties": {
    "iso:country":"US",
    "sg:address":"825 Lincoln St",
    "sg:city":"Rhinelander",
    "sg:classifiers":[
        {
            "category":"Restaurant",
            "type":"Food & Drink"
        }
    ],
    "sg:phone":"+1 715 369 1556",
    "sg:postcode":"54501",
    "sg:province":"WI",
    "sg:tags":[
        "eating"
    ],
    "wof:name":"Peking Chinese Restaurant",
    "wof:placetype":"venue"
},
  "geometry": {"coordinates":[-89.39953199999999,45.633071],"type":"Point"}
}