{
  "type": "Feature",
  "properties": {
    "iso:country":"US",
    "sg:address":"325 Carroll St",
    "sg:city":"Random Lake",
    "sg:classifiers":[
        {
            "category":"Retail",
            "subcategory":"Auto Repair",
            "type":"Services"
        }
    ],
    "sg:phone":"+1 920 994 2205",
    "sg:postcode":"53075",
    "sg:province":"WI",
    "sg:tags":[
        "repairing",
        "automobile"
    ],
    "wof:name":"Finnegan Automotive",
    "wof:placetype":"venue"
},
  "geometry": {"coordinates":[-87.962065,43.552355],"type":"Point"}
}