{
  "type": "Feature",
  "properties": {
    "iso:country":"US",
    "sg:address":"919 Summit Ave",
    "sg:city":"Oconomowoc",
    "sg:classifiers":[
        {
            "category":"Taxi",
            "type":"Transportation"
        }
    ],
    "sg:phone":"+1 262 567 6404",
    "sg:postcode":"53066",
    "sg:province":"WI",
    "sg:tags":[
        "taxicab"
    ],
    "wof:name":"Silver Streak Inc",
    "wof:placetype":"venue"
},
  "geometry": {"coordinates":[-88.48180499999999,43.097174],"type":"Point"}
}