{
  "type": "Feature",
  "properties": {
    "iso:country":"US",
    "sg:address":"2500 N Mayfair Rd",
    "sg:city":"Milwaukee",
    "sg:classifiers":[
        {
            "category":"Food & Beverages",
            "subcategory":"Groceries & Convenience Stores",
            "type":"Retail Goods"
        }
    ],
    "sg:phone":"+1 414 453 3422",
    "sg:postcode":"53222",
    "sg:province":"WI",
    "wof:name":"Mayfair Market",
    "wof:placetype":"venue"
},
  "geometry": {"coordinates":[-88.047678,43.063727],"type":"Point"}
}