{
  "type": "Feature",
  "properties": {
    "iso:country":"US",
    "sg:address":"237 Broadway St",
    "sg:city":"Berlin",
    "sg:classifiers":[
        {
            "category":"Organizations",
            "subcategory":"Non-profit Organization",
            "type":"Services"
        }
    ],
    "sg:phone":"+1 920 361 9880",
    "sg:postcode":"54923",
    "sg:province":"WI",
    "sg:tags":[
        "human"
    ],
    "sg:website":"www.advocap.org",
    "wof:name":"ADVOCAP",
    "wof:placetype":"venue"
},
  "geometry": {"coordinates":[-88.954098,43.968424],"type":"Point"}
}