{
  "type": "Feature",
  "properties": {
    "iso:country":"US",
    "sg:address":"322 Water St",
    "sg:city":"Eau Claire",
    "sg:classifiers":[
        {
            "category":"Bars & Pubs",
            "type":"Food & Drink"
        }
    ],
    "sg:phone":"+1 715 835 6959",
    "sg:postcode":"54703",
    "sg:province":"WI",
    "sg:tags":[
        "drinking"
    ],
    "wof:name":"Joynt The",
    "wof:placetype":"venue"
},
  "geometry": {"coordinates":[-91.507261,44.80224],"type":"Point"}
}