{
  "type": "Feature",
  "properties": {
    "iso:country":"US",
    "sg:address":"3267 S 16th St",
    "sg:city":"Milwaukee",
    "sg:classifiers":[
        {
            "category":"Health Services",
            "subcategory":"Doctor",
            "type":"Services"
        }
    ],
    "sg:phone":"+1 414 647 5505",
    "sg:postcode":"53215",
    "sg:province":"WI",
    "sg:tags":[
        "physician",
        "surgeon"
    ],
    "wof:name":"Medical Science Laboratories",
    "wof:placetype":"venue"
},
  "geometry": {"coordinates":[-87.933901,42.985956],"type":"Point"}
}