{
  "type": "Feature",
  "properties": {
    "iso:country":"US",
    "sg:address":"240 W Jefferson St",
    "sg:city":"Spring Green",
    "sg:classifiers":[
        {
            "category":"Health Services",
            "subcategory":"Doctor",
            "type":"Services"
        }
    ],
    "sg:phone":"+1 608 588 2122",
    "sg:postcode":"53588",
    "sg:province":"WI",
    "sg:tags":[
        "dentist"
    ],
    "wof:name":"Village Family Dental Assoc",
    "wof:placetype":"venue"
},
  "geometry": {"coordinates":[-90.070003,43.176735],"type":"Point"}
}