{
  "type": "Feature",
  "properties": {
    "iso:country":"US",
    "sg:address":"2050 Fish Hatchery Rd",
    "sg:city":"Madison",
    "sg:classifiers":[
        {
            "category":"Restaurant",
            "type":"Food & Drink"
        }
    ],
    "sg:phone":"+1 608 251 7827",
    "sg:postcode":"53713",
    "sg:province":"WI",
    "wof:name":"Jonny Thumbs Sub Station",
    "wof:placetype":"venue"
},
  "geometry": {"coordinates":[-89.403967,43.043071],"type":"Point"}
}