{
  "type": "Feature",
  "properties": {
    "iso:country":"US",
    "sg:address":"433 Jennifer Ave",
    "sg:city":"Burlington",
    "sg:classifiers":[
        {
            "category":"Professional",
            "subcategory":"Computer Services",
            "type":"Services"
        }
    ],
    "sg:phone":"+1 262 767 1881",
    "sg:postcode":"53105",
    "sg:province":"WI",
    "sg:tags":[
        "programing",
        "custom"
    ],
    "wof:name":"Freestanding",
    "wof:placetype":"venue"
},
  "geometry": {"coordinates":[-88.293875,42.669972],"type":"Point"}
}