{
  "type": "Feature",
  "properties": {
    "addr:full":"11050 W Co Rd B Hayward WI 54843",
    "addr:housenumber":"11050",
    "addr:postcode":"54843",
    "addr:street":"W Co Rd",
    "iso:country":"US",
    "sg:address":"11050 W Co Rd B",
    "sg:city":"Hayward",
    "sg:classifiers":[
        {
            "category":"Shopping",
            "subcategory":"Bicycles & Sporting Goods",
            "type":"Retail Goods"
        }
    ],
    "sg:phone":"+1 715 462 3055",
    "sg:postcode":"54843",
    "sg:province":"WI",
    "wof:name":"Jenks Bait & Tackle",
    "wof:placetype":"venue"
},
  "geometry": {"coordinates":[-91.21277000000001,45.982125],"type":"Point"}
}