{
  "type": "Feature",
  "properties": {
    "iso:country":"US",
    "sg:address":"4423 15th Rd",
    "sg:city":"Pound",
    "sg:classifiers":[
        {
            "category":"Real Estate",
            "subcategory":"Real Estate Operator",
            "type":"Services"
        }
    ],
    "sg:phone":"+1 920 897 3410",
    "sg:postcode":"54161",
    "sg:province":"WI",
    "sg:tags":[
        "property",
        "lessor"
    ],
    "wof:name":"Johnson Farm Kenneth",
    "wof:placetype":"venue"
},
  "geometry": {"coordinates":[-88.008152,45.118488],"type":"Point"}
}