{
  "type": "Feature",
  "properties": {
    "iso:country":"US",
    "sg:address":"737 218th St",
    "sg:city":"Osceola",
    "sg:classifiers":[
        {
            "category":"Manufacturing",
            "subcategory":"Pet Food",
            "type":"Manufacturing & Wholesale Goods"
        },
        {
            "category":"Farming",
            "subcategory":"Farm",
            "type":"Manufacturing & Wholesale Goods"
        }
    ],
    "sg:phone":"+1 715 755 3181",
    "sg:postcode":"54020",
    "sg:province":"WI",
    "sg:tags":[
        "hay"
    ],
    "wof:name":"Cronick, Gildo",
    "wof:placetype":"venue"
},
  "geometry": {"coordinates":[-92.606534,45.316689],"type":"Point"}
}