{
  "type": "Feature",
  "properties": {
    "iso:country":"US",
    "sg:address":"1838 Green Forest Run",
    "sg:city":"Janesville",
    "sg:classifiers":[
        {
            "category":"Real Estate",
            "subcategory":"Real Estate Operator",
            "type":"Services"
        }
    ],
    "sg:phone":"+1 608 758 3358",
    "sg:postcode":"53546",
    "sg:province":"WI",
    "sg:tags":[
        "building",
        "apartment"
    ],
    "wof:name":"Morningside Apartments",
    "wof:placetype":"venue"
},
  "geometry": {"coordinates":[-88.98055600000001,42.703837],"type":"Point"}
}