{
  "type": "Feature",
  "properties": {
    "iso:country":"US",
    "sg:address":"3734 S 52nd St",
    "sg:city":"Milwaukee",
    "sg:classifiers":[
        {
            "category":"Recreation",
            "subcategory":"Arcade",
            "type":"Entertainment"
        }
    ],
    "sg:phone":"+1 414 643 6174",
    "sg:postcode":"53220",
    "sg:province":"WI",
    "sg:tags":[
        "amusement",
        "devices"
    ],
    "wof:name":"Lincoln Novelty LTD",
    "wof:placetype":"venue"
},
  "geometry": {"coordinates":[-87.97927799999999,42.97636],"type":"Point"}
}