{
  "type": "Feature",
  "properties": {
    "iso:country":"US",
    "sg:address":"5014 Viking Trl",
    "sg:city":"Wautoma",
    "sg:classifiers":[
        {
            "category":"Professional",
            "subcategory":"Business Services",
            "type":"Services"
        }
    ],
    "sg:phone":"+1 920 787 3448",
    "sg:postcode":"54982",
    "sg:province":"WI",
    "wof:name":"Heimerl & Assoc",
    "wof:placetype":"venue"
},
  "geometry": {"coordinates":[-89.34632499999999,44.158979],"type":"Point"}
}