{
  "type": "Feature",
  "properties": {
    "iso:country":"US",
    "sg:address":"2013 3rd Ct",
    "sg:city":"Coloma",
    "sg:classifiers":[
        {
            "category":"Manufacturing",
            "subcategory":"Tools & Machinery",
            "type":"Manufacturing & Wholesale Goods"
        }
    ],
    "sg:phone":"+1 608 369 0878",
    "sg:postcode":"54930",
    "sg:province":"WI",
    "sg:tags":[
        "freight",
        "trucking"
    ],
    "wof:name":"Runabout Express Inc",
    "wof:placetype":"venue"
},
  "geometry": {"coordinates":[-89.647648,43.9616],"type":"Point"}
}