{
  "type": "Feature",
  "properties": {
    "iso:country":"US",
    "sg:address":"6014 W Lincoln Ave",
    "sg:city":"Milwaukee",
    "sg:classifiers":[
        {
            "category":"Shopping",
            "subcategory":"Clothing, Apparel, & Fashions",
            "type":"Retail Goods"
        }
    ],
    "sg:phone":"+1 414 541 8773",
    "sg:postcode":"53219",
    "sg:province":"WI",
    "sg:tags":[
        "tailor"
    ],
    "wof:name":"Joe's Tailor Shop",
    "wof:placetype":"venue"
},
  "geometry": {"coordinates":[-87.988688,43.003003],"type":"Point"}
}