{
  "type": "Feature",
  "properties": {
    "addr:full":"4327 N Wildwood Ave Milwaukee WI 53211",
    "addr:housenumber":"4327",
    "addr:postcode":"53211",
    "addr:street":"N Wildwood Ave",
    "iso:country":"US",
    "sg:address":"4327 N Wildwood Ave",
    "sg:city":"Milwaukee",
    "sg:classifiers":[
        {
            "category":"Professional",
            "subcategory":"Computer Services",
            "type":"Services"
        }
    ],
    "sg:phone":"+1 414 732 5000",
    "sg:postcode":"53211",
    "sg:province":"WI",
    "sg:tags":[
        "related"
    ],
    "wof:name":"Peter T Barry Co",
    "wof:placetype":"venue"
},
  "geometry": {"coordinates":[-87.896231,43.095624],"type":"Point"}
}