{
  "type": "Feature",
  "properties": {
    "addr:full":"817 Cedar Falls Rd Menomonie WI 54751",
    "addr:housenumber":"817",
    "addr:postcode":"54751",
    "addr:street":"Cedar Falls Rd",
    "iso:country":"US",
    "sg:address":"817 Cedar Falls Rd",
    "sg:city":"Menomonie",
    "sg:classifiers":[
        {
            "category":"Professional",
            "type":"Services"
        }
    ],
    "sg:phone":"+1 715 233 0209",
    "sg:postcode":"54751",
    "sg:province":"WI",
    "sg:tags":[
        "establishment"
    ],
    "wof:name":"B 2 Sports",
    "wof:placetype":"venue"
},
  "geometry": {"coordinates":[-91.922466,44.91182],"type":"Point"}
}