{
  "type": "Feature",
  "properties": {
    "iso:country":"US",
    "sg:address":"301 W Adams St",
    "sg:city":"La Farge",
    "sg:classifiers":[
        {
            "category":"Education",
            "subcategory":"School",
            "type":"Public Place"
        }
    ],
    "sg:phone":"+1 608 625 2400",
    "sg:postcode":"54639",
    "sg:province":"WI",
    "sg:website":"www.lafarge.k12.wi.us",
    "wof:name":"School District-LA Forge",
    "wof:placetype":"venue"
},
  "geometry": {"coordinates":[-90.63929,43.5798],"type":"Point"}
}