{
  "type": "Feature",
  "properties": {
    "iso:country":"US",
    "sg:address":"4379 S Howell Ave",
    "sg:city":"Milwaukee",
    "sg:classifiers":[
        {
            "category":"Social Services",
            "type":"Services"
        }
    ],
    "sg:phone":"+1 414 777 0740",
    "sg:postcode":"53207",
    "sg:province":"WI",
    "wof:name":"Solutions Behavioral Health Gr",
    "wof:placetype":"venue"
},
  "geometry": {"coordinates":[-87.90971999999999,42.964956],"type":"Point"}
}