{
  "type": "Feature",
  "properties": {
    "iso:country":"US",
    "sg:address":"1758 Appleton Rd",
    "sg:city":"Menasha",
    "sg:classifiers":[
        {
            "category":"Personal",
            "subcategory":"Beauty Salon",
            "type":"Services"
        }
    ],
    "sg:phone":"+1 920 969 3888",
    "sg:postcode":"54952",
    "sg:province":"WI",
    "sg:tags":[
        "shop"
    ],
    "wof:name":"Regis Salons",
    "wof:placetype":"venue"
},
  "geometry": {"coordinates":[-88.42406099999999,44.234967],"type":"Point"}
}