{
  "type": "Feature",
  "properties": {
    "iso:country":"US",
    "sg:address":"217 N Main St",
    "sg:city":"Shawano",
    "sg:classifiers":[
        {
            "category":"Personal",
            "subcategory":"Beauty Salon",
            "type":"Services"
        }
    ],
    "sg:phone":"+1 715 526 9555",
    "sg:postcode":"54166",
    "sg:province":"WI",
    "sg:tags":[
        "shop"
    ],
    "wof:name":"Kelly's Hair Studio",
    "wof:placetype":"venue"
},
  "geometry": {"coordinates":[-88.609508,44.783955],"type":"Point"}
}