{
  "type": "Feature",
  "properties": {
    "iso:country":"US",
    "sg:address":"1409 E Capitol Dr",
    "sg:city":"Milwaukee",
    "sg:classifiers":[
        {
            "category":"Professional",
            "subcategory":"Management & Consulting",
            "type":"Services"
        },
        {
            "category":"Banks & Credit Unions",
            "subcategory":"Financial Services",
            "type":"Services"
        }
    ],
    "sg:phone":"+1 414 967 8938",
    "sg:postcode":"53211",
    "sg:province":"WI",
    "sg:tags":[
        "consultant",
        "financing",
        "planning"
    ],
    "wof:name":"James Otzko",
    "wof:placetype":"venue"
},
  "geometry": {"coordinates":[-87.893439,43.089119],"type":"Point"}
}