{
  "type": "Feature",
  "properties": {
    "iso:country":"US",
    "sg:address":"19869 Mead Ave",
    "sg:city":"Norwalk",
    "sg:classifiers":[
        {
            "category":"Farming",
            "subcategory":"Dairy Farm",
            "type":"Manufacturing & Wholesale Goods"
        }
    ],
    "sg:phone":"+1 608 823 7505",
    "sg:postcode":"54648",
    "sg:province":"WI",
    "wof:name":"Glen Dreier",
    "wof:placetype":"venue"
},
  "geometry": {"coordinates":[-90.582292,43.81134],"type":"Point"}
}