{
  "type": "Feature",
  "properties": {
    "iso:country":"US",
    "sg:address":"5422 W Sunnyside Dr",
    "sg:city":"Thiensville",
    "sg:classifiers":[
        {
            "category":"Professional",
            "subcategory":"Business Services",
            "type":"Services"
        }
    ],
    "sg:phone":"+1 262 512 1256",
    "sg:postcode":"53092",
    "sg:province":"WI",
    "wof:name":"Petros Enterprise LLC",
    "wof:placetype":"venue"
},
  "geometry": {"coordinates":[-87.976833,43.222549],"type":"Point"}
}