{
  "type": "Feature",
  "properties": {
    "iso:country":"US",
    "sg:address":"841 Co Rd H",
    "sg:city":"Palmyra",
    "sg:classifiers":[
        {
            "category":"Wholesale",
            "subcategory":"Non-durable Goods",
            "type":"Manufacturing & Wholesale Goods"
        }
    ],
    "sg:phone":"+1 262 495 2033",
    "sg:postcode":"53156",
    "sg:province":"WI",
    "sg:tags":[
        "canvas"
    ],
    "wof:name":"Country Cover Ups",
    "wof:placetype":"venue"
},
  "geometry": {"coordinates":[-88.591825,42.872209],"type":"Point"}
}