{
  "type": "Feature",
  "properties": {
    "iso:country":"US",
    "sg:address":"654 E Green Bay Ave",
    "sg:city":"Saukville",
    "sg:classifiers":[
        {
            "category":"Building & Trades",
            "subcategory":"Construction",
            "type":"Services"
        }
    ],
    "sg:phone":"+1 262 268 2872",
    "sg:postcode":"53080",
    "sg:province":"WI",
    "sg:tags":[
        "general",
        "contractor"
    ],
    "wof:name":"Schneider Builders",
    "wof:placetype":"venue"
},
  "geometry": {"coordinates":[-87.934839,43.382881],"type":"Point"}
}