{
  "type": "Feature",
  "properties": {
    "iso:country":"US",
    "sg:address":"1500 Grange Ave",
    "sg:city":"Racine",
    "sg:classifiers":[
        {
            "category":"Organizations",
            "subcategory":"Religious Organization",
            "type":"Services"
        }
    ],
    "sg:phone":"+1 262 634 0631",
    "sg:postcode":"53405",
    "sg:province":"WI",
    "wof:name":"Bethany Methodist Church",
    "wof:placetype":"venue"
},
  "geometry": {"coordinates":[-87.811245,42.71241],"type":"Point"}
}