{
  "type": "Feature",
  "properties": {
    "iso:country":"US",
    "sg:address":"131 W Follett St",
    "sg:city":"Fond Du Lac",
    "sg:classifiers":[
        {
            "category":"Building & Trades",
            "subcategory":"Construction",
            "type":"Services"
        }
    ],
    "sg:phone":"+1 920 948 8045",
    "sg:postcode":"54935",
    "sg:province":"WI",
    "sg:tags":[
        "contractor",
        "dry wall",
        "hanging"
    ],
    "wof:name":"Rosenthal Drywall & Painting L",
    "wof:placetype":"venue"
},
  "geometry": {"coordinates":[-88.451437,43.784999],"type":"Point"}
}