{
  "type": "Feature",
  "properties": {
    "addr:full":"69 N 28th St Superior WI 54880",
    "addr:housenumber":"69",
    "addr:postcode":"54880",
    "addr:street":"N 28Th St",
    "iso:country":"US",
    "sg:address":"69 N 28th St",
    "sg:city":"Superior",
    "sg:classifiers":[
        {
            "category":"Shopping",
            "subcategory":"Department Store",
            "type":"Retail Goods"
        }
    ],
    "sg:phone":"+1 715 394 6107",
    "sg:postcode":"54880",
    "sg:province":"WI",
    "wof:name":"Dollar Days",
    "wof:placetype":"venue"
},
  "geometry": {"coordinates":[-92.079386,46.706255],"type":"Point"}
}