{
  "type": "Feature",
  "properties": {
    "iso:country":"US",
    "sg:address":"4775 450th St",
    "sg:city":"Ellsworth",
    "sg:classifiers":[
        {
            "category":"Recreation",
            "type":"Entertainment"
        }
    ],
    "sg:phone":"+1 715 273 3566",
    "sg:postcode":"54011",
    "sg:province":"WI",
    "sg:tags":[
        "club",
        "membership"
    ],
    "wof:name":"Rrtr Snowbile Club",
    "wof:placetype":"venue"
},
  "geometry": {"coordinates":[-92.358861,44.710815],"type":"Point"}
}