{
  "type": "Feature",
  "properties": {
    "iso:country":"US",
    "sg:address":"6829 Raymond Rd",
    "sg:city":"Madison",
    "sg:classifiers":[
        {
            "category":"Professional",
            "subcategory":"Computer Services",
            "type":"Services"
        }
    ],
    "sg:phone":"+1 608 288 0222",
    "sg:postcode":"53719",
    "sg:province":"WI",
    "sg:tags":[
        "related"
    ],
    "wof:name":"5 Deadmen Production",
    "wof:placetype":"venue"
},
  "geometry": {"coordinates":[-89.500891,43.031614],"type":"Point"}
}