{
  "type": "Feature",
  "properties": {
    "addr:full":"1810 Webster St Hudson WI 54016",
    "addr:housenumber":"1810",
    "addr:postcode":"54016",
    "addr:street":"Webster St",
    "iso:country":"US",
    "sg:address":"1810 Webster St",
    "sg:city":"Hudson",
    "sg:classifiers":[
        {
            "category":"Professional",
            "subcategory":"Management & Consulting",
            "type":"Services"
        }
    ],
    "sg:phone":"+1 715 381 5746",
    "sg:postcode":"54016",
    "sg:province":"WI",
    "sg:tags":[
        "consultant",
        "business"
    ],
    "wof:name":"Food Industry Group",
    "wof:placetype":"venue"
},
  "geometry": {"coordinates":[-92.73413499999999,44.960386],"type":"Point"}
}