{
  "type": "Feature",
  "properties": {
    "iso:country":"US",
    "sg:address":"6008 Lakeview Rd",
    "sg:city":"Larsen",
    "sg:classifiers":[
        {
            "category":"Manufacturing",
            "subcategory":"Tools & Machinery",
            "type":"Manufacturing & Wholesale Goods"
        }
    ],
    "sg:phone":"+1 920 836 3074",
    "sg:postcode":"54947",
    "sg:province":"WI",
    "sg:tags":[
        "machine",
        "shop"
    ],
    "wof:name":"A-Fab Inc",
    "wof:placetype":"venue"
},
  "geometry": {"coordinates":[-88.704376,44.1697],"type":"Point"}
}