{
  "type": "Feature",
  "properties": {
    "addr:full":"5522 Commerce Rd Onalaska WI 54650",
    "addr:housenumber":"5522",
    "addr:postcode":"54650",
    "addr:street":"Commerce Rd",
    "iso:country":"US",
    "sg:address":"5522 Commerce Rd",
    "sg:city":"Onalaska",
    "sg:classifiers":[
        {
            "category":"Building & Trades",
            "subcategory":"Construction",
            "type":"Services"
        }
    ],
    "sg:phone":"+1 608 781 3458",
    "sg:postcode":"54650",
    "sg:province":"WI",
    "sg:tags":[
        "general",
        "contractor"
    ],
    "wof:name":"Richard Volden Construction",
    "wof:placetype":"venue"
},
  "geometry": {"coordinates":[-91.243538,43.920789],"type":"Point"}
}