{
  "type": "Feature",
  "properties": {
    "iso:country":"US",
    "sg:address":"210 S Brooks St",
    "sg:city":"Madison",
    "sg:classifiers":[
        {
            "category":"Social Services",
            "subcategory":"Child Care",
            "type":"Services"
        }
    ],
    "sg:phone":"+1 608 267 6615",
    "sg:postcode":"53715",
    "sg:province":"WI",
    "sg:tags":[
        "day"
    ],
    "wof:name":"Meriter Child Care Center",
    "wof:placetype":"venue"
},
  "geometry": {"coordinates":[-89.402542,43.064358],"type":"Point"}
}