{
  "type": "Feature",
  "properties": {
    "iso:country":"US",
    "sg:address":"1776 American Dr",
    "sg:city":"Neenah",
    "sg:classifiers":[
        {
            "category":"Retail",
            "subcategory":"Car Wash",
            "type":"Services"
        }
    ],
    "sg:phone":"+1 920 722 7030",
    "sg:postcode":"54956",
    "sg:province":"WI",
    "sg:tags":[
        "carwash"
    ],
    "wof:name":"Quick Clean Car Wash",
    "wof:placetype":"venue"
},
  "geometry": {"coordinates":[-88.471666,44.222326],"type":"Point"}
}