{
  "type": "Feature",
  "properties": {
    "iso:country":"US",
    "sg:address":"1217 Kewaunee St",
    "sg:city":"Racine",
    "sg:classifiers":[
        {
            "category":"Social Services",
            "subcategory":"Child Care",
            "type":"Services"
        }
    ],
    "sg:phone":"+1 262 634 5353",
    "sg:postcode":"53404",
    "sg:province":"WI",
    "wof:name":"Innovative Child Care",
    "wof:placetype":"venue"
},
  "geometry": {"coordinates":[-87.79541999999999,42.739202],"type":"Point"}
}