{
  "type": "Feature",
  "properties": {
    "iso:country":"US",
    "sg:address":"1735 Nixon St",
    "sg:city":"Little Chute",
    "sg:classifiers":[
        {
            "category":"Professional",
            "subcategory":"Advertising",
            "type":"Services"
        }
    ],
    "sg:phone":"+1 920 788 5400",
    "sg:postcode":"54140",
    "sg:province":"WI",
    "sg:tags":[
        "designer",
        "display",
        "producer"
    ],
    "sg:website":"www.shapesunlimited.com",
    "wof:name":"Shapes Unlimited",
    "wof:placetype":"venue"
},
  "geometry": {"coordinates":[-88.300199,44.292357],"type":"Point"}
}