{
  "type": "Feature",
  "properties": {
    "addr:full":"1024 Western Dr Hartford WI 53027",
    "addr:housenumber":"1024",
    "addr:postcode":"53027",
    "addr:street":"Western Dr",
    "iso:country":"US",
    "sg:address":"1024 Western Dr",
    "sg:city":"Hartford",
    "sg:classifiers":[
        {
            "category":"Autos & Motor Vehicles",
            "subcategory":"Boat Sales",
            "type":"Retail Goods"
        }
    ],
    "sg:phone":"+1 262 644 0465",
    "sg:postcode":"53027",
    "sg:province":"WI",
    "sg:tags":[
        "equipment",
        "marine",
        "supply"
    ],
    "wof:name":"Pier D'Nort",
    "wof:placetype":"venue"
},
  "geometry": {"coordinates":[-88.397301,43.328236],"type":"Point"}
}