{
  "type": "Feature",
  "properties": {
    "iso:country":"US",
    "sg:address":"21605 Gateway Rd",
    "sg:city":"Brookfield",
    "sg:classifiers":[
        {
            "category":"Home & Garden",
            "subcategory":"Building Materials",
            "type":"Retail Goods"
        }
    ],
    "sg:phone":"+1 262 373 0400",
    "sg:postcode":"53045",
    "sg:province":"WI",
    "sg:tags":[
        "windows"
    ],
    "wof:name":"Weather-Tek Design Ctr Inc",
    "wof:placetype":"venue"
},
  "geometry": {"coordinates":[-88.18115400000001,43.074486],"type":"Point"}
}