{
  "type": "Feature",
  "properties": {
    "iso:country":"US",
    "sg:address":"510 Co Rd X",
    "sg:city":"Boyd",
    "sg:classifiers":[
        {
            "category":"Building & Trades",
            "subcategory":"Construction",
            "type":"Services"
        }
    ],
    "sg:phone":"+1 715 667 5377",
    "sg:postcode":"54726",
    "sg:province":"WI",
    "sg:tags":[
        "grading",
        "contractor"
    ],
    "wof:name":"Chippewa County Highway Dept",
    "wof:placetype":"venue"
},
  "geometry": {"coordinates":[-91.038215,44.944236],"type":"Point"}
}