{
  "type": "Feature",
  "properties": {
    "iso:country":"US",
    "sg:address":"2613 E Holmes Ave",
    "sg:city":"Cudahy",
    "sg:classifiers":[
        {
            "category":"Professional",
            "type":"Services"
        }
    ],
    "sg:phone":"+1 414 744 4759",
    "sg:postcode":"53110",
    "sg:province":"WI",
    "wof:name":"R & D Facility",
    "wof:placetype":"venue"
},
  "geometry": {"coordinates":[-87.875253,42.953748],"type":"Point"}
}