{
  "type": "Feature",
  "properties": {
    "iso:country":"US",
    "sg:address":"1250 W Washington Ave",
    "sg:city":"Cleveland",
    "sg:classifiers":[
        {
            "category":"Banks & Credit Unions",
            "subcategory":"Investment Brokerage",
            "type":"Services"
        }
    ],
    "sg:phone":"+1 920 693 3800",
    "sg:postcode":"53015",
    "sg:province":"WI",
    "sg:tags":[
        "security"
    ],
    "wof:name":"Invest Financial Corporation",
    "wof:placetype":"venue"
},
  "geometry": {"coordinates":[-87.752844,43.914046],"type":"Point"}
}