{
  "type": "Feature",
  "properties": {
    "iso:country":"US",
    "sg:address":"1109 E Orchard Beach Ln",
    "sg:city":"Rice Lake",
    "sg:classifiers":[
        {
            "category":"Social Services",
            "subcategory":"Child Care",
            "type":"Services"
        }
    ],
    "sg:phone":"+1 715 234 7931",
    "sg:postcode":"54868",
    "sg:province":"WI",
    "wof:name":"Early Headstart",
    "wof:placetype":"venue"
},
  "geometry": {"coordinates":[-91.718899,45.483685],"type":"Point"}
}