{
  "type": "Feature",
  "properties": {
    "iso:country":"US",
    "sg:address":"668 Co Rd C",
    "sg:city":"Independence",
    "sg:classifiers":[
        {
            "category":"Real Estate",
            "subcategory":"Real Estate Operator",
            "type":"Services"
        }
    ],
    "sg:phone":"+1 608 323 7298",
    "sg:postcode":"54747",
    "sg:province":"WI",
    "sg:tags":[
        "property",
        "lessor"
    ],
    "wof:name":"Rudy Christ",
    "wof:placetype":"venue"
},
  "geometry": {"coordinates":[-91.659723,44.341627],"type":"Point"}
}