{
  "type": "Feature",
  "properties": {
    "iso:country":"US",
    "sg:address":"5375 5th Rd",
    "sg:city":"Westfield",
    "sg:classifiers":[
        {
            "category":"Personal",
            "subcategory":"Beauty Salon",
            "type":"Services"
        }
    ],
    "sg:phone":"+1 608 296 4163",
    "sg:postcode":"53964",
    "sg:province":"WI",
    "sg:tags":[
        "shop"
    ],
    "wof:name":"Gr8 Cuts",
    "wof:placetype":"venue"
},
  "geometry": {"coordinates":[-89.512433,43.832366],"type":"Point"}
}