{
  "type": "Feature",
  "properties": {
    "addr:full":"237 S Curtis Rd West Allis WI 53214",
    "addr:housenumber":"237",
    "addr:postcode":"53214",
    "addr:street":"S Curtis Rd",
    "iso:country":"US",
    "sg:address":"237 S Curtis Rd",
    "sg:city":"West Allis",
    "sg:classifiers":[
        {
            "category":"Shopping",
            "type":"Retail Goods"
        }
    ],
    "sg:phone":"+1 414 258 2345",
    "sg:postcode":"53214",
    "sg:province":"WI",
    "sg:tags":[
        "water",
        "heater"
    ],
    "wof:name":"Tankless H20.Com-Takagi",
    "wof:placetype":"venue"
},
  "geometry": {"coordinates":[-88.062679,43.030438],"type":"Point"}
}