{
  "type": "Feature",
  "properties": {
    "addr:full":"321 N Prairie St Chippewa Falls WI 54729",
    "addr:housenumber":"321",
    "addr:postcode":"54729",
    "addr:street":"N Prairie St",
    "iso:country":"US",
    "sg:address":"321 N Prairie St",
    "sg:city":"Chippewa Falls",
    "sg:classifiers":[
        {
            "category":"Autos & Motor Vehicles",
            "subcategory":"Automobile Sales",
            "type":"Retail Goods"
        }
    ],
    "sg:phone":"+1 715 726 1261",
    "sg:postcode":"54729",
    "sg:province":"WI",
    "wof:name":"Markquart Motors",
    "wof:placetype":"venue"
},
  "geometry": {"coordinates":[-91.390759,44.939531],"type":"Point"}
}