{
  "type": "Feature",
  "properties": {
    "iso:country":"US",
    "sg:address":"216 W Walworth St",
    "sg:city":"Elkhorn",
    "sg:classifiers":[
        {
            "category":"Professional",
            "subcategory":"Computer Services",
            "type":"Services"
        }
    ],
    "sg:phone":"+1 262 723 1638",
    "sg:postcode":"53121",
    "sg:province":"WI",
    "sg:tags":[
        "internet"
    ],
    "wof:name":"Elknet Internet Svc",
    "wof:placetype":"venue"
},
  "geometry": {"coordinates":[-88.546406,42.671922],"type":"Point"}
}