{
  "type": "Feature",
  "properties": {
    "iso:country":"US",
    "sg:address":"1305 N Barker Rd",
    "sg:city":"Brookfield",
    "sg:classifiers":[
        {
            "category":"Professional",
            "type":"Services"
        }
    ],
    "sg:phone":"+1 262 784 4611",
    "sg:postcode":"53045",
    "sg:province":"WI",
    "sg:tags":[
        "establishment"
    ],
    "wof:name":"Modrock",
    "wof:placetype":"venue"
},
  "geometry": {"coordinates":[-88.166605,43.048009],"type":"Point"}
}