{
  "type": "Feature",
  "properties": {
    "addr:full":"1400 21st St Brodhead WI 53520",
    "addr:housenumber":"1400",
    "addr:postcode":"53520",
    "addr:street":"21St St",
    "iso:country":"US",
    "sg:address":"1400 21st St",
    "sg:city":"Brodhead",
    "sg:classifiers":[
        {
            "category":"Education",
            "subcategory":"School",
            "type":"Public Place"
        }
    ],
    "sg:phone":"+1 608 897 2146",
    "sg:postcode":"53520",
    "sg:province":"WI",
    "wof:name":"Albrecht Elementary School",
    "wof:placetype":"venue"
},
  "geometry": {"coordinates":[-89.383956,42.609971],"type":"Point"}
}