{
  "type": "Feature",
  "properties": {
    "iso:country":"US",
    "sg:address":"120 2nd St",
    "sg:city":"Hudson",
    "sg:classifiers":[
        {
            "category":"Banks & Credit Unions",
            "subcategory":"Bank",
            "type":"Services"
        }
    ],
    "sg:phone":"+1 715 381 2924",
    "sg:postcode":"54016",
    "sg:province":"WI",
    "sg:tags":[
        "loan",
        "mortgage",
        "real estate"
    ],
    "sg:website":"www.soundmortgagedecisions.com",
    "wof:name":"Sound Mortgage Decisions",
    "wof:placetype":"venue"
},
  "geometry": {"coordinates":[-92.75651999999999,44.971253],"type":"Point"}
}