{
  "type": "Feature",
  "properties": {
    "iso:country":"US",
    "sg:address":"463 Stageline Rd",
    "sg:city":"Hudson",
    "sg:classifiers":[
        {
            "category":"Shopping",
            "subcategory":"Used Merchandise",
            "type":"Retail Goods"
        }
    ],
    "sg:phone":"+1 715 386 7333",
    "sg:postcode":"54016",
    "sg:province":"WI",
    "sg:tags":[
        "antique"
    ],
    "wof:name":"Investments In The Past Inc",
    "wof:placetype":"venue"
},
  "geometry": {"coordinates":[-92.700126,44.958971],"type":"Point"}
}