{
  "type": "Feature",
  "properties": {
    "iso:country":"US",
    "sg:address":"3707 W Loomis Rd",
    "sg:city":"Milwaukee",
    "sg:classifiers":[
        {
            "category":"Retail",
            "subcategory":"Laundry & Dry Cleaning",
            "type":"Services"
        }
    ],
    "sg:phone":"+1 414 282 5095",
    "sg:postcode":"53221",
    "sg:province":"WI",
    "wof:name":"Alterations By Ellie",
    "wof:placetype":"venue"
},
  "geometry": {"coordinates":[-87.959718,42.97121],"type":"Point"}
}