{
  "type": "Feature",
  "properties": {
    "iso:country":"US",
    "sg:address":"7118 State Hwy 182",
    "sg:city":"Park Falls",
    "sg:classifiers":[
        {
            "category":"Recreation",
            "type":"Entertainment"
        },
        {
            "category":"Shopping",
            "subcategory":"Bicycles & Sporting Goods",
            "type":"Retail Goods"
        }
    ],
    "sg:phone":"+1 715 762 2272",
    "sg:postcode":"54552",
    "sg:province":"WI",
    "sg:tags":[
        "equipment",
        "archery",
        "supply"
    ],
    "wof:name":"Dave's Fletching & Archery",
    "wof:placetype":"venue"
},
  "geometry": {"coordinates":[-90.410454,45.940844],"type":"Point"}
}