{
  "type": "Feature",
  "properties": {
    "iso:country":"US",
    "sg:address":"867 Comus Dr",
    "sg:city":"Delavan",
    "sg:classifiers":[
        {
            "category":"Building & Trades",
            "subcategory":"Construction",
            "type":"Services"
        }
    ],
    "sg:phone":"+1 262 728 9530",
    "sg:postcode":"53115",
    "sg:province":"WI",
    "sg:tags":[
        "general",
        "contractor"
    ],
    "wof:name":"Martin Construction LLC",
    "wof:placetype":"venue"
},
  "geometry": {"coordinates":[-88.628454,42.643073],"type":"Point"}
}