{
  "type": "Feature",
  "properties": {
    "iso:country":"US",
    "sg:address":"23 N Pinckney St",
    "sg:city":"Madison",
    "sg:classifiers":[
        {
            "category":"Professional",
            "subcategory":"Lawyer & Legal Services",
            "type":"Services"
        }
    ],
    "sg:phone":"+1 608 258 1335",
    "sg:postcode":"53703",
    "sg:province":"WI",
    "sg:tags":[
        "attorney"
    ],
    "wof:name":"Susan La Cava",
    "wof:placetype":"venue"
},
  "geometry": {"coordinates":[-89.38382300000001,43.076101],"type":"Point"}
}