{
  "type": "Feature",
  "properties": {
    "iso:country":"US",
    "sg:address":"11211 120th Ave",
    "sg:city":"Pleasant Prairie",
    "sg:classifiers":[
        {
            "category":"Shopping",
            "subcategory":"Clothing, Apparel, & Fashions",
            "type":"Retail Goods"
        }
    ],
    "sg:phone":"+1 262 857 2049",
    "sg:postcode":"53142",
    "sg:province":"WI",
    "sg:tags":[
        "wear"
    ],
    "wof:name":"Carters Factory Outlet",
    "wof:placetype":"venue"
},
  "geometry": {"coordinates":[-87.954379,42.523679],"type":"Point"}
}