{
  "type": "Feature",
  "properties": {
    "addr:full":"9684 Beaverland Pkwy Beaver Dam WI 53916",
    "addr:housenumber":"9684",
    "addr:postcode":"53916",
    "addr:street":"Beaverland Pkwy",
    "iso:country":"US",
    "sg:address":"9684 Beaverland Pkwy",
    "sg:city":"Beaver Dam",
    "sg:classifiers":[
        {
            "category":"Building & Trades",
            "subcategory":"Construction",
            "type":"Services"
        }
    ],
    "sg:phone":"+1 920 885 3366",
    "sg:postcode":"53916",
    "sg:province":"WI",
    "sg:tags":[
        "designer",
        "dealer",
        "pool",
        "swimming"
    ],
    "sg:website":"www.neumanpools.com",
    "wof:name":"Neuman Pools Inc",
    "wof:placetype":"venue"
},
  "geometry": {"coordinates":[-88.883112,43.43009],"type":"Point"}
}