{
  "type": "Feature",
  "properties": {
    "iso:country":"US",
    "sg:address":"2737 Gust Rd",
    "sg:city":"Verona",
    "sg:classifiers":[
        {
            "category":"Autos & Motor Vehicles",
            "subcategory":"Auto Supplies",
            "type":"Retail Goods"
        }
    ],
    "sg:phone":"+1 608 845 3800",
    "sg:postcode":"53593",
    "sg:province":"WI",
    "sg:tags":[
        "trailer",
        "hitch"
    ],
    "wof:name":"Double D Svc",
    "wof:placetype":"venue"
},
  "geometry": {"coordinates":[-89.607062,43.009743],"type":"Point"}
}