{
  "type": "Feature",
  "properties": {
    "iso:country":"US",
    "sg:address":"419 Fredonia Ave",
    "sg:city":"Fredonia",
    "sg:classifiers":[
        {
            "category":"Building & Trades",
            "subcategory":"Construction",
            "type":"Services"
        }
    ],
    "sg:phone":"+1 262 692 3512",
    "sg:postcode":"53021",
    "sg:province":"WI",
    "sg:tags":[
        "contractor"
    ],
    "wof:name":"Master Craft Builders Inc",
    "wof:placetype":"venue"
},
  "geometry": {"coordinates":[-87.951622,43.47],"type":"Point"}
}