{
  "type": "Feature",
  "properties": {
    "iso:country":"US",
    "sg:address":"20720 Watertown Rd",
    "sg:city":"Waukesha",
    "sg:classifiers":[
        {
            "category":"Building & Trades",
            "subcategory":"Construction",
            "type":"Services"
        }
    ],
    "sg:phone":"+1 262 798 0777",
    "sg:postcode":"53186",
    "sg:province":"WI",
    "sg:tags":[
        "general",
        "contractor"
    ],
    "wof:name":"Full Circle Svc Inc",
    "wof:placetype":"venue"
},
  "geometry": {"coordinates":[-88.170976,43.038086],"type":"Point"}
}