{
  "type": "Feature",
  "properties": {
    "iso:country":"US",
    "sg:address":"325 3rd St",
    "sg:city":"Reedsburg",
    "sg:classifiers":[
        {
            "category":"Travel",
            "subcategory":"Hotels & Motels",
            "type":"Entertainment"
        }
    ],
    "sg:phone":"+1 608 524 6706",
    "sg:postcode":"53959",
    "sg:province":"WI",
    "sg:tags":[
        "breakfast",
        "accommodation",
        "bed"
    ],
    "wof:name":"Lavina Inn Bed & Breakfast",
    "wof:placetype":"venue"
},
  "geometry": {"coordinates":[-90.006333,43.534607],"type":"Point"}
}