{
  "type": "Feature",
  "properties": {
    "addr:full":"8800 Willow Pointe Pkwy Franklin WI 53132",
    "addr:housenumber":"8800",
    "addr:postcode":"53132",
    "addr:street":"Willow Pointe Pkwy",
    "iso:country":"US",
    "sg:address":"8800 Willow Pointe Pkwy",
    "sg:city":"Franklin",
    "sg:classifiers":[
        {
            "category":"Shopping",
            "subcategory":"Gifts & Souvenirs",
            "type":"Retail Goods"
        }
    ],
    "sg:phone":"+1 414 427 9169",
    "sg:postcode":"53132",
    "sg:province":"WI",
    "wof:name":"Mulberry Bush",
    "wof:placetype":"venue"
},
  "geometry": {"coordinates":[-88.024458,42.903087],"type":"Point"}
}