{
  "type": "Feature",
  "properties": {
    "addr:full":"6700 N Port Washington Rd Milwaukee WI 53217",
    "addr:housenumber":"6700",
    "addr:postcode":"53217",
    "addr:street":"N Port Washington Rd",
    "iso:country":"US",
    "sg:address":"6700 N Port Washington Rd",
    "sg:city":"Milwaukee",
    "sg:classifiers":[
        {
            "category":"Social Services",
            "subcategory":"Job Training",
            "type":"Services"
        }
    ],
    "sg:phone":"+1 414 351 8850",
    "sg:postcode":"53217",
    "sg:province":"WI",
    "sg:tags":[
        "rehabilitation"
    ],
    "wof:name":"Shared Therapeutic Svc",
    "wof:placetype":"venue"
},
  "geometry": {"coordinates":[-87.91316399999999,43.139569],"type":"Point"}
}