{
  "type": "Feature",
  "properties": {
    "addr:full":"133 E Chestnut St Burlington WI 53105",
    "addr:housenumber":"133",
    "addr:postcode":"53105",
    "addr:street":"E Chestnut St",
    "iso:country":"US",
    "sg:address":"133 E Chestnut St",
    "sg:city":"Burlington",
    "sg:classifiers":[
        {
            "category":"Professional",
            "subcategory":"Lawyer & Legal Services",
            "type":"Services"
        }
    ],
    "sg:phone":"+1 262 763 4743",
    "sg:postcode":"53105",
    "sg:province":"WI",
    "sg:tags":[
        "attorney"
    ],
    "wof:name":"Kathleen R Lang Muffitt",
    "wof:placetype":"venue"
},
  "geometry": {"coordinates":[-88.277289,42.679963],"type":"Point"}
}