{
  "type": "Feature",
  "properties": {
    "iso:country":"US",
    "sg:address":"715 E Hancock St",
    "sg:city":"Appleton",
    "sg:classifiers":[
        {
            "category":"Building & Trades",
            "subcategory":"Construction",
            "type":"Services"
        }
    ],
    "sg:phone":"+1 920 733 8659",
    "sg:postcode":"54911",
    "sg:province":"WI",
    "sg:tags":[
        "house"
    ],
    "wof:name":"Dereks Construction & Rmdlg",
    "wof:placetype":"venue"
},
  "geometry": {"coordinates":[-88.395245,44.268732],"type":"Point"}
}