{
  "type": "Feature",
  "properties": {
    "addr:full":"3288 Church St Stevens Point WI 54481",
    "addr:housenumber":"3288",
    "addr:postcode":"54481",
    "addr:street":"Church St",
    "iso:country":"US",
    "sg:address":"3288 Church St",
    "sg:city":"Stevens Point",
    "sg:classifiers":[
        {
            "category":"Autos & Motor Vehicles",
            "subcategory":"Auto Supplies",
            "type":"Retail Goods"
        }
    ],
    "sg:phone":"+1 715 345 7750",
    "sg:postcode":"54481",
    "sg:province":"WI",
    "sg:tags":[
        "automobile",
        "parts"
    ],
    "wof:name":"Advance Auto Parts Inc",
    "wof:placetype":"venue"
},
  "geometry": {"coordinates":[-89.564778,44.501775],"type":"Point"}
}