{
  "type": "Feature",
  "properties": {
    "iso:country":"US",
    "sg:address":"3199 Brooks Rd",
    "sg:city":"Oshkosh",
    "sg:classifiers":[
        {
            "category":"Recreation",
            "type":"Entertainment"
        }
    ],
    "sg:phone":"+1 920 231 0682",
    "sg:postcode":"54904",
    "sg:province":"WI",
    "sg:tags":[
        "range",
        "trap",
        "skeet"
    ],
    "wof:name":"Oshkosh Gun Club Inc",
    "wof:placetype":"venue"
},
  "geometry": {"coordinates":[-88.560285,44.097299],"type":"Point"}
}