{
  "type": "Feature",
  "properties": {
    "addr:full":"1155 Amherst Dr Madison WI 53705",
    "addr:housenumber":"1155",
    "addr:postcode":"53705",
    "addr:street":"Amherst Dr",
    "iso:country":"US",
    "sg:address":"1155 Amherst Dr",
    "sg:city":"Madison",
    "sg:classifiers":[
        {
            "category":"Professional",
            "subcategory":"Accounting & Tax Preparation",
            "type":"Services"
        }
    ],
    "sg:phone":"+1 608 231 9033",
    "sg:postcode":"53705",
    "sg:province":"WI",
    "sg:tags":[
        "accountant"
    ],
    "wof:name":"Badger Tax & Accounting",
    "wof:placetype":"venue"
},
  "geometry": {"coordinates":[-89.44153900000001,43.079839],"type":"Point"}
}