{
  "type": "Feature",
  "properties": {
    "iso:country":"US",
    "sg:address":"35 9th St",
    "sg:city":"Clintonville",
    "sg:classifiers":[
        {
            "category":"Travel",
            "subcategory":"Travel Agent",
            "type":"Entertainment"
        }
    ],
    "sg:phone":"+1 715 823 5903",
    "sg:postcode":"54929",
    "sg:province":"WI",
    "sg:tags":[
        "agency",
        "bureau"
    ],
    "wof:name":"Marathon Travel Shops",
    "wof:placetype":"venue"
},
  "geometry": {"coordinates":[-88.764308,44.62218],"type":"Point"}
}