{
  "type": "Feature",
  "properties": {
    "iso:country":"US",
    "sg:address":"1110 N Front St",
    "sg:city":"Spooner",
    "sg:classifiers":[
        {
            "category":"Home & Garden",
            "subcategory":"Hardware",
            "type":"Retail Goods"
        }
    ],
    "sg:phone":"+1 715 635 8106",
    "sg:postcode":"54801",
    "sg:province":"WI",
    "sg:tags":[
        "saw"
    ],
    "wof:name":"Harmon's Service Ctr",
    "wof:placetype":"venue"
},
  "geometry": {"coordinates":[-91.882443,45.832245],"type":"Point"}
}