{
  "type": "Feature",
  "properties": {
    "addr:full":"3700 Commerce Dr Madison WI 53719",
    "addr:housenumber":"3700",
    "addr:postcode":"53719",
    "addr:street":"Commerce Dr",
    "iso:country":"US",
    "sg:address":"3700 Commerce Dr",
    "sg:city":"Madison",
    "sg:classifiers":[
        {
            "category":"Retail",
            "subcategory":"Auto Rental",
            "type":"Services"
        }
    ],
    "sg:phone":"+1 608 833 0963",
    "sg:postcode":"53719",
    "sg:province":"WI",
    "sg:tags":[
        "truck"
    ],
    "wof:name":"Penske",
    "wof:placetype":"venue"
},
  "geometry": {"coordinates":[-89.52282099999999,43.058627],"type":"Point"}
}