{
  "type": "Feature",
  "properties": {
    "addr:full":"7330 Evergreen Dr Rib Lake WI 54470",
    "addr:housenumber":"7330",
    "addr:postcode":"54470",
    "addr:street":"Evergreen Dr Rib",
    "iso:country":"US",
    "sg:address":"7330 Evergreen Dr",
    "sg:city":"Rib Lake",
    "sg:classifiers":[
        {
            "category":"Farming",
            "subcategory":"Dairy Farm",
            "type":"Manufacturing & Wholesale Goods"
        }
    ],
    "sg:phone":"+1 715 427 5652",
    "sg:postcode":"54470",
    "sg:province":"WI",
    "wof:name":"Tom Enlow",
    "wof:placetype":"venue"
},
  "geometry": {"coordinates":[-90.218242,45.305344],"type":"Point"}
}