{
  "type": "Feature",
  "properties": {
    "iso:country":"US",
    "sg:address":"2531 Lovers Lane Rd",
    "sg:city":"Watertown",
    "sg:classifiers":[
        {
            "category":"Farming",
            "subcategory":"Farm",
            "type":"Manufacturing & Wholesale Goods"
        }
    ],
    "sg:phone":"+1 920 925 3533",
    "sg:postcode":"53098",
    "sg:province":"WI",
    "sg:tags":[
        "feedlot",
        "hog",
        "or",
        "crop",
        "general"
    ],
    "wof:name":"Lovers Lane Farm",
    "wof:placetype":"venue"
},
  "geometry": {"coordinates":[-88.655996,43.284528],"type":"Point"}
}