{
  "type": "Feature",
  "properties": {
    "iso:country":"US",
    "sg:address":"137 S Washington St",
    "sg:city":"Shawano",
    "sg:classifiers":[
        {
            "category":"Building & Trades",
            "subcategory":"Plumbing",
            "type":"Services"
        }
    ],
    "sg:phone":"+1 715 526 3620",
    "sg:postcode":"54166",
    "sg:province":"WI",
    "sg:tags":[
        "sheet",
        "metal",
        "heating",
        "air",
        "refrigeration",
        "conditioning",
        "co"
    ],
    "wof:name":"Montour Heating",
    "wof:placetype":"venue"
},
  "geometry": {"coordinates":[-88.61066,44.781342],"type":"Point"}
}