{
  "type": "Feature",
  "properties": {
    "iso:country":"US",
    "sg:address":"520 N Van Buren St",
    "sg:city":"Stoughton",
    "sg:classifiers":[
        {
            "category":"Organizations",
            "subcategory":"Religious Organization",
            "type":"Services"
        }
    ],
    "sg:phone":"+1 608 873 9284",
    "sg:postcode":"53589",
    "sg:province":"WI",
    "sg:tags":[
        "church"
    ],
    "wof:name":"United Methodist Church",
    "wof:placetype":"venue"
},
  "geometry": {"coordinates":[-89.230806,42.922252],"type":"Point"}
}