{
  "type": "Feature",
  "properties": {
    "iso:country":"US",
    "sg:address":"558 Riverview Dr",
    "sg:city":"Marshall",
    "sg:classifiers":[
        {
            "category":"Farming",
            "subcategory":"Fish & Marine Products",
            "type":"Manufacturing & Wholesale Goods"
        }
    ],
    "sg:phone":"+1 608 655 1611",
    "sg:postcode":"53559",
    "sg:province":"WI",
    "sg:tags":[
        "management"
    ],
    "wof:name":"Great Escape Hnting Prsrve LLC",
    "wof:placetype":"venue"
},
  "geometry": {"coordinates":[-89.065888,43.174529],"type":"Point"}
}