{
  "type": "Feature",
  "properties": {
    "addr:full":"13715 W Capitol Dr Brookfield WI 53005",
    "addr:housenumber":"13715",
    "addr:postcode":"53005",
    "addr:street":"W Capitol Dr",
    "iso:country":"US",
    "sg:address":"13715 W Capitol Dr",
    "sg:city":"Brookfield",
    "sg:phone":"+1 262 783 6649",
    "sg:postcode":"53005",
    "sg:province":"WI",
    "sg:website":"http://www.tanfastictanningsalon.com",
    "wof:name":"Tanfastic Tanning Salon",
    "wof:placetype":"venue"
},
  "geometry": {"coordinates":[-88.082317,43.089467],"type":"Point"}
}