{
  "type": "Feature",
  "properties": {
    "iso:country":"US",
    "sg:address":"106 Main St",
    "sg:city":"Eastman",
    "sg:classifiers":[
        {
            "category":"Personal",
            "subcategory":"Barber",
            "type":"Services"
        }
    ],
    "sg:phone":"+1 608 874 4586",
    "sg:postcode":"53826",
    "sg:province":"WI",
    "wof:name":"Haircutter",
    "wof:placetype":"venue"
},
  "geometry": {"coordinates":[-91.01573500000001,43.168408],"type":"Point"}
}