{
  "type": "Feature",
  "properties": {
    "addr:full":"9178 Co Rd G Beaver Dam WI 53916",
    "addr:housenumber":"9178",
    "addr:postcode":"53916",
    "addr:street":"Co Rd",
    "iso:country":"US",
    "sg:address":"9178 Co Rd G",
    "sg:city":"Beaver Dam",
    "sg:classifiers":[
        {
            "category":"Retail",
            "subcategory":"Auto Rental",
            "type":"Services"
        }
    ],
    "sg:phone":"+1 920 356 0920",
    "sg:postcode":"53916",
    "sg:province":"WI",
    "sg:tags":[
        "renting",
        "truck",
        "leasing"
    ],
    "wof:name":"U-Haul Co",
    "wof:placetype":"venue"
},
  "geometry": {"coordinates":[-88.88378,43.451968],"type":"Point"}
}