{
  "type": "Feature",
  "properties": {
    "addr:full":"342 State Rd 82 Oxford WI 53952",
    "addr:housenumber":"342;82",
    "addr:postcode":"53952",
    "addr:street":"State Rd",
    "iso:country":"US",
    "sg:address":"342 State Rd 82",
    "sg:city":"Oxford",
    "sg:classifiers":[
        {
            "category":"Building & Trades",
            "subcategory":"Construction",
            "type":"Services"
        }
    ],
    "sg:phone":"+1 608 586 6141",
    "sg:postcode":"53952",
    "sg:province":"WI",
    "sg:tags":[
        "contractor"
    ],
    "wof:name":"BWB Contracting",
    "wof:placetype":"venue"
},
  "geometry": {"coordinates":[-89.57330899999999,43.78149],"type":"Point"}
}