{
  "type": "Feature",
  "properties": {
    "addr:full":"1268 Co Hwy W Grafton WI 53024",
    "addr:housenumber":"1268",
    "addr:postcode":"53024",
    "addr:street":"Co Hwy W",
    "iso:country":"US",
    "sg:address":"1268 Co Hwy W",
    "sg:city":"Grafton",
    "sg:classifiers":[
        {
            "category":"Organizations",
            "subcategory":"Membership Organization",
            "type":"Services"
        }
    ],
    "sg:phone":"+1 262 376 4332",
    "sg:postcode":"53024",
    "sg:province":"WI",
    "wof:name":"Childrens Choir Waukesha In",
    "wof:placetype":"venue"
},
  "geometry": {"coordinates":[-87.919269,43.280301],"type":"Point"}
}