{
  "type": "Feature",
  "properties": {
    "iso:country":"US",
    "sg:address":"3778 E Pulaski Ave",
    "sg:city":"Cudahy",
    "sg:classifiers":[
        {
            "category":"Bars & Pubs",
            "type":"Food & Drink"
        }
    ],
    "sg:phone":"+1 414 481 2316",
    "sg:postcode":"53110",
    "sg:province":"WI",
    "sg:tags":[
        "drinking"
    ],
    "wof:name":"Construction Site",
    "wof:placetype":"venue"
},
  "geometry": {"coordinates":[-87.856621,42.951062],"type":"Point"}
}