{
  "type": "Feature",
  "properties": {
    "iso:country":"US",
    "sg:address":"17 Forest Ave",
    "sg:city":"Fond Du Lac",
    "sg:classifiers":[
        {
            "category":"Professional",
            "subcategory":"Employment Agencies",
            "type":"Services"
        }
    ],
    "sg:phone":"+1 920 924 7886",
    "sg:postcode":"54935",
    "sg:province":"WI",
    "sg:tags":[
        "help",
        "supply"
    ],
    "wof:name":"Seek Incorporated",
    "wof:placetype":"venue"
},
  "geometry": {"coordinates":[-88.447974,43.7772],"type":"Point"}
}