{
  "type": "Feature",
  "properties": {
    "iso:country":"US",
    "sg:address":"338 Cherry St",
    "sg:city":"Janesville",
    "sg:classifiers":[
        {
            "category":"Professional",
            "type":"Services"
        }
    ],
    "sg:phone":"+1 608 757 9947",
    "sg:postcode":"53548",
    "sg:province":"WI",
    "sg:tags":[
        "establishment"
    ],
    "wof:name":"Feets Of Healing",
    "wof:placetype":"venue"
},
  "geometry": {"coordinates":[-89.02689700000001,42.675765],"type":"Point"}
}