{
  "type": "Feature",
  "properties": {
    "addr:full":"17 W Willow St Chippewa Falls WI 54729",
    "addr:housenumber":"17",
    "addr:postcode":"54729",
    "addr:street":"W Willow St",
    "iso:country":"US",
    "sg:address":"17 W Willow St",
    "sg:city":"Chippewa Falls",
    "sg:classifiers":[
        {
            "category":"Retail",
            "subcategory":"Self-service Laundry",
            "type":"Services"
        },
        {
            "category":"Retail",
            "subcategory":"Laundry & Dry Cleaning",
            "type":"Services"
        }
    ],
    "sg:phone":"+1 715 723 0582",
    "sg:postcode":"54729",
    "sg:province":"WI",
    "sg:tags":[
        "coin"
    ],
    "wof:name":"Pams Quick Wash & Dry Cleaners",
    "wof:placetype":"venue"
},
  "geometry": {"coordinates":[-91.39601399999999,44.93767],"type":"Point"}
}