{
  "type": "Feature",
  "properties": {
    "iso:country":"US",
    "sg:address":"503 Ohio St",
    "sg:city":"Oshkosh",
    "sg:classifiers":[
        {
            "category":"Wholesale",
            "subcategory":"Toys & Hobbies",
            "type":"Manufacturing & Wholesale Goods"
        }
    ],
    "sg:phone":"+1 920 233 4112",
    "sg:postcode":"54902",
    "sg:province":"WI",
    "wof:name":"L & B Bingo Supply",
    "wof:placetype":"venue"
},
  "geometry": {"coordinates":[-88.552536,44.012394],"type":"Point"}
}