{
  "type": "Feature",
  "properties": {
    "iso:country":"US",
    "sg:address":"5132 Voges Rd",
    "sg:city":"Madison",
    "sg:classifiers":[
        {
            "category":"Retail",
            "subcategory":"Animal Services",
            "type":"Services"
        }
    ],
    "sg:phone":"+1 608 838 0413",
    "sg:postcode":"53718",
    "sg:province":"WI",
    "sg:tags":[
        "shelter"
    ],
    "wof:name":"Humane Society",
    "wof:placetype":"venue"
},
  "geometry": {"coordinates":[-89.292734,43.040727],"type":"Point"}
}