{
  "type": "Feature",
  "properties": {
    "iso:country":"US",
    "sg:address":"8697 Island Rd",
    "sg:city":"Waterloo",
    "sg:classifiers":[
        {
            "category":"Building & Trades",
            "subcategory":"Construction",
            "type":"Services"
        }
    ],
    "sg:phone":"+1 920 478 3074",
    "sg:postcode":"53594",
    "sg:province":"WI",
    "sg:tags":[
        "excavation",
        "excavating",
        "contractor"
    ],
    "wof:name":"Dunneisen Excavating LLC",
    "wof:placetype":"venue"
},
  "geometry": {"coordinates":[-88.955861,43.180105],"type":"Point"}
}