{
  "type": "Feature",
  "properties": {
    "iso:country":"US",
    "sg:address":"1428 N Farwell Ave",
    "sg:city":"Milwaukee",
    "sg:classifiers":[
        {
            "category":"Health Services",
            "subcategory":"Health Practitioner",
            "type":"Services"
        }
    ],
    "sg:phone":"+1 414 425 1433",
    "sg:postcode":"53202",
    "sg:province":"WI",
    "sg:tags":[
        "psychologist"
    ],
    "wof:name":"John V Liccione PHD",
    "wof:placetype":"venue"
},
  "geometry": {"coordinates":[-87.895732,43.049211],"type":"Point"}
}