{
  "type": "Feature",
  "properties": {
    "iso:country":"US",
    "sg:address":"7504 W Appleton Ave",
    "sg:city":"Milwaukee",
    "sg:classifiers":[
        {
            "category":"Building & Trades",
            "subcategory":"Construction",
            "type":"Services"
        }
    ],
    "sg:phone":"+1 414 463 1199",
    "sg:postcode":"53216",
    "sg:province":"WI",
    "sg:tags":[
        "house"
    ],
    "wof:name":"Budget Builders",
    "wof:placetype":"venue"
},
  "geometry": {"coordinates":[-88.005421,43.091615],"type":"Point"}
}