{
  "type": "Feature",
  "properties": {
    "iso:country":"US",
    "sg:address":"34618 Frenchtown Cir",
    "sg:city":"Prairie Du Chien",
    "sg:classifiers":[
        {
            "category":"Professional",
            "subcategory":"Engineering",
            "type":"Services"
        }
    ],
    "sg:phone":"+1 608 326 4820",
    "sg:postcode":"53821",
    "sg:province":"WI",
    "sg:tags":[
        "business"
    ],
    "wof:name":"Dillman Engineering & Eqp",
    "wof:placetype":"venue"
},
  "geometry": {"coordinates":[-91.14664399999999,43.100733],"type":"Point"}
}