{
  "type": "Feature",
  "properties": {
    "iso:country":"US",
    "sg:address":"14718 Co Hwy F",
    "sg:city":"Lakewood",
    "sg:classifiers":[
        {
            "category":"Real Estate",
            "subcategory":"Real Estate Agent",
            "type":"Services"
        }
    ],
    "sg:phone":"+1 715 276 6326",
    "sg:postcode":"54138",
    "sg:province":"WI",
    "wof:name":"Real Property Investments LLC",
    "wof:placetype":"venue"
},
  "geometry": {"coordinates":[-88.49684000000001,45.301153],"type":"Point"}
}