{
  "type": "Feature",
  "properties": {
    "iso:country":"US",
    "sg:address":"1497 Airport Rd",
    "sg:city":"Platteville",
    "sg:classifiers":[
        {
            "category":"Farming",
            "subcategory":"Farm",
            "type":"Manufacturing & Wholesale Goods"
        }
    ],
    "sg:phone":"+1 608 348 9204",
    "sg:postcode":"53818",
    "sg:province":"WI",
    "sg:tags":[
        "crop",
        "general"
    ],
    "wof:name":"G & J Farms",
    "wof:placetype":"venue"
},
  "geometry": {"coordinates":[-90.491289,42.674802],"type":"Point"}
}