{
  "type": "Feature",
  "properties": {
    "iso:country":"US",
    "sg:address":"55 1st Ave",
    "sg:city":"Benton",
    "sg:classifiers":[
        {
            "category":"Building & Trades",
            "subcategory":"Construction",
            "type":"Services"
        }
    ],
    "sg:phone":"+1 608 759 6500",
    "sg:postcode":"53803",
    "sg:province":"WI",
    "sg:tags":[
        "concrete",
        "contractor"
    ],
    "wof:name":"Hendrickson Restoration",
    "wof:placetype":"venue"
},
  "geometry": {"coordinates":[-90.38325500000001,42.570761],"type":"Point"}
}