{
  "type": "Feature",
  "properties": {
    "iso:country":"US",
    "sg:address":"5810 W Oklahoma Ave",
    "sg:city":"Milwaukee",
    "sg:classifiers":[
        {
            "category":"Shopping",
            "subcategory":"Optical Goods",
            "type":"Retail Goods"
        }
    ],
    "sg:phone":"+1 414 541 1190",
    "sg:postcode":"53219",
    "sg:province":"WI",
    "sg:tags":[
        "supply"
    ],
    "wof:name":"Georgies House of Vision",
    "wof:placetype":"venue"
},
  "geometry": {"coordinates":[-87.98747299999999,42.988489],"type":"Point"}
}