{
  "type": "Feature",
  "properties": {
    "addr:full":"1347 Ceape Ave Oshkosh WI 54901",
    "addr:housenumber":"1347",
    "addr:postcode":"54901",
    "addr:street":"Ceape Ave",
    "iso:country":"US",
    "sg:address":"1347 Ceape Ave",
    "sg:city":"Oshkosh",
    "sg:classifiers":[
        {
            "category":"Real Estate",
            "subcategory":"Architect",
            "type":"Services"
        }
    ],
    "sg:phone":"+1 920 233 6972",
    "sg:postcode":"54901",
    "sg:province":"WI",
    "sg:tags":[
        "architectural"
    ],
    "wof:name":"Clarke Associate Architects",
    "wof:placetype":"venue"
},
  "geometry": {"coordinates":[-88.518946,44.011738],"type":"Point"}
}