{
  "type": "Feature",
  "properties": {
    "iso:country":"US",
    "sg:address":"11062 Beach Rd",
    "sg:city":"Sister Bay",
    "sg:classifiers":[
        {
            "category":"Travel",
            "subcategory":"Hotels & Motels",
            "type":"Entertainment"
        }
    ],
    "sg:phone":"+1 920 854 2447",
    "sg:postcode":"54234",
    "sg:province":"WI",
    "sg:tags":[
        "cottage",
        "cabin"
    ],
    "sg:website":"www.scandiacottages.com",
    "wof:name":"Scandia Cottages LLC",
    "wof:placetype":"venue"
},
  "geometry": {"coordinates":[-87.118136,45.209085],"type":"Point"}
}