{
  "type": "Feature",
  "properties": {
    "iso:country":"US",
    "sg:address":"394 Stanley Ct",
    "sg:city":"Neenah",
    "sg:classifiers":[
        {
            "category":"Shopping",
            "subcategory":"Beauty & Cosmetics",
            "type":"Retail Goods"
        }
    ],
    "sg:phone":"+1 920 720 3448",
    "sg:postcode":"54956",
    "sg:province":"WI",
    "sg:tags":[
        "merchandise"
    ],
    "wof:name":"Natures Way LLC",
    "wof:placetype":"venue"
},
  "geometry": {"coordinates":[-88.470863,44.160306],"type":"Point"}
}