{
  "type": "Feature",
  "properties": {
    "iso:country":"US",
    "sg:address":"515 S Washburn St",
    "sg:city":"Oshkosh",
    "sg:classifiers":[
        {
            "category":"Social Services",
            "subcategory":"Job Training",
            "type":"Services"
        }
    ],
    "sg:phone":"+1 920 232 1400",
    "sg:postcode":"54904",
    "sg:province":"WI",
    "sg:tags":[
        "consultant",
        "occupational"
    ],
    "wof:name":"Career Development Group",
    "wof:placetype":"venue"
},
  "geometry": {"coordinates":[-88.58476,44.011611],"type":"Point"}
}