{
  "type": "Feature",
  "properties": {
    "iso:country":"US",
    "sg:address":"522 Water St",
    "sg:city":"Eau Claire",
    "sg:classifiers":[
        {
            "category":"Retail",
            "subcategory":"Auto Repair",
            "type":"Services"
        }
    ],
    "sg:phone":"+1 715 839 0890",
    "sg:postcode":"54703",
    "sg:province":"WI",
    "sg:tags":[
        "engine",
        "rebuilding"
    ],
    "wof:name":"Baxter Engines Inc",
    "wof:placetype":"venue"
},
  "geometry": {"coordinates":[-91.511383,44.802239],"type":"Point"}
}