{
  "type": "Feature",
  "properties": {
    "iso:country":"US",
    "sg:address":"7100 Dunkelow Rd",
    "sg:city":"Franksville",
    "sg:classifiers":[
        {
            "category":"Building & Trades",
            "subcategory":"Landscaping Services",
            "type":"Services"
        }
    ],
    "sg:phone":"+1 262 884 6591",
    "sg:postcode":"53126",
    "sg:province":"WI",
    "wof:name":"Wiez Lawn Care",
    "wof:placetype":"venue"
},
  "geometry": {"coordinates":[-87.867046,42.762619],"type":"Point"}
}