{
  "type": "Feature",
  "properties": {
    "iso:country":"US",
    "sg:address":"20 S Main St",
    "sg:city":"Janesville",
    "sg:classifiers":[
        {
            "category":"Health Services",
            "subcategory":"Health Practitioner",
            "type":"Services"
        },
        {
            "category":"Social Services",
            "type":"Services"
        }
    ],
    "sg:phone":"+1 608 756 0716",
    "sg:postcode":"53545",
    "sg:province":"WI",
    "wof:name":"Life Visions",
    "wof:placetype":"venue"
},
  "geometry": {"coordinates":[-89.021747,42.682264],"type":"Point"}
}