{
  "type": "Feature",
  "properties": {
    "iso:country":"US",
    "sg:address":"5 Walter St",
    "sg:city":"Madison",
    "sg:classifiers":[
        {
            "category":"Professional",
            "type":"Services"
        }
    ],
    "sg:phone":"+1 608 241 7735",
    "sg:postcode":"53714",
    "sg:province":"WI",
    "wof:name":"Frontier Systems Svc",
    "wof:placetype":"venue"
},
  "geometry": {"coordinates":[-89.326585,43.095809],"type":"Point"}
}