{
  "type": "Feature",
  "properties": {
    "addr:full":"1909 N 118th St Milwaukee WI 53226",
    "addr:housenumber":"1909",
    "addr:postcode":"53226",
    "addr:street":"N 118Th St",
    "iso:country":"US",
    "sg:address":"1909 N 118th St",
    "sg:city":"Milwaukee",
    "sg:classifiers":[
        {
            "category":"Manufacturing",
            "subcategory":"Printing",
            "type":"Manufacturing & Wholesale Goods"
        },
        {
            "category":"Travel",
            "subcategory":"Travel Agent",
            "type":"Entertainment"
        },
        {
            "category":"Wholesale",
            "subcategory":"Books, Periodicals, & Newspapers",
            "type":"Manufacturing & Wholesale Goods"
        }
    ],
    "sg:phone":"+1 414 258 5051",
    "sg:postcode":"53226",
    "sg:province":"WI",
    "sg:tags":[
        "magazines-distributors",
        "publishers-periodical",
        "magazines-subscription"
    ],
    "wof:name":"Sherry Magazine Service",
    "wof:placetype":"venue"
},
  "geometry": {"coordinates":[-88.060044,43.055016],"type":"Point"}
}