{
  "type": "Feature",
  "properties": {
    "iso:country":"US",
    "sg:address":"120 South St",
    "sg:city":"Kingston",
    "sg:classifiers":[
        {
            "category":"Banks & Credit Unions",
            "subcategory":"Bank",
            "type":"Services"
        }
    ],
    "sg:phone":"+1 920 394 3544",
    "sg:postcode":"53939",
    "sg:province":"WI",
    "wof:name":"National Exchange Bank & Trust",
    "wof:placetype":"venue"
},
  "geometry": {"coordinates":[-89.127782,43.69384],"type":"Point"}
}