{
  "type": "Feature",
  "properties": {
    "iso:country":"US",
    "sg:address":"223 Embarrass St",
    "sg:city":"Hortonville",
    "sg:classifiers":[
        {
            "category":"Professional",
            "subcategory":"Detective & Security Services",
            "type":"Services"
        }
    ],
    "sg:phone":"+1 920 735 5885",
    "sg:postcode":"54944",
    "sg:province":"WI",
    "sg:tags":[
        "system"
    ],
    "wof:name":"ADT Security Services Inc",
    "wof:placetype":"venue"
},
  "geometry": {"coordinates":[-88.63973900000001,44.336295],"type":"Point"}
}