{
  "type": "Feature",
  "properties": {
    "iso:country":"US",
    "sg:address":"311 Main St E",
    "sg:city":"Menomonie",
    "sg:classifiers":[
        {
            "category":"Restaurant",
            "type":"Food & Drink"
        }
    ],
    "sg:phone":"+1 715 235 1779",
    "sg:postcode":"54751",
    "sg:province":"WI",
    "sg:tags":[
        "eating"
    ],
    "wof:name":"Nethouse Cafe",
    "wof:placetype":"venue"
},
  "geometry": {"coordinates":[-91.926124,44.876589],"type":"Point"}
}