{
  "type": "Feature",
  "properties": {
    "addr:full":"408 S Division St Waupaca WI 54981",
    "addr:housenumber":"408",
    "addr:postcode":"54981",
    "addr:street":"S Division St",
    "iso:country":"US",
    "sg:address":"408 S Division St",
    "sg:city":"Waupaca",
    "sg:classifiers":[
        {
            "category":"Insurance",
            "subcategory":"Insurance Agent",
            "type":"Services"
        }
    ],
    "sg:phone":"+1 715 258 8493",
    "sg:postcode":"54981",
    "sg:province":"WI",
    "wof:name":"Farmers Insurance Group",
    "wof:placetype":"venue"
},
  "geometry": {"coordinates":[-89.082429,44.354658],"type":"Point"}
}