{
  "type": "Feature",
  "properties": {
    "iso:country":"US",
    "sg:address":"325 Chestnut St",
    "sg:city":"West Bend",
    "sg:classifiers":[
        {
            "category":"Shopping",
            "type":"Retail Goods"
        }
    ],
    "sg:phone":"+1 262 673 3793",
    "sg:postcode":"53095",
    "sg:province":"WI",
    "sg:tags":[
        "merchandise",
        "business"
    ],
    "wof:name":"County Wide Extinguisher",
    "wof:placetype":"venue"
},
  "geometry": {"coordinates":[-88.180798,43.419403],"type":"Point"}
}