{
  "type": "Feature",
  "properties": {
    "addr:full":"1594 State Road 60 Jackson WI 53037",
    "addr:housenumber":"1594",
    "addr:postcode":"53037",
    "addr:street":"State Road 60",
    "iso:country":"US",
    "sg:address":"1594 State Road 60",
    "sg:city":"Jackson",
    "sg:classifiers":[
        {
            "category":"Farming",
            "subcategory":"Dairy Farm",
            "type":"Manufacturing & Wholesale Goods"
        },
        {
            "category":"Farming",
            "subcategory":"Farm",
            "type":"Manufacturing & Wholesale Goods"
        }
    ],
    "sg:phone":"+1 262 677 3812",
    "sg:postcode":"53037",
    "sg:province":"WI",
    "wof:name":"Gary Goll",
    "wof:placetype":"venue"
},
  "geometry": {"coordinates":[-88.11241800000001,43.323162],"type":"Point"}
}