{
  "type": "Feature",
  "properties": {
    "addr:full":"615 N Westhill Blvd Appleton WI 54914",
    "addr:housenumber":"615",
    "addr:postcode":"54914",
    "addr:street":"N Westhill Blvd",
    "iso:country":"US",
    "sg:address":"615 N Westhill Blvd",
    "sg:city":"Appleton",
    "sg:classifiers":[
        {
            "category":"Retail",
            "subcategory":"Repair Shop",
            "type":"Services"
        }
    ],
    "sg:phone":"+1 920 733 1850",
    "sg:postcode":"54914",
    "sg:province":"WI",
    "sg:tags":[
        "electrical"
    ],
    "wof:name":"Oreck",
    "wof:placetype":"venue"
},
  "geometry": {"coordinates":[-88.46114799999999,44.266175],"type":"Point"}
}