{
  "type": "Feature",
  "properties": {
    "iso:country":"US",
    "sg:address":"301 N Lake Ave",
    "sg:city":"Crandon",
    "sg:classifiers":[
        {
            "category":"Retail",
            "subcategory":"Auto Repair",
            "type":"Services"
        }
    ],
    "sg:phone":"+1 715 478 8555",
    "sg:postcode":"54520",
    "sg:province":"WI",
    "sg:tags":[
        "body"
    ],
    "wof:name":"Scooters Custom Auto",
    "wof:placetype":"venue"
},
  "geometry": {"coordinates":[-88.90343,45.571594],"type":"Point"}
}