{
  "type": "Feature",
  "properties": {
    "iso:country":"US",
    "sg:address":"18783 Hartwill St",
    "sg:city":"Whitehall",
    "sg:classifiers":[
        {
            "category":"Recreation",
            "type":"Entertainment"
        }
    ],
    "sg:phone":"+1 715 797 3678",
    "sg:postcode":"54773",
    "sg:province":"WI",
    "sg:tags":[
        "martial",
        "arts",
        "instruction"
    ],
    "wof:name":"Ju's Taekwondo Karate Academy",
    "wof:placetype":"venue"
},
  "geometry": {"coordinates":[-91.323027,44.368161],"type":"Point"}
}