{
  "type": "Feature",
  "properties": {
    "iso:country":"US",
    "sg:address":"8427 W Burleigh St",
    "sg:city":"Milwaukee",
    "sg:classifiers":[
        {
            "category":"Retail",
            "subcategory":"Repair Shop",
            "type":"Services"
        }
    ],
    "sg:phone":"+1 414 871 2662",
    "sg:postcode":"53222",
    "sg:province":"WI",
    "sg:tags":[
        "locksmith"
    ],
    "wof:name":"Arogans Lock & Key",
    "wof:placetype":"venue"
},
  "geometry": {"coordinates":[-88.018476,43.075115],"type":"Point"}
}