{
  "type": "Feature",
  "properties": {
    "iso:country":"US",
    "sg:address":"10225 W Capitol Dr",
    "sg:city":"Milwaukee",
    "sg:classifiers":[
        {
            "category":"Health Services",
            "subcategory":"Doctor",
            "type":"Services"
        },
        {
            "category":"Health Services",
            "subcategory":"Dentist",
            "type":"Services"
        }
    ],
    "sg:phone":"+1 414 463 5800",
    "sg:postcode":"53222",
    "sg:province":"WI",
    "sg:tags":[
        "dentists-oral",
        "physician",
        "maxillofacial",
        "surgeons",
        "surgery",
        "oral"
    ],
    "wof:name":"Wussow, J R, Dds",
    "wof:placetype":"venue"
},
  "geometry": {"coordinates":[-88.04061799999999,43.089619],"type":"Point"}
}