{
  "type": "Feature",
  "properties": {
    "addr:full":"826 Walter St Spooner WI 54801",
    "addr:housenumber":"826",
    "addr:postcode":"54801",
    "addr:street":"Walter St",
    "iso:country":"US",
    "sg:address":"826 Walter St",
    "sg:city":"Spooner",
    "sg:classifiers":[
        {
            "category":"Restaurant",
            "type":"Food & Drink"
        }
    ],
    "sg:phone":"+1 715 468 7427",
    "sg:postcode":"54801",
    "sg:province":"WI",
    "sg:tags":[
        "eating"
    ],
    "wof:name":"Micheles",
    "wof:placetype":"venue"
},
  "geometry": {"coordinates":[-91.889774,45.831474],"type":"Point"}
}