{
  "type": "Feature",
  "properties": {
    "addr:full":"7850 Doyle Rd Theresa WI 53091",
    "addr:housenumber":"7850",
    "addr:postcode":"53091",
    "addr:street":"Doyle Rd",
    "iso:country":"US",
    "sg:address":"7850 Doyle Rd",
    "sg:city":"Theresa",
    "sg:classifiers":[
        {
            "category":"Farming",
            "subcategory":"Dairy Farm",
            "type":"Manufacturing & Wholesale Goods"
        }
    ],
    "sg:phone":"+1 920 488 3665",
    "sg:postcode":"53091",
    "sg:province":"WI",
    "wof:name":"Schnitzler John",
    "wof:placetype":"venue"
},
  "geometry": {"coordinates":[-88.43022000000001,43.473946],"type":"Point"}
}