{
  "type": "Feature",
  "properties": {
    "iso:country":"US",
    "sg:address":"835 S Van Buren St",
    "sg:city":"Green Bay",
    "sg:classifiers":[
        {
            "category":"Health Services",
            "subcategory":"Doctor",
            "type":"Services"
        }
    ],
    "sg:phone":"+1 920 433 8360",
    "sg:postcode":"54301",
    "sg:province":"WI",
    "sg:tags":[
        "physician",
        "surgeon"
    ],
    "wof:name":"Neonatal Consultants",
    "wof:placetype":"venue"
},
  "geometry": {"coordinates":[-88.013127,44.501061],"type":"Point"}
}