{
  "type": "Feature",
  "properties": {
    "addr:full":"2425 S Memorial Dr Racine WI 53403",
    "addr:housenumber":"2425",
    "addr:postcode":"53403",
    "addr:street":"S Memorial Dr",
    "iso:country":"US",
    "sg:address":"2425 S Memorial Dr",
    "sg:city":"Racine",
    "sg:classifiers":[
        {
            "category":"Building & Trades",
            "subcategory":"Construction",
            "type":"Services"
        }
    ],
    "sg:phone":"+1 262 637 5681",
    "sg:postcode":"53403",
    "sg:province":"WI",
    "sg:tags":[
        "general",
        "contractor"
    ],
    "sg:website":"www.unitedconstruction.net",
    "wof:name":"United Construction Corp",
    "wof:placetype":"venue"
},
  "geometry": {"coordinates":[-87.798878,42.699614],"type":"Point"}
}