{
  "type": "Feature",
  "properties": {
    "iso:country":"US",
    "sg:address":"5878 Persimmon Dr",
    "sg:city":"Fitchburg",
    "sg:classifiers":[
        {
            "category":"Building & Trades",
            "subcategory":"Construction",
            "type":"Services"
        }
    ],
    "sg:phone":"+1 608 277 9424",
    "sg:postcode":"53711",
    "sg:province":"WI",
    "sg:tags":[
        "home",
        "builder",
        "general",
        "contractor"
    ],
    "wof:name":"Thomas Zimmer Builders LLC",
    "wof:placetype":"venue"
},
  "geometry": {"coordinates":[-89.44788,43.006686],"type":"Point"}
}