{
  "type": "Feature",
  "properties": {
    "iso:country":"US",
    "sg:address":"2520 Main St",
    "sg:city":"Green Bay",
    "sg:classifiers":[
        {
            "category":"Building & Trades",
            "subcategory":"Equipment Rental",
            "type":"Services"
        }
    ],
    "sg:phone":"+1 920 406 5960",
    "sg:postcode":"54311",
    "sg:province":"WI",
    "sg:tags":[
        "yard"
    ],
    "wof:name":"Main Rental",
    "wof:placetype":"venue"
},
  "geometry": {"coordinates":[-87.963041,44.469891],"type":"Point"}
}