{
  "type": "Feature",
  "properties": {
    "iso:country":"US",
    "sg:address":"1231 W Mitchell St",
    "sg:city":"Milwaukee",
    "sg:classifiers":[
        {
            "category":"Education",
            "subcategory":"College",
            "type":"Public Place"
        }
    ],
    "sg:phone":"+1 414 643 8461",
    "sg:postcode":"53204",
    "sg:province":"WI",
    "sg:tags":[
        "medical"
    ],
    "wof:name":"Medical College of Wisconsin",
    "wof:placetype":"venue"
},
  "geometry": {"coordinates":[-87.92704000000001,43.012211],"type":"Point"}
}