{
  "type": "Feature",
  "properties": {
    "addr:full":"204 Mayfair St Antigo WI 54409",
    "addr:housenumber":"204",
    "addr:postcode":"54409",
    "addr:street":"Mayfair St",
    "iso:country":"US",
    "sg:address":"204 Mayfair St",
    "sg:city":"Antigo",
    "sg:classifiers":[
        {
            "category":"Retail",
            "subcategory":"Laundry & Dry Cleaning",
            "type":"Services"
        }
    ],
    "sg:phone":"+1 715 623 4132",
    "sg:postcode":"54409",
    "sg:province":"WI",
    "wof:name":"Home Alterations",
    "wof:placetype":"venue"
},
  "geometry": {"coordinates":[-89.17066,45.134726],"type":"Point"}
}