{
  "type": "Feature",
  "properties": {
    "addr:full":"3817 Nicholson Rd Franksville WI 53126",
    "addr:housenumber":"3817",
    "addr:postcode":"53126",
    "addr:street":"Nicholson Rd",
    "iso:country":"US",
    "sg:address":"3817 Nicholson Rd",
    "sg:city":"Franksville",
    "sg:classifiers":[
        {
            "category":"Manufacturing",
            "subcategory":"Tools & Machinery",
            "type":"Manufacturing & Wholesale Goods"
        }
    ],
    "sg:phone":"+1 262 835 4411",
    "sg:postcode":"53126",
    "sg:province":"WI",
    "sg:tags":[
        "food",
        "packaging",
        "labeling",
        "mfg"
    ],
    "wof:name":"Toledo Scales & Systems",
    "wof:placetype":"venue"
},
  "geometry": {"coordinates":[-87.89505699999999,42.768052],"type":"Point"}
}