{
  "type": "Feature",
  "properties": {
    "iso:country":"US",
    "sg:address":"403 Douglas Ln",
    "sg:city":"Cedarburg",
    "sg:classifiers":[
        {
            "category":"Real Estate",
            "subcategory":"Real Estate Agent",
            "type":"Services"
        }
    ],
    "sg:phone":"+1 262 377 8414",
    "sg:postcode":"53012",
    "sg:province":"WI",
    "wof:name":"North Star Realty",
    "wof:placetype":"venue"
},
  "geometry": {"coordinates":[-88.010457,43.287232],"type":"Point"}
}