{
  "type": "Feature",
  "properties": {
    "iso:country":"US",
    "sg:address":"10377 Hinker Rd",
    "sg:city":"Willard",
    "sg:phone":"+1 715 267 7437",
    "sg:postcode":"54493",
    "sg:province":"WI",
    "sg:tags":[
        "farm"
    ],
    "wof:name":"Albert Morrison",
    "wof:placetype":"venue"
},
  "geometry": {"coordinates":[-90.836634,44.752519],"type":"Point"}
}