{
  "type": "Feature",
  "properties": {
    "iso:country":"US",
    "sg:address":"814 N 26th St",
    "sg:city":"Milwaukee",
    "sg:classifiers":[
        {
            "category":"Building & Trades",
            "subcategory":"Construction",
            "type":"Services"
        }
    ],
    "sg:phone":"+1 414 933 7061",
    "sg:postcode":"53233",
    "sg:province":"WI",
    "sg:tags":[
        "dry wall",
        "contractor"
    ],
    "wof:name":"Speedy Drywall",
    "wof:placetype":"venue"
},
  "geometry": {"coordinates":[-87.946219,43.041435],"type":"Point"}
}