{
  "type": "Feature",
  "properties": {
    "addr:full":"6729 W Bottsford Ave Greenfield WI 53220",
    "addr:housenumber":"6729",
    "addr:postcode":"53220",
    "addr:street":"W Bottsford Ave",
    "iso:country":"US",
    "sg:address":"6729 W Bottsford Ave",
    "sg:city":"Greenfield",
    "sg:classifiers":[
        {
            "category":"Shopping",
            "subcategory":"Computers & Home Electronics",
            "type":"Retail Goods"
        }
    ],
    "sg:phone":"+1 414 546 2222",
    "sg:postcode":"53220",
    "sg:province":"WI",
    "sg:tags":[
        "parts",
        "supply"
    ],
    "wof:name":"Micro Trend Inc",
    "wof:placetype":"venue"
},
  "geometry": {"coordinates":[-87.99787000000001,42.965168],"type":"Point"}
}