{
  "type": "Feature",
  "properties": {
    "iso:country":"US",
    "sg:address":"1420 E Main St",
    "sg:city":"Little Chute",
    "sg:classifiers":[
        {
            "category":"Bars & Pubs",
            "type":"Food & Drink"
        }
    ],
    "sg:phone":"+1 920 788 9310",
    "sg:postcode":"54140",
    "sg:province":"WI",
    "wof:name":"Mary's Pop In",
    "wof:placetype":"venue"
},
  "geometry": {"coordinates":[-88.295754,44.284327],"type":"Point"}
}