{
  "type": "Feature",
  "properties": {
    "iso:country":"US",
    "sg:address":"708 Giese St",
    "sg:city":"Hortonville",
    "sg:classifiers":[
        {
            "category":"Autos & Motor Vehicles",
            "subcategory":"Auto Supplies",
            "type":"Retail Goods"
        }
    ],
    "sg:phone":"+1 920 779 9336",
    "sg:postcode":"54944",
    "sg:province":"WI",
    "sg:tags":[
        "alternator",
        "generator"
    ],
    "wof:name":"Remote Start Plus",
    "wof:placetype":"venue"
},
  "geometry": {"coordinates":[-88.637956,44.328563],"type":"Point"}
}