{
  "type": "Feature",
  "properties": {
    "iso:country":"US",
    "sg:address":"100 Belknap St",
    "sg:city":"Superior",
    "sg:classifiers":[
        {
            "category":"Restaurant",
            "type":"Food & Drink"
        }
    ],
    "sg:menulink":"http://www.allmenus.com/wi/superior/145774-subway/menu/",
    "sg:phone":"+1 715 394 3323",
    "sg:postcode":"54880",
    "sg:province":"WI",
    "sg:tags":[
        "american",
        "sandwich"
    ],
    "wof:name":"Subway",
    "wof:placetype":"venue"
},
  "geometry": {"coordinates":[-92.079925,46.720558],"type":"Point"}
}