{
  "type": "Feature",
  "properties": {
    "iso:country":"US",
    "sg:address":"8876 Co Hwy X",
    "sg:city":"Darien",
    "sg:classifiers":[
        {
            "category":"Wholesale",
            "subcategory":"Meat",
            "type":"Manufacturing & Wholesale Goods"
        }
    ],
    "sg:phone":"+1 262 724 5781",
    "sg:postcode":"53114",
    "sg:province":"WI",
    "wof:name":"Ero Meat Company",
    "wof:placetype":"venue"
},
  "geometry": {"coordinates":[-88.742722,42.584528],"type":"Point"}
}