{
  "type": "Feature",
  "properties": {
    "iso:country":"US",
    "sg:address":"1677 Lilac Ln",
    "sg:city":"Green Bay",
    "sg:classifiers":[
        {
            "category":"Wholesale",
            "subcategory":"Vending Machines",
            "type":"Manufacturing & Wholesale Goods"
        }
    ],
    "sg:phone":"+1 920 469 3321",
    "sg:postcode":"54302",
    "sg:province":"WI",
    "sg:tags":[
        "snack",
        "soda"
    ],
    "wof:name":"Fox River Vending",
    "wof:placetype":"venue"
},
  "geometry": {"coordinates":[-87.988394,44.489451],"type":"Point"}
}