{
  "type": "Feature",
  "properties": {
    "iso:country":"US",
    "sg:address":"131 E Wisconsin Ave",
    "sg:city":"Pewaukee",
    "sg:classifiers":[
        {
            "category":"Health Services",
            "subcategory":"Health Practitioner",
            "type":"Services"
        }
    ],
    "sg:phone":"+1 262 691 4727",
    "sg:postcode":"53072",
    "sg:province":"WI",
    "sg:tags":[
        "acupuncture"
    ],
    "wof:name":"Clinic Of Integrated Medicine",
    "wof:placetype":"venue"
},
  "geometry": {"coordinates":[-88.261978,43.081963],"type":"Point"}
}