{
  "type": "Feature",
  "properties": {
    "iso:country":"US",
    "sg:address":"850 Desoto Cir",
    "sg:city":"Oneida",
    "sg:classifiers":[
        {
            "category":"Real Estate",
            "subcategory":"Real Estate Operator",
            "type":"Services"
        }
    ],
    "sg:phone":"+1 920 405 0644",
    "sg:postcode":"54155",
    "sg:province":"WI",
    "sg:tags":[
        "condominium"
    ],
    "wof:name":"Pole Point Development",
    "wof:placetype":"venue"
},
  "geometry": {"coordinates":[-88.14531599999999,44.537252],"type":"Point"}
}