{
  "type": "Feature",
  "properties": {
    "iso:country":"US",
    "sg:address":"315 Badger St",
    "sg:city":"Taylor",
    "sg:classifiers":[
        {
            "category":"Manufacturing",
            "subcategory":"Apparel",
            "type":"Manufacturing & Wholesale Goods"
        }
    ],
    "sg:phone":"+1 715 662 2222",
    "sg:postcode":"54601",
    "sg:province":"WI",
    "sg:tags":[
        "athletic",
        "mfg",
        "uniform"
    ],
    "wof:name":"Ripon Awardjackets Inc",
    "wof:placetype":"venue"
},
  "geometry": {"coordinates":[-91.249093,43.816243],"type":"Point"}
}