{
  "type": "Feature",
  "properties": {
    "iso:country":"US",
    "sg:address":"8505 University Green",
    "sg:city":"Middleton",
    "sg:classifiers":[
        {
            "category":"Wholesale",
            "subcategory":"Machinery & Supplies",
            "type":"Manufacturing & Wholesale Goods"
        }
    ],
    "sg:phone":"+1 608 836 3457",
    "sg:postcode":"53562",
    "sg:province":"WI",
    "sg:tags":[
        "janitor"
    ],
    "wof:name":"Badgerland Chemical & Supply",
    "wof:placetype":"venue"
},
  "geometry": {"coordinates":[-89.534739,43.097357],"type":"Point"}
}