{
  "type": "Feature",
  "properties": {
    "iso:country":"US",
    "sg:address":"104 E Madison Ave",
    "sg:city":"Grantsburg",
    "sg:classifiers":[
        {
            "category":"Banks & Credit Unions",
            "subcategory":"Investment Brokerage",
            "type":"Services"
        }
    ],
    "sg:phone":"+1 715 463 3606",
    "sg:postcode":"54840",
    "sg:province":"WI",
    "sg:tags":[
        "security"
    ],
    "wof:name":"Edward Jones Co",
    "wof:placetype":"venue"
},
  "geometry": {"coordinates":[-92.68200899999999,45.778998],"type":"Point"}
}