{
  "type": "Feature",
  "properties": {
    "iso:country":"US",
    "sg:address":"615 N Parker Dr",
    "sg:city":"Janesville",
    "sg:classifiers":[
        {
            "category":"Manufacturing",
            "subcategory":"Textiles",
            "type":"Manufacturing & Wholesale Goods"
        }
    ],
    "sg:phone":"+1 608 755 1385",
    "sg:postcode":"53545",
    "sg:province":"WI",
    "sg:website":"www.alphaprotech.com",
    "wof:name":"Alpha Protech Inc",
    "wof:placetype":"venue"
},
  "geometry": {"coordinates":[-89.027729,42.69016],"type":"Point"}
}