{
  "type": "Feature",
  "properties": {
    "addr:full":"2334 Lakeshore Rd Kewaunee WI 54216",
    "addr:housenumber":"2334",
    "addr:postcode":"54216",
    "addr:street":"Lakeshore Rd",
    "iso:country":"US",
    "sg:address":"2334 Lakeshore Rd",
    "sg:city":"Kewaunee",
    "sg:classifiers":[
        {
            "category":"Farming",
            "subcategory":"Dairy Farm",
            "type":"Manufacturing & Wholesale Goods"
        }
    ],
    "sg:phone":"+1 920 388 2994",
    "sg:postcode":"54216",
    "sg:province":"WI",
    "wof:name":"Birchway Farm",
    "wof:placetype":"venue"
},
  "geometry": {"coordinates":[-87.514723,44.413114],"type":"Point"}
}