{
  "type": "Feature",
  "properties": {
    "iso:country":"US",
    "sg:address":"2733 W Carmen Ave",
    "sg:city":"Milwaukee",
    "sg:classifiers":[
        {
            "category":"Manufacturing",
            "subcategory":"Rubber & Plastics",
            "type":"Manufacturing & Wholesale Goods"
        }
    ],
    "sg:phone":"+1 414 464 6073",
    "sg:postcode":"53209",
    "sg:province":"WI",
    "sg:tags":[
        "product",
        "mfg"
    ],
    "wof:name":"B2 Technologies",
    "wof:placetype":"venue"
},
  "geometry": {"coordinates":[-87.948353,43.122691],"type":"Point"}
}