{
  "type": "Feature",
  "properties": {
    "addr:full":"6796 Pine Mead Ave Shawano WI 54166",
    "addr:housenumber":"6796",
    "addr:postcode":"54166",
    "addr:street":"Pine Mead Ave",
    "iso:country":"US",
    "sg:address":"6796 Pine Mead Ave",
    "sg:city":"Shawano",
    "sg:classifiers":[
        {
            "category":"Personal",
            "subcategory":"Beauty Salon",
            "type":"Services"
        }
    ],
    "sg:phone":"+1 715 524 2254",
    "sg:postcode":"54166",
    "sg:province":"WI",
    "sg:tags":[
        "shop"
    ],
    "wof:name":"Hair Oasis",
    "wof:placetype":"venue"
},
  "geometry": {"coordinates":[-88.580054,44.793114],"type":"Point"}
}