{
  "type": "Feature",
  "properties": {
    "iso:country":"US",
    "sg:address":"13801 7th St",
    "sg:city":"Osseo",
    "sg:classifiers":[
        {
            "category":"Insurance",
            "subcategory":"Insurance Agent",
            "type":"Services"
        }
    ],
    "sg:phone":"+1 715 597 3192",
    "sg:postcode":"54758",
    "sg:province":"WI",
    "sg:website":"www.kittelsoninsurance.com",
    "wof:name":"Kittelson Insurance",
    "wof:placetype":"venue"
},
  "geometry": {"coordinates":[-91.22392600000001,44.5772],"type":"Point"}
}