{
  "type": "Feature",
  "properties": {
    "addr:full":"1421 S Park St Madison WI 53715",
    "addr:housenumber":"1421",
    "addr:postcode":"53715",
    "addr:street":"S Park St",
    "iso:country":"US",
    "sg:address":"1421 S Park St",
    "sg:city":"Madison",
    "sg:classifiers":[
        {
            "category":"Shopping",
            "subcategory":"Books",
            "type":"Retail Goods"
        }
    ],
    "sg:phone":"+1 608 441 1957",
    "sg:postcode":"53715",
    "sg:province":"WI",
    "sg:tags":[
        "dealer"
    ],
    "wof:name":"20th Century Books",
    "wof:placetype":"venue"
},
  "geometry": {"coordinates":[-89.393986,43.049429],"type":"Point"}
}