{
  "type": "Feature",
  "properties": {
    "iso:country":"US",
    "sg:address":"676 Kettle Ridge",
    "sg:city":"Colgate",
    "sg:classifiers":[
        {
            "category":"Shopping",
            "type":"Retail Goods"
        }
    ],
    "sg:phone":"+1 262 628 8517",
    "sg:postcode":"53017",
    "sg:province":"WI",
    "sg:tags":[
        "merchandise"
    ],
    "wof:name":"American Fire & Safety",
    "wof:placetype":"venue"
},
  "geometry": {"coordinates":[-88.296419,43.215417],"type":"Point"}
}