{
  "type": "Feature",
  "properties": {
    "iso:country":"US",
    "sg:address":"2820 Plover Rd",
    "sg:city":"Wisconsin Rapids",
    "sg:classifiers":[
        {
            "category":"Freight",
            "type":"Transportation"
        }
    ],
    "sg:phone":"+1 715 421 1683",
    "sg:postcode":"54494",
    "sg:province":"WI",
    "sg:tags":[
        "trucking"
    ],
    "wof:name":"Classic Transport",
    "wof:placetype":"venue"
},
  "geometry": {"coordinates":[-89.788974,44.407159],"type":"Point"}
}