{
  "type": "Feature",
  "properties": {
    "iso:country":"US",
    "sg:address":"430 Ahnaip St",
    "sg:city":"Menasha",
    "sg:classifiers":[
        {
            "category":"Professional",
            "subcategory":"Lawyer & Legal Services",
            "type":"Services"
        }
    ],
    "sg:phone":"+1 920 725 8115",
    "sg:postcode":"54952",
    "sg:province":"WI",
    "wof:name":"Robert J Smead",
    "wof:placetype":"venue"
},
  "geometry": {"coordinates":[-88.446265,44.19752],"type":"Point"}
}