{
  "type": "Feature",
  "properties": {
    "iso:country":"US",
    "sg:address":"829 Clover Ln",
    "sg:city":"De Forest",
    "sg:classifiers":[
        {
            "category":"Building & Trades",
            "subcategory":"Landscaping Services",
            "type":"Services"
        }
    ],
    "sg:phone":"+1 608 846 7282",
    "sg:postcode":"53532",
    "sg:province":"WI",
    "wof:name":"Toms Lawn Care LLC",
    "wof:placetype":"venue"
},
  "geometry": {"coordinates":[-89.360618,43.24625],"type":"Point"}
}