{
  "type": "Feature",
  "properties": {
    "iso:country":"US",
    "sg:address":"2900 N 117th St",
    "sg:city":"Milwaukee",
    "sg:classifiers":[
        {
            "category":"Personal",
            "type":"Services"
        }
    ],
    "sg:phone":"+1 414 778 1202",
    "sg:postcode":"53222",
    "sg:province":"WI",
    "wof:name":"Lyonstin Hair Inc",
    "wof:placetype":"venue"
},
  "geometry": {"coordinates":[-88.05956399999999,43.074031],"type":"Point"}
}