{
  "type": "Feature",
  "properties": {
    "iso:country":"US",
    "sg:address":"890 Fond du Lac Ave",
    "sg:city":"Kewaskum",
    "sg:classifiers":[
        {
            "category":"Restaurant",
            "type":"Food & Drink"
        }
    ],
    "sg:phone":"+1 262 626 8467",
    "sg:postcode":"53040",
    "sg:province":"WI",
    "sg:tags":[
        "eating"
    ],
    "wof:name":"McDonalds",
    "wof:placetype":"venue"
},
  "geometry": {"coordinates":[-88.222793,43.512856],"type":"Point"}
}