{
  "type": "Feature",
  "properties": {
    "iso:country":"US",
    "sg:address":"422 Church St",
    "sg:city":"Clinton",
    "sg:classifiers":[
        {
            "category":"Organizations",
            "subcategory":"Religious Organization",
            "type":"Services"
        }
    ],
    "sg:phone":"+1 608 676 4431",
    "sg:postcode":"53525",
    "sg:province":"WI",
    "sg:tags":[
        "church"
    ],
    "wof:name":"Pella Lutheran Church",
    "wof:placetype":"venue"
},
  "geometry": {"coordinates":[-88.865218,42.560105],"type":"Point"}
}