{
  "type": "Feature",
  "properties": {
    "addr:full":"8333 W Capitol Dr Milwaukee WI 53222",
    "addr:housenumber":"8333",
    "addr:postcode":"53222",
    "addr:street":"W Capitol Dr",
    "iso:country":"US",
    "sg:address":"8333 W Capitol Dr",
    "sg:city":"Milwaukee",
    "sg:classifiers":[
        {
            "category":"Shopping",
            "subcategory":"Clothing, Apparel, & Fashions",
            "type":"Retail Goods"
        }
    ],
    "sg:phone":"+1 414 463 7777",
    "sg:postcode":"53222",
    "sg:province":"WI",
    "sg:tags":[
        "leather",
        "apparel",
        "fur",
        "business"
    ],
    "sg:website":"http://www.ugentfurs.com",
    "wof:name":"A J Ugent Furs & Fashions",
    "wof:placetype":"venue"
},
  "geometry": {"coordinates":[-88.01667399999999,43.089776],"type":"Point"}
}