{
  "type": "Feature",
  "properties": {
    "iso:country":"US",
    "sg:address":"12930 W Custer Ave",
    "sg:city":"Butler",
    "sg:classifiers":[
        {
            "category":"Utilities",
            "subcategory":"Electric",
            "type":"Services"
        },
        {
            "category":"Building & Trades",
            "subcategory":"Plumbing",
            "type":"Services"
        },
        {
            "category":"Building & Trades",
            "subcategory":"Construction",
            "type":"Services"
        }
    ],
    "sg:phone":"+1 262 781 5940",
    "sg:postcode":"53007",
    "sg:province":"WI",
    "sg:tags":[
        "engineer",
        "plumber",
        "industrial",
        "system",
        "heating",
        "specialty",
        "ventilating",
        "contractor",
        "air conditioning",
        "contractors-commercial"
    ],
    "sg:website":"http://www.midcityplumbing.com",
    "wof:name":"Mid City Plumbing & Heating Inc",
    "wof:placetype":"venue"
},
  "geometry": {"coordinates":[-88.073255,43.115012],"type":"Point"}
}