{
  "type": "Feature",
  "properties": {
    "iso:country":"US",
    "sg:address":"136 E Division St",
    "sg:city":"Shawano",
    "sg:classifiers":[
        {
            "category":"Professional",
            "subcategory":"Lawyer & Legal Services",
            "type":"Services"
        }
    ],
    "sg:phone":"+1 715 524 6262",
    "sg:postcode":"54166",
    "sg:province":"WI",
    "sg:tags":[
        "attorney"
    ],
    "wof:name":"Bartholomew Law Office",
    "wof:placetype":"venue"
},
  "geometry": {"coordinates":[-88.608738,44.780087],"type":"Point"}
}