{
  "type": "Feature",
  "properties": {
    "iso:country":"US",
    "sg:address":"2016 22nd Ave",
    "sg:city":"Bloomer",
    "sg:classifiers":[
        {
            "category":"Freight",
            "type":"Transportation"
        }
    ],
    "sg:phone":"+1 715 568 5640",
    "sg:postcode":"54724",
    "sg:province":"WI",
    "sg:tags":[
        "trucking"
    ],
    "wof:name":"Joe Larson Trucking Garage",
    "wof:placetype":"venue"
},
  "geometry": {"coordinates":[-91.503602,45.094191],"type":"Point"}
}