{
  "type": "Feature",
  "properties": {
    "addr:full":"8432 Co Rd Z Pound WI 54161",
    "addr:housenumber":"8432",
    "addr:postcode":"54161",
    "addr:street":"Co Rd",
    "iso:country":"US",
    "sg:address":"8432 Co Rd Z",
    "sg:city":"Pound",
    "sg:classifiers":[
        {
            "category":"Personal",
            "subcategory":"Beauty Salon",
            "type":"Services"
        }
    ],
    "sg:phone":"+1 920 897 5111",
    "sg:postcode":"54161",
    "sg:province":"WI",
    "sg:tags":[
        "shop"
    ],
    "wof:name":"Expressions Salon",
    "wof:placetype":"venue"
},
  "geometry": {"coordinates":[-88.17515400000001,45.068071],"type":"Point"}
}