{
  "type": "Feature",
  "properties": {
    "iso:country":"US",
    "sg:address":"2225 N Humboldt Blvd",
    "sg:city":"Milwaukee",
    "sg:classifiers":[
        {
            "category":"Shopping",
            "subcategory":"Used Merchandise",
            "type":"Retail Goods"
        },
        {
            "category":"Shopping",
            "subcategory":"Clothing, Apparel, & Fashions",
            "type":"Retail Goods"
        }
    ],
    "sg:phone":"+1 414 372 4744",
    "sg:postcode":"53212",
    "sg:province":"WI",
    "sg:tags":[
        "vintage",
        "family",
        "store"
    ],
    "wof:name":"Yellow Jacket Inc",
    "wof:placetype":"venue"
},
  "geometry": {"coordinates":[-87.89798500000001,43.061898],"type":"Point"}
}