{
  "type": "Feature",
  "properties": {
    "addr:full":"7056 Timblin Dr West Bend WI 53090",
    "addr:housenumber":"7056",
    "addr:postcode":"53090",
    "addr:street":"Timblin Dr",
    "iso:country":"US",
    "sg:address":"7056 Timblin Dr",
    "sg:city":"West Bend",
    "sg:classifiers":[
        {
            "category":"Manufacturing",
            "subcategory":"Printing",
            "type":"Manufacturing & Wholesale Goods"
        }
    ],
    "sg:phone":"+1 262 306 6727",
    "sg:postcode":"53090",
    "sg:province":"WI",
    "sg:tags":[
        "top",
        "publishing",
        "desk"
    ],
    "wof:name":"Peter A Altenhofen Graphics",
    "wof:placetype":"venue"
},
  "geometry": {"coordinates":[-88.208394,43.448078],"type":"Point"}
}