{
  "type": "Feature",
  "properties": {
    "addr:full":"1407 Summit Ave Waukesha WI 53188",
    "addr:housenumber":"1407",
    "addr:postcode":"53188",
    "addr:street":"Summit Ave",
    "iso:country":"US",
    "sg:address":"1407 Summit Ave",
    "sg:city":"Waukesha",
    "sg:classifiers":[
        {
            "category":"Professional",
            "subcategory":"Business Services",
            "type":"Services"
        },
        {
            "category":"Banks & Credit Unions",
            "subcategory":"Bank",
            "type":"Services"
        }
    ],
    "sg:phone":"+1 262 544 8242",
    "sg:postcode":"53188",
    "sg:province":"WI",
    "sg:tags":[
        "financing"
    ],
    "wof:name":"American General Finance Corp",
    "wof:placetype":"venue"
},
  "geometry": {"coordinates":[-88.25093699999999,43.021453],"type":"Point"}
}