{
  "type": "Feature",
  "properties": {
    "iso:country":"US",
    "sg:address":"2132 W Edgerton Ave",
    "sg:city":"Milwaukee",
    "sg:classifiers":[
        {
            "category":"Wholesale",
            "subcategory":"Non-durable Goods",
            "type":"Manufacturing & Wholesale Goods"
        },
        {
            "category":"Personal",
            "subcategory":"Barber",
            "type":"Services"
        }
    ],
    "sg:phone":"+1 414 281 6216",
    "sg:postcode":"53221",
    "sg:province":"WI",
    "sg:tags":[
        "beauty",
        "supply",
        "equipment",
        "salons-equipment",
        "supplies-wholesale",
        "manufacturer"
    ],
    "wof:name":"J S Supply",
    "wof:placetype":"venue"
},
  "geometry": {"coordinates":[-87.94099300000001,42.952056],"type":"Point"}
}