{
  "type": "Feature",
  "properties": {
    "iso:country":"US",
    "sg:address":"204 S Main St",
    "sg:city":"Shawano",
    "sg:classifiers":[
        {
            "category":"Shopping",
            "subcategory":"Florist",
            "type":"Retail Goods"
        }
    ],
    "sg:phone":"+1 715 524 2669",
    "sg:postcode":"54166",
    "sg:province":"WI",
    "wof:name":"Village Garden Flower Shop",
    "wof:placetype":"venue"
},
  "geometry": {"coordinates":[-88.609222,44.780081],"type":"Point"}
}