{
  "type": "Feature",
  "properties": {
    "addr:full":"6051 W Brown Deer Rd Milwaukee WI 53223",
    "addr:housenumber":"6051",
    "addr:postcode":"53223",
    "addr:street":"W Brown Deer Rd",
    "iso:country":"US",
    "sg:address":"6051 W Brown Deer Rd",
    "sg:city":"Milwaukee",
    "sg:classifiers":[
        {
            "category":"Professional",
            "subcategory":"Employment Agencies",
            "type":"Services"
        }
    ],
    "sg:phone":"+1 414 475 7409",
    "sg:postcode":"53223",
    "sg:province":"WI",
    "sg:tags":[
        "temporary",
        "help"
    ],
    "wof:name":"Crown Temporary Personnel",
    "wof:placetype":"venue"
},
  "geometry": {"coordinates":[-87.986028,43.177607],"type":"Point"}
}