{
  "type": "Feature",
  "properties": {
    "iso:country":"US",
    "sg:address":"4405 S Oakley Rd",
    "sg:city":"Janesville",
    "sg:classifiers":[
        {
            "category":"Building & Trades",
            "subcategory":"Construction",
            "type":"Services"
        }
    ],
    "sg:phone":"+1 608 757 1914",
    "sg:postcode":"53546",
    "sg:province":"WI",
    "sg:tags":[
        "home",
        "builder"
    ],
    "wof:name":"A C Construction",
    "wof:placetype":"venue"
},
  "geometry": {"coordinates":[-89.06865999999999,42.618588],"type":"Point"}
}