{
  "type": "Feature",
  "properties": {
    "addr:full":"9502 State Hwy 42 Cleveland WI 53015",
    "addr:housenumber":"9502",
    "addr:postcode":"53015",
    "addr:street":"State Hwy 42",
    "iso:country":"US",
    "sg:address":"9502 State Hwy 42",
    "sg:city":"Cleveland",
    "sg:classifiers":[
        {
            "category":"Retail",
            "subcategory":"Auto Repair",
            "type":"Services"
        }
    ],
    "sg:phone":"+1 920 759 1130",
    "sg:postcode":"53015",
    "sg:province":"WI",
    "sg:tags":[
        "automotive"
    ],
    "wof:name":"Kaukauna Kwik Lube",
    "wof:placetype":"venue"
},
  "geometry": {"coordinates":[-87.829615,43.886166],"type":"Point"}
}