{
  "type": "Feature",
  "properties": {
    "iso:country":"US",
    "sg:address":"642 S Gammon Rd",
    "sg:city":"Madison",
    "sg:classifiers":[
        {
            "category":"Insurance",
            "subcategory":"Insurance Agent",
            "type":"Services"
        }
    ],
    "sg:phone":"+1 608 271 7756",
    "sg:postcode":"53719",
    "sg:province":"WI",
    "wof:name":"Insurance Associates",
    "wof:placetype":"venue"
},
  "geometry": {"coordinates":[-89.503199,43.050926],"type":"Point"}
}