{
  "type": "Feature",
  "properties": {
    "iso:country":"US",
    "sg:address":"313 Dousman St",
    "sg:city":"Green Bay",
    "sg:classifiers":[
        {
            "category":"Brewery",
            "type":"Food & Drink"
        }
    ],
    "sg:menulink":"http://www.allmenus.com/wi/green-bay/267293-hinterland-brewery-restaurant/menu/",
    "sg:phone":"+1 920 438 8050",
    "sg:postcode":"54303",
    "sg:province":"WI",
    "sg:tags":[
        "new",
        "american"
    ],
    "wof:name":"Hinterland Brewery Restaurant",
    "wof:placetype":"venue"
},
  "geometry": {"coordinates":[-88.01917299999999,44.518938],"type":"Point"}
}