{
  "type": "Feature",
  "properties": {
    "addr:full":"330 Industrial Cir Stoughton WI 53589",
    "addr:housenumber":"330",
    "addr:postcode":"53589",
    "addr:street":"Industrial Cir",
    "iso:country":"US",
    "sg:address":"330 Industrial Cir",
    "sg:city":"Stoughton",
    "sg:classifiers":[
        {
            "category":"Building & Trades",
            "subcategory":"Plumbing",
            "type":"Services"
        }
    ],
    "sg:phone":"+1 608 873 6726",
    "sg:postcode":"53589",
    "sg:province":"WI",
    "sg:tags":[
        "septic"
    ],
    "wof:name":"Honey Wagon Svc",
    "wof:placetype":"venue"
},
  "geometry": {"coordinates":[-89.219117,42.926903],"type":"Point"}
}