{
  "type": "Feature",
  "properties": {
    "iso:country":"US",
    "sg:address":"26927 Krause Rd",
    "sg:city":"Webster",
    "sg:classifiers":[
        {
            "category":"Farming",
            "subcategory":"Farm",
            "type":"Manufacturing & Wholesale Goods"
        }
    ],
    "sg:phone":"+1 715 866 8902",
    "sg:postcode":"54893",
    "sg:province":"WI",
    "sg:tags":[
        "crop",
        "general"
    ],
    "wof:name":"Krause Farm",
    "wof:placetype":"venue"
},
  "geometry": {"coordinates":[-92.30337299999999,45.897536],"type":"Point"}
}