{
  "type": "Feature",
  "properties": {
    "iso:country":"US",
    "sg:address":"224 Linn St",
    "sg:city":"Baraboo",
    "sg:classifiers":[
        {
            "category":"Professional",
            "subcategory":"Art Services",
            "type":"Services"
        }
    ],
    "sg:phone":"+1 608 356 8123",
    "sg:postcode":"53913",
    "sg:province":"WI",
    "sg:tags":[
        "graphic",
        "designer"
    ],
    "wof:name":"Baraboo Sign Co",
    "wof:placetype":"venue"
},
  "geometry": {"coordinates":[-89.76243700000001,43.474727],"type":"Point"}
}