{
  "type": "Feature",
  "properties": {
    "addr:full":"6110 N Flint Rd Milwaukee WI 53209",
    "addr:housenumber":"6110",
    "addr:postcode":"53209",
    "addr:street":"N Flint Rd",
    "iso:country":"US",
    "sg:address":"6110 N Flint Rd",
    "sg:city":"Milwaukee",
    "sg:classifiers":[
        {
            "category":"Manufacturing",
            "subcategory":"Printing",
            "type":"Manufacturing & Wholesale Goods"
        }
    ],
    "sg:phone":"+1 414 228 0380",
    "sg:postcode":"53209",
    "sg:province":"WI",
    "sg:tags":[
        "periodical"
    ],
    "wof:name":"Journal Sentinel Inc",
    "wof:placetype":"venue"
},
  "geometry": {"coordinates":[-87.94258000000001,43.127301],"type":"Point"}
}