{
  "type": "Feature",
  "properties": {
    "iso:country":"US",
    "sg:address":"654 US Hwy 51",
    "sg:city":"Woodruff",
    "sg:classifiers":[
        {
            "category":"Freight",
            "type":"Transportation"
        }
    ],
    "sg:phone":"+1 715 356 7781",
    "sg:postcode":"54568",
    "sg:province":"WI",
    "sg:tags":[
        "general"
    ],
    "wof:name":"Old 51 Stor All",
    "wof:placetype":"venue"
},
  "geometry": {"coordinates":[-89.697713,45.896546],"type":"Point"}
}