{
  "type": "Feature",
  "properties": {
    "iso:country":"US",
    "sg:address":"1735 Thierer Rd",
    "sg:city":"Madison",
    "sg:classifiers":[
        {
            "category":"Shopping",
            "subcategory":"Crafts & Fabrics",
            "type":"Retail Goods"
        }
    ],
    "sg:phone":"+1 608 249 6110",
    "sg:postcode":"53704",
    "sg:province":"WI",
    "wof:name":"Hancock Fabrics Inc",
    "wof:placetype":"venue"
},
  "geometry": {"coordinates":[-89.31432100000001,43.123726],"type":"Point"}
}