{
  "type": "Feature",
  "properties": {
    "iso:country":"US",
    "sg:address":"711 E Main St",
    "sg:city":"Wauzeka",
    "sg:classifiers":[
        {
            "category":"Organizations",
            "subcategory":"Religious Organization",
            "type":"Services"
        }
    ],
    "sg:phone":"+1 608 875 5401",
    "sg:postcode":"53826",
    "sg:province":"WI",
    "sg:tags":[
        "church"
    ],
    "wof:name":"Sacred Heart Catholic Rectory",
    "wof:placetype":"venue"
},
  "geometry": {"coordinates":[-90.876892,43.087217],"type":"Point"}
}