{
  "type": "Feature",
  "properties": {
    "iso:country":"US",
    "sg:address":"1217 12th Ave",
    "sg:city":"Monroe",
    "sg:classifiers":[
        {
            "category":"Manufacturing",
            "subcategory":"Tools & Machinery",
            "type":"Manufacturing & Wholesale Goods"
        }
    ],
    "sg:phone":"+1 608 325 4568",
    "sg:postcode":"53566",
    "sg:province":"WI",
    "sg:tags":[
        "machine",
        "shop",
        "crane",
        "welding"
    ],
    "wof:name":"Carter Machine Works",
    "wof:placetype":"venue"
},
  "geometry": {"coordinates":[-89.64465800000001,42.600064],"type":"Point"}
}