{
  "type": "Feature",
  "properties": {
    "iso:country":"US",
    "sg:address":"12340 W Oklahoma Ave",
    "sg:city":"Milwaukee",
    "sg:classifiers":[
        {
            "category":"Food & Beverages",
            "subcategory":"Groceries & Convenience Stores",
            "type":"Retail Goods"
        }
    ],
    "sg:phone":"+1 414 327 1550",
    "sg:postcode":"53227",
    "sg:province":"WI",
    "wof:name":"Speedway 4118",
    "wof:placetype":"venue"
},
  "geometry": {"coordinates":[-88.06648199999999,42.988281],"type":"Point"}
}