{
  "type": "Feature",
  "properties": {
    "iso:country":"US",
    "sg:address":"825 Lexington Blvd",
    "sg:city":"Fort Atkinson",
    "sg:classifiers":[
        {
            "category":"Cinema",
            "subcategory":"Movie Rental",
            "type":"Entertainment"
        }
    ],
    "sg:phone":"+1 920 568 0999",
    "sg:postcode":"53538",
    "sg:province":"WI",
    "sg:tags":[
        "leasing",
        "video",
        "disc",
        "tape"
    ],
    "wof:name":"Movie Gallery",
    "wof:placetype":"venue"
},
  "geometry": {"coordinates":[-88.858711,42.939827],"type":"Point"}
}