{
  "type": "Feature",
  "properties": {
    "iso:country":"US",
    "sg:address":"12202 Berlin Ln",
    "sg:city":"Merrill",
    "sg:classifiers":[
        {
            "category":"Building & Trades",
            "subcategory":"Construction",
            "type":"Services"
        }
    ],
    "sg:phone":"+1 715 536 6132",
    "sg:postcode":"54452",
    "sg:province":"WI",
    "sg:tags":[
        "house"
    ],
    "wof:name":"Fenwick Builders",
    "wof:placetype":"venue"
},
  "geometry": {"coordinates":[-89.788513,45.083526],"type":"Point"}
}