{
  "type": "Feature",
  "properties": {
    "iso:country":"US",
    "sg:address":"5300 S 108th St",
    "sg:city":"Hales Corners",
    "sg:classifiers":[
        {
            "category":"Banks & Credit Unions",
            "subcategory":"Bank",
            "type":"Services"
        }
    ],
    "sg:phone":"+1 414 529 4660",
    "sg:postcode":"53130",
    "sg:province":"WI",
    "sg:tags":[
        "short",
        "institution",
        "business"
    ],
    "wof:name":"Wells Fargo",
    "wof:placetype":"venue"
},
  "geometry": {"coordinates":[-88.048186,42.948543],"type":"Point"}
}