{
  "type": "Feature",
  "properties": {
    "iso:country":"US",
    "sg:address":"1110 N Main St",
    "sg:city":"Edgerton",
    "sg:classifiers":[
        {
            "category":"Health Services",
            "subcategory":"Optometrist",
            "type":"Services"
        }
    ],
    "sg:phone":"+1 608 884 3314",
    "sg:postcode":"53534",
    "sg:province":"WI",
    "wof:name":"Edgerton Vision Center",
    "wof:placetype":"venue"
},
  "geometry": {"coordinates":[-89.058694,42.846916],"type":"Point"}
}