{
  "type": "Feature",
  "properties": {
    "addr:full":"4455 State Road 144 Slinger WI 53086",
    "addr:housenumber":"4455",
    "addr:postcode":"53086",
    "addr:street":"State Road 144",
    "iso:country":"US",
    "sg:address":"4455 State Road 144",
    "sg:city":"Slinger",
    "sg:classifiers":[
        {
            "category":"Home & Garden",
            "subcategory":"Garden Supply",
            "type":"Retail Goods"
        },
        {
            "category":"Home & Garden",
            "subcategory":"Building Materials",
            "type":"Retail Goods"
        },
        {
            "category":"Utilities",
            "subcategory":"Natural Gas",
            "type":"Services"
        }
    ],
    "sg:phone":"+1 262 644 9486",
    "sg:postcode":"53086",
    "sg:province":"WI",
    "sg:tags":[
        "stone",
        "landscaping",
        "mulch",
        "topsoil",
        "equipment",
        "sand",
        "gravel"
    ],
    "sg:website":"http://www.bechtelslandscape.com",
    "wof:name":"Bechtel's Landscape Supplies",
    "wof:placetype":"venue"
},
  "geometry": {"coordinates":[-88.28085,43.350924],"type":"Point"}
}