{
  "type": "Feature",
  "properties": {
    "iso:country":"US",
    "sg:address":"4225 Durand Ave",
    "sg:city":"Racine",
    "sg:classifiers":[
        {
            "category":"Real Estate",
            "subcategory":"Real Estate Operator",
            "type":"Services"
        }
    ],
    "sg:phone":"+1 262 554 9092",
    "sg:postcode":"53405",
    "sg:province":"WI",
    "sg:tags":[
        "building",
        "apartment"
    ],
    "wof:name":"Courtyard APT",
    "wof:placetype":"venue"
},
  "geometry": {"coordinates":[-87.830636,42.696782],"type":"Point"}
}