{
  "type": "Feature",
  "properties": {
    "iso:country":"US",
    "sg:address":"1415 Eagle St",
    "sg:city":"Rhinelander",
    "sg:classifiers":[
        {
            "category":"Government",
            "subcategory":"Office",
            "type":"Public Place"
        }
    ],
    "sg:phone":"+1 715 362 5941",
    "sg:postcode":"54501",
    "sg:province":"WI",
    "sg:tags":[
        "federal",
        "planning",
        "dev"
    ],
    "wof:name":"USDA Rural Development",
    "wof:placetype":"venue"
},
  "geometry": {"coordinates":[-89.401571,45.65487],"type":"Point"}
}