{
  "type": "Feature",
  "properties": {
    "iso:country":"US",
    "sg:address":"1910 Menominee Dr",
    "sg:city":"Oshkosh",
    "sg:classifiers":[
        {
            "category":"Professional",
            "subcategory":"Business Services",
            "type":"Services"
        }
    ],
    "sg:phone":"+1 920 233 3033",
    "sg:postcode":"54901",
    "sg:province":"WI",
    "wof:name":"Williams Steve D I L H R Weat",
    "wof:placetype":"venue"
},
  "geometry": {"coordinates":[-88.512041,44.037214],"type":"Point"}
}