{
  "type": "Feature",
  "properties": {
    "iso:country":"US",
    "sg:address":"100 S Baldwin St",
    "sg:city":"Madison",
    "sg:classifiers":[
        {
            "category":"Professional",
            "subcategory":"Business Services",
            "type":"Services"
        }
    ],
    "sg:phone":"+1 608 255 4555",
    "sg:postcode":"53703",
    "sg:province":"WI",
    "wof:name":"Sanchez Industrial Design Inc",
    "wof:placetype":"venue"
},
  "geometry": {"coordinates":[-89.365246,43.086661],"type":"Point"}
}