{
  "type": "Feature",
  "properties": {
    "iso:country":"US",
    "sg:address":"11090 Zawadski Rd",
    "sg:city":"Drummond",
    "sg:classifiers":[
        {
            "category":"Professional",
            "subcategory":"Lawyer & Legal Services",
            "type":"Services"
        }
    ],
    "sg:phone":"+1 715 739 6444",
    "sg:postcode":"54832",
    "sg:province":"WI",
    "sg:tags":[
        "attorney"
    ],
    "wof:name":"George D Knapp",
    "wof:placetype":"venue"
},
  "geometry": {"coordinates":[-91.343009,46.282001],"type":"Point"}
}