{
  "type": "Feature",
  "properties": {
    "iso:country":"US",
    "sg:address":"5000 S Sunnyslope Rd",
    "sg:city":"New Berlin",
    "sg:classifiers":[
        {
            "category":"Organizations",
            "subcategory":"Religious Organization",
            "type":"Services"
        }
    ],
    "sg:phone":"+1 414 425 7030",
    "sg:postcode":"53151",
    "sg:province":"WI",
    "wof:name":"Our Lords Untd Methdst Church",
    "wof:placetype":"venue"
},
  "geometry": {"coordinates":[-88.089269,42.949501],"type":"Point"}
}