{
  "type": "Feature",
  "properties": {
    "iso:country":"US",
    "sg:address":"2600 American Dr",
    "sg:city":"Appleton",
    "sg:classifiers":[
        {
            "category":"Manufacturing",
            "subcategory":"Motor Vehicles & Parts",
            "type":"Manufacturing & Wholesale Goods"
        }
    ],
    "sg:phone":"+1 920 832 3000",
    "sg:postcode":"54914",
    "sg:province":"WI",
    "sg:tags":[
        "fire",
        "truck"
    ],
    "sg:website":"www.piercemfg.com",
    "wof:name":"Pierce Manufacturing Inc",
    "wof:placetype":"venue"
},
  "geometry": {"coordinates":[-88.47037899999999,44.241813],"type":"Point"}
}