{
  "type": "Feature",
  "properties": {
    "iso:country":"US",
    "sg:address":"81 15th St",
    "sg:city":"Fond Du Lac",
    "sg:classifiers":[
        {
            "category":"Restaurant",
            "type":"Food & Drink"
        }
    ],
    "sg:phone":"+1 920 923 6294",
    "sg:postcode":"54935",
    "sg:province":"WI",
    "sg:tags":[
        "lounge",
        "style",
        "family"
    ],
    "wof:name":"Maxieboys Inc",
    "wof:placetype":"venue"
},
  "geometry": {"coordinates":[-88.442136,43.763229],"type":"Point"}
}