{
  "type": "Feature",
  "properties": {
    "iso:country":"US",
    "sg:address":"140 Commercial Dr",
    "sg:city":"Columbus",
    "sg:classifiers":[
        {
            "category":"Shopping",
            "type":"Retail Goods"
        }
    ],
    "sg:phone":"+1 920 623 5297",
    "sg:postcode":"53925",
    "sg:province":"WI",
    "sg:tags":[
        "pet",
        "food",
        "merchandise",
        "supply"
    ],
    "wof:name":"Automated Pet Care Products",
    "wof:placetype":"venue"
},
  "geometry": {"coordinates":[-89.03047100000001,43.3435],"type":"Point"}
}