{
  "type": "Feature",
  "properties": {
    "iso:country":"US",
    "sg:address":"28649 Great Bear Trail Way",
    "sg:city":"Danbury",
    "sg:classifiers":[
        {
            "category":"Bars & Pubs",
            "type":"Food & Drink"
        }
    ],
    "sg:phone":"+1 715 656 7913",
    "sg:postcode":"54830",
    "sg:province":"WI",
    "wof:name":"Frank's Angler Bar & Grill",
    "wof:placetype":"venue"
},
  "geometry": {"coordinates":[-92.175425,45.953532],"type":"Point"}
}