{
  "type": "Feature",
  "properties": {
    "iso:country":"US",
    "sg:address":"1900 Stillman Dr",
    "sg:city":"Oshkosh",
    "sg:classifiers":[
        {
            "category":"Manufacturing",
            "subcategory":"Glass & Minerals",
            "type":"Manufacturing & Wholesale Goods"
        }
    ],
    "sg:phone":"+1 920 426 3666",
    "sg:postcode":"54901",
    "sg:province":"WI",
    "sg:tags":[
        "ready",
        "concrete",
        "mfg"
    ],
    "wof:name":"Carew Concrete & Supply Co Inc",
    "wof:placetype":"venue"
},
  "geometry": {"coordinates":[-88.569717,44.05561],"type":"Point"}
}