{
  "type": "Feature",
  "properties": {
    "iso:country":"US",
    "sg:address":"2908 S Colony Ave",
    "sg:city":"Union Grove",
    "sg:classifiers":[
        {
            "category":"Organizations",
            "subcategory":"Religious Organization",
            "type":"Services"
        }
    ],
    "sg:phone":"+1 262 878 4156",
    "sg:postcode":"53182",
    "sg:province":"WI",
    "wof:name":"Trinity Ev Lutheran Church",
    "wof:placetype":"venue"
},
  "geometry": {"coordinates":[-88.05203,42.697064],"type":"Point"}
}