{
  "type": "Feature",
  "properties": {
    "iso:country":"US",
    "sg:address":"4640 State Hwy 97",
    "sg:city":"Stratford",
    "sg:classifiers":[
        {
            "category":"Wholesale",
            "subcategory":"Machinery & Supplies",
            "type":"Manufacturing & Wholesale Goods"
        }
    ],
    "sg:phone":"+1 715 687 2453",
    "sg:postcode":"54484",
    "sg:province":"WI",
    "sg:tags":[
        "material"
    ],
    "wof:name":"Cover-All of Wisconsin LLC",
    "wof:placetype":"venue"
},
  "geometry": {"coordinates":[-90.079066,44.841091],"type":"Point"}
}