{
  "type": "Feature",
  "properties": {
    "addr:full":"146 E Rhine St Elkhart Lake WI 53020",
    "addr:housenumber":"146",
    "addr:postcode":"53020",
    "addr:street":"E Rhine St",
    "iso:country":"US",
    "sg:address":"146 E Rhine St",
    "sg:city":"Elkhart Lake",
    "sg:classifiers":[
        {
            "category":"Government",
            "subcategory":"Post Office",
            "type":"Public Place"
        }
    ],
    "sg:phone":"+1 920 876 3332",
    "sg:postcode":"53020",
    "sg:province":"WI",
    "wof:name":"US Post Office",
    "wof:placetype":"venue"
},
  "geometry": {"coordinates":[-88.01653,43.833112],"type":"Point"}
}