{
  "type": "Feature",
  "properties": {
    "iso:country":"US",
    "sg:address":"8949 N 97th St",
    "sg:city":"Milwaukee",
    "sg:classifiers":[
        {
            "category":"Professional",
            "type":"Services"
        }
    ],
    "sg:phone":"+1 414 365 3557",
    "sg:postcode":"53224",
    "sg:province":"WI",
    "sg:tags":[
        "establishment"
    ],
    "wof:name":"Liebau M",
    "wof:placetype":"venue"
},
  "geometry": {"coordinates":[-88.033152,43.181911],"type":"Point"}
}