{
  "type": "Feature",
  "properties": {
    "iso:country":"US",
    "sg:address":"3807 W North Ave",
    "sg:city":"Milwaukee",
    "sg:classifiers":[
        {
            "category":"Shopping",
            "subcategory":"Gifts & Souvenirs",
            "type":"Retail Goods"
        }
    ],
    "sg:phone":"+1 414 444 2805",
    "sg:postcode":"53208",
    "sg:province":"WI",
    "sg:tags":[
        "balloon",
        "artist"
    ],
    "wof:name":"Toys Balloon Cage 2",
    "wof:placetype":"venue"
},
  "geometry": {"coordinates":[-87.962253,43.06054],"type":"Point"}
}