{
  "type": "Feature",
  "properties": {
    "iso:country":"US",
    "sg:address":"959 Hazel St",
    "sg:city":"River Falls",
    "sg:classifiers":[
        {
            "category":"Building & Trades",
            "subcategory":"Construction",
            "type":"Services"
        }
    ],
    "sg:phone":"+1 715 425 9786",
    "sg:postcode":"54022",
    "sg:province":"WI",
    "sg:tags":[
        "contractor"
    ],
    "wof:name":"Lyle Sunde",
    "wof:placetype":"venue"
},
  "geometry": {"coordinates":[-92.612182,44.857732],"type":"Point"}
}