{
  "type": "Feature",
  "properties": {
    "iso:country":"US",
    "sg:address":"135 S Falls St",
    "sg:city":"River Falls",
    "sg:classifiers":[
        {
            "category":"Education",
            "subcategory":"School",
            "type":"Public Place"
        }
    ],
    "sg:phone":"+1 715 425 1872",
    "sg:postcode":"54022",
    "sg:province":"WI",
    "sg:tags":[
        "elementary"
    ],
    "wof:name":"Saint Parish Bridges School",
    "wof:placetype":"venue"
},
  "geometry": {"coordinates":[-92.633622,44.858501],"type":"Point"}
}