{
  "type": "Feature",
  "properties": {
    "addr:full":"110 S Pacific St Spencer WI 54479",
    "addr:housenumber":"110",
    "addr:postcode":"54479",
    "addr:street":"S Pacific St",
    "iso:country":"US",
    "sg:address":"110 S Pacific St",
    "sg:city":"Spencer",
    "sg:classifiers":[
        {
            "category":"Manufacturing",
            "subcategory":"Tools & Machinery",
            "type":"Manufacturing & Wholesale Goods"
        }
    ],
    "sg:phone":"+1 715 659 4525",
    "sg:postcode":"54479",
    "sg:province":"WI",
    "sg:tags":[
        "machine",
        "shop"
    ],
    "wof:name":"Spencer Machine & Engineering",
    "wof:placetype":"venue"
},
  "geometry": {"coordinates":[-90.296447,44.757319],"type":"Point"}
}