{
  "type": "Feature",
  "properties": {
    "iso:country":"US",
    "sg:address":"4097 Elk Ave",
    "sg:city":"Montello",
    "sg:classifiers":[
        {
            "category":"Manufacturing",
            "subcategory":"Lumber",
            "type":"Manufacturing & Wholesale Goods"
        }
    ],
    "sg:phone":"+1 608 296 4500",
    "sg:postcode":"53949",
    "sg:province":"WI",
    "sg:tags":[
        "company",
        "logging"
    ],
    "wof:name":"Drew Kory",
    "wof:placetype":"venue"
},
  "geometry": {"coordinates":[-89.36702099999999,43.861185],"type":"Point"}
}