{
  "type": "Feature",
  "properties": {
    "iso:country":"US",
    "sg:address":"1875 N Stevens St",
    "sg:city":"Rhinelander",
    "sg:classifiers":[
        {
            "category":"Professional",
            "type":"Services"
        }
    ],
    "sg:phone":"+1 715 365 2010",
    "sg:postcode":"54501",
    "sg:province":"WI",
    "sg:tags":[
        "establishment"
    ],
    "wof:name":"Helping Hands Marketing",
    "wof:placetype":"venue"
},
  "geometry": {"coordinates":[-89.389052,45.655462],"type":"Point"}
}