{
  "type": "Feature",
  "properties": {
    "iso:country":"US",
    "sg:address":"2114 International Ln",
    "sg:city":"Madison",
    "sg:classifiers":[
        {
            "category":"Wholesale",
            "subcategory":"Meat",
            "type":"Manufacturing & Wholesale Goods"
        }
    ],
    "sg:phone":"+1 608 285 3507",
    "sg:postcode":"53704",
    "sg:province":"WI",
    "sg:tags":[
        "processed",
        "mfg"
    ],
    "wof:name":"Kraft Foods",
    "wof:placetype":"venue"
},
  "geometry": {"coordinates":[-89.351581,43.123702],"type":"Point"}
}