{
  "type": "Feature",
  "properties": {
    "addr:full":"8469 Spencer Rd Willard WI 54493",
    "addr:housenumber":"8469",
    "addr:postcode":"54493",
    "addr:street":"Spencer Rd",
    "iso:country":"US",
    "sg:address":"8469 Spencer Rd",
    "sg:city":"Willard",
    "sg:classifiers":[
        {
            "category":"Freight",
            "type":"Transportation"
        }
    ],
    "sg:phone":"+1 715 267 6504",
    "sg:postcode":"54493",
    "sg:province":"WI",
    "sg:tags":[
        "operator",
        "trucking"
    ],
    "wof:name":"Randy Bogdonovich Trucking",
    "wof:placetype":"venue"
},
  "geometry": {"coordinates":[-90.738372,44.756575],"type":"Point"}
}