{
  "type": "Feature",
  "properties": {
    "iso:country":"US",
    "sg:address":"6685 Co Rd T",
    "sg:city":"Oshkosh",
    "sg:classifiers":[
        {
            "category":"Professional",
            "subcategory":"Business Services",
            "type":"Services"
        }
    ],
    "sg:phone":"+1 920 915 1967",
    "sg:postcode":"54904",
    "sg:province":"WI",
    "wof:name":"Expressive Hands LLC",
    "wof:placetype":"venue"
},
  "geometry": {"coordinates":[-88.583807,44.132846],"type":"Point"}
}