{
  "type": "Feature",
  "properties": {
    "iso:country":"US",
    "sg:address":"456 Mount Vernon St",
    "sg:city":"Oshkosh",
    "sg:classifiers":[
        {
            "category":"Real Estate",
            "subcategory":"Architect",
            "type":"Services"
        },
        {
            "category":"Retail",
            "subcategory":"Repair Shop",
            "type":"Services"
        }
    ],
    "sg:phone":"+1 920 651 9846",
    "sg:postcode":"54901",
    "sg:province":"WI",
    "sg:tags":[
        "antique",
        "restoring",
        "architectural"
    ],
    "wof:name":"Architectural Elements LLC",
    "wof:placetype":"venue"
},
  "geometry": {"coordinates":[-88.535211,44.019373],"type":"Point"}
}