{
  "type": "Feature",
  "properties": {
    "iso:country":"US",
    "sg:address":"3315 S Taylor Ave",
    "sg:city":"Milwaukee",
    "sg:classifiers":[
        {
            "category":"Building & Trades",
            "subcategory":"Plumbing",
            "type":"Services"
        }
    ],
    "sg:phone":"+1 414 727 7013",
    "sg:postcode":"53207",
    "sg:province":"WI",
    "sg:tags":[
        "mechanical",
        "contractor"
    ],
    "wof:name":"Rockwell Mechanical",
    "wof:placetype":"venue"
},
  "geometry": {"coordinates":[-87.900634,42.983645],"type":"Point"}
}