{
  "type": "Feature",
  "properties": {
    "iso:country":"US",
    "sg:address":"4847 N 40th St",
    "sg:city":"Milwaukee",
    "sg:classifiers":[
        {
            "category":"Personal",
            "subcategory":"Beauty Salon",
            "type":"Services"
        }
    ],
    "sg:phone":"+1 414 464 6421",
    "sg:postcode":"53209",
    "sg:province":"WI",
    "wof:name":"Nikki's Hair Salon",
    "wof:placetype":"venue"
},
  "geometry": {"coordinates":[-87.962786,43.105584],"type":"Point"}
}