{
  "type": "Feature",
  "properties": {
    "iso:country":"US",
    "sg:address":"5753 N 34th St",
    "sg:city":"Milwaukee",
    "sg:classifiers":[
        {
            "category":"Building & Trades",
            "subcategory":"Equipment Rental",
            "type":"Services"
        }
    ],
    "sg:phone":"+1 414 873 6999",
    "sg:postcode":"53209",
    "sg:province":"WI",
    "sg:tags":[
        "yard",
        "leasing",
        "store"
    ],
    "wof:name":"Andre's Place",
    "wof:placetype":"venue"
},
  "geometry": {"coordinates":[-87.954938,43.121829],"type":"Point"}
}