{
  "type": "Feature",
  "properties": {
    "addr:full":"1102 S Westfield St Oshkosh WI 54902",
    "addr:housenumber":"1102",
    "addr:postcode":"54902",
    "addr:street":"S Westfield St",
    "iso:country":"US",
    "sg:address":"1102 S Westfield St",
    "sg:city":"Oshkosh",
    "sg:classifiers":[
        {
            "category":"Organizations",
            "subcategory":"Community Association",
            "type":"Services"
        }
    ],
    "sg:phone":"+1 920 233 3870",
    "sg:postcode":"54902",
    "sg:province":"WI",
    "wof:name":"American Veterans Post 7",
    "wof:placetype":"venue"
},
  "geometry": {"coordinates":[-88.576993,44.008651],"type":"Point"}
}