{
  "type": "Feature",
  "properties": {
    "addr:full":"120 N Jackson St Green Bay WI 54301",
    "addr:housenumber":"120",
    "addr:postcode":"54301",
    "addr:street":"N Jackson St",
    "iso:country":"US",
    "sg:address":"120 N Jackson St",
    "sg:city":"Green Bay",
    "sg:classifiers":[
        {
            "category":"Local Transit",
            "type":"Transportation"
        }
    ],
    "sg:phone":"+1 920 437 8049",
    "sg:postcode":"54301",
    "sg:province":"WI",
    "sg:tags":[
        "passenger",
        "taxicab"
    ],
    "wof:name":"Dream Limo Service",
    "wof:placetype":"venue"
},
  "geometry": {"coordinates":[-88.00700999999999,44.51205],"type":"Point"}
}