{
  "type": "Feature",
  "properties": {
    "iso:country":"US",
    "sg:address":"21445 Gumina Rd",
    "sg:city":"Pewaukee",
    "sg:classifiers":[
        {
            "category":"Restaurant",
            "type":"Food & Drink"
        }
    ],
    "sg:phone":"+1 262 781 7995",
    "sg:postcode":"53072",
    "sg:province":"WI",
    "sg:website":"www.foodspot.com",
    "wof:name":"Jake's Restaurants",
    "wof:placetype":"venue"
},
  "geometry": {"coordinates":[-88.18080999999999,43.084299],"type":"Point"}
}