{
  "type": "Feature",
  "properties": {
    "iso:country":"US",
    "sg:address":"4467 Co Hwy C",
    "sg:city":"Horicon",
    "sg:classifiers":[
        {
            "category":"Building & Trades",
            "subcategory":"Equipment Rental",
            "type":"Services"
        }
    ],
    "sg:phone":"+1 920 485 6730",
    "sg:postcode":"53097",
    "sg:province":"WI",
    "wof:name":"C & B Rentals LLC",
    "wof:placetype":"venue"
},
  "geometry": {"coordinates":[-87.96707600000001,43.279625],"type":"Point"}
}