{
  "type": "Feature",
  "properties": {
    "iso:country":"US",
    "sg:address":"935 Sherry St",
    "sg:city":"Neenah",
    "sg:classifiers":[
        {
            "category":"Building & Trades",
            "subcategory":"Construction",
            "type":"Services"
        }
    ],
    "sg:phone":"+1 920 867 2584",
    "sg:postcode":"54956",
    "sg:province":"WI",
    "sg:tags":[
        "contractor"
    ],
    "wof:name":"Build It Construction",
    "wof:placetype":"venue"
},
  "geometry": {"coordinates":[-88.479871,44.184928],"type":"Point"}
}