{
  "type": "Feature",
  "properties": {
    "iso:country":"US",
    "sg:address":"925 Golf Vu Dr",
    "sg:city":"Fond Du Lac",
    "sg:classifiers":[
        {
            "category":"Manufacturing",
            "subcategory":"Toys & Sporting Goods",
            "type":"Manufacturing & Wholesale Goods"
        }
    ],
    "sg:phone":"+1 920 923 0211",
    "sg:postcode":"54935",
    "sg:province":"WI",
    "sg:tags":[
        "athletic"
    ],
    "wof:name":"Witte Group",
    "wof:placetype":"venue"
},
  "geometry": {"coordinates":[-88.418079,43.759655],"type":"Point"}
}