{
  "type": "Feature",
  "properties": {
    "iso:country":"US",
    "sg:address":"2175 W Twin Willows Dr",
    "sg:city":"Appleton",
    "sg:classifiers":[
        {
            "category":"Real Estate",
            "subcategory":"Real Estate Agent",
            "type":"Services"
        }
    ],
    "sg:phone":"+1 920 832 9785",
    "sg:postcode":"54914",
    "sg:province":"WI",
    "wof:name":"Coldwell Banker",
    "wof:placetype":"venue"
},
  "geometry": {"coordinates":[-88.440896,44.29183],"type":"Point"}
}