{
  "type": "Feature",
  "properties": {
    "iso:country":"US",
    "sg:address":"4512 White Oak Ln",
    "sg:city":"Sheboygan",
    "sg:classifiers":[
        {
            "category":"Building & Trades",
            "subcategory":"Landscaping Services",
            "type":"Services"
        }
    ],
    "sg:phone":"+1 920 458 3736",
    "sg:postcode":"53083",
    "sg:province":"WI",
    "sg:tags":[
        "landscape",
        "contractor"
    ],
    "wof:name":"Daun's Professional Lawn",
    "wof:placetype":"venue"
},
  "geometry": {"coordinates":[-87.736698,43.79239],"type":"Point"}
}