{
  "type": "Feature",
  "properties": {
    "iso:country":"US",
    "sg:address":"432 Washington Dr",
    "sg:city":"West Bend",
    "sg:classifiers":[
        {
            "category":"Shopping",
            "subcategory":"News",
            "type":"Retail Goods"
        }
    ],
    "sg:phone":"+1 262 338 6880",
    "sg:postcode":"53095",
    "sg:province":"WI",
    "sg:tags":[
        "dealer"
    ],
    "wof:name":"Milwaukee Journal Washington",
    "wof:placetype":"venue"
},
  "geometry": {"coordinates":[-88.04364700000001,43.374557],"type":"Point"}
}