{
  "type": "Feature",
  "properties": {
    "iso:country":"US",
    "sg:address":"2215 Stoney Rd",
    "sg:city":"Mishicot",
    "sg:classifiers":[
        {
            "category":"Retail",
            "subcategory":"Car Wash",
            "type":"Services"
        }
    ],
    "sg:phone":"+1 920 755 3103",
    "sg:postcode":"54228",
    "sg:province":"WI",
    "sg:tags":[
        "carwash"
    ],
    "wof:name":"Skubal Properties & Power Wash",
    "wof:placetype":"venue"
},
  "geometry": {"coordinates":[-87.61471,44.291281],"type":"Point"}
}