{
  "type": "Feature",
  "properties": {
    "iso:country":"US",
    "sg:address":"112 Field St",
    "sg:city":"Antigo",
    "sg:classifiers":[
        {
            "category":"Sports & Exercise",
            "subcategory":"Gym",
            "type":"Entertainment"
        }
    ],
    "sg:phone":"+1 715 627 4415",
    "sg:postcode":"54409",
    "sg:province":"WI",
    "sg:tags":[
        "fitness",
        "physical",
        "facility"
    ],
    "wof:name":"Antigo Fitness Center",
    "wof:placetype":"venue"
},
  "geometry": {"coordinates":[-89.145948,45.133905],"type":"Point"}
}