{
  "type": "Feature",
  "properties": {
    "iso:country":"US",
    "sg:address":"6110 Aerotech Dr",
    "sg:city":"Appleton",
    "sg:classifiers":[
        {
            "category":"Professional",
            "subcategory":"Accounting & Tax Preparation",
            "type":"Services"
        }
    ],
    "sg:phone":"+1 920 225 6436",
    "sg:postcode":"54914",
    "sg:province":"WI",
    "sg:tags":[
        "accountant"
    ],
    "wof:name":"Murray CPA Firm",
    "wof:placetype":"venue"
},
  "geometry": {"coordinates":[-88.500608,44.261196],"type":"Point"}
}