{
  "type": "Feature",
  "properties": {
    "iso:country":"US",
    "sg:address":"4546 Butternut Ln",
    "sg:city":"Birnamwood",
    "sg:classifiers":[
        {
            "category":"Professional",
            "subcategory":"Management & Consulting",
            "type":"Services"
        }
    ],
    "sg:phone":"+1 715 449 2182",
    "sg:postcode":"54414",
    "sg:province":"WI",
    "sg:tags":[
        "business",
        "association"
    ],
    "wof:name":"Aquatic Rsrcs/Glcl Pnd Frms",
    "wof:placetype":"venue"
},
  "geometry": {"coordinates":[-89.25668,44.877899],"type":"Point"}
}