{
  "type": "Feature",
  "properties": {
    "iso:country":"US",
    "sg:address":"14040 W Glendale Ave",
    "sg:city":"Brookfield",
    "sg:classifiers":[
        {
            "category":"Wholesale",
            "subcategory":"Non-durable Goods",
            "type":"Manufacturing & Wholesale Goods"
        }
    ],
    "sg:phone":"+1 262 783 7655",
    "sg:postcode":"53005",
    "sg:province":"WI",
    "wof:name":"MRI Assoc",
    "wof:placetype":"venue"
},
  "geometry": {"coordinates":[-88.088562,43.099879],"type":"Point"}
}