{
  "type": "Feature",
  "properties": {
    "iso:country":"US",
    "sg:address":"829 N Marshall St",
    "sg:city":"Milwaukee",
    "sg:classifiers":[
        {
            "category":"Professional",
            "subcategory":"Lawyer & Legal Services",
            "type":"Services"
        }
    ],
    "sg:phone":"+1 414 272 3636",
    "sg:postcode":"53202",
    "sg:province":"WI",
    "sg:tags":[
        "attorney",
        "practice",
        "worker",
        "compensation",
        "labor",
        "benefit",
        "employee",
        "law",
        "employment"
    ],
    "sg:website":"http://www.danmccormicklaw.com",
    "wof:name":"McCormick Law Office",
    "wof:placetype":"venue"
},
  "geometry": {"coordinates":[-87.900567,43.041904],"type":"Point"}
}