{
  "type": "Feature",
  "properties": {
    "iso:country":"US",
    "sg:address":"907 W 8th Ave",
    "sg:city":"Oshkosh",
    "sg:classifiers":[
        {
            "category":"Education",
            "subcategory":"Dance Studio",
            "type":"Public Place"
        }
    ],
    "sg:phone":"+1 920 231 7020",
    "sg:postcode":"54902",
    "sg:province":"WI",
    "wof:name":"Stillman School Of Dance",
    "wof:placetype":"venue"
},
  "geometry": {"coordinates":[-88.56235,44.011136],"type":"Point"}
}