{
  "type": "Feature",
  "properties": {
    "iso:country":"US",
    "sg:address":"613 E Beacon Ave",
    "sg:city":"New London",
    "sg:classifiers":[
        {
            "category":"Manufacturing",
            "subcategory":"Furniture",
            "type":"Manufacturing & Wholesale Goods"
        }
    ],
    "sg:phone":"+1 920 982 2140",
    "sg:postcode":"54961",
    "sg:province":"WI",
    "sg:website":"www.simmonsjp.com",
    "wof:name":"Simmons Juvenile Products",
    "wof:placetype":"venue"
},
  "geometry": {"coordinates":[-88.729437,44.388393],"type":"Point"}
}