{
  "type": "Feature",
  "properties": {
    "iso:country":"US",
    "sg:address":"420 N Segoe Rd",
    "sg:city":"Madison",
    "sg:classifiers":[
        {
            "category":"Real Estate",
            "subcategory":"Real Estate Operator",
            "type":"Services"
        }
    ],
    "sg:phone":"+1 608 238 4228",
    "sg:postcode":"53705",
    "sg:province":"WI",
    "sg:tags":[
        "building",
        "apartment"
    ],
    "wof:name":"Karen Arms Garden Apartments",
    "wof:placetype":"venue"
},
  "geometry": {"coordinates":[-89.454179,43.069986],"type":"Point"}
}