{
  "type": "Feature",
  "properties": {
    "iso:country":"US",
    "sg:address":"109 N Main St",
    "sg:city":"Hartford",
    "sg:classifiers":[
        {
            "category":"Government",
            "subcategory":"Office",
            "type":"Public Place"
        }
    ],
    "sg:phone":"+1 262 673 8217",
    "sg:postcode":"53027",
    "sg:province":"WI",
    "sg:tags":[
        "housing",
        "authority"
    ],
    "wof:name":"Hartford Community Dev Auth",
    "wof:placetype":"venue"
},
  "geometry": {"coordinates":[-88.378942,43.319183],"type":"Point"}
}