{
  "type": "Feature",
  "properties": {
    "addr:full":"100 Wilburn Rd Sun Prairie WI 53590",
    "addr:housenumber":"100",
    "addr:postcode":"53590",
    "addr:street":"Wilburn Rd",
    "iso:country":"US",
    "sg:address":"100 Wilburn Rd",
    "sg:city":"Sun Prairie",
    "sg:classifiers":[
        {
            "category":"Real Estate",
            "subcategory":"Architect",
            "type":"Services"
        }
    ],
    "sg:phone":"+1 608 825 2222",
    "sg:postcode":"53590",
    "sg:province":"WI",
    "wof:name":"Knute Villand Consulting",
    "wof:placetype":"venue"
},
  "geometry": {"coordinates":[-89.20845199999999,43.198769],"type":"Point"}
}