{
  "type": "Feature",
  "properties": {
    "iso:country":"US",
    "sg:address":"7311 W Capitol Dr",
    "sg:city":"Milwaukee",
    "sg:classifiers":[
        {
            "category":"Autos & Motor Vehicles",
            "subcategory":"Fuel & Gas Station",
            "type":"Retail Goods"
        }
    ],
    "sg:phone":"+1 414 464 8743",
    "sg:postcode":"53216",
    "sg:province":"WI",
    "sg:tags":[
        "oil"
    ],
    "wof:name":"Amoco Food Shop",
    "wof:placetype":"venue"
},
  "geometry": {"coordinates":[-88.004712,43.08985],"type":"Point"}
}