{
  "type": "Feature",
  "properties": {
    "iso:country":"US",
    "sg:address":"2281 State Hwy 32",
    "sg:city":"Cedar Grove",
    "sg:classifiers":[
        {
            "category":"Freight",
            "type":"Transportation"
        }
    ],
    "sg:phone":"+1 920 668 6284",
    "sg:postcode":"53013",
    "sg:province":"WI",
    "sg:tags":[
        "operator",
        "local",
        "trucking"
    ],
    "wof:name":"Ranke Trucking Ltd",
    "wof:placetype":"venue"
},
  "geometry": {"coordinates":[-87.809306,43.572119],"type":"Point"}
}