{
  "type": "Feature",
  "properties": {
    "addr:full":"219 W Knapp St Rice Lake WI 54868",
    "addr:housenumber":"219",
    "addr:postcode":"54868",
    "addr:street":"W Knapp St",
    "iso:country":"US",
    "sg:address":"219 W Knapp St",
    "sg:city":"Rice Lake",
    "sg:classifiers":[
        {
            "category":"Professional",
            "subcategory":"Business Services",
            "type":"Services"
        }
    ],
    "sg:phone":"+1 715 234 3321",
    "sg:postcode":"54868",
    "sg:province":"WI",
    "sg:tags":[
        "microfilm"
    ],
    "wof:name":"Microfilm Service of Rice Lake",
    "wof:placetype":"venue"
},
  "geometry": {"coordinates":[-91.739552,45.508907],"type":"Point"}
}