{
  "type": "Feature",
  "properties": {
    "iso:country":"US",
    "sg:address":"113 Walker Dr",
    "sg:city":"Madison",
    "sg:classifiers":[
        {
            "category":"Professional",
            "subcategory":"Management & Consulting",
            "type":"Services"
        }
    ],
    "sg:phone":"+1 608 241 8803",
    "sg:postcode":"53714",
    "sg:province":"WI",
    "sg:tags":[
        "consultant",
        "business"
    ],
    "wof:name":"Entrepreneur's Source",
    "wof:placetype":"venue"
},
  "geometry": {"coordinates":[-89.299639,43.096769],"type":"Point"}
}