{
  "type": "Feature",
  "properties": {
    "iso:country":"US",
    "sg:address":"1423 Milwaukee Ave",
    "sg:city":"South Milwaukee",
    "sg:classifiers":[
        {
            "category":"Building & Trades",
            "subcategory":"Construction",
            "type":"Services"
        }
    ],
    "sg:phone":"+1 414 768 9757",
    "sg:postcode":"53172",
    "sg:province":"WI",
    "sg:tags":[
        "contractor"
    ],
    "wof:name":"Bosley Brothers Plastering LLC",
    "wof:placetype":"venue"
},
  "geometry": {"coordinates":[-87.870564,42.910832],"type":"Point"}
}