{
  "type": "Feature",
  "properties": {
    "iso:country":"US",
    "sg:address":"200 Patrick Blvd",
    "sg:city":"Brookfield",
    "sg:classifiers":[
        {
            "category":"Professional",
            "subcategory":"Employment Agencies",
            "type":"Services"
        }
    ],
    "sg:phone":"+1 262 879 0311",
    "sg:postcode":"53045",
    "sg:province":"WI",
    "sg:tags":[
        "modeling"
    ],
    "wof:name":"Mtm Model Talent Management",
    "wof:placetype":"venue"
},
  "geometry": {"coordinates":[-88.134923,43.034111],"type":"Point"}
}