{
  "type": "Feature",
  "properties": {
    "iso:country":"US",
    "sg:address":"6700 W Beloit Rd",
    "sg:city":"Milwaukee",
    "sg:classifiers":[
        {
            "category":"Real Estate",
            "subcategory":"Real Estate Services",
            "type":"Services"
        }
    ],
    "sg:phone":"+1 414 238 0625",
    "sg:postcode":"53219",
    "sg:province":"WI",
    "sg:tags":[
        "consultant",
        "housing",
        "referral"
    ],
    "wof:name":"Tri-Corp House",
    "wof:placetype":"venue"
},
  "geometry": {"coordinates":[-87.995628,43.00383],"type":"Point"}
}