{
  "type": "Feature",
  "properties": {
    "iso:country":"US",
    "sg:address":"603 2nd St",
    "sg:city":"Chetek",
    "sg:classifiers":[
        {
            "category":"Shopping",
            "subcategory":"Department Store",
            "type":"Retail Goods"
        }
    ],
    "sg:phone":"+1 715 924 3403",
    "sg:postcode":"54728",
    "sg:province":"WI",
    "sg:tags":[
        "shop"
    ],
    "wof:name":"Ben Franklin",
    "wof:placetype":"venue"
},
  "geometry": {"coordinates":[-91.651327,45.314837],"type":"Point"}
}