{
  "type": "Feature",
  "properties": {
    "iso:country":"US",
    "sg:address":"633 S Main St",
    "sg:city":"Deerfield",
    "sg:classifiers":[
        {
            "category":"Building & Trades",
            "subcategory":"Plumbing",
            "type":"Services"
        }
    ],
    "sg:phone":"+1 608 764 8649",
    "sg:postcode":"53531",
    "sg:province":"WI",
    "sg:tags":[
        "conditioning",
        "air",
        "system",
        "contractor"
    ],
    "wof:name":"Brown Heating & Air Cond",
    "wof:placetype":"venue"
},
  "geometry": {"coordinates":[-89.07674,43.045172],"type":"Point"}
}