{
  "type": "Feature",
  "properties": {
    "iso:country":"US",
    "sg:address":"4335 W Bradley Rd",
    "sg:city":"Milwaukee",
    "sg:classifiers":[
        {
            "category":"Food & Beverages",
            "subcategory":"Groceries & Convenience Stores",
            "type":"Retail Goods"
        }
    ],
    "sg:phone":"+1 414 355 5615",
    "sg:postcode":"53223",
    "sg:province":"WI",
    "sg:tags":[
        "product"
    ],
    "wof:name":"Brown Deer Country Foods Store",
    "wof:placetype":"venue"
},
  "geometry": {"coordinates":[-87.966157,43.163063],"type":"Point"}
}