{
  "type": "Feature",
  "properties": {
    "iso:country":"US",
    "sg:address":"916 Byrd Ave",
    "sg:city":"Neenah",
    "sg:classifiers":[
        {
            "category":"Manufacturing",
            "subcategory":"Printing",
            "type":"Manufacturing & Wholesale Goods"
        }
    ],
    "sg:phone":"+1 920 722 2486",
    "sg:postcode":"54956",
    "sg:province":"WI",
    "sg:tags":[
        "screen",
        "printer"
    ],
    "sg:website":"www.politicallawnsigns.com",
    "wof:name":"Cross & Oberlie",
    "wof:placetype":"venue"
},
  "geometry": {"coordinates":[-88.487101,44.163604],"type":"Point"}
}