{
  "type": "Feature",
  "properties": {
    "iso:country":"US",
    "sg:address":"7625 W Beloit Rd",
    "sg:city":"Milwaukee",
    "sg:classifiers":[
        {
            "category":"Restaurant",
            "type":"Food & Drink"
        }
    ],
    "sg:menulink":"http://www.allmenus.com/wi/west-allis/141615-peking-garden/menu/",
    "sg:phone":"+1 414 604 8888",
    "sg:postcode":"53219",
    "sg:province":"WI",
    "sg:tags":[
        "asian",
        "chinese"
    ],
    "wof:name":"Peking Garden",
    "wof:placetype":"venue"
},
  "geometry": {"coordinates":[-88.008121,42.996729],"type":"Point"}
}