{
  "type": "Feature",
  "properties": {
    "iso:country":"US",
    "sg:address":"7300 S 36th St",
    "sg:city":"Franklin",
    "sg:classifiers":[
        {
            "category":"Building & Trades",
            "subcategory":"Construction",
            "type":"Services"
        }
    ],
    "sg:phone":"+1 414 421 1836",
    "sg:postcode":"53132",
    "sg:province":"WI",
    "sg:tags":[
        "specializing",
        "finishing",
        "remodeling",
        "use"
    ],
    "wof:name":"Superior Surface Inc",
    "wof:placetype":"venue"
},
  "geometry": {"coordinates":[-87.961765,42.912802],"type":"Point"}
}