{
  "type": "Feature",
  "properties": {
    "iso:country":"US",
    "sg:address":"6122 N 76th St",
    "sg:city":"Milwaukee",
    "sg:classifiers":[
        {
            "category":"Retail",
            "subcategory":"Auto Repair",
            "type":"Services"
        }
    ],
    "sg:phone":"+1 414 527 0872",
    "sg:postcode":"53218",
    "sg:province":"WI",
    "sg:tags":[
        "wrecker"
    ],
    "wof:name":"Knights Towing Inc",
    "wof:placetype":"venue"
},
  "geometry": {"coordinates":[-88.00582300000001,43.129256],"type":"Point"}
}