{
  "type": "Feature",
  "properties": {
    "iso:country":"US",
    "sg:address":"1098 S Koeller St",
    "sg:city":"Oshkosh",
    "sg:classifiers":[
        {
            "category":"Shopping",
            "subcategory":"Optical Goods",
            "type":"Retail Goods"
        }
    ],
    "sg:phone":"+1 920 231 9380",
    "sg:postcode":"54902",
    "sg:province":"WI",
    "wof:name":"Pearle Vision",
    "wof:placetype":"venue"
},
  "geometry": {"coordinates":[-88.582089,43.999998],"type":"Point"}
}