{
  "type": "Feature",
  "properties": {
    "iso:country":"US",
    "sg:address":"1660 96th St",
    "sg:city":"Sturtevant",
    "sg:classifiers":[
        {
            "category":"Wholesale",
            "subcategory":"Vending Machines",
            "type":"Manufacturing & Wholesale Goods"
        }
    ],
    "sg:phone":"+1 262 886 3520",
    "sg:postcode":"53177",
    "sg:province":"WI",
    "wof:name":"Scott Johnson",
    "wof:placetype":"venue"
},
  "geometry": {"coordinates":[-87.90240799999999,42.718129],"type":"Point"}
}