{
  "type": "Feature",
  "properties": {
    "iso:country":"US",
    "sg:address":"1116 Greenmeadow Dr",
    "sg:city":"Waukesha",
    "sg:classifiers":[
        {
            "category":"Insurance",
            "subcategory":"Insurance Agent",
            "type":"Services"
        }
    ],
    "sg:phone":"+1 262 650 7112",
    "sg:postcode":"53188",
    "sg:province":"WI",
    "wof:name":"Bend Mutual Insurance Co",
    "wof:placetype":"venue"
},
  "geometry": {"coordinates":[-88.262784,43.02615],"type":"Point"}
}