{
  "type": "Feature",
  "properties": {
    "iso:country":"US",
    "sg:address":"1201 W Wright St",
    "sg:city":"Milwaukee",
    "sg:classifiers":[
        {
            "category":"Bars & Pubs",
            "type":"Food & Drink"
        }
    ],
    "sg:phone":"+1 414 263 1200",
    "sg:postcode":"53206",
    "sg:province":"WI",
    "wof:name":"Kern's Penthouse",
    "wof:placetype":"venue"
},
  "geometry": {"coordinates":[-87.927657,43.063981],"type":"Point"}
}