{
  "type": "Feature",
  "properties": {
    "addr:full":"3522 Oakwood Hills Pkwy Eau Claire WI 54701",
    "addr:housenumber":"3522",
    "addr:postcode":"54701",
    "addr:street":"Oakwood Hills Pkwy",
    "iso:country":"US",
    "sg:address":"3522 Oakwood Hills Pkwy",
    "sg:city":"Eau Claire",
    "sg:classifiers":[
        {
            "category":"Health Services",
            "subcategory":"Doctor",
            "type":"Services"
        }
    ],
    "sg:phone":"+1 715 834 2004",
    "sg:postcode":"54701",
    "sg:province":"WI",
    "wof:name":"Machgan Family Dental",
    "wof:placetype":"venue"
},
  "geometry": {"coordinates":[-91.44758400000001,44.777767],"type":"Point"}
}