{
  "type": "Feature",
  "properties": {
    "iso:country":"US",
    "sg:address":"10803 Lundeen Rd",
    "sg:city":"Frederic",
    "sg:phone":"+1 715 327 8282",
    "sg:postcode":"54837",
    "sg:province":"WI",
    "sg:tags":[
        "farm",
        "field",
        "crop"
    ],
    "wof:name":"Walter Lundeen Farm",
    "wof:placetype":"venue"
},
  "geometry": {"coordinates":[-92.545843,45.670986],"type":"Point"}
}