{
  "type": "Feature",
  "properties": {
    "iso:country":"US",
    "sg:address":"4735 N 76th St",
    "sg:city":"Milwaukee",
    "sg:classifiers":[
        {
            "category":"Retail",
            "subcategory":"Auto Repair",
            "type":"Services"
        }
    ],
    "sg:phone":"+1 414 464 8037",
    "sg:postcode":"53218",
    "sg:province":"WI",
    "sg:tags":[
        "repairing",
        "automobile"
    ],
    "wof:name":"Humpties Auto Maintenance Inc",
    "wof:placetype":"venue"
},
  "geometry": {"coordinates":[-88.00674100000001,43.104336],"type":"Point"}
}