{
  "type": "Feature",
  "properties": {
    "iso:country":"US",
    "sg:address":"5200 Washington Ave",
    "sg:city":"Racine",
    "sg:classifiers":[
        {
            "category":"Insurance",
            "subcategory":"Insurance Agent",
            "type":"Services"
        }
    ],
    "sg:phone":"+1 262 637 4468",
    "sg:postcode":"53406",
    "sg:province":"WI",
    "sg:tags":[
        "agency"
    ],
    "wof:name":"Michael Graham Insurance",
    "wof:placetype":"venue"
},
  "geometry": {"coordinates":[-87.842967,42.71888],"type":"Point"}
}