{
  "type": "Feature",
  "properties": {
    "addr:full":"3831 W Mason St Oneida WI 54155",
    "addr:housenumber":"3831",
    "addr:postcode":"54155",
    "addr:street":"W Mason St",
    "iso:country":"US",
    "sg:address":"3831 W Mason St",
    "sg:city":"Oneida",
    "sg:classifiers":[
        {
            "category":"Manufacturing",
            "subcategory":"Tools & Machinery",
            "type":"Manufacturing & Wholesale Goods"
        }
    ],
    "sg:phone":"+1 920 869 1268",
    "sg:postcode":"54155",
    "sg:province":"WI",
    "sg:tags":[
        "machine",
        "shop"
    ],
    "wof:name":"S & M Tool & Production Co",
    "wof:placetype":"venue"
},
  "geometry": {"coordinates":[-88.158357,44.510835],"type":"Point"}
}