{
  "type": "Feature",
  "properties": {
    "iso:country":"US",
    "sg:address":"2451 Brenner Pl",
    "sg:city":"Green Bay",
    "sg:classifiers":[
        {
            "category":"Banks & Credit Unions",
            "subcategory":"Financial Services",
            "type":"Services"
        }
    ],
    "sg:phone":"+1 920 432 0732",
    "sg:postcode":"54301",
    "sg:province":"WI",
    "sg:tags":[
        "investor"
    ],
    "wof:name":"Christoph Investments",
    "wof:placetype":"venue"
},
  "geometry": {"coordinates":[-88.021194,44.474921],"type":"Point"}
}