{
  "type": "Feature",
  "properties": {
    "addr:full":"1206 Industrial Blvd Chippewa Falls WI 54729",
    "addr:housenumber":"1206",
    "addr:postcode":"54729",
    "addr:street":"Industrial Blvd",
    "iso:country":"US",
    "sg:address":"1206 Industrial Blvd",
    "sg:city":"Chippewa Falls",
    "sg:classifiers":[
        {
            "category":"Professional",
            "subcategory":"Secretarial Services",
            "type":"Services"
        }
    ],
    "sg:phone":"+1 715 726 1017",
    "sg:postcode":"54729",
    "sg:province":"WI",
    "sg:tags":[
        "reporting"
    ],
    "wof:name":"Motion Pixels",
    "wof:placetype":"venue"
},
  "geometry": {"coordinates":[-91.36972900000001,44.935319],"type":"Point"}
}