{
  "type": "Feature",
  "properties": {
    "iso:country":"US",
    "sg:address":"13364 Lake Maria Rd",
    "sg:city":"Waupun",
    "sg:classifiers":[
        {
            "category":"Farming",
            "subcategory":"Dairy Farm",
            "type":"Manufacturing & Wholesale Goods"
        }
    ],
    "sg:phone":"+1 920 346 2361",
    "sg:postcode":"53963",
    "sg:province":"WI",
    "wof:name":"Cal Greenfield",
    "wof:placetype":"venue"
},
  "geometry": {"coordinates":[-88.833315,43.661971],"type":"Point"}
}