{
  "type": "Feature",
  "properties": {
    "iso:country":"US",
    "sg:address":"7155 Elm Ct",
    "sg:city":"Holmen",
    "sg:classifiers":[
        {
            "category":"Freight",
            "type":"Transportation"
        }
    ],
    "sg:phone":"+1 608 781 5617",
    "sg:postcode":"54636",
    "sg:province":"WI",
    "sg:tags":[
        "warehouse",
        "public"
    ],
    "wof:name":"H & L",
    "wof:placetype":"venue"
},
  "geometry": {"coordinates":[-91.31218800000001,43.980366],"type":"Point"}
}