{
  "type": "Feature",
  "properties": {
    "iso:country":"US",
    "sg:address":"2904 W Wells St",
    "sg:city":"Milwaukee",
    "sg:classifiers":[
        {
            "category":"Organizations",
            "subcategory":"Religious Organization",
            "type":"Services"
        }
    ],
    "sg:phone":"+1 414 342 5959",
    "sg:postcode":"53208",
    "sg:province":"WI",
    "wof:name":"Wisconsin Nzrene Cmpssnate Ctr",
    "wof:placetype":"venue"
},
  "geometry": {"coordinates":[-87.953118,43.040363],"type":"Point"}
}