{
  "type": "Feature",
  "properties": {
    "iso:country":"US",
    "sg:address":"5703 Bailey Rd",
    "sg:city":"Delavan",
    "sg:classifiers":[
        {
            "category":"Building & Trades",
            "subcategory":"Construction",
            "type":"Services"
        }
    ],
    "sg:phone":"+1 262 728 2425",
    "sg:postcode":"53115",
    "sg:province":"WI",
    "sg:tags":[
        "excavating",
        "sewer",
        "line"
    ],
    "wof:name":"Williams Enterprises Inc",
    "wof:placetype":"venue"
},
  "geometry": {"coordinates":[-88.594833,42.597027],"type":"Point"}
}