{
  "type": "Feature",
  "properties": {
    "iso:country":"US",
    "sg:address":"121 S Main St",
    "sg:city":"Mayville",
    "sg:classifiers":[
        {
            "category":"Bars & Pubs",
            "type":"Food & Drink"
        }
    ],
    "sg:phone":"+1 920 387 5560",
    "sg:postcode":"53050",
    "sg:province":"WI",
    "wof:name":"Jimmy K's",
    "wof:placetype":"venue"
},
  "geometry": {"coordinates":[-88.544198,43.494043],"type":"Point"}
}