{
  "type": "Feature",
  "properties": {
    "iso:country":"US",
    "sg:address":"422 Jenniton Ave",
    "sg:city":"Barneveld",
    "sg:classifiers":[
        {
            "category":"Building & Trades",
            "subcategory":"Construction",
            "type":"Services"
        }
    ],
    "sg:phone":"+1 608 924 3026",
    "sg:postcode":"53507",
    "sg:province":"WI",
    "sg:tags":[
        "floor",
        "laying",
        "contractor"
    ],
    "wof:name":"Twin Oaks Flooring Inc",
    "wof:placetype":"venue"
},
  "geometry": {"coordinates":[-89.90005600000001,43.012922],"type":"Point"}
}