{
  "type": "Feature",
  "properties": {
    "iso:country":"US",
    "sg:address":"5411 Lonesome Pine Rd",
    "sg:city":"Sheboygan",
    "sg:classifiers":[
        {
            "category":"Building & Trades",
            "subcategory":"Construction",
            "type":"Services"
        }
    ],
    "sg:phone":"+1 920 803 9528",
    "sg:postcode":"53081",
    "sg:province":"WI",
    "sg:tags":[
        "bathroom",
        "remodeling"
    ],
    "wof:name":"Jerry Gruenke Building",
    "wof:placetype":"venue"
},
  "geometry": {"coordinates":[-87.712817,43.692335],"type":"Point"}
}