{
  "type": "Feature",
  "properties": {
    "addr:full":"741 River Oaks Trl Mosinee WI 54455",
    "addr:housenumber":"741",
    "addr:postcode":"54455",
    "addr:street":"River Oaks Trl",
    "iso:country":"US",
    "sg:address":"741 River Oaks Trl",
    "sg:city":"Mosinee",
    "sg:classifiers":[
        {
            "category":"Home & Garden",
            "subcategory":"Building Materials",
            "type":"Retail Goods"
        }
    ],
    "sg:phone":"+1 715 693 0730",
    "sg:postcode":"54455",
    "sg:province":"WI",
    "wof:name":"Ney Inc",
    "wof:placetype":"venue"
},
  "geometry": {"coordinates":[-89.677836,44.83181],"type":"Point"}
}