{
  "type": "Feature",
  "properties": {
    "iso:country":"US",
    "sg:address":"719 Cameron Cir",
    "sg:city":"Hartland",
    "sg:classifiers":[
        {
            "category":"Shopping",
            "type":"Retail Goods"
        }
    ],
    "sg:phone":"+1 262 367 8214",
    "sg:postcode":"53029",
    "sg:province":"WI",
    "sg:tags":[
        "merchandise"
    ],
    "wof:name":"Concept Solution Innovation LL",
    "wof:placetype":"venue"
},
  "geometry": {"coordinates":[-88.33317,43.093742],"type":"Point"}
}