{
  "type": "Feature",
  "properties": {
    "iso:country":"US",
    "sg:address":"7514 W Lincoln Ave",
    "sg:city":"Milwaukee",
    "sg:classifiers":[
        {
            "category":"Shopping",
            "subcategory":"Gifts & Souvenirs",
            "type":"Retail Goods"
        }
    ],
    "sg:phone":"+1 414 329 0883",
    "sg:postcode":"53219",
    "sg:province":"WI",
    "sg:tags":[
        "shop"
    ],
    "wof:name":"Real World Products",
    "wof:placetype":"venue"
},
  "geometry": {"coordinates":[-88.007336,43.002881],"type":"Point"}
}