{
  "type": "Feature",
  "properties": {
    "iso:country":"US",
    "sg:address":"724 W Main St",
    "sg:city":"Lake Geneva",
    "sg:classifiers":[
        {
            "category":"Restaurant",
            "type":"Food & Drink"
        }
    ],
    "sg:phone":"+1 262 249 0660",
    "sg:postcode":"53147",
    "sg:province":"WI",
    "wof:name":"Mia Bella Bistro",
    "wof:placetype":"venue"
},
  "geometry": {"coordinates":[-88.43494,42.591654],"type":"Point"}
}