{
  "type": "Feature",
  "properties": {
    "iso:country":"US",
    "sg:address":"1011 Maple Ridge Rd",
    "sg:city":"Mosinee",
    "sg:classifiers":[
        {
            "category":"Professional",
            "subcategory":"Business Services",
            "type":"Services"
        }
    ],
    "sg:phone":"+1 715 693 6475",
    "sg:postcode":"54455",
    "sg:province":"WI",
    "wof:name":"White Star Testing LLC",
    "wof:placetype":"venue"
},
  "geometry": {"coordinates":[-89.66559599999999,44.811314],"type":"Point"}
}