{
  "type": "Feature",
  "properties": {
    "iso:country":"US",
    "sg:address":"245 N Metro Dr",
    "sg:city":"Appleton",
    "sg:classifiers":[
        {
            "category":"Shopping",
            "type":"Retail Goods"
        }
    ],
    "sg:phone":"+1 920 749 1685",
    "sg:postcode":"54913",
    "sg:province":"WI",
    "sg:tags":[
        "art",
        "gallery",
        "dealer"
    ],
    "wof:name":"Autum Galleries LLC",
    "wof:placetype":"venue"
},
  "geometry": {"coordinates":[-88.473429,44.265068],"type":"Point"}
}