{
  "type": "Feature",
  "properties": {
    "iso:country":"US",
    "sg:address":"5020 Milwaukee St",
    "sg:city":"Madison",
    "sg:classifiers":[
        {
            "category":"Building & Trades",
            "subcategory":"Landscaping Services",
            "type":"Services"
        }
    ],
    "sg:phone":"+1 608 242 7795",
    "sg:postcode":"53714",
    "sg:province":"WI",
    "wof:name":"Lawn & Snow",
    "wof:placetype":"venue"
},
  "geometry": {"coordinates":[-89.295945,43.099],"type":"Point"}
}