{
  "type": "Feature",
  "properties": {
    "addr:full":"3309 Brookside Dr Pulaski WI 54162",
    "addr:housenumber":"3309",
    "addr:postcode":"54162",
    "addr:street":"Brookside Dr",
    "iso:country":"US",
    "sg:address":"3309 Brookside Dr",
    "sg:city":"Pulaski",
    "sg:classifiers":[
        {
            "category":"Shopping",
            "subcategory":"Computers & Home Electronics",
            "type":"Retail Goods"
        }
    ],
    "sg:phone":"+1 920 822 5943",
    "sg:postcode":"54162",
    "sg:province":"WI",
    "wof:name":"Richard Olson",
    "wof:placetype":"venue"
},
  "geometry": {"coordinates":[-88.180522,44.633908],"type":"Point"}
}