{
  "type": "Feature",
  "properties": {
    "iso:country":"US",
    "sg:address":"4621 State Hwy 73 S",
    "sg:city":"Wisconsin Rapids",
    "sg:classifiers":[
        {
            "category":"Autos & Motor Vehicles",
            "subcategory":"Recreational Vehicle Sales",
            "type":"Retail Goods"
        }
    ],
    "sg:phone":"+1 715 325 5155",
    "sg:postcode":"54494",
    "sg:province":"WI",
    "sg:tags":[
        "travel",
        "trailer"
    ],
    "wof:name":"Knutson's Camping Ctr",
    "wof:placetype":"venue"
},
  "geometry": {"coordinates":[-89.767719,44.27674],"type":"Point"}
}