{
  "type": "Feature",
  "properties": {
    "addr:full":"242 W Court St Richland Center WI 53581",
    "addr:housenumber":"242",
    "addr:postcode":"53581",
    "addr:street":"W Court St",
    "iso:country":"US",
    "sg:address":"242 W Court St",
    "sg:city":"Richland Center",
    "sg:classifiers":[
        {
            "category":"Professional",
            "subcategory":"Accounting & Tax Preparation",
            "type":"Services"
        }
    ],
    "sg:phone":"+1 608 647 6357",
    "sg:postcode":"53581",
    "sg:province":"WI",
    "sg:tags":[
        "accountant"
    ],
    "wof:name":"Joseph L Halverson CPA SC",
    "wof:placetype":"venue"
},
  "geometry": {"coordinates":[-90.38749300000001,43.335609],"type":"Point"}
}