{
  "type": "Feature",
  "properties": {
    "addr:full":"8132 Taft Ave Bancroft WI 54921",
    "addr:housenumber":"8132",
    "addr:postcode":"54921",
    "addr:street":"Taft Ave",
    "iso:country":"US",
    "sg:address":"8132 Taft Ave",
    "sg:city":"Bancroft",
    "sg:classifiers":[
        {
            "category":"Building & Trades",
            "subcategory":"Landscaping Services",
            "type":"Services"
        }
    ],
    "sg:phone":"+1 715 335 4644",
    "sg:postcode":"54921",
    "sg:province":"WI",
    "sg:tags":[
        "landscape"
    ],
    "wof:name":"Buena Vista Landscaping",
    "wof:placetype":"venue"
},
  "geometry": {"coordinates":[-89.548997,44.3202],"type":"Point"}
}