{
  "type": "Feature",
  "properties": {
    "iso:country":"US",
    "sg:address":"11508 Co Rd Q",
    "sg:city":"Wausau",
    "sg:classifiers":[
        {
            "category":"Farming",
            "subcategory":"Dairy Farm",
            "type":"Manufacturing & Wholesale Goods"
        }
    ],
    "sg:phone":"+1 715 446 3532",
    "sg:postcode":"54403",
    "sg:province":"WI",
    "wof:name":"Weden Dairy Farm",
    "wof:placetype":"venue"
},
  "geometry": {"coordinates":[-89.427758,45.068419],"type":"Point"}
}