{
  "type": "Feature",
  "properties": {
    "iso:country":"US",
    "sg:address":"3131 Lockwood Blvd",
    "sg:city":"Lake Geneva",
    "sg:classifiers":[
        {
            "category":"Building & Trades",
            "subcategory":"Electrical",
            "type":"Services"
        }
    ],
    "sg:phone":"+1 262 248 3284",
    "sg:postcode":"53147",
    "sg:province":"WI",
    "sg:tags":[
        "installation"
    ],
    "wof:name":"Bob Brown Installations",
    "wof:placetype":"venue"
},
  "geometry": {"coordinates":[-88.417555,42.591719],"type":"Point"}
}