{
  "type": "Feature",
  "properties": {
    "addr:full":"1143 College Ave Racine WI 53403",
    "addr:housenumber":"1143",
    "addr:postcode":"53403",
    "addr:street":"College Ave",
    "iso:country":"US",
    "sg:address":"1143 College Ave",
    "sg:city":"Racine",
    "sg:classifiers":[
        {
            "category":"Organizations",
            "subcategory":"Religious Organization",
            "type":"Services"
        }
    ],
    "sg:phone":"+1 262 633 6039",
    "sg:postcode":"53403",
    "sg:province":"WI",
    "sg:website":"www.plymouthracine.org",
    "wof:name":"Plymouth Congregational Church",
    "wof:placetype":"venue"
},
  "geometry": {"coordinates":[-87.78474,42.719157],"type":"Point"}
}