{
  "type": "Feature",
  "properties": {
    "iso:country":"US",
    "sg:address":"203 Calvary St",
    "sg:city":"Mt Calvary",
    "sg:classifiers":[
        {
            "category":"Retail",
            "subcategory":"Portrait Studio",
            "type":"Services"
        }
    ],
    "sg:phone":"+1 920 753 5302",
    "sg:postcode":"53057",
    "sg:province":"WI",
    "sg:tags":[
        "photographer"
    ],
    "sg:website":"www.guellerphoto.com",
    "wof:name":"Gueller's Photography",
    "wof:placetype":"venue"
},
  "geometry": {"coordinates":[-88.24173399999999,43.826757],"type":"Point"}
}