{
  "type": "Feature",
  "properties": {
    "iso:country":"US",
    "sg:address":"11823 Old Green Bay Rd",
    "sg:city":"Pleasant Prairie",
    "sg:classifiers":[
        {
            "category":"Professional",
            "subcategory":"Business Services",
            "type":"Services"
        }
    ],
    "sg:phone":"+1 262 694 4752",
    "sg:postcode":"53158",
    "sg:province":"IL",
    "wof:name":"D Marotti",
    "wof:placetype":"venue"
},
  "geometry": {"coordinates":[-87.887718,42.507634],"type":"Point"}
}