{
  "type": "Feature",
  "properties": {
    "iso:country":"US",
    "sg:address":"740 Pilgrim Pkwy",
    "sg:city":"Elm Grove",
    "sg:classifiers":[
        {
            "category":"Professional",
            "subcategory":"Management & Consulting",
            "type":"Services"
        }
    ],
    "sg:phone":"+1 262 860 8704",
    "sg:postcode":"53122",
    "sg:province":"WI",
    "wof:name":"Guenter Bergmann Investment",
    "wof:placetype":"venue"
},
  "geometry": {"coordinates":[-88.106174,43.042243],"type":"Point"}
}