{
  "type": "Feature",
  "properties": {
    "iso:country":"US",
    "sg:address":"740 Indian Spring Dr",
    "sg:city":"Delafield",
    "sg:classifiers":[
        {
            "category":"Building & Trades",
            "subcategory":"Construction",
            "type":"Services"
        }
    ],
    "sg:phone":"+1 262 646 8971",
    "sg:postcode":"53018",
    "sg:province":"WI",
    "sg:tags":[
        "contractor"
    ],
    "wof:name":"Opportunity Homes Inc",
    "wof:placetype":"venue"
},
  "geometry": {"coordinates":[-88.395248,43.05326],"type":"Point"}
}