{
  "type": "Feature",
  "properties": {
    "addr:full":"3846 W Wisconsin Ave Milwaukee WI 53208",
    "addr:housenumber":"3846",
    "addr:postcode":"53208",
    "addr:street":"W Wisconsin Ave",
    "iso:country":"US",
    "sg:address":"3846 W Wisconsin Ave",
    "sg:city":"Milwaukee",
    "sg:classifiers":[
        {
            "category":"Organizations",
            "subcategory":"Community Association",
            "type":"Services"
        }
    ],
    "sg:phone":"+1 414 344 9112",
    "sg:postcode":"53208",
    "sg:province":"WI",
    "sg:tags":[
        "fraternal"
    ],
    "wof:name":"Rosicrucian Order Amorc",
    "wof:placetype":"venue"
},
  "geometry": {"coordinates":[-87.96216200000001,43.038869],"type":"Point"}
}