{
  "type": "Feature",
  "properties": {
    "addr:full":"1575 N Rivercenter Dr Milwaukee WI 53212",
    "addr:housenumber":"1575",
    "addr:postcode":"53212",
    "addr:street":"N Rivercenter Dr",
    "iso:country":"US",
    "sg:address":"1575 N Rivercenter Dr",
    "sg:city":"Milwaukee",
    "sg:classifiers":[
        {
            "category":"Shopping",
            "subcategory":"Pharmacy",
            "type":"Retail Goods"
        }
    ],
    "sg:phone":"+1 414 224 1555",
    "sg:postcode":"53212",
    "sg:province":"WI",
    "wof:name":"Newtowne Pharmacy",
    "wof:placetype":"venue"
},
  "geometry": {"coordinates":[-87.908963,43.050895],"type":"Point"}
}