{
  "type": "Feature",
  "properties": {
    "iso:country":"US",
    "sg:address":"12833 W Glendale Ave",
    "sg:city":"Butler",
    "sg:classifiers":[
        {
            "category":"Wholesale",
            "subcategory":"Machinery & Supplies",
            "type":"Manufacturing & Wholesale Goods"
        }
    ],
    "sg:phone":"+1 262 783 6868",
    "sg:postcode":"53007",
    "sg:province":"WI",
    "sg:tags":[
        "distributor",
        "turf",
        "industrial",
        "equipment"
    ],
    "wof:name":"White Bear Turf & Indus LLC",
    "wof:placetype":"venue"
},
  "geometry": {"coordinates":[-88.073852,43.100384],"type":"Point"}
}