{
  "type": "Feature",
  "properties": {
    "iso:country":"US",
    "sg:address":"231 W Cornelia St",
    "sg:city":"Darlington",
    "sg:classifiers":[
        {
            "category":"Building & Trades",
            "subcategory":"Electrical",
            "type":"Services"
        }
    ],
    "sg:phone":"+1 608 776 2294",
    "sg:postcode":"53530",
    "sg:province":"WI",
    "sg:tags":[
        "electric",
        "contractor"
    ],
    "wof:name":"Tuescher Electric & Refrig",
    "wof:placetype":"venue"
},
  "geometry": {"coordinates":[-90.119651,42.68098],"type":"Point"}
}