{
  "type": "Feature",
  "properties": {
    "iso:country":"US",
    "sg:address":"520 Edward Dr",
    "sg:city":"Green Bay",
    "sg:classifiers":[
        {
            "category":"Professional",
            "subcategory":"Management & Consulting",
            "type":"Services"
        }
    ],
    "sg:phone":"+1 920 465 0915",
    "sg:postcode":"54302",
    "sg:province":"WI",
    "sg:tags":[
        "business"
    ],
    "wof:name":"Bewabic Group Inc",
    "wof:placetype":"venue"
},
  "geometry": {"coordinates":[-87.943894,44.489475],"type":"Point"}
}