{
  "type": "Feature",
  "properties": {
    "iso:country":"US",
    "sg:address":"314 S Park Ave",
    "sg:city":"South Beloit",
    "sg:classifiers":[
        {
            "category":"Restaurant",
            "type":"Food & Drink"
        }
    ],
    "sg:phone":"+1 815 389 9959",
    "sg:postcode":"61080",
    "sg:province":"WI",
    "wof:name":"K's South Park Cafe",
    "wof:placetype":"venue"
},
  "geometry": {"coordinates":[-89.02696400000001,42.492959],"type":"Point"}
}