{
  "type": "Feature",
  "properties": {
    "iso:country":"US",
    "sg:address":"308 Douglas St",
    "sg:city":"Merrill",
    "sg:classifiers":[
        {
            "category":"Home & Garden",
            "subcategory":"Home Furnishings",
            "type":"Retail Goods"
        }
    ],
    "sg:phone":"+1 715 536 1441",
    "sg:postcode":"54452",
    "sg:province":"WI",
    "wof:name":"Alumitech",
    "wof:placetype":"venue"
},
  "geometry": {"coordinates":[-89.695384,45.183221],"type":"Point"}
}