{
  "type": "Feature",
  "properties": {
    "iso:country":"US",
    "sg:address":"2414 Mercantile Dr",
    "sg:city":"Eau Claire",
    "sg:classifiers":[
        {
            "category":"Banks & Credit Unions",
            "subcategory":"Bank",
            "type":"Services"
        }
    ],
    "sg:phone":"+1 715 836 1515",
    "sg:postcode":"54703",
    "sg:province":"WI",
    "sg:website":"www.wellsfargo.com",
    "wof:name":"Wells Fargo Bank",
    "wof:placetype":"venue"
},
  "geometry": {"coordinates":[-91.54476,44.824914],"type":"Point"}
}