{
  "type": "Feature",
  "properties": {
    "iso:country":"US",
    "sg:address":"4079 Sandy Hook Rd",
    "sg:city":"Hazel Green",
    "sg:classifiers":[
        {
            "category":"Building & Trades",
            "subcategory":"Construction",
            "type":"Services"
        }
    ],
    "sg:phone":"+1 608 748 5042",
    "sg:postcode":"53811",
    "sg:province":"WI",
    "sg:tags":[
        "contractor"
    ],
    "wof:name":"Kane Plastering",
    "wof:placetype":"venue"
},
  "geometry": {"coordinates":[-90.613207,42.544268],"type":"Point"}
}