{
  "type": "Feature",
  "properties": {
    "iso:country":"US",
    "sg:address":"1150 N Main St",
    "sg:city":"River Falls",
    "sg:classifiers":[
        {
            "category":"Banks & Credit Unions",
            "subcategory":"Bank",
            "type":"Services"
        }
    ],
    "sg:phone":"+1 715 425 6811",
    "sg:postcode":"54022",
    "sg:province":"WI",
    "wof:name":"S & C Bank",
    "wof:placetype":"venue"
},
  "geometry": {"coordinates":[-92.622185,44.87498],"type":"Point"}
}