{
  "type": "Feature",
  "properties": {
    "iso:country":"US",
    "sg:address":"4120 Brandywine Ave",
    "sg:city":"Racine",
    "sg:classifiers":[
        {
            "category":"Building & Trades",
            "subcategory":"Construction",
            "type":"Services"
        }
    ],
    "sg:phone":"+1 262 639 9101",
    "sg:postcode":"53404",
    "sg:province":"WI",
    "sg:tags":[
        "house"
    ],
    "wof:name":"Lackeys Home Repair",
    "wof:placetype":"venue"
},
  "geometry": {"coordinates":[-87.819568,42.772638],"type":"Point"}
}