{
  "type": "Feature",
  "properties": {
    "iso:country":"US",
    "sg:address":"10550 Main St",
    "sg:city":"Hayward",
    "sg:classifiers":[
        {
            "category":"Shopping",
            "subcategory":"Department Store",
            "type":"Retail Goods"
        }
    ],
    "sg:phone":"+1 715 634 4909",
    "sg:postcode":"54843",
    "sg:province":"WI",
    "sg:tags":[
        "shop"
    ],
    "wof:name":"Ben Franklin",
    "wof:placetype":"venue"
},
  "geometry": {"coordinates":[-91.484046,46.014088],"type":"Point"}
}