{
  "type": "Feature",
  "properties": {
    "addr:full":"2546 Main St East Troy WI 53120",
    "addr:housenumber":"2546",
    "addr:postcode":"53120",
    "addr:street":"Main St",
    "iso:country":"US",
    "sg:address":"2546 Main St",
    "sg:city":"East Troy",
    "sg:classifiers":[
        {
            "category":"Banks & Credit Unions",
            "subcategory":"Bank",
            "type":"Services"
        }
    ],
    "sg:phone":"+1 262 642 2530",
    "sg:postcode":"53120",
    "sg:province":"WI",
    "sg:website":"www.firstcitizensww.com",
    "wof:name":"First Citizens State Bank",
    "wof:placetype":"venue"
},
  "geometry": {"coordinates":[-88.39335199999999,42.79046],"type":"Point"}
}