{
  "type": "Feature",
  "properties": {
    "iso:country":"US",
    "sg:address":"2688 Trojan Dr",
    "sg:city":"Green Bay",
    "sg:classifiers":[
        {
            "category":"Insurance",
            "subcategory":"Insurance Agent",
            "type":"Services"
        }
    ],
    "sg:phone":"+1 920 409 9438",
    "sg:postcode":"54304",
    "sg:province":"WI",
    "sg:tags":[
        "accident"
    ],
    "wof:name":"American Republic Insurance Co",
    "wof:placetype":"venue"
},
  "geometry": {"coordinates":[-88.099974,44.521555],"type":"Point"}
}