{
  "type": "Feature",
  "properties": {
    "iso:country":"US",
    "sg:address":"15856 E 5th St",
    "sg:city":"Hayward",
    "sg:classifiers":[
        {
            "category":"Social Services",
            "subcategory":"Adult Care",
            "type":"Services"
        }
    ],
    "sg:phone":"+1 715 634 4680",
    "sg:postcode":"54843",
    "sg:province":"WI",
    "sg:tags":[
        "organization",
        "senior",
        "citizen"
    ],
    "wof:name":"Hayward Senior Ctr",
    "wof:placetype":"venue"
},
  "geometry": {"coordinates":[-91.486169,46.017409],"type":"Point"}
}