{
  "type": "Feature",
  "properties": {
    "addr:full":"4740 S Nicholson Ave Cudahy WI 53110",
    "addr:housenumber":"4740",
    "addr:postcode":"53110",
    "addr:street":"S Nicholson Ave",
    "iso:country":"US",
    "sg:address":"4740 S Nicholson Ave",
    "sg:city":"Cudahy",
    "sg:classifiers":[
        {
            "category":"Manufacturing",
            "subcategory":"Tools & Machinery",
            "type":"Manufacturing & Wholesale Goods"
        }
    ],
    "sg:phone":"+1 414 769 2960",
    "sg:postcode":"53110",
    "sg:province":"WI",
    "sg:tags":[
        "food",
        "product",
        "mfg"
    ],
    "wof:name":"Scott Technologies Inc",
    "wof:placetype":"venue"
},
  "geometry": {"coordinates":[-87.86989199999999,42.955666],"type":"Point"}
}