{
  "type": "Feature",
  "properties": {
    "iso:country":"US",
    "sg:address":"1814 Ward Ave",
    "sg:city":"La Crosse",
    "sg:classifiers":[
        {
            "category":"Food & Beverages",
            "subcategory":"Specialty",
            "type":"Retail Goods"
        }
    ],
    "sg:phone":"+1 608 787 5252",
    "sg:postcode":"54601",
    "sg:province":"WI",
    "sg:tags":[
        "eating"
    ],
    "wof:name":"Java Detour",
    "wof:placetype":"venue"
},
  "geometry": {"coordinates":[-91.224429,43.783259],"type":"Point"}
}