{
  "type": "Feature",
  "properties": {
    "iso:country":"US",
    "sg:address":"1551 Southland Ave",
    "sg:city":"Oshkosh",
    "sg:classifiers":[
        {
            "category":"Health Services",
            "subcategory":"Nursing And Care Facility",
            "type":"Services"
        },
        {
            "category":"Social Services",
            "subcategory":"Adult Care",
            "type":"Services"
        }
    ],
    "sg:phone":"+1 920 235 5599",
    "sg:postcode":"54902",
    "sg:province":"WI",
    "sg:tags":[
        "home",
        "intermediate",
        "residential"
    ],
    "wof:name":"Elijah's Place",
    "wof:placetype":"venue"
},
  "geometry": {"coordinates":[-88.577298,44.021695],"type":"Point"}
}