{
  "type": "Feature",
  "properties": {
    "iso:country":"US",
    "sg:address":"222 Evergreen Blvd",
    "sg:city":"Cedarburg",
    "sg:classifiers":[
        {
            "category":"Professional",
            "subcategory":"Engineering",
            "type":"Services"
        }
    ],
    "sg:phone":"+1 262 377 9828",
    "sg:postcode":"53012",
    "sg:province":"WI",
    "wof:name":"Geo Syntec Consultants Inc",
    "wof:placetype":"venue"
},
  "geometry": {"coordinates":[-87.99414,43.28053],"type":"Point"}
}