{
  "type": "Feature",
  "properties": {
    "iso:country":"US",
    "sg:address":"2065 Donmar Ln",
    "sg:city":"Brookfield",
    "sg:classifiers":[
        {
            "category":"Organizations",
            "subcategory":"Community Association",
            "type":"Services"
        }
    ],
    "sg:phone":"+1 262 821 2044",
    "sg:postcode":"53005",
    "sg:province":"WI",
    "sg:tags":[
        "environmental",
        "org"
    ],
    "sg:website":"www.waukeshalandconservancy.org",
    "wof:name":"Waukesha Land Conservancy",
    "wof:placetype":"venue"
},
  "geometry": {"coordinates":[-88.115564,43.058227],"type":"Point"}
}