{
  "type": "Feature",
  "properties": {
    "iso:country":"US",
    "sg:address":"2008 State Rd 175",
    "sg:city":"Richfield",
    "sg:classifiers":[
        {
            "category":"Government",
            "subcategory":"Fire Station",
            "type":"Public Place"
        }
    ],
    "sg:phone":"+1 262 628 1601",
    "sg:postcode":"53076",
    "sg:province":"WI",
    "sg:tags":[
        "department"
    ],
    "wof:name":"Richfield Fire Dept",
    "wof:placetype":"venue"
},
  "geometry": {"coordinates":[-88.200567,43.265002],"type":"Point"}
}