{
  "type": "Feature",
  "properties": {
    "addr:full":"4029 Fairlane Ave Sparta WI 54656",
    "addr:housenumber":"4029",
    "addr:postcode":"54656",
    "addr:street":"Fairlane Ave",
    "iso:country":"US",
    "sg:address":"4029 Fairlane Ave",
    "sg:city":"Sparta",
    "sg:phone":"+1 608 269 3255",
    "sg:postcode":"54656",
    "sg:province":"WI",
    "sg:tags":[
        "farm",
        "corn",
        "dairy"
    ],
    "wof:name":"Haas Farm",
    "wof:placetype":"venue"
},
  "geometry": {"coordinates":[-90.912065,43.992709],"type":"Point"}
}