{
  "type": "Feature",
  "properties": {
    "iso:country":"US",
    "sg:address":"9602 State Line Rd",
    "sg:city":"Sharon",
    "sg:phone":"+1 262 736 4746",
    "sg:postcode":"53585",
    "sg:province":"WI",
    "sg:tags":[
        "farm",
        "corn",
        "soybean"
    ],
    "wof:name":"Ken Franseen",
    "wof:placetype":"venue"
},
  "geometry": {"coordinates":[-88.77450399999999,42.491996],"type":"Point"}
}