{
  "type": "Feature",
  "properties": {
    "addr:full":"1421 Washington Ave Racine WI 53403",
    "addr:housenumber":"1421",
    "addr:postcode":"53403",
    "addr:street":"Washington Ave",
    "iso:country":"US",
    "sg:address":"1421 Washington Ave",
    "sg:city":"Racine",
    "sg:classifiers":[
        {
            "category":"Health Services",
            "subcategory":"Optometrist",
            "type":"Services"
        }
    ],
    "sg:phone":"+1 262 637 7494",
    "sg:postcode":"53403",
    "sg:province":"WI",
    "wof:name":"Vision Clinic",
    "wof:placetype":"venue"
},
  "geometry": {"coordinates":[-87.79746,42.715166],"type":"Point"}
}