{
  "type": "Feature",
  "properties": {
    "iso:country":"US",
    "sg:address":"7702 Radcliffe Dr",
    "sg:city":"Madison",
    "sg:classifiers":[
        {
            "category":"Arts & Performance",
            "subcategory":"Theater",
            "type":"Entertainment"
        }
    ],
    "sg:phone":"+1 608 827 0378",
    "sg:postcode":"53719",
    "sg:province":"WI",
    "sg:tags":[
        "entertainer"
    ],
    "wof:name":"A Piper & A Kit",
    "wof:placetype":"venue"
},
  "geometry": {"coordinates":[-89.515978,43.0589],"type":"Point"}
}