{
  "type": "Feature",
  "properties": {
    "iso:country":"US",
    "sg:address":"2913 Coventry Ln",
    "sg:city":"Waukesha",
    "sg:classifiers":[
        {
            "category":"Communications",
            "subcategory":"Radio Station",
            "type":"Services"
        }
    ],
    "sg:phone":"+1 262 524 1010",
    "sg:postcode":"53188",
    "sg:province":"WI",
    "sg:tags":[
        "company",
        "broadcasting"
    ],
    "wof:name":"Starboard Media Foundation",
    "wof:placetype":"venue"
},
  "geometry": {"coordinates":[-88.282741,43.045862],"type":"Point"}
}