{
  "type": "Feature",
  "properties": {
    "iso:country":"US",
    "sg:address":"6103 Conservancy Way",
    "sg:city":"Fitchburg",
    "sg:classifiers":[
        {
            "category":"Professional",
            "subcategory":"Management & Consulting",
            "type":"Services"
        }
    ],
    "sg:phone":"+1 608 270 0377",
    "sg:postcode":"53719",
    "sg:province":"WI",
    "sg:tags":[
        "marketing",
        "consultant"
    ],
    "wof:name":"Marketrek Inc",
    "wof:placetype":"venue"
},
  "geometry": {"coordinates":[-89.458922,43.018032],"type":"Point"}
}