{
  "type": "Feature",
  "properties": {
    "iso:country":"US",
    "sg:address":"1200 E Singer Cir",
    "sg:city":"Milwaukee",
    "sg:classifiers":[
        {
            "category":"Real Estate",
            "subcategory":"Real Estate Operator",
            "type":"Services"
        }
    ],
    "sg:phone":"+1 414 964 1544",
    "sg:postcode":"53212",
    "sg:province":"WI",
    "sg:tags":[
        "apartment"
    ],
    "wof:name":"Riverwood Apartments",
    "wof:placetype":"venue"
},
  "geometry": {"coordinates":[-87.895112,43.084851],"type":"Point"}
}