{
  "type": "Feature",
  "properties": {
    "iso:country":"US",
    "sg:address":"581 E Fox Dale Rd",
    "sg:city":"Milwaukee",
    "sg:classifiers":[
        {
            "category":"Personal",
            "type":"Services"
        }
    ],
    "sg:phone":"+1 414 351 5154",
    "sg:postcode":"53217",
    "sg:province":"WI",
    "wof:name":"Joie Devie Inc",
    "wof:placetype":"venue"
},
  "geometry": {"coordinates":[-87.903158,43.14207],"type":"Point"}
}