{
  "type": "Feature",
  "properties": {
    "iso:country":"US",
    "sg:address":"10502 Swan Rd",
    "sg:city":"Reedsville",
    "sg:classifiers":[
        {
            "category":"Building & Trades",
            "subcategory":"Electrical",
            "type":"Services"
        }
    ],
    "sg:phone":"+1 920 864 7638",
    "sg:postcode":"54230",
    "sg:province":"WI",
    "sg:tags":[
        "electrical",
        "contractor"
    ],
    "wof:name":"Schwahn Electric",
    "wof:placetype":"venue"
},
  "geometry": {"coordinates":[-87.928951,44.224631],"type":"Point"}
}