{
  "type": "Feature",
  "properties": {
    "iso:country":"US",
    "sg:address":"5415 W Washington Blvd",
    "sg:city":"Milwaukee",
    "sg:classifiers":[
        {
            "category":"Banks & Credit Unions",
            "subcategory":"Financial Services",
            "type":"Services"
        }
    ],
    "sg:phone":"+1 414 476 0305",
    "sg:postcode":"53208",
    "sg:province":"WI",
    "sg:tags":[
        "investor"
    ],
    "wof:name":"Jlc Investments LLC",
    "wof:placetype":"venue"
},
  "geometry": {"coordinates":[-87.981961,43.052869],"type":"Point"}
}