{
  "type": "Feature",
  "properties": {
    "iso:country":"US",
    "sg:address":"103 N Hamilton St",
    "sg:city":"Madison",
    "sg:classifiers":[
        {
            "category":"Real Estate",
            "subcategory":"Real Estate Agent",
            "type":"Services"
        }
    ],
    "sg:phone":"+1 608 255 3976",
    "sg:postcode":"53703",
    "sg:province":"WI",
    "wof:name":"Mc Grath Assoc Inc",
    "wof:placetype":"venue"
},
  "geometry": {"coordinates":[-89.384016,43.077033],"type":"Point"}
}