{
  "type": "Feature",
  "properties": {
    "iso:country":"US",
    "sg:address":"12298 Cottonville Ave",
    "sg:city":"Coloma",
    "sg:classifiers":[
        {
            "category":"Farming",
            "subcategory":"Farm",
            "type":"Manufacturing & Wholesale Goods"
        }
    ],
    "sg:phone":"+1 715 228 3881",
    "sg:postcode":"54930",
    "sg:province":"WI",
    "wof:name":"Bing Farms",
    "wof:placetype":"venue"
},
  "geometry": {"coordinates":[-89.492059,44.054421],"type":"Point"}
}