{
  "type": "Feature",
  "properties": {
    "addr:full":"4331 Plover Rd Plover WI 54467",
    "addr:housenumber":"4331",
    "addr:postcode":"54467",
    "addr:street":"Plover Rd",
    "iso:country":"US",
    "sg:address":"4331 Plover Rd",
    "sg:city":"Plover",
    "sg:classifiers":[
        {
            "category":"Building & Trades",
            "subcategory":"Equipment Rental",
            "type":"Services"
        }
    ],
    "sg:phone":"+1 715 342 8775",
    "sg:postcode":"54467",
    "sg:province":"WI",
    "wof:name":"Traffic Signing & Marking",
    "wof:placetype":"venue"
},
  "geometry": {"coordinates":[-89.57441,44.454296],"type":"Point"}
}