{
  "type": "Feature",
  "properties": {
    "iso:country":"US",
    "sg:address":"6540 N 80th St",
    "sg:city":"Milwaukee",
    "sg:classifiers":[
        {
            "category":"Real Estate",
            "subcategory":"Real Estate Operator",
            "type":"Services"
        }
    ],
    "sg:phone":"+1 414 353 6817",
    "sg:postcode":"53223",
    "sg:province":"WI",
    "sg:tags":[
        "apartment"
    ],
    "wof:name":"St Peter's Apartments",
    "wof:placetype":"venue"
},
  "geometry": {"coordinates":[-88.01056199999999,43.137021],"type":"Point"}
}