{
  "type": "Feature",
  "properties": {
    "iso:country":"US",
    "sg:address":"9523 Pfiefer Rd",
    "sg:city":"Tomahawk",
    "sg:classifiers":[
        {
            "category":"Professional",
            "type":"Services"
        }
    ],
    "sg:phone":"+1 715 453 0026",
    "sg:postcode":"54487",
    "sg:province":"WI",
    "wof:name":"Headwaters Resources LLC",
    "wof:placetype":"venue"
},
  "geometry": {"coordinates":[-89.754118,45.46036],"type":"Point"}
}