{
  "type": "Feature",
  "properties": {
    "iso:country":"US",
    "sg:address":"5388 Graff Rd",
    "sg:city":"Eau Claire",
    "sg:phone":"+1 715 832 4424",
    "sg:postcode":"54701",
    "sg:province":"WI",
    "sg:tags":[
        "farm",
        "corn",
        "grain",
        "cash"
    ],
    "wof:name":"Graff Farm",
    "wof:placetype":"venue"
},
  "geometry": {"coordinates":[-91.42312699999999,44.754578],"type":"Point"}
}