{
  "type": "Feature",
  "properties": {
    "addr:full":"8860 S Shepard Ave Oak Creek WI 53154",
    "addr:housenumber":"8860",
    "addr:postcode":"53154",
    "addr:street":"S Shepard Ave",
    "iso:country":"US",
    "sg:address":"8860 S Shepard Ave",
    "sg:city":"Oak Creek",
    "sg:classifiers":[
        {
            "category":"Social Services",
            "subcategory":"Adult Care",
            "type":"Services"
        }
    ],
    "sg:phone":"+1 414 762 2321",
    "sg:postcode":"53154",
    "sg:province":"WI",
    "sg:tags":[
        "home",
        "group"
    ],
    "wof:name":"Shephard House",
    "wof:placetype":"venue"
},
  "geometry": {"coordinates":[-87.902344,42.882622],"type":"Point"}
}