{
  "type": "Feature",
  "properties": {
    "iso:country":"US",
    "sg:address":"36 Jewelers Park Dr",
    "sg:city":"Neenah",
    "sg:classifiers":[
        {
            "category":"Professional",
            "subcategory":"Lawyer & Legal Services",
            "type":"Services"
        }
    ],
    "sg:phone":"+1 920 725 8887",
    "sg:postcode":"54956",
    "sg:province":"WI",
    "wof:name":"Winkel Law Office",
    "wof:placetype":"venue"
},
  "geometry": {"coordinates":[-88.483953,44.156022],"type":"Point"}
}