{
  "type": "Feature",
  "properties": {
    "iso:country":"US",
    "sg:address":"3967 N Teutonia Ave",
    "sg:city":"Milwaukee",
    "sg:classifiers":[
        {
            "category":"Social Services",
            "subcategory":"Job Training",
            "type":"Services"
        },
        {
            "category":"Professional",
            "subcategory":"Employment Agencies",
            "type":"Services"
        }
    ],
    "sg:phone":"+1 414 445 9540",
    "sg:postcode":"53206",
    "sg:province":"WI",
    "sg:tags":[
        "opportunity"
    ],
    "wof:name":"Focus on Employment Opportunities INC",
    "wof:placetype":"venue"
},
  "geometry": {"coordinates":[-87.938638,43.089262],"type":"Point"}
}