{
  "type": "Feature",
  "properties": {
    "addr:full":"203 Water St Cambridge WI 53523",
    "addr:housenumber":"203",
    "addr:postcode":"53523",
    "addr:street":"Water St",
    "iso:country":"US",
    "sg:address":"203 Water St",
    "sg:city":"Cambridge",
    "sg:classifiers":[
        {
            "category":"Personal",
            "subcategory":"Beauty Salon",
            "type":"Services"
        }
    ],
    "sg:phone":"+1 608 423 1401",
    "sg:postcode":"53523",
    "sg:province":"WI",
    "sg:tags":[
        "manicuring"
    ],
    "wof:name":"Hair Expressions",
    "wof:placetype":"venue"
},
  "geometry": {"coordinates":[-89.031272,42.972492],"type":"Point"}
}