{
  "type": "Feature",
  "properties": {
    "iso:country":"US",
    "sg:address":"2156 Colladay Point Dr",
    "sg:city":"Stoughton",
    "sg:classifiers":[
        {
            "category":"Utilities",
            "subcategory":"Telephone",
            "type":"Services"
        }
    ],
    "sg:phone":"+1 608 873 0557",
    "sg:postcode":"53589",
    "sg:province":"WI",
    "sg:tags":[
        "communications",
        "datum"
    ],
    "wof:name":"Web Net",
    "wof:placetype":"venue"
},
  "geometry": {"coordinates":[-89.275504,42.963532],"type":"Point"}
}