{
  "type": "Feature",
  "properties": {
    "iso:country":"US",
    "sg:address":"5477 176th St",
    "sg:city":"Chippewa Falls",
    "sg:classifiers":[
        {
            "category":"Wholesale",
            "subcategory":"Hardware",
            "type":"Manufacturing & Wholesale Goods"
        },
        {
            "category":"Retail",
            "subcategory":"Repair Shop",
            "type":"Services"
        }
    ],
    "sg:phone":"+1 715 726 1640",
    "sg:postcode":"54729",
    "sg:province":"WI",
    "sg:tags":[
        "refrigeration",
        "refrigerating"
    ],
    "wof:name":"Gunther Refrigeration Service",
    "wof:placetype":"venue"
},
  "geometry": {"coordinates":[-91.316007,44.92287],"type":"Point"}
}