{
  "type": "Feature",
  "properties": {
    "iso:country":"US",
    "sg:address":"707 6th Ave",
    "sg:city":"Antigo",
    "sg:classifiers":[
        {
            "category":"Health Services",
            "subcategory":"Doctor",
            "type":"Services"
        }
    ],
    "sg:phone":"+1 715 627 4391",
    "sg:postcode":"54409",
    "sg:province":"WI",
    "sg:tags":[
        "dentist"
    ],
    "wof:name":"Antigo Dental Clinic",
    "wof:placetype":"venue"
},
  "geometry": {"coordinates":[-89.154218,45.139045],"type":"Point"}
}