{
  "type": "Feature",
  "properties": {
    "iso:country":"US",
    "sg:address":"539 Karl St",
    "sg:city":"Green Bay",
    "sg:classifiers":[
        {
            "category":"Real Estate",
            "subcategory":"Real Estate Services",
            "type":"Services"
        }
    ],
    "sg:phone":"+1 920 430 1510",
    "sg:postcode":"54301",
    "sg:province":"WI",
    "sg:tags":[
        "company",
        "title"
    ],
    "wof:name":"Title Town Truckers Showdown",
    "wof:placetype":"venue"
},
  "geometry": {"coordinates":[-88.00888399999999,44.479038],"type":"Point"}
}