{
  "type": "Feature",
  "properties": {
    "iso:country":"US",
    "sg:address":"5110 Esker Dr",
    "sg:city":"Madison",
    "sg:classifiers":[
        {
            "category":"Organizations",
            "subcategory":"Religious Organization",
            "type":"Services"
        }
    ],
    "sg:phone":"+1 608 442 6379",
    "sg:postcode":"53704",
    "sg:province":"WI",
    "wof:name":"Stir Up Gift Faith Youth Cente",
    "wof:placetype":"venue"
},
  "geometry": {"coordinates":[-89.292663,43.115647],"type":"Point"}
}