{
  "type": "Feature",
  "properties": {
    "addr:full":"10035 Xanadu Rd Wisconsin Dells WI 53965",
    "addr:postcode":"10035;53965",
    "addr:street":"Xanadu Rd",
    "iso:country":"US",
    "sg:address":"10035 Xanadu Rd",
    "sg:city":"Wisconsin Dells",
    "sg:classifiers":[
        {
            "category":"Travel",
            "subcategory":"Hotels & Motels",
            "type":"Entertainment"
        }
    ],
    "sg:phone":"+1 608 254 4929",
    "sg:postcode":"53965",
    "sg:province":"WI",
    "sg:tags":[
        "resort"
    ],
    "wof:name":"Peppertree At Tamarack Hoa",
    "wof:placetype":"venue"
},
  "geometry": {"coordinates":[-89.81982499999999,43.583182],"type":"Point"}
}