{
  "type": "Feature",
  "properties": {
    "iso:country":"US",
    "sg:address":"1007 Tyler St",
    "sg:city":"La Crosse",
    "sg:classifiers":[
        {
            "category":"Shopping",
            "subcategory":"Used Merchandise",
            "type":"Retail Goods"
        }
    ],
    "sg:phone":"+1 608 782 1455",
    "sg:postcode":"54601",
    "sg:province":"WI",
    "wof:name":"Linda A Olson",
    "wof:placetype":"venue"
},
  "geometry": {"coordinates":[-91.24124999999999,43.797013],"type":"Point"}
}