{
  "type": "Feature",
  "properties": {
    "iso:country":"US",
    "sg:address":"200 S Executive Dr",
    "sg:city":"Brookfield",
    "sg:classifiers":[
        {
            "category":"Home & Garden",
            "subcategory":"Household Appliances",
            "type":"Retail Goods"
        }
    ],
    "sg:phone":"+1 262 789 2748",
    "sg:postcode":"53005",
    "sg:province":"WI",
    "sg:tags":[
        "major",
        "appliances-small"
    ],
    "wof:name":"Network Appliance",
    "wof:placetype":"venue"
},
  "geometry": {"coordinates":[-88.11436500000001,43.030688],"type":"Point"}
}