{
  "type": "Feature",
  "properties": {
    "iso:country":"US",
    "sg:address":"7845 State Hwy 173",
    "sg:city":"Tomah",
    "sg:classifiers":[
        {
            "category":"Farming",
            "subcategory":"Berry Farm",
            "type":"Manufacturing & Wholesale Goods"
        }
    ],
    "sg:phone":"+1 608 372 5208",
    "sg:postcode":"54660",
    "sg:province":"WI",
    "sg:tags":[
        "grower",
        "cranberry"
    ],
    "wof:name":"Valley Corp",
    "wof:placetype":"venue"
},
  "geometry": {"coordinates":[-90.411235,44.05551],"type":"Point"}
}