{
  "type": "Feature",
  "properties": {
    "addr:full":"1026 Chestnut St West Bend WI 53095",
    "addr:housenumber":"1026",
    "addr:postcode":"53095",
    "addr:street":"Chestnut St",
    "iso:country":"US",
    "sg:address":"1026 Chestnut St",
    "sg:city":"West Bend",
    "sg:classifiers":[
        {
            "category":"Manufacturing",
            "subcategory":"Printing",
            "type":"Manufacturing & Wholesale Goods"
        }
    ],
    "sg:phone":"+1 262 306 2923",
    "sg:postcode":"53095",
    "sg:province":"WI",
    "sg:tags":[
        "book"
    ],
    "wof:name":"Now Publishing Inc",
    "wof:placetype":"venue"
},
  "geometry": {"coordinates":[-88.19036699999999,43.419698],"type":"Point"}
}