{
  "type": "Feature",
  "properties": {
    "iso:country":"US",
    "sg:address":"6241 Upper Pkwy N",
    "sg:city":"Milwaukee",
    "sg:classifiers":[
        {
            "category":"Education",
            "subcategory":"Special Training",
            "type":"Public Place"
        }
    ],
    "sg:phone":"+1 414 431 0873",
    "sg:postcode":"53213",
    "sg:province":"WI",
    "wof:name":"Art House",
    "wof:placetype":"venue"
},
  "geometry": {"coordinates":[-87.991462,43.054787],"type":"Point"}
}