{
  "type": "Feature",
  "properties": {
    "iso:country":"US",
    "sg:address":"11933 W Co Rd C",
    "sg:city":"Exeland",
    "sg:classifiers":[
        {
            "category":"Farming",
            "subcategory":"Dairy Farm",
            "type":"Manufacturing & Wholesale Goods"
        }
    ],
    "sg:phone":"+1 715 943 2417",
    "sg:postcode":"54835",
    "sg:province":"WI",
    "wof:name":"Autumn View",
    "wof:placetype":"venue"
},
  "geometry": {"coordinates":[-91.28217600000001,45.667923],"type":"Point"}
}