{
  "type": "Feature",
  "properties": {
    "iso:country":"US",
    "sg:address":"8184 N 44th St",
    "sg:city":"Milwaukee",
    "sg:classifiers":[
        {
            "category":"Building & Trades",
            "subcategory":"Construction",
            "type":"Services"
        }
    ],
    "sg:phone":"+1 414 354 2780",
    "sg:postcode":"53223",
    "sg:province":"WI",
    "sg:tags":[
        "hanging",
        "contractor"
    ],
    "wof:name":"Realty Maintenance Systems",
    "wof:placetype":"venue"
},
  "geometry": {"coordinates":[-87.96642,43.16725],"type":"Point"}
}