{
  "type": "Feature",
  "properties": {
    "addr:full":"600 N Springdale Rd Waukesha WI 53186",
    "addr:housenumber":"600",
    "addr:postcode":"53186",
    "addr:street":"N Springdale Rd",
    "iso:country":"US",
    "sg:address":"600 N Springdale Rd",
    "sg:city":"Waukesha",
    "sg:classifiers":[
        {
            "category":"Autos & Motor Vehicles",
            "subcategory":"Auto Supplies",
            "type":"Retail Goods"
        },
        {
            "category":"Shopping",
            "subcategory":"Discount & Variety Stores",
            "type":"Retail Goods"
        },
        {
            "category":"Food & Beverages",
            "subcategory":"Supermarket",
            "type":"Retail Goods"
        },
        {
            "category":"Shopping",
            "type":"Retail Goods"
        }
    ],
    "sg:phone":"+1 262 798 1490",
    "sg:postcode":"53186",
    "sg:province":"WI",
    "sg:tags":[
        "super",
        "merchandise",
        "tire"
    ],
    "sg:website":"http://www.samsclub.com",
    "wof:name":"Sam's Club",
    "wof:placetype":"venue"
},
  "geometry": {"coordinates":[-88.18592200000001,43.037911],"type":"Point"}
}