{
  "type": "Feature",
  "properties": {
    "iso:country":"US",
    "sg:address":"1 Reynolds Dr",
    "sg:city":"Beloit",
    "sg:classifiers":[
        {
            "category":"Autos & Motor Vehicles",
            "subcategory":"Auto Supplies",
            "type":"Retail Goods"
        }
    ],
    "sg:phone":"+1 608 363 5200",
    "sg:postcode":"53511",
    "sg:province":"IL",
    "sg:tags":[
        "wheel",
        "cover"
    ],
    "wof:name":"Reynolds Wheels Intl",
    "wof:placetype":"venue"
},
  "geometry": {"coordinates":[-88.983533,42.520953],"type":"Point"}
}