{
  "type": "Feature",
  "properties": {
    "iso:country":"US",
    "sg:address":"215 Pine Ave E",
    "sg:city":"Menomonie",
    "sg:classifiers":[
        {
            "category":"Education",
            "subcategory":"School",
            "type":"Public Place"
        }
    ],
    "sg:phone":"+1 715 232 1172",
    "sg:postcode":"54751",
    "sg:province":"WI",
    "wof:name":"Menonomie Special Education",
    "wof:placetype":"venue"
},
  "geometry": {"coordinates":[-91.930588,44.900906],"type":"Point"}
}