{
  "type": "Feature",
  "properties": {
    "iso:country":"US",
    "sg:address":"2306 N Peach Ave",
    "sg:city":"Marshfield",
    "sg:classifiers":[
        {
            "category":"Recreation",
            "type":"Entertainment"
        }
    ],
    "sg:phone":"+1 715 387 4077",
    "sg:postcode":"54449",
    "sg:province":"WI",
    "wof:name":"Sandpiper Sport Fishing LLC",
    "wof:placetype":"venue"
},
  "geometry": {"coordinates":[-90.159842,44.686562],"type":"Point"}
}