{
  "type": "Feature",
  "properties": {
    "iso:country":"US",
    "sg:address":"4707 Washington Rd",
    "sg:city":"Kenosha",
    "sg:classifiers":[
        {
            "category":"Health Services",
            "subcategory":"Dentist",
            "type":"Services"
        }
    ],
    "sg:phone":"+1 262 658 8466",
    "sg:postcode":"53144",
    "sg:province":"WI",
    "sg:tags":[
        "dentists-pediatric",
        "dentistry"
    ],
    "wof:name":"Purnima Swearingen-Children's Dentist",
    "wof:placetype":"venue"
},
  "geometry": {"coordinates":[-87.86564,42.603039],"type":"Point"}
}