{
  "type": "Feature",
  "properties": {
    "iso:country":"US",
    "sg:address":"3358 N 6th St",
    "sg:city":"Milwaukee",
    "sg:classifiers":[
        {
            "category":"Travel",
            "subcategory":"Travel Agent",
            "type":"Entertainment"
        }
    ],
    "sg:phone":"+1 414 265 5212",
    "sg:postcode":"53212",
    "sg:province":"WI",
    "sg:tags":[
        "operator",
        "tour"
    ],
    "wof:name":"L T S Top Line Motorcoach",
    "wof:placetype":"venue"
},
  "geometry": {"coordinates":[-87.918412,43.080808],"type":"Point"}
}