{
  "type": "Feature",
  "properties": {
    "iso:country":"US",
    "sg:address":"1856 Co Rd U",
    "sg:city":"Cochrane",
    "sg:classifiers":[
        {
            "category":"Manufacturing",
            "subcategory":"Food",
            "type":"Manufacturing & Wholesale Goods"
        }
    ],
    "sg:phone":"+1 608 626 2121",
    "sg:postcode":"54622",
    "sg:province":"WI",
    "sg:tags":[
        "cheese",
        "mfg",
        "milk",
        "fluid",
        "processor"
    ],
    "wof:name":"Foremost Farms USA",
    "wof:placetype":"venue"
},
  "geometry": {"coordinates":[-91.686737,44.326224],"type":"Point"}
}