{
  "type": "Feature",
  "properties": {
    "iso:country":"US",
    "sg:address":"10935 US Hwy 14",
    "sg:city":"Mazomanie",
    "sg:classifiers":[
        {
            "category":"Restaurant",
            "type":"Food & Drink"
        }
    ],
    "sg:phone":"+1 608 767 3750",
    "sg:postcode":"53560",
    "sg:province":"WI",
    "wof:name":"Lunch Bucket Cafe",
    "wof:placetype":"venue"
},
  "geometry": {"coordinates":[-89.82669300000001,43.163446],"type":"Point"}
}