{
  "type": "Feature",
  "properties": {
    "addr:full":"2518 Co Rd Jj Appleton WI 54913",
    "addr:housenumber":"2518",
    "addr:postcode":"54913",
    "addr:street":"Co Rd",
    "iso:country":"US",
    "sg:address":"2518 Co Rd Jj",
    "sg:city":"Appleton",
    "sg:classifiers":[
        {
            "category":"Retail",
            "subcategory":"Veterinary Services",
            "type":"Services"
        }
    ],
    "sg:phone":"+1 920 788 6391",
    "sg:postcode":"54913",
    "sg:province":"WI",
    "sg:tags":[
        "veterinarian"
    ],
    "wof:name":"Countryside Veterinary Svc",
    "wof:placetype":"venue"
},
  "geometry": {"coordinates":[-88.45433300000001,44.329635],"type":"Point"}
}