{
  "type": "Feature",
  "properties": {
    "iso:country":"US",
    "sg:address":"6823 Co Rd H",
    "sg:city":"Sturgeon Bay",
    "sg:classifiers":[
        {
            "category":"Retail",
            "subcategory":"Photofinishing",
            "type":"Services"
        }
    ],
    "sg:phone":"+1 920 856 6962",
    "sg:postcode":"54235",
    "sg:province":"WI",
    "sg:tags":[
        "laboratory"
    ],
    "wof:name":"Evergreen Photo",
    "wof:placetype":"venue"
},
  "geometry": {"coordinates":[-87.42505300000001,44.755261],"type":"Point"}
}