{
  "type": "Feature",
  "properties": {
    "iso:country":"US",
    "sg:address":"753 E Perkins St",
    "sg:city":"Medford",
    "sg:classifiers":[
        {
            "category":"Banks & Credit Unions",
            "subcategory":"Bank",
            "type":"Services"
        }
    ],
    "sg:phone":"+1 715 748 3270",
    "sg:postcode":"54451",
    "sg:province":"WI",
    "sg:tags":[
        "loan"
    ],
    "wof:name":"FCS Financial Svc",
    "wof:placetype":"venue"
},
  "geometry": {"coordinates":[-90.333939,45.134751],"type":"Point"}
}