{
  "type": "Feature",
  "properties": {
    "addr:full":"1760 Superior St Three Lakes WI 54562",
    "addr:housenumber":"1760",
    "addr:postcode":"54562",
    "addr:street":"Superior St",
    "iso:country":"US",
    "sg:address":"1760 Superior St",
    "sg:city":"Three Lakes",
    "sg:classifiers":[
        {
            "category":"Shopping",
            "subcategory":"Gifts & Souvenirs",
            "type":"Retail Goods"
        }
    ],
    "sg:phone":"+1 715 546 8141",
    "sg:postcode":"54562",
    "sg:province":"WI",
    "wof:name":"Hodge Podge Lodge",
    "wof:placetype":"venue"
},
  "geometry": {"coordinates":[-89.168277,45.798275],"type":"Point"}
}