{
  "type": "Feature",
  "properties": {
    "iso:country":"US",
    "sg:address":"2847 Hall Dr",
    "sg:city":"Medford",
    "sg:classifiers":[
        {
            "category":"Farming",
            "subcategory":"Dairy Farm",
            "type":"Manufacturing & Wholesale Goods"
        }
    ],
    "sg:phone":"+1 715 748 3629",
    "sg:postcode":"54451",
    "sg:province":"WI",
    "wof:name":"Jim Laher Farm",
    "wof:placetype":"venue"
},
  "geometry": {"coordinates":[-90.249574,45.133138],"type":"Point"}
}