{
  "type": "Feature",
  "properties": {
    "addr:full":"620 Co Rd E Grand Marsh WI 53936",
    "addr:housenumber":"620",
    "addr:postcode":"53936",
    "addr:street":"Co Rd E Grand Marsh",
    "iso:country":"US",
    "sg:address":"620 Co Rd E",
    "sg:city":"Grand Marsh",
    "sg:classifiers":[
        {
            "category":"Education",
            "subcategory":"School",
            "type":"Public Place"
        }
    ],
    "sg:phone":"+1 608 339 6556",
    "sg:postcode":"53936",
    "sg:province":"WI",
    "wof:name":"Grand Marsh School",
    "wof:placetype":"venue"
},
  "geometry": {"coordinates":[-89.637711,43.923246],"type":"Point"}
}