{
  "type": "Feature",
  "properties": {
    "addr:full":"5307 E Jelinek Ave Schofield WI 54476",
    "addr:housenumber":"5307",
    "addr:postcode":"54476",
    "addr:street":"E Jelinek Ave",
    "iso:country":"US",
    "sg:address":"5307 E Jelinek Ave",
    "sg:city":"Schofield",
    "sg:classifiers":[
        {
            "category":"Freight",
            "type":"Transportation"
        }
    ],
    "sg:phone":"+1 715 359 5781",
    "sg:postcode":"54476",
    "sg:province":"WI",
    "sg:tags":[
        "trucking"
    ],
    "wof:name":"Guite Transportation",
    "wof:placetype":"venue"
},
  "geometry": {"coordinates":[-89.558539,44.902019],"type":"Point"}
}