{
  "type": "Feature",
  "properties": {
    "iso:country":"US",
    "sg:address":"3976 Eagle Point Rd",
    "sg:city":"Kieler",
    "sg:classifiers":[
        {
            "category":"Sports & Exercise",
            "subcategory":"Golf",
            "type":"Entertainment"
        }
    ],
    "sg:phone":"+1 608 748 4743",
    "sg:postcode":"53811",
    "sg:province":"WI",
    "sg:tags":[
        "course"
    ],
    "wof:name":"Birchwood Golf & Development",
    "wof:placetype":"venue"
},
  "geometry": {"coordinates":[-90.61308099999999,42.550222],"type":"Point"}
}