{
  "type": "Feature",
  "properties": {
    "iso:country":"US",
    "sg:address":"500 E Washington St",
    "sg:city":"New London",
    "sg:classifiers":[
        {
            "category":"Social Services",
            "subcategory":"Adult Care",
            "type":"Services"
        }
    ],
    "sg:phone":"+1 920 982 5354",
    "sg:postcode":"54961",
    "sg:province":"WI",
    "sg:tags":[
        "home",
        "residential"
    ],
    "wof:name":"Washington Center",
    "wof:placetype":"venue"
},
  "geometry": {"coordinates":[-88.731102,44.386705],"type":"Point"}
}