{
  "type": "Feature",
  "properties": {
    "iso:country":"US",
    "sg:address":"232 Birch St",
    "sg:city":"Tigerton",
    "sg:classifiers":[
        {
            "category":"Government",
            "subcategory":"Post Office",
            "type":"Public Place"
        }
    ],
    "sg:phone":"+1 715 535 2152",
    "sg:postcode":"54486",
    "sg:province":"WI",
    "wof:name":"US Post Office",
    "wof:placetype":"venue"
},
  "geometry": {"coordinates":[-89.062583,44.741452],"type":"Point"}
}