{
  "type": "Feature",
  "properties": {
    "iso:country":"US",
    "sg:address":"3526 W Capitol Dr",
    "sg:city":"Milwaukee",
    "sg:classifiers":[
        {
            "category":"Personal",
            "subcategory":"Beauty Salon",
            "type":"Services"
        }
    ],
    "sg:phone":"+1 414 445 6022",
    "sg:postcode":"53216",
    "sg:province":"WI",
    "wof:name":"I'Munique's Hair Salon & Full",
    "wof:placetype":"venue"
},
  "geometry": {"coordinates":[-87.95836199999999,43.089855],"type":"Point"}
}