{
  "type": "Feature",
  "properties": {
    "addr:full":"141 E James St Columbus WI 53925",
    "addr:housenumber":"141",
    "addr:postcode":"53925",
    "addr:street":"E James St",
    "iso:country":"US",
    "sg:address":"141 E James St",
    "sg:city":"Columbus",
    "sg:classifiers":[
        {
            "category":"Home & Garden",
            "subcategory":"Home Furnishings",
            "type":"Retail Goods"
        }
    ],
    "sg:phone":"+1 920 623 2669",
    "sg:postcode":"53925",
    "sg:province":"WI",
    "sg:tags":[
        "used",
        "merchandise"
    ],
    "wof:name":"Antique Shoppes Of Columbus",
    "wof:placetype":"venue"
},
  "geometry": {"coordinates":[-89.01416500000001,43.338079],"type":"Point"}
}