{
  "type": "Feature",
  "properties": {
    "iso:country":"US",
    "sg:address":"106 S Main St",
    "sg:city":"Thiensville",
    "sg:classifiers":[
        {
            "category":"Shopping",
            "subcategory":"Music",
            "type":"Retail Goods"
        }
    ],
    "sg:phone":"+1 262 242 7600",
    "sg:postcode":"53092",
    "sg:province":"WI",
    "sg:tags":[
        "used",
        "tapes",
        "vintage",
        "records",
        "cd's",
        "dvd's",
        "store"
    ],
    "wof:name":"Stardust Records & Collectibles",
    "wof:placetype":"venue"
},
  "geometry": {"coordinates":[-87.98375799999999,43.230181],"type":"Point"}
}