{
  "type": "Feature",
  "properties": {
    "iso:country":"US",
    "sg:address":"4424 Rib Mountain Dr",
    "sg:city":"Wausau",
    "sg:classifiers":[
        {
            "category":"Personal",
            "subcategory":"Beauty Salon",
            "type":"Services"
        }
    ],
    "sg:phone":"+1 715 359 2724",
    "sg:postcode":"54401",
    "sg:province":"WI",
    "sg:tags":[
        "shop"
    ],
    "wof:name":"Fantastic Sam's",
    "wof:placetype":"venue"
},
  "geometry": {"coordinates":[-89.650593,44.918927],"type":"Point"}
}