{
  "type": "Feature",
  "properties": {
    "addr:full":"657 State Road 35 Osceola WI 54020",
    "addr:housenumber":"657",
    "addr:postcode":"54020",
    "addr:street":"State Road 35",
    "iso:country":"US",
    "sg:address":"657 State Road 35",
    "sg:city":"Osceola",
    "sg:classifiers":[
        {
            "category":"Utilities",
            "subcategory":"Electric",
            "type":"Services"
        },
        {
            "category":"Manufacturing",
            "subcategory":"Electronics",
            "type":"Manufacturing & Wholesale Goods"
        }
    ],
    "sg:phone":"+1 715 755 3970",
    "sg:postcode":"54020",
    "sg:province":"WI",
    "sg:tags":[
        "equipment-testing"
    ],
    "wof:name":"Personal Membership",
    "wof:placetype":"venue"
},
  "geometry": {"coordinates":[-92.697613,45.29867],"type":"Point"}
}