{
  "type": "Feature",
  "properties": {
    "addr:full":"9 Johnson St Waupun WI 53963",
    "addr:housenumber":"9",
    "addr:postcode":"53963",
    "addr:street":"Johnson St",
    "iso:country":"US",
    "sg:address":"9 Johnson St",
    "sg:city":"Waupun",
    "sg:classifiers":[
        {
            "category":"Retail",
            "subcategory":"Repair Shop",
            "type":"Services"
        }
    ],
    "sg:phone":"+1 920 324 2044",
    "sg:postcode":"53963",
    "sg:province":"WI",
    "sg:tags":[
        "lock",
        "locksmith"
    ],
    "wof:name":"A & K Locksmiths",
    "wof:placetype":"venue"
},
  "geometry": {"coordinates":[-88.747997,43.633014],"type":"Point"}
}