{
  "type": "Feature",
  "properties": {
    "addr:full":"5631 Co Rd G Necedah WI 54646",
    "addr:housenumber":"5631",
    "addr:postcode":"54646",
    "addr:street":"Co Rd",
    "iso:country":"US",
    "sg:address":"5631 Co Rd G",
    "sg:city":"Necedah",
    "sg:classifiers":[
        {
            "category":"Organizations",
            "subcategory":"Non-profit Organization",
            "type":"Services"
        }
    ],
    "sg:phone":"+1 608 565 2417",
    "sg:postcode":"54646",
    "sg:province":"WI",
    "sg:tags":[
        "alternative",
        "abortion"
    ],
    "wof:name":"Seven Sorrows Of Our Mother",
    "wof:placetype":"venue"
},
  "geometry": {"coordinates":[-90.04666899999999,44.024628],"type":"Point"}
}