{
  "type": "Feature",
  "properties": {
    "addr:full":"717 Wisconsin Ave Racine WI 53403",
    "addr:housenumber":"717",
    "addr:postcode":"53403",
    "addr:street":"Wisconsin Ave",
    "iso:country":"US",
    "sg:address":"717 Wisconsin Ave",
    "sg:city":"Racine",
    "sg:classifiers":[
        {
            "category":"Government",
            "subcategory":"Police Station",
            "type":"Public Place"
        }
    ],
    "sg:phone":"+1 262 636 3154",
    "sg:postcode":"53403",
    "sg:province":"WI",
    "sg:tags":[
        "sheriff"
    ],
    "wof:name":"Racine Cnty Sheriff-Ct Officer",
    "wof:placetype":"venue"
},
  "geometry": {"coordinates":[-87.78366699999999,42.724715],"type":"Point"}
}