{
  "type": "Feature",
  "properties": {
    "iso:country":"US",
    "sg:address":"104 Yost St",
    "sg:city":"Beloit",
    "sg:classifiers":[
        {
            "category":"Retail",
            "subcategory":"Repair Shop",
            "type":"Services"
        }
    ],
    "sg:phone":"+1 608 365 1934",
    "sg:postcode":"53511",
    "sg:province":"WI",
    "sg:tags":[
        "refrigerator",
        "freezer"
    ],
    "wof:name":"Elmer Benedetti",
    "wof:placetype":"venue"
},
  "geometry": {"coordinates":[-89.039347,42.561033],"type":"Point"}
}