{
  "type": "Feature",
  "properties": {
    "iso:country":"US",
    "sg:address":"601 N Milwaukee St",
    "sg:city":"Waterford",
    "sg:classifiers":[
        {
            "category":"Shopping",
            "subcategory":"Pharmacy",
            "type":"Retail Goods"
        }
    ],
    "sg:phone":"+1 262 534 9222",
    "sg:postcode":"53185",
    "sg:province":"WI",
    "sg:tags":[
        "gasoline"
    ],
    "wof:name":"Pharmacy Station",
    "wof:placetype":"venue"
},
  "geometry": {"coordinates":[-88.204312,42.770413],"type":"Point"}
}