{
  "type": "Feature",
  "properties": {
    "iso:country":"US",
    "sg:address":"5558 Miranda Way",
    "sg:city":"Fond Du Lac",
    "sg:classifiers":[
        {
            "category":"Professional",
            "type":"Services"
        }
    ],
    "sg:phone":"+1 920 924 5489",
    "sg:postcode":"54937",
    "sg:province":"WI",
    "sg:tags":[
        "establishment"
    ],
    "wof:name":"Short & Saffy Truckn'",
    "wof:placetype":"venue"
},
  "geometry": {"coordinates":[-88.500941,43.742418],"type":"Point"}
}