{
  "type": "Feature",
  "properties": {
    "addr:full":"1700 Marco Dr La Crosse WI 54601",
    "addr:housenumber":"1700",
    "addr:postcode":"54601",
    "addr:street":"Marco Dr",
    "iso:country":"US",
    "sg:address":"1700 Marco Dr",
    "sg:city":"La Crosse",
    "sg:classifiers":[
        {
            "category":"Freight",
            "type":"Transportation"
        }
    ],
    "sg:phone":"+1 608 784 6313",
    "sg:postcode":"54601",
    "sg:province":"WI",
    "sg:tags":[
        "warehouse",
        "operator",
        "self",
        "storage",
        "trucking"
    ],
    "wof:name":"Hanke Terminal Inc",
    "wof:placetype":"venue"
},
  "geometry": {"coordinates":[-91.25616100000001,43.794135],"type":"Point"}
}