{
  "type": "Feature",
  "properties": {
    "iso:country":"US",
    "sg:address":"6125 W National Ave",
    "sg:city":"Milwaukee",
    "sg:classifiers":[
        {
            "category":"Professional",
            "subcategory":"Testing Lab",
            "type":"Services"
        }
    ],
    "sg:phone":"+1 414 475 6700",
    "sg:postcode":"53214",
    "sg:province":"WI",
    "sg:tags":[
        "laboratory"
    ],
    "sg:website":"www.sflabs.com",
    "wof:name":"S-F Analytical Labs",
    "wof:placetype":"venue"
},
  "geometry": {"coordinates":[-87.98959499999999,43.016805],"type":"Point"}
}