{
  "type": "Feature",
  "properties": {
    "iso:country":"US",
    "sg:address":"605 S Van Buren St",
    "sg:city":"Green Bay",
    "sg:classifiers":[
        {
            "category":"Building & Trades",
            "subcategory":"Construction",
            "type":"Services"
        }
    ],
    "sg:phone":"+1 920 497 7777",
    "sg:postcode":"54301",
    "sg:province":"WI",
    "sg:tags":[
        "general",
        "contractor"
    ],
    "wof:name":"Hougard Construction",
    "wof:placetype":"venue"
},
  "geometry": {"coordinates":[-88.01140599999999,44.503257],"type":"Point"}
}