{
  "type": "Feature",
  "properties": {
    "iso:country":"US",
    "sg:address":"205 Menomonie St",
    "sg:city":"Elk Mound",
    "sg:classifiers":[
        {
            "category":"Health Services",
            "subcategory":"Chiropractor",
            "type":"Services"
        }
    ],
    "sg:phone":"+1 715 879 5653",
    "sg:postcode":"54739",
    "sg:province":"WI",
    "wof:name":"Elk Mound Chiropractic",
    "wof:placetype":"venue"
},
  "geometry": {"coordinates":[-91.688637,44.872138],"type":"Point"}
}