{
  "type": "Feature",
  "properties": {
    "iso:country":"US",
    "sg:address":"717 Thayer St",
    "sg:city":"Rhinelander",
    "sg:classifiers":[
        {
            "category":"Shopping",
            "type":"Retail Goods"
        }
    ],
    "sg:phone":"+1 715 362 6118",
    "sg:postcode":"54501",
    "sg:province":"WI",
    "sg:tags":[
        "merchandise"
    ],
    "wof:name":"Air Cmmnctons of Cntl Wsconsin",
    "wof:placetype":"venue"
},
  "geometry": {"coordinates":[-89.413543,45.647723],"type":"Point"}
}