{
  "type": "Feature",
  "properties": {
    "addr:full":"2455 Buckingham Pl Brookfield WI 53045",
    "addr:housenumber":"2455",
    "addr:postcode":"53045",
    "addr:street":"Buckingham Pl",
    "iso:country":"US",
    "sg:address":"2455 Buckingham Pl",
    "sg:city":"Brookfield",
    "sg:classifiers":[
        {
            "category":"Professional",
            "type":"Services"
        }
    ],
    "sg:phone":"+1 262 784 9280",
    "sg:postcode":"53045",
    "sg:province":"WI",
    "wof:name":"Allgaier Foundation",
    "wof:placetype":"venue"
},
  "geometry": {"coordinates":[-88.15775600000001,43.064357],"type":"Point"}
}