{
  "type": "Feature",
  "properties": {
    "addr:full":"1846 Industrial Dr Green Bay WI 54302",
    "addr:housenumber":"1846",
    "addr:postcode":"54302",
    "addr:street":"Industrial Dr",
    "iso:country":"US",
    "sg:address":"1846 Industrial Dr",
    "sg:city":"Green Bay",
    "sg:classifiers":[
        {
            "category":"Freight",
            "type":"Transportation"
        }
    ],
    "sg:phone":"+1 920 884 2424",
    "sg:postcode":"54302",
    "sg:province":"WI",
    "sg:tags":[
        "special"
    ],
    "wof:name":"Access Storage LLC",
    "wof:placetype":"venue"
},
  "geometry": {"coordinates":[-87.99373,44.485214],"type":"Point"}
}