{
  "type": "Feature",
  "properties": {
    "iso:country":"US",
    "sg:address":"1502 Giese Rd",
    "sg:city":"Juda",
    "sg:classifiers":[
        {
            "category":"Farming",
            "subcategory":"Farm & Veterinary Services",
            "type":"Manufacturing & Wholesale Goods"
        }
    ],
    "sg:phone":"+1 608 897 4081",
    "sg:postcode":"53550",
    "sg:province":"WI",
    "sg:tags":[
        "for",
        "beef",
        "crop",
        "preparation",
        "market",
        "cattle",
        "feedlot"
    ],
    "wof:name":"James Coleman",
    "wof:placetype":"venue"
},
  "geometry": {"coordinates":[-89.434043,42.57374],"type":"Point"}
}