{
  "type": "Feature",
  "properties": {
    "iso:country":"US",
    "sg:address":"16305 W Marietta Dr",
    "sg:city":"New Berlin",
    "sg:classifiers":[
        {
            "category":"Social Services",
            "type":"Services"
        }
    ],
    "sg:phone":"+1 262 860 6375",
    "sg:postcode":"53151",
    "sg:province":"WI",
    "wof:name":"Mature Singles Inc",
    "wof:placetype":"venue"
},
  "geometry": {"coordinates":[-88.119739,42.9645],"type":"Point"}
}