{
  "type": "Feature",
  "properties": {
    "iso:country":"US",
    "sg:address":"195 27th St",
    "sg:city":"Caledonia",
    "sg:classifiers":[
        {
            "category":"Building & Trades",
            "subcategory":"Construction",
            "type":"Services"
        },
        {
            "category":"Manufacturing",
            "subcategory":"Lumber",
            "type":"Manufacturing & Wholesale Goods"
        }
    ],
    "sg:phone":"+1 262 835 9212",
    "sg:postcode":"53108",
    "sg:province":"WI",
    "sg:tags":[
        "provides",
        "hardwood",
        "drying",
        "kiln",
        "woodworker",
        "rough",
        "sawmill"
    ],
    "wof:name":"Kettle Moraine Hardwoods Inc",
    "wof:placetype":"venue"
},
  "geometry": {"coordinates":[-87.953251,42.842051],"type":"Point"}
}