{
  "type": "Feature",
  "properties": {
    "iso:country":"US",
    "sg:address":"14530 W Capitol Dr",
    "sg:city":"Brookfield",
    "sg:classifiers":[
        {
            "category":"Professional",
            "subcategory":"Accounting & Tax Preparation",
            "type":"Services"
        }
    ],
    "sg:phone":"+1 262 781 5750",
    "sg:postcode":"53005",
    "sg:province":"WI",
    "sg:tags":[
        "accountant"
    ],
    "wof:name":"Daniel G Schneider CPA",
    "wof:placetype":"venue"
},
  "geometry": {"coordinates":[-88.094575,43.08979],"type":"Point"}
}