{
  "type": "Feature",
  "properties": {
    "iso:country":"US",
    "sg:address":"3514 Blarney Rd",
    "sg:city":"Warrens",
    "sg:classifiers":[
        {
            "category":"Restaurant",
            "type":"Food & Drink"
        }
    ],
    "sg:phone":"+1 608 378 4989",
    "sg:postcode":"54666",
    "sg:province":"WI",
    "wof:name":"Kim's Texas Longhorn Grill Mts",
    "wof:placetype":"venue"
},
  "geometry": {"coordinates":[-90.536528,44.123779],"type":"Point"}
}