{
  "type": "Feature",
  "properties": {
    "addr:full":"335 N 115th St Milwaukee WI 53226",
    "addr:housenumber":"335",
    "addr:postcode":"53226",
    "addr:street":"N 115Th St",
    "iso:country":"US",
    "sg:address":"335 N 115th St",
    "sg:city":"Milwaukee",
    "sg:classifiers":[
        {
            "category":"Building & Trades",
            "subcategory":"Construction",
            "type":"Services"
        }
    ],
    "sg:phone":"+1 414 258 1651",
    "sg:postcode":"53226",
    "sg:province":"WI",
    "sg:tags":[
        "house"
    ],
    "wof:name":"Keaton Home Repairs",
    "wof:placetype":"venue"
},
  "geometry": {"coordinates":[-88.05619,43.035488],"type":"Point"}
}