{
  "type": "Feature",
  "properties": {
    "addr:full":"228 N Milwaukee St Waterford WI 53185",
    "addr:housenumber":"228",
    "addr:postcode":"53185",
    "addr:street":"N Milwaukee St",
    "iso:country":"US",
    "sg:address":"228 N Milwaukee St",
    "sg:city":"Waterford",
    "sg:classifiers":[
        {
            "category":"Manufacturing",
            "subcategory":"Printing",
            "type":"Manufacturing & Wholesale Goods"
        }
    ],
    "sg:phone":"+1 262 514 3084",
    "sg:postcode":"53185",
    "sg:province":"WI",
    "sg:tags":[
        "printer"
    ],
    "wof:name":"Excellent Online Inc",
    "wof:placetype":"venue"
},
  "geometry": {"coordinates":[-88.209395,42.76581],"type":"Point"}
}