{
  "type": "Feature",
  "properties": {
    "iso:country":"US",
    "sg:address":"714 Audubon Rd",
    "sg:city":"Sheboygan",
    "sg:classifiers":[
        {
            "category":"Freight",
            "type":"Transportation"
        }
    ],
    "sg:phone":"+1 920 565 3860",
    "sg:postcode":"53083",
    "sg:province":"WI",
    "sg:tags":[
        "general"
    ],
    "wof:name":"Blackjack LLC",
    "wof:placetype":"venue"
},
  "geometry": {"coordinates":[-87.82108599999999,43.824718],"type":"Point"}
}