{
  "type": "Feature",
  "properties": {
    "addr:full":"2930 New Pinery Rd Portage WI 53901",
    "addr:housenumber":"2930",
    "addr:postcode":"53901",
    "addr:street":"New Pinery Rd",
    "iso:country":"US",
    "sg:address":"2930 New Pinery Rd",
    "sg:city":"Portage",
    "sg:classifiers":[
        {
            "category":"Banks & Credit Unions",
            "subcategory":"Bank",
            "type":"Services"
        }
    ],
    "sg:phone":"+1 608 742 6088",
    "sg:postcode":"53901",
    "sg:province":"WI",
    "sg:tags":[
        "cashing",
        "check"
    ],
    "wof:name":"Check Advance",
    "wof:placetype":"venue"
},
  "geometry": {"coordinates":[-89.469385,43.568948],"type":"Point"}
}