{
  "type": "Feature",
  "properties": {
    "iso:country":"US",
    "sg:address":"3281 Mound View Rd",
    "sg:city":"Verona",
    "sg:classifiers":[
        {
            "category":"Professional",
            "type":"Services"
        }
    ],
    "sg:phone":"+1 608 845 7787",
    "sg:postcode":"53593",
    "sg:province":"WI",
    "sg:tags":[
        "scientist"
    ],
    "wof:name":"Science Consulting LLC",
    "wof:placetype":"venue"
},
  "geometry": {"coordinates":[-89.582368,43.033647],"type":"Point"}
}