{
  "type": "Feature",
  "properties": {
    "iso:country":"US",
    "sg:address":"821 W State St",
    "sg:city":"Milwaukee",
    "sg:classifiers":[
        {
            "category":"Government",
            "subcategory":"Office",
            "type":"Public Place"
        }
    ],
    "sg:phone":"+1 414 278 4764",
    "sg:postcode":"53233",
    "sg:province":"WI",
    "wof:name":"Honorable John Siefert",
    "wof:placetype":"venue"
},
  "geometry": {"coordinates":[-87.92025099999999,43.042939],"type":"Point"}
}