{
  "type": "Feature",
  "properties": {
    "addr:full":"6903 Schumacher Rd Fall Creek WI 54742",
    "addr:housenumber":"6903",
    "addr:postcode":"54742",
    "addr:street":"Schumacher Rd",
    "iso:country":"US",
    "sg:address":"6903 Schumacher Rd",
    "sg:city":"Fall Creek",
    "sg:classifiers":[
        {
            "category":"Farming",
            "subcategory":"Livestock Farm",
            "type":"Manufacturing & Wholesale Goods"
        }
    ],
    "sg:phone":"+1 715 832 5223",
    "sg:postcode":"54742",
    "sg:province":"WI",
    "sg:tags":[
        "beef",
        "feedlot",
        "cattle"
    ],
    "wof:name":"Schumacher Farms",
    "wof:placetype":"venue"
},
  "geometry": {"coordinates":[-91.39322199999999,44.77103],"type":"Point"}
}