{
  "type": "Feature",
  "properties": {
    "iso:country":"US",
    "sg:address":"238 Audley Dr",
    "sg:city":"Sun Prairie",
    "sg:classifiers":[
        {
            "category":"Building & Trades",
            "subcategory":"Construction",
            "type":"Services"
        }
    ],
    "sg:phone":"+1 608 837 6982",
    "sg:postcode":"53590",
    "sg:province":"WI",
    "sg:tags":[
        "painter"
    ],
    "wof:name":"Wake Decorating Svc",
    "wof:placetype":"venue"
},
  "geometry": {"coordinates":[-89.227656,43.185883],"type":"Point"}
}