{
  "type": "Feature",
  "properties": {
    "addr:full":"5750 W Airways Ave Franklin WI 53132",
    "addr:housenumber":"5750",
    "addr:postcode":"53132",
    "addr:street":"W Airways Ave",
    "iso:country":"US",
    "sg:address":"5750 W Airways Ave",
    "sg:city":"Franklin",
    "sg:classifiers":[
        {
            "category":"Retail",
            "subcategory":"Auto Repair",
            "type":"Services"
        }
    ],
    "sg:phone":"+1 414 421 8688",
    "sg:postcode":"53132",
    "sg:province":"WI",
    "sg:tags":[
        "truck"
    ],
    "wof:name":"Mooney's Repair Svc",
    "wof:placetype":"venue"
},
  "geometry": {"coordinates":[-87.987888,42.8671],"type":"Point"}
}