{
  "type": "Feature",
  "properties": {
    "iso:country":"US",
    "sg:address":"1300 Forestedge Dr",
    "sg:city":"Kaukauna",
    "sg:classifiers":[
        {
            "category":"Personal",
            "subcategory":"Beauty Salon",
            "type":"Services"
        }
    ],
    "sg:phone":"+1 920 766 5324",
    "sg:postcode":"54130",
    "sg:province":"WI",
    "sg:tags":[
        "shop"
    ],
    "wof:name":"Forest Edge Salon",
    "wof:placetype":"venue"
},
  "geometry": {"coordinates":[-88.259157,44.268585],"type":"Point"}
}