{
  "type": "Feature",
  "properties": {
    "addr:full":"8075 N 76th St Milwaukee WI 53223",
    "addr:housenumber":"8075",
    "addr:postcode":"53223",
    "addr:street":"N 76Th St",
    "iso:country":"US",
    "sg:address":"8075 N 76th St",
    "sg:city":"Milwaukee",
    "sg:classifiers":[
        {
            "category":"Shopping",
            "subcategory":"Used Merchandise",
            "type":"Retail Goods"
        }
    ],
    "sg:phone":"+1 414 357 8550",
    "sg:postcode":"53223",
    "sg:province":"WI",
    "sg:tags":[
        "furniture"
    ],
    "wof:name":"J B's New & Used Furniture",
    "wof:placetype":"venue"
},
  "geometry": {"coordinates":[-88.004734,43.163757],"type":"Point"}
}