{
  "type": "Feature",
  "properties": {
    "addr:full":"16607 Burlington Rd Union Grove WI 53182",
    "addr:housenumber":"16607",
    "addr:postcode":"53182",
    "addr:street":"Burlington Rd",
    "iso:country":"US",
    "sg:address":"16607 Burlington Rd",
    "sg:city":"Union Grove",
    "sg:classifiers":[
        {
            "category":"Government",
            "subcategory":"Fire Station",
            "type":"Public Place"
        }
    ],
    "sg:phone":"+1 262 859 3009",
    "sg:postcode":"53182",
    "sg:province":"WI",
    "sg:tags":[
        "department"
    ],
    "wof:name":"Paris Fire Dept",
    "wof:placetype":"venue"
},
  "geometry": {"coordinates":[-88.011717,42.629022],"type":"Point"}
}