{
  "type": "Feature",
  "properties": {
    "addr:full":"3408 W National Ave Milwaukee WI 53215",
    "addr:housenumber":"3408",
    "addr:postcode":"53215",
    "addr:street":"W National Ave",
    "iso:country":"US",
    "sg:address":"3408 W National Ave",
    "sg:city":"Milwaukee",
    "sg:classifiers":[
        {
            "category":"Cinema",
            "subcategory":"Movie Rental",
            "type":"Entertainment"
        }
    ],
    "sg:phone":"+1 414 649 9450",
    "sg:postcode":"53215",
    "sg:province":"WI",
    "sg:tags":[
        "video",
        "tape"
    ],
    "wof:name":"Rainbow Video",
    "wof:placetype":"venue"
},
  "geometry": {"coordinates":[-87.957626,43.021693],"type":"Point"}
}