{
  "type": "Feature",
  "properties": {
    "iso:country":"US",
    "sg:address":"5358 Tory Ln",
    "sg:city":"Colgate",
    "sg:classifiers":[
        {
            "category":"Retail",
            "subcategory":"Auto Repair",
            "type":"Services"
        }
    ],
    "sg:phone":"+1 262 628 2719",
    "sg:postcode":"53017",
    "sg:province":"WI",
    "sg:tags":[
        "automotive",
        "electrical",
        "vocational",
        "contractor"
    ],
    "wof:name":"Quest Systems Inc",
    "wof:placetype":"venue"
},
  "geometry": {"coordinates":[-88.304908,43.203047],"type":"Point"}
}