{
  "type": "Feature",
  "properties": {
    "iso:country":"US",
    "sg:address":"415 S 8th St",
    "sg:city":"Watertown",
    "sg:classifiers":[
        {
            "category":"Social Services",
            "subcategory":"Child Care",
            "type":"Services"
        }
    ],
    "sg:phone":"+1 920 261 8163",
    "sg:postcode":"53094",
    "sg:province":"WI",
    "sg:tags":[
        "kindergarten",
        "academic",
        "school"
    ],
    "wof:name":"Early Childhood",
    "wof:placetype":"venue"
},
  "geometry": {"coordinates":[-88.71738999999999,43.191091],"type":"Point"}
}