{
  "type": "Feature",
  "properties": {
    "iso:country":"US",
    "sg:address":"1209 W Wisconsin Ave",
    "sg:city":"Appleton",
    "sg:classifiers":[
        {
            "category":"Autos & Motor Vehicles",
            "subcategory":"Automobile Sales",
            "type":"Retail Goods"
        }
    ],
    "sg:phone":"+1 920 830 9777",
    "sg:postcode":"54914",
    "sg:province":"WI",
    "sg:tags":[
        "used"
    ],
    "wof:name":"Cruisin Auto Sales",
    "wof:placetype":"venue"
},
  "geometry": {"coordinates":[-88.424354,44.272964],"type":"Point"}
}