{
  "type": "Feature",
  "properties": {
    "iso:country":"US",
    "sg:address":"1717 Cambridge Ave",
    "sg:city":"Sheboygan",
    "sg:classifiers":[
        {
            "category":"Building & Trades",
            "subcategory":"Construction",
            "type":"Services"
        }
    ],
    "sg:phone":"+1 920 458 5722",
    "sg:postcode":"53081",
    "sg:province":"WI",
    "sg:tags":[
        "general",
        "home",
        "contractor",
        "remodeling",
        "an"
    ],
    "wof:name":"Sauermilch John Jr Gen Contrs",
    "wof:placetype":"venue"
},
  "geometry": {"coordinates":[-87.729089,43.763341],"type":"Point"}
}