{
  "type": "Feature",
  "properties": {
    "iso:country":"US",
    "sg:address":"1341 S 24th St",
    "sg:city":"Manitowoc",
    "sg:classifiers":[
        {
            "category":"Professional",
            "subcategory":"Art Services",
            "type":"Services"
        }
    ],
    "sg:phone":"+1 920 682 7988",
    "sg:postcode":"54220",
    "sg:province":"WI",
    "sg:tags":[
        "graphic",
        "designer"
    ],
    "sg:website":"www.idsardar.com",
    "wof:name":"Imperial Designs",
    "wof:placetype":"venue"
},
  "geometry": {"coordinates":[-87.67812600000001,44.081365],"type":"Point"}
}