{
  "type": "Feature",
  "properties": {
    "iso:country":"US",
    "sg:address":"2080 Old Peshtigo Rd",
    "sg:city":"Marinette",
    "sg:classifiers":[
        {
            "category":"Home & Garden",
            "subcategory":"Building Materials",
            "type":"Retail Goods"
        }
    ],
    "sg:phone":"+1 715 735 8300",
    "sg:postcode":"54143",
    "sg:province":"WI",
    "wof:name":"Menard Inc",
    "wof:placetype":"venue"
},
  "geometry": {"coordinates":[-87.655592,45.08313],"type":"Point"}
}