{
  "type": "Feature",
  "properties": {
    "iso:country":"US",
    "sg:address":"7090 Holy Cross Rd",
    "sg:city":"Fifield",
    "sg:classifiers":[
        {
            "category":"Building & Trades",
            "subcategory":"Landscaping Services",
            "type":"Services"
        }
    ],
    "sg:phone":"+1 715 339 2273",
    "sg:postcode":"54524",
    "sg:province":"WI",
    "sg:tags":[
        "tree"
    ],
    "wof:name":"Timber Tree Svc & Logging",
    "wof:placetype":"venue"
},
  "geometry": {"coordinates":[-90.404995,45.793917],"type":"Point"}
}