{
  "type": "Feature",
  "properties": {
    "iso:country":"US",
    "sg:address":"1127 S 4th St",
    "sg:city":"Milwaukee",
    "sg:classifiers":[
        {
            "category":"Professional",
            "subcategory":"Computer Services",
            "type":"Services"
        }
    ],
    "sg:phone":"+1 414 383 9311",
    "sg:postcode":"53204",
    "sg:province":"WI",
    "sg:tags":[
        "design",
        "system"
    ],
    "wof:name":"Coyote Designs",
    "wof:placetype":"venue"
},
  "geometry": {"coordinates":[-87.915513,43.019355],"type":"Point"}
}