{
  "type": "Feature",
  "properties": {
    "iso:country":"US",
    "sg:address":"10102 N Klug Rd",
    "sg:city":"Milton",
    "sg:classifiers":[
        {
            "category":"Professional",
            "subcategory":"Management & Consulting",
            "type":"Services"
        }
    ],
    "sg:phone":"+1 608 868 5217",
    "sg:postcode":"53563",
    "sg:province":"WI",
    "wof:name":"On The Rock Magazine",
    "wof:placetype":"venue"
},
  "geometry": {"coordinates":[-88.920732,42.805898],"type":"Point"}
}