{
  "type": "Feature",
  "properties": {
    "addr:full":"2810 9th St S Wisconsin Rapids WI 54494",
    "addr:housenumber":"2810",
    "addr:postcode":"54494",
    "addr:street":"9Th St S",
    "iso:country":"US",
    "sg:address":"2810 9th St S",
    "sg:city":"Wisconsin Rapids",
    "sg:classifiers":[
        {
            "category":"Organizations",
            "subcategory":"Non-profit Organization",
            "type":"Services"
        }
    ],
    "sg:phone":"+1 715 422 5055",
    "sg:postcode":"54494",
    "sg:province":"WI",
    "sg:tags":[
        "disability"
    ],
    "wof:name":"DEAF",
    "wof:placetype":"venue"
},
  "geometry": {"coordinates":[-89.815589,44.369103],"type":"Point"}
}