{
  "type": "Feature",
  "properties": {
    "iso:country":"US",
    "sg:address":"1220 Main St",
    "sg:city":"Gresham",
    "sg:classifiers":[
        {
            "category":"Home & Garden",
            "subcategory":"Hardware",
            "type":"Retail Goods"
        }
    ],
    "sg:phone":"+1 715 787 3288",
    "sg:postcode":"54128",
    "sg:province":"WI",
    "wof:name":"Hoffman's Gamble Store",
    "wof:placetype":"venue"
},
  "geometry": {"coordinates":[-88.78708399999999,44.851315],"type":"Point"}
}