{
  "type": "Feature",
  "properties": {
    "iso:country":"US",
    "sg:address":"350 Smc Dr",
    "sg:city":"Somerset",
    "sg:classifiers":[
        {
            "category":"Manufacturing",
            "subcategory":"Tools & Machinery",
            "type":"Manufacturing & Wholesale Goods"
        }
    ],
    "sg:phone":"+1 715 247 2625",
    "sg:postcode":"54025",
    "sg:province":"WI",
    "sg:tags":[
        "die",
        "maker"
    ],
    "wof:name":"Aero Machine Tool LLC",
    "wof:placetype":"venue"
},
  "geometry": {"coordinates":[-92.665593,45.132045],"type":"Point"}
}