{
  "type": "Feature",
  "properties": {
    "iso:country":"US",
    "sg:address":"145 W Wisconsin Ave",
    "sg:city":"Neenah",
    "sg:classifiers":[
        {
            "category":"Insurance",
            "subcategory":"Insurance Agent",
            "type":"Services"
        }
    ],
    "sg:phone":"+1 920 729 0370",
    "sg:postcode":"54956",
    "sg:province":"WI",
    "wof:name":"Northwestern Mutual Financial",
    "wof:placetype":"venue"
},
  "geometry": {"coordinates":[-88.46269700000001,44.186955],"type":"Point"}
}