{
  "type": "Feature",
  "properties": {
    "addr:full":"5801 W Airways Ave Franklin WI 53132",
    "addr:housenumber":"5801",
    "addr:postcode":"53132",
    "addr:street":"W Airways Ave",
    "iso:country":"US",
    "sg:address":"5801 W Airways Ave",
    "sg:city":"Franklin",
    "sg:classifiers":[
        {
            "category":"Wholesale",
            "subcategory":"Medical Equipment & Supplies",
            "type":"Manufacturing & Wholesale Goods"
        },
        {
            "category":"Shopping",
            "subcategory":"Pharmacy",
            "type":"Retail Goods"
        }
    ],
    "sg:phone":"+1 414 421 7707",
    "sg:postcode":"53132",
    "sg:province":"WI",
    "sg:tags":[
        "pharmaceutical",
        "medicines-patent",
        "proprietary",
        "products-wholesale",
        "manufacturer"
    ],
    "wof:name":"Carmex",
    "wof:placetype":"venue"
},
  "geometry": {"coordinates":[-87.98854799999999,42.867001],"type":"Point"}
}