{
  "type": "Feature",
  "properties": {
    "iso:country":"US",
    "sg:address":"1793 Elm Ave",
    "sg:city":"Wabeno",
    "sg:classifiers":[
        {
            "category":"Organizations",
            "subcategory":"Religious Organization",
            "type":"Services"
        }
    ],
    "sg:phone":"+1 715 473 2511",
    "sg:postcode":"54566",
    "sg:province":"WI",
    "sg:tags":[
        "church"
    ],
    "wof:name":"St Ambrose Catholic Church",
    "wof:placetype":"venue"
},
  "geometry": {"coordinates":[-88.644155,45.439154],"type":"Point"}
}