{
  "type": "Feature",
  "properties": {
    "addr:full":"3604 Hilltop Ave Wausau WI 54401",
    "addr:housenumber":"3604",
    "addr:postcode":"54401",
    "addr:street":"Hilltop Ave",
    "iso:country":"US",
    "sg:address":"3604 Hilltop Ave",
    "sg:city":"Wausau",
    "sg:classifiers":[
        {
            "category":"Building & Trades",
            "subcategory":"Plumbing",
            "type":"Services"
        }
    ],
    "sg:phone":"+1 715 845 9491",
    "sg:postcode":"54401",
    "sg:province":"WI",
    "sg:tags":[
        "bu",
        "work",
        "electrical",
        "heating",
        "air"
    ],
    "wof:name":"Mechanical Systems Of Wausau",
    "wof:placetype":"venue"
},
  "geometry": {"coordinates":[-89.682,44.966279],"type":"Point"}
}