{
  "type": "Feature",
  "properties": {
    "iso:country":"US",
    "sg:address":"2232 W Mill Rd",
    "sg:city":"Milwaukee",
    "sg:classifiers":[
        {
            "category":"Building & Trades",
            "subcategory":"Construction",
            "type":"Services"
        }
    ],
    "sg:phone":"+1 414 540 0177",
    "sg:postcode":"53209",
    "sg:province":"WI",
    "sg:tags":[
        "home",
        "improvement"
    ],
    "wof:name":"R Q Enterprises",
    "wof:placetype":"venue"
},
  "geometry": {"coordinates":[-87.94082400000001,43.133714],"type":"Point"}
}