{
  "type": "Feature",
  "properties": {
    "addr:full":"3700 S 2nd St Milwaukee WI 53207",
    "addr:housenumber":"3700",
    "addr:postcode":"53207",
    "addr:street":"S 2Nd St",
    "iso:country":"US",
    "sg:address":"3700 S 2nd St",
    "sg:city":"Milwaukee",
    "sg:classifiers":[
        {
            "category":"Recreation",
            "type":"Entertainment"
        }
    ],
    "sg:phone":"+1 414 482 4270",
    "sg:postcode":"53207",
    "sg:province":"WI",
    "sg:tags":[
        "parks"
    ],
    "wof:name":"Saveland Park",
    "wof:placetype":"venue"
},
  "geometry": {"coordinates":[-87.91307500000001,42.977382],"type":"Point"}
}