{
  "type": "Feature",
  "properties": {
    "iso:country":"US",
    "sg:address":"5920 School Forest Ln",
    "sg:city":"Crivitz",
    "sg:classifiers":[
        {
            "category":"Recreation",
            "subcategory":"Marina",
            "type":"Entertainment"
        }
    ],
    "sg:phone":"+1 715 854 3249",
    "sg:postcode":"54114",
    "sg:province":"WI",
    "sg:tags":[
        "operation"
    ],
    "wof:name":"Mullins Lake Noquebay Storage",
    "wof:placetype":"venue"
},
  "geometry": {"coordinates":[-87.89633,45.242842],"type":"Point"}
}