{
  "type": "Feature",
  "properties": {
    "iso:country":"US",
    "sg:address":"505 S 8th St",
    "sg:city":"Sheboygan",
    "sg:classifiers":[
        {
            "category":"Personal",
            "type":"Services"
        }
    ],
    "sg:phone":"+1 920 457 8266",
    "sg:postcode":"53081",
    "sg:province":"WI",
    "wof:name":"Caribbean Heat Tanning Salon",
    "wof:placetype":"venue"
},
  "geometry": {"coordinates":[-87.712862,43.749027],"type":"Point"}
}