{
  "type": "Feature",
  "properties": {
    "addr:full":"3305 Tower Ave Superior WI 54880",
    "addr:housenumber":"3305",
    "addr:postcode":"54880",
    "addr:street":"Tower Ave",
    "iso:country":"US",
    "sg:address":"3305 Tower Ave",
    "sg:city":"Superior",
    "sg:classifiers":[
        {
            "category":"Wholesale",
            "subcategory":"Auto Parts",
            "type":"Manufacturing & Wholesale Goods"
        }
    ],
    "sg:phone":"+1 715 394 7278",
    "sg:postcode":"54880",
    "sg:province":"WI",
    "wof:name":"NAPA Auto Parts",
    "wof:placetype":"venue"
},
  "geometry": {"coordinates":[-92.10414900000001,46.699138],"type":"Point"}
}