{
  "type": "Feature",
  "properties": {
    "addr:full":"2707 Charles St Racine WI 53402",
    "addr:housenumber":"2707",
    "addr:postcode":"53402",
    "addr:street":"Charles St",
    "iso:country":"US",
    "sg:address":"2707 Charles St",
    "sg:city":"Racine",
    "sg:classifiers":[
        {
            "category":"Freight",
            "type":"Transportation"
        }
    ],
    "sg:phone":"+1 262 681 3809",
    "sg:postcode":"53402",
    "sg:province":"WI",
    "sg:tags":[
        "operator",
        "local",
        "trucking"
    ],
    "wof:name":"Rcg Trucking Inc",
    "wof:placetype":"venue"
},
  "geometry": {"coordinates":[-87.79688400000001,42.753752],"type":"Point"}
}