{
  "type": "Feature",
  "properties": {
    "iso:country":"US",
    "sg:address":"317 Main Ave",
    "sg:city":"De Pere",
    "sg:classifiers":[
        {
            "category":"Home & Garden",
            "subcategory":"Building Materials",
            "type":"Retail Goods"
        },
        {
            "category":"Professional",
            "subcategory":"Business Services",
            "type":"Services"
        }
    ],
    "sg:phone":"+1 920 336 7725",
    "sg:postcode":"54115",
    "sg:province":"WI",
    "sg:tags":[
        "shop",
        "upholstery",
        "consultant",
        "window",
        "design",
        "treatment",
        "interior",
        "decorator",
        "furniture"
    ],
    "wof:name":"Kerkhoff Interiors & Designs",
    "wof:placetype":"venue"
},
  "geometry": {"coordinates":[-88.070352,44.447463],"type":"Point"}
}