{
  "type": "Feature",
  "properties": {
    "iso:country":"US",
    "sg:address":"3430 Oakwood Mall Dr",
    "sg:city":"Eau Claire",
    "sg:classifiers":[
        {
            "category":"Professional",
            "subcategory":"Lawyer & Legal Services",
            "type":"Services"
        }
    ],
    "sg:phone":"+1 715 834 7771",
    "sg:postcode":"54701",
    "sg:province":"WI",
    "sg:tags":[
        "attorney"
    ],
    "wof:name":"Parroni Siedow & Jackson",
    "wof:placetype":"venue"
},
  "geometry": {"coordinates":[-91.445456,44.776725],"type":"Point"}
}