{
  "type": "Feature",
  "properties": {
    "addr:full":"1342 W Prospect Ave Appleton WI 54914",
    "addr:housenumber":"1342",
    "addr:postcode":"54914",
    "addr:street":"W Prospect Ave",
    "iso:country":"US",
    "sg:address":"1342 W Prospect Ave",
    "sg:city":"Appleton",
    "sg:classifiers":[
        {
            "category":"Food & Beverages",
            "subcategory":"Groceries & Convenience Stores",
            "type":"Retail Goods"
        }
    ],
    "sg:phone":"+1 920 734 9260",
    "sg:postcode":"54914",
    "sg:province":"WI",
    "sg:tags":[
        "station",
        "gasoline"
    ],
    "sg:website":"www.kwiktrip.com",
    "wof:name":"KWIK Trip",
    "wof:placetype":"venue"
},
  "geometry": {"coordinates":[-88.42656599999999,44.254573],"type":"Point"}
}