{
  "type": "Feature",
  "properties": {
    "iso:country":"US",
    "sg:address":"15368 Borglin Ave",
    "sg:city":"Withee",
    "sg:classifiers":[
        {
            "category":"Farming",
            "subcategory":"Dairy Farm",
            "type":"Manufacturing & Wholesale Goods"
        }
    ],
    "sg:phone":"+1 715 229 4487",
    "sg:postcode":"54498",
    "sg:province":"WI",
    "wof:name":"Open Gate Farms Inc",
    "wof:placetype":"venue"
},
  "geometry": {"coordinates":[-90.58765699999999,44.976573],"type":"Point"}
}