{
  "type": "Feature",
  "properties": {
    "addr:full":"2945 N Oakland Ave Milwaukee WI 53211",
    "addr:housenumber":"2945",
    "addr:postcode":"53211",
    "addr:street":"N Oakland Ave",
    "iso:country":"US",
    "sg:address":"2945 N Oakland Ave",
    "sg:city":"Milwaukee",
    "sg:classifiers":[
        {
            "category":"Building & Trades",
            "subcategory":"Electrical",
            "type":"Services"
        }
    ],
    "sg:phone":"+1 414 961 1200",
    "sg:postcode":"53211",
    "sg:province":"WI",
    "sg:tags":[
        "electrical",
        "contractor"
    ],
    "wof:name":"D Germanotta & Son",
    "wof:placetype":"venue"
},
  "geometry": {"coordinates":[-87.887975,43.071998],"type":"Point"}
}