{
  "type": "Feature",
  "properties": {
    "addr:full":"1529 N Wauwatosa Ave Milwaukee WI 53213",
    "addr:housenumber":"1529",
    "addr:postcode":"53213",
    "addr:street":"N Wauwatosa Ave",
    "iso:country":"US",
    "sg:address":"1529 N Wauwatosa Ave",
    "sg:city":"Milwaukee",
    "sg:classifiers":[
        {
            "category":"Organizations",
            "subcategory":"Religious Organization",
            "type":"Services"
        }
    ],
    "sg:phone":"+1 414 453 0700",
    "sg:postcode":"53213",
    "sg:province":"WI",
    "sg:tags":[
        "churches-united",
        "methodist",
        "church"
    ],
    "sg:website":"http://www.waumc.org",
    "wof:name":"Wauwatosa Ave United Methodist",
    "wof:placetype":"venue"
},
  "geometry": {"coordinates":[-88.007434,43.051123],"type":"Point"}
}