{
  "type": "Feature",
  "properties": {
    "addr:full":"2586 110th Ave Woodville WI 54028",
    "addr:housenumber":"2586",
    "addr:postcode":"54028",
    "addr:street":"110Th Ave",
    "iso:country":"US",
    "sg:address":"2586 110th Ave",
    "sg:city":"Woodville",
    "sg:classifiers":[
        {
            "category":"Farming",
            "subcategory":"Dairy Farm",
            "type":"Manufacturing & Wholesale Goods"
        }
    ],
    "sg:phone":"+1 715 698 2671",
    "sg:postcode":"54028",
    "sg:province":"WI",
    "wof:name":"Dairy Delight",
    "wof:placetype":"venue"
},
  "geometry": {"coordinates":[-92.298508,45.018637],"type":"Point"}
}