{
  "type": "Feature",
  "properties": {
    "iso:country":"US",
    "sg:address":"454 E Oshkosh St",
    "sg:city":"Ripon",
    "sg:classifiers":[
        {
            "category":"Retail",
            "subcategory":"Laundry & Dry Cleaning",
            "type":"Services"
        }
    ],
    "sg:phone":"+1 920 748 3160",
    "sg:postcode":"54971",
    "sg:province":"WI",
    "sg:tags":[
        "cleaners"
    ],
    "wof:name":"Schure's Dry Cleaning",
    "wof:placetype":"venue"
},
  "geometry": {"coordinates":[-88.830213,43.851518],"type":"Point"}
}