{
  "type": "Feature",
  "properties": {
    "iso:country":"US",
    "sg:address":"307 S Paterson St",
    "sg:city":"Madison",
    "sg:classifiers":[
        {
            "category":"Social Services",
            "type":"Services"
        }
    ],
    "sg:phone":"+1 608 255 0539",
    "sg:postcode":"53703",
    "sg:province":"WI",
    "sg:tags":[
        "crisis",
        "intervention"
    ],
    "sg:website":"www.wcadv.org",
    "wof:name":"Wi Coalition Against Domestic",
    "wof:placetype":"venue"
},
  "geometry": {"coordinates":[-89.369938,43.079877],"type":"Point"}
}