{
  "type": "Feature",
  "properties": {
    "iso:country":"US",
    "sg:address":"3734 E Garden Pl",
    "sg:city":"Oak Creek",
    "sg:classifiers":[
        {
            "category":"Building & Trades",
            "subcategory":"Construction",
            "type":"Services"
        }
    ],
    "sg:phone":"+1 414 762 9137",
    "sg:postcode":"53154",
    "sg:province":"WI",
    "sg:tags":[
        "roofing",
        "siding",
        "gutter",
        "contractor"
    ],
    "wof:name":"Kat Home Improvement Inc",
    "wof:placetype":"venue"
},
  "geometry": {"coordinates":[-87.86081900000001,42.866519],"type":"Point"}
}