{
  "type": "Feature",
  "properties": {
    "addr:full":"216 US Hwy 141 Little Suamico WI 54141",
    "addr:housenumber":"216",
    "addr:postcode":"54141",
    "addr:street":"Us Hwy 141",
    "iso:country":"US",
    "sg:address":"216 US Hwy 141",
    "sg:city":"Little Suamico",
    "sg:classifiers":[
        {
            "category":"Restaurant",
            "type":"Food & Drink"
        }
    ],
    "sg:phone":"+1 920 826 2842",
    "sg:postcode":"54141",
    "sg:province":"WI",
    "sg:tags":[
        "eating"
    ],
    "wof:name":"Arbys",
    "wof:placetype":"venue"
},
  "geometry": {"coordinates":[-88.050479,44.683188],"type":"Point"}
}