{
  "type": "Feature",
  "properties": {
    "iso:country":"US",
    "sg:address":"227 Fargo St",
    "sg:city":"Lake Mills",
    "sg:classifiers":[
        {
            "category":"Real Estate",
            "subcategory":"Architect",
            "type":"Services"
        },
        {
            "category":"Professional",
            "subcategory":"Business Services",
            "type":"Services"
        }
    ],
    "sg:phone":"+1 920 648 8077",
    "sg:postcode":"53551",
    "sg:province":"WI",
    "wof:name":"Tyranena Design LLC",
    "wof:placetype":"venue"
},
  "geometry": {"coordinates":[-88.905463,43.082788],"type":"Point"}
}