{
  "type": "Feature",
  "properties": {
    "iso:country":"US",
    "sg:address":"1000 N Lynndale Dr",
    "sg:city":"Appleton",
    "sg:classifiers":[
        {
            "category":"Shopping",
            "type":"Retail Goods"
        }
    ],
    "sg:phone":"+1 920 738 1819",
    "sg:postcode":"54914",
    "sg:province":"WI",
    "sg:tags":[
        "hearing",
        "equipment",
        "supply",
        "merchandise",
        "impaired"
    ],
    "wof:name":"Hearing Clinics of Wisconsin",
    "wof:placetype":"venue"
},
  "geometry": {"coordinates":[-88.445898,44.267941],"type":"Point"}
}