{
  "type": "Feature",
  "properties": {
    "iso:country":"US",
    "sg:address":"1528 N 36th St",
    "sg:city":"Sheboygan",
    "sg:classifiers":[
        {
            "category":"Arts & Performance",
            "subcategory":"Theater",
            "type":"Entertainment"
        }
    ],
    "sg:phone":"+1 920 457 2273",
    "sg:postcode":"53081",
    "sg:province":"WI",
    "sg:tags":[
        "music"
    ],
    "wof:name":"Anthony Martin Entertainer",
    "wof:placetype":"venue"
},
  "geometry": {"coordinates":[-87.754674,43.762058],"type":"Point"}
}