{
  "type": "Feature",
  "properties": {
    "iso:country":"US",
    "sg:address":"5759 S Meadow Park Dr",
    "sg:city":"Hales Corners",
    "sg:classifiers":[
        {
            "category":"Freight",
            "type":"Transportation"
        }
    ],
    "sg:phone":"+1 414 427 9565",
    "sg:postcode":"53130",
    "sg:province":"WI",
    "sg:tags":[
        "trucking"
    ],
    "wof:name":"E W Jones Trucking Co",
    "wof:placetype":"venue"
},
  "geometry": {"coordinates":[-88.03258,42.941457],"type":"Point"}
}