{
  "type": "Feature",
  "properties": {
    "iso:country":"US",
    "sg:address":"1385 Co Rd Ww",
    "sg:city":"Eleva",
    "sg:classifiers":[
        {
            "category":"Professional",
            "subcategory":"Research",
            "type":"Services"
        }
    ],
    "sg:phone":"+1 715 287 3549",
    "sg:postcode":"54738",
    "sg:province":"WI",
    "sg:tags":[
        "nonphysical",
        "commercial"
    ],
    "wof:name":"Sizer Communications",
    "wof:placetype":"venue"
},
  "geometry": {"coordinates":[-91.516733,44.627898],"type":"Point"}
}