{
  "type": "Feature",
  "properties": {
    "iso:country":"US",
    "sg:address":"711 Washington Rd",
    "sg:city":"Kenosha",
    "sg:classifiers":[
        {
            "category":"Building & Trades",
            "subcategory":"Construction",
            "type":"Services"
        }
    ],
    "sg:phone":"+1 262 652 9808",
    "sg:postcode":"53140",
    "sg:province":"WI",
    "sg:tags":[
        "woodworker"
    ],
    "wof:name":"Wood Tech Products Inc",
    "wof:placetype":"venue"
},
  "geometry": {"coordinates":[-87.821696,42.598825],"type":"Point"}
}