{
  "type": "Feature",
  "properties": {
    "iso:country":"US",
    "sg:address":"15791 Co Hwy B",
    "sg:city":"Butternut",
    "sg:classifiers":[
        {
            "category":"Manufacturing",
            "subcategory":"Lumber",
            "type":"Manufacturing & Wholesale Goods"
        }
    ],
    "sg:phone":"+1 715 762 3252",
    "sg:postcode":"54514",
    "sg:province":"WI",
    "sg:tags":[
        "sawmill"
    ],
    "wof:name":"Beaver Creek Forest Products",
    "wof:placetype":"venue"
},
  "geometry": {"coordinates":[-90.541869,45.941854],"type":"Point"}
}