{
  "type": "Feature",
  "properties": {
    "iso:country":"US",
    "sg:address":"9705 Co Rd I",
    "sg:city":"Clintonville",
    "sg:classifiers":[
        {
            "category":"Wholesale",
            "subcategory":"Machinery & Supplies",
            "type":"Manufacturing & Wholesale Goods"
        }
    ],
    "sg:phone":"+1 715 823 4110",
    "sg:postcode":"54929",
    "sg:province":"WI",
    "sg:tags":[
        "equipment",
        "parts",
        "sawmill",
        "mach"
    ],
    "sg:website":"www.johnsmillsupply.com",
    "wof:name":"John's Mill Supply",
    "wof:placetype":"venue"
},
  "geometry": {"coordinates":[-88.72350299999999,44.605159],"type":"Point"}
}