{
  "type": "Feature",
  "properties": {
    "iso:country":"US",
    "sg:address":"916 E State St",
    "sg:city":"Milwaukee",
    "sg:classifiers":[
        {
            "category":"Travel",
            "subcategory":"Hotels & Motels",
            "type":"Entertainment"
        }
    ],
    "sg:phone":"+1 414 276 8800",
    "sg:postcode":"53202",
    "sg:province":"WI",
    "sg:website":"www.parkeasthotel.com",
    "wof:name":"Park East Hotel",
    "wof:placetype":"venue"
},
  "geometry": {"coordinates":[-87.899676,43.044107],"type":"Point"}
}