{
  "type": "Feature",
  "properties": {
    "iso:country":"US",
    "sg:address":"625 S Wuthering Hills Dr",
    "sg:city":"Janesville",
    "sg:classifiers":[
        {
            "category":"Shopping",
            "type":"Retail Goods"
        }
    ],
    "sg:phone":"+1 608 373 7720",
    "sg:postcode":"53546",
    "sg:province":"WI",
    "sg:tags":[
        "equipment",
        "care",
        "health",
        "home"
    ],
    "wof:name":"Kinetic Concepts Inc",
    "wof:placetype":"venue"
},
  "geometry": {"coordinates":[-88.963431,42.670926],"type":"Point"}
}