{
  "type": "Feature",
  "properties": {
    "iso:country":"US",
    "sg:address":"1022 Sequoia Trl",
    "sg:city":"Madison",
    "sg:classifiers":[
        {
            "category":"Professional",
            "subcategory":"Computer Services",
            "type":"Services"
        }
    ],
    "sg:phone":"+1 608 255 2414",
    "sg:postcode":"53713",
    "sg:province":"WI",
    "sg:tags":[
        "website",
        "design"
    ],
    "wof:name":"Secure World Hosting LLC",
    "wof:placetype":"venue"
},
  "geometry": {"coordinates":[-89.402362,43.040657],"type":"Point"}
}