{
  "type": "Feature",
  "properties": {
    "iso:country":"US",
    "sg:address":"18862 State Hwy 29",
    "sg:city":"Wittenberg",
    "sg:classifiers":[
        {
            "category":"Wholesale",
            "subcategory":"Toys & Hobbies",
            "type":"Manufacturing & Wholesale Goods"
        }
    ],
    "sg:phone":"+1 715 253 2719",
    "sg:postcode":"54499",
    "sg:province":"WI",
    "sg:tags":[
        "firework"
    ],
    "wof:name":"Fireworks Country",
    "wof:placetype":"venue"
},
  "geometry": {"coordinates":[-89.202241,44.826934],"type":"Point"}
}