{
  "type": "Feature",
  "properties": {
    "iso:country":"US",
    "sg:address":"2721 State Hwy 33",
    "sg:city":"Mayville",
    "sg:classifiers":[
        {
            "category":"Building & Trades",
            "subcategory":"Construction",
            "type":"Services"
        }
    ],
    "sg:phone":"+1 920 387 5434",
    "sg:postcode":"53050",
    "sg:province":"WI",
    "sg:tags":[
        "water",
        "well",
        "drilling"
    ],
    "wof:name":"Rick's Well & Pump",
    "wof:placetype":"venue"
},
  "geometry": {"coordinates":[-88.52207799999999,43.442721],"type":"Point"}
}