{
  "type": "Feature",
  "properties": {
    "iso:country":"US",
    "sg:address":"2801 Burton Dr",
    "sg:city":"Waukesha",
    "sg:phone":"+1 262 524 9567",
    "sg:postcode":"53188",
    "sg:province":"WI",
    "sg:tags":[
        "leather",
        "product"
    ],
    "wof:name":"Deutsch Industrial Products",
    "wof:placetype":"venue"
},
  "geometry": {"coordinates":[-88.272263,43.016923],"type":"Point"}
}