{
  "type": "Feature",
  "properties": {
    "addr:full":"121 Spring St Berlin WI 54923",
    "addr:housenumber":"121",
    "addr:postcode":"54923",
    "addr:street":"Spring St",
    "iso:country":"US",
    "sg:address":"121 Spring St",
    "sg:city":"Berlin",
    "sg:classifiers":[
        {
            "category":"Social Services",
            "subcategory":"Child Care",
            "type":"Services"
        }
    ],
    "sg:phone":"+1 920 361 0563",
    "sg:postcode":"54923",
    "sg:province":"WI",
    "sg:tags":[
        "day"
    ],
    "wof:name":"Irene Colburn",
    "wof:placetype":"venue"
},
  "geometry": {"coordinates":[-88.94428000000001,43.967748],"type":"Point"}
}