{
  "type": "Feature",
  "properties": {
    "iso:country":"US",
    "sg:address":"606 E Wisconsin Ave",
    "sg:city":"Milwaukee",
    "sg:classifiers":[
        {
            "category":"Manufacturing",
            "subcategory":"Chemicals & Compounds",
            "type":"Manufacturing & Wholesale Goods"
        }
    ],
    "sg:phone":"+1 414 271 9110",
    "sg:postcode":"53202",
    "sg:province":"WI",
    "sg:tags":[
        "preparation",
        "pharmaceutical"
    ],
    "wof:name":"Pfizer",
    "wof:placetype":"venue"
},
  "geometry": {"coordinates":[-87.902828,43.039033],"type":"Point"}
}