{
  "type": "Feature",
  "properties": {
    "addr:full":"3355 N 47th St Milwaukee WI 53216",
    "addr:housenumber":"3355",
    "addr:postcode":"53216",
    "addr:street":"N 47Th St",
    "iso:country":"US",
    "sg:address":"3355 N 47th St",
    "sg:city":"Milwaukee",
    "sg:classifiers":[
        {
            "category":"Social Services",
            "subcategory":"Child Care",
            "type":"Services"
        }
    ],
    "sg:phone":"+1 414 442 8139",
    "sg:postcode":"53216",
    "sg:province":"WI",
    "wof:name":"Chocolate Chips Child Care",
    "wof:placetype":"venue"
},
  "geometry": {"coordinates":[-87.972628,43.081062],"type":"Point"}
}