{
  "type": "Feature",
  "properties": {
    "iso:country":"US",
    "sg:address":"1572 S 60th St",
    "sg:city":"Milwaukee",
    "sg:classifiers":[
        {
            "category":"Social Services",
            "subcategory":"Adult Care",
            "type":"Services"
        }
    ],
    "sg:phone":"+1 414 259 1257",
    "sg:postcode":"53214",
    "sg:province":"WI",
    "sg:tags":[
        "home",
        "group"
    ],
    "wof:name":"Creative Community Living Svc",
    "wof:placetype":"venue"
},
  "geometry": {"coordinates":[-87.987261,43.015284],"type":"Point"}
}