{
  "type": "Feature",
  "properties": {
    "iso:country":"US",
    "sg:address":"3484 Co Rd K",
    "sg:city":"Amherst Junction",
    "sg:classifiers":[
        {
            "category":"Building & Trades",
            "subcategory":"Construction",
            "type":"Services"
        }
    ],
    "sg:phone":"+1 715 824 5540",
    "sg:postcode":"54407",
    "sg:province":"WI",
    "sg:tags":[
        "contractor"
    ],
    "wof:name":"Steves Drywall Service LLC",
    "wof:placetype":"venue"
},
  "geometry": {"coordinates":[-89.365666,44.486837],"type":"Point"}
}