{
  "type": "Feature",
  "properties": {
    "addr:full":"3592 Jensen Ln Deerfield WI 53531",
    "addr:housenumber":"3592",
    "addr:postcode":"53531",
    "addr:street":"Jensen Ln",
    "iso:country":"US",
    "sg:address":"3592 Jensen Ln",
    "sg:city":"Deerfield",
    "sg:classifiers":[
        {
            "category":"Building & Trades",
            "subcategory":"Construction",
            "type":"Services"
        }
    ],
    "sg:phone":"+1 608 764 5541",
    "sg:postcode":"53531",
    "sg:province":"WI",
    "sg:tags":[
        "industrial"
    ],
    "wof:name":"Douglas Storms Construction",
    "wof:placetype":"venue"
},
  "geometry": {"coordinates":[-89.088573,43.047471],"type":"Point"}
}