{
  "type": "Feature",
  "properties": {
    "iso:country":"US",
    "sg:address":"301 Riverside Dr",
    "sg:city":"Madison",
    "sg:classifiers":[
        {
            "category":"Organizations",
            "subcategory":"Religious Organization",
            "type":"Services"
        }
    ],
    "sg:phone":"+1 608 244 3656",
    "sg:postcode":"53704",
    "sg:province":"WI",
    "sg:tags":[
        "church"
    ],
    "sg:website":"www.bethanyfreechurch.org",
    "wof:name":"Bethany Evangelical Free Chr",
    "wof:placetype":"venue"
},
  "geometry": {"coordinates":[-89.356394,43.087592],"type":"Point"}
}