{
  "type": "Feature",
  "properties": {
    "addr:full":"3536 Siggelkow Rd Mc Farland WI 53558",
    "addr:housenumber":"3536",
    "addr:postcode":"53558",
    "addr:street":"Siggelkow Rd",
    "iso:country":"US",
    "sg:address":"3536 Siggelkow Rd",
    "sg:city":"Mc Farland",
    "sg:classifiers":[
        {
            "category":"Building & Trades",
            "subcategory":"Construction",
            "type":"Services"
        }
    ],
    "sg:phone":"+1 608 838 8271",
    "sg:postcode":"53558",
    "sg:province":"WI",
    "sg:tags":[
        "house"
    ],
    "wof:name":"Albrecht Construction Inc",
    "wof:placetype":"venue"
},
  "geometry": {"coordinates":[-89.279731,43.026367],"type":"Point"}
}