{
  "type": "Feature",
  "properties": {
    "iso:country":"US",
    "sg:address":"2639 N Humboldt Blvd",
    "sg:city":"Milwaukee",
    "sg:classifiers":[
        {
            "category":"Building & Trades",
            "subcategory":"Construction",
            "type":"Services"
        }
    ],
    "sg:phone":"+1 414 264 6830",
    "sg:postcode":"53212",
    "sg:province":"WI",
    "sg:tags":[
        "painter"
    ],
    "wof:name":"On The Mark Home Improvement",
    "wof:placetype":"venue"
},
  "geometry": {"coordinates":[-87.897927,43.066707],"type":"Point"}
}