{
  "type": "Feature",
  "properties": {
    "iso:country":"US",
    "sg:address":"1961 Bellevue St",
    "sg:city":"Green Bay",
    "sg:classifiers":[
        {
            "category":"Building & Trades",
            "subcategory":"Construction",
            "type":"Services"
        }
    ],
    "sg:phone":"+1 920 468 4485",
    "sg:postcode":"54311",
    "sg:province":"WI",
    "sg:tags":[
        "b",
        "family",
        "commercial",
        "general",
        "home",
        "contractor"
    ],
    "wof:name":"Earl P Zolper Construction Co",
    "wof:placetype":"venue"
},
  "geometry": {"coordinates":[-88.001231,44.471269],"type":"Point"}
}