{
  "type": "Feature",
  "properties": {
    "iso:country":"US",
    "sg:address":"5936 Seminole Centre Ct",
    "sg:city":"Fitchburg",
    "sg:classifiers":[
        {
            "category":"Organizations",
            "subcategory":"Professional Association",
            "type":"Services"
        }
    ],
    "sg:phone":"+1 608 288 1133",
    "sg:postcode":"53711",
    "sg:province":"WI",
    "sg:tags":[
        "business",
        "real estate"
    ],
    "sg:website":"www.maba.org",
    "wof:name":"Madison Area Builders Assn",
    "wof:placetype":"venue"
},
  "geometry": {"coordinates":[-89.454864,43.014308],"type":"Point"}
}