{
  "type": "Feature",
  "properties": {
    "addr:full":"4865 S 27th St Milwaukee WI 53221",
    "addr:housenumber":"4865",
    "addr:postcode":"53221",
    "addr:street":"S 27Th St",
    "iso:country":"US",
    "sg:address":"4865 S 27th St",
    "sg:city":"Milwaukee",
    "sg:classifiers":[
        {
            "category":"Sports & Exercise",
            "subcategory":"Gym",
            "type":"Entertainment"
        }
    ],
    "sg:phone":"+1 414 281 8500",
    "sg:postcode":"53221",
    "sg:province":"WI",
    "sg:tags":[
        "club",
        "health",
        "studio",
        "gymnasium"
    ],
    "wof:name":"Curves For Women",
    "wof:placetype":"venue"
},
  "geometry": {"coordinates":[-87.948853,42.956952],"type":"Point"}
}