{
  "type": "Feature",
  "properties": {
    "iso:country":"US",
    "sg:address":"5860 Forest Ln",
    "sg:city":"Rhinelander",
    "sg:classifiers":[
        {
            "category":"Building & Trades",
            "subcategory":"Construction",
            "type":"Services"
        }
    ],
    "sg:phone":"+1 715 362 8837",
    "sg:postcode":"54501",
    "sg:province":"WI",
    "sg:tags":[
        "downspouts",
        "gutter"
    ],
    "wof:name":"Ad-Vantage Seamless Gutter",
    "wof:placetype":"venue"
},
  "geometry": {"coordinates":[-89.45088199999999,45.651009],"type":"Point"}
}