{
  "type": "Feature",
  "properties": {
    "iso:country":"US",
    "sg:address":"800 Wisconsin St",
    "sg:city":"Eau Claire",
    "sg:classifiers":[
        {
            "category":"Manufacturing",
            "subcategory":"Tools & Machinery",
            "type":"Manufacturing & Wholesale Goods"
        }
    ],
    "sg:phone":"+1 715 839 9585",
    "sg:postcode":"54703",
    "sg:province":"WI",
    "sg:tags":[
        "fixture",
        "commercial",
        "electrical",
        "lighting",
        "mfg"
    ],
    "wof:name":"Ldpi Lighting",
    "wof:placetype":"venue"
},
  "geometry": {"coordinates":[-91.49755399999999,44.815965],"type":"Point"}
}