{
  "type": "Feature",
  "properties": {
    "iso:country":"US",
    "sg:address":"8265 N 49th St",
    "sg:city":"Milwaukee",
    "sg:classifiers":[
        {
            "category":"Retail",
            "subcategory":"Laundry & Dry Cleaning",
            "type":"Services"
        },
        {
            "category":"Building & Trades",
            "subcategory":"Cleaning & Sanitation",
            "type":"Services"
        }
    ],
    "sg:phone":"+1 414 354 7151",
    "sg:postcode":"53223",
    "sg:province":"WI",
    "sg:tags":[
        "cleaner",
        "fabric",
        "rug",
        "protection",
        "furniture",
        "carpet"
    ],
    "wof:name":"Brown Deer Carpet Cleaning",
    "wof:placetype":"venue"
},
  "geometry": {"coordinates":[-87.97177499999999,43.167544],"type":"Point"}
}