{
  "type": "Feature",
  "properties": {
    "iso:country":"US",
    "sg:address":"2100 Stewart Ave",
    "sg:city":"Wausau",
    "sg:classifiers":[
        {
            "category":"Professional",
            "subcategory":"Employment Agencies",
            "type":"Services"
        }
    ],
    "sg:phone":"+1 715 845 4245",
    "sg:postcode":"54401",
    "sg:province":"WI",
    "sg:tags":[
        "temporary",
        "help"
    ],
    "wof:name":"Manpower",
    "wof:placetype":"venue"
},
  "geometry": {"coordinates":[-89.663292,44.958582],"type":"Point"}
}