{
  "type": "Feature",
  "properties": {
    "iso:country":"US",
    "sg:address":"930 W Main St",
    "sg:city":"Whitewater",
    "sg:classifiers":[
        {
            "category":"Arts & Performance",
            "subcategory":"Theater",
            "type":"Entertainment"
        }
    ],
    "sg:phone":"+1 262 472 4444",
    "sg:postcode":"53190",
    "sg:province":"WI",
    "sg:tags":[
        "building",
        "theatrical",
        "o",
        "nonresidential"
    ],
    "wof:name":"Young Auditorium Uw Whitewater",
    "wof:placetype":"venue"
},
  "geometry": {"coordinates":[-88.74401400000001,42.835016],"type":"Point"}
}