{
  "type": "Feature",
  "properties": {
    "iso:country":"US",
    "sg:address":"903 E Tennessee Ave",
    "sg:city":"Oshkosh",
    "sg:classifiers":[
        {
            "category":"Organizations",
            "subcategory":"Religious Organization",
            "type":"Services"
        }
    ],
    "sg:phone":"+1 920 410 0921",
    "sg:postcode":"54901",
    "sg:province":"WI",
    "sg:tags":[
        "church"
    ],
    "wof:name":"Our Father's House Church",
    "wof:placetype":"venue"
},
  "geometry": {"coordinates":[-88.525108,44.033373],"type":"Point"}
}