{
  "type": "Feature",
  "properties": {
    "addr:full":"4702 Dutch Mill Rd Madison WI 53716",
    "addr:housenumber":"4702",
    "addr:postcode":"53716",
    "addr:street":"Dutch Mill Rd",
    "iso:country":"US",
    "sg:address":"4702 Dutch Mill Rd",
    "sg:city":"Madison",
    "sg:classifiers":[
        {
            "category":"Building & Trades",
            "subcategory":"Construction",
            "type":"Services"
        }
    ],
    "sg:phone":"+1 608 221 9119",
    "sg:postcode":"53716",
    "sg:province":"WI",
    "sg:tags":[
        "mobile",
        "home",
        "repair"
    ],
    "wof:name":"Dutch Mill Contractors",
    "wof:placetype":"venue"
},
  "geometry": {"coordinates":[-89.300454,43.05024],"type":"Point"}
}