{
  "type": "Feature",
  "properties": {
    "addr:full":"3554 E Washington Ave Madison WI 53704",
    "addr:housenumber":"3554",
    "addr:postcode":"53704",
    "addr:street":"E Washington Ave",
    "iso:country":"US",
    "sg:address":"3554 E Washington Ave",
    "sg:city":"Madison",
    "sg:classifiers":[
        {
            "category":"Bars & Pubs",
            "type":"Food & Drink"
        }
    ],
    "sg:phone":"+1 608 244 9771",
    "sg:postcode":"53704",
    "sg:province":"WI",
    "sg:tags":[
        "club",
        "night"
    ],
    "sg:website":"www.visionsnightclub.com",
    "wof:name":"Visions Night Club",
    "wof:placetype":"venue"
},
  "geometry": {"coordinates":[-89.32696,43.115376],"type":"Point"}
}