{
  "type": "Feature",
  "properties": {
    "addr:full":"21020 Aspen Ave Warrens WI 54666",
    "addr:housenumber":"21020",
    "addr:postcode":"54666",
    "addr:street":"Aspen Ave",
    "iso:country":"US",
    "sg:address":"21020 Aspen Ave",
    "sg:city":"Warrens",
    "sg:classifiers":[
        {
            "category":"Building & Trades",
            "subcategory":"Construction",
            "type":"Services"
        }
    ],
    "sg:phone":"+1 608 797 2664",
    "sg:postcode":"54666",
    "sg:province":"WI",
    "sg:tags":[
        "concrete",
        "contractor"
    ],
    "wof:name":"Outdoor Image LLC",
    "wof:placetype":"venue"
},
  "geometry": {"coordinates":[-90.55554100000001,44.143793],"type":"Point"}
}