{
  "type": "Feature",
  "properties": {
    "addr:full":"17797 Dayton Ridge Rd Richland Center WI 53581",
    "addr:housenumber":"17797",
    "addr:postcode":"53581",
    "addr:street":"Dayton Ridge Rd",
    "iso:country":"US",
    "sg:address":"17797 Dayton Ridge Rd",
    "sg:city":"Richland Center",
    "sg:classifiers":[
        {
            "category":"Wholesale",
            "subcategory":"Machinery & Supplies",
            "type":"Manufacturing & Wholesale Goods"
        }
    ],
    "sg:phone":"+1 608 536 3700",
    "sg:postcode":"53581",
    "sg:province":"WI",
    "sg:tags":[
        "contractor"
    ],
    "wof:name":"Great Northern Construction",
    "wof:placetype":"venue"
},
  "geometry": {"coordinates":[-90.510755,43.334135],"type":"Point"}
}