{
  "type": "Feature",
  "properties": {
    "iso:country":"US",
    "sg:address":"651 Springbrook Cir",
    "sg:city":"De Forest",
    "sg:classifiers":[
        {
            "category":"Manufacturing",
            "subcategory":"Lumber",
            "type":"Manufacturing & Wholesale Goods"
        }
    ],
    "sg:phone":"+1 608 846 7808",
    "sg:postcode":"53532",
    "sg:province":"WI",
    "sg:tags":[
        "farm",
        "crop",
        "general",
        "tract",
        "operation",
        "timber"
    ],
    "wof:name":"Dedolph Farms",
    "wof:placetype":"venue"
},
  "geometry": {"coordinates":[-89.353081,43.256741],"type":"Point"}
}