{
  "type": "Feature",
  "properties": {
    "iso:country":"US",
    "sg:address":"4001 W Cheyenne St",
    "sg:city":"Milwaukee",
    "sg:classifiers":[
        {
            "category":"Building & Trades",
            "subcategory":"Construction",
            "type":"Services"
        }
    ],
    "sg:phone":"+1 414 228 9167",
    "sg:postcode":"53209",
    "sg:province":"WI",
    "sg:tags":[
        "contractor"
    ],
    "wof:name":"Absolute Drywall",
    "wof:placetype":"venue"
},
  "geometry": {"coordinates":[-87.962046,43.142337],"type":"Point"}
}