{
  "type": "Feature",
  "properties": {
    "iso:country":"US",
    "sg:address":"123 N Jackson St",
    "sg:city":"Janesville",
    "sg:classifiers":[
        {
            "category":"Real Estate",
            "subcategory":"Real Estate Agent",
            "type":"Services"
        }
    ],
    "sg:phone":"+1 608 754 2266",
    "sg:postcode":"53548",
    "sg:province":"WI",
    "sg:tags":[
        "manager"
    ],
    "wof:name":"Smith R K Rlty Prprty Managers",
    "wof:placetype":"venue"
},
  "geometry": {"coordinates":[-89.028565,42.683383],"type":"Point"}
}