{
  "type": "Feature",
  "properties": {
    "iso:country":"US",
    "sg:address":"521 6th St",
    "sg:city":"Monroe",
    "sg:classifiers":[
        {
            "category":"Real Estate",
            "subcategory":"Real Estate Services",
            "type":"Services"
        },
        {
            "category":"Real Estate",
            "subcategory":"Developer",
            "type":"Services"
        },
        {
            "category":"Real Estate",
            "subcategory":"Real Estate Agent",
            "type":"Services"
        }
    ],
    "sg:phone":"+1 608 328 8211",
    "sg:postcode":"53566",
    "sg:province":"WI",
    "sg:tags":[
        "buyer",
        "broker"
    ],
    "wof:name":"John Bruni Archetecht",
    "wof:placetype":"venue"
},
  "geometry": {"coordinates":[-89.652717,42.606636],"type":"Point"}
}