{
  "type": "Feature",
  "properties": {
    "iso:country":"US",
    "sg:address":"N116w15841 Main St",
    "sg:city":"Germantown",
    "sg:classifiers":[
        {
            "category":"Restaurant",
            "type":"Food & Drink"
        }
    ],
    "sg:phone":"+1 262 251 4455",
    "sg:postcode":"53022",
    "sg:province":"WI",
    "sg:tags":[
        "american"
    ],
    "sg:website":"http://www.jerrysworldfamousribs.com",
    "wof:name":"Jerry's Old Town Inn",
    "wof:placetype":"venue"
},
  "geometry": {"coordinates":[-88.107212,43.22826],"type":"Point"}
}