{
  "type": "Feature",
  "properties": {
    "iso:country":"US",
    "sg:address":"204 S Main St",
    "sg:city":"Alma",
    "sg:classifiers":[
        {
            "category":"Health Services",
            "subcategory":"Doctor",
            "type":"Services"
        }
    ],
    "sg:phone":"+1 608 685 3241",
    "sg:postcode":"54610",
    "sg:province":"WI",
    "sg:tags":[
        "medical"
    ],
    "wof:name":"Alma Clinic",
    "wof:placetype":"venue"
},
  "geometry": {"coordinates":[-91.914542,44.3191],"type":"Point"}
}