{
  "type": "Feature",
  "properties": {
    "iso:country":"US",
    "sg:address":"5734 Co Rd D",
    "sg:city":"Princeton",
    "sg:classifiers":[
        {
            "category":"Wholesale",
            "subcategory":"Machinery & Supplies",
            "type":"Manufacturing & Wholesale Goods"
        }
    ],
    "sg:phone":"+1 920 295 6572",
    "sg:postcode":"54968",
    "sg:province":"WI",
    "wof:name":"Cliffs Inc",
    "wof:placetype":"venue"
},
  "geometry": {"coordinates":[-89.122647,43.840058],"type":"Point"}
}