{
  "type": "Feature",
  "properties": {
    "iso:country":"US",
    "sg:address":"1369 Huckleberry Rd",
    "sg:city":"Edgar",
    "sg:classifiers":[
        {
            "category":"Farming",
            "subcategory":"Dairy Farm",
            "type":"Manufacturing & Wholesale Goods"
        }
    ],
    "sg:phone":"+1 715 352 3154",
    "sg:postcode":"54426",
    "sg:province":"WI",
    "wof:name":"Rick Schwoerer",
    "wof:placetype":"venue"
},
  "geometry": {"coordinates":[-90.084818,44.916383],"type":"Point"}
}