{
  "type": "Feature",
  "properties": {
    "iso:country":"US",
    "sg:address":"2810 Fish Hatchery Rd",
    "sg:city":"Madison",
    "sg:classifiers":[
        {
            "category":"Autos & Motor Vehicles",
            "subcategory":"Fuel & Gas Station",
            "type":"Retail Goods"
        }
    ],
    "sg:phone":"+1 608 271 9779",
    "sg:postcode":"53713",
    "sg:province":"WI",
    "sg:tags":[
        "grocery",
        "station",
        "gasoline"
    ],
    "wof:name":"Speedway 4170",
    "wof:placetype":"venue"
},
  "geometry": {"coordinates":[-89.41065,43.029427],"type":"Point"}
}