{
  "type": "Feature",
  "properties": {
    "iso:country":"US",
    "sg:address":"1239 Co Rd H",
    "sg:city":"New Richmond",
    "sg:classifiers":[
        {
            "category":"Freight",
            "type":"Transportation"
        }
    ],
    "sg:phone":"+1 715 248 7277",
    "sg:postcode":"54017",
    "sg:province":"WI",
    "sg:tags":[
        "trucking"
    ],
    "wof:name":"Redneck Transport",
    "wof:placetype":"venue"
},
  "geometry": {"coordinates":[-92.558863,45.197173],"type":"Point"}
}