{
  "type": "Feature",
  "properties": {
    "iso:country":"US",
    "sg:address":"600 S Monroe St",
    "sg:city":"New Lisbon",
    "sg:classifiers":[
        {
            "category":"Health Services",
            "subcategory":"Doctor",
            "type":"Services"
        }
    ],
    "sg:phone":"+1 608 562 3111",
    "sg:postcode":"53950",
    "sg:province":"WI",
    "sg:tags":[
        "medical",
        "clinic"
    ],
    "wof:name":"New Lisbon Community Clinic",
    "wof:placetype":"venue"
},
  "geometry": {"coordinates":[-90.165505,43.874868],"type":"Point"}
}