{
  "type": "Feature",
  "properties": {
    "iso:country":"US",
    "sg:address":"4440 Poplar Rd",
    "sg:city":"Tony",
    "sg:classifiers":[
        {
            "category":"Farming",
            "subcategory":"Dairy Farm",
            "type":"Manufacturing & Wholesale Goods"
        }
    ],
    "sg:phone":"+1 715 532 3035",
    "sg:postcode":"54563",
    "sg:province":"WI",
    "wof:name":"Lavaugh Farms",
    "wof:placetype":"venue"
},
  "geometry": {"coordinates":[-90.976754,45.430643],"type":"Point"}
}