{
  "type": "Feature",
  "properties": {
    "iso:country":"US",
    "sg:address":"1133 Horicon St",
    "sg:city":"Mayville",
    "sg:classifiers":[
        {
            "category":"Autos & Motor Vehicles",
            "subcategory":"Automobile Sales",
            "type":"Retail Goods"
        }
    ],
    "sg:phone":"+1 920 387 9568",
    "sg:postcode":"53050",
    "sg:province":"WI",
    "sg:tags":[
        "car",
        "dealer"
    ],
    "wof:name":"J J's Auto Spa",
    "wof:placetype":"venue"
},
  "geometry": {"coordinates":[-88.559331,43.494036],"type":"Point"}
}