{
  "type": "Feature",
  "properties": {
    "addr:full":"290 Jonsue Ln Racine WI 53402",
    "addr:housenumber":"290",
    "addr:postcode":"53402",
    "addr:street":"Jonsue Ln",
    "iso:country":"US",
    "sg:address":"290 Jonsue Ln",
    "sg:city":"Racine",
    "sg:classifiers":[
        {
            "category":"Education",
            "subcategory":"School",
            "type":"Public Place"
        }
    ],
    "sg:phone":"+1 262 664 6125",
    "sg:postcode":"53402",
    "sg:province":"WI",
    "sg:tags":[
        "elementary"
    ],
    "wof:name":"Wind Point Elementary School",
    "wof:placetype":"venue"
},
  "geometry": {"coordinates":[-87.78050399999999,42.782803],"type":"Point"}
}