{
  "type": "Feature",
  "properties": {
    "iso:country":"US",
    "sg:address":"300 S Main St",
    "sg:city":"Birchwood",
    "sg:classifiers":[
        {
            "category":"Restaurant",
            "type":"Food & Drink"
        }
    ],
    "sg:phone":"+1 715 354 7087",
    "sg:postcode":"54817",
    "sg:province":"WI",
    "wof:name":"Porch",
    "wof:placetype":"venue"
},
  "geometry": {"coordinates":[-91.555873,45.653658],"type":"Point"}
}