{
  "type": "Feature",
  "properties": {
    "iso:country":"US",
    "sg:address":"2631 Northern Rd",
    "sg:city":"Appleton",
    "sg:classifiers":[
        {
            "category":"Real Estate",
            "subcategory":"Real Estate Operator",
            "type":"Services"
        }
    ],
    "sg:phone":"+1 920 733 6102",
    "sg:postcode":"54914",
    "sg:province":"WI",
    "sg:tags":[
        "building",
        "nonresidential"
    ],
    "wof:name":"A L Boettcher & Co Inc",
    "wof:placetype":"venue"
},
  "geometry": {"coordinates":[-88.461472,44.243251],"type":"Point"}
}