{
  "type": "Feature",
  "properties": {
    "iso:country":"US",
    "sg:address":"1801 Hillcrest Dr",
    "sg:city":"Kaukauna",
    "sg:classifiers":[
        {
            "category":"Travel",
            "subcategory":"Campground",
            "type":"Entertainment"
        }
    ],
    "sg:phone":"+1 920 766 9880",
    "sg:postcode":"54130",
    "sg:province":"WI",
    "sg:tags":[
        "camp"
    ],
    "wof:name":"Winnecomac Girl Scout Camp",
    "wof:placetype":"venue"
},
  "geometry": {"coordinates":[-88.255735,44.26315],"type":"Point"}
}