{
  "type": "Feature",
  "properties": {
    "iso:country":"US",
    "sg:address":"34688 145th Ave",
    "sg:city":"Stanley",
    "sg:classifiers":[
        {
            "category":"Retail",
            "subcategory":"Auto Repair",
            "type":"Services"
        }
    ],
    "sg:phone":"+1 715 644 5559",
    "sg:postcode":"54768",
    "sg:province":"WI",
    "sg:tags":[
        "automotive"
    ],
    "wof:name":"Bobs Service Shop",
    "wof:placetype":"venue"
},
  "geometry": {"coordinates":[-90.969961,45.052965],"type":"Point"}
}