{
  "type": "Feature",
  "properties": {
    "iso:country":"US",
    "sg:address":"603 Chieftain St",
    "sg:city":"Osceola",
    "sg:phone":"+1 715 294 3255",
    "sg:postcode":"54020",
    "sg:province":"WI",
    "wof:name":"John Letch Realty",
    "wof:placetype":"venue"
},
  "geometry": {"coordinates":[-92.702527,45.323372],"type":"Point"}
}