{
  "type": "Feature",
  "properties": {
    "iso:country":"US",
    "sg:address":"18175 Redvere Dr",
    "sg:city":"Brookfield",
    "sg:classifiers":[
        {
            "category":"Organizations",
            "subcategory":"Religious Organization",
            "type":"Services"
        }
    ],
    "sg:phone":"+1 262 783 5975",
    "sg:postcode":"53045",
    "sg:province":"WI",
    "sg:tags":[
        "clergy"
    ],
    "wof:name":"John Bylsma",
    "wof:placetype":"venue"
},
  "geometry": {"coordinates":[-88.137492,43.098433],"type":"Point"}
}