{
  "type": "Feature",
  "properties": {
    "iso:country":"US",
    "sg:address":"512 Westgate Mall",
    "sg:city":"Madison",
    "sg:classifiers":[
        {
            "category":"Shopping",
            "subcategory":"Hobbies, Toys, & Games",
            "type":"Retail Goods"
        }
    ],
    "sg:phone":"+1 608 274 1610",
    "sg:postcode":"53711",
    "sg:province":"WI",
    "sg:tags":[
        "shop",
        "rock"
    ],
    "wof:name":"Relics",
    "wof:placetype":"venue"
},
  "geometry": {"coordinates":[-89.472347,43.051964],"type":"Point"}
}