{
  "type": "Feature",
  "properties": {
    "addr:full":"805 N Main St Lake Mills WI 53551",
    "addr:housenumber":"805",
    "addr:postcode":"53551",
    "addr:street":"N Main St",
    "iso:country":"US",
    "sg:address":"805 N Main St",
    "sg:city":"Lake Mills",
    "sg:classifiers":[
        {
            "category":"Shopping",
            "subcategory":"Music",
            "type":"Retail Goods"
        },
        {
            "category":"Cinema",
            "subcategory":"Movie Rental",
            "type":"Entertainment"
        }
    ],
    "sg:phone":"+1 920 648 5007",
    "sg:postcode":"53551",
    "sg:province":"WI",
    "sg:tags":[
        "leasing",
        "video",
        "disc",
        "tape"
    ],
    "wof:name":"Movie Magic Inc",
    "wof:placetype":"venue"
},
  "geometry": {"coordinates":[-88.909447,43.089366],"type":"Point"}
}