{
  "type": "Feature",
  "properties": {
    "iso:country":"US",
    "sg:address":"9304 S Oak Creek Ct",
    "sg:city":"Franklin",
    "sg:classifiers":[
        {
            "category":"Professional",
            "subcategory":"Business Services",
            "type":"Services"
        }
    ],
    "sg:phone":"+1 414 855 0211",
    "sg:postcode":"53132",
    "sg:province":"WI",
    "wof:name":"Gamboa Enterprises LLC",
    "wof:placetype":"venue"
},
  "geometry": {"coordinates":[-87.965952,42.875443],"type":"Point"}
}