{
  "type": "Feature",
  "properties": {
    "iso:country":"US",
    "sg:address":"6317 Rostad Dr",
    "sg:city":"Windsor",
    "sg:classifiers":[
        {
            "category":"Professional",
            "type":"Services"
        }
    ],
    "sg:phone":"+1 608 846 7787",
    "sg:postcode":"53598",
    "sg:province":"WI",
    "sg:tags":[
        "establishment"
    ],
    "wof:name":"Stockade",
    "wof:placetype":"venue"
},
  "geometry": {"coordinates":[-89.338894,43.193019],"type":"Point"}
}