{
  "type": "Feature",
  "properties": {
    "iso:country":"US",
    "sg:address":"6811 103rd Ave",
    "sg:city":"Kenosha",
    "sg:classifiers":[
        {
            "category":"Shopping",
            "subcategory":"Jewelry",
            "type":"Retail Goods"
        }
    ],
    "sg:phone":"+1 262 697 9191",
    "sg:postcode":"53142",
    "sg:province":"IL",
    "wof:name":"Zale Group",
    "wof:placetype":"venue"
},
  "geometry": {"coordinates":[-87.933284,42.572881],"type":"Point"}
}