{
  "type": "Feature",
  "properties": {
    "iso:country":"US",
    "sg:address":"8031 N 94th St",
    "sg:city":"Milwaukee",
    "sg:classifiers":[
        {
            "category":"Home & Garden",
            "subcategory":"Home Furnishings",
            "type":"Retail Goods"
        }
    ],
    "sg:phone":"+1 414 365 3010",
    "sg:postcode":"53224",
    "sg:province":"WI",
    "sg:tags":[
        "bathroom",
        "fixture",
        "accessory"
    ],
    "wof:name":"S B Products The Hang Away",
    "wof:placetype":"venue"
},
  "geometry": {"coordinates":[-88.029167,43.163781],"type":"Point"}
}