{
  "type": "Feature",
  "properties": {
    "iso:country":"US",
    "sg:address":"4645 Co Rd K",
    "sg:city":"Reedsburg",
    "sg:classifiers":[
        {
            "category":"Farming",
            "subcategory":"Dairy Farm",
            "type":"Manufacturing & Wholesale Goods"
        }
    ],
    "sg:phone":"+1 608 524 1901",
    "sg:postcode":"53959",
    "sg:province":"WI",
    "wof:name":"Dale Culp Culp Farms",
    "wof:placetype":"venue"
},
  "geometry": {"coordinates":[-90.08858499999999,43.517142],"type":"Point"}
}