{
  "type": "Feature",
  "properties": {
    "iso:country":"US",
    "sg:address":"3309 W National Ave",
    "sg:city":"Milwaukee",
    "sg:classifiers":[
        {
            "category":"Professional",
            "subcategory":"Business Services",
            "type":"Services"
        }
    ],
    "sg:phone":"+1 414 383 9662",
    "sg:postcode":"53215",
    "sg:province":"WI",
    "sg:tags":[
        "sales",
        "estate"
    ],
    "wof:name":"Trio Wolf 2 Estate Stores",
    "wof:placetype":"venue"
},
  "geometry": {"coordinates":[-87.955799,43.021648],"type":"Point"}
}