{
  "type": "Feature",
  "properties": {
    "iso:country":"US",
    "sg:address":"325 Oak Grove Ave",
    "sg:city":"South Beloit",
    "sg:classifiers":[
        {
            "category":"Organizations",
            "subcategory":"Religious Organization",
            "type":"Services"
        }
    ],
    "sg:phone":"+1 815 389 9091",
    "sg:postcode":"61080",
    "sg:province":"WI",
    "sg:tags":[
        "church"
    ],
    "wof:name":"St Peter's Religious",
    "wof:placetype":"venue"
},
  "geometry": {"coordinates":[-89.041331,42.48776],"type":"Point"}
}