{
  "type": "Feature",
  "properties": {
    "iso:country":"US",
    "sg:address":"3006 Essen Rd",
    "sg:city":"Green Bay",
    "sg:classifiers":[
        {
            "category":"Shopping",
            "type":"Retail Goods"
        }
    ],
    "sg:phone":"+1 920 465 0808",
    "sg:postcode":"54311",
    "sg:province":"WI",
    "sg:tags":[
        "merchandise"
    ],
    "wof:name":"Dog Guard Pet Fencing",
    "wof:placetype":"venue"
},
  "geometry": {"coordinates":[-87.931161,44.461077],"type":"Point"}
}