{
  "type": "Feature",
  "properties": {
    "iso:country":"US",
    "sg:address":"1900 Kentucky St",
    "sg:city":"Racine",
    "sg:classifiers":[
        {
            "category":"Local Transit",
            "type":"Transportation"
        },
        {
            "category":"Government",
            "subcategory":"Office",
            "type":"Public Place"
        }
    ],
    "sg:phone":"+1 262 637 9000",
    "sg:postcode":"53405",
    "sg:province":"WI",
    "sg:tags":[
        "bus",
        "township",
        "government-city",
        "line",
        "village"
    ],
    "wof:name":"Bus The Belle Urban System",
    "wof:placetype":"venue"
},
  "geometry": {"coordinates":[-87.829628,42.707199],"type":"Point"}
}