{
  "type": "Feature",
  "properties": {
    "iso:country":"US",
    "sg:address":"1110 Milwaukee Ave",
    "sg:city":"South Milwaukee",
    "sg:classifiers":[
        {
            "category":"Real Estate",
            "subcategory":"Real Estate Operator",
            "type":"Services"
        }
    ],
    "sg:phone":"+1 414 764 0668",
    "sg:postcode":"53172",
    "sg:province":"WI",
    "sg:tags":[
        "building",
        "nonresidential"
    ],
    "wof:name":"Gvh Properties LLC",
    "wof:placetype":"venue"
},
  "geometry": {"coordinates":[-87.862741,42.910805],"type":"Point"}
}