{
  "type": "Feature",
  "properties": {
    "iso:country":"US",
    "sg:address":"1001 Delafield St",
    "sg:city":"Waukesha",
    "sg:classifiers":[
        {
            "category":"Real Estate",
            "subcategory":"Real Estate Operator",
            "type":"Services"
        }
    ],
    "sg:phone":"+1 262 548 9786",
    "sg:postcode":"53188",
    "sg:province":"WI",
    "sg:tags":[
        "building",
        "apartment"
    ],
    "wof:name":"Willow Park Apts",
    "wof:placetype":"venue"
},
  "geometry": {"coordinates":[-88.240092,43.021318],"type":"Point"}
}