{
  "type": "Feature",
  "properties": {
    "iso:country":"US",
    "sg:address":"525 Flight Rd",
    "sg:city":"Antigo",
    "sg:classifiers":[
        {
            "category":"Health Services",
            "subcategory":"Nursing And Care Facility",
            "type":"Services"
        }
    ],
    "sg:phone":"+1 715 627 4403",
    "sg:postcode":"54409",
    "sg:province":"WI",
    "sg:tags":[
        "intermediate"
    ],
    "wof:name":"Pine Meadow Retirement Communi",
    "wof:placetype":"venue"
},
  "geometry": {"coordinates":[-89.13440900000001,45.147404],"type":"Point"}
}