{
  "type": "Feature",
  "properties": {
    "iso:country":"US",
    "sg:address":"100 E Headquarters Rd",
    "sg:city":"Sparta",
    "sg:classifiers":[
        {
            "category":"Government",
            "subcategory":"Office",
            "type":"Public Place"
        }
    ],
    "sg:phone":"+1 608 388 4209",
    "sg:postcode":"54656",
    "sg:province":"WI",
    "sg:tags":[
        "national",
        "security"
    ],
    "wof:name":"Fort Mc Coy",
    "wof:placetype":"venue"
},
  "geometry": {"coordinates":[-90.682233,44.025134],"type":"Point"}
}