{
  "type": "Feature",
  "properties": {
    "iso:country":"US",
    "sg:address":"2025 Wyoming Ave",
    "sg:city":"Sun Prairie",
    "sg:classifiers":[
        {
            "category":"Real Estate",
            "subcategory":"Real Estate Operator",
            "type":"Services"
        }
    ],
    "sg:phone":"+1 608 837 8369",
    "sg:postcode":"53590",
    "sg:province":"WI",
    "sg:tags":[
        "building",
        "apartment"
    ],
    "wof:name":"Oakview Garden Apartments",
    "wof:placetype":"venue"
},
  "geometry": {"coordinates":[-89.24910800000001,43.178587],"type":"Point"}
}