{
  "type": "Feature",
  "properties": {
    "iso:country":"US",
    "sg:address":"1428 Peters Rd",
    "sg:city":"Sharon",
    "sg:classifiers":[
        {
            "category":"Real Estate",
            "subcategory":"Real Estate Operator",
            "type":"Services"
        }
    ],
    "sg:phone":"+1 262 736 3600",
    "sg:postcode":"53585",
    "sg:province":"WI",
    "sg:tags":[
        "property",
        "lessor"
    ],
    "wof:name":"Camen Enterprises LLC",
    "wof:placetype":"venue"
},
  "geometry": {"coordinates":[-88.70768700000001,42.532594],"type":"Point"}
}