{
  "type": "Feature",
  "properties": {
    "iso:country":"US",
    "sg:address":"601 E Main St",
    "sg:city":"Madison",
    "sg:classifiers":[
        {
            "category":"Professional",
            "type":"Services"
        }
    ],
    "sg:phone":"+1 608 257 1222",
    "sg:postcode":"53703",
    "sg:province":"WI",
    "sg:tags":[
        "business",
        "association"
    ],
    "wof:name":"Madison Area Safety Council",
    "wof:placetype":"venue"
},
  "geometry": {"coordinates":[-89.375795,43.078922],"type":"Point"}
}