{
  "type": "Feature",
  "properties": {
    "iso:country":"US",
    "sg:address":"4371 Wildwood Dr",
    "sg:city":"Rhinelander",
    "sg:classifiers":[
        {
            "category":"Building & Trades",
            "subcategory":"Cleaning & Sanitation",
            "type":"Services"
        }
    ],
    "sg:phone":"+1 715 362 6361",
    "sg:postcode":"54501",
    "sg:province":"WI",
    "sg:tags":[
        "maintenance",
        "mechanical"
    ],
    "wof:name":"Thomas L Waydick",
    "wof:placetype":"venue"
},
  "geometry": {"coordinates":[-89.458659,45.676738],"type":"Point"}
}