{
  "type": "Feature",
  "properties": {
    "addr:full":"1723 Hyacinth Ln Greenville WI 54942",
    "addr:housenumber":"1723",
    "addr:postcode":"54942",
    "addr:street":"Hyacinth Ln",
    "iso:country":"US",
    "sg:address":"1723 Hyacinth Ln",
    "sg:city":"Greenville",
    "sg:classifiers":[
        {
            "category":"Restaurant",
            "type":"Food & Drink"
        }
    ],
    "sg:phone":"+1 920 757 1144",
    "sg:postcode":"54942",
    "sg:province":"WI",
    "wof:name":"Subway Sandwiches & Salads",
    "wof:placetype":"venue"
},
  "geometry": {"coordinates":[-88.539851,44.302572],"type":"Point"}
}