{
  "type": "Feature",
  "properties": {
    "iso:country":"US",
    "sg:address":"9336 N 85th St",
    "sg:city":"Milwaukee",
    "sg:classifiers":[
        {
            "category":"Building & Trades",
            "subcategory":"Cleaning & Sanitation",
            "type":"Services"
        }
    ],
    "sg:phone":"+1 414 355 3503",
    "sg:postcode":"53224",
    "sg:province":"WI",
    "sg:tags":[
        "janitor"
    ],
    "wof:name":"Centennial Building Mntnc",
    "wof:placetype":"venue"
},
  "geometry": {"coordinates":[-88.015764,43.187649],"type":"Point"}
}