{
  "type": "Feature",
  "properties": {
    "iso:country":"US",
    "sg:address":"1204 Woodland Dr",
    "sg:city":"Milton",
    "sg:classifiers":[
        {
            "category":"Building & Trades",
            "subcategory":"Construction",
            "type":"Services"
        }
    ],
    "sg:phone":"+1 608 868 5123",
    "sg:postcode":"53563",
    "sg:province":"WI",
    "sg:tags":[
        "house"
    ],
    "wof:name":"Aok Remodeling",
    "wof:placetype":"venue"
},
  "geometry": {"coordinates":[-88.97456,42.787377],"type":"Point"}
}