{
  "type": "Feature",
  "properties": {
    "iso:country":"US",
    "sg:address":"11829 W Beloit Rd",
    "sg:city":"Milwaukee",
    "sg:classifiers":[
        {
            "category":"Health Services",
            "subcategory":"Clinic",
            "type":"Services"
        }
    ],
    "sg:phone":"+1 414 321 6834",
    "sg:postcode":"53228",
    "sg:province":"WI",
    "sg:tags":[
        "wellness",
        "program"
    ],
    "wof:name":"Global Wellness",
    "wof:placetype":"venue"
},
  "geometry": {"coordinates":[-88.061053,42.968531],"type":"Point"}
}