{
  "type": "Feature",
  "properties": {
    "iso:country":"US",
    "sg:address":"2112 Mac Arthur Rd",
    "sg:city":"Waukesha",
    "sg:classifiers":[
        {
            "category":"Building & Trades",
            "subcategory":"Plumbing",
            "type":"Services"
        }
    ],
    "sg:phone":"+1 262 521 9828",
    "sg:postcode":"53188",
    "sg:province":"WI",
    "sg:tags":[
        "plumbing",
        "contractor"
    ],
    "wof:name":"Peterson Plumbing Co",
    "wof:placetype":"venue"
},
  "geometry": {"coordinates":[-88.264247,42.998388],"type":"Point"}
}