{
  "type": "Feature",
  "properties": {
    "iso:country":"US",
    "sg:address":"144 W Pulaski St",
    "sg:city":"Pulaski",
    "sg:classifiers":[
        {
            "category":"Real Estate",
            "subcategory":"Real Estate Agent",
            "type":"Services"
        }
    ],
    "sg:phone":"+1 920 822 4663",
    "sg:postcode":"54162",
    "sg:province":"WI",
    "sg:website":"www.countrypriderealty.com",
    "wof:name":"Country Pride Realty Inc",
    "wof:placetype":"venue"
},
  "geometry": {"coordinates":[-88.244229,44.67237],"type":"Point"}
}