{
  "type": "Feature",
  "properties": {
    "iso:country":"US",
    "sg:address":"60 W Montello St",
    "sg:city":"Montello",
    "sg:classifiers":[
        {
            "category":"Bars & Pubs",
            "type":"Food & Drink"
        }
    ],
    "sg:phone":"+1 608 297 2007",
    "sg:postcode":"53949",
    "sg:province":"WI",
    "sg:tags":[
        "drinking"
    ],
    "wof:name":"Yahooz Bar & Char",
    "wof:placetype":"venue"
},
  "geometry": {"coordinates":[-89.328494,43.791822],"type":"Point"}
}