{
  "type": "Feature",
  "properties": {
    "iso:country":"US",
    "sg:address":"1805 Christie Ct",
    "sg:city":"De Pere",
    "sg:classifiers":[
        {
            "category":"Wholesale",
            "subcategory":"Stationery",
            "type":"Manufacturing & Wholesale Goods"
        },
        {
            "category":"Professional",
            "subcategory":"Business Services",
            "type":"Services"
        }
    ],
    "sg:phone":"+1 920 338 8507",
    "sg:postcode":"54115",
    "sg:province":"WI",
    "sg:tags":[
        "packaging",
        "material"
    ],
    "wof:name":"Poly Cello Inc",
    "wof:placetype":"venue"
},
  "geometry": {"coordinates":[-88.121388,44.394561],"type":"Point"}
}