{
  "type": "Feature",
  "properties": {
    "iso:country":"US",
    "sg:address":"490 Madison St",
    "sg:city":"Walworth",
    "sg:classifiers":[
        {
            "category":"Retail",
            "subcategory":"Auto Repair",
            "type":"Services"
        }
    ],
    "sg:phone":"+1 262 275 6575",
    "sg:postcode":"53184",
    "sg:province":"WI",
    "sg:tags":[
        "repairing",
        "automobile",
        "general"
    ],
    "wof:name":"Mark's Motor Mechanics",
    "wof:placetype":"venue"
},
  "geometry": {"coordinates":[-88.60310200000001,42.53382],"type":"Point"}
}