{
  "type": "Feature",
  "properties": {
    "iso:country":"US",
    "sg:address":"151 E Park Ave",
    "sg:city":"Berlin",
    "sg:classifiers":[
        {
            "category":"Retail",
            "subcategory":"Repair Shop",
            "type":"Services"
        }
    ],
    "sg:phone":"+1 920 361 3258",
    "sg:postcode":"54923",
    "sg:province":"WI",
    "wof:name":"All State Electronics",
    "wof:placetype":"venue"
},
  "geometry": {"coordinates":[-88.945065,43.969359],"type":"Point"}
}