{
  "type": "Feature",
  "properties": {
    "iso:country":"US",
    "sg:address":"2248 N 22nd St",
    "sg:city":"Milwaukee",
    "sg:classifiers":[
        {
            "category":"Personal",
            "subcategory":"Beauty Salon",
            "type":"Services"
        }
    ],
    "sg:phone":"+1 414 931 4144",
    "sg:postcode":"53205",
    "sg:province":"WI",
    "wof:name":"Head & Not The Tail",
    "wof:placetype":"venue"
},
  "geometry": {"coordinates":[-87.939969,43.059831],"type":"Point"}
}