{
  "type": "Feature",
  "properties": {
    "iso:country":"US",
    "sg:address":"2205 Fairmont St",
    "sg:city":"Manitowoc",
    "sg:classifiers":[
        {
            "category":"Building & Trades",
            "subcategory":"Landscaping Services",
            "type":"Services"
        }
    ],
    "sg:phone":"+1 920 682 5844",
    "sg:postcode":"54220",
    "sg:province":"WI",
    "sg:tags":[
        "lawn",
        "maintenance",
        "grounds"
    ],
    "wof:name":"Lawn Mower Man",
    "wof:placetype":"venue"
},
  "geometry": {"coordinates":[-87.678267,44.110025],"type":"Point"}
}