{
  "type": "Feature",
  "properties": {
    "addr:full":"330 State Hwy 27 Cadott WI 54727",
    "addr:housenumber":"330",
    "addr:postcode":"54727",
    "addr:street":"State Hwy 27",
    "iso:country":"US",
    "sg:address":"330 State Hwy 27",
    "sg:city":"Cadott",
    "sg:classifiers":[
        {
            "category":"Autos & Motor Vehicles",
            "subcategory":"Auto Supplies",
            "type":"Retail Goods"
        }
    ],
    "sg:phone":"+1 715 289 3088",
    "sg:postcode":"54727",
    "sg:province":"WI",
    "wof:name":"Mickelsons Repair",
    "wof:placetype":"venue"
},
  "geometry": {"coordinates":[-91.14640199999999,44.941816],"type":"Point"}
}