{
  "type": "Feature",
  "properties": {
    "addr:full":"41106 Tiller Rd Soldiers Grove WI 54655",
    "addr:postcode":"41106;54655",
    "addr:street":"Tiller Rd",
    "iso:country":"US",
    "sg:address":"41106 Tiller Rd",
    "sg:city":"Soldiers Grove",
    "sg:classifiers":[
        {
            "category":"Real Estate",
            "subcategory":"Architect",
            "type":"Services"
        }
    ],
    "sg:phone":"+1 608 872 2317",
    "sg:postcode":"54655",
    "sg:province":"WI",
    "sg:tags":[
        "architectural"
    ],
    "wof:name":"Splinter Associates",
    "wof:placetype":"venue"
},
  "geometry": {"coordinates":[-90.68976600000001,43.346293],"type":"Point"}
}