{
  "type": "Feature",
  "properties": {
    "addr:full":"7140 Honey Creek Rd Honey Creek WI 53105",
    "addr:housenumber":"7140",
    "addr:postcode":"53105",
    "addr:street":"Honey Creek Rd",
    "iso:country":"US",
    "sg:address":"7140 Honey Creek Rd",
    "sg:city":"Honey Creek",
    "sg:classifiers":[
        {
            "category":"Government",
            "subcategory":"Post Office",
            "type":"Public Place"
        }
    ],
    "sg:phone":"+1 262 000 1111",
    "sg:postcode":"53105",
    "sg:province":"WI",
    "wof:name":"US Post Office",
    "wof:placetype":"venue"
},
  "geometry": {"coordinates":[-88.309235,42.753049],"type":"Point"}
}