{
  "type": "Feature",
  "properties": {
    "iso:country":"US",
    "sg:address":"6424 State Rd 23",
    "sg:city":"Spring Green",
    "sg:classifiers":[
        {
            "category":"Building & Trades",
            "subcategory":"Construction",
            "type":"Services"
        }
    ],
    "sg:phone":"+1 608 753 2838",
    "sg:postcode":"53588",
    "sg:province":"WI",
    "sg:tags":[
        "water",
        "well",
        "drilling"
    ],
    "wof:name":"Water Maker Well Drilling",
    "wof:placetype":"venue"
},
  "geometry": {"coordinates":[-90.113053,43.123743],"type":"Point"}
}