{
  "type": "Feature",
  "properties": {
    "iso:country":"US",
    "sg:address":"5722 S 108th St",
    "sg:city":"Hales Corners",
    "sg:classifiers":[
        {
            "category":"Shopping",
            "subcategory":"Bicycles & Sporting Goods",
            "type":"Retail Goods"
        }
    ],
    "sg:phone":"+1 414 529 6600",
    "sg:postcode":"53130",
    "sg:province":"WI",
    "wof:name":"Hales Corners Store",
    "wof:placetype":"venue"
},
  "geometry": {"coordinates":[-88.048366,42.940508],"type":"Point"}
}