{
  "type": "Feature",
  "properties": {
    "iso:country":"US",
    "sg:address":"310 Roadhouse St",
    "sg:city":"Potosi",
    "sg:classifiers":[
        {
            "category":"Bars & Pubs",
            "type":"Food & Drink"
        }
    ],
    "sg:phone":"+1 608 763 2208",
    "sg:postcode":"53820",
    "sg:province":"WI",
    "sg:tags":[
        "drinking"
    ],
    "wof:name":"Road House",
    "wof:placetype":"venue"
},
  "geometry": {"coordinates":[-90.690839,42.687751],"type":"Point"}
}