{
  "type": "Feature",
  "properties": {
    "iso:country":"US",
    "sg:address":"64 Spring St",
    "sg:city":"Plymouth",
    "sg:classifiers":[
        {
            "category":"Railroad",
            "type":"Transportation"
        }
    ],
    "sg:phone":"+1 920 892 8311",
    "sg:postcode":"53073",
    "sg:province":"WI",
    "sg:tags":[
        "operator",
        "line"
    ],
    "wof:name":"Wisconsin Central Ltd",
    "wof:placetype":"venue"
},
  "geometry": {"coordinates":[-87.98252,43.747741],"type":"Point"}
}