{
  "type": "Feature",
  "properties": {
    "addr:full":"20265 Downing Ct Brookfield WI 53045",
    "addr:housenumber":"20265",
    "addr:postcode":"53045",
    "addr:street":"Downing Ct",
    "iso:country":"US",
    "sg:address":"20265 Downing Ct",
    "sg:city":"Brookfield",
    "sg:classifiers":[
        {
            "category":"Professional",
            "type":"Services"
        }
    ],
    "sg:phone":"+1 414 797 6606",
    "sg:postcode":"53045",
    "sg:province":"WI",
    "wof:name":"Arun Garg PHD Cpe",
    "wof:placetype":"venue"
},
  "geometry": {"coordinates":[-88.165358,43.066776],"type":"Point"}
}