{
  "type": "Feature",
  "properties": {
    "addr:full":"490 Orbiting Dr Mosinee WI 54455",
    "addr:housenumber":"490",
    "addr:postcode":"54455",
    "addr:street":"Orbiting Dr",
    "iso:country":"US",
    "sg:address":"490 Orbiting Dr",
    "sg:city":"Mosinee",
    "sg:classifiers":[
        {
            "category":"Restaurant",
            "type":"Food & Drink"
        }
    ],
    "sg:menulink":"http://www.allmenus.com/wi/mosinee/145655-subway/menu/",
    "sg:phone":"+1 715 693 7777",
    "sg:postcode":"54455",
    "sg:province":"WI",
    "sg:tags":[
        "american",
        "sandwich"
    ],
    "wof:name":"Subway",
    "wof:placetype":"venue"
},
  "geometry": {"coordinates":[-89.68257699999999,44.783879],"type":"Point"}
}