{
  "type": "Feature",
  "properties": {
    "addr:full":"26232 Co Hwy Ca Tomah WI 54660",
    "addr:housenumber":"26232",
    "addr:postcode":"54660",
    "addr:street":"Co",
    "iso:country":"US",
    "sg:address":"26232 Co Hwy Ca",
    "sg:city":"Tomah",
    "sg:classifiers":[
        {
            "category":"Education",
            "subcategory":"School",
            "type":"Public Place"
        }
    ],
    "sg:phone":"+1 608 374 7101",
    "sg:postcode":"54660",
    "sg:province":"WI",
    "wof:name":"Robert Kupper Learning Ctr",
    "wof:placetype":"venue"
},
  "geometry": {"coordinates":[-90.46901,43.957074],"type":"Point"}
}