{
  "type": "Feature",
  "properties": {
    "iso:country":"US",
    "sg:address":"341 S 9th St",
    "sg:city":"De Pere",
    "sg:classifiers":[
        {
            "category":"Building & Trades",
            "subcategory":"Construction",
            "type":"Services"
        }
    ],
    "sg:phone":"+1 920 337 0343",
    "sg:postcode":"54115",
    "sg:province":"WI",
    "sg:tags":[
        "contractor"
    ],
    "wof:name":"Annen Roofing",
    "wof:placetype":"venue"
},
  "geometry": {"coordinates":[-88.08747099999999,44.447167],"type":"Point"}
}