{
  "type": "Feature",
  "properties": {
    "iso:country":"US",
    "sg:address":"1047 Cove Rd",
    "sg:city":"Sturgeon Bay",
    "sg:classifiers":[
        {
            "category":"Professional",
            "subcategory":"Business Services",
            "type":"Services"
        }
    ],
    "sg:phone":"+1 920 743 9630",
    "sg:postcode":"54235",
    "sg:province":"WI",
    "wof:name":"Gerald P Lamer Partnership",
    "wof:placetype":"venue"
},
  "geometry": {"coordinates":[-87.341317,44.822416],"type":"Point"}
}