{
  "type": "Feature",
  "properties": {
    "iso:country":"US",
    "sg:address":"521 Biddle St",
    "sg:city":"Waukesha",
    "sg:classifiers":[
        {
            "category":"Manufacturing",
            "subcategory":"Chemicals & Compounds",
            "type":"Manufacturing & Wholesale Goods"
        }
    ],
    "sg:phone":"+1 262 542 8072",
    "sg:postcode":"53186",
    "sg:province":"WI",
    "sg:tags":[
        "paint",
        "varnish",
        "allied",
        "product"
    ],
    "sg:website":"www.gaco.com",
    "wof:name":"Gaco Western Inc",
    "wof:placetype":"venue"
},
  "geometry": {"coordinates":[-88.20978100000001,43.007711],"type":"Point"}
}