{
  "type": "Feature",
  "properties": {
    "iso:country":"US",
    "sg:address":"3727 W Layton Ave",
    "sg:city":"Milwaukee",
    "sg:classifiers":[
        {
            "category":"Manufacturing",
            "subcategory":"Tools & Machinery",
            "type":"Manufacturing & Wholesale Goods"
        }
    ],
    "sg:phone":"+1 414 871 8985",
    "sg:postcode":"53221",
    "sg:province":"WI",
    "sg:tags":[
        "machine",
        "shop"
    ],
    "wof:name":"Golden Stone Automation Co",
    "wof:placetype":"venue"
},
  "geometry": {"coordinates":[-87.96064200000001,42.959327],"type":"Point"}
}