{
  "type": "Feature",
  "properties": {
    "addr:full":"5782 Grandview Rd Fond Du Lac WI 54935",
    "addr:housenumber":"5782",
    "addr:postcode":"54935",
    "addr:street":"Grandview Rd",
    "iso:country":"US",
    "sg:address":"5782 Grandview Rd",
    "sg:city":"Fond Du Lac",
    "sg:classifiers":[
        {
            "category":"Building & Trades",
            "subcategory":"Landscaping Services",
            "type":"Services"
        }
    ],
    "sg:phone":"+1 920 922 8468",
    "sg:postcode":"54935",
    "sg:province":"WI",
    "wof:name":"Insta Shade Large Tree Moving",
    "wof:placetype":"venue"
},
  "geometry": {"coordinates":[-88.37111400000001,43.763537],"type":"Point"}
}