{
  "type": "Feature",
  "properties": {
    "iso:country":"US",
    "sg:address":"5273 26th St E",
    "sg:city":"Necedah",
    "sg:classifiers":[
        {
            "category":"Building & Trades",
            "subcategory":"Construction",
            "type":"Services"
        }
    ],
    "sg:phone":"+1 608 565 3812",
    "sg:postcode":"54646",
    "sg:province":"WI",
    "sg:tags":[
        "house"
    ],
    "wof:name":"Freedom Builders",
    "wof:placetype":"venue"
},
  "geometry": {"coordinates":[-90.033844,43.988099],"type":"Point"}
}