{
  "type": "Feature",
  "properties": {
    "iso:country":"US",
    "sg:address":"26868 Hopkins Rd",
    "sg:city":"Webster",
    "sg:classifiers":[
        {
            "category":"Utilities",
            "subcategory":"Cable",
            "type":"Services"
        }
    ],
    "sg:phone":"+1 715 866 4578",
    "sg:postcode":"54893",
    "sg:province":"WI",
    "sg:tags":[
        "television"
    ],
    "wof:name":"Duane J Cable",
    "wof:placetype":"venue"
},
  "geometry": {"coordinates":[-92.277241,45.888892],"type":"Point"}
}