{
  "type": "Feature",
  "properties": {
    "iso:country":"US",
    "sg:address":"2000 E Birchwood Ave",
    "sg:city":"Cudahy",
    "sg:classifiers":[
        {
            "category":"Arts & Performance",
            "subcategory":"Theater",
            "type":"Entertainment"
        }
    ],
    "sg:phone":"+1 414 486 1961",
    "sg:postcode":"53110",
    "sg:province":"WI",
    "sg:tags":[
        "group"
    ],
    "wof:name":"Pioneer Drum & Bugle Corps & C",
    "wof:placetype":"venue"
},
  "geometry": {"coordinates":[-87.88095800000001,42.940371],"type":"Point"}
}