{
  "type": "Feature",
  "properties": {
    "iso:country":"US",
    "sg:address":"8296 580th St",
    "sg:city":"Colfax",
    "sg:classifiers":[
        {
            "category":"Banks & Credit Unions",
            "subcategory":"Financial Services",
            "type":"Services"
        }
    ],
    "sg:phone":"+1 715 232 0834",
    "sg:postcode":"54730",
    "sg:province":"WI",
    "sg:tags":[
        "investor"
    ],
    "wof:name":"John R Becker Phoenix Investme",
    "wof:placetype":"venue"
},
  "geometry": {"coordinates":[-91.869604,44.978944],"type":"Point"}
}