{
  "type": "Feature",
  "properties": {
    "iso:country":"US",
    "sg:address":"524 Kissel Ave",
    "sg:city":"Cashton",
    "sg:classifiers":[
        {
            "category":"Professional",
            "subcategory":"Business Services",
            "type":"Services"
        }
    ],
    "sg:phone":"+1 608 654 5542",
    "sg:postcode":"54619",
    "sg:province":"WI",
    "wof:name":"National Builders",
    "wof:placetype":"venue"
},
  "geometry": {"coordinates":[-90.778606,43.740687],"type":"Point"}
}