{
  "type": "Feature",
  "properties": {
    "addr:full":"2052 Hazen Rd Green Bay WI 54311",
    "addr:housenumber":"2052",
    "addr:postcode":"54311",
    "addr:street":"Hazen Rd",
    "iso:country":"US",
    "sg:address":"2052 Hazen Rd",
    "sg:city":"Green Bay",
    "sg:classifiers":[
        {
            "category":"Shopping",
            "type":"Retail Goods"
        }
    ],
    "sg:phone":"+1 920 406 0989",
    "sg:postcode":"54311",
    "sg:province":"WI",
    "sg:tags":[
        "pet",
        "shop"
    ],
    "wof:name":"Gooch's Corals",
    "wof:placetype":"venue"
},
  "geometry": {"coordinates":[-87.968227,44.463494],"type":"Point"}
}