{
  "type": "Feature",
  "properties": {
    "iso:country":"US",
    "sg:address":"55730 Island Dr",
    "sg:city":"Solon Springs",
    "sg:classifiers":[
        {
            "category":"Retail",
            "subcategory":"Repair Shop",
            "type":"Services"
        }
    ],
    "sg:phone":"+1 715 795 2841",
    "sg:postcode":"54873",
    "sg:province":"WI",
    "wof:name":"R B Electronics",
    "wof:placetype":"venue"
},
  "geometry": {"coordinates":[-91.530765,46.382297],"type":"Point"}
}