{
  "type": "Feature",
  "properties": {
    "addr:full":"19639 210th St Jim Falls WI 54748",
    "addr:housenumber":"19639",
    "addr:postcode":"54748",
    "addr:street":"210Th St",
    "iso:country":"US",
    "sg:address":"19639 210th St",
    "sg:city":"Jim Falls",
    "sg:classifiers":[
        {
            "category":"Farming",
            "subcategory":"Dairy Farm",
            "type":"Manufacturing & Wholesale Goods"
        }
    ],
    "sg:phone":"+1 715 239 6749",
    "sg:postcode":"54748",
    "sg:province":"WI",
    "wof:name":"James Hrdlicka",
    "wof:placetype":"venue"
},
  "geometry": {"coordinates":[-91.253962,45.125159],"type":"Point"}
}