{
  "type": "Feature",
  "properties": {
    "iso:country":"US",
    "sg:address":"6117 Hemlock Rd",
    "sg:city":"Vesper",
    "sg:classifiers":[
        {
            "category":"Farming",
            "subcategory":"Berry Farm",
            "type":"Manufacturing & Wholesale Goods"
        }
    ],
    "sg:phone":"+1 715 423 6288",
    "sg:postcode":"54489",
    "sg:province":"WI",
    "sg:tags":[
        "crop"
    ],
    "wof:name":"Krabb Hill Cranberries LLC",
    "wof:placetype":"venue"
},
  "geometry": {"coordinates":[-90.036581,44.409036],"type":"Point"}
}