{
  "type": "Feature",
  "properties": {
    "iso:country":"US",
    "sg:address":"1252 N 12th Pl",
    "sg:city":"Sturgeon Bay",
    "sg:classifiers":[
        {
            "category":"Real Estate",
            "subcategory":"Real Estate Operator",
            "type":"Services"
        }
    ],
    "sg:phone":"+1 920 743 7762",
    "sg:postcode":"54235",
    "sg:province":"WI",
    "sg:tags":[
        "building",
        "apartment"
    ],
    "wof:name":"Orchard Valley Apartments Inc",
    "wof:placetype":"venue"
},
  "geometry": {"coordinates":[-87.364152,44.850936],"type":"Point"}
}