{
  "type": "Feature",
  "properties": {
    "iso:country":"US",
    "sg:address":"1910 Co Hwy Nn",
    "sg:city":"West Bend",
    "sg:classifiers":[
        {
            "category":"Real Estate",
            "subcategory":"Real Estate Agent",
            "type":"Services"
        }
    ],
    "sg:phone":"+1 262 335 2655",
    "sg:postcode":"53095",
    "sg:province":"WI",
    "wof:name":"Castle Appraisal Services LLC",
    "wof:placetype":"venue"
},
  "geometry": {"coordinates":[-88.131005,43.368495],"type":"Point"}
}