{
  "type": "Feature",
  "properties": {
    "addr:full":"6312 W Capitol Dr Milwaukee WI 53216",
    "addr:housenumber":"6312",
    "addr:postcode":"53216",
    "addr:street":"W Capitol Dr",
    "iso:country":"US",
    "sg:address":"6312 W Capitol Dr",
    "sg:city":"Milwaukee",
    "sg:classifiers":[
        {
            "category":"Autos & Motor Vehicles",
            "subcategory":"Auto Supplies",
            "type":"Retail Goods"
        }
    ],
    "sg:phone":"+1 414 536 7310",
    "sg:postcode":"53216",
    "sg:province":"WI",
    "sg:website":"www.autozone.com",
    "wof:name":"Autozone",
    "wof:placetype":"venue"
},
  "geometry": {"coordinates":[-87.99195,43.090034],"type":"Point"}
}