{
  "type": "Feature",
  "properties": {
    "iso:country":"US",
    "sg:address":"320 Country Walk Ln",
    "sg:city":"Sister Bay",
    "sg:classifiers":[
        {
            "category":"Food & Beverages",
            "subcategory":"Groceries & Convenience Stores",
            "type":"Retail Goods"
        }
    ],
    "sg:phone":"+1 920 854 2391",
    "sg:postcode":"54234",
    "sg:province":"WI",
    "sg:tags":[
        "grocer"
    ],
    "wof:name":"Piggly Wiggly",
    "wof:placetype":"venue"
},
  "geometry": {"coordinates":[-87.12729299999999,45.183365],"type":"Point"}
}