{
  "type": "Feature",
  "properties": {
    "addr:full":"185 Bay Park Sq Green Bay WI 54304",
    "addr:housenumber":"185",
    "addr:postcode":"54304",
    "addr:street":"Bay Park Sq",
    "iso:country":"US",
    "sg:address":"185 Bay Park Sq",
    "sg:city":"Green Bay",
    "sg:classifiers":[
        {
            "category":"Bakery",
            "type":"Food & Drink"
        }
    ],
    "sg:menulink":"http://www.allmenus.com/wi/ashwaubenon/220348-auntie-annes-pretzels/menu/",
    "sg:phone":"+1 920 497 0467",
    "sg:postcode":"54304",
    "sg:province":"WI",
    "sg:tags":[
        "american",
        "pastry"
    ],
    "wof:name":"Auntie Anne's Pretzels",
    "wof:placetype":"venue"
},
  "geometry": {"coordinates":[-88.06765799999999,44.484575],"type":"Point"}
}