{
  "type": "Feature",
  "properties": {
    "iso:country":"US",
    "sg:address":"168 N Main St",
    "sg:city":"Richland Center",
    "sg:classifiers":[
        {
            "category":"Real Estate",
            "subcategory":"Real Estate Agent",
            "type":"Services"
        }
    ],
    "sg:phone":"+1 608 647 2161",
    "sg:postcode":"53581",
    "sg:province":"WI",
    "wof:name":"Country Land Realty",
    "wof:placetype":"venue"
},
  "geometry": {"coordinates":[-90.386614,43.335522],"type":"Point"}
}