{
  "type": "Feature",
  "properties": {
    "iso:country":"US",
    "sg:address":"214 S Hickory St",
    "sg:city":"Fond Du Lac",
    "sg:classifiers":[
        {
            "category":"Professional",
            "subcategory":"Business Services",
            "type":"Services"
        }
    ],
    "sg:phone":"+1 920 924 9149",
    "sg:postcode":"54935",
    "sg:province":"WI",
    "wof:name":"Mirowski Home Inspection",
    "wof:placetype":"venue"
},
  "geometry": {"coordinates":[-88.462012,43.772599],"type":"Point"}
}