{
  "type": "Feature",
  "properties": {
    "addr:full":"1428 Broadway St S Menomonie WI 54751",
    "addr:housenumber":"1428",
    "addr:postcode":"54751",
    "addr:street":"Broadway St S",
    "iso:country":"US",
    "sg:address":"1428 Broadway St S",
    "sg:city":"Menomonie",
    "sg:classifiers":[
        {
            "category":"Retail",
            "subcategory":"Car Wash",
            "type":"Services"
        }
    ],
    "sg:phone":"+1 715 232 8051",
    "sg:postcode":"54751",
    "sg:province":"WI",
    "sg:tags":[
        "carwash",
        "automotive"
    ],
    "wof:name":"Wonder Lube",
    "wof:placetype":"venue"
},
  "geometry": {"coordinates":[-91.929687,44.869859],"type":"Point"}
}