{
  "type": "Feature",
  "properties": {
    "iso:country":"US",
    "sg:address":"3531 Elder Dr",
    "sg:city":"Gilman",
    "sg:classifiers":[
        {
            "category":"Social Services",
            "subcategory":"Adult Care",
            "type":"Services"
        }
    ],
    "sg:phone":"+1 715 447 8318",
    "sg:postcode":"54433",
    "sg:province":"WI",
    "sg:tags":[
        "residential"
    ],
    "wof:name":"Country Vw Resid Cre Unit",
    "wof:placetype":"venue"
},
  "geometry": {"coordinates":[-90.864115,45.155274],"type":"Point"}
}