{
  "type": "Feature",
  "properties": {
    "iso:country":"US",
    "sg:address":"701 N River St",
    "sg:city":"Spooner",
    "sg:classifiers":[
        {
            "category":"Health Services",
            "subcategory":"Doctor",
            "type":"Services"
        }
    ],
    "sg:phone":"+1 715 635 8282",
    "sg:postcode":"54801",
    "sg:province":"WI",
    "wof:name":"Jon M McKinney DDS",
    "wof:placetype":"venue"
},
  "geometry": {"coordinates":[-91.886229,45.829552],"type":"Point"}
}