{
  "type": "Feature",
  "properties": {
    "addr:full":"3980 Prairie Ct Oshkosh WI 54901",
    "addr:housenumber":"3980",
    "addr:postcode":"54901",
    "addr:street":"Prairie Ct",
    "iso:country":"US",
    "sg:address":"3980 Prairie Ct",
    "sg:city":"Oshkosh",
    "sg:classifiers":[
        {
            "category":"Real Estate",
            "subcategory":"Real Estate Agent",
            "type":"Services"
        }
    ],
    "sg:phone":"+1 920 231 3629",
    "sg:postcode":"54901",
    "sg:province":"WI",
    "sg:tags":[
        "inspection"
    ],
    "wof:name":"Tony's Home Inspection Svc",
    "wof:placetype":"venue"
},
  "geometry": {"coordinates":[-88.539019,44.072703],"type":"Point"}
}