{
  "type": "Feature",
  "properties": {
    "iso:country":"US",
    "sg:address":"209 Forest St",
    "sg:city":"Fox Lake",
    "sg:classifiers":[
        {
            "category":"Health Services",
            "subcategory":"Nursing And Care Facility",
            "type":"Services"
        }
    ],
    "sg:phone":"+1 920 928 2339",
    "sg:postcode":"53933",
    "sg:province":"WI",
    "sg:tags":[
        "home",
        "retirement",
        "community"
    ],
    "wof:name":"Victorian Villa",
    "wof:placetype":"venue"
},
  "geometry": {"coordinates":[-88.918093,43.56509],"type":"Point"}
}