{
  "type": "Feature",
  "properties": {
    "iso:country":"US",
    "sg:address":"7306 Perkinstown Ave",
    "sg:city":"Medford",
    "sg:classifiers":[
        {
            "category":"Arts & Performance",
            "subcategory":"Theater",
            "type":"Entertainment"
        }
    ],
    "sg:phone":"+1 715 748 5855",
    "sg:postcode":"54451",
    "sg:province":"WI",
    "sg:tags":[
        "prefabricated",
        "wood",
        "group",
        "mfg"
    ],
    "wof:name":"Timberwolf Log Homes",
    "wof:placetype":"venue"
},
  "geometry": {"coordinates":[-90.418901,45.190035],"type":"Point"}
}