{
  "type": "Feature",
  "properties": {
    "iso:country":"US",
    "sg:address":"3013 Park Ridge Ave",
    "sg:city":"Appleton",
    "sg:classifiers":[
        {
            "category":"Utilities",
            "subcategory":"Telephone",
            "type":"Services"
        }
    ],
    "sg:phone":"+1 920 882 9888",
    "sg:postcode":"54914",
    "sg:province":"WI",
    "sg:tags":[
        "telecommunication"
    ],
    "wof:name":"Future Communications",
    "wof:placetype":"venue"
},
  "geometry": {"coordinates":[-88.453056,44.293106],"type":"Point"}
}