{
  "type": "Feature",
  "properties": {
    "iso:country":"US",
    "sg:address":"25364 Bortle Rd",
    "sg:city":"Galesville",
    "sg:classifiers":[
        {
            "category":"Building & Trades",
            "subcategory":"Landscaping Services",
            "type":"Services"
        }
    ],
    "sg:phone":"+1 608 539 4405",
    "sg:postcode":"54630",
    "sg:province":"WI",
    "wof:name":"Lawncare Unlimited",
    "wof:placetype":"venue"
},
  "geometry": {"coordinates":[-91.45457399999999,44.107189],"type":"Point"}
}