{
  "type": "Feature",
  "properties": {
    "iso:country":"US",
    "sg:address":"119 Birch St W",
    "sg:city":"Amery",
    "sg:classifiers":[
        {
            "category":"Organizations",
            "subcategory":"Religious Organization",
            "type":"Services"
        }
    ],
    "sg:phone":"+1 715 268 6989",
    "sg:postcode":"54001",
    "sg:province":"WI",
    "wof:name":"New Life Christian Fellowship",
    "wof:placetype":"venue"
},
  "geometry": {"coordinates":[-92.363388,45.31252],"type":"Point"}
}