{
  "type": "Feature",
  "properties": {
    "iso:country":"US",
    "sg:address":"8274 San Rd",
    "sg:city":"South Range",
    "sg:classifiers":[
        {
            "category":"Health Services",
            "subcategory":"Nursing And Care Facility",
            "type":"Services"
        }
    ],
    "sg:phone":"+1 715 398 3523",
    "sg:postcode":"54874",
    "sg:province":"WI",
    "sg:tags":[
        "home"
    ],
    "wof:name":"Middle River Health Care Ctr",
    "wof:placetype":"venue"
},
  "geometry": {"coordinates":[-91.876276,46.541545],"type":"Point"}
}