{
  "type": "Feature",
  "properties": {
    "iso:country":"US",
    "sg:address":"36358 Main St",
    "sg:city":"Whitehall",
    "sg:classifiers":[
        {
            "category":"Government",
            "subcategory":"Office",
            "type":"Public Place"
        }
    ],
    "sg:phone":"+1 715 538 2274",
    "sg:postcode":"54773",
    "sg:province":"WI",
    "wof:name":"Trempealeau County Housing",
    "wof:placetype":"venue"
},
  "geometry": {"coordinates":[-91.316607,44.368518],"type":"Point"}
}