{
  "type": "Feature",
  "properties": {
    "addr:full":"507 Cherry Ln Roberts WI 54023",
    "addr:housenumber":"507",
    "addr:postcode":"54023",
    "addr:street":"Cherry Ln",
    "iso:country":"US",
    "sg:address":"507 Cherry Ln",
    "sg:city":"Roberts",
    "sg:classifiers":[
        {
            "category":"Health Services",
            "subcategory":"Chiropractor",
            "type":"Services"
        }
    ],
    "sg:phone":"+1 715 749 4010",
    "sg:postcode":"54023",
    "sg:province":"WI",
    "sg:tags":[
        "chiropractic"
    ],
    "wof:name":"McCabe Chiropractic",
    "wof:placetype":"venue"
},
  "geometry": {"coordinates":[-92.555672,44.978955],"type":"Point"}
}