{
  "type": "Feature",
  "properties": {
    "iso:country":"US",
    "sg:address":"5834 W Villard Ave",
    "sg:city":"Milwaukee",
    "sg:classifiers":[
        {
            "category":"Restaurant",
            "type":"Food & Drink"
        }
    ],
    "sg:phone":"+1 414 464 8888",
    "sg:postcode":"53218",
    "sg:province":"WI",
    "wof:name":"Shark's Fish & Chicken",
    "wof:placetype":"venue"
},
  "geometry": {"coordinates":[-87.986034,43.112109],"type":"Point"}
}