{
  "type": "Feature",
  "properties": {
    "iso:country":"US",
    "sg:address":"2097 Division St",
    "sg:city":"East Troy",
    "sg:classifiers":[
        {
            "category":"Autos & Motor Vehicles",
            "subcategory":"Fuel & Gas Station",
            "type":"Retail Goods"
        }
    ],
    "sg:phone":"+1 262 642 5664",
    "sg:postcode":"53120",
    "sg:province":"WI",
    "sg:tags":[
        "station",
        "gasoline"
    ],
    "wof:name":"East Troy Self Serv",
    "wof:placetype":"venue"
},
  "geometry": {"coordinates":[-88.406011,42.78496],"type":"Point"}
}