{
  "type": "Feature",
  "properties": {
    "iso:country":"US",
    "sg:address":"172 Riviera Ave",
    "sg:city":"Merrillan",
    "sg:classifiers":[
        {
            "category":"Personal",
            "subcategory":"Beauty Salon",
            "type":"Services"
        }
    ],
    "sg:phone":"+1 715 333 2141",
    "sg:postcode":"54754",
    "sg:province":"WI",
    "sg:tags":[
        "shop"
    ],
    "wof:name":"Beauty Nook LLC",
    "wof:placetype":"venue"
},
  "geometry": {"coordinates":[-90.71785300000001,44.428172],"type":"Point"}
}