{
  "type": "Feature",
  "properties": {
    "iso:country":"US",
    "sg:address":"458 Mill Rd",
    "sg:city":"Sister Bay",
    "sg:classifiers":[
        {
            "category":"Travel",
            "subcategory":"Hotels & Motels",
            "type":"Entertainment"
        }
    ],
    "sg:phone":"+1 920 854 9972",
    "sg:postcode":"54234",
    "sg:province":"WI",
    "sg:tags":[
        "operation"
    ],
    "wof:name":"Yacht Club At Sister Bay",
    "wof:placetype":"venue"
},
  "geometry": {"coordinates":[-87.122983,45.188983],"type":"Point"}
}