{
  "type": "Feature",
  "properties": {
    "iso:country":"US",
    "sg:address":"7155 Kertesz Ln",
    "sg:city":"Crivitz",
    "sg:classifiers":[
        {
            "category":"Building & Trades",
            "subcategory":"Construction",
            "type":"Services"
        }
    ],
    "sg:phone":"+1 715 854 7505",
    "sg:postcode":"54114",
    "sg:province":"WI",
    "sg:tags":[
        "driveway"
    ],
    "sg:website":"www.acornlodge.com",
    "wof:name":"Kwiatkowski Construction",
    "wof:placetype":"venue"
},
  "geometry": {"coordinates":[-88.094051,45.219124],"type":"Point"}
}