{
  "type": "Feature",
  "properties": {
    "addr:full":"220 Grove St Cottage Grove WI 53527",
    "addr:housenumber":"220",
    "addr:postcode":"53527",
    "addr:street":"Grove St",
    "iso:country":"US",
    "sg:address":"220 Grove St",
    "sg:city":"Cottage Grove",
    "sg:classifiers":[
        {
            "category":"Government",
            "subcategory":"Office",
            "type":"Public Place"
        }
    ],
    "sg:phone":"+1 608 839 8904",
    "sg:postcode":"53527",
    "sg:province":"WI",
    "sg:tags":[
        "village"
    ],
    "wof:name":"Firemans Park Village Office",
    "wof:placetype":"venue"
},
  "geometry": {"coordinates":[-89.204661,43.074242],"type":"Point"}
}