{
  "type": "Feature",
  "properties": {
    "iso:country":"US",
    "sg:address":"8338 Washington Ave",
    "sg:city":"Racine",
    "sg:classifiers":[
        {
            "category":"Real Estate",
            "subcategory":"Real Estate Services",
            "type":"Services"
        }
    ],
    "sg:phone":"+1 262 886 1530",
    "sg:postcode":"53406",
    "sg:province":"WI",
    "sg:tags":[
        "company",
        "title"
    ],
    "wof:name":"Stuart Title",
    "wof:placetype":"venue"
},
  "geometry": {"coordinates":[-87.894903,42.719527],"type":"Point"}
}