{
  "type": "Feature",
  "properties": {
    "iso:country":"US",
    "sg:address":"6860 Forest Ridge Rd",
    "sg:city":"Ripon",
    "sg:classifiers":[
        {
            "category":"Farming",
            "subcategory":"Livestock Farm",
            "type":"Manufacturing & Wholesale Goods"
        }
    ],
    "sg:phone":"+1 920 748 3085",
    "sg:postcode":"54971",
    "sg:province":"WI",
    "sg:tags":[
        "crop",
        "cattle"
    ],
    "wof:name":"Oak Ridge Farms",
    "wof:placetype":"venue"
},
  "geometry": {"coordinates":[-88.9256,43.875661],"type":"Point"}
}