{
  "type": "Feature",
  "properties": {
    "addr:full":"2744 6th Ave Grand Marsh WI 53936",
    "addr:housenumber":"2744",
    "addr:postcode":"53936",
    "addr:street":"6Th Ave",
    "iso:country":"US",
    "sg:address":"2744 6th Ave",
    "sg:city":"Grand Marsh",
    "sg:classifiers":[
        {
            "category":"Farming",
            "subcategory":"Farm",
            "type":"Manufacturing & Wholesale Goods"
        }
    ],
    "sg:phone":"+1 608 339 3082",
    "sg:postcode":"53936",
    "sg:province":"WI",
    "sg:tags":[
        "crop",
        "general"
    ],
    "wof:name":"William Grabarski",
    "wof:placetype":"venue"
},
  "geometry": {"coordinates":[-89.697655,43.855184],"type":"Point"}
}