{
  "type": "Feature",
  "properties": {
    "iso:country":"US",
    "sg:address":"4581 N Hopkins St",
    "sg:city":"Milwaukee",
    "sg:classifiers":[
        {
            "category":"Personal",
            "subcategory":"Beauty Salon",
            "type":"Services"
        }
    ],
    "sg:phone":"+1 414 447 1416",
    "sg:postcode":"53209",
    "sg:province":"WI",
    "sg:tags":[
        "shop"
    ],
    "wof:name":"Adroits Beauty Salon",
    "wof:placetype":"venue"
},
  "geometry": {"coordinates":[-87.958256,43.100316],"type":"Point"}
}