{
  "type": "Feature",
  "properties": {
    "iso:country":"US",
    "sg:address":"343 W Wisconsin Ave",
    "sg:city":"Appleton",
    "sg:classifiers":[
        {
            "category":"Retail",
            "subcategory":"Repair Shop",
            "type":"Services"
        }
    ],
    "sg:phone":"+1 920 731 9514",
    "sg:postcode":"54911",
    "sg:province":"WI",
    "wof:name":"GE",
    "wof:placetype":"venue"
},
  "geometry": {"coordinates":[-88.410545,44.272862],"type":"Point"}
}