{
  "type": "Feature",
  "properties": {
    "iso:country":"US",
    "sg:address":"1104 Mills St",
    "sg:city":"Black Earth",
    "sg:classifiers":[
        {
            "category":"Social Services",
            "type":"Services"
        }
    ],
    "sg:phone":"+1 608 767 3691",
    "sg:postcode":"53515",
    "sg:province":"WI",
    "sg:tags":[
        "organization",
        "welfare"
    ],
    "wof:name":"Dane County Dept Of Human Svc",
    "wof:placetype":"venue"
},
  "geometry": {"coordinates":[-89.74805499999999,43.138981],"type":"Point"}
}