{
  "type": "Feature",
  "properties": {
    "iso:country":"US",
    "sg:address":"3120 W Riverland Dr",
    "sg:city":"Thiensville",
    "sg:classifiers":[
        {
            "category":"Health Services",
            "subcategory":"Nursing And Care Facility",
            "type":"Services"
        }
    ],
    "sg:phone":"+1 262 242 2051",
    "sg:postcode":"53092",
    "sg:province":"WI",
    "sg:tags":[
        "personal"
    ],
    "wof:name":"New Living Concept Ltd",
    "wof:placetype":"venue"
},
  "geometry": {"coordinates":[-87.948678,43.234411],"type":"Point"}
}