{
  "type": "Feature",
  "properties": {
    "iso:country":"US",
    "sg:address":"3302 Sorenson Ln",
    "sg:city":"Viroqua",
    "sg:classifiers":[
        {
            "category":"Farming",
            "subcategory":"Farm",
            "type":"Manufacturing & Wholesale Goods"
        }
    ],
    "sg:phone":"+1 608 483 2141",
    "sg:postcode":"54665",
    "sg:province":"WI",
    "sg:tags":[
        "dairy",
        "crop",
        "general"
    ],
    "wof:name":"Bill Lehmann",
    "wof:placetype":"venue"
},
  "geometry": {"coordinates":[-91.083083,43.598722],"type":"Point"}
}