{
  "type": "Feature",
  "properties": {
    "addr:full":"2324 18th St Kenosha WI 53140",
    "addr:housenumber":"2324",
    "addr:postcode":"53140",
    "addr:street":"18Th St",
    "iso:country":"US",
    "sg:address":"2324 18th St",
    "sg:city":"Kenosha",
    "sg:classifiers":[
        {
            "category":"Restaurant",
            "type":"Food & Drink"
        }
    ],
    "sg:menulink":"http://www.allmenus.com/wi/kenosha/77396-papa-murphys/menu/",
    "sg:phone":"+1 262 551 7200",
    "sg:postcode":"53140",
    "sg:province":"WI",
    "sg:tags":[
        "american",
        "pizza"
    ],
    "wof:name":"Papa Murphy's",
    "wof:placetype":"venue"
},
  "geometry": {"coordinates":[-87.83763399999999,42.62442],"type":"Point"}
}