{
  "type": "Feature",
  "properties": {
    "iso:country":"US",
    "sg:address":"12714 W Euclid Ave",
    "sg:city":"New Berlin",
    "sg:classifiers":[
        {
            "category":"Building & Trades",
            "subcategory":"Construction",
            "type":"Services"
        }
    ],
    "sg:phone":"+1 414 840 3155",
    "sg:postcode":"53151",
    "sg:province":"WI",
    "sg:tags":[
        "painter"
    ],
    "wof:name":"DJJJ A's Painting",
    "wof:placetype":"venue"
},
  "geometry": {"coordinates":[-88.07220100000001,42.98602],"type":"Point"}
}