{
  "type": "Feature",
  "properties": {
    "iso:country":"US",
    "sg:address":"7051 Leanne Ct",
    "sg:city":"Hartland",
    "sg:classifiers":[
        {
            "category":"Professional",
            "type":"Services"
        }
    ],
    "sg:phone":"+1 262 538 4426",
    "sg:postcode":"53029",
    "sg:province":"WI",
    "wof:name":"Russell & Kathleen Kinney Fami",
    "wof:placetype":"venue"
},
  "geometry": {"coordinates":[-88.323705,43.147087],"type":"Point"}
}