{
  "type": "Feature",
  "properties": {
    "iso:country":"US",
    "sg:address":"4800 W Green Brook Dr",
    "sg:city":"Milwaukee",
    "sg:classifiers":[
        {
            "category":"Government",
            "subcategory":"Office",
            "type":"Public Place"
        },
        {
            "category":"Professional",
            "subcategory":"Management & Consulting",
            "type":"Services"
        }
    ],
    "sg:phone":"+1 414 371 3031",
    "sg:postcode":"53223",
    "sg:province":"WI",
    "sg:tags":[
        "village"
    ],
    "wof:name":"Brown Deer Village Hall",
    "wof:placetype":"venue"
},
  "geometry": {"coordinates":[-87.974458,43.181708],"type":"Point"}
}