{
  "type": "Feature",
  "properties": {
    "addr:full":"8703 W Greenfield Ave Milwaukee WI 53214",
    "addr:housenumber":"8703",
    "addr:postcode":"53214",
    "addr:street":"W Greenfield Ave",
    "iso:country":"US",
    "sg:address":"8703 W Greenfield Ave",
    "sg:city":"Milwaukee",
    "sg:classifiers":[
        {
            "category":"Insurance",
            "subcategory":"Insurance Agent",
            "type":"Services"
        }
    ],
    "sg:phone":"+1 414 257 2787",
    "sg:postcode":"53214",
    "sg:province":"WI",
    "wof:name":"State Farm Insurance",
    "wof:placetype":"venue"
},
  "geometry": {"coordinates":[-88.021961,43.016459],"type":"Point"}
}