{
  "type": "Feature",
  "properties": {
    "iso:country":"US",
    "sg:address":"5914 W Appleton Ave",
    "sg:city":"Milwaukee",
    "sg:classifiers":[
        {
            "category":"Restaurant",
            "type":"Food & Drink"
        }
    ],
    "sg:phone":"+1 414 873 5937",
    "sg:postcode":"53210",
    "sg:province":"WI",
    "sg:tags":[
        "greek"
    ],
    "wof:name":"Gyros Corners Inc",
    "wof:placetype":"venue"
},
  "geometry": {"coordinates":[-87.98724799999999,43.070994],"type":"Point"}
}