{
  "type": "Feature",
  "properties": {
    "addr:full":"1850 Bohman Dr Richland Center WI 53581",
    "addr:housenumber":"1850",
    "addr:postcode":"53581",
    "addr:street":"Bohman Dr",
    "iso:country":"US",
    "sg:address":"1850 Bohman Dr",
    "sg:city":"Richland Center",
    "sg:classifiers":[
        {
            "category":"Government",
            "subcategory":"Office",
            "type":"Public Place"
        }
    ],
    "sg:phone":"+1 608 647 8874",
    "sg:postcode":"53581",
    "sg:province":"WI",
    "sg:tags":[
        "farm",
        "agency"
    ],
    "wof:name":"Farm Service Agency",
    "wof:placetype":"venue"
},
  "geometry": {"coordinates":[-90.37908400000001,43.319291],"type":"Point"}
}