{
  "type": "Feature",
  "properties": {
    "addr:full":"1210 Miller Park Way Milwaukee WI 53214",
    "addr:housenumber":"1210",
    "addr:postcode":"53214",
    "addr:street":"Miller Park Way",
    "iso:country":"US",
    "sg:address":"1210 Miller Park Way",
    "sg:city":"Milwaukee",
    "sg:classifiers":[
        {
            "category":"Restaurant",
            "type":"Food & Drink"
        }
    ],
    "sg:menulink":"http://www.allmenus.com/wi/west-milwaukee/137871-boston-market/menu/",
    "sg:phone":"+1 414 647 0660",
    "sg:postcode":"53214",
    "sg:province":"WI",
    "sg:tags":[
        "barbecue",
        "american",
        "soup"
    ],
    "wof:name":"Boston Market",
    "wof:placetype":"venue"
},
  "geometry": {"coordinates":[-87.96921500000001,43.019717],"type":"Point"}
}