{
  "type": "Feature",
  "properties": {
    "iso:country":"US",
    "sg:address":"130 Memorial Dr",
    "sg:city":"Oconto",
    "sg:classifiers":[
        {
            "category":"Real Estate",
            "subcategory":"Real Estate Operator",
            "type":"Services"
        }
    ],
    "sg:phone":"+1 920 834 5544",
    "sg:postcode":"54153",
    "sg:province":"WI",
    "sg:tags":[
        "building",
        "apartment"
    ],
    "wof:name":"Northland Oconto Apts",
    "wof:placetype":"venue"
},
  "geometry": {"coordinates":[-87.869094,44.897063],"type":"Point"}
}