{
  "type": "Feature",
  "properties": {
    "addr:full":"1604 Appleton Rd Menasha WI 54952",
    "addr:housenumber":"1604",
    "addr:postcode":"54952",
    "addr:street":"Appleton Rd",
    "iso:country":"US",
    "sg:address":"1604 Appleton Rd",
    "sg:city":"Menasha",
    "sg:classifiers":[
        {
            "category":"Personal",
            "subcategory":"Beauty Salon",
            "type":"Services"
        }
    ],
    "sg:phone":"+1 920 729 6284",
    "sg:postcode":"54952",
    "sg:province":"WI",
    "sg:tags":[
        "shop"
    ],
    "wof:name":"Happy Nails",
    "wof:placetype":"venue"
},
  "geometry": {"coordinates":[-88.42406800000001,44.23242],"type":"Point"}
}