{
  "type": "Feature",
  "properties": {
    "addr:full":"200 Veterans Rd Stoughton WI 53589",
    "addr:housenumber":"200",
    "addr:postcode":"53589",
    "addr:street":"Veterans Rd",
    "iso:country":"US",
    "sg:address":"200 Veterans Rd",
    "sg:city":"Stoughton",
    "sg:classifiers":[
        {
            "category":"Organizations",
            "subcategory":"Community Association",
            "type":"Services"
        }
    ],
    "sg:phone":"+1 608 873 9042",
    "sg:postcode":"53589",
    "sg:province":"WI",
    "sg:tags":[
        "club"
    ],
    "wof:name":"Veterans Of Foreign Wars",
    "wof:placetype":"venue"
},
  "geometry": {"coordinates":[-89.200586,42.91726],"type":"Point"}
}