{
  "type": "Feature",
  "properties": {
    "addr:full":"3201 S 16th St Milwaukee WI 53215",
    "addr:housenumber":"3201",
    "addr:postcode":"53215",
    "addr:street":"S 16Th St",
    "iso:country":"US",
    "sg:address":"3201 S 16th St",
    "sg:city":"Milwaukee",
    "sg:classifiers":[
        {
            "category":"Health Services",
            "subcategory":"Doctor",
            "type":"Services"
        }
    ],
    "sg:phone":"+1 414 384 4700",
    "sg:postcode":"53215",
    "sg:province":"WI",
    "sg:tags":[
        "physician",
        "medical",
        "surgeon"
    ],
    "wof:name":"James D Boblin MD",
    "wof:placetype":"venue"
},
  "geometry": {"coordinates":[-87.933849,42.984736],"type":"Point"}
}