{
  "type": "Feature",
  "properties": {
    "iso:country":"US",
    "sg:address":"8249 Brazelton Dr",
    "sg:city":"Random Lake",
    "sg:classifiers":[
        {
            "category":"Farming",
            "subcategory":"Dairy Farm",
            "type":"Manufacturing & Wholesale Goods"
        }
    ],
    "sg:phone":"+1 920 994 9200",
    "sg:postcode":"53075",
    "sg:province":"WI",
    "wof:name":"Dairy Farm",
    "wof:placetype":"venue"
},
  "geometry": {"coordinates":[-88.11679100000001,43.57163],"type":"Point"}
}