{
  "type": "Feature",
  "properties": {
    "addr:full":"2228 State Hwy 88 Alma WI 54610",
    "addr:housenumber":"2228",
    "addr:postcode":"54610",
    "addr:street":"State Hwy 88",
    "iso:country":"US",
    "sg:address":"2228 State Hwy 88",
    "sg:city":"Alma",
    "sg:classifiers":[
        {
            "category":"Farming",
            "subcategory":"Dairy Farm",
            "type":"Manufacturing & Wholesale Goods"
        }
    ],
    "sg:phone":"+1 608 626 3991",
    "sg:postcode":"54610",
    "sg:province":"WI",
    "wof:name":"Don Dittrich",
    "wof:placetype":"venue"
},
  "geometry": {"coordinates":[-91.756142,44.271036],"type":"Point"}
}