{
  "type": "Feature",
  "properties": {
    "addr:full":"16401 W Greenfield Ave New Berlin WI 53151",
    "addr:housenumber":"16401",
    "addr:postcode":"53151",
    "addr:street":"W Greenfield Ave",
    "iso:country":"US",
    "sg:address":"16401 W Greenfield Ave",
    "sg:city":"New Berlin",
    "sg:classifiers":[
        {
            "category":"Autos & Motor Vehicles",
            "subcategory":"Fuel & Gas Station",
            "type":"Retail Goods"
        }
    ],
    "sg:phone":"+1 262 789 1865",
    "sg:postcode":"53151",
    "sg:province":"WI",
    "sg:tags":[
        "convenience",
        "station",
        "store"
    ],
    "wof:name":"Quick Trip Pantry",
    "wof:placetype":"venue"
},
  "geometry": {"coordinates":[-88.118427,43.016784],"type":"Point"}
}