{
  "type": "Feature",
  "properties": {
    "iso:country":"US",
    "sg:address":"9000 Michigan Ave",
    "sg:city":"Sturtevant",
    "sg:classifiers":[
        {
            "category":"Freight",
            "type":"Transportation"
        }
    ],
    "sg:phone":"+1 262 886 9898",
    "sg:postcode":"53177",
    "sg:province":"WI",
    "wof:name":"Safe T Store",
    "wof:placetype":"venue"
},
  "geometry": {"coordinates":[-87.896048,42.701254],"type":"Point"}
}