{
  "type": "Feature",
  "properties": {
    "addr:full":"205 E Hudson St Mondovi WI 54755",
    "addr:housenumber":"205",
    "addr:postcode":"54755",
    "addr:street":"E Hudson St",
    "iso:country":"US",
    "sg:address":"205 E Hudson St",
    "sg:city":"Mondovi",
    "sg:classifiers":[
        {
            "category":"Building & Trades",
            "subcategory":"Construction",
            "type":"Services"
        }
    ],
    "sg:phone":"+1 715 926 4685",
    "sg:postcode":"54755",
    "sg:province":"WI",
    "sg:tags":[
        "concrete",
        "contractor"
    ],
    "wof:name":"W T Concrete Construction",
    "wof:placetype":"venue"
},
  "geometry": {"coordinates":[-91.669408,44.566639],"type":"Point"}
}