{
  "type": "Feature",
  "properties": {
    "iso:country":"US",
    "sg:address":"510 E Garfield St",
    "sg:city":"Mt Horeb",
    "sg:classifiers":[
        {
            "category":"Wholesale",
            "subcategory":"Farm Supplies",
            "type":"Manufacturing & Wholesale Goods"
        }
    ],
    "sg:phone":"+1 608 437 8697",
    "sg:postcode":"53572",
    "sg:province":"WI",
    "sg:tags":[
        "fertilizer"
    ],
    "wof:name":"Agriliance",
    "wof:placetype":"venue"
},
  "geometry": {"coordinates":[-89.732507,43.005619],"type":"Point"}
}