{
  "type": "Feature",
  "properties": {
    "iso:country":"US",
    "sg:address":"7628 S 10th St",
    "sg:city":"Oak Creek",
    "sg:classifiers":[
        {
            "category":"Freight",
            "type":"Transportation"
        }
    ],
    "sg:phone":"+1 414 427 2478",
    "sg:postcode":"53154",
    "sg:province":"WI",
    "wof:name":"Diamond Logistics Inc",
    "wof:placetype":"venue"
},
  "geometry": {"coordinates":[-87.927081,42.905261],"type":"Point"}
}