{
  "type": "Feature",
  "properties": {
    "iso:country":"US",
    "sg:address":"600 E Fulton St",
    "sg:city":"Waupaca",
    "sg:classifiers":[
        {
            "category":"Government",
            "subcategory":"Office",
            "type":"Public Place"
        }
    ],
    "sg:phone":"+1 715 258 7050",
    "sg:postcode":"54981",
    "sg:province":"WI",
    "wof:name":"Waupaca County Shop",
    "wof:placetype":"venue"
},
  "geometry": {"coordinates":[-89.07844299999999,44.357873],"type":"Point"}
}