{
  "type": "Feature",
  "properties": {
    "iso:country":"US",
    "sg:address":"350 Bishops Way",
    "sg:city":"Brookfield",
    "sg:classifiers":[
        {
            "category":"Banks & Credit Unions",
            "subcategory":"Investment Brokerage",
            "type":"Services"
        }
    ],
    "sg:phone":"+1 262 796 2320",
    "sg:postcode":"53005",
    "sg:province":"WI",
    "sg:tags":[
        "security"
    ],
    "wof:name":"Elmbrook Financial Services",
    "wof:placetype":"venue"
},
  "geometry": {"coordinates":[-88.079273,43.032866],"type":"Point"}
}