{
  "type": "Feature",
  "properties": {
    "addr:full":"6200 W Mitchell St Milwaukee WI 53214",
    "addr:housenumber":"6200",
    "addr:postcode":"53214",
    "addr:street":"W Mitchell St",
    "iso:country":"US",
    "sg:address":"6200 W Mitchell St",
    "sg:city":"Milwaukee",
    "sg:classifiers":[
        {
            "category":"Real Estate",
            "subcategory":"Real Estate Agent",
            "type":"Services"
        }
    ],
    "sg:phone":"+1 414 727 9646",
    "sg:postcode":"53214",
    "sg:province":"WI",
    "wof:name":"Kiss Real Estate Management",
    "wof:placetype":"venue"
},
  "geometry": {"coordinates":[-87.99107600000001,43.01226],"type":"Point"}
}