{
  "type": "Feature",
  "properties": {
    "iso:country":"US",
    "sg:address":"7060 Roberts Rd",
    "sg:city":"Cambria",
    "sg:phone":"+1 920 348 5459",
    "sg:postcode":"53923",
    "sg:province":"WI",
    "sg:tags":[
        "farm",
        "corn"
    ],
    "wof:name":"Raymond Oft",
    "wof:placetype":"venue"
},
  "geometry": {"coordinates":[-89.117025,43.533771],"type":"Point"}
}