{
  "type": "Feature",
  "properties": {
    "iso:country":"US",
    "sg:address":"614 5th St",
    "sg:city":"Baraboo",
    "sg:classifiers":[
        {
            "category":"Shopping",
            "subcategory":"Clothing, Apparel, & Fashions",
            "type":"Retail Goods"
        }
    ],
    "sg:phone":"+1 608 355 9554",
    "sg:postcode":"53913",
    "sg:province":"WI",
    "wof:name":"Melissa Pyfferoen",
    "wof:placetype":"venue"
},
  "geometry": {"coordinates":[-89.733832,43.471747],"type":"Point"}
}