{
  "type": "Feature",
  "properties": {
    "iso:country":"US",
    "sg:address":"145 W Green Bay St",
    "sg:city":"Pulaski",
    "sg:classifiers":[
        {
            "category":"Education",
            "subcategory":"School",
            "type":"Public Place"
        }
    ],
    "sg:phone":"+1 920 822 6100",
    "sg:postcode":"54162",
    "sg:province":"WI",
    "sg:website":"www.pulaski.k12.wi.us",
    "wof:name":"Glenbrook Elementary School",
    "wof:placetype":"venue"
},
  "geometry": {"coordinates":[-88.243723,44.669235],"type":"Point"}
}