{
  "type": "Feature",
  "properties": {
    "iso:country":"US",
    "sg:address":"8202 Jade Dr",
    "sg:city":"Lodi",
    "sg:classifiers":[
        {
            "category":"Real Estate",
            "subcategory":"Real Estate Operator",
            "type":"Services"
        }
    ],
    "sg:phone":"+1 608 643 0028",
    "sg:postcode":"53555",
    "sg:province":"WI",
    "sg:tags":[
        "building",
        "nonresidential"
    ],
    "wof:name":"Pat & Dawn Properties LLC",
    "wof:placetype":"venue"
},
  "geometry": {"coordinates":[-89.623015,43.283308],"type":"Point"}
}