{
  "type": "Feature",
  "properties": {
    "addr:full":"18720 Pleasant St Brookfield WI 53045",
    "addr:housenumber":"18720",
    "addr:postcode":"53045",
    "addr:street":"Pleasant St",
    "iso:country":"US",
    "sg:address":"18720 Pleasant St",
    "sg:city":"Brookfield",
    "sg:classifiers":[
        {
            "category":"Real Estate",
            "subcategory":"Real Estate Services",
            "type":"Services"
        },
        {
            "category":"Professional",
            "subcategory":"Business Services",
            "type":"Services"
        },
        {
            "category":"Real Estate",
            "subcategory":"Surveying",
            "type":"Services"
        }
    ],
    "sg:phone":"+1 262 782 8200",
    "sg:postcode":"53045",
    "sg:province":"WI",
    "sg:tags":[
        "commercial",
        "appraisers-business",
        "industrial",
        "appraisers-commercial",
        "appraiser"
    ],
    "wof:name":"Mccartan Appraisal",
    "wof:placetype":"venue"
},
  "geometry": {"coordinates":[-88.144582,43.073273],"type":"Point"}
}