{
  "type": "Feature",
  "properties": {
    "iso:country":"US",
    "sg:address":"2726 State Hwy 213",
    "sg:city":"Evansville",
    "sg:classifiers":[
        {
            "category":"Retail",
            "subcategory":"Repair Shop",
            "type":"Services"
        }
    ],
    "sg:phone":"+1 608 882 5851",
    "sg:postcode":"53536",
    "sg:province":"WI",
    "sg:tags":[
        "welding"
    ],
    "wof:name":"D & B Welding & Fabricating",
    "wof:placetype":"venue"
},
  "geometry": {"coordinates":[-89.288763,42.720578],"type":"Point"}
}