{
  "type": "Feature",
  "properties": {
    "addr:full":"8825 N 76th St Milwaukee WI 53223",
    "addr:housenumber":"8825",
    "addr:postcode":"53223",
    "addr:street":"N 76Th St",
    "iso:country":"US",
    "sg:address":"8825 N 76th St",
    "sg:city":"Milwaukee",
    "sg:classifiers":[
        {
            "category":"Shopping",
            "subcategory":"Hobbies, Toys, & Games",
            "type":"Retail Goods"
        }
    ],
    "sg:phone":"+1 414 355 4110",
    "sg:postcode":"53223",
    "sg:province":"WI",
    "wof:name":"Toys R Us",
    "wof:placetype":"venue"
},
  "geometry": {"coordinates":[-88.00450600000001,43.18074],"type":"Point"}
}