{
  "type": "Feature",
  "properties": {
    "iso:country":"US",
    "sg:address":"1061 Clausen Rd",
    "sg:city":"Burlington",
    "sg:classifiers":[
        {
            "category":"Real Estate",
            "subcategory":"Real Estate Operator",
            "type":"Services"
        }
    ],
    "sg:phone":"+1 262 763 4637",
    "sg:postcode":"53105",
    "sg:province":"WI",
    "sg:tags":[
        "property",
        "lessor"
    ],
    "wof:name":"Clausen Farm Inc",
    "wof:placetype":"venue"
},
  "geometry": {"coordinates":[-88.37445200000001,42.66141],"type":"Point"}
}