{
  "type": "Feature",
  "properties": {
    "iso:country":"US",
    "sg:address":"38 Maple St",
    "sg:city":"Eau Claire",
    "sg:classifiers":[
        {
            "category":"Autos & Motor Vehicles",
            "subcategory":"Automobile Sales",
            "type":"Retail Goods"
        }
    ],
    "sg:phone":"+1 715 831 9720",
    "sg:postcode":"54703",
    "sg:province":"WI",
    "sg:tags":[
        "used"
    ],
    "wof:name":"I Cars Inc",
    "wof:placetype":"venue"
},
  "geometry": {"coordinates":[-91.51085500000001,44.82063],"type":"Point"}
}