{
  "type": "Feature",
  "properties": {
    "iso:country":"US",
    "sg:address":"1969 Co Rd T",
    "sg:city":"New Richmond",
    "sg:classifiers":[
        {
            "category":"Farming",
            "subcategory":"Dairy Farm",
            "type":"Manufacturing & Wholesale Goods"
        }
    ],
    "sg:phone":"+1 715 246 5117",
    "sg:postcode":"54017",
    "sg:province":"WI",
    "wof:name":"Thomas McNamara",
    "wof:placetype":"venue"
},
  "geometry": {"coordinates":[-92.436268,45.141182],"type":"Point"}
}