{
  "type": "Feature",
  "properties": {
    "iso:country":"US",
    "sg:address":"3901 Geano Beach Rd",
    "sg:city":"Little Suamico",
    "sg:classifiers":[
        {
            "category":"Travel",
            "subcategory":"Hotels & Motels",
            "type":"Entertainment"
        }
    ],
    "sg:phone":"+1 920 826 5845",
    "sg:postcode":"54141",
    "sg:province":"WI",
    "sg:tags":[
        "operation"
    ],
    "wof:name":"Geano Beach",
    "wof:placetype":"venue"
},
  "geometry": {"coordinates":[-87.960699,44.750421],"type":"Point"}
}