{
  "type": "Feature",
  "properties": {
    "addr:full":"2744 Klee St Green Bay WI 54313",
    "addr:housenumber":"2744",
    "addr:postcode":"54313",
    "addr:street":"Klee St",
    "iso:country":"US",
    "sg:address":"2744 Klee St",
    "sg:city":"Green Bay",
    "sg:classifiers":[
        {
            "category":"Retail",
            "subcategory":"Laundry & Dry Cleaning",
            "type":"Services"
        }
    ],
    "sg:phone":"+1 920 499 9942",
    "sg:postcode":"54313",
    "sg:province":"WI",
    "wof:name":"ABRA Chem-Dry",
    "wof:placetype":"venue"
},
  "geometry": {"coordinates":[-88.108058,44.533411],"type":"Point"}
}