{
  "type": "Feature",
  "properties": {
    "iso:country":"US",
    "sg:address":"1139 N Sunnyslope Dr",
    "sg:city":"Racine",
    "sg:classifiers":[
        {
            "category":"Professional",
            "subcategory":"Engineering",
            "type":"Services"
        }
    ],
    "sg:phone":"+1 262 886 3882",
    "sg:postcode":"53406",
    "sg:province":"WI",
    "sg:tags":[
        "engineer"
    ],
    "sg:website":"www.rbeng.com",
    "wof:name":"River's Bend Engineering Inc",
    "wof:placetype":"venue"
},
  "geometry": {"coordinates":[-87.862897,42.734828],"type":"Point"}
}