{
  "type": "Feature",
  "properties": {
    "iso:country":"US",
    "sg:address":"119 E Main St",
    "sg:city":"Gillett",
    "sg:classifiers":[
        {
            "category":"Real Estate",
            "subcategory":"Real Estate Services",
            "type":"Services"
        }
    ],
    "sg:phone":"+1 920 855 2956",
    "sg:postcode":"54124",
    "sg:province":"WI",
    "sg:tags":[
        "company",
        "title"
    ],
    "wof:name":"Northwoods Title",
    "wof:placetype":"venue"
},
  "geometry": {"coordinates":[-88.307219,44.890222],"type":"Point"}
}