{
  "type": "Feature",
  "properties": {
    "iso:country":"US",
    "sg:address":"3670 State Hwy 76",
    "sg:city":"Hortonville",
    "sg:classifiers":[
        {
            "category":"Bars & Pubs",
            "type":"Food & Drink"
        }
    ],
    "sg:phone":"+1 920 757 5059",
    "sg:postcode":"54944",
    "sg:province":"WI",
    "sg:tags":[
        "drinking"
    ],
    "wof:name":"Twisters",
    "wof:placetype":"venue"
},
  "geometry": {"coordinates":[-88.584475,44.373186],"type":"Point"}
}