{
  "type": "Feature",
  "properties": {
    "iso:country":"US",
    "sg:address":"1610 Cavour Ave",
    "sg:city":"Wabeno",
    "sg:classifiers":[
        {
            "category":"Professional",
            "subcategory":"Business Services",
            "type":"Services"
        }
    ],
    "sg:phone":"+1 715 473 4009",
    "sg:postcode":"54566",
    "sg:province":"WI",
    "wof:name":"Cavour Enterprises",
    "wof:placetype":"venue"
},
  "geometry": {"coordinates":[-88.65978699999999,45.435394],"type":"Point"}
}