{
  "type": "Feature",
  "properties": {
    "iso:country":"US",
    "sg:address":"411 E Court St",
    "sg:city":"Janesville",
    "sg:classifiers":[
        {
            "category":"Social Services",
            "type":"Services"
        }
    ],
    "sg:phone":"+1 608 373 0766",
    "sg:postcode":"53545",
    "sg:province":"WI",
    "sg:tags":[
        "housing",
        "assistance"
    ],
    "wof:name":"Lazarus Foundation Inc",
    "wof:placetype":"venue"
},
  "geometry": {"coordinates":[-89.017684,42.684192],"type":"Point"}
}