{
  "type": "Feature",
  "properties": {
    "iso:country":"US",
    "sg:address":"1720 Tower Ave",
    "sg:city":"Superior",
    "sg:classifiers":[
        {
            "category":"Manufacturing",
            "subcategory":"Retail Goods",
            "type":"Manufacturing & Wholesale Goods"
        }
    ],
    "sg:phone":"+1 715 395 9402",
    "sg:postcode":"54880",
    "sg:province":"WI",
    "sg:tags":[
        "product",
        "mfg"
    ],
    "wof:name":"Framing By Nancy",
    "wof:placetype":"venue"
},
  "geometry": {"coordinates":[-92.103869,46.717255],"type":"Point"}
}