{
  "type": "Feature",
  "properties": {
    "addr:full":"3392 Level Valley Rd Hustisford WI 53034",
    "addr:housenumber":"3392",
    "addr:postcode":"53034",
    "addr:street":"Level Valley Rd",
    "iso:country":"US",
    "sg:address":"3392 Level Valley Rd",
    "sg:city":"Hustisford",
    "sg:classifiers":[
        {
            "category":"Real Estate",
            "subcategory":"Real Estate Operator",
            "type":"Services"
        }
    ],
    "sg:phone":"+1 920 349 3743",
    "sg:postcode":"53034",
    "sg:province":"WI",
    "sg:tags":[
        "property",
        "lessor"
    ],
    "wof:name":"Level Valley Dairy Farm",
    "wof:placetype":"venue"
},
  "geometry": {"coordinates":[-88.608052,43.338404],"type":"Point"}
}