{
  "type": "Feature",
  "properties": {
    "iso:country":"US",
    "sg:address":"17464 N Main St",
    "sg:city":"Galesville",
    "sg:classifiers":[
        {
            "category":"Building & Trades",
            "subcategory":"Equipment Rental",
            "type":"Services"
        }
    ],
    "sg:phone":"+1 608 582 3322",
    "sg:postcode":"54630",
    "sg:province":"WI",
    "wof:name":"Indepndnce Lmbr/True Vlue Hdwr",
    "wof:placetype":"venue"
},
  "geometry": {"coordinates":[-91.342719,44.091404],"type":"Point"}
}