{
  "type": "Feature",
  "properties": {
    "iso:country":"US",
    "sg:address":"6484 US Hwy 45",
    "sg:city":"Land O Lakes",
    "sg:classifiers":[
        {
            "category":"Organizations",
            "subcategory":"Professional Association",
            "type":"Services"
        }
    ],
    "sg:phone":"+1 715 547 3432",
    "sg:postcode":"54540",
    "sg:province":"WI",
    "sg:tags":[
        "chambers",
        "business",
        "commerce"
    ],
    "wof:name":"Land OLakes Chamber Commerce",
    "wof:placetype":"venue"
},
  "geometry": {"coordinates":[-89.20538999999999,46.159672],"type":"Point"}
}