{
  "type": "Feature",
  "properties": {
    "iso:country":"US",
    "sg:address":"7 Jachim Dr",
    "sg:city":"Rice Lake",
    "sg:classifiers":[
        {
            "category":"Freight",
            "type":"Transportation"
        }
    ],
    "sg:phone":"+1 715 234 7376",
    "sg:postcode":"54868",
    "sg:province":"WI",
    "sg:tags":[
        "operator",
        "local",
        "trucking"
    ],
    "wof:name":"Paul A Jachim Trucking Inc",
    "wof:placetype":"venue"
},
  "geometry": {"coordinates":[-91.714491,45.483845],"type":"Point"}
}