{
  "type": "Feature",
  "properties": {
    "iso:country":"US",
    "sg:address":"2001 Deerfield Rd",
    "sg:city":"Saukville",
    "sg:classifiers":[
        {
            "category":"Building & Trades",
            "subcategory":"Construction",
            "type":"Services"
        }
    ],
    "sg:phone":"+1 262 284 5933",
    "sg:postcode":"53080",
    "sg:province":"WI",
    "sg:tags":[
        "excavation",
        "contractor"
    ],
    "wof:name":"Burich Excavating",
    "wof:placetype":"venue"
},
  "geometry": {"coordinates":[-87.966304,43.42292],"type":"Point"}
}