{
  "type": "Feature",
  "properties": {
    "iso:country":"US",
    "sg:address":"734 N 4th St",
    "sg:city":"Milwaukee",
    "sg:classifiers":[
        {
            "category":"Government",
            "subcategory":"Office",
            "type":"Public Place"
        }
    ],
    "sg:phone":"+1 414 454 4480",
    "sg:postcode":"53203",
    "sg:province":"WI",
    "wof:name":"Milwaukee County of",
    "wof:placetype":"venue"
},
  "geometry": {"coordinates":[-87.916051,43.039278],"type":"Point"}
}