{
  "type": "Feature",
  "properties": {
    "iso:country":"US",
    "sg:address":"125 Wisconsin St",
    "sg:city":"Darien",
    "sg:classifiers":[
        {
            "category":"Government",
            "subcategory":"Office",
            "type":"Public Place"
        }
    ],
    "sg:phone":"+1 262 882 2030",
    "sg:postcode":"53114",
    "sg:province":"WI",
    "sg:tags":[
        "village"
    ],
    "wof:name":"Lauderdale Lakes Water Patrol",
    "wof:placetype":"venue"
},
  "geometry": {"coordinates":[-88.707757,42.602817],"type":"Point"}
}