{
  "type": "Feature",
  "properties": {
    "iso:country":"US",
    "sg:address":"7710 Westman Way Rd",
    "sg:city":"Middleton",
    "sg:classifiers":[
        {
            "category":"Wholesale",
            "subcategory":"Electrical",
            "type":"Manufacturing & Wholesale Goods"
        }
    ],
    "sg:phone":"+1 608 836 5844",
    "sg:postcode":"53562",
    "sg:province":"WI",
    "sg:tags":[
        "equipment",
        "mfg"
    ],
    "wof:name":"F C I Burndy Electrical",
    "wof:placetype":"venue"
},
  "geometry": {"coordinates":[-89.58787599999999,43.114273],"type":"Point"}
}