{
  "type": "Feature",
  "properties": {
    "iso:country":"US",
    "sg:address":"1111 W Historic Mitchell St",
    "sg:city":"Milwaukee",
    "sg:classifiers":[
        {
            "category":"Shopping",
            "subcategory":"Clothing, Apparel, & Fashions",
            "type":"Retail Goods"
        }
    ],
    "sg:phone":"+1 414 672 4492",
    "sg:postcode":"53204",
    "sg:province":"WI",
    "sg:tags":[
        "fur",
        "business"
    ],
    "wof:name":"Holzmans Furs",
    "wof:placetype":"venue"
},
  "geometry": {"coordinates":[-87.926821,43.012213],"type":"Point"}
}