{
  "type": "Feature",
  "properties": {
    "iso:country":"US",
    "sg:address":"4217 Nakoosa Trl",
    "sg:city":"Madison",
    "sg:classifiers":[
        {
            "category":"Wholesale",
            "subcategory":"Farm Supplies",
            "type":"Manufacturing & Wholesale Goods"
        }
    ],
    "sg:phone":"+1 608 244 0200",
    "sg:postcode":"53714",
    "sg:province":"WI",
    "sg:tags":[
        "equipment",
        "ornamental",
        "nursery",
        "dist",
        "turf"
    ],
    "wof:name":"Reinders Turf & Irrigation",
    "wof:placetype":"venue"
},
  "geometry": {"coordinates":[-89.313282,43.108703],"type":"Point"}
}