{
  "type": "Feature",
  "properties": {
    "iso:country":"US",
    "sg:address":"109 Warren St",
    "sg:city":"Beaver Dam",
    "sg:classifiers":[
        {
            "category":"Health Services",
            "subcategory":"Health Practitioner",
            "type":"Services"
        }
    ],
    "sg:phone":"+1 920 885 9776",
    "sg:postcode":"53916",
    "sg:province":"WI",
    "sg:tags":[
        "audiologists"
    ],
    "wof:name":"Michael C Stupich",
    "wof:placetype":"venue"
},
  "geometry": {"coordinates":[-88.824046,43.449503],"type":"Point"}
}