{
  "type": "Feature",
  "properties": {
    "iso:country":"US",
    "sg:address":"621 Cross St",
    "sg:city":"La Crosse",
    "sg:classifiers":[
        {
            "category":"Real Estate",
            "subcategory":"Real Estate Operator",
            "type":"Services"
        }
    ],
    "sg:phone":"+1 608 784 5110",
    "sg:postcode":"54601",
    "sg:province":"WI",
    "sg:tags":[
        "building",
        "water",
        "transport",
        "nonresidential"
    ],
    "wof:name":"Bikini Yacht Club Inc",
    "wof:placetype":"venue"
},
  "geometry": {"coordinates":[-91.25590800000001,43.807913],"type":"Point"}
}