{
  "type": "Feature",
  "properties": {
    "iso:country":"US",
    "sg:address":"309 W Main St",
    "sg:city":"Arcadia",
    "sg:classifiers":[
        {
            "category":"Bars & Pubs",
            "type":"Food & Drink"
        }
    ],
    "sg:phone":"+1 608 323 2028",
    "sg:postcode":"54612",
    "sg:province":"WI",
    "wof:name":"Farmers Inn",
    "wof:placetype":"venue"
},
  "geometry": {"coordinates":[-91.502825,44.252747],"type":"Point"}
}