{
  "type": "Feature",
  "properties": {
    "iso:country":"US",
    "sg:address":"3776 Stone Pass",
    "sg:city":"Oregon",
    "sg:classifiers":[
        {
            "category":"Shopping",
            "subcategory":"Books",
            "type":"Retail Goods"
        }
    ],
    "sg:phone":"+1 608 455 1913",
    "sg:postcode":"53575",
    "sg:province":"WI",
    "sg:tags":[
        "dealer"
    ],
    "wof:name":"Jeannie's Personalized Books",
    "wof:placetype":"venue"
},
  "geometry": {"coordinates":[-89.297217,42.868476],"type":"Point"}
}