{
  "type": "Feature",
  "properties": {
    "iso:country":"US",
    "sg:address":"611 148th Ave",
    "sg:city":"Somerset",
    "sg:classifiers":[
        {
            "category":"Manufacturing",
            "subcategory":"Tools & Machinery",
            "type":"Manufacturing & Wholesale Goods"
        }
    ],
    "sg:phone":"+1 715 247 3550",
    "sg:postcode":"54025",
    "sg:province":"WI",
    "sg:tags":[
        "farm",
        "mfg"
    ],
    "wof:name":"Schottler Pumping",
    "wof:placetype":"venue"
},
  "geometry": {"coordinates":[-92.678332,45.0765],"type":"Point"}
}