{
  "type": "Feature",
  "properties": {
    "iso:country":"US",
    "sg:address":"5461 Panther Creek Rd",
    "sg:city":"Neillsville",
    "sg:classifiers":[
        {
            "category":"Farming",
            "subcategory":"Livestock Farm",
            "type":"Manufacturing & Wholesale Goods"
        }
    ],
    "sg:phone":"+1 715 743 4539",
    "sg:postcode":"54456",
    "sg:province":"WI",
    "sg:tags":[
        "beef",
        "feedlot",
        "cattle"
    ],
    "wof:name":"Glen Halle",
    "wof:placetype":"venue"
},
  "geometry": {"coordinates":[-90.591427,44.639934],"type":"Point"}
}