{
  "type": "Feature",
  "properties": {
    "iso:country":"US",
    "sg:address":"9893 408th Ave",
    "sg:city":"Eau Claire",
    "sg:classifiers":[
        {
            "category":"Shopping",
            "subcategory":"Computers & Home Electronics",
            "type":"Retail Goods"
        }
    ],
    "sg:phone":"+1 715 874 5298",
    "sg:postcode":"54739",
    "sg:province":"WI",
    "wof:name":"Audio Video Clinic",
    "wof:placetype":"venue"
},
  "geometry": {"coordinates":[-91.661295,44.827744],"type":"Point"}
}