{
  "type": "Feature",
  "properties": {
    "iso:country":"US",
    "sg:address":"4061 State Hwy 28",
    "sg:city":"Sheboygan Falls",
    "sg:classifiers":[
        {
            "category":"Shopping",
            "subcategory":"Clothing, Apparel, & Fashions",
            "type":"Retail Goods"
        }
    ],
    "sg:phone":"+1 920 208 6005",
    "sg:postcode":"53085",
    "sg:province":"WI",
    "wof:name":"Dress Barn",
    "wof:placetype":"venue"
},
  "geometry": {"coordinates":[-87.897761,43.699231],"type":"Point"}
}