{
  "type": "Feature",
  "properties": {
    "iso:country":"US",
    "sg:address":"555 N Hickory Farm Ln",
    "sg:city":"Appleton",
    "sg:classifiers":[
        {
            "category":"Professional",
            "type":"Services"
        }
    ],
    "sg:phone":"+1 920 997 2200",
    "sg:postcode":"54914",
    "sg:province":"WI",
    "sg:tags":[
        "establishment"
    ],
    "wof:name":"Anchor Express",
    "wof:placetype":"venue"
},
  "geometry": {"coordinates":[-88.44839,44.267959],"type":"Point"}
}