{
  "type": "Feature",
  "properties": {
    "iso:country":"US",
    "sg:address":"8660 N 107th St",
    "sg:city":"Milwaukee",
    "sg:classifiers":[
        {
            "category":"Restaurant",
            "type":"Food & Drink"
        }
    ],
    "sg:phone":"+1 414 354 8950",
    "sg:postcode":"53224",
    "sg:province":"WI",
    "sg:tags":[
        "bar"
    ],
    "wof:name":"Black Kettle",
    "wof:placetype":"venue"
},
  "geometry": {"coordinates":[-88.044156,43.175381],"type":"Point"}
}