{
  "type": "Feature",
  "properties": {
    "iso:country":"US",
    "sg:address":"44128 Wheatville Rd",
    "sg:city":"Gays Mills",
    "sg:classifiers":[
        {
            "category":"Manufacturing",
            "subcategory":"Building Materials",
            "type":"Manufacturing & Wholesale Goods"
        },
        {
            "category":"Building & Trades",
            "subcategory":"Construction",
            "type":"Services"
        }
    ],
    "sg:phone":"+1 608 872 2466",
    "sg:postcode":"54631",
    "sg:province":"WI",
    "sg:tags":[
        "cabinet",
        "wood",
        "maker",
        "kitchen",
        "mfg"
    ],
    "wof:name":"Walkers Custom Cabinetry LLC",
    "wof:placetype":"venue"
},
  "geometry": {"coordinates":[-90.7358,43.270287],"type":"Point"}
}