{
  "type": "Feature",
  "properties": {
    "iso:country":"US",
    "sg:address":"54225 Co Hwy D",
    "sg:city":"Grand View",
    "sg:classifiers":[
        {
            "category":"Recreation",
            "type":"Entertainment"
        }
    ],
    "sg:phone":"+1 715 763 3160",
    "sg:postcode":"54839",
    "sg:province":"WI",
    "sg:tags":[
        "parks"
    ],
    "wof:name":"Grand View Ball Park",
    "wof:placetype":"venue"
},
  "geometry": {"coordinates":[-91.10548,46.36082],"type":"Point"}
}