{
  "type": "Feature",
  "properties": {
    "addr:full":"116 S Main St Elmwood WI 54740",
    "addr:housenumber":"116",
    "addr:postcode":"54740",
    "addr:street":"S Main St",
    "iso:country":"US",
    "sg:address":"116 S Main St",
    "sg:city":"Elmwood",
    "sg:classifiers":[
        {
            "category":"Utilities",
            "subcategory":"Cable",
            "type":"Services"
        }
    ],
    "sg:phone":"+1 715 639 2121",
    "sg:postcode":"54740",
    "sg:province":"WI",
    "sg:tags":[
        "television"
    ],
    "wof:name":"De Marce TV",
    "wof:placetype":"venue"
},
  "geometry": {"coordinates":[-92.151349,44.779362],"type":"Point"}
}