{
  "type": "Feature",
  "properties": {
    "addr:full":"1840 Meadow Ln Elkhorn WI 53121",
    "addr:housenumber":"1840",
    "addr:postcode":"53121",
    "addr:street":"Meadow Ln",
    "iso:country":"US",
    "sg:address":"1840 Meadow Ln",
    "sg:city":"Elkhorn",
    "sg:classifiers":[
        {
            "category":"Banks & Credit Unions",
            "subcategory":"Bank",
            "type":"Services"
        }
    ],
    "sg:phone":"+1 262 549 0947",
    "sg:postcode":"53121",
    "sg:province":"WI",
    "sg:tags":[
        "cashing",
        "check"
    ],
    "wof:name":"Advance America",
    "wof:placetype":"venue"
},
  "geometry": {"coordinates":[-88.538877,42.641254],"type":"Point"}
}