{
  "type": "Feature",
  "properties": {
    "iso:country":"US",
    "sg:address":"2221 63rd St",
    "sg:city":"Kenosha",
    "sg:classifiers":[
        {
            "category":"Professional",
            "subcategory":"Lawyer & Legal Services",
            "type":"Services"
        }
    ],
    "sg:phone":"+1 262 654 8669",
    "sg:postcode":"53143",
    "sg:province":"WI",
    "sg:tags":[
        "attorney"
    ],
    "wof:name":"Easton Law Office",
    "wof:placetype":"venue"
},
  "geometry": {"coordinates":[-87.836589,42.577573],"type":"Point"}
}