{
  "type": "Feature",
  "properties": {
    "iso:country":"US",
    "sg:address":"2215 S Oneida St",
    "sg:city":"Appleton",
    "sg:classifiers":[
        {
            "category":"Wholesale",
            "subcategory":"Stationery",
            "type":"Manufacturing & Wholesale Goods"
        }
    ],
    "sg:phone":"+1 920 749 2820",
    "sg:postcode":"54915",
    "sg:province":"WI",
    "sg:tags":[
        "product",
        "paper"
    ],
    "wof:name":"Strategic Paper Group",
    "wof:placetype":"venue"
},
  "geometry": {"coordinates":[-88.403998,44.24181],"type":"Point"}
}