{
  "type": "Feature",
  "properties": {
    "iso:country":"US",
    "sg:address":"1011 Industrial Dr",
    "sg:city":"Fort Atkinson",
    "sg:classifiers":[
        {
            "category":"Home & Garden",
            "subcategory":"Building Materials",
            "type":"Retail Goods"
        },
        {
            "category":"Building & Trades",
            "subcategory":"Construction",
            "type":"Services"
        }
    ],
    "sg:phone":"+1 920 563 5555",
    "sg:postcode":"53538",
    "sg:province":"WI",
    "sg:tags":[
        "plate",
        "glazing",
        "automotive",
        "replace",
        "glass",
        "window",
        "contractor"
    ],
    "wof:name":"Fort Atkinson Glass and Mirror",
    "wof:placetype":"venue"
},
  "geometry": {"coordinates":[-88.850854,42.916052],"type":"Point"}
}