{
  "type": "Feature",
  "properties": {
    "iso:country":"US",
    "sg:address":"816 Erie Ave",
    "sg:city":"Sheboygan",
    "sg:classifiers":[
        {
            "category":"Home & Garden",
            "subcategory":"Building Materials",
            "type":"Retail Goods"
        }
    ],
    "sg:phone":"+1 920 459 0687",
    "sg:postcode":"53081",
    "sg:province":"WI",
    "sg:tags":[
        "glass",
        "window",
        "plate"
    ],
    "wof:name":"Triumph Auto Glass",
    "wof:placetype":"venue"
},
  "geometry": {"coordinates":[-87.71440800000001,43.756424],"type":"Point"}
}