{
  "type": "Feature",
  "properties": {
    "iso:country":"US",
    "sg:address":"10202 Sunny Point Rd",
    "sg:city":"Tomahawk",
    "sg:classifiers":[
        {
            "category":"Travel",
            "subcategory":"Hotels & Motels",
            "type":"Entertainment"
        }
    ],
    "sg:phone":"+1 715 453 3271",
    "sg:postcode":"54487",
    "sg:province":"WI",
    "sg:tags":[
        "resort",
        "operation"
    ],
    "wof:name":"Edd's Sunny Point Resort",
    "wof:placetype":"venue"
},
  "geometry": {"coordinates":[-89.60482399999999,45.48286],"type":"Point"}
}