{
  "type": "Feature",
  "properties": {
    "iso:country":"US",
    "sg:address":"401 W 4th St N",
    "sg:city":"Ladysmith",
    "sg:classifiers":[
        {
            "category":"Health Services",
            "subcategory":"Clinic",
            "type":"Services"
        }
    ],
    "sg:phone":"+1 715 532 3727",
    "sg:postcode":"54848",
    "sg:province":"WI",
    "sg:tags":[
        "medical",
        "care"
    ],
    "wof:name":"Key Care Inc",
    "wof:placetype":"venue"
},
  "geometry": {"coordinates":[-91.10494799999999,45.469063],"type":"Point"}
}