{
  "type": "Feature",
  "properties": {
    "iso:country":"US",
    "sg:address":"7727 W Center St",
    "sg:city":"Milwaukee",
    "sg:classifiers":[
        {
            "category":"Social Services",
            "subcategory":"Child Care",
            "type":"Services"
        }
    ],
    "sg:phone":"+1 414 479 0095",
    "sg:postcode":"53222",
    "sg:province":"WI",
    "wof:name":"Enders Bluemound Preschool Inc",
    "wof:placetype":"venue"
},
  "geometry": {"coordinates":[-88.008639,43.067956],"type":"Point"}
}