{
  "type": "Feature",
  "properties": {
    "iso:country":"US",
    "sg:address":"2230 S Ashland Ave",
    "sg:city":"Green Bay",
    "sg:classifiers":[
        {
            "category":"Manufacturing",
            "subcategory":"Metals",
            "type":"Manufacturing & Wholesale Goods"
        },
        {
            "category":"Wholesale",
            "subcategory":"Durable Goods & Equipment",
            "type":"Manufacturing & Wholesale Goods"
        }
    ],
    "sg:phone":"+1 920 965 1924",
    "sg:postcode":"54304",
    "sg:province":"WI",
    "sg:tags":[
        "dry wall",
        "contractor"
    ],
    "wof:name":"Badgeriand Supply Inc",
    "wof:placetype":"venue"
},
  "geometry": {"coordinates":[-88.050683,44.488838],"type":"Point"}
}