{
  "type": "Feature",
  "properties": {
    "iso:country":"US",
    "sg:address":"777 20th Ave",
    "sg:city":"Clear Lake",
    "sg:classifiers":[
        {
            "category":"Building & Trades",
            "subcategory":"Construction",
            "type":"Services"
        }
    ],
    "sg:phone":"+1 715 263 3441",
    "sg:postcode":"54005",
    "sg:province":"WI",
    "sg:tags":[
        "contractor"
    ],
    "wof:name":"Bobs Sandblasting & Painting",
    "wof:placetype":"venue"
},
  "geometry": {"coordinates":[-92.319334,45.238687],"type":"Point"}
}