{
  "type": "Feature",
  "properties": {
    "iso:country":"US",
    "sg:address":"3413 Berkshire Rd",
    "sg:city":"Janesville",
    "sg:classifiers":[
        {
            "category":"Manufacturing",
            "subcategory":"Printing",
            "type":"Manufacturing & Wholesale Goods"
        }
    ],
    "sg:phone":"+1 608 756 0222",
    "sg:postcode":"53546",
    "sg:province":"WI",
    "sg:tags":[
        "lithographic",
        "commercial"
    ],
    "wof:name":"Print Tech",
    "wof:placetype":"venue"
},
  "geometry": {"coordinates":[-88.977555,42.679429],"type":"Point"}
}