{
  "type": "Feature",
  "properties": {
    "addr:full":"1818 W National Ave Milwaukee WI 53204",
    "addr:housenumber":"1818",
    "addr:postcode":"53204",
    "addr:street":"W National Ave",
    "iso:country":"US",
    "sg:address":"1818 W National Ave",
    "sg:city":"Milwaukee",
    "sg:classifiers":[
        {
            "category":"Banks & Credit Unions",
            "subcategory":"Bank",
            "type":"Services"
        }
    ],
    "sg:phone":"+1 414 645 4271",
    "sg:postcode":"53204",
    "sg:province":"WI",
    "sg:tags":[
        "cashing",
        "check"
    ],
    "wof:name":"Money Express",
    "wof:placetype":"venue"
},
  "geometry": {"coordinates":[-87.938024,43.022837],"type":"Point"}
}