{
  "type": "Feature",
  "properties": {
    "addr:full":"3614 Rock Rd Appleton WI 54913",
    "addr:housenumber":"3614",
    "addr:postcode":"54913",
    "addr:street":"Rock Rd",
    "iso:country":"US",
    "sg:address":"3614 Rock Rd",
    "sg:city":"Appleton",
    "sg:classifiers":[
        {
            "category":"Building & Trades",
            "subcategory":"Landscaping Services",
            "type":"Services"
        }
    ],
    "sg:phone":"+1 920 730 0477",
    "sg:postcode":"54913",
    "sg:province":"WI",
    "sg:tags":[
        "topsoil"
    ],
    "wof:name":"CLK Materials",
    "wof:placetype":"venue"
},
  "geometry": {"coordinates":[-88.369753,44.372397],"type":"Point"}
}