{
  "type": "Feature",
  "properties": {
    "iso:country":"US",
    "sg:address":"4737 83rd St",
    "sg:city":"Kenosha",
    "sg:classifiers":[
        {
            "category":"Professional",
            "subcategory":"Management & Consulting",
            "type":"Services"
        }
    ],
    "sg:phone":"+1 262 697 1588",
    "sg:postcode":"53142",
    "sg:province":"WI",
    "sg:tags":[
        "consultant",
        "business"
    ],
    "wof:name":"Lincoln Aviation Management",
    "wof:placetype":"venue"
},
  "geometry": {"coordinates":[-87.865733,42.554839],"type":"Point"}
}