{
  "type": "Feature",
  "properties": {
    "iso:country":"US",
    "sg:address":"761 W Beaverbrook Ave",
    "sg:city":"Spooner",
    "sg:classifiers":[
        {
            "category":"Professional",
            "type":"Services"
        },
        {
            "category":"Recreation",
            "type":"Entertainment"
        }
    ],
    "sg:phone":"+1 715 635 6688",
    "sg:postcode":"54801",
    "sg:province":"WI",
    "sg:tags":[
        "establishment"
    ],
    "wof:name":"Northwest Wisconsin Knights Ho",
    "wof:placetype":"venue"
},
  "geometry": {"coordinates":[-91.908216,45.815683],"type":"Point"}
}