{
  "type": "Feature",
  "properties": {
    "iso:country":"US",
    "sg:address":"1040 Williamson St",
    "sg:city":"Madison",
    "sg:classifiers":[
        {
            "category":"Professional",
            "type":"Services"
        }
    ],
    "sg:phone":"+1 608 257 1755",
    "sg:postcode":"53703",
    "sg:province":"WI",
    "sg:tags":[
        "establishment"
    ],
    "wof:name":"LA Samaritaine House",
    "wof:placetype":"venue"
},
  "geometry": {"coordinates":[-89.36668899999999,43.081546],"type":"Point"}
}