{
  "type": "Feature",
  "properties": {
    "iso:country":"US",
    "sg:address":"2180 S Danny Rd",
    "sg:city":"New Berlin",
    "sg:classifiers":[
        {
            "category":"Manufacturing",
            "subcategory":"Tools & Machinery",
            "type":"Manufacturing & Wholesale Goods"
        }
    ],
    "sg:phone":"+1 262 542 2306",
    "sg:postcode":"53146",
    "sg:province":"WI",
    "sg:tags":[
        "machine",
        "shop"
    ],
    "wof:name":"Jensen Tool and Manufacturing",
    "wof:placetype":"venue"
},
  "geometry": {"coordinates":[-88.168406,43.004258],"type":"Point"}
}