{
  "type": "Feature",
  "properties": {
    "iso:country":"US",
    "sg:address":"218 S Spring St",
    "sg:city":"Beaver Dam",
    "sg:classifiers":[
        {
            "category":"Shopping",
            "subcategory":"Bicycles & Sporting Goods",
            "type":"Retail Goods"
        }
    ],
    "sg:phone":"+1 920 885 2233",
    "sg:postcode":"53916",
    "sg:province":"WI",
    "wof:name":"All Seasons Archery Place",
    "wof:placetype":"venue"
},
  "geometry": {"coordinates":[-88.836905,43.455088],"type":"Point"}
}