{
  "type": "Feature",
  "properties": {
    "iso:country":"US",
    "sg:address":"7530 N Co Rd M",
    "sg:city":"Evansville",
    "sg:classifiers":[
        {
            "category":"Bars & Pubs",
            "type":"Food & Drink"
        }
    ],
    "sg:phone":"+1 608 882 4583",
    "sg:postcode":"53536",
    "sg:province":"WI",
    "sg:tags":[
        "dance",
        "drinking",
        "eating"
    ],
    "wof:name":"White Bar",
    "wof:placetype":"venue"
},
  "geometry": {"coordinates":[-89.274481,42.78094],"type":"Point"}
}