{
  "type": "Feature",
  "properties": {
    "iso:country":"US",
    "sg:address":"1115 Superior Ave",
    "sg:city":"Tomah",
    "sg:classifiers":[
        {
            "category":"Bars & Pubs",
            "type":"Food & Drink"
        }
    ],
    "sg:phone":"+1 608 372 7888",
    "sg:postcode":"54660",
    "sg:province":"WI",
    "sg:tags":[
        "drinking"
    ],
    "wof:name":"Frannys",
    "wof:placetype":"venue"
},
  "geometry": {"coordinates":[-90.504866,43.976033],"type":"Point"}
}