{
  "type": "Feature",
  "properties": {
    "iso:country":"US",
    "sg:address":"3613 Schofield Ave",
    "sg:city":"Schofield",
    "sg:classifiers":[
        {
            "category":"Restaurant",
            "type":"Food & Drink"
        }
    ],
    "sg:phone":"+1 715 241 7282",
    "sg:postcode":"54476",
    "sg:province":"WI",
    "sg:tags":[
        "shop",
        "coffee"
    ],
    "wof:name":"Superior Coffee",
    "wof:placetype":"venue"
},
  "geometry": {"coordinates":[-89.57964,44.904712],"type":"Point"}
}