{
  "type": "Feature",
  "properties": {
    "iso:country":"US",
    "sg:address":"112 S 68th St",
    "sg:city":"Milwaukee",
    "sg:classifiers":[
        {
            "category":"Retail",
            "subcategory":"Car Wash",
            "type":"Services"
        }
    ],
    "sg:phone":"+1 414 258 0777",
    "sg:postcode":"53214",
    "sg:province":"WI",
    "sg:tags":[
        "carwash"
    ],
    "wof:name":"Soft Touch Car Wash",
    "wof:placetype":"venue"
},
  "geometry": {"coordinates":[-87.997313,43.031131],"type":"Point"}
}