{
  "type": "Feature",
  "properties": {
    "addr:full":"5634 Rankin Ln Waunakee WI 53597",
    "addr:housenumber":"5634",
    "addr:postcode":"53597",
    "addr:street":"Rankin Ln",
    "iso:country":"US",
    "sg:address":"5634 Rankin Ln",
    "sg:city":"Waunakee",
    "sg:classifiers":[
        {
            "category":"Professional",
            "type":"Services"
        }
    ],
    "sg:phone":"+1 608 850 3244",
    "sg:postcode":"53597",
    "sg:province":"WI",
    "sg:tags":[
        "establishment"
    ],
    "wof:name":"Krysinski & Assoc",
    "wof:placetype":"venue"
},
  "geometry": {"coordinates":[-89.428912,43.16291],"type":"Point"}
}