{
  "type": "Feature",
  "properties": {
    "iso:country":"US",
    "sg:address":"136 W Main St",
    "sg:city":"Winneconne",
    "sg:classifiers":[
        {
            "category":"Professional",
            "subcategory":"Business Services",
            "type":"Services"
        }
    ],
    "sg:phone":"+1 920 582 4840",
    "sg:postcode":"54986",
    "sg:province":"WI",
    "wof:name":"Michels Sportswear Ltd",
    "wof:placetype":"venue"
},
  "geometry": {"coordinates":[-88.71170499999999,44.110922],"type":"Point"}
}