{
  "type": "Feature",
  "properties": {
    "iso:country":"US",
    "sg:address":"1325 S 70th St",
    "sg:city":"Milwaukee",
    "sg:classifiers":[
        {
            "category":"Bars & Pubs",
            "type":"Food & Drink"
        }
    ],
    "sg:phone":"+1 414 443 9337",
    "sg:postcode":"53214",
    "sg:province":"WI",
    "sg:tags":[
        "drinking"
    ],
    "wof:name":"Bozs Sports Bar",
    "wof:placetype":"venue"
},
  "geometry": {"coordinates":[-88.00010899999999,43.017135],"type":"Point"}
}