{
  "type": "Feature",
  "properties": {
    "addr:full":"7750 243rd Ave Salem WI 53168",
    "addr:housenumber":"7750",
    "addr:postcode":"53168",
    "addr:street":"243Rd Ave",
    "iso:country":"US",
    "sg:address":"7750 243rd Ave",
    "sg:city":"Salem",
    "sg:classifiers":[
        {
            "category":"Health Services",
            "subcategory":"Nursing And Care Facility",
            "type":"Services"
        }
    ],
    "sg:phone":"+1 262 843 2220",
    "sg:postcode":"53168",
    "sg:province":"WI",
    "sg:tags":[
        "home",
        "convalescent"
    ],
    "wof:name":"Brotoloc Health Care",
    "wof:placetype":"venue"
},
  "geometry": {"coordinates":[-88.10247,42.565428],"type":"Point"}
}