{
  "type": "Feature",
  "properties": {
    "iso:country":"US",
    "sg:address":"2094 Atwood Ave",
    "sg:city":"Madison",
    "sg:classifiers":[
        {
            "category":"Food & Beverages",
            "subcategory":"Specialty",
            "type":"Retail Goods"
        }
    ],
    "sg:phone":"+1 608 244 9297",
    "sg:postcode":"53704",
    "sg:province":"WI",
    "sg:tags":[
        "herb"
    ],
    "wof:name":"Green Earth",
    "wof:placetype":"venue"
},
  "geometry": {"coordinates":[-89.35256,43.0926],"type":"Point"}
}