{
  "type": "Feature",
  "properties": {
    "iso:country":"US",
    "sg:address":"259 Wildfire Ln",
    "sg:city":"Milton",
    "sg:classifiers":[
        {
            "category":"Shopping",
            "subcategory":"Hobbies, Toys, & Games",
            "type":"Retail Goods"
        },
        {
            "category":"Building & Trades",
            "subcategory":"Construction",
            "type":"Services"
        }
    ],
    "sg:phone":"+1 608 868 4722",
    "sg:postcode":"53563",
    "sg:province":"WI",
    "sg:tags":[
        "home",
        "builder",
        "nonresidential",
        "contractor"
    ],
    "wof:name":"Beaty Construction LLC",
    "wof:placetype":"venue"
},
  "geometry": {"coordinates":[-88.948007,42.772182],"type":"Point"}
}