{
  "type": "Feature",
  "properties": {
    "iso:country":"US",
    "sg:address":"1124 Stewart St",
    "sg:city":"Madison",
    "sg:classifiers":[
        {
            "category":"Wholesale",
            "subcategory":"Non-durable Goods",
            "type":"Manufacturing & Wholesale Goods"
        }
    ],
    "sg:phone":"+1 608 278 8804",
    "sg:postcode":"53713",
    "sg:province":"WI",
    "wof:name":"P D S Services L L C",
    "wof:placetype":"venue"
},
  "geometry": {"coordinates":[-89.39989199999999,43.030153],"type":"Point"}
}