{
  "type": "Feature",
  "properties": {
    "iso:country":"US",
    "sg:address":"331 W Division St",
    "sg:city":"Mazomanie",
    "sg:classifiers":[
        {
            "category":"Education",
            "subcategory":"School",
            "type":"Public Place"
        }
    ],
    "sg:phone":"+1 608 795 2591",
    "sg:postcode":"53560",
    "sg:province":"WI",
    "wof:name":"Wi Heights School District",
    "wof:placetype":"venue"
},
  "geometry": {"coordinates":[-89.79990100000001,43.172893],"type":"Point"}
}