{
  "type": "Feature",
  "properties": {
    "iso:country":"US",
    "sg:address":"2567 Carnie Rd",
    "sg:city":"Monroe",
    "sg:classifiers":[
        {
            "category":"Building & Trades",
            "subcategory":"Construction",
            "type":"Services"
        }
    ],
    "sg:phone":"+1 608 325 2434",
    "sg:postcode":"53566",
    "sg:province":"WI",
    "sg:tags":[
        "house",
        "improvement",
        "home"
    ],
    "wof:name":"Lindh's Home Improvements",
    "wof:placetype":"venue"
},
  "geometry": {"coordinates":[-89.681085,42.600598],"type":"Point"}
}