{
  "type": "Feature",
  "properties": {
    "addr:full":"1515 Lapham St Janesville WI 53546",
    "addr:housenumber":"1515",
    "addr:postcode":"53546",
    "addr:street":"Lapham St",
    "iso:country":"US",
    "sg:address":"1515 Lapham St",
    "sg:city":"Janesville",
    "sg:classifiers":[
        {
            "category":"Education",
            "subcategory":"School",
            "type":"Public Place"
        }
    ],
    "sg:phone":"+1 608 743 7100",
    "sg:postcode":"53546",
    "sg:province":"WI",
    "wof:name":"Van Buren Elementary School",
    "wof:placetype":"venue"
},
  "geometry": {"coordinates":[-89.037752,42.66316],"type":"Point"}
}