{
  "type": "Feature",
  "properties": {
    "iso:country":"US",
    "sg:address":"2314 Carney Ave",
    "sg:city":"Marinette",
    "sg:classifiers":[
        {
            "category":"Social Services",
            "subcategory":"Child Care",
            "type":"Services"
        }
    ],
    "sg:phone":"+1 715 735 5131",
    "sg:postcode":"54143",
    "sg:province":"WI",
    "sg:tags":[
        "day"
    ],
    "wof:name":"Little Rascals Family Daycare",
    "wof:placetype":"venue"
},
  "geometry": {"coordinates":[-87.637556,45.092516],"type":"Point"}
}