{
  "type": "Feature",
  "properties": {
    "iso:country":"US",
    "sg:address":"10545 W Donges Ct",
    "sg:city":"Milwaukee",
    "sg:classifiers":[
        {
            "category":"Professional",
            "subcategory":"Advertising",
            "type":"Services"
        }
    ],
    "sg:phone":"+1 414 354 1423",
    "sg:postcode":"53224",
    "sg:province":"WI",
    "sg:tags":[
        "mailing",
        "direct"
    ],
    "wof:name":"Publishers Mail Service Inc",
    "wof:placetype":"venue"
},
  "geometry": {"coordinates":[-88.04148000000001,43.18995],"type":"Point"}
}