{
  "type": "Feature",
  "properties": {
    "iso:country":"US",
    "sg:address":"300 Wolf River Plz",
    "sg:city":"New London",
    "sg:classifiers":[
        {
            "category":"Home & Garden",
            "subcategory":"Hardware",
            "type":"Retail Goods"
        }
    ],
    "sg:phone":"+1 920 982 2100",
    "sg:postcode":"54961",
    "sg:province":"WI",
    "wof:name":"Phillips True Value Hardware",
    "wof:placetype":"venue"
},
  "geometry": {"coordinates":[-88.74217,44.393292],"type":"Point"}
}