{
  "type": "Feature",
  "properties": {
    "addr:full":"4519 State Rd 133 E Boscobel WI 53805",
    "addr:housenumber":"4519",
    "addr:postcode":"53805",
    "addr:street":"State Rd 133 E",
    "iso:country":"US",
    "sg:address":"4519 State Rd 133 E",
    "sg:city":"Boscobel",
    "sg:classifiers":[
        {
            "category":"Building & Trades",
            "subcategory":"Construction",
            "type":"Services"
        }
    ],
    "sg:phone":"+1 608 375 2135",
    "sg:postcode":"53805",
    "sg:province":"WI",
    "sg:tags":[
        "concrete",
        "contractor"
    ],
    "wof:name":"Greg Brown Construction",
    "wof:placetype":"venue"
},
  "geometry": {"coordinates":[-90.649317,43.163881],"type":"Point"}
}