{
  "type": "Feature",
  "properties": {
    "iso:country":"US",
    "sg:address":"28537 Filla Ln",
    "sg:city":"Arcadia",
    "sg:classifiers":[
        {
            "category":"Farming",
            "subcategory":"Dairy Farm",
            "type":"Manufacturing & Wholesale Goods"
        }
    ],
    "sg:phone":"+1 608 323 2228",
    "sg:postcode":"54612",
    "sg:province":"WI",
    "wof:name":"Charles Pyka",
    "wof:placetype":"venue"
},
  "geometry": {"coordinates":[-91.521273,44.315928],"type":"Point"}
}