{
  "type": "Feature",
  "properties": {
    "iso:country":"US",
    "sg:address":"3240 Gateway Rd",
    "sg:city":"Brookfield",
    "sg:classifiers":[
        {
            "category":"Retail",
            "subcategory":"Auto Repair",
            "type":"Services"
        }
    ],
    "sg:phone":"+1 262 781 0074",
    "sg:postcode":"53045",
    "sg:province":"WI",
    "sg:tags":[
        "general"
    ],
    "wof:name":"Mraz Import Automotive Inc",
    "wof:placetype":"venue"
},
  "geometry": {"coordinates":[-88.18052,43.078465],"type":"Point"}
}