{
  "type": "Feature",
  "properties": {
    "iso:country":"US",
    "sg:address":"138 Mill St",
    "sg:city":"Campbellsport",
    "sg:classifiers":[
        {
            "category":"Building & Trades",
            "subcategory":"Construction",
            "type":"Services"
        }
    ],
    "sg:phone":"+1 920 533 4222",
    "sg:postcode":"53010",
    "sg:province":"WI",
    "sg:tags":[
        "house"
    ],
    "wof:name":"Creative Builders",
    "wof:placetype":"venue"
},
  "geometry": {"coordinates":[-88.283046,43.599143],"type":"Point"}
}