{
  "type": "Feature",
  "properties": {
    "addr:full":"22142 Maule Coulee Rd Independence WI 54747",
    "addr:postcode":"22142;54747",
    "addr:street":"Coulee Rd",
    "iso:country":"US",
    "sg:address":"22142 Maule Coulee Rd",
    "sg:city":"Independence",
    "sg:classifiers":[
        {
            "category":"Farming",
            "subcategory":"Farm",
            "type":"Manufacturing & Wholesale Goods"
        }
    ],
    "sg:phone":"+1 715 985 3160",
    "sg:postcode":"54747",
    "sg:province":"WI",
    "sg:tags":[
        "crop",
        "general"
    ],
    "wof:name":"Tim Maule",
    "wof:placetype":"venue"
},
  "geometry": {"coordinates":[-91.397582,44.385228],"type":"Point"}
}