{
  "type": "Feature",
  "properties": {
    "iso:country":"US",
    "sg:address":"1514 Cemetery Rd",
    "sg:city":"Randolph",
    "sg:classifiers":[
        {
            "category":"Professional",
            "type":"Services"
        }
    ],
    "sg:phone":"+1 920 348 5604",
    "sg:postcode":"53956",
    "sg:province":"WI",
    "wof:name":"Kenneth W Pritchard",
    "wof:placetype":"venue"
},
  "geometry": {"coordinates":[-89.077224,43.530219],"type":"Point"}
}