{
  "type": "Feature",
  "properties": {
    "iso:country":"US",
    "sg:address":"210 S 6th St",
    "sg:city":"Stoughton",
    "sg:classifiers":[
        {
            "category":"Wholesale",
            "subcategory":"Jewelry",
            "type":"Manufacturing & Wholesale Goods"
        }
    ],
    "sg:phone":"+1 608 877 9538",
    "sg:postcode":"53589",
    "sg:province":"WI",
    "sg:tags":[
        "stone"
    ],
    "wof:name":"Ladysmith Custom Design Jwly",
    "wof:placetype":"venue"
},
  "geometry": {"coordinates":[-89.215518,42.915912],"type":"Point"}
}