{
  "type": "Feature",
  "properties": {
    "iso:country":"US",
    "sg:address":"3811 Co Rd G",
    "sg:city":"Caledonia",
    "sg:classifiers":[
        {
            "category":"Professional",
            "subcategory":"Accounting & Tax Preparation",
            "type":"Services"
        }
    ],
    "sg:phone":"+1 262 835 1498",
    "sg:postcode":"53108",
    "sg:province":"WI",
    "sg:tags":[
        "return",
        "filing"
    ],
    "wof:name":"Robert Schroeder",
    "wof:placetype":"venue"
},
  "geometry": {"coordinates":[-87.964778,42.807859],"type":"Point"}
}