{
  "type": "Feature",
  "properties": {
    "iso:country":"US",
    "sg:address":"1317 31st Ave",
    "sg:city":"Monroe",
    "sg:classifiers":[
        {
            "category":"Retail",
            "subcategory":"Veterinary Services",
            "type":"Services"
        }
    ],
    "sg:phone":"+1 608 325 2106",
    "sg:postcode":"53566",
    "sg:province":"WI",
    "sg:tags":[
        "veterinarian"
    ],
    "wof:name":"Monroe Veterinary Svc",
    "wof:placetype":"venue"
},
  "geometry": {"coordinates":[-89.622085,42.598826],"type":"Point"}
}