{
  "type": "Feature",
  "properties": {
    "iso:country":"US",
    "sg:address":"15784 40th St",
    "sg:city":"Bloomer",
    "sg:classifiers":[
        {
            "category":"Government",
            "subcategory":"Office",
            "type":"Public Place"
        }
    ],
    "sg:phone":"+1 715 568 4711",
    "sg:postcode":"54724",
    "sg:province":"WI",
    "sg:tags":[
        "city"
    ],
    "wof:name":"Cooks Valley Town Hall",
    "wof:placetype":"venue"
},
  "geometry": {"coordinates":[-91.590981,45.076719],"type":"Point"}
}