{
  "type": "Feature",
  "properties": {
    "iso:country":"US",
    "sg:address":"3001 Willow Dr",
    "sg:city":"La Crosse",
    "sg:classifiers":[
        {
            "category":"Wholesale",
            "subcategory":"Sporting Goods",
            "type":"Manufacturing & Wholesale Goods"
        }
    ],
    "sg:phone":"+1 608 788 1753",
    "sg:postcode":"54601",
    "sg:province":"WI",
    "wof:name":"Warren M Office",
    "wof:placetype":"venue"
},
  "geometry": {"coordinates":[-91.204217,43.778707],"type":"Point"}
}