{
  "type": "Feature",
  "properties": {
    "addr:full":"9418 W Washington St Milwaukee WI 53214",
    "addr:housenumber":"9418",
    "addr:postcode":"53214",
    "addr:street":"W Washington St",
    "iso:country":"US",
    "sg:address":"9418 W Washington St",
    "sg:city":"Milwaukee",
    "sg:classifiers":[
        {
            "category":"Recreation",
            "type":"Entertainment"
        }
    ],
    "sg:phone":"+1 414 327 8900",
    "sg:postcode":"53214",
    "sg:province":"WI",
    "sg:tags":[
        "parks"
    ],
    "wof:name":"LA Follette Park",
    "wof:placetype":"venue"
},
  "geometry": {"coordinates":[-88.02945,43.019665],"type":"Point"}
}