{
  "type": "Feature",
  "properties": {
    "iso:country":"US",
    "sg:address":"731 N Jackson St",
    "sg:city":"Milwaukee",
    "sg:classifiers":[
        {
            "category":"Real Estate",
            "subcategory":"Real Estate Operator",
            "type":"Services"
        }
    ],
    "sg:phone":"+1 414 481 7571",
    "sg:postcode":"53202",
    "sg:province":"WI",
    "sg:tags":[
        "building",
        "apartment"
    ],
    "wof:name":"South Shore Point Apartments",
    "wof:placetype":"venue"
},
  "geometry": {"coordinates":[-87.904149,43.039345],"type":"Point"}
}