{
  "type": "Feature",
  "properties": {
    "addr:full":"7503 Co Rd T Holmen WI 54636",
    "addr:housenumber":"7503",
    "addr:postcode":"54636",
    "addr:street":"Co Rd",
    "iso:country":"US",
    "sg:address":"7503 Co Rd T",
    "sg:city":"Holmen",
    "sg:classifiers":[
        {
            "category":"Organizations",
            "subcategory":"Community Association",
            "type":"Services"
        }
    ],
    "sg:phone":"+1 608 526 3710",
    "sg:postcode":"54636",
    "sg:province":"WI",
    "sg:tags":[
        "club"
    ],
    "wof:name":"Holmen Rod & Gun Club",
    "wof:placetype":"venue"
},
  "geometry": {"coordinates":[-91.275728,44.049178],"type":"Point"}
}