{
  "type": "Feature",
  "properties": {
    "iso:country":"US",
    "sg:address":"100 N Main St",
    "sg:city":"Westby",
    "sg:classifiers":[
        {
            "category":"Banks & Credit Unions",
            "subcategory":"Investment Brokerage",
            "type":"Services"
        }
    ],
    "sg:phone":"+1 608 634 9046",
    "sg:postcode":"54667",
    "sg:province":"WI",
    "sg:tags":[
        "security"
    ],
    "wof:name":"Link Financial Svc",
    "wof:placetype":"venue"
},
  "geometry": {"coordinates":[-90.85675500000001,43.654333],"type":"Point"}
}