{
  "type": "Feature",
  "properties": {
    "iso:country":"US",
    "sg:address":"901 S 5th St",
    "sg:city":"Milwaukee",
    "sg:classifiers":[
        {
            "category":"Manufacturing",
            "subcategory":"Paper Products",
            "type":"Manufacturing & Wholesale Goods"
        }
    ],
    "sg:phone":"+1 414 645 5760",
    "sg:postcode":"53204",
    "sg:province":"WI",
    "sg:tags":[
        "envelope"
    ],
    "sg:website":"www.leaderpaper.com",
    "wof:name":"Leader Paper Products",
    "wof:placetype":"venue"
},
  "geometry": {"coordinates":[-87.916839,43.021133],"type":"Point"}
}