{
  "type": "Feature",
  "properties": {
    "addr:full":"9321 N 107th St Milwaukee WI 53224",
    "addr:housenumber":"9321",
    "addr:postcode":"53224",
    "addr:street":"N 107Th St",
    "iso:country":"US",
    "sg:address":"9321 N 107th St",
    "sg:city":"Milwaukee",
    "sg:classifiers":[
        {
            "category":"Home & Garden",
            "subcategory":"Household Appliances",
            "type":"Retail Goods"
        }
    ],
    "sg:phone":"+1 414 354 9092",
    "sg:postcode":"53224",
    "sg:province":"WI",
    "sg:tags":[
        "cleaners",
        "vacuum"
    ],
    "wof:name":"Hydrotech",
    "wof:placetype":"venue"
},
  "geometry": {"coordinates":[-88.044214,43.179212],"type":"Point"}
}