{
  "type": "Feature",
  "properties": {
    "iso:country":"US",
    "sg:address":"524 Mill St",
    "sg:city":"Green Lake",
    "sg:classifiers":[
        {
            "category":"Shopping",
            "subcategory":"Gifts & Souvenirs",
            "type":"Retail Goods"
        }
    ],
    "sg:phone":"+1 920 294 1080",
    "sg:postcode":"54941",
    "sg:province":"WI",
    "sg:tags":[
        "shop"
    ],
    "wof:name":"Raspberry Gables/Blueberry",
    "wof:placetype":"venue"
},
  "geometry": {"coordinates":[-88.960013,43.845558],"type":"Point"}
}