{
  "type": "Feature",
  "properties": {
    "iso:country":"US",
    "sg:address":"1920 Broadway St S",
    "sg:city":"Menomonie",
    "sg:classifiers":[
        {
            "category":"Building & Trades",
            "subcategory":"Construction",
            "type":"Services"
        }
    ],
    "sg:phone":"+1 715 235 2975",
    "sg:postcode":"54751",
    "sg:province":"WI",
    "sg:tags":[
        "shelter"
    ],
    "wof:name":"House Of Hope",
    "wof:placetype":"venue"
},
  "geometry": {"coordinates":[-91.929693,44.865464],"type":"Point"}
}