{
  "type": "Feature",
  "properties": {
    "iso:country":"US",
    "sg:address":"1801 Shopiere Rd",
    "sg:city":"Beloit",
    "sg:classifiers":[
        {
            "category":"Government",
            "subcategory":"Fire Station",
            "type":"Public Place"
        }
    ],
    "sg:phone":"+1 608 362 7984",
    "sg:postcode":"53511",
    "sg:province":"WI",
    "sg:tags":[
        "department"
    ],
    "wof:name":"Beloit Fire Dept",
    "wof:placetype":"venue"
},
  "geometry": {"coordinates":[-89.014162,42.523097],"type":"Point"}
}