{
  "type": "Feature",
  "properties": {
    "iso:country":"US",
    "sg:address":"1234 12th Ave",
    "sg:city":"Grafton",
    "sg:classifiers":[
        {
            "category":"Building & Trades",
            "subcategory":"Construction",
            "type":"Services"
        }
    ],
    "sg:phone":"+1 262 375 8121",
    "sg:postcode":"53024",
    "sg:province":"WI",
    "sg:tags":[
        "boring",
        "drilling",
        "contractor"
    ],
    "sg:website":"www.m-bco.com",
    "wof:name":"North Shore Drilling",
    "wof:placetype":"venue"
},
  "geometry": {"coordinates":[-87.951642,43.319012],"type":"Point"}
}