{
  "type": "Feature",
  "properties": {
    "iso:country":"US",
    "sg:address":"400 N Executive Dr",
    "sg:city":"Brookfield",
    "sg:classifiers":[
        {
            "category":"Wholesale",
            "subcategory":"Machinery & Supplies",
            "type":"Manufacturing & Wholesale Goods"
        }
    ],
    "sg:phone":"+1 262 641 3400",
    "sg:postcode":"53005",
    "sg:province":"WI",
    "sg:tags":[
        "installs",
        "fire",
        "sprinkler",
        "system"
    ],
    "wof:name":"Grinnell Supply Sales",
    "wof:placetype":"venue"
},
  "geometry": {"coordinates":[-88.114724,43.035749],"type":"Point"}
}