{
  "type": "Feature",
  "properties": {
    "iso:country":"US",
    "sg:address":"405 Sauk St",
    "sg:city":"Lodi",
    "sg:classifiers":[
        {
            "category":"Social Services",
            "subcategory":"Child Care",
            "type":"Services"
        }
    ],
    "sg:phone":"+1 608 592 5418",
    "sg:postcode":"53555",
    "sg:province":"WI",
    "sg:tags":[
        "day"
    ],
    "wof:name":"Kellys Day Care",
    "wof:placetype":"venue"
},
  "geometry": {"coordinates":[-89.533525,43.312398],"type":"Point"}
}