{
  "type": "Feature",
  "properties": {
    "iso:country":"US",
    "sg:address":"11940 170th St",
    "sg:city":"Chippewa Falls",
    "sg:classifiers":[
        {
            "category":"Bars & Pubs",
            "type":"Food & Drink"
        }
    ],
    "sg:phone":"+1 715 288 6108",
    "sg:postcode":"54729",
    "sg:province":"WI",
    "sg:tags":[
        "drinking"
    ],
    "wof:name":"Mallards Resort Bar",
    "wof:placetype":"venue"
},
  "geometry": {"coordinates":[-91.32748100000001,45.018443],"type":"Point"}
}