{
  "type": "Feature",
  "properties": {
    "iso:country":"US",
    "sg:address":"2013 Schofield Ave",
    "sg:city":"Schofield",
    "sg:classifiers":[
        {
            "category":"Insurance",
            "subcategory":"Insurance Agent",
            "type":"Services"
        }
    ],
    "sg:phone":"+1 715 359 2400",
    "sg:postcode":"54476",
    "sg:province":"WI",
    "wof:name":"Jamie Thomas Agency",
    "wof:placetype":"venue"
},
  "geometry": {"coordinates":[-89.596917,44.909022],"type":"Point"}
}