{
  "type": "Feature",
  "properties": {
    "addr:full":"11120 Western Ave Cedarburg WI 53012",
    "addr:housenumber":"11120",
    "addr:postcode":"53012",
    "addr:street":"Western Ave",
    "iso:country":"US",
    "sg:address":"11120 Western Ave",
    "sg:city":"Cedarburg",
    "sg:classifiers":[
        {
            "category":"Wholesale",
            "subcategory":"Motor Vehicles",
            "type":"Manufacturing & Wholesale Goods"
        }
    ],
    "sg:phone":"+1 262 377 6696",
    "sg:postcode":"53012",
    "sg:province":"WI",
    "wof:name":"Campbells Auto Sport Inc",
    "wof:placetype":"venue"
},
  "geometry": {"coordinates":[-88.052222,43.293378],"type":"Point"}
}