{
  "type": "Feature",
  "properties": {
    "addr:full":"13045 Dam Rd Hayward WI 54843",
    "addr:housenumber":"13045",
    "addr:postcode":"54843",
    "addr:street":"Dam Rd",
    "iso:country":"US",
    "sg:address":"13045 Dam Rd",
    "sg:city":"Hayward",
    "sg:classifiers":[
        {
            "category":"Travel",
            "subcategory":"Hotels & Motels",
            "type":"Entertainment"
        }
    ],
    "sg:phone":"+1 715 634 4175",
    "sg:postcode":"54843",
    "sg:province":"WI",
    "sg:tags":[
        "resort",
        "operation",
        "trailer"
    ],
    "wof:name":"Nelson Lake Landing & R V Park",
    "wof:placetype":"venue"
},
  "geometry": {"coordinates":[-91.512652,46.101526],"type":"Point"}
}