{
  "type": "Feature",
  "properties": {
    "iso:country":"US",
    "sg:address":"5776 Durand Ave",
    "sg:city":"Racine",
    "sg:classifiers":[
        {
            "category":"Shopping",
            "subcategory":"Jewelry",
            "type":"Retail Goods"
        }
    ],
    "sg:phone":"+1 262 554 2417",
    "sg:postcode":"53406",
    "sg:province":"WI",
    "wof:name":"Silver & Gold Connection 510",
    "wof:placetype":"venue"
},
  "geometry": {"coordinates":[-87.848663,42.697346],"type":"Point"}
}