{
  "type": "Feature",
  "properties": {
    "iso:country":"US",
    "sg:address":"13 E Main St",
    "sg:city":"Watertown",
    "sg:classifiers":[
        {
            "category":"Insurance",
            "subcategory":"Insurance Agent",
            "type":"Services"
        }
    ],
    "sg:phone":"+1 920 261 1935",
    "sg:postcode":"53094",
    "sg:province":"WI",
    "wof:name":"State Farm Insurance",
    "wof:placetype":"venue"
},
  "geometry": {"coordinates":[-88.724707,43.194299],"type":"Point"}
}