{
  "type": "Feature",
  "properties": {
    "iso:country":"US",
    "sg:address":"2646 N Swan Blvd",
    "sg:city":"Milwaukee",
    "sg:classifiers":[
        {
            "category":"Education",
            "subcategory":"School",
            "type":"Public Place"
        }
    ],
    "sg:phone":"+1 414 258 4160",
    "sg:postcode":"53226",
    "sg:province":"WI",
    "sg:website":"www.christkingparish.org",
    "wof:name":"Christ King Elementary School",
    "wof:placetype":"venue"
},
  "geometry": {"coordinates":[-88.027446,43.06641],"type":"Point"}
}