{
  "type": "Feature",
  "properties": {
    "iso:country":"US",
    "sg:address":"3051 Mann Rd",
    "sg:city":"Loyal",
    "sg:classifiers":[
        {
            "category":"Freight",
            "type":"Transportation"
        }
    ],
    "sg:phone":"+1 715 255 8718",
    "sg:postcode":"54446",
    "sg:province":"WI",
    "sg:tags":[
        "trucking"
    ],
    "wof:name":"Lap Transport LLC",
    "wof:placetype":"venue"
},
  "geometry": {"coordinates":[-90.470628,44.697781],"type":"Point"}
}