{
  "type": "Feature",
  "properties": {
    "iso:country":"US",
    "sg:address":"3748 Co Rd K",
    "sg:city":"Amherst Junction",
    "sg:phone":"+1 715 824 3209",
    "sg:postcode":"54407",
    "sg:province":"WI",
    "sg:tags":[
        "farm",
        "corn",
        "cash",
        "crop",
        "field",
        "grain"
    ],
    "wof:name":"Jerome Iwanski",
    "wof:placetype":"venue"
},
  "geometry": {"coordinates":[-89.365661,44.480122],"type":"Point"}
}