{
  "type": "Feature",
  "properties": {
    "iso:country":"US",
    "sg:address":"15061 Thorofare Rd",
    "sg:city":"Park Falls",
    "sg:classifiers":[
        {
            "category":"Travel",
            "subcategory":"Hotels & Motels",
            "type":"Entertainment"
        }
    ],
    "sg:phone":"+1 715 762 3566",
    "sg:postcode":"54552",
    "sg:province":"WI",
    "sg:tags":[
        "operation",
        "drinking"
    ],
    "wof:name":"Wild Goose Resort",
    "wof:placetype":"venue"
},
  "geometry": {"coordinates":[-90.07245,45.911992],"type":"Point"}
}