{
  "type": "Feature",
  "properties": {
    "iso:country":"US",
    "sg:address":"633 W Wisconsin Ave",
    "sg:city":"Milwaukee",
    "sg:classifiers":[
        {
            "category":"Professional",
            "subcategory":"Lawyer & Legal Services",
            "type":"Services"
        }
    ],
    "sg:phone":"+1 414 390 2900",
    "sg:postcode":"53233",
    "sg:province":"WI",
    "sg:tags":[
        "attorney"
    ],
    "wof:name":"Cornwall Rhiel",
    "wof:placetype":"venue"
},
  "geometry": {"coordinates":[-87.919965,43.038734],"type":"Point"}
}