{
  "type": "Feature",
  "properties": {
    "iso:country":"US",
    "sg:address":"44423 Trout Creek Rd",
    "sg:city":"Soldiers Grove",
    "sg:classifiers":[
        {
            "category":"Insurance",
            "subcategory":"Insurance Agent",
            "type":"Services"
        }
    ],
    "sg:phone":"+1 608 624 5723",
    "sg:postcode":"54655",
    "sg:province":"WI",
    "wof:name":"Lutheran Brotherhood",
    "wof:placetype":"venue"
},
  "geometry": {"coordinates":[-90.768907,43.406766],"type":"Point"}
}