{
  "type": "Feature",
  "properties": {
    "addr:full":"4252 Deprey Rd Abrams WI 54101",
    "addr:housenumber":"4252",
    "addr:postcode":"54101",
    "addr:street":"Deprey Rd",
    "iso:country":"US",
    "sg:address":"4252 Deprey Rd",
    "sg:city":"Abrams",
    "sg:classifiers":[
        {
            "category":"Manufacturing",
            "subcategory":"Lumber",
            "type":"Manufacturing & Wholesale Goods"
        }
    ],
    "sg:phone":"+1 920 826 7377",
    "sg:postcode":"54101",
    "sg:province":"WI",
    "sg:tags":[
        "timber",
        "operation",
        "tract",
        "supply"
    ],
    "wof:name":"Williamson Nursery Inc",
    "wof:placetype":"venue"
},
  "geometry": {"coordinates":[-87.973895,44.79976],"type":"Point"}
}