{
  "type": "Feature",
  "properties": {
    "iso:country":"US",
    "sg:address":"6814 39th Ave",
    "sg:city":"Kenosha",
    "sg:classifiers":[
        {
            "category":"Retail",
            "subcategory":"Auto Rental",
            "type":"Services"
        }
    ],
    "sg:phone":"+1 262 697 3540",
    "sg:postcode":"53142",
    "sg:province":"WI",
    "wof:name":"U-Save Auto Rental",
    "wof:placetype":"venue"
},
  "geometry": {"coordinates":[-87.855332,42.572948],"type":"Point"}
}