{
  "type": "Feature",
  "properties": {
    "iso:country":"US",
    "sg:address":"412 Riverwood Ln",
    "sg:city":"Green Bay",
    "sg:classifiers":[
        {
            "category":"Professional",
            "type":"Services"
        }
    ],
    "sg:phone":"+1 920 434 5115",
    "sg:postcode":"54313",
    "sg:province":"WI",
    "wof:name":"Woodfield Villager",
    "wof:placetype":"venue"
},
  "geometry": {"coordinates":[-88.089743,44.551235],"type":"Point"}
}