{
  "type": "Feature",
  "properties": {
    "addr:full":"1632 W Main St Sun Prairie WI 53590",
    "addr:housenumber":"1632",
    "addr:postcode":"53590",
    "addr:street":"W Main St",
    "iso:country":"US",
    "sg:address":"1632 W Main St",
    "sg:city":"Sun Prairie",
    "sg:classifiers":[
        {
            "category":"Insurance",
            "subcategory":"Insurance Agent",
            "type":"Services"
        }
    ],
    "sg:phone":"+1 608 837 4111",
    "sg:postcode":"53590",
    "sg:province":"WI",
    "wof:name":"Allstate Insurance",
    "wof:placetype":"venue"
},
  "geometry": {"coordinates":[-89.24118300000001,43.178011],"type":"Point"}
}