{
  "type": "Feature",
  "properties": {
    "iso:country":"US",
    "sg:address":"154 Woodlawn Dr",
    "sg:city":"Shawano",
    "sg:classifiers":[
        {
            "category":"Health Services",
            "subcategory":"Chiropractor",
            "type":"Services"
        }
    ],
    "sg:phone":"+1 715 524 6720",
    "sg:postcode":"54166",
    "sg:province":"WI",
    "wof:name":"Ritter Chiropractic",
    "wof:placetype":"venue"
},
  "geometry": {"coordinates":[-88.586297,44.784478],"type":"Point"}
}