{
  "type": "Feature",
  "properties": {
    "iso:country":"US",
    "sg:address":"11270 W Park Pl",
    "sg:city":"Milwaukee",
    "sg:classifiers":[
        {
            "category":"Insurance",
            "subcategory":"Insurance Agent",
            "type":"Services"
        },
        {
            "category":"Insurance",
            "subcategory":"Hazard Insurance",
            "type":"Services"
        }
    ],
    "sg:phone":"+1 414 577 2100",
    "sg:postcode":"53224",
    "sg:province":"WI",
    "sg:tags":[
        "business",
        "fire",
        "commercial",
        "property",
        "casualty"
    ],
    "sg:website":"http://www.employmentspot.com",
    "wof:name":"Wausau Insurance Companies",
    "wof:placetype":"venue"
},
  "geometry": {"coordinates":[-88.052409,43.149672],"type":"Point"}
}