{
  "type": "Feature",
  "properties": {
    "iso:country":"US",
    "sg:address":"2315 S 170th St",
    "sg:city":"New Berlin",
    "sg:classifiers":[
        {
            "category":"Professional",
            "type":"Services"
        }
    ],
    "sg:phone":"+1 262 827 1440",
    "sg:postcode":"53151",
    "sg:province":"WI",
    "wof:name":"Roy Muehl Universal Joint Svc",
    "wof:placetype":"venue"
},
  "geometry": {"coordinates":[-88.124823,42.997522],"type":"Point"}
}