{
  "type": "Feature",
  "properties": {
    "iso:country":"US",
    "sg:address":"6191 S 108th St",
    "sg:city":"Hales Corners",
    "sg:classifiers":[
        {
            "category":"Health Services",
            "subcategory":"Doctor",
            "type":"Services"
        }
    ],
    "sg:phone":"+1 414 427 9090",
    "sg:postcode":"53130",
    "sg:province":"WI",
    "sg:website":"www.drczaplicki.com",
    "wof:name":"Czaplicki Family Dentistry",
    "wof:placetype":"venue"
},
  "geometry": {"coordinates":[-88.048489,42.933568],"type":"Point"}
}