{
  "type": "Feature",
  "properties": {
    "addr:full":"203 S Cottrell Ln Saukville WI 53080",
    "addr:housenumber":"203",
    "addr:postcode":"53080",
    "addr:street":"S Cottrell Ln",
    "iso:country":"US",
    "sg:address":"203 S Cottrell Ln",
    "sg:city":"Saukville",
    "sg:classifiers":[
        {
            "category":"Organizations",
            "subcategory":"Professional Association",
            "type":"Services"
        }
    ],
    "sg:phone":"+1 262 268 1970",
    "sg:postcode":"53080",
    "sg:province":"WI",
    "sg:tags":[
        "business"
    ],
    "wof:name":"Saukville Chamber of Commerce",
    "wof:placetype":"venue"
},
  "geometry": {"coordinates":[-87.95625800000001,43.380487],"type":"Point"}
}