{
  "type": "Feature",
  "properties": {
    "iso:country":"US",
    "sg:address":"2180 Slinger Rd",
    "sg:city":"Richfield",
    "sg:classifiers":[
        {
            "category":"Retail",
            "subcategory":"Repair Shop",
            "type":"Services"
        }
    ],
    "sg:phone":"+1 262 644 6555",
    "sg:postcode":"53076",
    "sg:province":"WI",
    "wof:name":"Jerrys Midwest Taxidermy",
    "wof:placetype":"venue"
},
  "geometry": {"coordinates":[-88.281251,43.268538],"type":"Point"}
}