{
  "type": "Feature",
  "properties": {
    "iso:country":"US",
    "sg:address":"112 W Division St",
    "sg:city":"Shawano",
    "sg:classifiers":[
        {
            "category":"Professional",
            "subcategory":"Accounting & Tax Preparation",
            "type":"Services"
        }
    ],
    "sg:phone":"+1 715 524 2302",
    "sg:postcode":"54166",
    "sg:province":"WI",
    "sg:tags":[
        "accountant"
    ],
    "wof:name":"LA Violette Accounting & Tax",
    "wof:placetype":"venue"
},
  "geometry": {"coordinates":[-88.609413,44.780082],"type":"Point"}
}