{
  "type": "Feature",
  "properties": {
    "addr:full":"5353 Harding Ave Plover WI 54467",
    "addr:housenumber":"5353",
    "addr:postcode":"54467",
    "addr:street":"Harding Ave",
    "iso:country":"US",
    "sg:address":"5353 Harding Ave",
    "sg:city":"Plover",
    "sg:classifiers":[
        {
            "category":"Autos & Motor Vehicles",
            "subcategory":"Auto Supplies",
            "type":"Retail Goods"
        }
    ],
    "sg:phone":"+1 715 342 6912",
    "sg:postcode":"54467",
    "sg:province":"WI",
    "wof:name":"Midwest Express Tire & RE",
    "wof:placetype":"venue"
},
  "geometry": {"coordinates":[-89.515968,44.426698],"type":"Point"}
}