{
  "type": "Feature",
  "properties": {
    "iso:country":"US",
    "sg:address":"1210 Alpine Dr",
    "sg:city":"Janesville",
    "sg:classifiers":[
        {
            "category":"Building & Trades",
            "subcategory":"Construction",
            "type":"Services"
        }
    ],
    "sg:phone":"+1 608 314 9151",
    "sg:postcode":"53546",
    "sg:province":"WI",
    "sg:tags":[
        "hanging",
        "contractor"
    ],
    "wof:name":"Rockwell Painting Inc",
    "wof:placetype":"venue"
},
  "geometry": {"coordinates":[-88.959414,42.699701],"type":"Point"}
}