{
  "type": "Feature",
  "properties": {
    "addr:full":"1225 Summit Ave Oshkosh WI 54901",
    "addr:housenumber":"1225",
    "addr:postcode":"54901",
    "addr:street":"Summit Ave",
    "iso:country":"US",
    "sg:address":"1225 Summit Ave",
    "sg:city":"Oshkosh",
    "sg:classifiers":[
        {
            "category":"Health Services",
            "subcategory":"Clinic",
            "type":"Services"
        }
    ],
    "sg:phone":"+1 920 233 5999",
    "sg:postcode":"54901",
    "sg:province":"WI",
    "sg:tags":[
        "specialty",
        "outpatient"
    ],
    "wof:name":"Reynolds Wm J Voc Assmnt Svcs",
    "wof:placetype":"venue"
},
  "geometry": {"coordinates":[-88.55942400000001,44.032324],"type":"Point"}
}