{
  "type": "Feature",
  "properties": {
    "addr:full":"1744 Grange Ave Racine WI 53403",
    "addr:housenumber":"1744",
    "addr:postcode":"53403",
    "addr:street":"Grange Ave",
    "iso:country":"US",
    "sg:address":"1744 Grange Ave",
    "sg:city":"Racine",
    "sg:classifiers":[
        {
            "category":"Freight",
            "type":"Transportation"
        }
    ],
    "sg:phone":"+1 262 634 8303",
    "sg:postcode":"53403",
    "sg:province":"WI",
    "sg:tags":[
        "commercial",
        "storage"
    ],
    "wof:name":"Stow Away",
    "wof:placetype":"venue"
},
  "geometry": {"coordinates":[-87.81129300000001,42.709103],"type":"Point"}
}