{
  "type": "Feature",
  "properties": {
    "iso:country":"US",
    "sg:address":"9603 Argue Rd",
    "sg:city":"New Glarus",
    "sg:classifiers":[
        {
            "category":"Sports & Exercise",
            "subcategory":"Golf",
            "type":"Entertainment"
        }
    ],
    "sg:phone":"+1 608 527 6366",
    "sg:postcode":"53574",
    "sg:province":"WI",
    "sg:tags":[
        "course",
        "public"
    ],
    "wof:name":"Argue-Ment Golf Course",
    "wof:placetype":"venue"
},
  "geometry": {"coordinates":[-89.602749,42.852774],"type":"Point"}
}