{
  "type": "Feature",
  "properties": {
    "iso:country":"US",
    "sg:address":"611 E Woodland Ave",
    "sg:city":"Barron",
    "sg:classifiers":[
        {
            "category":"Government",
            "subcategory":"Office",
            "type":"Public Place"
        }
    ],
    "sg:phone":"+1 715 537 5989",
    "sg:postcode":"54812",
    "sg:province":"WI",
    "sg:tags":[
        "housing",
        "program"
    ],
    "wof:name":"Barron County Housing Auth",
    "wof:placetype":"venue"
},
  "geometry": {"coordinates":[-91.849796,45.397085],"type":"Point"}
}