{
  "type": "Feature",
  "properties": {
    "iso:country":"US",
    "sg:address":"7938 Sandy Ridge Rd",
    "sg:city":"Kewaskum",
    "sg:classifiers":[
        {
            "category":"Shopping",
            "subcategory":"Department Store",
            "type":"Retail Goods"
        }
    ],
    "sg:phone":"+1 262 334 1077",
    "sg:postcode":"53040",
    "sg:province":"WI",
    "wof:name":"Scan Electronics LLC",
    "wof:placetype":"venue"
},
  "geometry": {"coordinates":[-88.206546,43.478359],"type":"Point"}
}