{
  "type": "Feature",
  "properties": {
    "addr:full":"5253 N Lovers Lane Rd Milwaukee WI 53225",
    "addr:housenumber":"5253",
    "addr:postcode":"53225",
    "addr:street":"N Lovers Lane Rd",
    "iso:country":"US",
    "sg:address":"5253 N Lovers Lane Rd",
    "sg:city":"Milwaukee",
    "sg:classifiers":[
        {
            "category":"Real Estate",
            "subcategory":"Real Estate Agent",
            "type":"Services"
        }
    ],
    "sg:phone":"+1 414 265 2311",
    "sg:postcode":"53225",
    "sg:province":"WI",
    "wof:name":"Bolt Action Development Co",
    "wof:placetype":"venue"
},
  "geometry": {"coordinates":[-88.05510599999999,43.108745],"type":"Point"}
}