{
  "type": "Feature",
  "properties": {
    "iso:country":"US",
    "sg:address":"208 S State St",
    "sg:city":"Mishicot",
    "sg:classifiers":[
        {
            "category":"Retail",
            "subcategory":"Auto Repair",
            "type":"Services"
        }
    ],
    "sg:phone":"+1 920 755 2588",
    "sg:postcode":"54228",
    "sg:province":"WI",
    "sg:tags":[
        "wrecker"
    ],
    "wof:name":"P K's Auto Body",
    "wof:placetype":"venue"
},
  "geometry": {"coordinates":[-87.645269,44.238664],"type":"Point"}
}