{
  "type": "Feature",
  "properties": {
    "iso:country":"US",
    "sg:address":"1200 W North Ave",
    "sg:city":"Milwaukee",
    "sg:classifiers":[
        {
            "category":"Shopping",
            "subcategory":"Used Merchandise",
            "type":"Retail Goods"
        }
    ],
    "sg:phone":"+1 414 263 4790",
    "sg:postcode":"53205",
    "sg:province":"WI",
    "sg:tags":[
        "furniture"
    ],
    "wof:name":"Railroad Used Furniture & Appl",
    "wof:placetype":"venue"
},
  "geometry": {"coordinates":[-87.927683,43.060392],"type":"Point"}
}