{
  "type": "Feature",
  "properties": {
    "iso:country":"US",
    "sg:address":"108 Park Ave",
    "sg:city":"Beaver Dam",
    "sg:classifiers":[
        {
            "category":"Education",
            "subcategory":"Dance Studio",
            "type":"Public Place"
        }
    ],
    "sg:phone":"+1 920 885 9665",
    "sg:postcode":"53916",
    "sg:province":"WI",
    "wof:name":"Mirror Image Dance",
    "wof:placetype":"venue"
},
  "geometry": {"coordinates":[-88.83439300000001,43.456345],"type":"Point"}
}