{
  "type": "Feature",
  "properties": {
    "iso:country":"US",
    "sg:address":"1733 Black Ave",
    "sg:city":"Eau Claire",
    "sg:classifiers":[
        {
            "category":"Professional",
            "type":"Services"
        }
    ],
    "sg:phone":"+1 715 831 1718",
    "sg:postcode":"54703",
    "sg:province":"WI",
    "sg:tags":[
        "business"
    ],
    "wof:name":"Berry Inspections Inc",
    "wof:placetype":"venue"
},
  "geometry": {"coordinates":[-91.447877,44.834314],"type":"Point"}
}