{
  "type": "Feature",
  "properties": {
    "iso:country":"US",
    "sg:address":"60 Waunona Woods Ct",
    "sg:city":"Madison",
    "sg:classifiers":[
        {
            "category":"Organizations",
            "subcategory":"Political Organization",
            "type":"Services"
        }
    ],
    "sg:phone":"+1 608 222 3323",
    "sg:postcode":"53713",
    "sg:province":"WI",
    "wof:name":"Friends Of Don Eggert",
    "wof:placetype":"venue"
},
  "geometry": {"coordinates":[-89.34114099999999,43.048636],"type":"Point"}
}