{
  "type": "Feature",
  "properties": {
    "iso:country":"US",
    "sg:address":"302 E Walworth Ave",
    "sg:city":"Delavan",
    "sg:classifiers":[
        {
            "category":"Shopping",
            "type":"Retail Goods"
        }
    ],
    "sg:phone":"+1 262 728 3910",
    "sg:postcode":"53115",
    "sg:province":"WI",
    "sg:tags":[
        "plant",
        "flower",
        "tree",
        "artificial"
    ],
    "wof:name":"Delavan's Flower Store & More",
    "wof:placetype":"venue"
},
  "geometry": {"coordinates":[-88.645356,42.633064],"type":"Point"}
}