{
  "type": "Feature",
  "properties": {
    "iso:country":"US",
    "sg:address":"754 N 4th St Suite 500",
    "sg:city":"Milwaukee",
    "sg:classifiers":[
        {
            "category":"Banks & Credit Unions",
            "subcategory":"Financial Services",
            "type":"Services"
        }
    ],
    "sg:phone":"+1 414 831 5296",
    "sg:postcode":"53203",
    "sg:province":"WI",
    "sg:tags":[
        "card-merchant",
        "card"
    ],
    "wof:name":"Newtek Merchant Solutions",
    "wof:placetype":"venue"
},
  "geometry": {"coordinates":[-87.916045,43.03956],"type":"Point"}
}