{
  "type": "Feature",
  "properties": {
    "iso:country":"US",
    "sg:address":"1833 Executive Dr",
    "sg:city":"Oconomowoc",
    "sg:classifiers":[
        {
            "category":"Building & Trades",
            "subcategory":"Construction",
            "type":"Services"
        }
    ],
    "sg:phone":"+1 262 569 0077",
    "sg:postcode":"53066",
    "sg:province":"WI",
    "sg:tags":[
        "house"
    ],
    "wof:name":"Visionary Cnstr Svcs Ltd",
    "wof:placetype":"venue"
},
  "geometry": {"coordinates":[-88.475491,43.075267],"type":"Point"}
}