{
  "type": "Feature",
  "properties": {
    "iso:country":"US",
    "sg:address":"504 233rd St",
    "sg:city":"Baldwin",
    "sg:classifiers":[
        {
            "category":"Wholesale",
            "subcategory":"Auto Parts",
            "type":"Manufacturing & Wholesale Goods"
        }
    ],
    "sg:phone":"+1 715 684 3603",
    "sg:postcode":"54002",
    "sg:province":"WI",
    "wof:name":"Precision Clutching & Prfmce",
    "wof:placetype":"venue"
},
  "geometry": {"coordinates":[-92.334146,44.937708],"type":"Point"}
}