{
  "type": "Feature",
  "properties": {
    "iso:country":"US",
    "sg:address":"2220 Division St",
    "sg:city":"Stevens Point",
    "sg:classifiers":[
        {
            "category":"Organizations",
            "subcategory":"Labor Organization",
            "type":"Services"
        }
    ],
    "sg:phone":"+1 715 344 4536",
    "sg:postcode":"54481",
    "sg:province":"WI",
    "wof:name":"General Teamsters Union 662",
    "wof:placetype":"venue"
},
  "geometry": {"coordinates":[-89.574844,44.515324],"type":"Point"}
}