{
  "type": "Feature",
  "properties": {
    "iso:country":"US",
    "sg:address":"703 Kavanaugh St",
    "sg:city":"Elroy",
    "sg:classifiers":[
        {
            "category":"Professional",
            "type":"Services"
        }
    ],
    "sg:phone":"+1 608 462 5273",
    "sg:postcode":"53929",
    "sg:province":"WI",
    "sg:tags":[
        "establishment"
    ],
    "wof:name":"Kustom Kraft Laser",
    "wof:placetype":"venue"
},
  "geometry": {"coordinates":[-90.263173,43.744326],"type":"Point"}
}