{
  "type": "Feature",
  "properties": {
    "addr:full":"524 N 13th St Oostburg WI 53070",
    "addr:housenumber":"524",
    "addr:postcode":"53070",
    "addr:street":"N 13Th St",
    "iso:country":"US",
    "sg:address":"524 N 13th St",
    "sg:city":"Oostburg",
    "sg:classifiers":[
        {
            "category":"Wholesale",
            "subcategory":"Groceries",
            "type":"Manufacturing & Wholesale Goods"
        }
    ],
    "sg:phone":"+1 920 564 3862",
    "sg:postcode":"53070",
    "sg:province":"WI",
    "sg:tags":[
        "general"
    ],
    "wof:name":"A & D Food Brokers",
    "wof:placetype":"venue"
},
  "geometry": {"coordinates":[-87.805707,43.627965],"type":"Point"}
}