{
  "type": "Feature",
  "properties": {
    "iso:country":"US",
    "sg:address":"408 S Main St",
    "sg:city":"Elmwood",
    "sg:classifiers":[
        {
            "category":"Government",
            "subcategory":"Office",
            "type":"Public Place"
        }
    ],
    "sg:phone":"+1 715 647 2210",
    "sg:postcode":"54740",
    "sg:province":"WI",
    "sg:tags":[
        "county",
        "program",
        "health"
    ],
    "wof:name":"Pierce County Public Health",
    "wof:placetype":"venue"
},
  "geometry": {"coordinates":[-92.151302,44.776387],"type":"Point"}
}