{
  "type": "Feature",
  "properties": {
    "iso:country":"US",
    "sg:address":"6508 Decator Dr",
    "sg:city":"Wausau",
    "sg:classifiers":[
        {
            "category":"Building & Trades",
            "subcategory":"Construction",
            "type":"Services"
        }
    ],
    "sg:phone":"+1 715 675 7978",
    "sg:postcode":"54401",
    "sg:province":"WI",
    "sg:tags":[
        "house"
    ],
    "wof:name":"Howe Construction",
    "wof:placetype":"venue"
},
  "geometry": {"coordinates":[-89.71907,45.002266],"type":"Point"}
}