{
  "type": "Feature",
  "properties": {
    "iso:country":"US",
    "sg:address":"1001 S Whitney Way",
    "sg:city":"Madison",
    "sg:classifiers":[
        {
            "category":"Professional",
            "subcategory":"Employment Agencies",
            "type":"Services"
        }
    ],
    "sg:phone":"+1 608 274 0290",
    "sg:postcode":"53711",
    "sg:province":"WI",
    "sg:tags":[
        "opportunity"
    ],
    "wof:name":"Advanced Employment Svc LLC",
    "wof:placetype":"venue"
},
  "geometry": {"coordinates":[-89.474145,43.044092],"type":"Point"}
}