{
  "type": "Feature",
  "properties": {
    "iso:country":"US",
    "sg:address":"5224 Roberts Dr",
    "sg:city":"Greendale",
    "sg:classifiers":[
        {
            "category":"Professional",
            "subcategory":"Computer Services",
            "type":"Services"
        }
    ],
    "sg:phone":"+1 414 421 3723",
    "sg:postcode":"53129",
    "sg:province":"WI",
    "sg:tags":[
        "prepackaged",
        "software"
    ],
    "wof:name":"Myrunscom",
    "wof:placetype":"venue"
},
  "geometry": {"coordinates":[-87.979866,42.927497],"type":"Point"}
}