{
  "type": "Feature",
  "properties": {
    "iso:country":"US",
    "sg:address":"1303 Bayview Ave",
    "sg:city":"Rice Lake",
    "sg:classifiers":[
        {
            "category":"Professional",
            "subcategory":"Business Services",
            "type":"Services"
        }
    ],
    "sg:phone":"+1 715 736 1330",
    "sg:postcode":"54868",
    "sg:province":"WI",
    "sg:tags":[
        "home",
        "inspection"
    ],
    "wof:name":"Jnj Inpection Inc",
    "wof:placetype":"venue"
},
  "geometry": {"coordinates":[-91.722782,45.48727],"type":"Point"}
}