{
  "type": "Feature",
  "properties": {
    "iso:country":"US",
    "sg:address":"1603 S 92nd St",
    "sg:city":"Milwaukee",
    "sg:classifiers":[
        {
            "category":"Building & Trades",
            "subcategory":"Plumbing",
            "type":"Services"
        }
    ],
    "sg:phone":"+1 414 719 1496",
    "sg:postcode":"53214",
    "sg:province":"WI",
    "sg:tags":[
        "plumbing",
        "contractor"
    ],
    "wof:name":"Tuffy's Sewer & Drain",
    "wof:placetype":"venue"
},
  "geometry": {"coordinates":[-88.027188,43.012016],"type":"Point"}
}