{
  "type": "Feature",
  "properties": {
    "addr:full":"2730 US Hwy 141 Coleman WI 54112",
    "addr:housenumber":"2730",
    "addr:postcode":"54112",
    "addr:street":"Us Hwy 141",
    "iso:country":"US",
    "sg:address":"2730 US Hwy 141",
    "sg:city":"Coleman",
    "sg:classifiers":[
        {
            "category":"Shopping",
            "subcategory":"Florist",
            "type":"Retail Goods"
        }
    ],
    "sg:phone":"+1 920 897 3331",
    "sg:postcode":"54112",
    "sg:province":"WI",
    "wof:name":"Coleman Floral & Greenhouse",
    "wof:placetype":"venue"
},
  "geometry": {"coordinates":[-88.044061,45.060176],"type":"Point"}
}