{
  "type": "Feature",
  "properties": {
    "iso:country":"US",
    "sg:address":"1840 8th St S",
    "sg:city":"Wisconsin Rapids",
    "sg:classifiers":[
        {
            "category":"Restaurant",
            "type":"Food & Drink"
        }
    ],
    "sg:menulink":"http://www.allmenus.com/wi/wisconsin-rapids/162991-rallys/menu/",
    "sg:phone":"+1 715 421 5140",
    "sg:postcode":"54494",
    "sg:province":"WI",
    "sg:tags":[
        "sandwich",
        "dog",
        "burger",
        "hot",
        "wrap",
        "american"
    ],
    "wof:name":"Rally's",
    "wof:placetype":"venue"
},
  "geometry": {"coordinates":[-89.81721,44.378152],"type":"Point"}
}