{
  "type": "Feature",
  "properties": {
    "iso:country":"US",
    "sg:address":"1217 McKinley St",
    "sg:city":"West Bend",
    "sg:classifiers":[
        {
            "category":"Personal",
            "subcategory":"Beauty Salon",
            "type":"Services"
        }
    ],
    "sg:phone":"+1 262 334 8468",
    "sg:postcode":"53090",
    "sg:province":"WI",
    "sg:tags":[
        "shop"
    ],
    "wof:name":"Guided Touch By Pam Schall LLC",
    "wof:placetype":"venue"
},
  "geometry": {"coordinates":[-88.192119,43.439584],"type":"Point"}
}