{
  "type": "Feature",
  "properties": {
    "iso:country":"US",
    "sg:address":"2713 Atwood Ave",
    "sg:city":"Madison",
    "sg:classifiers":[
        {
            "category":"Health Services",
            "subcategory":"Health Practitioner",
            "type":"Services"
        }
    ],
    "sg:phone":"+1 608 241 3733",
    "sg:postcode":"53704",
    "sg:province":"WI",
    "sg:tags":[
        "psychologist"
    ],
    "wof:name":"Psychological Atwood Assoc",
    "wof:placetype":"venue"
},
  "geometry": {"coordinates":[-89.344885,43.09383],"type":"Point"}
}