{
  "type": "Feature",
  "properties": {
    "iso:country":"US",
    "sg:address":"2320 S Howell Ave",
    "sg:city":"Milwaukee",
    "sg:classifiers":[
        {
            "category":"Bars & Pubs",
            "type":"Food & Drink"
        }
    ],
    "sg:phone":"+1 414 486 7949",
    "sg:postcode":"53207",
    "sg:province":"WI",
    "sg:tags":[
        "drinking"
    ],
    "wof:name":"Pandora's Box",
    "wof:placetype":"venue"
},
  "geometry": {"coordinates":[-87.904697,43.001464],"type":"Point"}
}