{
  "type": "Feature",
  "properties": {
    "iso:country":"US",
    "sg:address":"617 Royal Park Rd",
    "sg:city":"Racine",
    "sg:classifiers":[
        {
            "category":"Professional",
            "subcategory":"Art Services",
            "type":"Services"
        }
    ],
    "sg:phone":"+1 262 898 7059",
    "sg:postcode":"53402",
    "sg:province":"WI",
    "sg:tags":[
        "commercial",
        "design"
    ],
    "wof:name":"Flights of Fancy",
    "wof:placetype":"venue"
},
  "geometry": {"coordinates":[-87.787752,42.783363],"type":"Point"}
}