{
  "type": "Feature",
  "properties": {
    "iso:country":"US",
    "sg:address":"160 S 2nd St Stop 1",
    "sg:city":"Milwaukee",
    "sg:classifiers":[
        {
            "category":"Manufacturing",
            "subcategory":"Rubber & Plastics",
            "type":"Manufacturing & Wholesale Goods"
        },
        {
            "category":"Autos & Motor Vehicles",
            "subcategory":"Auto Supplies",
            "type":"Retail Goods"
        }
    ],
    "sg:phone":"+1 414 906 1400",
    "sg:postcode":"53204",
    "sg:province":"WI",
    "sg:tags":[
        "tires-wholesale",
        "tire",
        "manufacturer"
    ],
    "sg:website":"http://www.teamtba.com",
    "wof:name":"Team Tba",
    "wof:placetype":"venue"
},
  "geometry": {"coordinates":[-87.91258999999999,43.030531],"type":"Point"}
}