{
  "type": "Feature",
  "properties": {
    "iso:country":"US",
    "sg:address":"376 S Koeller St",
    "sg:city":"Oshkosh",
    "sg:classifiers":[
        {
            "category":"Banks & Credit Unions",
            "subcategory":"Bank",
            "type":"Services"
        }
    ],
    "sg:phone":"+1 920 231 1501",
    "sg:postcode":"54902",
    "sg:province":"WI",
    "sg:tags":[
        "financing"
    ],
    "wof:name":"Security Finance Corp",
    "wof:placetype":"venue"
},
  "geometry": {"coordinates":[-88.58158400000001,44.012684],"type":"Point"}
}