{
  "type": "Feature",
  "properties": {
    "addr:full":"410 S Bridge St Markesan WI 53946",
    "addr:housenumber":"410",
    "addr:postcode":"53946",
    "addr:street":"S Bridge St",
    "iso:country":"US",
    "sg:address":"410 S Bridge St",
    "sg:city":"Markesan",
    "sg:classifiers":[
        {
            "category":"Building & Trades",
            "subcategory":"Plumbing",
            "type":"Services"
        }
    ],
    "sg:phone":"+1 920 398 3833",
    "sg:postcode":"53946",
    "sg:province":"WI",
    "sg:tags":[
        "plumbing",
        "contractor"
    ],
    "wof:name":"A 1 Markesan Plumbing",
    "wof:placetype":"venue"
},
  "geometry": {"coordinates":[-88.987994,43.70251],"type":"Point"}
}