{
  "type": "Feature",
  "properties": {
    "iso:country":"US",
    "sg:address":"8376 Murphy Dr",
    "sg:city":"Middleton",
    "sg:classifiers":[
        {
            "category":"Retail",
            "subcategory":"Repair Shop",
            "type":"Services"
        }
    ],
    "sg:phone":"+1 608 831 9390",
    "sg:postcode":"53562",
    "sg:province":"WI",
    "wof:name":"Bensons Hot Tub Repair",
    "wof:placetype":"venue"
},
  "geometry": {"coordinates":[-89.525322,43.0985],"type":"Point"}
}