{
  "type": "Feature",
  "properties": {
    "iso:country":"US",
    "sg:address":"4267 State Hwy 17",
    "sg:city":"Rhinelander",
    "sg:classifiers":[
        {
            "category":"Building & Trades",
            "subcategory":"Construction",
            "type":"Services"
        }
    ],
    "sg:phone":"+1 715 369 5737",
    "sg:postcode":"54501",
    "sg:province":"WI",
    "sg:tags":[
        "general",
        "contractor"
    ],
    "wof:name":"Energy Wise Builders",
    "wof:placetype":"venue"
},
  "geometry": {"coordinates":[-89.37437,45.675154],"type":"Point"}
}