{
  "type": "Feature",
  "properties": {
    "iso:country":"US",
    "sg:address":"1345 17th St",
    "sg:city":"Barron",
    "sg:classifiers":[
        {
            "category":"Government",
            "subcategory":"Office",
            "type":"Public Place"
        }
    ],
    "sg:phone":"+1 715 537 5339",
    "sg:postcode":"54812",
    "sg:province":"WI",
    "wof:name":"Barron County Shop",
    "wof:placetype":"venue"
},
  "geometry": {"coordinates":[-91.807141,45.399917],"type":"Point"}
}