{
  "type": "Feature",
  "properties": {
    "iso:country":"US",
    "sg:address":"2640 N Humboldt Blvd",
    "sg:city":"Milwaukee",
    "sg:classifiers":[
        {
            "category":"Social Services",
            "subcategory":"Child Care",
            "type":"Services"
        }
    ],
    "sg:phone":"+1 414 562 2477",
    "sg:postcode":"53212",
    "sg:province":"WI",
    "sg:tags":[
        "day"
    ],
    "wof:name":"One Stop Quaility Child Care",
    "wof:placetype":"venue"
},
  "geometry": {"coordinates":[-87.897778,43.06667],"type":"Point"}
}