{
  "type": "Feature",
  "properties": {
    "iso:country":"US",
    "sg:address":"8721 36th Ave",
    "sg:city":"Kenosha",
    "sg:classifiers":[
        {
            "category":"Building & Trades",
            "subcategory":"Landscaping Services",
            "type":"Services"
        }
    ],
    "sg:phone":"+1 262 694 7807",
    "sg:postcode":"53142",
    "sg:province":"IL",
    "sg:tags":[
        "lawn",
        "maintenance",
        "grounds"
    ],
    "wof:name":"John's Lawn Care",
    "wof:placetype":"venue"
},
  "geometry": {"coordinates":[-87.852232,42.546484],"type":"Point"}
}