{
  "type": "Feature",
  "properties": {
    "addr:full":"311 S Forrest St Stoughton WI 53589",
    "addr:housenumber":"311",
    "addr:postcode":"53589",
    "addr:street":"S Forrest St",
    "iso:country":"US",
    "sg:address":"311 S Forrest St",
    "sg:city":"Stoughton",
    "sg:classifiers":[
        {
            "category":"Shopping",
            "subcategory":"Gifts & Souvenirs",
            "type":"Retail Goods"
        }
    ],
    "sg:phone":"+1 608 873 6258",
    "sg:postcode":"53589",
    "sg:province":"WI",
    "sg:tags":[
        "shop"
    ],
    "wof:name":"Oriental Treasures",
    "wof:placetype":"venue"
},
  "geometry": {"coordinates":[-89.219061,42.916472],"type":"Point"}
}