{
  "type": "Feature",
  "properties": {
    "addr:full":"3808 Co Rd V Eden WI 53019",
    "addr:housenumber":"3808",
    "addr:postcode":"53019",
    "addr:street":"Co Rd V",
    "iso:country":"US",
    "sg:address":"3808 Co Rd V",
    "sg:city":"Eden",
    "sg:classifiers":[
        {
            "category":"Recreation",
            "type":"Entertainment"
        }
    ],
    "sg:phone":"+1 920 477 2751",
    "sg:postcode":"53019",
    "sg:province":"WI",
    "sg:tags":[
        "club",
        "membership"
    ],
    "wof:name":"Rod Goodfellows Gun Club",
    "wof:placetype":"venue"
},
  "geometry": {"coordinates":[-88.354856,43.677451],"type":"Point"}
}