{
  "type": "Feature",
  "properties": {
    "iso:country":"US",
    "sg:address":"3470 Indian Echoes Ln",
    "sg:city":"Montello",
    "sg:classifiers":[
        {
            "category":"Real Estate",
            "subcategory":"Real Estate Agent",
            "type":"Services"
        }
    ],
    "sg:phone":"+1 608 297 7783",
    "sg:postcode":"53949",
    "sg:province":"WI",
    "sg:tags":[
        "appraiser"
    ],
    "wof:name":"Adler Appraisal",
    "wof:placetype":"venue"
},
  "geometry": {"coordinates":[-89.295046,43.763142],"type":"Point"}
}