{
  "type": "Feature",
  "properties": {
    "iso:country":"US",
    "sg:address":"520 W Main St",
    "sg:city":"Durand",
    "sg:classifiers":[
        {
            "category":"Shopping",
            "subcategory":"Pharmacy",
            "type":"Retail Goods"
        }
    ],
    "sg:phone":"+1 715 672 5900",
    "sg:postcode":"54736",
    "sg:province":"WI",
    "wof:name":"Econo Foods Quality Care Phrmc",
    "wof:placetype":"venue"
},
  "geometry": {"coordinates":[-91.970071,44.626989],"type":"Point"}
}