{
  "type": "Feature",
  "properties": {
    "addr:full":"627 Michaelis St Marinette WI 54143",
    "addr:housenumber":"627",
    "addr:postcode":"54143",
    "addr:street":"Michaelis St",
    "iso:country":"US",
    "sg:address":"627 Michaelis St",
    "sg:city":"Marinette",
    "sg:classifiers":[
        {
            "category":"Organizations",
            "subcategory":"Religious Organization",
            "type":"Services"
        }
    ],
    "sg:phone":"+1 715 732 9030",
    "sg:postcode":"54143",
    "sg:province":"WI",
    "sg:tags":[
        "church"
    ],
    "wof:name":"Good Shepherd Fellowship Chr",
    "wof:placetype":"venue"
},
  "geometry": {"coordinates":[-87.654275,45.099262],"type":"Point"}
}