{
  "type": "Feature",
  "properties": {
    "addr:full":"1009 1st St Stevens Point WI 54481",
    "addr:housenumber":"1009",
    "addr:postcode":"54481",
    "addr:street":"1St St",
    "iso:country":"US",
    "sg:address":"1009 1st St",
    "sg:city":"Stevens Point",
    "sg:classifiers":[
        {
            "category":"Shopping",
            "subcategory":"Computers & Home Electronics",
            "type":"Retail Goods"
        }
    ],
    "sg:phone":"+1 715 344 9313",
    "sg:postcode":"54481",
    "sg:province":"WI",
    "sg:tags":[
        "equipment",
        "dealer"
    ],
    "sg:website":"www.cardaysupply.com",
    "wof:name":"Carday Supply Management",
    "wof:placetype":"venue"
},
  "geometry": {"coordinates":[-89.586628,44.526171],"type":"Point"}
}