{
  "type": "Feature",
  "properties": {
    "iso:country":"US",
    "sg:address":"8945 McHenry St",
    "sg:city":"Burlington",
    "sg:classifiers":[
        {
            "category":"Building & Trades",
            "subcategory":"Construction",
            "type":"Services"
        }
    ],
    "sg:phone":"+1 262 539 3655",
    "sg:postcode":"53105",
    "sg:province":"WI",
    "sg:tags":[
        "concrete",
        "contractor"
    ],
    "wof:name":"Quality Concrete Inc",
    "wof:placetype":"venue"
},
  "geometry": {"coordinates":[-88.302423,42.610962],"type":"Point"}
}