{
  "type": "Feature",
  "properties": {
    "iso:country":"US",
    "sg:address":"1109 Michigan Ave",
    "sg:city":"Sheboygan",
    "sg:classifiers":[
        {
            "category":"Personal",
            "subcategory":"Beauty Salon",
            "type":"Services"
        }
    ],
    "sg:phone":"+1 920 452 0028",
    "sg:postcode":"53081",
    "sg:province":"WI",
    "sg:tags":[
        "shop"
    ],
    "wof:name":"Xpressions Family Hair Care",
    "wof:placetype":"venue"
},
  "geometry": {"coordinates":[-87.719516,43.758476],"type":"Point"}
}