{
  "type": "Feature",
  "properties": {
    "iso:country":"US",
    "sg:address":"16990 US Hwy 61",
    "sg:city":"Boscobel",
    "sg:classifiers":[
        {
            "category":"Home & Garden",
            "subcategory":"Carpets & Floor Coverings",
            "type":"Retail Goods"
        }
    ],
    "sg:phone":"+1 608 375 4647",
    "sg:postcode":"53805",
    "sg:province":"WI",
    "sg:tags":[
        "material"
    ],
    "wof:name":"Achenbach's Furniture & Flrng",
    "wof:placetype":"venue"
},
  "geometry": {"coordinates":[-90.705676,43.123639],"type":"Point"}
}