{
  "type": "Feature",
  "properties": {
    "iso:country":"US",
    "sg:address":"1015 Reserve St",
    "sg:city":"Stevens Point",
    "sg:classifiers":[
        {
            "category":"Restaurant",
            "type":"Food & Drink"
        }
    ],
    "sg:phone":"+1 715 346 3430",
    "sg:postcode":"54481",
    "sg:province":"WI",
    "sg:tags":[
        "eating"
    ],
    "wof:name":"Taco Bell",
    "wof:placetype":"venue"
},
  "geometry": {"coordinates":[-89.569574,44.526139],"type":"Point"}
}