{
  "type": "Feature",
  "properties": {
    "iso:country":"US",
    "sg:address":"488 N Main St",
    "sg:city":"Juneau",
    "sg:classifiers":[
        {
            "category":"Autos & Motor Vehicles",
            "subcategory":"Fuel & Gas Station",
            "type":"Retail Goods"
        },
        {
            "category":"Retail",
            "subcategory":"Auto Repair",
            "type":"Services"
        }
    ],
    "sg:phone":"+1 920 386 2244",
    "sg:postcode":"53039",
    "sg:province":"WI",
    "sg:tags":[
        "repairing",
        "automobile",
        "station",
        "gasoline",
        "general"
    ],
    "wof:name":"Mike's Automotive",
    "wof:placetype":"venue"
},
  "geometry": {"coordinates":[-88.70177700000001,43.4122],"type":"Point"}
}