{
  "type": "Feature",
  "properties": {
    "iso:country":"US",
    "sg:address":"3402 Jandt Rd",
    "sg:city":"Peshtigo",
    "sg:classifiers":[
        {
            "category":"Retail",
            "subcategory":"Repair Shop",
            "type":"Services"
        }
    ],
    "sg:phone":"+1 715 789 2488",
    "sg:postcode":"54157",
    "sg:province":"WI",
    "wof:name":"Huss Bernie Swr Cleaning Svc",
    "wof:placetype":"venue"
},
  "geometry": {"coordinates":[-87.799499,45.078698],"type":"Point"}
}