{
  "type": "Feature",
  "properties": {
    "iso:country":"US",
    "sg:address":"29750 Long Lake Rd",
    "sg:city":"Danbury",
    "sg:classifiers":[
        {
            "category":"Autos & Motor Vehicles",
            "subcategory":"Boat Sales",
            "type":"Retail Goods"
        },
        {
            "category":"Autos & Motor Vehicles",
            "subcategory":"Motorcycle Sales",
            "type":"Retail Goods"
        }
    ],
    "sg:phone":"+1 715 259 3286",
    "sg:postcode":"54830",
    "sg:province":"WI",
    "sg:tags":[
        "repair",
        "all",
        "terrain"
    ],
    "wof:name":"Four Star Sports",
    "wof:placetype":"venue"
},
  "geometry": {"coordinates":[-92.143361,45.987686],"type":"Point"}
}