{
  "type": "Feature",
  "properties": {
    "iso:country":"US",
    "sg:address":"549 E State St",
    "sg:city":"Burlington",
    "sg:classifiers":[
        {
            "category":"Professional",
            "type":"Services"
        }
    ],
    "sg:phone":"+1 262 763 7331",
    "sg:postcode":"53105",
    "sg:province":"WI",
    "sg:tags":[
        "establishment"
    ],
    "wof:name":"Miller Trinity",
    "wof:placetype":"venue"
},
  "geometry": {"coordinates":[-88.268301,42.678877],"type":"Point"}
}