{
  "type": "Feature",
  "properties": {
    "iso:country":"US",
    "sg:address":"2707 N 54th St",
    "sg:city":"Milwaukee",
    "sg:classifiers":[
        {
            "category":"Social Services",
            "subcategory":"Child Care",
            "type":"Services"
        }
    ],
    "sg:phone":"+1 414 873 6405",
    "sg:postcode":"53210",
    "sg:province":"WI",
    "sg:tags":[
        "day"
    ],
    "wof:name":"Appletree Learning Center",
    "wof:placetype":"venue"
},
  "geometry": {"coordinates":[-87.981041,43.069701],"type":"Point"}
}