{
  "type": "Feature",
  "properties": {
    "iso:country":"US",
    "sg:address":"206 N Ludington St",
    "sg:city":"Columbus",
    "sg:classifiers":[
        {
            "category":"Shopping",
            "subcategory":"Used Merchandise",
            "type":"Retail Goods"
        }
    ],
    "sg:phone":"+1 920 623 3738",
    "sg:postcode":"53925",
    "sg:province":"WI",
    "wof:name":"Pull It Together",
    "wof:placetype":"venue"
},
  "geometry": {"coordinates":[-89.012711,43.339703],"type":"Point"}
}