{
  "type": "Feature",
  "properties": {
    "iso:country":"US",
    "sg:address":"505 State Hwy 67",
    "sg:city":"Kiel",
    "sg:classifiers":[
        {
            "category":"Insurance",
            "subcategory":"Insurance Agent",
            "type":"Services"
        }
    ],
    "sg:phone":"+1 920 894 7835",
    "sg:postcode":"53042",
    "sg:province":"WI",
    "wof:name":"Riesterer Financial Svc",
    "wof:placetype":"venue"
},
  "geometry": {"coordinates":[-88.02258999999999,43.912597],"type":"Point"}
}