{
  "type": "Feature",
  "properties": {
    "iso:country":"US",
    "sg:address":"928 N 13th St",
    "sg:city":"Manitowoc",
    "sg:classifiers":[
        {
            "category":"Wholesale",
            "subcategory":"Machinery & Supplies",
            "type":"Manufacturing & Wholesale Goods"
        },
        {
            "category":"Wholesale",
            "subcategory":"Durable Goods & Equipment",
            "type":"Manufacturing & Wholesale Goods"
        }
    ],
    "sg:phone":"+1 920 684 1985",
    "sg:postcode":"54220",
    "sg:province":"WI",
    "sg:tags":[
        "industrial",
        "representative",
        "manufacturer"
    ],
    "wof:name":"A J Holzinger & Assoc Inc",
    "wof:placetype":"venue"
},
  "geometry": {"coordinates":[-87.664777,44.106005],"type":"Point"}
}