{
  "type": "Feature",
  "properties": {
    "iso:country":"US",
    "sg:address":"32508 State Hwy 21",
    "sg:city":"Warrens",
    "sg:classifiers":[
        {
            "category":"Manufacturing",
            "subcategory":"Buildings",
            "type":"Manufacturing & Wholesale Goods"
        }
    ],
    "sg:phone":"+1 608 427 6804",
    "sg:postcode":"54666",
    "sg:province":"WI",
    "sg:tags":[
        "home",
        "log",
        "cabin"
    ],
    "wof:name":"Countryside Log Homes",
    "wof:placetype":"venue"
},
  "geometry": {"coordinates":[-90.341271,44.026005],"type":"Point"}
}