{
  "type": "Feature",
  "properties": {
    "iso:country":"US",
    "sg:address":"6922 Nicholson Rd",
    "sg:city":"Caledonia",
    "sg:classifiers":[
        {
            "category":"Government",
            "subcategory":"Office",
            "type":"Public Place"
        }
    ],
    "sg:phone":"+1 262 835 7765",
    "sg:postcode":"53108",
    "sg:province":"WI",
    "sg:tags":[
        "govt",
        "city"
    ],
    "wof:name":"Caledonia Utility District",
    "wof:placetype":"venue"
},
  "geometry": {"coordinates":[-87.89502400000001,42.799692],"type":"Point"}
}