{
  "type": "Feature",
  "properties": {
    "iso:country":"US",
    "sg:address":"607 Main St",
    "sg:city":"Ridgeway",
    "sg:classifiers":[
        {
            "category":"Bars & Pubs",
            "type":"Food & Drink"
        }
    ],
    "sg:phone":"+1 608 924 3635",
    "sg:postcode":"53582",
    "sg:province":"WI",
    "wof:name":"Doodle's",
    "wof:placetype":"venue"
},
  "geometry": {"coordinates":[-89.992799,42.999499],"type":"Point"}
}