{
  "type": "Feature",
  "properties": {
    "iso:country":"US",
    "sg:address":"1217 Jenifer St",
    "sg:city":"Madison",
    "sg:classifiers":[
        {
            "category":"Retail",
            "subcategory":"Laundry & Dry Cleaning",
            "type":"Services"
        }
    ],
    "sg:phone":"+1 608 258 9004",
    "sg:postcode":"53703",
    "sg:province":"WI",
    "wof:name":"Marango Carpet",
    "wof:placetype":"venue"
},
  "geometry": {"coordinates":[-89.361837,43.083584],"type":"Point"}
}