{
  "type": "Feature",
  "properties": {
    "addr:full":"310 Westgate Mall Madison WI 53711",
    "addr:housenumber":"310",
    "addr:postcode":"53711",
    "addr:street":"Westgate Mall",
    "iso:country":"US",
    "sg:address":"310 Westgate Mall",
    "sg:city":"Madison",
    "sg:classifiers":[
        {
            "category":"Personal",
            "subcategory":"Beauty Salon",
            "type":"Services"
        }
    ],
    "sg:phone":"+1 608 271 4204",
    "sg:postcode":"53711",
    "sg:province":"WI",
    "sg:tags":[
        "shop"
    ],
    "sg:website":"www.cosmetologycollege.com",
    "wof:name":"Madison Cosmetology College",
    "wof:placetype":"venue"
},
  "geometry": {"coordinates":[-89.472075,43.051959],"type":"Point"}
}