{
  "type": "Feature",
  "properties": {
    "iso:country":"US",
    "sg:address":"215 S Memorial Dr",
    "sg:city":"Appleton",
    "sg:classifiers":[
        {
            "category":"Restaurant",
            "type":"Food & Drink"
        }
    ],
    "sg:phone":"+1 920 380 4745",
    "sg:postcode":"54911",
    "sg:province":"WI",
    "sg:tags":[
        "eating"
    ],
    "wof:name":"Black & Tan Grille",
    "wof:placetype":"venue"
},
  "geometry": {"coordinates":[-88.415449,44.259848],"type":"Point"}
}