{
  "type": "Feature",
  "properties": {
    "addr:full":"6315 Co Rd Tt Marshall WI 53559",
    "addr:housenumber":"6315",
    "addr:postcode":"53559",
    "addr:street":"Co Rd",
    "iso:country":"US",
    "sg:address":"6315 Co Rd Tt",
    "sg:city":"Marshall",
    "sg:classifiers":[
        {
            "category":"Farming",
            "subcategory":"Dairy Farm",
            "type":"Manufacturing & Wholesale Goods"
        }
    ],
    "sg:phone":"+1 608 655 4468",
    "sg:postcode":"53559",
    "sg:province":"WI",
    "wof:name":"Allen Wendt",
    "wof:placetype":"venue"
},
  "geometry": {"coordinates":[-89.083456,43.198583],"type":"Point"}
}