{
  "type": "Feature",
  "properties": {
    "iso:country":"US",
    "sg:address":"644 S 9th St",
    "sg:city":"Milwaukee",
    "sg:classifiers":[
        {
            "category":"Bars & Pubs",
            "type":"Food & Drink"
        }
    ],
    "sg:phone":"+1 414 277 8371",
    "sg:postcode":"53204",
    "sg:province":"WI",
    "wof:name":"Chivas",
    "wof:placetype":"venue"
},
  "geometry": {"coordinates":[-87.922456,43.024712],"type":"Point"}
}