{
  "type": "Feature",
  "properties": {
    "iso:country":"US",
    "sg:address":"105 21st St N",
    "sg:city":"Menomonie",
    "sg:classifiers":[
        {
            "category":"Organizations",
            "subcategory":"Labor Organization",
            "type":"Services"
        }
    ],
    "sg:phone":"+1 715 235 6808",
    "sg:postcode":"54751",
    "sg:province":"WI",
    "wof:name":"West Central Education Assn",
    "wof:placetype":"venue"
},
  "geometry": {"coordinates":[-91.904594,44.882721],"type":"Point"}
}