{
  "type": "Feature",
  "properties": {
    "iso:country":"US",
    "sg:address":"2525 Milton Ave",
    "sg:city":"Janesville",
    "sg:classifiers":[
        {
            "category":"Health Services",
            "subcategory":"Doctor",
            "type":"Services"
        }
    ],
    "sg:phone":"+1 608 754 5340",
    "sg:postcode":"53545",
    "sg:province":"WI",
    "sg:tags":[
        "medical"
    ],
    "wof:name":"Daniel G Wong DDS",
    "wof:placetype":"venue"
},
  "geometry": {"coordinates":[-89.001648,42.712447],"type":"Point"}
}