{
  "type": "Feature",
  "properties": {
    "iso:country":"US",
    "sg:address":"795 Fond du Lac Ave",
    "sg:city":"Fond Du Lac",
    "sg:classifiers":[
        {
            "category":"Organizations",
            "subcategory":"Community Association",
            "type":"Services"
        }
    ],
    "sg:phone":"+1 920 921 9165",
    "sg:postcode":"54935",
    "sg:province":"WI",
    "wof:name":"Knights Of Columbus",
    "wof:placetype":"venue"
},
  "geometry": {"coordinates":[-88.42026799999999,43.760157],"type":"Point"}
}