{
  "type": "Feature",
  "properties": {
    "iso:country":"US",
    "sg:address":"3994 State Hwy 32",
    "sg:city":"Laona",
    "sg:classifiers":[
        {
            "category":"Retail",
            "subcategory":"Auto Repair",
            "type":"Services"
        }
    ],
    "sg:phone":"+1 715 674 2059",
    "sg:postcode":"54541",
    "sg:province":"WI",
    "sg:tags":[
        "truck",
        "general"
    ],
    "wof:name":"G & R Truck Repair",
    "wof:placetype":"venue"
},
  "geometry": {"coordinates":[-88.67543499999999,45.521859],"type":"Point"}
}