{
  "type": "Feature",
  "properties": {
    "iso:country":"US",
    "sg:address":"1977 S 80th St",
    "sg:city":"Milwaukee",
    "sg:classifiers":[
        {
            "category":"Bars & Pubs",
            "type":"Food & Drink"
        }
    ],
    "sg:phone":"+1 414 545 1390",
    "sg:postcode":"53219",
    "sg:province":"WI",
    "sg:tags":[
        "drinking"
    ],
    "wof:name":"Breaking Point",
    "wof:placetype":"venue"
},
  "geometry": {"coordinates":[-88.012957,43.008799],"type":"Point"}
}