{
  "type": "Feature",
  "properties": {
    "addr:full":"2727 W Roosevelt Dr Milwaukee WI 53216",
    "addr:housenumber":"2727",
    "addr:postcode":"53216",
    "addr:street":"W Roosevelt Dr",
    "iso:country":"US",
    "sg:address":"2727 W Roosevelt Dr",
    "sg:city":"Milwaukee",
    "sg:classifiers":[
        {
            "category":"Education",
            "subcategory":"Special Training",
            "type":"Public Place"
        }
    ],
    "sg:phone":"+1 414 445 4190",
    "sg:postcode":"53216",
    "sg:province":"WI",
    "sg:tags":[
        "craft"
    ],
    "wof:name":"Heavenly Creations",
    "wof:placetype":"venue"
},
  "geometry": {"coordinates":[-87.947827,43.095083],"type":"Point"}
}