{
  "type": "Feature",
  "properties": {
    "addr:full":"1701 Washington St Manitowoc WI 54220",
    "addr:housenumber":"1701",
    "addr:postcode":"54220",
    "addr:street":"Washington St",
    "iso:country":"US",
    "sg:address":"1701 Washington St",
    "sg:city":"Manitowoc",
    "sg:classifiers":[
        {
            "category":"Health Services",
            "subcategory":"Clinic",
            "type":"Services"
        }
    ],
    "sg:phone":"+1 920 652 0969",
    "sg:postcode":"54220",
    "sg:province":"WI",
    "sg:tags":[
        "home"
    ],
    "wof:name":"WI-Personal Care Svc",
    "wof:placetype":"venue"
},
  "geometry": {"coordinates":[-87.67144399999999,44.088935],"type":"Point"}
}