{
  "type": "Feature",
  "properties": {
    "iso:country":"US",
    "sg:address":"407 N Progress Dr",
    "sg:city":"Saukville",
    "sg:classifiers":[
        {
            "category":"Wholesale",
            "subcategory":"Durable Goods & Equipment",
            "type":"Manufacturing & Wholesale Goods"
        }
    ],
    "sg:phone":"+1 262 268 9399",
    "sg:postcode":"53080",
    "sg:province":"WI",
    "sg:tags":[
        "representative",
        "manufacturer"
    ],
    "wof:name":"Conway Incentives",
    "wof:placetype":"venue"
},
  "geometry": {"coordinates":[-87.947097,43.387678],"type":"Point"}
}