{
  "type": "Feature",
  "properties": {
    "iso:country":"US",
    "sg:address":"28230 College Farm Rd",
    "sg:city":"Platteville",
    "sg:classifiers":[
        {
            "category":"Farming",
            "subcategory":"Dairy Farm",
            "type":"Manufacturing & Wholesale Goods"
        }
    ],
    "sg:phone":"+1 608 348 3983",
    "sg:postcode":"53818",
    "sg:province":"WI",
    "wof:name":"Voigtscrest Holsteins",
    "wof:placetype":"venue"
},
  "geometry": {"coordinates":[-90.377224,42.711661],"type":"Point"}
}