{
  "type": "Feature",
  "properties": {
    "iso:country":"US",
    "sg:address":"1032 S Cesar E Chavez Dr",
    "sg:city":"Milwaukee",
    "sg:classifiers":[
        {
            "category":"Health Services",
            "subcategory":"Doctor",
            "type":"Services"
        },
        {
            "category":"Health Services",
            "subcategory":"Clinic",
            "type":"Services"
        },
        {
            "category":"Community Center",
            "type":"Public Place"
        }
    ],
    "sg:phone":"+1 414 672 1353",
    "sg:postcode":"53204",
    "sg:province":"WI",
    "sg:tags":[
        "physician",
        "pediatrics",
        "family",
        "medical",
        "practice",
        "surgeons",
        "medicine"
    ],
    "wof:name":"Sixteenth Street Community Health Center",
    "wof:placetype":"venue"
},
  "geometry": {"coordinates":[-87.933052,43.020824],"type":"Point"}
}