{
  "type": "Feature",
  "properties": {
    "iso:country":"US",
    "sg:address":"15659 Apple Grove Church Rd",
    "sg:city":"Argyle",
    "sg:classifiers":[
        {
            "category":"Real Estate",
            "subcategory":"Real Estate Operator",
            "type":"Services"
        }
    ],
    "sg:phone":"+1 608 543 3045",
    "sg:postcode":"53504",
    "sg:province":"WI",
    "sg:tags":[
        "property",
        "lessor"
    ],
    "wof:name":"Nelson Paul & Ruth",
    "wof:placetype":"venue"
},
  "geometry": {"coordinates":[-89.931741,42.725503],"type":"Point"}
}