{
  "type": "Feature",
  "properties": {
    "iso:country":"US",
    "sg:address":"666 Deerwood Dr",
    "sg:city":"Hudson",
    "sg:classifiers":[
        {
            "category":"Freight",
            "type":"Transportation"
        }
    ],
    "sg:phone":"+1 715 386 9180",
    "sg:postcode":"54016",
    "sg:province":"WI",
    "sg:tags":[
        "company",
        "trucking"
    ],
    "wof:name":"Christianson Trucking",
    "wof:placetype":"venue"
},
  "geometry": {"coordinates":[-92.66717800000001,44.947617],"type":"Point"}
}