{
  "type": "Feature",
  "properties": {
    "iso:country":"US",
    "sg:address":"3845 Schielke Rd",
    "sg:city":"Gleason",
    "sg:classifiers":[
        {
            "category":"Farming",
            "subcategory":"Livestock Farm",
            "type":"Manufacturing & Wholesale Goods"
        }
    ],
    "sg:phone":"+1 715 536 5009",
    "sg:postcode":"54435",
    "sg:province":"WI",
    "sg:tags":[
        "beef",
        "feedlot",
        "cattle"
    ],
    "wof:name":"Frank Schelkie",
    "wof:placetype":"venue"
},
  "geometry": {"coordinates":[-89.445571,45.259038],"type":"Point"}
}