{
  "type": "Feature",
  "properties": {
    "iso:country":"US",
    "sg:address":"2680 Kennedy Rd",
    "sg:city":"Rhinelander",
    "sg:classifiers":[
        {
            "category":"Retail",
            "subcategory":"Veterinary Services",
            "type":"Services"
        }
    ],
    "sg:phone":"+1 715 362 6333",
    "sg:postcode":"54501",
    "sg:province":"WI",
    "sg:tags":[
        "hospital",
        "animal"
    ],
    "wof:name":"Cornerstone Equine Service",
    "wof:placetype":"venue"
},
  "geometry": {"coordinates":[-89.378433,45.59624],"type":"Point"}
}