{
  "type": "Feature",
  "properties": {
    "iso:country":"US",
    "sg:address":"71595 Hoover Line Rd",
    "sg:city":"Iron River",
    "sg:classifiers":[
        {
            "category":"Freight",
            "type":"Transportation"
        }
    ],
    "sg:phone":"+1 715 372 5210",
    "sg:postcode":"54847",
    "sg:province":"WI",
    "sg:tags":[
        "operator",
        "local",
        "trucking"
    ],
    "wof:name":"Middleman Trucking",
    "wof:placetype":"venue"
},
  "geometry": {"coordinates":[-91.490409,46.618794],"type":"Point"}
}