{
  "type": "Feature",
  "properties": {
    "iso:country":"US",
    "sg:address":"2122 S West Ave",
    "sg:city":"Waukesha",
    "sg:classifiers":[
        {
            "category":"Building & Trades",
            "subcategory":"Construction",
            "type":"Services"
        }
    ],
    "sg:phone":"+1 262 650 1300",
    "sg:postcode":"53189",
    "sg:province":"WI",
    "sg:tags":[
        "house",
        "contractor",
        "concrete"
    ],
    "sg:website":"www.pouredfoundations.com",
    "wof:name":"Coello & Associates Inc",
    "wof:placetype":"venue"
},
  "geometry": {"coordinates":[-88.235809,42.976256],"type":"Point"}
}