{
  "type": "Feature",
  "properties": {
    "iso:country":"US",
    "sg:address":"2436 Shoop St",
    "sg:city":"Racine",
    "sg:classifiers":[
        {
            "category":"Restaurant",
            "type":"Food & Drink"
        }
    ],
    "sg:phone":"+1 262 632 6612",
    "sg:postcode":"53404",
    "sg:province":"WI",
    "sg:tags":[
        "eating"
    ],
    "wof:name":"European Cafe",
    "wof:placetype":"venue"
},
  "geometry": {"coordinates":[-87.805769,42.750934],"type":"Point"}
}