{
  "type": "Feature",
  "properties": {
    "iso:country":"US",
    "sg:address":"642 Northview Rd",
    "sg:city":"Waukesha",
    "sg:classifiers":[
        {
            "category":"Organizations",
            "subcategory":"Membership Organization",
            "type":"Services"
        },
        {
            "category":"Professional",
            "type":"Services"
        }
    ],
    "sg:phone":"+1 262 513 9670",
    "sg:postcode":"53188",
    "sg:province":"WI",
    "sg:tags":[
        "establishment"
    ],
    "wof:name":"Judson & Assoc",
    "wof:placetype":"venue"
},
  "geometry": {"coordinates":[-88.231481,43.032363],"type":"Point"}
}