{
  "type": "Feature",
  "properties": {
    "addr:full":"910 N Sawyer St Oshkosh WI 54902",
    "addr:housenumber":"910",
    "addr:postcode":"54902",
    "addr:street":"N Sawyer St",
    "iso:country":"US",
    "sg:address":"910 N Sawyer St",
    "sg:city":"Oshkosh",
    "sg:classifiers":[
        {
            "category":"Education",
            "subcategory":"School",
            "type":"Public Place"
        }
    ],
    "sg:phone":"+1 920 424 0411",
    "sg:postcode":"54902",
    "sg:province":"WI",
    "sg:tags":[
        "elementary"
    ],
    "sg:website":"www.oshkosh.k12.wi.us",
    "wof:name":"Roosevelt Elementary School",
    "wof:placetype":"venue"
},
  "geometry": {"coordinates":[-88.567069,44.028643],"type":"Point"}
}