{
  "type": "Feature",
  "properties": {
    "addr:full":"915 West St Boyceville WI 54725",
    "addr:housenumber":"915",
    "addr:postcode":"54725",
    "addr:street":"West St",
    "iso:country":"US",
    "sg:address":"915 West St",
    "sg:city":"Boyceville",
    "sg:classifiers":[
        {
            "category":"Real Estate",
            "subcategory":"Real Estate Operator",
            "type":"Services"
        }
    ],
    "sg:phone":"+1 715 643 2010",
    "sg:postcode":"54725",
    "sg:province":"WI",
    "sg:tags":[
        "property",
        "lessor"
    ],
    "wof:name":"Jdt Rental Properties LLC",
    "wof:placetype":"venue"
},
  "geometry": {"coordinates":[-92.050962,45.041949],"type":"Point"}
}