{
  "type": "Feature",
  "properties": {
    "addr:full":"2700 S Shore Dr Milwaukee WI 53207",
    "addr:housenumber":"2700",
    "addr:postcode":"53207",
    "addr:street":"S Shore Dr",
    "iso:country":"US",
    "sg:address":"2700 S Shore Dr",
    "sg:city":"Milwaukee",
    "sg:classifiers":[
        {
            "category":"Professional",
            "subcategory":"Management & Consulting",
            "type":"Services"
        }
    ],
    "sg:phone":"+1 414 482 1214",
    "sg:postcode":"53207",
    "sg:province":"WI",
    "sg:tags":[
        "consultant",
        "attorney",
        "relations",
        "government"
    ],
    "wof:name":"Schreiber Martin J & Assoc",
    "wof:placetype":"venue"
},
  "geometry": {"coordinates":[-87.884367,42.99583],"type":"Point"}
}