{
  "type": "Feature",
  "properties": {
    "iso:country":"US",
    "sg:address":"1001 Trinity Rd",
    "sg:city":"Hilbert",
    "sg:classifiers":[
        {
            "category":"Wholesale",
            "subcategory":"Machinery & Supplies",
            "type":"Manufacturing & Wholesale Goods"
        }
    ],
    "sg:phone":"+1 920 853 3953",
    "sg:postcode":"54129",
    "sg:province":"WI",
    "sg:tags":[
        "equipment",
        "industrial"
    ],
    "wof:name":"Miller Services",
    "wof:placetype":"venue"
},
  "geometry": {"coordinates":[-88.088932,44.109731],"type":"Point"}
}