{
  "type": "Feature",
  "properties": {
    "iso:country":"US",
    "sg:address":"1923 Ramona Rd",
    "sg:city":"Waukesha",
    "sg:classifiers":[
        {
            "category":"Retail",
            "subcategory":"Self-service Laundry",
            "type":"Services"
        }
    ],
    "sg:phone":"+1 262 524 8058",
    "sg:postcode":"53186",
    "sg:province":"WI",
    "sg:tags":[
        "coin"
    ],
    "wof:name":"Grand Ave Laundry",
    "wof:placetype":"venue"
},
  "geometry": {"coordinates":[-88.18962500000001,43.030124],"type":"Point"}
}