{
  "type": "Feature",
  "properties": {
    "iso:country":"US",
    "sg:address":"320 N Adams St",
    "sg:city":"Green Bay",
    "sg:classifiers":[
        {
            "category":"Health Services",
            "subcategory":"Clinic",
            "type":"Services"
        }
    ],
    "sg:phone":"+1 920 431 0100",
    "sg:postcode":"54301",
    "sg:province":"WI",
    "sg:tags":[
        "agency",
        "welfare"
    ],
    "wof:name":"Breast Cancer Family Fndtn",
    "wof:placetype":"venue"
},
  "geometry": {"coordinates":[-88.012995,44.516132],"type":"Point"}
}