{
  "type": "Feature",
  "properties": {
    "iso:country":"US",
    "sg:address":"700 S 2nd St",
    "sg:city":"Delavan",
    "sg:classifiers":[
        {
            "category":"Sports & Exercise",
            "subcategory":"Golf",
            "type":"Entertainment"
        }
    ],
    "sg:phone":"+1 262 728 3966",
    "sg:postcode":"53115",
    "sg:province":"WI",
    "sg:tags":[
        "course",
        "public"
    ],
    "wof:name":"Delavan City of Inc",
    "wof:placetype":"venue"
},
  "geometry": {"coordinates":[-88.646861,42.624898],"type":"Point"}
}