{
  "type": "Feature",
  "properties": {
    "iso:country":"US",
    "sg:address":"1020 Kabel Ave",
    "sg:city":"Rhinelander",
    "sg:classifiers":[
        {
            "category":"Health Services",
            "subcategory":"Health Practitioner",
            "type":"Services"
        }
    ],
    "sg:phone":"+1 715 361 4710",
    "sg:postcode":"54501",
    "sg:province":"WI",
    "sg:tags":[
        "nurse",
        "registry"
    ],
    "wof:name":"Barbara Gartmann",
    "wof:placetype":"venue"
},
  "geometry": {"coordinates":[-89.41296800000001,45.628493],"type":"Point"}
}