{
  "type": "Feature",
  "properties": {
    "addr:full":"6001 Research Park Blvd Madison WI 53719",
    "addr:housenumber":"6001",
    "addr:postcode":"53719",
    "addr:street":"Research Park Blvd",
    "iso:country":"US",
    "sg:address":"6001 Research Park Blvd",
    "sg:city":"Madison",
    "sg:classifiers":[
        {
            "category":"Health Services",
            "subcategory":"Doctor",
            "type":"Services"
        }
    ],
    "sg:phone":"+1 608 263 6098",
    "sg:postcode":"53719",
    "sg:province":"WI",
    "sg:tags":[
        "medical"
    ],
    "wof:name":"Ronald J Diamond MD",
    "wof:placetype":"venue"
},
  "geometry": {"coordinates":[-89.48272799999999,43.055652],"type":"Point"}
}