{
  "type": "Feature",
  "properties": {
    "addr:full":"8027 S 66th St Franklin WI 53132",
    "addr:housenumber":"8027",
    "addr:postcode":"53132",
    "addr:street":"S 66Th St",
    "iso:country":"US",
    "sg:address":"8027 S 66th St",
    "sg:city":"Franklin",
    "sg:classifiers":[
        {
            "category":"Building & Trades",
            "subcategory":"Construction",
            "type":"Services"
        }
    ],
    "sg:phone":"+1 414 425 8875",
    "sg:postcode":"53132",
    "sg:province":"WI",
    "sg:tags":[
        "contractor"
    ],
    "wof:name":"Abbey Homes LLC",
    "wof:placetype":"venue"
},
  "geometry": {"coordinates":[-87.99742000000001,42.898179],"type":"Point"}
}