{
  "type": "Feature",
  "properties": {
    "iso:country":"US",
    "sg:address":"725 8th St",
    "sg:city":"Monroe",
    "sg:classifiers":[
        {
            "category":"Shopping",
            "subcategory":"Florist",
            "type":"Retail Goods"
        }
    ],
    "sg:phone":"+1 608 325 5050",
    "sg:postcode":"53566",
    "sg:province":"WI",
    "wof:name":"The Blooming Basket",
    "wof:placetype":"venue"
},
  "geometry": {"coordinates":[-89.650936,42.603405],"type":"Point"}
}