{
  "type": "Feature",
  "properties": {
    "iso:country":"US",
    "sg:address":"6568 Anderson Dr",
    "sg:city":"Delavan",
    "sg:classifiers":[
        {
            "category":"Real Estate",
            "subcategory":"Real Estate Agent",
            "type":"Services"
        }
    ],
    "sg:phone":"+1 262 728 1449",
    "sg:postcode":"53115",
    "sg:province":"WI",
    "sg:tags":[
        "appraiser"
    ],
    "wof:name":"Pamela Paul & Assoc",
    "wof:placetype":"venue"
},
  "geometry": {"coordinates":[-88.675275,42.730315],"type":"Point"}
}