{
  "type": "Feature",
  "properties": {
    "iso:country":"US",
    "sg:address":"915 E Calumet Rd",
    "sg:city":"Milwaukee",
    "sg:classifiers":[
        {
            "category":"Wholesale",
            "subcategory":"Machinery & Supplies",
            "type":"Manufacturing & Wholesale Goods"
        }
    ],
    "sg:phone":"+1 414 228 1640",
    "sg:postcode":"53217",
    "sg:province":"WI",
    "sg:tags":[
        "equipment",
        "printing"
    ],
    "wof:name":"Comexi America Inc",
    "wof:placetype":"venue"
},
  "geometry": {"coordinates":[-87.89688,43.154702],"type":"Point"}
}