{
  "type": "Feature",
  "properties": {
    "iso:country":"US",
    "sg:address":"1462 Strongs Ave",
    "sg:city":"Stevens Point",
    "sg:classifiers":[
        {
            "category":"Government",
            "subcategory":"Office",
            "type":"Public Place"
        }
    ],
    "sg:phone":"+1 715 346 1330",
    "sg:postcode":"54481",
    "sg:province":"WI",
    "sg:tags":[
        "county",
        "taxation"
    ],
    "wof:name":"Portage County Finance Dept",
    "wof:placetype":"venue"
},
  "geometry": {"coordinates":[-89.582044,44.521264],"type":"Point"}
}