{
  "type": "Feature",
  "properties": {
    "iso:country":"US",
    "sg:address":"2385 N Brookfield Rd",
    "sg:city":"Brookfield",
    "sg:classifiers":[
        {
            "category":"Bars & Pubs",
            "type":"Food & Drink"
        }
    ],
    "sg:phone":"+1 262 797 0300",
    "sg:postcode":"53045",
    "sg:province":"WI",
    "wof:name":"Side Track Bar",
    "wof:placetype":"venue"
},
  "geometry": {"coordinates":[-88.145945,43.063708],"type":"Point"}
}