{
  "type": "Feature",
  "properties": {
    "iso:country":"US",
    "sg:address":"904 E Pleasant St",
    "sg:city":"Milwaukee",
    "sg:classifiers":[
        {
            "category":"Shopping",
            "subcategory":"Beauty & Cosmetics",
            "type":"Retail Goods"
        }
    ],
    "sg:phone":"+1 414 272 2717",
    "sg:postcode":"53202",
    "sg:province":"WI",
    "sg:tags":[
        "merchandise"
    ],
    "wof:name":"Lynn Grassy Permanent Cosmetic",
    "wof:placetype":"venue"
},
  "geometry": {"coordinates":[-87.899691,43.050604],"type":"Point"}
}