{
  "type": "Feature",
  "properties": {
    "addr:full":"240 Church St Woodville WI 54028",
    "addr:housenumber":"240",
    "addr:postcode":"54028",
    "addr:street":"Church St",
    "iso:country":"US",
    "sg:address":"240 Church St",
    "sg:city":"Woodville",
    "sg:classifiers":[
        {
            "category":"Real Estate",
            "subcategory":"Real Estate Agent",
            "type":"Services"
        }
    ],
    "sg:phone":"+1 715 698 2487",
    "sg:postcode":"54028",
    "sg:province":"WI",
    "sg:tags":[
        "authorities",
        "housing"
    ],
    "wof:name":"Woodville Housing Authority",
    "wof:placetype":"venue"
},
  "geometry": {"coordinates":[-92.288105,44.948976],"type":"Point"}
}