{
  "type": "Feature",
  "properties": {
    "iso:country":"US",
    "sg:address":"5632 Broad St",
    "sg:city":"Greendale",
    "sg:classifiers":[
        {
            "category":"Shopping",
            "subcategory":"Gifts & Souvenirs",
            "type":"Retail Goods"
        }
    ],
    "sg:phone":"+1 414 421 1938",
    "sg:postcode":"53129",
    "sg:province":"WI",
    "sg:tags":[
        "shop"
    ],
    "wof:name":"Season's Of The Heart LTD",
    "wof:placetype":"venue"
},
  "geometry": {"coordinates":[-87.995932,42.941177],"type":"Point"}
}