{
  "type": "Feature",
  "properties": {
    "iso:country":"US",
    "sg:address":"1105 Grand Ave",
    "sg:city":"Wausau",
    "sg:classifiers":[
        {
            "category":"Shopping",
            "subcategory":"Department Store",
            "type":"Retail Goods"
        }
    ],
    "sg:phone":"+1 715 359 4251",
    "sg:postcode":"54403",
    "sg:province":"WI",
    "wof:name":"Shopko",
    "wof:placetype":"venue"
},
  "geometry": {"coordinates":[-89.620783,44.946194],"type":"Point"}
}