{
  "type": "Feature",
  "properties": {
    "iso:country":"US",
    "sg:address":"335 W Menasha Ave",
    "sg:city":"Whitelaw",
    "sg:classifiers":[
        {
            "category":"Building & Trades",
            "subcategory":"Construction",
            "type":"Services"
        }
    ],
    "sg:phone":"+1 920 732 3333",
    "sg:postcode":"54247",
    "sg:province":"WI",
    "sg:tags":[
        "home",
        "improvement"
    ],
    "wof:name":"Intergrity Improvements",
    "wof:placetype":"venue"
},
  "geometry": {"coordinates":[-87.832277,44.143499],"type":"Point"}
}