{
  "type": "Feature",
  "properties": {
    "iso:country":"US",
    "sg:address":"11083 1st Rd",
    "sg:city":"Wausaukee",
    "sg:classifiers":[
        {
            "category":"Professional",
            "type":"Services"
        }
    ],
    "sg:phone":"+1 715 856 5045",
    "sg:postcode":"54177",
    "sg:province":"WI",
    "wof:name":"Side Door Video",
    "wof:placetype":"venue"
},
  "geometry": {"coordinates":[-87.95496199999999,45.359962],"type":"Point"}
}