{
  "type": "Feature",
  "properties": {
    "iso:country":"US",
    "sg:address":"4492 Highland Dr",
    "sg:city":"Sullivan",
    "sg:classifiers":[
        {
            "category":"Retail",
            "subcategory":"Auto Repair",
            "type":"Services"
        }
    ],
    "sg:phone":"+1 262 593 5443",
    "sg:postcode":"53178",
    "sg:province":"WI",
    "sg:tags":[
        "automotive"
    ],
    "wof:name":"R T Automotive",
    "wof:placetype":"venue"
},
  "geometry": {"coordinates":[-88.560991,43.007147],"type":"Point"}
}