{
  "type": "Feature",
  "properties": {
    "addr:full":"800 30th St Monroe WI 53566",
    "addr:housenumber":"800",
    "addr:postcode":"53566",
    "addr:street":"30Th St",
    "iso:country":"US",
    "sg:address":"800 30th St",
    "sg:city":"Monroe",
    "sg:classifiers":[
        {
            "category":"Professional",
            "subcategory":"Advertising",
            "type":"Services"
        }
    ],
    "sg:phone":"+1 608 325 5282",
    "sg:postcode":"53566",
    "sg:province":"WI",
    "sg:tags":[
        "counselor"
    ],
    "wof:name":"Advize Advertising Agency",
    "wof:placetype":"venue"
},
  "geometry": {"coordinates":[-89.649884,42.584785],"type":"Point"}
}