{
  "type": "Feature",
  "properties": {
    "iso:country":"US",
    "sg:address":"2100 Church St",
    "sg:city":"East Troy",
    "sg:classifiers":[
        {
            "category":"Professional",
            "subcategory":"Lawyer & Legal Services",
            "type":"Services"
        }
    ],
    "sg:phone":"+1 262 642 3000",
    "sg:postcode":"53120",
    "sg:province":"WI",
    "sg:tags":[
        "attorney"
    ],
    "wof:name":"Hudec Law Offices",
    "wof:placetype":"venue"
},
  "geometry": {"coordinates":[-88.40496400000001,42.78479],"type":"Point"}
}