{
  "type": "Feature",
  "properties": {
    "iso:country":"US",
    "sg:address":"237 E Main St",
    "sg:city":"Whitewater",
    "sg:classifiers":[
        {
            "category":"Retail",
            "subcategory":"Auto Repair",
            "type":"Services"
        }
    ],
    "sg:phone":"+1 262 473 4646",
    "sg:postcode":"53190",
    "sg:province":"WI",
    "sg:tags":[
        "repairing",
        "automobile"
    ],
    "wof:name":"Whitewater Auto Repair",
    "wof:placetype":"venue"
},
  "geometry": {"coordinates":[-88.727366,42.833857],"type":"Point"}
}