{
  "type": "Feature",
  "properties": {
    "iso:country":"US",
    "sg:address":"2606 S 51st St",
    "sg:city":"Milwaukee",
    "sg:classifiers":[
        {
            "category":"Place Of Worship",
            "subcategory":"Monastery",
            "type":"Public Place"
        }
    ],
    "sg:phone":"+1 414 321 1775",
    "sg:postcode":"53219",
    "sg:province":"WI",
    "sg:tags":[
        "convent"
    ],
    "sg:website":"http://www.snd1.org",
    "wof:name":"Sisters of Notre Dame",
    "wof:placetype":"venue"
},
  "geometry": {"coordinates":[-87.977142,42.997325],"type":"Point"}
}