{
  "type": "Feature",
  "properties": {
    "iso:country":"US",
    "sg:address":"830 2nd Ave",
    "sg:city":"Antigo",
    "sg:classifiers":[
        {
            "category":"Real Estate",
            "subcategory":"Real Estate Services",
            "type":"Services"
        }
    ],
    "sg:phone":"+1 715 627 2424",
    "sg:postcode":"54409",
    "sg:province":"WI",
    "sg:tags":[
        "abstract",
        "title"
    ],
    "wof:name":"Amerititle & Abstract Inc",
    "wof:placetype":"venue"
},
  "geometry": {"coordinates":[-89.154938,45.144811],"type":"Point"}
}