{
  "type": "Feature",
  "properties": {
    "addr:full":"11546 Sauk Prairie Rd Prairie Du Sac WI 53578",
    "addr:housenumber":"11546",
    "addr:postcode":"53578",
    "addr:street":"Sauk Prairie Rd",
    "iso:country":"US",
    "sg:address":"11546 Sauk Prairie Rd",
    "sg:city":"Prairie Du Sac",
    "sg:classifiers":[
        {
            "category":"Farming",
            "subcategory":"Dairy Farm",
            "type":"Manufacturing & Wholesale Goods"
        }
    ],
    "sg:phone":"+1 608 643 6512",
    "sg:postcode":"53578",
    "sg:province":"WI",
    "wof:name":"Dave Litscher",
    "wof:placetype":"venue"
},
  "geometry": {"coordinates":[-89.747913,43.281899],"type":"Point"}
}