{
  "type": "Feature",
  "properties": {
    "iso:country":"US",
    "sg:address":"785 Bloom Rd",
    "sg:city":"Eagle River",
    "sg:classifiers":[
        {
            "category":"Recreation",
            "type":"Entertainment"
        }
    ],
    "sg:phone":"+1 715 479 7642",
    "sg:postcode":"54521",
    "sg:province":"WI",
    "wof:name":"Pine Ridge Equestrian Center",
    "wof:placetype":"venue"
},
  "geometry": {"coordinates":[-89.229304,45.895199],"type":"Point"}
}