{
  "type": "Feature",
  "properties": {
    "iso:country":"US",
    "sg:address":"5515 W Carmen Ave",
    "sg:city":"Milwaukee",
    "sg:classifiers":[
        {
            "category":"Manufacturing",
            "subcategory":"Printing",
            "type":"Manufacturing & Wholesale Goods"
        }
    ],
    "sg:phone":"+1 414 461 5791",
    "sg:postcode":"53218",
    "sg:province":"WI",
    "sg:tags":[
        "book"
    ],
    "wof:name":"Aegis Financial Publishing Co",
    "wof:placetype":"venue"
},
  "geometry": {"coordinates":[-87.982561,43.12245],"type":"Point"}
}