{
  "type": "Feature",
  "properties": {
    "iso:country":"US",
    "sg:address":"288 College St",
    "sg:city":"Medford",
    "sg:classifiers":[
        {
            "category":"Social Services",
            "subcategory":"Adult Care",
            "type":"Services"
        }
    ],
    "sg:phone":"+1 715 748 9799",
    "sg:postcode":"54451",
    "sg:province":"WI",
    "sg:tags":[
        "residential"
    ],
    "wof:name":"Alternative Living Services",
    "wof:placetype":"venue"
},
  "geometry": {"coordinates":[-90.339268,45.129865],"type":"Point"}
}