{
  "type": "Feature",
  "properties": {
    "iso:country":"US",
    "sg:address":"800 Ash St",
    "sg:city":"Green Bay",
    "sg:classifiers":[
        {
            "category":"Wholesale",
            "subcategory":"Machinery & Supplies",
            "type":"Manufacturing & Wholesale Goods"
        }
    ],
    "sg:phone":"+1 920 434 2952",
    "sg:postcode":"54313",
    "sg:province":"WI",
    "sg:tags":[
        "salon",
        "beauty"
    ],
    "wof:name":"Sharpeez",
    "wof:placetype":"venue"
},
  "geometry": {"coordinates":[-88.088984,44.565604],"type":"Point"}
}