{
  "type": "Feature",
  "properties": {
    "iso:country":"US",
    "sg:address":"229 Williams St",
    "sg:city":"Pulaski",
    "sg:classifiers":[
        {
            "category":"Government",
            "subcategory":"Office",
            "type":"Public Place"
        }
    ],
    "sg:phone":"+1 920 822 8618",
    "sg:postcode":"54162",
    "sg:province":"WI",
    "sg:tags":[
        "govt",
        "city"
    ],
    "wof:name":"Pulaski Water & Sewer Dept",
    "wof:placetype":"venue"
},
  "geometry": {"coordinates":[-88.237684,44.670234],"type":"Point"}
}