{
  "type": "Feature",
  "properties": {
    "iso:country":"US",
    "sg:address":"3774 Granton Rd",
    "sg:city":"Granton",
    "sg:classifiers":[
        {
            "category":"Real Estate",
            "subcategory":"Real Estate Operator",
            "type":"Services"
        }
    ],
    "sg:phone":"+1 715 238 7781",
    "sg:postcode":"54436",
    "sg:province":"WI",
    "sg:tags":[
        "property",
        "lessor"
    ],
    "wof:name":"Dale Vine",
    "wof:placetype":"venue"
},
  "geometry": {"coordinates":[-90.513896,44.581986],"type":"Point"}
}