{
  "type": "Feature",
  "properties": {
    "iso:country":"US",
    "sg:address":"205 E Mill St",
    "sg:city":"Richland Center",
    "sg:classifiers":[
        {
            "category":"Government",
            "subcategory":"Fire Station",
            "type":"Public Place"
        }
    ],
    "sg:phone":"+1 608 647 4556",
    "sg:postcode":"53581",
    "sg:province":"WI",
    "sg:tags":[
        "department"
    ],
    "wof:name":"Richland Center Fire Station",
    "wof:placetype":"venue"
},
  "geometry": {"coordinates":[-90.384062,43.336364],"type":"Point"}
}