{
  "type": "Feature",
  "properties": {
    "iso:country":"US",
    "sg:address":"2500 N Mayfair Rd",
    "sg:city":"Milwaukee",
    "sg:classifiers":[
        {
            "category":"Shopping",
            "subcategory":"Clothing, Apparel, & Fashions",
            "type":"Retail Goods"
        }
    ],
    "sg:phone":"+1 414 476 2911",
    "sg:postcode":"53226",
    "sg:province":"WI",
    "sg:tags":[
        "men's",
        "women's",
        "apparel",
        "accessory",
        "clothing",
        "store"
    ],
    "sg:website":"http://www.bananarepublic.com",
    "wof:name":"Banana Republic",
    "wof:placetype":"venue"
},
  "geometry": {"coordinates":[-88.04764400000001,43.064602],"type":"Point"}
}