{
  "type": "Feature",
  "properties": {
    "addr:full":"9929 Co Rd Y Gordon WI 54838",
    "addr:housenumber":"9929",
    "addr:postcode":"54838",
    "addr:street":"Co Rd Y Gordon",
    "iso:country":"US",
    "sg:address":"9929 Co Rd Y",
    "sg:city":"Gordon",
    "sg:classifiers":[
        {
            "category":"Government",
            "subcategory":"Office",
            "type":"Public Place"
        }
    ],
    "sg:phone":"+1 715 376 2276",
    "sg:postcode":"54838",
    "sg:province":"WI",
    "sg:tags":[
        "village"
    ],
    "wof:name":"Gordon Town Garage",
    "wof:placetype":"venue"
},
  "geometry": {"coordinates":[-91.7799,46.248732],"type":"Point"}
}