{
  "type": "Feature",
  "properties": {
    "addr:full":"1604 Hagar St La Crosse WI 54603",
    "addr:housenumber":"1604",
    "addr:postcode":"54603",
    "addr:street":"Hagar St",
    "iso:country":"US",
    "sg:address":"1604 Hagar St",
    "sg:city":"La Crosse",
    "sg:classifiers":[
        {
            "category":"Autos & Motor Vehicles",
            "subcategory":"Boat Sales",
            "type":"Retail Goods"
        }
    ],
    "sg:phone":"+1 608 785 2669",
    "sg:postcode":"54603",
    "sg:province":"WI",
    "wof:name":"Bills Engineering",
    "wof:placetype":"venue"
},
  "geometry": {"coordinates":[-91.23268299999999,43.834677],"type":"Point"}
}