{
  "type": "Feature",
  "properties": {
    "addr:full":"8218 W Dixon St Milwaukee WI 53214",
    "addr:housenumber":"8218",
    "addr:postcode":"53214",
    "addr:street":"W Dixon St",
    "iso:country":"US",
    "sg:address":"8218 W Dixon St",
    "sg:city":"Milwaukee",
    "sg:classifiers":[
        {
            "category":"Professional",
            "subcategory":"Management & Consulting",
            "type":"Services"
        }
    ],
    "sg:phone":"+1 414 774 0264",
    "sg:postcode":"53214",
    "sg:province":"WI",
    "sg:tags":[
        "business"
    ],
    "wof:name":"Molstad Consulting",
    "wof:placetype":"venue"
},
  "geometry": {"coordinates":[-88.01584800000001,43.028729],"type":"Point"}
}