{
  "type": "Feature",
  "properties": {
    "iso:country":"US",
    "sg:address":"19540 W North Ave",
    "sg:city":"Brookfield",
    "sg:classifiers":[
        {
            "category":"Wholesale",
            "subcategory":"Vending Machines",
            "type":"Manufacturing & Wholesale Goods"
        }
    ],
    "sg:phone":"+1 262 797 9990",
    "sg:postcode":"53045",
    "sg:province":"WI",
    "wof:name":"American Vending Inc",
    "wof:placetype":"venue"
},
  "geometry": {"coordinates":[-88.156446,43.061468],"type":"Point"}
}