{
  "type": "Feature",
  "properties": {
    "iso:country":"US",
    "sg:address":"1128 Metron Ct",
    "sg:city":"Racine",
    "sg:classifiers":[
        {
            "category":"Building & Trades",
            "subcategory":"Cleaning & Sanitation",
            "type":"Services"
        }
    ],
    "sg:phone":"+1 262 637 7073",
    "sg:postcode":"53403",
    "sg:province":"WI",
    "sg:tags":[
        "house",
        "maintenance"
    ],
    "wof:name":"Mya's Housekeeping",
    "wof:placetype":"venue"
},
  "geometry": {"coordinates":[-87.796091,42.719275],"type":"Point"}
}