{
  "type": "Feature",
  "properties": {
    "iso:country":"US",
    "sg:address":"1141 S Main St",
    "sg:city":"River Falls",
    "sg:classifiers":[
        {
            "category":"Food & Beverages",
            "subcategory":"Liquor & Beverages",
            "type":"Retail Goods"
        }
    ],
    "sg:phone":"+1 715 425 2973",
    "sg:postcode":"54022",
    "sg:province":"WI",
    "wof:name":"Hometown Liquor Dick's Plus",
    "wof:placetype":"venue"
},
  "geometry": {"coordinates":[-92.629411,44.845894],"type":"Point"}
}