{
  "type": "Feature",
  "properties": {
    "iso:country":"US",
    "sg:address":"848 Arthur Dr",
    "sg:city":"Milton",
    "sg:classifiers":[
        {
            "category":"Banks & Credit Unions",
            "subcategory":"Investment Brokerage",
            "type":"Services"
        }
    ],
    "sg:phone":"+1 608 868 4273",
    "sg:postcode":"53563",
    "sg:province":"WI",
    "sg:tags":[
        "security"
    ],
    "wof:name":"Edward Jones 03820",
    "wof:placetype":"venue"
},
  "geometry": {"coordinates":[-88.93813,42.768401],"type":"Point"}
}