{
  "type": "Feature",
  "properties": {
    "iso:country":"US",
    "sg:address":"801 Main Ave",
    "sg:city":"Crivitz",
    "sg:classifiers":[
        {
            "category":"Retail",
            "subcategory":"Auto Repair",
            "type":"Services"
        }
    ],
    "sg:phone":"+1 715 854 7404",
    "sg:postcode":"54114",
    "sg:province":"WI",
    "sg:tags":[
        "body",
        "automobile",
        "painting"
    ],
    "sg:website":"www.wittauto.com",
    "wof:name":"WITT Ford Inc",
    "wof:placetype":"venue"
},
  "geometry": {"coordinates":[-88.009675,45.232395],"type":"Point"}
}