{
  "type": "Feature",
  "properties": {
    "iso:country":"US",
    "sg:address":"135 W Geneva St",
    "sg:city":"Elkhorn",
    "sg:classifiers":[
        {
            "category":"Building & Trades",
            "subcategory":"Construction",
            "type":"Services"
        }
    ],
    "sg:phone":"+1 262 723 1773",
    "sg:postcode":"53121",
    "sg:province":"WI",
    "sg:tags":[
        "siding",
        "contractor"
    ],
    "wof:name":"Amazing Siding Corp-Wi",
    "wof:placetype":"venue"
},
  "geometry": {"coordinates":[-88.545196,42.670198],"type":"Point"}
}