{
  "type": "Feature",
  "properties": {
    "iso:country":"US",
    "sg:address":"24101 31st St",
    "sg:city":"Salem",
    "sg:classifiers":[
        {
            "category":"Farming",
            "subcategory":"Dairy Farm",
            "type":"Manufacturing & Wholesale Goods"
        }
    ],
    "sg:phone":"+1 262 878 2696",
    "sg:postcode":"53168",
    "sg:province":"WI",
    "sg:tags":[
        "field",
        "crop"
    ],
    "wof:name":"Myron Daniels",
    "wof:placetype":"venue"
},
  "geometry": {"coordinates":[-88.108445,42.611857],"type":"Point"}
}