{
  "type": "Feature",
  "properties": {
    "addr:full":"1720 Humes Rd Janesville WI 53545",
    "addr:housenumber":"1720",
    "addr:postcode":"53545",
    "addr:street":"Humes Rd",
    "iso:country":"US",
    "sg:address":"1720 Humes Rd",
    "sg:city":"Janesville",
    "sg:classifiers":[
        {
            "category":"Wholesale",
            "subcategory":"Groceries",
            "type":"Manufacturing & Wholesale Goods"
        }
    ],
    "sg:phone":"+1 608 754 5541",
    "sg:postcode":"53545",
    "sg:province":"WI",
    "sg:tags":[
        "bakery",
        "retail"
    ],
    "wof:name":"Sara Lee Bakery Group Inc",
    "wof:placetype":"venue"
},
  "geometry": {"coordinates":[-89.003162,42.721889],"type":"Point"}
}