{
  "type": "Feature",
  "properties": {
    "iso:country":"US",
    "sg:address":"10034 Co Rd B",
    "sg:city":"Coleman",
    "sg:classifiers":[
        {
            "category":"Real Estate",
            "subcategory":"Real Estate Agent",
            "type":"Services"
        }
    ],
    "sg:phone":"+1 920 897 3754",
    "sg:postcode":"54112",
    "sg:province":"WI",
    "wof:name":"Rupiper Insurance Agcy & Rlty",
    "wof:placetype":"venue"
},
  "geometry": {"coordinates":[-88.160939,45.038114],"type":"Point"}
}