{
  "type": "Feature",
  "properties": {
    "iso:country":"US",
    "sg:address":"2000 State Hwy 78",
    "sg:city":"Mount Horeb",
    "sg:classifiers":[
        {
            "category":"Farming",
            "subcategory":"Farm",
            "type":"Manufacturing & Wholesale Goods"
        }
    ],
    "sg:phone":"+1 608 437 8260",
    "sg:postcode":"53572",
    "sg:province":"WI",
    "sg:tags":[
        "crop",
        "general"
    ],
    "wof:name":"Dennis Jelle",
    "wof:placetype":"venue"
},
  "geometry": {"coordinates":[-89.771576,42.963428],"type":"Point"}
}