{
  "type": "Feature",
  "properties": {
    "iso:country":"US",
    "sg:address":"107 Adams St",
    "sg:city":"Boscobel",
    "sg:classifiers":[
        {
            "category":"Building & Trades",
            "subcategory":"Plumbing",
            "type":"Services"
        }
    ],
    "sg:phone":"+1 608 375 5338",
    "sg:postcode":"53805",
    "sg:province":"WI",
    "sg:tags":[
        "conditioning",
        "contractor",
        "electrical",
        "system",
        "air"
    ],
    "wof:name":"Fischer Electric Heating & Air",
    "wof:placetype":"venue"
},
  "geometry": {"coordinates":[-90.705676,43.131182],"type":"Point"}
}