{
  "type": "Feature",
  "properties": {
    "iso:country":"US",
    "sg:address":"1639 Deckner Ave",
    "sg:city":"Green Bay",
    "sg:classifiers":[
        {
            "category":"Personal",
            "subcategory":"Beauty Salon",
            "type":"Services"
        },
        {
            "category":"Personal",
            "subcategory":"Barber",
            "type":"Services"
        }
    ],
    "sg:phone":"+1 920 468 9732",
    "sg:postcode":"54302",
    "sg:province":"WI",
    "sg:tags":[
        "shop"
    ],
    "wof:name":"Royal Hair Designs",
    "wof:placetype":"venue"
},
  "geometry": {"coordinates":[-87.98338699999999,44.502444],"type":"Point"}
}