{
  "type": "Feature",
  "properties": {
    "iso:country":"US",
    "sg:address":"224 Thayer St",
    "sg:city":"Rhinelander",
    "sg:classifiers":[
        {
            "category":"Retail",
            "subcategory":"Laundry & Dry Cleaning",
            "type":"Services"
        }
    ],
    "sg:phone":"+1 715 369 1212",
    "sg:postcode":"54501",
    "sg:province":"WI",
    "sg:tags":[
        "cleaners"
    ],
    "wof:name":"City Cleaners & Laundry Inc",
    "wof:placetype":"venue"
},
  "geometry": {"coordinates":[-89.415521,45.640984],"type":"Point"}
}