{
  "type": "Feature",
  "properties": {
    "addr:full":"5016 Puls Rd Shiocton WI 54170",
    "addr:housenumber":"5016",
    "addr:postcode":"54170",
    "addr:street":"Puls Rd",
    "iso:country":"US",
    "sg:address":"5016 Puls Rd",
    "sg:city":"Shiocton",
    "sg:classifiers":[
        {
            "category":"Professional",
            "type":"Services"
        }
    ],
    "sg:phone":"+1 920 986 3230",
    "sg:postcode":"54170",
    "sg:province":"WI",
    "wof:name":"Bruce Kosmerchock",
    "wof:placetype":"venue"
},
  "geometry": {"coordinates":[-88.535803,44.430332],"type":"Point"}
}