{
  "type": "Feature",
  "properties": {
    "iso:country":"US",
    "sg:address":"11090 Badger Rd",
    "sg:city":"Spring Green",
    "sg:classifiers":[
        {
            "category":"Farming",
            "subcategory":"Dairy Farm",
            "type":"Manufacturing & Wholesale Goods"
        }
    ],
    "sg:phone":"+1 608 544 3375",
    "sg:postcode":"53588",
    "sg:province":"WI",
    "wof:name":"Steven Sorg",
    "wof:placetype":"venue"
},
  "geometry": {"coordinates":[-89.929218,43.243376],"type":"Point"}
}