{
  "type": "Feature",
  "properties": {
    "iso:country":"US",
    "sg:address":"1432 Milwaukee Ave",
    "sg:city":"South Milwaukee",
    "sg:classifiers":[
        {
            "category":"Restaurant",
            "type":"Food & Drink"
        }
    ],
    "sg:phone":"+1 414 764 4948",
    "sg:postcode":"53172",
    "sg:province":"WI",
    "sg:tags":[
        "eating"
    ],
    "wof:name":"James G Hartley",
    "wof:placetype":"venue"
},
  "geometry": {"coordinates":[-87.870398,42.910977],"type":"Point"}
}