{
  "type": "Feature",
  "properties": {
    "iso:country":"US",
    "sg:address":"2004 Greenway Cross",
    "sg:city":"Fitchburg",
    "sg:classifiers":[
        {
            "category":"Personal",
            "subcategory":"Adult",
            "type":"Services"
        }
    ],
    "sg:phone":"+1 608 442 1561",
    "sg:postcode":"53713",
    "sg:province":"WI",
    "sg:tags":[
        "escort"
    ],
    "wof:name":"Intimate Encounters",
    "wof:placetype":"venue"
},
  "geometry": {"coordinates":[-89.41621000000001,43.030943],"type":"Point"}
}