{
  "type": "Feature",
  "properties": {
    "iso:country":"US",
    "sg:address":"7188 Patchin Rd",
    "sg:city":"Pardeeville",
    "sg:classifiers":[
        {
            "category":"Retail",
            "subcategory":"Auto Repair",
            "type":"Services"
        }
    ],
    "sg:phone":"+1 608 429 3080",
    "sg:postcode":"53954",
    "sg:province":"WI",
    "sg:tags":[
        "body",
        "automobile",
        "painting"
    ],
    "wof:name":"Steve's Body & Repair",
    "wof:placetype":"venue"
},
  "geometry": {"coordinates":[-89.350902,43.477304],"type":"Point"}
}