{
  "type": "Feature",
  "properties": {
    "iso:country":"US",
    "sg:address":"1194 River Dr",
    "sg:city":"River Falls",
    "sg:classifiers":[
        {
            "category":"Travel",
            "subcategory":"Hotels & Motels",
            "type":"Entertainment"
        }
    ],
    "sg:phone":"+1 715 425 1449",
    "sg:postcode":"54022",
    "sg:province":"WI",
    "sg:tags":[
        "operation"
    ],
    "wof:name":"Apple River Inn Inc",
    "wof:placetype":"venue"
},
  "geometry": {"coordinates":[-92.55923,44.89484],"type":"Point"}
}