{
  "type": "Feature",
  "properties": {
    "iso:country":"US",
    "sg:address":"2670 E Main St",
    "sg:city":"Reedsburg",
    "sg:classifiers":[
        {
            "category":"Professional",
            "subcategory":"Computer Services",
            "type":"Services"
        }
    ],
    "sg:phone":"+1 608 524 2610",
    "sg:postcode":"53959",
    "sg:province":"WI",
    "sg:tags":[
        "consultant",
        "designer"
    ],
    "wof:name":"Computer Connections",
    "wof:placetype":"venue"
},
  "geometry": {"coordinates":[-89.967204,43.532642],"type":"Point"}
}