{
  "type": "Feature",
  "properties": {
    "iso:country":"US",
    "sg:address":"3003 Superior Ave",
    "sg:city":"Sheboygan",
    "sg:classifiers":[
        {
            "category":"Health Services",
            "subcategory":"Doctor",
            "type":"Services"
        }
    ],
    "sg:phone":"+1 920 452 9953",
    "sg:postcode":"53081",
    "sg:province":"WI",
    "sg:tags":[
        "dentist"
    ],
    "wof:name":"George L Hess III DDS",
    "wof:placetype":"venue"
},
  "geometry": {"coordinates":[-87.747122,43.761051],"type":"Point"}
}