{
  "type": "Feature",
  "properties": {
    "iso:country":"US",
    "sg:address":"201 E Albert St",
    "sg:city":"Portage",
    "sg:classifiers":[
        {
            "category":"Retail",
            "subcategory":"Car Wash",
            "type":"Services"
        }
    ],
    "sg:phone":"+1 608 745 0779",
    "sg:postcode":"53901",
    "sg:province":"WI",
    "sg:tags":[
        "carwash"
    ],
    "wof:name":"Detail Works",
    "wof:placetype":"venue"
},
  "geometry": {"coordinates":[-89.461884,43.548633],"type":"Point"}
}