{
  "type": "Feature",
  "properties": {
    "addr:full":"7259 N 76th St Milwaukee WI 53223",
    "addr:housenumber":"7259",
    "addr:postcode":"53223",
    "addr:street":"N 76Th St",
    "iso:country":"US",
    "sg:address":"7259 N 76th St",
    "sg:city":"Milwaukee",
    "sg:classifiers":[
        {
            "category":"Wholesale",
            "subcategory":"Auto Parts",
            "type":"Manufacturing & Wholesale Goods"
        }
    ],
    "sg:phone":"+1 414 760 8860",
    "sg:postcode":"53223",
    "sg:province":"WI",
    "wof:name":"NAPA Auto Parts",
    "wof:placetype":"venue"
},
  "geometry": {"coordinates":[-88.005353,43.150657],"type":"Point"}
}