{
  "type": "Feature",
  "properties": {
    "iso:country":"US",
    "sg:address":"2659 17th St",
    "sg:city":"Rice Lake",
    "sg:classifiers":[
        {
            "category":"Professional",
            "type":"Services"
        }
    ],
    "sg:phone":"+1 715 537 9093",
    "sg:postcode":"54868",
    "sg:province":"WI",
    "wof:name":"Brent D Hanson",
    "wof:placetype":"venue"
},
  "geometry": {"coordinates":[-91.806544,45.587473],"type":"Point"}
}