{
  "type": "Feature",
  "properties": {
    "iso:country":"US",
    "sg:address":"8087 Wall Rd",
    "sg:city":"Armstrong Creek",
    "sg:classifiers":[
        {
            "category":"Building & Trades",
            "subcategory":"Construction",
            "type":"Services"
        }
    ],
    "sg:phone":"+1 715 336 2035",
    "sg:postcode":"54103",
    "sg:province":"WI",
    "sg:tags":[
        "house"
    ],
    "wof:name":"Timberdick Const",
    "wof:placetype":"venue"
},
  "geometry": {"coordinates":[-88.48750800000001,45.65997],"type":"Point"}
}