{
  "type": "Feature",
  "properties": {
    "iso:country":"US",
    "sg:address":"1020 N 12th St",
    "sg:city":"Milwaukee",
    "sg:classifiers":[
        {
            "category":"Health Services",
            "subcategory":"Doctor",
            "type":"Services"
        },
        {
            "category":"Health Services",
            "subcategory":"Clinic",
            "type":"Services"
        },
        {
            "category":"Health Services",
            "subcategory":"Hospital",
            "type":"Services"
        }
    ],
    "sg:phone":"+1 414 219 5219",
    "sg:postcode":"53233",
    "sg:province":"WI",
    "sg:tags":[
        "physician",
        "oncology",
        "pediatrics",
        "cardiology",
        "gynecology",
        "surgeons",
        "urgent",
        "neurology",
        "obstetrics",
        "surgeon",
        "care"
    ],
    "sg:website":"http://www.aurorahealthcare.com",
    "wof:name":"Aurora Sinai Family Care Center",
    "wof:placetype":"venue"
},
  "geometry": {"coordinates":[-87.927159,43.043452],"type":"Point"}
}