{
  "type": "Feature",
  "properties": {
    "iso:country":"US",
    "sg:address":"1414 W Bradley Rd",
    "sg:city":"Milwaukee",
    "sg:classifiers":[
        {
            "category":"Organizations",
            "subcategory":"Religious Organization",
            "type":"Services"
        }
    ],
    "sg:phone":"+1 414 357 6277",
    "sg:postcode":"53217",
    "sg:province":"WI",
    "sg:tags":[
        "membership"
    ],
    "wof:name":"Salvation Army Thrift Store 8",
    "wof:placetype":"venue"
},
  "geometry": {"coordinates":[-87.926801,43.1625],"type":"Point"}
}