{
  "type": "Feature",
  "properties": {
    "iso:country":"US",
    "sg:address":"8104 Barker Lake Rd",
    "sg:city":"Winter",
    "sg:classifiers":[
        {
            "category":"Travel",
            "subcategory":"Campground",
            "type":"Entertainment"
        }
    ],
    "sg:phone":"+1 715 266 3263",
    "sg:postcode":"54896",
    "sg:province":"WI",
    "sg:tags":[
        "camp"
    ],
    "sg:website":"www.campwehakee.com",
    "wof:name":"Camp We-Ha-Kee",
    "wof:placetype":"venue"
},
  "geometry": {"coordinates":[-91.013214,45.916554],"type":"Point"}
}