{
  "type": "Feature",
  "properties": {
    "addr:full":"928 Main St Onalaska WI 54650",
    "addr:housenumber":"928",
    "addr:postcode":"54650",
    "addr:street":"Main St",
    "iso:country":"US",
    "sg:address":"928 Main St",
    "sg:city":"Onalaska",
    "sg:classifiers":[
        {
            "category":"Shopping",
            "type":"Retail Goods"
        }
    ],
    "sg:phone":"+1 608 781 8088",
    "sg:postcode":"54650",
    "sg:province":"WI",
    "sg:tags":[
        "plumbing",
        "b",
        "merchandise"
    ],
    "wof:name":"Affordable Water Conditioning",
    "wof:placetype":"venue"
},
  "geometry": {"coordinates":[-91.22474,43.884275],"type":"Point"}
}