{
  "type": "Feature",
  "properties": {
    "iso:country":"US",
    "sg:address":"13327 Pine Rd",
    "sg:city":"Suring",
    "sg:classifiers":[
        {
            "category":"Building & Trades",
            "subcategory":"Construction",
            "type":"Services"
        }
    ],
    "sg:phone":"+1 920 842 4231",
    "sg:postcode":"54174",
    "sg:province":"WI",
    "sg:tags":[
        "mfg",
        "prefabricated",
        "wood",
        "house"
    ],
    "wof:name":"Frontier Log Homes Inc",
    "wof:placetype":"venue"
},
  "geometry": {"coordinates":[-88.435416,44.964099],"type":"Point"}
}