{
  "type": "Feature",
  "properties": {
    "iso:country":"US",
    "sg:address":"2750 Killarney Ct",
    "sg:city":"Oshkosh",
    "sg:classifiers":[
        {
            "category":"Retail",
            "subcategory":"Repair Shop",
            "type":"Services"
        }
    ],
    "sg:phone":"+1 920 235 9020",
    "sg:postcode":"54904",
    "sg:province":"WI",
    "sg:tags":[
        "repairing",
        "piano",
        "refinishing"
    ],
    "wof:name":"Stratz's Pianos Svc",
    "wof:placetype":"venue"
},
  "geometry": {"coordinates":[-88.602674,44.005599],"type":"Point"}
}