{
  "type": "Feature",
  "properties": {
    "iso:country":"US",
    "sg:address":"3200 Larsen Rd",
    "sg:city":"Madison",
    "sg:classifiers":[
        {
            "category":"Banks & Credit Unions",
            "subcategory":"Financial Services",
            "type":"Services"
        }
    ],
    "sg:phone":"+1 608 224 1600",
    "sg:postcode":"53711",
    "sg:province":"WI",
    "sg:tags":[
        "investor"
    ],
    "wof:name":"Rosewood Investments LLC",
    "wof:placetype":"venue"
},
  "geometry": {"coordinates":[-89.365131,43.020391],"type":"Point"}
}