{
  "type": "Feature",
  "properties": {
    "iso:country":"US",
    "sg:address":"228 Morris St",
    "sg:city":"Holmen",
    "sg:classifiers":[
        {
            "category":"Organizations",
            "subcategory":"Religious Organization",
            "type":"Services"
        }
    ],
    "sg:phone":"+1 608 526 3621",
    "sg:postcode":"54636",
    "sg:province":"WI",
    "sg:tags":[
        "church"
    ],
    "sg:website":"www.holmenlutheranchurch.org",
    "wof:name":"Holmen Lutheran Church",
    "wof:placetype":"venue"
},
  "geometry": {"coordinates":[-91.257733,43.966589],"type":"Point"}
}