{
  "type": "Feature",
  "properties": {
    "iso:country":"US",
    "sg:address":"333 S Westfield Rd",
    "sg:city":"Madison",
    "sg:classifiers":[
        {
            "category":"Banks & Credit Unions",
            "subcategory":"Bank",
            "type":"Services"
        }
    ],
    "sg:phone":"+1 608 829 2270",
    "sg:postcode":"53717",
    "sg:province":"WI",
    "sg:website":"www.anchorbank.com",
    "wof:name":"Anchor Bank",
    "wof:placetype":"venue"
},
  "geometry": {"coordinates":[-89.507719,43.063924],"type":"Point"}
}