{
  "type": "Feature",
  "properties": {
    "iso:country":"US",
    "sg:address":"909 W Layton Ave",
    "sg:city":"Milwaukee",
    "sg:classifiers":[
        {
            "category":"Restaurant",
            "type":"Food & Drink"
        }
    ],
    "sg:phone":"+1 414 769 1300",
    "sg:postcode":"53221",
    "sg:province":"WI",
    "wof:name":"Prime Quarter Steak House",
    "wof:placetype":"venue"
},
  "geometry": {"coordinates":[-87.922489,42.959152],"type":"Point"}
}