{
  "type": "Feature",
  "properties": {
    "iso:country":"US",
    "sg:address":"8037 Co Rd B",
    "sg:city":"Amherst",
    "sg:classifiers":[
        {
            "category":"Building & Trades",
            "subcategory":"Construction",
            "type":"Services"
        }
    ],
    "sg:phone":"+1 715 824 5772",
    "sg:postcode":"54406",
    "sg:province":"WI",
    "wof:name":"River Valley Electrical Cnstr",
    "wof:placetype":"venue"
},
  "geometry": {"coordinates":[-89.384532,44.448371],"type":"Point"}
}