{
  "type": "Feature",
  "properties": {
    "iso:country":"US",
    "sg:address":"4138 W Cemetery Rd",
    "sg:city":"Janesville",
    "sg:classifiers":[
        {
            "category":"Organizations",
            "subcategory":"Religious Organization",
            "type":"Services"
        }
    ],
    "sg:phone":"+1 608 755 5707",
    "sg:postcode":"53548",
    "sg:province":"WI",
    "sg:tags":[
        "church"
    ],
    "wof:name":"Harvesters Church-Rock County",
    "wof:placetype":"venue"
},
  "geometry": {"coordinates":[-89.079437,42.620995],"type":"Point"}
}