{
  "type": "Feature",
  "properties": {
    "iso:country":"US",
    "sg:address":"3807 State Hwy 80",
    "sg:city":"Platteville",
    "sg:classifiers":[
        {
            "category":"Professional",
            "type":"Services"
        }
    ],
    "sg:phone":"+1 608 348 3385",
    "sg:postcode":"53818",
    "sg:province":"WI",
    "wof:name":"Vosberg Boumatic LLC",
    "wof:placetype":"venue"
},
  "geometry": {"coordinates":[-90.435738,42.642886],"type":"Point"}
}