{
  "type": "Feature",
  "properties": {
    "addr:full":"6018 Achterberg Rd Winneconne WI 54986",
    "addr:postcode":"6018;54986",
    "addr:street":"Achterberg Rd",
    "iso:country":"US",
    "sg:address":"6018 Achterberg Rd",
    "sg:city":"Winneconne",
    "sg:classifiers":[
        {
            "category":"Manufacturing",
            "subcategory":"Printing",
            "type":"Manufacturing & Wholesale Goods"
        }
    ],
    "sg:phone":"+1 920 582 4299",
    "sg:postcode":"54986",
    "sg:province":"WI",
    "sg:tags":[
        "engraving"
    ],
    "wof:name":"Hanco Engravers",
    "wof:placetype":"venue"
},
  "geometry": {"coordinates":[-88.733572,44.111567],"type":"Point"}
}