{
  "type": "Feature",
  "properties": {
    "iso:country":"US",
    "sg:address":"1741 Baker Dr",
    "sg:city":"Wisconsin Rapids",
    "sg:classifiers":[
        {
            "category":"Retail",
            "subcategory":"Auto Repair",
            "type":"Services"
        }
    ],
    "sg:phone":"+1 715 421 5220",
    "sg:postcode":"54494",
    "sg:province":"WI",
    "sg:tags":[
        "repairing",
        "automobile"
    ],
    "wof:name":"Dwayne's Service Ctr",
    "wof:placetype":"venue"
},
  "geometry": {"coordinates":[-89.80477500000001,44.393503],"type":"Point"}
}