{
  "type": "Feature",
  "properties": {
    "iso:country":"US",
    "sg:address":"1225 E Gorham St",
    "sg:city":"Madison",
    "sg:classifiers":[
        {
            "category":"Manufacturing",
            "subcategory":"Food",
            "type":"Manufacturing & Wholesale Goods"
        }
    ],
    "sg:phone":"+1 608 257 4423",
    "sg:postcode":"53703",
    "sg:province":"WI",
    "sg:tags":[
        "product",
        "manufacturer"
    ],
    "wof:name":"Samosawala",
    "wof:placetype":"venue"
},
  "geometry": {"coordinates":[-89.369723,43.089243],"type":"Point"}
}