{
  "type": "Feature",
  "properties": {
    "addr:full":"7181 Spring Brook Rd Green Lake WI 54941",
    "addr:housenumber":"7181",
    "addr:postcode":"54941",
    "addr:street":"Spring Brook Rd",
    "iso:country":"US",
    "sg:address":"7181 Spring Brook Rd",
    "sg:city":"Green Lake",
    "sg:classifiers":[
        {
            "category":"Shopping",
            "subcategory":"Computers & Home Electronics",
            "type":"Retail Goods"
        }
    ],
    "sg:phone":"+1 920 294 3443",
    "sg:postcode":"54941",
    "sg:province":"WI",
    "wof:name":"Fox River Valley Computers",
    "wof:placetype":"venue"
},
  "geometry": {"coordinates":[-88.956461,43.893258],"type":"Point"}
}