{
  "type": "Feature",
  "properties": {
    "iso:country":"US",
    "sg:address":"1301 Gateway Ct",
    "sg:city":"Hudson",
    "sg:classifiers":[
        {
            "category":"Retail",
            "subcategory":"Auto Repair",
            "type":"Services"
        }
    ],
    "sg:phone":"+1 715 377 2155",
    "sg:postcode":"54016",
    "sg:province":"WI",
    "sg:tags":[
        "van",
        "conversion",
        "truck",
        "accessory"
    ],
    "wof:name":"Midwest Truck & Auto Accssrs",
    "wof:placetype":"venue"
},
  "geometry": {"coordinates":[-92.723236,44.959332],"type":"Point"}
}