{
  "type": "Feature",
  "properties": {
    "iso:country":"US",
    "sg:address":"5341 W Forest Home Ave",
    "sg:city":"Milwaukee",
    "sg:classifiers":[
        {
            "category":"Shopping",
            "subcategory":"Clothing, Apparel, & Fashions",
            "type":"Retail Goods"
        }
    ],
    "sg:phone":"+1 414 321 8826",
    "sg:postcode":"53220",
    "sg:province":"WI",
    "sg:tags":[
        "alterations-clothing"
    ],
    "wof:name":"Consentino Alterations",
    "wof:placetype":"venue"
},
  "geometry": {"coordinates":[-87.98154599999999,42.980663],"type":"Point"}
}