{
  "type": "Feature",
  "properties": {
    "iso:country":"US",
    "sg:address":"7481 E Dover Rd",
    "sg:city":"Phillips",
    "sg:classifiers":[
        {
            "category":"Shopping",
            "subcategory":"Hobbies, Toys, & Games",
            "type":"Retail Goods"
        }
    ],
    "sg:phone":"+1 715 339 6463",
    "sg:postcode":"54555",
    "sg:province":"WI",
    "wof:name":"Chastain Fmly Floral & Crafts",
    "wof:placetype":"venue"
},
  "geometry": {"coordinates":[-90.187321,45.655874],"type":"Point"}
}