{
  "type": "Feature",
  "properties": {
    "iso:country":"US",
    "sg:address":"1325 Appleton Rd",
    "sg:city":"Menasha",
    "sg:classifiers":[
        {
            "category":"Autos & Motor Vehicles",
            "subcategory":"Auto Supplies",
            "type":"Retail Goods"
        }
    ],
    "sg:phone":"+1 920 720 8909",
    "sg:postcode":"54952",
    "sg:province":"WI",
    "sg:website":"www.autozone.com",
    "wof:name":"Autozone",
    "wof:placetype":"venue"
},
  "geometry": {"coordinates":[-88.424409,44.226033],"type":"Point"}
}