{
  "type": "Feature",
  "properties": {
    "iso:country":"US",
    "sg:address":"1054 E Commerce Blvd",
    "sg:city":"Slinger",
    "sg:classifiers":[
        {
            "category":"Shopping",
            "subcategory":"Pharmacy",
            "type":"Retail Goods"
        }
    ],
    "sg:phone":"+1 262 644 5246",
    "sg:postcode":"53086",
    "sg:province":"WI",
    "wof:name":"Aurora Pharmacy",
    "wof:placetype":"venue"
},
  "geometry": {"coordinates":[-88.27913100000001,43.324036],"type":"Point"}
}