{
  "type": "Feature",
  "properties": {
    "iso:country":"US",
    "sg:address":"4035 Co Hwy Z",
    "sg:city":"Fredonia",
    "sg:classifiers":[
        {
            "category":"Shopping",
            "subcategory":"Used Merchandise",
            "type":"Retail Goods"
        }
    ],
    "sg:phone":"+1 262 692 2200",
    "sg:postcode":"53021",
    "sg:province":"WI",
    "sg:tags":[
        "shop",
        "consignment"
    ],
    "wof:name":"Diane's This & That",
    "wof:placetype":"venue"
},
  "geometry": {"coordinates":[-87.985235,43.477474],"type":"Point"}
}