{
  "type": "Feature",
  "properties": {
    "addr:full":"3820 52nd St Kenosha WI 53144",
    "addr:housenumber":"3820",
    "addr:postcode":"53144",
    "addr:street":"52Nd St",
    "iso:country":"US",
    "sg:address":"3820 52nd St",
    "sg:city":"Kenosha",
    "sg:classifiers":[
        {
            "category":"Shopping",
            "subcategory":"Pharmacy",
            "type":"Retail Goods"
        }
    ],
    "sg:phone":"+1 262 652 9662",
    "sg:postcode":"53144",
    "sg:province":"WI",
    "wof:name":"Walgreens",
    "wof:placetype":"venue"
},
  "geometry": {"coordinates":[-87.85550600000001,42.588404],"type":"Point"}
}