{
  "type": "Feature",
  "properties": {
    "iso:country":"US",
    "sg:address":"1003 E Potter Ave",
    "sg:city":"Milwaukee",
    "sg:classifiers":[
        {
            "category":"Wholesale",
            "subcategory":"Poultry",
            "type":"Manufacturing & Wholesale Goods"
        },
        {
            "category":"Farming",
            "subcategory":"Livestock Farm",
            "type":"Manufacturing & Wholesale Goods"
        }
    ],
    "sg:phone":"+1 414 747 9298",
    "sg:postcode":"53207",
    "sg:province":"WI",
    "sg:tags":[
        "auction",
        "market"
    ],
    "wof:name":"The Roaming Goat",
    "wof:placetype":"venue"
},
  "geometry": {"coordinates":[-87.89671300000001,42.997119],"type":"Point"}
}