{
  "type": "Feature",
  "properties": {
    "addr:full":"3201 S Lake Dr Milwaukee WI 53235",
    "addr:housenumber":"3201",
    "addr:postcode":"53235",
    "addr:street":"S Lake Dr",
    "iso:country":"US",
    "sg:address":"3201 S Lake Dr",
    "sg:city":"Milwaukee",
    "sg:classifiers":[
        {
            "category":"Real Estate",
            "subcategory":"Real Estate Operator",
            "type":"Services"
        }
    ],
    "sg:phone":"+1 414 744 9959",
    "sg:postcode":"53235",
    "sg:province":"WI",
    "sg:tags":[
        "building",
        "apartment"
    ],
    "wof:name":"Canticle Court Apartments",
    "wof:placetype":"venue"
},
  "geometry": {"coordinates":[-87.860345,42.978588],"type":"Point"}
}