{
  "type": "Feature",
  "properties": {
    "iso:country":"US",
    "sg:address":"1058 N 2nd St",
    "sg:city":"Medford",
    "sg:classifiers":[
        {
            "category":"Building & Trades",
            "subcategory":"Landscaping Services",
            "type":"Services"
        }
    ],
    "sg:phone":"+1 715 748 5941",
    "sg:postcode":"54451",
    "sg:province":"WI",
    "sg:tags":[
        "tree"
    ],
    "wof:name":"Brunner Lake Tree Removal",
    "wof:placetype":"venue"
},
  "geometry": {"coordinates":[-90.350457,45.150332],"type":"Point"}
}