{
  "type": "Feature",
  "properties": {
    "iso:country":"US",
    "sg:address":"5585 State Hwy 70",
    "sg:city":"Spooner",
    "sg:classifiers":[
        {
            "category":"Personal",
            "subcategory":"Beauty Salon",
            "type":"Services"
        }
    ],
    "sg:phone":"+1 715 635 8544",
    "sg:postcode":"54801",
    "sg:province":"WI",
    "sg:tags":[
        "shop"
    ],
    "wof:name":"Country Aire Hair Design",
    "wof:placetype":"venue"
},
  "geometry": {"coordinates":[-91.812836,45.814023],"type":"Point"}
}