{
  "type": "Feature",
  "properties": {
    "iso:country":"US",
    "sg:address":"1895 Cold Spring Rd",
    "sg:city":"Saukville",
    "sg:classifiers":[
        {
            "category":"Building & Trades",
            "subcategory":"Construction",
            "type":"Services"
        }
    ],
    "sg:phone":"+1 262 284 3317",
    "sg:postcode":"53080",
    "sg:province":"WI",
    "sg:tags":[
        "house",
        "residential"
    ],
    "wof:name":"Schreiner Construction",
    "wof:placetype":"venue"
},
  "geometry": {"coordinates":[-87.954196,43.396823],"type":"Point"}
}