{
  "type": "Feature",
  "properties": {
    "iso:country":"US",
    "sg:address":"1000 Grandview Dr",
    "sg:city":"Elm Grove",
    "sg:classifiers":[
        {
            "category":"Professional",
            "subcategory":"Engineering",
            "type":"Services"
        }
    ],
    "sg:phone":"+1 262 782 0410",
    "sg:postcode":"53122",
    "sg:province":"WI",
    "sg:tags":[
        "engineer"
    ],
    "wof:name":"Russ Henke Assoc",
    "wof:placetype":"venue"
},
  "geometry": {"coordinates":[-88.09045999999999,43.043583],"type":"Point"}
}