{
  "type": "Feature",
  "properties": {
    "iso:country":"US",
    "sg:address":"5066 Radloff Rd",
    "sg:city":"Cecil",
    "sg:classifiers":[
        {
            "category":"Farming",
            "subcategory":"Dairy Farm",
            "type":"Manufacturing & Wholesale Goods"
        }
    ],
    "sg:phone":"+1 715 745 6329",
    "sg:postcode":"54111",
    "sg:province":"WI",
    "wof:name":"Donald Radloff",
    "wof:placetype":"venue"
},
  "geometry": {"coordinates":[-88.417096,44.780142],"type":"Point"}
}