{
  "type": "Feature",
  "properties": {
    "iso:country":"US",
    "sg:address":"1925 US Hwy 51",
    "sg:city":"Stoughton",
    "sg:classifiers":[
        {
            "category":"Building & Trades",
            "subcategory":"Construction",
            "type":"Services"
        }
    ],
    "sg:phone":"+1 608 873 4272",
    "sg:postcode":"53589",
    "sg:province":"WI",
    "sg:tags":[
        "acoustical",
        "contractor"
    ],
    "sg:website":"www.universal-silencer.com",
    "wof:name":"Universal Silencer Inc",
    "wof:placetype":"venue"
},
  "geometry": {"coordinates":[-89.235398,42.917936],"type":"Point"}
}