{
  "type": "Feature",
  "properties": {
    "addr:full":"910 State St Marinette WI 54143",
    "addr:housenumber":"910",
    "addr:postcode":"54143",
    "addr:street":"State St",
    "iso:country":"US",
    "sg:address":"910 State St",
    "sg:city":"Marinette",
    "sg:classifiers":[
        {
            "category":"Manufacturing",
            "subcategory":"Pottery",
            "type":"Manufacturing & Wholesale Goods"
        }
    ],
    "sg:phone":"+1 715 732 2771",
    "sg:postcode":"54143",
    "sg:province":"WI",
    "sg:tags":[
        "article",
        "fine",
        "earthenware"
    ],
    "wof:name":"Decor Porcelain Co",
    "wof:placetype":"venue"
},
  "geometry": {"coordinates":[-87.63879,45.097311],"type":"Point"}
}