{
  "type": "Feature",
  "properties": {
    "iso:country":"US",
    "sg:address":"419 E Taft Ave",
    "sg:city":"Appleton",
    "sg:classifiers":[
        {
            "category":"Manufacturing",
            "subcategory":"Printing",
            "type":"Manufacturing & Wholesale Goods"
        }
    ],
    "sg:phone":"+1 920 734 6693",
    "sg:postcode":"54915",
    "sg:province":"WI",
    "sg:tags":[
        "book"
    ],
    "wof:name":"Ceareter Building For Family",
    "wof:placetype":"venue"
},
  "geometry": {"coordinates":[-88.39824,44.239706],"type":"Point"}
}