{
  "type": "Feature",
  "properties": {
    "iso:country":"US",
    "sg:address":"454 E Church Rd",
    "sg:city":"Cambridge",
    "sg:classifiers":[
        {
            "category":"Organizations",
            "subcategory":"Religious Organization",
            "type":"Services"
        }
    ],
    "sg:phone":"+1 608 423 3017",
    "sg:postcode":"53523",
    "sg:province":"WI",
    "sg:tags":[
        "church"
    ],
    "wof:name":"East Koshkonong CHURCH-Elca",
    "wof:placetype":"venue"
},
  "geometry": {"coordinates":[-89.04887600000001,42.952823],"type":"Point"}
}