{
  "type": "Feature",
  "properties": {
    "iso:country":"US",
    "sg:address":"4849 W Jefferson Rd",
    "sg:city":"Chilton",
    "sg:phone":"+1 920 849 4293",
    "sg:postcode":"53014",
    "sg:province":"WI",
    "sg:tags":[
        "farm",
        "corn"
    ],
    "wof:name":"Don Schaefer",
    "wof:placetype":"venue"
},
  "geometry": {"coordinates":[-88.28119700000001,43.98788],"type":"Point"}
}