{
  "type": "Feature",
  "properties": {
    "addr:full":"3355 S 27th St Milwaukee WI 53215",
    "addr:housenumber":"3355",
    "addr:postcode":"53215",
    "addr:street":"S 27Th St",
    "iso:country":"US",
    "sg:address":"3355 S 27th St",
    "sg:city":"Milwaukee",
    "sg:classifiers":[
        {
            "category":"Professional",
            "subcategory":"Accounting & Tax Preparation",
            "type":"Services"
        }
    ],
    "sg:phone":"+1 414 384 4588",
    "sg:postcode":"53215",
    "sg:province":"WI",
    "sg:tags":[
        "return",
        "filing"
    ],
    "wof:name":"H & R Block Tax Svc",
    "wof:placetype":"venue"
},
  "geometry": {"coordinates":[-87.94838799999999,42.984131],"type":"Point"}
}