{
  "type": "Feature",
  "properties": {
    "addr:full":"131 S Barstow St Eau Claire WI 54701",
    "addr:housenumber":"131",
    "addr:postcode":"54701",
    "addr:street":"S Barstow St",
    "iso:country":"US",
    "sg:address":"131 S Barstow St",
    "sg:city":"Eau Claire",
    "sg:classifiers":[
        {
            "category":"Banks & Credit Unions",
            "subcategory":"Bank",
            "type":"Services"
        }
    ],
    "sg:phone":"+1 715 839 7766",
    "sg:postcode":"54701",
    "sg:province":"WI",
    "sg:tags":[
        "mortgage"
    ],
    "wof:name":"US Bank Mortgage",
    "wof:placetype":"venue"
},
  "geometry": {"coordinates":[-91.500191,44.811849],"type":"Point"}
}