{
  "type": "Feature",
  "properties": {
    "iso:country":"US",
    "sg:address":"4351 Hideaway Hollow",
    "sg:city":"Racine",
    "sg:classifiers":[
        {
            "category":"Shopping",
            "subcategory":"Used Merchandise",
            "type":"Retail Goods"
        }
    ],
    "sg:phone":"+1 262 554 7015",
    "sg:postcode":"53403",
    "sg:province":"WI",
    "sg:tags":[
        "wear"
    ],
    "wof:name":"Childrens Cupboard",
    "wof:placetype":"venue"
},
  "geometry": {"coordinates":[-87.840042,42.681148],"type":"Point"}
}