{
  "type": "Feature",
  "properties": {
    "addr:full":"5684 N Centerpark Way Milwaukee WI 53217",
    "addr:housenumber":"5684",
    "addr:postcode":"53217",
    "addr:street":"N Centerpark Way",
    "iso:country":"US",
    "sg:address":"5684 N Centerpark Way",
    "sg:city":"Milwaukee",
    "sg:classifiers":[
        {
            "category":"Shopping",
            "subcategory":"Optical Goods",
            "type":"Retail Goods"
        },
        {
            "category":"Shopping",
            "subcategory":"Optician",
            "type":"Retail Goods"
        }
    ],
    "sg:phone":"+1 414 962 2021",
    "sg:postcode":"53217",
    "sg:province":"WI",
    "sg:tags":[
        "repair",
        "eyeglass"
    ],
    "sg:website":"http://www.lenscrafters.com/",
    "wof:name":"Lenscrafters",
    "wof:placetype":"venue"
},
  "geometry": {"coordinates":[-87.91506800000001,43.120592],"type":"Point"}
}