{
  "type": "Feature",
  "properties": {
    "addr:full":"1830 Wisconsin Dells Pkwy N Wisconsin Dells WI 53965",
    "addr:housenumber":"1830",
    "addr:postcode":"53965",
    "addr:street":"Wisconsin Dells Pkwy N",
    "iso:country":"US",
    "sg:address":"1830 Wisconsin Dells Pkwy N",
    "sg:city":"Wisconsin Dells",
    "sg:classifiers":[
        {
            "category":"Recreation",
            "type":"Entertainment"
        }
    ],
    "sg:phone":"+1 608 253 7170",
    "sg:postcode":"53965",
    "sg:province":"WI",
    "wof:name":"Adare Go Carts",
    "wof:placetype":"venue"
},
  "geometry": {"coordinates":[-89.789467,43.612993],"type":"Point"}
}