{
  "type": "Feature",
  "properties": {
    "iso:country":"US",
    "sg:address":"4695 138th St",
    "sg:city":"Chippewa Falls",
    "sg:classifiers":[
        {
            "category":"Bars & Pubs",
            "type":"Food & Drink"
        }
    ],
    "sg:phone":"+1 715 720 9281",
    "sg:postcode":"54729",
    "sg:province":"WI",
    "sg:tags":[
        "drinking"
    ],
    "wof:name":"West Hill Bar",
    "wof:placetype":"venue"
},
  "geometry": {"coordinates":[-91.39131500000001,44.911662],"type":"Point"}
}