{
  "type": "Feature",
  "properties": {
    "iso:country":"US",
    "sg:address":"6468 Maplewood Rd",
    "sg:city":"Sturgeon Bay",
    "sg:classifiers":[
        {
            "category":"Farming",
            "subcategory":"Dairy Farm",
            "type":"Manufacturing & Wholesale Goods"
        }
    ],
    "sg:phone":"+1 920 743 1125",
    "sg:postcode":"54235",
    "sg:province":"WI",
    "wof:name":"Gigstad Farms",
    "wof:placetype":"venue"
},
  "geometry": {"coordinates":[-87.413481,44.733758],"type":"Point"}
}