{
  "type": "Feature",
  "properties": {
    "iso:country":"US",
    "sg:address":"2981 Triverton Pike Dr",
    "sg:city":"Fitchburg",
    "sg:classifiers":[
        {
            "category":"Insurance",
            "subcategory":"Insurance Agent",
            "type":"Services"
        }
    ],
    "sg:phone":"+1 608 274 7120",
    "sg:postcode":"53711",
    "sg:province":"WI",
    "wof:name":"State Farm Insurance",
    "wof:placetype":"venue"
},
  "geometry": {"coordinates":[-89.429723,43.017674],"type":"Point"}
}