{
  "type": "Feature",
  "properties": {
    "addr:full":"620 N 12th Ave Sturgeon Bay WI 54235",
    "addr:housenumber":"620",
    "addr:postcode":"54235",
    "addr:street":"N 12Th Ave",
    "iso:country":"US",
    "sg:address":"620 N 12th Ave",
    "sg:city":"Sturgeon Bay",
    "sg:classifiers":[
        {
            "category":"Health Services",
            "subcategory":"Hospital",
            "type":"Services"
        }
    ],
    "sg:phone":"+1 920 743 9554",
    "sg:postcode":"54235",
    "sg:province":"WI",
    "sg:tags":[
        "mental"
    ],
    "wof:name":"Counseling Associates",
    "wof:placetype":"venue"
},
  "geometry": {"coordinates":[-87.364338,44.844456],"type":"Point"}
}