{
  "type": "Feature",
  "properties": {
    "addr:full":"272 Vine St West Bend WI 53095",
    "addr:housenumber":"272",
    "addr:postcode":"53095",
    "addr:street":"Vine St",
    "iso:country":"US",
    "sg:address":"272 Vine St",
    "sg:city":"West Bend",
    "sg:classifiers":[
        {
            "category":"Professional",
            "type":"Services"
        }
    ],
    "sg:phone":"+1 262 306 1954",
    "sg:postcode":"53095",
    "sg:province":"WI",
    "wof:name":"Beth Vogts Designs LLC",
    "wof:placetype":"venue"
},
  "geometry": {"coordinates":[-88.177865,43.404877],"type":"Point"}
}