{
  "type": "Feature",
  "properties": {
    "iso:country":"US",
    "sg:address":"1716 S Hycrest Dr",
    "sg:city":"Appleton",
    "sg:classifiers":[
        {
            "category":"Social Services",
            "type":"Services"
        }
    ],
    "sg:phone":"+1 920 735 1025",
    "sg:postcode":"54914",
    "sg:province":"WI",
    "sg:tags":[
        "organization",
        "welfare"
    ],
    "wof:name":"P Flag",
    "wof:placetype":"venue"
},
  "geometry": {"coordinates":[-88.429339,44.247188],"type":"Point"}
}