{
  "type": "Feature",
  "properties": {
    "iso:country":"US",
    "sg:address":"36 W Yew St",
    "sg:city":"Sturgeon Bay",
    "sg:classifiers":[
        {
            "category":"Manufacturing",
            "subcategory":"Tools & Machinery",
            "type":"Manufacturing & Wholesale Goods"
        }
    ],
    "sg:phone":"+1 920 743 8575",
    "sg:postcode":"54235",
    "sg:province":"WI",
    "sg:tags":[
        "machine",
        "shop"
    ],
    "wof:name":"N E W Industries Inc",
    "wof:placetype":"venue"
},
  "geometry": {"coordinates":[-87.38534799999999,44.817039],"type":"Point"}
}