{
  "type": "Feature",
  "properties": {
    "iso:country":"US",
    "sg:address":"6031 W National Ave",
    "sg:city":"Milwaukee",
    "sg:classifiers":[
        {
            "category":"Social Services",
            "type":"Services"
        }
    ],
    "sg:phone":"+1 414 258 6640",
    "sg:postcode":"53214",
    "sg:province":"WI",
    "wof:name":"Bethany Christian Services",
    "wof:placetype":"venue"
},
  "geometry": {"coordinates":[-87.98833399999999,43.017203],"type":"Point"}
}