{
  "type": "Feature",
  "properties": {
    "iso:country":"US",
    "sg:address":"30422 Mountain Ln",
    "sg:city":"Waterford",
    "sg:classifiers":[
        {
            "category":"Retail",
            "subcategory":"Repair Shop",
            "type":"Services"
        }
    ],
    "sg:phone":"+1 262 514 3811",
    "sg:postcode":"53185",
    "sg:province":"WI",
    "sg:tags":[
        "television",
        "radio-service"
    ],
    "wof:name":"Vintage Auto Radio",
    "wof:placetype":"venue"
},
  "geometry": {"coordinates":[-88.21539300000001,42.770757],"type":"Point"}
}