{
  "type": "Feature",
  "properties": {
    "iso:country":"US",
    "sg:address":"460 Broad St",
    "sg:city":"Oshkosh",
    "sg:classifiers":[
        {
            "category":"Building & Trades",
            "subcategory":"Construction",
            "type":"Services"
        }
    ],
    "sg:phone":"+1 920 426 2386",
    "sg:postcode":"54901",
    "sg:province":"WI",
    "sg:tags":[
        "painter",
        "contractor"
    ],
    "wof:name":"Davis Painting & Decorating",
    "wof:placetype":"venue"
},
  "geometry": {"coordinates":[-88.531368,44.019641],"type":"Point"}
}