{
  "type": "Feature",
  "properties": {
    "iso:country":"US",
    "sg:address":"8801 W Brown Deer Rd",
    "sg:city":"Milwaukee",
    "sg:classifiers":[
        {
            "category":"Home & Garden",
            "subcategory":"Garden Supply",
            "type":"Retail Goods"
        }
    ],
    "sg:phone":"+1 414 362 7878",
    "sg:postcode":"53224",
    "sg:province":"WI",
    "sg:tags":[
        "bamboo",
        "product"
    ],
    "wof:name":"Stein Garden & Gifts",
    "wof:placetype":"venue"
},
  "geometry": {"coordinates":[-88.020229,43.177671],"type":"Point"}
}