{
  "type": "Feature",
  "properties": {
    "iso:country":"US",
    "sg:address":"43378 Dull Rd",
    "sg:city":"Soldiers Grove",
    "sg:classifiers":[
        {
            "category":"Farming",
            "subcategory":"Dairy Farm",
            "type":"Manufacturing & Wholesale Goods"
        }
    ],
    "sg:phone":"+1 608 624 3487",
    "sg:postcode":"54655",
    "sg:province":"WI",
    "wof:name":"Roger Copus",
    "wof:placetype":"venue"
},
  "geometry": {"coordinates":[-90.753032,43.39468],"type":"Point"}
}