{
  "type": "Feature",
  "properties": {
    "addr:full":"2900 S Main St Rice Lake WI 54868",
    "addr:housenumber":"2900",
    "addr:postcode":"54868",
    "addr:street":"S Main St",
    "iso:country":"US",
    "sg:address":"2900 S Main St",
    "sg:city":"Rice Lake",
    "sg:classifiers":[
        {
            "category":"Shopping",
            "subcategory":"Shoes",
            "type":"Retail Goods"
        }
    ],
    "sg:phone":"+1 715 234 9727",
    "sg:postcode":"54868",
    "sg:province":"WI",
    "wof:name":"Tradehome Shoes 39",
    "wof:placetype":"venue"
},
  "geometry": {"coordinates":[-91.735208,45.472985],"type":"Point"}
}