{
  "type": "Feature",
  "properties": {
    "iso:country":"US",
    "sg:address":"230 Reservoir Ave",
    "sg:city":"Wausau",
    "sg:classifiers":[
        {
            "category":"Organizations",
            "subcategory":"Professional Association",
            "type":"Services"
        }
    ],
    "sg:phone":"+1 715 842 9510",
    "sg:postcode":"54401",
    "sg:province":"WI",
    "sg:tags":[
        "business"
    ],
    "wof:name":"Wausau Area Builders Assoc",
    "wof:placetype":"venue"
},
  "geometry": {"coordinates":[-89.649311,44.966066],"type":"Point"}
}