{
  "type": "Feature",
  "properties": {
    "iso:country":"US",
    "sg:address":"1123 3rd St S",
    "sg:city":"La Crosse",
    "sg:classifiers":[
        {
            "category":"Bars & Pubs",
            "type":"Food & Drink"
        }
    ],
    "sg:phone":"+1 608 784 8541",
    "sg:postcode":"54601",
    "sg:province":"WI",
    "wof:name":"Kramer's Bar & Grill",
    "wof:placetype":"venue"
},
  "geometry": {"coordinates":[-91.253423,43.801769],"type":"Point"}
}