{
  "type": "Feature",
  "properties": {
    "iso:country":"US",
    "sg:address":"1746 Executive Dr",
    "sg:city":"Oconomowoc",
    "sg:classifiers":[
        {
            "category":"Government",
            "subcategory":"Office",
            "type":"Public Place"
        }
    ],
    "sg:phone":"+1 262 567 5520",
    "sg:postcode":"53066",
    "sg:province":"WI",
    "sg:tags":[
        "village"
    ],
    "wof:name":"Homes For Independent Living",
    "wof:placetype":"venue"
},
  "geometry": {"coordinates":[-88.478534,43.073946],"type":"Point"}
}