{
  "type": "Feature",
  "properties": {
    "addr:full":"422 Technology Dr E Menomonie WI 54751",
    "addr:housenumber":"422",
    "addr:postcode":"54751",
    "addr:street":"Technology Dr E",
    "iso:country":"US",
    "sg:address":"422 Technology Dr E",
    "sg:city":"Menomonie",
    "sg:classifiers":[
        {
            "category":"Manufacturing",
            "subcategory":"Metals",
            "type":"Manufacturing & Wholesale Goods"
        }
    ],
    "sg:phone":"+1 715 233 4000",
    "sg:postcode":"54751",
    "sg:province":"WI",
    "wof:name":"Phillips Plastics Corp",
    "wof:placetype":"venue"
},
  "geometry": {"coordinates":[-91.89189500000001,44.881209],"type":"Point"}
}