{
  "type": "Feature",
  "properties": {
    "iso:country":"US",
    "sg:address":"1285 Morgan Dr",
    "sg:city":"Hubertus",
    "sg:classifiers":[
        {
            "category":"Retail",
            "subcategory":"Auto Repair",
            "type":"Services"
        }
    ],
    "sg:phone":"+1 262 628 2806",
    "sg:postcode":"53033",
    "sg:province":"WI",
    "sg:tags":[
        "general"
    ],
    "wof:name":"Hillside Service",
    "wof:placetype":"venue"
},
  "geometry": {"coordinates":[-88.190597,43.235996],"type":"Point"}
}