{
  "type": "Feature",
  "properties": {
    "addr:full":"150 S Sunny Slope Rd Brookfield WI 53005",
    "addr:housenumber":"150",
    "addr:postcode":"53005",
    "addr:street":"S Sunny Slope Rd",
    "iso:country":"US",
    "sg:address":"150 S Sunny Slope Rd",
    "sg:city":"Brookfield",
    "sg:classifiers":[
        {
            "category":"Professional",
            "subcategory":"Advertising",
            "type":"Services"
        }
    ],
    "sg:phone":"+1 262 789 8481",
    "sg:postcode":"53005",
    "sg:province":"WI",
    "sg:tags":[
        "agency"
    ],
    "wof:name":"Stephenson & Assoc",
    "wof:placetype":"venue"
},
  "geometry": {"coordinates":[-88.086833,43.030849],"type":"Point"}
}