{
  "type": "Feature",
  "properties": {
    "iso:country":"US",
    "sg:address":"13524 Clement Rd",
    "sg:city":"Saxon",
    "sg:classifiers":[
        {
            "category":"Farming",
            "subcategory":"Dairy Farm",
            "type":"Manufacturing & Wholesale Goods"
        }
    ],
    "sg:phone":"+1 715 893 2284",
    "sg:postcode":"54559",
    "sg:province":"WI",
    "wof:name":"Springcreek Farms",
    "wof:placetype":"venue"
},
  "geometry": {"coordinates":[-90.4473,46.470829],"type":"Point"}
}