{
  "type": "Feature",
  "properties": {
    "addr:full":"1901 Durand Ave Racine WI 53403",
    "addr:housenumber":"1901",
    "addr:postcode":"53403",
    "addr:street":"Durand Ave",
    "iso:country":"US",
    "sg:address":"1901 Durand Ave",
    "sg:city":"Racine",
    "sg:classifiers":[
        {
            "category":"Manufacturing",
            "subcategory":"Food",
            "type":"Manufacturing & Wholesale Goods"
        }
    ],
    "sg:phone":"+1 262 634 2164",
    "sg:postcode":"53403",
    "sg:province":"WI",
    "sg:tags":[
        "frozen",
        "processor"
    ],
    "wof:name":"Day Foods",
    "wof:placetype":"venue"
},
  "geometry": {"coordinates":[-87.80371100000001,42.697001],"type":"Point"}
}