{
  "type": "Feature",
  "properties": {
    "addr:full":"2155 Gross St Green Bay WI 54304",
    "addr:housenumber":"2155",
    "addr:postcode":"54304",
    "addr:street":"Gross St",
    "iso:country":"US",
    "sg:address":"2155 Gross St",
    "sg:city":"Green Bay",
    "sg:classifiers":[
        {
            "category":"Utilities",
            "subcategory":"Water",
            "type":"Services"
        }
    ],
    "sg:phone":"+1 920 492 2335",
    "sg:postcode":"54304",
    "sg:province":"WI",
    "sg:tags":[
        "supply"
    ],
    "wof:name":"Ashwaubenon Water Sewer",
    "wof:placetype":"venue"
},
  "geometry": {"coordinates":[-88.05730200000001,44.492579],"type":"Point"}
}