{
  "type": "Feature",
  "properties": {
    "iso:country":"US",
    "sg:address":"2222 N 45th St",
    "sg:city":"Milwaukee",
    "sg:classifiers":[
        {
            "category":"Personal",
            "subcategory":"Beauty Salon",
            "type":"Services"
        }
    ],
    "sg:phone":"+1 414 444 4007",
    "sg:postcode":"53208",
    "sg:province":"WI",
    "wof:name":"Johnson Hair Salon",
    "wof:placetype":"venue"
},
  "geometry": {"coordinates":[-87.969992,43.060315],"type":"Point"}
}