{
  "type": "Feature",
  "properties": {
    "iso:country":"US",
    "sg:address":"139 W Wilson St",
    "sg:city":"Madison",
    "sg:classifiers":[
        {
            "category":"Food & Beverages",
            "subcategory":"Groceries & Convenience Stores",
            "type":"Retail Goods"
        }
    ],
    "sg:phone":"+1 608 258 1800",
    "sg:postcode":"53703",
    "sg:province":"WI",
    "wof:name":"Hees Petroleum Corp",
    "wof:placetype":"venue"
},
  "geometry": {"coordinates":[-89.384007,43.07064],"type":"Point"}
}