{
  "type": "Feature",
  "properties": {
    "iso:country":"US",
    "sg:address":"2700 Clark St",
    "sg:city":"Stevens Point",
    "sg:classifiers":[
        {
            "category":"Retail",
            "subcategory":"Repair Shop",
            "type":"Services"
        }
    ],
    "sg:phone":"+1 715 342 1548",
    "sg:postcode":"54481",
    "sg:province":"WI",
    "sg:tags":[
        "tanner"
    ],
    "wof:name":"Martin's Taxidermy",
    "wof:placetype":"venue"
},
  "geometry": {"coordinates":[-89.559831,44.522428],"type":"Point"}
}