{
  "type": "Feature",
  "properties": {
    "addr:full":"20 N Allen St Madison WI 53726",
    "addr:housenumber":"20",
    "addr:postcode":"53726",
    "addr:street":"N Allen St",
    "iso:country":"US",
    "sg:address":"20 N Allen St",
    "sg:city":"Madison",
    "sg:classifiers":[
        {
            "category":"Professional",
            "subcategory":"Business Services",
            "type":"Services"
        }
    ],
    "sg:phone":"+1 608 218 9001",
    "sg:postcode":"53726",
    "sg:province":"WI",
    "wof:name":"Stratagem Group Inc",
    "wof:placetype":"venue"
},
  "geometry": {"coordinates":[-89.42385400000001,43.068004],"type":"Point"}
}