{
  "type": "Feature",
  "properties": {
    "iso:country":"US",
    "sg:address":"4105 S Kirkwood Ave",
    "sg:city":"Milwaukee",
    "sg:classifiers":[
        {
            "category":"Wholesale",
            "subcategory":"Metals & Minerals",
            "type":"Manufacturing & Wholesale Goods"
        }
    ],
    "sg:phone":"+1 414 481 7782",
    "sg:postcode":"53235",
    "sg:province":"WI",
    "sg:tags":[
        "aluminum"
    ],
    "wof:name":"Mc Clory Metal Svc Inc",
    "wof:placetype":"venue"
},
  "geometry": {"coordinates":[-87.857657,42.970245],"type":"Point"}
}