{
  "type": "Feature",
  "properties": {
    "iso:country":"US",
    "sg:address":"16 E Main St",
    "sg:city":"Waupun",
    "sg:classifiers":[
        {
            "category":"Government",
            "subcategory":"Police Station",
            "type":"Public Place"
        }
    ],
    "sg:phone":"+1 920 324 7911",
    "sg:postcode":"53963",
    "sg:province":"WI",
    "sg:tags":[
        "department"
    ],
    "wof:name":"Waupun Police Dept",
    "wof:placetype":"venue"
},
  "geometry": {"coordinates":[-88.734264,43.63323],"type":"Point"}
}