{
  "type": "Feature",
  "properties": {
    "iso:country":"US",
    "sg:address":"3129 State Hwy 149",
    "sg:city":"Malone",
    "sg:classifiers":[
        {
            "category":"Farming",
            "subcategory":"Dairy Farm",
            "type":"Manufacturing & Wholesale Goods"
        }
    ],
    "sg:phone":"+1 920 795 1368",
    "sg:postcode":"53049",
    "sg:province":"WI",
    "wof:name":"Petrie John",
    "wof:placetype":"venue"
},
  "geometry": {"coordinates":[-88.31855299999999,43.833812],"type":"Point"}
}