{
  "type": "Feature",
  "properties": {
    "iso:country":"US",
    "sg:address":"314 W Main St",
    "sg:city":"Watertown",
    "sg:classifiers":[
        {
            "category":"Insurance",
            "subcategory":"Insurance Agent",
            "type":"Services"
        }
    ],
    "sg:phone":"+1 920 261 7676",
    "sg:postcode":"53094",
    "sg:province":"WI",
    "wof:name":"Gr Zastrow & Associates",
    "wof:placetype":"venue"
},
  "geometry": {"coordinates":[-88.72839,43.194847],"type":"Point"}
}