{
  "type": "Feature",
  "properties": {
    "iso:country":"US",
    "sg:address":"1005 Cypress Ct",
    "sg:city":"Hartland",
    "sg:classifiers":[
        {
            "category":"Professional",
            "subcategory":"Management & Consulting",
            "type":"Services"
        }
    ],
    "sg:phone":"+1 262 367 5889",
    "sg:postcode":"53029",
    "sg:province":"WI",
    "wof:name":"Wax Solutions",
    "wof:placetype":"venue"
},
  "geometry": {"coordinates":[-88.318344,43.118743],"type":"Point"}
}