{
  "type": "Feature",
  "properties": {
    "addr:full":"1010 N Bird St Sun Prairie WI 53590",
    "addr:housenumber":"1010",
    "addr:postcode":"53590",
    "addr:street":"N Bird St",
    "iso:country":"US",
    "sg:address":"1010 N Bird St",
    "sg:city":"Sun Prairie",
    "sg:classifiers":[
        {
            "category":"Personal",
            "subcategory":"Beauty Salon",
            "type":"Services"
        }
    ],
    "sg:phone":"+1 608 837 4300",
    "sg:postcode":"53590",
    "sg:province":"WI",
    "sg:tags":[
        "shop"
    ],
    "wof:name":"Hair Excellence",
    "wof:placetype":"venue"
},
  "geometry": {"coordinates":[-89.22594599999999,43.191948],"type":"Point"}
}