{
  "type": "Feature",
  "properties": {
    "iso:country":"US",
    "sg:address":"1924 14th St S",
    "sg:city":"La Crosse",
    "sg:classifiers":[
        {
            "category":"Building & Trades",
            "subcategory":"Construction",
            "type":"Services"
        }
    ],
    "sg:phone":"+1 608 779 9677",
    "sg:postcode":"54601",
    "sg:province":"WI",
    "sg:tags":[
        "general",
        "contractor"
    ],
    "wof:name":"River Valley Contractors Inc",
    "wof:placetype":"venue"
},
  "geometry": {"coordinates":[-91.23603199999999,43.791688],"type":"Point"}
}