{
  "type": "Feature",
  "properties": {
    "iso:country":"US",
    "sg:address":"1005 S 60th St",
    "sg:city":"Milwaukee",
    "sg:classifiers":[
        {
            "category":"Shopping",
            "subcategory":"Used Merchandise",
            "type":"Retail Goods"
        }
    ],
    "sg:phone":"+1 414 771 1958",
    "sg:postcode":"53214",
    "sg:province":"WI",
    "wof:name":"Gallery of Antiques",
    "wof:placetype":"venue"
},
  "geometry": {"coordinates":[-87.98755199999999,43.020087],"type":"Point"}
}