{
  "type": "Feature",
  "properties": {
    "addr:full":"6401 University Ave Middleton WI 53562",
    "addr:housenumber":"6401",
    "addr:postcode":"53562",
    "addr:street":"University Ave",
    "iso:country":"US",
    "sg:address":"6401 University Ave",
    "sg:city":"Middleton",
    "sg:classifiers":[
        {
            "category":"Restaurant",
            "type":"Food & Drink"
        }
    ],
    "sg:menulink":"http://www.allmenus.com/wi/middleton/19309-crandalls-carryout--catering/menu/",
    "sg:phone":"+1 608 231 2000",
    "sg:postcode":"53562",
    "sg:province":"WI",
    "sg:tags":[
        "american",
        "sandwich",
        "salad"
    ],
    "wof:name":"Crandall's Carryout & Catering",
    "wof:placetype":"venue"
},
  "geometry": {"coordinates":[-89.49142500000001,43.093357],"type":"Point"}
}