{
  "type": "Feature",
  "properties": {
    "iso:country":"US",
    "sg:address":"1720 Marvin Ct",
    "sg:city":"Sheboygan",
    "sg:classifiers":[
        {
            "category":"Building & Trades",
            "subcategory":"Landscaping Services",
            "type":"Services"
        }
    ],
    "sg:phone":"+1 920 452 5897",
    "sg:postcode":"53081",
    "sg:province":"WI",
    "wof:name":"Brians Lawn Service",
    "wof:placetype":"venue"
},
  "geometry": {"coordinates":[-87.72953099999999,43.736764],"type":"Point"}
}