{
  "type": "Feature",
  "properties": {
    "iso:country":"US",
    "sg:address":"333 Washington Dr",
    "sg:city":"West Bend",
    "sg:classifiers":[
        {
            "category":"Government",
            "subcategory":"Office",
            "type":"Public Place"
        }
    ],
    "sg:phone":"+1 262 335 4600",
    "sg:postcode":"53095",
    "sg:province":"WI",
    "sg:website":"www.co.washington.wi.us",
    "wof:name":"Washington County Treatment",
    "wof:placetype":"venue"
},
  "geometry": {"coordinates":[-88.048602,43.374387],"type":"Point"}
}