{
  "type": "Feature",
  "properties": {
    "iso:country":"US",
    "sg:address":"206 Lake St",
    "sg:city":"Pepin",
    "sg:classifiers":[
        {
            "category":"Bars & Pubs",
            "type":"Food & Drink"
        }
    ],
    "sg:phone":"+1 715 442 3451",
    "sg:postcode":"54759",
    "sg:province":"WI",
    "wof:name":"Ralph's",
    "wof:placetype":"venue"
},
  "geometry": {"coordinates":[-92.147746,44.441022],"type":"Point"}
}