{
  "type": "Feature",
  "properties": {
    "iso:country":"US",
    "sg:address":"20555 Co Rd G",
    "sg:city":"Dodge",
    "sg:classifiers":[
        {
            "category":"Organizations",
            "subcategory":"Religious Organization",
            "type":"Services"
        }
    ],
    "sg:phone":"+1 608 539 3704",
    "sg:postcode":"54612",
    "sg:province":"WI",
    "sg:tags":[
        "church"
    ],
    "wof:name":"Sacred Heart Parish",
    "wof:placetype":"venue"
},
  "geometry": {"coordinates":[-91.52135,44.134578],"type":"Point"}
}