{
  "type": "Feature",
  "properties": {
    "addr:full":"1895 Wood Run Pl Onalaska WI 54650",
    "addr:housenumber":"1895",
    "addr:postcode":"54650",
    "addr:street":"Wood Run Pl",
    "iso:country":"US",
    "sg:address":"1895 Wood Run Pl",
    "sg:city":"Onalaska",
    "sg:classifiers":[
        {
            "category":"Building & Trades",
            "subcategory":"Construction",
            "type":"Services"
        }
    ],
    "sg:phone":"+1 608 783 4242",
    "sg:postcode":"54650",
    "sg:province":"WI",
    "sg:tags":[
        "home",
        "builder"
    ],
    "wof:name":"Gorman Construction Inc",
    "wof:placetype":"venue"
},
  "geometry": {"coordinates":[-91.206957,43.892727],"type":"Point"}
}