{
  "type": "Feature",
  "properties": {
    "addr:full":"1720 Broadway St N Menomonie WI 54751",
    "addr:housenumber":"1720",
    "addr:postcode":"54751",
    "addr:street":"Broadway St N",
    "iso:country":"US",
    "sg:address":"1720 Broadway St N",
    "sg:city":"Menomonie",
    "sg:classifiers":[
        {
            "category":"Bakery",
            "type":"Food & Drink"
        }
    ],
    "sg:menulink":"http://www.allmenus.com/wi/menomonie/102363-perkins-restaurant--bakery/menu/",
    "sg:phone":"+1 715 235 2234",
    "sg:postcode":"54751",
    "sg:province":"WI",
    "sg:tags":[
        "sandwich",
        "salad",
        "soup",
        "american",
        "pastry",
        "wrap"
    ],
    "wof:name":"Perkins Restaurant & Bakery",
    "wof:placetype":"venue"
},
  "geometry": {"coordinates":[-91.93198700000001,44.902258],"type":"Point"}
}