{
  "type": "Feature",
  "properties": {
    "addr:full":"7525 Beaver Lake Rd Oconto Falls WI 54154",
    "addr:housenumber":"7525",
    "addr:postcode":"54154",
    "addr:street":"Beaver Lake Rd",
    "iso:country":"US",
    "sg:address":"7525 Beaver Lake Rd",
    "sg:city":"Oconto Falls",
    "sg:classifiers":[
        {
            "category":"Building & Trades",
            "subcategory":"Construction",
            "type":"Services"
        }
    ],
    "sg:phone":"+1 920 373 1967",
    "sg:postcode":"54154",
    "sg:province":"WI",
    "sg:tags":[
        "house"
    ],
    "wof:name":"Apple Creek Construction",
    "wof:placetype":"venue"
},
  "geometry": {"coordinates":[-88.15398500000001,44.922711],"type":"Point"}
}