{
  "type": "Feature",
  "properties": {
    "addr:full":"324 Poeppel Rd Fort Atkinson WI 53538",
    "addr:housenumber":"324",
    "addr:postcode":"53538",
    "addr:street":"Poeppel Rd",
    "iso:country":"US",
    "sg:address":"324 Poeppel Rd",
    "sg:city":"Fort Atkinson",
    "sg:classifiers":[
        {
            "category":"Autos & Motor Vehicles",
            "subcategory":"Fuel & Gas Station",
            "type":"Retail Goods"
        }
    ],
    "sg:phone":"+1 920 563 0937",
    "sg:postcode":"53538",
    "sg:province":"WI",
    "sg:tags":[
        "station",
        "gasoline"
    ],
    "wof:name":"L & K Properties of Wisconsin",
    "wof:placetype":"venue"
},
  "geometry": {"coordinates":[-88.865976,42.855746],"type":"Point"}
}