{
  "type": "Feature",
  "properties": {
    "iso:country":"US",
    "sg:address":"6354 W Silver Spring Dr",
    "sg:city":"Milwaukee",
    "sg:classifiers":[
        {
            "category":"Food & Beverages",
            "subcategory":"Groceries & Convenience Stores",
            "type":"Retail Goods"
        }
    ],
    "sg:phone":"+1 414 535 0774",
    "sg:postcode":"53218",
    "sg:province":"WI",
    "wof:name":"S S Fashion",
    "wof:placetype":"venue"
},
  "geometry": {"coordinates":[-87.989379,43.119446],"type":"Point"}
}