{
  "type": "Feature",
  "properties": {
    "addr:full":"2506 Roosevelt Rd Marinette WI 54143",
    "addr:housenumber":"2506",
    "addr:postcode":"54143",
    "addr:street":"Roosevelt Rd",
    "iso:country":"US",
    "sg:address":"2506 Roosevelt Rd",
    "sg:city":"Marinette",
    "sg:classifiers":[
        {
            "category":"Shopping",
            "subcategory":"Clothing, Apparel, & Fashions",
            "type":"Retail Goods"
        }
    ],
    "sg:phone":"+1 715 735 5630",
    "sg:postcode":"54143",
    "sg:province":"WI",
    "sg:tags":[
        "item",
        "boutique"
    ],
    "wof:name":"Claire's Boutique",
    "wof:placetype":"venue"
},
  "geometry": {"coordinates":[-87.65782900000001,45.052115],"type":"Point"}
}