{
  "type": "Feature",
  "properties": {
    "addr:full":"2954 Sandalwood Rd Abrams WI 54101",
    "addr:housenumber":"2954",
    "addr:postcode":"54101",
    "addr:street":"Sandalwood Rd",
    "iso:country":"US",
    "sg:address":"2954 Sandalwood Rd",
    "sg:city":"Abrams",
    "sg:classifiers":[
        {
            "category":"Restaurant",
            "type":"Food & Drink"
        }
    ],
    "sg:phone":"+1 920 826 7770",
    "sg:postcode":"54101",
    "sg:province":"WI",
    "sg:tags":[
        "club",
        "course",
        "golf",
        "supper"
    ],
    "wof:name":"Sandalwood Country Club",
    "wof:placetype":"venue"
},
  "geometry": {"coordinates":[-88.090642,44.78248],"type":"Point"}
}