{
  "type": "Feature",
  "properties": {
    "iso:country":"US",
    "sg:address":"525 Pine St",
    "sg:city":"Hartford",
    "sg:classifiers":[
        {
            "category":"Retail",
            "subcategory":"Auto Repair",
            "type":"Services"
        }
    ],
    "sg:phone":"+1 262 673 0477",
    "sg:postcode":"53027",
    "sg:province":"WI",
    "sg:tags":[
        "general"
    ],
    "wof:name":"Reliable Truck & Auto",
    "wof:placetype":"venue"
},
  "geometry": {"coordinates":[-88.389718,43.325052],"type":"Point"}
}