{
  "type": "Feature",
  "properties": {
    "addr:full":"1306 Kensington Ave Oshkosh WI 54902",
    "addr:housenumber":"1306",
    "addr:postcode":"54902",
    "addr:street":"Kensington Ave",
    "iso:country":"US",
    "sg:address":"1306 Kensington Ave",
    "sg:city":"Oshkosh",
    "sg:classifiers":[
        {
            "category":"Food & Beverages",
            "subcategory":"Meat & Fish",
            "type":"Retail Goods"
        }
    ],
    "sg:phone":"+1 920 231 1189",
    "sg:postcode":"54902",
    "sg:province":"WI",
    "wof:name":"B & D Meats LLC",
    "wof:placetype":"venue"
},
  "geometry": {"coordinates":[-88.57130600000001,44.007988],"type":"Point"}
}