{
  "type": "Feature",
  "properties": {
    "addr:full":"3004 Abbe Ct Eau Claire WI 54703",
    "addr:housenumber":"3004",
    "addr:postcode":"54703",
    "addr:street":"Abbe Ct",
    "iso:country":"US",
    "sg:address":"3004 Abbe Ct",
    "sg:city":"Eau Claire",
    "sg:classifiers":[
        {
            "category":"Insurance",
            "subcategory":"Insurance Agent",
            "type":"Services"
        }
    ],
    "sg:phone":"+1 715 835 0966",
    "sg:postcode":"54703",
    "sg:province":"WI",
    "wof:name":"Independent Insurance Services",
    "wof:placetype":"venue"
},
  "geometry": {"coordinates":[-91.46736300000001,44.84311],"type":"Point"}
}