{
  "type": "Feature",
  "properties": {
    "iso:country":"US",
    "sg:address":"416 S 7th St",
    "sg:city":"Delavan",
    "sg:classifiers":[
        {
            "category":"Retail",
            "subcategory":"Auto Repair",
            "type":"Services"
        }
    ],
    "sg:phone":"+1 262 728 8920",
    "sg:postcode":"53115",
    "sg:province":"WI",
    "sg:tags":[
        "automobile",
        "lubrication"
    ],
    "wof:name":"Valvoline Express Care & Dtl",
    "wof:placetype":"venue"
},
  "geometry": {"coordinates":[-88.63767900000001,42.628424],"type":"Point"}
}