{
  "type": "Feature",
  "properties": {
    "addr:full":"1933 Elk St Stevens Point WI 54481",
    "addr:housenumber":"1933",
    "addr:postcode":"54481",
    "addr:street":"Elk St",
    "iso:country":"US",
    "sg:address":"1933 Elk St",
    "sg:city":"Stevens Point",
    "sg:classifiers":[
        {
            "category":"Professional",
            "subcategory":"Computer Services",
            "type":"Services"
        }
    ],
    "sg:phone":"+1 715 340 2317",
    "sg:postcode":"54481",
    "sg:province":"WI",
    "sg:tags":[
        "design",
        "system"
    ],
    "wof:name":"Point Web Design",
    "wof:placetype":"venue"
},
  "geometry": {"coordinates":[-89.57887700000001,44.516767],"type":"Point"}
}