{
  "type": "Feature",
  "properties": {
    "iso:country":"US",
    "sg:address":"2213 Eagle Dr",
    "sg:city":"Middleton",
    "sg:classifiers":[
        {
            "category":"Professional",
            "type":"Services"
        },
        {
            "category":"Professional",
            "subcategory":"Business Services",
            "type":"Services"
        }
    ],
    "sg:phone":"+1 608 831 1185",
    "sg:postcode":"53562",
    "sg:province":"WI",
    "sg:tags":[
        "embroidery"
    ],
    "wof:name":"B W Designs LLC",
    "wof:placetype":"venue"
},
  "geometry": {"coordinates":[-89.527686,43.100651],"type":"Point"}
}