{
  "type": "Feature",
  "properties": {
    "iso:country":"US",
    "sg:address":"1604 Randolph St",
    "sg:city":"Watertown",
    "sg:classifiers":[
        {
            "category":"Building & Trades",
            "subcategory":"Construction",
            "type":"Services"
        }
    ],
    "sg:phone":"+1 920 261 5176",
    "sg:postcode":"53094",
    "sg:province":"WI",
    "wof:name":"Ready Home Improvement",
    "wof:placetype":"venue"
},
  "geometry": {"coordinates":[-88.71732900000001,43.174887],"type":"Point"}
}