{
  "type": "Feature",
  "properties": {
    "iso:country":"US",
    "sg:address":"3126 N 105th St",
    "sg:city":"Milwaukee",
    "sg:classifiers":[
        {
            "category":"Building & Trades",
            "subcategory":"Cleaning & Sanitation",
            "type":"Services"
        }
    ],
    "sg:phone":"+1 414 774 7931",
    "sg:postcode":"53222",
    "sg:province":"WI",
    "sg:tags":[
        "house"
    ],
    "wof:name":"Bud's Home Cleaners Inc",
    "wof:placetype":"venue"
},
  "geometry": {"coordinates":[-88.044249,43.076182],"type":"Point"}
}