{
  "type": "Feature",
  "properties": {
    "iso:country":"US",
    "sg:address":"88 Bryn Mawr Cir",
    "sg:city":"Fond Du Lac",
    "sg:classifiers":[
        {
            "category":"Professional",
            "subcategory":"Engineering",
            "type":"Services"
        }
    ],
    "sg:phone":"+1 920 921 8499",
    "sg:postcode":"54935",
    "sg:province":"WI",
    "wof:name":"Podolak Consulting",
    "wof:placetype":"venue"
},
  "geometry": {"coordinates":[-88.41711100000001,43.781927],"type":"Point"}
}