{
  "type": "Feature",
  "properties": {
    "addr:full":"1486 North Ave Cleveland WI 53015",
    "addr:housenumber":"1486",
    "addr:postcode":"53015",
    "addr:street":"North Ave",
    "iso:country":"US",
    "sg:address":"1486 North Ave",
    "sg:city":"Cleveland",
    "sg:classifiers":[
        {
            "category":"Retail",
            "subcategory":"Auto Repair",
            "type":"Services"
        }
    ],
    "sg:phone":"+1 920 693 8115",
    "sg:postcode":"53015",
    "sg:province":"WI",
    "sg:tags":[
        "a",
        "used",
        "parts",
        "general"
    ],
    "wof:name":"Cleveland Auto Sales & Salvage",
    "wof:placetype":"venue"
},
  "geometry": {"coordinates":[-87.761612,43.921311],"type":"Point"}
}