{
  "type": "Feature",
  "properties": {
    "iso:country":"US",
    "sg:address":"4626 S Packard Ave",
    "sg:city":"Cudahy",
    "sg:classifiers":[
        {
            "category":"Government",
            "subcategory":"Fire Station",
            "type":"Public Place"
        }
    ],
    "sg:phone":"+1 414 769 2232",
    "sg:postcode":"53110",
    "sg:province":"WI",
    "sg:tags":[
        "protection"
    ],
    "wof:name":"Cudahy Fire Department",
    "wof:placetype":"venue"
},
  "geometry": {"coordinates":[-87.859992,42.960537],"type":"Point"}
}