{
  "type": "Feature",
  "properties": {
    "iso:country":"US",
    "sg:address":"1217 Clara Ave",
    "sg:city":"Lake Delton",
    "sg:classifiers":[
        {
            "category":"Building & Trades",
            "subcategory":"Electrical",
            "type":"Services"
        }
    ],
    "sg:phone":"+1 608 253 4040",
    "sg:postcode":"53965",
    "sg:province":"WI",
    "sg:tags":[
        "electric",
        "contractor"
    ],
    "wof:name":"Mid State Electrical Contr Inc",
    "wof:placetype":"venue"
},
  "geometry": {"coordinates":[-89.798819,43.604087],"type":"Point"}
}