{
  "type": "Feature",
  "properties": {
    "addr:full":"5376 Faro Springs Rd Hilbert WI 54129",
    "addr:postcode":"5376;54129",
    "addr:street":"Faro Springs Rd",
    "iso:country":"US",
    "sg:address":"5376 Faro Springs Rd",
    "sg:city":"Hilbert",
    "sg:classifiers":[
        {
            "category":"Wholesale",
            "subcategory":"Machinery & Supplies",
            "type":"Manufacturing & Wholesale Goods"
        },
        {
            "category":"Building & Trades",
            "subcategory":"Construction",
            "type":"Services"
        }
    ],
    "sg:phone":"+1 920 989 1986",
    "sg:postcode":"54129",
    "sg:province":"WI",
    "sg:tags":[
        "nonresidential",
        "contractor"
    ],
    "wof:name":"Fisher and Mader Construction",
    "wof:placetype":"venue"
},
  "geometry": {"coordinates":[-88.308617,44.122671],"type":"Point"}
}