{
  "type": "Feature",
  "properties": {
    "iso:country":"US",
    "sg:address":"1321 Contractors Blvd",
    "sg:city":"Plover",
    "sg:classifiers":[
        {
            "category":"Retail",
            "subcategory":"Auto Repair",
            "type":"Services"
        }
    ],
    "sg:phone":"+1 715 344 4600",
    "sg:postcode":"54467",
    "sg:province":"WI",
    "sg:tags":[
        "general"
    ],
    "wof:name":"Pro Auto Service",
    "wof:placetype":"venue"
},
  "geometry": {"coordinates":[-89.551492,44.477478],"type":"Point"}
}