{
  "type": "Feature",
  "properties": {
    "iso:country":"US",
    "sg:address":"102 We-Go Trl",
    "sg:city":"Fox Lake",
    "sg:classifiers":[
        {
            "category":"Professional",
            "type":"Services"
        }
    ],
    "sg:phone":"+1 920 928 2134",
    "sg:postcode":"53933",
    "sg:province":"WI",
    "wof:name":"James Zindars",
    "wof:placetype":"venue"
},
  "geometry": {"coordinates":[-88.91309,43.56774],"type":"Point"}
}