{
  "type": "Feature",
  "properties": {
    "iso:country":"US",
    "sg:address":"1822 Highview Rd",
    "sg:city":"Ellison Bay",
    "sg:classifiers":[
        {
            "category":"Real Estate",
            "subcategory":"Real Estate Agent",
            "type":"Services"
        }
    ],
    "sg:phone":"+1 520 749 4778",
    "sg:postcode":"54210",
    "sg:province":"WI",
    "wof:name":"Milagrosa Realty LLC",
    "wof:placetype":"venue"
},
  "geometry": {"coordinates":[-87.089973,45.229678],"type":"Point"}
}