{
  "type": "Feature",
  "properties": {
    "iso:country":"US",
    "sg:address":"12760 W North Ave",
    "sg:city":"Brookfield",
    "sg:classifiers":[
        {
            "category":"Real Estate",
            "subcategory":"Real Estate Agent",
            "type":"Services"
        }
    ],
    "sg:phone":"+1 262 784 6500",
    "sg:postcode":"53005",
    "sg:province":"WI",
    "sg:website":"www.thomsoncorporation.com",
    "wof:name":"Thomson Corp",
    "wof:placetype":"venue"
},
  "geometry": {"coordinates":[-88.069333,43.060156],"type":"Point"}
}