{
  "type": "Feature",
  "properties": {
    "addr:full":"412 Laudan Blvd Neenah WI 54956",
    "addr:housenumber":"412",
    "addr:postcode":"54956",
    "addr:street":"Laudan Blvd",
    "iso:country":"US",
    "sg:address":"412 Laudan Blvd",
    "sg:city":"Neenah",
    "sg:classifiers":[
        {
            "category":"Building & Trades",
            "subcategory":"Construction",
            "type":"Services"
        }
    ],
    "sg:phone":"+1 920 725 7638",
    "sg:postcode":"54956",
    "sg:province":"WI",
    "sg:tags":[
        "hanging",
        "contractor"
    ],
    "wof:name":"Woerfel Painting",
    "wof:placetype":"venue"
},
  "geometry": {"coordinates":[-88.453383,44.174715],"type":"Point"}
}