{
  "type": "Feature",
  "properties": {
    "iso:country":"US",
    "sg:address":"4359 State Hwy 13",
    "sg:city":"Unity",
    "sg:classifiers":[
        {
            "category":"Retail",
            "subcategory":"Auto Repair",
            "type":"Services"
        }
    ],
    "sg:phone":"+1 715 223 0237",
    "sg:postcode":"54488",
    "sg:province":"WI",
    "sg:tags":[
        "repairing",
        "automobile"
    ],
    "wof:name":"D & A Automotive Inc",
    "wof:placetype":"venue"
},
  "geometry": {"coordinates":[-90.309839,44.821576],"type":"Point"}
}