{
  "type": "Feature",
  "properties": {
    "iso:country":"US",
    "sg:address":"11505 W National Ave",
    "sg:city":"Milwaukee",
    "sg:classifiers":[
        {
            "category":"Bars & Pubs",
            "subcategory":"Lounge",
            "type":"Food & Drink"
        }
    ],
    "sg:menulink":"http://www.allmenus.com/wi/west-allis/114402-bobus-steakhouse--lounge/menu/",
    "sg:phone":"+1 414 321 7300",
    "sg:postcode":"53227",
    "sg:province":"WI",
    "sg:tags":[
        "american",
        "steakhouse"
    ],
    "wof:name":"Bobu's Steakhouse & Lounge",
    "wof:placetype":"venue"
},
  "geometry": {"coordinates":[-88.05488800000001,42.989176],"type":"Point"}
}