{
  "type": "Feature",
  "properties": {
    "iso:country":"US",
    "sg:address":"1103 Adams St",
    "sg:city":"West Bend",
    "sg:classifiers":[
        {
            "category":"Building & Trades",
            "subcategory":"Construction",
            "type":"Services"
        }
    ],
    "sg:phone":"+1 262 338 0378",
    "sg:postcode":"53090",
    "sg:province":"WI",
    "sg:tags":[
        "painting",
        "contractor"
    ],
    "wof:name":"George S Connelly III",
    "wof:placetype":"venue"
},
  "geometry": {"coordinates":[-88.19112,43.44301],"type":"Point"}
}