{
  "type": "Feature",
  "properties": {
    "iso:country":"US",
    "sg:address":"558 State Hwy 73 S",
    "sg:city":"Nekoosa",
    "sg:classifiers":[
        {
            "category":"Shopping",
            "subcategory":"Discount & Variety Stores",
            "type":"Retail Goods"
        }
    ],
    "sg:phone":"+1 715 886 5815",
    "sg:postcode":"54457",
    "sg:province":"WI",
    "sg:tags":[
        "merchandise",
        "general"
    ],
    "wof:name":"Sirmart",
    "wof:placetype":"venue"
},
  "geometry": {"coordinates":[-89.871717,44.307299],"type":"Point"}
}