{
  "type": "Feature",
  "properties": {
    "iso:country":"US",
    "sg:address":"3251 Woodland Rd",
    "sg:city":"Medford",
    "sg:classifiers":[
        {
            "category":"Building & Trades",
            "subcategory":"Landscaping Services",
            "type":"Services"
        }
    ],
    "sg:phone":"+1 715 748 5727",
    "sg:postcode":"54451",
    "sg:province":"WI",
    "wof:name":"Guden Lawn Service",
    "wof:placetype":"venue"
},
  "geometry": {"coordinates":[-90.364351,45.149703],"type":"Point"}
}