{
  "type": "Feature",
  "properties": {
    "iso:country":"US",
    "sg:address":"1198 State Hwy 13",
    "sg:city":"Park Falls",
    "sg:classifiers":[
        {
            "category":"Autos & Motor Vehicles",
            "subcategory":"Auto Supplies",
            "type":"Retail Goods"
        }
    ],
    "sg:phone":"+1 715 762 3717",
    "sg:postcode":"54552",
    "sg:province":"WI",
    "sg:tags":[
        "automobile",
        "parts"
    ],
    "wof:name":"NAPA Auto Parts",
    "wof:placetype":"venue"
},
  "geometry": {"coordinates":[-90.46170499999999,45.946023],"type":"Point"}
}