{
  "type": "Feature",
  "properties": {
    "iso:country":"US",
    "sg:address":"777 S Barker Rd",
    "sg:city":"Brookfield",
    "sg:classifiers":[
        {
            "category":"Shopping",
            "subcategory":"News",
            "type":"Retail Goods"
        }
    ],
    "sg:phone":"+1 262 786 6478",
    "sg:postcode":"53045",
    "sg:province":"WI",
    "sg:tags":[
        "magazine"
    ],
    "sg:website":"www.justbetweenus.org",
    "wof:name":"Just Between Us",
    "wof:placetype":"venue"
},
  "geometry": {"coordinates":[-88.16687,43.023159],"type":"Point"}
}