{
  "type": "Feature",
  "properties": {
    "iso:country":"US",
    "sg:address":"10041 Co Rd Y",
    "sg:city":"Mazomanie",
    "sg:classifiers":[
        {
            "category":"Organizations",
            "subcategory":"Community Association",
            "type":"Services"
        }
    ],
    "sg:phone":"+1 608 795 4640",
    "sg:postcode":"53560",
    "sg:province":"WI",
    "sg:tags":[
        "club"
    ],
    "wof:name":"Wisconsin River Sportsman Club",
    "wof:placetype":"venue"
},
  "geometry": {"coordinates":[-89.762944,43.237657],"type":"Point"}
}