{
  "type": "Feature",
  "properties": {
    "iso:country":"US",
    "sg:address":"434 1st Ave S",
    "sg:city":"Wisconsin Rapids",
    "sg:classifiers":[
        {
            "category":"Professional",
            "subcategory":"Computer Services",
            "type":"Services"
        }
    ],
    "sg:phone":"+1 715 424 1203",
    "sg:postcode":"54495",
    "sg:province":"WI",
    "sg:tags":[
        "website",
        "design"
    ],
    "sg:website":"www.wisrapids.com",
    "wof:name":"WISRAPIDS.COM",
    "wof:placetype":"venue"
},
  "geometry": {"coordinates":[-89.83092600000001,44.390622],"type":"Point"}
}