{
  "type": "Feature",
  "properties": {
    "iso:country":"US",
    "sg:address":"535 Science Dr",
    "sg:city":"Madison",
    "sg:classifiers":[
        {
            "category":"Professional",
            "type":"Services"
        }
    ],
    "sg:phone":"+1 608 231 3100",
    "sg:postcode":"53711",
    "sg:province":"WI",
    "wof:name":"Mentor Biologics",
    "wof:placetype":"venue"
},
  "geometry": {"coordinates":[-89.46786400000001,43.056058],"type":"Point"}
}