{
  "type": "Feature",
  "properties": {
    "iso:country":"US",
    "sg:address":"478 Townhall Rd",
    "sg:city":"Luxemburg",
    "sg:classifiers":[
        {
            "category":"Professional",
            "subcategory":"Management & Consulting",
            "type":"Services"
        }
    ],
    "sg:phone":"+1 920 866 3418",
    "sg:postcode":"54217",
    "sg:province":"WI",
    "wof:name":"Proven Concepts LLC",
    "wof:placetype":"venue"
},
  "geometry": {"coordinates":[-87.747583,44.632115],"type":"Point"}
}