{
  "type": "Feature",
  "properties": {
    "iso:country":"US",
    "sg:address":"511 W Prairie St",
    "sg:city":"Wautoma",
    "sg:classifiers":[
        {
            "category":"Social Services",
            "type":"Services"
        }
    ],
    "sg:phone":"+1 920 787 4346",
    "sg:postcode":"54982",
    "sg:province":"WI",
    "wof:name":"Living Environmental",
    "wof:placetype":"venue"
},
  "geometry": {"coordinates":[-89.297318,44.065002],"type":"Point"}
}