{
  "type": "Feature",
  "properties": {
    "iso:country":"US",
    "sg:address":"10207 Co Rd K",
    "sg:city":"Lodi",
    "sg:classifiers":[
        {
            "category":"Retail",
            "subcategory":"Laundry & Dry Cleaning",
            "type":"Services"
        }
    ],
    "sg:phone":"+1 608 592 3191",
    "sg:postcode":"53555",
    "sg:province":"WI",
    "sg:tags":[
        "cleaners",
        "rug",
        "carpet"
    ],
    "wof:name":"Deluxe Carpet & Upholstery Clg",
    "wof:placetype":"venue"
},
  "geometry": {"coordinates":[-89.50887,43.310572],"type":"Point"}
}