{
  "type": "Feature",
  "properties": {
    "iso:country":"US",
    "sg:address":"2001 Alford Park Dr",
    "sg:city":"Kenosha",
    "sg:classifiers":[
        {
            "category":"Education",
            "subcategory":"College",
            "type":"Public Place"
        }
    ],
    "sg:phone":"+1 262 551 8500",
    "sg:postcode":"53140",
    "sg:province":"WI",
    "sg:website":"www.carthage.edu",
    "wof:name":"Carthage College",
    "wof:placetype":"venue"
},
  "geometry": {"coordinates":[-87.821325,42.608399],"type":"Point"}
}