{
  "type": "Feature",
  "properties": {
    "iso:country":"US",
    "sg:address":"323 Superior St",
    "sg:city":"Antigo",
    "sg:classifiers":[
        {
            "category":"Shopping",
            "subcategory":"Bicycles & Sporting Goods",
            "type":"Retail Goods"
        }
    ],
    "sg:phone":"+1 715 627 4601",
    "sg:postcode":"54409",
    "sg:province":"WI",
    "sg:tags":[
        "club",
        "health"
    ],
    "wof:name":"Antigo Athletic Club",
    "wof:placetype":"venue"
},
  "geometry": {"coordinates":[-89.152277,45.137306],"type":"Point"}
}