{
  "type": "Feature",
  "properties": {
    "addr:full":"6091 578th Ave Menomonie WI 54751",
    "addr:housenumber":"6091",
    "addr:postcode":"54751",
    "addr:street":"578Th Ave",
    "iso:country":"US",
    "sg:address":"6091 578th Ave",
    "sg:city":"Menomonie",
    "sg:classifiers":[
        {
            "category":"Wholesale",
            "subcategory":"Machinery & Supplies",
            "type":"Manufacturing & Wholesale Goods"
        }
    ],
    "sg:phone":"+1 715 235 9688",
    "sg:postcode":"54751",
    "sg:province":"WI",
    "sg:tags":[
        "farm",
        "equipment"
    ],
    "sg:website":"www.valueimplement.com",
    "wof:name":"Value Implement",
    "wof:placetype":"venue"
},
  "geometry": {"coordinates":[-91.85904499999999,44.889283],"type":"Point"}
}