{
  "type": "Feature",
  "properties": {
    "iso:country":"US",
    "sg:address":"5301 Tri Lakes Rd",
    "sg:city":"Superior",
    "sg:classifiers":[
        {
            "category":"Organizations",
            "subcategory":"Community Association",
            "type":"Services"
        }
    ],
    "sg:phone":"+1 715 399 9966",
    "sg:postcode":"54874",
    "sg:province":"WI",
    "wof:name":"Camp Newman Boy Scouts of",
    "wof:placetype":"venue"
},
  "geometry": {"coordinates":[-92.025499,46.474593],"type":"Point"}
}