{
  "type": "Feature",
  "properties": {
    "addr:full":"221 E Main St Sun Prairie WI 53590",
    "addr:housenumber":"221",
    "addr:postcode":"53590",
    "addr:street":"E Main St",
    "iso:country":"US",
    "sg:address":"221 E Main St",
    "sg:city":"Sun Prairie",
    "sg:classifiers":[
        {
            "category":"Shopping",
            "subcategory":"Crafts & Fabrics",
            "type":"Retail Goods"
        }
    ],
    "sg:phone":"+1 608 837 2266",
    "sg:postcode":"53590",
    "sg:province":"WI",
    "sg:tags":[
        "notion"
    ],
    "wof:name":"J J Stitches",
    "wof:placetype":"venue"
},
  "geometry": {"coordinates":[-89.212423,43.183101],"type":"Point"}
}