{
  "type": "Feature",
  "properties": {
    "addr:full":"5521 N Lydell Ave Milwaukee WI 53217",
    "addr:housenumber":"5521",
    "addr:postcode":"53217",
    "addr:street":"N Lydell Ave",
    "iso:country":"US",
    "sg:address":"5521 N Lydell Ave",
    "sg:city":"Milwaukee",
    "sg:classifiers":[
        {
            "category":"Professional",
            "subcategory":"Lawyer & Legal Services",
            "type":"Services"
        }
    ],
    "sg:phone":"+1 414 332 1200",
    "sg:postcode":"53217",
    "sg:province":"WI",
    "sg:tags":[
        "attorney"
    ],
    "wof:name":"Henry J Gefke",
    "wof:placetype":"venue"
},
  "geometry": {"coordinates":[-87.91180900000001,43.116442],"type":"Point"}
}