{
  "type": "Feature",
  "properties": {
    "iso:country":"US",
    "sg:address":"1705 W Main St",
    "sg:city":"Sun Prairie",
    "sg:classifiers":[
        {
            "category":"Food & Beverages",
            "subcategory":"Groceries & Convenience Stores",
            "type":"Retail Goods"
        }
    ],
    "sg:phone":"+1 608 837 2935",
    "sg:postcode":"53590",
    "sg:province":"WI",
    "wof:name":"Open Pantry Food Mart",
    "wof:placetype":"venue"
},
  "geometry": {"coordinates":[-89.24261,43.17746],"type":"Point"}
}