{
  "type": "Feature",
  "properties": {
    "iso:country":"US",
    "sg:address":"643 S Fair St",
    "sg:city":"Wautoma",
    "sg:classifiers":[
        {
            "category":"Building & Trades",
            "subcategory":"Equipment Rental",
            "type":"Services"
        }
    ],
    "sg:phone":"+1 920 787 4898",
    "sg:postcode":"54982",
    "sg:province":"WI",
    "wof:name":"Port A Potty Rental",
    "wof:placetype":"venue"
},
  "geometry": {"coordinates":[-89.287359,44.06565],"type":"Point"}
}