{
  "type": "Feature",
  "properties": {
    "addr:full":"2402 Gowen St Wausau WI 54403",
    "addr:housenumber":"2402",
    "addr:postcode":"54403",
    "addr:street":"Gowen St",
    "iso:country":"US",
    "sg:address":"2402 Gowen St",
    "sg:city":"Wausau",
    "sg:classifiers":[
        {
            "category":"Building & Trades",
            "subcategory":"Landscaping Services",
            "type":"Services"
        }
    ],
    "sg:phone":"+1 715 298 0199",
    "sg:postcode":"54403",
    "sg:province":"WI",
    "wof:name":"A Plus Landscaping",
    "wof:placetype":"venue"
},
  "geometry": {"coordinates":[-89.62487400000001,44.976195],"type":"Point"}
}