{
  "type": "Feature",
  "properties": {
    "iso:country":"US",
    "sg:address":"3921 W Rollingwood Dr",
    "sg:city":"Janesville",
    "sg:classifiers":[
        {
            "category":"Building & Trades",
            "subcategory":"Plumbing",
            "type":"Services"
        }
    ],
    "sg:phone":"+1 608 741 7474",
    "sg:postcode":"53545",
    "sg:province":"WI",
    "sg:tags":[
        "plumbing",
        "contractor"
    ],
    "wof:name":"Schuh Plumbing Contractors LLC",
    "wof:placetype":"venue"
},
  "geometry": {"coordinates":[-89.075614,42.743922],"type":"Point"}
}