{
  "type": "Feature",
  "properties": {
    "iso:country":"US",
    "sg:address":"581 N Main St",
    "sg:city":"Oshkosh",
    "sg:classifiers":[
        {
            "category":"Real Estate",
            "subcategory":"Architect",
            "type":"Services"
        }
    ],
    "sg:phone":"+1 920 233 0476",
    "sg:postcode":"54901",
    "sg:province":"WI",
    "sg:tags":[
        "architectural"
    ],
    "wof:name":"Rick Schroeder AIA Architect",
    "wof:placetype":"venue"
},
  "geometry": {"coordinates":[-88.53761299999999,44.020132],"type":"Point"}
}