{
  "type": "Feature",
  "properties": {
    "addr:full":"206 6th Ave W Ashland WI 54806",
    "addr:housenumber":"206",
    "addr:postcode":"54806",
    "addr:street":"6Th Ave W",
    "iso:country":"US",
    "sg:address":"206 6th Ave W",
    "sg:city":"Ashland",
    "sg:classifiers":[
        {
            "category":"Organizations",
            "subcategory":"Community Association",
            "type":"Services"
        }
    ],
    "sg:phone":"+1 715 682 3270",
    "sg:postcode":"54806",
    "sg:province":"WI",
    "sg:tags":[
        "fraternal"
    ],
    "wof:name":"Masonic Lodge",
    "wof:placetype":"venue"
},
  "geometry": {"coordinates":[-90.88929400000001,46.58875],"type":"Point"}
}