{
  "type": "Feature",
  "properties": {
    "addr:full":"10288 Baker Rd Reeseville WI 53579",
    "addr:housenumber":"10288",
    "addr:postcode":"53579",
    "addr:street":"Baker Rd",
    "iso:country":"US",
    "sg:address":"10288 Baker Rd",
    "sg:city":"Reeseville",
    "sg:classifiers":[
        {
            "category":"Freight",
            "type":"Transportation"
        }
    ],
    "sg:phone":"+1 920 927 3868",
    "sg:postcode":"53579",
    "sg:province":"WI",
    "wof:name":"Cda Transport",
    "wof:placetype":"venue"
},
  "geometry": {"coordinates":[-88.90525100000001,43.256082],"type":"Point"}
}