{
  "type": "Feature",
  "properties": {
    "iso:country":"US",
    "sg:address":"9048 Co Rd D",
    "sg:city":"Amherst",
    "sg:classifiers":[
        {
            "category":"Farming",
            "subcategory":"Dairy Farm",
            "type":"Manufacturing & Wholesale Goods"
        }
    ],
    "sg:phone":"+1 715 824 2162",
    "sg:postcode":"54406",
    "sg:province":"WI",
    "sg:tags":[
        "corn"
    ],
    "wof:name":"Dan Maves",
    "wof:placetype":"venue"
},
  "geometry": {"coordinates":[-89.333631,44.413977],"type":"Point"}
}