{
  "type": "Feature",
  "properties": {
    "iso:country":"US",
    "sg:address":"916 Madison Ave",
    "sg:city":"Fort Atkinson",
    "sg:classifiers":[
        {
            "category":"Restaurant",
            "type":"Food & Drink"
        }
    ],
    "sg:phone":"+1 920 563 7501",
    "sg:postcode":"53538",
    "sg:province":"WI",
    "sg:tags":[
        "eating",
        "desert",
        "ice",
        "mfg"
    ],
    "wof:name":"Kents Old Fashioned Ice Cream",
    "wof:placetype":"venue"
},
  "geometry": {"coordinates":[-88.84988199999999,42.934667],"type":"Point"}
}