{
  "type": "Feature",
  "properties": {
    "iso:country":"US",
    "sg:address":"4052 Co Hwy B",
    "sg:city":"Colfax",
    "sg:classifiers":[
        {
            "category":"Government",
            "subcategory":"Fire Station",
            "type":"Public Place"
        }
    ],
    "sg:phone":"+1 715 568 5525",
    "sg:postcode":"54730",
    "sg:province":"WI",
    "sg:tags":[
        "department"
    ],
    "wof:name":"Howard Town Hall & Fire Stat",
    "wof:placetype":"venue"
},
  "geometry": {"coordinates":[-91.59026,45.008692],"type":"Point"}
}