{
  "type": "Feature",
  "properties": {
    "iso:country":"US",
    "sg:address":"917 N 49th St",
    "sg:city":"Milwaukee",
    "sg:classifiers":[
        {
            "category":"Organizations",
            "subcategory":"Religious Organization",
            "type":"Services"
        }
    ],
    "sg:phone":"+1 414 774 9418",
    "sg:postcode":"53208",
    "sg:province":"WI",
    "sg:tags":[
        "building",
        "operator",
        "nonresidential"
    ],
    "wof:name":"Sacred Hart Rman Cthlic Church",
    "wof:placetype":"venue"
},
  "geometry": {"coordinates":[-87.975396,43.040408],"type":"Point"}
}