{
  "type": "Feature",
  "properties": {
    "iso:country":"US",
    "sg:address":"10148 Hogan Rd",
    "sg:city":"Portage",
    "sg:classifiers":[
        {
            "category":"Building & Trades",
            "subcategory":"Construction",
            "type":"Services"
        }
    ],
    "sg:phone":"+1 608 742 6950",
    "sg:postcode":"53901",
    "sg:province":"WI",
    "sg:tags":[
        "carpentry",
        "contractor"
    ],
    "wof:name":"Carpenter Craftsman",
    "wof:placetype":"venue"
},
  "geometry": {"coordinates":[-89.509693,43.612937],"type":"Point"}
}