{
  "type": "Feature",
  "properties": {
    "iso:country":"US",
    "sg:address":"3308 Mall Dr",
    "sg:city":"Eau Claire",
    "sg:classifiers":[
        {
            "category":"Retail",
            "subcategory":"Animal Services",
            "type":"Services"
        }
    ],
    "sg:phone":"+1 715 552 3565",
    "sg:postcode":"54701",
    "sg:province":"WI",
    "wof:name":"Invisable Fence of Chippwega",
    "wof:placetype":"venue"
},
  "geometry": {"coordinates":[-91.461269,44.782022],"type":"Point"}
}