{
  "type": "Feature",
  "properties": {
    "addr:full":"3510 Millpond Rd Madison WI 53718",
    "addr:housenumber":"3510",
    "addr:postcode":"53718",
    "addr:street":"Millpond Rd",
    "iso:country":"US",
    "sg:address":"3510 Millpond Rd",
    "sg:city":"Madison",
    "sg:classifiers":[
        {
            "category":"Travel",
            "subcategory":"Hotels & Motels",
            "type":"Entertainment"
        }
    ],
    "sg:phone":"+1 608 224 1500",
    "sg:postcode":"53718",
    "sg:province":"WI",
    "sg:tags":[
        "operation",
        "fitness",
        "physical",
        "facility"
    ],
    "sg:website":"www.wingateinnmadison.com",
    "wof:name":"Wingate Inn",
    "wof:placetype":"venue"
},
  "geometry": {"coordinates":[-89.269115,43.04375],"type":"Point"}
}