{
  "type": "Feature",
  "properties": {
    "iso:country":"US",
    "sg:address":"7547 Green Meadow Rd",
    "sg:city":"Oshkosh",
    "sg:classifiers":[
        {
            "category":"Freight",
            "type":"Transportation"
        }
    ],
    "sg:phone":"+1 920 836 3896",
    "sg:postcode":"54904",
    "sg:province":"WI",
    "sg:tags":[
        "hauling",
        "trucking"
    ],
    "wof:name":"Arrow Valley Express",
    "wof:placetype":"venue"
},
  "geometry": {"coordinates":[-88.634799,44.162814],"type":"Point"}
}