{
  "type": "Feature",
  "properties": {
    "iso:country":"US",
    "sg:address":"1806 Franklin St",
    "sg:city":"Wausau",
    "sg:classifiers":[
        {
            "category":"Shopping",
            "subcategory":"Clothing, Apparel, & Fashions",
            "type":"Retail Goods"
        }
    ],
    "sg:phone":"+1 715 842 8646",
    "sg:postcode":"54403",
    "sg:province":"WI",
    "sg:tags":[
        "personal"
    ],
    "wof:name":"Bridal Boutique",
    "wof:placetype":"venue"
},
  "geometry": {"coordinates":[-89.60378,44.963326],"type":"Point"}
}