{
  "type": "Feature",
  "properties": {
    "iso:country":"US",
    "sg:address":"4716 Co Rd Nn",
    "sg:city":"Green Bay",
    "sg:classifiers":[
        {
            "category":"Farming",
            "subcategory":"Dairy Farm",
            "type":"Manufacturing & Wholesale Goods"
        }
    ],
    "sg:phone":"+1 920 863 6390",
    "sg:postcode":"54311",
    "sg:province":"WI",
    "wof:name":"Pine Grove Dairy",
    "wof:placetype":"venue"
},
  "geometry": {"coordinates":[-87.887231,44.40812],"type":"Point"}
}