{
  "type": "Feature",
  "properties": {
    "iso:country":"US",
    "sg:address":"470 Grand Ave",
    "sg:city":"Denmark",
    "sg:classifiers":[
        {
            "category":"Professional",
            "subcategory":"Computer Services",
            "type":"Services"
        }
    ],
    "sg:phone":"+1 920 863 3670",
    "sg:postcode":"54208",
    "sg:province":"WI",
    "sg:tags":[
        "development",
        "design",
        "software"
    ],
    "wof:name":"Cerebral Systems Inc",
    "wof:placetype":"venue"
},
  "geometry": {"coordinates":[-87.81860500000001,44.346044],"type":"Point"}
}