{
  "type": "Feature",
  "properties": {
    "iso:country":"US",
    "sg:address":"620 W Lawrence St",
    "sg:city":"Appleton",
    "sg:classifiers":[
        {
            "category":"Building & Trades",
            "subcategory":"Construction",
            "type":"Services"
        }
    ],
    "sg:phone":"+1 920 954 9282",
    "sg:postcode":"54911",
    "sg:province":"WI",
    "sg:tags":[
        "general",
        "contractor"
    ],
    "wof:name":"Northstar Contracting Inc",
    "wof:placetype":"venue"
},
  "geometry": {"coordinates":[-88.415369,44.260704],"type":"Point"}
}