{
  "type": "Feature",
  "properties": {
    "iso:country":"US",
    "sg:address":"217 N 89th St",
    "sg:city":"Milwaukee",
    "sg:classifiers":[
        {
            "category":"Professional",
            "subcategory":"Business Services",
            "type":"Services"
        },
        {
            "category":"Professional",
            "subcategory":"Management & Consulting",
            "type":"Services"
        }
    ],
    "sg:phone":"+1 414 475 0662",
    "sg:postcode":"53226",
    "sg:province":"WI",
    "sg:tags":[
        "event"
    ],
    "wof:name":"Chris Lorenz Events",
    "wof:placetype":"venue"
},
  "geometry": {"coordinates":[-88.02312999999999,43.035362],"type":"Point"}
}