{
  "type": "Feature",
  "properties": {
    "iso:country":"US",
    "sg:address":"2361 N Hastings Way",
    "sg:city":"Eau Claire",
    "sg:classifiers":[
        {
            "category":"Organizations",
            "subcategory":"Religious Organization",
            "type":"Services"
        }
    ],
    "sg:phone":"+1 715 832 5019",
    "sg:postcode":"54703",
    "sg:province":"WI",
    "wof:name":"Bethel Church",
    "wof:placetype":"venue"
},
  "geometry": {"coordinates":[-91.472954,44.846445],"type":"Point"}
}