{
  "type": "Feature",
  "properties": {
    "iso:country":"US",
    "sg:address":"10931 State Hwy 42",
    "sg:city":"Sister Bay",
    "sg:classifiers":[
        {
            "category":"Recreation",
            "type":"Entertainment"
        }
    ],
    "sg:phone":"+1 920 854 2113",
    "sg:postcode":"54234",
    "sg:province":"WI",
    "sg:tags":[
        "guide"
    ],
    "wof:name":"Hubbard's Pier Charter Fishing",
    "wof:placetype":"venue"
},
  "geometry": {"coordinates":[-87.11898100000001,45.200008],"type":"Point"}
}