{
  "type": "Feature",
  "properties": {
    "iso:country":"US",
    "sg:address":"315 S Bluemound Dr",
    "sg:city":"Appleton",
    "sg:classifiers":[
        {
            "category":"Organizations",
            "subcategory":"Professional Association",
            "type":"Services"
        }
    ],
    "sg:phone":"+1 920 738 9220",
    "sg:postcode":"54914",
    "sg:province":"WI",
    "sg:tags":[
        "business"
    ],
    "wof:name":"Masonic Center",
    "wof:placetype":"venue"
},
  "geometry": {"coordinates":[-88.45596500000001,44.259662],"type":"Point"}
}