{
  "type": "Feature",
  "properties": {
    "iso:country":"US",
    "sg:address":"13605 Underwood River Pkwy",
    "sg:city":"Elm Grove",
    "sg:classifiers":[
        {
            "category":"Education",
            "subcategory":"School",
            "type":"Public Place"
        }
    ],
    "sg:phone":"+1 262 785 3950",
    "sg:postcode":"53122",
    "sg:province":"WI",
    "sg:tags":[
        "elementary"
    ],
    "wof:name":"Tonawanda Elementary School",
    "wof:placetype":"venue"
},
  "geometry": {"coordinates":[-88.081895,43.054637],"type":"Point"}
}