{
  "type": "Feature",
  "properties": {
    "iso:country":"US",
    "sg:address":"337 N 9th St",
    "sg:city":"River Falls",
    "sg:classifiers":[
        {
            "category":"Manufacturing",
            "subcategory":"Tools & Machinery",
            "type":"Manufacturing & Wholesale Goods"
        }
    ],
    "sg:phone":"+1 715 426 1244",
    "sg:postcode":"54022",
    "sg:province":"WI",
    "sg:tags":[
        "electronic",
        "devices",
        "mfg"
    ],
    "wof:name":"Sensormatic Electronics Corp",
    "wof:placetype":"venue"
},
  "geometry": {"coordinates":[-92.615414,44.859319],"type":"Point"}
}