{
  "type": "Feature",
  "properties": {
    "addr:full":"7601 Ganser Way Madison WI 53719",
    "addr:housenumber":"7601",
    "addr:postcode":"53719",
    "addr:street":"Ganser Way",
    "iso:country":"US",
    "sg:address":"7601 Ganser Way",
    "sg:city":"Madison",
    "sg:classifiers":[
        {
            "category":"Professional",
            "subcategory":"Business Services",
            "type":"Services"
        },
        {
            "category":"Professional",
            "subcategory":"Accounting & Tax Preparation",
            "type":"Services"
        }
    ],
    "sg:phone":"+1 608 826 0400",
    "sg:postcode":"53719",
    "sg:province":"WI",
    "sg:tags":[
        "accountant"
    ],
    "wof:name":"Padgett Business Srvc",
    "wof:placetype":"venue"
},
  "geometry": {"coordinates":[-89.514819,43.05964],"type":"Point"}
}