{
  "type": "Feature",
  "properties": {
    "addr:full":"2161 E Rawson Ave Oak Creek WI 53154",
    "addr:housenumber":"2161",
    "addr:postcode":"53154",
    "addr:street":"E Rawson Ave",
    "iso:country":"US",
    "sg:address":"2161 E Rawson Ave",
    "sg:city":"Oak Creek",
    "sg:classifiers":[
        {
            "category":"Retail",
            "subcategory":"Self-service Laundry",
            "type":"Services"
        }
    ],
    "sg:phone":"+1 414 768 0300",
    "sg:postcode":"53154",
    "sg:province":"WI",
    "sg:tags":[
        "coin"
    ],
    "wof:name":"Laundry Basket",
    "wof:placetype":"venue"
},
  "geometry": {"coordinates":[-87.881933,42.915328],"type":"Point"}
}