{
  "type": "Feature",
  "properties": {
    "iso:country":"US",
    "sg:address":"312 Torrey Pines Dr",
    "sg:city":"Twin Lakes",
    "sg:classifiers":[
        {
            "category":"Banks & Credit Unions",
            "subcategory":"Investment Brokerage",
            "type":"Services"
        }
    ],
    "sg:phone":"+1 262 877 3965",
    "sg:postcode":"53181",
    "sg:province":"WI",
    "sg:tags":[
        "advisory"
    ],
    "wof:name":"Jureebo Investment Group LLC",
    "wof:placetype":"venue"
},
  "geometry": {"coordinates":[-88.233772,42.530309],"type":"Point"}
}