{
  "type": "Feature",
  "properties": {
    "iso:country":"US",
    "sg:address":"2918 Washington Rd",
    "sg:city":"Kenosha",
    "sg:classifiers":[
        {
            "category":"Restaurant",
            "type":"Food & Drink"
        }
    ],
    "sg:phone":"+1 262 657 7768",
    "sg:postcode":"53140",
    "sg:province":"WI",
    "sg:tags":[
        "eating"
    ],
    "wof:name":"In Spot Drive",
    "wof:placetype":"venue"
},
  "geometry": {"coordinates":[-87.845564,42.602827],"type":"Point"}
}