{
  "type": "Feature",
  "properties": {
    "iso:country":"US",
    "sg:address":"2813 W Kenlar Cir",
    "sg:city":"Green Bay",
    "sg:classifiers":[
        {
            "category":"Building & Trades",
            "subcategory":"Plumbing",
            "type":"Services"
        }
    ],
    "sg:phone":"+1 920 434 3366",
    "sg:postcode":"54313",
    "sg:province":"WI",
    "sg:tags":[
        "plumbing",
        "contractor"
    ],
    "wof:name":"Conrad Plumbing LLC",
    "wof:placetype":"venue"
},
  "geometry": {"coordinates":[-88.11403,44.618265],"type":"Point"}
}