{
  "type": "Feature",
  "properties": {
    "iso:country":"US",
    "sg:address":"1609 NE Frontage Rd",
    "sg:city":"Sturtevant",
    "sg:classifiers":[
        {
            "category":"Bars & Pubs",
            "type":"Food & Drink"
        }
    ],
    "sg:phone":"+1 262 886 2210",
    "sg:postcode":"53177",
    "sg:province":"WI",
    "wof:name":"Vic's Clique",
    "wof:placetype":"venue"
},
  "geometry": {"coordinates":[-87.953654,42.742531],"type":"Point"}
}