{
  "type": "Feature",
  "properties": {
    "iso:country":"US",
    "sg:address":"4170 Stonegate Dr",
    "sg:city":"Oshkosh",
    "sg:classifiers":[
        {
            "category":"Manufacturing",
            "subcategory":"Furniture",
            "type":"Manufacturing & Wholesale Goods"
        }
    ],
    "sg:phone":"+1 920 235 5233",
    "sg:postcode":"54904",
    "sg:province":"WI",
    "sg:tags":[
        "upholstered",
        "household",
        "mfg"
    ],
    "wof:name":"Wayne Hawley Inc",
    "wof:placetype":"venue"
},
  "geometry": {"coordinates":[-88.638521,44.049316],"type":"Point"}
}