{
  "type": "Feature",
  "properties": {
    "iso:country":"US",
    "sg:address":"1377 Kimberly Dr",
    "sg:city":"Neenah",
    "sg:classifiers":[
        {
            "category":"Manufacturing",
            "subcategory":"Tools & Machinery",
            "type":"Manufacturing & Wholesale Goods"
        }
    ],
    "sg:phone":"+1 920 722 0101",
    "sg:postcode":"54956",
    "sg:province":"WI",
    "sg:tags":[
        "equipment",
        "lifting",
        "mfg"
    ],
    "sg:website":"www.contrxcranes.com",
    "wof:name":"Contrx Industries Inc",
    "wof:placetype":"venue"
},
  "geometry": {"coordinates":[-88.49502099999999,44.205658],"type":"Point"}
}