{
  "type": "Feature",
  "properties": {
    "addr:full":"5832 S Packard Ave Cudahy WI 53110",
    "addr:housenumber":"5832",
    "addr:postcode":"53110",
    "addr:street":"S Packard Ave",
    "iso:country":"US",
    "sg:address":"5832 S Packard Ave",
    "sg:city":"Cudahy",
    "sg:classifiers":[
        {
            "category":"Bars & Pubs",
            "type":"Food & Drink"
        }
    ],
    "sg:phone":"+1 414 483 7787",
    "sg:postcode":"53110",
    "sg:province":"WI",
    "sg:tags":[
        "tavern"
    ],
    "wof:name":"Coaches Corner",
    "wof:placetype":"venue"
},
  "geometry": {"coordinates":[-87.860191,42.937497],"type":"Point"}
}