{
  "type": "Feature",
  "properties": {
    "iso:country":"US",
    "sg:address":"4756 N New Franken Rd",
    "sg:city":"New Franken",
    "sg:classifiers":[
        {
            "category":"Social Services",
            "subcategory":"Child Care",
            "type":"Services"
        }
    ],
    "sg:phone":"+1 920 866 2727",
    "sg:postcode":"54229",
    "sg:province":"WI",
    "sg:tags":[
        "day"
    ],
    "wof:name":"Kids Korner Inc",
    "wof:placetype":"venue"
},
  "geometry": {"coordinates":[-87.824575,44.614534],"type":"Point"}
}