{
  "type": "Feature",
  "properties": {
    "iso:country":"US",
    "sg:address":"1902 N 6th St",
    "sg:city":"Wausau",
    "sg:classifiers":[
        {
            "category":"Retail",
            "subcategory":"Laundry & Dry Cleaning",
            "type":"Services"
        }
    ],
    "sg:phone":"+1 715 848 4023",
    "sg:postcode":"54403",
    "sg:province":"WI",
    "sg:tags":[
        "plant"
    ],
    "sg:website":"www.classiccleaners.com",
    "wof:name":"Classic Cleaners",
    "wof:placetype":"venue"
},
  "geometry": {"coordinates":[-89.623477,44.972784],"type":"Point"}
}