{
  "type": "Feature",
  "properties": {
    "iso:country":"US",
    "sg:address":"5286 Co Rd A",
    "sg:city":"Lancaster",
    "sg:classifiers":[
        {
            "category":"Manufacturing",
            "subcategory":"Tools & Machinery",
            "type":"Manufacturing & Wholesale Goods"
        }
    ],
    "sg:phone":"+1 608 723 7374",
    "sg:postcode":"53813",
    "sg:province":"WI",
    "sg:tags":[
        "machine",
        "shop"
    ],
    "wof:name":"J C Sitts Mfg",
    "wof:placetype":"venue"
},
  "geometry": {"coordinates":[-90.683457,42.849798],"type":"Point"}
}