{
  "type": "Feature",
  "properties": {
    "iso:country":"US",
    "sg:address":"5150 Co Hwy Kk",
    "sg:city":"Monroe",
    "sg:classifiers":[
        {
            "category":"Building & Trades",
            "subcategory":"Construction",
            "type":"Services"
        }
    ],
    "sg:phone":"+1 608 325 1744",
    "sg:postcode":"53566",
    "sg:province":"WI",
    "sg:tags":[
        "gutter",
        "exterior"
    ],
    "wof:name":"Guys Home Improvement Inc",
    "wof:placetype":"venue"
},
  "geometry": {"coordinates":[-89.608509,42.596247],"type":"Point"}
}