{
  "type": "Feature",
  "properties": {
    "iso:country":"US",
    "sg:address":"8 Pierce Ct",
    "sg:city":"Appleton",
    "sg:classifiers":[
        {
            "category":"Professional",
            "subcategory":"Management & Consulting",
            "type":"Services"
        }
    ],
    "sg:phone":"+1 920 739 1862",
    "sg:postcode":"54914",
    "sg:province":"WI",
    "wof:name":"Macgregor Paper Consulting",
    "wof:placetype":"venue"
},
  "geometry": {"coordinates":[-88.418767,44.253121],"type":"Point"}
}