{
  "type": "Feature",
  "properties": {
    "addr:full":"407 Grand Ave Merrill WI 54452",
    "addr:housenumber":"407",
    "addr:postcode":"54452",
    "addr:street":"Grand Ave",
    "iso:country":"US",
    "sg:address":"407 Grand Ave",
    "sg:city":"Merrill",
    "sg:classifiers":[
        {
            "category":"Shopping",
            "subcategory":"Used Merchandise",
            "type":"Retail Goods"
        }
    ],
    "sg:phone":"+1 715 536 7241",
    "sg:postcode":"54452",
    "sg:province":"WI",
    "sg:tags":[
        "shop",
        "thrift"
    ],
    "wof:name":"Helping Hands Bargain Center",
    "wof:placetype":"venue"
},
  "geometry": {"coordinates":[-89.705676,45.180258],"type":"Point"}
}