{
  "type": "Feature",
  "properties": {
    "addr:full":"901 University Ave Green Bay WI 54302",
    "addr:housenumber":"901",
    "addr:postcode":"54302",
    "addr:street":"University Ave",
    "iso:country":"US",
    "sg:address":"901 University Ave",
    "sg:city":"Green Bay",
    "sg:classifiers":[
        {
            "category":"Government",
            "subcategory":"Office",
            "type":"Public Place"
        }
    ],
    "sg:phone":"+1 920 448 3454",
    "sg:postcode":"54302",
    "sg:province":"WI",
    "sg:tags":[
        "city",
        "program"
    ],
    "wof:name":"Green Bay City Transit Office",
    "wof:placetype":"venue"
},
  "geometry": {"coordinates":[-88.00303,44.517316],"type":"Point"}
}