{
  "type": "Feature",
  "properties": {
    "iso:country":"US",
    "sg:address":"111 N Main St",
    "sg:city":"Shawano",
    "sg:classifiers":[
        {
            "category":"Professional",
            "subcategory":"Lawyer & Legal Services",
            "type":"Services"
        }
    ],
    "sg:phone":"+1 715 526 2022",
    "sg:postcode":"54166",
    "sg:province":"WI",
    "sg:tags":[
        "attorney"
    ],
    "wof:name":"David R Winter Law Office",
    "wof:placetype":"venue"
},
  "geometry": {"coordinates":[-88.60948999999999,44.783125],"type":"Point"}
}