{
  "type": "Feature",
  "properties": {
    "iso:country":"US",
    "sg:address":"16760 Victor Rd",
    "sg:city":"New Berlin",
    "sg:classifiers":[
        {
            "category":"Recreation",
            "type":"Entertainment"
        }
    ],
    "sg:phone":"+1 262 789 6885",
    "sg:postcode":"53151",
    "sg:province":"WI",
    "sg:tags":[
        "instruction",
        "gymnastic"
    ],
    "sg:website":"www.mmgymnastics.com",
    "wof:name":"M & M Gymnastics",
    "wof:placetype":"venue"
},
  "geometry": {"coordinates":[-88.121814,42.986861],"type":"Point"}
}