{
  "type": "Feature",
  "properties": {
    "iso:country":"US",
    "sg:address":"6180 N 64th St",
    "sg:city":"Milwaukee",
    "sg:classifiers":[
        {
            "category":"Bars & Pubs",
            "type":"Food & Drink"
        }
    ],
    "sg:phone":"+1 414 464 3114",
    "sg:postcode":"53218",
    "sg:province":"WI",
    "sg:tags":[
        "drinking",
        "eating"
    ],
    "wof:name":"Douglas Inn",
    "wof:placetype":"venue"
},
  "geometry": {"coordinates":[-87.990809,43.130906],"type":"Point"}
}