{
  "type": "Feature",
  "properties": {
    "iso:country":"US",
    "sg:address":"1791 220th Ave",
    "sg:city":"New Richmond",
    "sg:phone":"+1 715 248 3690",
    "sg:postcode":"54017",
    "sg:province":"WI",
    "sg:tags":[
        "farm",
        "field",
        "corn",
        "soybean",
        "crop"
    ],
    "wof:name":"Craig Erlitz",
    "wof:placetype":"venue"
},
  "geometry": {"coordinates":[-92.439166,45.180464],"type":"Point"}
}