{
  "type": "Feature",
  "properties": {
    "iso:country":"US",
    "sg:address":"670 Co Rd Ss",
    "sg:city":"Luxemburg",
    "sg:classifiers":[
        {
            "category":"Real Estate",
            "subcategory":"Real Estate Operator",
            "type":"Services"
        }
    ],
    "sg:phone":"+1 920 866 2247",
    "sg:postcode":"54217",
    "sg:province":"WI",
    "sg:tags":[
        "property",
        "lessor"
    ],
    "wof:name":"Marvin Mercier",
    "wof:placetype":"venue"
},
  "geometry": {"coordinates":[-87.736475,44.617677],"type":"Point"}
}