{
  "type": "Feature",
  "properties": {
    "iso:country":"US",
    "sg:address":"2201 E River Rd",
    "sg:city":"Berlin",
    "sg:classifiers":[
        {
            "category":"Farming",
            "subcategory":"Livestock Farm",
            "type":"Manufacturing & Wholesale Goods"
        }
    ],
    "sg:phone":"+1 920 361 3396",
    "sg:postcode":"54923",
    "sg:province":"WI",
    "sg:tags":[
        "beef",
        "feedlot",
        "cattle"
    ],
    "wof:name":"Daniel Hardel",
    "wof:placetype":"venue"
},
  "geometry": {"coordinates":[-88.986916,43.931742],"type":"Point"}
}