{
  "type": "Feature",
  "properties": {
    "iso:country":"US",
    "sg:address":"8824 W Brown Deer Rd",
    "sg:city":"Milwaukee",
    "sg:classifiers":[
        {
            "category":"Freight",
            "type":"Transportation"
        }
    ],
    "sg:phone":"+1 414 354 1467",
    "sg:postcode":"53224",
    "sg:province":"WI",
    "sg:tags":[
        "commercial",
        "storage",
        "general"
    ],
    "wof:name":"Public Storage Inc",
    "wof:placetype":"venue"
},
  "geometry": {"coordinates":[-88.0205,43.17783],"type":"Point"}
}