{
  "type": "Feature",
  "properties": {
    "addr:full":"3172 Muirfield Rd Madison WI 53719",
    "addr:housenumber":"3172",
    "addr:postcode":"53719",
    "addr:street":"Muirfield Rd",
    "iso:country":"US",
    "sg:address":"3172 Muirfield Rd",
    "sg:city":"Madison",
    "sg:classifiers":[
        {
            "category":"Restaurant",
            "type":"Food & Drink"
        }
    ],
    "sg:phone":"+1 608 848 2570",
    "sg:postcode":"53719",
    "sg:province":"WI",
    "sg:tags":[
        "eating"
    ],
    "wof:name":"O Wah Tung",
    "wof:placetype":"venue"
},
  "geometry": {"coordinates":[-89.511577,43.016566],"type":"Point"}
}