{
  "type": "Feature",
  "properties": {
    "iso:country":"US",
    "sg:address":"1 University Plz",
    "sg:city":"Platteville",
    "sg:classifiers":[
        {
            "category":"Education",
            "subcategory":"College",
            "type":"Public Place"
        }
    ],
    "sg:phone":"+1 608 342 1151",
    "sg:postcode":"53818",
    "sg:province":"WI",
    "sg:tags":[
        "university"
    ],
    "wof:name":"College Liberal Arts & Educatn",
    "wof:placetype":"venue"
},
  "geometry": {"coordinates":[-90.49310699999999,42.733786],"type":"Point"}
}