{
  "type": "Feature",
  "properties": {
    "iso:country":"US",
    "sg:address":"323 N Dewey St",
    "sg:city":"Eau Claire",
    "sg:classifiers":[
        {
            "category":"Freight",
            "type":"Transportation"
        }
    ],
    "sg:phone":"+1 715 858 5800",
    "sg:postcode":"54703",
    "sg:province":"WI",
    "sg:tags":[
        "commercial",
        "storage"
    ],
    "wof:name":"Affordable Self Storage",
    "wof:placetype":"venue"
},
  "geometry": {"coordinates":[-91.499078,44.816404],"type":"Point"}
}