{
  "type": "Feature",
  "properties": {
    "iso:country":"US",
    "sg:address":"38582 US Hwy 18",
    "sg:city":"Prairie Du Chien",
    "sg:classifiers":[
        {
            "category":"Wholesale",
            "subcategory":"Toys & Hobbies",
            "type":"Manufacturing & Wholesale Goods"
        }
    ],
    "sg:phone":"+1 608 326 0015",
    "sg:postcode":"53821",
    "sg:province":"WI",
    "sg:tags":[
        "firework"
    ],
    "wof:name":"Platt River Fireworks",
    "wof:placetype":"venue"
},
  "geometry": {"coordinates":[-91.074652,43.012051],"type":"Point"}
}