{
  "type": "Feature",
  "properties": {
    "iso:country":"US",
    "sg:address":"6166 S Packard Ave",
    "sg:city":"Cudahy",
    "sg:classifiers":[
        {
            "category":"Building & Trades",
            "subcategory":"Plumbing",
            "type":"Services"
        }
    ],
    "sg:phone":"+1 414 744 9910",
    "sg:postcode":"53110",
    "sg:province":"WI",
    "sg:tags":[
        "plumbing",
        "contractor"
    ],
    "wof:name":"AAA All American Plumbing",
    "wof:placetype":"venue"
},
  "geometry": {"coordinates":[-87.860787,42.931046],"type":"Point"}
}