{
  "type": "Feature",
  "properties": {
    "iso:country":"US",
    "sg:address":"250 Galena St",
    "sg:city":"Prairie Du Sac",
    "sg:classifiers":[
        {
            "category":"Retail",
            "subcategory":"Self-service Laundry",
            "type":"Services"
        }
    ],
    "sg:phone":"+1 608 643 2856",
    "sg:postcode":"53578",
    "sg:province":"WI",
    "sg:tags":[
        "coin"
    ],
    "wof:name":"Hometown Laundry Center",
    "wof:placetype":"venue"
},
  "geometry": {"coordinates":[-89.72246699999999,43.291875],"type":"Point"}
}