{
  "type": "Feature",
  "properties": {
    "iso:country":"US",
    "sg:address":"307 W Madison St",
    "sg:city":"Lake Mills",
    "sg:classifiers":[
        {
            "category":"Organizations",
            "subcategory":"Religious Organization",
            "type":"Services"
        }
    ],
    "sg:phone":"+1 920 648 5813",
    "sg:postcode":"53551",
    "sg:province":"WI",
    "sg:tags":[
        "church"
    ],
    "sg:website":"www.ucclakemills.org",
    "wof:name":"First Congregational United",
    "wof:placetype":"venue"
},
  "geometry": {"coordinates":[-88.913186,43.08267],"type":"Point"}
}