{
  "type": "Feature",
  "properties": {
    "addr:full":"7311 Edgewater Ct Eau Claire WI 54703",
    "addr:housenumber":"7311",
    "addr:postcode":"54703",
    "addr:street":"Edgewater Ct",
    "iso:country":"US",
    "sg:address":"7311 Edgewater Ct",
    "sg:city":"Eau Claire",
    "sg:classifiers":[
        {
            "category":"Shopping",
            "subcategory":"Bicycles & Sporting Goods",
            "type":"Retail Goods"
        }
    ],
    "sg:phone":"+1 715 855 8380",
    "sg:postcode":"54703",
    "sg:province":"WI",
    "sg:tags":[
        "equipment",
        "exercise"
    ],
    "wof:name":"Magnum Fitness Systems",
    "wof:placetype":"venue"
},
  "geometry": {"coordinates":[-91.38494799999999,44.814191],"type":"Point"}
}