{
  "type": "Feature",
  "properties": {
    "iso:country":"US",
    "sg:address":"2657 Finger Rd",
    "sg:city":"Green Bay",
    "sg:classifiers":[
        {
            "category":"Building & Trades",
            "subcategory":"Construction",
            "type":"Services"
        }
    ],
    "sg:phone":"+1 920 366 5221",
    "sg:postcode":"54302",
    "sg:province":"WI",
    "sg:tags":[
        "painter"
    ],
    "wof:name":"Pro Painting & Design",
    "wof:placetype":"venue"
},
  "geometry": {"coordinates":[-87.948706,44.488174],"type":"Point"}
}