{
  "type": "Feature",
  "properties": {
    "iso:country":"US",
    "sg:address":"3931 State Hwy 22",
    "sg:city":"Oconto",
    "sg:classifiers":[
        {
            "category":"Autos & Motor Vehicles",
            "subcategory":"Auto Supplies",
            "type":"Retail Goods"
        }
    ],
    "sg:phone":"+1 920 834 5594",
    "sg:postcode":"54153",
    "sg:province":"WI",
    "wof:name":"Piontek Auto & Storage",
    "wof:placetype":"venue"
},
  "geometry": {"coordinates":[-87.961868,44.89264],"type":"Point"}
}