{
  "type": "Feature",
  "properties": {
    "iso:country":"US",
    "sg:address":"21218 W Main St",
    "sg:city":"Lannon",
    "sg:classifiers":[
        {
            "category":"Shopping",
            "subcategory":"Gifts & Souvenirs",
            "type":"Retail Goods"
        }
    ],
    "sg:phone":"+1 262 255 0515",
    "sg:postcode":"53046",
    "sg:province":"WI",
    "wof:name":"Creative Treasures & Gifts",
    "wof:placetype":"venue"
},
  "geometry": {"coordinates":[-88.183,43.139704],"type":"Point"}
}