{
  "type": "Feature",
  "properties": {
    "addr:full":"6439 W North Ave Milwaukee WI 53213",
    "addr:housenumber":"6439",
    "addr:postcode":"53213",
    "addr:street":"W North Ave",
    "iso:country":"US",
    "sg:address":"6439 W North Ave",
    "sg:city":"Milwaukee",
    "sg:classifiers":[
        {
            "category":"Personal",
            "subcategory":"Beauty Salon",
            "type":"Services"
        }
    ],
    "sg:phone":"+1 414 443 1386",
    "sg:postcode":"53213",
    "sg:province":"WI",
    "sg:tags":[
        "shop"
    ],
    "wof:name":"Fifi Expert African Hair Braid",
    "wof:placetype":"venue"
},
  "geometry": {"coordinates":[-87.99310699999999,43.060646],"type":"Point"}
}