{
  "type": "Feature",
  "properties": {
    "iso:country":"US",
    "sg:address":"319 E Howard Ave",
    "sg:city":"Milwaukee",
    "sg:classifiers":[
        {
            "category":"Shopping",
            "subcategory":"Florist",
            "type":"Retail Goods"
        }
    ],
    "sg:phone":"+1 414 489 9463",
    "sg:postcode":"53207",
    "sg:province":"WI",
    "wof:name":"Tulipomania Inc",
    "wof:placetype":"venue"
},
  "geometry": {"coordinates":[-87.90640399999999,42.973679],"type":"Point"}
}