{
  "type": "Feature",
  "properties": {
    "iso:country":"US",
    "sg:address":"6712 Odana Rd",
    "sg:city":"Madison",
    "sg:classifiers":[
        {
            "category":"Wholesale",
            "subcategory":"Machinery & Supplies",
            "type":"Manufacturing & Wholesale Goods"
        }
    ],
    "sg:phone":"+1 608 829 0299",
    "sg:postcode":"53719",
    "sg:province":"WI",
    "sg:tags":[
        "equipment",
        "salon",
        "establishment",
        "beauty"
    ],
    "wof:name":"National Supply Beauty Mart",
    "wof:placetype":"venue"
},
  "geometry": {"coordinates":[-89.501284,43.056673],"type":"Point"}
}