{
  "type": "Feature",
  "properties": {
    "iso:country":"US",
    "sg:address":"4800 Terminal Dr",
    "sg:city":"Mc Farland",
    "sg:classifiers":[
        {
            "category":"Freight",
            "type":"Transportation"
        }
    ],
    "sg:phone":"+1 608 838 7867",
    "sg:postcode":"53558",
    "sg:province":"WI",
    "sg:tags":[
        "commercial",
        "storage"
    ],
    "wof:name":"Store More Storage",
    "wof:placetype":"venue"
},
  "geometry": {"coordinates":[-89.30264200000001,43.028911],"type":"Point"}
}