{
  "type": "Feature",
  "properties": {
    "iso:country":"US",
    "sg:address":"1372 Co Rd S",
    "sg:city":"Onalaska",
    "sg:classifiers":[
        {
            "category":"Building & Trades",
            "subcategory":"Cleaning & Sanitation",
            "type":"Services"
        }
    ],
    "sg:phone":"+1 608 781 1994",
    "sg:postcode":"54650",
    "sg:province":"WI",
    "sg:tags":[
        "maintenance"
    ],
    "wof:name":"Classic Quality Service",
    "wof:placetype":"venue"
},
  "geometry": {"coordinates":[-89.831541,44.111833],"type":"Point"}
}