{
  "type": "Feature",
  "properties": {
    "iso:country":"US",
    "sg:address":"21495 Woodchuck Ln",
    "sg:city":"Brookfield",
    "sg:classifiers":[
        {
            "category":"Real Estate",
            "subcategory":"Real Estate Agent",
            "type":"Services"
        }
    ],
    "sg:phone":"+1 262 827 4933",
    "sg:postcode":"53045",
    "sg:province":"WI",
    "wof:name":"V E Wandrus Co",
    "wof:placetype":"venue"
},
  "geometry": {"coordinates":[-88.17725,43.057142],"type":"Point"}
}