{
  "type": "Feature",
  "properties": {
    "iso:country":"US",
    "sg:address":"625 S 5th St",
    "sg:city":"Milwaukee",
    "sg:classifiers":[
        {
            "category":"Restaurant",
            "type":"Food & Drink"
        }
    ],
    "sg:phone":"+1 414 271 8595",
    "sg:postcode":"53204",
    "sg:province":"WI",
    "sg:tags":[
        "mexican"
    ],
    "wof:name":"La Fuente Ltd",
    "wof:placetype":"venue"
},
  "geometry": {"coordinates":[-87.916924,43.024475],"type":"Point"}
}