{
  "type": "Feature",
  "properties": {
    "iso:country":"US",
    "sg:address":"12117 Cedar Creek Rd",
    "sg:city":"Cedarburg",
    "sg:classifiers":[
        {
            "category":"Manufacturing",
            "subcategory":"Metals",
            "type":"Manufacturing & Wholesale Goods"
        }
    ],
    "sg:phone":"+1 262 546 0073",
    "sg:postcode":"53012",
    "sg:province":"WI",
    "wof:name":"General Metal Works",
    "wof:placetype":"venue"
},
  "geometry": {"coordinates":[-88.059049,43.336704],"type":"Point"}
}