{
  "type": "Feature",
  "properties": {
    "addr:full":"6596 Riverview Rd Plymouth WI 53073",
    "addr:housenumber":"6596",
    "addr:postcode":"53073",
    "addr:street":"Riverview Rd",
    "iso:country":"US",
    "sg:address":"6596 Riverview Rd",
    "sg:city":"Plymouth",
    "sg:classifiers":[
        {
            "category":"Professional",
            "subcategory":"Accounting & Tax Preparation",
            "type":"Services"
        }
    ],
    "sg:phone":"+1 920 893 5656",
    "sg:postcode":"53073",
    "sg:province":"WI",
    "wof:name":"Jk Executive Direction LLC",
    "wof:placetype":"venue"
},
  "geometry": {"coordinates":[-87.993236,43.7789],"type":"Point"}
}