{
  "type": "Feature",
  "properties": {
    "iso:country":"US",
    "sg:address":"3491 Co Rd F",
    "sg:city":"Helenville",
    "sg:classifiers":[
        {
            "category":"Personal",
            "type":"Services"
        }
    ],
    "sg:phone":"+1 262 593 2295",
    "sg:postcode":"53137",
    "sg:province":"WI",
    "wof:name":"Allmax LLC",
    "wof:placetype":"venue"
},
  "geometry": {"coordinates":[-88.630716,42.945262],"type":"Point"}
}