{
  "type": "Feature",
  "properties": {
    "addr:full":"498 W Scott St Fond Du Lac WI 54937",
    "addr:housenumber":"498",
    "addr:postcode":"54937",
    "addr:street":"W Scott St",
    "iso:country":"US",
    "sg:address":"498 W Scott St",
    "sg:city":"Fond Du Lac",
    "sg:classifiers":[
        {
            "category":"Insurance",
            "subcategory":"Insurance Agent",
            "type":"Services"
        }
    ],
    "sg:phone":"+1 920 921 0500",
    "sg:postcode":"54937",
    "sg:province":"WI",
    "wof:name":"State Farm Insurance",
    "wof:placetype":"venue"
},
  "geometry": {"coordinates":[-88.46743499999999,43.79172],"type":"Point"}
}