{
  "type": "Feature",
  "properties": {
    "iso:country":"US",
    "sg:address":"1705 Cranston Rd",
    "sg:city":"Beloit",
    "sg:classifiers":[
        {
            "category":"Manufacturing",
            "subcategory":"Metals",
            "type":"Manufacturing & Wholesale Goods"
        },
        {
            "category":"Professional",
            "subcategory":"Business Services",
            "type":"Services"
        }
    ],
    "sg:phone":"+1 608 361 0200",
    "sg:postcode":"53511",
    "sg:province":"WI",
    "sg:tags":[
        "tool"
    ],
    "wof:name":"American Industrial Mfg Inc",
    "wof:placetype":"venue"
},
  "geometry": {"coordinates":[-89.018974,42.532244],"type":"Point"}
}