{
  "type": "Feature",
  "properties": {
    "iso:country":"US",
    "sg:address":"8635 W. Warnimont St.",
    "sg:city":"Milwaukee",
    "sg:classifiers":[
        {
            "category":"Place Of Worship",
            "subcategory":"Church",
            "type":"Public Place"
        },
        {
            "category":"Place Of Worship",
            "type":"Public Place"
        }
    ],
    "sg:phone":"+1 414 383 1477",
    "sg:postcode":"53204",
    "sg:province":"WI",
    "sg:tags":[
        "churches-eastern",
        "orthodox"
    ],
    "wof:name":"Holy Trinity Russian Orthodox Church",
    "wof:placetype":"venue"
},
  "geometry": {"coordinates":[-88.02065899999999,42.979164],"type":"Point"}
}