{
  "type": "Feature",
  "properties": {
    "iso:country":"US",
    "sg:address":"762 Armstrong Rd",
    "sg:city":"Campbellsport",
    "sg:classifiers":[
        {
            "category":"Organizations",
            "subcategory":"Religious Organization",
            "type":"Services"
        }
    ],
    "sg:phone":"+1 920 477 3201",
    "sg:postcode":"53010",
    "sg:province":"WI",
    "wof:name":"Our Lady of The Angels Parish",
    "wof:placetype":"venue"
},
  "geometry": {"coordinates":[-88.195652,43.710485],"type":"Point"}
}