{
  "type": "Feature",
  "properties": {
    "iso:country":"US",
    "sg:address":"225 Parkview Dr",
    "sg:city":"Milton",
    "sg:classifiers":[
        {
            "category":"Professional",
            "subcategory":"Advertising",
            "type":"Services"
        }
    ],
    "sg:phone":"+1 608 868 7288",
    "sg:postcode":"53563",
    "sg:province":"WI",
    "sg:tags":[
        "agency"
    ],
    "wof:name":"USA Easy ADS",
    "wof:placetype":"venue"
},
  "geometry": {"coordinates":[-88.938875,42.774381],"type":"Point"}
}