{
  "type": "Feature",
  "properties": {
    "iso:country":"US",
    "sg:address":"2535 Knapp St",
    "sg:city":"Oshkosh",
    "sg:classifiers":[
        {
            "category":"Personal",
            "type":"Services"
        }
    ],
    "sg:phone":"+1 920 235 7081",
    "sg:postcode":"54902",
    "sg:province":"WI",
    "wof:name":"Gams LLC",
    "wof:placetype":"venue"
},
  "geometry": {"coordinates":[-88.562791,43.986147],"type":"Point"}
}