{
  "type": "Feature",
  "properties": {
    "iso:country":"US",
    "sg:address":"4101 Hoover Ave",
    "sg:city":"Plover",
    "sg:classifiers":[
        {
            "category":"Home & Garden",
            "subcategory":"Building Materials",
            "type":"Retail Goods"
        }
    ],
    "sg:phone":"+1 715 343 2713",
    "sg:postcode":"54467",
    "sg:province":"WI",
    "sg:tags":[
        "glass",
        "window",
        "plate"
    ],
    "wof:name":"Safelite Auto Glass",
    "wof:placetype":"venue"
},
  "geometry": {"coordinates":[-89.528792,44.437613],"type":"Point"}
}