{
  "type": "Feature",
  "properties": {
    "iso:country":"US",
    "sg:address":"4737 Jackson Dr",
    "sg:city":"West Bend",
    "sg:classifiers":[
        {
            "category":"Recreation",
            "type":"Entertainment"
        }
    ],
    "sg:phone":"+1 262 677 2356",
    "sg:postcode":"53095",
    "sg:province":"WI",
    "sg:tags":[
        "stable"
    ],
    "wof:name":"Whisperwood Acres Boarding",
    "wof:placetype":"venue"
},
  "geometry": {"coordinates":[-88.161703,43.359255],"type":"Point"}
}