{
  "type": "Feature",
  "properties": {
    "iso:country":"US",
    "sg:address":"8781 Co Rd F",
    "sg:city":"Fish Creek",
    "sg:classifiers":[
        {
            "category":"Organizations",
            "subcategory":"Religious Organization",
            "type":"Services"
        }
    ],
    "sg:phone":"+1 920 839 9758",
    "sg:postcode":"54212",
    "sg:province":"WI",
    "sg:tags":[
        "church"
    ],
    "wof:name":"Zion United Methodist",
    "wof:placetype":"venue"
},
  "geometry": {"coordinates":[-87.161653,45.099372],"type":"Point"}
}