{
  "type": "Feature",
  "properties": {
    "iso:country":"US",
    "sg:address":"2325 Sun Valley Dr",
    "sg:city":"Delafield",
    "sg:classifiers":[
        {
            "category":"Retail",
            "subcategory":"Auto Repair",
            "type":"Services"
        }
    ],
    "sg:phone":"+1 262 646 5640",
    "sg:postcode":"53018",
    "sg:province":"WI",
    "sg:tags":[
        "automotive"
    ],
    "wof:name":"Pennzoil 10 Minute Oil Change",
    "wof:placetype":"venue"
},
  "geometry": {"coordinates":[-88.37903900000001,43.050871],"type":"Point"}
}