{
  "type": "Feature",
  "properties": {
    "iso:country":"US",
    "sg:address":"2500 Milton Ave",
    "sg:city":"Janesville",
    "sg:classifiers":[
        {
            "category":"Shopping",
            "subcategory":"Optical Goods",
            "type":"Retail Goods"
        }
    ],
    "sg:phone":"+1 608 757 1494",
    "sg:postcode":"53545",
    "sg:province":"WI",
    "sg:tags":[
        "center"
    ],
    "wof:name":"Lenscrafters 540",
    "wof:placetype":"venue"
},
  "geometry": {"coordinates":[-89.001144,42.712623],"type":"Point"}
}