{
  "type": "Feature",
  "properties": {
    "iso:country":"US",
    "sg:address":"4266 S 60th St",
    "sg:city":"Milwaukee",
    "sg:classifiers":[
        {
            "category":"Retail",
            "subcategory":"Auto Repair",
            "type":"Services"
        }
    ],
    "sg:phone":"+1 414 543 0934",
    "sg:postcode":"53220",
    "sg:province":"WI",
    "sg:tags":[
        "automotive"
    ],
    "wof:name":"North Star Automotive Group",
    "wof:placetype":"venue"
},
  "geometry": {"coordinates":[-87.988169,42.967035],"type":"Point"}
}