{
  "type": "Feature",
  "properties": {
    "addr:full":"11700 N Port Washington Rd Mequon WI 53092",
    "addr:housenumber":"11700",
    "addr:postcode":"53092",
    "addr:street":"N Port Washington Rd",
    "iso:country":"US",
    "sg:address":"11700 N Port Washington Rd",
    "sg:city":"Mequon",
    "sg:classifiers":[
        {
            "category":"Restaurant",
            "type":"Food & Drink"
        }
    ],
    "sg:phone":"+1 262 241 8484",
    "sg:postcode":"53092",
    "sg:province":"WI",
    "sg:tags":[
        "italian",
        "pizza"
    ],
    "sg:website":"www.zaffirospizzabar.com/",
    "wof:name":"Zaffiro's",
    "wof:placetype":"venue"
},
  "geometry": {"coordinates":[-87.92406099999999,43.230897],"type":"Point"}
}