{
  "type": "Feature",
  "properties": {
    "iso:country":"US",
    "sg:address":"10841 Smokey Mountain Trl",
    "sg:city":"Blue Mounds",
    "sg:classifiers":[
        {
            "category":"Food & Beverages",
            "subcategory":"Specialty",
            "type":"Retail Goods"
        },
        {
            "category":"Professional",
            "subcategory":"Management & Consulting",
            "type":"Services"
        }
    ],
    "sg:phone":"+1 608 437 7021",
    "sg:postcode":"53517",
    "sg:province":"WI",
    "sg:tags":[
        "bulk",
        "water",
        "company",
        "direct",
        "sales"
    ],
    "wof:name":"Nicolet Water Mount Horeb LLC",
    "wof:placetype":"venue"
},
  "geometry": {"coordinates":[-89.821671,43.014908],"type":"Point"}
}