{
  "type": "Feature",
  "properties": {
    "iso:country":"US",
    "sg:address":"205 S Jefferson St",
    "sg:city":"Green Bay",
    "sg:classifiers":[
        {
            "category":"Professional",
            "type":"Services"
        }
    ],
    "sg:phone":"+1 920 431 0602",
    "sg:postcode":"54301",
    "sg:province":"WI",
    "sg:tags":[
        "establishment"
    ],
    "wof:name":"Netlec",
    "wof:placetype":"venue"
},
  "geometry": {"coordinates":[-88.014779,44.51105],"type":"Point"}
}