{
  "type": "Feature",
  "properties": {
    "iso:country":"US",
    "sg:address":"2711 Pendleton Pl",
    "sg:city":"Waukesha",
    "sg:classifiers":[
        {
            "category":"Professional",
            "type":"Services"
        }
    ],
    "sg:phone":"+1 262 548 6103",
    "sg:postcode":"53188",
    "sg:province":"WI",
    "wof:name":"Corinne Kangas",
    "wof:placetype":"venue"
},
  "geometry": {"coordinates":[-88.276547,43.003421],"type":"Point"}
}