{
  "type": "Feature",
  "properties": {
    "iso:country":"US",
    "sg:address":"317 S Main St",
    "sg:city":"Clintonville",
    "sg:classifiers":[
        {
            "category":"Restaurant",
            "type":"Food & Drink"
        }
    ],
    "sg:phone":"+1 715 823 6137",
    "sg:postcode":"54929",
    "sg:province":"WI",
    "wof:name":"Jerry & Pat's Cafe",
    "wof:placetype":"venue"
},
  "geometry": {"coordinates":[-88.764665,44.605681],"type":"Point"}
}