{
  "type": "Feature",
  "properties": {
    "addr:full":"28226 Durand Ave Burlington WI 53105",
    "addr:housenumber":"28226",
    "addr:postcode":"53105",
    "addr:street":"Durand Ave",
    "iso:country":"US",
    "sg:address":"28226 Durand Ave",
    "sg:city":"Burlington",
    "sg:classifiers":[
        {
            "category":"Retail",
            "subcategory":"Auto Repair",
            "type":"Services"
        }
    ],
    "sg:phone":"+1 262 534 2081",
    "sg:postcode":"53105",
    "sg:province":"WI",
    "sg:tags":[
        "truck"
    ],
    "wof:name":"Clover Leaf Truck Svc",
    "wof:placetype":"venue"
},
  "geometry": {"coordinates":[-88.19879899999999,42.683782],"type":"Point"}
}