{
  "type": "Feature",
  "properties": {
    "addr:full":"775 N Jackson St Milwaukee WI 53202",
    "addr:housenumber":"775",
    "addr:postcode":"53202",
    "addr:street":"N Jackson St",
    "iso:country":"US",
    "sg:address":"775 N Jackson St",
    "sg:city":"Milwaukee",
    "sg:classifiers":[
        {
            "category":"Restaurant",
            "type":"Food & Drink"
        }
    ],
    "sg:phone":"+1 414 276 6262",
    "sg:postcode":"53202",
    "sg:province":"WI",
    "sg:tags":[
        "mexican"
    ],
    "wof:name":"Nacho Mama's",
    "wof:placetype":"venue"
},
  "geometry": {"coordinates":[-87.904202,43.040751],"type":"Point"}
}