{
  "type": "Feature",
  "properties": {
    "iso:country":"US",
    "sg:address":"3529 Gateway Dr",
    "sg:city":"Eau Claire",
    "sg:classifiers":[
        {
            "category":"Restaurant",
            "type":"Food & Drink"
        }
    ],
    "sg:phone":"+1 715 552 0525",
    "sg:postcode":"54701",
    "sg:province":"WI",
    "sg:tags":[
        "eating"
    ],
    "wof:name":"Noodle Wrap",
    "wof:placetype":"venue"
},
  "geometry": {"coordinates":[-91.43177900000001,44.781813],"type":"Point"}
}