{
  "type": "Feature",
  "properties": {
    "iso:country":"US",
    "sg:address":"1620 Miller Park Way",
    "sg:city":"Milwaukee",
    "sg:classifiers":[
        {
            "category":"Home & Garden",
            "subcategory":"Building Materials",
            "type":"Retail Goods"
        }
    ],
    "sg:phone":"+1 414 672 2371",
    "sg:postcode":"53214",
    "sg:province":"WI",
    "sg:tags":[
        "paint"
    ],
    "wof:name":"Pittsburgh Paints",
    "wof:placetype":"venue"
},
  "geometry": {"coordinates":[-87.967553,43.013789],"type":"Point"}
}