{
  "type": "Feature",
  "properties": {
    "addr:full":"270 Kierstead Ln Oregon WI 53575",
    "addr:housenumber":"270",
    "addr:postcode":"53575",
    "addr:street":"Kierstead Ln",
    "iso:country":"US",
    "sg:address":"270 Kierstead Ln",
    "sg:city":"Oregon",
    "sg:classifiers":[
        {
            "category":"Building & Trades",
            "subcategory":"Construction",
            "type":"Services"
        }
    ],
    "sg:phone":"+1 608 938 2150",
    "sg:postcode":"53575",
    "sg:province":"WI",
    "sg:tags":[
        "contractor"
    ],
    "wof:name":"Bychowski Construction LLC",
    "wof:placetype":"venue"
},
  "geometry": {"coordinates":[-89.381017,42.921472],"type":"Point"}
}