{
  "type": "Feature",
  "properties": {
    "iso:country":"US",
    "sg:address":"703 S 2nd St",
    "sg:city":"Milwaukee",
    "sg:classifiers":[
        {
            "category":"Museum",
            "type":"Entertainment"
        },
        {
            "category":"Arts & Performance",
            "subcategory":"Theater",
            "type":"Entertainment"
        }
    ],
    "sg:phone":"+1 414 383 3727",
    "sg:postcode":"53204",
    "sg:province":"WI",
    "sg:tags":[
        "theatres-concert",
        "venue",
        "hall",
        "theatre"
    ],
    "wof:name":"Gay Milwaukee Arts Center Inc",
    "wof:placetype":"venue"
},
  "geometry": {"coordinates":[-87.912628,43.024162],"type":"Point"}
}