{
  "type": "Feature",
  "properties": {
    "addr:city":"Milwaukee",
    "addr:full":"703 S 2Nd St Milwaukee, Wi 53204-1874",
    "addr:house_number":"703",
    "addr:housenumber":"703",
    "addr:phone":"+1 414-383-3727",
    "addr:postcode":"53204-1874",
    "addr:road":"S 2Nd St",
    "addr:state":"WI",
    "addr:street":"S 2Nd St",
    "iso:country":"US",
    "sg:address":"703 S 2nd St",
    "sg:city":"Milwaukee",
    "sg:classifiers":[
        {
            "category":"Museum",
            "type":"Entertainment"
        },
        {
            "category":"Arts & Performance",
            "subcategory":"Theater",
            "type":"Entertainment"
        }
    ],
    "sg:phone":"+1 414 383 3727",
    "sg:postcode":"53204",
    "sg:province":"WI",
    "sg:tags":[
        "theatres-concert",
        "venue",
        "hall",
        "theatre"
    ],
    "wof:airports":[
        102530849
    ],
    "wof:name":"Gay Milwaukee Arts Center",
    "wof:placetype":"venue"
},
  "geometry": {"coordinates":[-87.91271999999999,43.02416],"type":"Point"}
}