{
  "type": "Feature",
  "properties": {
    "iso:country":"US",
    "sg:address":"2527 Mall Dr",
    "sg:city":"Eau Claire",
    "sg:classifiers":[
        {
            "category":"Insurance",
            "subcategory":"Insurance Agent",
            "type":"Services"
        }
    ],
    "sg:phone":"+1 715 858 5540",
    "sg:postcode":"54701",
    "sg:province":"WI",
    "sg:tags":[
        "claim",
        "medical"
    ],
    "wof:name":"Americhoice Health Services",
    "wof:placetype":"venue"
},
  "geometry": {"coordinates":[-91.461502,44.792556],"type":"Point"}
}