{
  "type": "Feature",
  "properties": {
    "addr:full":"530 N Union St Ripon WI 54971",
    "addr:housenumber":"530",
    "addr:postcode":"54971",
    "addr:street":"N Union St",
    "iso:country":"US",
    "sg:address":"530 N Union St",
    "sg:city":"Ripon",
    "sg:classifiers":[
        {
            "category":"Social Services",
            "subcategory":"Adult Care",
            "type":"Services"
        }
    ],
    "sg:phone":"+1 920 745 2959",
    "sg:postcode":"54971",
    "sg:province":"WI",
    "sg:tags":[
        "home",
        "residential"
    ],
    "wof:name":"Michalene's",
    "wof:placetype":"venue"
},
  "geometry": {"coordinates":[-88.849694,43.85302],"type":"Point"}
}