{
  "type": "Feature",
  "properties": {
    "addr:full":"8944 90th Ave Chippewa Falls WI 54729",
    "addr:housenumber":"8944",
    "addr:postcode":"54729",
    "addr:street":"90Th Ave",
    "iso:country":"US",
    "sg:address":"8944 90th Ave",
    "sg:city":"Chippewa Falls",
    "sg:classifiers":[
        {
            "category":"Freight",
            "type":"Transportation"
        }
    ],
    "sg:phone":"+1 715 720 7073",
    "sg:postcode":"54729",
    "sg:province":"WI",
    "sg:tags":[
        "local",
        "trucking",
        "storage",
        "no"
    ],
    "wof:name":"Thonton Trucking LLC",
    "wof:placetype":"venue"
},
  "geometry": {"coordinates":[-91.483559,44.973473],"type":"Point"}
}