{
  "type": "Feature",
  "properties": {
    "iso:country":"US",
    "sg:address":"11430 W North Ave",
    "sg:city":"Milwaukee",
    "sg:classifiers":[
        {
            "category":"Real Estate",
            "subcategory":"Real Estate Agent",
            "type":"Services"
        }
    ],
    "sg:phone":"+1 414 778 5400",
    "sg:postcode":"53226",
    "sg:province":"WI",
    "sg:website":"www.metromls.com",
    "wof:name":"Multiple Listing Svc Inc",
    "wof:placetype":"venue"
},
  "geometry": {"coordinates":[-88.056245,43.059977],"type":"Point"}
}