{
  "type": "Feature",
  "properties": {
    "iso:country":"US",
    "sg:address":"4950 State Hwy 86",
    "sg:city":"Ogema",
    "sg:classifiers":[
        {
            "category":"Organizations",
            "subcategory":"Religious Organization",
            "type":"Services"
        }
    ],
    "sg:phone":"+1 715 767 5155",
    "sg:postcode":"54459",
    "sg:province":"WI",
    "sg:tags":[
        "church"
    ],
    "wof:name":"First Lutheran Church",
    "wof:placetype":"venue"
},
  "geometry": {"coordinates":[-90.293579,45.44607],"type":"Point"}
}