{
  "type": "Feature",
  "properties": {
    "iso:country":"US",
    "sg:address":"1130 N Westfield St",
    "sg:city":"Oshkosh",
    "sg:classifiers":[
        {
            "category":"Health Services",
            "subcategory":"Nursing And Care Facility",
            "type":"Services"
        }
    ],
    "sg:phone":"+1 920 233 2340",
    "sg:postcode":"54902",
    "sg:province":"WI",
    "sg:tags":[
        "home",
        "retirement",
        "community"
    ],
    "sg:website":"www.evergreenoshkosh.com",
    "wof:name":"Evergreen Retirement Community",
    "wof:placetype":"venue"
},
  "geometry": {"coordinates":[-88.57418800000001,44.031873],"type":"Point"}
}