{
  "type": "Feature",
  "properties": {
    "iso:country":"US",
    "sg:address":"659 Acadia Way",
    "sg:city":"Verona",
    "sg:classifiers":[
        {
            "category":"Professional",
            "subcategory":"Advertising",
            "type":"Services"
        }
    ],
    "sg:phone":"+1 608 848 6570",
    "sg:postcode":"53593",
    "sg:province":"WI",
    "sg:tags":[
        "counselor"
    ],
    "wof:name":"Malahat Group Intl",
    "wof:placetype":"venue"
},
  "geometry": {"coordinates":[-89.549154,42.998036],"type":"Point"}
}