{
  "type": "Feature",
  "properties": {
    "iso:country":"US",
    "sg:address":"1818 N Water St",
    "sg:city":"Milwaukee",
    "sg:classifiers":[
        {
            "category":"Professional",
            "subcategory":"Lawyer & Legal Services",
            "type":"Services"
        }
    ],
    "sg:phone":"+1 414 276 7460",
    "sg:postcode":"53202",
    "sg:province":"WI",
    "sg:tags":[
        "firm",
        "law"
    ],
    "wof:name":"Nitschke & Sika SC",
    "wof:placetype":"venue"
},
  "geometry": {"coordinates":[-87.900182,43.055882],"type":"Point"}
}