{
  "type": "Feature",
  "properties": {
    "addr:full":"427 Tower Rd Wautoma WI 54921",
    "addr:housenumber":"427",
    "addr:postcode":"54921",
    "addr:street":"Tower Rd",
    "iso:country":"US",
    "sg:address":"427 Tower Rd",
    "sg:city":"Wautoma",
    "sg:classifiers":[
        {
            "category":"Social Services",
            "type":"Services"
        }
    ],
    "sg:phone":"+1 920 787 4406",
    "sg:postcode":"54921",
    "sg:province":"WI",
    "sg:tags":[
        "probation"
    ],
    "wof:name":"Probation & Parole Div",
    "wof:placetype":"venue"
},
  "geometry": {"coordinates":[-89.586288,44.277607],"type":"Point"}
}