{
  "type": "Feature",
  "properties": {
    "iso:country":"US",
    "sg:address":"10723 Williston Springs Rd",
    "sg:city":"Crivitz",
    "sg:classifiers":[
        {
            "category":"Building & Trades",
            "subcategory":"Construction",
            "type":"Services"
        }
    ],
    "sg:phone":"+1 715 854 7544",
    "sg:postcode":"54114",
    "sg:province":"WI",
    "sg:tags":[
        "house"
    ],
    "wof:name":"Brand Ray General Cnstruction",
    "wof:placetype":"venue"
},
  "geometry": {"coordinates":[-88.14321099999999,45.196842],"type":"Point"}
}