{
  "type": "Feature",
  "properties": {
    "iso:country":"US",
    "sg:address":"782 US Hwy 12",
    "sg:city":"Wisconsin Dells",
    "sg:classifiers":[
        {
            "category":"Retail",
            "subcategory":"Auto Repair",
            "type":"Services"
        }
    ],
    "sg:phone":"+1 608 253 6188",
    "sg:postcode":"53965",
    "sg:province":"WI",
    "sg:tags":[
        "repairing",
        "automobile"
    ],
    "wof:name":"Rodwell Repairs",
    "wof:placetype":"venue"
},
  "geometry": {"coordinates":[-89.79356900000001,43.598673],"type":"Point"}
}