{
  "type": "Feature",
  "properties": {
    "iso:country":"US",
    "sg:address":"2050 Co Rd Mm",
    "sg:city":"Fitchburg",
    "sg:classifiers":[
        {
            "category":"Food & Beverages",
            "subcategory":"Groceries & Convenience Stores",
            "type":"Retail Goods"
        }
    ],
    "sg:phone":"+1 608 835 1696",
    "sg:postcode":"53575",
    "sg:province":"WI",
    "wof:name":"Town & Country Mart",
    "wof:placetype":"venue"
},
  "geometry": {"coordinates":[-89.37235200000001,42.964291],"type":"Point"}
}