{
  "type": "Feature",
  "properties": {
    "iso:country":"US",
    "sg:address":"8880 S Howell Ave",
    "sg:city":"Oak Creek",
    "sg:classifiers":[
        {
            "category":"Real Estate",
            "subcategory":"Real Estate Agent",
            "type":"Services"
        }
    ],
    "sg:phone":"+1 414 762 2900",
    "sg:postcode":"53154",
    "sg:province":"WI",
    "wof:name":"Shorewest Realtors",
    "wof:placetype":"venue"
},
  "geometry": {"coordinates":[-87.912475,42.878235],"type":"Point"}
}