{
  "type": "Feature",
  "properties": {
    "iso:country":"US",
    "sg:address":"5732 W Villard Ave",
    "sg:city":"Milwaukee",
    "sg:classifiers":[
        {
            "category":"Real Estate",
            "subcategory":"Real Estate Agent",
            "type":"Services"
        },
        {
            "category":"Professional",
            "subcategory":"Business Services",
            "type":"Services"
        }
    ],
    "sg:phone":"+1 414 461 4991",
    "sg:postcode":"53218",
    "sg:province":"WI",
    "sg:tags":[
        "inspection"
    ],
    "wof:name":"Complete Inspection Service",
    "wof:placetype":"venue"
},
  "geometry": {"coordinates":[-87.984591,43.112101],"type":"Point"}
}