{
  "type": "Feature",
  "properties": {
    "iso:country":"US",
    "sg:address":"5440 Willow Rd",
    "sg:city":"Waunakee",
    "sg:classifiers":[
        {
            "category":"Insurance",
            "subcategory":"Insurance Agent",
            "type":"Services"
        }
    ],
    "sg:phone":"+1 608 244 1191",
    "sg:postcode":"53597",
    "sg:province":"WI",
    "wof:name":"State Farm Insurance",
    "wof:placetype":"venue"
},
  "geometry": {"coordinates":[-89.41373,43.15154],"type":"Point"}
}