{
  "type": "Feature",
  "properties": {
    "addr:full":"5750 Randal Ln Racine WI 53402",
    "addr:postcode":"5750;53402",
    "addr:street":"Randal Ln",
    "iso:country":"US",
    "sg:address":"5750 Randal Ln",
    "sg:city":"Racine",
    "sg:classifiers":[
        {
            "category":"Organizations",
            "subcategory":"Religious Organization",
            "type":"Services"
        }
    ],
    "sg:phone":"+1 262 681 5746",
    "sg:postcode":"53402",
    "sg:province":"WI",
    "wof:name":"Shiloh Cogic",
    "wof:placetype":"venue"
},
  "geometry": {"coordinates":[-87.809296,42.793907],"type":"Point"}
}