{
  "type": "Feature",
  "properties": {
    "iso:country":"US",
    "sg:address":"1526 Algoma Blvd",
    "sg:city":"Oshkosh",
    "sg:classifiers":[
        {
            "category":"Organizations",
            "subcategory":"Religious Organization",
            "type":"Services"
        }
    ],
    "sg:phone":"+1 920 235 1612",
    "sg:postcode":"54901",
    "sg:province":"WI",
    "sg:tags":[
        "church"
    ],
    "sg:website":"www.martinlutheroshkosh.com",
    "wof:name":"Martin Luther Evan Lutheran",
    "wof:placetype":"venue"
},
  "geometry": {"coordinates":[-88.559176,44.036361],"type":"Point"}
}