{
  "type": "Feature",
  "properties": {
    "addr:full":"4799 Leins Mill Rd East Troy WI 53120",
    "addr:housenumber":"4799",
    "addr:postcode":"53120",
    "addr:street":"Leins Mill Rd",
    "iso:country":"US",
    "sg:address":"4799 Leins Mill Rd",
    "sg:city":"East Troy",
    "sg:classifiers":[
        {
            "category":"Professional",
            "subcategory":"Engineering",
            "type":"Services"
        }
    ],
    "sg:phone":"+1 262 642 7021",
    "sg:postcode":"53120",
    "sg:province":"WI",
    "wof:name":"Idas Engineering",
    "wof:placetype":"venue"
},
  "geometry": {"coordinates":[-88.53694400000001,42.778543],"type":"Point"}
}