{
  "type": "Feature",
  "properties": {
    "addr:full":"1434 N 38th St Sheboygan WI 53081",
    "addr:housenumber":"1434",
    "addr:postcode":"53081",
    "addr:street":"N 38Th St",
    "iso:country":"US",
    "sg:address":"1434 N 38th St",
    "sg:city":"Sheboygan",
    "sg:classifiers":[
        {
            "category":"Retail",
            "subcategory":"Auto Rental",
            "type":"Services"
        }
    ],
    "sg:phone":"+1 920 457 8679",
    "sg:postcode":"53081",
    "sg:province":"WI",
    "sg:tags":[
        "renting",
        "truck",
        "leasing"
    ],
    "wof:name":"Budget Truck Rental",
    "wof:placetype":"venue"
},
  "geometry": {"coordinates":[-87.757707,43.75673],"type":"Point"}
}