{
  "type": "Feature",
  "properties": {
    "iso:country":"US",
    "sg:address":"110 N Main St",
    "sg:city":"Mayville",
    "sg:classifiers":[
        {
            "category":"Home & Garden",
            "subcategory":"Furniture",
            "type":"Retail Goods"
        }
    ],
    "sg:phone":"+1 920 387 3250",
    "sg:postcode":"53050",
    "sg:province":"WI",
    "sg:tags":[
        "appliance"
    ],
    "wof:name":"Guse Appliances and Furniture",
    "wof:placetype":"venue"
},
  "geometry": {"coordinates":[-88.54468900000001,43.497197],"type":"Point"}
}