{
  "type": "Feature",
  "properties": {
    "iso:country":"US",
    "sg:address":"2120 Neva Rd",
    "sg:city":"Antigo",
    "sg:phone":"+1 715 623 4972",
    "sg:postcode":"54409",
    "sg:province":"WI",
    "sg:tags":[
        "product",
        "petroleum"
    ],
    "wof:name":"Citgo North C-North",
    "wof:placetype":"venue"
},
  "geometry": {"coordinates":[-89.148259,45.160223],"type":"Point"}
}