{
  "type": "Feature",
  "properties": {
    "iso:country":"US",
    "sg:address":"307 Madison Ave",
    "sg:city":"Fort Atkinson",
    "sg:classifiers":[
        {
            "category":"Cinema",
            "subcategory":"Movie Rental",
            "type":"Entertainment"
        }
    ],
    "sg:phone":"+1 920 563 7449",
    "sg:postcode":"53538",
    "sg:province":"WI",
    "sg:tags":[
        "leasing",
        "video",
        "disc",
        "tape"
    ],
    "wof:name":"Video Country Inc",
    "wof:placetype":"venue"
},
  "geometry": {"coordinates":[-88.842108,42.93244],"type":"Point"}
}