{
  "type": "Feature",
  "properties": {
    "iso:country":"US",
    "sg:address":"8730 Lakeshore Dr",
    "sg:city":"Pleasant Prairie",
    "sg:classifiers":[
        {
            "category":"Professional",
            "subcategory":"Management & Consulting",
            "type":"Services"
        }
    ],
    "sg:phone":"+1 262 694 7891",
    "sg:postcode":"53158",
    "sg:province":"WI",
    "sg:tags":[
        "construction"
    ],
    "wof:name":"White Construction Consultants",
    "wof:placetype":"venue"
},
  "geometry": {"coordinates":[-87.81408,42.532007],"type":"Point"}
}