{
  "type": "Feature",
  "properties": {
    "iso:country":"US",
    "sg:address":"8677 N Port Washington Rd",
    "sg:city":"Milwaukee",
    "sg:classifiers":[
        {
            "category":"Education",
            "subcategory":"School",
            "type":"Public Place"
        }
    ],
    "sg:phone":"+1 414 352 6115",
    "sg:postcode":"53217",
    "sg:province":"WI",
    "wof:name":"Seton Childrens School",
    "wof:placetype":"venue"
},
  "geometry": {"coordinates":[-87.91286599999999,43.175899],"type":"Point"}
}