{
  "type": "Feature",
  "properties": {
    "iso:country":"US",
    "sg:address":"111 E 4th St",
    "sg:city":"Marshfield",
    "sg:classifiers":[
        {
            "category":"Professional",
            "type":"Services"
        }
    ],
    "sg:phone":"+1 715 389 1186",
    "sg:postcode":"54449",
    "sg:province":"WI",
    "sg:tags":[
        "establishment"
    ],
    "wof:name":"Finishing Supply",
    "wof:placetype":"venue"
},
  "geometry": {"coordinates":[-90.175313,44.664114],"type":"Point"}
}