{
  "type": "Feature",
  "properties": {
    "addr:full":"641 18th St S Wisconsin Rapids WI 54494",
    "addr:housenumber":"641",
    "addr:postcode":"54494",
    "addr:street":"18Th St S",
    "iso:country":"US",
    "sg:address":"641 18th St S",
    "sg:city":"Wisconsin Rapids",
    "sg:classifiers":[
        {
            "category":"Organizations",
            "subcategory":"Religious Organization",
            "type":"Services"
        }
    ],
    "sg:phone":"+1 715 423 3490",
    "sg:postcode":"54494",
    "sg:province":"WI",
    "sg:tags":[
        "church"
    ],
    "wof:name":"St Paul Lutheran Church",
    "wof:placetype":"venue"
},
  "geometry": {"coordinates":[-89.80432999999999,44.384688],"type":"Point"}
}