{
  "type": "Feature",
  "properties": {
    "iso:country":"US",
    "sg:address":"403 Superior Ave",
    "sg:city":"Tomah",
    "sg:classifiers":[
        {
            "category":"Personal",
            "subcategory":"Beauty Salon",
            "type":"Services"
        }
    ],
    "sg:phone":"+1 608 372 6303",
    "sg:postcode":"54660",
    "sg:province":"WI",
    "sg:tags":[
        "shop"
    ],
    "wof:name":"Marians Beauty Centre",
    "wof:placetype":"venue"
},
  "geometry": {"coordinates":[-90.50478200000001,43.983491],"type":"Point"}
}