{
  "type": "Feature",
  "properties": {
    "iso:country":"US",
    "sg:address":"14551 Kaul Ave",
    "sg:city":"Menomonee Falls",
    "sg:classifiers":[
        {
            "category":"Professional",
            "type":"Services"
        }
    ],
    "sg:phone":"+1 262 703 9025",
    "sg:postcode":"53051",
    "sg:province":"WI",
    "wof:name":"Exclusive Services",
    "wof:placetype":"venue"
},
  "geometry": {"coordinates":[-88.091922,43.127392],"type":"Point"}
}