{
  "type": "Feature",
  "properties": {
    "iso:country":"US",
    "sg:address":"2659 S Kinnickinnic Ave",
    "sg:city":"Milwaukee",
    "sg:classifiers":[
        {
            "category":"Bars & Pubs",
            "type":"Food & Drink"
        }
    ],
    "sg:phone":"+1 414 483 4663",
    "sg:postcode":"53207",
    "sg:province":"WI",
    "sg:tags":[
        "drinking"
    ],
    "wof:name":"Home Bar LLC",
    "wof:placetype":"venue"
},
  "geometry": {"coordinates":[-87.898348,42.996847],"type":"Point"}
}