{
  "type": "Feature",
  "properties": {
    "iso:country":"US",
    "sg:address":"2301 W Wisconsin Ave",
    "sg:city":"Milwaukee",
    "sg:classifiers":[
        {
            "category":"Restaurant",
            "type":"Food & Drink"
        }
    ],
    "sg:phone":"+1 414 934 8882",
    "sg:postcode":"53233",
    "sg:province":"WI",
    "sg:tags":[
        "eating"
    ],
    "wof:name":"Old Siam Restaurant",
    "wof:placetype":"venue"
},
  "geometry": {"coordinates":[-87.94289499999999,43.038689],"type":"Point"}
}