{
  "type": "Feature",
  "properties": {
    "iso:country":"US",
    "sg:address":"7610 Saint Pats Church Rd",
    "sg:city":"Greenleaf",
    "sg:classifiers":[
        {
            "category":"Farming",
            "subcategory":"Farm",
            "type":"Manufacturing & Wholesale Goods"
        }
    ],
    "sg:phone":"+1 920 532 4460",
    "sg:postcode":"54126",
    "sg:province":"WI",
    "sg:tags":[
        "crop",
        "general"
    ],
    "wof:name":"Country Ear Farms",
    "wof:placetype":"venue"
},
  "geometry": {"coordinates":[-88.090848,44.277173],"type":"Point"}
}