{
  "type": "Feature",
  "properties": {
    "iso:country":"US",
    "sg:address":"3953 Co Rd G",
    "sg:city":"Mauston",
    "sg:classifiers":[
        {
            "category":"Retail",
            "subcategory":"Auto Repair",
            "type":"Services"
        }
    ],
    "sg:phone":"+1 608 847 1153",
    "sg:postcode":"53948",
    "sg:province":"WI",
    "sg:tags":[
        "general"
    ],
    "wof:name":"D&C Diesel Repair LLC",
    "wof:placetype":"venue"
},
  "geometry": {"coordinates":[-90.091855,43.784327],"type":"Point"}
}