{
  "type": "Feature",
  "properties": {
    "iso:country":"US",
    "sg:address":"5616 75th St",
    "sg:city":"Kenosha",
    "sg:classifiers":[
        {
            "category":"Food & Beverages",
            "subcategory":"Groceries & Convenience Stores",
            "type":"Retail Goods"
        }
    ],
    "sg:phone":"+1 262 697 5773",
    "sg:postcode":"53142",
    "sg:province":"WI",
    "wof:name":"Highway Fifty Citgo",
    "wof:placetype":"venue"
},
  "geometry": {"coordinates":[-87.87462,42.566532],"type":"Point"}
}