{
  "type": "Feature",
  "properties": {
    "addr:full":"9604 Crescent Ave Eau Claire WI 54703",
    "addr:housenumber":"9604",
    "addr:postcode":"54703",
    "addr:street":"Crescent Ave",
    "iso:country":"US",
    "sg:address":"9604 Crescent Ave",
    "sg:city":"Eau Claire",
    "sg:classifiers":[
        {
            "category":"Building & Trades",
            "subcategory":"Construction",
            "type":"Services"
        }
    ],
    "sg:phone":"+1 715 874 5187",
    "sg:postcode":"54703",
    "sg:province":"WI",
    "sg:tags":[
        "house"
    ],
    "wof:name":"Dokkestul Construction",
    "wof:placetype":"venue"
},
  "geometry": {"coordinates":[-91.63997999999999,44.785023],"type":"Point"}
}