{
  "type": "Feature",
  "properties": {
    "iso:country":"US",
    "sg:address":"5980 W Loomis Rd",
    "sg:city":"Greendale",
    "sg:classifiers":[
        {
            "category":"Organizations",
            "subcategory":"Religious Organization",
            "type":"Services"
        }
    ],
    "sg:phone":"+1 414 423 8660",
    "sg:postcode":"53129",
    "sg:province":"WI",
    "wof:name":"Volunteer Missionary Movement",
    "wof:placetype":"venue"
},
  "geometry": {"coordinates":[-87.99166,42.935038],"type":"Point"}
}