{
  "type": "Feature",
  "properties": {
    "iso:country":"US",
    "sg:address":"2808 Heritage Dr",
    "sg:city":"Delafield",
    "sg:classifiers":[
        {
            "category":"Health Services",
            "subcategory":"Doctor",
            "type":"Services"
        }
    ],
    "sg:phone":"+1 262 646 1440",
    "sg:postcode":"53018",
    "sg:province":"WI",
    "sg:tags":[
        "physician",
        "surgeon"
    ],
    "wof:name":"Wilkinson Medical Clinic",
    "wof:placetype":"venue"
},
  "geometry": {"coordinates":[-88.372877,43.050064],"type":"Point"}
}