{
  "type": "Feature",
  "properties": {
    "iso:country":"US",
    "sg:address":"386 S Koeller St",
    "sg:city":"Oshkosh",
    "sg:classifiers":[
        {
            "category":"Health Services",
            "subcategory":"Clinic",
            "type":"Services"
        }
    ],
    "sg:phone":"+1 920 651 0780",
    "sg:postcode":"54902",
    "sg:province":"WI",
    "wof:name":"Salisbury Clinic Chiroprati",
    "wof:placetype":"venue"
},
  "geometry": {"coordinates":[-88.581597,44.012794],"type":"Point"}
}