{
  "type": "Feature",
  "properties": {
    "iso:country":"US",
    "sg:address":"5600 W Good Hope Rd",
    "sg:city":"Milwaukee",
    "sg:classifiers":[
        {
            "category":"Manufacturing",
            "subcategory":"Paper Products",
            "type":"Manufacturing & Wholesale Goods"
        }
    ],
    "sg:phone":"+1 414 353 6200",
    "sg:postcode":"53223",
    "sg:province":"WI",
    "sg:tags":[
        "converted",
        "prod"
    ],
    "wof:name":"Packaging Corp Of America",
    "wof:placetype":"venue"
},
  "geometry": {"coordinates":[-87.984431,43.14862],"type":"Point"}
}