{
  "type": "Feature",
  "properties": {
    "addr:full":"2600 Tower Dr Kaukauna WI 54130",
    "addr:housenumber":"2600",
    "addr:postcode":"54130",
    "addr:street":"Tower Dr",
    "iso:country":"US",
    "sg:address":"2600 Tower Dr",
    "sg:city":"Kaukauna",
    "sg:classifiers":[
        {
            "category":"Professional",
            "subcategory":"Engineering",
            "type":"Services"
        }
    ],
    "sg:phone":"+1 920 759 1100",
    "sg:postcode":"54130",
    "sg:province":"WI",
    "sg:tags":[
        "engineer"
    ],
    "wof:name":"MSB Corp",
    "wof:placetype":"venue"
},
  "geometry": {"coordinates":[-88.26718099999999,44.300142],"type":"Point"}
}