{
  "type": "Feature",
  "properties": {
    "addr:full":"1606 Wendy Ln Madison WI 53716",
    "addr:housenumber":"1606",
    "addr:postcode":"53716",
    "addr:street":"Wendy Ln",
    "iso:country":"US",
    "sg:address":"1606 Wendy Ln",
    "sg:city":"Madison",
    "sg:classifiers":[
        {
            "category":"Professional",
            "subcategory":"Advertising",
            "type":"Services"
        }
    ],
    "sg:phone":"+1 608 222 4880",
    "sg:postcode":"53716",
    "sg:province":"WI",
    "sg:tags":[
        "demonstration"
    ],
    "wof:name":"Roma's Personalized Demo Svc",
    "wof:placetype":"venue"
},
  "geometry": {"coordinates":[-89.294652,43.074687],"type":"Point"}
}