{
  "type": "Feature",
  "properties": {
    "iso:country":"US",
    "sg:address":"535 S Industrial Dr",
    "sg:city":"Hartland",
    "sg:classifiers":[
        {
            "category":"Manufacturing",
            "subcategory":"Metals",
            "type":"Manufacturing & Wholesale Goods"
        }
    ],
    "sg:phone":"+1 262 367 4469",
    "sg:postcode":"53029",
    "sg:province":"WI",
    "sg:tags":[
        "stampings",
        "mfg"
    ],
    "sg:website":"www.sjobergtool.com",
    "wof:name":"Sjoberg Tool and Mfg Corp",
    "wof:placetype":"venue"
},
  "geometry": {"coordinates":[-88.360063,43.09713],"type":"Point"}
}