{
  "type": "Feature",
  "properties": {
    "iso:country":"US",
    "sg:address":"1691 Ohio St",
    "sg:city":"Oshkosh",
    "sg:classifiers":[
        {
            "category":"Personal",
            "subcategory":"Beauty Salon",
            "type":"Services"
        }
    ],
    "sg:phone":"+1 920 236 8724",
    "sg:postcode":"54902",
    "sg:province":"WI",
    "sg:tags":[
        "manicuring"
    ],
    "wof:name":"Painted Desert",
    "wof:placetype":"venue"
},
  "geometry": {"coordinates":[-88.55256199999999,44.003253],"type":"Point"}
}