{
  "type": "Feature",
  "properties": {
    "iso:country":"US",
    "sg:address":"47 Eastbrook Ln",
    "sg:city":"Fond Du Lac",
    "sg:classifiers":[
        {
            "category":"Education",
            "subcategory":"Special Training",
            "type":"Public Place"
        }
    ],
    "sg:phone":"+1 920 979 9229",
    "sg:postcode":"54935",
    "sg:province":"WI",
    "sg:tags":[
        "instrument",
        "musical"
    ],
    "wof:name":"Piano Playground LLC",
    "wof:placetype":"venue"
},
  "geometry": {"coordinates":[-88.42057200000001,43.766691],"type":"Point"}
}