{
  "type": "Feature",
  "properties": {
    "iso:country":"US",
    "sg:address":"1755 Linse Rd",
    "sg:city":"Wabeno",
    "sg:classifiers":[
        {
            "category":"Social Services",
            "subcategory":"Child Care",
            "type":"Services"
        }
    ],
    "sg:phone":"+1 715 473 2524",
    "sg:postcode":"54566",
    "sg:province":"WI",
    "sg:tags":[
        "day"
    ],
    "wof:name":"Jumping Jack LLC",
    "wof:placetype":"venue"
},
  "geometry": {"coordinates":[-88.552725,45.438421],"type":"Point"}
}