{
  "type": "Feature",
  "properties": {
    "iso:country":"US",
    "sg:address":"3520 S 108th St",
    "sg:city":"Milwaukee",
    "sg:classifiers":[
        {
            "category":"Autos & Motor Vehicles",
            "subcategory":"Automobile Sales",
            "type":"Retail Goods"
        }
    ],
    "sg:phone":"+1 414 329 5800",
    "sg:postcode":"53228",
    "sg:province":"WI",
    "sg:tags":[
        "car",
        "used",
        "repair",
        "new"
    ],
    "sg:website":"http://russdarrow.com",
    "wof:name":"Darrow Russ Group Inc",
    "wof:placetype":"venue"
},
  "geometry": {"coordinates":[-88.047318,42.980276],"type":"Point"}
}