{
  "type": "Feature",
  "properties": {
    "iso:country":"US",
    "sg:address":"100 Lake Pointe Dr",
    "sg:city":"Oshkosh",
    "sg:classifiers":[
        {
            "category":"Retail",
            "subcategory":"Funeral Services",
            "type":"Services"
        }
    ],
    "sg:phone":"+1 920 232 5485",
    "sg:postcode":"54904",
    "sg:province":"WI",
    "sg:tags":[
        "director"
    ],
    "wof:name":"Konrad-Behlman Funeral Home",
    "wof:placetype":"venue"
},
  "geometry": {"coordinates":[-88.591335,44.018705],"type":"Point"}
}