{
  "type": "Feature",
  "properties": {
    "addr:full":"385 W Fountainview Dr Milwaukee WI 53217",
    "addr:housenumber":"385",
    "addr:postcode":"53217",
    "addr:street":"W Fountainview Dr",
    "iso:country":"US",
    "sg:address":"385 W Fountainview Dr",
    "sg:city":"Milwaukee",
    "sg:classifiers":[
        {
            "category":"Shopping",
            "subcategory":"Clothing, Apparel, & Fashions",
            "type":"Retail Goods"
        }
    ],
    "sg:phone":"+1 414 963 0303",
    "sg:postcode":"53217",
    "sg:province":"WI",
    "sg:tags":[
        "made",
        "tuxedo",
        "suits-custom",
        "men's",
        "sale",
        "wear",
        "clothing",
        "rental",
        "formal"
    ],
    "sg:website":"http://www.menswearhouse.com",
    "wof:name":"Men's Wearhouse",
    "wof:placetype":"venue"
},
  "geometry": {"coordinates":[-87.91321600000001,43.12088],"type":"Point"}
}