{
  "type": "Feature",
  "properties": {
    "iso:country":"US",
    "sg:address":"111 E Jackson St",
    "sg:city":"Wisconsin Rapids",
    "sg:classifiers":[
        {
            "category":"Organizations",
            "subcategory":"Labor Organization",
            "type":"Services"
        }
    ],
    "sg:phone":"+1 715 424 0494",
    "sg:postcode":"54494",
    "sg:province":"WI",
    "wof:name":"Labor Union Upiu Local 94",
    "wof:placetype":"venue"
},
  "geometry": {"coordinates":[-89.823778,44.392452],"type":"Point"}
}