{
  "type": "Feature",
  "properties": {
    "addr:full":"720 N Midvale Blvd Madison WI 53705",
    "addr:housenumber":"720",
    "addr:postcode":"53705",
    "addr:street":"N Midvale Blvd",
    "iso:country":"US",
    "sg:address":"720 N Midvale Blvd",
    "sg:city":"Madison",
    "sg:classifiers":[
        {
            "category":"Shopping",
            "type":"Retail Goods"
        }
    ],
    "sg:phone":"+1 608 232 2419",
    "sg:postcode":"53705",
    "sg:province":"WI",
    "sg:tags":[
        "cosmetic",
        "perfume"
    ],
    "wof:name":"Origins",
    "wof:placetype":"venue"
},
  "geometry": {"coordinates":[-89.451205,43.074361],"type":"Point"}
}