{
  "type": "Feature",
  "properties": {
    "iso:country":"US",
    "sg:address":"4029 Waldo Blvd",
    "sg:city":"Manitowoc",
    "sg:classifiers":[
        {
            "category":"Building & Trades",
            "subcategory":"Construction",
            "type":"Services"
        }
    ],
    "sg:phone":"+1 920 682 9055",
    "sg:postcode":"54220",
    "sg:province":"WI",
    "sg:tags":[
        "painter"
    ],
    "wof:name":"Grapentine Painting",
    "wof:placetype":"venue"
},
  "geometry": {"coordinates":[-87.698339,44.108791],"type":"Point"}
}