{
  "type": "Feature",
  "properties": {
    "addr:full":"7135 Green Valley Rd Spooner WI 54801",
    "addr:housenumber":"7135",
    "addr:postcode":"54801",
    "addr:street":"Green Valley Rd",
    "iso:country":"US",
    "sg:address":"7135 Green Valley Rd",
    "sg:city":"Spooner",
    "sg:classifiers":[
        {
            "category":"Organizations",
            "subcategory":"Religious Organization",
            "type":"Services"
        }
    ],
    "sg:phone":"+1 715 635 2277",
    "sg:postcode":"54801",
    "sg:province":"WI",
    "wof:name":"Spooner Baptist Church",
    "wof:placetype":"venue"
},
  "geometry": {"coordinates":[-91.901252,45.807389],"type":"Point"}
}