{
  "type": "Feature",
  "properties": {
    "iso:country":"US",
    "sg:address":"117 N Bristol St",
    "sg:city":"Sun Prairie",
    "sg:classifiers":[
        {
            "category":"Building & Trades",
            "subcategory":"Construction",
            "type":"Services"
        }
    ],
    "sg:phone":"+1 608 755 4644",
    "sg:postcode":"53590",
    "sg:province":"WI",
    "sg:tags":[
        "waterproofing",
        "contractor"
    ],
    "wof:name":"Badger Basement Systems Inc",
    "wof:placetype":"venue"
},
  "geometry": {"coordinates":[-89.21342199999999,43.183841],"type":"Point"}
}