{
  "type": "Feature",
  "properties": {
    "iso:country":"US",
    "sg:address":"201 W 2nd St",
    "sg:city":"Kaukauna",
    "sg:classifiers":[
        {
            "category":"Recreation",
            "type":"Entertainment"
        }
    ],
    "sg:phone":"+1 920 766 6335",
    "sg:postcode":"54130",
    "sg:province":"WI",
    "sg:tags":[
        "parks"
    ],
    "sg:website":"www.cityofkaukauna.com",
    "wof:name":"Kaukauna City Recreation",
    "wof:placetype":"venue"
},
  "geometry": {"coordinates":[-88.273891,44.279379],"type":"Point"}
}