{
  "type": "Feature",
  "properties": {
    "iso:country":"US",
    "sg:address":"6104 Radio Rd",
    "sg:city":"Brandon",
    "sg:classifiers":[
        {
            "category":"Retail",
            "subcategory":"Animal Services",
            "type":"Services"
        }
    ],
    "sg:phone":"+1 920 748 9246",
    "sg:postcode":"53919",
    "sg:province":"WI",
    "wof:name":"Bz Kennel",
    "wof:placetype":"venue"
},
  "geometry": {"coordinates":[-88.84566,43.768],"type":"Point"}
}