{
  "type": "Feature",
  "properties": {
    "iso:country":"US",
    "sg:address":"1305 2nd Ave",
    "sg:city":"Cumberland",
    "sg:classifiers":[
        {
            "category":"Education",
            "subcategory":"Library",
            "type":"Public Place"
        }
    ],
    "sg:phone":"+1 715 822 2767",
    "sg:postcode":"54829",
    "sg:province":"WI",
    "wof:name":"Cumberland Public Library",
    "wof:placetype":"venue"
},
  "geometry": {"coordinates":[-92.021486,45.535441],"type":"Point"}
}