{
  "type": "Feature",
  "properties": {
    "addr:full":"11641 Co Rd F W Randolph WI 53956",
    "addr:housenumber":"11641",
    "addr:postcode":"53956",
    "addr:street":"Co Rd;W",
    "iso:country":"US",
    "sg:address":"11641 Co Rd F W",
    "sg:city":"Randolph",
    "sg:phone":"+1 920 326 3571",
    "sg:postcode":"53956",
    "sg:province":"WI",
    "sg:tags":[
        "farm",
        "corn",
        "dairy"
    ],
    "wof:name":"Braker John",
    "wof:placetype":"venue"
},
  "geometry": {"coordinates":[-88.981014,43.452173],"type":"Point"}
}