{
  "type": "Feature",
  "properties": {
    "iso:country":"US",
    "sg:address":"3740 Dominic Dr",
    "sg:city":"Brookfield",
    "sg:classifiers":[
        {
            "category":"Real Estate",
            "subcategory":"Real Estate Agent",
            "type":"Services"
        }
    ],
    "sg:phone":"+1 262 781 8121",
    "sg:postcode":"53045",
    "sg:province":"WI",
    "wof:name":"Lwl Properties",
    "wof:placetype":"venue"
},
  "geometry": {"coordinates":[-88.138672,43.08628],"type":"Point"}
}