{
  "type": "Feature",
  "properties": {
    "iso:country":"US",
    "sg:address":"137 S Pine St",
    "sg:city":"Reedsburg",
    "sg:classifiers":[
        {
            "category":"Shopping",
            "subcategory":"Florist",
            "type":"Retail Goods"
        }
    ],
    "sg:phone":"+1 608 524 3414",
    "sg:postcode":"53959",
    "sg:province":"WI",
    "sg:tags":[
        "flower",
        "gift"
    ],
    "wof:name":"Reedsburg Floral & Garden Room",
    "wof:placetype":"venue"
},
  "geometry": {"coordinates":[-90.003881,43.53215],"type":"Point"}
}