{
  "type": "Feature",
  "properties": {
    "iso:country":"US",
    "sg:address":"611 S 28th St",
    "sg:city":"Milwaukee",
    "sg:classifiers":[
        {
            "category":"Real Estate",
            "subcategory":"Real Estate Agent",
            "type":"Services"
        }
    ],
    "sg:phone":"+1 414 671 8037",
    "sg:postcode":"53215",
    "sg:province":"WI",
    "wof:name":"Schwerman Virginia LLC",
    "wof:placetype":"venue"
},
  "geometry": {"coordinates":[-87.949179,43.02428],"type":"Point"}
}