{
  "type": "Feature",
  "properties": {
    "iso:country":"US",
    "sg:address":"1210 Arndt St",
    "sg:city":"Fort Atkinson",
    "sg:classifiers":[
        {
            "category":"Local Transit",
            "type":"Transportation"
        }
    ],
    "sg:phone":"+1 920 691 0060",
    "sg:postcode":"53538",
    "sg:province":"WI",
    "sg:tags":[
        "ambulance"
    ],
    "wof:name":"Ryan Bro Ambulance Svc",
    "wof:placetype":"venue"
},
  "geometry": {"coordinates":[-88.833927,42.912666],"type":"Point"}
}