{
  "type": "Feature",
  "properties": {
    "iso:country":"US",
    "sg:address":"221 US Hwy 51",
    "sg:city":"Poynette",
    "sg:classifiers":[
        {
            "category":"Real Estate",
            "subcategory":"Real Estate Services",
            "type":"Services"
        }
    ],
    "sg:phone":"+1 608 742 3823",
    "sg:postcode":"53955",
    "sg:province":"WI",
    "sg:tags":[
        "company",
        "title"
    ],
    "wof:name":"Naset Title",
    "wof:placetype":"venue"
},
  "geometry": {"coordinates":[-89.39514200000001,43.392624],"type":"Point"}
}