{
  "type": "Feature",
  "properties": {
    "iso:country":"US",
    "sg:address":"2913 Wimbledon Way",
    "sg:city":"Madison",
    "sg:classifiers":[
        {
            "category":"Retail",
            "subcategory":"Laundry & Dry Cleaning",
            "type":"Services"
        }
    ],
    "sg:phone":"+1 608 848 9971",
    "sg:postcode":"53713",
    "sg:province":"WI",
    "sg:tags":[
        "drycleaning",
        "plant"
    ],
    "wof:name":"TLC Dry Cleaning",
    "wof:placetype":"venue"
},
  "geometry": {"coordinates":[-89.428777,43.026564],"type":"Point"}
}