{
  "type": "Feature",
  "properties": {
    "iso:country":"US",
    "sg:address":"416 Zinnia Ave",
    "sg:city":"Palmyra",
    "sg:classifiers":[
        {
            "category":"Retail",
            "subcategory":"Repair Shop",
            "type":"Services"
        }
    ],
    "sg:phone":"+1 262 495 2120",
    "sg:postcode":"53156",
    "sg:province":"WI",
    "sg:tags":[
        "television",
        "radio"
    ],
    "wof:name":"O K Radio & Sound",
    "wof:placetype":"venue"
},
  "geometry": {"coordinates":[-88.57631499999999,42.876199],"type":"Point"}
}