{
  "type": "Feature",
  "properties": {
    "iso:country":"US",
    "sg:address":"2323 Bluemound Rd",
    "sg:city":"Waukesha",
    "sg:classifiers":[
        {
            "category":"Building & Trades",
            "subcategory":"Construction",
            "type":"Services"
        }
    ],
    "sg:phone":"+1 262 717 1300",
    "sg:postcode":"53186",
    "sg:province":"WI",
    "sg:tags":[
        "residential",
        "commercial",
        "remodeling"
    ],
    "wof:name":"Giertsen Company",
    "wof:placetype":"venue"
},
  "geometry": {"coordinates":[-88.18156500000001,43.036227],"type":"Point"}
}