{
  "type": "Feature",
  "properties": {
    "iso:country":"US",
    "sg:address":"10855 Main St",
    "sg:city":"Hewitt",
    "sg:classifiers":[
        {
            "category":"Freight",
            "type":"Transportation"
        }
    ],
    "sg:phone":"+1 715 384 0995",
    "sg:postcode":"54441",
    "sg:province":"WI",
    "sg:tags":[
        "commercial",
        "storage",
        "general"
    ],
    "wof:name":"Eilers Store All LLC",
    "wof:placetype":"venue"
},
  "geometry": {"coordinates":[-90.099803,44.639321],"type":"Point"}
}