{
  "type": "Feature",
  "properties": {
    "iso:country":"US",
    "sg:address":"301 1st St",
    "sg:city":"Plum City",
    "sg:classifiers":[
        {
            "category":"Autos & Motor Vehicles",
            "subcategory":"Fuel & Gas Station",
            "type":"Retail Goods"
        }
    ],
    "sg:phone":"+1 715 647 4366",
    "sg:postcode":"54761",
    "sg:province":"WI",
    "sg:tags":[
        "oil"
    ],
    "wof:name":"Corner Garage",
    "wof:placetype":"venue"
},
  "geometry": {"coordinates":[-92.19127400000001,44.631339],"type":"Point"}
}