{
  "type": "Feature",
  "properties": {
    "iso:country":"US",
    "sg:address":"110 Woodside Ln",
    "sg:city":"Neenah",
    "sg:classifiers":[
        {
            "category":"Professional",
            "subcategory":"Business Services",
            "type":"Services"
        }
    ],
    "sg:phone":"+1 920 725 1382",
    "sg:postcode":"54956",
    "sg:province":"WI",
    "wof:name":"Designs By Dagny",
    "wof:placetype":"venue"
},
  "geometry": {"coordinates":[-88.51544699999999,44.163731],"type":"Point"}
}