{
  "type": "Feature",
  "properties": {
    "iso:country":"US",
    "sg:address":"450 Lake Dr",
    "sg:city":"Mellen",
    "sg:classifiers":[
        {
            "category":"Health Services",
            "subcategory":"Nursing And Care Facility",
            "type":"Services"
        }
    ],
    "sg:phone":"+1 715 274 5706",
    "sg:postcode":"54546",
    "sg:province":"WI",
    "sg:tags":[
        "skilled"
    ],
    "wof:name":"Mellen Manor Nursing Home",
    "wof:placetype":"venue"
},
  "geometry": {"coordinates":[-90.654797,46.32176],"type":"Point"}
}