{
  "type": "Feature",
  "properties": {
    "iso:country":"US",
    "sg:address":"3652 S Rutland Ave",
    "sg:city":"Milwaukee",
    "sg:classifiers":[
        {
            "category":"Social Services",
            "subcategory":"Adult Care",
            "type":"Services"
        }
    ],
    "sg:phone":"+1 414 486 9404",
    "sg:postcode":"53235",
    "sg:province":"WI",
    "sg:tags":[
        "residential"
    ],
    "wof:name":"Sullivan House St Francis",
    "wof:placetype":"venue"
},
  "geometry": {"coordinates":[-87.883312,42.97712],"type":"Point"}
}