{
  "type": "Feature",
  "properties": {
    "iso:country":"US",
    "sg:address":"225 Memorial Dr",
    "sg:city":"Berlin",
    "sg:classifiers":[
        {
            "category":"Health Services",
            "subcategory":"Hospital",
            "type":"Services"
        }
    ],
    "sg:phone":"+1 920 361 1313",
    "sg:postcode":"54923",
    "sg:province":"WI",
    "sg:tags":[
        "home",
        "skilled",
        "nursing"
    ],
    "sg:website":"www.communityhealthnetwork.org",
    "wof:name":"Berlin Memorial Hospital",
    "wof:placetype":"venue"
},
  "geometry": {"coordinates":[-88.94349200000001,43.97773],"type":"Point"}
}