{
  "type": "Feature",
  "properties": {
    "iso:country":"US",
    "sg:address":"3789 Flak Rd",
    "sg:city":"Elton",
    "sg:classifiers":[
        {
            "category":"Professional",
            "subcategory":"Management & Consulting",
            "type":"Services"
        }
    ],
    "sg:phone":"+1 715 882 2800",
    "sg:postcode":"54430",
    "sg:province":"WI",
    "wof:name":"Wheels R US",
    "wof:placetype":"venue"
},
  "geometry": {"coordinates":[-88.89731,45.157575],"type":"Point"}
}