{
  "type": "Feature",
  "properties": {
    "iso:country":"US",
    "sg:address":"11950 Seward St",
    "sg:city":"Trempealeau",
    "sg:classifiers":[
        {
            "category":"Professional",
            "subcategory":"Business Services",
            "type":"Services"
        }
    ],
    "sg:phone":"+1 608 534 7709",
    "sg:postcode":"54661",
    "sg:province":"WI",
    "wof:name":"Coulee Region Home Inspection",
    "wof:placetype":"venue"
},
  "geometry": {"coordinates":[-91.443313,44.012726],"type":"Point"}
}