{
  "type": "Feature",
  "properties": {
    "iso:country":"US",
    "sg:address":"3502 Milton Ave",
    "sg:city":"Janesville",
    "sg:classifiers":[
        {
            "category":"Restaurant",
            "type":"Food & Drink"
        }
    ],
    "sg:menulink":"http://www.allmenus.com/wi/janesville/222240-country-kitchen/menu/",
    "sg:phone":"+1 608 756 2131",
    "sg:postcode":"53545",
    "sg:province":"WI",
    "sg:tags":[
        "american",
        "southern"
    ],
    "wof:name":"Country Kitchen",
    "wof:placetype":"venue"
},
  "geometry": {"coordinates":[-88.99393600000001,42.723166],"type":"Point"}
}