{
  "type": "Feature",
  "properties": {
    "addr:full":"2553 Sun Ter Green Bay WI 54311",
    "addr:housenumber":"2553",
    "addr:postcode":"54311",
    "addr:street":"Sun Ter",
    "iso:country":"US",
    "sg:address":"2553 Sun Ter",
    "sg:city":"Green Bay",
    "sg:classifiers":[
        {
            "category":"Home & Garden",
            "subcategory":"Furniture",
            "type":"Retail Goods"
        }
    ],
    "sg:phone":"+1 920 429 1123",
    "sg:postcode":"54311",
    "sg:province":"WI",
    "wof:name":"Emmons Business Interiors",
    "wof:placetype":"venue"
},
  "geometry": {"coordinates":[-87.954994,44.486768],"type":"Point"}
}