{
  "type": "Feature",
  "properties": {
    "iso:country":"US",
    "sg:address":"1120 W Mallory Ave",
    "sg:city":"Milwaukee",
    "sg:classifiers":[
        {
            "category":"Freight",
            "type":"Transportation"
        }
    ],
    "sg:phone":"+1 414 281 5888",
    "sg:postcode":"53221",
    "sg:province":"WI",
    "sg:tags":[
        "operator",
        "trucking"
    ],
    "wof:name":"Truckers Express Inc",
    "wof:placetype":"venue"
},
  "geometry": {"coordinates":[-87.929218,42.946639],"type":"Point"}
}