{
  "type": "Feature",
  "properties": {
    "addr:full":"914 Oakly St Kohler WI 53044",
    "addr:housenumber":"914",
    "addr:postcode":"53044",
    "addr:street":"Oakly St",
    "iso:country":"US",
    "sg:address":"914 Oakly St",
    "sg:city":"Kohler",
    "sg:classifiers":[
        {
            "category":"Travel",
            "subcategory":"Travel Agent",
            "type":"Entertainment"
        }
    ],
    "sg:phone":"+1 920 457 2165",
    "sg:postcode":"53044",
    "sg:province":"WI",
    "sg:tags":[
        "agency"
    ],
    "wof:name":"Passport Health",
    "wof:placetype":"venue"
},
  "geometry": {"coordinates":[-87.78721899999999,43.738942],"type":"Point"}
}