{
  "type": "Feature",
  "properties": {
    "iso:country":"US",
    "sg:address":"5232 B K Line Rd",
    "sg:city":"Luxemburg",
    "sg:classifiers":[
        {
            "category":"Farming",
            "subcategory":"Dairy Farm",
            "type":"Manufacturing & Wholesale Goods"
        }
    ],
    "sg:phone":"+1 920 845 2244",
    "sg:postcode":"54217",
    "sg:province":"WI",
    "wof:name":"Da-Ran DAIRY LLC",
    "wof:placetype":"venue"
},
  "geometry": {"coordinates":[-87.764989,44.511199],"type":"Point"}
}