{
  "type": "Feature",
  "properties": {
    "iso:country":"US",
    "sg:address":"300 Mark Ct",
    "sg:city":"Neenah",
    "sg:classifiers":[
        {
            "category":"Home & Garden",
            "subcategory":"Hardware",
            "type":"Retail Goods"
        }
    ],
    "sg:phone":"+1 920 729 5612",
    "sg:postcode":"54956",
    "sg:province":"WI",
    "wof:name":"C L Tool LLC",
    "wof:placetype":"venue"
},
  "geometry": {"coordinates":[-88.46989499999999,44.159619],"type":"Point"}
}