{
  "type": "Feature",
  "properties": {
    "addr:full":"1601 Shawano Ave Green Bay WI 54303",
    "addr:housenumber":"1601",
    "addr:postcode":"54303",
    "addr:street":"Shawano Ave",
    "iso:country":"US",
    "sg:address":"1601 Shawano Ave",
    "sg:city":"Green Bay",
    "sg:classifiers":[
        {
            "category":"Restaurant",
            "type":"Food & Drink"
        }
    ],
    "sg:menulink":"http://www.allmenus.com/wi/green-bay/80013-pizza-hut/menu/",
    "sg:phone":"+1 920 494 4200",
    "sg:postcode":"54303",
    "sg:province":"WI",
    "sg:tags":[
        "american",
        "pizza"
    ],
    "wof:name":"Pizza Hut",
    "wof:placetype":"venue"
},
  "geometry": {"coordinates":[-88.061016,44.530209],"type":"Point"}
}