{
  "type": "Feature",
  "properties": {
    "iso:country":"US",
    "sg:address":"6050 St Anthony Rd",
    "sg:city":"West Bend",
    "sg:classifiers":[
        {
            "category":"Farming",
            "subcategory":"Farm",
            "type":"Manufacturing & Wholesale Goods"
        }
    ],
    "sg:phone":"+1 262 629 9144",
    "sg:postcode":"53090",
    "sg:province":"WI",
    "sg:tags":[
        "crop",
        "general"
    ],
    "wof:name":"Larry Weiss",
    "wof:placetype":"venue"
},
  "geometry": {"coordinates":[-88.339192,43.442381],"type":"Point"}
}