{
  "type": "Feature",
  "properties": {
    "addr:full":"1036 Starr Ave Eau Claire WI 54703",
    "addr:housenumber":"1036",
    "addr:postcode":"54703",
    "addr:street":"Starr Ave",
    "iso:country":"US",
    "sg:address":"1036 Starr Ave",
    "sg:city":"Eau Claire",
    "sg:classifiers":[
        {
            "category":"Professional",
            "subcategory":"Computer Services",
            "type":"Services"
        }
    ],
    "sg:phone":"+1 715 855 2448",
    "sg:postcode":"54703",
    "sg:province":"WI",
    "wof:name":"Agem Online",
    "wof:placetype":"venue"
},
  "geometry": {"coordinates":[-91.479016,44.828837],"type":"Point"}
}