{
  "type": "Feature",
  "properties": {
    "iso:country":"US",
    "sg:address":"607 Prospect Ave",
    "sg:city":"Wausau",
    "sg:classifiers":[
        {
            "category":"Personal",
            "subcategory":"Beauty Salon",
            "type":"Services"
        }
    ],
    "sg:phone":"+1 715 845 2666",
    "sg:postcode":"54403",
    "sg:province":"WI",
    "wof:name":"Hair Design",
    "wof:placetype":"venue"
},
  "geometry": {"coordinates":[-89.620138,44.952198],"type":"Point"}
}