{
  "type": "Feature",
  "properties": {
    "iso:country":"US",
    "sg:address":"205 Green Bay Rd",
    "sg:city":"Thiensville",
    "sg:classifiers":[
        {
            "category":"Manufacturing",
            "subcategory":"Signs",
            "type":"Manufacturing & Wholesale Goods"
        }
    ],
    "sg:phone":"+1 262 238 9586",
    "sg:postcode":"53092",
    "sg:province":"WI",
    "sg:tags":[
        "specialty",
        "mfg"
    ],
    "wof:name":"Creative Signs Express",
    "wof:placetype":"venue"
},
  "geometry": {"coordinates":[-87.980859,43.236143],"type":"Point"}
}