{
  "type": "Feature",
  "properties": {
    "iso:country":"US",
    "sg:address":"9912 Co Rd Jj",
    "sg:city":"Wautoma",
    "sg:classifiers":[
        {
            "category":"Building & Trades",
            "subcategory":"Construction",
            "type":"Services"
        }
    ],
    "sg:phone":"+1 920 787 7458",
    "sg:postcode":"54982",
    "sg:province":"WI",
    "sg:tags":[
        "roofing",
        "contractor"
    ],
    "wof:name":"Goody's Roofing Co",
    "wof:placetype":"venue"
},
  "geometry": {"coordinates":[-89.38035000000001,44.000424],"type":"Point"}
}