{
  "type": "Feature",
  "properties": {
    "iso:country":"US",
    "sg:address":"1025 N Main St",
    "sg:city":"Edgerton",
    "sg:classifiers":[
        {
            "category":"Home & Garden",
            "subcategory":"Hardware",
            "type":"Retail Goods"
        }
    ],
    "sg:phone":"+1 608 884 3913",
    "sg:postcode":"53534",
    "sg:province":"WI",
    "wof:name":"Deegan's Hardware",
    "wof:placetype":"venue"
},
  "geometry": {"coordinates":[-89.060275,42.84426],"type":"Point"}
}