{
  "type": "Feature",
  "properties": {
    "iso:country":"US",
    "sg:address":"4951 W Fond du Lac Ave",
    "sg:city":"Milwaukee",
    "sg:classifiers":[
        {
            "category":"Organizations",
            "subcategory":"Religious Organization",
            "type":"Services"
        }
    ],
    "sg:phone":"+1 414 447 9710",
    "sg:postcode":"53216",
    "sg:province":"WI",
    "sg:tags":[
        "church"
    ],
    "wof:name":"Greater House-Joy-Church-God",
    "wof:placetype":"venue"
},
  "geometry": {"coordinates":[-87.975762,43.089296],"type":"Point"}
}