{
  "type": "Feature",
  "properties": {
    "iso:country":"US",
    "sg:address":"612 E Main St",
    "sg:city":"Waunakee",
    "sg:classifiers":[
        {
            "category":"Health Services",
            "subcategory":"Doctor",
            "type":"Services"
        }
    ],
    "sg:phone":"+1 608 849 9014",
    "sg:postcode":"53597",
    "sg:province":"WI",
    "sg:tags":[
        "physician",
        "surgeon"
    ],
    "wof:name":"Bakke Chiropractic Clinic",
    "wof:placetype":"venue"
},
  "geometry": {"coordinates":[-89.442946,43.191927],"type":"Point"}
}