{
  "type": "Feature",
  "properties": {
    "iso:country":"US",
    "sg:address":"6767 N Industrial Rd",
    "sg:city":"Milwaukee",
    "sg:classifiers":[
        {
            "category":"Wholesale",
            "subcategory":"Medical Equipment & Supplies",
            "type":"Manufacturing & Wholesale Goods"
        }
    ],
    "sg:phone":"+1 414 358 2805",
    "sg:postcode":"53223",
    "sg:province":"WI",
    "sg:website":"www.directsupply.com",
    "wof:name":"Direct Supply Inc",
    "wof:placetype":"venue"
},
  "geometry": {"coordinates":[-87.991348,43.134844],"type":"Point"}
}