{
  "type": "Feature",
  "properties": {
    "iso:country":"US",
    "sg:address":"2310 Daniels St",
    "sg:city":"Madison",
    "sg:classifiers":[
        {
            "category":"Home & Garden",
            "subcategory":"Carpets & Floor Coverings",
            "type":"Retail Goods"
        }
    ],
    "sg:phone":"+1 608 221 4300",
    "sg:postcode":"53718",
    "sg:province":"WI",
    "sg:tags":[
        "dealer",
        "rug"
    ],
    "wof:name":"Crown Flooring & Design",
    "wof:placetype":"venue"
},
  "geometry": {"coordinates":[-89.29771,43.063661],"type":"Point"}
}