{
  "type": "Feature",
  "properties": {
    "iso:country":"US",
    "sg:address":"900 W Wisconsin Ave",
    "sg:city":"Milwaukee",
    "sg:classifiers":[
        {
            "category":"Health Services",
            "subcategory":"Doctor",
            "type":"Services"
        }
    ],
    "sg:phone":"+1 414 266 2932",
    "sg:postcode":"53233",
    "sg:province":"WI",
    "sg:tags":[
        "physician",
        "surgeon"
    ],
    "wof:name":"Child Psychiatry Ctr",
    "wof:placetype":"venue"
},
  "geometry": {"coordinates":[-87.924419,43.038821],"type":"Point"}
}