{
  "type": "Feature",
  "properties": {
    "iso:country":"US",
    "sg:address":"2231 Calumet Dr",
    "sg:city":"Sheboygan",
    "sg:classifiers":[
        {
            "category":"Banks & Credit Unions",
            "subcategory":"Bank",
            "type":"Services"
        }
    ],
    "sg:phone":"+1 920 457 4611",
    "sg:postcode":"53083",
    "sg:province":"WI",
    "sg:tags":[
        "cashing",
        "check"
    ],
    "wof:name":"Check Into Cash",
    "wof:placetype":"venue"
},
  "geometry": {"coordinates":[-87.72867599999999,43.768631],"type":"Point"}
}