{
  "type": "Feature",
  "properties": {
    "addr:full":"1789 Grant Rd Rubicon WI 53078",
    "addr:housenumber":"1789",
    "addr:postcode":"53078",
    "addr:street":"Grant Rd",
    "iso:country":"US",
    "sg:address":"1789 Grant Rd",
    "sg:city":"Rubicon",
    "sg:classifiers":[
        {
            "category":"Building & Trades",
            "subcategory":"Construction",
            "type":"Services"
        }
    ],
    "sg:phone":"+1 414 828 5669",
    "sg:postcode":"53078",
    "sg:province":"WI",
    "sg:tags":[
        "contractor"
    ],
    "wof:name":"Mark L Hoeppmer",
    "wof:placetype":"venue"
},
  "geometry": {"coordinates":[-88.484173,43.347483],"type":"Point"}
}