{
  "type": "Feature",
  "properties": {
    "addr:full":"308 Wisconsin St Merrill WI 54452",
    "addr:housenumber":"308",
    "addr:postcode":"54452",
    "addr:street":"Wisconsin St",
    "iso:country":"US",
    "sg:address":"308 Wisconsin St",
    "sg:city":"Merrill",
    "sg:classifiers":[
        {
            "category":"Building & Trades",
            "subcategory":"Construction",
            "type":"Services"
        }
    ],
    "sg:phone":"+1 715 536 6699",
    "sg:postcode":"54452",
    "sg:province":"WI",
    "sg:tags":[
        "hanging",
        "contractor"
    ],
    "wof:name":"E JS Painting & Construction",
    "wof:placetype":"venue"
},
  "geometry": {"coordinates":[-89.711448,45.182454],"type":"Point"}
}