{
  "type": "Feature",
  "properties": {
    "iso:country":"US",
    "sg:address":"4375 N 133rd St",
    "sg:city":"Brookfield",
    "sg:classifiers":[
        {
            "category":"Recreation",
            "type":"Entertainment"
        }
    ],
    "sg:phone":"+1 262 783 5587",
    "sg:postcode":"53005",
    "sg:province":"WI",
    "wof:name":"Your Total Image Inc",
    "wof:placetype":"venue"
},
  "geometry": {"coordinates":[-88.07715399999999,43.096595],"type":"Point"}
}