{
  "type": "Feature",
  "properties": {
    "addr:full":"401 S Randall Ave Janesville WI 53545",
    "addr:housenumber":"401",
    "addr:postcode":"53545",
    "addr:street":"S Randall Ave",
    "iso:country":"US",
    "sg:address":"401 S Randall Ave",
    "sg:city":"Janesville",
    "sg:classifiers":[
        {
            "category":"Education",
            "subcategory":"School",
            "type":"Public Place"
        }
    ],
    "sg:phone":"+1 608 743 5200",
    "sg:postcode":"53545",
    "sg:province":"WI",
    "wof:name":"Joseph A Craig High School",
    "wof:placetype":"venue"
},
  "geometry": {"coordinates":[-89.00284499999999,42.67887],"type":"Point"}
}