{
  "type": "Feature",
  "properties": {
    "iso:country":"US",
    "sg:address":"27344 Neville Rd",
    "sg:city":"Cashton",
    "sg:classifiers":[
        {
            "category":"Farming",
            "subcategory":"Dairy Farm",
            "type":"Manufacturing & Wholesale Goods"
        }
    ],
    "sg:phone":"+1 608 654 7335",
    "sg:postcode":"54619",
    "sg:province":"WI",
    "wof:name":"Paul Brueggen",
    "wof:placetype":"venue"
},
  "geometry": {"coordinates":[-90.70630800000001,43.783994],"type":"Point"}
}