{
  "type": "Feature",
  "properties": {
    "addr:full":"7840 Partridge Rd Eau Claire WI 54703",
    "addr:housenumber":"7840",
    "addr:postcode":"54703",
    "addr:street":"Partridge Rd",
    "iso:country":"US",
    "sg:address":"7840 Partridge Rd",
    "sg:city":"Eau Claire",
    "sg:classifiers":[
        {
            "category":"Wholesale",
            "subcategory":"Machinery & Supplies",
            "type":"Manufacturing & Wholesale Goods"
        }
    ],
    "sg:phone":"+1 715 874 6440",
    "sg:postcode":"54703",
    "sg:province":"WI",
    "sg:tags":[
        "equipment"
    ],
    "wof:name":"Fabco Rents",
    "wof:placetype":"venue"
},
  "geometry": {"coordinates":[-91.616517,44.843484],"type":"Point"}
}