{
  "type": "Feature",
  "properties": {
    "iso:country":"US",
    "sg:address":"2305 US Hwy 45",
    "sg:city":"Antigo",
    "sg:classifiers":[
        {
            "category":"Food & Beverages",
            "subcategory":"Groceries & Convenience Stores",
            "type":"Retail Goods"
        }
    ],
    "sg:phone":"+1 715 623 4515",
    "sg:postcode":"54409",
    "sg:province":"WI",
    "wof:name":"Remington Oil Co Inc",
    "wof:placetype":"venue"
},
  "geometry": {"coordinates":[-89.148178,45.163201],"type":"Point"}
}