{
  "type": "Feature",
  "properties": {
    "addr:full":"4106 State Rd 93 Eau Claire WI 54701",
    "addr:housenumber":"4106;93",
    "addr:postcode":"54701",
    "addr:street":"State Rd",
    "iso:country":"US",
    "sg:address":"4106 State Rd 93",
    "sg:city":"Eau Claire",
    "sg:classifiers":[
        {
            "category":"Banks & Credit Unions",
            "subcategory":"Bank",
            "type":"Services"
        }
    ],
    "sg:phone":"+1 715 833 1444",
    "sg:postcode":"54701",
    "sg:province":"WI",
    "sg:tags":[
        "member",
        "state"
    ],
    "wof:name":"M & I Marshall & Ilsley Bank",
    "wof:placetype":"venue"
},
  "geometry": {"coordinates":[-91.45960100000001,44.773392],"type":"Point"}
}