{
  "type": "Feature",
  "properties": {
    "addr:full":"639 4th Ave Monroe WI 53566",
    "addr:housenumber":"639",
    "addr:postcode":"53566",
    "addr:street":"4Th Ave",
    "iso:country":"US",
    "sg:address":"639 4th Ave",
    "sg:city":"Monroe",
    "sg:classifiers":[
        {
            "category":"Shopping",
            "subcategory":"Department Store",
            "type":"Retail Goods"
        },
        {
            "category":"Shopping",
            "subcategory":"Discount & Variety Stores",
            "type":"Retail Goods"
        },
        {
            "category":"Shopping",
            "type":"Retail Goods"
        },
        {
            "category":"Food & Beverages",
            "subcategory":"Groceries & Convenience Stores",
            "type":"Retail Goods"
        }
    ],
    "sg:phone":"+1 608 325 6994",
    "sg:postcode":"53566",
    "sg:province":"WI",
    "sg:tags":[
        "merchandise"
    ],
    "sg:website":"http://www.dollargeneral.com",
    "wof:name":"Dollar General",
    "wof:placetype":"venue"
},
  "geometry": {"coordinates":[-89.653311,42.606026],"type":"Point"}
}