{
  "type": "Feature",
  "properties": {
    "iso:country":"US",
    "sg:address":"5701 Tower Ave",
    "sg:city":"Superior",
    "sg:classifiers":[
        {
            "category":"Food & Beverages",
            "subcategory":"Groceries & Convenience Stores",
            "type":"Retail Goods"
        }
    ],
    "sg:phone":"+1 715 392 4222",
    "sg:postcode":"54880",
    "sg:province":"WI",
    "wof:name":"Jacks Fast Food Inc",
    "wof:placetype":"venue"
},
  "geometry": {"coordinates":[-92.104295,46.669472],"type":"Point"}
}