{
  "type": "Feature",
  "properties": {
    "iso:country":"US",
    "sg:address":"1681 Granville Rd",
    "sg:city":"Cedarburg",
    "sg:classifiers":[
        {
            "category":"Health Services",
            "subcategory":"Clinic",
            "type":"Services"
        }
    ],
    "sg:phone":"+1 262 377 1312",
    "sg:postcode":"53012",
    "sg:province":"WI",
    "sg:tags":[
        "organization",
        "maintenance"
    ],
    "wof:name":"Healthquest Inc",
    "wof:placetype":"venue"
},
  "geometry": {"coordinates":[-88.044679,43.334484],"type":"Point"}
}