{
  "type": "Feature",
  "properties": {
    "iso:country":"US",
    "sg:address":"11888 Velp Ave",
    "sg:city":"Green Bay",
    "sg:classifiers":[
        {
            "category":"Farming",
            "subcategory":"Nursery",
            "type":"Manufacturing & Wholesale Goods"
        }
    ],
    "sg:phone":"+1 920 434 6799",
    "sg:postcode":"54313",
    "sg:province":"WI",
    "sg:tags":[
        "ornamental",
        "greenhouse"
    ],
    "wof:name":"Bonnie's Mayflowers",
    "wof:placetype":"venue"
},
  "geometry": {"coordinates":[-88.077844,44.593245],"type":"Point"}
}