{
  "type": "Feature",
  "properties": {
    "addr:full":"2402 N 115th St Wauwatosa WI 53226",
    "addr:housenumber":"2402",
    "addr:postcode":"53226",
    "addr:street":"N 115Th St",
    "iso:country":"US",
    "sg:address":"2402 N 115th St",
    "sg:city":"Wauwatosa",
    "sg:classifiers":[
        {
            "category":"Real Estate",
            "subcategory":"Real Estate Agent",
            "type":"Services"
        }
    ],
    "sg:phone":"+1 414 257 0000",
    "sg:postcode":"53226",
    "sg:province":"WI",
    "wof:name":"Bluemound Investments",
    "wof:placetype":"venue"
},
  "geometry": {"coordinates":[-88.056304,43.064955],"type":"Point"}
}