{
  "type": "Feature",
  "properties": {
    "iso:country":"US",
    "sg:address":"5704 Grandview Rd",
    "sg:city":"Fond Du Lac",
    "sg:classifiers":[
        {
            "category":"Building & Trades",
            "subcategory":"Construction",
            "type":"Services"
        }
    ],
    "sg:phone":"+1 920 921 9354",
    "sg:postcode":"54935",
    "sg:province":"WI",
    "sg:tags":[
        "house",
        "builder",
        "operative"
    ],
    "wof:name":"Home Life Style Inc",
    "wof:placetype":"venue"
},
  "geometry": {"coordinates":[-88.371006,43.743364],"type":"Point"}
}