{
  "type": "Feature",
  "properties": {
    "addr:full":"12995 Halweg Rd Merrimac WI 53561",
    "addr:housenumber":"12995",
    "addr:postcode":"53561",
    "addr:street":"Halweg Rd",
    "iso:country":"US",
    "sg:address":"12995 Halweg Rd",
    "sg:city":"Merrimac",
    "sg:classifiers":[
        {
            "category":"Travel",
            "subcategory":"Campground",
            "type":"Entertainment"
        }
    ],
    "sg:phone":"+1 608 493 2367",
    "sg:postcode":"53561",
    "sg:province":"WI",
    "wof:name":"Merry Mac's Camp'n",
    "wof:placetype":"venue"
},
  "geometry": {"coordinates":[-89.675489,43.394326],"type":"Point"}
}