{
  "type": "Feature",
  "properties": {
    "iso:country":"US",
    "sg:address":"588 State Rd 49",
    "sg:city":"Berlin",
    "sg:classifiers":[
        {
            "category":"Retail",
            "subcategory":"Auto Repair",
            "type":"Services"
        }
    ],
    "sg:phone":"+1 920 361 4933",
    "sg:postcode":"54923",
    "sg:province":"WI",
    "sg:tags":[
        "body",
        "automobile",
        "painting"
    ],
    "wof:name":"Dave's Auto Body",
    "wof:placetype":"venue"
},
  "geometry": {"coordinates":[-88.95673,44.001484],"type":"Point"}
}