{
  "type": "Feature",
  "properties": {
    "iso:country":"US",
    "sg:address":"342 Cheviot Chase",
    "sg:city":"Waukesha",
    "sg:classifiers":[
        {
            "category":"Professional",
            "type":"Services"
        }
    ],
    "sg:phone":"+1 262 968 5321",
    "sg:postcode":"53186",
    "sg:province":"WI",
    "wof:name":"Cyberanalyzer",
    "wof:placetype":"venue"
},
  "geometry": {"coordinates":[-88.205704,42.997706],"type":"Point"}
}