{
  "type": "Feature",
  "properties": {
    "iso:country":"US",
    "sg:address":"1647 East St",
    "sg:city":"Racine",
    "sg:classifiers":[
        {
            "category":"Professional",
            "type":"Services"
        }
    ],
    "sg:phone":"+1 262 632 5957",
    "sg:postcode":"53402",
    "sg:province":"WI",
    "sg:tags":[
        "establishment"
    ],
    "wof:name":"Family Petty's",
    "wof:placetype":"venue"
},
  "geometry": {"coordinates":[-87.787476,42.74149],"type":"Point"}
}