{
  "type": "Feature",
  "properties": {
    "iso:country":"US",
    "sg:address":"500 W Milwaukee St",
    "sg:city":"Janesville",
    "sg:classifiers":[
        {
            "category":"Shopping",
            "subcategory":"Used Merchandise",
            "type":"Retail Goods"
        }
    ],
    "sg:phone":"+1 608 756 1058",
    "sg:postcode":"53545",
    "sg:province":"WI",
    "sg:tags":[
        "antique"
    ],
    "wof:name":"Packrats Den",
    "wof:placetype":"venue"
},
  "geometry": {"coordinates":[-89.030194,42.680001],"type":"Point"}
}