{
  "type": "Feature",
  "properties": {
    "addr:full":"205 United Way Frederic WI 54837",
    "addr:housenumber":"205",
    "addr:postcode":"54837",
    "addr:street":"United",
    "iso:country":"US",
    "sg:address":"205 United Way",
    "sg:city":"Frederic",
    "sg:classifiers":[
        {
            "category":"Health Services",
            "subcategory":"Nursing And Care Facility",
            "type":"Services"
        }
    ],
    "sg:phone":"+1 715 327 4297",
    "sg:postcode":"54837",
    "sg:province":"WI",
    "sg:tags":[
        "home",
        "skilled",
        "convalescent"
    ],
    "wof:name":"Frederic Care Center",
    "wof:placetype":"venue"
},
  "geometry": {"coordinates":[-92.46413099999999,45.643365],"type":"Point"}
}