{
  "type": "Feature",
  "properties": {
    "iso:country":"US",
    "sg:address":"22409 Co Rd Xx",
    "sg:city":"Kiel",
    "sg:classifiers":[
        {
            "category":"Building & Trades",
            "subcategory":"Landscaping Services",
            "type":"Services"
        }
    ],
    "sg:phone":"+1 920 894 7235",
    "sg:postcode":"53042",
    "sg:province":"WI",
    "sg:tags":[
        "landscape",
        "contractor"
    ],
    "wof:name":"Rivercrest Landscaping",
    "wof:placetype":"venue"
},
  "geometry": {"coordinates":[-88.000652,43.927838],"type":"Point"}
}