{
  "type": "Feature",
  "properties": {
    "iso:country":"US",
    "sg:address":"604 Water St",
    "sg:city":"Prairie Du Sac",
    "sg:classifiers":[
        {
            "category":"Insurance",
            "subcategory":"Insurance Agent",
            "type":"Services"
        }
    ],
    "sg:phone":"+1 608 643 8528",
    "sg:postcode":"53578",
    "sg:province":"WI",
    "wof:name":"State Farm Insurance",
    "wof:placetype":"venue"
},
  "geometry": {"coordinates":[-89.71854399999999,43.287742],"type":"Point"}
}