{
  "type": "Feature",
  "properties": {
    "iso:country":"US",
    "sg:address":"7120 School Dr",
    "sg:city":"Adell",
    "sg:classifiers":[
        {
            "category":"Wholesale",
            "subcategory":"Hardware",
            "type":"Manufacturing & Wholesale Goods"
        }
    ],
    "sg:phone":"+1 920 994 4772",
    "sg:postcode":"53001",
    "sg:province":"WI",
    "wof:name":"Thriftee Products",
    "wof:placetype":"venue"
},
  "geometry": {"coordinates":[-88.052349,43.593871],"type":"Point"}
}