{
  "type": "Feature",
  "properties": {
    "iso:country":"US",
    "sg:address":"2350 E Main St",
    "sg:city":"Reedsburg",
    "sg:classifiers":[
        {
            "category":"Real Estate",
            "subcategory":"Real Estate Agent",
            "type":"Services"
        }
    ],
    "sg:phone":"+1 608 524 8284",
    "sg:postcode":"53959",
    "sg:province":"WI",
    "wof:name":"Evergreen Realty Inc",
    "wof:placetype":"venue"
},
  "geometry": {"coordinates":[-89.975023,43.532449],"type":"Point"}
}