{
  "type": "Feature",
  "properties": {
    "iso:country":"US",
    "sg:address":"2564 Shore Dr",
    "sg:city":"Marinette",
    "sg:classifiers":[
        {
            "category":"Professional",
            "subcategory":"Engineering",
            "type":"Services"
        }
    ],
    "sg:phone":"+1 715 732 4339",
    "sg:postcode":"54143",
    "sg:province":"WI",
    "sg:tags":[
        "engineer"
    ],
    "wof:name":"Exworthy Engineering",
    "wof:placetype":"venue"
},
  "geometry": {"coordinates":[-87.619249,45.078625],"type":"Point"}
}