{
  "type": "Feature",
  "properties": {
    "iso:country":"US",
    "sg:address":"22721 Fish and Game Rd",
    "sg:city":"Kiel",
    "sg:classifiers":[
        {
            "category":"Organizations",
            "subcategory":"Community Association",
            "type":"Services"
        }
    ],
    "sg:phone":"+1 920 894 7397",
    "sg:postcode":"53042",
    "sg:province":"WI",
    "sg:tags":[
        "club"
    ],
    "wof:name":"Kiel Fish & Game Inc",
    "wof:placetype":"venue"
},
  "geometry": {"coordinates":[-88.017777,43.935313],"type":"Point"}
}