{
  "type": "Feature",
  "properties": {
    "iso:country":"US",
    "sg:address":"1247 N 51 St",
    "sg:city":"Caledonia",
    "sg:classifiers":[
        {
            "category":"Farming",
            "subcategory":"Nursery",
            "type":"Manufacturing & Wholesale Goods"
        }
    ],
    "sg:phone":"+1 262 835 4238",
    "sg:postcode":"53108",
    "sg:province":"WI",
    "sg:tags":[
        "ornamental"
    ],
    "wof:name":"West View Gardens",
    "wof:placetype":"venue"
},
  "geometry": {"coordinates":[-87.982456,42.815562],"type":"Point"}
}