{
  "type": "Feature",
  "properties": {
    "iso:country":"US",
    "sg:address":"1521 N Prospect Ave",
    "sg:city":"Milwaukee",
    "sg:classifiers":[
        {
            "category":"Recreation",
            "type":"Entertainment"
        }
    ],
    "sg:phone":"+1 414 278 9102",
    "sg:postcode":"53202",
    "sg:province":"WI",
    "sg:tags":[
        "club",
        "membership"
    ],
    "wof:name":"Alano Foundation Club",
    "wof:placetype":"venue"
},
  "geometry": {"coordinates":[-87.894253,43.049153],"type":"Point"}
}