{
  "type": "Feature",
  "properties": {
    "iso:country":"US",
    "sg:address":"2104 Oak St",
    "sg:city":"La Crosse",
    "sg:classifiers":[
        {
            "category":"Building & Trades",
            "subcategory":"Construction",
            "type":"Services"
        }
    ],
    "sg:phone":"+1 608 781 2770",
    "sg:postcode":"54603",
    "sg:province":"WI",
    "sg:tags":[
        "painter"
    ],
    "wof:name":"Rucker Painting Inc",
    "wof:placetype":"venue"
},
  "geometry": {"coordinates":[-91.229375,43.854292],"type":"Point"}
}