{
  "type": "Feature",
  "properties": {
    "iso:country":"US",
    "sg:address":"4419 Church Rd",
    "sg:city":"Eden",
    "sg:classifiers":[
        {
            "category":"Farming",
            "subcategory":"Dairy Farm",
            "type":"Manufacturing & Wholesale Goods"
        }
    ],
    "sg:phone":"+1 920 477 7033",
    "sg:postcode":"53019",
    "sg:province":"WI",
    "wof:name":"Murphy Way Farms",
    "wof:placetype":"venue"
},
  "geometry": {"coordinates":[-88.338712,43.703213],"type":"Point"}
}