{
  "type": "Feature",
  "properties": {
    "iso:country":"US",
    "sg:address":"510 54th Ave E",
    "sg:city":"Superior",
    "sg:classifiers":[
        {
            "category":"Railroad",
            "type":"Transportation"
        }
    ],
    "sg:phone":"+1 715 398 7241",
    "sg:postcode":"54880",
    "sg:province":"WI",
    "sg:tags":[
        "operator",
        "line"
    ],
    "wof:name":"Union Pacific Railroad Company",
    "wof:placetype":"venue"
},
  "geometry": {"coordinates":[-92.008345,46.671012],"type":"Point"}
}