{
  "type": "Feature",
  "properties": {
    "iso:country":"US",
    "sg:address":"10375 Riverside Rd",
    "sg:city":"Darlington",
    "sg:classifiers":[
        {
            "category":"Farming",
            "subcategory":"Farm",
            "type":"Manufacturing & Wholesale Goods"
        }
    ],
    "sg:phone":"+1 608 968 3361",
    "sg:postcode":"53530",
    "sg:province":"WI",
    "sg:tags":[
        "crop",
        "general"
    ],
    "wof:name":"Jerry Eamos",
    "wof:placetype":"venue"
},
  "geometry": {"coordinates":[-90.009987,42.643536],"type":"Point"}
}