{
  "type": "Feature",
  "properties": {
    "iso:country":"US",
    "sg:address":"3705 Country View Rd",
    "sg:city":"Sturgeon Bay",
    "sg:classifiers":[
        {
            "category":"Professional",
            "subcategory":"Business Services",
            "type":"Services"
        }
    ],
    "sg:phone":"+1 920 743 7309",
    "sg:postcode":"54235",
    "sg:province":"WI",
    "wof:name":"Auction Spclst-K C Auctioneers",
    "wof:placetype":"venue"
},
  "geometry": {"coordinates":[-87.295162,44.860692],"type":"Point"}
}