{
  "type": "Feature",
  "properties": {
    "iso:country":"US",
    "sg:address":"12975 40th Ave",
    "sg:city":"Chippewa Falls",
    "sg:classifiers":[
        {
            "category":"Autos & Motor Vehicles",
            "subcategory":"Boat Sales",
            "type":"Retail Goods"
        }
    ],
    "sg:phone":"+1 715 723 7670",
    "sg:postcode":"54729",
    "sg:province":"WI",
    "sg:tags":[
        "canoe"
    ],
    "wof:name":"Canoes Outfitters LLC",
    "wof:placetype":"venue"
},
  "geometry": {"coordinates":[-91.40933099999999,44.900712],"type":"Point"}
}