{
  "type": "Feature",
  "properties": {
    "iso:country":"US",
    "sg:address":"4332 W Noss Rd",
    "sg:city":"Beloit",
    "sg:classifiers":[
        {
            "category":"Building & Trades",
            "subcategory":"Electrical",
            "type":"Services"
        }
    ],
    "sg:phone":"+1 608 363 8538",
    "sg:postcode":"53511",
    "sg:province":"WI",
    "sg:tags":[
        "electric",
        "contractor"
    ],
    "wof:name":"K E Electric",
    "wof:placetype":"venue"
},
  "geometry": {"coordinates":[-89.08047000000001,42.591828],"type":"Point"}
}