{
  "type": "Feature",
  "properties": {
    "iso:country":"US",
    "sg:address":"13128 N Fox Hollow Rd",
    "sg:city":"Mequon",
    "sg:classifiers":[
        {
            "category":"Health Services",
            "subcategory":"Doctor",
            "type":"Services"
        }
    ],
    "sg:phone":"+1 262 242 2226",
    "sg:postcode":"53097",
    "sg:province":"WI",
    "sg:tags":[
        "contract"
    ],
    "wof:name":"Ronald G Rubin MD",
    "wof:placetype":"venue"
},
  "geometry": {"coordinates":[-88.0564,43.251386],"type":"Point"}
}