{
  "type": "Feature",
  "properties": {
    "iso:country":"US",
    "sg:address":"1153 Oakwood Manor Dr",
    "sg:city":"Hubertus",
    "sg:classifiers":[
        {
            "category":"Shopping",
            "subcategory":"Bicycles & Sporting Goods",
            "type":"Retail Goods"
        }
    ],
    "sg:phone":"+1 262 628 0758",
    "sg:postcode":"53033",
    "sg:province":"WI",
    "sg:tags":[
        "saddlery",
        "harness"
    ],
    "wof:name":"Main Event Saddlery",
    "wof:placetype":"venue"
},
  "geometry": {"coordinates":[-88.224522,43.232495],"type":"Point"}
}