{
  "type": "Feature",
  "properties": {
    "iso:country":"US",
    "sg:address":"1842 College Ave",
    "sg:city":"Racine",
    "sg:classifiers":[
        {
            "category":"Professional",
            "subcategory":"Employment Agencies",
            "type":"Services"
        }
    ],
    "sg:phone":"+1 262 632 8309",
    "sg:postcode":"53403",
    "sg:province":"WI",
    "wof:name":"Diversitygrads Co LLC",
    "wof:placetype":"venue"
},
  "geometry": {"coordinates":[-87.784806,42.708304],"type":"Point"}
}