{
  "type": "Feature",
  "properties": {
    "iso:country":"US",
    "sg:address":"32 S Wisconsin St",
    "sg:city":"Elkhorn",
    "sg:classifiers":[
        {
            "category":"Real Estate",
            "subcategory":"Architect",
            "type":"Services"
        }
    ],
    "sg:phone":"+1 262 723 4399",
    "sg:postcode":"53121",
    "sg:province":"WI",
    "sg:tags":[
        "architectural",
        "engineer"
    ],
    "wof:name":"Wmr Associates",
    "wof:placetype":"venue"
},
  "geometry": {"coordinates":[-88.543606,42.671397],"type":"Point"}
}