{
  "type": "Feature",
  "properties": {
    "iso:country":"US",
    "sg:address":"511 E Sheffield Ln",
    "sg:city":"Appleton",
    "sg:classifiers":[
        {
            "category":"Personal",
            "type":"Services"
        }
    ],
    "sg:phone":"+1 920 915 1702",
    "sg:postcode":"54913",
    "sg:province":"WI",
    "sg:tags":[
        "consultant",
        "wedding"
    ],
    "wof:name":"Ideal Printing",
    "wof:placetype":"venue"
},
  "geometry": {"coordinates":[-88.39826499999999,44.309553],"type":"Point"}
}