{
  "type": "Feature",
  "properties": {
    "iso:country":"US",
    "sg:address":"138 Douglass Ave",
    "sg:city":"Waukesha",
    "sg:classifiers":[
        {
            "category":"Social Services",
            "subcategory":"Child Care",
            "type":"Services"
        }
    ],
    "sg:phone":"+1 262 542 7834",
    "sg:postcode":"53186",
    "sg:province":"WI",
    "sg:tags":[
        "day"
    ],
    "wof:name":"Tots N Toddlers Day Care",
    "wof:placetype":"venue"
},
  "geometry": {"coordinates":[-88.22949699999999,42.99438],"type":"Point"}
}