{
  "type": "Feature",
  "properties": {
    "iso:country":"US",
    "sg:address":"3825 N 124th St",
    "sg:city":"Brookfield",
    "sg:classifiers":[
        {
            "category":"Professional",
            "subcategory":"Detective & Security Services",
            "type":"Services"
        }
    ],
    "sg:phone":"+1 262 790 4520",
    "sg:postcode":"53005",
    "sg:province":"WI",
    "sg:tags":[
        "system"
    ],
    "wof:name":"ADT Security Services Inc",
    "wof:placetype":"venue"
},
  "geometry": {"coordinates":[-88.066478,43.087008],"type":"Point"}
}