{
  "type": "Feature",
  "properties": {
    "iso:country":"US",
    "sg:address":"2613 N 4th St",
    "sg:city":"Milwaukee",
    "sg:classifiers":[
        {
            "category":"Social Services",
            "subcategory":"Child Care",
            "type":"Services"
        }
    ],
    "sg:phone":"+1 414 264 6361",
    "sg:postcode":"53212",
    "sg:province":"WI",
    "sg:tags":[
        "day"
    ],
    "wof:name":"Angels LI Academy",
    "wof:placetype":"venue"
},
  "geometry": {"coordinates":[-87.915614,43.06734],"type":"Point"}
}