{
  "type": "Feature",
  "properties": {
    "addr:full":"2491 Co Rd H Kewaskum WI 53040",
    "addr:housenumber":"2491",
    "addr:postcode":"53040",
    "addr:street":"Co Rd H",
    "iso:country":"US",
    "sg:address":"2491 Co Rd H",
    "sg:city":"Kewaskum",
    "sg:classifiers":[
        {
            "category":"Building & Trades",
            "subcategory":"Construction",
            "type":"Services"
        }
    ],
    "sg:phone":"+1 262 626 8049",
    "sg:postcode":"53040",
    "sg:province":"WI",
    "sg:tags":[
        "excavation",
        "contractor"
    ],
    "wof:name":"Flasch Excavating Inc",
    "wof:placetype":"venue"
},
  "geometry": {"coordinates":[-88.159633,43.498589],"type":"Point"}
}