{
  "type": "Feature",
  "properties": {
    "iso:country":"US",
    "sg:address":"517 E Wisconsin Ave # 258",
    "sg:city":"Milwaukee",
    "sg:classifiers":[
        {
            "category":"Government",
            "subcategory":"Court House",
            "type":"Public Place"
        },
        {
            "category":"Government",
            "subcategory":"Office",
            "type":"Public Place"
        }
    ],
    "sg:phone":"+1 414 297 3963",
    "sg:postcode":"53202",
    "sg:province":"WI",
    "sg:tags":[
        "justice",
        "government-united",
        "state"
    ],
    "sg:website":"http://www.alnb.uscourts.gov",
    "wof:name":"United State Magistrate Judge",
    "wof:placetype":"venue"
},
  "geometry": {"coordinates":[-87.905051,43.038821],"type":"Point"}
}