{
  "type": "Feature",
  "properties": {
    "iso:country":"US",
    "sg:address":"1003 Firethorn Dr",
    "sg:city":"West Bend",
    "sg:classifiers":[
        {
            "category":"Building & Trades",
            "subcategory":"Cleaning & Sanitation",
            "type":"Services"
        }
    ],
    "sg:phone":"+1 262 306 7622",
    "sg:postcode":"53090",
    "sg:province":"WI",
    "sg:tags":[
        "maintenance"
    ],
    "wof:name":"Summit Cleaning Services LLC",
    "wof:placetype":"venue"
},
  "geometry": {"coordinates":[-88.16508899999999,43.434586],"type":"Point"}
}