{
  "type": "Feature",
  "properties": {
    "iso:country":"US",
    "sg:address":"220 N Lynnwood Ln",
    "sg:city":"Brookfield",
    "sg:classifiers":[
        {
            "category":"Professional",
            "subcategory":"Advertising",
            "type":"Services"
        }
    ],
    "sg:phone":"+1 262 780 1091",
    "sg:postcode":"53005",
    "sg:province":"WI",
    "sg:tags":[
        "agency"
    ],
    "wof:name":"G2 Ad Venture LLC",
    "wof:placetype":"venue"
},
  "geometry": {"coordinates":[-88.09810899999999,43.032285],"type":"Point"}
}