{
  "type": "Feature",
  "properties": {
    "iso:country":"US",
    "sg:address":"2909 N Holton St",
    "sg:city":"Milwaukee",
    "sg:classifiers":[
        {
            "category":"Food & Beverages",
            "subcategory":"Groceries & Convenience Stores",
            "type":"Retail Goods"
        }
    ],
    "sg:phone":"+1 414 562 4404",
    "sg:postcode":"53212",
    "sg:province":"WI",
    "sg:tags":[
        "grocer"
    ],
    "wof:name":"Riverwest Superfoods Inc",
    "wof:placetype":"venue"
},
  "geometry": {"coordinates":[-87.905321,43.072801],"type":"Point"}
}