{
  "type": "Feature",
  "properties": {
    "addr:full":"217 W Wisconsin Ave Waukesha WI 53186",
    "addr:housenumber":"217",
    "addr:postcode":"53186",
    "addr:street":"W Wisconsin Ave",
    "iso:country":"US",
    "sg:address":"217 W Wisconsin Ave",
    "sg:city":"Waukesha",
    "sg:classifiers":[
        {
            "category":"Health Services",
            "subcategory":"Hospital",
            "type":"Services"
        }
    ],
    "sg:phone":"+1 262 524 8886",
    "sg:postcode":"53186",
    "sg:province":"WI",
    "sg:tags":[
        "mental"
    ],
    "wof:name":"NAMI Waukesha",
    "wof:placetype":"venue"
},
  "geometry": {"coordinates":[-88.23128199999999,43.009677],"type":"Point"}
}