{
  "type": "Feature",
  "properties": {
    "iso:country":"US",
    "sg:address":"1833 Boyd Ave",
    "sg:city":"Madison",
    "sg:classifiers":[
        {
            "category":"Personal",
            "subcategory":"Beauty Salon",
            "type":"Services"
        }
    ],
    "sg:phone":"+1 608 245 2712",
    "sg:postcode":"53704",
    "sg:province":"WI",
    "sg:tags":[
        "spa",
        "day"
    ],
    "wof:name":"Kneaded Relief Day Spa",
    "wof:placetype":"venue"
},
  "geometry": {"coordinates":[-89.359142,43.115309],"type":"Point"}
}