{
  "type": "Feature",
  "properties": {
    "iso:country":"US",
    "sg:address":"2103 S 15th St",
    "sg:city":"Milwaukee",
    "sg:classifiers":[
        {
            "category":"Building & Trades",
            "subcategory":"Cleaning & Sanitation",
            "type":"Services"
        }
    ],
    "sg:phone":"+1 414 383 3861",
    "sg:postcode":"53215",
    "sg:province":"WI",
    "sg:tags":[
        "janitor"
    ],
    "wof:name":"IMC Cleaning Enterprises",
    "wof:placetype":"venue"
},
  "geometry": {"coordinates":[-87.931203,43.004728],"type":"Point"}
}