{
  "type": "Feature",
  "properties": {
    "iso:country":"US",
    "sg:address":"124 Main St",
    "sg:city":"Luxemburg",
    "sg:classifiers":[
        {
            "category":"Food & Beverages",
            "subcategory":"Dairy",
            "type":"Retail Goods"
        }
    ],
    "sg:phone":"+1 920 845 5330",
    "sg:postcode":"54217",
    "sg:province":"WI",
    "sg:tags":[
        "cheese"
    ],
    "wof:name":"Ron's Wisconsin Cheese & Coin",
    "wof:placetype":"venue"
},
  "geometry": {"coordinates":[-87.703277,44.545004],"type":"Point"}
}