{
  "type": "Feature",
  "properties": {
    "iso:country":"US",
    "sg:address":"2000 N Oxford Ave",
    "sg:city":"Eau Claire",
    "sg:classifiers":[
        {
            "category":"Utilities",
            "subcategory":"Cable",
            "type":"Services"
        }
    ],
    "sg:phone":"+1 715 552 1287",
    "sg:postcode":"54703",
    "sg:province":"WI",
    "sg:tags":[
        "television"
    ],
    "wof:name":"Future Visions Satellites LLC",
    "wof:placetype":"venue"
},
  "geometry": {"coordinates":[-91.5098,44.81941],"type":"Point"}
}