{
  "type": "Feature",
  "properties": {
    "iso:country":"US",
    "sg:address":"3824 W Vliet St",
    "sg:city":"Milwaukee",
    "sg:classifiers":[
        {
            "category":"Organizations",
            "subcategory":"Community Association",
            "type":"Services"
        }
    ],
    "sg:phone":"+1 414 344 6575",
    "sg:postcode":"53208",
    "sg:province":"WI",
    "sg:tags":[
        "workers'",
        "placement",
        "volunteer"
    ],
    "wof:name":"Hmong American Friendship Association Inc",
    "wof:placetype":"venue"
},
  "geometry": {"coordinates":[-87.961952,43.048771],"type":"Point"}
}