{
  "type": "Feature",
  "properties": {
    "iso:country":"US",
    "sg:address":"7941 S Cecily Dr",
    "sg:city":"Oak Creek",
    "sg:classifiers":[
        {
            "category":"Professional",
            "subcategory":"Business Services",
            "type":"Services"
        }
    ],
    "sg:phone":"+1 414 571 9906",
    "sg:postcode":"53154",
    "sg:province":"WI",
    "wof:name":"Patriot Partners SCM LLC",
    "wof:placetype":"venue"
},
  "geometry": {"coordinates":[-87.904178,42.899929],"type":"Point"}
}