{
  "type": "Feature",
  "properties": {
    "iso:country":"US",
    "sg:address":"2829 S 99th St",
    "sg:city":"Milwaukee",
    "sg:classifiers":[
        {
            "category":"Manufacturing",
            "subcategory":"Watercraft",
            "type":"Manufacturing & Wholesale Goods"
        }
    ],
    "sg:phone":"+1 414 321 9662",
    "sg:postcode":"53227",
    "sg:province":"WI",
    "wof:name":"Schillings Trolling Motor Svc",
    "wof:placetype":"venue"
},
  "geometry": {"coordinates":[-88.035927,42.995136],"type":"Point"}
}