{
  "type": "Feature",
  "properties": {
    "iso:country":"US",
    "sg:address":"4613 Amanda Ln",
    "sg:city":"Sheboygan",
    "sg:classifiers":[
        {
            "category":"Shopping",
            "subcategory":"Gifts & Souvenirs",
            "type":"Retail Goods"
        }
    ],
    "sg:phone":"+1 920 208 0618",
    "sg:postcode":"53081",
    "sg:province":"WI",
    "wof:name":"Quality Cards & Statione",
    "wof:placetype":"venue"
},
  "geometry": {"coordinates":[-87.743419,43.701898],"type":"Point"}
}