{
  "type": "Feature",
  "properties": {
    "iso:country":"US",
    "sg:address":"2542 S 11th Rd",
    "sg:city":"Coleman",
    "sg:classifiers":[
        {
            "category":"Freight",
            "type":"Transportation"
        }
    ],
    "sg:phone":"+1 920 897 4380",
    "sg:postcode":"54112",
    "sg:province":"WI",
    "wof:name":"Mursau Transport LLC",
    "wof:placetype":"venue"
},
  "geometry": {"coordinates":[-88.00425199999999,45.034847],"type":"Point"}
}