{
  "type": "Feature",
  "properties": {
    "iso:country":"US",
    "sg:address":"5522 Dahlen Dr",
    "sg:city":"Madison",
    "sg:classifiers":[
        {
            "category":"Professional",
            "subcategory":"Accounting & Tax Preparation",
            "type":"Services"
        }
    ],
    "sg:phone":"+1 608 233 1667",
    "sg:postcode":"53705",
    "sg:province":"WI",
    "wof:name":"Hildebrand Accountant",
    "wof:placetype":"venue"
},
  "geometry": {"coordinates":[-89.476325,43.077479],"type":"Point"}
}