{
  "type": "Feature",
  "properties": {
    "iso:country":"US",
    "sg:address":"1509 Post Ave",
    "sg:city":"Schofield",
    "sg:classifiers":[
        {
            "category":"Personal",
            "type":"Services"
        },
        {
            "category":"Retail",
            "subcategory":"Auto Repair",
            "type":"Services"
        }
    ],
    "sg:phone":"+1 715 359 8561",
    "sg:postcode":"54476",
    "sg:province":"WI",
    "sg:tags":[
        "body",
        "repairing",
        "automobile",
        "removal",
        "towing",
        "truck",
        "dent",
        "painting"
    ],
    "sg:website":"http://www.precisionbodyandframe.com",
    "wof:name":"Precision Body & Frame",
    "wof:placetype":"venue"
},
  "geometry": {"coordinates":[-89.60517900000001,44.907873],"type":"Point"}
}