{
  "type": "Feature",
  "properties": {
    "iso:country":"US",
    "sg:address":"1719 Johnson Ct",
    "sg:city":"Stoughton",
    "sg:classifiers":[
        {
            "category":"Building & Trades",
            "subcategory":"Construction",
            "type":"Services"
        }
    ],
    "sg:phone":"+1 608 873 8696",
    "sg:postcode":"53589",
    "sg:province":"WI",
    "sg:tags":[
        "house"
    ],
    "wof:name":"All Custom Remodeling",
    "wof:placetype":"venue"
},
  "geometry": {"coordinates":[-89.224555,42.932307],"type":"Point"}
}