{
  "type": "Feature",
  "properties": {
    "iso:country":"US",
    "sg:address":"8330 Corporate Dr",
    "sg:city":"Racine",
    "sg:classifiers":[
        {
            "category":"Professional",
            "subcategory":"Employment Agencies",
            "type":"Services"
        }
    ],
    "sg:phone":"+1 262 884 8674",
    "sg:postcode":"53406",
    "sg:province":"WI",
    "sg:tags":[
        "consultant",
        "search",
        "executive"
    ],
    "wof:name":"Human Resource Consulting Grp",
    "wof:placetype":"venue"
},
  "geometry": {"coordinates":[-87.885859,42.722242],"type":"Point"}
}