{
  "type": "Feature",
  "properties": {
    "iso:country":"US",
    "sg:address":"8290 390th Ave",
    "sg:city":"Ellsworth",
    "sg:classifiers":[
        {
            "category":"Building & Trades",
            "subcategory":"Construction",
            "type":"Services"
        },
        {
            "category":"Home & Garden",
            "subcategory":"Furniture",
            "type":"Retail Goods"
        }
    ],
    "sg:phone":"+1 715 792 5400",
    "sg:postcode":"54011",
    "sg:province":"WI",
    "sg:tags":[
        "mfg",
        "kitchen",
        "cabinet",
        "wood",
        "contractor",
        "carpentry"
    ],
    "wof:name":"Boyd's Quality Cabinets",
    "wof:placetype":"venue"
},
  "geometry": {"coordinates":[-92.547616,44.680973],"type":"Point"}
}