{
  "type": "Feature",
  "properties": {
    "iso:country":"US",
    "sg:address":"6279 Lake Shore Dr",
    "sg:city":"Hilbert",
    "sg:classifiers":[
        {
            "category":"Farming",
            "subcategory":"Farm & Veterinary Services",
            "type":"Manufacturing & Wholesale Goods"
        }
    ],
    "sg:phone":"+1 920 989 2222",
    "sg:postcode":"54129",
    "sg:province":"WI",
    "sg:tags":[
        "livestock"
    ],
    "wof:name":"Graycliff LLC",
    "wof:placetype":"venue"
},
  "geometry": {"coordinates":[-88.311898,44.106446],"type":"Point"}
}