{
  "type": "Feature",
  "properties": {
    "iso:country":"US",
    "sg:address":"1214 Belknap St",
    "sg:city":"Superior",
    "sg:classifiers":[
        {
            "category":"Professional",
            "subcategory":"Lawyer & Legal Services",
            "type":"Services"
        }
    ],
    "sg:phone":"+1 715 394 6624",
    "sg:postcode":"54880",
    "sg:province":"WI",
    "wof:name":"Marcovich Cochrane & Milliken",
    "wof:placetype":"venue"
},
  "geometry": {"coordinates":[-92.09623499999999,46.72058],"type":"Point"}
}