{
  "type": "Feature",
  "properties": {
    "iso:country":"US",
    "sg:address":"1344 Main St",
    "sg:city":"Green Bay",
    "sg:classifiers":[
        {
            "category":"Shopping",
            "subcategory":"Used Merchandise",
            "type":"Retail Goods"
        }
    ],
    "sg:phone":"+1 920 437 3596",
    "sg:postcode":"54302",
    "sg:province":"WI",
    "sg:tags":[
        "antique"
    ],
    "wof:name":"Red's Antiques",
    "wof:placetype":"venue"
},
  "geometry": {"coordinates":[-87.995031,44.510607],"type":"Point"}
}