{
  "type": "Feature",
  "properties": {
    "addr:full":"2925 Town Hall Rd Mount Horeb WI 53572",
    "addr:housenumber":"2925",
    "addr:postcode":"53572",
    "addr:street":"Town Hall Rd",
    "iso:country":"US",
    "sg:address":"2925 Town Hall Rd",
    "sg:city":"Mount Horeb",
    "sg:classifiers":[
        {
            "category":"Building & Trades",
            "subcategory":"Construction",
            "type":"Services"
        }
    ],
    "sg:phone":"+1 608 437 4696",
    "sg:postcode":"53572",
    "sg:province":"WI",
    "sg:tags":[
        "hanging",
        "contractor"
    ],
    "wof:name":"Fox Painting Service",
    "wof:placetype":"venue"
},
  "geometry": {"coordinates":[-89.691813,43.016533],"type":"Point"}
}