{
  "type": "Feature",
  "properties": {
    "addr:full":"612 Grove St Neenah WI 54956",
    "addr:housenumber":"612",
    "addr:postcode":"54956",
    "addr:street":"Grove St",
    "iso:country":"US",
    "sg:address":"612 Grove St",
    "sg:city":"Neenah",
    "sg:classifiers":[
        {
            "category":"Building & Trades",
            "subcategory":"Construction",
            "type":"Services"
        }
    ],
    "sg:phone":"+1 920 725 7458",
    "sg:postcode":"54956",
    "sg:province":"WI",
    "sg:tags":[
        "hanging",
        "contractor"
    ],
    "wof:name":"Jan Williams Painting",
    "wof:placetype":"venue"
},
  "geometry": {"coordinates":[-88.461089,44.175474],"type":"Point"}
}