{
  "type": "Feature",
  "properties": {
    "iso:country":"US",
    "sg:address":"4061 Co Hwy Bc",
    "sg:city":"Sparta",
    "sg:classifiers":[
        {
            "category":"Professional",
            "type":"Services"
        }
    ],
    "sg:phone":"+1 608 366 1992",
    "sg:postcode":"54656",
    "sg:province":"WI",
    "wof:name":"Todd Langrehr",
    "wof:placetype":"venue"
},
  "geometry": {"coordinates":[-90.89169699999999,43.973968],"type":"Point"}
}