{
  "type": "Feature",
  "properties": {
    "iso:country":"US",
    "sg:address":"1012 West St",
    "sg:city":"Baraboo",
    "sg:classifiers":[
        {
            "category":"Organizations",
            "subcategory":"Religious Organization",
            "type":"Services"
        }
    ],
    "sg:phone":"+1 608 356 7622",
    "sg:postcode":"53913",
    "sg:province":"WI",
    "sg:tags":[
        "church"
    ],
    "wof:name":"Church Of Christ",
    "wof:placetype":"venue"
},
  "geometry": {"coordinates":[-89.747661,43.475203],"type":"Point"}
}