{
  "type": "Feature",
  "properties": {
    "iso:country":"US",
    "sg:address":"3522 W Pierce St",
    "sg:city":"Milwaukee",
    "sg:classifiers":[
        {
            "category":"Food & Beverages",
            "subcategory":"Specialty",
            "type":"Retail Goods"
        }
    ],
    "sg:phone":"+1 414 384 7258",
    "sg:postcode":"53215",
    "sg:province":"WI",
    "sg:tags":[
        "salt"
    ],
    "wof:name":"Superior Salt Svc",
    "wof:placetype":"venue"
},
  "geometry": {"coordinates":[-87.958633,43.023721],"type":"Point"}
}