{
  "type": "Feature",
  "properties": {
    "iso:country":"US",
    "sg:address":"206 Church Ave",
    "sg:city":"Casco",
    "sg:classifiers":[
        {
            "category":"Wholesale",
            "subcategory":"Farm Supplies",
            "type":"Manufacturing & Wholesale Goods"
        }
    ],
    "sg:phone":"+1 920 837 7442",
    "sg:postcode":"54205",
    "sg:province":"WI",
    "sg:tags":[
        "feed"
    ],
    "wof:name":"Frank's Feedmill Inc",
    "wof:placetype":"venue"
},
  "geometry": {"coordinates":[-87.617956,44.555921],"type":"Point"}
}