{
  "type": "Feature",
  "properties": {
    "iso:country":"US",
    "sg:address":"2110 W Clybourn St",
    "sg:city":"Milwaukee",
    "sg:classifiers":[
        {
            "category":"Building & Trades",
            "subcategory":"Electrical",
            "type":"Services"
        }
    ],
    "sg:phone":"+1 414 933 6970",
    "sg:postcode":"53233",
    "sg:province":"WI",
    "sg:tags":[
        "general",
        "electrical",
        "contractor"
    ],
    "sg:website":"www.terminalandrae.com",
    "wof:name":"Terminal-Andrae Inc",
    "wof:placetype":"venue"
},
  "geometry": {"coordinates":[-87.93975399999999,43.036198],"type":"Point"}
}