{
  "type": "Feature",
  "properties": {
    "addr:full":"996 S Green Bay Rd Neenah WI 54956",
    "addr:housenumber":"996",
    "addr:postcode":"54956",
    "addr:street":"S Green Bay Rd",
    "iso:country":"US",
    "sg:address":"996 S Green Bay Rd",
    "sg:city":"Neenah",
    "sg:classifiers":[
        {
            "category":"Health Services",
            "subcategory":"Doctor",
            "type":"Services"
        }
    ],
    "sg:phone":"+1 920 729 1031",
    "sg:postcode":"54956",
    "sg:province":"WI",
    "sg:tags":[
        "medical"
    ],
    "wof:name":"John Steiner Od",
    "wof:placetype":"venue"
},
  "geometry": {"coordinates":[-88.48489499999999,44.174544],"type":"Point"}
}