{
  "type": "Feature",
  "properties": {
    "iso:country":"US",
    "sg:address":"5996 Valley Heights Rd",
    "sg:city":"Fredonia",
    "sg:classifiers":[
        {
            "category":"Building & Trades",
            "subcategory":"Construction",
            "type":"Services"
        }
    ],
    "sg:phone":"+1 262 692 6359",
    "sg:postcode":"53021",
    "sg:province":"WI",
    "sg:tags":[
        "house"
    ],
    "wof:name":"Bb Contractors",
    "wof:placetype":"venue"
},
  "geometry": {"coordinates":[-88.026848,43.497614],"type":"Point"}
}