{
  "type": "Feature",
  "properties": {
    "addr:full":"502 22nd Ave E Superior WI 54880",
    "addr:housenumber":"502",
    "addr:postcode":"54880",
    "addr:street":"22Nd Ave E",
    "iso:country":"US",
    "sg:address":"502 22nd Ave E",
    "sg:city":"Superior",
    "sg:classifiers":[
        {
            "category":"Insurance",
            "subcategory":"Insurance Agent",
            "type":"Services"
        }
    ],
    "sg:phone":"+1 715 398 7993",
    "sg:postcode":"54880",
    "sg:province":"WI",
    "wof:name":"C A Gray Insurance",
    "wof:placetype":"venue"
},
  "geometry": {"coordinates":[-92.051389,46.704233],"type":"Point"}
}