{
  "type": "Feature",
  "properties": {
    "iso:country":"US",
    "sg:address":"5437 Co Rd Cj",
    "sg:city":"Rosholt",
    "sg:phone":"+1 715 341 0240",
    "sg:postcode":"54473",
    "sg:province":"WI",
    "sg:tags":[
        "farm",
        "irish",
        "machinery",
        "potato"
    ],
    "wof:name":"Anton Dombrowski",
    "wof:placetype":"venue"
},
  "geometry": {"coordinates":[-89.44176299999999,44.713346],"type":"Point"}
}