{
  "type": "Feature",
  "properties": {
    "iso:country":"US",
    "sg:address":"101 Christopher Ct",
    "sg:city":"Eden",
    "sg:classifiers":[
        {
            "category":"Manufacturing",
            "subcategory":"Tools & Machinery",
            "type":"Manufacturing & Wholesale Goods"
        }
    ],
    "sg:phone":"+1 920 477 6833",
    "sg:postcode":"53019",
    "sg:province":"WI",
    "sg:tags":[
        "equipment",
        "petroleum"
    ],
    "wof:name":"Petro-Chemical Systems Inc",
    "wof:placetype":"venue"
},
  "geometry": {"coordinates":[-88.369282,43.690276],"type":"Point"}
}