{
  "type": "Feature",
  "properties": {
    "addr:full":"7872 Deer Run Rd Cross Plains WI 53528",
    "addr:housenumber":"7872",
    "addr:postcode":"53528",
    "addr:street":"Deer Run Rd",
    "iso:country":"US",
    "sg:address":"7872 Deer Run Rd",
    "sg:city":"Cross Plains",
    "sg:classifiers":[
        {
            "category":"Building & Trades",
            "subcategory":"Landscaping Services",
            "type":"Services"
        }
    ],
    "sg:phone":"+1 608 798 3772",
    "sg:postcode":"53528",
    "sg:province":"WI",
    "sg:tags":[
        "landscape"
    ],
    "wof:name":"Blade Techgenetics Co LLC",
    "wof:placetype":"venue"
},
  "geometry": {"coordinates":[-89.59958,43.090463],"type":"Point"}
}