{
  "type": "Feature",
  "properties": {
    "iso:country":"US",
    "sg:address":"358 E Lakeside St",
    "sg:city":"Madison",
    "sg:classifiers":[
        {
            "category":"Shopping",
            "subcategory":"Musical Instruments",
            "type":"Retail Goods"
        }
    ],
    "sg:phone":"+1 608 260 9424",
    "sg:postcode":"53715",
    "sg:province":"WI",
    "wof:name":"Mike Wenglers Guitar Studio",
    "wof:placetype":"venue"
},
  "geometry": {"coordinates":[-89.38034399999999,43.056016],"type":"Point"}
}