{
  "type": "Feature",
  "properties": {
    "addr:full":"187 E Becher St Milwaukee WI 53207",
    "addr:housenumber":"187",
    "addr:postcode":"53207",
    "addr:street":"E Becher St",
    "iso:country":"US",
    "sg:address":"187 E Becher St",
    "sg:city":"Milwaukee",
    "sg:classifiers":[
        {
            "category":"Wholesale",
            "subcategory":"Construction Materials",
            "type":"Manufacturing & Wholesale Goods"
        }
    ],
    "sg:phone":"+1 414 482 4860",
    "sg:postcode":"53207",
    "sg:province":"WI",
    "sg:tags":[
        "building",
        "roofing",
        "industrial",
        "contractor",
        "siding",
        "contractors-commercial"
    ],
    "wof:name":"Architectural Sales Corp",
    "wof:placetype":"venue"
},
  "geometry": {"coordinates":[-87.908209,43.006503],"type":"Point"}
}