{
  "type": "Feature",
  "properties": {
    "iso:country":"US",
    "sg:address":"14536 Bruce Mound Ave",
    "sg:city":"Thorp",
    "sg:classifiers":[
        {
            "category":"Farming",
            "subcategory":"Dairy Farm",
            "type":"Manufacturing & Wholesale Goods"
        }
    ],
    "sg:phone":"+1 715 669 3327",
    "sg:postcode":"54771",
    "sg:province":"WI",
    "wof:name":"Our Kine Inc",
    "wof:placetype":"venue"
},
  "geometry": {"coordinates":[-90.780633,44.951474],"type":"Point"}
}