{
  "type": "Feature",
  "properties": {
    "addr:full":"5514 Hammersley Rd Madison WI 53711",
    "addr:housenumber":"5514",
    "addr:postcode":"53711",
    "addr:street":"Hammersley Rd",
    "iso:country":"US",
    "sg:address":"5514 Hammersley Rd",
    "sg:city":"Madison",
    "sg:classifiers":[
        {
            "category":"Building & Trades",
            "subcategory":"Construction",
            "type":"Services"
        }
    ],
    "sg:phone":"+1 608 298 9803",
    "sg:postcode":"53711",
    "sg:province":"WI",
    "sg:tags":[
        "contractor"
    ],
    "wof:name":"Ciaria Tile Studio",
    "wof:placetype":"venue"
},
  "geometry": {"coordinates":[-89.477389,43.039237],"type":"Point"}
}