{
  "type": "Feature",
  "properties": {
    "iso:country":"US",
    "sg:address":"4351 Co Rd Hh",
    "sg:city":"Plum City",
    "sg:classifiers":[
        {
            "category":"Recreation",
            "type":"Entertainment"
        }
    ],
    "sg:phone":"+1 715 639 5611",
    "sg:postcode":"54761",
    "sg:province":"WI",
    "sg:tags":[
        "parks"
    ],
    "wof:name":"Nugget Lake County Park",
    "wof:placetype":"venue"
},
  "geometry": {"coordinates":[-92.221497,44.698154],"type":"Point"}
}