{
  "type": "Feature",
  "properties": {
    "iso:country":"US",
    "sg:address":"1227 E Division Ave",
    "sg:city":"Barron",
    "sg:classifiers":[
        {
            "category":"Food & Beverages",
            "subcategory":"Liquor & Beverages",
            "type":"Retail Goods"
        }
    ],
    "sg:phone":"+1 715 537 3007",
    "sg:postcode":"54812",
    "sg:province":"WI",
    "wof:name":"Warren G's Liquors",
    "wof:placetype":"venue"
},
  "geometry": {"coordinates":[-91.841273,45.401354],"type":"Point"}
}