{
  "type": "Feature",
  "properties": {
    "iso:country":"US",
    "sg:address":"1055 Charnley Lk Rd",
    "sg:city":"Park Falls",
    "sg:classifiers":[
        {
            "category":"Building & Trades",
            "subcategory":"Landscaping Services",
            "type":"Services"
        }
    ],
    "sg:phone":"+1 715 583 4558",
    "sg:postcode":"54552",
    "sg:province":"WI",
    "sg:tags":[
        "landscape",
        "contractor"
    ],
    "wof:name":"K M Landscaping",
    "wof:placetype":"venue"
},
  "geometry": {"coordinates":[-90.146038,46.014669],"type":"Point"}
}