{
  "type": "Feature",
  "properties": {
    "iso:country":"US",
    "sg:address":"335 Whitewater Ave",
    "sg:city":"Fort Atkinson",
    "sg:classifiers":[
        {
            "category":"Insurance",
            "subcategory":"Insurance Agent",
            "type":"Services"
        }
    ],
    "sg:phone":"+1 920 563 6047",
    "sg:postcode":"53538",
    "sg:province":"WI",
    "wof:name":"State Farm Insurance",
    "wof:placetype":"venue"
},
  "geometry": {"coordinates":[-88.836646,42.924663],"type":"Point"}
}