{
  "type": "Feature",
  "properties": {
    "addr:full":"4181 Island View Rd Rhinelander WI 54501",
    "addr:housenumber":"4181",
    "addr:postcode":"54501",
    "addr:street":"Island View Rd",
    "iso:country":"US",
    "sg:address":"4181 Island View Rd",
    "sg:city":"Rhinelander",
    "sg:classifiers":[
        {
            "category":"Wholesale",
            "subcategory":"Construction Materials",
            "type":"Manufacturing & Wholesale Goods"
        }
    ],
    "sg:phone":"+1 715 362 3555",
    "sg:postcode":"54501",
    "sg:province":"WI",
    "wof:name":"Energycraft Systems Inc",
    "wof:placetype":"venue"
},
  "geometry": {"coordinates":[-89.333755,45.607634],"type":"Point"}
}