{
  "type": "Feature",
  "properties": {
    "iso:country":"US",
    "sg:address":"1441 Co Rd V",
    "sg:city":"Campbellsport",
    "sg:classifiers":[
        {
            "category":"Personal",
            "subcategory":"Beauty Salon",
            "type":"Services"
        }
    ],
    "sg:phone":"+1 920 533 4922",
    "sg:postcode":"53010",
    "sg:province":"WI",
    "wof:name":"Charles' Hair Styling Salon",
    "wof:placetype":"venue"
},
  "geometry": {"coordinates":[-88.282141,43.592388],"type":"Point"}
}