{
  "type": "Feature",
  "properties": {
    "iso:country":"US",
    "sg:address":"2625 Henrietta St",
    "sg:city":"Stevens Point",
    "sg:classifiers":[
        {
            "category":"Home & Garden",
            "subcategory":"Home Furnishings",
            "type":"Retail Goods"
        }
    ],
    "sg:phone":"+1 715 342 3700",
    "sg:postcode":"54481",
    "sg:province":"WI",
    "sg:tags":[
        "pottery"
    ],
    "wof:name":"Pointe Pottery",
    "wof:placetype":"venue"
},
  "geometry": {"coordinates":[-89.573058,44.510932],"type":"Point"}
}