{
  "type": "Feature",
  "properties": {
    "iso:country":"US",
    "sg:address":"188 Amory St",
    "sg:city":"Fond Du Lac",
    "sg:classifiers":[
        {
            "category":"Building & Trades",
            "subcategory":"Construction",
            "type":"Services"
        }
    ],
    "sg:phone":"+1 920 803 8159",
    "sg:postcode":"54935",
    "sg:province":"WI",
    "sg:tags":[
        "roofing",
        "residential",
        "frame",
        "general",
        "rough",
        "contractor"
    ],
    "wof:name":"Advantage Construction Inc",
    "wof:placetype":"venue"
},
  "geometry": {"coordinates":[-88.443569,43.783741],"type":"Point"}
}