{
  "type": "Feature",
  "properties": {
    "iso:country":"US",
    "sg:address":"727 S 36th St",
    "sg:city":"Milwaukee",
    "sg:classifiers":[
        {
            "category":"Banks & Credit Unions",
            "subcategory":"Investment Brokerage",
            "type":"Services"
        }
    ],
    "sg:phone":"+1 414 672 3877",
    "sg:postcode":"53215",
    "sg:province":"WI",
    "sg:tags":[
        "advisory"
    ],
    "wof:name":"RB Financial",
    "wof:placetype":"venue"
},
  "geometry": {"coordinates":[-87.958967,43.021806],"type":"Point"}
}