{
  "type": "Feature",
  "properties": {
    "iso:country":"US",
    "sg:address":"85 N Pioneer Rd",
    "sg:city":"Fond Du Lac",
    "sg:classifiers":[
        {
            "category":"Professional",
            "subcategory":"Printing & Photocopies",
            "type":"Services"
        },
        {
            "category":"Manufacturing",
            "subcategory":"Printing",
            "type":"Manufacturing & Wholesale Goods"
        }
    ],
    "sg:phone":"+1 920 923 0800",
    "sg:postcode":"54935",
    "sg:province":"WI",
    "sg:tags":[
        "lithographic",
        "commercial",
        "duplicating",
        "copying"
    ],
    "wof:name":"Minuteman Press",
    "wof:placetype":"venue"
},
  "geometry": {"coordinates":[-88.48188500000001,43.779102],"type":"Point"}
}