{
  "type": "Feature",
  "properties": {
    "iso:country":"US",
    "sg:address":"125 Plain St",
    "sg:city":"Sharon",
    "sg:classifiers":[
        {
            "category":"Government",
            "subcategory":"Office",
            "type":"Public Place"
        }
    ],
    "sg:phone":"+1 262 736 4888",
    "sg:postcode":"53585",
    "sg:province":"WI",
    "sg:tags":[
        "village"
    ],
    "wof:name":"Sharon Village Hall",
    "wof:placetype":"venue"
},
  "geometry": {"coordinates":[-88.72904200000001,42.502545],"type":"Point"}
}