{
  "type": "Feature",
  "properties": {
    "iso:country":"US",
    "sg:address":"1689 N Franklin Pl",
    "sg:city":"Milwaukee",
    "sg:classifiers":[
        {
            "category":"Bars & Pubs",
            "type":"Food & Drink"
        }
    ],
    "sg:phone":"+1 414 278 7897",
    "sg:postcode":"53202",
    "sg:province":"WI",
    "sg:tags":[
        "drinking"
    ],
    "wof:name":"Franklin Place",
    "wof:placetype":"venue"
},
  "geometry": {"coordinates":[-87.89696499999999,43.050756],"type":"Point"}
}