{
  "type": "Feature",
  "properties": {
    "iso:country":"US",
    "sg:address":"2545 N Mayfair Rd",
    "sg:city":"Milwaukee",
    "sg:classifiers":[
        {
            "category":"Shopping",
            "subcategory":"Department Store",
            "type":"Retail Goods"
        }
    ],
    "sg:phone":"+1 414 774 7250",
    "sg:postcode":"53226",
    "sg:province":"WI",
    "sg:tags":[
        "shop"
    ],
    "sg:website":"www.pier1.com",
    "wof:name":"Pier 1 Imports",
    "wof:placetype":"venue"
},
  "geometry": {"coordinates":[-88.047911,43.074745],"type":"Point"}
}