{
  "type": "Feature",
  "properties": {
    "iso:country":"US",
    "sg:address":"608 Water St",
    "sg:city":"Prairie Du Sac",
    "sg:classifiers":[
        {
            "category":"Professional",
            "subcategory":"Engineering",
            "type":"Services"
        }
    ],
    "sg:phone":"+1 608 643 4355",
    "sg:postcode":"53578",
    "sg:province":"WI",
    "sg:website":"www.bunchengineering.com",
    "wof:name":"Bunch Engineering",
    "wof:placetype":"venue"
},
  "geometry": {"coordinates":[-89.718532,43.287706],"type":"Point"}
}