{
  "type": "Feature",
  "properties": {
    "iso:country":"US",
    "sg:address":"1412 Main St",
    "sg:city":"Luxemburg",
    "sg:classifiers":[
        {
            "category":"Organizations",
            "subcategory":"Religious Organization",
            "type":"Services"
        }
    ],
    "sg:phone":"+1 920 845 2056",
    "sg:postcode":"54217",
    "sg:province":"WI",
    "wof:name":"Immaculate Conception",
    "wof:placetype":"venue"
},
  "geometry": {"coordinates":[-87.70371,44.532322],"type":"Point"}
}