{
  "type": "Feature",
  "properties": {
    "iso:country":"US",
    "sg:address":"3189 Co Rd H",
    "sg:city":"Elk Mound",
    "sg:classifiers":[
        {
            "category":"Farming",
            "subcategory":"Farm",
            "type":"Manufacturing & Wholesale Goods"
        }
    ],
    "sg:phone":"+1 715 874 6566",
    "sg:postcode":"54739",
    "sg:province":"WI",
    "wof:name":"L G Farms",
    "wof:placetype":"venue"
},
  "geometry": {"coordinates":[-91.690663,44.789015],"type":"Point"}
}