{
  "type": "Feature",
  "properties": {
    "iso:country":"US",
    "sg:address":"1010 Maritime Dr",
    "sg:city":"Manitowoc",
    "sg:classifiers":[
        {
            "category":"Health Services",
            "subcategory":"Doctor",
            "type":"Services"
        }
    ],
    "sg:phone":"+1 920 684 3350",
    "sg:postcode":"54220",
    "sg:province":"WI",
    "sg:tags":[
        "dentist"
    ],
    "wof:name":"Associated Orthodontists",
    "wof:placetype":"venue"
},
  "geometry": {"coordinates":[-87.646237,44.105529],"type":"Point"}
}