{
  "type": "Feature",
  "properties": {
    "addr:full":"1400 E Fox Ln Milwaukee WI 53217",
    "addr:housenumber":"1400",
    "addr:postcode":"53217",
    "addr:street":"E Fox Ln",
    "iso:country":"US",
    "sg:address":"1400 E Fox Ln",
    "sg:city":"Milwaukee",
    "sg:classifiers":[
        {
            "category":"Real Estate",
            "subcategory":"Real Estate Agent",
            "type":"Services"
        }
    ],
    "sg:phone":"+1 414 352 5200",
    "sg:postcode":"53217",
    "sg:province":"WI",
    "wof:name":"Castle Realty Associates Inc",
    "wof:placetype":"venue"
},
  "geometry": {"coordinates":[-87.89540599999999,43.164908],"type":"Point"}
}