{
  "type": "Feature",
  "properties": {
    "iso:country":"US",
    "sg:address":"22993 Sand Rd",
    "sg:city":"Shell Lake",
    "sg:classifiers":[
        {
            "category":"Farming",
            "subcategory":"Livestock Farm",
            "type":"Manufacturing & Wholesale Goods"
        }
    ],
    "sg:phone":"+1 715 468 2956",
    "sg:postcode":"54871",
    "sg:province":"WI",
    "sg:tags":[
        "beef",
        "feedlot",
        "cattle"
    ],
    "wof:name":"Tim Delawyer",
    "wof:placetype":"venue"
},
  "geometry": {"coordinates":[-92.154267,45.746626],"type":"Point"}
}