{
  "type": "Feature",
  "properties": {
    "iso:country":"US",
    "sg:address":"108 Hotel St",
    "sg:city":"Brooklyn",
    "sg:classifiers":[
        {
            "category":"Restaurant",
            "type":"Food & Drink"
        }
    ],
    "sg:phone":"+1 608 455 9221",
    "sg:postcode":"53521",
    "sg:province":"WI",
    "wof:name":"Kounty Korners",
    "wof:placetype":"venue"
},
  "geometry": {"coordinates":[-89.364864,42.853248],"type":"Point"}
}