{
  "type": "Feature",
  "properties": {
    "iso:country":"US",
    "sg:address":"27539 Northview Rd",
    "sg:city":"Waukesha",
    "sg:classifiers":[
        {
            "category":"Restaurant",
            "type":"Food & Drink"
        }
    ],
    "sg:phone":"+1 262 549 5783",
    "sg:postcode":"53188",
    "sg:province":"WI",
    "sg:tags":[
        "eating"
    ],
    "wof:name":"Its A Beautiful Day Cafe LLC",
    "wof:placetype":"venue"
},
  "geometry": {"coordinates":[-88.299628,43.039122],"type":"Point"}
}