{
  "type": "Feature",
  "properties": {
    "addr:full":"42 Springbrook Circle Dr Appleton WI 54914",
    "addr:housenumber":"42",
    "addr:postcode":"54914",
    "addr:street":"Springbrook Circle Dr",
    "iso:country":"US",
    "sg:address":"42 Springbrook Circle Dr",
    "sg:city":"Appleton",
    "sg:classifiers":[
        {
            "category":"Utilities",
            "subcategory":"Mobile Phone",
            "type":"Services"
        }
    ],
    "sg:phone":"+1 920 991 9963",
    "sg:postcode":"54914",
    "sg:province":"WI",
    "sg:tags":[
        "communication",
        "radiotelephone"
    ],
    "wof:name":"Extreme Wireless Inc",
    "wof:placetype":"venue"
},
  "geometry": {"coordinates":[-88.470716,44.256732],"type":"Point"}
}