{
  "type": "Feature",
  "properties": {
    "iso:country":"US",
    "sg:address":"2109 Fairfax St",
    "sg:city":"Eau Claire",
    "sg:classifiers":[
        {
            "category":"Home & Garden",
            "subcategory":"Furniture",
            "type":"Retail Goods"
        }
    ],
    "sg:phone":"+1 715 839 0466",
    "sg:postcode":"54701",
    "sg:province":"WI",
    "sg:tags":[
        "bed"
    ],
    "wof:name":"P M Sleep Ctr",
    "wof:placetype":"venue"
},
  "geometry": {"coordinates":[-91.46827399999999,44.79813],"type":"Point"}
}