{
  "type": "Feature",
  "properties": {
    "iso:country":"US",
    "sg:address":"13674 Co Rd M",
    "sg:city":"Suring",
    "sg:classifiers":[
        {
            "category":"Farming",
            "subcategory":"Dairy Farm",
            "type":"Manufacturing & Wholesale Goods"
        }
    ],
    "sg:phone":"+1 920 842 2479",
    "sg:postcode":"54174",
    "sg:province":"WI",
    "wof:name":"Dads Farms Inc",
    "wof:placetype":"venue"
},
  "geometry": {"coordinates":[-88.445618,44.993517],"type":"Point"}
}