{
  "type": "Feature",
  "properties": {
    "iso:country":"US",
    "sg:address":"5116 W Spencer St",
    "sg:city":"Appleton",
    "sg:classifiers":[
        {
            "category":"Building & Trades",
            "subcategory":"Construction",
            "type":"Services"
        }
    ],
    "sg:phone":"+1 920 993 9880",
    "sg:postcode":"54914",
    "sg:province":"WI",
    "sg:tags":[
        "home",
        "improvement"
    ],
    "wof:name":"North Valley Construction",
    "wof:placetype":"venue"
},
  "geometry": {"coordinates":[-88.48675299999999,44.258469],"type":"Point"}
}