{
  "type": "Feature",
  "properties": {
    "addr:full":"5902 Raymond Rd Madison WI 53711",
    "addr:housenumber":"5902",
    "addr:postcode":"53711",
    "addr:street":"Raymond Rd",
    "iso:country":"US",
    "sg:address":"5902 Raymond Rd",
    "sg:city":"Madison",
    "sg:classifiers":[
        {
            "category":"Insurance",
            "subcategory":"Insurance Agent",
            "type":"Services"
        }
    ],
    "sg:phone":"+1 608 274 0333",
    "sg:postcode":"53711",
    "sg:province":"WI",
    "wof:name":"Kapinus Ray Insurance",
    "wof:placetype":"venue"
},
  "geometry": {"coordinates":[-89.483492,43.031993],"type":"Point"}
}