{
  "type": "Feature",
  "properties": {
    "iso:country":"US",
    "sg:address":"1359 Aebischer Rd",
    "sg:city":"Chilton",
    "sg:classifiers":[
        {
            "category":"Building & Trades",
            "subcategory":"Landscaping Services",
            "type":"Services"
        }
    ],
    "sg:phone":"+1 920 849 2328",
    "sg:postcode":"53014",
    "sg:province":"WI",
    "sg:tags":[
        "tree"
    ],
    "wof:name":"Casey's Tree Svc",
    "wof:placetype":"venue"
},
  "geometry": {"coordinates":[-88.103277,44.044029],"type":"Point"}
}