{
  "type": "Feature",
  "properties": {
    "iso:country":"US",
    "sg:address":"2332 N 51st St",
    "sg:city":"Milwaukee",
    "sg:classifiers":[
        {
            "category":"Social Services",
            "subcategory":"Child Care",
            "type":"Services"
        }
    ],
    "sg:phone":"+1 414 444 4011",
    "sg:postcode":"53210",
    "sg:province":"WI",
    "wof:name":"Teetee's Daycare",
    "wof:placetype":"venue"
},
  "geometry": {"coordinates":[-87.97747099999999,43.061868],"type":"Point"}
}