{
  "type": "Feature",
  "properties": {
    "iso:country":"US",
    "sg:address":"7811 W Palmetto Ave",
    "sg:city":"Milwaukee",
    "sg:classifiers":[
        {
            "category":"Building & Trades",
            "subcategory":"Pest Control",
            "type":"Services"
        }
    ],
    "sg:phone":"+1 414 393 9200",
    "sg:postcode":"53218",
    "sg:province":"WI",
    "wof:name":"Get Rid Pest Control LLC",
    "wof:placetype":"venue"
},
  "geometry": {"coordinates":[-88.011138,43.106413],"type":"Point"}
}