{
  "type": "Feature",
  "properties": {
    "iso:country":"US",
    "sg:address":"1830 W Mason St",
    "sg:city":"Green Bay",
    "sg:classifiers":[
        {
            "category":"Banks & Credit Unions",
            "subcategory":"Bank",
            "type":"Services"
        }
    ],
    "sg:phone":"+1 920 497 7661",
    "sg:postcode":"54303",
    "sg:province":"WI",
    "sg:tags":[
        "loan",
        "real estate"
    ],
    "sg:website":"www.greenbaymortgages.com",
    "wof:name":"Five Star Mortgage Svc",
    "wof:placetype":"venue"
},
  "geometry": {"coordinates":[-88.077454,44.524386],"type":"Point"}
}