{
  "type": "Feature",
  "properties": {
    "iso:country":"US",
    "sg:address":"5608 Castle Ct",
    "sg:city":"Racine",
    "sg:classifiers":[
        {
            "category":"Organizations",
            "subcategory":"Religious Organization",
            "type":"Services"
        }
    ],
    "sg:phone":"+1 262 619 1797",
    "sg:postcode":"53406",
    "sg:province":"WI",
    "sg:tags":[
        "church"
    ],
    "wof:name":"Church Of Jesus Christ Of Lds",
    "wof:placetype":"venue"
},
  "geometry": {"coordinates":[-87.847683,42.708262],"type":"Point"}
}