{
  "type": "Feature",
  "properties": {
    "iso:country":"US",
    "sg:address":"2838 Stevens St",
    "sg:city":"Madison",
    "sg:classifiers":[
        {
            "category":"Professional",
            "subcategory":"Computer Services",
            "type":"Services"
        }
    ],
    "sg:phone":"+1 608 238 4833",
    "sg:postcode":"53705",
    "sg:province":"WI",
    "sg:tags":[
        "programing",
        "custom"
    ],
    "wof:name":"Jess Anderson Computing C",
    "wof:placetype":"venue"
},
  "geometry": {"coordinates":[-89.43829100000001,43.072609],"type":"Point"}
}