{
  "type": "Feature",
  "properties": {
    "iso:country":"US",
    "sg:address":"1931 Otter Ln",
    "sg:city":"Eagle River",
    "sg:classifiers":[
        {
            "category":"Travel",
            "subcategory":"Hotels & Motels",
            "type":"Entertainment"
        }
    ],
    "sg:phone":"+1 715 479 4090",
    "sg:postcode":"54521",
    "sg:province":"WI",
    "sg:tags":[
        "resort"
    ],
    "wof:name":"Otter Cove Resort",
    "wof:placetype":"venue"
},
  "geometry": {"coordinates":[-89.21775,45.945852],"type":"Point"}
}