{
  "type": "Feature",
  "properties": {
    "iso:country":"US",
    "sg:address":"1918 Emery St",
    "sg:city":"Eau Claire",
    "sg:classifiers":[
        {
            "category":"Building & Trades",
            "subcategory":"Construction",
            "type":"Services"
        }
    ],
    "sg:phone":"+1 715 834 9978",
    "sg:postcode":"54701",
    "sg:province":"WI",
    "sg:tags":[
        "contractor"
    ],
    "wof:name":"Envirosafe LLC",
    "wof:placetype":"venue"
},
  "geometry": {"coordinates":[-91.473647,44.810998],"type":"Point"}
}