{
  "type": "Feature",
  "properties": {
    "iso:country":"US",
    "sg:address":"2025 E Norse Ave",
    "sg:city":"Cudahy",
    "sg:classifiers":[
        {
            "category":"Manufacturing",
            "subcategory":"Chemicals & Compounds",
            "type":"Manufacturing & Wholesale Goods"
        }
    ],
    "sg:phone":"+1 414 744 6320",
    "sg:postcode":"53110",
    "sg:province":"WI",
    "sg:tags":[
        "mfg",
        "plastic"
    ],
    "wof:name":"Solus Indus Innovations LLC",
    "wof:placetype":"venue"
},
  "geometry": {"coordinates":[-87.883938,42.936527],"type":"Point"}
}