{
  "type": "Feature",
  "properties": {
    "addr:full":"539 N Eau Claire St Mondovi WI 54755",
    "addr:housenumber":"539",
    "addr:postcode":"54755",
    "addr:street":"N Eau Claire St",
    "iso:country":"US",
    "sg:address":"539 N Eau Claire St",
    "sg:city":"Mondovi",
    "sg:classifiers":[
        {
            "category":"Social Services",
            "subcategory":"Adult Care",
            "type":"Services"
        }
    ],
    "sg:phone":"+1 715 926 5818",
    "sg:postcode":"54755",
    "sg:province":"WI",
    "sg:tags":[
        "home",
        "group"
    ],
    "wof:name":"Garlick's Community Based Res",
    "wof:placetype":"venue"
},
  "geometry": {"coordinates":[-91.670767,44.571572],"type":"Point"}
}