{
  "type": "Feature",
  "properties": {
    "iso:country":"US",
    "sg:address":"408 N Jefferson St",
    "sg:city":"Waterford",
    "sg:classifiers":[
        {
            "category":"Education",
            "subcategory":"Special Training",
            "type":"Public Place"
        }
    ],
    "sg:phone":"+1 262 534 2661",
    "sg:postcode":"53185",
    "sg:province":"WI",
    "sg:tags":[
        "school",
        "music"
    ],
    "wof:name":"Wmc Enterprises",
    "wof:placetype":"venue"
},
  "geometry": {"coordinates":[-88.214906,42.767951],"type":"Point"}
}