{
  "type": "Feature",
  "properties": {
    "iso:country":"US",
    "sg:address":"1039 W Mason St",
    "sg:city":"Green Bay",
    "sg:classifiers":[
        {
            "category":"Social Services",
            "type":"Services"
        }
    ],
    "sg:phone":"+1 920 884 1083",
    "sg:postcode":"54303",
    "sg:province":"WI",
    "wof:name":"Buechler Therapy Foundation",
    "wof:placetype":"venue"
},
  "geometry": {"coordinates":[-88.041235,44.515588],"type":"Point"}
}