{
  "type": "Feature",
  "properties": {
    "addr:full":"10411 Hickory Hills Rd Brillion WI 54110",
    "addr:housenumber":"10411",
    "addr:postcode":"54110",
    "addr:street":"Hickory Hills Rd",
    "iso:country":"US",
    "sg:address":"10411 Hickory Hills Rd",
    "sg:city":"Brillion",
    "sg:classifiers":[
        {
            "category":"Farming",
            "subcategory":"Livestock Farm",
            "type":"Manufacturing & Wholesale Goods"
        }
    ],
    "sg:phone":"+1 920 864 2114",
    "sg:postcode":"54110",
    "sg:province":"WI",
    "sg:tags":[
        "beef",
        "feedlot",
        "cattle"
    ],
    "wof:name":"Peter Hoyer",
    "wof:placetype":"venue"
},
  "geometry": {"coordinates":[-88.004594,44.220796],"type":"Point"}
}