{
  "type": "Feature",
  "properties": {
    "iso:country":"US",
    "sg:address":"3533 E Ramsey Ave",
    "sg:city":"Cudahy",
    "sg:classifiers":[
        {
            "category":"Shopping",
            "subcategory":"Pharmacy",
            "type":"Retail Goods"
        }
    ],
    "sg:phone":"+1 414 769 6150",
    "sg:postcode":"53110",
    "sg:province":"WI",
    "wof:name":"Cudahy Clinic Serv-U Pharmacy",
    "wof:placetype":"venue"
},
  "geometry": {"coordinates":[-87.86041299999999,42.937272],"type":"Point"}
}