{
  "type": "Feature",
  "properties": {
    "addr:full":"946 Streblow St Onalaska WI 54650",
    "addr:housenumber":"946",
    "addr:postcode":"54650",
    "addr:street":"Streblow St",
    "iso:country":"US",
    "sg:address":"946 Streblow St",
    "sg:city":"Onalaska",
    "sg:classifiers":[
        {
            "category":"Professional",
            "subcategory":"Business Services",
            "type":"Services"
        }
    ],
    "sg:phone":"+1 608 783 3752",
    "sg:postcode":"54650",
    "sg:province":"WI",
    "wof:name":"Randall Family Partnership",
    "wof:placetype":"venue"
},
  "geometry": {"coordinates":[-91.22689699999999,43.907102],"type":"Point"}
}