{
  "type": "Feature",
  "properties": {
    "iso:country":"US",
    "sg:address":"1317 Lombardi Access Rd",
    "sg:city":"Green Bay",
    "sg:classifiers":[
        {
            "category":"Insurance",
            "subcategory":"Insurance Agent",
            "type":"Services"
        }
    ],
    "sg:phone":"+1 920 499 3100",
    "sg:postcode":"54304",
    "sg:province":"WI",
    "wof:name":"Prudential",
    "wof:placetype":"venue"
},
  "geometry": {"coordinates":[-88.074983,44.507043],"type":"Point"}
}