{
  "type": "Feature",
  "properties": {
    "iso:country":"US",
    "sg:address":"1404 Fairplay Rd",
    "sg:city":"Cuba City",
    "sg:classifiers":[
        {
            "category":"Farming",
            "subcategory":"Farm",
            "type":"Manufacturing & Wholesale Goods"
        }
    ],
    "sg:phone":"+1 608 748 4575",
    "sg:postcode":"53807",
    "sg:province":"WI",
    "sg:tags":[
        "crop",
        "general"
    ],
    "wof:name":"Thomas Fleege",
    "wof:placetype":"venue"
},
  "geometry": {"coordinates":[-90.55376699999999,42.556794],"type":"Point"}
}