{
  "type": "Feature",
  "properties": {
    "iso:country":"US",
    "sg:address":"4221 W Hilands Ct",
    "sg:city":"Mequon",
    "sg:classifiers":[
        {
            "category":"Wholesale",
            "subcategory":"Electrical",
            "type":"Manufacturing & Wholesale Goods"
        }
    ],
    "sg:phone":"+1 262 242 4095",
    "sg:postcode":"53092",
    "sg:province":"WI",
    "sg:tags":[
        "electric",
        "motor"
    ],
    "wof:name":"Leeson Electric District Sales",
    "wof:placetype":"venue"
},
  "geometry": {"coordinates":[-87.961209,43.213871],"type":"Point"}
}