{
  "type": "Feature",
  "properties": {
    "iso:country":"US",
    "sg:address":"525 N 6th St",
    "sg:city":"Sheboygan",
    "sg:classifiers":[
        {
            "category":"Government",
            "subcategory":"Police Station",
            "type":"Public Place"
        }
    ],
    "sg:phone":"+1 920 459 3111",
    "sg:postcode":"53081",
    "sg:province":"WI",
    "sg:tags":[
        "protection"
    ],
    "wof:name":"Sheriffs Department",
    "wof:placetype":"venue"
},
  "geometry": {"coordinates":[-87.709533,43.7506],"type":"Point"}
}