{
  "type": "Feature",
  "properties": {
    "iso:country":"US",
    "sg:address":"10110 S 54th St",
    "sg:city":"Franklin",
    "sg:classifiers":[
        {
            "category":"Wholesale",
            "subcategory":"Machinery & Supplies",
            "type":"Manufacturing & Wholesale Goods"
        },
        {
            "category":"Retail",
            "subcategory":"Repair Shop",
            "type":"Services"
        }
    ],
    "sg:phone":"+1 414 423 5500",
    "sg:postcode":"53132",
    "sg:province":"WI",
    "sg:tags":[
        "machine",
        "tool",
        "parts"
    ],
    "sg:website":"www.precisionmt.com",
    "wof:name":"Precision Automation Inc",
    "wof:placetype":"venue"
},
  "geometry": {"coordinates":[-87.98531,42.862104],"type":"Point"}
}