{
  "type": "Feature",
  "properties": {
    "addr:full":"3736 Oak Acre Dr Fond Du Lac WI 54935",
    "addr:housenumber":"3736",
    "addr:postcode":"54935",
    "addr:street":"Oak Acre Dr",
    "iso:country":"US",
    "sg:address":"3736 Oak Acre Dr",
    "sg:city":"Fond Du Lac",
    "sg:classifiers":[
        {
            "category":"Professional",
            "subcategory":"Business Services",
            "type":"Services"
        }
    ],
    "sg:phone":"+1 920 929 0491",
    "sg:postcode":"54935",
    "sg:province":"WI",
    "wof:name":"Orth Enterprises Inc",
    "wof:placetype":"venue"
},
  "geometry": {"coordinates":[-88.34286400000001,43.740668],"type":"Point"}
}