{
  "type": "Feature",
  "properties": {
    "iso:country":"US",
    "sg:address":"22234 86th Pl",
    "sg:city":"Salem",
    "sg:classifiers":[
        {
            "category":"Shopping",
            "subcategory":"Hobbies, Toys, & Games",
            "type":"Retail Goods"
        }
    ],
    "sg:phone":"+1 262 843 8004",
    "sg:postcode":"53168",
    "sg:province":"WI",
    "wof:name":"Creative Pleasures",
    "wof:placetype":"venue"
},
  "geometry": {"coordinates":[-88.07863500000001,42.550687],"type":"Point"}
}