{
  "type": "Feature",
  "properties": {
    "iso:country":"US",
    "sg:address":"701 US Hwy 12",
    "sg:city":"Wisconsin Dells",
    "sg:classifiers":[
        {
            "category":"Organizations",
            "subcategory":"Religious Organization",
            "type":"Services"
        }
    ],
    "sg:phone":"+1 608 254 2393",
    "sg:postcode":"53965",
    "sg:province":"WI",
    "sg:tags":[
        "church"
    ],
    "wof:name":"Community Bible Church",
    "wof:placetype":"venue"
},
  "geometry": {"coordinates":[-89.793639,43.599292],"type":"Point"}
}