{
  "type": "Feature",
  "properties": {
    "iso:country":"US",
    "sg:address":"212 E Davis St",
    "sg:city":"Beaver Dam",
    "sg:classifiers":[
        {
            "category":"Home & Garden",
            "subcategory":"Carpets & Floor Coverings",
            "type":"Retail Goods"
        }
    ],
    "sg:phone":"+1 920 356 1093",
    "sg:postcode":"53916",
    "sg:province":"WI",
    "wof:name":"Specialty Floors & More",
    "wof:placetype":"venue"
},
  "geometry": {"coordinates":[-88.829187,43.448984],"type":"Point"}
}