{
  "type": "Feature",
  "properties": {
    "iso:country":"US",
    "sg:address":"4469 State Hwy 55",
    "sg:city":"Chilton",
    "sg:phone":"+1 920 439 1746",
    "sg:postcode":"53014",
    "sg:province":"WI",
    "sg:tags":[
        "farm",
        "soybean"
    ],
    "wof:name":"Beantime Soyfood Company",
    "wof:placetype":"venue"
},
  "geometry": {"coordinates":[-88.299108,44.047863],"type":"Point"}
}