{
  "type": "Feature",
  "properties": {
    "iso:country":"US",
    "sg:address":"5120 Byrd Ave",
    "sg:city":"Racine",
    "sg:classifiers":[
        {
            "category":"Education",
            "subcategory":"School",
            "type":"Public Place"
        }
    ],
    "sg:phone":"+1 262 664 8250",
    "sg:postcode":"53406",
    "sg:province":"WI",
    "sg:tags":[
        "elementary"
    ],
    "wof:name":"Giese Elementary School",
    "wof:placetype":"venue"
},
  "geometry": {"coordinates":[-87.84234600000001,42.709578],"type":"Point"}
}