{
  "type": "Feature",
  "properties": {
    "iso:country":"US",
    "sg:address":"11010 W Welsh Rd",
    "sg:city":"Janesville",
    "sg:classifiers":[
        {
            "category":"Farming",
            "subcategory":"Farm",
            "type":"Manufacturing & Wholesale Goods"
        }
    ],
    "sg:phone":"+1 608 876 6186",
    "sg:postcode":"53548",
    "sg:province":"WI",
    "sg:tags":[
        "crop",
        "general"
    ],
    "wof:name":"Philip Johnson",
    "wof:placetype":"venue"
},
  "geometry": {"coordinates":[-89.209234,42.650585],"type":"Point"}
}