{
  "type": "Feature",
  "properties": {
    "iso:country":"US",
    "sg:address":"613 N Division St",
    "sg:city":"Appleton",
    "sg:classifiers":[
        {
            "category":"Social Services",
            "subcategory":"Adult Care",
            "type":"Services"
        }
    ],
    "sg:phone":"+1 920 739 5337",
    "sg:postcode":"54911",
    "sg:province":"WI",
    "sg:tags":[
        "home",
        "residential"
    ],
    "wof:name":"Villa Hope Halfway House",
    "wof:placetype":"venue"
},
  "geometry": {"coordinates":[-88.410783,44.26668],"type":"Point"}
}