{
  "type": "Feature",
  "properties": {
    "iso:country":"US",
    "sg:address":"7611 Voss Pkwy",
    "sg:city":"Middleton",
    "sg:classifiers":[
        {
            "category":"Professional",
            "subcategory":"Management & Consulting",
            "type":"Services"
        }
    ],
    "sg:phone":"+1 608 836 7474",
    "sg:postcode":"53562",
    "sg:province":"WI",
    "wof:name":"Feldman Shel",
    "wof:placetype":"venue"
},
  "geometry": {"coordinates":[-89.51431100000001,43.088622],"type":"Point"}
}