{
  "type": "Feature",
  "properties": {
    "iso:country":"US",
    "sg:address":"1414 N Taylor Dr",
    "sg:city":"Sheboygan",
    "sg:classifiers":[
        {
            "category":"Health Services",
            "subcategory":"Doctor",
            "type":"Services"
        }
    ],
    "sg:phone":"+1 920 458 9800",
    "sg:postcode":"53081",
    "sg:province":"WI",
    "sg:tags":[
        "medical"
    ],
    "wof:name":"Coulis Louie MD Facc",
    "wof:placetype":"venue"
},
  "geometry": {"coordinates":[-87.749719,43.760843],"type":"Point"}
}