{
  "type": "Feature",
  "properties": {
    "iso:country":"US",
    "sg:address":"434 N Star Rd",
    "sg:city":"Holmen",
    "sg:classifiers":[
        {
            "category":"Health Services",
            "subcategory":"Chiropractor",
            "type":"Services"
        }
    ],
    "sg:phone":"+1 608 526 3343",
    "sg:postcode":"54636",
    "sg:province":"WI",
    "wof:name":"Bronston Orthopedic Chiro",
    "wof:placetype":"venue"
},
  "geometry": {"coordinates":[-91.265404,43.965744],"type":"Point"}
}