{
  "type": "Feature",
  "properties": {
    "iso:country":"US",
    "sg:address":"1621 Coulee Rd",
    "sg:city":"Hudson",
    "sg:classifiers":[
        {
            "category":"Autos & Motor Vehicles",
            "subcategory":"Automobile Sales",
            "type":"Retail Goods"
        }
    ],
    "sg:phone":"+1 715 386 5155",
    "sg:postcode":"54016",
    "sg:province":"WI",
    "sg:tags":[
        "car",
        "dealer"
    ],
    "wof:name":"Denny Hecker's Hudson Pontiac",
    "wof:placetype":"venue"
},
  "geometry": {"coordinates":[-92.73521599999999,44.963416],"type":"Point"}
}