{
  "type": "Feature",
  "properties": {
    "iso:country":"US",
    "sg:address":"1303 Villa St",
    "sg:city":"Racine",
    "sg:classifiers":[
        {
            "category":"Professional",
            "subcategory":"Computer Services",
            "type":"Services"
        }
    ],
    "sg:phone":"+1 262 634 3667",
    "sg:postcode":"53403",
    "sg:province":"WI",
    "sg:tags":[
        "consultant",
        "designer",
        "related"
    ],
    "wof:name":"Open Door Computing S Corp",
    "wof:placetype":"venue"
},
  "geometry": {"coordinates":[-87.786961,42.715558],"type":"Point"}
}