{
  "type": "Feature",
  "properties": {
    "iso:country":"US",
    "sg:address":"8527 16th Ave",
    "sg:city":"Kenosha",
    "sg:classifiers":[
        {
            "category":"Banks & Credit Unions",
            "subcategory":"Investment Brokerage",
            "type":"Services"
        }
    ],
    "sg:phone":"+1 262 942 1291",
    "sg:postcode":"53143",
    "sg:province":"WI",
    "sg:tags":[
        "advisory"
    ],
    "wof:name":"Cims Investment Mgt Aliance",
    "wof:placetype":"venue"
},
  "geometry": {"coordinates":[-87.827256,42.550272],"type":"Point"}
}