{
  "type": "Feature",
  "properties": {
    "iso:country":"US",
    "sg:address":"1120 Buena Vista Dr",
    "sg:city":"Black River Fls",
    "sg:classifiers":[
        {
            "category":"Shopping",
            "type":"Retail Goods"
        }
    ],
    "sg:phone":"+1 715 284 5518",
    "sg:postcode":"54615",
    "sg:province":"WI",
    "sg:tags":[
        "monument"
    ],
    "wof:name":"Falls Monument Svc",
    "wof:placetype":"venue"
},
  "geometry": {"coordinates":[-90.864369,44.285142],"type":"Point"}
}