{
  "type": "Feature",
  "properties": {
    "iso:country":"US",
    "sg:address":"127 Garfield Ave",
    "sg:city":"Waukesha",
    "sg:classifiers":[
        {
            "category":"Shopping",
            "type":"Retail Goods"
        }
    ],
    "sg:phone":"+1 262 542 2825",
    "sg:postcode":"53186",
    "sg:province":"WI",
    "sg:tags":[
        "merchandise"
    ],
    "wof:name":"United States Flag Place",
    "wof:placetype":"venue"
},
  "geometry": {"coordinates":[-88.229474,43.001822],"type":"Point"}
}