{
  "type": "Feature",
  "properties": {
    "iso:country":"US",
    "sg:address":"2043 Schanock Dr",
    "sg:city":"Green Bay",
    "sg:classifiers":[
        {
            "category":"Building & Trades",
            "subcategory":"Construction",
            "type":"Services"
        }
    ],
    "sg:phone":"+1 920 490 0308",
    "sg:postcode":"54303",
    "sg:province":"WI",
    "wof:name":"Construction Specialist",
    "wof:placetype":"venue"
},
  "geometry": {"coordinates":[-88.064517,44.545169],"type":"Point"}
}