{
  "type": "Feature",
  "properties": {
    "iso:country":"US",
    "sg:address":"710 Peace Pipe Ln",
    "sg:city":"Lac Du Flambeau",
    "sg:classifiers":[
        {
            "category":"Shopping",
            "subcategory":"Gifts & Souvenirs",
            "type":"Retail Goods"
        }
    ],
    "sg:phone":"+1 715 588 3130",
    "sg:postcode":"54538",
    "sg:province":"WI",
    "wof:name":"Totem Trading Post",
    "wof:placetype":"venue"
},
  "geometry": {"coordinates":[-89.89857499999999,45.95122],"type":"Point"}
}