{
  "type": "Feature",
  "properties": {
    "addr:full":"301 N Iowa St Dodgeville WI 53533",
    "addr:housenumber":"301",
    "addr:postcode":"53533",
    "addr:street":"N Iowa St",
    "iso:country":"US",
    "sg:address":"301 N Iowa St",
    "sg:city":"Dodgeville",
    "sg:classifiers":[
        {
            "category":"Travel",
            "subcategory":"Travel Agent",
            "type":"Entertainment"
        }
    ],
    "sg:phone":"+1 608 935 2766",
    "sg:postcode":"53533",
    "sg:province":"WI",
    "sg:tags":[
        "agency"
    ],
    "wof:name":"Dodgeville Travel Agency",
    "wof:placetype":"venue"
},
  "geometry": {"coordinates":[-90.130257,42.962536],"type":"Point"}
}