{
  "type": "Feature",
  "properties": {
    "addr:full":"9240 400th Ave Genoa City WI 53128",
    "addr:housenumber":"9240",
    "addr:postcode":"53128",
    "addr:street":"400Th Ave",
    "iso:country":"US",
    "sg:address":"9240 400th Ave",
    "sg:city":"Genoa City",
    "sg:classifiers":[
        {
            "category":"Building & Trades",
            "subcategory":"Landscaping Services",
            "type":"Services"
        }
    ],
    "sg:phone":"+1 262 279 2271",
    "sg:postcode":"53128",
    "sg:province":"WI",
    "sg:tags":[
        "landscape",
        "contractor"
    ],
    "wof:name":"Elverman Landscape",
    "wof:placetype":"venue"
},
  "geometry": {"coordinates":[-88.296173,42.539081],"type":"Point"}
}