{
  "type": "Feature",
  "properties": {
    "iso:country":"US",
    "sg:address":"3211 Franklin St",
    "sg:city":"Wisconsin Rapids",
    "sg:classifiers":[
        {
            "category":"Real Estate",
            "subcategory":"Real Estate Operator",
            "type":"Services"
        }
    ],
    "sg:phone":"+1 715 421 4385",
    "sg:postcode":"54494",
    "sg:province":"WI",
    "sg:tags":[
        "building",
        "apartment"
    ],
    "wof:name":"Timber Trails Apartments",
    "wof:placetype":"venue"
},
  "geometry": {"coordinates":[-89.784959,44.395868],"type":"Point"}
}