{
  "type": "Feature",
  "properties": {
    "addr:full":"3277 Creek View Ln Appleton WI 54915",
    "addr:housenumber":"3277",
    "addr:postcode":"54915",
    "addr:street":"Creek View Ln",
    "iso:country":"US",
    "sg:address":"3277 Creek View Ln",
    "sg:city":"Appleton",
    "sg:classifiers":[
        {
            "category":"Home & Garden",
            "subcategory":"Home Furnishings",
            "type":"Retail Goods"
        }
    ],
    "sg:phone":"+1 920 734 2882",
    "sg:postcode":"54915",
    "sg:province":"WI",
    "sg:tags":[
        "equipment",
        "fireplace"
    ],
    "wof:name":"Darboy Stone & Brick Co",
    "wof:placetype":"venue"
},
  "geometry": {"coordinates":[-88.352521,44.252759],"type":"Point"}
}