{
  "type": "Feature",
  "properties": {
    "iso:country":"US",
    "sg:address":"202 S Main St",
    "sg:city":"Reeseville",
    "sg:classifiers":[
        {
            "category":"Shopping",
            "subcategory":"Pharmacy",
            "type":"Retail Goods"
        }
    ],
    "sg:phone":"+1 920 927 3305",
    "sg:postcode":"53579",
    "sg:province":"WI",
    "wof:name":"Village Pharmacy",
    "wof:placetype":"venue"
},
  "geometry": {"coordinates":[-88.84629,43.303581],"type":"Point"}
}