{
  "type": "Feature",
  "properties": {
    "iso:country":"US",
    "sg:address":"140 Sandridge Trl",
    "sg:city":"Sun Prairie",
    "sg:classifiers":[
        {
            "category":"Insurance",
            "subcategory":"Insurance Agent",
            "type":"Services"
        }
    ],
    "sg:phone":"+1 608 825 4716",
    "sg:postcode":"53590",
    "sg:province":"WI",
    "wof:name":"Tina J Paulus",
    "wof:placetype":"venue"
},
  "geometry": {"coordinates":[-89.21494800000001,43.199333],"type":"Point"}
}