{
  "type": "Feature",
  "properties": {
    "iso:country":"US",
    "sg:address":"15084 State Hwy 121",
    "sg:city":"Hixton",
    "sg:classifiers":[
        {
            "category":"Organizations",
            "subcategory":"Religious Organization",
            "type":"Services"
        }
    ],
    "sg:phone":"+1 715 984 2234",
    "sg:postcode":"54635",
    "sg:province":"WI",
    "sg:tags":[
        "church"
    ],
    "wof:name":"Upper Pigeon Creek Luth Chr",
    "wof:placetype":"venue"
},
  "geometry": {"coordinates":[-91.06853,44.450521],"type":"Point"}
}