{
  "type": "Feature",
  "properties": {
    "iso:country":"US",
    "sg:address":"2363 S 13th St",
    "sg:city":"Milwaukee",
    "sg:classifiers":[
        {
            "category":"Professional",
            "subcategory":"Accounting & Tax Preparation",
            "type":"Services"
        }
    ],
    "sg:phone":"+1 414 384 0093",
    "sg:postcode":"53215",
    "sg:province":"WI",
    "sg:tags":[
        "bookkeeping",
        "billing"
    ],
    "wof:name":"Town & Country",
    "wof:placetype":"venue"
},
  "geometry": {"coordinates":[-87.928496,43.001827],"type":"Point"}
}