{
  "type": "Feature",
  "properties": {
    "iso:country":"US",
    "sg:address":"2312 Sunnybrook Dr",
    "sg:city":"Kewaskum",
    "sg:classifiers":[
        {
            "category":"Building & Trades",
            "subcategory":"Construction",
            "type":"Services"
        }
    ],
    "sg:phone":"+1 262 334 4278",
    "sg:postcode":"53040",
    "sg:province":"WI",
    "sg:tags":[
        "house",
        "commercial"
    ],
    "wof:name":"Wagner David Construction LLC",
    "wof:placetype":"venue"
},
  "geometry": {"coordinates":[-88.152202,43.476735],"type":"Point"}
}