{
  "type": "Feature",
  "properties": {
    "iso:country":"US",
    "sg:address":"1138 Hayes Ave",
    "sg:city":"Racine",
    "sg:classifiers":[
        {
            "category":"Retail",
            "subcategory":"Repair Shop",
            "type":"Services"
        }
    ],
    "sg:phone":"+1 262 634 7656",
    "sg:postcode":"53405",
    "sg:province":"WI",
    "sg:tags":[
        "leather",
        "good"
    ],
    "wof:name":"West Racine Shoe Svc",
    "wof:placetype":"venue"
},
  "geometry": {"coordinates":[-87.818609,42.719292],"type":"Point"}
}