{
  "type": "Feature",
  "properties": {
    "iso:country":"US",
    "sg:address":"5109 Maywood Rd",
    "sg:city":"Monona",
    "sg:classifiers":[
        {
            "category":"Building & Trades",
            "subcategory":"Construction",
            "type":"Services"
        }
    ],
    "sg:phone":"+1 608 222 2243",
    "sg:postcode":"53716",
    "sg:province":"WI",
    "sg:tags":[
        "painter"
    ],
    "wof:name":"Paint Authority",
    "wof:placetype":"venue"
},
  "geometry": {"coordinates":[-89.33721300000001,43.065094],"type":"Point"}
}