{
  "type": "Feature",
  "properties": {
    "iso:country":"US",
    "sg:address":"343 Nichols Rd",
    "sg:city":"Bonduel",
    "sg:classifiers":[
        {
            "category":"Freight",
            "type":"Transportation"
        }
    ],
    "sg:phone":"+1 920 525 3348",
    "sg:postcode":"54107",
    "sg:province":"WI",
    "sg:tags":[
        "operator",
        "local",
        "trucking"
    ],
    "wof:name":"Steve Diemel Trucking",
    "wof:placetype":"venue"
},
  "geometry": {"coordinates":[-88.466736,44.60224],"type":"Point"}
}