{
  "type": "Feature",
  "properties": {
    "iso:country":"US",
    "sg:address":"117 W Front St",
    "sg:city":"Cassville",
    "sg:classifiers":[
        {
            "category":"Travel",
            "subcategory":"Hotels & Motels",
            "type":"Entertainment"
        }
    ],
    "sg:phone":"+1 608 725 5895",
    "sg:postcode":"53806",
    "sg:province":"WI",
    "sg:tags":[
        "breakfast",
        "accommodation",
        "bed"
    ],
    "sg:website":"www.riverviewbb.com",
    "wof:name":"River View Bed & Breakfast",
    "wof:placetype":"venue"
},
  "geometry": {"coordinates":[-90.991547,42.713591],"type":"Point"}
}