{
  "type": "Feature",
  "properties": {
    "iso:country":"US",
    "sg:address":"2741 N 27th St",
    "sg:city":"Milwaukee",
    "sg:classifiers":[
        {
            "category":"Place Of Worship",
            "subcategory":"Church",
            "type":"Public Place"
        },
        {
            "category":"Place Of Worship",
            "type":"Public Place"
        }
    ],
    "sg:phone":"+1 414 264 8040",
    "sg:postcode":"53210",
    "sg:province":"WI",
    "sg:tags":[
        "churches-baptist-general",
        "churches-baptist"
    ],
    "wof:name":"Luke Greater Saint Baptist Church",
    "wof:placetype":"venue"
},
  "geometry": {"coordinates":[-87.947337,43.068667],"type":"Point"}
}