{
  "type": "Feature",
  "properties": {
    "iso:country":"US",
    "sg:address":"24056 State Rd 35",
    "sg:city":"Siren",
    "sg:classifiers":[
        {
            "category":"Building & Trades",
            "subcategory":"Plumbing",
            "type":"Services"
        }
    ],
    "sg:phone":"+1 715 349 5533",
    "sg:postcode":"54872",
    "sg:province":"WI",
    "sg:tags":[
        "plumbing",
        "contractor"
    ],
    "wof:name":"Daniels Plumbing & Heating Inc",
    "wof:placetype":"venue"
},
  "geometry": {"coordinates":[-92.380814,45.786434],"type":"Point"}
}