{
  "type": "Feature",
  "properties": {
    "iso:country":"US",
    "sg:address":"118 Larkspur Ct",
    "sg:city":"Wausau",
    "sg:classifiers":[
        {
            "category":"Freight",
            "type":"Transportation"
        }
    ],
    "sg:phone":"+1 715 241 8394",
    "sg:postcode":"54401",
    "sg:province":"WI",
    "sg:tags":[
        "courier"
    ],
    "wof:name":"Badger Transportation",
    "wof:placetype":"venue"
},
  "geometry": {"coordinates":[-89.63479,44.894916],"type":"Point"}
}