{
  "type": "Feature",
  "properties": {
    "addr:full":"1812 Hall Ave Marinette WI 54143",
    "addr:housenumber":"1812",
    "addr:postcode":"54143",
    "addr:street":"Hall Ave",
    "iso:country":"US",
    "sg:address":"1812 Hall Ave",
    "sg:city":"Marinette",
    "sg:classifiers":[
        {
            "category":"Organizations",
            "subcategory":"Non-profit Organization",
            "type":"Services"
        }
    ],
    "sg:phone":"+1 715 732 6280",
    "sg:postcode":"54143",
    "sg:province":"WI",
    "sg:tags":[
        "human"
    ],
    "wof:name":"Habitat For Humanities Inc",
    "wof:placetype":"venue"
},
  "geometry": {"coordinates":[-87.630994,45.099817],"type":"Point"}
}