{
  "type": "Feature",
  "properties": {
    "iso:country":"US",
    "sg:address":"2020 E Milwaukee St",
    "sg:city":"Janesville",
    "sg:classifiers":[
        {
            "category":"Social Services",
            "type":"Services"
        }
    ],
    "sg:phone":"+1 608 754 0197",
    "sg:postcode":"53545",
    "sg:province":"WI",
    "wof:name":"Mentoring Moms Inc",
    "wof:placetype":"venue"
},
  "geometry": {"coordinates":[-88.998123,42.692134],"type":"Point"}
}