{
  "type": "Feature",
  "properties": {
    "iso:country":"US",
    "sg:address":"2759 S 28th St",
    "sg:city":"Milwaukee",
    "sg:classifiers":[
        {
            "category":"Manufacturing",
            "subcategory":"Tools & Machinery",
            "type":"Manufacturing & Wholesale Goods"
        }
    ],
    "sg:phone":"+1 414 384 9472",
    "sg:postcode":"53215",
    "sg:province":"WI",
    "sg:tags":[
        "piston",
        "carburetor"
    ],
    "wof:name":"Grover Piston Ring Inc",
    "wof:placetype":"venue"
},
  "geometry": {"coordinates":[-87.949479,42.995256],"type":"Point"}
}