{
  "type": "Feature",
  "properties": {
    "iso:country":"US",
    "sg:address":"600 S Park Ave",
    "sg:city":"Neenah",
    "sg:classifiers":[
        {
            "category":"Recreation",
            "type":"Entertainment"
        }
    ],
    "sg:phone":"+1 920 886 6080",
    "sg:postcode":"54956",
    "sg:province":"WI",
    "sg:tags":[
        "pool",
        "swimming"
    ],
    "wof:name":"Neenah Swimming Pool",
    "wof:placetype":"venue"
},
  "geometry": {"coordinates":[-88.447909,44.176781],"type":"Point"}
}