{
  "type": "Feature",
  "properties": {
    "addr:full":"122 S Lincoln St Stetsonville WI 54480",
    "addr:housenumber":"122",
    "addr:postcode":"54480",
    "addr:street":"S Lincoln St",
    "iso:country":"US",
    "sg:address":"122 S Lincoln St",
    "sg:city":"Stetsonville",
    "sg:classifiers":[
        {
            "category":"Organizations",
            "subcategory":"Religious Organization",
            "type":"Services"
        }
    ],
    "sg:phone":"+1 715 678 2204",
    "sg:postcode":"54480",
    "sg:province":"WI",
    "sg:tags":[
        "clergy"
    ],
    "wof:name":"James Babler",
    "wof:placetype":"venue"
},
  "geometry": {"coordinates":[-90.313351,45.076663],"type":"Point"}
}