{
  "type": "Feature",
  "properties": {
    "addr:full":"621 E Blackhawk Ave Prairie Du Chien WI 53821",
    "addr:housenumber":"621",
    "addr:postcode":"53821",
    "addr:street":"E Blackhawk Ave",
    "iso:country":"US",
    "sg:address":"621 E Blackhawk Ave",
    "sg:city":"Prairie Du Chien",
    "sg:classifiers":[
        {
            "category":"Personal",
            "subcategory":"Beauty Salon",
            "type":"Services"
        }
    ],
    "sg:phone":"+1 608 326 2400",
    "sg:postcode":"53821",
    "sg:province":"WI",
    "wof:name":"Red's House Of Hair",
    "wof:placetype":"venue"
},
  "geometry": {"coordinates":[-91.13824099999999,43.052079],"type":"Point"}
}