{
  "type": "Feature",
  "properties": {
    "iso:country":"US",
    "sg:address":"317 8th St",
    "sg:city":"Monroe",
    "sg:classifiers":[
        {
            "category":"Food & Beverages",
            "subcategory":"Groceries & Convenience Stores",
            "type":"Retail Goods"
        }
    ],
    "sg:phone":"+1 608 325 3578",
    "sg:postcode":"53566",
    "sg:province":"WI",
    "wof:name":"Kundert Oil Co",
    "wof:placetype":"venue"
},
  "geometry": {"coordinates":[-89.65549900000001,42.603391],"type":"Point"}
}