{
  "type": "Feature",
  "properties": {
    "iso:country":"US",
    "sg:address":"10932 Co Rd A",
    "sg:city":"Tomahawk",
    "sg:classifiers":[
        {
            "category":"Autos & Motor Vehicles",
            "subcategory":"Automobile Sales",
            "type":"Retail Goods"
        }
    ],
    "sg:phone":"+1 715 453 2626",
    "sg:postcode":"54487",
    "sg:province":"WI",
    "sg:tags":[
        "motorcycle"
    ],
    "wof:name":"North Country Yamaha",
    "wof:placetype":"venue"
},
  "geometry": {"coordinates":[-89.712722,45.524533],"type":"Point"}
}