{
  "type": "Feature",
  "properties": {
    "iso:country":"US",
    "sg:address":"1643 S 31st St",
    "sg:city":"Milwaukee",
    "sg:classifiers":[
        {
            "category":"Social Services",
            "subcategory":"Child Care",
            "type":"Services"
        }
    ],
    "sg:phone":"+1 414 389 1027",
    "sg:postcode":"53215",
    "sg:province":"WI",
    "sg:tags":[
        "day"
    ],
    "wof:name":"Little Hands Day Care",
    "wof:placetype":"venue"
},
  "geometry": {"coordinates":[-87.952804,43.013178],"type":"Point"}
}