{
  "type": "Feature",
  "properties": {
    "iso:country":"US",
    "sg:address":"14187 Co Rd K",
    "sg:city":"Clear Lake",
    "sg:classifiers":[
        {
            "category":"Manufacturing",
            "subcategory":"Metals",
            "type":"Manufacturing & Wholesale Goods"
        }
    ],
    "sg:phone":"+1 715 643 6300",
    "sg:postcode":"54005",
    "sg:province":"WI",
    "sg:tags":[
        "prefab",
        "component",
        "mfg"
    ],
    "wof:name":"Tacoma Company",
    "wof:placetype":"venue"
},
  "geometry": {"coordinates":[-92.096226,45.170022],"type":"Point"}
}