{
  "type": "Feature",
  "properties": {
    "iso:country":"US",
    "sg:address":"10365 Co Rd K",
    "sg:city":"Lancaster",
    "sg:classifiers":[
        {
            "category":"Shopping",
            "subcategory":"Clothing, Apparel, & Fashions",
            "type":"Retail Goods"
        }
    ],
    "sg:phone":"+1 608 723 7164",
    "sg:postcode":"53813",
    "sg:province":"WI",
    "sg:tags":[
        "alteration"
    ],
    "wof:name":"Custom Sewing & Crafts",
    "wof:placetype":"venue"
},
  "geometry": {"coordinates":[-90.73873399999999,42.879108],"type":"Point"}
}