{
  "type": "Feature",
  "properties": {
    "iso:country":"US",
    "sg:address":"5586 Spur Ln",
    "sg:city":"Plymouth",
    "sg:classifiers":[
        {
            "category":"Retail",
            "subcategory":"Repair Shop",
            "type":"Services"
        }
    ],
    "sg:phone":"+1 920 892 2191",
    "sg:postcode":"53073",
    "sg:province":"WI",
    "sg:tags":[
        "glass",
        "fiber"
    ],
    "wof:name":"Excel Tub & Shower Repair",
    "wof:placetype":"venue"
},
  "geometry": {"coordinates":[-87.941726,43.742855],"type":"Point"}
}