{
  "type": "Feature",
  "properties": {
    "iso:country":"US",
    "sg:address":"735 Fox Fire Dr",
    "sg:city":"Oshkosh",
    "sg:classifiers":[
        {
            "category":"Building & Trades",
            "subcategory":"Construction",
            "type":"Services"
        }
    ],
    "sg:phone":"+1 920 882 9299",
    "sg:postcode":"54904",
    "sg:province":"WI",
    "sg:tags":[
        "house",
        "builder",
        "home"
    ],
    "wof:name":"Geurts Custom Homes Inc",
    "wof:placetype":"venue"
},
  "geometry": {"coordinates":[-88.607158,44.011645],"type":"Point"}
}