{
  "type": "Feature",
  "properties": {
    "iso:country":"US",
    "sg:address":"2311 Windsor St",
    "sg:city":"Sun Prairie",
    "sg:classifiers":[
        {
            "category":"Banks & Credit Unions",
            "subcategory":"Bank",
            "type":"Services"
        }
    ],
    "sg:phone":"+1 608 825 4899",
    "sg:postcode":"53590",
    "sg:province":"WI",
    "wof:name":"US Bank",
    "wof:placetype":"venue"
},
  "geometry": {"coordinates":[-89.254718,43.18713],"type":"Point"}
}