{
  "type": "Feature",
  "properties": {
    "iso:country":"US",
    "sg:address":"1001 E Keefe Ave",
    "sg:city":"Milwaukee",
    "sg:classifiers":[
        {
            "category":"Organizations",
            "subcategory":"Political Organization",
            "type":"Services"
        }
    ],
    "sg:phone":"+1 414 964 8683",
    "sg:postcode":"53212",
    "sg:province":"WI",
    "wof:name":"Green Party Greater Milwauk",
    "wof:placetype":"venue"
},
  "geometry": {"coordinates":[-87.897542,43.081972],"type":"Point"}
}