{
  "type": "Feature",
  "properties": {
    "iso:country":"US",
    "sg:address":"2645 Harlem St",
    "sg:city":"Eau Claire",
    "sg:classifiers":[
        {
            "category":"Banks & Credit Unions",
            "subcategory":"Bank",
            "type":"Services"
        }
    ],
    "sg:phone":"+1 715 834 3275",
    "sg:postcode":"54701",
    "sg:province":"WI",
    "sg:tags":[
        "federal"
    ],
    "wof:name":"Eau Claire Teachers Credit Un",
    "wof:placetype":"venue"
},
  "geometry": {"coordinates":[-91.464415,44.79927],"type":"Point"}
}