{
  "type": "Feature",
  "properties": {
    "iso:country":"US",
    "sg:address":"115 4th St",
    "sg:city":"Nekoosa",
    "sg:classifiers":[
        {
            "category":"Building & Trades",
            "subcategory":"Construction",
            "type":"Services"
        }
    ],
    "sg:phone":"+1 715 886 2953",
    "sg:postcode":"54457",
    "sg:province":"WI",
    "sg:tags":[
        "contractor"
    ],
    "wof:name":"Bethel Builders",
    "wof:placetype":"venue"
},
  "geometry": {"coordinates":[-89.888473,44.319101],"type":"Point"}
}