{
  "type": "Feature",
  "properties": {
    "addr:full":"1820 Main St Green Bay WI 54302",
    "addr:housenumber":"1820",
    "addr:postcode":"54302",
    "addr:street":"Main St",
    "iso:country":"US",
    "sg:address":"1820 Main St",
    "sg:city":"Green Bay",
    "sg:classifiers":[
        {
            "category":"Food & Beverages",
            "subcategory":"Groceries & Convenience Stores",
            "type":"Retail Goods"
        }
    ],
    "sg:phone":"+1 920 468 9523",
    "sg:postcode":"54302",
    "sg:province":"WI",
    "wof:name":"Agente",
    "wof:placetype":"venue"
},
  "geometry": {"coordinates":[-87.97749399999999,44.494183],"type":"Point"}
}