{
  "type": "Feature",
  "properties": {
    "iso:country":"US",
    "sg:address":"9277 State Hwy 55",
    "sg:city":"Pickerel",
    "sg:classifiers":[
        {
            "category":"Freight",
            "type":"Transportation"
        }
    ],
    "sg:phone":"+1 715 484 5029",
    "sg:postcode":"54465",
    "sg:province":"WI",
    "sg:tags":[
        "hauling",
        "trucking"
    ],
    "wof:name":"Goeman Trucking LTD",
    "wof:placetype":"venue"
},
  "geometry": {"coordinates":[-88.923556,45.366568],"type":"Point"}
}