{
  "type": "Feature",
  "properties": {
    "iso:country":"US",
    "sg:address":"805 S Division St",
    "sg:city":"Waunakee",
    "sg:classifiers":[
        {
            "category":"Building & Trades",
            "subcategory":"Construction",
            "type":"Services"
        }
    ],
    "sg:phone":"+1 608 849 6039",
    "sg:postcode":"53597",
    "sg:province":"WI",
    "sg:tags":[
        "house"
    ],
    "wof:name":"Stewart Construction",
    "wof:placetype":"venue"
},
  "geometry": {"coordinates":[-89.44703800000001,43.186031],"type":"Point"}
}