{
  "type": "Feature",
  "properties": {
    "iso:country":"US",
    "sg:address":"9596 E Kroghville Rd",
    "sg:city":"Waterloo",
    "sg:classifiers":[
        {
            "category":"Building & Trades",
            "subcategory":"Landscaping Services",
            "type":"Services"
        }
    ],
    "sg:phone":"+1 920 648 4063",
    "sg:postcode":"53594",
    "sg:province":"WI",
    "wof:name":"Red Hawk Nursery",
    "wof:placetype":"venue"
},
  "geometry": {"coordinates":[-88.997266,43.059906],"type":"Point"}
}