{
  "type": "Feature",
  "properties": {
    "iso:country":"US",
    "sg:address":"617 Court St",
    "sg:city":"Neillsville",
    "sg:classifiers":[
        {
            "category":"Government",
            "subcategory":"Office",
            "type":"Public Place"
        }
    ],
    "sg:phone":"+1 715 743 5144",
    "sg:postcode":"54456",
    "sg:province":"WI",
    "sg:tags":[
        "county",
        "resource"
    ],
    "wof:name":"Clark County Aging & Nutrition",
    "wof:placetype":"venue"
},
  "geometry": {"coordinates":[-90.594687,44.561143],"type":"Point"}
}