{
  "type": "Feature",
  "properties": {
    "iso:country":"US",
    "sg:address":"2264 S Kinnickinnic Ave",
    "sg:city":"Milwaukee",
    "sg:classifiers":[
        {
            "category":"Retail",
            "subcategory":"Laundry & Dry Cleaning",
            "type":"Services"
        }
    ],
    "sg:phone":"+1 414 481 8660",
    "sg:postcode":"53207",
    "sg:province":"WI",
    "sg:tags":[
        "cleaners"
    ],
    "wof:name":"Jefferson Cleaners",
    "wof:placetype":"venue"
},
  "geometry": {"coordinates":[-87.904352,43.003214],"type":"Point"}
}