{
  "type": "Feature",
  "properties": {
    "iso:country":"US",
    "sg:address":"4431 Co Hwy I",
    "sg:city":"Saukville",
    "sg:classifiers":[
        {
            "category":"Shopping",
            "subcategory":"Stationery & Office Supplies",
            "type":"Retail Goods"
        }
    ],
    "sg:phone":"+1 262 335 2451",
    "sg:postcode":"53080",
    "sg:province":"WI",
    "sg:tags":[
        "album",
        "scrapbook"
    ],
    "wof:name":"Creative Papers & Supplies",
    "wof:placetype":"venue"
},
  "geometry": {"coordinates":[-87.98077000000001,43.435231],"type":"Point"}
}