{
  "type": "Feature",
  "properties": {
    "iso:country":"US",
    "sg:address":"1922 Sharon Ln",
    "sg:city":"Manitowoc",
    "sg:classifiers":[
        {
            "category":"Banks & Credit Unions",
            "subcategory":"Financial Services",
            "type":"Services"
        }
    ],
    "sg:phone":"+1 920 684 7053",
    "sg:postcode":"54220",
    "sg:province":"WI",
    "sg:tags":[
        "investment",
        "closed"
    ],
    "wof:name":"Shoto Investments LLC",
    "wof:placetype":"venue"
},
  "geometry": {"coordinates":[-87.703681,44.123055],"type":"Point"}
}