{
  "type": "Feature",
  "properties": {
    "iso:country":"US",
    "sg:address":"4734 W Lisbon Ave",
    "sg:city":"Milwaukee",
    "sg:classifiers":[
        {
            "category":"Personal",
            "subcategory":"Beauty Salon",
            "type":"Services"
        }
    ],
    "sg:phone":"+1 414 444 2200",
    "sg:postcode":"53208",
    "sg:province":"WI",
    "wof:name":"Trendsetters Salons LTD",
    "wof:placetype":"venue"
},
  "geometry": {"coordinates":[-87.973589,43.060967],"type":"Point"}
}