{
  "type": "Feature",
  "properties": {
    "iso:country":"US",
    "sg:address":"4261 Lien Rd",
    "sg:city":"Madison",
    "sg:classifiers":[
        {
            "category":"Travel",
            "subcategory":"Travel Agent",
            "type":"Entertainment"
        }
    ],
    "sg:phone":"+1 608 241 3878",
    "sg:postcode":"53704",
    "sg:province":"WI",
    "sg:tags":[
        "passenger",
        "agency",
        "transportation",
        "arrangement"
    ],
    "wof:name":"Gateway Trvl Crlson Trvl Ntwrk",
    "wof:placetype":"venue"
},
  "geometry": {"coordinates":[-89.309737,43.120966],"type":"Point"}
}