{
  "type": "Feature",
  "properties": {
    "addr:full":"811 Two Mile Ave Wisconsin Rapids WI 54494",
    "addr:housenumber":"811",
    "addr:postcode":"54494",
    "addr:street":"Two Mile Ave",
    "iso:country":"US",
    "sg:address":"811 Two Mile Ave",
    "sg:city":"Wisconsin Rapids",
    "sg:classifiers":[
        {
            "category":"Restaurant",
            "type":"Food & Drink"
        }
    ],
    "sg:phone":"+1 715 424 2048",
    "sg:postcode":"54494",
    "sg:province":"WI",
    "sg:tags":[
        "eating"
    ],
    "wof:name":"Cousins Subs",
    "wof:placetype":"venue"
},
  "geometry": {"coordinates":[-89.816755,44.362346],"type":"Point"}
}