{
  "type": "Feature",
  "properties": {
    "iso:country":"US",
    "sg:address":"107 W 5th St",
    "sg:city":"Marshfield",
    "sg:classifiers":[
        {
            "category":"Personal",
            "subcategory":"Beauty Salon",
            "type":"Services"
        }
    ],
    "sg:phone":"+1 715 384 2299",
    "sg:postcode":"54449",
    "sg:province":"WI",
    "sg:tags":[
        "shop",
        "barber"
    ],
    "wof:name":"Unique Styles By Phyllis",
    "wof:placetype":"venue"
},
  "geometry": {"coordinates":[-90.177536,44.663627],"type":"Point"}
}