{
  "type": "Feature",
  "properties": {
    "addr:full":"400 Water Ave Hillsboro WI 54634",
    "addr:housenumber":"400",
    "addr:postcode":"54634",
    "addr:street":"Water Ave",
    "iso:country":"US",
    "sg:address":"400 Water Ave",
    "sg:city":"Hillsboro",
    "sg:classifiers":[
        {
            "category":"Health Services",
            "subcategory":"Podiatrist",
            "type":"Services"
        }
    ],
    "sg:phone":"+1 608 489 2211",
    "sg:postcode":"54634",
    "sg:province":"WI",
    "wof:name":"Associated Podiatrists",
    "wof:placetype":"venue"
},
  "geometry": {"coordinates":[-90.345308,43.648896],"type":"Point"}
}