{
  "type": "Feature",
  "properties": {
    "iso:country":"US",
    "sg:address":"2123 W North Ave",
    "sg:city":"Milwaukee",
    "sg:classifiers":[
        {
            "category":"Shopping",
            "subcategory":"Clothing, Apparel, & Fashions",
            "type":"Retail Goods"
        }
    ],
    "sg:phone":"+1 414 344 1174",
    "sg:postcode":"53205",
    "sg:province":"WI",
    "wof:name":"Top Fashions",
    "wof:placetype":"venue"
},
  "geometry": {"coordinates":[-87.939779,43.060436],"type":"Point"}
}