{
  "type": "Feature",
  "properties": {
    "iso:country":"US",
    "sg:address":"2610 W Glendale Ave",
    "sg:city":"Milwaukee",
    "sg:classifiers":[
        {
            "category":"Social Services",
            "subcategory":"Child Care",
            "type":"Services"
        }
    ],
    "sg:phone":"+1 414 442 4675",
    "sg:postcode":"53209",
    "sg:province":"WI",
    "wof:name":"Tiny Toon Daycare",
    "wof:placetype":"venue"
},
  "geometry": {"coordinates":[-87.94668,43.100907],"type":"Point"}
}