{
  "type": "Feature",
  "properties": {
    "iso:country":"US",
    "sg:address":"1130 E Oklahoma Ave",
    "sg:city":"Milwaukee",
    "sg:classifiers":[
        {
            "category":"Autos & Motor Vehicles",
            "subcategory":"Fuel & Gas Station",
            "type":"Retail Goods"
        }
    ],
    "sg:phone":"+1 414 282 2077",
    "sg:postcode":"53207",
    "sg:province":"WI",
    "sg:tags":[
        "repair",
        "gasoline"
    ],
    "wof:name":"Badger Auto Repair",
    "wof:placetype":"venue"
},
  "geometry": {"coordinates":[-87.89473,42.988347],"type":"Point"}
}