{
  "type": "Feature",
  "properties": {
    "iso:country":"US",
    "sg:address":"14330 Co Hwy G",
    "sg:city":"Boyd",
    "sg:classifiers":[
        {
            "category":"Building & Trades",
            "subcategory":"Plumbing",
            "type":"Services"
        }
    ],
    "sg:phone":"+1 715 644 2332",
    "sg:postcode":"54726",
    "sg:province":"WI",
    "sg:tags":[
        "septic"
    ],
    "wof:name":"Rural Septic Svc LLC",
    "wof:placetype":"venue"
},
  "geometry": {"coordinates":[-90.984643,45.048085],"type":"Point"}
}