{
  "type": "Feature",
  "properties": {
    "iso:country":"US",
    "sg:address":"912 S Wells St",
    "sg:city":"Lake Geneva",
    "sg:classifiers":[
        {
            "category":"Professional",
            "subcategory":"Management & Consulting",
            "type":"Services"
        }
    ],
    "sg:phone":"+1 262 248 4399",
    "sg:postcode":"53147",
    "sg:province":"WI",
    "sg:tags":[
        "consultant",
        "educational"
    ],
    "wof:name":"Science Alliance",
    "wof:placetype":"venue"
},
  "geometry": {"coordinates":[-88.425487,42.583319],"type":"Point"}
}