{
  "type": "Feature",
  "properties": {
    "addr:full":"800 3rd St W Ashland WI 54806",
    "addr:housenumber":"800",
    "addr:postcode":"54806",
    "addr:street":"3Rd St W",
    "iso:country":"US",
    "sg:address":"800 3rd St W",
    "sg:city":"Ashland",
    "sg:classifiers":[
        {
            "category":"Retail",
            "subcategory":"Repair Shop",
            "type":"Services"
        }
    ],
    "sg:phone":"+1 715 682 4111",
    "sg:postcode":"54806",
    "sg:province":"WI",
    "sg:tags":[
        "welding"
    ],
    "wof:name":"Ashland Welding & Marine",
    "wof:placetype":"venue"
},
  "geometry": {"coordinates":[-90.89108,46.58687],"type":"Point"}
}