{
  "type": "Feature",
  "properties": {
    "iso:country":"US",
    "sg:address":"1509 N 4th St",
    "sg:city":"Tomahawk",
    "sg:classifiers":[
        {
            "category":"Freight",
            "type":"Transportation"
        }
    ],
    "sg:phone":"+1 715 224 2300",
    "sg:postcode":"54487",
    "sg:province":"WI",
    "wof:name":"Truck Train Transportation",
    "wof:placetype":"venue"
},
  "geometry": {"coordinates":[-89.729369,45.491235],"type":"Point"}
}