{
  "type": "Feature",
  "properties": {
    "iso:country":"US",
    "sg:address":"2050 Emerald Dr",
    "sg:city":"Green Bay",
    "sg:classifiers":[
        {
            "category":"Professional",
            "subcategory":"Business Services",
            "type":"Services"
        }
    ],
    "sg:phone":"+1 920 469 2076",
    "sg:postcode":"54311",
    "sg:province":"WI",
    "wof:name":"Ribbens Enterprises Inc",
    "wof:placetype":"venue"
},
  "geometry": {"coordinates":[-87.932057,44.46342],"type":"Point"}
}