{
  "type": "Feature",
  "properties": {
    "iso:country":"US",
    "sg:address":"271 Co Rd B",
    "sg:city":"Montfort",
    "sg:classifiers":[
        {
            "category":"Farming",
            "subcategory":"Livestock Farm",
            "type":"Manufacturing & Wholesale Goods"
        }
    ],
    "sg:phone":"+1 608 943 6472",
    "sg:postcode":"53569",
    "sg:province":"WI",
    "sg:tags":[
        "beef",
        "feedlot",
        "cattle"
    ],
    "wof:name":"David Faull",
    "wof:placetype":"venue"
},
  "geometry": {"coordinates":[-90.419578,42.951457],"type":"Point"}
}