{
  "type": "Feature",
  "properties": {
    "iso:country":"US",
    "sg:address":"131 E Main St",
    "sg:city":"Marshall",
    "sg:classifiers":[
        {
            "category":"Health Services",
            "subcategory":"Doctor",
            "type":"Services"
        }
    ],
    "sg:phone":"+1 608 655 4164",
    "sg:postcode":"53529",
    "sg:province":"WI",
    "sg:tags":[
        "clinic"
    ],
    "wof:name":"Litang Family Chiropractic",
    "wof:placetype":"venue"
},
  "geometry": {"coordinates":[-89.063996,43.167382],"type":"Point"}
}