{
  "type": "Feature",
  "properties": {
    "iso:country":"US",
    "sg:address":"2027 McCoy Rd",
    "sg:city":"Sun Prairie",
    "sg:classifiers":[
        {
            "category":"Food & Beverages",
            "subcategory":"Specialty",
            "type":"Retail Goods"
        }
    ],
    "sg:phone":"+1 608 825 2024",
    "sg:postcode":"53590",
    "sg:province":"WI",
    "sg:tags":[
        "health",
        "diet"
    ],
    "wof:name":"Nature's Way Health",
    "wof:placetype":"venue"
},
  "geometry": {"coordinates":[-89.24613,43.175968],"type":"Point"}
}