{
  "type": "Feature",
  "properties": {
    "addr:full":"1182 Sandy Hook Ln Luck WI 54853",
    "addr:housenumber":"1182",
    "addr:postcode":"54853",
    "addr:street":"Sandy Hook Ln",
    "iso:country":"US",
    "sg:address":"1182 Sandy Hook Ln",
    "sg:city":"Luck",
    "sg:classifiers":[
        {
            "category":"Building & Trades",
            "subcategory":"Plumbing",
            "type":"Services"
        }
    ],
    "sg:phone":"+1 715 472 4616",
    "sg:postcode":"54853",
    "sg:province":"WI",
    "sg:tags":[
        "contractor"
    ],
    "wof:name":"After Hours Heating & Air",
    "wof:placetype":"venue"
},
  "geometry": {"coordinates":[-92.40387800000001,45.547853],"type":"Point"}
}