{
  "type": "Feature",
  "properties": {
    "iso:country":"US",
    "sg:address":"605 W Commercial St",
    "sg:city":"Mazomanie",
    "sg:classifiers":[
        {
            "category":"Farming",
            "subcategory":"Livestock Farm",
            "type":"Manufacturing & Wholesale Goods"
        }
    ],
    "sg:phone":"+1 608 795 9817",
    "sg:postcode":"53560",
    "sg:province":"WI",
    "sg:tags":[
        "animal",
        "general"
    ],
    "wof:name":"Mitten Ranch LLC",
    "wof:placetype":"venue"
},
  "geometry": {"coordinates":[-89.799323,43.171735],"type":"Point"}
}