{
  "type": "Feature",
  "properties": {
    "iso:country":"US",
    "sg:address":"2136 E Dayton St",
    "sg:city":"Madison",
    "sg:classifiers":[
        {
            "category":"Building & Trades",
            "subcategory":"Construction",
            "type":"Services"
        }
    ],
    "sg:phone":"+1 608 249 8944",
    "sg:postcode":"53704",
    "sg:province":"WI",
    "sg:tags":[
        "floor",
        "laying",
        "contractor"
    ],
    "wof:name":"Duane Sippola",
    "wof:placetype":"venue"
},
  "geometry": {"coordinates":[-89.356702,43.097147],"type":"Point"}
}