{
  "type": "Feature",
  "properties": {
    "iso:country":"US",
    "sg:address":"3530 Memorial Dr",
    "sg:city":"Madison",
    "sg:classifiers":[
        {
            "category":"Organizations",
            "subcategory":"Labor Organization",
            "type":"Services"
        }
    ],
    "sg:phone":"+1 608 244 4640",
    "sg:postcode":"53704",
    "sg:province":"WI",
    "wof:name":"WSEU",
    "wof:placetype":"venue"
},
  "geometry": {"coordinates":[-89.405788,43.130255],"type":"Point"}
}