{
  "type": "Feature",
  "properties": {
    "iso:country":"US",
    "sg:address":"24924 60th St # 50",
    "sg:city":"Salem",
    "sg:classifiers":[
        {
            "category":"Building & Trades",
            "subcategory":"Cleaning & Sanitation",
            "type":"Services"
        }
    ],
    "sg:phone":"+1 262 843 3000",
    "sg:postcode":"53168",
    "sg:province":"WI",
    "sg:tags":[
        "carpet"
    ],
    "wof:name":"Rug Doctor Rents",
    "wof:placetype":"venue"
},
  "geometry": {"coordinates":[-88.11091,42.582823],"type":"Point"}
}