{
  "type": "Feature",
  "properties": {
    "iso:country":"US",
    "sg:address":"621 N Park St",
    "sg:city":"Reedsburg",
    "sg:classifiers":[
        {
            "category":"Social Services",
            "subcategory":"Child Care",
            "type":"Services"
        }
    ],
    "sg:phone":"+1 608 524 6363",
    "sg:postcode":"53959",
    "sg:province":"WI",
    "sg:tags":[
        "day"
    ],
    "wof:name":"Little Folks Playhouse",
    "wof:placetype":"venue"
},
  "geometry": {"coordinates":[-90.00669600000001,43.538709],"type":"Point"}
}