{
  "type": "Feature",
  "properties": {
    "iso:country":"US",
    "sg:address":"4643 Butternut Rd",
    "sg:city":"Edgar",
    "sg:classifiers":[
        {
            "category":"Freight",
            "type":"Transportation"
        }
    ],
    "sg:phone":"+1 715 352 3081",
    "sg:postcode":"54426",
    "sg:province":"WI",
    "sg:tags":[
        "trucking"
    ],
    "wof:name":"William Martyn Trucking LLC",
    "wof:placetype":"venue"
},
  "geometry": {"coordinates":[-90.098715,44.925011],"type":"Point"}
}