{
  "type": "Feature",
  "properties": {
    "iso:country":"US",
    "sg:address":"1228 Memorial Dr",
    "sg:city":"Manitowoc",
    "sg:classifiers":[
        {
            "category":"Restaurant",
            "type":"Food & Drink"
        }
    ],
    "sg:phone":"+1 920 684 7188",
    "sg:postcode":"54220",
    "sg:province":"WI",
    "wof:name":"Kasper's Family Restaurant",
    "wof:placetype":"venue"
},
  "geometry": {"coordinates":[-87.635105,44.115839],"type":"Point"}
}