{
  "type": "Feature",
  "properties": {
    "addr:full":"2521 Allen Blvd Middleton WI 53562",
    "addr:housenumber":"2521",
    "addr:postcode":"53562",
    "addr:street":"Allen Blvd",
    "iso:country":"US",
    "sg:address":"2521 Allen Blvd",
    "sg:city":"Middleton",
    "sg:classifiers":[
        {
            "category":"Health Services",
            "subcategory":"Doctor",
            "type":"Services"
        }
    ],
    "sg:phone":"+1 608 831 2070",
    "sg:postcode":"53562",
    "sg:province":"WI",
    "sg:tags":[
        "physician",
        "surgeon"
    ],
    "wof:name":"Meriter Hospital Physical",
    "wof:placetype":"venue"
},
  "geometry": {"coordinates":[-89.486215,43.100834],"type":"Point"}
}