{
  "type": "Feature",
  "properties": {
    "addr:full":"3575 N 18th St Milwaukee WI 53206",
    "addr:housenumber":"3575",
    "addr:postcode":"53206",
    "addr:street":"N 18Th St",
    "iso:country":"US",
    "sg:address":"3575 N 18th St",
    "sg:city":"Milwaukee",
    "sg:classifiers":[
        {
            "category":"Professional",
            "type":"Services"
        }
    ],
    "sg:phone":"+1 414 445 2669",
    "sg:postcode":"53206",
    "sg:province":"WI",
    "wof:name":"Make Money Inc",
    "wof:placetype":"venue"
},
  "geometry": {"coordinates":[-87.93349600000001,43.082221],"type":"Point"}
}