{
  "type": "Feature",
  "properties": {
    "iso:country":"US",
    "sg:address":"114 4th Ave",
    "sg:city":"Baraboo",
    "sg:classifiers":[
        {
            "category":"Banks & Credit Unions",
            "subcategory":"Bank",
            "type":"Services"
        }
    ],
    "sg:phone":"+1 608 355 4161",
    "sg:postcode":"53913",
    "sg:province":"WI",
    "sg:tags":[
        "loan",
        "real estate"
    ],
    "wof:name":"Countrywide Home Loans",
    "wof:placetype":"venue"
},
  "geometry": {"coordinates":[-89.744055,43.470971],"type":"Point"}
}