{
  "type": "Feature",
  "properties": {
    "addr:full":"5385 W River Rd Waunakee WI 53597",
    "addr:housenumber":"5385",
    "addr:postcode":"53597",
    "addr:street":"W River Rd",
    "iso:country":"US",
    "sg:address":"5385 W River Rd",
    "sg:city":"Waunakee",
    "sg:classifiers":[
        {
            "category":"Home & Garden",
            "subcategory":"Building Materials",
            "type":"Retail Goods"
        }
    ],
    "sg:phone":"+1 608 849 5951",
    "sg:postcode":"53597",
    "sg:province":"WI",
    "sg:tags":[
        "mixed",
        "concrete"
    ],
    "sg:website":"www.wingra.com",
    "wof:name":"Wingra Redi-Mix Inc",
    "wof:placetype":"venue"
},
  "geometry": {"coordinates":[-89.40741300000001,43.159142],"type":"Point"}
}