{
  "type": "Feature",
  "properties": {
    "iso:country":"US",
    "sg:address":"6702 University Rd",
    "sg:city":"Elkhorn",
    "sg:classifiers":[
        {
            "category":"Building & Trades",
            "subcategory":"Construction",
            "type":"Services"
        }
    ],
    "sg:phone":"+1 262 742 4820",
    "sg:postcode":"53121",
    "sg:province":"WI",
    "sg:tags":[
        "concrete",
        "contractor"
    ],
    "wof:name":"Contractors Choice Concrete",
    "wof:placetype":"venue"
},
  "geometry": {"coordinates":[-88.56801400000001,42.736945],"type":"Point"}
}