{
  "type": "Feature",
  "properties": {
    "iso:country":"US",
    "sg:address":"75 W Maple St",
    "sg:city":"Sturgeon Bay",
    "sg:classifiers":[
        {
            "category":"Autos & Motor Vehicles",
            "subcategory":"Automobile Sales",
            "type":"Retail Goods"
        }
    ],
    "sg:phone":"+1 920 743 3838",
    "sg:postcode":"54235",
    "sg:province":"WI",
    "sg:tags":[
        "equipment",
        "lawn",
        "motorcycle",
        "snowmobile",
        "garden"
    ],
    "wof:name":"Mays Sport Center",
    "wof:placetype":"venue"
},
  "geometry": {"coordinates":[-87.385583,44.828898],"type":"Point"}
}