{
  "type": "Feature",
  "properties": {
    "iso:country":"US",
    "sg:address":"68 Co Rd Aa",
    "sg:city":"Durand",
    "sg:classifiers":[
        {
            "category":"Professional",
            "subcategory":"Business Services",
            "type":"Services"
        }
    ],
    "sg:phone":"+1 715 672 5035",
    "sg:postcode":"54736",
    "sg:province":"WI",
    "wof:name":"Mt Enterprises",
    "wof:placetype":"venue"
},
  "geometry": {"coordinates":[-91.97939,44.585249],"type":"Point"}
}