{
  "type": "Feature",
  "properties": {
    "iso:country":"US",
    "sg:address":"2275 State Hwy 22",
    "sg:city":"Pulcifer",
    "sg:classifiers":[
        {
            "category":"Building & Trades",
            "subcategory":"Plumbing",
            "type":"Services"
        }
    ],
    "sg:phone":"+1 715 745 6663",
    "sg:postcode":"54124",
    "sg:province":"WI",
    "sg:tags":[
        "plumbing",
        "contractor"
    ],
    "sg:website":"www.mikesplumbinginc.com",
    "wof:name":"Mike's Plumbing Heating Inc",
    "wof:placetype":"venue"
},
  "geometry": {"coordinates":[-88.358469,44.84504],"type":"Point"}
}