{
  "type": "Feature",
  "properties": {
    "iso:country":"US",
    "sg:address":"3957 Washington Ave",
    "sg:city":"Kaukauna",
    "sg:classifiers":[
        {
            "category":"Professional",
            "type":"Services"
        }
    ],
    "sg:phone":"+1 920 788 4416",
    "sg:postcode":"54130",
    "sg:province":"WI",
    "wof:name":"Tim Clark",
    "wof:placetype":"venue"
},
  "geometry": {"coordinates":[-88.294191,44.379856],"type":"Point"}
}