{
  "type": "Feature",
  "properties": {
    "iso:country":"US",
    "sg:address":"730 N Grand Ave",
    "sg:city":"Waukesha",
    "sg:classifiers":[
        {
            "category":"Professional",
            "subcategory":"Management & Consulting",
            "type":"Services"
        },
        {
            "category":"Professional",
            "subcategory":"Advertising",
            "type":"Services"
        }
    ],
    "sg:phone":"+1 262 549 6848",
    "sg:postcode":"53186",
    "sg:province":"WI",
    "sg:tags":[
        "firm",
        "counselor",
        "agency",
        "public",
        "relations"
    ],
    "wof:name":"Roberts Group Inc",
    "wof:placetype":"venue"
},
  "geometry": {"coordinates":[-88.23164300000001,43.010425],"type":"Point"}
}