{
  "type": "Feature",
  "properties": {
    "addr:full":"5140 N Ballard Rd Appleton WI 54913",
    "addr:housenumber":"5140",
    "addr:postcode":"54913",
    "addr:street":"N Ballard Rd",
    "iso:country":"US",
    "sg:address":"5140 N Ballard Rd",
    "sg:city":"Appleton",
    "sg:classifiers":[
        {
            "category":"Professional",
            "subcategory":"Computer Services",
            "type":"Services"
        }
    ],
    "sg:phone":"+1 920 735 0299",
    "sg:postcode":"54913",
    "sg:province":"WI",
    "sg:tags":[
        "personal",
        "repair"
    ],
    "sg:website":"www.mkenterprises.com",
    "wof:name":"M & K Enterprises",
    "wof:placetype":"venue"
},
  "geometry": {"coordinates":[-88.375041,44.315903],"type":"Point"}
}