{
  "type": "Feature",
  "properties": {
    "iso:country":"US",
    "sg:address":"704 S. 2nd Street",
    "sg:city":"Milwaukee",
    "sg:classifiers":[
        {
            "category":"Professional",
            "subcategory":"Advertising",
            "type":"Services"
        }
    ],
    "sg:phone":"+1 414 202 5874",
    "sg:postcode":"53204",
    "sg:province":"WI",
    "sg:tags":[
        "marketing",
        "advertising",
        "business-to-business",
        "b2b",
        "strategy"
    ],
    "sg:website":"http://www.gravitym.com",
    "wof:name":"Gravity Marketing",
    "wof:placetype":"venue"
},
  "geometry": {"coordinates":[-87.912558,43.02325],"type":"Point"}
}