{
  "type": "Feature",
  "properties": {
    "iso:country":"US",
    "sg:address":"200 Main St",
    "sg:city":"La Crosse",
    "sg:classifiers":[
        {
            "category":"Shopping",
            "subcategory":"Clothing, Apparel, & Fashions",
            "type":"Retail Goods"
        }
    ],
    "sg:phone":"+1 608 784 1122",
    "sg:postcode":"54601",
    "sg:province":"WI",
    "wof:name":"La Boutique Bridal",
    "wof:placetype":"venue"
},
  "geometry": {"coordinates":[-91.252524,43.812857],"type":"Point"}
}