{
  "type": "Feature",
  "properties": {
    "iso:country":"US",
    "sg:address":"403 C P Ave",
    "sg:city":"Lake Mills",
    "sg:classifiers":[
        {
            "category":"Retail",
            "subcategory":"Auto Repair",
            "type":"Services"
        }
    ],
    "sg:phone":"+1 920 648 4777",
    "sg:postcode":"53551",
    "sg:province":"WI",
    "sg:tags":[
        "body",
        "automobile",
        "painting"
    ],
    "wof:name":"Cruisin Auto Body Inc",
    "wof:placetype":"venue"
},
  "geometry": {"coordinates":[-88.898586,43.071433],"type":"Point"}
}