{
  "type": "Feature",
  "properties": {
    "iso:country":"US",
    "sg:address":"1004 E Ogden Ave",
    "sg:city":"Milwaukee",
    "sg:classifiers":[
        {
            "category":"Professional",
            "subcategory":"Business Services",
            "type":"Services"
        }
    ],
    "sg:phone":"+1 414 961 2463",
    "sg:postcode":"53202",
    "sg:province":"WI",
    "sg:tags":[
        "interior",
        "design"
    ],
    "wof:name":"Design Accents Inc",
    "wof:placetype":"venue"
},
  "geometry": {"coordinates":[-87.89827699999999,43.048169],"type":"Point"}
}