{
  "type": "Feature",
  "properties": {
    "iso:country":"US",
    "sg:address":"829 S Green Bay Rd",
    "sg:city":"Racine",
    "sg:classifiers":[
        {
            "category":"Shopping",
            "type":"Retail Goods"
        },
        {
            "category":"Manufacturing",
            "subcategory":"Tools & Machinery",
            "type":"Manufacturing & Wholesale Goods"
        }
    ],
    "sg:phone":"+1 262 635 0191",
    "sg:postcode":"53406",
    "sg:province":"WI",
    "sg:tags":[
        "limb",
        "surgical",
        "artificial",
        "mfg"
    ],
    "wof:name":"Actra Rehabilitation Assoc",
    "wof:placetype":"venue"
},
  "geometry": {"coordinates":[-87.844996,42.721358],"type":"Point"}
}