{
  "type": "Feature",
  "properties": {
    "iso:country":"US",
    "sg:address":"7885 Lea Ln",
    "sg:city":"Fort Atkinson",
    "sg:classifiers":[
        {
            "category":"Farming",
            "subcategory":"Dairy Farm",
            "type":"Manufacturing & Wholesale Goods"
        }
    ],
    "sg:phone":"+1 920 563 2829",
    "sg:postcode":"53538",
    "sg:province":"WI",
    "wof:name":"Oak View Farms",
    "wof:placetype":"venue"
},
  "geometry": {"coordinates":[-88.92388099999999,42.986809],"type":"Point"}
}