{
  "type": "Feature",
  "properties": {
    "addr:full":"1706 Main St Marinette WI 54143",
    "addr:housenumber":"1706",
    "addr:postcode":"54143",
    "addr:street":"Main St",
    "iso:country":"US",
    "sg:address":"1706 Main St",
    "sg:city":"Marinette",
    "sg:classifiers":[
        {
            "category":"Shopping",
            "type":"Retail Goods"
        }
    ],
    "sg:phone":"+1 715 732 5365",
    "sg:postcode":"54143",
    "sg:province":"WI",
    "sg:tags":[
        "hearing",
        "equipment",
        "supply",
        "impaired"
    ],
    "wof:name":"Professional Hearing Aid Ctr",
    "wof:placetype":"venue"
},
  "geometry": {"coordinates":[-87.628737,45.098681],"type":"Point"}
}