{
  "type": "Feature",
  "properties": {
    "iso:country":"US",
    "sg:address":"2311 Schofield Ave",
    "sg:city":"Schofield",
    "sg:classifiers":[
        {
            "category":"Home & Garden",
            "subcategory":"Building Materials",
            "type":"Retail Goods"
        }
    ],
    "sg:phone":"+1 715 359 0431",
    "sg:postcode":"54476",
    "sg:province":"WI",
    "sg:tags":[
        "household",
        "appliance"
    ],
    "wof:name":"Kitchens By Stratford",
    "wof:placetype":"venue"
},
  "geometry": {"coordinates":[-89.595348,44.909044],"type":"Point"}
}