{
  "type": "Feature",
  "properties": {
    "iso:country":"US",
    "sg:address":"1270 Main St",
    "sg:city":"Green Bay",
    "sg:classifiers":[
        {
            "category":"Building & Trades",
            "subcategory":"Construction",
            "type":"Services"
        }
    ],
    "sg:phone":"+1 920 436 0432",
    "sg:postcode":"54302",
    "sg:province":"WI",
    "sg:tags":[
        "plastering",
        "contractor"
    ],
    "wof:name":"Select Plastering Corp",
    "wof:placetype":"venue"
},
  "geometry": {"coordinates":[-87.99641699999999,44.510971],"type":"Point"}
}