{
  "type": "Feature",
  "properties": {
    "iso:country":"US",
    "sg:address":"8810 State Hwy 13 S",
    "sg:city":"Wisconsin Rapids",
    "sg:classifiers":[
        {
            "category":"Autos & Motor Vehicles",
            "subcategory":"Fuel & Gas Station",
            "type":"Retail Goods"
        }
    ],
    "sg:phone":"+1 715 325 2233",
    "sg:postcode":"54494",
    "sg:province":"WI",
    "sg:tags":[
        "oil"
    ],
    "wof:name":"Saratoga Mini Mart",
    "wof:placetype":"venue"
},
  "geometry": {"coordinates":[-89.81021,44.313785],"type":"Point"}
}