{
  "type": "Feature",
  "properties": {
    "iso:country":"US",
    "sg:address":"1848 Strawberry Rd",
    "sg:city":"Deerfield",
    "sg:classifiers":[
        {
            "category":"Building & Trades",
            "subcategory":"Landscaping Services",
            "type":"Services"
        }
    ],
    "sg:phone":"+1 608 764 8684",
    "sg:postcode":"53531",
    "sg:province":"WI",
    "wof:name":"Royal Island Sod",
    "wof:placetype":"venue"
},
  "geometry": {"coordinates":[-89.154156,43.087334],"type":"Point"}
}