{
  "type": "Feature",
  "properties": {
    "addr:full":"5808 Allen Rd Little Suamico WI 54141",
    "addr:housenumber":"5808",
    "addr:postcode":"54141",
    "addr:street":"Allen Rd",
    "iso:country":"US",
    "sg:address":"5808 Allen Rd",
    "sg:city":"Little Suamico",
    "sg:classifiers":[
        {
            "category":"Social Services",
            "subcategory":"Child Care",
            "type":"Services"
        }
    ],
    "sg:phone":"+1 920 826 6454",
    "sg:postcode":"54141",
    "sg:province":"WI",
    "wof:name":"Tenderhearts Learning Ctr",
    "wof:placetype":"venue"
},
  "geometry": {"coordinates":[-88.053997,44.706294],"type":"Point"}
}