{
  "type": "Feature",
  "properties": {
    "addr:full":"9745 S 58th St Franklin WI 53132",
    "addr:housenumber":"9745",
    "addr:postcode":"53132",
    "addr:street":"S 58Th St",
    "iso:country":"US",
    "sg:address":"9745 S 58th St",
    "sg:city":"Franklin",
    "sg:classifiers":[
        {
            "category":"Retail",
            "subcategory":"Auto Repair",
            "type":"Services"
        }
    ],
    "sg:phone":"+1 414 421 7222",
    "sg:postcode":"53132",
    "sg:province":"WI",
    "sg:tags":[
        "injection",
        "part",
        "engines-diesel-fuel"
    ],
    "sg:website":"http://www.napaautocare.com/",
    "wof:name":"Huckstorf Diesel Pump & Injector Service",
    "wof:placetype":"venue"
},
  "geometry": {"coordinates":[-87.988449,42.871846],"type":"Point"}
}