{
  "type": "Feature",
  "properties": {
    "iso:country":"US",
    "sg:address":"7695 Co Rd C",
    "sg:city":"Pittsville",
    "sg:classifiers":[
        {
            "category":"Farming",
            "subcategory":"Dairy Farm",
            "type":"Manufacturing & Wholesale Goods"
        }
    ],
    "sg:phone":"+1 715 884 6827",
    "sg:postcode":"54466",
    "sg:province":"WI",
    "wof:name":"Marvin Hahn",
    "wof:placetype":"venue"
},
  "geometry": {"coordinates":[-90.096524,44.481991],"type":"Point"}
}