{
  "type": "Feature",
  "properties": {
    "iso:country":"US",
    "sg:address":"252 Co Rd I",
    "sg:city":"Balsam Lake",
    "sg:classifiers":[
        {
            "category":"Autos & Motor Vehicles",
            "subcategory":"Boat Sales",
            "type":"Retail Goods"
        }
    ],
    "sg:phone":"+1 715 485 3393",
    "sg:postcode":"54810",
    "sg:province":"WI",
    "sg:tags":[
        "marina",
        "campground",
        "dealer",
        "sales"
    ],
    "wof:name":"Reed's Sunnyside Marina",
    "wof:placetype":"venue"
},
  "geometry": {"coordinates":[-92.453035,45.451245],"type":"Point"}
}