{
  "type": "Feature",
  "properties": {
    "iso:country":"US",
    "sg:address":"1086 N Archers Way",
    "sg:city":"Nekoosa",
    "sg:classifiers":[
        {
            "category":"Utilities",
            "type":"Services"
        }
    ],
    "sg:phone":"+1 715 325 5971",
    "sg:postcode":"54457",
    "sg:province":"WI",
    "sg:tags":[
        "sanitary"
    ],
    "wof:name":"B & D Snowplowing",
    "wof:placetype":"venue"
},
  "geometry": {"coordinates":[-89.791189,44.206991],"type":"Point"}
}