{
  "type": "Feature",
  "properties": {
    "addr:full":"360 Pine St Manawa WI 54949",
    "addr:housenumber":"360",
    "addr:postcode":"54949",
    "addr:street":"Pine St",
    "iso:country":"US",
    "sg:address":"360 Pine St",
    "sg:city":"Manawa",
    "sg:classifiers":[
        {
            "category":"Home & Garden",
            "subcategory":"Household Appliances",
            "type":"Retail Goods"
        }
    ],
    "sg:phone":"+1 920 596 3180",
    "sg:postcode":"54949",
    "sg:province":"WI",
    "sg:tags":[
        "machine",
        "sewing"
    ],
    "wof:name":"Drath Sewing Center Inc",
    "wof:placetype":"venue"
},
  "geometry": {"coordinates":[-88.925546,44.449654],"type":"Point"}
}