{
  "type": "Feature",
  "properties": {
    "iso:country":"US",
    "sg:address":"178 N Iowa St",
    "sg:city":"Dodgeville",
    "sg:classifiers":[
        {
            "category":"Real Estate",
            "subcategory":"Architect",
            "type":"Services"
        }
    ],
    "sg:phone":"+1 608 935 9020",
    "sg:postcode":"53533",
    "sg:province":"WI",
    "sg:tags":[
        "architectural"
    ],
    "wof:name":"Amber Westerman Design Studios",
    "wof:placetype":"venue"
},
  "geometry": {"coordinates":[-90.130406,42.95996],"type":"Point"}
}