{
  "type": "Feature",
  "properties": {
    "addr:full":"2823 Co Rd V Sheboygan WI 53081",
    "addr:housenumber":"2823",
    "addr:postcode":"53081",
    "addr:street":"Co Rd V",
    "iso:country":"US",
    "sg:address":"2823 Co Rd V",
    "sg:city":"Sheboygan",
    "sg:classifiers":[
        {
            "category":"Retail",
            "subcategory":"Repair Shop",
            "type":"Services"
        }
    ],
    "sg:phone":"+1 920 458 6075",
    "sg:postcode":"53081",
    "sg:province":"WI",
    "wof:name":"Batterman Sales & Service",
    "wof:placetype":"venue"
},
  "geometry": {"coordinates":[-87.745025,43.673175],"type":"Point"}
}