{
  "type": "Feature",
  "properties": {
    "iso:country":"US",
    "sg:address":"1332 S Broadway",
    "sg:city":"Green Bay",
    "sg:classifiers":[
        {
            "category":"Bars & Pubs",
            "type":"Food & Drink"
        }
    ],
    "sg:phone":"+1 920 432 9095",
    "sg:postcode":"54304",
    "sg:province":"WI",
    "wof:name":"Hut",
    "wof:placetype":"venue"
},
  "geometry": {"coordinates":[-88.031519,44.501641],"type":"Point"}
}