{
  "type": "Feature",
  "properties": {
    "iso:country":"US",
    "sg:address":"216 W Park St",
    "sg:city":"Neshkoro",
    "sg:classifiers":[
        {
            "category":"Wholesale",
            "subcategory":"Construction Materials",
            "type":"Manufacturing & Wholesale Goods"
        }
    ],
    "sg:phone":"+1 920 293 4004",
    "sg:postcode":"54960",
    "sg:province":"WI",
    "sg:tags":[
        "lumber"
    ],
    "wof:name":"Interstate Lumber Connection",
    "wof:placetype":"venue"
},
  "geometry": {"coordinates":[-89.22009,43.965591],"type":"Point"}
}