{
  "type": "Feature",
  "properties": {
    "iso:country":"US",
    "sg:address":"334 E Silver Spring Dr",
    "sg:city":"Milwaukee",
    "sg:classifiers":[
        {
            "category":"Cinema",
            "subcategory":"Movie Theater",
            "type":"Entertainment"
        }
    ],
    "sg:phone":"+1 414 906 9999",
    "sg:postcode":"53217",
    "sg:province":"WI",
    "sg:tags":[
        "motion",
        "picture",
        "except",
        "drive"
    ],
    "wof:name":"Fox Bay Cinema Grill",
    "wof:placetype":"venue"
},
  "geometry": {"coordinates":[-87.905808,43.118586],"type":"Point"}
}