{
  "type": "Feature",
  "properties": {
    "iso:country":"US",
    "sg:address":"223 E Spring St",
    "sg:city":"Loyal",
    "sg:classifiers":[
        {
            "category":"Building & Trades",
            "subcategory":"Construction",
            "type":"Services"
        }
    ],
    "sg:phone":"+1 715 255 8362",
    "sg:postcode":"54446",
    "sg:province":"WI",
    "sg:tags":[
        "concrete",
        "contractor"
    ],
    "wof:name":"Loyal Concrete Products",
    "wof:placetype":"venue"
},
  "geometry": {"coordinates":[-90.493047,44.739881],"type":"Point"}
}