{
  "type": "Feature",
  "properties": {
    "addr:full":"1262 John Q Hammons Dr Madison WI 53717",
    "addr:housenumber":"1262",
    "addr:postcode":"53717",
    "addr:street":"John Q Hammons Dr",
    "iso:country":"US",
    "sg:address":"1262 John Q Hammons Dr",
    "sg:city":"Madison",
    "sg:classifiers":[
        {
            "category":"Restaurant",
            "type":"Food & Drink"
        }
    ],
    "sg:phone":"+1 608 254 4131",
    "sg:postcode":"53717",
    "sg:province":"WI",
    "sg:tags":[
        "eating"
    ],
    "wof:name":"Copa Restaurants Madison LLC",
    "wof:placetype":"venue"
},
  "geometry": {"coordinates":[-89.52406999999999,43.085557],"type":"Point"}
}