{
  "type": "Feature",
  "properties": {
    "addr:full":"328 Lake St N Prescott WI 54021",
    "addr:housenumber":"328",
    "addr:postcode":"54021",
    "addr:street":"Lake St N",
    "iso:country":"US",
    "sg:address":"328 Lake St N",
    "sg:city":"Prescott",
    "sg:classifiers":[
        {
            "category":"Ice Cream",
            "type":"Food & Drink"
        }
    ],
    "sg:menulink":"http://www.allmenus.com/wi/prescott/192707-dairy-queen/menu/",
    "sg:phone":"+1 715 262 0067",
    "sg:postcode":"54021",
    "sg:province":"WI",
    "sg:tags":[
        "burger",
        "american"
    ],
    "wof:name":"Dairy Queen",
    "wof:placetype":"venue"
},
  "geometry": {"coordinates":[-92.803602,44.752453],"type":"Point"}
}