{
  "type": "Feature",
  "properties": {
    "addr:full":"2136 N 56th St Milwaukee WI 53208",
    "addr:housenumber":"2136",
    "addr:postcode":"53208",
    "addr:street":"N 56Th St",
    "iso:country":"US",
    "sg:address":"2136 N 56th St",
    "sg:city":"Milwaukee",
    "sg:classifiers":[
        {
            "category":"Professional",
            "subcategory":"Art Services",
            "type":"Services"
        }
    ],
    "sg:phone":"+1 414 445 6592",
    "sg:postcode":"53208",
    "sg:province":"WI",
    "sg:tags":[
        "photographer"
    ],
    "wof:name":"Wolfe Photography Inc",
    "wof:placetype":"venue"
},
  "geometry": {"coordinates":[-87.982978,43.058521],"type":"Point"}
}