{
  "type": "Feature",
  "properties": {
    "iso:country":"US",
    "sg:address":"1333 12th Ave",
    "sg:city":"Green Bay",
    "sg:classifiers":[
        {
            "category":"Building & Trades",
            "subcategory":"Construction",
            "type":"Services"
        }
    ],
    "sg:phone":"+1 920 494 1233",
    "sg:postcode":"54304",
    "sg:province":"WI",
    "sg:tags":[
        "house"
    ],
    "wof:name":"C Ravey Bld Remodeling",
    "wof:placetype":"venue"
},
  "geometry": {"coordinates":[-88.042005,44.504758],"type":"Point"}
}