{
  "type": "Feature",
  "properties": {
    "iso:country":"US",
    "sg:address":"11104 Hillcrest Rd",
    "sg:city":"Sister Bay",
    "sg:classifiers":[
        {
            "category":"Professional",
            "subcategory":"Management & Consulting",
            "type":"Services"
        }
    ],
    "sg:phone":"+1 920 854 9483",
    "sg:postcode":"54234",
    "sg:province":"WI",
    "wof:name":"Stevens and Associates Inc",
    "wof:placetype":"venue"
},
  "geometry": {"coordinates":[-87.114265,45.204085],"type":"Point"}
}