{
  "type": "Feature",
  "properties": {
    "iso:country":"US",
    "sg:address":"21 Maplewood Dr",
    "sg:city":"Stevens Point",
    "sg:classifiers":[
        {
            "category":"Professional",
            "subcategory":"Advertising",
            "type":"Services"
        }
    ],
    "sg:phone":"+1 715 342 3689",
    "sg:postcode":"54481",
    "sg:province":"WI",
    "sg:tags":[
        "mail",
        "direct"
    ],
    "wof:name":"Val-Pak of Central Wisconsin",
    "wof:placetype":"venue"
},
  "geometry": {"coordinates":[-89.547985,44.517598],"type":"Point"}
}