{
  "type": "Feature",
  "properties": {
    "iso:country":"US",
    "sg:address":"120 N Beaumont Rd",
    "sg:city":"Prairie Du Chien",
    "sg:classifiers":[
        {
            "category":"Shopping",
            "subcategory":"Clothing, Apparel, & Fashions",
            "type":"Retail Goods"
        }
    ],
    "sg:phone":"+1 608 326 6016",
    "sg:postcode":"53821",
    "sg:province":"WI",
    "wof:name":"Kozelka's Western & Work Wear",
    "wof:placetype":"venue"
},
  "geometry": {"coordinates":[-91.146423,43.052304],"type":"Point"}
}