{
  "type": "Feature",
  "properties": {
    "iso:country":"US",
    "sg:address":"108 W Park Ridge Ave",
    "sg:city":"Appleton",
    "sg:classifiers":[
        {
            "category":"Restaurant",
            "type":"Food & Drink"
        }
    ],
    "sg:phone":"+1 920 749 0948",
    "sg:postcode":"54911",
    "sg:province":"WI",
    "sg:tags":[
        "eating"
    ],
    "wof:name":"Mobile Chef",
    "wof:placetype":"venue"
},
  "geometry": {"coordinates":[-88.410512,44.292866],"type":"Point"}
}