{
  "type": "Feature",
  "properties": {
    "iso:country":"US",
    "sg:address":"187 E Court St",
    "sg:city":"Richland Center",
    "sg:classifiers":[
        {
            "category":"Shopping",
            "subcategory":"Gifts & Souvenirs",
            "type":"Retail Goods"
        }
    ],
    "sg:phone":"+1 608 647 6556",
    "sg:postcode":"53581",
    "sg:province":"WI",
    "sg:tags":[
        "shop"
    ],
    "wof:name":"Raindrops & Roses",
    "wof:placetype":"venue"
},
  "geometry": {"coordinates":[-90.384595,43.335417],"type":"Point"}
}