{
  "type": "Feature",
  "properties": {
    "iso:country":"US",
    "sg:address":"442 Clay St",
    "sg:city":"Chilton",
    "sg:classifiers":[
        {
            "category":"Building & Trades",
            "subcategory":"Construction",
            "type":"Services"
        }
    ],
    "sg:phone":"+1 920 849 2333",
    "sg:postcode":"53014",
    "sg:province":"WI",
    "sg:tags":[
        "product",
        "retail",
        "painting",
        "painter",
        "contractor"
    ],
    "wof:name":"Quality Painters Inc",
    "wof:placetype":"venue"
},
  "geometry": {"coordinates":[-88.152118,44.031236],"type":"Point"}
}