{
  "type": "Feature",
  "properties": {
    "iso:country":"US",
    "sg:address":"511 South St",
    "sg:city":"Durand",
    "sg:classifiers":[
        {
            "category":"Social Services",
            "subcategory":"Child Care",
            "type":"Services"
        }
    ],
    "sg:phone":"+1 715 672 3195",
    "sg:postcode":"54736",
    "sg:province":"WI",
    "sg:tags":[
        "day"
    ],
    "wof:name":"Little Inspirations Child Care",
    "wof:placetype":"venue"
},
  "geometry": {"coordinates":[-91.954511,44.61995],"type":"Point"}
}