{
  "type": "Feature",
  "properties": {
    "iso:country":"US",
    "sg:address":"2172 Black Hawk Dr",
    "sg:city":"Lodi",
    "sg:classifiers":[
        {
            "category":"Building & Trades",
            "subcategory":"Construction",
            "type":"Services"
        }
    ],
    "sg:phone":"+1 608 592 4876",
    "sg:postcode":"53555",
    "sg:province":"WI",
    "sg:tags":[
        "resurfacing",
        "laying",
        "refinishing",
        "floor"
    ],
    "wof:name":"Harrenstein Wood Floors",
    "wof:placetype":"venue"
},
  "geometry": {"coordinates":[-89.64010399999999,43.354241],"type":"Point"}
}