{
  "type": "Feature",
  "properties": {
    "iso:country":"US",
    "sg:address":"208 S Main St",
    "sg:city":"Lodi",
    "sg:classifiers":[
        {
            "category":"Personal",
            "type":"Services"
        },
        {
            "category":"Health Services",
            "subcategory":"Health Practitioner",
            "type":"Services"
        }
    ],
    "sg:phone":"+1 608 592 7026",
    "sg:postcode":"53555",
    "sg:province":"WI",
    "sg:tags":[
        "therapist",
        "massage"
    ],
    "wof:name":"A Touch Above The Rest",
    "wof:placetype":"venue"
},
  "geometry": {"coordinates":[-89.526326,43.313476],"type":"Point"}
}