{
  "type": "Feature",
  "properties": {
    "iso:country":"US",
    "sg:address":"5229 W Capitol Dr",
    "sg:city":"Milwaukee",
    "sg:classifiers":[
        {
            "category":"Organizations",
            "subcategory":"Religious Organization",
            "type":"Services"
        }
    ],
    "sg:phone":"+1 414 445 1656",
    "sg:postcode":"53216",
    "sg:province":"WI",
    "wof:name":"Capitol Drive Lutheran Church",
    "wof:placetype":"venue"
},
  "geometry": {"coordinates":[-87.979209,43.089822],"type":"Point"}
}