{
  "type": "Feature",
  "properties": {
    "addr:full":"1133 N Sherman Ave Madison WI 53704",
    "addr:housenumber":"1133",
    "addr:postcode":"53704",
    "addr:street":"N Sherman Ave",
    "iso:country":"US",
    "sg:address":"1133 N Sherman Ave",
    "sg:city":"Madison",
    "sg:classifiers":[
        {
            "category":"Shopping",
            "subcategory":"Clothing, Apparel, & Fashions",
            "type":"Retail Goods"
        },
        {
            "category":"Shopping",
            "subcategory":"Thrift Store",
            "type":"Retail Goods"
        },
        {
            "category":"Banks & Credit Unions",
            "subcategory":"Bank",
            "type":"Services"
        },
        {
            "category":"Shopping",
            "subcategory":"Used Merchandise",
            "type":"Retail Goods"
        }
    ],
    "sg:phone":"+1 608 268 0793",
    "sg:postcode":"53704",
    "sg:province":"WI",
    "sg:tags":[
        "shop",
        "vintage",
        "period",
        "hand",
        "resale",
        "second",
        "clothing-collectible",
        "furniture"
    ],
    "sg:website":"http://boomerangsresale.org",
    "wof:name":"Boomerangs Resale Shop",
    "wof:placetype":"venue"
},
  "geometry": {"coordinates":[-89.363787,43.111901],"type":"Point"}
}