{
  "type": "Feature",
  "properties": {
    "addr:full":"501 S Center Ave Merrill WI 54452",
    "addr:housenumber":"501",
    "addr:postcode":"54452",
    "addr:street":"S Center Ave",
    "iso:country":"US",
    "sg:address":"501 S Center Ave",
    "sg:city":"Merrill",
    "sg:classifiers":[
        {
            "category":"Professional",
            "type":"Services"
        }
    ],
    "sg:phone":"+1 715 539 5000",
    "sg:postcode":"54452",
    "sg:province":"WI",
    "wof:name":"Sisters of Mercy of Holy",
    "wof:placetype":"venue"
},
  "geometry": {"coordinates":[-89.682743,45.177016],"type":"Point"}
}