{
  "type": "Feature",
  "properties": {
    "iso:country":"US",
    "sg:address":"4402 State Hwy 72",
    "sg:city":"Menomonie",
    "sg:classifiers":[
        {
            "category":"Building & Trades",
            "subcategory":"Electrical",
            "type":"Services"
        }
    ],
    "sg:phone":"+1 715 495 6924",
    "sg:postcode":"54751",
    "sg:province":"WI",
    "sg:tags":[
        "electrical",
        "contractor"
    ],
    "wof:name":"Ktb Electric",
    "wof:placetype":"venue"
},
  "geometry": {"coordinates":[-91.939694,44.772594],"type":"Point"}
}