{
  "type": "Feature",
  "properties": {
    "iso:country":"US",
    "sg:address":"128 High St",
    "sg:city":"Mineral Point",
    "sg:classifiers":[
        {
            "category":"Shopping",
            "subcategory":"Pharmacy",
            "type":"Retail Goods"
        }
    ],
    "sg:phone":"+1 608 987 2336",
    "sg:postcode":"53565",
    "sg:province":"WI",
    "sg:tags":[
        "drug"
    ],
    "wof:name":"Ivey's Pharmacy Inc",
    "wof:placetype":"venue"
},
  "geometry": {"coordinates":[-90.179474,42.85987],"type":"Point"}
}