{
  "type": "Feature",
  "properties": {
    "iso:country":"US",
    "sg:address":"1500 Lincoln Ave",
    "sg:city":"Tomah",
    "sg:classifiers":[
        {
            "category":"Real Estate",
            "subcategory":"Real Estate Operator",
            "type":"Services"
        }
    ],
    "sg:phone":"+1 414 362 7240",
    "sg:postcode":"54660",
    "sg:province":"WI",
    "sg:tags":[
        "building",
        "apartment"
    ],
    "wof:name":"Alton Manor",
    "wof:placetype":"venue"
},
  "geometry": {"coordinates":[-90.51237399999999,43.972501],"type":"Point"}
}