{
  "type": "Feature",
  "properties": {
    "iso:country":"US",
    "sg:address":"12824 W Colfax Pl",
    "sg:city":"Butler",
    "sg:classifiers":[
        {
            "category":"Building & Trades",
            "subcategory":"Construction",
            "type":"Services"
        }
    ],
    "sg:phone":"+1 262 781 6987",
    "sg:postcode":"53007",
    "sg:province":"WI",
    "sg:tags":[
        "repairing",
        "remodeling",
        "contractor"
    ],
    "wof:name":"Hurst Development",
    "wof:placetype":"venue"
},
  "geometry": {"coordinates":[-88.07368,43.109044],"type":"Point"}
}