{
  "type": "Feature",
  "properties": {
    "iso:country":"US",
    "sg:address":"680 Co Hwy P",
    "sg:city":"Port Washington",
    "sg:phone":"+1 262 285 3363",
    "sg:postcode":"53074",
    "sg:province":"WI",
    "sg:tags":[
        "farm",
        "corn",
        "wheat",
        "soybean"
    ],
    "wof:name":"Allen Poull",
    "wof:placetype":"venue"
},
  "geometry": {"coordinates":[-87.819582,43.455982],"type":"Point"}
}