{
  "type": "Feature",
  "properties": {
    "addr:full":"1211 Lakeview Dr Sullivan WI 53178",
    "addr:housenumber":"1211",
    "addr:postcode":"53178",
    "addr:street":"Lakeview Dr",
    "iso:country":"US",
    "sg:address":"1211 Lakeview Dr",
    "sg:city":"Sullivan",
    "sg:classifiers":[
        {
            "category":"Building & Trades",
            "subcategory":"Landscaping Services",
            "type":"Services"
        }
    ],
    "sg:phone":"+1 262 593 5635",
    "sg:postcode":"53178",
    "sg:province":"WI",
    "sg:tags":[
        "landscape",
        "contractor"
    ],
    "wof:name":"Lakeside Landscaping & Design",
    "wof:placetype":"venue"
},
  "geometry": {"coordinates":[-88.588177,43.041242],"type":"Point"}
}