{
  "type": "Feature",
  "properties": {
    "iso:country":"US",
    "sg:address":"2021 Verlin Rd",
    "sg:city":"Green Bay",
    "sg:classifiers":[
        {
            "category":"Shopping",
            "subcategory":"Bicycles & Sporting Goods",
            "type":"Retail Goods"
        }
    ],
    "sg:phone":"+1 920 465 1766",
    "sg:postcode":"54311",
    "sg:province":"WI",
    "sg:tags":[
        "shop",
        "trophy",
        "wholesale",
        "pro",
        "bow",
        "bowling"
    ],
    "wof:name":"Weber Bowling & Awards",
    "wof:placetype":"venue"
},
  "geometry": {"coordinates":[-87.979037,44.472429],"type":"Point"}
}