{
  "type": "Feature",
  "properties": {
    "iso:country":"US",
    "sg:address":"1024 W Wisconsin Ave",
    "sg:city":"Appleton",
    "sg:classifiers":[
        {
            "category":"Autos & Motor Vehicles",
            "subcategory":"Automobile Sales",
            "type":"Retail Goods"
        }
    ],
    "sg:phone":"+1 920 380 1321",
    "sg:postcode":"54914",
    "sg:province":"WI",
    "sg:tags":[
        "used"
    ],
    "wof:name":"Auto Plaza",
    "wof:placetype":"venue"
},
  "geometry": {"coordinates":[-88.422197,44.273086],"type":"Point"}
}