{
  "type": "Feature",
  "properties": {
    "iso:country":"US",
    "sg:address":"1740 Northport Dr",
    "sg:city":"Madison",
    "sg:classifiers":[
        {
            "category":"Real Estate",
            "subcategory":"Real Estate Operator",
            "type":"Services"
        }
    ],
    "sg:phone":"+1 608 249 9281",
    "sg:postcode":"53704",
    "sg:province":"WI",
    "sg:tags":[
        "building",
        "apartment"
    ],
    "sg:website":"www.northport.org",
    "wof:name":"Northport Packer Apartments",
    "wof:placetype":"venue"
},
  "geometry": {"coordinates":[-89.36278900000001,43.130511],"type":"Point"}
}