{
  "type": "Feature",
  "properties": {
    "iso:country":"US",
    "sg:address":"10175 N Amber Trl",
    "sg:city":"Edgerton",
    "sg:classifiers":[
        {
            "category":"Professional",
            "subcategory":"Accounting & Tax Preparation",
            "type":"Services"
        }
    ],
    "sg:phone":"+1 608 884 6172",
    "sg:postcode":"53534",
    "sg:province":"WI",
    "sg:tags":[
        "return",
        "filing"
    ],
    "wof:name":"H & R Block Tax Svc",
    "wof:placetype":"venue"
},
  "geometry": {"coordinates":[-89.073043,42.820168],"type":"Point"}
}