{
  "type": "Feature",
  "properties": {
    "iso:country":"US",
    "sg:address":"121 W Main",
    "sg:city":"Cedarburg",
    "sg:classifiers":[
        {
            "category":"Government",
            "subcategory":"City Hall",
            "type":"Public Place"
        }
    ],
    "sg:phone":"+1 262 238 8128",
    "sg:postcode":"53012",
    "sg:province":"WI",
    "wof:name":"Ozaukee County",
    "wof:placetype":"venue"
},
  "geometry": {"coordinates":[-87.997597,43.304699],"type":"Point"}
}