{
  "type": "Feature",
  "properties": {
    "iso:country":"US",
    "sg:address":"311 Ash St",
    "sg:city":"Marshfield",
    "sg:classifiers":[
        {
            "category":"Retail",
            "subcategory":"Veterinary Services",
            "type":"Services"
        }
    ],
    "sg:phone":"+1 715 384 4727",
    "sg:postcode":"54449",
    "sg:province":"WI",
    "sg:tags":[
        "veterinarian"
    ],
    "wof:name":"Muellers Animal Clinic",
    "wof:placetype":"venue"
},
  "geometry": {"coordinates":[-90.155653,44.692392],"type":"Point"}
}