{
  "type": "Feature",
  "properties": {
    "iso:country":"US",
    "sg:address":"5339 N 46th St",
    "sg:city":"Milwaukee",
    "sg:classifiers":[
        {
            "category":"Organizations",
            "subcategory":"Religious Organization",
            "type":"Services"
        }
    ],
    "sg:phone":"+1 414 462 9642",
    "sg:postcode":"53218",
    "sg:province":"WI",
    "wof:name":"Open Door Ministries Inc",
    "wof:placetype":"venue"
},
  "geometry": {"coordinates":[-87.970196,43.114934],"type":"Point"}
}