{
  "type": "Feature",
  "properties": {
    "iso:country":"US",
    "sg:address":"3504 Madson Rd",
    "sg:city":"Manitowoc",
    "sg:classifiers":[
        {
            "category":"Farming",
            "subcategory":"Dairy Farm",
            "type":"Manufacturing & Wholesale Goods"
        }
    ],
    "sg:phone":"+1 920 758 2661",
    "sg:postcode":"54220",
    "sg:province":"WI",
    "wof:name":"Robley John",
    "wof:placetype":"venue"
},
  "geometry": {"coordinates":[-87.821686,44.05599],"type":"Point"}
}