{
  "type": "Feature",
  "properties": {
    "addr:full":"740 Industry Ct Green Bay WI 54304",
    "addr:housenumber":"740",
    "addr:postcode":"54304",
    "addr:street":"Industry Ct",
    "iso:country":"US",
    "sg:address":"740 Industry Ct",
    "sg:city":"Green Bay",
    "sg:classifiers":[
        {
            "category":"Wholesale",
            "subcategory":"Auto Parts",
            "type":"Manufacturing & Wholesale Goods"
        }
    ],
    "sg:phone":"+1 920 496 0400",
    "sg:postcode":"54304",
    "sg:province":"WI",
    "sg:tags":[
        "body",
        "automotive",
        "paint",
        "shop",
        "automobile"
    ],
    "wof:name":"Auto Paint Specialists Inc",
    "wof:placetype":"venue"
},
  "geometry": {"coordinates":[-88.06706200000001,44.475125],"type":"Point"}
}