{
  "type": "Feature",
  "properties": {
    "iso:country":"US",
    "sg:address":"2692 Kelleen Dr",
    "sg:city":"Waupaca",
    "sg:classifiers":[
        {
            "category":"Insurance",
            "subcategory":"Insurance Agent",
            "type":"Services"
        }
    ],
    "sg:phone":"+1 715 258 0458",
    "sg:postcode":"54981",
    "sg:province":"WI",
    "wof:name":"Rusch Insurance Service",
    "wof:placetype":"venue"
},
  "geometry": {"coordinates":[-89.131154,44.33745],"type":"Point"}
}