{
  "type": "Feature",
  "properties": {
    "iso:country":"US",
    "sg:address":"4791 Co Hwy H",
    "sg:city":"Fredonia",
    "sg:classifiers":[
        {
            "category":"Retail",
            "subcategory":"Auto Repair",
            "type":"Services"
        }
    ],
    "sg:phone":"+1 262 692 9449",
    "sg:postcode":"53021",
    "sg:province":"WI",
    "sg:tags":[
        "body",
        "automobile",
        "painting"
    ],
    "wof:name":"D & D Auto Body Repair",
    "wof:placetype":"venue"
},
  "geometry": {"coordinates":[-88.02306900000001,43.496123],"type":"Point"}
}