{
  "type": "Feature",
  "properties": {
    "addr:full":"309 N 5th St Wausau WI 54403",
    "addr:housenumber":"309",
    "addr:postcode":"54403",
    "addr:street":"N 5Th St",
    "iso:country":"US",
    "sg:address":"309 N 5th St",
    "sg:city":"Wausau",
    "sg:classifiers":[
        {
            "category":"Professional",
            "subcategory":"Lawyer & Legal Services",
            "type":"Services"
        }
    ],
    "sg:phone":"+1 715 845 8286",
    "sg:postcode":"54403",
    "sg:province":"WI",
    "sg:tags":[
        "attorney"
    ],
    "wof:name":"Karoblis & Peterson",
    "wof:placetype":"venue"
},
  "geometry": {"coordinates":[-89.62552599999999,44.959582],"type":"Point"}
}