{
  "type": "Feature",
  "properties": {
    "iso:country":"US",
    "sg:address":"3017 US Hwy 10",
    "sg:city":"Maiden Rock",
    "sg:classifiers":[
        {
            "category":"Farming",
            "subcategory":"Dairy Farm",
            "type":"Manufacturing & Wholesale Goods"
        }
    ],
    "sg:phone":"+1 715 647 4032",
    "sg:postcode":"54750",
    "sg:province":"WI",
    "wof:name":"Catts Four Seasons",
    "wof:placetype":"venue"
},
  "geometry": {"coordinates":[-92.291262,44.653142],"type":"Point"}
}