{
  "type": "Feature",
  "properties": {
    "iso:country":"US",
    "sg:address":"1995 S Van Dyke Rd",
    "sg:city":"Appleton",
    "sg:classifiers":[
        {
            "category":"Restaurant",
            "type":"Food & Drink"
        }
    ],
    "sg:phone":"+1 920 733 1007",
    "sg:postcode":"54914",
    "sg:province":"WI",
    "sg:tags":[
        "eating"
    ],
    "wof:name":"Subway",
    "wof:placetype":"venue"
},
  "geometry": {"coordinates":[-88.469584,44.245193],"type":"Point"}
}