{
  "type": "Feature",
  "properties": {
    "iso:country":"US",
    "sg:address":"2113 S Clubhouse Dr",
    "sg:city":"New Berlin",
    "sg:classifiers":[
        {
            "category":"Banks & Credit Unions",
            "subcategory":"Bank",
            "type":"Services"
        }
    ],
    "sg:phone":"+1 262 784 0910",
    "sg:postcode":"53151",
    "sg:province":"WI",
    "sg:tags":[
        "loan"
    ],
    "wof:name":"Equity Corperate Housing",
    "wof:placetype":"venue"
},
  "geometry": {"coordinates":[-88.106847,43.005793],"type":"Point"}
}