{
  "type": "Feature",
  "properties": {
    "iso:country":"US",
    "sg:address":"2015 Mystic Hills Ter",
    "sg:city":"Green Bay",
    "sg:classifiers":[
        {
            "category":"Building & Trades",
            "subcategory":"Electrical",
            "type":"Services"
        }
    ],
    "sg:phone":"+1 920 434 9979",
    "sg:postcode":"54313",
    "sg:province":"WI",
    "sg:tags":[
        "electrical",
        "electric",
        "contractor"
    ],
    "wof:name":"Ace Electric Inc",
    "wof:placetype":"venue"
},
  "geometry": {"coordinates":[-88.105389,44.595138],"type":"Point"}
}