{
  "type": "Feature",
  "properties": {
    "iso:country":"US",
    "sg:address":"2912 London Rd",
    "sg:city":"Eau Claire",
    "sg:classifiers":[
        {
            "category":"Shopping",
            "subcategory":"Computers & Home Electronics",
            "type":"Retail Goods"
        }
    ],
    "sg:phone":"+1 715 832 6763",
    "sg:postcode":"54701",
    "sg:province":"WI",
    "sg:tags":[
        "mobile",
        "repair",
        "radio"
    ],
    "sg:website":"www.rassbachcommunications.com",
    "wof:name":"Rassbach Communications",
    "wof:placetype":"venue"
},
  "geometry": {"coordinates":[-91.463217,44.785737],"type":"Point"}
}