{
  "type": "Feature",
  "properties": {
    "addr:full":"616 Hickory Dr Hudson WI 54016",
    "addr:housenumber":"616",
    "addr:postcode":"54016",
    "addr:street":"Hickory Dr",
    "iso:country":"US",
    "sg:address":"616 Hickory Dr",
    "sg:city":"Hudson",
    "sg:classifiers":[
        {
            "category":"Social Services",
            "subcategory":"Job Training",
            "type":"Services"
        }
    ],
    "sg:phone":"+1 715 386 8410",
    "sg:postcode":"54016",
    "sg:province":"WI",
    "wof:name":"D Five Coaching LLC",
    "wof:placetype":"venue"
},
  "geometry": {"coordinates":[-92.739898,44.97739],"type":"Point"}
}