{
  "type": "Feature",
  "properties": {
    "iso:country":"US",
    "sg:address":"5846 Baltes Rd",
    "sg:city":"Waunakee",
    "sg:classifiers":[
        {
            "category":"Farming",
            "subcategory":"Farm",
            "type":"Manufacturing & Wholesale Goods"
        }
    ],
    "sg:phone":"+1 608 831 4224",
    "sg:postcode":"53597",
    "sg:province":"WI",
    "sg:tags":[
        "general"
    ],
    "wof:name":"Tom Helt Farms",
    "wof:placetype":"venue"
},
  "geometry": {"coordinates":[-89.561227,43.180465],"type":"Point"}
}