{
  "type": "Feature",
  "properties": {
    "iso:country":"US",
    "sg:address":"101 W Edison Ave",
    "sg:city":"Appleton",
    "sg:classifiers":[
        {
            "category":"Professional",
            "subcategory":"Computer Services",
            "type":"Services"
        }
    ],
    "sg:phone":"+1 920 993 9884",
    "sg:postcode":"54915",
    "sg:province":"WI",
    "sg:tags":[
        "website",
        "design"
    ],
    "wof:name":"Best Image",
    "wof:placetype":"venue"
},
  "geometry": {"coordinates":[-88.40435600000001,44.255362],"type":"Point"}
}