{
  "type": "Feature",
  "properties": {
    "iso:country":"US",
    "sg:address":"2120 N 73rd St",
    "sg:city":"Milwaukee",
    "sg:classifiers":[
        {
            "category":"Wholesale",
            "subcategory":"Computers",
            "type":"Manufacturing & Wholesale Goods"
        }
    ],
    "sg:phone":"+1 414 454 0219",
    "sg:postcode":"53213",
    "sg:province":"WI",
    "wof:name":"Cicero & Assocation Inc",
    "wof:placetype":"venue"
},
  "geometry": {"coordinates":[-88.003573,43.058654],"type":"Point"}
}