{
  "type": "Feature",
  "properties": {
    "iso:country":"US",
    "sg:address":"3584 Ll Townline Rd",
    "sg:city":"Mauston",
    "sg:classifiers":[
        {
            "category":"Shopping",
            "subcategory":"Discount & Variety Stores",
            "type":"Retail Goods"
        }
    ],
    "sg:phone":"+1 608 847 2202",
    "sg:postcode":"53948",
    "sg:province":"WI",
    "sg:tags":[
        "merchandise",
        "general"
    ],
    "wof:name":"Manthey Salvage",
    "wof:placetype":"venue"
},
  "geometry": {"coordinates":[-90.069845,43.783821],"type":"Point"}
}