{
  "type": "Feature",
  "properties": {
    "iso:country":"US",
    "sg:address":"8436 W Old Sauk Rd",
    "sg:city":"Middleton",
    "sg:classifiers":[
        {
            "category":"Personal",
            "subcategory":"Beauty Salon",
            "type":"Services"
        }
    ],
    "sg:phone":"+1 608 833 2690",
    "sg:postcode":"53717",
    "sg:province":"WI",
    "sg:tags":[
        "shop"
    ],
    "wof:name":"Q Nails & Spa",
    "wof:placetype":"venue"
},
  "geometry": {"coordinates":[-89.535533,43.074783],"type":"Point"}
}