{
  "type": "Feature",
  "properties": {
    "iso:country":"US",
    "sg:address":"1007 N Wisconsin Dr",
    "sg:city":"Howards Grove",
    "sg:classifiers":[
        {
            "category":"Professional",
            "subcategory":"Business Services",
            "type":"Services"
        }
    ],
    "sg:phone":"+1 920 565 4116",
    "sg:postcode":"53083",
    "sg:province":"WI",
    "sg:tags":[
        "painter",
        "sign"
    ],
    "wof:name":"Critter-Grams",
    "wof:placetype":"venue"
},
  "geometry": {"coordinates":[-87.821016,43.842479],"type":"Point"}
}