{
  "type": "Feature",
  "properties": {
    "iso:country":"US",
    "sg:address":"113 N Cascade St",
    "sg:city":"Osceola",
    "sg:classifiers":[
        {
            "category":"Place Of Worship",
            "type":"Public Place"
        },
        {
            "category":"Organizations",
            "subcategory":"Religious Organization",
            "type":"Services"
        }
    ],
    "sg:phone":"+1 715 755 4644",
    "sg:postcode":"54020",
    "sg:province":"WI",
    "sg:tags":[
        "clergy",
        "church"
    ],
    "wof:name":"Janes Kenneth Pastor",
    "wof:placetype":"venue"
},
  "geometry": {"coordinates":[-92.705901,45.319804],"type":"Point"}
}