{
  "type": "Feature",
  "properties": {
    "iso:country":"US",
    "sg:address":"139 N 3rd Ave",
    "sg:city":"Sturgeon Bay",
    "sg:classifiers":[
        {
            "category":"Shopping",
            "subcategory":"Gifts & Souvenirs",
            "type":"Retail Goods"
        }
    ],
    "sg:phone":"+1 810 730 5697",
    "sg:postcode":"54235",
    "sg:province":"WI",
    "sg:tags":[
        "shop"
    ],
    "wof:name":"Abdul-Jabbar Insaf",
    "wof:placetype":"venue"
},
  "geometry": {"coordinates":[-87.37770399999999,44.835543],"type":"Point"}
}