{
  "type": "Feature",
  "properties": {
    "addr:full":"406 S Pearl St New London WI 54961",
    "addr:housenumber":"406",
    "addr:postcode":"54961",
    "addr:street":"S Pearl St",
    "iso:country":"US",
    "sg:address":"406 S Pearl St",
    "sg:city":"New London",
    "sg:classifiers":[
        {
            "category":"Education",
            "subcategory":"Library",
            "type":"Public Place"
        }
    ],
    "sg:phone":"+1 920 982 8519",
    "sg:postcode":"54961",
    "sg:province":"WI",
    "sg:tags":[
        "executive"
    ],
    "wof:name":"New London Public Library",
    "wof:placetype":"venue"
},
  "geometry": {"coordinates":[-88.739565,44.389916],"type":"Point"}
}