{
  "type": "Feature",
  "properties": {
    "iso:country":"US",
    "sg:address":"2345 Co Rd D",
    "sg:city":"Elkhorn",
    "sg:classifiers":[
        {
            "category":"Real Estate",
            "subcategory":"Real Estate Agent",
            "type":"Services"
        }
    ],
    "sg:phone":"+1 262 642 7788",
    "sg:postcode":"53121",
    "sg:province":"WI",
    "sg:tags":[
        "appraiser"
    ],
    "wof:name":"Atkinson Appraising Inc",
    "wof:placetype":"venue"
},
  "geometry": {"coordinates":[-88.422325,42.748651],"type":"Point"}
}