{
  "type": "Feature",
  "properties": {
    "addr:full":"3371 Westover Ln Eau Claire WI 54701",
    "addr:housenumber":"3371",
    "addr:postcode":"54701",
    "addr:street":"Westover Ln",
    "iso:country":"US",
    "sg:address":"3371 Westover Ln",
    "sg:city":"Eau Claire",
    "sg:classifiers":[
        {
            "category":"Food & Beverages",
            "subcategory":"Specialty",
            "type":"Retail Goods"
        }
    ],
    "sg:phone":"+1 715 834 2543",
    "sg:postcode":"54701",
    "sg:province":"WI",
    "wof:name":"Shaklee Distributor",
    "wof:placetype":"venue"
},
  "geometry": {"coordinates":[-91.50234500000001,44.783801],"type":"Point"}
}