{
  "type": "Feature",
  "properties": {
    "iso:country":"US",
    "sg:address":"5844 N Lovers Lane Rd",
    "sg:city":"Milwaukee",
    "sg:classifiers":[
        {
            "category":"Restaurant",
            "type":"Food & Drink"
        }
    ],
    "sg:phone":"+1 414 760 8829",
    "sg:postcode":"53225",
    "sg:province":"WI",
    "sg:tags":[
        "eating"
    ],
    "wof:name":"Adrianos Pizza of SE WI",
    "wof:placetype":"venue"
},
  "geometry": {"coordinates":[-88.055443,43.123963],"type":"Point"}
}