{
  "type": "Feature",
  "properties": {
    "iso:country":"US",
    "sg:address":"2200 Patch St",
    "sg:city":"Stevens Point",
    "sg:classifiers":[
        {
            "category":"Professional",
            "subcategory":"Computer Services",
            "type":"Services"
        }
    ],
    "sg:phone":"+1 715 295 0350",
    "sg:postcode":"54481",
    "sg:province":"WI",
    "sg:tags":[
        "repair"
    ],
    "wof:name":"Hometown Computer Repair",
    "wof:placetype":"venue"
},
  "geometry": {"coordinates":[-89.565614,44.512125],"type":"Point"}
}