{
  "type": "Feature",
  "properties": {
    "iso:country":"US",
    "sg:address":"1301 Holtan Rd",
    "sg:city":"Stoughton",
    "sg:classifiers":[
        {
            "category":"Social Services",
            "subcategory":"Child Care",
            "type":"Services"
        }
    ],
    "sg:phone":"+1 608 873 6659",
    "sg:postcode":"53589",
    "sg:province":"WI",
    "sg:tags":[
        "day"
    ],
    "wof:name":"Tiny Treasures Child Care",
    "wof:placetype":"venue"
},
  "geometry": {"coordinates":[-89.23625,42.925963],"type":"Point"}
}