{
  "type": "Feature",
  "properties": {
    "addr:full":"2239 N Prospect Ave Milwaukee WI 53202",
    "addr:housenumber":"2239",
    "addr:postcode":"53202",
    "addr:street":"N Prospect Ave",
    "iso:country":"US",
    "sg:address":"2239 N Prospect Ave",
    "sg:city":"Milwaukee",
    "sg:classifiers":[
        {
            "category":"Shopping",
            "subcategory":"Music",
            "type":"Retail Goods"
        }
    ],
    "sg:phone":"+1 414 276 1321",
    "sg:postcode":"53202",
    "sg:province":"WI",
    "sg:tags":[
        "book"
    ],
    "wof:name":"Recycled Records & Books Inc",
    "wof:placetype":"venue"
},
  "geometry": {"coordinates":[-87.885188,43.058668],"type":"Point"}
}