{
  "type": "Feature",
  "properties": {
    "iso:country":"US",
    "sg:address":"916 E Clifford St",
    "sg:city":"Plymouth",
    "sg:classifiers":[
        {
            "category":"Health Services",
            "subcategory":"Clinic",
            "type":"Services"
        }
    ],
    "sg:phone":"+1 920 893 5830",
    "sg:postcode":"53073",
    "sg:province":"WI",
    "wof:name":"Plmouth Care Center",
    "wof:placetype":"venue"
},
  "geometry": {"coordinates":[-87.96815700000001,43.742104],"type":"Point"}
}