{
  "type": "Feature",
  "properties": {
    "iso:country":"US",
    "sg:address":"479 Co Rd Aa",
    "sg:city":"Durand",
    "sg:classifiers":[
        {
            "category":"Autos & Motor Vehicles",
            "subcategory":"Auto Supplies",
            "type":"Retail Goods"
        }
    ],
    "sg:phone":"+1 715 672 5869",
    "sg:postcode":"54736",
    "sg:province":"WI",
    "sg:tags":[
        "tire"
    ],
    "wof:name":"Weisenbeck Tire Svc",
    "wof:placetype":"venue"
},
  "geometry": {"coordinates":[-91.933376,44.531582],"type":"Point"}
}