{
  "type": "Feature",
  "properties": {
    "iso:country":"US",
    "sg:address":"410 W Doege St",
    "sg:city":"Marshfield",
    "sg:classifiers":[
        {
            "category":"Travel",
            "subcategory":"Bed & Breakfast",
            "type":"Entertainment"
        }
    ],
    "sg:phone":"+1 715 387 3629",
    "sg:postcode":"54449",
    "sg:province":"WI",
    "sg:tags":[
        "house"
    ],
    "wof:name":"Cat Nap Corner Rooming House",
    "wof:placetype":"venue"
},
  "geometry": {"coordinates":[-90.175752,44.673254],"type":"Point"}
}