{
  "type": "Feature",
  "properties": {
    "iso:country":"US",
    "sg:address":"2623 7th Ave",
    "sg:city":"Chetek",
    "sg:classifiers":[
        {
            "category":"Travel",
            "subcategory":"Hotels & Motels",
            "type":"Entertainment"
        }
    ],
    "sg:phone":"+1 715 924 4674",
    "sg:postcode":"54728",
    "sg:province":"WI",
    "sg:tags":[
        "operation"
    ],
    "wof:name":"Watersmeet Resort",
    "wof:placetype":"venue"
},
  "geometry": {"coordinates":[-91.618508,45.307204],"type":"Point"}
}