{
  "type": "Feature",
  "properties": {
    "iso:country":"US",
    "sg:address":"3534 Timber Ln",
    "sg:city":"Cross Plains",
    "sg:classifiers":[
        {
            "category":"Real Estate",
            "subcategory":"Real Estate Agent",
            "type":"Services"
        }
    ],
    "sg:phone":"+1 608 798 1109",
    "sg:postcode":"53528",
    "sg:province":"WI",
    "wof:name":"Td Rentals",
    "wof:placetype":"venue"
},
  "geometry": {"coordinates":[-89.601039,43.047433],"type":"Point"}
}