{
  "type": "Feature",
  "properties": {
    "addr:full":"11823 Ready Hollow Rd Bagley WI 53801",
    "addr:housenumber":"11823",
    "addr:postcode":"53801",
    "addr:street":"Ready Hollow Rd",
    "iso:country":"US",
    "sg:address":"11823 Ready Hollow Rd",
    "sg:city":"Bagley",
    "sg:classifiers":[
        {
            "category":"Organizations",
            "subcategory":"Religious Organization",
            "type":"Services"
        }
    ],
    "sg:phone":"+1 608 996 2672",
    "sg:postcode":"53801",
    "sg:province":"WI",
    "sg:tags":[
        "church"
    ],
    "wof:name":"Zion Lutheran Church",
    "wof:placetype":"venue"
},
  "geometry": {"coordinates":[-91.098189,42.929378],"type":"Point"}
}