{
  "type": "Feature",
  "properties": {
    "addr:full":"8052 Co Rd F Arpin WI 54410",
    "addr:housenumber":"8052",
    "addr:postcode":"54410",
    "addr:street":"Co Rd",
    "iso:country":"US",
    "sg:address":"8052 Co Rd F",
    "sg:city":"Arpin",
    "sg:classifiers":[
        {
            "category":"Farming",
            "subcategory":"Dairy Farm",
            "type":"Manufacturing & Wholesale Goods"
        }
    ],
    "sg:phone":"+1 715 569 4177",
    "sg:postcode":"54410",
    "sg:province":"WI",
    "wof:name":"Ronald Lobner",
    "wof:placetype":"venue"
},
  "geometry": {"coordinates":[-89.92550300000001,44.53145],"type":"Point"}
}