{
  "type": "Feature",
  "properties": {
    "iso:country":"US",
    "sg:address":"3918 Hollow Rd",
    "sg:city":"New London",
    "sg:classifiers":[
        {
            "category":"Government",
            "subcategory":"Office",
            "type":"Public Place"
        }
    ],
    "sg:phone":"+1 920 982 0270",
    "sg:postcode":"54961",
    "sg:province":"WI",
    "sg:tags":[
        "executive"
    ],
    "wof:name":"Town of Liberty",
    "wof:placetype":"venue"
},
  "geometry": {"coordinates":[-88.65557200000001,44.385321],"type":"Point"}
}