{
  "type": "Feature",
  "properties": {
    "addr:full":"30 S Franklin St Madison WI 53703",
    "addr:housenumber":"30",
    "addr:postcode":"53703",
    "addr:street":"S Franklin St",
    "iso:country":"US",
    "sg:address":"30 S Franklin St",
    "sg:city":"Madison",
    "sg:classifiers":[
        {
            "category":"Social Services",
            "type":"Services"
        }
    ],
    "sg:phone":"+1 608 256 2358",
    "sg:postcode":"53703",
    "sg:province":"WI",
    "sg:tags":[
        "organization",
        "welfare"
    ],
    "wof:name":"Catholic Charities Inc",
    "wof:placetype":"venue"
},
  "geometry": {"coordinates":[-89.378803,43.077244],"type":"Point"}
}