{
  "type": "Feature",
  "properties": {
    "iso:country":"US",
    "sg:address":"7817 Mineral Point Rd",
    "sg:city":"Madison",
    "sg:classifiers":[
        {
            "category":"Professional",
            "subcategory":"Employment Agencies",
            "type":"Services"
        }
    ],
    "sg:phone":"+1 608 833 5101",
    "sg:postcode":"53717",
    "sg:province":"WI",
    "sg:tags":[
        "help",
        "supply"
    ],
    "wof:name":"Skil Tech Inc",
    "wof:placetype":"venue"
},
  "geometry": {"coordinates":[-89.519706,43.060578],"type":"Point"}
}