{
  "type": "Feature",
  "properties": {
    "iso:country":"US",
    "sg:address":"520 Evergreen Rd",
    "sg:city":"Wausau",
    "sg:classifiers":[
        {
            "category":"Building & Trades",
            "subcategory":"Construction",
            "type":"Services"
        }
    ],
    "sg:phone":"+1 715 675 4000",
    "sg:postcode":"54403",
    "sg:province":"WI",
    "sg:tags":[
        "concrete",
        "foundation",
        "contractor"
    ],
    "wof:name":"Advanced Concrete Foundations",
    "wof:placetype":"venue"
},
  "geometry": {"coordinates":[-89.62111899999999,45.002765],"type":"Point"}
}