{
  "type": "Feature",
  "properties": {
    "iso:country":"US",
    "sg:address":"2639 N Downer Ave",
    "sg:city":"Milwaukee",
    "sg:classifiers":[
        {
            "category":"Professional",
            "type":"Services"
        }
    ],
    "sg:phone":"+1 414 332 0770",
    "sg:postcode":"53211",
    "sg:province":"WI",
    "sg:tags":[
        "writer"
    ],
    "wof:name":"Mullins & Associates",
    "wof:placetype":"venue"
},
  "geometry": {"coordinates":[-87.87814299999999,43.066846],"type":"Point"}
}