{
  "type": "Feature",
  "properties": {
    "iso:country":"US",
    "sg:address":"1332 10th St",
    "sg:city":"Barron",
    "sg:classifiers":[
        {
            "category":"Farming",
            "subcategory":"Dairy Farm",
            "type":"Manufacturing & Wholesale Goods"
        }
    ],
    "sg:phone":"+1 715 357 3074",
    "sg:postcode":"54812",
    "sg:province":"WI",
    "wof:name":"Russell Hammann",
    "wof:placetype":"venue"
},
  "geometry": {"coordinates":[-91.95127,45.401131],"type":"Point"}
}