{
  "type": "Feature",
  "properties": {
    "iso:country":"US",
    "sg:address":"4258 State Hwy 13",
    "sg:city":"Medford",
    "sg:classifiers":[
        {
            "category":"Building & Trades",
            "subcategory":"Plumbing",
            "type":"Services"
        }
    ],
    "sg:phone":"+1 715 748 9990",
    "sg:postcode":"54451",
    "sg:province":"WI",
    "sg:tags":[
        "septic"
    ],
    "wof:name":"Super Bee Septic",
    "wof:placetype":"venue"
},
  "geometry": {"coordinates":[-90.332978,45.191727],"type":"Point"}
}