{
  "type": "Feature",
  "properties": {
    "iso:country":"US",
    "sg:address":"18661 52nd Ave",
    "sg:city":"Chippewa Falls",
    "sg:classifiers":[
        {
            "category":"Professional",
            "type":"Services"
        }
    ],
    "sg:phone":"+1 715 839 5830",
    "sg:postcode":"54729",
    "sg:province":"WI",
    "wof:name":"Cathie Mercier",
    "wof:placetype":"venue"
},
  "geometry": {"coordinates":[-91.293989,44.917177],"type":"Point"}
}