{
  "type": "Feature",
  "properties": {
    "iso:country":"US",
    "sg:address":"2526 N 38th St",
    "sg:city":"Milwaukee",
    "sg:classifiers":[
        {
            "category":"Personal",
            "subcategory":"Beauty Salon",
            "type":"Services"
        }
    ],
    "sg:phone":"+1 414 445 6595",
    "sg:postcode":"53210",
    "sg:province":"WI",
    "wof:name":"Steven's Hair & Body",
    "wof:placetype":"venue"
},
  "geometry": {"coordinates":[-87.960956,43.065585],"type":"Point"}
}