{
  "type": "Feature",
  "properties": {
    "iso:country":"US",
    "sg:address":"1879 Horseshoe Ln",
    "sg:city":"De Pere",
    "sg:classifiers":[
        {
            "category":"Professional",
            "subcategory":"Computer Services",
            "type":"Services"
        }
    ],
    "sg:phone":"+1 920 983 0588",
    "sg:postcode":"54115",
    "sg:province":"WI",
    "sg:tags":[
        "related"
    ],
    "wof:name":"Warren Mutsch",
    "wof:placetype":"venue"
},
  "geometry": {"coordinates":[-88.040976,44.431524],"type":"Point"}
}