{
  "type": "Feature",
  "properties": {
    "addr:full":"2301 N 28th St Sheboygan WI 53083",
    "addr:housenumber":"2301",
    "addr:postcode":"53083",
    "addr:street":"N 28Th St",
    "iso:country":"US",
    "sg:address":"2301 N 28th St",
    "sg:city":"Sheboygan",
    "sg:classifiers":[
        {
            "category":"Real Estate",
            "subcategory":"Real Estate Agent",
            "type":"Services"
        }
    ],
    "sg:phone":"+1 920 458 8202",
    "sg:postcode":"53083",
    "sg:province":"WI",
    "wof:name":"Dick Warden Realty",
    "wof:placetype":"venue"
},
  "geometry": {"coordinates":[-87.74318100000001,43.771535],"type":"Point"}
}