{
  "type": "Feature",
  "properties": {
    "iso:country":"US",
    "sg:address":"220 51st Pl",
    "sg:city":"Kenosha",
    "sg:classifiers":[
        {
            "category":"Museum",
            "type":"Entertainment"
        }
    ],
    "sg:phone":"+1 262 654 5770",
    "sg:postcode":"53140",
    "sg:province":"WI",
    "sg:website":"www.kenoshahistorycenter.org",
    "wof:name":"Kenosha County Historical Soc",
    "wof:placetype":"venue"
},
  "geometry": {"coordinates":[-87.81475500000001,42.58897],"type":"Point"}
}