{
  "type": "Feature",
  "properties": {
    "iso:country":"US",
    "sg:address":"1806 State Road 83",
    "sg:city":"Hartland",
    "sg:classifiers":[
        {
            "category":"Manufacturing",
            "subcategory":"Buildings",
            "type":"Manufacturing & Wholesale Goods"
        },
        {
            "category":"Building & Trades",
            "subcategory":"Construction",
            "type":"Services"
        }
    ],
    "sg:phone":"+1 262 367 0131",
    "sg:postcode":"53029",
    "sg:province":"WI",
    "sg:tags":[
        "management",
        "consultant",
        "builder",
        "carpenter",
        "contractor",
        "home"
    ],
    "sg:website":"http://www.jeffhorwath.com",
    "wof:name":"Jeff Horwath Family Builders",
    "wof:placetype":"venue"
},
  "geometry": {"coordinates":[-88.36520899999999,43.071959],"type":"Point"}
}