{
  "type": "Feature",
  "properties": {
    "iso:country":"US",
    "sg:address":"4330 Golf Ter",
    "sg:city":"Eau Claire",
    "sg:classifiers":[
        {
            "category":"Real Estate",
            "subcategory":"Real Estate Agent",
            "type":"Services"
        }
    ],
    "sg:phone":"+1 715 597 0012",
    "sg:postcode":"54701",
    "sg:province":"WI",
    "sg:website":"www.americanrealitygroup.com",
    "wof:name":"American Realty Group LLC",
    "wof:placetype":"venue"
},
  "geometry": {"coordinates":[-91.45791699999999,44.771345],"type":"Point"}
}