{
  "type": "Feature",
  "properties": {
    "iso:country":"US",
    "sg:address":"560 W Rolling Meadows Dr",
    "sg:city":"Fond Du Lac",
    "sg:classifiers":[
        {
            "category":"Sports & Exercise",
            "subcategory":"Golf",
            "type":"Entertainment"
        }
    ],
    "sg:phone":"+1 920 929 3735",
    "sg:postcode":"54937",
    "sg:province":"WI",
    "sg:tags":[
        "course"
    ],
    "wof:name":"Rolling Meadows Golf Course",
    "wof:placetype":"venue"
},
  "geometry": {"coordinates":[-88.474614,43.753471],"type":"Point"}
}