{
  "type": "Feature",
  "properties": {
    "addr:full":"14085 Co Rd Vv Ridgeland WI 54763",
    "addr:housenumber":"14085",
    "addr:postcode":"54763",
    "addr:street":"Co Rd",
    "iso:country":"US",
    "sg:address":"14085 Co Rd Vv",
    "sg:city":"Ridgeland",
    "sg:classifiers":[
        {
            "category":"Organizations",
            "subcategory":"Religious Organization",
            "type":"Services"
        }
    ],
    "sg:phone":"+1 715 949 1407",
    "sg:postcode":"54763",
    "sg:province":"WI",
    "sg:tags":[
        "church"
    ],
    "wof:name":"Hay River KKSG",
    "wof:placetype":"venue"
},
  "geometry": {"coordinates":[-91.930384,45.187581],"type":"Point"}
}