{
  "type": "Feature",
  "properties": {
    "iso:country":"US",
    "sg:address":"2203 de Koven Ave",
    "sg:city":"Racine",
    "sg:classifiers":[
        {
            "category":"Bars & Pubs",
            "type":"Food & Drink"
        }
    ],
    "sg:phone":"+1 262 633 1357",
    "sg:postcode":"53403",
    "sg:province":"WI",
    "sg:tags":[
        "drinking"
    ],
    "wof:name":"Russ's Tap",
    "wof:placetype":"venue"
},
  "geometry": {"coordinates":[-87.806286,42.707465],"type":"Point"}
}