{
  "type": "Feature",
  "properties": {
    "iso:country":"US",
    "sg:address":"3665 Oak Hill St",
    "sg:city":"Delavan",
    "sg:phone":"+1 262 882 2381",
    "sg:postcode":"53115",
    "sg:province":"WI",
    "sg:tags":[
        "oil"
    ],
    "wof:name":"Downing Oil Co",
    "wof:placetype":"venue"
},
  "geometry": {"coordinates":[-88.69749,42.621127],"type":"Point"}
}