{
  "type": "Feature",
  "properties": {
    "addr:full":"2243 Merganser Ct Green Bay WI 54313",
    "addr:housenumber":"2243",
    "addr:postcode":"54313",
    "addr:street":"Merganser Ct",
    "iso:country":"US",
    "sg:address":"2243 Merganser Ct",
    "sg:city":"Green Bay",
    "sg:classifiers":[
        {
            "category":"Building & Trades",
            "subcategory":"Construction",
            "type":"Services"
        }
    ],
    "sg:phone":"+1 920 434 4897",
    "sg:postcode":"54313",
    "sg:province":"WI",
    "sg:tags":[
        "masonry",
        "contractor"
    ],
    "wof:name":"Mc Quillan Masonry",
    "wof:placetype":"venue"
},
  "geometry": {"coordinates":[-88.07128400000001,44.625487],"type":"Point"}
}