{
  "type": "Feature",
  "properties": {
    "addr:full":"8982 Scenic Dr Cascade WI 53011",
    "addr:housenumber":"8982",
    "addr:postcode":"53011",
    "addr:street":"Scenic Dr Cascade",
    "iso:country":"US",
    "sg:address":"8982 Scenic Dr",
    "sg:city":"Cascade",
    "sg:classifiers":[
        {
            "category":"Farming",
            "subcategory":"Farm",
            "type":"Manufacturing & Wholesale Goods"
        }
    ],
    "sg:phone":"+1 920 528 7081",
    "sg:postcode":"53011",
    "sg:province":"WI",
    "sg:tags":[
        "crop",
        "general"
    ],
    "wof:name":"True Grit Acres",
    "wof:placetype":"venue"
},
  "geometry": {"coordinates":[-88.14410100000001,43.688715],"type":"Point"}
}