{
  "type": "Feature",
  "properties": {
    "iso:country":"US",
    "sg:address":"405 High St",
    "sg:city":"Racine",
    "sg:classifiers":[
        {
            "category":"Personal",
            "subcategory":"Beauty Salon",
            "type":"Services"
        }
    ],
    "sg:phone":"+1 262 638 8444",
    "sg:postcode":"53402",
    "sg:province":"WI",
    "sg:tags":[
        "shop"
    ],
    "wof:name":"Linda's Hair Extraordinair",
    "wof:placetype":"venue"
},
  "geometry": {"coordinates":[-87.785935,42.742273],"type":"Point"}
}