{
  "type": "Feature",
  "properties": {
    "iso:country":"US",
    "sg:address":"1870 Sheridan Rd",
    "sg:city":"Kenosha",
    "sg:classifiers":[
        {
            "category":"Professional",
            "type":"Services"
        }
    ],
    "sg:phone":"+1 262 551 7663",
    "sg:postcode":"53140",
    "sg:province":"WI",
    "sg:tags":[
        "establishment"
    ],
    "wof:name":"Alford's Park Mobile Hm Court",
    "wof:placetype":"venue"
},
  "geometry": {"coordinates":[-87.825308,42.624464],"type":"Point"}
}