{
  "type": "Feature",
  "properties": {
    "iso:country":"US",
    "sg:address":"623 Brakke Dr",
    "sg:city":"Hudson",
    "sg:classifiers":[
        {
            "category":"Wholesale",
            "subcategory":"Electrical",
            "type":"Manufacturing & Wholesale Goods"
        }
    ],
    "sg:phone":"+1 715 381 2971",
    "sg:postcode":"54016",
    "sg:province":"WI",
    "sg:tags":[
        "lighting",
        "fixture"
    ],
    "sg:website":"www.paragonlighting.com",
    "wof:name":"Paragon Technologies",
    "wof:placetype":"venue"
},
  "geometry": {"coordinates":[-92.67022,44.968379],"type":"Point"}
}