{
  "type": "Feature",
  "properties": {
    "addr:full":"18901 W Pinecrest Ln New Berlin WI 53146",
    "addr:housenumber":"18901",
    "addr:postcode":"53146",
    "addr:street":"W Pinecrest Ln",
    "iso:country":"US",
    "sg:address":"18901 W Pinecrest Ln",
    "sg:city":"New Berlin",
    "sg:classifiers":[
        {
            "category":"Social Services",
            "type":"Services"
        }
    ],
    "sg:phone":"+1 262 780 0880",
    "sg:postcode":"53146",
    "sg:province":"WI",
    "wof:name":"Access Care Services LLC",
    "wof:placetype":"venue"
},
  "geometry": {"coordinates":[-88.14908,43.015575],"type":"Point"}
}