{
  "type": "Feature",
  "properties": {
    "iso:country":"US",
    "sg:address":"1515 W Paradise Dr",
    "sg:city":"West Bend",
    "sg:classifiers":[
        {
            "category":"Bakery",
            "type":"Food & Drink"
        }
    ],
    "sg:menulink":"http://www.allmenus.com/wi/west-bend/220354-auntie-annes-pretzels/menu/",
    "sg:phone":"+1 262 334 9430",
    "sg:postcode":"53095",
    "sg:province":"WI",
    "sg:tags":[
        "american",
        "pastry"
    ],
    "wof:name":"Auntie Anne's Pretzels",
    "wof:placetype":"venue"
},
  "geometry": {"coordinates":[-88.186435,43.397677],"type":"Point"}
}