{
  "type": "Feature",
  "properties": {
    "iso:country":"US",
    "sg:address":"227 E South Railroad St",
    "sg:city":"Kendall",
    "sg:classifiers":[
        {
            "category":"Travel",
            "subcategory":"Hotels & Motels",
            "type":"Entertainment"
        }
    ],
    "sg:phone":"+1 608 463 7135",
    "sg:postcode":"54638",
    "sg:province":"WI",
    "wof:name":"Country Livin' Motel",
    "wof:placetype":"venue"
},
  "geometry": {"coordinates":[-90.364343,43.790416],"type":"Point"}
}