{
  "type": "Feature",
  "properties": {
    "iso:country":"US",
    "sg:address":"915 Katherine Dr",
    "sg:city":"Elm Grove",
    "sg:classifiers":[
        {
            "category":"Banks & Credit Unions",
            "subcategory":"Investment Brokerage",
            "type":"Services"
        }
    ],
    "sg:phone":"+1 262 786 7467",
    "sg:postcode":"53122",
    "sg:province":"WI",
    "sg:tags":[
        "advisory",
        "consulting",
        "management"
    ],
    "wof:name":"Heartland Management Corp",
    "wof:placetype":"venue"
},
  "geometry": {"coordinates":[-88.082088,43.042018],"type":"Point"}
}