{
  "type": "Feature",
  "properties": {
    "iso:country":"US",
    "sg:address":"407 State Hwy 82",
    "sg:city":"Mauston",
    "sg:classifiers":[
        {
            "category":"Retail",
            "subcategory":"Auto Repair",
            "type":"Services"
        }
    ],
    "sg:phone":"+1 608 847 3450",
    "sg:postcode":"53948",
    "sg:province":"WI",
    "sg:tags":[
        "automobile",
        "lubrication",
        "automotive"
    ],
    "wof:name":"Null's Quik Lube",
    "wof:placetype":"venue"
},
  "geometry": {"coordinates":[-90.077034,43.793443],"type":"Point"}
}