{
  "type": "Feature",
  "properties": {
    "iso:country":"US",
    "sg:address":"7904 Washington Ave",
    "sg:city":"Racine",
    "sg:classifiers":[
        {
            "category":"Autos & Motor Vehicles",
            "subcategory":"Automobile Sales",
            "type":"Retail Goods"
        }
    ],
    "sg:phone":"+1 262 886 4565",
    "sg:postcode":"53406",
    "sg:province":"WI",
    "sg:tags":[
        "car",
        "dealer"
    ],
    "wof:name":"Mc Farland Auto Sales",
    "wof:placetype":"venue"
},
  "geometry": {"coordinates":[-87.882342,42.719292],"type":"Point"}
}