{
  "type": "Feature",
  "properties": {
    "iso:country":"US",
    "sg:address":"8933 E 29th St",
    "sg:city":"Marshfield",
    "sg:classifiers":[
        {
            "category":"Recreation",
            "subcategory":"Amusement Park",
            "type":"Entertainment"
        }
    ],
    "sg:phone":"+1 715 591 2116",
    "sg:postcode":"54449",
    "sg:province":"WI",
    "wof:name":"T R Amusements LLC",
    "wof:placetype":"venue"
},
  "geometry": {"coordinates":[-90.159975,44.641107],"type":"Point"}
}