{
  "type": "Feature",
  "properties": {
    "iso:country":"US",
    "sg:address":"3215 N Percival St",
    "sg:city":"Hazel Green",
    "sg:classifiers":[
        {
            "category":"Retail",
            "subcategory":"Veterinary Services",
            "type":"Services"
        }
    ],
    "sg:phone":"+1 608 854 2283",
    "sg:postcode":"53811",
    "sg:province":"WI",
    "sg:tags":[
        "veterinarian"
    ],
    "wof:name":"Veterinary Associates",
    "wof:placetype":"venue"
},
  "geometry": {"coordinates":[-90.437696,42.541514],"type":"Point"}
}