{
  "type": "Feature",
  "properties": {
    "iso:country":"US",
    "sg:address":"632 E Main St",
    "sg:city":"Plymouth",
    "sg:classifiers":[
        {
            "category":"Travel",
            "subcategory":"Hotels & Motels",
            "type":"Entertainment"
        }
    ],
    "sg:phone":"+1 920 892 8566",
    "sg:postcode":"53073",
    "sg:province":"WI",
    "sg:tags":[
        "operation"
    ],
    "wof:name":"Bl Nutt Inn",
    "wof:placetype":"venue"
},
  "geometry": {"coordinates":[-87.972565,43.748798],"type":"Point"}
}