{
  "type": "Feature",
  "properties": {
    "addr:full":"5211 Von Kanel St Schofield WI 54476",
    "addr:housenumber":"5211",
    "addr:postcode":"54476",
    "addr:street":"Von Kanel St",
    "iso:country":"US",
    "sg:address":"5211 Von Kanel St",
    "sg:city":"Schofield",
    "sg:classifiers":[
        {
            "category":"Home & Garden",
            "subcategory":"Home Furnishings",
            "type":"Retail Goods"
        }
    ],
    "sg:phone":"+1 715 355 0772",
    "sg:postcode":"54476",
    "sg:province":"WI",
    "wof:name":"Accent Window Fashions",
    "wof:placetype":"venue"
},
  "geometry": {"coordinates":[-89.562011,44.9103],"type":"Point"}
}