{
  "type": "Feature",
  "properties": {
    "iso:country":"US",
    "sg:address":"4631 Milltown Rd",
    "sg:city":"Green Bay",
    "sg:classifiers":[
        {
            "category":"Manufacturing",
            "subcategory":"Printing",
            "type":"Manufacturing & Wholesale Goods"
        }
    ],
    "sg:phone":"+1 920 865 1350",
    "sg:postcode":"54313",
    "sg:province":"WI",
    "sg:tags":[
        "printer"
    ],
    "wof:name":"Absolute Printing Solutions",
    "wof:placetype":"venue"
},
  "geometry": {"coordinates":[-88.16412800000001,44.574337],"type":"Point"}
}