{
  "type": "Feature",
  "properties": {
    "addr:full":"528 Washington St Sheboygan Falls WI 53085",
    "addr:housenumber":"528",
    "addr:postcode":"53085",
    "addr:street":"Washington St",
    "iso:country":"US",
    "sg:address":"528 Washington St",
    "sg:city":"Sheboygan Falls",
    "sg:classifiers":[
        {
            "category":"Organizations",
            "subcategory":"Community Association",
            "type":"Services"
        }
    ],
    "sg:phone":"+1 920 467 8551",
    "sg:postcode":"53085",
    "sg:province":"WI",
    "wof:name":"Knights of Columbus",
    "wof:placetype":"venue"
},
  "geometry": {"coordinates":[-87.809325,43.731647],"type":"Point"}
}