{
  "type": "Feature",
  "properties": {
    "iso:country":"US",
    "sg:address":"536 Saxony Ct",
    "sg:city":"Hartland",
    "sg:classifiers":[
        {
            "category":"Professional",
            "subcategory":"Management & Consulting",
            "type":"Services"
        }
    ],
    "sg:phone":"+1 414 803 4626",
    "sg:postcode":"53029",
    "sg:province":"WI",
    "wof:name":"DCL Financial Consulting Inc",
    "wof:placetype":"venue"
},
  "geometry": {"coordinates":[-88.337288,43.090434],"type":"Point"}
}