{
  "type": "Feature",
  "properties": {
    "iso:country":"US",
    "sg:address":"820 S Main St",
    "sg:city":"West Bend",
    "sg:classifiers":[
        {
            "category":"Shopping",
            "subcategory":"Shoes",
            "type":"Retail Goods"
        }
    ],
    "sg:phone":"+1 262 306 8681",
    "sg:postcode":"53095",
    "sg:province":"WI",
    "wof:name":"Brown's Shoe Fit Co",
    "wof:placetype":"venue"
},
  "geometry": {"coordinates":[-88.181116,43.411558],"type":"Point"}
}