{
  "type": "Feature",
  "properties": {
    "addr:full":"6116 Leeward Ln Racine WI 53402",
    "addr:housenumber":"6116",
    "addr:postcode":"53402",
    "addr:street":"Leeward Ln",
    "iso:country":"US",
    "sg:address":"6116 Leeward Ln",
    "sg:city":"Racine",
    "sg:classifiers":[
        {
            "category":"Manufacturing",
            "subcategory":"Chemicals & Compounds",
            "type":"Manufacturing & Wholesale Goods"
        }
    ],
    "sg:phone":"+1 262 681 2829",
    "sg:postcode":"53402",
    "sg:province":"WI",
    "sg:tags":[
        "active",
        "surface",
        "agent",
        "mfg"
    ],
    "wof:name":"Titetaniun",
    "wof:placetype":"venue"
},
  "geometry": {"coordinates":[-87.854241,42.780119],"type":"Point"}
}