{
  "type": "Feature",
  "properties": {
    "iso:country":"US",
    "sg:address":"128 Slazing Rd",
    "sg:city":"Potosi",
    "sg:classifiers":[
        {
            "category":"Professional",
            "type":"Services"
        }
    ],
    "sg:phone":"+1 608 763 2693",
    "sg:postcode":"53820",
    "sg:province":"WI",
    "wof:name":"Hawes Tower Service LLC",
    "wof:placetype":"venue"
},
  "geometry": {"coordinates":[-90.70159,42.68215],"type":"Point"}
}