{
  "type": "Feature",
  "properties": {
    "iso:country":"US",
    "sg:address":"1134 E Sylvan Ave",
    "sg:city":"Milwaukee",
    "sg:classifiers":[
        {
            "category":"Real Estate",
            "subcategory":"Real Estate Agent",
            "type":"Services"
        }
    ],
    "sg:phone":"+1 414 962 6992",
    "sg:postcode":"53217",
    "sg:province":"WI",
    "wof:name":"Farwell Cramer LLC",
    "wof:placetype":"venue"
},
  "geometry": {"coordinates":[-87.89545099999999,43.112206],"type":"Point"}
}