{
  "type": "Feature",
  "properties": {
    "addr:full":"2763 Main St East Troy WI 53120",
    "addr:housenumber":"2763",
    "addr:postcode":"53120",
    "addr:street":"Main St",
    "iso:country":"US",
    "sg:address":"2763 Main St",
    "sg:city":"East Troy",
    "sg:classifiers":[
        {
            "category":"Home & Garden",
            "subcategory":"Carpets & Floor Coverings",
            "type":"Retail Goods"
        }
    ],
    "sg:phone":"+1 262 642 2866",
    "sg:postcode":"53120",
    "sg:province":"WI",
    "sg:tags":[
        "dealer",
        "rug"
    ],
    "wof:name":"Mr G's Go Floor It",
    "wof:placetype":"venue"
},
  "geometry": {"coordinates":[-88.40048899999999,42.787452],"type":"Point"}
}