{
  "type": "Feature",
  "properties": {
    "iso:country":"US",
    "sg:address":"521 Trillium Ln",
    "sg:city":"Hudson",
    "sg:classifiers":[
        {
            "category":"Professional",
            "subcategory":"Management & Consulting",
            "type":"Services"
        }
    ],
    "sg:phone":"+1 715 381 0154",
    "sg:postcode":"54016",
    "sg:province":"WI",
    "wof:name":"R&R Knapp LLC",
    "wof:placetype":"venue"
},
  "geometry": {"coordinates":[-92.667905,44.938858],"type":"Point"}
}