{
  "type": "Feature",
  "properties": {
    "iso:country":"US",
    "sg:address":"7761 Summerfield Dr",
    "sg:city":"Verona",
    "sg:classifiers":[
        {
            "category":"Professional",
            "subcategory":"Management & Consulting",
            "type":"Services"
        }
    ],
    "sg:phone":"+1 608 828 9547",
    "sg:postcode":"53593",
    "sg:province":"WI",
    "wof:name":"Rjvb LLC",
    "wof:placetype":"venue"
},
  "geometry": {"coordinates":[-89.58658800000001,43.073871],"type":"Point"}
}