{
  "type": "Feature",
  "properties": {
    "iso:country":"US",
    "sg:address":"400 W State St",
    "sg:city":"Westby",
    "sg:classifiers":[
        {
            "category":"Professional",
            "subcategory":"Detective & Security Services",
            "type":"Services"
        }
    ],
    "sg:phone":"+1 608 377 0247",
    "sg:postcode":"54667",
    "sg:province":"WI",
    "wof:name":"Midwest Investigations",
    "wof:placetype":"venue"
},
  "geometry": {"coordinates":[-90.861616,43.653538],"type":"Point"}
}