{
  "type": "Feature",
  "properties": {
    "iso:country":"US",
    "sg:address":"3405 Commerce Ct",
    "sg:city":"Appleton",
    "sg:classifiers":[
        {
            "category":"Insurance",
            "subcategory":"Insurance Agent",
            "type":"Services"
        }
    ],
    "sg:phone":"+1 920 731 6234",
    "sg:postcode":"54911",
    "sg:province":"WI",
    "wof:name":"Gary Wynveen & Assoc",
    "wof:placetype":"venue"
},
  "geometry": {"coordinates":[-88.376228,44.296606],"type":"Point"}
}