{
  "type": "Feature",
  "properties": {
    "iso:country":"US",
    "sg:address":"2323 Bluemound Rd",
    "sg:city":"Waukesha",
    "sg:classifiers":[
        {
            "category":"Wholesale",
            "subcategory":"Durable Goods & Equipment",
            "type":"Manufacturing & Wholesale Goods"
        }
    ],
    "sg:phone":"+1 262 798 8900",
    "sg:postcode":"53186",
    "sg:province":"WI",
    "sg:tags":[
        "representative",
        "manufacturer"
    ],
    "wof:name":"K R Schaetz & Assoc",
    "wof:placetype":"venue"
},
  "geometry": {"coordinates":[-88.18156500000001,43.036227],"type":"Point"}
}