{
  "type": "Feature",
  "properties": {
    "iso:country":"US",
    "sg:address":"111 E Wisconsin Ave",
    "sg:city":"Milwaukee",
    "sg:classifiers":[
        {
            "category":"Banks & Credit Unions",
            "subcategory":"Bank",
            "type":"Services"
        }
    ],
    "sg:phone":"+1 414 765 2186",
    "sg:postcode":"53202",
    "sg:province":"WI",
    "sg:tags":[
        "national",
        "commercial"
    ],
    "wof:name":"Cbrei Banc 1 Portfolio",
    "wof:placetype":"venue"
},
  "geometry": {"coordinates":[-87.909159,43.038495],"type":"Point"}
}