{
  "type": "Feature",
  "properties": {
    "iso:country":"US",
    "sg:address":"9538 E 16 Frontage Rd",
    "sg:city":"Onalaska",
    "sg:classifiers":[
        {
            "category":"Professional",
            "subcategory":"Business Services",
            "type":"Services"
        }
    ],
    "sg:phone":"+1 608 782 4030",
    "sg:postcode":"54650",
    "sg:province":"WI",
    "sg:tags":[
        "credit",
        "debt",
        "consultant"
    ],
    "wof:name":"American Debt Co LLC",
    "wof:placetype":"venue"
},
  "geometry": {"coordinates":[-91.17183,43.883517],"type":"Point"}
}