{
  "type": "Feature",
  "properties": {
    "iso:country":"US",
    "sg:address":"1621 Rockvale Rd",
    "sg:city":"Ixonia",
    "sg:classifiers":[
        {
            "category":"Wholesale",
            "subcategory":"Petroleum",
            "type":"Manufacturing & Wholesale Goods"
        }
    ],
    "sg:phone":"+1 262 567 9538",
    "sg:postcode":"53036",
    "sg:province":"WI",
    "sg:tags":[
        "pipe",
        "line",
        "company"
    ],
    "wof:name":"Guardian Pipeline",
    "wof:placetype":"venue"
},
  "geometry": {"coordinates":[-88.610817,43.127237],"type":"Point"}
}