{
  "type": "Feature",
  "properties": {
    "iso:country":"US",
    "sg:address":"498 Co Rd C",
    "sg:city":"De Forest",
    "sg:classifiers":[
        {
            "category":"Food & Beverages",
            "subcategory":"Groceries & Convenience Stores",
            "type":"Retail Goods"
        }
    ],
    "sg:phone":"+1 608 846 4202",
    "sg:postcode":"53532",
    "sg:province":"WI",
    "sg:tags":[
        "grocer"
    ],
    "wof:name":"C B Gilbertson Store",
    "wof:placetype":"venue"
},
  "geometry": {"coordinates":[-89.255376,43.290395],"type":"Point"}
}