{
  "type": "Feature",
  "properties": {
    "iso:country":"US",
    "sg:address":"1419 9th St",
    "sg:city":"Racine",
    "sg:classifiers":[
        {
            "category":"Shopping",
            "type":"Retail Goods"
        }
    ],
    "sg:phone":"+1 262 633 4140",
    "sg:postcode":"53403",
    "sg:province":"WI",
    "sg:tags":[
        "religious"
    ],
    "wof:name":"Victoria Victory's",
    "wof:placetype":"venue"
},
  "geometry": {"coordinates":[-87.797158,42.722593],"type":"Point"}
}