{
  "type": "Feature",
  "properties": {
    "iso:country":"US",
    "sg:address":"728 Booster Blvd",
    "sg:city":"Reedsburg",
    "sg:classifiers":[
        {
            "category":"Manufacturing",
            "subcategory":"Food",
            "type":"Manufacturing & Wholesale Goods"
        }
    ],
    "sg:phone":"+1 608 524 4343",
    "sg:postcode":"53959",
    "sg:province":"WI",
    "sg:tags":[
        "canned",
        "specialty"
    ],
    "wof:name":"Gerber Products Co",
    "wof:placetype":"venue"
},
  "geometry": {"coordinates":[-90.002978,43.526995],"type":"Point"}
}