{
  "type": "Feature",
  "properties": {
    "addr:full":"1022 N 2nd St Watertown WI 53098",
    "addr:housenumber":"1022",
    "addr:postcode":"53098",
    "addr:street":"N 2Nd St",
    "iso:country":"US",
    "sg:address":"1022 N 2nd St",
    "sg:city":"Watertown",
    "sg:classifiers":[
        {
            "category":"Retail",
            "subcategory":"Repair Shop",
            "type":"Services"
        }
    ],
    "sg:phone":"+1 920 261 5672",
    "sg:postcode":"53098",
    "sg:province":"WI",
    "sg:tags":[
        "television",
        "radio"
    ],
    "wof:name":"Stuebe Television & Radio Svc",
    "wof:placetype":"venue"
},
  "geometry": {"coordinates":[-88.721648,43.200962],"type":"Point"}
}