{
  "type": "Feature",
  "properties": {
    "iso:country":"US",
    "sg:address":"1641 Co Rd H",
    "sg:city":"Stanley",
    "sg:classifiers":[
        {
            "category":"Farming",
            "subcategory":"Farm & Veterinary Services",
            "type":"Manufacturing & Wholesale Goods"
        }
    ],
    "sg:phone":"+1 715 644 5364",
    "sg:postcode":"54726",
    "sg:province":"WI",
    "sg:tags":[
        "livestock"
    ],
    "wof:name":"Awe Enterprises",
    "wof:placetype":"venue"
},
  "geometry": {"coordinates":[-90.942301,44.828618],"type":"Point"}
}