{
  "type": "Feature",
  "properties": {
    "iso:country":"US",
    "sg:address":"3266 125th St",
    "sg:city":"Pleasant Prairie",
    "sg:classifiers":[
        {
            "category":"Professional",
            "subcategory":"Business Services",
            "type":"Services"
        }
    ],
    "sg:phone":"+1 262 925 8791",
    "sg:postcode":"53158",
    "sg:province":"WI",
    "wof:name":"Precision Inventory Inc",
    "wof:placetype":"venue"
},
  "geometry": {"coordinates":[-87.846101,42.497267],"type":"Point"}
}