{
  "type": "Feature",
  "properties": {
    "iso:country":"US",
    "sg:address":"2689 S 13th St",
    "sg:city":"Milwaukee",
    "sg:classifiers":[
        {
            "category":"Bars & Pubs",
            "type":"Food & Drink"
        }
    ],
    "sg:phone":"+1 414 383 0978",
    "sg:postcode":"53215",
    "sg:province":"WI",
    "wof:name":"Secret's",
    "wof:placetype":"venue"
},
  "geometry": {"coordinates":[-87.92868,42.996797],"type":"Point"}
}