{
  "type": "Feature",
  "properties": {
    "iso:country":"US",
    "sg:address":"117 Canary Cir",
    "sg:city":"Watertown",
    "sg:classifiers":[
        {
            "category":"Building & Trades",
            "subcategory":"Construction",
            "type":"Services"
        }
    ],
    "sg:phone":"+1 920 206 8858",
    "sg:postcode":"53098",
    "sg:province":"WI",
    "sg:tags":[
        "house"
    ],
    "wof:name":"Tods Home Improvement Inc",
    "wof:placetype":"venue"
},
  "geometry": {"coordinates":[-88.614683,43.203525],"type":"Point"}
}