{
  "type": "Feature",
  "properties": {
    "iso:country":"US",
    "sg:address":"200 S Water St W",
    "sg:city":"Fort Atkinson",
    "sg:classifiers":[
        {
            "category":"Social Services",
            "subcategory":"Adult Care",
            "type":"Services"
        }
    ],
    "sg:phone":"+1 920 563 6959",
    "sg:postcode":"53538",
    "sg:province":"WI",
    "sg:tags":[
        "residential"
    ],
    "wof:name":"Wellington Place Inc",
    "wof:placetype":"venue"
},
  "geometry": {"coordinates":[-88.839476,42.927466],"type":"Point"}
}