{
  "type": "Feature",
  "properties": {
    "addr:full":"1144 N Edison St Milwaukee WI 53202",
    "addr:housenumber":"1144",
    "addr:postcode":"53202",
    "addr:street":"N Edison St",
    "iso:country":"US",
    "sg:address":"1144 N Edison St",
    "sg:city":"Milwaukee",
    "sg:classifiers":[
        {
            "category":"Wholesale",
            "subcategory":"Plants",
            "type":"Manufacturing & Wholesale Goods"
        }
    ],
    "sg:phone":"+1 414 272 2440",
    "sg:postcode":"53202",
    "sg:province":"WI",
    "sg:tags":[
        "florist",
        "supply"
    ],
    "wof:name":"Platz Flowers & Supply Inc",
    "wof:placetype":"venue"
},
  "geometry": {"coordinates":[-87.912307,43.045169],"type":"Point"}
}