{
  "type": "Feature",
  "properties": {
    "iso:country":"US",
    "sg:address":"430 S John Paul Rd",
    "sg:city":"Milton",
    "sg:classifiers":[
        {
            "category":"Home & Garden",
            "subcategory":"Hardware",
            "type":"Retail Goods"
        }
    ],
    "sg:phone":"+1 608 868 2843",
    "sg:postcode":"53563",
    "sg:province":"WI",
    "sg:website":"www.davesace.com",
    "wof:name":"Dave's Milton Ace Hardware",
    "wof:placetype":"venue"
},
  "geometry": {"coordinates":[-88.961504,42.775229],"type":"Point"}
}