{
  "type": "Feature",
  "properties": {
    "iso:country":"US",
    "sg:address":"1440 Lily Ln",
    "sg:city":"Wisconsin Rapids",
    "sg:classifiers":[
        {
            "category":"Organizations",
            "subcategory":"Religious Organization",
            "type":"Services"
        }
    ],
    "sg:phone":"+1 715 421 1424",
    "sg:postcode":"54494",
    "sg:province":"WI",
    "sg:tags":[
        "clergy"
    ],
    "wof:name":"Martin Baur",
    "wof:placetype":"venue"
},
  "geometry": {"coordinates":[-89.808933,44.379129],"type":"Point"}
}