{
  "type": "Feature",
  "properties": {
    "iso:country":"US",
    "sg:address":"147 N State St",
    "sg:city":"Berlin",
    "sg:classifiers":[
        {
            "category":"Health Services",
            "subcategory":"Chiropractor",
            "type":"Services"
        }
    ],
    "sg:phone":"+1 920 361 3515",
    "sg:postcode":"54923",
    "sg:province":"WI",
    "wof:name":"Wepner Chiropractic Office",
    "wof:placetype":"venue"
},
  "geometry": {"coordinates":[-88.943037,43.969715],"type":"Point"}
}