{
  "type": "Feature",
  "properties": {
    "iso:country":"US",
    "sg:address":"5587 Glen Lake Rd",
    "sg:city":"Boulder Junction",
    "sg:classifiers":[
        {
            "category":"Government",
            "subcategory":"Office",
            "type":"Public Place"
        }
    ],
    "sg:phone":"+1 715 385 3269",
    "sg:postcode":"54512",
    "sg:province":"WI",
    "wof:name":"Brandon Clough",
    "wof:placetype":"venue"
},
  "geometry": {"coordinates":[-89.649616,46.115119],"type":"Point"}
}