{
  "type": "Feature",
  "properties": {
    "iso:country":"US",
    "sg:address":"941 Ashwaubenon St",
    "sg:city":"Green Bay",
    "sg:classifiers":[
        {
            "category":"Professional",
            "subcategory":"Business Services",
            "type":"Services"
        },
        {
            "category":"Professional",
            "subcategory":"Management & Consulting",
            "type":"Services"
        }
    ],
    "sg:phone":"+1 920 339 1107",
    "sg:postcode":"54304",
    "sg:province":"WI",
    "sg:tags":[
        "marketing",
        "program"
    ],
    "wof:name":"Metropolitan Management System",
    "wof:placetype":"venue"
},
  "geometry": {"coordinates":[-88.08631099999999,44.462817],"type":"Point"}
}