{
  "type": "Feature",
  "properties": {
    "iso:country":"US",
    "sg:address":"903 Waube Ln",
    "sg:city":"Green Bay",
    "sg:classifiers":[
        {
            "category":"Manufacturing",
            "subcategory":"Printing",
            "type":"Manufacturing & Wholesale Goods"
        }
    ],
    "sg:phone":"+1 920 337 6330",
    "sg:postcode":"54304",
    "sg:province":"WI",
    "sg:tags":[
        "lithographic",
        "commercial"
    ],
    "wof:name":"Insty-Prints",
    "wof:placetype":"venue"
},
  "geometry": {"coordinates":[-88.083763,44.468258],"type":"Point"}
}