{
  "type": "Feature",
  "properties": {
    "iso:country":"US",
    "sg:address":"5523 Integrity Way",
    "sg:city":"Appleton",
    "sg:classifiers":[
        {
            "category":"Real Estate",
            "subcategory":"Architect",
            "type":"Services"
        }
    ],
    "sg:phone":"+1 920 968 0469",
    "sg:postcode":"54913",
    "sg:province":"WI",
    "wof:name":"Larson Meyer Architects",
    "wof:placetype":"venue"
},
  "geometry": {"coordinates":[-88.49311,44.270303],"type":"Point"}
}