{
  "type": "Feature",
  "properties": {
    "iso:country":"US",
    "sg:address":"727 Southgate Dr",
    "sg:city":"Tomahawk",
    "sg:classifiers":[
        {
            "category":"Manufacturing",
            "subcategory":"Metals",
            "type":"Manufacturing & Wholesale Goods"
        }
    ],
    "sg:phone":"+1 715 453 4999",
    "sg:postcode":"54487",
    "sg:province":"WI",
    "sg:tags":[
        "steel",
        "structural"
    ],
    "wof:name":"Daigle Brothers Inc",
    "wof:placetype":"venue"
},
  "geometry": {"coordinates":[-89.72999299999999,45.462185],"type":"Point"}
}