{
  "type": "Feature",
  "properties": {
    "iso:country":"US",
    "sg:address":"365 Cain Creek Rd",
    "sg:city":"Merrill",
    "sg:classifiers":[
        {
            "category":"Organizations",
            "subcategory":"Religious Organization",
            "type":"Services"
        }
    ],
    "sg:phone":"+1 715 536 6011",
    "sg:postcode":"54452",
    "sg:province":"WI",
    "sg:tags":[
        "church"
    ],
    "wof:name":"Calvary Lutheran Church",
    "wof:placetype":"venue"
},
  "geometry": {"coordinates":[-89.507949,45.130402],"type":"Point"}
}