{
  "type": "Feature",
  "properties": {
    "addr:full":"21099 Lakewood Dr Grantsburg WI 54840",
    "addr:housenumber":"21099",
    "addr:postcode":"54840",
    "addr:street":"Lakewood Dr",
    "iso:country":"US",
    "sg:address":"21099 Lakewood Dr",
    "sg:city":"Grantsburg",
    "sg:classifiers":[
        {
            "category":"Retail",
            "subcategory":"Auto Repair",
            "type":"Services"
        }
    ],
    "sg:phone":"+1 715 488 2625",
    "sg:postcode":"54840",
    "sg:province":"WI",
    "sg:tags":[
        "general"
    ],
    "wof:name":"Fine Tuning",
    "wof:placetype":"venue"
},
  "geometry": {"coordinates":[-92.60794199999999,45.674887],"type":"Point"}
}