{
  "type": "Feature",
  "properties": {
    "iso:country":"US",
    "sg:address":"226 Washington St",
    "sg:city":"Menasha",
    "sg:classifiers":[
        {
            "category":"Organizations",
            "subcategory":"Religious Organization",
            "type":"Services"
        }
    ],
    "sg:phone":"+1 920 725 5601",
    "sg:postcode":"54952",
    "sg:province":"WI",
    "sg:tags":[
        "church"
    ],
    "sg:website":"www.stthomaswi.com",
    "wof:name":"Saint Thomas Episcopal Church",
    "wof:placetype":"venue"
},
  "geometry": {"coordinates":[-88.454736,44.19374],"type":"Point"}
}