{
  "type": "Feature",
  "properties": {
    "addr:full":"3409 Crocker Ave Sheboygan WI 53081",
    "addr:housenumber":"3409",
    "addr:postcode":"53081",
    "addr:street":"Crocker Ave",
    "iso:country":"US",
    "sg:address":"3409 Crocker Ave",
    "sg:city":"Sheboygan",
    "sg:classifiers":[
        {
            "category":"Freight",
            "type":"Transportation"
        }
    ],
    "sg:phone":"+1 920 457 9694",
    "sg:postcode":"53081",
    "sg:province":"WI",
    "sg:tags":[
        "courier"
    ],
    "wof:name":"UPS",
    "wof:placetype":"venue"
},
  "geometry": {"coordinates":[-87.756703,43.721343],"type":"Point"}
}