{
  "type": "Feature",
  "properties": {
    "addr:full":"18620 Pleasant St Brookfield WI 53045",
    "addr:housenumber":"18620",
    "addr:postcode":"53045",
    "addr:street":"Pleasant St",
    "iso:country":"US",
    "sg:address":"18620 Pleasant St",
    "sg:city":"Brookfield",
    "sg:classifiers":[
        {
            "category":"Building & Trades",
            "subcategory":"Construction",
            "type":"Services"
        }
    ],
    "sg:phone":"+1 262 797 8209",
    "sg:postcode":"53045",
    "sg:province":"WI",
    "sg:tags":[
        "well",
        "drilling"
    ],
    "wof:name":"Fred Richert Co",
    "wof:placetype":"venue"
},
  "geometry": {"coordinates":[-88.144285,43.073345],"type":"Point"}
}