{
  "type": "Feature",
  "properties": {
    "iso:country":"US",
    "sg:address":"614 Vera Ct",
    "sg:city":"Madison",
    "sg:classifiers":[
        {
            "category":"Government",
            "subcategory":"Office",
            "type":"Public Place"
        }
    ],
    "sg:phone":"+1 608 241 4849",
    "sg:postcode":"53704",
    "sg:province":"WI",
    "wof:name":"Joining Forces For Families",
    "wof:placetype":"venue"
},
  "geometry": {"coordinates":[-89.385243,43.135631],"type":"Point"}
}