{
  "type": "Feature",
  "properties": {
    "iso:country":"US",
    "sg:address":"300 E Walnut St",
    "sg:city":"Green Bay",
    "sg:classifiers":[
        {
            "category":"Government",
            "subcategory":"Police Station",
            "type":"Public Place"
        }
    ],
    "sg:phone":"+1 920 448 4229",
    "sg:postcode":"54301",
    "sg:province":"WI",
    "sg:tags":[
        "sheriff"
    ],
    "wof:name":"Sheriff's Dept-Investigative",
    "wof:placetype":"venue"
},
  "geometry": {"coordinates":[-88.013291,44.513314],"type":"Point"}
}