{
  "type": "Feature",
  "properties": {
    "addr:full":"8579 Hay Creek Rd Willard WI 54493",
    "addr:housenumber":"8579",
    "addr:postcode":"54493",
    "addr:street":"Hay Creek Rd",
    "iso:country":"US",
    "sg:address":"8579 Hay Creek Rd",
    "sg:city":"Willard",
    "sg:classifiers":[
        {
            "category":"Manufacturing",
            "subcategory":"Tools & Machinery",
            "type":"Manufacturing & Wholesale Goods"
        }
    ],
    "sg:phone":"+1 715 267 7284",
    "sg:postcode":"54493",
    "sg:province":"WI",
    "sg:tags":[
        "mfg"
    ],
    "wof:name":"Ellison Machine Tool",
    "wof:placetype":"venue"
},
  "geometry": {"coordinates":[-90.848748,44.731365],"type":"Point"}
}