{
  "type": "Feature",
  "properties": {
    "iso:country":"US",
    "sg:address":"6953 Hyer Rd",
    "sg:city":"Waunakee",
    "sg:classifiers":[
        {
            "category":"Professional",
            "type":"Services"
        }
    ],
    "sg:phone":"+1 608 850 4460",
    "sg:postcode":"53597",
    "sg:province":"WI",
    "sg:tags":[
        "establishment"
    ],
    "wof:name":"Wisconsin Hog Unit",
    "wof:placetype":"venue"
},
  "geometry": {"coordinates":[-89.54627,43.202406],"type":"Point"}
}