{
  "type": "Feature",
  "properties": {
    "iso:country":"US",
    "sg:address":"4049 Jessie Ln",
    "sg:city":"Denmark",
    "sg:classifiers":[
        {
            "category":"Building & Trades",
            "subcategory":"Construction",
            "type":"Services"
        }
    ],
    "sg:phone":"+1 920 863 8457",
    "sg:postcode":"54208",
    "sg:province":"WI",
    "sg:tags":[
        "house"
    ],
    "wof:name":"R D Construction",
    "wof:placetype":"venue"
},
  "geometry": {"coordinates":[-87.811892,44.428709],"type":"Point"}
}