{
  "type": "Feature",
  "properties": {
    "addr:full":"3863 Pumphouse Rd Mindoro WI 54644",
    "addr:housenumber":"3863",
    "addr:postcode":"54644",
    "addr:street":"Pumphouse Rd",
    "iso:country":"US",
    "sg:address":"3863 Pumphouse Rd",
    "sg:city":"Mindoro",
    "sg:classifiers":[
        {
            "category":"Building & Trades",
            "subcategory":"Landscaping Services",
            "type":"Services"
        }
    ],
    "sg:phone":"+1 608 857 3636",
    "sg:postcode":"54644",
    "sg:province":"WI",
    "wof:name":"Dennis Waller",
    "wof:placetype":"venue"
},
  "geometry": {"coordinates":[-91.101032,44.017522],"type":"Point"}
}