{
  "type": "Feature",
  "properties": {
    "iso:country":"US",
    "sg:address":"512 Five Corner Rd",
    "sg:city":"Monroe",
    "sg:classifiers":[
        {
            "category":"Wholesale",
            "subcategory":"Machinery & Supplies",
            "type":"Manufacturing & Wholesale Goods"
        }
    ],
    "sg:phone":"+1 608 328 1770",
    "sg:postcode":"53566",
    "sg:province":"WI",
    "sg:tags":[
        "farm",
        "equipment"
    ],
    "wof:name":"Southern Wisconsin Machine",
    "wof:placetype":"venue"
},
  "geometry": {"coordinates":[-89.601428,42.520967],"type":"Point"}
}