{
  "type": "Feature",
  "properties": {
    "iso:country":"US",
    "sg:address":"11124 Cedarburg Rd",
    "sg:city":"Thiensville",
    "sg:classifiers":[
        {
            "category":"Professional",
            "subcategory":"Management & Consulting",
            "type":"Services"
        }
    ],
    "sg:phone":"+1 262 236 3970",
    "sg:postcode":"53092",
    "sg:province":"WI",
    "sg:tags":[
        "public",
        "relations"
    ],
    "wof:name":"SCI Promotions",
    "wof:placetype":"venue"
},
  "geometry": {"coordinates":[-87.982268,43.221144],"type":"Point"}
}