{
  "type": "Feature",
  "properties": {
    "addr:full":"8013 State Hwy 57 Baileys Harbor WI 54202",
    "addr:housenumber":"8013",
    "addr:postcode":"54202",
    "addr:street":"State Hwy 57",
    "iso:country":"US",
    "sg:address":"8013 State Hwy 57",
    "sg:city":"Baileys Harbor",
    "sg:classifiers":[
        {
            "category":"Organizations",
            "subcategory":"Religious Organization",
            "type":"Services"
        }
    ],
    "sg:phone":"+1 920 839 2041",
    "sg:postcode":"54202",
    "sg:province":"WI",
    "sg:tags":[
        "church"
    ],
    "wof:name":"St Mary's Of The Lake Church",
    "wof:placetype":"venue"
},
  "geometry": {"coordinates":[-87.124335,45.061753],"type":"Point"}
}