{
  "type": "Feature",
  "properties": {
    "iso:country":"US",
    "sg:address":"231 Shirland Ave",
    "sg:city":"Beloit",
    "sg:classifiers":[
        {
            "category":"Retail",
            "subcategory":"Auto Repair",
            "type":"Services"
        }
    ],
    "sg:phone":"+1 608 362 2126",
    "sg:postcode":"53511",
    "sg:province":"WI",
    "wof:name":"Gales Autos Inc",
    "wof:placetype":"venue"
},
  "geometry": {"coordinates":[-89.039216,42.496548],"type":"Point"}
}