{
  "type": "Feature",
  "properties": {
    "iso:country":"US",
    "sg:address":"1008 Co Rd T",
    "sg:city":"Birchwood",
    "sg:classifiers":[
        {
            "category":"Building & Trades",
            "subcategory":"Construction",
            "type":"Services"
        }
    ],
    "sg:phone":"+1 715 354 3305",
    "sg:postcode":"54817",
    "sg:province":"WI",
    "sg:tags":[
        "house"
    ],
    "wof:name":"Woodlands Construction LLC",
    "wof:placetype":"venue"
},
  "geometry": {"coordinates":[-91.561138,45.66706],"type":"Point"}
}