{
  "type": "Feature",
  "properties": {
    "iso:country":"US",
    "sg:address":"304 Crestview Ct",
    "sg:city":"Portage",
    "sg:classifiers":[
        {
            "category":"Building & Trades",
            "subcategory":"Electrical",
            "type":"Services"
        }
    ],
    "sg:phone":"+1 608 742 6969",
    "sg:postcode":"53901",
    "sg:province":"WI",
    "sg:tags":[
        "electrical",
        "contractor"
    ],
    "wof:name":"H B Power Services LLC",
    "wof:placetype":"venue"
},
  "geometry": {"coordinates":[-89.487256,43.54654],"type":"Point"}
}