{
  "type": "Feature",
  "properties": {
    "iso:country":"US",
    "sg:address":"3171 Manitowoc Rd",
    "sg:city":"Green Bay",
    "sg:classifiers":[
        {
            "category":"Professional",
            "type":"Services"
        }
    ],
    "sg:phone":"+1 920 863 5470",
    "sg:postcode":"54311",
    "sg:province":"WI",
    "wof:name":"Gorjo LLC",
    "wof:placetype":"venue"
},
  "geometry": {"coordinates":[-87.926661,44.448688],"type":"Point"}
}