{
  "type": "Feature",
  "properties": {
    "addr:full":"214 E Seward St Poynette WI 53955",
    "addr:housenumber":"214",
    "addr:postcode":"53955",
    "addr:street":"E Seward St",
    "iso:country":"US",
    "sg:address":"214 E Seward St",
    "sg:city":"Poynette",
    "sg:classifiers":[
        {
            "category":"Personal",
            "subcategory":"Beauty Salon",
            "type":"Services"
        }
    ],
    "sg:phone":"+1 608 635 9490",
    "sg:postcode":"53955",
    "sg:province":"WI",
    "wof:name":"Finishing Touch",
    "wof:placetype":"venue"
},
  "geometry": {"coordinates":[-89.401309,43.3916],"type":"Point"}
}