{
  "type": "Feature",
  "properties": {
    "iso:country":"US",
    "sg:address":"213 Air Park Rd",
    "sg:city":"Marshfield",
    "sg:classifiers":[
        {
            "category":"Shopping",
            "type":"Retail Goods"
        }
    ],
    "sg:phone":"+1 715 384 5839",
    "sg:postcode":"54449",
    "sg:province":"WI",
    "sg:tags":[
        "trophy",
        "medal",
        "award"
    ],
    "wof:name":"Burt Trophy & Awards Inc",
    "wof:placetype":"venue"
},
  "geometry": {"coordinates":[-90.18274599999999,44.633025],"type":"Point"}
}