{
  "type": "Feature",
  "properties": {
    "iso:country":"US",
    "sg:address":"2700 E Shorewood Blvd",
    "sg:city":"Milwaukee",
    "sg:classifiers":[
        {
            "category":"Wholesale",
            "subcategory":"Hardware",
            "type":"Manufacturing & Wholesale Goods"
        }
    ],
    "sg:phone":"+1 414 243 2302",
    "sg:postcode":"53211",
    "sg:province":"WI",
    "sg:tags":[
        "water",
        "devices",
        "purification"
    ],
    "wof:name":"First Water Ltd",
    "wof:placetype":"venue"
},
  "geometry": {"coordinates":[-87.87520000000001,43.08715],"type":"Point"}
}