{
  "type": "Feature",
  "properties": {
    "iso:country":"US",
    "sg:address":"4647 Stadium Rd",
    "sg:city":"Brantwood",
    "sg:classifiers":[
        {
            "category":"Professional",
            "type":"Services"
        }
    ],
    "sg:phone":"+1 715 564 3237",
    "sg:postcode":"54513",
    "sg:province":"WI",
    "wof:name":"Johnson Brothers Forest Pdts",
    "wof:placetype":"venue"
},
  "geometry": {"coordinates":[-90.114999,45.546563],"type":"Point"}
}