{
  "type": "Feature",
  "properties": {
    "iso:country":"US",
    "sg:address":"7509 Proden Rd",
    "sg:city":"Ladysmith",
    "sg:classifiers":[
        {
            "category":"Retail",
            "subcategory":"Veterinary Services",
            "type":"Services"
        }
    ],
    "sg:phone":"+1 715 532 7501",
    "sg:postcode":"54848",
    "sg:province":"WI",
    "wof:name":"Victoria Sokolowski",
    "wof:placetype":"venue"
},
  "geometry": {"coordinates":[-91.050095,45.55917],"type":"Point"}
}