{
  "type": "Feature",
  "properties": {
    "iso:country":"US",
    "sg:address":"307 Main St",
    "sg:city":"Black River Fls",
    "sg:classifiers":[
        {
            "category":"Government",
            "subcategory":"Office",
            "type":"Public Place"
        }
    ],
    "sg:phone":"+1 715 284 0215",
    "sg:postcode":"54615",
    "sg:province":"WI",
    "wof:name":"Jackson County Personnel",
    "wof:placetype":"venue"
},
  "geometry": {"coordinates":[-90.85197599999999,44.295061],"type":"Point"}
}