{
  "type": "Feature",
  "properties": {
    "iso:country":"US",
    "sg:address":"134 W North St",
    "sg:city":"Waukesha",
    "sg:classifiers":[
        {
            "category":"Social Services",
            "type":"Services"
        }
    ],
    "sg:phone":"+1 262 549 8720",
    "sg:postcode":"53188",
    "sg:province":"WI",
    "sg:tags":[
        "shelter",
        "homeless"
    ],
    "wof:name":"Hebron House",
    "wof:placetype":"venue"
},
  "geometry": {"coordinates":[-88.236144,43.013025],"type":"Point"}
}