{
  "type": "Feature",
  "properties": {
    "iso:country":"US",
    "sg:address":"534 Indian Mound Rd",
    "sg:city":"Sheboygan",
    "sg:classifiers":[
        {
            "category":"Home & Garden",
            "subcategory":"Home Furnishings",
            "type":"Retail Goods"
        },
        {
            "category":"Wholesale",
            "subcategory":"Home Furnishings",
            "type":"Manufacturing & Wholesale Goods"
        }
    ],
    "sg:phone":"+1 920 452 2122",
    "sg:postcode":"53081",
    "sg:province":"WI",
    "sg:tags":[
        "venetian",
        "blind"
    ],
    "wof:name":"Renaissance Window Decor",
    "wof:placetype":"venue"
},
  "geometry": {"coordinates":[-87.710714,43.690851],"type":"Point"}
}