{
  "type": "Feature",
  "properties": {
    "iso:country":"US",
    "sg:address":"10101 W Capitol Dr",
    "sg:city":"Milwaukee",
    "sg:classifiers":[
        {
            "category":"Home & Garden",
            "subcategory":"Home Furnishings",
            "type":"Retail Goods"
        }
    ],
    "sg:phone":"+1 414 461 8800",
    "sg:postcode":"53222",
    "sg:province":"WI",
    "sg:tags":[
        "lighting",
        "fixture"
    ],
    "wof:name":"Light Unlimited",
    "wof:placetype":"venue"
},
  "geometry": {"coordinates":[-88.039526,43.089681],"type":"Point"}
}