{
  "type": "Feature",
  "properties": {
    "addr:full":"106 Industrial Ln Endeavor WI 53930",
    "addr:housenumber":"106",
    "addr:postcode":"53930",
    "addr:street":"Industrial Ln",
    "iso:country":"US",
    "sg:address":"106 Industrial Ln",
    "sg:city":"Endeavor",
    "sg:classifiers":[
        {
            "category":"Recreation",
            "type":"Entertainment"
        }
    ],
    "sg:phone":"+1 608 587 2203",
    "sg:postcode":"53930",
    "sg:province":"WI",
    "sg:tags":[
        "stable"
    ],
    "wof:name":"Braun Services Inc",
    "wof:placetype":"venue"
},
  "geometry": {"coordinates":[-89.470827,43.712065],"type":"Point"}
}