{
  "type": "Feature",
  "properties": {
    "iso:country":"US",
    "sg:address":"3624 W Silver Spring Dr",
    "sg:city":"Milwaukee",
    "sg:classifiers":[
        {
            "category":"Retail",
            "subcategory":"Repair Shop",
            "type":"Services"
        }
    ],
    "sg:phone":"+1 414 466 8666",
    "sg:postcode":"53209",
    "sg:province":"WI",
    "sg:tags":[
        "cleaner",
        "part",
        "vacuum"
    ],
    "wof:name":"Mr Vak",
    "wof:placetype":"venue"
},
  "geometry": {"coordinates":[-87.957778,43.119245],"type":"Point"}
}