{
  "type": "Feature",
  "properties": {
    "iso:country":"US",
    "sg:address":"4410 Custer St",
    "sg:city":"Manitowoc",
    "sg:classifiers":[
        {
            "category":"Retail",
            "subcategory":"Repair Shop",
            "type":"Services"
        }
    ],
    "sg:phone":"+1 920 682 5989",
    "sg:postcode":"54220",
    "sg:province":"WI",
    "sg:tags":[
        "radio",
        "fm"
    ],
    "wof:name":"Franks Radio Service Inc",
    "wof:placetype":"venue"
},
  "geometry": {"coordinates":[-87.70459,44.085267],"type":"Point"}
}