{
  "type": "Feature",
  "properties": {
    "addr:full":"846 Fox Point Plz Neenah WI 54956",
    "addr:housenumber":"846",
    "addr:postcode":"54956",
    "addr:street":"Fox Point Plz",
    "iso:country":"US",
    "sg:address":"846 Fox Point Plz",
    "sg:city":"Neenah",
    "sg:classifiers":[
        {
            "category":"Health Services",
            "subcategory":"Chiropractor",
            "type":"Services"
        }
    ],
    "sg:phone":"+1 920 727 1234",
    "sg:postcode":"54956",
    "sg:province":"WI",
    "sg:tags":[
        "chiropractic"
    ],
    "wof:name":"Neenah West Chiropractic Inc",
    "wof:placetype":"venue"
},
  "geometry": {"coordinates":[-88.48326299999999,44.175499],"type":"Point"}
}