{
  "type": "Feature",
  "properties": {
    "iso:country":"US",
    "sg:address":"145 S Main St",
    "sg:city":"Shawano",
    "sg:classifiers":[
        {
            "category":"Restaurant",
            "type":"Food & Drink"
        }
    ],
    "sg:phone":"+1 715 526 5820",
    "sg:postcode":"54166",
    "sg:province":"WI",
    "sg:tags":[
        "eating"
    ],
    "wof:name":"Hunan Chinese Restaurant",
    "wof:placetype":"venue"
},
  "geometry": {"coordinates":[-88.609425,44.781189],"type":"Point"}
}