{
  "type": "Feature",
  "properties": {
    "addr:full":"1331 N Astor St Milwaukee WI 53202",
    "addr:housenumber":"1331",
    "addr:postcode":"53202",
    "addr:street":"N Astor St",
    "iso:country":"US",
    "sg:address":"1331 N Astor St",
    "sg:city":"Milwaukee",
    "sg:classifiers":[
        {
            "category":"Travel",
            "subcategory":"Bed & Breakfast",
            "type":"Entertainment"
        }
    ],
    "sg:phone":"+1 414 278 0220",
    "sg:postcode":"53202",
    "sg:province":"WI",
    "sg:tags":[
        "housing",
        "student"
    ],
    "sg:website":"www.petawa.org",
    "wof:name":"Petawa Student Residence",
    "wof:placetype":"venue"
},
  "geometry": {"coordinates":[-87.899778,43.047748],"type":"Point"}
}