{
  "type": "Feature",
  "properties": {
    "addr:full":"3335 Parkside Dr Brookfield WI 53005",
    "addr:housenumber":"3335",
    "addr:postcode":"53005",
    "addr:street":"Parkside Dr",
    "iso:country":"US",
    "sg:address":"3335 Parkside Dr",
    "sg:city":"Brookfield",
    "sg:classifiers":[
        {
            "category":"Health Services",
            "subcategory":"Doctor",
            "type":"Services"
        }
    ],
    "sg:phone":"+1 262 781 4508",
    "sg:postcode":"53005",
    "sg:province":"WI",
    "sg:tags":[
        "medical"
    ],
    "wof:name":"Ui IL Chung MD Ltd",
    "wof:placetype":"venue"
},
  "geometry": {"coordinates":[-88.081164,43.075037],"type":"Point"}
}