{
  "type": "Feature",
  "properties": {
    "iso:country":"US",
    "sg:address":"1543 Park Pl",
    "sg:city":"Green Bay",
    "sg:classifiers":[
        {
            "category":"Social Services",
            "subcategory":"Job Training",
            "type":"Services"
        },
        {
            "category":"Education",
            "subcategory":"Special Training",
            "type":"Public Place"
        }
    ],
    "sg:phone":"+1 920 499 1747",
    "sg:postcode":"54304",
    "sg:province":"WI",
    "sg:tags":[
        "case",
        "medical",
        "vocational",
        "expert",
        "rehabilitation"
    ],
    "wof:name":"Consulting Experts Inc",
    "wof:placetype":"venue"
},
  "geometry": {"coordinates":[-88.08532700000001,44.508932],"type":"Point"}
}