{
  "type": "Feature",
  "properties": {
    "addr:full":"730 Mourning Dove Dr Cottage Grove WI 53527",
    "addr:housenumber":"730",
    "addr:postcode":"53527",
    "addr:street":"Mourning Dove Dr",
    "iso:country":"US",
    "sg:address":"730 Mourning Dove Dr",
    "sg:city":"Cottage Grove",
    "sg:classifiers":[
        {
            "category":"Building & Trades",
            "subcategory":"Construction",
            "type":"Services"
        }
    ],
    "sg:phone":"+1 608 839 4633",
    "sg:postcode":"53527",
    "sg:province":"WI",
    "sg:tags":[
        "contractor"
    ],
    "wof:name":"Ultimate Construction",
    "wof:placetype":"venue"
},
  "geometry": {"coordinates":[-89.207778,43.096525],"type":"Point"}
}