{
  "type": "Feature",
  "properties": {
    "iso:country":"US",
    "sg:address":"30 N 18th Ave",
    "sg:city":"Sturgeon Bay",
    "sg:classifiers":[
        {
            "category":"Banks & Credit Unions",
            "subcategory":"Investment Brokerage",
            "type":"Services"
        }
    ],
    "sg:phone":"+1 920 743 7575",
    "sg:postcode":"54235",
    "sg:province":"WI",
    "sg:tags":[
        "security"
    ],
    "wof:name":"Rbc Dain Rauscher Corporation",
    "wof:placetype":"venue"
},
  "geometry": {"coordinates":[-87.351389,44.835989],"type":"Point"}
}