{
  "type": "Feature",
  "properties": {
    "iso:country":"US",
    "sg:address":"4062 State Rd 23",
    "sg:city":"Dodgeville",
    "sg:classifiers":[
        {
            "category":"Food & Beverages",
            "subcategory":"Groceries & Convenience Stores",
            "type":"Retail Goods"
        }
    ],
    "sg:phone":"+1 608 935 1388",
    "sg:postcode":"53533",
    "sg:province":"WI",
    "sg:tags":[
        "grocer"
    ],
    "wof:name":"Jumping Jupiter General Store",
    "wof:placetype":"venue"
},
  "geometry": {"coordinates":[-90.141983,43.020046],"type":"Point"}
}