{
  "type": "Feature",
  "properties": {
    "iso:country":"US",
    "sg:address":"421 Water St",
    "sg:city":"Prairie Du Sac",
    "sg:classifiers":[
        {
            "category":"Shopping",
            "subcategory":"Gifts & Souvenirs",
            "type":"Retail Goods"
        }
    ],
    "sg:phone":"+1 608 644 0004",
    "sg:postcode":"53578",
    "sg:province":"WI",
    "sg:tags":[
        "collectible"
    ],
    "wof:name":"Goal Line Sports",
    "wof:placetype":"venue"
},
  "geometry": {"coordinates":[-89.719063,43.288912],"type":"Point"}
}