{
  "type": "Feature",
  "properties": {
    "iso:country":"US",
    "sg:address":"2050 Porter Rd",
    "sg:city":"Plover",
    "sg:classifiers":[
        {
            "category":"Organizations",
            "subcategory":"Religious Organization",
            "type":"Services"
        }
    ],
    "sg:phone":"+1 715 254 0350",
    "sg:postcode":"54467",
    "sg:province":"WI",
    "sg:tags":[
        "church"
    ],
    "wof:name":"Good Shepherd Lutheran Intern",
    "wof:placetype":"venue"
},
  "geometry": {"coordinates":[-89.529647,44.482913],"type":"Point"}
}