{
  "type": "Feature",
  "properties": {
    "addr:full":"1501 E Main St Stoughton WI 53589",
    "addr:housenumber":"1501",
    "addr:postcode":"53589",
    "addr:street":"E Main St",
    "iso:country":"US",
    "sg:address":"1501 E Main St",
    "sg:city":"Stoughton",
    "sg:classifiers":[
        {
            "category":"Restaurant",
            "type":"Food & Drink"
        }
    ],
    "sg:phone":"+1 608 877 2512",
    "sg:postcode":"53589",
    "sg:province":"WI",
    "wof:name":"Norse Chalet",
    "wof:placetype":"venue"
},
  "geometry": {"coordinates":[-89.20442799999999,42.918484],"type":"Point"}
}