{
  "type": "Feature",
  "properties": {
    "iso:country":"US",
    "sg:address":"2507 Taylor St",
    "sg:city":"Marinette",
    "sg:classifiers":[
        {
            "category":"Shopping",
            "subcategory":"Jewelry",
            "type":"Retail Goods"
        }
    ],
    "sg:phone":"+1 715 732 0344",
    "sg:postcode":"54143",
    "sg:province":"WI",
    "wof:name":"Victorian House of Silver LLC",
    "wof:placetype":"venue"
},
  "geometry": {"coordinates":[-87.64121,45.102247],"type":"Point"}
}