{
  "type": "Feature",
  "properties": {
    "iso:country":"US",
    "sg:address":"2878 S 108th St",
    "sg:city":"Milwaukee",
    "sg:classifiers":[
        {
            "category":"Bakery",
            "type":"Food & Drink"
        }
    ],
    "sg:menulink":"http://www.allmenus.com/wi/west-allis/102378-perkins-restaurant--bakery/menu/",
    "sg:phone":"+1 414 545 0569",
    "sg:postcode":"53227",
    "sg:province":"WI",
    "sg:tags":[
        "sandwich",
        "salad",
        "soup",
        "american",
        "pastry",
        "wrap"
    ],
    "wof:name":"Perkins Restaurant & Bakery",
    "wof:placetype":"venue"
},
  "geometry": {"coordinates":[-88.046519,42.991585],"type":"Point"}
}