{
  "type": "Feature",
  "properties": {
    "addr:full":"87340 Co Hwy J Bayfield WI 54814",
    "addr:housenumber":"87340",
    "addr:postcode":"54814",
    "addr:street":"Co Hwy J",
    "iso:country":"US",
    "sg:address":"87340 Co Hwy J",
    "sg:city":"Bayfield",
    "sg:classifiers":[
        {
            "category":"Wholesale",
            "subcategory":"Fruits & Vegetables",
            "type":"Manufacturing & Wholesale Goods"
        }
    ],
    "sg:phone":"+1 715 779 3332",
    "sg:postcode":"54814",
    "sg:province":"WI",
    "sg:tags":[
        "shipper"
    ],
    "wof:name":"Rocky Acres Berry Farm",
    "wof:placetype":"venue"
},
  "geometry": {"coordinates":[-90.841301,46.834708],"type":"Point"}
}