{
  "type": "Feature",
  "properties": {
    "addr:full":"3570 N 10th St Milwaukee WI 53206",
    "addr:housenumber":"3570",
    "addr:postcode":"53206",
    "addr:street":"N 10Th St",
    "iso:country":"US",
    "sg:address":"3570 N 10th St",
    "sg:city":"Milwaukee",
    "sg:classifiers":[
        {
            "category":"Personal",
            "subcategory":"Beauty Salon",
            "type":"Services"
        }
    ],
    "sg:phone":"+1 414 263 9212",
    "sg:postcode":"53206",
    "sg:province":"WI",
    "wof:name":"Lillie Mae's Beauty Salon",
    "wof:placetype":"venue"
},
  "geometry": {"coordinates":[-87.92352700000001,43.082138],"type":"Point"}
}