{
  "type": "Feature",
  "properties": {
    "iso:country":"US",
    "sg:address":"2241 22nd St",
    "sg:city":"Rice Lake",
    "sg:classifiers":[
        {
            "category":"Building & Trades",
            "subcategory":"Construction",
            "type":"Services"
        }
    ],
    "sg:phone":"+1 715 736 5550",
    "sg:postcode":"54868",
    "sg:province":"WI",
    "sg:tags":[
        "repair",
        "carpentry",
        "contractor"
    ],
    "wof:name":"Furniture Medic",
    "wof:placetype":"venue"
},
  "geometry": {"coordinates":[-91.70369100000001,45.524486],"type":"Point"}
}