{
  "type": "Feature",
  "properties": {
    "iso:country":"US",
    "sg:address":"1722 Westgate Rd",
    "sg:city":"Eau Claire",
    "sg:classifiers":[
        {
            "category":"Building & Trades",
            "subcategory":"Construction",
            "type":"Services"
        }
    ],
    "sg:phone":"+1 715 831 2260",
    "sg:postcode":"54703",
    "sg:province":"WI",
    "sg:tags":[
        "utility",
        "contractor"
    ],
    "sg:website":"www.sm-p.com",
    "wof:name":"S M & P Utility Resources",
    "wof:placetype":"venue"
},
  "geometry": {"coordinates":[-91.537182,44.81507],"type":"Point"}
}