{
  "type": "Feature",
  "properties": {
    "iso:country":"US",
    "sg:address":"162 S River St",
    "sg:city":"Janesville",
    "sg:classifiers":[
        {
            "category":"Wholesale",
            "subcategory":"Vending Machines",
            "type":"Manufacturing & Wholesale Goods"
        }
    ],
    "sg:phone":"+1 608 754 8161",
    "sg:postcode":"53548",
    "sg:province":"WI",
    "wof:name":"Central Vending Co",
    "wof:placetype":"venue"
},
  "geometry": {"coordinates":[-89.022449,42.67925],"type":"Point"}
}