{
  "type": "Feature",
  "properties": {
    "iso:country":"US",
    "sg:address":"221 Crocket Ln",
    "sg:city":"Wisconsin Rapids",
    "sg:classifiers":[
        {
            "category":"Restaurant",
            "type":"Food & Drink"
        }
    ],
    "sg:phone":"+1 715 421 0870",
    "sg:postcode":"54495",
    "sg:province":"WI",
    "sg:tags":[
        "eating"
    ],
    "wof:name":"Cancun",
    "wof:placetype":"venue"
},
  "geometry": {"coordinates":[-89.863958,44.382714],"type":"Point"}
}