{
  "type": "Feature",
  "properties": {
    "iso:country":"US",
    "sg:address":"1410 Labus Dr",
    "sg:city":"Bangor",
    "sg:classifiers":[
        {
            "category":"Building & Trades",
            "subcategory":"Construction",
            "type":"Services"
        }
    ],
    "sg:phone":"+1 608 486 2972",
    "sg:postcode":"54614",
    "sg:province":"WI",
    "sg:tags":[
        "concrete",
        "contractor"
    ],
    "wof:name":"Modern Striping",
    "wof:placetype":"venue"
},
  "geometry": {"coordinates":[-90.98651599999999,43.888011],"type":"Point"}
}