{
  "type": "Feature",
  "properties": {
    "iso:country":"US",
    "sg:address":"2624 N Lillian Ct",
    "sg:city":"Appleton",
    "sg:classifiers":[
        {
            "category":"Health Services",
            "subcategory":"Doctor",
            "type":"Services"
        }
    ],
    "sg:phone":"+1 920 707 1166",
    "sg:postcode":"54911",
    "sg:province":"WI",
    "sg:tags":[
        "medical"
    ],
    "wof:name":"RG Gadbois Co",
    "wof:placetype":"venue"
},
  "geometry": {"coordinates":[-88.393147,44.285842],"type":"Point"}
}