{
  "type": "Feature",
  "properties": {
    "iso:country":"US",
    "sg:address":"36636 Wilmot Rd",
    "sg:city":"Twin Lakes",
    "sg:classifiers":[
        {
            "category":"Building & Trades",
            "subcategory":"Landscaping Services",
            "type":"Services"
        }
    ],
    "sg:phone":"+1 262 877 2570",
    "sg:postcode":"53181",
    "sg:province":"WI",
    "sg:tags":[
        "carpentry",
        "contractor"
    ],
    "wof:name":"Outdoor Designs",
    "wof:placetype":"venue"
},
  "geometry": {"coordinates":[-88.25110100000001,42.504035],"type":"Point"}
}