{
  "type": "Feature",
  "properties": {
    "iso:country":"US",
    "sg:address":"4902 Verona Rd",
    "sg:city":"Madison",
    "sg:classifiers":[
        {
            "category":"Autos & Motor Vehicles",
            "subcategory":"Fuel & Gas Station",
            "type":"Retail Goods"
        }
    ],
    "sg:phone":"+1 608 271 2467",
    "sg:postcode":"53711",
    "sg:province":"WI",
    "sg:tags":[
        "grocery",
        "station",
        "gasoline"
    ],
    "wof:name":"Speedway 4132",
    "wof:placetype":"venue"
},
  "geometry": {"coordinates":[-89.461078,43.030956],"type":"Point"}
}