{
  "type": "Feature",
  "properties": {
    "addr:full":"1170 Rome Rd Rubicon WI 53078",
    "addr:housenumber":"1170",
    "addr:postcode":"53078",
    "addr:street":"Rome Rd",
    "iso:country":"US",
    "sg:address":"1170 Rome Rd",
    "sg:city":"Rubicon",
    "sg:classifiers":[
        {
            "category":"Organizations",
            "subcategory":"Religious Organization",
            "type":"Services"
        }
    ],
    "sg:phone":"+1 262 673 3380",
    "sg:postcode":"53078",
    "sg:province":"WI",
    "sg:tags":[
        "church"
    ],
    "wof:name":"St John's Catholic Church",
    "wof:placetype":"venue"
},
  "geometry": {"coordinates":[-88.45216600000001,43.339959],"type":"Point"}
}