{
  "type": "Feature",
  "properties": {
    "addr:full":"20921 Main St Collins WI 54207",
    "addr:housenumber":"20921",
    "addr:postcode":"54207",
    "addr:street":"Main St",
    "iso:country":"US",
    "sg:address":"20921 Main St",
    "sg:city":"Collins",
    "sg:classifiers":[
        {
            "category":"Manufacturing",
            "subcategory":"Metals",
            "type":"Manufacturing & Wholesale Goods"
        }
    ],
    "sg:phone":"+1 920 772 4410",
    "sg:postcode":"54207",
    "sg:province":"WI",
    "sg:tags":[
        "brass",
        "foundry",
        "bronze"
    ],
    "wof:name":"Union Brass & Aluminum Foundry",
    "wof:placetype":"venue"
},
  "geometry": {"coordinates":[-87.982348,44.086598],"type":"Point"}
}