{
  "type": "Feature",
  "properties": {
    "addr:full":"800 Riverside St Janesville WI 53545",
    "addr:housenumber":"800",
    "addr:postcode":"53545",
    "addr:street":"Riverside St",
    "iso:country":"US",
    "sg:address":"800 Riverside St",
    "sg:city":"Janesville",
    "sg:classifiers":[
        {
            "category":"Recreation",
            "type":"Entertainment"
        }
    ],
    "sg:phone":"+1 608 755 3025",
    "sg:postcode":"53545",
    "sg:province":"WI",
    "sg:tags":[
        "parks"
    ],
    "wof:name":"Monterey Park",
    "wof:placetype":"venue"
},
  "geometry": {"coordinates":[-89.021007,42.671504],"type":"Point"}
}