{
  "type": "Feature",
  "properties": {
    "iso:country":"US",
    "sg:address":"27517 Pauls Hill Dr",
    "sg:city":"Richland Center",
    "sg:classifiers":[
        {
            "category":"Retail",
            "subcategory":"Animal Services",
            "type":"Services"
        }
    ],
    "sg:phone":"+1 608 647 3753",
    "sg:postcode":"53581",
    "sg:province":"WI",
    "sg:tags":[
        "pet",
        "boarding",
        "sitting"
    ],
    "wof:name":"Wyngalan Kennel",
    "wof:placetype":"venue"
},
  "geometry": {"coordinates":[-90.41101,43.302831],"type":"Point"}
}