{
  "type": "Feature",
  "properties": {
    "addr:full":"119 N Wisconsin St Berlin WI 54923",
    "addr:housenumber":"119",
    "addr:postcode":"54923",
    "addr:street":"N Wisconsin St",
    "iso:country":"US",
    "sg:address":"119 N Wisconsin St",
    "sg:city":"Berlin",
    "sg:classifiers":[
        {
            "category":"Real Estate",
            "subcategory":"Real Estate Agent",
            "type":"Services"
        }
    ],
    "sg:phone":"+1 920 361 2940",
    "sg:postcode":"54923",
    "sg:province":"WI",
    "wof:name":"Tom Swan Appraisal Inc",
    "wof:placetype":"venue"
},
  "geometry": {"coordinates":[-88.9468,43.968534],"type":"Point"}
}