{
  "type": "Feature",
  "properties": {
    "iso:country":"US",
    "sg:address":"110 Maple St",
    "sg:city":"Woodruff",
    "sg:classifiers":[
        {
            "category":"Health Services",
            "subcategory":"Doctor",
            "type":"Services"
        }
    ],
    "sg:phone":"+1 715 356 6339",
    "sg:postcode":"54568",
    "sg:province":"WI",
    "sg:tags":[
        "dentist"
    ],
    "wof:name":"Northwoods Dental Clinic",
    "wof:placetype":"venue"
},
  "geometry": {"coordinates":[-89.703081,45.892692],"type":"Point"}
}