{
  "type": "Feature",
  "properties": {
    "iso:country":"US",
    "sg:address":"301 5th Ave W",
    "sg:city":"Durand",
    "sg:classifiers":[
        {
            "category":"Wholesale",
            "subcategory":"Farm Supplies",
            "type":"Manufacturing & Wholesale Goods"
        }
    ],
    "sg:phone":"+1 715 672 4255",
    "sg:postcode":"54736",
    "sg:province":"WI",
    "wof:name":"Blacks Valley Ag Supply Inc",
    "wof:placetype":"venue"
},
  "geometry": {"coordinates":[-91.969597,44.626592],"type":"Point"}
}