{
  "type": "Feature",
  "properties": {
    "iso:country":"US",
    "sg:address":"17445 W Bluemound Rd",
    "sg:city":"Brookfield",
    "sg:classifiers":[
        {
            "category":"Shopping",
            "subcategory":"Computers & Home Electronics",
            "type":"Retail Goods"
        }
    ],
    "sg:phone":"+1 262 789 1195",
    "sg:postcode":"53045",
    "sg:province":"WI",
    "sg:tags":[
        "equipment",
        "system"
    ],
    "sg:website":"www.flanners.com",
    "wof:name":"Flanners Audio & Video Inc",
    "wof:placetype":"venue"
},
  "geometry": {"coordinates":[-88.133171,43.036348],"type":"Point"}
}