{
  "type": "Feature",
  "properties": {
    "iso:country":"US",
    "sg:address":"107 W Main St",
    "sg:city":"Bowler",
    "sg:classifiers":[
        {
            "category":"Government",
            "subcategory":"Office",
            "type":"Public Place"
        }
    ],
    "sg:phone":"+1 715 793 4910",
    "sg:postcode":"54416",
    "sg:province":"WI",
    "sg:tags":[
        "village"
    ],
    "wof:name":"Bowler Village Hall",
    "wof:placetype":"venue"
},
  "geometry": {"coordinates":[-88.988445,44.864204],"type":"Point"}
}