{
  "type": "Feature",
  "properties": {
    "iso:country":"US",
    "sg:address":"221 Park St",
    "sg:city":"Chilton",
    "sg:classifiers":[
        {
            "category":"Education",
            "subcategory":"Library",
            "type":"Public Place"
        }
    ],
    "sg:phone":"+1 920 849 4414",
    "sg:postcode":"53014",
    "sg:province":"WI",
    "wof:name":"Chilton Public Library",
    "wof:placetype":"venue"
},
  "geometry": {"coordinates":[-88.15839099999999,44.030017],"type":"Point"}
}