{
  "type": "Feature",
  "properties": {
    "iso:country":"US",
    "sg:address":"1039 4th Ave N",
    "sg:city":"Park Falls",
    "sg:classifiers":[
        {
            "category":"Building & Trades",
            "subcategory":"Electrical",
            "type":"Services"
        }
    ],
    "sg:phone":"+1 715 762 2659",
    "sg:postcode":"54552",
    "sg:province":"WI",
    "sg:tags":[
        "electric",
        "contractor"
    ],
    "wof:name":"Strand Electrical Svc Inc",
    "wof:placetype":"venue"
},
  "geometry": {"coordinates":[-90.46173400000001,45.945944],"type":"Point"}
}