{
  "type": "Feature",
  "properties": {
    "iso:country":"US",
    "sg:address":"4417 N Oakland Ave",
    "sg:city":"Milwaukee",
    "sg:classifiers":[
        {
            "category":"Real Estate",
            "subcategory":"Real Estate Agent",
            "type":"Services"
        }
    ],
    "sg:phone":"+1 414 431 0641",
    "sg:postcode":"53211",
    "sg:province":"WI",
    "sg:tags":[
        "management"
    ],
    "wof:name":"American Property Management",
    "wof:placetype":"venue"
},
  "geometry": {"coordinates":[-87.887494,43.097831],"type":"Point"}
}