{
  "type": "Feature",
  "properties": {
    "iso:country":"US",
    "sg:address":"1407 N 21st St",
    "sg:city":"Milwaukee",
    "sg:classifiers":[
        {
            "category":"Professional",
            "type":"Services"
        }
    ],
    "sg:phone":"+1 414 935 9530",
    "sg:postcode":"53205",
    "sg:province":"WI",
    "wof:name":"Children R Future Foundation",
    "wof:placetype":"venue"
},
  "geometry": {"coordinates":[-87.93905599999999,43.049923],"type":"Point"}
}