{
  "type": "Feature",
  "properties": {
    "iso:country":"US",
    "sg:address":"2500 Burl Oak Curve",
    "sg:city":"Hudson",
    "sg:classifiers":[
        {
            "category":"Recreation",
            "type":"Entertainment"
        }
    ],
    "sg:phone":"+1 715 381 1093",
    "sg:postcode":"54016",
    "sg:province":"WI",
    "wof:name":"Perfect Swing Batting Cages LL",
    "wof:placetype":"venue"
},
  "geometry": {"coordinates":[-92.722275,44.987297],"type":"Point"}
}