{
  "type": "Feature",
  "properties": {
    "iso:country":"US",
    "sg:address":"1302 Troy Dr",
    "sg:city":"Madison",
    "sg:classifiers":[
        {
            "category":"Building & Trades",
            "subcategory":"Construction",
            "type":"Services"
        }
    ],
    "sg:phone":"+1 608 241 4572",
    "sg:postcode":"53704",
    "sg:province":"WI",
    "sg:tags":[
        "roofing",
        "contractor"
    ],
    "wof:name":"Capuex Roofing",
    "wof:placetype":"venue"
},
  "geometry": {"coordinates":[-89.376062,43.133804],"type":"Point"}
}