{
  "type": "Feature",
  "properties": {
    "iso:country":"US",
    "sg:address":"2802 Rib Mountain Dr",
    "sg:city":"Wausau",
    "sg:classifiers":[
        {
            "category":"Wholesale",
            "subcategory":"Machinery & Supplies",
            "type":"Manufacturing & Wholesale Goods"
        }
    ],
    "sg:phone":"+1 715 842 9696",
    "sg:postcode":"54401",
    "sg:province":"WI",
    "sg:tags":[
        "equipment",
        "industrial"
    ],
    "wof:name":"M R O Tech Inc",
    "wof:placetype":"venue"
},
  "geometry": {"coordinates":[-89.655812,44.930702],"type":"Point"}
}