{
  "type": "Feature",
  "properties": {
    "iso:country":"US",
    "sg:address":"305 S Forrest St",
    "sg:city":"Stoughton",
    "sg:classifiers":[
        {
            "category":"Shopping",
            "subcategory":"Gifts & Souvenirs",
            "type":"Retail Goods"
        }
    ],
    "sg:phone":"+1 608 877 1444",
    "sg:postcode":"53589",
    "sg:province":"WI",
    "wof:name":"Nelsons Cards",
    "wof:placetype":"venue"
},
  "geometry": {"coordinates":[-89.219069,42.916536],"type":"Point"}
}