{
  "type": "Feature",
  "properties": {
    "addr:full":"418 Main St Wilton WI 54670",
    "addr:housenumber":"418",
    "addr:postcode":"54670",
    "addr:street":"Main St",
    "iso:country":"US",
    "sg:address":"418 Main St",
    "sg:city":"Wilton",
    "sg:classifiers":[
        {
            "category":"Government",
            "subcategory":"Post Office",
            "type":"Public Place"
        }
    ],
    "sg:phone":"+1 608 435 6833",
    "sg:postcode":"54670",
    "sg:province":"WI",
    "wof:name":"US Post Office",
    "wof:placetype":"venue"
},
  "geometry": {"coordinates":[-90.528159,43.813988],"type":"Point"}
}