{
  "type": "Feature",
  "properties": {
    "iso:country":"US",
    "sg:address":"300 S Broadway",
    "sg:city":"Green Bay",
    "sg:classifiers":[
        {
            "category":"Personal",
            "subcategory":"Beauty Salon",
            "type":"Services"
        }
    ],
    "sg:phone":"+1 920 438 8399",
    "sg:postcode":"54303",
    "sg:province":"WI",
    "sg:tags":[
        "spa",
        "day"
    ],
    "wof:name":"Tranquility Spa",
    "wof:placetype":"venue"
},
  "geometry": {"coordinates":[-88.02363099999999,44.513535],"type":"Point"}
}