{
  "type": "Feature",
  "properties": {
    "iso:country":"US",
    "sg:address":"7668 N Peebles Ln",
    "sg:city":"Fond Du Lac",
    "sg:classifiers":[
        {
            "category":"Insurance",
            "subcategory":"Insurance Agent",
            "type":"Services"
        }
    ],
    "sg:phone":"+1 920 922 7740",
    "sg:postcode":"54935",
    "sg:province":"WI",
    "wof:name":"Bob Royea Insurance",
    "wof:placetype":"venue"
},
  "geometry": {"coordinates":[-88.376789,43.818068],"type":"Point"}
}