{
  "type": "Feature",
  "properties": {
    "iso:country":"US",
    "sg:address":"3471 Earlwyn Rd",
    "sg:city":"Cottage Grove",
    "sg:classifiers":[
        {
            "category":"Freight",
            "type":"Transportation"
        }
    ],
    "sg:phone":"+1 608 764 5218",
    "sg:postcode":"53527",
    "sg:province":"WI",
    "sg:tags":[
        "local",
        "without",
        "storage",
        "trucking"
    ],
    "wof:name":"Tsw Express",
    "wof:placetype":"venue"
},
  "geometry": {"coordinates":[-89.163376,43.038495],"type":"Point"}
}