{
  "type": "Feature",
  "properties": {
    "iso:country":"US",
    "sg:address":"1701 Knutes Rd",
    "sg:city":"Pittsville",
    "sg:classifiers":[
        {
            "category":"Wholesale",
            "subcategory":"Fruits & Vegetables",
            "type":"Manufacturing & Wholesale Goods"
        }
    ],
    "sg:phone":"+1 715 884 7285",
    "sg:postcode":"54466",
    "sg:province":"WI",
    "sg:tags":[
        "shipper"
    ],
    "wof:name":"Ranger Cranberry Co LLC",
    "wof:placetype":"venue"
},
  "geometry": {"coordinates":[-90.379405,44.379661],"type":"Point"}
}