{
  "type": "Feature",
  "properties": {
    "iso:country":"US",
    "sg:address":"753 Washington St",
    "sg:city":"Rhinelander",
    "sg:classifiers":[
        {
            "category":"Manufacturing",
            "subcategory":"Metals",
            "type":"Manufacturing & Wholesale Goods"
        }
    ],
    "sg:phone":"+1 715 362 5104",
    "sg:postcode":"54501",
    "sg:province":"WI",
    "sg:tags":[
        "plate",
        "c",
        "fabricated",
        "mfg"
    ],
    "wof:name":"Northstar Steel Fabricating",
    "wof:placetype":"venue"
},
  "geometry": {"coordinates":[-89.396242,45.630208],"type":"Point"}
}