{
  "type": "Feature",
  "properties": {
    "addr:full":"4977 Dead End Rd Rhinelander WI 54501",
    "addr:housenumber":"4977",
    "addr:postcode":"54501",
    "addr:street":"Dead End Rd",
    "iso:country":"US",
    "sg:address":"4977 Dead End Rd",
    "sg:city":"Rhinelander",
    "sg:classifiers":[
        {
            "category":"Manufacturing",
            "subcategory":"Buildings",
            "type":"Manufacturing & Wholesale Goods"
        },
        {
            "category":"Building & Trades",
            "subcategory":"Construction",
            "type":"Services"
        }
    ],
    "sg:phone":"+1 715 369 5604",
    "sg:postcode":"54501",
    "sg:province":"WI",
    "sg:tags":[
        "industrial",
        "system",
        "specialty",
        "builder",
        "heating",
        "contractor",
        "contractors-commercial",
        "home",
        "air conditioning"
    ],
    "wof:name":"North Construction",
    "wof:placetype":"venue"
},
  "geometry": {"coordinates":[-89.391505,45.670108],"type":"Point"}
}