{
  "type": "Feature",
  "properties": {
    "iso:country":"US",
    "sg:address":"401 Raintree Dr",
    "sg:city":"Fort Atkinson",
    "sg:classifiers":[
        {
            "category":"Building & Trades",
            "subcategory":"Construction",
            "type":"Services"
        }
    ],
    "sg:phone":"+1 920 563 6850",
    "sg:postcode":"53538",
    "sg:province":"WI",
    "sg:tags":[
        "contractor"
    ],
    "wof:name":"R B Roofing",
    "wof:placetype":"venue"
},
  "geometry": {"coordinates":[-88.84432099999999,42.909317],"type":"Point"}
}