{
  "type": "Feature",
  "properties": {
    "iso:country":"US",
    "sg:address":"1651 W South Park Ave",
    "sg:city":"Oshkosh",
    "sg:classifiers":[
        {
            "category":"Restaurant",
            "type":"Food & Drink"
        }
    ],
    "sg:phone":"+1 920 231 9555",
    "sg:postcode":"54902",
    "sg:province":"WI",
    "wof:name":"Friar Tuck's",
    "wof:placetype":"venue"
},
  "geometry": {"coordinates":[-88.576372,43.994041],"type":"Point"}
}