{
  "type": "Feature",
  "properties": {
    "iso:country":"US",
    "sg:address":"217 W Main St",
    "sg:city":"La Farge",
    "sg:classifiers":[
        {
            "category":"Food & Beverages",
            "subcategory":"Groceries & Convenience Stores",
            "type":"Retail Goods"
        }
    ],
    "sg:phone":"+1 608 625 2203",
    "sg:postcode":"54639",
    "sg:province":"WI",
    "wof:name":"Zzip Stop",
    "wof:placetype":"venue"
},
  "geometry": {"coordinates":[-90.638698,43.574293],"type":"Point"}
}