{
  "type": "Feature",
  "properties": {
    "iso:country":"US",
    "sg:address":"7527 38th Ave",
    "sg:city":"Kenosha",
    "sg:classifiers":[
        {
            "category":"Professional",
            "type":"Services"
        }
    ],
    "sg:phone":"+1 262 653 8990",
    "sg:postcode":"53142",
    "sg:province":"WI",
    "sg:tags":[
        "writer"
    ],
    "wof:name":"Design Works",
    "wof:placetype":"venue"
},
  "geometry": {"coordinates":[-87.853881,42.565324],"type":"Point"}
}