{
  "type": "Feature",
  "properties": {
    "addr:full":"27900 100th Ave Cadott WI 54727",
    "addr:housenumber":"27900",
    "addr:postcode":"54727",
    "addr:street":"100Th Ave",
    "iso:country":"US",
    "sg:address":"27900 100th Ave",
    "sg:city":"Cadott",
    "sg:classifiers":[
        {
            "category":"Building & Trades",
            "subcategory":"Construction",
            "type":"Services"
        }
    ],
    "sg:phone":"+1 715 289 3161",
    "sg:postcode":"54727",
    "sg:province":"WI",
    "sg:tags":[
        "real",
        "property",
        "lessor",
        "contractor"
    ],
    "wof:name":"Chimney Doctor",
    "wof:placetype":"venue"
},
  "geometry": {"coordinates":[-91.10800399999999,44.987385],"type":"Point"}
}