{
  "type": "Feature",
  "properties": {
    "iso:country":"US",
    "sg:address":"4459 Gray Rd",
    "sg:city":"De Forest",
    "sg:classifiers":[
        {
            "category":"Organizations",
            "subcategory":"Religious Organization",
            "type":"Services"
        }
    ],
    "sg:phone":"+1 608 846 7880",
    "sg:postcode":"53532",
    "sg:province":"WI",
    "sg:tags":[
        "church"
    ],
    "sg:website":"www.wcucc.org",
    "wof:name":"Wisconsin Conference-United",
    "wof:placetype":"venue"
},
  "geometry": {"coordinates":[-89.34046499999999,43.223563],"type":"Point"}
}