{
  "type": "Feature",
  "properties": {
    "iso:country":"US",
    "sg:address":"811 W College Ave",
    "sg:city":"Waukesha",
    "sg:classifiers":[
        {
            "category":"Building & Trades",
            "subcategory":"Construction",
            "type":"Services"
        }
    ],
    "sg:phone":"+1 262 547 6096",
    "sg:postcode":"53186",
    "sg:province":"WI",
    "sg:tags":[
        "siding",
        "gutter",
        "installation",
        "contractor"
    ],
    "wof:name":"Security Aluminum Co Inc",
    "wof:placetype":"venue"
},
  "geometry": {"coordinates":[-88.247895,43.002654],"type":"Point"}
}