{
  "type": "Feature",
  "properties": {
    "iso:country":"US",
    "sg:address":"6249 Lodi Springfield Rd",
    "sg:city":"Waunakee",
    "sg:classifiers":[
        {
            "category":"Freight",
            "type":"Transportation"
        }
    ],
    "sg:phone":"+1 608 849 5590",
    "sg:postcode":"53597",
    "sg:province":"WI",
    "sg:tags":[
        "operator",
        "trucking"
    ],
    "wof:name":"Middleton Trucking Enterprises",
    "wof:placetype":"venue"
},
  "geometry": {"coordinates":[-89.551261,43.198892],"type":"Point"}
}