{
  "type": "Feature",
  "properties": {
    "addr:full":"5415 N 73rd St Milwaukee WI 53218",
    "addr:housenumber":"5415",
    "addr:postcode":"53218",
    "addr:street":"N 73Rd St",
    "iso:country":"US",
    "sg:address":"5415 N 73rd St",
    "sg:city":"Milwaukee",
    "sg:classifiers":[
        {
            "category":"Building & Trades",
            "subcategory":"Construction",
            "type":"Services"
        }
    ],
    "sg:phone":"+1 414 536 5719",
    "sg:postcode":"53218",
    "sg:province":"WI",
    "sg:tags":[
        "paving",
        "contractor"
    ],
    "wof:name":"Sti Inc",
    "wof:placetype":"venue"
},
  "geometry": {"coordinates":[-88.002212,43.116055],"type":"Point"}
}