{
  "type": "Feature",
  "properties": {
    "iso:country":"US",
    "sg:address":"9004 W Lincoln Ave",
    "sg:city":"Milwaukee",
    "sg:classifiers":[
        {
            "category":"Professional",
            "subcategory":"Employment Agencies",
            "type":"Services"
        }
    ],
    "sg:phone":"+1 414 321 5411",
    "sg:postcode":"53227",
    "sg:province":"WI",
    "sg:tags":[
        "consulting",
        "management",
        "help",
        "supply"
    ],
    "wof:name":"Cornwell Staffing Services",
    "wof:placetype":"venue"
},
  "geometry": {"coordinates":[-88.02591099999999,43.002775],"type":"Point"}
}