{
  "type": "Feature",
  "properties": {
    "iso:country":"US",
    "sg:address":"1937 S 94th St",
    "sg:city":"Milwaukee",
    "sg:classifiers":[
        {
            "category":"Shopping",
            "subcategory":"Gifts & Souvenirs",
            "type":"Retail Goods"
        }
    ],
    "sg:phone":"+1 414 546 4464",
    "sg:postcode":"53227",
    "sg:province":"WI",
    "wof:name":"Nalc Aux Inc",
    "wof:placetype":"venue"
},
  "geometry": {"coordinates":[-88.029669,43.008704],"type":"Point"}
}