{
  "type": "Feature",
  "properties": {
    "iso:country":"US",
    "sg:address":"101 W Main St",
    "sg:city":"La Farge",
    "sg:classifiers":[
        {
            "category":"Home & Garden",
            "subcategory":"Hardware",
            "type":"Retail Goods"
        }
    ],
    "sg:phone":"+1 608 625 2145",
    "sg:postcode":"54639",
    "sg:province":"WI",
    "wof:name":"LA Farge Hardware",
    "wof:placetype":"venue"
},
  "geometry": {"coordinates":[-90.637598,43.574354],"type":"Point"}
}