{
  "type": "Feature",
  "properties": {
    "addr:full":"3348 Kewaunee Rd Green Bay WI 54311",
    "addr:housenumber":"3348",
    "addr:postcode":"54311",
    "addr:street":"Kewaunee Rd",
    "iso:country":"US",
    "sg:address":"3348 Kewaunee Rd",
    "sg:city":"Green Bay",
    "sg:classifiers":[
        {
            "category":"Farming",
            "subcategory":"Farm & Veterinary Services",
            "type":"Manufacturing & Wholesale Goods"
        }
    ],
    "sg:phone":"+1 920 468 8658",
    "sg:postcode":"54311",
    "sg:province":"WI",
    "sg:tags":[
        "livestock"
    ],
    "wof:name":"Dalebroux Meats",
    "wof:placetype":"venue"
},
  "geometry": {"coordinates":[-87.92043099999999,44.444108],"type":"Point"}
}