{
  "type": "Feature",
  "properties": {
    "iso:country":"US",
    "sg:address":"6895 Springs Dr",
    "sg:city":"Phillips",
    "sg:classifiers":[
        {
            "category":"Government",
            "subcategory":"Office",
            "type":"Public Place"
        }
    ],
    "sg:phone":"+1 715 339 3430",
    "sg:postcode":"54555",
    "sg:province":"WI",
    "sg:tags":[
        "executive"
    ],
    "wof:name":"Worcester Town Hall",
    "wof:placetype":"venue"
},
  "geometry": {"coordinates":[-90.38557,45.666671],"type":"Point"}
}