{
  "type": "Feature",
  "properties": {
    "iso:country":"US",
    "sg:address":"812 5th Ave",
    "sg:city":"Eau Claire",
    "sg:classifiers":[
        {
            "category":"Shopping",
            "subcategory":"Used Merchandise",
            "type":"Retail Goods"
        }
    ],
    "sg:phone":"+1 715 832 8289",
    "sg:postcode":"54703",
    "sg:province":"WI",
    "sg:tags":[
        "book",
        "rare",
        "dealer"
    ],
    "wof:name":"Book Peddler",
    "wof:placetype":"venue"
},
  "geometry": {"coordinates":[-91.509891,44.808684],"type":"Point"}
}