{
  "type": "Feature",
  "properties": {
    "iso:country":"US",
    "sg:address":"704 S Bellis St",
    "sg:city":"Wausau",
    "sg:classifiers":[
        {
            "category":"Professional",
            "type":"Services"
        }
    ],
    "sg:phone":"+1 715 845 5242",
    "sg:postcode":"54403",
    "sg:province":"WI",
    "sg:tags":[
        "establishment"
    ],
    "wof:name":"Marmet Corp",
    "wof:placetype":"venue"
},
  "geometry": {"coordinates":[-89.615893,44.950207],"type":"Point"}
}