{
  "type": "Feature",
  "properties": {
    "iso:country":"US",
    "sg:address":"1716 Fordem Ave",
    "sg:city":"Madison",
    "sg:classifiers":[
        {
            "category":"Professional",
            "subcategory":"Computer Services",
            "type":"Services"
        }
    ],
    "sg:phone":"+1 608 241 7100",
    "sg:postcode":"53704",
    "sg:province":"WI",
    "sg:tags":[
        "consultant",
        "designer"
    ],
    "sg:website":"www.geoanalytics.com",
    "wof:name":"Geo Analytics",
    "wof:placetype":"venue"
},
  "geometry": {"coordinates":[-89.363568,43.094942],"type":"Point"}
}