{
  "type": "Feature",
  "properties": {
    "iso:country":"US",
    "sg:address":"411 Main St",
    "sg:city":"Wilton",
    "sg:classifiers":[
        {
            "category":"Home & Garden",
            "subcategory":"Hardware",
            "type":"Retail Goods"
        }
    ],
    "sg:phone":"+1 608 435 6616",
    "sg:postcode":"54670",
    "sg:province":"WI",
    "wof:name":"Hardware Hank",
    "wof:placetype":"venue"
},
  "geometry": {"coordinates":[-90.528228,43.813881],"type":"Point"}
}