{
  "type": "Feature",
  "properties": {
    "addr:full":"2554 Breaker Rd Tigerton WI 54486",
    "addr:housenumber":"2554",
    "addr:postcode":"54486",
    "addr:street":"Breaker Rd",
    "iso:country":"US",
    "sg:address":"2554 Breaker Rd",
    "sg:city":"Tigerton",
    "sg:classifiers":[
        {
            "category":"Farming",
            "subcategory":"Livestock Farm",
            "type":"Manufacturing & Wholesale Goods"
        }
    ],
    "sg:phone":"+1 715 535 2363",
    "sg:postcode":"54486",
    "sg:province":"WI",
    "sg:tags":[
        "animal",
        "general"
    ],
    "wof:name":"Dennis Breaker",
    "wof:placetype":"venue"
},
  "geometry": {"coordinates":[-89.14824299999999,44.696973],"type":"Point"}
}