{
  "type": "Feature",
  "properties": {
    "addr:full":"660 S Whitney Way Madison WI 53711",
    "addr:housenumber":"660",
    "addr:postcode":"53711",
    "addr:street":"S Whitney Way",
    "iso:country":"US",
    "sg:address":"660 S Whitney Way",
    "sg:city":"Madison",
    "sg:classifiers":[
        {
            "category":"Restaurant",
            "type":"Food & Drink"
        }
    ],
    "sg:menulink":"http://www.allmenus.com/wi/madison/35902-applebees/menu/",
    "sg:phone":"+1 608 271 5450",
    "sg:postcode":"53711",
    "sg:province":"WI",
    "sg:tags":[
        "burger",
        "american",
        "sandwich",
        "soup"
    ],
    "wof:name":"Applebee's",
    "wof:placetype":"venue"
},
  "geometry": {"coordinates":[-89.473625,43.053931],"type":"Point"}
}