{
  "type": "Feature",
  "properties": {
    "iso:country":"US",
    "sg:address":"1460 Ashwood Dr",
    "sg:city":"Plover",
    "sg:classifiers":[
        {
            "category":"Real Estate",
            "subcategory":"Real Estate Agent",
            "type":"Services"
        }
    ],
    "sg:phone":"+1 715 345 7298",
    "sg:postcode":"54467",
    "sg:province":"WI",
    "wof:name":"Gandd Properties LLC",
    "wof:placetype":"venue"
},
  "geometry": {"coordinates":[-89.534023,44.476647],"type":"Point"}
}