{
  "type": "Feature",
  "properties": {
    "iso:country":"US",
    "sg:address":"5028 Co Rd Nn",
    "sg:city":"Denmark",
    "sg:classifiers":[
        {
            "category":"Retail",
            "subcategory":"Repair Shop",
            "type":"Services"
        }
    ],
    "sg:phone":"+1 920 863 6493",
    "sg:postcode":"54208",
    "sg:province":"WI",
    "wof:name":"Havlovitz Repair",
    "wof:placetype":"venue"
},
  "geometry": {"coordinates":[-87.88724999999999,44.399009],"type":"Point"}
}