{
  "type": "Feature",
  "properties": {
    "iso:country":"US",
    "sg:address":"2227 Branch St",
    "sg:city":"Middleton",
    "sg:classifiers":[
        {
            "category":"Manufacturing",
            "subcategory":"Printing",
            "type":"Manufacturing & Wholesale Goods"
        }
    ],
    "sg:phone":"+1 608 836 1970",
    "sg:postcode":"53562",
    "sg:province":"WI",
    "sg:tags":[
        "publishing"
    ],
    "wof:name":"Microscopy Today",
    "wof:placetype":"venue"
},
  "geometry": {"coordinates":[-89.493588,43.099741],"type":"Point"}
}