{
  "type": "Feature",
  "properties": {
    "addr:full":"2223 Calumet Dr Sheboygan WI 53083",
    "addr:housenumber":"2223",
    "addr:postcode":"53083",
    "addr:street":"Calumet Dr",
    "iso:country":"US",
    "sg:address":"2223 Calumet Dr",
    "sg:city":"Sheboygan",
    "sg:classifiers":[
        {
            "category":"Shopping",
            "subcategory":"Pharmacy",
            "type":"Retail Goods"
        }
    ],
    "sg:phone":"+1 920 457 5659",
    "sg:postcode":"53083",
    "sg:province":"WI",
    "sg:tags":[
        "photofinishing",
        "laboratory"
    ],
    "sg:website":"www.walgreens.com",
    "wof:name":"Walgreens",
    "wof:placetype":"venue"
},
  "geometry": {"coordinates":[-87.72881599999999,43.768773],"type":"Point"}
}