{
  "type": "Feature",
  "properties": {
    "iso:country":"US",
    "sg:address":"2117 S Oneida St",
    "sg:city":"Green Bay",
    "sg:classifiers":[
        {
            "category":"Professional",
            "subcategory":"Advertising",
            "type":"Services"
        }
    ],
    "sg:phone":"+1 920 496 9447",
    "sg:postcode":"54304",
    "sg:province":"WI",
    "sg:tags":[
        "counselor",
        "agency"
    ],
    "wof:name":"Ad Vantage Marketing & Media",
    "wof:placetype":"venue"
},
  "geometry": {"coordinates":[-88.061677,44.494603],"type":"Point"}
}