{
  "type": "Feature",
  "properties": {
    "addr:full":"433 W Appletree Ct Thiensville WI 53092",
    "addr:housenumber":"433",
    "addr:postcode":"53092",
    "addr:street":"W Appletree Ct",
    "iso:country":"US",
    "sg:address":"433 W Appletree Ct",
    "sg:city":"Thiensville",
    "sg:classifiers":[
        {
            "category":"Home & Garden",
            "subcategory":"Carpets & Floor Coverings",
            "type":"Retail Goods"
        }
    ],
    "sg:phone":"+1 262 241 3665",
    "sg:postcode":"53092",
    "sg:province":"WI",
    "sg:tags":[
        "distributor",
        "rug",
        "manufacturer"
    ],
    "wof:name":"Red Carpet Real Estate",
    "wof:placetype":"venue"
},
  "geometry": {"coordinates":[-87.91327,43.198102],"type":"Point"}
}