{
  "type": "Feature",
  "properties": {
    "iso:country":"US",
    "sg:address":"851 Saratoga St",
    "sg:city":"Wisconsin Rapids",
    "sg:classifiers":[
        {
            "category":"Social Services",
            "subcategory":"Child Care",
            "type":"Services"
        }
    ],
    "sg:phone":"+1 715 423 3005",
    "sg:postcode":"54494",
    "sg:province":"WI",
    "sg:tags":[
        "day"
    ],
    "wof:name":"Tootsie Bear Day Care",
    "wof:placetype":"venue"
},
  "geometry": {"coordinates":[-89.816382,44.391117],"type":"Point"}
}