{
  "type": "Feature",
  "properties": {
    "iso:country":"US",
    "sg:address":"6726 Raymond Rd",
    "sg:city":"Madison",
    "sg:classifiers":[
        {
            "category":"Social Services",
            "subcategory":"Child Care",
            "type":"Services"
        }
    ],
    "sg:phone":"+1 608 271 0775",
    "sg:postcode":"53719",
    "sg:province":"WI",
    "sg:tags":[
        "day"
    ],
    "wof:name":"Kindercare Center 891",
    "wof:placetype":"venue"
},
  "geometry": {"coordinates":[-89.49712,43.031877],"type":"Point"}
}