{
  "type": "Feature",
  "properties": {
    "iso:country":"US",
    "sg:address":"10890 Co Rd X",
    "sg:city":"Portage",
    "sg:classifiers":[
        {
            "category":"Shopping",
            "type":"Retail Goods"
        }
    ],
    "sg:phone":"+1 608 981 2365",
    "sg:postcode":"53901",
    "sg:province":"WI",
    "sg:tags":[
        "wedding",
        "supply"
    ],
    "wof:name":"Vickie's Wedding Svc",
    "wof:placetype":"venue"
},
  "geometry": {"coordinates":[-89.537191,43.613402],"type":"Point"}
}