{
  "type": "Feature",
  "properties": {
    "iso:country":"US",
    "sg:address":"202 Main St",
    "sg:city":"Mosinee",
    "sg:classifiers":[
        {
            "category":"Bars & Pubs",
            "type":"Food & Drink"
        }
    ],
    "sg:phone":"+1 715 692 2222",
    "sg:postcode":"54455",
    "sg:province":"WI",
    "sg:tags":[
        "drinking"
    ],
    "wof:name":"Dinger's Sports Bar",
    "wof:placetype":"venue"
},
  "geometry": {"coordinates":[-89.701431,44.791757],"type":"Point"}
}