{
  "type": "Feature",
  "properties": {
    "iso:country":"US",
    "sg:address":"136 Jackson St",
    "sg:city":"Oshkosh",
    "sg:classifiers":[
        {
            "category":"Health Services",
            "subcategory":"Doctor",
            "type":"Services"
        }
    ],
    "sg:phone":"+1 920 231 0110",
    "sg:postcode":"54901",
    "sg:province":"WI",
    "wof:name":"Jumes George M",
    "wof:placetype":"venue"
},
  "geometry": {"coordinates":[-88.54246500000001,44.018087],"type":"Point"}
}