{
  "type": "Feature",
  "properties": {
    "iso:country":"US",
    "sg:address":"2629 N Downer Ave",
    "sg:city":"Milwaukee",
    "sg:classifiers":[
        {
            "category":"Home & Garden",
            "subcategory":"Hardware",
            "type":"Retail Goods"
        }
    ],
    "sg:phone":"+1 414 332 2820",
    "sg:postcode":"53211",
    "sg:province":"WI",
    "wof:name":"Downer Hardware Inc",
    "wof:placetype":"venue"
},
  "geometry": {"coordinates":[-87.878141,43.066974],"type":"Point"}
}