{
  "type": "Feature",
  "properties": {
    "addr:full":"6666 S 20th St Milwaukee WI 53221",
    "addr:housenumber":"6666",
    "addr:postcode":"53221",
    "addr:street":"S 20Th St",
    "iso:country":"US",
    "sg:address":"6666 S 20th St",
    "sg:city":"Milwaukee",
    "sg:classifiers":[
        {
            "category":"Building & Trades",
            "subcategory":"Cleaning & Sanitation",
            "type":"Services"
        }
    ],
    "sg:phone":"+1 414 761 6411",
    "sg:postcode":"53221",
    "sg:province":"WI",
    "sg:tags":[
        "ventilating",
        "system",
        "maintenance"
    ],
    "wof:name":"Advanced Maintenance LLC",
    "wof:placetype":"venue"
},
  "geometry": {"coordinates":[-87.94026700000001,42.925201],"type":"Point"}
}