{
  "type": "Feature",
  "properties": {
    "iso:country":"US",
    "sg:address":"8175 Rolling Hills Dr",
    "sg:city":"Fond Du Lac",
    "sg:classifiers":[
        {
            "category":"Manufacturing",
            "subcategory":"Metals",
            "type":"Manufacturing & Wholesale Goods"
        }
    ],
    "sg:phone":"+1 920 921 9206",
    "sg:postcode":"54935",
    "sg:province":"WI",
    "sg:tags":[
        "tool",
        "mfg"
    ],
    "wof:name":"Goldfire Ltd",
    "wof:placetype":"venue"
},
  "geometry": {"coordinates":[-88.371087,43.836406],"type":"Point"}
}