{
  "type": "Feature",
  "properties": {
    "iso:country":"US",
    "sg:address":"513 E Wisconsin Ave",
    "sg:city":"Appleton",
    "sg:classifiers":[
        {
            "category":"Manufacturing",
            "subcategory":"Tools & Machinery",
            "type":"Manufacturing & Wholesale Goods"
        }
    ],
    "sg:phone":"+1 920 730 0615",
    "sg:postcode":"54911",
    "sg:province":"WI",
    "sg:tags":[
        "lab",
        "mfg"
    ],
    "wof:name":"Centerline Inc",
    "wof:placetype":"venue"
},
  "geometry": {"coordinates":[-88.399362,44.272841],"type":"Point"}
}