{
  "type": "Feature",
  "properties": {
    "addr:full":"6105 8th Ct Westfield WI 53964",
    "addr:housenumber":"6105",
    "addr:postcode":"53964",
    "addr:street":"8Th Ct",
    "iso:country":"US",
    "sg:address":"6105 8th Ct",
    "sg:city":"Westfield",
    "sg:classifiers":[
        {
            "category":"Professional",
            "subcategory":"Business Services",
            "type":"Services"
        }
    ],
    "sg:phone":"+1 608 296 1576",
    "sg:postcode":"53964",
    "sg:province":"WI",
    "sg:tags":[
        "appraiser"
    ],
    "wof:name":"A-1 Appraisals",
    "wof:placetype":"venue"
},
  "geometry": {"coordinates":[-89.460263,43.862532],"type":"Point"}
}