{
  "type": "Feature",
  "properties": {
    "iso:country":"US",
    "sg:address":"3733 S 34th St",
    "sg:city":"Milwaukee",
    "sg:classifiers":[
        {
            "category":"Professional",
            "subcategory":"Computer Services",
            "type":"Services"
        }
    ],
    "sg:phone":"+1 414 643 8775",
    "sg:postcode":"53221",
    "sg:province":"WI",
    "sg:tags":[
        "datum"
    ],
    "wof:name":"Giantessorg",
    "wof:placetype":"venue"
},
  "geometry": {"coordinates":[-87.957063,42.979247],"type":"Point"}
}