{
  "type": "Feature",
  "properties": {
    "iso:country":"US",
    "sg:address":"165 Bishops Way",
    "sg:city":"Brookfield",
    "sg:classifiers":[
        {
            "category":"Insurance",
            "subcategory":"Insurance Agent",
            "type":"Services"
        }
    ],
    "sg:phone":"+1 262 641 9827",
    "sg:postcode":"53005",
    "sg:province":"WI",
    "wof:name":"AGIS Insurance Inc",
    "wof:placetype":"venue"
},
  "geometry": {"coordinates":[-88.07942199999999,43.030655],"type":"Point"}
}