{
  "type": "Feature",
  "properties": {
    "iso:country":"US",
    "sg:address":"988 Main St",
    "sg:city":"Genoa City",
    "sg:classifiers":[
        {
            "category":"Building & Trades",
            "subcategory":"Construction",
            "type":"Services"
        }
    ],
    "sg:phone":"+1 262 279 5424",
    "sg:postcode":"53128",
    "sg:province":"WI",
    "wof:name":"Wick Buildings",
    "wof:placetype":"venue"
},
  "geometry": {"coordinates":[-88.338286,42.498373],"type":"Point"}
}