{
  "type": "Feature",
  "properties": {
    "iso:country":"US",
    "sg:address":"2127 Jackson St",
    "sg:city":"Oshkosh",
    "sg:classifiers":[
        {
            "category":"Banks & Credit Unions",
            "subcategory":"Bank",
            "type":"Services"
        }
    ],
    "sg:phone":"+1 920 236 6605",
    "sg:postcode":"54901",
    "sg:province":"WI",
    "wof:name":"Associated Bank",
    "wof:placetype":"venue"
},
  "geometry": {"coordinates":[-88.542742,44.043743],"type":"Point"}
}