{
  "type": "Feature",
  "properties": {
    "iso:country":"US",
    "sg:address":"3850 N Bremen St",
    "sg:city":"Milwaukee",
    "sg:classifiers":[
        {
            "category":"Banks & Credit Unions",
            "subcategory":"Bank",
            "type":"Services"
        }
    ],
    "sg:phone":"+1 414 332 3800",
    "sg:postcode":"53212",
    "sg:province":"WI",
    "sg:tags":[
        "personal",
        "car",
        "institution"
    ],
    "wof:name":"United Armred Svcs of Wsconsin",
    "wof:placetype":"venue"
},
  "geometry": {"coordinates":[-87.899462,43.085803],"type":"Point"}
}