{
  "type": "Feature",
  "properties": {
    "iso:country":"US",
    "sg:address":"2978 Voyager Dr",
    "sg:city":"Green Bay",
    "sg:classifiers":[
        {
            "category":"Professional",
            "subcategory":"Computer Services",
            "type":"Services"
        }
    ],
    "sg:phone":"+1 920 432 4454",
    "sg:postcode":"54311",
    "sg:province":"WI",
    "sg:tags":[
        "development",
        "consulting",
        "it",
        "software"
    ],
    "wof:name":"Dynamic Software Inc",
    "wof:placetype":"venue"
},
  "geometry": {"coordinates":[-87.93284800000001,44.48593],"type":"Point"}
}