{
  "type": "Feature",
  "properties": {
    "iso:country":"US",
    "sg:address":"323 S Hartwell Ave",
    "sg:city":"Waukesha",
    "sg:classifiers":[
        {
            "category":"Home & Garden",
            "subcategory":"Building Materials",
            "type":"Retail Goods"
        }
    ],
    "sg:phone":"+1 262 542 9282",
    "sg:postcode":"53186",
    "sg:province":"WI",
    "sg:tags":[
        "windows"
    ],
    "wof:name":"Homelite Custom Windows",
    "wof:placetype":"venue"
},
  "geometry": {"coordinates":[-88.221865,42.999098],"type":"Point"}
}