{
  "type": "Feature",
  "properties": {
    "iso:country":"US",
    "sg:address":"320 S Main St",
    "sg:city":"Rice Lake",
    "sg:classifiers":[
        {
            "category":"Building & Trades",
            "subcategory":"Construction",
            "type":"Services"
        }
    ],
    "sg:phone":"+1 715 234 2868",
    "sg:postcode":"54868",
    "sg:province":"WI",
    "sg:tags":[
        "contractor"
    ],
    "wof:name":"Esco Insulation Pdts & Svcs",
    "wof:placetype":"venue"
},
  "geometry": {"coordinates":[-91.733443,45.497503],"type":"Point"}
}