{
  "type": "Feature",
  "properties": {
    "iso:country":"US",
    "sg:address":"2604 280th Ave",
    "sg:city":"Salem",
    "sg:classifiers":[
        {
            "category":"Recreation",
            "type":"Entertainment"
        }
    ],
    "sg:phone":"+1 262 537 2262",
    "sg:postcode":"53168",
    "sg:province":"WI",
    "sg:tags":[
        "stable"
    ],
    "wof:name":"Karen's Quarter Horse Ranch",
    "wof:placetype":"venue"
},
  "geometry": {"coordinates":[-88.149284,42.617627],"type":"Point"}
}