{
  "type": "Feature",
  "properties": {
    "iso:country":"US",
    "sg:address":"2907 Co Rd A",
    "sg:city":"Baraboo",
    "sg:classifiers":[
        {
            "category":"Wholesale",
            "subcategory":"Machinery & Supplies",
            "type":"Manufacturing & Wholesale Goods"
        }
    ],
    "sg:phone":"+1 608 356 6670",
    "sg:postcode":"53913",
    "sg:province":"WI",
    "wof:name":"Glacier Valley Enterprises",
    "wof:placetype":"venue"
},
  "geometry": {"coordinates":[-89.738409,43.549175],"type":"Point"}
}