{
  "type": "Feature",
  "properties": {
    "iso:country":"US",
    "sg:address":"1921 Green Tree Rd",
    "sg:city":"West Bend",
    "sg:classifiers":[
        {
            "category":"Building & Trades",
            "subcategory":"Construction",
            "type":"Services"
        }
    ],
    "sg:phone":"+1 262 338 9947",
    "sg:postcode":"53090",
    "sg:province":"WI",
    "sg:tags":[
        "contractor"
    ],
    "wof:name":"Capital Construction",
    "wof:placetype":"venue"
},
  "geometry": {"coordinates":[-88.194281,43.444667],"type":"Point"}
}