{
  "type": "Feature",
  "properties": {
    "iso:country":"US",
    "sg:address":"174 S Royal Ave",
    "sg:city":"Fond Du Lac",
    "sg:classifiers":[
        {
            "category":"Wholesale",
            "subcategory":"Electrical",
            "type":"Manufacturing & Wholesale Goods"
        }
    ],
    "sg:phone":"+1 920 921 0031",
    "sg:postcode":"54935",
    "sg:province":"WI",
    "sg:tags":[
        "equipment"
    ],
    "wof:name":"Toneheirs Enterprises Inc",
    "wof:placetype":"venue"
},
  "geometry": {"coordinates":[-88.421848,43.772427],"type":"Point"}
}