{
  "type": "Feature",
  "properties": {
    "iso:country":"US",
    "sg:address":"8696 N Reedsburg Rd",
    "sg:city":"Reedsburg",
    "sg:classifiers":[
        {
            "category":"Professional",
            "type":"Services"
        }
    ],
    "sg:phone":"+1 608 524 0360",
    "sg:postcode":"53959",
    "sg:province":"WI",
    "wof:name":"David Gjerseth",
    "wof:placetype":"venue"
},
  "geometry": {"coordinates":[-89.88710399999999,43.540313],"type":"Point"}
}