{
  "type": "Feature",
  "properties": {
    "iso:country":"US",
    "sg:address":"36353 Main St",
    "sg:city":"Whitehall",
    "sg:classifiers":[
        {
            "category":"Insurance",
            "subcategory":"Insurance Agent",
            "type":"Services"
        }
    ],
    "sg:phone":"+1 715 538 4001",
    "sg:postcode":"54773",
    "sg:province":"WI",
    "wof:name":"Gretchen Erickson Insurance",
    "wof:placetype":"venue"
},
  "geometry": {"coordinates":[-91.316765,44.369348],"type":"Point"}
}