{
  "type": "Feature",
  "properties": {
    "addr:full":"2009 Wyoming Ave Superior WI 54880",
    "addr:housenumber":"2009",
    "addr:postcode":"54880",
    "addr:street":"Wyoming Ave",
    "iso:country":"US",
    "sg:address":"2009 Wyoming Ave",
    "sg:city":"Superior",
    "sg:classifiers":[
        {
            "category":"Shopping",
            "type":"Retail Goods"
        }
    ],
    "sg:phone":"+1 715 394 6185",
    "sg:postcode":"54880",
    "sg:province":"WI",
    "sg:tags":[
        "merchandise"
    ],
    "wof:name":"Watkins Products",
    "wof:placetype":"venue"
},
  "geometry": {"coordinates":[-92.124527,46.713607],"type":"Point"}
}