{
  "type": "Feature",
  "properties": {
    "addr:full":"9084 Co Rd Es East Troy WI 53120",
    "addr:housenumber":"9084",
    "addr:postcode":"53120",
    "addr:street":"Co Rd",
    "iso:country":"US",
    "sg:address":"9084 Co Rd Es",
    "sg:city":"East Troy",
    "sg:classifiers":[
        {
            "category":"Manufacturing",
            "subcategory":"Tools & Machinery",
            "type":"Manufacturing & Wholesale Goods"
        }
    ],
    "sg:phone":"+1 262 642 5323",
    "sg:postcode":"53120",
    "sg:province":"WI",
    "sg:tags":[
        "machine",
        "shop"
    ],
    "wof:name":"S & G Self Storage",
    "wof:placetype":"venue"
},
  "geometry": {"coordinates":[-88.35926000000001,42.823571],"type":"Point"}
}