{
  "type": "Feature",
  "properties": {
    "iso:country":"US",
    "sg:address":"442 S Hickory St",
    "sg:city":"Fond Du Lac",
    "sg:classifiers":[
        {
            "category":"Insurance",
            "subcategory":"Insurance Agent",
            "type":"Services"
        }
    ],
    "sg:phone":"+1 920 922 7480",
    "sg:postcode":"54935",
    "sg:province":"WI",
    "wof:name":"Bob Schuchardt Insurance Inc",
    "wof:placetype":"venue"
},
  "geometry": {"coordinates":[-88.462082,43.767307],"type":"Point"}
}