{
  "type": "Feature",
  "properties": {
    "iso:country":"US",
    "sg:address":"108 Parallel St",
    "sg:city":"Beaver Dam",
    "sg:classifiers":[
        {
            "category":"Education",
            "subcategory":"Special Training",
            "type":"Public Place"
        }
    ],
    "sg:phone":"+1 920 887 7727",
    "sg:postcode":"53916",
    "sg:province":"WI",
    "sg:tags":[
        "instruction",
        "driving"
    ],
    "wof:name":"Best Way Driving School",
    "wof:placetype":"venue"
},
  "geometry": {"coordinates":[-88.830865,43.468761],"type":"Point"}
}