{
  "type": "Feature",
  "properties": {
    "addr:full":"6155 W Fond du Lac Ave Milwaukee WI 53218",
    "addr:housenumber":"6155",
    "addr:postcode":"53218",
    "addr:street":"W Fond Du Lac Ave",
    "iso:country":"US",
    "sg:address":"6155 W Fond du Lac Ave",
    "sg:city":"Milwaukee",
    "sg:classifiers":[
        {
            "category":"Professional",
            "type":"Services"
        }
    ],
    "sg:phone":"+1 414 527 3018",
    "sg:postcode":"53218",
    "sg:province":"WI",
    "sg:tags":[
        "establishment"
    ],
    "wof:name":"Brondel Inc",
    "wof:placetype":"venue"
},
  "geometry": {"coordinates":[-87.98774,43.098517],"type":"Point"}
}