{
  "type": "Feature",
  "properties": {
    "iso:country":"US",
    "sg:address":"115 School St",
    "sg:city":"Gays Mills",
    "sg:classifiers":[
        {
            "category":"Organizations",
            "subcategory":"Religious Organization",
            "type":"Services"
        }
    ],
    "sg:phone":"+1 608 735 4420",
    "sg:postcode":"54631",
    "sg:province":"WI",
    "wof:name":"St Marys Parish",
    "wof:placetype":"venue"
},
  "geometry": {"coordinates":[-90.846369,43.314799],"type":"Point"}
}