{
  "type": "Feature",
  "properties": {
    "iso:country":"US",
    "sg:address":"8170 N Granville Woods Rd",
    "sg:city":"Milwaukee",
    "sg:classifiers":[
        {
            "category":"Wholesale",
            "subcategory":"Farm Supplies",
            "type":"Manufacturing & Wholesale Goods"
        }
    ],
    "sg:phone":"+1 414 355 2300",
    "sg:postcode":"53223",
    "sg:province":"WI",
    "sg:tags":[
        "horticultural",
        "product"
    ],
    "sg:website":"www.carlinsales.com",
    "wof:name":"Carlin Sales Corp",
    "wof:placetype":"venue"
},
  "geometry": {"coordinates":[-87.996323,43.166084],"type":"Point"}
}