{
  "type": "Feature",
  "properties": {
    "addr:full":"435 W Starin Rd Whitewater WI 53190",
    "addr:housenumber":"435",
    "addr:postcode":"53190",
    "addr:street":"W Starin Rd",
    "iso:country":"US",
    "sg:address":"435 W Starin Rd",
    "sg:city":"Whitewater",
    "sg:classifiers":[
        {
            "category":"Organizations",
            "subcategory":"Professional Association",
            "type":"Services"
        }
    ],
    "sg:phone":"+1 262 473 5209",
    "sg:postcode":"53190",
    "sg:province":"WI",
    "sg:tags":[
        "membership"
    ],
    "wof:name":"World Federalist Association",
    "wof:placetype":"venue"
},
  "geometry": {"coordinates":[-88.735268,42.839865],"type":"Point"}
}