{
  "type": "Feature",
  "properties": {
    "iso:country":"US",
    "sg:address":"443 E Grand Ave",
    "sg:city":"Beloit",
    "sg:classifiers":[
        {
            "category":"Shopping",
            "subcategory":"Gifts & Souvenirs",
            "type":"Retail Goods"
        }
    ],
    "sg:phone":"+1 608 365 5159",
    "sg:postcode":"53511",
    "sg:province":"WI",
    "wof:name":"Midnight Sun",
    "wof:placetype":"venue"
},
  "geometry": {"coordinates":[-89.034888,42.499686],"type":"Point"}
}