{
  "type": "Feature",
  "properties": {
    "iso:country":"US",
    "sg:address":"1310 N Main St",
    "sg:city":"Viroqua",
    "sg:classifiers":[
        {
            "category":"Autos & Motor Vehicles",
            "subcategory":"Automobile Sales",
            "type":"Retail Goods"
        }
    ],
    "sg:phone":"+1 608 637 3482",
    "sg:postcode":"54665",
    "sg:province":"WI",
    "sg:tags":[
        "car",
        "dealer"
    ],
    "wof:name":"Vernon County Chrysler Jeep",
    "wof:placetype":"venue"
},
  "geometry": {"coordinates":[-90.888966,43.567423],"type":"Point"}
}