{
  "type": "Feature",
  "properties": {
    "addr:full":"824 E Perkins St Medford WI 54451",
    "addr:housenumber":"824",
    "addr:postcode":"54451",
    "addr:street":"E Perkins St",
    "iso:country":"US",
    "sg:address":"824 E Perkins St",
    "sg:city":"Medford",
    "sg:classifiers":[
        {
            "category":"Organizations",
            "subcategory":"Religious Organization",
            "type":"Services"
        }
    ],
    "sg:phone":"+1 715 748 9331",
    "sg:postcode":"54451",
    "sg:province":"WI",
    "sg:tags":[
        "church"
    ],
    "wof:name":"Medford Area United Pentecost",
    "wof:placetype":"venue"
},
  "geometry": {"coordinates":[-90.332499,45.134607],"type":"Point"}
}