{
  "type": "Feature",
  "properties": {
    "iso:country":"US",
    "sg:address":"234 Walnut St",
    "sg:city":"Spooner",
    "sg:classifiers":[
        {
            "category":"Home & Garden",
            "subcategory":"Furniture",
            "type":"Retail Goods"
        }
    ],
    "sg:phone":"+1 715 635 2927",
    "sg:postcode":"54801",
    "sg:province":"WI",
    "sg:tags":[
        "furnishing"
    ],
    "wof:name":"Dahl's Home Store",
    "wof:placetype":"venue"
},
  "geometry": {"coordinates":[-91.889167,45.827073],"type":"Point"}
}