{
  "type": "Feature",
  "properties": {
    "iso:country":"US",
    "sg:address":"70 Church St",
    "sg:city":"Algoma",
    "sg:classifiers":[
        {
            "category":"Restaurant",
            "type":"Food & Drink"
        }
    ],
    "sg:phone":"+1 920 487 3244",
    "sg:postcode":"54201",
    "sg:province":"WI",
    "wof:name":"Pier 42 Marina On The Lake",
    "wof:placetype":"venue"
},
  "geometry": {"coordinates":[-87.43334400000001,44.610009],"type":"Point"}
}