{
  "type": "Feature",
  "properties": {
    "iso:country":"US",
    "sg:address":"824 E Johnson St",
    "sg:city":"Madison",
    "sg:classifiers":[
        {
            "category":"Recreation",
            "type":"Entertainment"
        }
    ],
    "sg:phone":"+1 608 287 1100",
    "sg:postcode":"53703",
    "sg:province":"WI",
    "sg:tags":[
        "art",
        "gallery"
    ],
    "wof:name":"Wendy Cooper Gallery LLC",
    "wof:placetype":"venue"
},
  "geometry": {"coordinates":[-89.37656699999999,43.084192],"type":"Point"}
}