{
  "type": "Feature",
  "properties": {
    "addr:full":"2193 S 60th St Milwaukee WI 53219",
    "addr:housenumber":"2193",
    "addr:postcode":"53219",
    "addr:street":"S 60Th St",
    "iso:country":"US",
    "sg:address":"2193 S 60th St",
    "sg:city":"Milwaukee",
    "sg:classifiers":[
        {
            "category":"Personal",
            "type":"Services"
        }
    ],
    "sg:phone":"+1 414 327 3090",
    "sg:postcode":"53219",
    "sg:province":"WI",
    "wof:name":"Inch By Inch Tanning",
    "wof:placetype":"venue"
},
  "geometry": {"coordinates":[-87.987494,43.006674],"type":"Point"}
}