{
  "type": "Feature",
  "properties": {
    "iso:country":"US",
    "sg:address":"3742 N Teutonia Ave",
    "sg:city":"Milwaukee",
    "sg:classifiers":[
        {
            "category":"Building & Trades",
            "subcategory":"Cleaning & Sanitation",
            "type":"Services"
        }
    ],
    "sg:phone":"+1 414 444 7477",
    "sg:postcode":"53206",
    "sg:province":"WI",
    "sg:tags":[
        "butler",
        "maid"
    ],
    "wof:name":"Tailor Maid Fades",
    "wof:placetype":"venue"
},
  "geometry": {"coordinates":[-87.936593,43.085539],"type":"Point"}
}