{
  "type": "Feature",
  "properties": {
    "iso:country":"US",
    "sg:address":"3630 Co Rd B",
    "sg:city":"La Crosse",
    "sg:classifiers":[
        {
            "category":"Organizations",
            "subcategory":"Religious Organization",
            "type":"Services"
        }
    ],
    "sg:phone":"+1 608 782 7833",
    "sg:postcode":"54601",
    "sg:province":"WI",
    "sg:tags":[
        "church"
    ],
    "sg:website":"www.ccc-pca.org",
    "wof:name":"Christ Covenant Church PCA",
    "wof:placetype":"venue"
},
  "geometry": {"coordinates":[-91.20586299999999,43.858231],"type":"Point"}
}