{
  "type": "Feature",
  "properties": {
    "addr:full":"917 Main St Plum City WI 54761",
    "addr:housenumber":"917",
    "addr:postcode":"54761",
    "addr:street":"Main St",
    "iso:country":"US",
    "sg:address":"917 Main St",
    "sg:city":"Plum City",
    "sg:classifiers":[
        {
            "category":"Autos & Motor Vehicles",
            "subcategory":"Fuel & Gas Station",
            "type":"Retail Goods"
        }
    ],
    "sg:phone":"+1 715 647 2100",
    "sg:postcode":"54761",
    "sg:province":"WI",
    "sg:tags":[
        "product",
        "petroleum",
        "convenience"
    ],
    "wof:name":"Binkowski Oil Co",
    "wof:placetype":"venue"
},
  "geometry": {"coordinates":[-92.192624,44.635027],"type":"Point"}
}