{
  "type": "Feature",
  "properties": {
    "iso:country":"US",
    "sg:address":"1671 Blueberry Rd",
    "sg:city":"Edgar",
    "sg:classifiers":[
        {
            "category":"Retail",
            "subcategory":"Repair Shop",
            "type":"Services"
        }
    ],
    "sg:phone":"+1 715 687 3218",
    "sg:postcode":"54426",
    "sg:province":"WI",
    "sg:tags":[
        "farming",
        "dairy",
        "motor",
        "silo"
    ],
    "wof:name":"R & R Sales",
    "wof:placetype":"venue"
},
  "geometry": {"coordinates":[-90.106401,44.887341],"type":"Point"}
}