{
  "type": "Feature",
  "properties": {
    "addr:full":"1709 S Park St Madison WI 53713",
    "addr:housenumber":"1709",
    "addr:postcode":"53713",
    "addr:street":"S Park St",
    "iso:country":"US",
    "sg:address":"1709 S Park St",
    "sg:city":"Madison",
    "sg:classifiers":[
        {
            "category":"Social Services",
            "type":"Services"
        }
    ],
    "sg:phone":"+1 608 259 9499",
    "sg:postcode":"53713",
    "sg:province":"WI",
    "wof:name":"Thomaslarue Assoc",
    "wof:placetype":"venue"
},
  "geometry": {"coordinates":[-89.393967,43.047672],"type":"Point"}
}