{
  "type": "Feature",
  "properties": {
    "iso:country":"US",
    "sg:address":"7203 Edgehill Rd",
    "sg:city":"Greendale",
    "sg:classifiers":[
        {
            "category":"Building & Trades",
            "subcategory":"Construction",
            "type":"Services"
        }
    ],
    "sg:phone":"+1 414 881 5907",
    "sg:postcode":"53129",
    "sg:province":"WI",
    "sg:tags":[
        "residential"
    ],
    "wof:name":"G&S Cnstrction Mtro Mlwkee LLC",
    "wof:placetype":"venue"
},
  "geometry": {"coordinates":[-88.005337,42.940891],"type":"Point"}
}