{
  "type": "Feature",
  "properties": {
    "iso:country":"US",
    "sg:address":"424 S 3rd St",
    "sg:city":"Cedar Grove",
    "sg:classifiers":[
        {
            "category":"Building & Trades",
            "subcategory":"Electrical",
            "type":"Services"
        }
    ],
    "sg:phone":"+1 920 668 8001",
    "sg:postcode":"53013",
    "sg:province":"WI",
    "sg:tags":[
        "electrical",
        "contractor"
    ],
    "wof:name":"D & D Electric",
    "wof:placetype":"venue"
},
  "geometry": {"coordinates":[-87.82673,43.566857],"type":"Point"}
}