{
  "type": "Feature",
  "properties": {
    "addr:full":"4115 N 56th St Milwaukee WI 53216",
    "addr:housenumber":"4115",
    "addr:postcode":"53216",
    "addr:street":"N 56Th St",
    "iso:country":"US",
    "sg:address":"4115 N 56th St",
    "sg:city":"Milwaukee",
    "sg:classifiers":[
        {
            "category":"Utilities",
            "subcategory":"Mobile Phone",
            "type":"Services"
        },
        {
            "category":"Shopping",
            "subcategory":"Mobile Phones",
            "type":"Retail Goods"
        },
        {
            "category":"Utilities",
            "subcategory":"Telephone",
            "type":"Services"
        },
        {
            "category":"Professional",
            "subcategory":"Computer Services",
            "type":"Services"
        }
    ],
    "sg:phone":"+1 414 444 0278",
    "sg:postcode":"53216",
    "sg:province":"WI",
    "sg:tags":[
        "telecommunication",
        "supply",
        "communication",
        "system",
        "wireless",
        "equipment",
        "cellular"
    ],
    "sg:website":"http://clickserve.dartsearch.net/link/click?lid=43000000308049899",
    "wof:name":"T-Mobile",
    "wof:placetype":"venue"
},
  "geometry": {"coordinates":[-87.983107,43.090902],"type":"Point"}
}