{
  "type": "Feature",
  "properties": {
    "addr:full":"1935 N Water St Milwaukee WI 53202",
    "addr:housenumber":"1935",
    "addr:postcode":"53202",
    "addr:street":"N Water St",
    "iso:country":"US",
    "sg:address":"1935 N Water St",
    "sg:city":"Milwaukee",
    "sg:classifiers":[
        {
            "category":"Restaurant",
            "type":"Food & Drink"
        }
    ],
    "sg:menulink":"http://www.allmenus.com/wi/milwaukee/141291-good-life/menu/",
    "sg:phone":"+1 414 271 5375",
    "sg:postcode":"53202",
    "sg:province":"WI",
    "sg:tags":[
        "caribbean"
    ],
    "wof:name":"Good Life",
    "wof:placetype":"venue"
},
  "geometry": {"coordinates":[-87.89869899999999,43.056165],"type":"Point"}
}