{
  "type": "Feature",
  "properties": {
    "iso:country":"US",
    "sg:address":"7828 Parkside Ct",
    "sg:city":"Minocqua",
    "sg:classifiers":[
        {
            "category":"Building & Trades",
            "subcategory":"Landscaping Services",
            "type":"Services"
        }
    ],
    "sg:phone":"+1 715 356 4099",
    "sg:postcode":"54548",
    "sg:province":"WI",
    "sg:tags":[
        "landscape",
        "contractor"
    ],
    "wof:name":"Lakeland Landscaping Inc",
    "wof:placetype":"venue"
},
  "geometry": {"coordinates":[-89.732542,45.845511],"type":"Point"}
}