{
  "type": "Feature",
  "properties": {
    "iso:country":"US",
    "sg:address":"400 Co Hwy H",
    "sg:city":"Elkhorn",
    "sg:classifiers":[
        {
            "category":"Education",
            "subcategory":"Junior College",
            "type":"Public Place"
        }
    ],
    "sg:phone":"+1 262 741 6100",
    "sg:postcode":"53121",
    "sg:province":"WI",
    "wof:name":"Gateway Technical College",
    "wof:placetype":"venue"
},
  "geometry": {"coordinates":[-88.533774,42.670013],"type":"Point"}
}