{
  "type": "Feature",
  "properties": {
    "iso:country":"US",
    "sg:address":"249 Rittenhouse Ave",
    "sg:city":"Bayfield",
    "sg:classifiers":[
        {
            "category":"Travel",
            "subcategory":"Hotels & Motels",
            "type":"Entertainment"
        }
    ],
    "sg:phone":"+1 715 779 5575",
    "sg:postcode":"54814",
    "sg:province":"WI",
    "sg:tags":[
        "breakfast",
        "accommodation",
        "bed"
    ],
    "wof:name":"Silvernail Guest House",
    "wof:placetype":"venue"
},
  "geometry": {"coordinates":[-90.817769,46.811051],"type":"Point"}
}