{
  "type": "Feature",
  "properties": {
    "iso:country":"US",
    "sg:address":"118 W Session St",
    "sg:city":"Waupaca",
    "sg:classifiers":[
        {
            "category":"Banks & Credit Unions",
            "subcategory":"Bank",
            "type":"Services"
        }
    ],
    "sg:phone":"+1 715 258 1413",
    "sg:postcode":"54981",
    "sg:province":"WI",
    "wof:name":"Farmers State Bank",
    "wof:placetype":"venue"
},
  "geometry": {"coordinates":[-89.086017,44.358894],"type":"Point"}
}