{
  "type": "Feature",
  "properties": {
    "iso:country":"US",
    "sg:address":"3085 Hawks Haven Trl",
    "sg:city":"De Forest",
    "sg:classifiers":[
        {
            "category":"Professional",
            "subcategory":"Business Services",
            "type":"Services"
        }
    ],
    "sg:phone":"+1 608 846 9172",
    "sg:postcode":"53532",
    "sg:province":"WI",
    "sg:tags":[
        "interior",
        "consultant",
        "design",
        "decorator"
    ],
    "wof:name":"Legacy Design-Nancy Startup",
    "wof:placetype":"venue"
},
  "geometry": {"coordinates":[-89.238539,43.247456],"type":"Point"}
}