{
  "type": "Feature",
  "properties": {
    "iso:country":"US",
    "sg:address":"1500 Quincy Ave",
    "sg:city":"Racine",
    "sg:classifiers":[
        {
            "category":"Professional",
            "subcategory":"Business Services",
            "type":"Services"
        }
    ],
    "sg:phone":"+1 262 632 3164",
    "sg:postcode":"53405",
    "sg:province":"WI",
    "wof:name":"Red Snapper Productions",
    "wof:placetype":"venue"
},
  "geometry": {"coordinates":[-87.81367899999999,42.7124],"type":"Point"}
}