{
  "type": "Feature",
  "properties": {
    "addr:full":"422 Cass St La Crosse WI 54601",
    "addr:housenumber":"422",
    "addr:postcode":"54601",
    "addr:street":"Cass St",
    "iso:country":"US",
    "sg:address":"422 Cass St",
    "sg:city":"La Crosse",
    "sg:classifiers":[
        {
            "category":"Insurance",
            "subcategory":"Insurance Agent",
            "type":"Services"
        }
    ],
    "sg:phone":"+1 608 782 2266",
    "sg:postcode":"54601",
    "sg:province":"WI",
    "sg:tags":[
        "adjuster"
    ],
    "wof:name":"LA Crosse Claim Svc",
    "wof:placetype":"venue"
},
  "geometry": {"coordinates":[-91.250311,43.808642],"type":"Point"}
}