{
  "type": "Feature",
  "properties": {
    "addr:full":"2111 Industrial St Wisconsin Rapids WI 54495",
    "addr:housenumber":"2111",
    "addr:postcode":"54495",
    "addr:street":"Industrial St",
    "iso:country":"US",
    "sg:address":"2111 Industrial St",
    "sg:city":"Wisconsin Rapids",
    "sg:classifiers":[
        {
            "category":"Shopping",
            "subcategory":"Clothing, Apparel, & Fashions",
            "type":"Retail Goods"
        }
    ],
    "sg:phone":"+1 715 421 1137",
    "sg:postcode":"54495",
    "sg:province":"WI",
    "sg:tags":[
        "uniform"
    ],
    "wof:name":"G & K Svc",
    "wof:placetype":"venue"
},
  "geometry": {"coordinates":[-89.84978099999999,44.401925],"type":"Point"}
}