{
  "type": "Feature",
  "properties": {
    "iso:country":"US",
    "sg:address":"936 Craftsmen Dr",
    "sg:city":"Greenville",
    "sg:classifiers":[
        {
            "category":"Manufacturing",
            "subcategory":"Paper Products",
            "type":"Manufacturing & Wholesale Goods"
        }
    ],
    "sg:phone":"+1 920 721 3945",
    "sg:postcode":"54942",
    "sg:province":"WI",
    "sg:tags":[
        "mill",
        "asphalt",
        "mfg"
    ],
    "wof:name":"Kimberly-Clark",
    "wof:placetype":"venue"
},
  "geometry": {"coordinates":[-88.519111,44.274449],"type":"Point"}
}