{
  "type": "Feature",
  "properties": {
    "addr:full":"4531 Reforestation Rd Green Bay WI 54313",
    "addr:housenumber":"4531",
    "addr:postcode":"54313",
    "addr:street":"Reforestation Rd",
    "iso:country":"US",
    "sg:address":"4531 Reforestation Rd",
    "sg:city":"Green Bay",
    "sg:classifiers":[
        {
            "category":"Professional",
            "subcategory":"Engineering",
            "type":"Services"
        }
    ],
    "sg:phone":"+1 920 884 1093",
    "sg:postcode":"54313",
    "sg:province":"WI",
    "wof:name":"Ensr Corporation",
    "wof:placetype":"venue"
},
  "geometry": {"coordinates":[-88.09038099999999,44.655545],"type":"Point"}
}