{
  "type": "Feature",
  "properties": {
    "iso:country":"US",
    "sg:address":"145 E Wisconsin Ave",
    "sg:city":"Oconomowoc",
    "sg:classifiers":[
        {
            "category":"Food & Beverages",
            "subcategory":"Bakery",
            "type":"Retail Goods"
        }
    ],
    "sg:phone":"+1 262 567 3212",
    "sg:postcode":"53066",
    "sg:province":"WI",
    "sg:tags":[
        "baker"
    ],
    "wof:name":"J P Daytime Bakery Inc",
    "wof:placetype":"venue"
},
  "geometry": {"coordinates":[-88.498012,43.110864],"type":"Point"}
}