{
  "type": "Feature",
  "properties": {
    "iso:country":"US",
    "sg:address":"223 W State St",
    "sg:city":"Fox Lake",
    "sg:classifiers":[
        {
            "category":"Organizations",
            "subcategory":"Religious Organization",
            "type":"Services"
        }
    ],
    "sg:phone":"+1 920 928 6610",
    "sg:postcode":"53933",
    "sg:province":"WI",
    "sg:tags":[
        "church"
    ],
    "wof:name":"Living Hope Community Church",
    "wof:placetype":"venue"
},
  "geometry": {"coordinates":[-88.909403,43.565993],"type":"Point"}
}