{
  "type": "Feature",
  "properties": {
    "addr:full":"2618 Birch St Eau Claire WI 54703",
    "addr:housenumber":"2618",
    "addr:postcode":"54703",
    "addr:street":"Birch St",
    "iso:country":"US",
    "sg:address":"2618 Birch St",
    "sg:city":"Eau Claire",
    "sg:classifiers":[
        {
            "category":"Wholesale",
            "subcategory":"Machinery & Supplies",
            "type":"Manufacturing & Wholesale Goods"
        }
    ],
    "sg:phone":"+1 715 834 5093",
    "sg:postcode":"54703",
    "sg:province":"WI",
    "sg:tags":[
        "construction",
        "fastener",
        "industrial",
        "suppl",
        "threaded"
    ],
    "wof:name":"Fastenal Company",
    "wof:placetype":"venue"
},
  "geometry": {"coordinates":[-91.474828,44.820839],"type":"Point"}
}