{
  "type": "Feature",
  "properties": {
    "iso:country":"US",
    "sg:address":"454 Masters Ln",
    "sg:city":"Green Bay",
    "sg:classifiers":[
        {
            "category":"Real Estate",
            "subcategory":"Real Estate Operator",
            "type":"Services"
        }
    ],
    "sg:phone":"+1 920 406 3696",
    "sg:postcode":"54311",
    "sg:province":"WI",
    "sg:tags":[
        "building",
        "nonresidential"
    ],
    "wof:name":"Marinette County Properties LL",
    "wof:placetype":"venue"
},
  "geometry": {"coordinates":[-87.926187,44.511496],"type":"Point"}
}