{
  "type": "Feature",
  "properties": {
    "iso:country":"US",
    "sg:address":"2501 32nd St S",
    "sg:city":"La Crosse",
    "sg:classifiers":[
        {
            "category":"Real Estate",
            "subcategory":"Real Estate Operator",
            "type":"Services"
        }
    ],
    "sg:phone":"+1 608 787 8326",
    "sg:postcode":"54601",
    "sg:province":"WI",
    "sg:tags":[
        "building",
        "apartment"
    ],
    "wof:name":"River Bluffs Apartment",
    "wof:placetype":"venue"
},
  "geometry": {"coordinates":[-91.20917,43.785565],"type":"Point"}
}