{
  "type": "Feature",
  "properties": {
    "iso:country":"US",
    "sg:address":"801 Randall Pl",
    "sg:city":"Oshkosh",
    "sg:classifiers":[
        {
            "category":"Wholesale",
            "subcategory":"Non-durable Goods",
            "type":"Manufacturing & Wholesale Goods"
        }
    ],
    "sg:phone":"+1 920 237 4748",
    "sg:postcode":"54901",
    "sg:province":"WI",
    "sg:tags":[
        "product",
        "graphic",
        "design",
        "promotional"
    ],
    "wof:name":"K B Images",
    "wof:placetype":"venue"
},
  "geometry": {"coordinates":[-88.53813599999999,44.027795],"type":"Point"}
}