{
  "type": "Feature",
  "properties": {
    "addr:full":"6111 Chuck Ln Eau Claire WI 54703",
    "addr:housenumber":"6111",
    "addr:postcode":"54703",
    "addr:street":"Chuck Ln",
    "iso:country":"US",
    "sg:address":"6111 Chuck Ln",
    "sg:city":"Eau Claire",
    "sg:classifiers":[
        {
            "category":"Retail",
            "subcategory":"Auto Repair",
            "type":"Services"
        }
    ],
    "sg:phone":"+1 715 874 4850",
    "sg:postcode":"54703",
    "sg:province":"WI",
    "sg:tags":[
        "automotive"
    ],
    "wof:name":"Interstate Auto & Towing",
    "wof:placetype":"venue"
},
  "geometry": {"coordinates":[-91.594204,44.845053],"type":"Point"}
}