{
  "type": "Feature",
  "properties": {
    "iso:country":"US",
    "sg:address":"721 Oxford Ave",
    "sg:city":"Eau Claire",
    "sg:classifiers":[
        {
            "category":"Government",
            "subcategory":"Court House",
            "type":"Public Place"
        }
    ],
    "sg:phone":"+1 715 839 4828",
    "sg:postcode":"54703",
    "sg:province":"WI",
    "sg:tags":[
        "county",
        "counsel"
    ],
    "wof:name":"Eau Claire District Attorney",
    "wof:placetype":"venue"
},
  "geometry": {"coordinates":[-91.504845,44.808377],"type":"Point"}
}