{
  "type": "Feature",
  "properties": {
    "addr:full":"211 Hiawatha St Watertown WI 53098",
    "addr:housenumber":"211",
    "addr:postcode":"53098",
    "addr:street":"Hiawatha St",
    "iso:country":"US",
    "sg:address":"211 Hiawatha St",
    "sg:city":"Watertown",
    "sg:classifiers":[
        {
            "category":"School Buses",
            "type":"Transportation"
        }
    ],
    "sg:phone":"+1 920 261 5062",
    "sg:postcode":"53098",
    "sg:province":"WI",
    "sg:tags":[
        "charter"
    ],
    "wof:name":"Tsi",
    "wof:placetype":"venue"
},
  "geometry": {"coordinates":[-88.74519600000001,43.19945],"type":"Point"}
}