{
  "type": "Feature",
  "properties": {
    "iso:country":"US",
    "sg:address":"2211 Fordem Ave",
    "sg:city":"Madison",
    "sg:classifiers":[
        {
            "category":"Manufacturing",
            "subcategory":"Printing",
            "type":"Manufacturing & Wholesale Goods"
        }
    ],
    "sg:phone":"+1 608 244 3561",
    "sg:postcode":"53704",
    "sg:province":"WI",
    "sg:tags":[
        "printer"
    ],
    "sg:website":"www.webcrafters-inc2.com",
    "wof:name":"Webcrafters",
    "wof:placetype":"venue"
},
  "geometry": {"coordinates":[-89.36395,43.101418],"type":"Point"}
}