{
  "type": "Feature",
  "properties": {
    "addr:full":"2340 W Dunwood Rd Milwaukee WI 53209",
    "addr:housenumber":"2340",
    "addr:postcode":"53209",
    "addr:street":"W Dunwood Rd",
    "iso:country":"US",
    "sg:address":"2340 W Dunwood Rd",
    "sg:city":"Milwaukee",
    "sg:classifiers":[
        {
            "category":"Professional",
            "subcategory":"Computer Services",
            "type":"Services"
        }
    ],
    "sg:phone":"+1 414 228 8976",
    "sg:postcode":"53209",
    "sg:province":"WI",
    "sg:tags":[
        "consultant",
        "designer",
        "system"
    ],
    "wof:name":"Shai's Computer Services",
    "wof:placetype":"venue"
},
  "geometry": {"coordinates":[-87.938463,43.157871],"type":"Point"}
}