{
  "type": "Feature",
  "properties": {
    "iso:country":"US",
    "sg:address":"513 4th St",
    "sg:city":"Hudson",
    "sg:classifiers":[
        {
            "category":"Freight",
            "type":"Transportation"
        }
    ],
    "sg:phone":"+1 715 386 6466",
    "sg:postcode":"54016",
    "sg:province":"WI",
    "sg:tags":[
        "station",
        "petroleum"
    ],
    "wof:name":"Yocum Oil Company Inc",
    "wof:placetype":"venue"
},
  "geometry": {"coordinates":[-92.75405000000001,44.975031],"type":"Point"}
}