{
  "type": "Feature",
  "properties": {
    "iso:country":"US",
    "sg:address":"636 N Galvin Ave",
    "sg:city":"Stratford",
    "sg:classifiers":[
        {
            "category":"Farming",
            "subcategory":"Livestock Farm",
            "type":"Manufacturing & Wholesale Goods"
        }
    ],
    "sg:phone":"+1 715 687 4741",
    "sg:postcode":"54484",
    "sg:province":"WI",
    "sg:tags":[
        "chicken"
    ],
    "wof:name":"Cathy Wineman",
    "wof:placetype":"venue"
},
  "geometry": {"coordinates":[-90.139673,44.757337],"type":"Point"}
}