{
  "type": "Feature",
  "properties": {
    "iso:country":"US",
    "sg:address":"1201 Co Rd C",
    "sg:city":"Stevens Point",
    "sg:classifiers":[
        {
            "category":"Retail",
            "subcategory":"Portrait Studio",
            "type":"Services"
        }
    ],
    "sg:phone":"+1 715 341 7005",
    "sg:postcode":"54481",
    "sg:province":"WI",
    "sg:tags":[
        "photo"
    ],
    "wof:name":"Sears Portrait Studio Ka8",
    "wof:placetype":"venue"
},
  "geometry": {"coordinates":[-89.621804,44.518889],"type":"Point"}
}