{
  "type": "Feature",
  "properties": {
    "iso:country":"US",
    "sg:address":"1233 Roosevelt Rd",
    "sg:city":"Niagara",
    "sg:classifiers":[
        {
            "category":"Professional",
            "subcategory":"Computer Services",
            "type":"Services"
        }
    ],
    "sg:phone":"+1 715 251 1122",
    "sg:postcode":"54151",
    "sg:province":"WI",
    "wof:name":"Artisan Networking & Consltng",
    "wof:placetype":"venue"
},
  "geometry": {"coordinates":[-88.00843500000001,45.783867],"type":"Point"}
}