{
  "type": "Feature",
  "properties": {
    "iso:country":"US",
    "sg:address":"1234 Douglas Ave",
    "sg:city":"Racine",
    "sg:classifiers":[
        {
            "category":"Organizations",
            "subcategory":"Community Association",
            "type":"Services"
        }
    ],
    "sg:phone":"+1 262 634 1177",
    "sg:postcode":"53402",
    "sg:province":"WI",
    "wof:name":"American Legion Post 546",
    "wof:placetype":"venue"
},
  "geometry": {"coordinates":[-87.789357,42.736336],"type":"Point"}
}