{
  "type": "Feature",
  "properties": {
    "iso:country":"US",
    "sg:address":"625 Madison St",
    "sg:city":"Burlington",
    "sg:classifiers":[
        {
            "category":"Manufacturing",
            "subcategory":"Tools & Machinery",
            "type":"Manufacturing & Wholesale Goods"
        }
    ],
    "sg:phone":"+1 262 763 3036",
    "sg:postcode":"53105",
    "sg:province":"WI",
    "sg:tags":[
        "equipment",
        "system",
        "automation"
    ],
    "sg:website":"www.encoderoptical.com",
    "wof:name":"Schmitz Engineering Liaison",
    "wof:placetype":"venue"
},
  "geometry": {"coordinates":[-88.263838,42.680753],"type":"Point"}
}