{
  "type": "Feature",
  "properties": {
    "iso:country":"US",
    "sg:address":"2204 Harris Highland Dr",
    "sg:city":"Waukesha",
    "sg:classifiers":[
        {
            "category":"Building & Trades",
            "subcategory":"Construction",
            "type":"Services"
        }
    ],
    "sg:phone":"+1 262 549 9640",
    "sg:postcode":"53188",
    "sg:province":"WI",
    "sg:tags":[
        "metal"
    ],
    "sg:website":"http://www.wickbuildings.com",
    "wof:name":"Wick Buildings",
    "wof:placetype":"venue"
},
  "geometry": {"coordinates":[-88.26250899999999,43.003678],"type":"Point"}
}