{
  "type": "Feature",
  "properties": {
    "addr:full":"619 Spring St Somerset WI 54025",
    "addr:housenumber":"619",
    "addr:postcode":"54025",
    "addr:street":"Spring St",
    "iso:country":"US",
    "sg:address":"619 Spring St",
    "sg:city":"Somerset",
    "sg:classifiers":[
        {
            "category":"Retail",
            "subcategory":"Auto Repair",
            "type":"Services"
        }
    ],
    "sg:phone":"+1 715 247 2233",
    "sg:postcode":"54025",
    "sg:province":"WI",
    "sg:tags":[
        "body",
        "painting",
        "repairing",
        "automobile"
    ],
    "sg:website":"http://www.somersetcollision.com",
    "wof:name":"Rhino Linings Of St Croix Vly",
    "wof:placetype":"venue"
},
  "geometry": {"coordinates":[-92.68002,45.127893],"type":"Point"}
}