{
  "type": "Feature",
  "properties": {
    "iso:country":"US",
    "sg:address":"1101 Main St",
    "sg:city":"Onalaska",
    "sg:classifiers":[
        {
            "category":"Banks & Credit Unions",
            "subcategory":"Bank",
            "type":"Services"
        }
    ],
    "sg:phone":"+1 608 783 4545",
    "sg:postcode":"54650",
    "sg:province":"WI",
    "wof:name":"Associated Bank National Assn",
    "wof:placetype":"venue"
},
  "geometry": {"coordinates":[-91.220816,43.884322],"type":"Point"}
}