{
  "type": "Feature",
  "properties": {
    "addr:full":"803 Main St Ridgeway WI 53582",
    "addr:housenumber":"803",
    "addr:postcode":"53582",
    "addr:street":"Main St",
    "iso:country":"US",
    "sg:address":"803 Main St",
    "sg:city":"Ridgeway",
    "sg:classifiers":[
        {
            "category":"Organizations",
            "subcategory":"Religious Organization",
            "type":"Services"
        }
    ],
    "sg:phone":"+1 608 924 2441",
    "sg:postcode":"53582",
    "sg:province":"WI",
    "sg:tags":[
        "church"
    ],
    "wof:name":"St Bridgets Catholic Church",
    "wof:placetype":"venue"
},
  "geometry": {"coordinates":[-89.995599,42.998225],"type":"Point"}
}