{
  "type": "Feature",
  "properties": {
    "iso:country":"US",
    "sg:address":"545 Antelope Trl",
    "sg:city":"Green Bay",
    "sg:classifiers":[
        {
            "category":"Wholesale",
            "subcategory":"Apparel",
            "type":"Manufacturing & Wholesale Goods"
        }
    ],
    "sg:phone":"+1 920 498 2575",
    "sg:postcode":"54313",
    "sg:province":"WI",
    "sg:tags":[
        "bridal",
        "accessory"
    ],
    "wof:name":"Lacey Legs",
    "wof:placetype":"venue"
},
  "geometry": {"coordinates":[-88.113676,44.5298],"type":"Point"}
}