{
  "type": "Feature",
  "properties": {
    "iso:country":"US",
    "sg:address":"1460 S Muskego Ave",
    "sg:city":"Milwaukee",
    "sg:classifiers":[
        {
            "category":"Bars & Pubs",
            "type":"Food & Drink"
        }
    ],
    "sg:phone":"+1 414 647 8101",
    "sg:postcode":"53204",
    "sg:province":"WI",
    "sg:tags":[
        "drinking"
    ],
    "wof:name":"El Tequila Bar",
    "wof:placetype":"venue"
},
  "geometry": {"coordinates":[-87.933621,43.016492],"type":"Point"}
}