{
  "type": "Feature",
  "properties": {
    "addr:full":"800 S Division St Waunakee WI 53597",
    "addr:housenumber":"800",
    "addr:postcode":"53597",
    "addr:street":"S Division St",
    "iso:country":"US",
    "sg:address":"800 S Division St",
    "sg:city":"Waunakee",
    "sg:classifiers":[
        {
            "category":"Building & Trades",
            "subcategory":"Electrical",
            "type":"Services"
        },
        {
            "category":"Building & Trades",
            "subcategory":"Plumbing",
            "type":"Services"
        }
    ],
    "sg:phone":"+1 608 850 5657",
    "sg:postcode":"53597",
    "sg:province":"WI",
    "sg:tags":[
        "electric",
        "contractor"
    ],
    "wof:name":"Quality Control Inc",
    "wof:placetype":"venue"
},
  "geometry": {"coordinates":[-89.44717300000001,43.186611],"type":"Point"}
}