{
  "type": "Feature",
  "properties": {
    "iso:country":"US",
    "sg:address":"206 N Main St",
    "sg:city":"Blanchardville",
    "sg:classifiers":[
        {
            "category":"Retail",
            "subcategory":"Veterinary Services",
            "type":"Services"
        }
    ],
    "sg:phone":"+1 608 523 4051",
    "sg:postcode":"53516",
    "sg:province":"WI",
    "sg:tags":[
        "veterinarian"
    ],
    "wof:name":"Blanchardville Veterinary",
    "wof:placetype":"venue"
},
  "geometry": {"coordinates":[-89.86048599999999,42.814107],"type":"Point"}
}