{
  "type": "Feature",
  "properties": {
    "iso:country":"US",
    "sg:address":"2357 W Mason St",
    "sg:city":"Green Bay",
    "sg:classifiers":[
        {
            "category":"Professional",
            "subcategory":"Engineering",
            "type":"Services"
        }
    ],
    "sg:phone":"+1 920 499 0260",
    "sg:postcode":"54303",
    "sg:province":"WI",
    "sg:tags":[
        "consulting",
        "structural",
        "engineer"
    ],
    "sg:website":"www.brandercti.com",
    "wof:name":"Brander Construction Tech Inc",
    "wof:placetype":"venue"
},
  "geometry": {"coordinates":[-88.091482,44.524007],"type":"Point"}
}