{
  "type": "Feature",
  "properties": {
    "iso:country":"US",
    "sg:address":"2436 Pecan St",
    "sg:city":"Green Bay",
    "sg:classifiers":[
        {
            "category":"Personal",
            "subcategory":"Beauty Salon",
            "type":"Services"
        }
    ],
    "sg:phone":"+1 920 465 7795",
    "sg:postcode":"54311",
    "sg:province":"WI",
    "sg:tags":[
        "shop"
    ],
    "wof:name":"Susies Salon",
    "wof:placetype":"venue"
},
  "geometry": {"coordinates":[-87.95957,44.479925],"type":"Point"}
}