{
  "type": "Feature",
  "properties": {
    "iso:country":"US",
    "sg:address":"2211 Atwood Ave",
    "sg:city":"Madison",
    "sg:classifiers":[
        {
            "category":"Professional",
            "subcategory":"Art Services",
            "type":"Services"
        }
    ],
    "sg:phone":"+1 608 249 1247",
    "sg:postcode":"53704",
    "sg:province":"WI",
    "sg:tags":[
        "artist"
    ],
    "wof:name":"P S Mueller",
    "wof:placetype":"venue"
},
  "geometry": {"coordinates":[-89.348579,43.093301],"type":"Point"}
}