{
  "type": "Feature",
  "properties": {
    "iso:country":"US",
    "sg:address":"3151 Co Rd J",
    "sg:city":"Verona",
    "sg:classifiers":[
        {
            "category":"Autos & Motor Vehicles",
            "subcategory":"Auto Supplies",
            "type":"Retail Goods"
        }
    ],
    "sg:phone":"+1 608 845 7855",
    "sg:postcode":"53593",
    "sg:province":"WI",
    "wof:name":"Carlstrom Car Parts LLC",
    "wof:placetype":"venue"
},
  "geometry": {"coordinates":[-89.626888,43.005855],"type":"Point"}
}