{
  "type": "Feature",
  "properties": {
    "iso:country":"US",
    "sg:address":"12065 W Janesville Rd",
    "sg:city":"Hales Corners",
    "sg:classifiers":[
        {
            "category":"Wholesale",
            "subcategory":"Meat",
            "type":"Manufacturing & Wholesale Goods"
        }
    ],
    "sg:phone":"+1 414 427 7850",
    "sg:postcode":"53130",
    "sg:province":"WI",
    "wof:name":"Badgerpoulrty Plus",
    "wof:placetype":"venue"
},
  "geometry": {"coordinates":[-88.062345,42.9365],"type":"Point"}
}