{
  "type": "Feature",
  "properties": {
    "iso:country":"US",
    "sg:address":"3478 Swamp Rd",
    "sg:city":"Shawano",
    "sg:classifiers":[
        {
            "category":"Wholesale",
            "subcategory":"Scrap",
            "type":"Manufacturing & Wholesale Goods"
        }
    ],
    "sg:phone":"+1 715 526 2392",
    "sg:postcode":"54166",
    "sg:province":"WI",
    "sg:tags":[
        "metal",
        "iron"
    ],
    "wof:name":"Ellie's Auto",
    "wof:placetype":"venue"
},
  "geometry": {"coordinates":[-88.55539,44.700341],"type":"Point"}
}