{
  "type": "Feature",
  "properties": {
    "iso:country":"US",
    "sg:address":"5073 Blackbird Rd",
    "sg:city":"Beaver Dam",
    "sg:classifiers":[
        {
            "category":"Farming",
            "subcategory":"Livestock Farm",
            "type":"Manufacturing & Wholesale Goods"
        }
    ],
    "sg:phone":"+1 920 927 7372",
    "sg:postcode":"53916",
    "sg:province":"WI",
    "sg:tags":[
        "corn",
        "beef",
        "feedlot",
        "cattle"
    ],
    "wof:name":"SJS Trucking",
    "wof:placetype":"venue"
},
  "geometry": {"coordinates":[-88.823235,43.38621],"type":"Point"}
}