{
  "type": "Feature",
  "properties": {
    "iso:country":"US",
    "sg:address":"2330 Co Rd Q",
    "sg:city":"Pelican Lake",
    "sg:classifiers":[
        {
            "category":"Bars & Pubs",
            "type":"Food & Drink"
        }
    ],
    "sg:phone":"+1 715 487 5290",
    "sg:postcode":"54463",
    "sg:province":"WI",
    "wof:name":"Christian's Lake View Inn",
    "wof:placetype":"venue"
},
  "geometry": {"coordinates":[-89.20078100000001,45.526953],"type":"Point"}
}