{
  "type": "Feature",
  "properties": {
    "iso:country":"US",
    "sg:address":"4346 Co Rd Q",
    "sg:city":"Colgate",
    "sg:classifiers":[
        {
            "category":"Wholesale",
            "subcategory":"Hardware",
            "type":"Manufacturing & Wholesale Goods"
        }
    ],
    "sg:phone":"+1 262 628 4605",
    "sg:postcode":"53017",
    "sg:province":"WI",
    "sg:tags":[
        "water",
        "mfg",
        "waste",
        "representative",
        "purification"
    ],
    "wof:name":"PWR Inc",
    "wof:placetype":"venue"
},
  "geometry": {"coordinates":[-88.253212,43.193344],"type":"Point"}
}