{
  "type": "Feature",
  "properties": {
    "iso:country":"US",
    "sg:address":"1001 Alpine Dr",
    "sg:city":"Green Bay",
    "sg:classifiers":[
        {
            "category":"Building & Trades",
            "subcategory":"Construction",
            "type":"Services"
        }
    ],
    "sg:phone":"+1 920 639 6799",
    "sg:postcode":"54311",
    "sg:province":"WI",
    "sg:tags":[
        "concrete",
        "contractor"
    ],
    "wof:name":"N & L Concrete Construction",
    "wof:placetype":"venue"
},
  "geometry": {"coordinates":[-87.947881,44.482808],"type":"Point"}
}