{
  "type": "Feature",
  "properties": {
    "iso:country":"US",
    "sg:address":"3410 Mall Dr",
    "sg:city":"Eau Claire",
    "sg:classifiers":[
        {
            "category":"Personal",
            "subcategory":"Beauty Salon",
            "type":"Services"
        }
    ],
    "sg:phone":"+1 715 835 3375",
    "sg:postcode":"54701",
    "sg:province":"WI",
    "wof:name":"Fantastic Sam's Regional",
    "wof:placetype":"venue"
},
  "geometry": {"coordinates":[-91.461124,44.783899],"type":"Point"}
}