{
  "type": "Feature",
  "properties": {
    "addr:full":"107 E 2nd St Kaukauna WI 54130",
    "addr:housenumber":"107",
    "addr:postcode":"54130",
    "addr:street":"E 2Nd St",
    "iso:country":"US",
    "sg:address":"107 E 2nd St",
    "sg:city":"Kaukauna",
    "sg:classifiers":[
        {
            "category":"Restaurant",
            "type":"Food & Drink"
        }
    ],
    "sg:phone":"+1 920 759 1521",
    "sg:postcode":"54130",
    "sg:province":"WI",
    "sg:tags":[
        "eating"
    ],
    "wof:name":"R Cafe",
    "wof:placetype":"venue"
},
  "geometry": {"coordinates":[-88.27106499999999,44.277167],"type":"Point"}
}