{
  "type": "Feature",
  "properties": {
    "addr:full":"1038 Park Ave Racine WI 53403",
    "addr:housenumber":"1038",
    "addr:postcode":"53403",
    "addr:street":"Park Ave",
    "iso:country":"US",
    "sg:address":"1038 Park Ave",
    "sg:city":"Racine",
    "sg:classifiers":[
        {
            "category":"Social Services",
            "subcategory":"Child Care",
            "type":"Services"
        }
    ],
    "sg:phone":"+1 262 636 0043",
    "sg:postcode":"53403",
    "sg:province":"WI",
    "wof:name":"Hick's Daycare",
    "wof:placetype":"venue"
},
  "geometry": {"coordinates":[-87.78603099999999,42.720572],"type":"Point"}
}