{
  "type": "Feature",
  "properties": {
    "iso:country":"US",
    "sg:address":"1600 26th St",
    "sg:city":"Monroe",
    "sg:classifiers":[
        {
            "category":"Education",
            "subcategory":"School",
            "type":"Public Place"
        }
    ],
    "sg:phone":"+1 608 328 7166",
    "sg:postcode":"53566",
    "sg:province":"WI",
    "sg:tags":[
        "high"
    ],
    "sg:website":"http://www.monroeschools.com",
    "wof:name":"Senior High School",
    "wof:placetype":"venue"
},
  "geometry": {"coordinates":[-89.639107,42.58778],"type":"Point"}
}