{
  "type": "Feature",
  "properties": {
    "iso:country":"US",
    "sg:address":"7940 W Layton Ave",
    "sg:city":"Milwaukee",
    "sg:classifiers":[
        {
            "category":"Shopping",
            "subcategory":"Gifts & Souvenirs",
            "type":"Retail Goods"
        }
    ],
    "sg:phone":"+1 414 281 4210",
    "sg:postcode":"53220",
    "sg:province":"WI",
    "sg:website":"www.acountrymouse.com",
    "wof:name":"A Country Mouse Gift Shop",
    "wof:placetype":"venue"
},
  "geometry": {"coordinates":[-88.00873300000001,42.95933],"type":"Point"}
}