{
  "type": "Feature",
  "properties": {
    "addr:full":"524 S 2nd St Milwaukee WI 53204",
    "addr:housenumber":"524",
    "addr:postcode":"53204",
    "addr:street":"S 2Nd St",
    "iso:country":"US",
    "sg:address":"524 S 2nd St",
    "sg:city":"Milwaukee",
    "sg:classifiers":[
        {
            "category":"Building & Trades",
            "subcategory":"Construction",
            "type":"Services"
        }
    ],
    "sg:phone":"+1 414 273 7663",
    "sg:postcode":"53204",
    "sg:province":"WI",
    "sg:tags":[
        "roofing",
        "industrial",
        "contractors-commercial",
        "contractor"
    ],
    "sg:website":"http://www.altecroofing.net",
    "wof:name":"Altec Commercial Roofing",
    "wof:placetype":"venue"
},
  "geometry": {"coordinates":[-87.912598,43.026064],"type":"Point"}
}