{
  "type": "Feature",
  "properties": {
    "addr:full":"330 E Kilbourn Ave Milwaukee WI 53202",
    "addr:housenumber":"330",
    "addr:postcode":"53202",
    "addr:street":"E Kilbourn Ave",
    "iso:country":"US",
    "sg:address":"330 E Kilbourn Ave",
    "sg:city":"Milwaukee",
    "sg:classifiers":[
        {
            "category":"Building & Trades",
            "subcategory":"Cleaning & Sanitation",
            "type":"Services"
        }
    ],
    "sg:phone":"+1 414 289 7749",
    "sg:postcode":"53202",
    "sg:province":"WI",
    "sg:tags":[
        "janitor",
        "maintenance"
    ],
    "wof:name":"Lakeside Building Maintenance",
    "wof:placetype":"venue"
},
  "geometry": {"coordinates":[-87.907285,43.042515],"type":"Point"}
}