{
  "type": "Feature",
  "properties": {
    "addr:full":"3189 US Hwy 51 Mercer WI 54547",
    "addr:housenumber":"3189",
    "addr:postcode":"54547",
    "addr:street":"Us Hwy 51",
    "iso:country":"US",
    "sg:address":"3189 US Hwy 51",
    "sg:city":"Mercer",
    "sg:classifiers":[
        {
            "category":"Communications",
            "type":"Services"
        }
    ],
    "sg:phone":"+1 715 476 7674",
    "sg:postcode":"54547",
    "sg:province":"WI",
    "wof:name":"Nationwide Communications Inc",
    "wof:placetype":"venue"
},
  "geometry": {"coordinates":[-90.066468,46.166825],"type":"Point"}
}