{
  "type": "Feature",
  "properties": {
    "addr:full":"602 Oak Park Cir Mosinee WI 54455",
    "addr:housenumber":"602",
    "addr:postcode":"54455",
    "addr:street":"Oak Park Cir",
    "iso:country":"US",
    "sg:address":"602 Oak Park Cir",
    "sg:city":"Mosinee",
    "sg:classifiers":[
        {
            "category":"Building & Trades",
            "subcategory":"Construction",
            "type":"Services"
        }
    ],
    "sg:phone":"+1 715 693 1035",
    "sg:postcode":"54455",
    "sg:province":"WI",
    "sg:tags":[
        "general",
        "contractor"
    ],
    "wof:name":"Colbert Construction",
    "wof:placetype":"venue"
},
  "geometry": {"coordinates":[-89.72452199999999,44.797194],"type":"Point"}
}