{
  "type": "Feature",
  "properties": {
    "iso:country":"US",
    "sg:address":"9200 W Loomis Rd",
    "sg:city":"Franklin",
    "sg:classifiers":[
        {
            "category":"Health Services",
            "subcategory":"Doctor",
            "type":"Services"
        }
    ],
    "sg:phone":"+1 414 529 9261",
    "sg:postcode":"53132",
    "sg:province":"WI",
    "sg:tags":[
        "physician",
        "surgeon"
    ],
    "wof:name":"Southeastern Pediatrics",
    "wof:placetype":"venue"
},
  "geometry": {"coordinates":[-88.028938,42.900714],"type":"Point"}
}