{
  "type": "Feature",
  "properties": {
    "iso:country":"US",
    "sg:address":"6803 29th Ave",
    "sg:city":"Kenosha",
    "sg:classifiers":[
        {
            "category":"Retail",
            "subcategory":"Auto Repair",
            "type":"Services"
        }
    ],
    "sg:phone":"+1 262 657 3366",
    "sg:postcode":"53143",
    "sg:province":"WI",
    "sg:tags":[
        "body",
        "automobile",
        "painting"
    ],
    "wof:name":"Millhouse Auto Body Inc",
    "wof:placetype":"venue"
},
  "geometry": {"coordinates":[-87.84398400000001,42.57097],"type":"Point"}
}