{
  "type": "Feature",
  "properties": {
    "addr:full":"2251 S Syene Rd Fitchburg WI 53711",
    "addr:housenumber":"2251",
    "addr:postcode":"53711",
    "addr:street":"S Syene Rd",
    "iso:country":"US",
    "sg:address":"2251 S Syene Rd",
    "sg:city":"Fitchburg",
    "sg:classifiers":[
        {
            "category":"Building & Trades",
            "subcategory":"Construction",
            "type":"Services"
        }
    ],
    "sg:phone":"+1 608 274 2196",
    "sg:postcode":"53711",
    "sg:province":"WI",
    "sg:tags":[
        "concrete",
        "contractor"
    ],
    "wof:name":"Casey Concrete & Construction",
    "wof:placetype":"venue"
},
  "geometry": {"coordinates":[-89.397071,42.978215],"type":"Point"}
}