{
  "type": "Feature",
  "properties": {
    "iso:country":"US",
    "sg:address":"4875 N Cumberland Blvd",
    "sg:city":"Milwaukee",
    "sg:classifiers":[
        {
            "category":"Professional",
            "subcategory":"Printing & Photocopies",
            "type":"Services"
        }
    ],
    "sg:phone":"+1 414 963 0432",
    "sg:postcode":"53217",
    "sg:province":"WI",
    "sg:tags":[
        "lithographer"
    ],
    "wof:name":"Prism Printing",
    "wof:placetype":"venue"
},
  "geometry": {"coordinates":[-87.892319,43.105257],"type":"Point"}
}