{
  "type": "Feature",
  "properties": {
    "iso:country":"US",
    "sg:address":"1945 Prairie Ln",
    "sg:city":"Eau Claire",
    "sg:classifiers":[
        {
            "category":"Wholesale",
            "subcategory":"Machinery & Supplies",
            "type":"Manufacturing & Wholesale Goods"
        }
    ],
    "sg:phone":"+1 715 874 4480",
    "sg:postcode":"54703",
    "sg:province":"WI",
    "sg:tags":[
        "equipment",
        "establishment"
    ],
    "wof:name":"Badger Burial Vault Co",
    "wof:placetype":"venue"
},
  "geometry": {"coordinates":[-91.533402,44.843292],"type":"Point"}
}