{
  "type": "Feature",
  "properties": {
    "iso:country":"US",
    "sg:address":"2613 W Rogers St",
    "sg:city":"Milwaukee",
    "sg:classifiers":[
        {
            "category":"Freight",
            "type":"Transportation"
        }
    ],
    "sg:phone":"+1 414 645 7596",
    "sg:postcode":"53204",
    "sg:province":"WI",
    "sg:tags":[
        "distance",
        "long",
        "trucking"
    ],
    "wof:name":"Hagen Trucking & Service Inc",
    "wof:placetype":"venue"
},
  "geometry": {"coordinates":[-87.94783099999999,43.008503],"type":"Point"}
}