{
  "type": "Feature",
  "properties": {
    "iso:country":"US",
    "sg:address":"834 Hockridge St",
    "sg:city":"Marinette",
    "sg:classifiers":[
        {
            "category":"Professional",
            "subcategory":"Employment Agencies",
            "type":"Services"
        }
    ],
    "sg:phone":"+1 715 735 3231",
    "sg:postcode":"54143",
    "sg:province":"WI",
    "sg:tags":[
        "help",
        "supply"
    ],
    "wof:name":"All In One Support Service",
    "wof:placetype":"venue"
},
  "geometry": {"coordinates":[-87.644623,45.097566],"type":"Point"}
}