{
  "type": "Feature",
  "properties": {
    "iso:country":"US",
    "sg:address":"505 Lincoln Ave",
    "sg:city":"Kaukauna",
    "sg:classifiers":[
        {
            "category":"Professional",
            "type":"Services"
        }
    ],
    "sg:phone":"+1 920 766 9989",
    "sg:postcode":"54130",
    "sg:province":"WI",
    "sg:tags":[
        "establishment"
    ],
    "wof:name":"Van Boxtel & Van Boxtel",
    "wof:placetype":"venue"
},
  "geometry": {"coordinates":[-88.271111,44.287656],"type":"Point"}
}