{
  "type": "Feature",
  "properties": {
    "iso:country":"US",
    "sg:address":"2126 Esmond Rd",
    "sg:city":"Eau Claire",
    "sg:classifiers":[
        {
            "category":"Wholesale",
            "subcategory":"Machinery & Supplies",
            "type":"Manufacturing & Wholesale Goods"
        }
    ],
    "sg:phone":"+1 715 838 9815",
    "sg:postcode":"54701",
    "sg:province":"WI",
    "sg:tags":[
        "janitor"
    ],
    "wof:name":"Hillyard",
    "wof:placetype":"venue"
},
  "geometry": {"coordinates":[-91.464896,44.796535],"type":"Point"}
}