{
  "type": "Feature",
  "properties": {
    "iso:country":"US",
    "sg:address":"225 W Wisconsin Ave",
    "sg:city":"Neenah",
    "sg:classifiers":[
        {
            "category":"Manufacturing",
            "subcategory":"Paper Products",
            "type":"Manufacturing & Wholesale Goods"
        }
    ],
    "sg:phone":"+1 920 727 2440",
    "sg:postcode":"54956",
    "sg:province":"WI",
    "sg:tags":[
        "converter"
    ],
    "sg:website":"www.glatfelter.com",
    "wof:name":"P H Glatfelter Co",
    "wof:placetype":"venue"
},
  "geometry": {"coordinates":[-88.46436199999999,44.18781],"type":"Point"}
}