{
  "type": "Feature",
  "properties": {
    "addr:full":"5725 Windy Dr Stevens Point WI 54481",
    "addr:housenumber":"5725",
    "addr:postcode":"54481",
    "addr:street":"Windy Dr",
    "iso:country":"US",
    "sg:address":"5725 Windy Dr",
    "sg:city":"Stevens Point",
    "sg:classifiers":[
        {
            "category":"Food & Beverages",
            "subcategory":"Specialty",
            "type":"Retail Goods"
        }
    ],
    "sg:phone":"+1 715 342 4871",
    "sg:postcode":"54481",
    "sg:province":"WI",
    "sg:tags":[
        "gourmet",
        "shop"
    ],
    "sg:website":"www.glacierbaystore.com",
    "wof:name":"Glacier Bay",
    "wof:placetype":"venue"
},
  "geometry": {"coordinates":[-89.50398199999999,44.524747],"type":"Point"}
}