{
  "type": "Feature",
  "properties": {
    "iso:country":"US",
    "sg:address":"14165 W Ranch Rd",
    "sg:city":"Brookfield",
    "sg:classifiers":[
        {
            "category":"Wholesale",
            "subcategory":"Hardware",
            "type":"Manufacturing & Wholesale Goods"
        }
    ],
    "sg:phone":"+1 262 781 4262",
    "sg:postcode":"53005",
    "sg:province":"WI",
    "wof:name":"American Oil Controls Corp",
    "wof:placetype":"venue"
},
  "geometry": {"coordinates":[-88.089057,43.090429],"type":"Point"}
}