{
  "type": "Feature",
  "properties": {
    "iso:country":"US",
    "sg:address":"214 N Main St",
    "sg:city":"River Falls",
    "sg:classifiers":[
        {
            "category":"Banks & Credit Unions",
            "subcategory":"Bank",
            "type":"Services"
        }
    ],
    "sg:phone":"+1 715 425 6906",
    "sg:postcode":"54022",
    "sg:province":"WI",
    "sg:tags":[
        "loan",
        "real estate"
    ],
    "wof:name":"BMC Mortgage Co",
    "wof:placetype":"venue"
},
  "geometry": {"coordinates":[-92.624932,44.860462],"type":"Point"}
}