{
  "type": "Feature",
  "properties": {
    "iso:country":"US",
    "sg:address":"10 S Carroll St",
    "sg:city":"Madison",
    "sg:classifiers":[
        {
            "category":"Shopping",
            "subcategory":"Used Merchandise",
            "type":"Retail Goods"
        }
    ],
    "sg:phone":"+1 608 280 9000",
    "sg:postcode":"53703",
    "sg:province":"WI",
    "sg:tags":[
        "clothing"
    ],
    "wof:name":"Winter Silks",
    "wof:placetype":"venue"
},
  "geometry": {"coordinates":[-89.38434599999999,43.073166],"type":"Point"}
}