{
  "type": "Feature",
  "properties": {
    "addr:full":"11251 W Forest Home Ave Franklin WI 53132",
    "addr:housenumber":"11251",
    "addr:postcode":"53132",
    "addr:street":"W Forest Home Ave",
    "iso:country":"US",
    "sg:address":"11251 W Forest Home Ave",
    "sg:city":"Franklin",
    "sg:classifiers":[
        {
            "category":"Building & Trades",
            "subcategory":"Construction",
            "type":"Services"
        }
    ],
    "sg:phone":"+1 414 425 3326",
    "sg:postcode":"53132",
    "sg:province":"WI",
    "sg:tags":[
        "concrete",
        "contractor"
    ],
    "wof:name":"Extruded Concrete Curbs",
    "wof:placetype":"venue"
},
  "geometry": {"coordinates":[-88.056951,42.9172],"type":"Point"}
}