{
  "type": "Feature",
  "properties": {
    "iso:country":"US",
    "sg:address":"6008 W Vliet St",
    "sg:city":"Milwaukee",
    "sg:classifiers":[
        {
            "category":"Personal",
            "subcategory":"Beauty Salon",
            "type":"Services"
        }
    ],
    "sg:phone":"+1 414 453 1314",
    "sg:postcode":"53213",
    "sg:province":"WI",
    "wof:name":"Hot Heads",
    "wof:placetype":"venue"
},
  "geometry": {"coordinates":[-87.988499,43.050249],"type":"Point"}
}