{
  "type": "Feature",
  "properties": {
    "addr:full":"1185 Mutual Way Appleton WI 54913",
    "addr:housenumber":"1185",
    "addr:postcode":"54913",
    "addr:street":"Mutual Way",
    "iso:country":"US",
    "sg:address":"1185 Mutual Way",
    "sg:city":"Appleton",
    "sg:classifiers":[
        {
            "category":"Manufacturing",
            "subcategory":"Apparel",
            "type":"Manufacturing & Wholesale Goods"
        }
    ],
    "sg:phone":"+1 920 993 9769",
    "sg:postcode":"54913",
    "sg:province":"WI",
    "wof:name":"Life's A Stitch",
    "wof:placetype":"venue"
},
  "geometry": {"coordinates":[-88.477572,44.267662],"type":"Point"}
}