{
  "type": "Feature",
  "properties": {
    "addr:full":"411 N Parker Dr Janesville WI 53545",
    "addr:housenumber":"411",
    "addr:postcode":"53545",
    "addr:street":"N Parker Dr",
    "iso:country":"US",
    "sg:address":"411 N Parker Dr",
    "sg:city":"Janesville",
    "sg:classifiers":[
        {
            "category":"Retail",
            "subcategory":"Car Wash",
            "type":"Services"
        }
    ],
    "sg:phone":"+1 608 755 6996",
    "sg:postcode":"53545",
    "sg:province":"WI",
    "sg:tags":[
        "carwash"
    ],
    "wof:name":"Roger Johnson",
    "wof:placetype":"venue"
},
  "geometry": {"coordinates":[-89.025983,42.68779],"type":"Point"}
}