{
  "type": "Feature",
  "properties": {
    "iso:country":"US",
    "sg:address":"115 W Church St",
    "sg:city":"Oakfield",
    "sg:classifiers":[
        {
            "category":"Building & Trades",
            "subcategory":"Construction",
            "type":"Services"
        }
    ],
    "sg:phone":"+1 920 583 4469",
    "sg:postcode":"53065",
    "sg:province":"WI",
    "sg:tags":[
        "home",
        "builder",
        "house"
    ],
    "wof:name":"Paul Schaefer Construction",
    "wof:placetype":"venue"
},
  "geometry": {"coordinates":[-88.548131,43.68625],"type":"Point"}
}