{
  "type": "Feature",
  "properties": {
    "iso:country":"US",
    "sg:address":"309 High Ave",
    "sg:city":"Oshkosh",
    "sg:classifiers":[
        {
            "category":"Insurance",
            "subcategory":"Insurance Agent",
            "type":"Services"
        }
    ],
    "sg:phone":"+1 920 233 9000",
    "sg:postcode":"54901",
    "sg:province":"WI",
    "wof:name":"Alliance Insur & Fincl Svcs",
    "wof:placetype":"venue"
},
  "geometry": {"coordinates":[-88.541773,44.018648],"type":"Point"}
}