{
  "type": "Feature",
  "properties": {
    "iso:country":"US",
    "sg:address":"313 N 3rd Ave",
    "sg:city":"Stratford",
    "sg:classifiers":[
        {
            "category":"Government",
            "subcategory":"Post Office",
            "type":"Public Place"
        }
    ],
    "sg:phone":"+1 715 000 1111",
    "sg:postcode":"54484",
    "sg:province":"WI",
    "sg:website":"www.usps.gov",
    "wof:name":"US Post Office",
    "wof:placetype":"venue"
},
  "geometry": {"coordinates":[-90.076283,44.803848],"type":"Point"}
}