{
  "type": "Feature",
  "properties": {
    "addr:full":"1046 Saratoga Ct Oconomowoc WI 53066",
    "addr:housenumber":"1046",
    "addr:postcode":"53066",
    "addr:street":"Saratoga Ct",
    "iso:country":"US",
    "sg:address":"1046 Saratoga Ct",
    "sg:city":"Oconomowoc",
    "sg:classifiers":[
        {
            "category":"Real Estate",
            "subcategory":"Real Estate Operator",
            "type":"Services"
        }
    ],
    "sg:phone":"+1 262 567 6206",
    "sg:postcode":"53066",
    "sg:province":"WI",
    "sg:tags":[
        "building",
        "nonresidential"
    ],
    "wof:name":"Neighbors Properties LLC",
    "wof:placetype":"venue"
},
  "geometry": {"coordinates":[-88.475573,43.093963],"type":"Point"}
}