{
  "type": "Feature",
  "properties": {
    "addr:full":"325 W Silver Spring Dr Milwaukee WI 53209",
    "addr:housenumber":"325",
    "addr:postcode":"53209",
    "addr:street":"W Silver Spring Dr",
    "iso:country":"US",
    "sg:address":"325 W Silver Spring Dr",
    "sg:city":"Milwaukee",
    "sg:classifiers":[
        {
            "category":"Building & Trades",
            "subcategory":"Construction",
            "type":"Services"
        }
    ],
    "sg:phone":"+1 414 961 2440",
    "sg:postcode":"53209",
    "sg:province":"WI",
    "sg:tags":[
        "home",
        "improvement"
    ],
    "wof:name":"Miller Builders",
    "wof:placetype":"venue"
},
  "geometry": {"coordinates":[-87.913794,43.118546],"type":"Point"}
}