{
  "type": "Feature",
  "properties": {
    "iso:country":"US",
    "sg:address":"7712 W Fiebrantz Ave",
    "sg:city":"Milwaukee",
    "sg:classifiers":[
        {
            "category":"Professional",
            "subcategory":"Business Services",
            "type":"Services"
        }
    ],
    "sg:phone":"+1 414 464 1131",
    "sg:postcode":"53222",
    "sg:province":"WI",
    "sg:tags":[
        "embroidery"
    ],
    "wof:name":"Designs Unlimited",
    "wof:placetype":"venue"
},
  "geometry": {"coordinates":[-88.010834,43.090908],"type":"Point"}
}