{
  "type": "Feature",
  "properties": {
    "addr:full":"325 Main St Sayner WI 54560",
    "addr:housenumber":"325",
    "addr:postcode":"54560",
    "addr:street":"Main St",
    "iso:country":"US",
    "sg:address":"325 Main St",
    "sg:city":"Sayner",
    "sg:classifiers":[
        {
            "category":"Home & Garden",
            "subcategory":"Home Furnishings",
            "type":"Retail Goods"
        }
    ],
    "sg:phone":"+1 715 542 2386",
    "sg:postcode":"54560",
    "sg:province":"WI",
    "sg:tags":[
        "contractor"
    ],
    "wof:name":"Earth Sense Energy Systems",
    "wof:placetype":"venue"
},
  "geometry": {"coordinates":[-89.531901,45.98928],"type":"Point"}
}