{
  "type": "Feature",
  "properties": {
    "iso:country":"US",
    "sg:address":"307 Nestles St",
    "sg:city":"Lodi",
    "sg:classifiers":[
        {
            "category":"Manufacturing",
            "subcategory":"Food",
            "type":"Manufacturing & Wholesale Goods"
        }
    ],
    "sg:phone":"+1 608 592 4236",
    "sg:postcode":"53555",
    "sg:province":"WI",
    "sg:tags":[
        "canning"
    ],
    "wof:name":"Lodi Canning Co",
    "wof:placetype":"venue"
},
  "geometry": {"coordinates":[-89.53046399999999,43.309537],"type":"Point"}
}