{
  "type": "Feature",
  "properties": {
    "iso:country":"US",
    "sg:address":"6001 E Co Rd A",
    "sg:city":"Janesville",
    "sg:classifiers":[
        {
            "category":"Farming",
            "subcategory":"Dairy Farm",
            "type":"Manufacturing & Wholesale Goods"
        }
    ],
    "sg:phone":"+1 608 754 8696",
    "sg:postcode":"53546",
    "sg:province":"WI",
    "wof:name":"Brad Kemp Cloverhill Farms",
    "wof:placetype":"venue"
},
  "geometry": {"coordinates":[-88.920321,42.699365],"type":"Point"}
}