{
  "type": "Feature",
  "properties": {
    "iso:country":"US",
    "sg:address":"18915 Thomson Dr",
    "sg:city":"Brookfield",
    "sg:classifiers":[
        {
            "category":"Personal",
            "subcategory":"Beauty Salon",
            "type":"Services"
        }
    ],
    "sg:phone":"+1 262 781 1759",
    "sg:postcode":"53045",
    "sg:province":"WI",
    "sg:tags":[
        "shop"
    ],
    "wof:name":"Traditions In Hair Designs",
    "wof:placetype":"venue"
},
  "geometry": {"coordinates":[-88.146307,43.087527],"type":"Point"}
}