{
  "type": "Feature",
  "properties": {
    "iso:country":"US",
    "sg:address":"835 E Johnson St",
    "sg:city":"Madison",
    "sg:classifiers":[
        {
            "category":"Travel",
            "subcategory":"Travel Agent",
            "type":"Entertainment"
        }
    ],
    "sg:phone":"+1 608 251 0140",
    "sg:postcode":"53703",
    "sg:province":"WI",
    "sg:tags":[
        "agency"
    ],
    "wof:name":"Sadhana Travels",
    "wof:placetype":"venue"
},
  "geometry": {"coordinates":[-89.376734,43.083958],"type":"Point"}
}