{
  "type": "Feature",
  "properties": {
    "iso:country":"US",
    "sg:address":"4381 S Pennsylvania Ave",
    "sg:city":"Milwaukee",
    "sg:classifiers":[
        {
            "category":"Real Estate",
            "subcategory":"Real Estate Agent",
            "type":"Services"
        }
    ],
    "sg:phone":"+1 414 481 6231",
    "sg:postcode":"53235",
    "sg:province":"WI",
    "wof:name":"Benjamin M Real Estate",
    "wof:placetype":"venue"
},
  "geometry": {"coordinates":[-87.879851,42.962791],"type":"Point"}
}