{
  "type": "Feature",
  "properties": {
    "iso:country":"US",
    "sg:address":"318 Grand Ave",
    "sg:city":"Merrill",
    "sg:classifiers":[
        {
            "category":"Retail",
            "subcategory":"Laundry & Dry Cleaning",
            "type":"Services"
        }
    ],
    "sg:phone":"+1 715 536 8871",
    "sg:postcode":"54452",
    "sg:province":"WI",
    "sg:tags":[
        "sewing"
    ],
    "wof:name":"Sewing Basket",
    "wof:placetype":"venue"
},
  "geometry": {"coordinates":[-89.704793,45.179595],"type":"Point"}
}