{
  "type": "Feature",
  "properties": {
    "addr:full":"2290 N Shore Dr La Pointe WI 54850",
    "addr:housenumber":"2290",
    "addr:postcode":"54850",
    "addr:street":"N Shore Dr",
    "iso:country":"US",
    "sg:address":"2290 N Shore Dr",
    "sg:city":"La Pointe",
    "sg:classifiers":[
        {
            "category":"Real Estate",
            "subcategory":"Real Estate Agent",
            "type":"Services"
        }
    ],
    "sg:phone":"+1 715 747 2091",
    "sg:postcode":"54850",
    "sg:province":"WI",
    "wof:name":"Mad Isle Appraisal Services LL",
    "wof:placetype":"venue"
},
  "geometry": {"coordinates":[-90.706598,46.819778],"type":"Point"}
}