{
  "type": "Feature",
  "properties": {
    "iso:country":"US",
    "sg:address":"517 Rudolph Rd",
    "sg:city":"Cameron",
    "sg:classifiers":[
        {
            "category":"Manufacturing",
            "subcategory":"Lumber",
            "type":"Manufacturing & Wholesale Goods"
        }
    ],
    "sg:phone":"+1 715 458 4463",
    "sg:postcode":"54822",
    "sg:province":"WI",
    "sg:tags":[
        "company",
        "logging"
    ],
    "wof:name":"Red Cedar Logging Inc",
    "wof:placetype":"venue"
},
  "geometry": {"coordinates":[-91.760908,45.416577],"type":"Point"}
}