{
  "type": "Feature",
  "properties": {
    "iso:country":"US",
    "sg:address":"3216 S 92nd St",
    "sg:city":"Milwaukee",
    "sg:classifiers":[
        {
            "category":"Professional",
            "subcategory":"Employment Agencies",
            "type":"Services"
        }
    ],
    "sg:phone":"+1 414 321 2862",
    "sg:postcode":"53227",
    "sg:province":"WI",
    "sg:tags":[
        "opportunity"
    ],
    "wof:name":"Team Dental LLC",
    "wof:placetype":"venue"
},
  "geometry": {"coordinates":[-88.027484,42.98348],"type":"Point"}
}