{
  "type": "Feature",
  "properties": {
    "iso:country":"US",
    "sg:address":"673 Emmer St",
    "sg:city":"Mayville",
    "sg:classifiers":[
        {
            "category":"Real Estate",
            "subcategory":"Real Estate Agent",
            "type":"Services"
        }
    ],
    "sg:phone":"+1 920 387 4187",
    "sg:postcode":"53050",
    "sg:province":"WI",
    "wof:name":"Hilker Real Estate Dev",
    "wof:placetype":"venue"
},
  "geometry": {"coordinates":[-88.559934,43.50517],"type":"Point"}
}