{
  "type": "Feature",
  "properties": {
    "iso:country":"US",
    "sg:address":"115 N 6th St",
    "sg:city":"Wausau",
    "sg:classifiers":[
        {
            "category":"Real Estate",
            "subcategory":"Real Estate Agent",
            "type":"Services"
        }
    ],
    "sg:phone":"+1 715 849 5500",
    "sg:postcode":"54403",
    "sg:province":"WI",
    "wof:name":"Premier Property",
    "wof:placetype":"venue"
},
  "geometry": {"coordinates":[-89.62366299999999,44.957707],"type":"Point"}
}