{
  "type": "Feature",
  "properties": {
    "iso:country":"US",
    "sg:address":"15565 W North Ave",
    "sg:city":"Brookfield",
    "sg:classifiers":[
        {
            "category":"Banks & Credit Unions",
            "subcategory":"Bank",
            "type":"Services"
        }
    ],
    "sg:phone":"+1 262 860 2120",
    "sg:postcode":"53005",
    "sg:province":"WI",
    "wof:name":"Ridge Stone Bank",
    "wof:placetype":"venue"
},
  "geometry": {"coordinates":[-88.105596,43.060377],"type":"Point"}
}