{
  "type": "Feature",
  "properties": {
    "addr:full":"3811 Spring St Racine WI 53405",
    "addr:housenumber":"3811",
    "addr:postcode":"53405",
    "addr:street":"Spring St",
    "iso:country":"US",
    "sg:address":"3811 Spring St",
    "sg:city":"Racine",
    "sg:classifiers":[
        {
            "category":"Health Services",
            "subcategory":"Doctor",
            "type":"Services"
        }
    ],
    "sg:phone":"+1 262 687 5800",
    "sg:postcode":"53405",
    "sg:province":"WI",
    "sg:tags":[
        "medicine",
        "sport",
        "orthopedist"
    ],
    "sg:website":"www.mywheaton.org",
    "wof:name":"Siegert Robt F MD",
    "wof:placetype":"venue"
},
  "geometry": {"coordinates":[-87.82579800000001,42.733601],"type":"Point"}
}