{
  "type": "Feature",
  "properties": {
    "addr:full":"501 Commercial Ct Lake Geneva WI 53147",
    "addr:housenumber":"501",
    "addr:postcode":"53147",
    "addr:street":"Commercial Ct",
    "iso:country":"US",
    "sg:address":"501 Commercial Ct",
    "sg:city":"Lake Geneva",
    "sg:classifiers":[
        {
            "category":"Wholesale",
            "subcategory":"Office Equipment",
            "type":"Manufacturing & Wholesale Goods"
        }
    ],
    "sg:phone":"+1 262 248 8911",
    "sg:postcode":"53147",
    "sg:province":"WI",
    "sg:tags":[
        "machine",
        "duplicating",
        "copying"
    ],
    "sg:website":"www.martingroup.com",
    "wof:name":"Martin Business Group Inc",
    "wof:placetype":"venue"
},
  "geometry": {"coordinates":[-88.407336,42.576321],"type":"Point"}
}