{
  "type": "Feature",
  "properties": {
    "iso:country":"US",
    "sg:address":"13150 W Glendale Ave",
    "sg:city":"Butler",
    "sg:classifiers":[
        {
            "category":"Wholesale",
            "subcategory":"Machinery & Supplies",
            "type":"Manufacturing & Wholesale Goods"
        }
    ],
    "sg:phone":"+1 262 783 5808",
    "sg:postcode":"53007",
    "sg:province":"WI",
    "sg:tags":[
        "dyer",
        "cleaners",
        "equipment"
    ],
    "wof:name":"Herb Fitzgerald Co Inc",
    "wof:placetype":"venue"
},
  "geometry": {"coordinates":[-88.074544,43.10053],"type":"Point"}
}