{
  "type": "Feature",
  "properties": {
    "iso:country":"US",
    "sg:address":"8064 N 76th St",
    "sg:city":"Milwaukee",
    "sg:classifiers":[
        {
            "category":"Shopping",
            "subcategory":"Tobacco",
            "type":"Retail Goods"
        }
    ],
    "sg:phone":"+1 414 371 1732",
    "sg:postcode":"53223",
    "sg:province":"WI",
    "sg:tags":[
        "product"
    ],
    "wof:name":"Smokers Haven",
    "wof:placetype":"venue"
},
  "geometry": {"coordinates":[-88.004583,43.163948],"type":"Point"}
}