{
  "type": "Feature",
  "properties": {
    "iso:country":"US",
    "sg:address":"4366 Section 11 Rd",
    "sg:city":"La Valle",
    "sg:classifiers":[
        {
            "category":"Freight",
            "type":"Transportation"
        }
    ],
    "sg:phone":"+1 608 985 7737",
    "sg:postcode":"53941",
    "sg:province":"WI",
    "sg:tags":[
        "operator",
        "local",
        "trucking"
    ],
    "wof:name":"Schultz Trucking",
    "wof:placetype":"venue"
},
  "geometry": {"coordinates":[-90.098386,43.620068],"type":"Point"}
}