{
  "type": "Feature",
  "properties": {
    "iso:country":"US",
    "sg:address":"17800 W Bluemound Rd",
    "sg:city":"Brookfield",
    "sg:classifiers":[
        {
            "category":"Professional",
            "subcategory":"Lawyer & Legal Services",
            "type":"Services"
        }
    ],
    "sg:phone":"+1 262 786 7777",
    "sg:postcode":"53045",
    "sg:province":"WI",
    "sg:tags":[
        "attorney"
    ],
    "wof:name":"Brookmound Plaza",
    "wof:placetype":"venue"
},
  "geometry": {"coordinates":[-88.13656,43.03658],"type":"Point"}
}