{
  "type": "Feature",
  "properties": {
    "iso:country":"US",
    "sg:address":"1017 Kellogg Ave",
    "sg:city":"Janesville",
    "sg:classifiers":[
        {
            "category":"Professional",
            "subcategory":"Accounting & Tax Preparation",
            "type":"Services"
        }
    ],
    "sg:phone":"+1 608 741 0770",
    "sg:postcode":"53546",
    "sg:province":"WI",
    "sg:tags":[
        "return"
    ],
    "wof:name":"H & R Block",
    "wof:placetype":"venue"
},
  "geometry": {"coordinates":[-89.031971,42.649665],"type":"Point"}
}