{
  "type": "Feature",
  "properties": {
    "iso:country":"US",
    "sg:address":"329 North St",
    "sg:city":"Madison",
    "sg:classifiers":[
        {
            "category":"Organizations",
            "subcategory":"Religious Organization",
            "type":"Services"
        }
    ],
    "sg:phone":"+1 608 249 9222",
    "sg:postcode":"53704",
    "sg:province":"WI",
    "sg:tags":[
        "church"
    ],
    "sg:website":"www.wisconsinumc.org/bashford",
    "wof:name":"Bashford Unit Methodist Church",
    "wof:placetype":"venue"
},
  "geometry": {"coordinates":[-89.35063,43.103919],"type":"Point"}
}