{
  "type": "Feature",
  "properties": {
    "iso:country":"US",
    "sg:address":"63095 Vineyard Rd",
    "sg:city":"Prairie Du Chien",
    "sg:classifiers":[
        {
            "category":"Manufacturing",
            "subcategory":"Motor Vehicles & Parts",
            "type":"Manufacturing & Wholesale Goods"
        }
    ],
    "sg:phone":"+1 608 326 4333",
    "sg:postcode":"53821",
    "sg:province":"WI",
    "sg:tags":[
        "automobile",
        "supply"
    ],
    "sg:website":"www.mpc-inc.com",
    "wof:name":"Miniature Precision Components",
    "wof:placetype":"venue"
},
  "geometry": {"coordinates":[-91.095687,43.043469],"type":"Point"}
}