{
  "type": "Feature",
  "properties": {
    "addr:full":"2440 US Hwy 45 Antigo WI 54409",
    "addr:housenumber":"2440",
    "addr:postcode":"54409",
    "addr:street":"Us Hwy 45",
    "iso:country":"US",
    "sg:address":"2440 US Hwy 45",
    "sg:city":"Antigo",
    "sg:classifiers":[
        {
            "category":"Autos & Motor Vehicles",
            "subcategory":"Auto Supplies",
            "type":"Retail Goods"
        }
    ],
    "sg:phone":"+1 715 627 4311",
    "sg:postcode":"54409",
    "sg:province":"WI",
    "sg:tags":[
        "automobile",
        "parts"
    ],
    "wof:name":"Checker Auto Parts",
    "wof:placetype":"venue"
},
  "geometry": {"coordinates":[-89.147963,45.165192],"type":"Point"}
}