{
  "type": "Feature",
  "properties": {
    "addr:full":"551 N 62nd St Milwaukee WI 53213",
    "addr:housenumber":"551",
    "addr:postcode":"53213",
    "addr:street":"N 62Nd St",
    "iso:country":"US",
    "sg:address":"551 N 62nd St",
    "sg:city":"Milwaukee",
    "sg:classifiers":[
        {
            "category":"Shopping",
            "subcategory":"Jewelry",
            "type":"Retail Goods"
        }
    ],
    "sg:phone":"+1 414 774 0588",
    "sg:postcode":"53213",
    "sg:province":"WI",
    "wof:name":"K&A Jewelry LLC",
    "wof:placetype":"venue"
},
  "geometry": {"coordinates":[-87.990022,43.038505],"type":"Point"}
}