{
  "type": "Feature",
  "properties": {
    "iso:country":"US",
    "sg:address":"213 N Wisconsin St",
    "sg:city":"Port Washington",
    "sg:classifiers":[
        {
            "category":"Banks & Credit Unions",
            "subcategory":"Investment Brokerage",
            "type":"Services"
        }
    ],
    "sg:phone":"+1 262 284 7153",
    "sg:postcode":"53074",
    "sg:province":"WI",
    "sg:tags":[
        "security"
    ],
    "wof:name":"Edward Jones Co",
    "wof:placetype":"venue"
},
  "geometry": {"coordinates":[-87.870976,43.388605],"type":"Point"}
}