{
  "type": "Feature",
  "properties": {
    "addr:full":"138 E Geneva Sq Lake Geneva WI 53147",
    "addr:housenumber":"138",
    "addr:postcode":"53147",
    "addr:street":"E Geneva Sq",
    "iso:country":"US",
    "sg:address":"138 E Geneva Sq",
    "sg:city":"Lake Geneva",
    "sg:classifiers":[
        {
            "category":"Professional",
            "subcategory":"Management & Consulting",
            "type":"Services"
        }
    ],
    "sg:phone":"+1 262 248 6268",
    "sg:postcode":"53147",
    "sg:province":"WI",
    "sg:tags":[
        "home",
        "retail",
        "fixture",
        "furnishing"
    ],
    "wof:name":"Paper Dolls Ltd",
    "wof:placetype":"venue"
},
  "geometry": {"coordinates":[-88.424764,42.606551],"type":"Point"}
}