{
  "type": "Feature",
  "properties": {
    "iso:country":"US",
    "sg:address":"516 Oak St",
    "sg:city":"Baraboo",
    "sg:classifiers":[
        {
            "category":"Shopping",
            "subcategory":"Hobbies, Toys, & Games",
            "type":"Retail Goods"
        },
        {
            "category":"Shopping",
            "subcategory":"Gifts & Souvenirs",
            "type":"Retail Goods"
        }
    ],
    "sg:phone":"+1 608 356 6901",
    "sg:postcode":"53913",
    "sg:province":"WI",
    "sg:tags":[
        "shop"
    ],
    "wof:name":"Jerry's Hallmark Shop",
    "wof:placetype":"venue"
},
  "geometry": {"coordinates":[-89.742406,43.470733],"type":"Point"}
}