{
  "type": "Feature",
  "properties": {
    "iso:country":"US",
    "sg:address":"10551 Main St",
    "sg:city":"Hayward",
    "sg:classifiers":[
        {
            "category":"Shopping",
            "subcategory":"Discount & Variety Stores",
            "type":"Retail Goods"
        }
    ],
    "sg:phone":"+1 715 634 6035",
    "sg:postcode":"54843",
    "sg:province":"WI",
    "sg:tags":[
        "merchandise",
        "general"
    ],
    "wof:name":"Pavillion",
    "wof:placetype":"venue"
},
  "geometry": {"coordinates":[-91.48404600000001,46.014088],"type":"Point"}
}