{
  "type": "Feature",
  "properties": {
    "iso:country":"US",
    "sg:address":"7997 S Loomis Rd",
    "sg:city":"Wind Lake",
    "sg:classifiers":[
        {
            "category":"Real Estate",
            "subcategory":"Real Estate Agent",
            "type":"Services"
        }
    ],
    "sg:phone":"+1 414 425 4030",
    "sg:postcode":"53185",
    "sg:province":"WI",
    "sg:website":"www.wendt-realty.com",
    "wof:name":"Mel Wendt Realty Inc",
    "wof:placetype":"venue"
},
  "geometry": {"coordinates":[-88.15936000000001,42.828074],"type":"Point"}
}