{
  "type": "Feature",
  "properties": {
    "iso:country":"US",
    "sg:address":"10726 Hidden Valley Rd",
    "sg:city":"Cedarburg",
    "sg:classifiers":[
        {
            "category":"Professional",
            "subcategory":"Management & Consulting",
            "type":"Services"
        }
    ],
    "sg:phone":"+1 262 375 2303",
    "sg:postcode":"53012",
    "sg:province":"WI",
    "wof:name":"National Emergency Services",
    "wof:placetype":"venue"
},
  "geometry": {"coordinates":[-88.046818,43.333792],"type":"Point"}
}