{
  "type": "Feature",
  "properties": {
    "iso:country":"US",
    "sg:address":"1704 George St",
    "sg:city":"La Crosse",
    "sg:classifiers":[
        {
            "category":"Shopping",
            "subcategory":"Computers & Home Electronics",
            "type":"Retail Goods"
        }
    ],
    "sg:phone":"+1 608 782 8300",
    "sg:postcode":"54603",
    "sg:province":"WI",
    "sg:tags":[
        "equipment",
        "satellite",
        "system"
    ],
    "wof:name":"Best Satellite Systems & Svc",
    "wof:placetype":"venue"
},
  "geometry": {"coordinates":[-91.239688,43.849156],"type":"Point"}
}