{
  "type": "Feature",
  "properties": {
    "addr:full":"308 N Gwinn St Loyal WI 54446",
    "addr:housenumber":"308",
    "addr:postcode":"54446",
    "addr:street":"N Gwinn St",
    "iso:country":"US",
    "sg:address":"308 N Gwinn St",
    "sg:city":"Loyal",
    "sg:classifiers":[
        {
            "category":"Professional",
            "type":"Services"
        }
    ],
    "sg:phone":"+1 715 255 9408",
    "sg:postcode":"54446",
    "sg:province":"WI",
    "sg:tags":[
        "establishment"
    ],
    "wof:name":"Brostowitz & Brostowitz",
    "wof:placetype":"venue"
},
  "geometry": {"coordinates":[-90.50102,44.740209],"type":"Point"}
}