{
  "type": "Feature",
  "properties": {
    "addr:full":"212 3rd St De Pere WI 54115",
    "addr:housenumber":"212",
    "addr:postcode":"54115",
    "addr:street":"3Rd St",
    "iso:country":"US",
    "sg:address":"212 3rd St",
    "sg:city":"De Pere",
    "sg:classifiers":[
        {
            "category":"Education",
            "subcategory":"College",
            "type":"Public Place"
        }
    ],
    "sg:phone":"+1 920 337 1160",
    "sg:postcode":"54115",
    "sg:province":"WI",
    "sg:tags":[
        "academic",
        "school"
    ],
    "wof:name":"St Norbert College",
    "wof:placetype":"venue"
},
  "geometry": {"coordinates":[-88.06866599999999,44.445437],"type":"Point"}
}