{
  "type": "Feature",
  "properties": {
    "iso:country":"US",
    "sg:address":"2323 E Capitol Dr",
    "sg:city":"Appleton",
    "sg:classifiers":[
        {
            "category":"Professional",
            "subcategory":"Engineering",
            "type":"Services"
        }
    ],
    "sg:phone":"+1 920 954 2000",
    "sg:postcode":"54911",
    "sg:province":"WI",
    "sg:tags":[
        "consultant",
        "engineer"
    ],
    "wof:name":"Marathon Eng/Archtect/Planners",
    "wof:placetype":"venue"
},
  "geometry": {"coordinates":[-88.37047800000001,44.294393],"type":"Point"}
}