{
  "type": "Feature",
  "properties": {
    "iso:country":"US",
    "sg:address":"777 S Barker Rd",
    "sg:city":"Brookfield",
    "sg:classifiers":[
        {
            "category":"Shopping",
            "subcategory":"Books",
            "type":"Retail Goods"
        }
    ],
    "sg:phone":"+1 262 796 5720",
    "sg:postcode":"53045",
    "sg:province":"WI",
    "sg:tags":[
        "dealer"
    ],
    "sg:website":"www.gardenofreadin.com",
    "wof:name":"Garden Of Readin'",
    "wof:placetype":"venue"
},
  "geometry": {"coordinates":[-88.16687,43.023159],"type":"Point"}
}