{
  "type": "Feature",
  "properties": {
    "iso:country":"US",
    "sg:address":"1215 Deer Path",
    "sg:city":"Phelps",
    "sg:classifiers":[
        {
            "category":"Building & Trades",
            "subcategory":"Construction",
            "type":"Services"
        }
    ],
    "sg:phone":"+1 715 545 8340",
    "sg:postcode":"54554",
    "sg:province":"WI",
    "sg:tags":[
        "contractor"
    ],
    "wof:name":"James & Karen Cyganiak",
    "wof:placetype":"venue"
},
  "geometry": {"coordinates":[-89.006573,46.066403],"type":"Point"}
}