{
  "type": "Feature",
  "properties": {
    "iso:country":"US",
    "sg:address":"6713 Odana Rd",
    "sg:city":"Madison",
    "sg:classifiers":[
        {
            "category":"Building & Trades",
            "subcategory":"Plumbing",
            "type":"Services"
        }
    ],
    "sg:phone":"+1 608 836 7890",
    "sg:postcode":"53719",
    "sg:province":"WI",
    "sg:tags":[
        "conditioning",
        "air",
        "system",
        "contractor"
    ],
    "wof:name":"Always Affordable Heating & AC",
    "wof:placetype":"venue"
},
  "geometry": {"coordinates":[-89.501277,43.056523],"type":"Point"}
}