{
  "type": "Feature",
  "properties": {
    "iso:country":"US",
    "sg:address":"964 Co Rd J",
    "sg:city":"Mondovi",
    "sg:classifiers":[
        {
            "category":"Organizations",
            "subcategory":"Religious Organization",
            "type":"Services"
        }
    ],
    "sg:phone":"+1 715 946 3840",
    "sg:postcode":"54755",
    "sg:province":"WI",
    "wof:name":"Modena Lutheran Church",
    "wof:placetype":"venue"
},
  "geometry": {"coordinates":[-91.795774,44.454221],"type":"Point"}
}