{
  "type": "Feature",
  "properties": {
    "iso:country":"US",
    "sg:address":"301 S Bedford St",
    "sg:city":"Madison",
    "sg:classifiers":[
        {
            "category":"Health Services",
            "subcategory":"Health Practitioner",
            "type":"Services"
        }
    ],
    "sg:phone":"+1 608 294 5943",
    "sg:postcode":"53703",
    "sg:province":"WI",
    "sg:tags":[
        "therapist",
        "physical"
    ],
    "wof:name":"Karen Jaeger",
    "wof:placetype":"venue"
},
  "geometry": {"coordinates":[-89.388616,43.065943],"type":"Point"}
}