{
  "type": "Feature",
  "properties": {
    "iso:country":"US",
    "sg:address":"402 W River St",
    "sg:city":"Chippewa Falls",
    "sg:classifiers":[
        {
            "category":"Cinema",
            "subcategory":"Movie Rental",
            "type":"Entertainment"
        }
    ],
    "sg:phone":"+1 715 723 8002",
    "sg:postcode":"54729",
    "sg:province":"WI",
    "sg:tags":[
        "leasing",
        "video",
        "disc",
        "tape"
    ],
    "wof:name":"Celebrity Video & Tan",
    "wof:placetype":"venue"
},
  "geometry": {"coordinates":[-91.401741,44.930154],"type":"Point"}
}