{
  "type": "Feature",
  "properties": {
    "iso:country":"US",
    "sg:address":"4573 US Hwy 45",
    "sg:city":"Watersmeet",
    "sg:classifiers":[
        {
            "category":"Autos & Motor Vehicles",
            "subcategory":"Fuel & Gas Station",
            "type":"Retail Goods"
        }
    ],
    "sg:phone":"+1 906 358 4252",
    "sg:postcode":"49969",
    "sg:province":"WI",
    "sg:tags":[
        "oil"
    ],
    "wof:name":"Citgo Quik Food Mart",
    "wof:placetype":"venue"
},
  "geometry": {"coordinates":[-89.17852999999999,46.264075],"type":"Point"}
}