{
  "type": "Feature",
  "properties": {
    "iso:country":"US",
    "sg:address":"5707 W Vliet St",
    "sg:city":"Milwaukee",
    "sg:classifiers":[
        {
            "category":"Government",
            "subcategory":"Fire Station",
            "type":"Public Place"
        }
    ],
    "sg:phone":"+1 414 774 0772",
    "sg:postcode":"53208",
    "sg:province":"WI",
    "sg:tags":[
        "extinguisher"
    ],
    "wof:name":"Milwaukee Recharging Service Inc",
    "wof:placetype":"venue"
},
  "geometry": {"coordinates":[-87.984245,43.049666],"type":"Point"}
}