{
  "type": "Feature",
  "properties": {
    "addr:full":"604 Joes Ln Platteville WI 53818",
    "addr:housenumber":"604",
    "addr:postcode":"53818",
    "addr:street":"Joes Ln",
    "iso:country":"US",
    "sg:address":"604 Joes Ln",
    "sg:city":"Platteville",
    "sg:classifiers":[
        {
            "category":"Manufacturing",
            "subcategory":"Tools & Machinery",
            "type":"Manufacturing & Wholesale Goods"
        }
    ],
    "sg:phone":"+1 608 348 9176",
    "sg:postcode":"53818",
    "sg:province":"WI",
    "sg:tags":[
        "equipment",
        "welding",
        "supply"
    ],
    "wof:name":"Leo Wilcox Gases & Steel",
    "wof:placetype":"venue"
},
  "geometry": {"coordinates":[-90.45226700000001,42.835128],"type":"Point"}
}