{
  "type": "Feature",
  "properties": {
    "iso:country":"US",
    "sg:address":"3360 Co Hwy C",
    "sg:city":"Barnes",
    "sg:classifiers":[
        {
            "category":"Wholesale",
            "subcategory":"Scrap",
            "type":"Manufacturing & Wholesale Goods"
        }
    ],
    "sg:phone":"+1 715 795 2244",
    "sg:postcode":"54835",
    "sg:province":"WI",
    "sg:tags":[
        "recycling",
        "center"
    ],
    "wof:name":"Barnes Compactor & Recycling",
    "wof:placetype":"venue"
},
  "geometry": {"coordinates":[-91.354898,45.756006],"type":"Point"}
}