{
  "type": "Feature",
  "properties": {
    "iso:country":"US",
    "sg:address":"620 W Clairemont Ave",
    "sg:city":"Eau Claire",
    "sg:classifiers":[
        {
            "category":"Organizations",
            "subcategory":"Membership Organization",
            "type":"Services"
        }
    ],
    "sg:phone":"+1 715 833 6276",
    "sg:postcode":"54701",
    "sg:province":"WI",
    "wof:name":"Momentum Chippewa Valley Inc",
    "wof:placetype":"venue"
},
  "geometry": {"coordinates":[-91.506592,44.79327],"type":"Point"}
}