{
  "type": "Feature",
  "properties": {
    "iso:country":"US",
    "sg:address":"4429 Robertson Rd",
    "sg:city":"Madison",
    "sg:classifiers":[
        {
            "category":"Wholesale",
            "subcategory":"Machinery & Supplies",
            "type":"Manufacturing & Wholesale Goods"
        }
    ],
    "sg:phone":"+1 608 244 5678",
    "sg:postcode":"53714",
    "sg:province":"WI",
    "sg:tags":[
        "tool"
    ],
    "wof:name":"Gordon Engineering Inc",
    "wof:placetype":"venue"
},
  "geometry": {"coordinates":[-89.310205,43.093167],"type":"Point"}
}