{
  "type": "Feature",
  "properties": {
    "iso:country":"US",
    "sg:address":"1405 N Main St",
    "sg:city":"West Bend",
    "sg:classifiers":[
        {
            "category":"Retail",
            "subcategory":"Auto Repair",
            "type":"Services"
        }
    ],
    "sg:phone":"+1 262 334 2245",
    "sg:postcode":"53090",
    "sg:province":"WI",
    "sg:tags":[
        "body",
        "automobile",
        "frame",
        "painting"
    ],
    "wof:name":"Vrana Frame & Body Shop Inc",
    "wof:placetype":"venue"
},
  "geometry": {"coordinates":[-88.184173,43.436486],"type":"Point"}
}