{
  "type": "Feature",
  "properties": {
    "iso:country":"US",
    "sg:address":"4734 State Hwy 78",
    "sg:city":"Black Earth",
    "sg:classifiers":[
        {
            "category":"Freight",
            "type":"Transportation"
        }
    ],
    "sg:phone":"+1 608 767 3000",
    "sg:postcode":"53515",
    "sg:province":"WI",
    "sg:tags":[
        "commercial",
        "storage"
    ],
    "wof:name":"Vermont Stor-All",
    "wof:placetype":"venue"
},
  "geometry": {"coordinates":[-89.754162,43.111466],"type":"Point"}
}