{
  "type": "Feature",
  "properties": {
    "iso:country":"US",
    "sg:address":"602 E Division St",
    "sg:city":"Sparta",
    "sg:classifiers":[
        {
            "category":"Government",
            "subcategory":"Office",
            "type":"Public Place"
        }
    ],
    "sg:phone":"+1 608 269 2776",
    "sg:postcode":"54656",
    "sg:province":"WI",
    "sg:tags":[
        "national",
        "security"
    ],
    "wof:name":"Wisconsin Nat Gard 107th Maint",
    "wof:placetype":"venue"
},
  "geometry": {"coordinates":[-90.802928,43.953575],"type":"Point"}
}