{
  "type": "Feature",
  "properties": {
    "iso:country":"US",
    "sg:address":"7271 S 48th St",
    "sg:city":"Franklin",
    "sg:classifiers":[
        {
            "category":"Retail",
            "subcategory":"Repair Shop",
            "type":"Services"
        }
    ],
    "sg:phone":"+1 414 421 1353",
    "sg:postcode":"53132",
    "sg:province":"WI",
    "sg:tags":[
        "electrical"
    ],
    "wof:name":"All American Appliance",
    "wof:placetype":"venue"
},
  "geometry": {"coordinates":[-87.974813,42.910851],"type":"Point"}
}