{
  "type": "Feature",
  "properties": {
    "iso:country":"US",
    "sg:address":"12426 S Florence Dr",
    "sg:city":"Clinton",
    "sg:classifiers":[
        {
            "category":"Building & Trades",
            "subcategory":"Landscaping Services",
            "type":"Services"
        }
    ],
    "sg:phone":"+1 262 296 1635",
    "sg:postcode":"53525",
    "sg:province":"WI",
    "sg:tags":[
        "tree",
        "stump",
        "grinding",
        "removal"
    ],
    "wof:name":"Mark Franseen & Son Stump Grinding",
    "wof:placetype":"venue"
},
  "geometry": {"coordinates":[-88.868205,42.494676],"type":"Point"}
}