{
  "type": "Feature",
  "properties": {
    "iso:country":"US",
    "sg:address":"1606 US Hwy 2",
    "sg:city":"Ashland",
    "sg:classifiers":[
        {
            "category":"Autos & Motor Vehicles",
            "subcategory":"Automobile Sales",
            "type":"Retail Goods"
        }
    ],
    "sg:phone":"+1 715 682 8141",
    "sg:postcode":"54806",
    "sg:province":"WI",
    "sg:tags":[
        "car",
        "dealer"
    ],
    "sg:website":"www.vonholzen.com",
    "wof:name":"Von Holzen Pontiac Buick Inc",
    "wof:placetype":"venue"
},
  "geometry": {"coordinates":[-90.86609799999999,46.601235],"type":"Point"}
}