{
  "type": "Feature",
  "properties": {
    "iso:country":"US",
    "sg:address":"828 Center Ave",
    "sg:city":"Sheboygan",
    "sg:classifiers":[
        {
            "category":"Banks & Credit Unions",
            "subcategory":"Bank",
            "type":"Services"
        }
    ],
    "sg:phone":"+1 920 459 3333",
    "sg:postcode":"53081",
    "sg:province":"WI",
    "sg:tags":[
        "state"
    ],
    "wof:name":"Sheboygan Credit Union",
    "wof:placetype":"venue"
},
  "geometry": {"coordinates":[-87.71426700000001,43.750958],"type":"Point"}
}