{
  "type": "Feature",
  "properties": {
    "iso:country":"US",
    "sg:address":"121 W Edgewater St",
    "sg:city":"Portage",
    "sg:classifiers":[
        {
            "category":"Personal",
            "subcategory":"Beauty Salon",
            "type":"Services"
        }
    ],
    "sg:phone":"+1 920 348 5851",
    "sg:postcode":"53901",
    "sg:province":"WI",
    "wof:name":"A Little Off The Top",
    "wof:placetype":"venue"
},
  "geometry": {"coordinates":[-89.459047,43.539123],"type":"Point"}
}