{
  "type": "Feature",
  "properties": {
    "addr:full":"1919 S Broadway Green Bay WI 54304",
    "addr:housenumber":"1919",
    "addr:postcode":"54304",
    "addr:street":"S Broadway",
    "iso:country":"US",
    "sg:address":"1919 S Broadway",
    "sg:city":"Green Bay",
    "sg:classifiers":[
        {
            "category":"Manufacturing",
            "subcategory":"Paper Products",
            "type":"Manufacturing & Wholesale Goods"
        }
    ],
    "sg:phone":"+1 920 435 8821",
    "sg:postcode":"54304",
    "sg:province":"WI",
    "sg:tags":[
        "sanitary"
    ],
    "wof:name":"Georgia-Pacific Corp",
    "wof:placetype":"venue"
},
  "geometry": {"coordinates":[-88.037329,44.493004],"type":"Point"}
}