{
  "type": "Feature",
  "properties": {
    "addr:full":"5871 State Rd 22 Wild Rose WI 54984",
    "addr:housenumber":"5871;22",
    "addr:postcode":"54984",
    "addr:street":"State Rd",
    "iso:country":"US",
    "sg:address":"5871 State Rd 22",
    "sg:city":"Wild Rose",
    "sg:classifiers":[
        {
            "category":"Government",
            "subcategory":"Office",
            "type":"Public Place"
        }
    ],
    "sg:phone":"+1 920 622 3527",
    "sg:postcode":"54984",
    "sg:province":"WI",
    "sg:tags":[
        "hatchery",
        "state",
        "fish"
    ],
    "wof:name":"Dnr Fish Hatchery",
    "wof:placetype":"venue"
},
  "geometry": {"coordinates":[-89.247299,44.186112],"type":"Point"}
}