{
  "type": "Feature",
  "properties": {
    "iso:country":"US",
    "sg:address":"2827 Co Rd K",
    "sg:city":"Fond Du Lac",
    "sg:classifiers":[
        {
            "category":"Professional",
            "subcategory":"Accounting & Tax Preparation",
            "type":"Services"
        }
    ],
    "sg:phone":"+1 920 923 4436",
    "sg:postcode":"54935",
    "sg:province":"WI",
    "sg:tags":[
        "return"
    ],
    "wof:name":"Toshner Tax Service",
    "wof:placetype":"venue"
},
  "geometry": {"coordinates":[-88.401081,43.643137],"type":"Point"}
}