{
  "type": "Feature",
  "properties": {
    "addr:full":"1822 University Ave Green Bay WI 54302",
    "addr:housenumber":"1822",
    "addr:postcode":"54302",
    "addr:street":"University Ave",
    "iso:country":"US",
    "sg:address":"1822 University Ave",
    "sg:city":"Green Bay",
    "sg:classifiers":[
        {
            "category":"Travel",
            "subcategory":"Travel Agent",
            "type":"Entertainment"
        }
    ],
    "sg:phone":"+1 920 432 3226",
    "sg:postcode":"54302",
    "sg:province":"WI",
    "sg:tags":[
        "agency"
    ],
    "wof:name":"More Fun Tours & Travel",
    "wof:placetype":"venue"
},
  "geometry": {"coordinates":[-87.974357,44.512469],"type":"Point"}
}