{
  "type": "Feature",
  "properties": {
    "iso:country":"US",
    "sg:address":"1513 E Harding Dr",
    "sg:city":"Appleton",
    "sg:classifiers":[
        {
            "category":"Manufacturing",
            "subcategory":"Building Materials",
            "type":"Manufacturing & Wholesale Goods"
        }
    ],
    "sg:phone":"+1 920 954 5963",
    "sg:postcode":"54915",
    "sg:province":"WI",
    "sg:tags":[
        "shutter",
        "mfg"
    ],
    "wof:name":"Shutter Specials",
    "wof:placetype":"venue"
},
  "geometry": {"coordinates":[-88.38094599999999,44.24163],"type":"Point"}
}