{
  "type": "Feature",
  "properties": {
    "iso:country":"US",
    "sg:address":"2274 Willow Way Dr",
    "sg:city":"Oshkosh",
    "sg:classifiers":[
        {
            "category":"Building & Trades",
            "subcategory":"Construction",
            "type":"Services"
        }
    ],
    "sg:phone":"+1 920 426 1556",
    "sg:postcode":"54904",
    "sg:province":"WI",
    "sg:tags":[
        "residential"
    ],
    "wof:name":"Fasel Mark Cstm Bilt Homes LLC",
    "wof:placetype":"venue"
},
  "geometry": {"coordinates":[-88.590585,44.036052],"type":"Point"}
}