{
  "type": "Feature",
  "properties": {
    "iso:country":"US",
    "sg:address":"4320 W Prospect Ave",
    "sg:city":"Appleton",
    "sg:classifiers":[
        {
            "category":"Food & Beverages",
            "subcategory":"Groceries & Convenience Stores",
            "type":"Retail Goods"
        },
        {
            "category":"Autos & Motor Vehicles",
            "subcategory":"Fuel & Gas Station",
            "type":"Retail Goods"
        }
    ],
    "sg:phone":"+1 920 738 5667",
    "sg:postcode":"54914",
    "sg:province":"WI",
    "sg:tags":[
        "oil"
    ],
    "wof:name":"B B Mobil Mart",
    "wof:placetype":"venue"
},
  "geometry": {"coordinates":[-88.47045900000001,44.244176],"type":"Point"}
}