{
  "type": "Feature",
  "properties": {
    "iso:country":"US",
    "sg:address":"4484 Potter Rd",
    "sg:city":"Elkhorn",
    "sg:classifiers":[
        {
            "category":"Freight",
            "type":"Transportation"
        }
    ],
    "sg:phone":"+1 262 723 2937",
    "sg:postcode":"53121",
    "sg:province":"WI",
    "sg:tags":[
        "trucking"
    ],
    "wof:name":"De Young Trucking",
    "wof:placetype":"venue"
},
  "geometry": {"coordinates":[-88.51351,42.706425],"type":"Point"}
}