{
  "type": "Feature",
  "properties": {
    "iso:country":"US",
    "sg:address":"1102 N 8th St",
    "sg:city":"Sheboygan",
    "sg:classifiers":[
        {
            "category":"Banks & Credit Unions",
            "subcategory":"Bank",
            "type":"Services"
        }
    ],
    "sg:phone":"+1 920 451 1001",
    "sg:postcode":"53081",
    "sg:province":"WI",
    "sg:tags":[
        "mortgage"
    ],
    "wof:name":"Countrywide",
    "wof:placetype":"venue"
},
  "geometry": {"coordinates":[-87.713016,43.757414],"type":"Point"}
}