{
  "type": "Feature",
  "properties": {
    "iso:country":"US",
    "sg:address":"2936 Freedom Rd",
    "sg:city":"Oneida",
    "sg:classifiers":[
        {
            "category":"Government",
            "subcategory":"Office",
            "type":"Public Place"
        }
    ],
    "sg:phone":"+1 920 869 3091",
    "sg:postcode":"54115",
    "sg:province":"WI",
    "wof:name":"Oneida Tribe Parish Hall",
    "wof:placetype":"venue"
},
  "geometry": {"coordinates":[-88.182205,44.386223],"type":"Point"}
}