{
  "type": "Feature",
  "properties": {
    "iso:country":"US",
    "sg:address":"10239 Cedarburg Rd",
    "sg:city":"Mequon",
    "sg:classifiers":[
        {
            "category":"Professional",
            "subcategory":"Business Services",
            "type":"Services"
        }
    ],
    "sg:phone":"+1 262 242 0711",
    "sg:postcode":"53092",
    "sg:province":"WI",
    "sg:tags":[
        "water",
        "treatment"
    ],
    "wof:name":"Kaiser Water Conditioning Co",
    "wof:placetype":"venue"
},
  "geometry": {"coordinates":[-87.970924,43.203882],"type":"Point"}
}