{
  "type": "Feature",
  "properties": {
    "iso:country":"US",
    "sg:address":"114 Jefferson Ave",
    "sg:city":"Janesville",
    "sg:classifiers":[
        {
            "category":"Shopping",
            "subcategory":"Gifts & Souvenirs",
            "type":"Retail Goods"
        }
    ],
    "sg:phone":"+1 608 756 5565",
    "sg:postcode":"53545",
    "sg:province":"WI",
    "wof:name":"Draft",
    "wof:placetype":"venue"
},
  "geometry": {"coordinates":[-89.011182,42.684952],"type":"Point"}
}