{
  "type": "Feature",
  "properties": {
    "addr:full":"109 South St Waunakee WI 53597",
    "addr:housenumber":"109",
    "addr:postcode":"53597",
    "addr:street":"South St",
    "iso:country":"US",
    "sg:address":"109 South St",
    "sg:city":"Waunakee",
    "sg:classifiers":[
        {
            "category":"Building & Trades",
            "subcategory":"Electrical",
            "type":"Services"
        }
    ],
    "sg:phone":"+1 608 849 4412",
    "sg:postcode":"53597",
    "sg:province":"WI",
    "sg:tags":[
        "electric",
        "contractor"
    ],
    "wof:name":"Kuehn Electric Inc",
    "wof:placetype":"venue"
},
  "geometry": {"coordinates":[-89.45503100000001,43.190896],"type":"Point"}
}