{
  "type": "Feature",
  "properties": {
    "addr:full":"15862 W 2nd St Hayward WI 54843",
    "addr:housenumber":"15862",
    "addr:postcode":"54843",
    "addr:street":"W 2Nd St",
    "iso:country":"US",
    "sg:address":"15862 W 2nd St",
    "sg:city":"Hayward",
    "sg:classifiers":[
        {
            "category":"Shopping",
            "subcategory":"Computers & Home Electronics",
            "type":"Retail Goods"
        }
    ],
    "sg:phone":"+1 715 638 2410",
    "sg:postcode":"54843",
    "sg:province":"WI",
    "sg:tags":[
        "software"
    ],
    "wof:name":"Pro Consulting Inc",
    "wof:placetype":"venue"
},
  "geometry": {"coordinates":[-91.486131,46.013436],"type":"Point"}
}