{
  "type": "Feature",
  "properties": {
    "iso:country":"US",
    "sg:address":"4710 Camp Phillips Rd",
    "sg:city":"Schofield",
    "sg:classifiers":[
        {
            "category":"Wholesale",
            "subcategory":"Painting Supplies",
            "type":"Manufacturing & Wholesale Goods"
        }
    ],
    "sg:phone":"+1 715 355 4611",
    "sg:postcode":"54476",
    "sg:province":"WI",
    "sg:tags":[
        "body",
        "paint",
        "auto",
        "repair"
    ],
    "wof:name":"Pauls Paint Center Inc",
    "wof:placetype":"venue"
},
  "geometry": {"coordinates":[-89.572457,44.913513],"type":"Point"}
}