{
  "type": "Feature",
  "properties": {
    "iso:country":"US",
    "sg:address":"824 Milwaukee St",
    "sg:city":"Collins",
    "sg:classifiers":[
        {
            "category":"Retail",
            "subcategory":"Auto Repair",
            "type":"Services"
        }
    ],
    "sg:phone":"+1 920 772 4214",
    "sg:postcode":"54207",
    "sg:province":"WI",
    "sg:tags":[
        "repairing",
        "automobile"
    ],
    "wof:name":"Don's Auto Repair",
    "wof:placetype":"venue"
},
  "geometry": {"coordinates":[-87.982578,44.086491],"type":"Point"}
}