{
  "type": "Feature",
  "properties": {
    "addr:full":"656 Jaworski Rd Pulaski WI 54162",
    "addr:housenumber":"656",
    "addr:postcode":"54162",
    "addr:street":"Jaworski Rd",
    "iso:country":"US",
    "sg:address":"656 Jaworski Rd",
    "sg:city":"Pulaski",
    "sg:classifiers":[
        {
            "category":"Building & Trades",
            "subcategory":"Cleaning & Sanitation",
            "type":"Services"
        }
    ],
    "sg:phone":"+1 920 822 4136",
    "sg:postcode":"54162",
    "sg:province":"WI",
    "sg:tags":[
        "maintenance"
    ],
    "wof:name":"Ms Maintenance LLC",
    "wof:placetype":"venue"
},
  "geometry": {"coordinates":[-88.201221,44.693644],"type":"Point"}
}