{
  "type": "Feature",
  "properties": {
    "iso:country":"US",
    "sg:address":"13780 W Greenfield Ave",
    "sg:city":"Brookfield",
    "sg:classifiers":[
        {
            "category":"Personal",
            "subcategory":"Tanning Parlor",
            "type":"Services"
        }
    ],
    "sg:phone":"+1 262 797 8485",
    "sg:postcode":"53005",
    "sg:province":"WI",
    "sg:tags":[
        "salon"
    ],
    "wof:name":"Karlberg Tan",
    "wof:placetype":"venue"
},
  "geometry": {"coordinates":[-88.08569,43.016618],"type":"Point"}
}