{
  "type": "Feature",
  "properties": {
    "iso:country":"US",
    "sg:address":"383 Oak St",
    "sg:city":"Arena",
    "sg:classifiers":[
        {
            "category":"Organizations",
            "subcategory":"Religious Organization",
            "type":"Services"
        }
    ],
    "sg:phone":"+1 608 753 2242",
    "sg:postcode":"53503",
    "sg:province":"WI",
    "wof:name":"Arena Congregational Church",
    "wof:placetype":"venue"
},
  "geometry": {"coordinates":[-89.91388999999999,43.1639],"type":"Point"}
}