{
  "type": "Feature",
  "properties": {
    "iso:country":"US",
    "sg:address":"1201 Union Ave",
    "sg:city":"Sheboygan",
    "sg:classifiers":[
        {
            "category":"Retail",
            "subcategory":"Repair Shop",
            "type":"Services"
        }
    ],
    "sg:phone":"+1 920 459 9419",
    "sg:postcode":"53081",
    "sg:province":"WI",
    "sg:tags":[
        "instrument",
        "musical"
    ],
    "wof:name":"Schieble's Instrument Repair",
    "wof:placetype":"venue"
},
  "geometry": {"coordinates":[-87.720389,43.732028],"type":"Point"}
}