{
  "type": "Feature",
  "properties": {
    "iso:country":"US",
    "sg:address":"232 Cove Ln",
    "sg:city":"Hudson",
    "sg:classifiers":[
        {
            "category":"Building & Trades",
            "subcategory":"Construction",
            "type":"Services"
        }
    ],
    "sg:phone":"+1 715 386 1475",
    "sg:postcode":"54016",
    "sg:province":"WI",
    "sg:tags":[
        "general",
        "contractor"
    ],
    "wof:name":"Cascade Construction Svc Inc",
    "wof:placetype":"venue"
},
  "geometry": {"coordinates":[-92.756483,44.898698],"type":"Point"}
}