{
  "type": "Feature",
  "properties": {
    "addr:full":"13200 W Greenfield Ave Brookfield WI 53005",
    "addr:housenumber":"13200",
    "addr:postcode":"53005",
    "addr:street":"W Greenfield Ave",
    "iso:country":"US",
    "sg:address":"13200 W Greenfield Ave",
    "sg:city":"Brookfield",
    "sg:classifiers":[
        {
            "category":"Organizations",
            "subcategory":"Religious Organization",
            "type":"Services"
        }
    ],
    "sg:phone":"+1 262 782 8370",
    "sg:postcode":"53005",
    "sg:province":"WI",
    "sg:tags":[
        "church"
    ],
    "wof:name":"Gethsemane Evangelical Luth",
    "wof:placetype":"venue"
},
  "geometry": {"coordinates":[-88.078435,43.016486],"type":"Point"}
}