{
  "type": "Feature",
  "properties": {
    "iso:country":"US",
    "sg:address":"11069 Co Rd D",
    "sg:city":"Marion",
    "sg:classifiers":[
        {
            "category":"Bars & Pubs",
            "type":"Food & Drink"
        }
    ],
    "sg:phone":"+1 715 754 2531",
    "sg:postcode":"54950",
    "sg:province":"WI",
    "wof:name":"Fritzies Bar",
    "wof:placetype":"venue"
},
  "geometry": {"coordinates":[-88.808875,44.743212],"type":"Point"}
}