{
  "type": "Feature",
  "properties": {
    "iso:country":"US",
    "sg:address":"1021 11th Ave",
    "sg:city":"Union Grove",
    "sg:classifiers":[
        {
            "category":"Organizations",
            "subcategory":"Community Association",
            "type":"Services"
        }
    ],
    "sg:phone":"+1 262 878 9938",
    "sg:postcode":"53182",
    "sg:province":"WI",
    "sg:tags":[
        "club"
    ],
    "wof:name":"Masonic Lodge",
    "wof:placetype":"venue"
},
  "geometry": {"coordinates":[-88.052054,42.686371],"type":"Point"}
}