{
  "type": "Feature",
  "properties": {
    "iso:country":"US",
    "sg:address":"7521 Nicholson Rd",
    "sg:city":"Caledonia",
    "sg:classifiers":[
        {
            "category":"Building & Trades",
            "subcategory":"Construction",
            "type":"Services"
        }
    ],
    "sg:phone":"+1 262 835 4321",
    "sg:postcode":"53108",
    "sg:province":"WI",
    "sg:tags":[
        "layer",
        "contractor",
        "laying",
        "floor",
        "carpet"
    ],
    "wof:name":"Mokry Carpet & Vinyl Inc",
    "wof:placetype":"venue"
},
  "geometry": {"coordinates":[-87.894611,42.820704],"type":"Point"}
}