{
  "type": "Feature",
  "properties": {
    "addr:full":"3495 Co Rd J Tigerton WI 54486",
    "addr:housenumber":"3495",
    "addr:postcode":"54486",
    "addr:street":"Co Rd;Tigerton",
    "iso:country":"US",
    "sg:address":"3495 Co Rd J",
    "sg:city":"Tigerton",
    "sg:classifiers":[
        {
            "category":"Bars & Pubs",
            "type":"Food & Drink"
        }
    ],
    "sg:phone":"+1 715 535 2263",
    "sg:postcode":"54486",
    "sg:province":"WI",
    "sg:tags":[
        "grill",
        "bar"
    ],
    "wof:name":"Dales One More",
    "wof:placetype":"venue"
},
  "geometry": {"coordinates":[-89.062774,44.7185],"type":"Point"}
}