{
  "type": "Feature",
  "properties": {
    "iso:country":"US",
    "sg:address":"7341 100th Ave",
    "sg:city":"Chippewa Falls",
    "sg:classifiers":[
        {
            "category":"Farming",
            "subcategory":"Dairy Farm",
            "type":"Manufacturing & Wholesale Goods"
        }
    ],
    "sg:phone":"+1 715 288 6084",
    "sg:postcode":"54729",
    "sg:province":"WI",
    "wof:name":"Steinmetz Dairy Farm",
    "wof:placetype":"venue"
},
  "geometry": {"coordinates":[-91.52277,44.987705],"type":"Point"}
}