{
  "type": "Feature",
  "properties": {
    "iso:country":"US",
    "sg:address":"1733 Dayton St",
    "sg:city":"Mayville",
    "sg:classifiers":[
        {
            "category":"Health Services",
            "subcategory":"Chiropractor",
            "type":"Services"
        }
    ],
    "sg:phone":"+1 920 387 3936",
    "sg:postcode":"53050",
    "sg:province":"WI",
    "wof:name":"Deborah Carr Chiropractors",
    "wof:placetype":"venue"
},
  "geometry": {"coordinates":[-88.563306,43.497524],"type":"Point"}
}