{
  "type": "Feature",
  "properties": {
    "addr:full":"127 E James St Columbus WI 53925",
    "addr:housenumber":"127",
    "addr:postcode":"53925",
    "addr:street":"E James St",
    "iso:country":"US",
    "sg:address":"127 E James St",
    "sg:city":"Columbus",
    "sg:classifiers":[
        {
            "category":"Shopping",
            "subcategory":"Stationery & Office Supplies",
            "type":"Retail Goods"
        }
    ],
    "sg:phone":"+1 920 623 2136",
    "sg:postcode":"53925",
    "sg:province":"WI",
    "wof:name":"M C Computer & Office Supplies",
    "wof:placetype":"venue"
},
  "geometry": {"coordinates":[-89.014346,43.338173],"type":"Point"}
}