{
  "type": "Feature",
  "properties": {
    "iso:country":"US",
    "sg:address":"7088 Cedar Ln",
    "sg:city":"Crivitz",
    "sg:classifiers":[
        {
            "category":"Shopping",
            "subcategory":"Discount & Variety Stores",
            "type":"Retail Goods"
        }
    ],
    "sg:phone":"+1 715 854 8121",
    "sg:postcode":"54114",
    "sg:province":"WI",
    "sg:tags":[
        "merchandise",
        "general"
    ],
    "wof:name":"Lehigh Salvage",
    "wof:placetype":"venue"
},
  "geometry": {"coordinates":[-87.928817,45.213077],"type":"Point"}
}