{
  "type": "Feature",
  "properties": {
    "iso:country":"US",
    "sg:address":"1481 S Evergreen Ct",
    "sg:city":"Wisconsin Dells",
    "sg:classifiers":[
        {
            "category":"Building & Trades",
            "subcategory":"Plumbing",
            "type":"Services"
        }
    ],
    "sg:phone":"+1 608 339 4199",
    "sg:postcode":"53965",
    "sg:province":"WI",
    "sg:tags":[
        "contractor"
    ],
    "wof:name":"Comfort Air Control & Heating",
    "wof:placetype":"venue"
},
  "geometry": {"coordinates":[-89.853914,43.826449],"type":"Point"}
}