{
  "type": "Feature",
  "properties": {
    "iso:country":"US",
    "sg:address":"5301 W Washington Blvd",
    "sg:city":"Milwaukee",
    "sg:classifiers":[
        {
            "category":"Education",
            "subcategory":"School",
            "type":"Public Place"
        }
    ],
    "sg:phone":"+1 414 774 2200",
    "sg:postcode":"53208",
    "sg:province":"WI",
    "wof:name":"Mount Olive Lutheran School",
    "wof:placetype":"venue"
},
  "geometry": {"coordinates":[-87.98095600000001,43.052941],"type":"Point"}
}