{
  "type": "Feature",
  "properties": {
    "iso:country":"US",
    "sg:address":"2 Science Ct",
    "sg:city":"Madison",
    "sg:classifiers":[
        {
            "category":"Real Estate",
            "subcategory":"Real Estate Operator",
            "type":"Services"
        }
    ],
    "sg:phone":"+1 608 238 2600",
    "sg:postcode":"53711",
    "sg:province":"WI",
    "sg:tags":[
        "co",
        "holding"
    ],
    "wof:name":"Yankee Hill Hsng Ptnrs Ltd",
    "wof:placetype":"venue"
},
  "geometry": {"coordinates":[-89.468119,43.059532],"type":"Point"}
}