{
  "type": "Feature",
  "properties": {
    "iso:country":"US",
    "sg:address":"5028 Little River Rd",
    "sg:city":"Weyauwega",
    "sg:phone":"+1 920 867 3034",
    "sg:postcode":"54983",
    "sg:province":"WI",
    "sg:tags":[
        "farm",
        "field",
        "crop"
    ],
    "wof:name":"James Ponto",
    "wof:placetype":"venue"
},
  "geometry": {"coordinates":[-88.963971,44.290341],"type":"Point"}
}