{
  "type": "Feature",
  "properties": {
    "iso:country":"US",
    "sg:address":"8234 N Teutonia Ave",
    "sg:city":"Milwaukee",
    "sg:classifiers":[
        {
            "category":"Personal",
            "subcategory":"Beauty Salon",
            "type":"Services"
        }
    ],
    "sg:phone":"+1 414 355 1340",
    "sg:postcode":"53209",
    "sg:province":"WI",
    "wof:name":"Poor Richard's",
    "wof:placetype":"venue"
},
  "geometry": {"coordinates":[-87.96458199999999,43.170007],"type":"Point"}
}