{
  "type": "Feature",
  "properties": {
    "iso:country":"US",
    "sg:address":"2033 Wyatt Ave",
    "sg:city":"Stevens Point",
    "sg:classifiers":[
        {
            "category":"Health Services",
            "subcategory":"Clinic",
            "type":"Services"
        }
    ],
    "sg:phone":"+1 715 345 0741",
    "sg:postcode":"54481",
    "sg:province":"WI",
    "wof:name":"Your Paramed Resource",
    "wof:placetype":"venue"
},
  "geometry": {"coordinates":[-89.572891,44.517219],"type":"Point"}
}