{
  "type": "Feature",
  "properties": {
    "addr:full":"12725 W Cleveland Ave New Berlin WI 53151",
    "addr:housenumber":"12725",
    "addr:postcode":"53151",
    "addr:street":"W Cleveland Ave",
    "iso:country":"US",
    "sg:address":"12725 W Cleveland Ave",
    "sg:city":"New Berlin",
    "sg:classifiers":[
        {
            "category":"Shopping",
            "type":"Retail Goods"
        }
    ],
    "sg:phone":"+1 262 827 1103",
    "sg:postcode":"53151",
    "sg:province":"WI",
    "sg:tags":[
        "merchandise"
    ],
    "wof:name":"Client Tele Inc",
    "wof:placetype":"venue"
},
  "geometry": {"coordinates":[-88.07198099999999,42.995457],"type":"Point"}
}