{
  "type": "Feature",
  "properties": {
    "iso:country":"US",
    "sg:address":"1600 W State St",
    "sg:city":"Milwaukee",
    "sg:classifiers":[
        {
            "category":"Recreation",
            "type":"Entertainment"
        }
    ],
    "sg:phone":"+1 414 933 7739",
    "sg:postcode":"53233",
    "sg:province":"WI",
    "sg:tags":[
        "instruction",
        "golf"
    ],
    "wof:name":"Bridging The Gap Learning Ctr",
    "wof:placetype":"venue"
},
  "geometry": {"coordinates":[-87.93401,43.04322],"type":"Point"}
}