{
  "type": "Feature",
  "properties": {
    "iso:country":"US",
    "sg:address":"417 Ash St",
    "sg:city":"Baraboo",
    "sg:classifiers":[
        {
            "category":"Personal",
            "type":"Services"
        }
    ],
    "sg:phone":"+1 608 356 0552",
    "sg:postcode":"53913",
    "sg:province":"WI",
    "sg:tags":[
        "therapist",
        "massage"
    ],
    "wof:name":"Baraboo Turning Point Studio",
    "wof:placetype":"venue"
},
  "geometry": {"coordinates":[-89.740794,43.469744],"type":"Point"}
}