{
  "type": "Feature",
  "properties": {
    "iso:country":"US",
    "sg:address":"2015 Ward Ave",
    "sg:city":"La Crosse",
    "sg:classifiers":[
        {
            "category":"Organizations",
            "subcategory":"Religious Organization",
            "type":"Services"
        }
    ],
    "sg:phone":"+1 608 787 5922",
    "sg:postcode":"54601",
    "sg:province":"WI",
    "sg:tags":[
        "church"
    ],
    "wof:name":"Living Word Christian Church",
    "wof:placetype":"venue"
},
  "geometry": {"coordinates":[-91.226906,43.783416],"type":"Point"}
}