{
  "type": "Feature",
  "properties": {
    "iso:country":"US",
    "sg:address":"6275 S Ace Industrial Dr",
    "sg:city":"Cudahy",
    "sg:classifiers":[
        {
            "category":"Freight",
            "type":"Transportation"
        }
    ],
    "sg:phone":"+1 414 571 8340",
    "sg:postcode":"53110",
    "sg:province":"WI",
    "wof:name":"Panalpina Inc",
    "wof:placetype":"venue"
},
  "geometry": {"coordinates":[-87.88334399999999,42.930603],"type":"Point"}
}