{
  "type": "Feature",
  "properties": {
    "iso:country":"US",
    "sg:address":"2236 US Hwy 63",
    "sg:city":"Cumberland",
    "sg:classifiers":[
        {
            "category":"Autos & Motor Vehicles",
            "subcategory":"Recreational Vehicle Sales",
            "type":"Retail Goods"
        }
    ],
    "sg:phone":"+1 715 822 8714",
    "sg:postcode":"54829",
    "sg:province":"WI",
    "sg:tags":[
        "trailer"
    ],
    "wof:name":"Lundmark Camper Sales Inc",
    "wof:placetype":"venue"
},
  "geometry": {"coordinates":[-92.04296600000001,45.530643],"type":"Point"}
}