{
  "type": "Feature",
  "properties": {
    "addr:full":"444 W Grand Ave Wisconsin Rapids WI 54495",
    "addr:housenumber":"444",
    "addr:postcode":"54495",
    "addr:street":"W Grand Ave",
    "iso:country":"US",
    "sg:address":"444 W Grand Ave",
    "sg:city":"Wisconsin Rapids",
    "sg:classifiers":[
        {
            "category":"Government",
            "subcategory":"Office",
            "type":"Public Place"
        }
    ],
    "sg:phone":"+1 715 421 8226",
    "sg:postcode":"54495",
    "sg:province":"WI",
    "sg:tags":[
        "village"
    ],
    "wof:name":"Wisconsin Rapids Bldg Inspctr",
    "wof:placetype":"venue"
},
  "geometry": {"coordinates":[-89.82995,44.395007],"type":"Point"}
}