{
  "type": "Feature",
  "properties": {
    "iso:country":"US",
    "sg:address":"763 E Hillcrest Dr",
    "sg:city":"Verona",
    "sg:classifiers":[
        {
            "category":"Manufacturing",
            "subcategory":"Wood Products",
            "type":"Manufacturing & Wholesale Goods"
        }
    ],
    "sg:phone":"+1 608 848 4533",
    "sg:postcode":"53593",
    "sg:province":"WI",
    "sg:tags":[
        "mfg"
    ],
    "wof:name":"Woodwicks",
    "wof:placetype":"venue"
},
  "geometry": {"coordinates":[-89.522576,42.982913],"type":"Point"}
}