{
  "type": "Feature",
  "properties": {
    "iso:country":"US",
    "sg:address":"10621 Gazebo Hill Pkwy E",
    "sg:city":"Thiensville",
    "sg:classifiers":[
        {
            "category":"Professional",
            "type":"Services"
        }
    ],
    "sg:phone":"+1 262 242 4556",
    "sg:postcode":"53092",
    "sg:province":"WI",
    "wof:name":"Ronk LLC",
    "wof:placetype":"venue"
},
  "geometry": {"coordinates":[-87.956753,43.210993],"type":"Point"}
}