{
  "type": "Feature",
  "properties": {
    "iso:country":"US",
    "sg:address":"525 E Riverside Dr",
    "sg:city":"Kohler",
    "sg:classifiers":[
        {
            "category":"Building & Trades",
            "subcategory":"Construction",
            "type":"Services"
        }
    ],
    "sg:phone":"+1 920 457 7565",
    "sg:postcode":"53044",
    "sg:province":"WI",
    "sg:tags":[
        "home",
        "builder",
        "contractor"
    ],
    "wof:name":"O'Donnell Builders",
    "wof:placetype":"venue"
},
  "geometry": {"coordinates":[-87.776447,43.73515],"type":"Point"}
}