{
  "type": "Feature",
  "properties": {
    "iso:country":"US",
    "sg:address":"205 McArthur Dr",
    "sg:city":"Mukwonago",
    "sg:classifiers":[
        {
            "category":"Real Estate",
            "subcategory":"Developer",
            "type":"Services"
        }
    ],
    "sg:phone":"+1 262 363 8252",
    "sg:postcode":"53149",
    "sg:province":"WI",
    "sg:tags":[
        "cemetery"
    ],
    "wof:name":"Caldwell Cemetery Association",
    "wof:placetype":"venue"
},
  "geometry": {"coordinates":[-88.338207,42.870494],"type":"Point"}
}