{
  "type": "Feature",
  "properties": {
    "addr:full":"1209 E Main St Stoughton WI 53589",
    "addr:housenumber":"1209",
    "addr:postcode":"53589",
    "addr:street":"E Main St",
    "iso:country":"US",
    "sg:address":"1209 E Main St",
    "sg:city":"Stoughton",
    "sg:classifiers":[
        {
            "category":"Social Services",
            "subcategory":"Adult Care",
            "type":"Services"
        }
    ],
    "sg:phone":"+1 608 873 7374",
    "sg:postcode":"53589",
    "sg:province":"WI",
    "sg:tags":[
        "residential"
    ],
    "wof:name":"Andreas House",
    "wof:placetype":"venue"
},
  "geometry": {"coordinates":[-89.20559799999999,42.918477],"type":"Point"}
}