{
  "type": "Feature",
  "properties": {
    "addr:full":"1303 State Hwy 69 New Glarus WI 53574",
    "addr:housenumber":"1303",
    "addr:postcode":"53574",
    "addr:street":"State Hwy 69",
    "iso:country":"US",
    "sg:address":"1303 State Hwy 69",
    "sg:city":"New Glarus",
    "sg:classifiers":[
        {
            "category":"Autos & Motor Vehicles",
            "subcategory":"Auto Supplies",
            "type":"Retail Goods"
        }
    ],
    "sg:phone":"+1 608 527 2123",
    "sg:postcode":"53574",
    "sg:province":"WI",
    "sg:tags":[
        "automobile",
        "parts"
    ],
    "wof:name":"Weaver Auto Parts",
    "wof:placetype":"venue"
},
  "geometry": {"coordinates":[-89.631471,42.80784],"type":"Point"}
}