{
  "type": "Feature",
  "properties": {
    "addr:full":"161 E 5th St Neillsville WI 54456",
    "addr:housenumber":"161",
    "addr:postcode":"54456",
    "addr:street":"E 5Th St",
    "iso:country":"US",
    "sg:address":"161 E 5th St",
    "sg:city":"Neillsville",
    "sg:classifiers":[
        {
            "category":"Real Estate",
            "subcategory":"Real Estate Operator",
            "type":"Services"
        }
    ],
    "sg:phone":"+1 715 743 2233",
    "sg:postcode":"54456",
    "sg:province":"WI",
    "sg:tags":[
        "building",
        "apartment"
    ],
    "wof:name":"Concern",
    "wof:placetype":"venue"
},
  "geometry": {"coordinates":[-90.595513,44.559948],"type":"Point"}
}