{
  "type": "Feature",
  "properties": {
    "iso:country":"US",
    "sg:address":"122 W Maple St",
    "sg:city":"Grafton",
    "sg:classifiers":[
        {
            "category":"Building & Trades",
            "subcategory":"Construction",
            "type":"Services"
        }
    ],
    "sg:phone":"+1 262 375 7424",
    "sg:postcode":"53024",
    "sg:province":"WI",
    "sg:tags":[
        "concrete",
        "contractor"
    ],
    "wof:name":"Jarvis Lutynski Concrete",
    "wof:placetype":"venue"
},
  "geometry": {"coordinates":[-87.966521,43.311668],"type":"Point"}
}