{
  "type": "Feature",
  "properties": {
    "iso:country":"US",
    "sg:address":"419 Maple St",
    "sg:city":"Strum",
    "sg:classifiers":[
        {
            "category":"Manufacturing",
            "subcategory":"Building Materials",
            "type":"Manufacturing & Wholesale Goods"
        }
    ],
    "sg:phone":"+1 715 695 3418",
    "sg:postcode":"54770",
    "sg:province":"WI",
    "wof:name":"Blade Millworks Inc",
    "wof:placetype":"venue"
},
  "geometry": {"coordinates":[-91.387477,44.55078],"type":"Point"}
}