{
  "type": "Feature",
  "properties": {
    "iso:country":"US",
    "sg:address":"215 Pine St",
    "sg:city":"Spooner",
    "sg:classifiers":[
        {
            "category":"Shopping",
            "subcategory":"Florist",
            "type":"Retail Goods"
        }
    ],
    "sg:phone":"+1 715 635 4501",
    "sg:postcode":"54801",
    "sg:province":"WI",
    "wof:name":"Pine Street Floral & Gifts Inc",
    "wof:placetype":"venue"
},
  "geometry": {"coordinates":[-91.886896,45.828596],"type":"Point"}
}