{
  "type": "Feature",
  "properties": {
    "iso:country":"US",
    "sg:address":"501 Main St",
    "sg:city":"Scales Mound",
    "sg:classifiers":[
        {
            "category":"Food & Beverages",
            "subcategory":"Groceries & Convenience Stores",
            "type":"Retail Goods"
        }
    ],
    "sg:phone":"+1 815 845 2316",
    "sg:postcode":"61075",
    "sg:province":"WI",
    "sg:tags":[
        "grocer"
    ],
    "wof:name":"Country House Grocery",
    "wof:placetype":"venue"
},
  "geometry": {"coordinates":[-90.251229,42.477812],"type":"Point"}
}