{
  "type": "Feature",
  "properties": {
    "addr:full":"1235 S Kimps Ct Green Bay WI 54313",
    "addr:housenumber":"1235",
    "addr:postcode":"54313",
    "addr:street":"S Kimps Ct",
    "iso:country":"US",
    "sg:address":"1235 S Kimps Ct",
    "sg:city":"Green Bay",
    "sg:classifiers":[
        {
            "category":"Home & Garden",
            "subcategory":"Furniture",
            "type":"Retail Goods"
        }
    ],
    "sg:phone":"+1 920 434 5188",
    "sg:postcode":"54313",
    "sg:province":"WI",
    "sg:tags":[
        "equipment",
        "kitchen",
        "cabinet"
    ],
    "wof:name":"Hoffman Cabinetry & Woodwork",
    "wof:placetype":"venue"
},
  "geometry": {"coordinates":[-88.064194,44.575284],"type":"Point"}
}