{
  "type": "Feature",
  "properties": {
    "addr:full":"225 Packerland Dr Green Bay WI 54303",
    "addr:housenumber":"225",
    "addr:postcode":"54303",
    "addr:street":"Packerland Dr",
    "iso:country":"US",
    "sg:address":"225 Packerland Dr",
    "sg:city":"Green Bay",
    "sg:phone":"+1 920 490 8249",
    "sg:postcode":"54303",
    "sg:province":"WI",
    "sg:tags":[
        "computer",
        "scale",
        "combination"
    ],
    "wof:name":"Multipond America Inc",
    "wof:placetype":"venue"
},
  "geometry": {"coordinates":[-88.09437200000001,44.535589],"type":"Point"}
}