{
  "type": "Feature",
  "properties": {
    "iso:country":"US",
    "sg:address":"8928 E Bowers Lake Rd",
    "sg:city":"Milton",
    "sg:phone":"+1 608 868 7593",
    "sg:postcode":"53563",
    "sg:province":"WI",
    "sg:tags":[
        "farm",
        "corn",
        "machinery"
    ],
    "wof:name":"Boston Farms & Supply",
    "wof:placetype":"venue"
},
  "geometry": {"coordinates":[-88.870924,42.808066],"type":"Point"}
}