{
  "type": "Feature",
  "properties": {
    "addr:full":"28040 Peloch Ln Eastman WI 54626",
    "addr:postcode":"28040;54626",
    "addr:street":"Peloch Ln",
    "iso:country":"US",
    "sg:address":"28040 Peloch Ln",
    "sg:city":"Eastman",
    "sg:classifiers":[
        {
            "category":"Farming",
            "subcategory":"Dairy Farm",
            "type":"Manufacturing & Wholesale Goods"
        }
    ],
    "sg:phone":"+1 608 874 4178",
    "sg:postcode":"54626",
    "sg:province":"WI",
    "sg:tags":[
        "livestock"
    ],
    "wof:name":"Peloch Farms",
    "wof:placetype":"venue"
},
  "geometry": {"coordinates":[-91.115403,43.156679],"type":"Point"}
}