{
  "type": "Feature",
  "properties": {
    "addr:full":"5974 Schroeder Rd Madison WI 53711",
    "addr:housenumber":"5974",
    "addr:postcode":"53711",
    "addr:street":"Schroeder Rd",
    "iso:country":"US",
    "sg:address":"5974 Schroeder Rd",
    "sg:city":"Madison",
    "sg:classifiers":[
        {
            "category":"Building & Trades",
            "subcategory":"Construction",
            "type":"Services"
        }
    ],
    "sg:phone":"+1 608 575 6119",
    "sg:postcode":"53711",
    "sg:province":"WI",
    "sg:tags":[
        "house"
    ],
    "wof:name":"Bly Builders",
    "wof:placetype":"venue"
},
  "geometry": {"coordinates":[-89.47921599999999,43.046431],"type":"Point"}
}