{
  "type": "Feature",
  "properties": {
    "addr:full":"9696 Lincicum Rd Browntown WI 53522",
    "addr:housenumber":"9696",
    "addr:postcode":"53522",
    "addr:street":"Lincicum Rd",
    "iso:country":"US",
    "sg:address":"9696 Lincicum Rd",
    "sg:city":"Browntown",
    "sg:classifiers":[
        {
            "category":"Building & Trades",
            "subcategory":"Landscaping Services",
            "type":"Services"
        }
    ],
    "sg:phone":"+1 608 439 1900",
    "sg:postcode":"53522",
    "sg:province":"WI",
    "sg:tags":[
        "tree"
    ],
    "wof:name":"Foxy's Tree Svc",
    "wof:placetype":"venue"
},
  "geometry": {"coordinates":[-89.83748199999999,42.535139],"type":"Point"}
}