{
  "type": "Feature",
  "properties": {
    "iso:country":"US",
    "sg:address":"180 S Foster Dr",
    "sg:city":"Saukville",
    "sg:classifiers":[
        {
            "category":"Travel",
            "subcategory":"Hotels & Motels",
            "type":"Entertainment"
        }
    ],
    "sg:phone":"+1 262 284 9399",
    "sg:postcode":"53080",
    "sg:province":"WI",
    "wof:name":"Super 8 Motel",
    "wof:placetype":"venue"
},
  "geometry": {"coordinates":[-87.93044,43.381919],"type":"Point"}
}