{
  "type": "Feature",
  "properties": {
    "addr:full":"410 S Park St Madison WI 53715",
    "addr:housenumber":"410",
    "addr:postcode":"53715",
    "addr:street":"S Park St",
    "iso:country":"US",
    "sg:address":"410 S Park St",
    "sg:city":"Madison",
    "sg:classifiers":[
        {
            "category":"Building & Trades",
            "subcategory":"Cleaning & Sanitation",
            "type":"Services"
        }
    ],
    "sg:phone":"+1 608 283 6240",
    "sg:postcode":"53715",
    "sg:province":"WI",
    "wof:name":"Northern Building Maintenance",
    "wof:placetype":"venue"
},
  "geometry": {"coordinates":[-89.400834,43.062695],"type":"Point"}
}