{
  "type": "Feature",
  "properties": {
    "iso:country":"US",
    "sg:address":"1911 Milton Ave",
    "sg:city":"Janesville",
    "sg:classifiers":[
        {
            "category":"Autos & Motor Vehicles",
            "subcategory":"Auto Supplies",
            "type":"Retail Goods"
        }
    ],
    "sg:phone":"+1 608 752 7117",
    "sg:postcode":"53545",
    "sg:province":"WI",
    "sg:tags":[
        "parts"
    ],
    "sg:website":"www.autozone.com",
    "wof:name":"Autozone",
    "wof:placetype":"venue"
},
  "geometry": {"coordinates":[-89.006208,42.705037],"type":"Point"}
}