{
  "type": "Feature",
  "properties": {
    "iso:country":"US",
    "sg:address":"1701 Washington St",
    "sg:city":"Manitowoc",
    "sg:classifiers":[
        {
            "category":"Health Services",
            "subcategory":"Clinic",
            "type":"Services"
        }
    ],
    "sg:phone":"+1 920 686 9222",
    "sg:postcode":"54220",
    "sg:province":"WI",
    "sg:tags":[
        "home",
        "care"
    ],
    "wof:name":"Caregivers Home Health",
    "wof:placetype":"venue"
},
  "geometry": {"coordinates":[-87.671444,44.088935],"type":"Point"}
}