{
  "type": "Feature",
  "properties": {
    "addr:full":"1113 N Sherman Ave Madison WI 53704",
    "addr:housenumber":"1113",
    "addr:postcode":"53704",
    "addr:street":"N Sherman Ave",
    "iso:country":"US",
    "sg:address":"1113 N Sherman Ave",
    "sg:city":"Madison",
    "sg:classifiers":[
        {
            "category":"Real Estate",
            "subcategory":"Real Estate Operator",
            "type":"Services"
        }
    ],
    "sg:phone":"+1 608 244 2463",
    "sg:postcode":"53704",
    "sg:province":"WI",
    "sg:tags":[
        "building",
        "nonresidential"
    ],
    "wof:name":"Northgate Partnership",
    "wof:placetype":"venue"
},
  "geometry": {"coordinates":[-89.363725,43.112591],"type":"Point"}
}