{
  "type": "Feature",
  "properties": {
    "iso:country":"US",
    "sg:address":"825 S Iowa St",
    "sg:city":"Dodgeville",
    "sg:classifiers":[
        {
            "category":"Health Services",
            "subcategory":"Doctor",
            "type":"Services"
        }
    ],
    "sg:phone":"+1 608 935 2711",
    "sg:postcode":"53533",
    "sg:province":"WI",
    "sg:tags":[
        "physician",
        "surgeon"
    ],
    "wof:name":"Memorial Hospital-Iowa County",
    "wof:placetype":"venue"
},
  "geometry": {"coordinates":[-90.130403,42.951827],"type":"Point"}
}