{
  "type": "Feature",
  "properties": {
    "iso:country":"US",
    "sg:address":"574 Commercial Ave",
    "sg:city":"Green Lake",
    "sg:classifiers":[
        {
            "category":"Government",
            "subcategory":"Fire Station",
            "type":"Public Place"
        }
    ],
    "sg:phone":"+1 920 294 6092",
    "sg:postcode":"54941",
    "sg:province":"WI",
    "sg:tags":[
        "protection"
    ],
    "wof:name":"Green Lk Brklyn Frst Rsponders",
    "wof:placetype":"venue"
},
  "geometry": {"coordinates":[-88.941648,43.844279],"type":"Point"}
}