{
  "type": "Feature",
  "properties": {
    "addr:full":"176 Woodlawn Dr Shawano WI 54166",
    "addr:housenumber":"176",
    "addr:postcode":"54166",
    "addr:street":"Woodlawn Dr",
    "iso:country":"US",
    "sg:address":"176 Woodlawn Dr",
    "sg:city":"Shawano",
    "sg:classifiers":[
        {
            "category":"Food & Beverages",
            "subcategory":"Specialty",
            "type":"Retail Goods"
        }
    ],
    "sg:phone":"+1 715 524 5555",
    "sg:postcode":"54166",
    "sg:province":"WI",
    "wof:name":"GNC",
    "wof:placetype":"venue"
},
  "geometry": {"coordinates":[-88.586304,44.783274],"type":"Point"}
}