{
  "type": "Feature",
  "properties": {
    "iso:country":"US",
    "sg:address":"13851 Co Rd H",
    "sg:city":"Soldiers Grove",
    "sg:classifiers":[
        {
            "category":"Shopping",
            "subcategory":"Musical Instruments",
            "type":"Retail Goods"
        }
    ],
    "sg:phone":"+1 608 624 5439",
    "sg:postcode":"54655",
    "sg:province":"WI",
    "wof:name":"Rock N Rose Ranch Garden",
    "wof:placetype":"venue"
},
  "geometry": {"coordinates":[-90.461444,43.495729],"type":"Point"}
}