{
  "type": "Feature",
  "properties": {
    "iso:country":"US",
    "sg:address":"564 N Pine St",
    "sg:city":"Burlington",
    "sg:classifiers":[
        {
            "category":"Personal",
            "subcategory":"Beauty Salon",
            "type":"Services"
        }
    ],
    "sg:phone":"+1 262 763 3455",
    "sg:postcode":"53105",
    "sg:province":"WI",
    "sg:tags":[
        "nail",
        "shop"
    ],
    "wof:name":"Nancy's Hair Affair",
    "wof:placetype":"venue"
},
  "geometry": {"coordinates":[-88.27660400000001,42.680599],"type":"Point"}
}