{
  "type": "Feature",
  "properties": {
    "iso:country":"US",
    "sg:address":"8820 Dey Rd",
    "sg:city":"New London",
    "sg:classifiers":[
        {
            "category":"Building & Trades",
            "subcategory":"Electrical",
            "type":"Services"
        }
    ],
    "sg:phone":"+1 920 982 4418",
    "sg:postcode":"54961",
    "sg:province":"WI",
    "sg:tags":[
        "fire",
        "protection",
        "sportswear",
        "contractor"
    ],
    "wof:name":"First Choice Enterprises Inc",
    "wof:placetype":"venue"
},
  "geometry": {"coordinates":[-88.77864599999999,44.369948],"type":"Point"}
}