{
  "type": "Feature",
  "properties": {
    "addr:full":"416 Clark St River Falls WI 54022",
    "addr:housenumber":"416",
    "addr:postcode":"54022",
    "addr:street":"Clark St",
    "iso:country":"US",
    "sg:address":"416 Clark St",
    "sg:city":"River Falls",
    "sg:classifiers":[
        {
            "category":"Building & Trades",
            "subcategory":"Plumbing",
            "type":"Services"
        }
    ],
    "sg:phone":"+1 715 425 6483",
    "sg:postcode":"54022",
    "sg:province":"WI",
    "sg:tags":[
        "conditioning",
        "air",
        "system",
        "contractor"
    ],
    "wof:name":"Gem Engineering Heating",
    "wof:placetype":"venue"
},
  "geometry": {"coordinates":[-92.626524,44.862489],"type":"Point"}
}