{
  "type": "Feature",
  "properties": {
    "iso:country":"US",
    "sg:address":"2760 Chief Little Wave Rd",
    "sg:city":"Keshena",
    "sg:classifiers":[
        {
            "category":"Education",
            "subcategory":"Library",
            "type":"Public Place"
        }
    ],
    "sg:phone":"+1 715 799 5212",
    "sg:postcode":"54135",
    "sg:province":"WI",
    "wof:name":"Menominee Tribal Library",
    "wof:placetype":"venue"
},
  "geometry": {"coordinates":[-88.62555500000001,44.873559],"type":"Point"}
}