{
  "type": "Feature",
  "properties": {
    "iso:country":"US",
    "sg:address":"130 S Main St",
    "sg:city":"Mayville",
    "sg:classifiers":[
        {
            "category":"Travel",
            "subcategory":"Travel Agent",
            "type":"Entertainment"
        }
    ],
    "sg:phone":"+1 920 387 5707",
    "sg:postcode":"53050",
    "sg:province":"WI",
    "sg:tags":[
        "agency"
    ],
    "wof:name":"Flyway Travel Ltd Inc",
    "wof:placetype":"venue"
},
  "geometry": {"coordinates":[-88.544163,43.493902],"type":"Point"}
}