{
  "type": "Feature",
  "properties": {
    "iso:country":"US",
    "sg:address":"213 de Witt St",
    "sg:city":"Portage",
    "sg:classifiers":[
        {
            "category":"Shopping",
            "type":"Retail Goods"
        }
    ],
    "sg:phone":"+1 608 742 7278",
    "sg:postcode":"53901",
    "sg:province":"WI",
    "sg:tags":[
        "merchandise"
    ],
    "wof:name":"Surface Creations",
    "wof:placetype":"venue"
},
  "geometry": {"coordinates":[-89.459463,43.539861],"type":"Point"}
}