{
  "type": "Feature",
  "properties": {
    "iso:country":"US",
    "sg:address":"175 N Western Ave",
    "sg:city":"Neenah",
    "sg:classifiers":[
        {
            "category":"Manufacturing",
            "subcategory":"Rubber & Plastics",
            "type":"Manufacturing & Wholesale Goods"
        }
    ],
    "sg:phone":"+1 920 727 6321",
    "sg:postcode":"54956",
    "sg:province":"WI",
    "sg:tags":[
        "product",
        "management",
        "foam",
        "mfg"
    ],
    "wof:name":"Pechiney Plastic Packaging",
    "wof:placetype":"venue"
},
  "geometry": {"coordinates":[-88.480225,44.189815],"type":"Point"}
}