{
  "type": "Feature",
  "properties": {
    "iso:country":"US",
    "sg:address":"501 US Hwy 63",
    "sg:city":"Baldwin",
    "sg:classifiers":[
        {
            "category":"Food & Beverages",
            "subcategory":"Groceries & Convenience Stores",
            "type":"Retail Goods"
        }
    ],
    "sg:phone":"+1 715 684 2482",
    "sg:postcode":"54002",
    "sg:province":"WI",
    "wof:name":"Super Truck Stop",
    "wof:placetype":"venue"
},
  "geometry": {"coordinates":[-92.374802,44.93468],"type":"Point"}
}