{
  "type": "Feature",
  "properties": {
    "iso:country":"US",
    "sg:address":"7400 W National Ave",
    "sg:city":"Milwaukee",
    "sg:classifiers":[
        {
            "category":"Retail",
            "subcategory":"Auto Rental",
            "type":"Services"
        }
    ],
    "sg:phone":"+1 414 258 1210",
    "sg:postcode":"53214",
    "sg:province":"WI",
    "sg:tags":[
        "passenger",
        "car"
    ],
    "wof:name":"Lease Planning & Management Co",
    "wof:placetype":"venue"
},
  "geometry": {"coordinates":[-88.006112,43.011959],"type":"Point"}
}