{
  "type": "Feature",
  "properties": {
    "iso:country":"US",
    "sg:address":"37 E 1st St",
    "sg:city":"Clintonville",
    "sg:classifiers":[
        {
            "category":"Building & Trades",
            "subcategory":"Construction",
            "type":"Services"
        }
    ],
    "sg:phone":"+1 715 823 4138",
    "sg:postcode":"54929",
    "sg:province":"WI",
    "sg:tags":[
        "contractor"
    ],
    "wof:name":"Moldenhauer Painting",
    "wof:placetype":"venue"
},
  "geometry": {"coordinates":[-88.759845,44.612379],"type":"Point"}
}