{
  "type": "Feature",
  "properties": {
    "iso:country":"US",
    "sg:address":"1819 Main St",
    "sg:city":"Green Bay",
    "sg:classifiers":[
        {
            "category":"Food & Beverages",
            "subcategory":"Groceries & Convenience Stores",
            "type":"Retail Goods"
        }
    ],
    "sg:phone":"+1 920 468 0447",
    "sg:postcode":"54302",
    "sg:province":"WI",
    "sg:tags":[
        "grocer"
    ],
    "wof:name":"Copps Food Ctr",
    "wof:placetype":"venue"
},
  "geometry": {"coordinates":[-87.97735299999999,44.494238],"type":"Point"}
}