{
  "type": "Feature",
  "properties": {
    "iso:country":"US",
    "sg:address":"719 Montreal Pl",
    "sg:city":"De Pere",
    "sg:classifiers":[
        {
            "category":"Retail",
            "subcategory":"Repair Shop",
            "type":"Services"
        }
    ],
    "sg:phone":"+1 920 339 9970",
    "sg:postcode":"54115",
    "sg:province":"WI",
    "sg:tags":[
        "tank",
        "cleaning"
    ],
    "wof:name":"Schroeder Environmental Svc",
    "wof:placetype":"venue"
},
  "geometry": {"coordinates":[-88.030879,44.446971],"type":"Point"}
}