{
  "type": "Feature",
  "properties": {
    "iso:country":"US",
    "sg:address":"1414 Ortlepp Rd",
    "sg:city":"Chilton",
    "sg:classifiers":[
        {
            "category":"Building & Trades",
            "subcategory":"Construction",
            "type":"Services"
        }
    ],
    "sg:phone":"+1 920 853 3454",
    "sg:postcode":"53014",
    "sg:province":"WI",
    "sg:tags":[
        "excavating",
        "contractor"
    ],
    "wof:name":"Jannette Trucking and Excvtg",
    "wof:placetype":"venue"
},
  "geometry": {"coordinates":[-88.109477,44.088109],"type":"Point"}
}