{
  "type": "Feature",
  "properties": {
    "addr:full":"1830 Rose St La Crosse WI 54603",
    "addr:housenumber":"1830",
    "addr:postcode":"54603",
    "addr:street":"Rose St",
    "iso:country":"US",
    "sg:address":"1830 Rose St",
    "sg:city":"La Crosse",
    "sg:classifiers":[
        {
            "category":"Travel",
            "subcategory":"Hotels & Motels",
            "type":"Entertainment"
        }
    ],
    "sg:phone":"+1 608 781 1400",
    "sg:postcode":"54603",
    "sg:province":"WI",
    "sg:tags":[
        "operation"
    ],
    "sg:website":"www.brookstoneinn.com",
    "wof:name":"Brookstone Inn",
    "wof:placetype":"venue"
},
  "geometry": {"coordinates":[-91.248122,43.850881],"type":"Point"}
}