{
  "type": "Feature",
  "properties": {
    "iso:country":"US",
    "sg:address":"10803 175th St",
    "sg:city":"Chippewa Falls",
    "sg:classifiers":[
        {
            "category":"Building & Trades",
            "subcategory":"Construction",
            "type":"Services"
        }
    ],
    "sg:phone":"+1 715 552 1481",
    "sg:postcode":"54729",
    "sg:province":"WI",
    "sg:tags":[
        "masonry",
        "contractor"
    ],
    "wof:name":"Two Rivers Enterprise",
    "wof:placetype":"venue"
},
  "geometry": {"coordinates":[-91.317425,44.999819],"type":"Point"}
}