{
  "type": "Feature",
  "properties": {
    "iso:country":"US",
    "sg:address":"2631 University Ave",
    "sg:city":"Madison",
    "sg:classifiers":[
        {
            "category":"Wholesale",
            "subcategory":"Non-durable Goods",
            "type":"Manufacturing & Wholesale Goods"
        }
    ],
    "sg:phone":"+1 608 233 1501",
    "sg:postcode":"53705",
    "sg:province":"WI",
    "sg:tags":[
        "fund",
        "raising",
        "merchandise"
    ],
    "wof:name":"Phoenix Fundraising Counsel",
    "wof:placetype":"venue"
},
  "geometry": {"coordinates":[-89.432731,43.073004],"type":"Point"}
}