{
  "type": "Feature",
  "properties": {
    "addr:full":"1610 N 2nd St Milwaukee WI 53212",
    "addr:housenumber":"1610",
    "addr:postcode":"53212",
    "addr:street":"N 2Nd St",
    "iso:country":"US",
    "sg:address":"1610 N 2nd St",
    "sg:city":"Milwaukee",
    "sg:classifiers":[
        {
            "category":"Utilities",
            "subcategory":"Cable",
            "type":"Services"
        }
    ],
    "sg:phone":"+1 414 771 8400",
    "sg:postcode":"53212",
    "sg:province":"WI",
    "sg:tags":[
        "television"
    ],
    "wof:name":"Time Warner Cable",
    "wof:placetype":"venue"
},
  "geometry": {"coordinates":[-87.91271999999999,43.052399],"type":"Point"}
}