{
  "type": "Feature",
  "properties": {
    "iso:country":"US",
    "sg:address":"6436 S Co Rd T",
    "sg:city":"Denmark",
    "sg:classifiers":[
        {
            "category":"Retail",
            "subcategory":"Repair Shop",
            "type":"Services"
        }
    ],
    "sg:phone":"+1 920 863 6147",
    "sg:postcode":"54208",
    "sg:province":"WI",
    "wof:name":"Sterletske Repair",
    "wof:placetype":"venue"
},
  "geometry": {"coordinates":[-87.826545,44.381904],"type":"Point"}
}