{
  "type": "Feature",
  "properties": {
    "iso:country":"US",
    "sg:address":"7226 Hubbard Ave",
    "sg:city":"Middleton",
    "sg:classifiers":[
        {
            "category":"Building & Trades",
            "subcategory":"Construction",
            "type":"Services"
        }
    ],
    "sg:phone":"+1 608 831 4343",
    "sg:postcode":"53562",
    "sg:province":"WI",
    "sg:tags":[
        "painter"
    ],
    "wof:name":"Melvyn Niesen",
    "wof:placetype":"venue"
},
  "geometry": {"coordinates":[-89.506415,43.095204],"type":"Point"}
}