{
  "type": "Feature",
  "properties": {
    "iso:country":"US",
    "sg:address":"1715 Dixie Rd",
    "sg:city":"Neenah",
    "sg:classifiers":[
        {
            "category":"Freight",
            "type":"Transportation"
        }
    ],
    "sg:phone":"+1 920 725 7413",
    "sg:postcode":"54956",
    "sg:province":"WI",
    "sg:tags":[
        "distribution",
        "center"
    ],
    "wof:name":"Premium Waters Inc",
    "wof:placetype":"venue"
},
  "geometry": {"coordinates":[-88.488441,44.139084],"type":"Point"}
}