{
  "type": "Feature",
  "properties": {
    "addr:full":"2939 New Pinery Rd Portage WI 53901",
    "addr:housenumber":"2939",
    "addr:postcode":"53901",
    "addr:street":"New Pinery Rd",
    "iso:country":"US",
    "sg:address":"2939 New Pinery Rd",
    "sg:city":"Portage",
    "sg:classifiers":[
        {
            "category":"Health Services",
            "subcategory":"Chiropractor",
            "type":"Services"
        }
    ],
    "sg:phone":"+1 608 742 8389",
    "sg:postcode":"53901",
    "sg:province":"WI",
    "wof:name":"Anderson Chiropractic Center",
    "wof:placetype":"venue"
},
  "geometry": {"coordinates":[-89.469717,43.571126],"type":"Point"}
}