{
  "type": "Feature",
  "properties": {
    "iso:country":"US",
    "sg:address":"243 W Seward St",
    "sg:city":"Poynette",
    "sg:classifiers":[
        {
            "category":"Retail",
            "subcategory":"Animal Services",
            "type":"Services"
        }
    ],
    "sg:phone":"+1 608 635 2213",
    "sg:postcode":"53955",
    "sg:province":"WI",
    "sg:tags":[
        "pet",
        "grooming",
        "washing"
    ],
    "wof:name":"Zoom & Groom",
    "wof:placetype":"venue"
},
  "geometry": {"coordinates":[-89.405473,43.39148],"type":"Point"}
}