{
  "type": "Feature",
  "properties": {
    "addr:full":"6802 Raymond Rd Madison WI 53719",
    "addr:housenumber":"6802",
    "addr:postcode":"53719",
    "addr:street":"Raymond Rd",
    "iso:country":"US",
    "sg:address":"6802 Raymond Rd",
    "sg:city":"Madison",
    "sg:classifiers":[
        {
            "category":"Organizations",
            "subcategory":"Professional Association",
            "type":"Services"
        }
    ],
    "sg:phone":"+1 608 278 9350",
    "sg:postcode":"53719",
    "sg:province":"WI",
    "wof:name":"Parkhill Condo Assoc",
    "wof:placetype":"venue"
},
  "geometry": {"coordinates":[-89.501099,43.031761],"type":"Point"}
}