{
  "type": "Feature",
  "properties": {
    "iso:country":"US",
    "sg:address":"5334 Percival Ln",
    "sg:city":"Racine",
    "sg:classifiers":[
        {
            "category":"Professional",
            "type":"Services"
        }
    ],
    "sg:phone":"+1 262 639 3109",
    "sg:postcode":"53406",
    "sg:province":"WI",
    "wof:name":"Toxlink LLC",
    "wof:placetype":"venue"
},
  "geometry": {"coordinates":[-87.843017,42.745366],"type":"Point"}
}