{
  "type": "Feature",
  "properties": {
    "iso:country":"US",
    "sg:address":"844 Depere St",
    "sg:city":"Menasha",
    "sg:classifiers":[
        {
            "category":"Restaurant",
            "type":"Food & Drink"
        }
    ],
    "sg:phone":"+1 920 725 8538",
    "sg:postcode":"54952",
    "sg:province":"WI",
    "wof:name":"Pitzi's Pizza",
    "wof:placetype":"venue"
},
  "geometry": {"coordinates":[-88.44009200000001,44.21446],"type":"Point"}
}