{
  "type": "Feature",
  "properties": {
    "iso:country":"US",
    "sg:address":"8937 Theis Dr",
    "sg:city":"Woodruff",
    "sg:classifiers":[
        {
            "category":"Shopping",
            "subcategory":"Books",
            "type":"Retail Goods"
        }
    ],
    "sg:phone":"+1 715 356 7906",
    "sg:postcode":"54568",
    "sg:province":"WI",
    "wof:name":"Boardwalk Books & Music LLC",
    "wof:placetype":"venue"
},
  "geometry": {"coordinates":[-89.663595,45.886572],"type":"Point"}
}