{
  "type": "Feature",
  "properties": {
    "iso:country":"US",
    "sg:address":"4390 Bennett Rd",
    "sg:city":"Benton",
    "sg:classifiers":[
        {
            "category":"Farming",
            "subcategory":"Livestock Farm",
            "type":"Manufacturing & Wholesale Goods"
        }
    ],
    "sg:phone":"+1 608 759 3715",
    "sg:postcode":"53803",
    "sg:province":"WI",
    "sg:tags":[
        "beef",
        "feedlot",
        "cattle"
    ],
    "wof:name":"Clarence Bennett",
    "wof:placetype":"venue"
},
  "geometry": {"coordinates":[-90.351496,42.561688],"type":"Point"}
}