{
  "type": "Feature",
  "properties": {
    "iso:country":"US",
    "sg:address":"4001 Courier Rd",
    "sg:city":"Green Bay",
    "sg:classifiers":[
        {
            "category":"Bars & Pubs",
            "type":"Food & Drink"
        }
    ],
    "sg:phone":"+1 920 469 1850",
    "sg:postcode":"54311",
    "sg:province":"WI",
    "sg:tags":[
        "drinking"
    ],
    "wof:name":"Double Gee Bar",
    "wof:placetype":"venue"
},
  "geometry": {"coordinates":[-87.884173,44.502274],"type":"Point"}
}