{
  "type": "Feature",
  "properties": {
    "iso:country":"US",
    "sg:address":"24963 Hilldale Ave",
    "sg:city":"Tomah",
    "sg:classifiers":[
        {
            "category":"Building & Trades",
            "subcategory":"Plumbing",
            "type":"Services"
        }
    ],
    "sg:phone":"+1 608 374 4999",
    "sg:postcode":"54660",
    "sg:province":"WI",
    "sg:tags":[
        "contractor"
    ],
    "wof:name":"Heating & Cooling Specialists",
    "wof:placetype":"venue"
},
  "geometry": {"coordinates":[-90.485997,43.935435],"type":"Point"}
}