{
  "type": "Feature",
  "properties": {
    "iso:country":"US",
    "sg:address":"148 E Main St",
    "sg:city":"Reedsburg",
    "sg:classifiers":[
        {
            "category":"Shopping",
            "subcategory":"Clothing, Apparel, & Fashions",
            "type":"Retail Goods"
        }
    ],
    "sg:phone":"+1 608 768 5678",
    "sg:postcode":"53959",
    "sg:province":"WI",
    "wof:name":"Creative Motion LLC",
    "wof:placetype":"venue"
},
  "geometry": {"coordinates":[-90.009402,43.532429],"type":"Point"}
}