{
  "type": "Feature",
  "properties": {
    "iso:country":"US",
    "sg:address":"311 Miner Ave E",
    "sg:city":"Ladysmith",
    "sg:classifiers":[
        {
            "category":"Government",
            "subcategory":"Office",
            "type":"Public Place"
        }
    ],
    "sg:phone":"+1 715 532 2147",
    "sg:postcode":"54848",
    "sg:province":"WI",
    "wof:name":"Rusk County Probate Register",
    "wof:placetype":"venue"
},
  "geometry": {"coordinates":[-91.09814299999999,45.464336],"type":"Point"}
}