{
  "type": "Feature",
  "properties": {
    "iso:country":"US",
    "sg:address":"217 E Elm St",
    "sg:city":"River Falls",
    "sg:classifiers":[
        {
            "category":"Professional",
            "type":"Services"
        }
    ],
    "sg:phone":"+1 715 425 7323",
    "sg:postcode":"54022",
    "sg:province":"WI",
    "wof:name":"Tom Parent",
    "wof:placetype":"venue"
},
  "geometry": {"coordinates":[-92.624284,44.858169],"type":"Point"}
}