{
  "type": "Feature",
  "properties": {
    "iso:country":"US",
    "sg:address":"10807 W Hafeman Rd",
    "sg:city":"Orfordville",
    "sg:classifiers":[
        {
            "category":"Building & Trades",
            "subcategory":"Construction",
            "type":"Services"
        }
    ],
    "sg:phone":"+1 608 879 3545",
    "sg:postcode":"53576",
    "sg:province":"WI",
    "sg:tags":[
        "house"
    ],
    "wof:name":"Allen Construction",
    "wof:placetype":"venue"
},
  "geometry": {"coordinates":[-89.241146,42.599686],"type":"Point"}
}