{
  "type": "Feature",
  "properties": {
    "addr:full":"2398 Sheridan Dr Madison WI 53704",
    "addr:housenumber":"2398",
    "addr:postcode":"53704",
    "addr:street":"Sheridan Dr",
    "iso:country":"US",
    "sg:address":"2398 Sheridan Dr",
    "sg:city":"Madison",
    "sg:classifiers":[
        {
            "category":"Real Estate",
            "subcategory":"Developer",
            "type":"Services"
        }
    ],
    "sg:phone":"+1 608 249 2804",
    "sg:postcode":"53704",
    "sg:province":"WI",
    "wof:name":"Dovetail Development Inc",
    "wof:placetype":"venue"
},
  "geometry": {"coordinates":[-89.372505,43.123977],"type":"Point"}
}