{
  "type": "Feature",
  "properties": {
    "iso:country":"US",
    "sg:address":"322 N Franklin St",
    "sg:city":"Port Washington",
    "sg:classifiers":[
        {
            "category":"Shopping",
            "subcategory":"Gifts & Souvenirs",
            "type":"Retail Goods"
        }
    ],
    "sg:phone":"+1 262 268 1505",
    "sg:postcode":"53074",
    "sg:province":"WI",
    "sg:tags":[
        "collectible"
    ],
    "wof:name":"Brewmeister's Trading Post",
    "wof:placetype":"venue"
},
  "geometry": {"coordinates":[-87.869219,43.389923],"type":"Point"}
}