{
  "type": "Feature",
  "properties": {
    "iso:country":"US",
    "sg:address":"401 Wisconsin Ave",
    "sg:city":"Madison",
    "sg:classifiers":[
        {
            "category":"Insurance",
            "subcategory":"Insurance Agent",
            "type":"Services"
        }
    ],
    "sg:phone":"+1 608 251 3422",
    "sg:postcode":"53703",
    "sg:province":"WI",
    "wof:name":"Claire A Thomas",
    "wof:placetype":"venue"
},
  "geometry": {"coordinates":[-89.38869099999999,43.078151],"type":"Point"}
}