{
  "type": "Feature",
  "properties": {
    "iso:country":"US",
    "sg:address":"52 Merchant Row",
    "sg:city":"Milton",
    "sg:classifiers":[
        {
            "category":"Restaurant",
            "type":"Food & Drink"
        }
    ],
    "sg:phone":"+1 608 868 1755",
    "sg:postcode":"53563",
    "sg:province":"WI",
    "sg:tags":[
        "cafe"
    ],
    "wof:name":"Blue Moon Internet Cafe",
    "wof:placetype":"venue"
},
  "geometry": {"coordinates":[-88.962386,42.782633],"type":"Point"}
}