{
  "type": "Feature",
  "properties": {
    "addr:full":"3315 W North Ave Milwaukee WI 53208",
    "addr:housenumber":"3315",
    "addr:postcode":"53208",
    "addr:street":"W North Ave",
    "iso:country":"US",
    "sg:address":"3315 W North Ave",
    "sg:city":"Milwaukee",
    "sg:classifiers":[
        {
            "category":"Building & Trades",
            "subcategory":"Construction",
            "type":"Services"
        }
    ],
    "sg:phone":"+1 414 444 9690",
    "sg:postcode":"53208",
    "sg:province":"WI",
    "sg:tags":[
        "residential"
    ],
    "wof:name":"Titan Building Company",
    "wof:placetype":"venue"
},
  "geometry": {"coordinates":[-87.956289,43.06054],"type":"Point"}
}