{
  "type": "Feature",
  "properties": {
    "iso:country":"US",
    "sg:address":"22 Main St",
    "sg:city":"Montello",
    "sg:classifiers":[
        {
            "category":"Shopping",
            "subcategory":"Florist",
            "type":"Retail Goods"
        }
    ],
    "sg:phone":"+1 608 297 7770",
    "sg:postcode":"53949",
    "sg:province":"WI",
    "wof:name":"Spees Montello Floral",
    "wof:placetype":"venue"
},
  "geometry": {"coordinates":[-89.327238,43.791601],"type":"Point"}
}