{
  "type": "Feature",
  "properties": {
    "iso:country":"US",
    "sg:address":"1430 2nd St N",
    "sg:city":"Wisconsin Rapids",
    "sg:classifiers":[
        {
            "category":"Freight",
            "type":"Transportation"
        }
    ],
    "sg:phone":"+1 715 421 1740",
    "sg:postcode":"54494",
    "sg:province":"WI",
    "sg:tags":[
        "operator",
        "trucking"
    ],
    "wof:name":"Standard Forwarding Co Inc",
    "wof:placetype":"venue"
},
  "geometry": {"coordinates":[-89.814656,44.400362],"type":"Point"}
}