{
  "type": "Feature",
  "properties": {
    "iso:country":"US",
    "sg:address":"12473 Co Rd C",
    "sg:city":"Black River Fls",
    "sg:classifiers":[
        {
            "category":"Building & Trades",
            "subcategory":"Construction",
            "type":"Services"
        }
    ],
    "sg:phone":"+1 715 284 0887",
    "sg:postcode":"54615",
    "sg:province":"WI",
    "sg:tags":[
        "resurfacing",
        "laying",
        "refinishing",
        "floor"
    ],
    "wof:name":"Neville's Industrial Applctrs",
    "wof:placetype":"venue"
},
  "geometry": {"coordinates":[-90.92359,44.280467],"type":"Point"}
}