{
  "type": "Feature",
  "properties": {
    "addr:full":"1684 Main St Green Bay WI 54302",
    "addr:housenumber":"1684",
    "addr:postcode":"54302",
    "addr:street":"Main St",
    "iso:country":"US",
    "sg:address":"1684 Main St",
    "sg:city":"Green Bay",
    "sg:classifiers":[
        {
            "category":"Banks & Credit Unions",
            "subcategory":"Bank",
            "type":"Services"
        }
    ],
    "sg:phone":"+1 920 468 8694",
    "sg:postcode":"54302",
    "sg:province":"WI",
    "sg:tags":[
        "institution",
        "business"
    ],
    "wof:name":"Loan Max",
    "wof:placetype":"venue"
},
  "geometry": {"coordinates":[-87.980901,44.499407],"type":"Point"}
}