{
  "type": "Feature",
  "properties": {
    "iso:country":"US",
    "sg:address":"425 Wilmot Ave",
    "sg:city":"Twin Lakes",
    "sg:classifiers":[
        {
            "category":"Professional",
            "subcategory":"Business Services",
            "type":"Services"
        }
    ],
    "sg:phone":"+1 262 877 3364",
    "sg:postcode":"53181",
    "sg:province":"WI",
    "wof:name":"Laurins Landing",
    "wof:placetype":"venue"
},
  "geometry": {"coordinates":[-88.246394,42.529454],"type":"Point"}
}