{
  "type": "Feature",
  "properties": {
    "iso:country":"US",
    "sg:address":"17495 W Capitol Dr",
    "sg:city":"Brookfield",
    "sg:classifiers":[
        {
            "category":"Personal",
            "subcategory":"Beauty Salon",
            "type":"Services"
        }
    ],
    "sg:phone":"+1 262 790 9720",
    "sg:postcode":"53045",
    "sg:province":"WI",
    "sg:tags":[
        "shop"
    ],
    "wof:name":"Versi Color",
    "wof:placetype":"venue"
},
  "geometry": {"coordinates":[-88.127067,43.089915],"type":"Point"}
}