{
  "type": "Feature",
  "properties": {
    "iso:country":"US",
    "sg:address":"33074 Huron Ave",
    "sg:city":"Camp Douglas",
    "sg:phone":"+1 608 427 3566",
    "sg:postcode":"54618",
    "sg:province":"WI",
    "sg:tags":[
        "farm",
        "corn",
        "soybean"
    ],
    "wof:name":"Dennis Jilek",
    "wof:placetype":"venue"
},
  "geometry": {"coordinates":[-90.332514,43.927998],"type":"Point"}
}