{
  "type": "Feature",
  "properties": {
    "iso:country":"US",
    "sg:address":"427 Main St",
    "sg:city":"Darlington",
    "sg:classifiers":[
        {
            "category":"Professional",
            "subcategory":"Accounting & Tax Preparation",
            "type":"Services"
        }
    ],
    "sg:phone":"+1 608 776 8388",
    "sg:postcode":"53530",
    "sg:province":"WI",
    "wof:name":"Verlyn G Adamson CPA",
    "wof:placetype":"venue"
},
  "geometry": {"coordinates":[-90.11767500000001,42.680802],"type":"Point"}
}