{
  "type": "Feature",
  "properties": {
    "iso:country":"US",
    "sg:address":"220 E Sunset Dr",
    "sg:city":"Waukesha",
    "sg:classifiers":[
        {
            "category":"Food & Beverages",
            "subcategory":"Groceries & Convenience Stores",
            "type":"Retail Goods"
        }
    ],
    "sg:phone":"+1 262 547 7801",
    "sg:postcode":"53189",
    "sg:province":"WI",
    "sg:tags":[
        "grocer"
    ],
    "sg:website":"www.roundys.com",
    "wof:name":"Pick'n Save",
    "wof:placetype":"venue"
},
  "geometry": {"coordinates":[-88.224174,42.98843],"type":"Point"}
}