{
  "type": "Feature",
  "properties": {
    "iso:country":"US",
    "sg:address":"226 E State St",
    "sg:city":"Dresser",
    "sg:classifiers":[
        {
            "category":"Health Services",
            "subcategory":"Health Practitioner",
            "type":"Services"
        }
    ],
    "sg:phone":"+1 715 755 3750",
    "sg:postcode":"54009",
    "sg:province":"WI",
    "sg:tags":[
        "acupuncture"
    ],
    "wof:name":"St Croix Valley Acupuncture Co",
    "wof:placetype":"venue"
},
  "geometry": {"coordinates":[-92.630759,45.353983],"type":"Point"}
}