{
  "type": "Feature",
  "properties": {
    "iso:country":"US",
    "sg:address":"14713 N Shore Dr",
    "sg:city":"Valders",
    "sg:classifiers":[
        {
            "category":"Wholesale",
            "subcategory":"Non-durable Goods",
            "type":"Manufacturing & Wholesale Goods"
        }
    ],
    "sg:phone":"+1 920 758 3300",
    "sg:postcode":"54245",
    "sg:province":"WI",
    "sg:tags":[
        "advertising"
    ],
    "sg:website":"www.pro-mot-e.com",
    "wof:name":"Pro Mot E",
    "wof:placetype":"venue"
},
  "geometry": {"coordinates":[-87.87339900000001,43.990922],"type":"Point"}
}