{
  "type": "Feature",
  "properties": {
    "iso:country":"US",
    "sg:address":"15210 State Hwy 16",
    "sg:city":"Wisconsin Dells",
    "sg:classifiers":[
        {
            "category":"Retail",
            "subcategory":"Auto Rental",
            "type":"Services"
        }
    ],
    "sg:phone":"+1 608 254 7773",
    "sg:postcode":"53965",
    "sg:province":"WI",
    "sg:tags":[
        "renting",
        "automobile"
    ],
    "wof:name":"Avis Rent A Car",
    "wof:placetype":"venue"
},
  "geometry": {"coordinates":[-89.754588,43.61931],"type":"Point"}
}