{
  "type": "Feature",
  "properties": {
    "iso:country":"US",
    "sg:address":"7231 N Rehor Rd",
    "sg:city":"Hayward",
    "sg:classifiers":[
        {
            "category":"Travel",
            "subcategory":"Hotels & Motels",
            "type":"Entertainment"
        }
    ],
    "sg:phone":"+1 715 634 5724",
    "sg:postcode":"54843",
    "sg:province":"WI",
    "wof:name":"Lumbermans Mansion Inn",
    "wof:placetype":"venue"
},
  "geometry": {"coordinates":[-91.463813,45.898636],"type":"Point"}
}