{
  "type": "Feature",
  "properties": {
    "iso:country":"US",
    "sg:address":"1372 Fox Ridge Trl",
    "sg:city":"Hudson",
    "sg:classifiers":[
        {
            "category":"Professional",
            "subcategory":"Business Services",
            "type":"Services"
        }
    ],
    "sg:phone":"+1 715 549 5963",
    "sg:postcode":"54082",
    "sg:province":"WI",
    "sg:tags":[
        "interior",
        "design"
    ],
    "wof:name":"Inside Image Inc",
    "wof:placetype":"venue"
},
  "geometry": {"coordinates":[-92.713099,45.061964],"type":"Point"}
}