{
  "type": "Feature",
  "properties": {
    "addr:full":"2104 S River Rd Janesville WI 53546",
    "addr:housenumber":"2104",
    "addr:postcode":"53546",
    "addr:street":"S River Rd",
    "iso:country":"US",
    "sg:address":"2104 S River Rd",
    "sg:city":"Janesville",
    "sg:classifiers":[
        {
            "category":"Farming",
            "subcategory":"Farm",
            "type":"Manufacturing & Wholesale Goods"
        }
    ],
    "sg:phone":"+1 608 754 3253",
    "sg:postcode":"53546",
    "sg:province":"WI",
    "sg:tags":[
        "crop",
        "general"
    ],
    "wof:name":"Robert Giese Farm",
    "wof:placetype":"venue"
},
  "geometry": {"coordinates":[-89.061314,42.646893],"type":"Point"}
}