{
  "type": "Feature",
  "properties": {
    "iso:country":"US",
    "sg:address":"1601 Beaser Ave",
    "sg:city":"Ashland",
    "sg:classifiers":[
        {
            "category":"Health Services",
            "subcategory":"Clinic",
            "type":"Services"
        }
    ],
    "sg:phone":"+1 715 682 9500",
    "sg:postcode":"54806",
    "sg:province":"WI",
    "sg:tags":[
        "home",
        "care"
    ],
    "wof:name":"Bay Area Home Health Center",
    "wof:placetype":"venue"
},
  "geometry": {"coordinates":[-90.885658,46.570741],"type":"Point"}
}