{
  "type": "Feature",
  "properties": {
    "addr:full":"9722 W Watertown Plank Rd Milwaukee WI 53226",
    "addr:housenumber":"9722",
    "addr:postcode":"53226",
    "addr:street":"W Watertown Plank Rd",
    "iso:country":"US",
    "sg:address":"9722 W Watertown Plank Rd",
    "sg:city":"Milwaukee",
    "sg:classifiers":[
        {
            "category":"Organizations",
            "subcategory":"Non-profit Organization",
            "type":"Services"
        }
    ],
    "sg:phone":"+1 414 774 2233",
    "sg:postcode":"53226",
    "sg:province":"WI",
    "sg:tags":[
        "medical",
        "management"
    ],
    "sg:website":"www.mtmi.net",
    "wof:name":"Medical Technology Management",
    "wof:placetype":"venue"
},
  "geometry": {"coordinates":[-88.036038,43.045439],"type":"Point"}
}