{
  "type": "Feature",
  "properties": {
    "iso:country":"US",
    "sg:address":"421 N Main St",
    "sg:city":"River Falls",
    "sg:classifiers":[
        {
            "category":"Manufacturing",
            "subcategory":"Buildings",
            "type":"Manufacturing & Wholesale Goods"
        }
    ],
    "sg:phone":"+1 715 425 1739",
    "sg:postcode":"54022",
    "sg:province":"WI",
    "sg:tags":[
        "home",
        "log",
        "cabin"
    ],
    "wof:name":"Natural Log Homes",
    "wof:placetype":"venue"
},
  "geometry": {"coordinates":[-92.623979,44.86248],"type":"Point"}
}