{
  "type": "Feature",
  "properties": {
    "iso:country":"US",
    "sg:address":"2194 Heywood Cir",
    "sg:city":"Oregon",
    "sg:classifiers":[
        {
            "category":"Health Services",
            "subcategory":"Doctor",
            "type":"Services"
        }
    ],
    "sg:phone":"+1 608 274 5769",
    "sg:postcode":"53575",
    "sg:province":"WI",
    "sg:tags":[
        "nonprofit",
        "eye"
    ],
    "wof:name":"Free Rural Eye Clinics Corp",
    "wof:placetype":"venue"
},
  "geometry": {"coordinates":[-89.435855,42.974004],"type":"Point"}
}