{
  "type": "Feature",
  "properties": {
    "iso:country":"US",
    "sg:address":"30135 W Woodlawn Dr",
    "sg:city":"Burlington",
    "sg:classifiers":[
        {
            "category":"Professional",
            "subcategory":"Business Services",
            "type":"Services"
        }
    ],
    "sg:phone":"+1 262 767 2725",
    "sg:postcode":"53105",
    "sg:province":"WI",
    "sg:tags":[
        "embroidery"
    ],
    "wof:name":"Stitch Shoppe",
    "wof:placetype":"venue"
},
  "geometry": {"coordinates":[-88.23085500000001,42.689008],"type":"Point"}
}