{
  "type": "Feature",
  "properties": {
    "iso:country":"US",
    "sg:address":"3015 Douglas Ave",
    "sg:city":"Racine",
    "sg:classifiers":[
        {
            "category":"Shopping",
            "subcategory":"Clothing, Apparel, & Fashions",
            "type":"Retail Goods"
        }
    ],
    "sg:phone":"+1 262 639 4954",
    "sg:postcode":"53402",
    "sg:province":"WI",
    "sg:tags":[
        "tailor"
    ],
    "wof:name":"Harry's Tailor Shop",
    "wof:placetype":"venue"
},
  "geometry": {"coordinates":[-87.799515,42.755756],"type":"Point"}
}