{
  "type": "Feature",
  "properties": {
    "iso:country":"US",
    "sg:address":"607 Walden Ct",
    "sg:city":"Altoona",
    "sg:classifiers":[
        {
            "category":"Retail",
            "subcategory":"Auto Repair",
            "type":"Services"
        }
    ],
    "sg:phone":"+1 715 839 9453",
    "sg:postcode":"54720",
    "sg:province":"WI",
    "sg:tags":[
        "repairing",
        "automobile"
    ],
    "wof:name":"Water Well Specialists",
    "wof:placetype":"venue"
},
  "geometry": {"coordinates":[-91.423911,44.802911],"type":"Point"}
}