{
  "type": "Feature",
  "properties": {
    "addr:full":"714 E Sumner St Hartford WI 53027",
    "addr:housenumber":"714",
    "addr:postcode":"53027",
    "addr:street":"E Sumner St",
    "iso:country":"US",
    "sg:address":"714 E Sumner St",
    "sg:city":"Hartford",
    "sg:classifiers":[
        {
            "category":"Food & Beverages",
            "subcategory":"Liquor & Beverages",
            "type":"Retail Goods"
        }
    ],
    "sg:phone":"+1 262 673 5555",
    "sg:postcode":"53027",
    "sg:province":"WI",
    "wof:name":"Rand Liquor",
    "wof:placetype":"venue"
},
  "geometry": {"coordinates":[-88.36791100000001,43.316554],"type":"Point"}
}