{
  "type": "Feature",
  "properties": {
    "addr:full":"13883 Co Hwy S S Jim Falls WI 54748",
    "addr:housenumber":"13883",
    "addr:postcode":"54748",
    "addr:street":"Co Hwy",
    "iso:country":"US",
    "sg:address":"13883 Co Hwy S S",
    "sg:city":"Jim Falls",
    "sg:classifiers":[
        {
            "category":"Organizations",
            "subcategory":"Religious Organization",
            "type":"Services"
        }
    ],
    "sg:phone":"+1 715 382 4191",
    "sg:postcode":"54748",
    "sg:province":"WI",
    "sg:tags":[
        "church"
    ],
    "wof:name":"United Methodist Church",
    "wof:placetype":"venue"
},
  "geometry": {"coordinates":[-91.274593,45.044136],"type":"Point"}
}