{
  "type": "Feature",
  "properties": {
    "iso:country":"US",
    "sg:address":"432 Higgins Dr",
    "sg:city":"Evansville",
    "sg:classifiers":[
        {
            "category":"Banks & Credit Unions",
            "subcategory":"Financial Services",
            "type":"Services"
        }
    ],
    "sg:phone":"+1 608 882 0273",
    "sg:postcode":"53536",
    "sg:province":"WI",
    "sg:tags":[
        "company",
        "holding"
    ],
    "wof:name":"Wilke Holdings LLC",
    "wof:placetype":"venue"
},
  "geometry": {"coordinates":[-89.31214199999999,42.773941],"type":"Point"}
}