{
  "type": "Feature",
  "properties": {
    "iso:country":"US",
    "sg:address":"2239 S 75th St",
    "sg:city":"West Allis",
    "sg:classifiers":[
        {
            "category":"Retail",
            "subcategory":"Auto Repair",
            "type":"Services"
        }
    ],
    "sg:phone":"+1 414 327 7540",
    "sg:postcode":"53219",
    "sg:province":"WI",
    "sg:tags":[
        "wrecker"
    ],
    "wof:name":"B & R Towing",
    "wof:placetype":"venue"
},
  "geometry": {"coordinates":[-88.006348,43.003486],"type":"Point"}
}