{
  "type": "Feature",
  "properties": {
    "iso:country":"US",
    "sg:address":"7943 W National Ave",
    "sg:city":"Milwaukee",
    "sg:classifiers":[
        {
            "category":"Manufacturing",
            "subcategory":"Printing",
            "type":"Manufacturing & Wholesale Goods"
        }
    ],
    "sg:phone":"+1 414 276 1000",
    "sg:postcode":"53214",
    "sg:province":"WI",
    "sg:tags":[
        "commercial"
    ],
    "wof:name":"Ott Advertising Inc",
    "wof:placetype":"venue"
},
  "geometry": {"coordinates":[-88.012152,43.010785],"type":"Point"}
}