{
  "type": "Feature",
  "properties": {
    "iso:country":"US",
    "sg:address":"419 State St",
    "sg:city":"Beloit",
    "sg:classifiers":[
        {
            "category":"Professional",
            "subcategory":"Lawyer & Legal Services",
            "type":"Services"
        }
    ],
    "sg:phone":"+1 608 879 2112",
    "sg:postcode":"53511",
    "sg:province":"IL",
    "wof:name":"Elliott Jerome - Attorney",
    "wof:placetype":"venue"
},
  "geometry": {"coordinates":[-89.034908,42.500393],"type":"Point"}
}