{
  "type": "Feature",
  "properties": {
    "iso:country":"US",
    "sg:address":"4701 Willow Creek Ln",
    "sg:city":"Sheboygan",
    "sg:classifiers":[
        {
            "category":"Real Estate",
            "subcategory":"Real Estate Operator",
            "type":"Services"
        }
    ],
    "sg:phone":"+1 920 803 6411",
    "sg:postcode":"53083",
    "sg:province":"WI",
    "sg:tags":[
        "building",
        "apartment"
    ],
    "wof:name":"Dr Apts LLC",
    "wof:placetype":"venue"
},
  "geometry": {"coordinates":[-87.73461500000001,43.795546],"type":"Point"}
}