{
  "type": "Feature",
  "properties": {
    "addr:full":"11106 N Port Washington Rd Mequon WI 53092",
    "addr:housenumber":"11106",
    "addr:postcode":"53092",
    "addr:street":"N Port Washington Rd",
    "iso:country":"US",
    "sg:address":"11106 N Port Washington Rd",
    "sg:city":"Mequon",
    "sg:classifiers":[
        {
            "category":"Retail",
            "subcategory":"Laundry & Dry Cleaning",
            "type":"Services"
        }
    ],
    "sg:phone":"+1 262 241 3535",
    "sg:postcode":"53092",
    "sg:province":"WI",
    "sg:tags":[
        "cleaners"
    ],
    "wof:name":"One Hour Martinizing",
    "wof:placetype":"venue"
},
  "geometry": {"coordinates":[-87.923892,43.218212],"type":"Point"}
}