{
  "type": "Feature",
  "properties": {
    "iso:country":"US",
    "sg:address":"14504 Frelich Rd",
    "sg:city":"Maribel",
    "sg:phone":"+1 920 863 2423",
    "sg:postcode":"54227",
    "sg:province":"WI",
    "sg:tags":[
        "beef",
        "farm",
        "corn",
        "soybean",
        "cattle",
        "feedlot"
    ],
    "wof:name":"Frelich Homestead",
    "wof:placetype":"venue"
},
  "geometry": {"coordinates":[-87.882604,44.291359],"type":"Point"}
}