{
  "type": "Feature",
  "properties": {
    "addr:full":"116 E Gilman St Madison WI 53703",
    "addr:housenumber":"116",
    "addr:postcode":"53703",
    "addr:street":"E Gilman St",
    "iso:country":"US",
    "sg:address":"116 E Gilman St",
    "sg:city":"Madison",
    "sg:classifiers":[
        {
            "category":"Real Estate",
            "subcategory":"Real Estate Agent",
            "type":"Services"
        }
    ],
    "sg:phone":"+1 608 287 1436",
    "sg:postcode":"53703",
    "sg:province":"WI",
    "wof:name":"Towne Realty Inc",
    "wof:placetype":"venue"
},
  "geometry": {"coordinates":[-89.38601199999999,43.080073],"type":"Point"}
}