{
  "type": "Feature",
  "properties": {
    "iso:country":"US",
    "sg:address":"806 N Old World 3rd St",
    "sg:city":"Milwaukee",
    "sg:classifiers":[
        {
            "category":"Shopping",
            "subcategory":"Optical Goods",
            "type":"Retail Goods"
        },
        {
            "category":"Shopping",
            "subcategory":"Optician",
            "type":"Retail Goods"
        }
    ],
    "sg:phone":"+1 414 276 7217",
    "sg:postcode":"53203",
    "sg:province":"WI",
    "sg:tags":[
        "lens",
        "contact"
    ],
    "wof:name":"Quality Optical Services",
    "wof:placetype":"venue"
},
  "geometry": {"coordinates":[-87.914511,43.040242],"type":"Point"}
}