{
  "type": "Feature",
  "properties": {
    "iso:country":"US",
    "sg:address":"1840 US Hwy 41",
    "sg:city":"Marinette",
    "sg:classifiers":[
        {
            "category":"Freight",
            "type":"Transportation"
        }
    ],
    "sg:phone":"+1 715 735 5159",
    "sg:postcode":"54143",
    "sg:province":"WI",
    "sg:tags":[
        "arrangement"
    ],
    "wof:name":"Behnke Transport Inc",
    "wof:placetype":"venue"
},
  "geometry": {"coordinates":[-87.631288,45.099776],"type":"Point"}
}