{
  "type": "Feature",
  "properties": {
    "iso:country":"US",
    "sg:address":"816 W National Ave",
    "sg:city":"Milwaukee",
    "sg:classifiers":[
        {
            "category":"Wholesale",
            "subcategory":"Office Equipment",
            "type":"Manufacturing & Wholesale Goods"
        },
        {
            "category":"Professional",
            "subcategory":"Printing & Photocopies",
            "type":"Services"
        },
        {
            "category":"Shopping",
            "subcategory":"Computers & Home Electronics",
            "type":"Retail Goods"
        }
    ],
    "sg:phone":"+1 414 672 4432",
    "sg:postcode":"53204",
    "sg:province":"WI",
    "sg:tags":[
        "scanning",
        "printer",
        "supply",
        "services-commercial",
        "plotting"
    ],
    "wof:name":"Icon Press",
    "wof:placetype":"venue"
},
  "geometry": {"coordinates":[-87.921553,43.023246],"type":"Point"}
}