{
  "type": "Feature",
  "properties": {
    "iso:country":"US",
    "sg:address":"1418 N 30th St",
    "sg:city":"Sheboygan",
    "sg:classifiers":[
        {
            "category":"Building & Trades",
            "subcategory":"Construction",
            "type":"Services"
        }
    ],
    "sg:phone":"+1 920 457 6385",
    "sg:postcode":"53081",
    "sg:province":"WI",
    "sg:tags":[
        "contractor"
    ],
    "wof:name":"A Guy & His Truck",
    "wof:placetype":"venue"
},
  "geometry": {"coordinates":[-87.745965,43.759555],"type":"Point"}
}