{
  "type": "Feature",
  "properties": {
    "iso:country":"US",
    "sg:address":"1333 Racine Dr",
    "sg:city":"Spooner",
    "sg:classifiers":[
        {
            "category":"Shopping",
            "subcategory":"Bicycles & Sporting Goods",
            "type":"Retail Goods"
        }
    ],
    "sg:phone":"+1 715 635 8955",
    "sg:postcode":"54801",
    "sg:province":"WI",
    "wof:name":"Boones A & H Outpost",
    "wof:placetype":"venue"
},
  "geometry": {"coordinates":[-92.051365,45.947427],"type":"Point"}
}