{
  "type": "Feature",
  "properties": {
    "addr:full":"3684 S Pine Central Rd Poplar WI 54864",
    "addr:housenumber":"3684",
    "addr:postcode":"54864",
    "addr:street":"S Pine Central Rd",
    "iso:country":"US",
    "sg:address":"3684 S Pine Central Rd",
    "sg:city":"Poplar",
    "sg:classifiers":[
        {
            "category":"Farming",
            "subcategory":"Dairy Farm",
            "type":"Manufacturing & Wholesale Goods"
        }
    ],
    "sg:phone":"+1 715 363 2706",
    "sg:postcode":"54864",
    "sg:province":"WI",
    "wof:name":"Dolsen Dairy",
    "wof:placetype":"venue"
},
  "geometry": {"coordinates":[-91.762968,46.626348],"type":"Point"}
}