{
  "type": "Feature",
  "properties": {
    "addr:full":"9480 Spruce St Fish Creek WI 54212",
    "addr:housenumber":"9480",
    "addr:postcode":"54212",
    "addr:street":"Spruce St",
    "iso:country":"US",
    "sg:address":"9480 Spruce St",
    "sg:city":"Fish Creek",
    "sg:classifiers":[
        {
            "category":"Recreation",
            "subcategory":"Marina",
            "type":"Entertainment"
        }
    ],
    "sg:phone":"+1 920 868 3789",
    "sg:postcode":"54212",
    "sg:province":"WI",
    "sg:tags":[
        "operation"
    ],
    "wof:name":"Alibi Dock Marina",
    "wof:placetype":"venue"
},
  "geometry": {"coordinates":[-87.247649,45.130385],"type":"Point"}
}