{
  "type": "Feature",
  "properties": {
    "addr:full":"1410 12th Ave Ofc Grafton WI 53024",
    "addr:housenumber":"1410",
    "addr:postcode":"53024",
    "addr:street":"12Th Ave",
    "iso:country":"US",
    "sg:address":"1410 12th Ave Ofc",
    "sg:city":"Grafton",
    "sg:classifiers":[
        {
            "category":"Real Estate",
            "subcategory":"Real Estate Operator",
            "type":"Services"
        }
    ],
    "sg:phone":"+1 262 377 2225",
    "sg:postcode":"53024",
    "sg:province":"WI",
    "sg:tags":[
        "apartment"
    ],
    "wof:name":"Westwood Hills",
    "wof:placetype":"venue"
},
  "geometry": {"coordinates":[-87.95169799999999,43.317402],"type":"Point"}
}