{
  "type": "Feature",
  "properties": {
    "iso:country":"US",
    "sg:address":"3257 S Lake Dr",
    "sg:city":"Milwaukee",
    "sg:classifiers":[
        {
            "category":"Education",
            "subcategory":"College",
            "type":"Public Place"
        }
    ],
    "sg:phone":"+1 414 747 6400",
    "sg:postcode":"53235",
    "sg:province":"WI",
    "sg:tags":[
        "organization",
        "school",
        "religious",
        "academic"
    ],
    "wof:name":"St Francis Seminary",
    "wof:placetype":"venue"
},
  "geometry": {"coordinates":[-87.861197,42.979492],"type":"Point"}
}