{
  "type": "Feature",
  "properties": {
    "iso:country":"US",
    "sg:address":"5925 Sugarbush Ln",
    "sg:city":"Greendale",
    "sg:classifiers":[
        {
            "category":"Manufacturing",
            "subcategory":"Signs",
            "type":"Manufacturing & Wholesale Goods"
        }
    ],
    "sg:phone":"+1 414 421 5924",
    "sg:postcode":"53129",
    "sg:province":"WI",
    "sg:tags":[
        "specialty",
        "mfg"
    ],
    "wof:name":"Bernie's Sign Studio",
    "wof:placetype":"venue"
},
  "geometry": {"coordinates":[-87.97389099999999,42.934965],"type":"Point"}
}