{
  "type": "Feature",
  "properties": {
    "iso:country":"US",
    "sg:address":"5818 W Capitol Dr",
    "sg:city":"Milwaukee",
    "sg:classifiers":[
        {
            "category":"Health Services",
            "subcategory":"Doctor",
            "type":"Services"
        }
    ],
    "sg:phone":"+1 414 449 2114",
    "sg:postcode":"53216",
    "sg:province":"WI",
    "sg:tags":[
        "physician",
        "pediatrics",
        "family",
        "cardiology",
        "gynecology",
        "practice",
        "surgeons",
        "neurology",
        "obstetrics",
        "medicine",
        "orthopedics",
        "surgeon",
        "internal"
    ],
    "wof:name":"Midtown Health Ctr",
    "wof:placetype":"venue"
},
  "geometry": {"coordinates":[-87.985838,43.09008],"type":"Point"}
}