{
  "type": "Feature",
  "properties": {
    "iso:country":"US",
    "sg:address":"28 N Water St E",
    "sg:city":"Fort Atkinson",
    "sg:classifiers":[
        {
            "category":"Bars & Pubs",
            "type":"Food & Drink"
        }
    ],
    "sg:phone":"+1 920 563 8046",
    "sg:postcode":"53538",
    "sg:province":"WI",
    "sg:tags":[
        "drinking"
    ],
    "wof:name":"Bienfang's Bar",
    "wof:placetype":"venue"
},
  "geometry": {"coordinates":[-88.836067,42.928979],"type":"Point"}
}