{
  "type": "Feature",
  "properties": {
    "iso:country":"US",
    "sg:address":"712 Chapple Ave",
    "sg:city":"Ashland",
    "sg:classifiers":[
        {
            "category":"Professional",
            "type":"Services"
        }
    ],
    "sg:phone":"+1 715 682 5429",
    "sg:postcode":"54806",
    "sg:province":"WI",
    "wof:name":"Bob & Denise Inc",
    "wof:placetype":"venue"
},
  "geometry": {"coordinates":[-90.886581,46.583936],"type":"Point"}
}