{
  "type": "Feature",
  "properties": {
    "iso:country":"US",
    "sg:address":"2608 Oakcrest Dr",
    "sg:city":"Neenah",
    "sg:classifiers":[
        {
            "category":"Professional",
            "subcategory":"Management & Consulting",
            "type":"Services"
        }
    ],
    "sg:phone":"+1 920 751 3687",
    "sg:postcode":"54956",
    "sg:province":"WI",
    "sg:tags":[
        "retail",
        "selling",
        "establishment",
        "sales",
        "direct"
    ],
    "wof:name":"Shaklee Authorized Distributor",
    "wof:placetype":"venue"
},
  "geometry": {"coordinates":[-88.525462,44.157094],"type":"Point"}
}