{
  "type": "Feature",
  "properties": {
    "iso:country":"US",
    "sg:address":"34 S Mills St",
    "sg:city":"Madison",
    "sg:classifiers":[
        {
            "category":"Retail",
            "subcategory":"Auto Rental",
            "type":"Services"
        }
    ],
    "sg:phone":"+1 608 245 4066",
    "sg:postcode":"53715",
    "sg:province":"WI",
    "sg:tags":[
        "passenger",
        "car"
    ],
    "wof:name":"U Rent Auto LLC",
    "wof:placetype":"venue"
},
  "geometry": {"coordinates":[-89.404132,43.066513],"type":"Point"}
}