{
  "type": "Feature",
  "properties": {
    "iso:country":"US",
    "sg:address":"423 Melvin Ave",
    "sg:city":"Racine",
    "sg:classifiers":[
        {
            "category":"Professional",
            "subcategory":"Computer Services",
            "type":"Services"
        }
    ],
    "sg:phone":"+1 262 639 9575",
    "sg:postcode":"53402",
    "sg:province":"WI",
    "sg:tags":[
        "info",
        "consultant",
        "designer",
        "system"
    ],
    "sg:website":"www.inhouse.com",
    "wof:name":"In House Information Systems",
    "wof:placetype":"venue"
},
  "geometry": {"coordinates":[-87.784097,42.755418],"type":"Point"}
}