{
  "type": "Feature",
  "properties": {
    "iso:country":"US",
    "sg:address":"1911 Harriet St",
    "sg:city":"Racine",
    "sg:classifiers":[
        {
            "category":"Building & Trades",
            "subcategory":"Construction",
            "type":"Services"
        }
    ],
    "sg:phone":"+1 262 637 9619",
    "sg:postcode":"53404",
    "sg:province":"WI",
    "sg:tags":[
        "handyman"
    ],
    "wof:name":"Ricky's Repair",
    "wof:placetype":"venue"
},
  "geometry": {"coordinates":[-87.807091,42.735061],"type":"Point"}
}