{
  "type": "Feature",
  "properties": {
    "addr:full":"3849 Decora Rd Horicon WI 53032",
    "addr:housenumber":"3849",
    "addr:postcode":"53032",
    "addr:street":"Decora Rd",
    "iso:country":"US",
    "sg:address":"3849 Decora Rd",
    "sg:city":"Horicon",
    "sg:classifiers":[
        {
            "category":"Banks & Credit Unions",
            "subcategory":"Financial Services",
            "type":"Services"
        }
    ],
    "sg:phone":"+1 920 485 4310",
    "sg:postcode":"53032",
    "sg:province":"WI",
    "sg:tags":[
        "company",
        "bank",
        "holding"
    ],
    "wof:name":"Excellent Corp",
    "wof:placetype":"venue"
},
  "geometry": {"coordinates":[-88.59107299999999,43.45412],"type":"Point"}
}