{
  "type": "Feature",
  "properties": {
    "iso:country":"US",
    "sg:address":"130 4th Ave",
    "sg:city":"Baraboo",
    "sg:classifiers":[
        {
            "category":"Education",
            "subcategory":"Dance Studio",
            "type":"Public Place"
        }
    ],
    "sg:phone":"+1 608 356 0865",
    "sg:postcode":"53913",
    "sg:province":"WI",
    "sg:tags":[
        "instruction",
        "dancing"
    ],
    "wof:name":"Bravo Center LLC",
    "wof:placetype":"venue"
},
  "geometry": {"coordinates":[-89.743846,43.47097],"type":"Point"}
}