{
  "type": "Feature",
  "properties": {
    "addr:full":"2300 Deerfield Ln E Suamico WI 54173",
    "addr:housenumber":"2300",
    "addr:postcode":"54173",
    "addr:street":"Deerfield Ln E Suamico",
    "iso:country":"US",
    "sg:address":"2300 Deerfield Ln E",
    "sg:city":"Suamico",
    "sg:classifiers":[
        {
            "category":"Building & Trades",
            "subcategory":"Construction",
            "type":"Services"
        }
    ],
    "sg:phone":"+1 920 434 9999",
    "sg:postcode":"54173",
    "sg:province":"WI",
    "sg:tags":[
        "excavating",
        "contractor",
        "water",
        "concrete",
        "poured",
        "sewer"
    ],
    "wof:name":"DCI",
    "wof:placetype":"venue"
},
  "geometry": {"coordinates":[-88.04952900000001,44.605556],"type":"Point"}
}