{
  "type": "Feature",
  "properties": {
    "iso:country":"US",
    "sg:address":"829 Mitscher Ave",
    "sg:city":"Hillsboro",
    "sg:classifiers":[
        {
            "category":"Shopping",
            "subcategory":"Clothing, Apparel, & Fashions",
            "type":"Retail Goods"
        }
    ],
    "sg:phone":"+1 608 489 3273",
    "sg:postcode":"54634",
    "sg:province":"WI",
    "sg:tags":[
        "garment",
        "lettering"
    ],
    "wof:name":"Shirts N Stuff",
    "wof:placetype":"venue"
},
  "geometry": {"coordinates":[-90.345613,43.6547],"type":"Point"}
}