{
  "type": "Feature",
  "properties": {
    "iso:country":"US",
    "sg:address":"4750 N Ardmore Ave",
    "sg:city":"Milwaukee",
    "sg:classifiers":[
        {
            "category":"Building & Trades",
            "subcategory":"Construction",
            "type":"Services"
        }
    ],
    "sg:phone":"+1 414 964 5799",
    "sg:postcode":"53211",
    "sg:province":"WI",
    "sg:tags":[
        "hanging",
        "contractor"
    ],
    "wof:name":"M&B Painters LLC",
    "wof:placetype":"venue"
},
  "geometry": {"coordinates":[-87.894644,43.102809],"type":"Point"}
}