{
  "type": "Feature",
  "properties": {
    "iso:country":"US",
    "sg:address":"2833 Lincolnshire Ct",
    "sg:city":"Waukesha",
    "sg:classifiers":[
        {
            "category":"Professional",
            "type":"Services"
        }
    ],
    "sg:phone":"+1 262 542 2998",
    "sg:postcode":"53188",
    "sg:province":"WI",
    "wof:name":"Home Page Writing Services",
    "wof:placetype":"venue"
},
  "geometry": {"coordinates":[-88.278003,43.039912],"type":"Point"}
}