{
  "type": "Feature",
  "properties": {
    "addr:full":"6641 University Ave Middleton WI 53562",
    "addr:housenumber":"6641",
    "addr:postcode":"53562",
    "addr:street":"University Ave",
    "iso:country":"US",
    "sg:address":"6641 University Ave",
    "sg:city":"Middleton",
    "sg:classifiers":[
        {
            "category":"Shopping",
            "subcategory":"Bicycles & Sporting Goods",
            "type":"Retail Goods"
        }
    ],
    "sg:phone":"+1 608 831 7433",
    "sg:postcode":"53562",
    "sg:province":"WI",
    "wof:name":"Middleton Cycle",
    "wof:placetype":"venue"
},
  "geometry": {"coordinates":[-89.494663,43.095549],"type":"Point"}
}