{
  "type": "Feature",
  "properties": {
    "addr:full":"200 N Executive Dr Brookfield WI 53005",
    "addr:housenumber":"200",
    "addr:postcode":"53005",
    "addr:street":"N Executive Dr",
    "iso:country":"US",
    "sg:address":"200 N Executive Dr",
    "sg:city":"Brookfield",
    "sg:classifiers":[
        {
            "category":"Professional",
            "subcategory":"Business Services",
            "type":"Services"
        }
    ],
    "sg:phone":"+1 262 780 1559",
    "sg:postcode":"53005",
    "sg:province":"WI",
    "wof:name":"Claim Source",
    "wof:placetype":"venue"
},
  "geometry": {"coordinates":[-88.11474200000001,43.032829],"type":"Point"}
}