{
  "type": "Feature",
  "properties": {
    "iso:country":"US",
    "sg:address":"3932 Superior Ave",
    "sg:city":"Sheboygan",
    "sg:classifiers":[
        {
            "category":"Government",
            "subcategory":"Office",
            "type":"Public Place"
        }
    ],
    "sg:phone":"+1 920 451 2325",
    "sg:postcode":"53081",
    "sg:province":"WI",
    "sg:tags":[
        "city",
        "program"
    ],
    "wof:name":"Sanitary District Sewer Dept",
    "wof:placetype":"venue"
},
  "geometry": {"coordinates":[-87.758421,43.761056],"type":"Point"}
}