{
  "type": "Feature",
  "properties": {
    "iso:country":"US",
    "sg:address":"8251 Dragonfly Rd",
    "sg:city":"Warrens",
    "sg:classifiers":[
        {
            "category":"Home & Garden",
            "subcategory":"Building Materials",
            "type":"Retail Goods"
        }
    ],
    "sg:phone":"+1 608 372 3669",
    "sg:postcode":"54666",
    "sg:province":"WI",
    "wof:name":"Unique Chimney Liners",
    "wof:placetype":"venue"
},
  "geometry": {"coordinates":[-90.352801,44.048831],"type":"Point"}
}