{
  "type": "Feature",
  "properties": {
    "iso:country":"US",
    "sg:address":"1711 S 124th St",
    "sg:city":"New Berlin",
    "sg:classifiers":[
        {
            "category":"Manufacturing",
            "subcategory":"Printing",
            "type":"Manufacturing & Wholesale Goods"
        }
    ],
    "sg:phone":"+1 262 782 2315",
    "sg:postcode":"53151",
    "sg:province":"WI",
    "sg:tags":[
        "commercial"
    ],
    "wof:name":"Redi Graphics",
    "wof:placetype":"venue"
},
  "geometry": {"coordinates":[-88.067463,43.011786],"type":"Point"}
}