{
  "type": "Feature",
  "properties": {
    "iso:country":"US",
    "sg:address":"17 Main St",
    "sg:city":"Black River Fls",
    "sg:classifiers":[
        {
            "category":"Insurance",
            "subcategory":"Insurance Agent",
            "type":"Services"
        }
    ],
    "sg:phone":"+1 715 284 4956",
    "sg:postcode":"54758",
    "sg:province":"WI",
    "sg:tags":[
        "administrator"
    ],
    "wof:name":"Greater Insurance Service",
    "wof:placetype":"venue"
},
  "geometry": {"coordinates":[-90.84735,44.294978],"type":"Point"}
}