{
  "type": "Feature",
  "properties": {
    "addr:full":"528 W Johnson St Fond Du Lac WI 54935",
    "addr:housenumber":"528",
    "addr:postcode":"54935",
    "addr:street":"W Johnson St",
    "iso:country":"US",
    "sg:address":"528 W Johnson St",
    "sg:city":"Fond Du Lac",
    "sg:classifiers":[
        {
            "category":"Cinema",
            "subcategory":"Movie Rental",
            "type":"Entertainment"
        }
    ],
    "sg:phone":"+1 920 924 4431",
    "sg:postcode":"54935",
    "sg:province":"WI",
    "sg:tags":[
        "video",
        "tape"
    ],
    "wof:name":"Blockbuster",
    "wof:placetype":"venue"
},
  "geometry": {"coordinates":[-88.465704,43.784267],"type":"Point"}
}