{
  "type": "Feature",
  "properties": {
    "iso:country":"US",
    "sg:address":"3951 N 24th Pl",
    "sg:city":"Milwaukee",
    "sg:classifiers":[
        {
            "category":"Real Estate",
            "subcategory":"Real Estate Operator",
            "type":"Services"
        }
    ],
    "sg:phone":"+1 414 899 1248",
    "sg:postcode":"53206",
    "sg:province":"WI",
    "sg:tags":[
        "small",
        "home",
        "improvement"
    ],
    "wof:name":"LBC",
    "wof:placetype":"venue"
},
  "geometry": {"coordinates":[-87.943637,43.088849],"type":"Point"}
}