{
  "type": "Feature",
  "properties": {
    "iso:country":"US",
    "sg:address":"5713 W Rawson Ave",
    "sg:city":"Franklin",
    "sg:classifiers":[
        {
            "category":"Mining & Drilling",
            "type":"Manufacturing & Wholesale Goods"
        }
    ],
    "sg:phone":"+1 414 421 2330",
    "sg:postcode":"53132",
    "sg:province":"WI",
    "sg:tags":[
        "stone",
        "construction"
    ],
    "sg:website":"www.vulcanmaterials.com",
    "wof:name":"Vulcan Materials Company",
    "wof:placetype":"venue"
},
  "geometry": {"coordinates":[-87.991231,42.915832],"type":"Point"}
}