{
  "type": "Feature",
  "properties": {
    "addr:full":"2219 Garfield St Two Rivers WI 54241",
    "addr:housenumber":"2219",
    "addr:postcode":"54241",
    "addr:street":"Garfield St",
    "iso:country":"US",
    "sg:address":"2219 Garfield St",
    "sg:city":"Two Rivers",
    "sg:classifiers":[
        {
            "category":"Health Services",
            "subcategory":"Doctor",
            "type":"Services"
        }
    ],
    "sg:phone":"+1 920 793 2281",
    "sg:postcode":"54241",
    "sg:province":"WI",
    "sg:tags":[
        "medical"
    ],
    "wof:name":"Diane Staudinger MD Daafp",
    "wof:placetype":"venue"
},
  "geometry": {"coordinates":[-87.557968,44.154492],"type":"Point"}
}