{
  "type": "Feature",
  "properties": {
    "iso:country":"US",
    "sg:address":"1820 Main St",
    "sg:city":"Green Bay",
    "sg:classifiers":[
        {
            "category":"Restaurant",
            "type":"Food & Drink"
        }
    ],
    "sg:phone":"+1 920 468 0327",
    "sg:postcode":"54302",
    "sg:province":"WI",
    "wof:name":"Los Arcos",
    "wof:placetype":"venue"
},
  "geometry": {"coordinates":[-87.97749399999999,44.494183],"type":"Point"}
}