{
  "type": "Feature",
  "properties": {
    "iso:country":"US",
    "sg:address":"12235 Viebahn Rd",
    "sg:city":"Manitowoc",
    "sg:classifiers":[
        {
            "category":"Farming",
            "subcategory":"Dairy Farm",
            "type":"Manufacturing & Wholesale Goods"
        }
    ],
    "sg:phone":"+1 920 758 2678",
    "sg:postcode":"54220",
    "sg:province":"WI",
    "wof:name":"Road N Vue",
    "wof:placetype":"venue"
},
  "geometry": {"coordinates":[-87.82770600000001,44.066116],"type":"Point"}
}