{
  "type": "Feature",
  "properties": {
    "iso:country":"US",
    "sg:address":"1320 Poplar Dr",
    "sg:city":"Waukesha",
    "sg:classifiers":[
        {
            "category":"Retail",
            "subcategory":"Auto Repair",
            "type":"Services"
        }
    ],
    "sg:phone":"+1 262 549 6444",
    "sg:postcode":"53188",
    "sg:province":"WI",
    "sg:tags":[
        "repairing",
        "automobile",
        "general"
    ],
    "wof:name":"Auto Tech",
    "wof:placetype":"venue"
},
  "geometry": {"coordinates":[-88.277896,42.993393],"type":"Point"}
}