{
  "type": "Feature",
  "properties": {
    "iso:country":"US",
    "sg:address":"1068 Crescent Ln",
    "sg:city":"Ellison Bay",
    "sg:classifiers":[
        {
            "category":"Building & Trades",
            "subcategory":"Construction",
            "type":"Services"
        }
    ],
    "sg:phone":"+1 920 854 5391",
    "sg:postcode":"54210",
    "sg:province":"WI",
    "sg:tags":[
        "carpentry",
        "contractor"
    ],
    "wof:name":"Michael Carpenter Co",
    "wof:placetype":"venue"
},
  "geometry": {"coordinates":[-87.038203,45.223082],"type":"Point"}
}