{
  "type": "Feature",
  "properties": {
    "iso:country":"US",
    "sg:address":"10568 Main St",
    "sg:city":"Hayward",
    "sg:classifiers":[
        {
            "category":"Home & Garden",
            "subcategory":"Furniture",
            "type":"Retail Goods"
        }
    ],
    "sg:phone":"+1 715 634 4303",
    "sg:postcode":"54843",
    "sg:province":"WI",
    "wof:name":"Alexander Mc Gill Inc",
    "wof:placetype":"venue"
},
  "geometry": {"coordinates":[-91.4853,46.015121],"type":"Point"}
}