{
  "type": "Feature",
  "properties": {
    "iso:country":"US",
    "sg:address":"2000 Columbus St",
    "sg:city":"Sun Prairie",
    "sg:classifiers":[
        {
            "category":"Shopping",
            "subcategory":"Used Merchandise",
            "type":"Retail Goods"
        }
    ],
    "sg:phone":"+1 608 837 5712",
    "sg:postcode":"53590",
    "sg:province":"WI",
    "wof:name":"Ward Trading Post",
    "wof:placetype":"venue"
},
  "geometry": {"coordinates":[-89.198043,43.200095],"type":"Point"}
}