{
  "type": "Feature",
  "properties": {
    "addr:full":"2924 E Dale Ave Cudahy WI 53110",
    "addr:housenumber":"2924",
    "addr:postcode":"53110",
    "addr:street":"E Dale Ave",
    "iso:country":"US",
    "sg:address":"2924 E Dale Ave",
    "sg:city":"Cudahy",
    "sg:classifiers":[
        {
            "category":"Real Estate",
            "subcategory":"Real Estate Operator",
            "type":"Services"
        }
    ],
    "sg:phone":"+1 414 747 9896",
    "sg:postcode":"53110",
    "sg:province":"WI",
    "sg:tags":[
        "property",
        "lessor"
    ],
    "wof:name":"Brunzelle LLC",
    "wof:placetype":"venue"
},
  "geometry": {"coordinates":[-87.87282,42.940987],"type":"Point"}
}