{
  "type": "Feature",
  "properties": {
    "iso:country":"US",
    "sg:address":"726 E Day Ave",
    "sg:city":"Milwaukee",
    "sg:classifiers":[
        {
            "category":"Restaurant",
            "type":"Food & Drink"
        }
    ],
    "sg:phone":"+1 414 559 6437",
    "sg:postcode":"53217",
    "sg:province":"WI",
    "sg:tags":[
        "management"
    ],
    "wof:name":"Restaurant Resource Grouping",
    "wof:placetype":"venue"
},
  "geometry": {"coordinates":[-87.901188,43.122354],"type":"Point"}
}