{
  "type": "Feature",
  "properties": {
    "iso:country":"US",
    "sg:address":"1402 Seminole Hwy",
    "sg:city":"Madison",
    "sg:classifiers":[
        {
            "category":"Personal",
            "subcategory":"Beauty Salon",
            "type":"Services"
        }
    ],
    "sg:phone":"+1 608 258 9080",
    "sg:postcode":"53711",
    "sg:province":"WI",
    "sg:tags":[
        "shop"
    ],
    "wof:name":"Toni and Guy",
    "wof:placetype":"venue"
},
  "geometry": {"coordinates":[-89.443661,43.036909],"type":"Point"}
}