{
  "type": "Feature",
  "properties": {
    "iso:country":"US",
    "sg:address":"305 W Franklin St",
    "sg:city":"Portage",
    "sg:classifiers":[
        {
            "category":"Arts & Performance",
            "subcategory":"Theater",
            "type":"Entertainment"
        }
    ],
    "sg:phone":"+1 608 742 5266",
    "sg:postcode":"53901",
    "sg:province":"WI",
    "sg:tags":[
        "group"
    ],
    "wof:name":"D J Dave D & L Entertainment",
    "wof:placetype":"venue"
},
  "geometry": {"coordinates":[-89.469299,43.542935],"type":"Point"}
}