{
  "type": "Feature",
  "properties": {
    "iso:country":"US",
    "sg:address":"1214 Longtail Beach Rd",
    "sg:city":"Suamico",
    "sg:classifiers":[
        {
            "category":"Retail",
            "subcategory":"Auto Repair",
            "type":"Services"
        }
    ],
    "sg:phone":"+1 920 469 9866",
    "sg:postcode":"54173",
    "sg:province":"WI",
    "sg:tags":[
        "body",
        "automobile",
        "painting"
    ],
    "wof:name":"Auto Appearance Specialists",
    "wof:placetype":"venue"
},
  "geometry": {"coordinates":[-88.020999,44.613515],"type":"Point"}
}