{
  "type": "Feature",
  "properties": {
    "iso:country":"US",
    "sg:address":"317 Ontario St",
    "sg:city":"Portage",
    "sg:classifiers":[
        {
            "category":"Shopping",
            "subcategory":"Beauty & Cosmetics",
            "type":"Retail Goods"
        }
    ],
    "sg:phone":"+1 608 742 4622",
    "sg:postcode":"53901",
    "sg:province":"WI",
    "sg:tags":[
        "merchandise"
    ],
    "wof:name":"Avon Store",
    "wof:placetype":"venue"
},
  "geometry": {"coordinates":[-89.441247,43.536931],"type":"Point"}
}