{
  "type": "Feature",
  "properties": {
    "iso:country":"US",
    "sg:address":"14763 Dublin Rd",
    "sg:city":"Darlington",
    "sg:classifiers":[
        {
            "category":"Professional",
            "subcategory":"Engineering",
            "type":"Services"
        }
    ],
    "sg:phone":"+1 608 776 3275",
    "sg:postcode":"53530",
    "sg:province":"WI",
    "wof:name":"Jamison Construction LLC",
    "wof:placetype":"venue"
},
  "geometry": {"coordinates":[-90.104875,42.624531],"type":"Point"}
}