{
  "type": "Feature",
  "properties": {
    "iso:country":"US",
    "sg:address":"3695 N 126th St",
    "sg:city":"Brookfield",
    "sg:classifiers":[
        {
            "category":"Wholesale",
            "subcategory":"Construction Materials",
            "type":"Manufacturing & Wholesale Goods"
        },
        {
            "category":"Wholesale",
            "subcategory":"Machinery & Supplies",
            "type":"Manufacturing & Wholesale Goods"
        }
    ],
    "sg:phone":"+1 262 781 0911",
    "sg:postcode":"53005",
    "sg:province":"WI",
    "sg:tags":[
        "insulation",
        "equipment",
        "industrial"
    ],
    "wof:name":"Foster Fiberglass & Foam Inc",
    "wof:placetype":"venue"
},
  "geometry": {"coordinates":[-88.069026,43.085625],"type":"Point"}
}