{
  "type": "Feature",
  "properties": {
    "iso:country":"US",
    "sg:address":"744 N 8th Ave",
    "sg:city":"Sturgeon Bay",
    "sg:classifiers":[
        {
            "category":"Organizations",
            "subcategory":"Community Association",
            "type":"Services"
        }
    ],
    "sg:phone":"+1 920 743 4294",
    "sg:postcode":"54235",
    "sg:province":"WI",
    "wof:name":"Sons of Norway",
    "wof:placetype":"venue"
},
  "geometry": {"coordinates":[-87.371301,44.843695],"type":"Point"}
}