{
  "type": "Feature",
  "properties": {
    "iso:country":"US",
    "sg:address":"201 Ferry St",
    "sg:city":"La Crosse",
    "sg:classifiers":[
        {
            "category":"Retail",
            "subcategory":"Car Wash",
            "type":"Services"
        }
    ],
    "sg:phone":"+1 608 791 6459",
    "sg:postcode":"54601",
    "sg:province":"WI",
    "sg:tags":[
        "automobile",
        "detail",
        "clean"
    ],
    "wof:name":"Superior Clean",
    "wof:placetype":"venue"
},
  "geometry": {"coordinates":[-91.253446,43.805665],"type":"Point"}
}