{
  "type": "Feature",
  "properties": {
    "iso:country":"US",
    "sg:address":"6211 22nd Ave",
    "sg:city":"Kenosha",
    "sg:classifiers":[
        {
            "category":"Personal",
            "subcategory":"Beauty Salon",
            "type":"Services"
        }
    ],
    "sg:phone":"+1 262 657 6125",
    "sg:postcode":"53143",
    "sg:province":"WI",
    "wof:name":"Hair Gallery",
    "wof:placetype":"venue"
},
  "geometry": {"coordinates":[-87.835471,42.577744],"type":"Point"}
}