{
  "type": "Feature",
  "properties": {
    "iso:country":"US",
    "sg:address":"1617 N 19th St",
    "sg:city":"Superior",
    "sg:classifiers":[
        {
            "category":"Retail",
            "subcategory":"Funeral Services",
            "type":"Services"
        }
    ],
    "sg:phone":"+1 715 394 7746",
    "sg:postcode":"54880",
    "sg:province":"WI",
    "sg:tags":[
        "director"
    ],
    "wof:name":"Downs Funeral Home",
    "wof:placetype":"venue"
},
  "geometry": {"coordinates":[-92.10225800000001,46.71594],"type":"Point"}
}