{
  "type": "Feature",
  "properties": {
    "addr:full":"1822 19th Ave Rice Lake WI 54868",
    "addr:housenumber":"1822",
    "addr:postcode":"54868",
    "addr:street":"19Th Ave",
    "iso:country":"US",
    "sg:address":"1822 19th Ave",
    "sg:city":"Rice Lake",
    "sg:classifiers":[
        {
            "category":"Manufacturing",
            "subcategory":"Metals",
            "type":"Manufacturing & Wholesale Goods"
        }
    ],
    "sg:phone":"+1 715 234 8010",
    "sg:postcode":"54868",
    "sg:province":"WI",
    "sg:tags":[
        "product",
        "fabricated",
        "mfg"
    ],
    "wof:name":"Greisen Manufacturer",
    "wof:placetype":"venue"
},
  "geometry": {"coordinates":[-91.783131,45.480872],"type":"Point"}
}