{
  "type": "Feature",
  "properties": {
    "iso:country":"US",
    "sg:address":"1792 E 20th Ct",
    "sg:city":"Arkdale",
    "sg:classifiers":[
        {
            "category":"Building & Trades",
            "subcategory":"Construction",
            "type":"Services"
        }
    ],
    "sg:phone":"+1 608 339 9641",
    "sg:postcode":"54613",
    "sg:province":"WI",
    "sg:tags":[
        "contractor"
    ],
    "wof:name":"A&E Masonry Specialist",
    "wof:placetype":"venue"
},
  "geometry": {"coordinates":[-89.956576,43.997808],"type":"Point"}
}