{
  "type": "Feature",
  "properties": {
    "iso:country":"US",
    "sg:address":"10622 School Rd",
    "sg:city":"Fremont",
    "sg:classifiers":[
        {
            "category":"Wholesale",
            "subcategory":"Machinery & Supplies",
            "type":"Manufacturing & Wholesale Goods"
        }
    ],
    "sg:phone":"+1 920 667 4747",
    "sg:postcode":"54940",
    "sg:province":"WI",
    "sg:tags":[
        "fire",
        "department",
        "equipment"
    ],
    "wof:name":"Fire Apparatus & Equipment Inc",
    "wof:placetype":"venue"
},
  "geometry": {"coordinates":[-88.739067,44.286984],"type":"Point"}
}