{
  "type": "Feature",
  "properties": {
    "addr:full":"129 N Central St New Auburn WI 54757",
    "addr:housenumber":"129",
    "addr:postcode":"54757",
    "addr:street":"N Central St",
    "iso:country":"US",
    "sg:address":"129 N Central St",
    "sg:city":"New Auburn",
    "sg:classifiers":[
        {
            "category":"Organizations",
            "subcategory":"Religious Organization",
            "type":"Services"
        }
    ],
    "sg:phone":"+1 715 237 2933",
    "sg:postcode":"54757",
    "sg:province":"WI",
    "sg:tags":[
        "church"
    ],
    "wof:name":"United Methodist Church",
    "wof:placetype":"venue"
},
  "geometry": {"coordinates":[-91.56134400000001,45.204575],"type":"Point"}
}