{
  "type": "Feature",
  "properties": {
    "iso:country":"US",
    "sg:address":"8280 River Ave",
    "sg:city":"Greenwood",
    "sg:classifiers":[
        {
            "category":"Farming",
            "subcategory":"Dairy Farm",
            "type":"Manufacturing & Wholesale Goods"
        }
    ],
    "sg:phone":"+1 715 267 6213",
    "sg:postcode":"54437",
    "sg:province":"WI",
    "wof:name":"Stieglitz Dairy",
    "wof:placetype":"venue"
},
  "geometry": {"coordinates":[-90.61843,44.718078],"type":"Point"}
}