{
  "type": "Feature",
  "properties": {
    "iso:country":"US",
    "sg:address":"200 E Washington St",
    "sg:city":"Appleton",
    "sg:classifiers":[
        {
            "category":"Professional",
            "subcategory":"Accounting & Tax Preparation",
            "type":"Services"
        }
    ],
    "sg:phone":"+1 920 731 8111",
    "sg:postcode":"54911",
    "sg:province":"WI",
    "sg:tags":[
        "accountant"
    ],
    "sg:website":"www.schenckcpa.com",
    "wof:name":"Schenck Business Solutions",
    "wof:placetype":"venue"
},
  "geometry": {"coordinates":[-88.402749,44.262941],"type":"Point"}
}