{
  "type": "Feature",
  "properties": {
    "iso:country":"US",
    "sg:address":"2501 S Superior St",
    "sg:city":"Milwaukee",
    "sg:classifiers":[
        {
            "category":"Recreation",
            "type":"Entertainment"
        }
    ],
    "sg:phone":"+1 414 483 6335",
    "sg:postcode":"53207",
    "sg:province":"WI",
    "sg:tags":[
        "hall",
        "auditorium"
    ],
    "wof:name":"Club Garabaldi",
    "wof:placetype":"venue"
},
  "geometry": {"coordinates":[-87.888864,42.998425],"type":"Point"}
}