{
  "type": "Feature",
  "properties": {
    "iso:country":"US",
    "sg:address":"1978 Holmgren Way",
    "sg:city":"Green Bay",
    "sg:classifiers":[
        {
            "category":"Travel",
            "subcategory":"Hotels & Motels",
            "type":"Entertainment"
        }
    ],
    "sg:phone":"+1 920 498 8088",
    "sg:postcode":"54304",
    "sg:province":"WI",
    "wof:name":"Days Inn",
    "wof:placetype":"venue"
},
  "geometry": {"coordinates":[-88.054609,44.496491],"type":"Point"}
}