{
  "type": "Feature",
  "properties": {
    "iso:country":"US",
    "sg:address":"109 Valleywood Ct",
    "sg:city":"Oconomowoc",
    "sg:classifiers":[
        {
            "category":"Banks & Credit Unions",
            "subcategory":"Bank",
            "type":"Services"
        }
    ],
    "sg:phone":"+1 262 965 2094",
    "sg:postcode":"53066",
    "sg:province":"WI",
    "sg:tags":[
        "personal",
        "institution"
    ],
    "wof:name":"Strategic Financial",
    "wof:placetype":"venue"
},
  "geometry": {"coordinates":[-88.438463,43.033802],"type":"Point"}
}