{
  "type": "Feature",
  "properties": {
    "iso:country":"US",
    "sg:address":"1202 1st St",
    "sg:city":"Wausau",
    "sg:classifiers":[
        {
            "category":"Professional",
            "subcategory":"Research",
            "type":"Services"
        }
    ],
    "sg:phone":"+1 715 849 1612",
    "sg:postcode":"54403",
    "sg:province":"WI",
    "sg:tags":[
        "laboratory"
    ],
    "wof:name":"Marathon County Dhia",
    "wof:placetype":"venue"
},
  "geometry": {"coordinates":[-89.629623,44.966322],"type":"Point"}
}