{
  "type": "Feature",
  "properties": {
    "iso:country":"US",
    "sg:address":"6119 N Teutonia Ave",
    "sg:city":"Milwaukee",
    "sg:classifiers":[
        {
            "category":"Professional",
            "subcategory":"Business Services",
            "type":"Services"
        }
    ],
    "sg:phone":"+1 414 393 0297",
    "sg:postcode":"53209",
    "sg:province":"WI",
    "sg:tags":[
        "recording",
        "studio"
    ],
    "wof:name":"Str8-P Records",
    "wof:placetype":"venue"
},
  "geometry": {"coordinates":[-87.95232799999999,43.129025],"type":"Point"}
}