{
  "type": "Feature",
  "properties": {
    "iso:country":"US",
    "sg:address":"7927 W Capitol Dr",
    "sg:city":"Milwaukee",
    "sg:classifiers":[
        {
            "category":"Banks & Credit Unions",
            "subcategory":"Bank",
            "type":"Services"
        }
    ],
    "sg:phone":"+1 414 464 4400",
    "sg:postcode":"53222",
    "sg:province":"WI",
    "sg:website":"www.northshorebank.com",
    "wof:name":"North Shore Bank",
    "wof:placetype":"venue"
},
  "geometry": {"coordinates":[-88.012024,43.089804],"type":"Point"}
}