{
  "type": "Feature",
  "properties": {
    "iso:country":"US",
    "sg:address":"810 E Green Bay Ave",
    "sg:city":"Saukville",
    "sg:classifiers":[
        {
            "category":"Shopping",
            "subcategory":"Florist",
            "type":"Retail Goods"
        }
    ],
    "sg:phone":"+1 262 268 6894",
    "sg:postcode":"53080",
    "sg:province":"WI",
    "wof:name":"Pick 'n Save Food Stores",
    "wof:placetype":"venue"
},
  "geometry": {"coordinates":[-87.923052,43.384911],"type":"Point"}
}