{
  "type": "Feature",
  "properties": {
    "iso:country":"US",
    "sg:address":"1828 Taylor Ave",
    "sg:city":"Racine",
    "sg:classifiers":[
        {
            "category":"Social Services",
            "subcategory":"Child Care",
            "type":"Services"
        }
    ],
    "sg:phone":"+1 262 632 7313",
    "sg:postcode":"53403",
    "sg:province":"WI",
    "sg:tags":[
        "day"
    ],
    "wof:name":"Hickmans Learning Enterprise",
    "wof:placetype":"venue"
},
  "geometry": {"coordinates":[-87.808184,42.707978],"type":"Point"}
}