{
  "type": "Feature",
  "properties": {
    "addr:full":"980 E Circle Dr Milwaukee WI 53217",
    "addr:housenumber":"980",
    "addr:postcode":"53217",
    "addr:street":"E Circle Dr",
    "iso:country":"US",
    "sg:address":"980 E Circle Dr",
    "sg:city":"Milwaukee",
    "sg:classifiers":[
        {
            "category":"Professional",
            "subcategory":"Computer Services",
            "type":"Services"
        }
    ],
    "sg:phone":"+1 414 332 9876",
    "sg:postcode":"53217",
    "sg:province":"WI",
    "sg:tags":[
        "consultant",
        "designer"
    ],
    "wof:name":"Hentzenwerke",
    "wof:placetype":"venue"
},
  "geometry": {"coordinates":[-87.899815,43.114427],"type":"Point"}
}