{
  "type": "Feature",
  "properties": {
    "iso:country":"US",
    "sg:address":"419 Chapple Ave",
    "sg:city":"Ashland",
    "sg:classifiers":[
        {
            "category":"Sports & Exercise",
            "subcategory":"Gym",
            "type":"Entertainment"
        }
    ],
    "sg:phone":"+1 715 682 8590",
    "sg:postcode":"54806",
    "sg:province":"WI",
    "sg:tags":[
        "club",
        "health",
        "studio",
        "gymnasium"
    ],
    "wof:name":"Chequamegon Hlth & Fitnes Ctr",
    "wof:placetype":"venue"
},
  "geometry": {"coordinates":[-90.889135,46.586512],"type":"Point"}
}