{
  "type": "Feature",
  "properties": {
    "addr:full":"6495 Kinker Rd Fond Du Lac WI 54937",
    "addr:housenumber":"6495",
    "addr:postcode":"54937",
    "addr:street":"Kinker Rd",
    "iso:country":"US",
    "sg:address":"6495 Kinker Rd",
    "sg:city":"Fond Du Lac",
    "sg:phone":"+1 920 923 0140",
    "sg:postcode":"54937",
    "sg:province":"WI",
    "sg:tags":[
        "farm",
        "dairy",
        "corn",
        "wheat",
        "soybean"
    ],
    "wof:name":"Jan Schumacher",
    "wof:placetype":"venue"
},
  "geometry": {"coordinates":[-88.494811,43.849734],"type":"Point"}
}