{
  "type": "Feature",
  "properties": {
    "addr:full":"2363 S 102nd St Milwaukee WI 53227",
    "addr:housenumber":"2363",
    "addr:postcode":"53227",
    "addr:street":"S 102Nd St",
    "iso:country":"US",
    "sg:address":"2363 S 102nd St",
    "sg:city":"Milwaukee",
    "sg:classifiers":[
        {
            "category":"Arts & Performance",
            "subcategory":"Theater",
            "type":"Entertainment"
        }
    ],
    "sg:phone":"+1 414 321 6210",
    "sg:postcode":"53227",
    "sg:province":"WI",
    "sg:tags":[
        "program",
        "radio",
        "producer"
    ],
    "sg:website":"www.newsbroadcastnetwork.com",
    "wof:name":"News Broadcast Network",
    "wof:placetype":"venue"
},
  "geometry": {"coordinates":[-88.04075400000001,43.001696],"type":"Point"}
}