{
  "type": "Feature",
  "properties": {
    "iso:country":"US",
    "sg:address":"8220 Buttercup Ct",
    "sg:city":"Wautoma",
    "sg:classifiers":[
        {
            "category":"Restaurant",
            "type":"Food & Drink"
        }
    ],
    "sg:phone":"+1 920 787 7787",
    "sg:postcode":"54982",
    "sg:province":"WI",
    "sg:tags":[
        "eating"
    ],
    "wof:name":"Milty-Wilty Drive-In Rest",
    "wof:placetype":"venue"
},
  "geometry": {"coordinates":[-89.291444,44.079933],"type":"Point"}
}