{
  "type": "Feature",
  "properties": {
    "iso:country":"US",
    "sg:address":"814 School Rd",
    "sg:city":"New Auburn",
    "sg:classifiers":[
        {
            "category":"Shopping",
            "subcategory":"Bicycles & Sporting Goods",
            "type":"Retail Goods"
        }
    ],
    "sg:phone":"+1 715 868 2398",
    "sg:postcode":"54757",
    "sg:province":"WI",
    "wof:name":"Frank's Island Lake Sports Shp",
    "wof:placetype":"venue"
},
  "geometry": {"coordinates":[-91.37021,45.31942],"type":"Point"}
}