{
  "type": "Feature",
  "properties": {
    "iso:country":"US",
    "sg:address":"17 N Madison St",
    "sg:city":"Waupun",
    "sg:classifiers":[
        {
            "category":"Restaurant",
            "type":"Food & Drink"
        }
    ],
    "sg:phone":"+1 920 239 0103",
    "sg:postcode":"53963",
    "sg:province":"WI",
    "sg:tags":[
        "eating"
    ],
    "wof:name":"Vande Hof Title",
    "wof:placetype":"venue"
},
  "geometry": {"coordinates":[-88.729747,43.634043],"type":"Point"}
}