{
  "type": "Feature",
  "properties": {
    "addr:full":"4616 Town Line Rd Amherst WI 54406",
    "addr:housenumber":"4616",
    "addr:postcode":"54406",
    "addr:street":"Town Line Rd",
    "iso:country":"US",
    "sg:address":"4616 Town Line Rd",
    "sg:city":"Amherst",
    "sg:classifiers":[
        {
            "category":"Retail",
            "subcategory":"Repair Shop",
            "type":"Services"
        }
    ],
    "sg:phone":"+1 715 824 5902",
    "sg:postcode":"54406",
    "sg:province":"WI",
    "wof:name":"New Life Taxidermy",
    "wof:placetype":"venue"
},
  "geometry": {"coordinates":[-89.36555199999999,44.44692],"type":"Point"}
}