{
  "type": "Feature",
  "properties": {
    "iso:country":"US",
    "sg:address":"3940 Pelsdorf Ave",
    "sg:city":"Granton",
    "sg:classifiers":[
        {
            "category":"Farming",
            "subcategory":"Farm",
            "type":"Manufacturing & Wholesale Goods"
        }
    ],
    "sg:phone":"+1 715 238 7484",
    "sg:postcode":"54436",
    "sg:province":"WI",
    "sg:tags":[
        "crop",
        "general"
    ],
    "wof:name":"Frederick Garbisch",
    "wof:placetype":"venue"
},
  "geometry": {"coordinates":[-90.47652,44.565949],"type":"Point"}
}