{
  "type": "Feature",
  "properties": {
    "addr:full":"145 Robin Ln Shawano WI 54166",
    "addr:housenumber":"145",
    "addr:postcode":"54166",
    "addr:street":"Robin Ln",
    "iso:country":"US",
    "sg:address":"145 Robin Ln",
    "sg:city":"Shawano",
    "sg:classifiers":[
        {
            "category":"Insurance",
            "subcategory":"Insurance Agent",
            "type":"Services"
        }
    ],
    "sg:phone":"+1 715 526 6022",
    "sg:postcode":"54166",
    "sg:province":"WI",
    "wof:name":"Physicians Mutual Insurance Co",
    "wof:placetype":"venue"
},
  "geometry": {"coordinates":[-88.599856,44.763174],"type":"Point"}
}