{
  "type": "Feature",
  "properties": {
    "iso:country":"US",
    "sg:address":"1820 Charles St",
    "sg:city":"De Pere",
    "sg:classifiers":[
        {
            "category":"Building & Trades",
            "subcategory":"Construction",
            "type":"Services"
        }
    ],
    "sg:phone":"+1 920 983 8446",
    "sg:postcode":"54115",
    "sg:province":"WI",
    "sg:tags":[
        "heavy"
    ],
    "wof:name":"K D T LLC",
    "wof:placetype":"venue"
},
  "geometry": {"coordinates":[-88.03598,44.44396],"type":"Point"}
}