{
  "type": "Feature",
  "properties": {
    "iso:country":"US",
    "sg:address":"126 2nd St",
    "sg:city":"Hudson",
    "sg:classifiers":[
        {
            "category":"Building & Trades",
            "subcategory":"Construction",
            "type":"Services"
        }
    ],
    "sg:phone":"+1 715 386 3942",
    "sg:postcode":"54016",
    "sg:province":"WI",
    "sg:tags":[
        "home",
        "contractor"
    ],
    "wof:name":"Coldwell Banker",
    "wof:placetype":"venue"
},
  "geometry": {"coordinates":[-92.756528,44.97131],"type":"Point"}
}