{
  "type": "Feature",
  "properties": {
    "iso:country":"US",
    "sg:address":"1401 W Washington St",
    "sg:city":"Milwaukee",
    "sg:classifiers":[
        {
            "category":"Restaurant",
            "type":"Food & Drink"
        }
    ],
    "sg:phone":"+1 414 647 1899",
    "sg:postcode":"53204",
    "sg:province":"WI",
    "wof:name":"El Farol Restaurant & Grocery",
    "wof:placetype":"venue"
},
  "geometry": {"coordinates":[-87.93053999999999,43.02012],"type":"Point"}
}