{
  "type": "Feature",
  "properties": {
    "iso:country":"US",
    "sg:address":"3905 Wood Duck Ln",
    "sg:city":"Wausau",
    "sg:classifiers":[
        {
            "category":"Freight",
            "type":"Transportation"
        }
    ],
    "sg:phone":"+1 715 355 1516",
    "sg:postcode":"54401",
    "sg:province":"WI",
    "sg:tags":[
        "trucking"
    ],
    "wof:name":"ABF Freight System Inc",
    "wof:placetype":"venue"
},
  "geometry": {"coordinates":[-89.64948200000001,44.921002],"type":"Point"}
}