{
  "type": "Feature",
  "properties": {
    "iso:country":"US",
    "sg:address":"625 W Veterans St",
    "sg:city":"Tomah",
    "sg:classifiers":[
        {
            "category":"Organizations",
            "subcategory":"Religious Organization",
            "type":"Services"
        }
    ],
    "sg:phone":"+1 608 372 9377",
    "sg:postcode":"54660",
    "sg:province":"WI",
    "sg:website":"www.bibleefc.com",
    "wof:name":"Bible Evangelical Free Church",
    "wof:placetype":"venue"
},
  "geometry": {"coordinates":[-90.510488,44.000829],"type":"Point"}
}