{
  "type": "Feature",
  "properties": {
    "iso:country":"US",
    "sg:address":"606 Cooper Rd",
    "sg:city":"Waunakee",
    "sg:classifiers":[
        {
            "category":"Manufacturing",
            "subcategory":"Tools & Machinery",
            "type":"Manufacturing & Wholesale Goods"
        }
    ],
    "sg:phone":"+1 608 849 5012",
    "sg:postcode":"53597",
    "sg:province":"WI",
    "sg:tags":[
        "equipment",
        "mfg",
        "dairy",
        "automated"
    ],
    "sg:website":"www.germaniadairy.com",
    "wof:name":"Germania Dairy Automation Inc",
    "wof:placetype":"venue"
},
  "geometry": {"coordinates":[-89.4447,43.190969],"type":"Point"}
}