{
  "type": "Feature",
  "properties": {
    "iso:country":"US",
    "sg:address":"205 W South St",
    "sg:city":"Beaver Dam",
    "sg:classifiers":[
        {
            "category":"Recreation",
            "type":"Entertainment"
        }
    ],
    "sg:phone":"+1 920 887 4623",
    "sg:postcode":"53916",
    "sg:province":"WI",
    "sg:tags":[
        "parks"
    ],
    "wof:name":"Beaver Dam Park Shop",
    "wof:placetype":"venue"
},
  "geometry": {"coordinates":[-88.841842,43.45087],"type":"Point"}
}