{
  "type": "Feature",
  "properties": {
    "iso:country":"US",
    "sg:address":"6585 Co Hwy O",
    "sg:city":"Millston",
    "sg:classifiers":[
        {
            "category":"Manufacturing",
            "subcategory":"Chemicals & Compounds",
            "type":"Manufacturing & Wholesale Goods"
        }
    ],
    "sg:phone":"+1 715 284 2296",
    "sg:postcode":"54615",
    "sg:province":"WI",
    "sg:tags":[
        "fertilizer",
        "mixing",
        "only"
    ],
    "sg:website":"www.mosserlee.com",
    "wof:name":"Mosser Lee Co",
    "wof:placetype":"venue"
},
  "geometry": {"coordinates":[-90.72107099999999,44.349951],"type":"Point"}
}