{
  "type": "Feature",
  "properties": {
    "iso:country":"US",
    "sg:address":"1459 E Main St",
    "sg:city":"Madison",
    "sg:classifiers":[
        {
            "category":"Professional",
            "subcategory":"Management & Consulting",
            "type":"Services"
        }
    ],
    "sg:phone":"+1 608 255 8845",
    "sg:postcode":"53704",
    "sg:province":"WI",
    "sg:tags":[
        "business"
    ],
    "wof:name":"Pony Reserves Ltd",
    "wof:placetype":"venue"
},
  "geometry": {"coordinates":[-89.361225,43.089105],"type":"Point"}
}