{
  "type": "Feature",
  "properties": {
    "iso:country":"US",
    "sg:address":"7607 Hixon Rd",
    "sg:city":"Minocqua",
    "sg:classifiers":[
        {
            "category":"Professional",
            "subcategory":"Lawyer & Legal Services",
            "type":"Services"
        }
    ],
    "sg:phone":"+1 715 356 6230",
    "sg:postcode":"54548",
    "sg:province":"WI",
    "sg:tags":[
        "attorney"
    ],
    "wof:name":"Jon Cassady Law Office",
    "wof:placetype":"venue"
},
  "geometry": {"coordinates":[-89.72613,45.836188],"type":"Point"}
}