{
  "type": "Feature",
  "properties": {
    "iso:country":"US",
    "sg:address":"4027 S Business Dr",
    "sg:city":"Sheboygan",
    "sg:classifiers":[
        {
            "category":"Professional",
            "subcategory":"Computer Services",
            "type":"Services"
        }
    ],
    "sg:phone":"+1 920 208 7610",
    "sg:postcode":"53081",
    "sg:province":"WI",
    "sg:tags":[
        "prepackaged",
        "software"
    ],
    "wof:name":"Results Intl Systems Inc",
    "wof:placetype":"venue"
},
  "geometry": {"coordinates":[-87.741688,43.710228],"type":"Point"}
}