{
  "type": "Feature",
  "properties": {
    "iso:country":"US",
    "sg:address":"8815 Co Rd Oo",
    "sg:city":"Clintonville",
    "sg:classifiers":[
        {
            "category":"Farming",
            "subcategory":"Farm",
            "type":"Manufacturing & Wholesale Goods"
        }
    ],
    "sg:phone":"+1 715 752 3048",
    "sg:postcode":"54929",
    "sg:province":"WI",
    "sg:tags":[
        "crop",
        "general"
    ],
    "wof:name":"R & P Farms LLC",
    "wof:placetype":"venue"
},
  "geometry": {"coordinates":[-88.879872,44.55768],"type":"Point"}
}