{
  "type": "Feature",
  "properties": {
    "addr:full":"2710 Calumet Ave Manitowoc WI 54220",
    "addr:housenumber":"2710",
    "addr:postcode":"54220",
    "addr:street":"Calumet Ave",
    "iso:country":"US",
    "sg:address":"2710 Calumet Ave",
    "sg:city":"Manitowoc",
    "sg:classifiers":[
        {
            "category":"Autos & Motor Vehicles",
            "subcategory":"Fuel & Gas Station",
            "type":"Retail Goods"
        }
    ],
    "sg:phone":"+1 920 682 0304",
    "sg:postcode":"54220",
    "sg:province":"WI",
    "sg:tags":[
        "gasoline",
        "tire"
    ],
    "wof:name":"Schmidt Tire & Muffler Center",
    "wof:placetype":"venue"
},
  "geometry": {"coordinates":[-87.682002,44.087146],"type":"Point"}
}