{
  "type": "Feature",
  "properties": {
    "iso:country":"US",
    "sg:address":"105 S Main St",
    "sg:city":"West Bend",
    "sg:classifiers":[
        {
            "category":"Shopping",
            "subcategory":"Clothing, Apparel, & Fashions",
            "type":"Retail Goods"
        }
    ],
    "sg:phone":"+1 262 335 6708",
    "sg:postcode":"53095",
    "sg:province":"WI",
    "wof:name":"Peek A Bootique I",
    "wof:placetype":"venue"
},
  "geometry": {"coordinates":[-88.182389,43.423444],"type":"Point"}
}