{
  "type": "Feature",
  "properties": {
    "iso:country":"US",
    "sg:address":"109 W Kimberly Ave",
    "sg:city":"Kimberly",
    "sg:classifiers":[
        {
            "category":"Building & Trades",
            "subcategory":"Plumbing",
            "type":"Services"
        }
    ],
    "sg:phone":"+1 920 788 5804",
    "sg:postcode":"54136",
    "sg:province":"WI",
    "sg:tags":[
        "conditioning",
        "air",
        "system",
        "contractor"
    ],
    "wof:name":"Kimberly Hardware Inc",
    "wof:placetype":"venue"
},
  "geometry": {"coordinates":[-88.334884,44.272298],"type":"Point"}
}