{
  "type": "Feature",
  "properties": {
    "iso:country":"US",
    "sg:address":"9674 Wilhilm Dr",
    "sg:city":"Prairie Du Sac",
    "sg:classifiers":[
        {
            "category":"Professional",
            "subcategory":"Business Services",
            "type":"Services"
        }
    ],
    "sg:phone":"+1 608 544 4004",
    "sg:postcode":"53578",
    "sg:province":"WI",
    "wof:name":"T&M Enterprises Inc",
    "wof:placetype":"venue"
},
  "geometry": {"coordinates":[-89.82711,43.293265],"type":"Point"}
}