{
  "type": "Feature",
  "properties": {
    "iso:country":"US",
    "sg:address":"151 Linmar Ln",
    "sg:city":"Johnson Creek",
    "sg:classifiers":[
        {
            "category":"Shopping",
            "subcategory":"Catalog Store",
            "type":"Retail Goods"
        }
    ],
    "sg:phone":"+1 920 699 7214",
    "sg:postcode":"53038",
    "sg:province":"WI",
    "sg:tags":[
        "basket",
        "fruit",
        "gift"
    ],
    "wof:name":"Harry and David",
    "wof:placetype":"venue"
},
  "geometry": {"coordinates":[-88.759598,43.089794],"type":"Point"}
}