{
  "type": "Feature",
  "properties": {
    "addr:full":"3300 S Stonegate Cir New Berlin WI 53151",
    "addr:housenumber":"3300",
    "addr:postcode":"53151",
    "addr:street":"S Stonegate Cir",
    "iso:country":"US",
    "sg:address":"3300 S Stonegate Cir",
    "sg:city":"New Berlin",
    "sg:classifiers":[
        {
            "category":"Professional",
            "subcategory":"Computer Services",
            "type":"Services"
        }
    ],
    "sg:phone":"+1 262 780 9725",
    "sg:postcode":"53151",
    "sg:province":"WI",
    "sg:tags":[
        "datum"
    ],
    "wof:name":"Zorigo LLC",
    "wof:placetype":"venue"
},
  "geometry": {"coordinates":[-88.08076800000001,42.98575],"type":"Point"}
}