{
  "type": "Feature",
  "properties": {
    "iso:country":"US",
    "sg:address":"5657 S Lake Dr",
    "sg:city":"Cudahy",
    "sg:classifiers":[
        {
            "category":"Wholesale",
            "subcategory":"Poultry",
            "type":"Manufacturing & Wholesale Goods"
        }
    ],
    "sg:phone":"+1 414 769 6416",
    "sg:postcode":"53110",
    "sg:province":"WI",
    "sg:tags":[
        "eggs"
    ],
    "wof:name":"EGGS",
    "wof:placetype":"venue"
},
  "geometry": {"coordinates":[-87.84989899999999,42.944638],"type":"Point"}
}