{
  "type": "Feature",
  "properties": {
    "iso:country":"US",
    "sg:address":"6715 Middle Rd",
    "sg:city":"Racine",
    "sg:phone":"+1 262 681 2946",
    "sg:postcode":"53402",
    "sg:province":"WI",
    "sg:tags":[
        "product",
        "petroleum"
    ],
    "wof:name":"American Mobile Petroleum",
    "wof:placetype":"venue"
},
  "geometry": {"coordinates":[-87.815718,42.809674],"type":"Point"}
}