{
  "type": "Feature",
  "properties": {
    "addr:full":"S84w19234 Enterprise Dr Muskego WI 53150",
    "addr:postcode":"53150",
    "addr:street":"Enterprise",
    "iso:country":"US",
    "sg:address":"S84w19234 Enterprise Dr",
    "sg:city":"Muskego",
    "sg:classifiers":[
        {
            "category":"Manufacturing",
            "subcategory":"Tools & Machinery",
            "type":"Manufacturing & Wholesale Goods"
        },
        {
            "category":"Wholesale",
            "subcategory":"Petroleum",
            "type":"Manufacturing & Wholesale Goods"
        }
    ],
    "sg:phone":"+1 262 971 1717",
    "sg:postcode":"53150",
    "sg:province":"WI",
    "sg:tags":[
        "building",
        "construction",
        "tools-pneumatic",
        "equipment"
    ],
    "sg:website":"http://www.nelsonsales.com",
    "wof:name":"Nelson Sales",
    "wof:placetype":"venue"
},
  "geometry": {"coordinates":[-88.144634,42.891689],"type":"Point"}
}