{
  "type": "Feature",
  "properties": {
    "iso:country":"US",
    "sg:address":"1272 N 117th St",
    "sg:city":"Milwaukee",
    "sg:classifiers":[
        {
            "category":"Recreation",
            "type":"Entertainment"
        }
    ],
    "sg:phone":"+1 414 476 4698",
    "sg:postcode":"53226",
    "sg:province":"WI",
    "sg:tags":[
        "club",
        "membership"
    ],
    "wof:name":"Greenfield Womens Golf Club",
    "wof:placetype":"venue"
},
  "geometry": {"coordinates":[-88.058522,43.045973],"type":"Point"}
}