{
  "type": "Feature",
  "properties": {
    "iso:country":"US",
    "sg:address":"135 W Wisconsin Ave",
    "sg:city":"Milwaukee",
    "sg:classifiers":[
        {
            "category":"Restaurant",
            "type":"Food & Drink"
        }
    ],
    "sg:menulink":"http://www.allmenus.com/wi/milwaukee/114540-potbelly-sandwich-works/menu/",
    "sg:phone":"+1 414 226 0014",
    "sg:postcode":"53203",
    "sg:province":"WI",
    "sg:tags":[
        "wrap",
        "american",
        "sandwich"
    ],
    "wof:name":"Potbelly Sandwich Works",
    "wof:placetype":"venue"
},
  "geometry": {"coordinates":[-87.911337,43.038759],"type":"Point"}
}