{
  "type": "Feature",
  "properties": {
    "iso:country":"US",
    "sg:address":"1180 Walnut Ridge Dr",
    "sg:city":"Hartland",
    "sg:classifiers":[
        {
            "category":"Manufacturing",
            "subcategory":"Printing",
            "type":"Manufacturing & Wholesale Goods"
        }
    ],
    "sg:phone":"+1 877 387 9500",
    "sg:postcode":"53029",
    "sg:province":"WI",
    "sg:tags":[
        "lithograph"
    ],
    "wof:name":"Shared Acqisitions Midwest LLC",
    "wof:placetype":"venue"
},
  "geometry": {"coordinates":[-88.35602900000001,43.080903],"type":"Point"}
}