{
  "type": "Feature",
  "properties": {
    "addr:full":"6211 S Ace Industrial Dr Cudahy WI 53110",
    "addr:housenumber":"6211",
    "addr:postcode":"53110",
    "addr:street":"S Ace Industrial Dr",
    "iso:country":"US",
    "sg:address":"6211 S Ace Industrial Dr",
    "sg:city":"Cudahy",
    "sg:classifiers":[
        {
            "category":"Freight",
            "type":"Transportation"
        }
    ],
    "sg:phone":"+1 414 764 0408",
    "sg:postcode":"53110",
    "sg:province":"WI",
    "sg:tags":[
        "mover"
    ],
    "wof:name":"Ace Worldwide",
    "wof:placetype":"venue"
},
  "geometry": {"coordinates":[-87.88333299999999,42.932125],"type":"Point"}
}