{
  "type": "Feature",
  "properties": {
    "addr:full":"219 N Main St Thiensville WI 53092",
    "addr:housenumber":"219",
    "addr:postcode":"53092",
    "addr:street":"N Main St",
    "iso:country":"US",
    "sg:address":"219 N Main St",
    "sg:city":"Thiensville",
    "sg:classifiers":[
        {
            "category":"Shopping",
            "subcategory":"Musical Instruments",
            "type":"Retail Goods"
        }
    ],
    "sg:phone":"+1 262 238 6530",
    "sg:postcode":"53092",
    "sg:province":"WI",
    "wof:name":"Mequon Music",
    "wof:placetype":"venue"
},
  "geometry": {"coordinates":[-87.98428800000001,43.235645],"type":"Point"}
}