{
  "type": "Feature",
  "properties": {
    "addr:full":"10437 W Innovation Dr Milwaukee WI 53226",
    "addr:housenumber":"10437",
    "addr:postcode":"53226",
    "addr:street":"W Innovation Dr",
    "iso:country":"US",
    "sg:address":"10437 W Innovation Dr",
    "sg:city":"Milwaukee",
    "sg:classifiers":[
        {
            "category":"Professional",
            "subcategory":"Advertising",
            "type":"Services"
        }
    ],
    "sg:phone":"+1 414 778 2150",
    "sg:postcode":"53226",
    "sg:province":"WI",
    "sg:tags":[
        "agency"
    ],
    "wof:name":"Brand Thirty-Three Inc",
    "wof:placetype":"venue"
},
  "geometry": {"coordinates":[-88.037644,43.041894],"type":"Point"}
}