{
  "type": "Feature",
  "properties": {
    "iso:country":"US",
    "sg:address":"2301 State Hwy 29",
    "sg:city":"Menomonie",
    "sg:classifiers":[
        {
            "category":"Government",
            "subcategory":"Office",
            "type":"Public Place"
        }
    ],
    "sg:phone":"+1 715 235 3853",
    "sg:postcode":"54751",
    "sg:province":"WI",
    "sg:tags":[
        "city"
    ],
    "wof:name":"Lucas Town Hall",
    "wof:placetype":"venue"
},
  "geometry": {"coordinates":[-91.90137799999999,44.882121],"type":"Point"}
}