{
  "type": "Feature",
  "properties": {
    "iso:country":"US",
    "sg:address":"130 Vilas Hibbard Pkwy",
    "sg:city":"Lodi",
    "sg:classifiers":[
        {
            "category":"Organizations",
            "subcategory":"Religious Organization",
            "type":"Services"
        }
    ],
    "sg:phone":"+1 608 592 4515",
    "sg:postcode":"53555",
    "sg:province":"WI",
    "wof:name":"Kenneth Schaub",
    "wof:placetype":"venue"
},
  "geometry": {"coordinates":[-89.537857,43.318909],"type":"Point"}
}