{
  "type": "Feature",
  "properties": {
    "iso:country":"US",
    "sg:address":"4802 Dakota Dr",
    "sg:city":"Madison",
    "sg:classifiers":[
        {
            "category":"Organizations",
            "subcategory":"Religious Organization",
            "type":"Services"
        }
    ],
    "sg:phone":"+1 608 663 1485",
    "sg:postcode":"53704",
    "sg:province":"WI",
    "wof:name":"Youth With A Mission",
    "wof:placetype":"venue"
},
  "geometry": {"coordinates":[-89.366649,43.145118],"type":"Point"}
}