{
  "type": "Feature",
  "properties": {
    "iso:country":"US",
    "sg:address":"6473 Co Rd H",
    "sg:city":"Athens",
    "sg:classifiers":[
        {
            "category":"Freight",
            "type":"Transportation"
        }
    ],
    "sg:phone":"+1 715 257 7799",
    "sg:postcode":"54411",
    "sg:province":"WI",
    "sg:tags":[
        "livestock",
        "hauling"
    ],
    "wof:name":"Kim Kottke Trucking",
    "wof:placetype":"venue"
},
  "geometry": {"coordinates":[-89.974245,45.057444],"type":"Point"}
}