{
  "type": "Feature",
  "properties": {
    "addr:full":"4049 Old Hwy 33 Baraboo WI 53913",
    "addr:housenumber":"4049",
    "addr:postcode":"53913",
    "addr:street":"Old Hwy 33",
    "iso:country":"US",
    "sg:address":"4049 Old Hwy 33",
    "sg:city":"Baraboo",
    "sg:classifiers":[
        {
            "category":"Retail",
            "subcategory":"Animal Services",
            "type":"Services"
        }
    ],
    "sg:phone":"+1 608 356 4701",
    "sg:postcode":"53913",
    "sg:province":"WI",
    "sg:tags":[
        "breeder",
        "horse"
    ],
    "wof:name":"Domino Stables Inc",
    "wof:placetype":"venue"
},
  "geometry": {"coordinates":[-89.782295,43.496341],"type":"Point"}
}