{
  "type": "Feature",
  "properties": {
    "iso:country":"US",
    "sg:address":"6610 US Hwy 53",
    "sg:city":"Eau Claire",
    "sg:classifiers":[
        {
            "category":"Professional",
            "subcategory":"Business Services",
            "type":"Services"
        }
    ],
    "sg:phone":"+1 715 835 0820",
    "sg:postcode":"54701",
    "sg:province":"WI",
    "sg:tags":[
        "used",
        "merchandise"
    ],
    "wof:name":"Andrews Auction Service",
    "wof:placetype":"venue"
},
  "geometry": {"coordinates":[-91.378609,44.73478],"type":"Point"}
}