{
  "type": "Feature",
  "properties": {
    "iso:country":"US",
    "sg:address":"212 Edgewood Dr",
    "sg:city":"Neenah",
    "sg:classifiers":[
        {
            "category":"Real Estate",
            "subcategory":"Real Estate Agent",
            "type":"Services"
        }
    ],
    "sg:phone":"+1 920 720 0565",
    "sg:postcode":"54956",
    "sg:province":"WI",
    "wof:name":"Re/Max",
    "wof:placetype":"venue"
},
  "geometry": {"coordinates":[-88.460396,44.16103],"type":"Point"}
}