{
  "type": "Feature",
  "properties": {
    "iso:country":"US",
    "sg:address":"2323 S Lincoln Memorial Dr",
    "sg:city":"Milwaukee",
    "sg:classifiers":[
        {
            "category":"Professional",
            "subcategory":"Business Services",
            "type":"Services"
        }
    ],
    "sg:phone":"+1 414 489 7961",
    "sg:postcode":"53207",
    "sg:province":"WI",
    "wof:name":"Lake Express",
    "wof:placetype":"venue"
},
  "geometry": {"coordinates":[-87.888648,43.000467],"type":"Point"}
}