{
  "type": "Feature",
  "properties": {
    "iso:country":"US",
    "sg:address":"11566 Waite Ln",
    "sg:city":"Crandon",
    "sg:classifiers":[
        {
            "category":"Shopping",
            "subcategory":"Gifts & Souvenirs",
            "type":"Retail Goods"
        }
    ],
    "sg:phone":"+1 715 478 4688",
    "sg:postcode":"54520",
    "sg:province":"WI",
    "wof:name":"Promotion Specialty Co",
    "wof:placetype":"venue"
},
  "geometry": {"coordinates":[-89.016622,45.589276],"type":"Point"}
}