{
  "type": "Feature",
  "properties": {
    "iso:country":"US",
    "sg:address":"5890 Monches Rd",
    "sg:city":"Colgate",
    "sg:classifiers":[
        {
            "category":"Home & Garden",
            "subcategory":"Garden Supply",
            "type":"Retail Goods"
        }
    ],
    "sg:phone":"+1 262 966 2787",
    "sg:postcode":"53017",
    "sg:province":"WI",
    "sg:tags":[
        "nurseryman"
    ],
    "wof:name":"Monches Farm",
    "wof:placetype":"venue"
},
  "geometry": {"coordinates":[-88.328278,43.199998],"type":"Point"}
}