{
  "type": "Feature",
  "properties": {
    "iso:country":"US",
    "sg:address":"143 N Main St",
    "sg:city":"Pardeeville",
    "sg:classifiers":[
        {
            "category":"Health Services",
            "subcategory":"Clinic",
            "type":"Services"
        }
    ],
    "sg:phone":"+1 608 429 3439",
    "sg:postcode":"53954",
    "sg:province":"WI",
    "sg:tags":[
        "home"
    ],
    "wof:name":"South Central Respite Inc",
    "wof:placetype":"venue"
},
  "geometry": {"coordinates":[-89.300173,43.537402],"type":"Point"}
}