{
  "type": "Feature",
  "properties": {
    "iso:country":"US",
    "sg:address":"105 McKay Ave",
    "sg:city":"Spring Valley",
    "sg:classifiers":[
        {
            "category":"Wholesale",
            "subcategory":"Medical Equipment & Supplies",
            "type":"Manufacturing & Wholesale Goods"
        }
    ],
    "sg:phone":"+1 715 778 5725",
    "sg:postcode":"54767",
    "sg:province":"WI",
    "sg:tags":[
        "veterinary"
    ],
    "wof:name":"Elm Valley Veterinary Clinic",
    "wof:placetype":"venue"
},
  "geometry": {"coordinates":[-92.238574,44.847781],"type":"Point"}
}