{
  "type": "Feature",
  "properties": {
    "iso:country":"US",
    "sg:address":"5219 Co Rd T",
    "sg:city":"Princeton",
    "sg:classifiers":[
        {
            "category":"Building & Trades",
            "subcategory":"Cleaning & Sanitation",
            "type":"Services"
        }
    ],
    "sg:phone":"+1 920 295 4457",
    "sg:postcode":"54968",
    "sg:province":"WI",
    "sg:tags":[
        "maintenance"
    ],
    "wof:name":"Clear Reflections",
    "wof:placetype":"venue"
},
  "geometry": {"coordinates":[-89.14554099999999,43.819815],"type":"Point"}
}