{
  "type": "Feature",
  "properties": {
    "iso:country":"US",
    "sg:address":"4314 N Oakland Ave",
    "sg:city":"Milwaukee",
    "sg:classifiers":[
        {
            "category":"Shopping",
            "subcategory":"Optical Goods",
            "type":"Retail Goods"
        },
        {
            "category":"Shopping",
            "subcategory":"Optician",
            "type":"Retail Goods"
        },
        {
            "category":"Health Services",
            "subcategory":"Optometrist",
            "type":"Services"
        }
    ],
    "sg:phone":"+1 414 481 0868",
    "sg:postcode":"53211",
    "sg:province":"WI",
    "sg:tags":[
        "eyeglass"
    ],
    "sg:website":"http://www.eyezunique.com",
    "wof:name":"Eyez Boutique",
    "wof:placetype":"venue"
},
  "geometry": {"coordinates":[-87.887441,43.094727],"type":"Point"}
}