{
  "type": "Feature",
  "properties": {
    "iso:country":"US",
    "sg:address":"5601 Hammersley Rd",
    "sg:city":"Madison",
    "sg:classifiers":[
        {
            "category":"Shopping",
            "type":"Retail Goods"
        }
    ],
    "sg:phone":"+1 608 278 1307",
    "sg:postcode":"53711",
    "sg:province":"WI",
    "sg:tags":[
        "equipment",
        "telephone",
        "supply"
    ],
    "wof:name":"Badger Telecom & Sounds",
    "wof:placetype":"venue"
},
  "geometry": {"coordinates":[-89.475782,43.039074],"type":"Point"}
}