{
  "type": "Feature",
  "properties": {
    "iso:country":"US",
    "sg:address":"3755 Rolling Meadows Rd",
    "sg:city":"Oneida",
    "sg:classifiers":[
        {
            "category":"Real Estate",
            "subcategory":"Real Estate Operator",
            "type":"Services"
        }
    ],
    "sg:phone":"+1 920 869 3498",
    "sg:postcode":"54155",
    "sg:province":"WI",
    "sg:tags":[
        "property",
        "lessor"
    ],
    "wof:name":"Baf Real Estate LLC",
    "wof:placetype":"venue"
},
  "geometry": {"coordinates":[-88.160235,44.52777],"type":"Point"}
}