{
  "type": "Feature",
  "properties": {
    "iso:country":"US",
    "sg:address":"2525 Co Rd Jj",
    "sg:city":"Spring Green",
    "sg:classifiers":[
        {
            "category":"Airport",
            "type":"Transportation"
        }
    ],
    "sg:phone":"+1 608 583 2130",
    "sg:postcode":"53588",
    "sg:province":"WI",
    "wof:name":"Cardinal Airport Hanger",
    "wof:placetype":"venue"
},
  "geometry": {"coordinates":[-90.17850199999999,43.213486],"type":"Point"}
}