{
  "type": "Feature",
  "properties": {
    "iso:country":"US",
    "sg:address":"5126 W Howard Ave",
    "sg:city":"Milwaukee",
    "sg:classifiers":[
        {
            "category":"Restaurant",
            "type":"Food & Drink"
        }
    ],
    "sg:phone":"+1 414 546 4976",
    "sg:postcode":"53220",
    "sg:province":"WI",
    "sg:tags":[
        "eating"
    ],
    "wof:name":"Gyro King",
    "wof:placetype":"venue"
},
  "geometry": {"coordinates":[-87.97907600000001,42.973985],"type":"Point"}
}