{
  "type": "Feature",
  "properties": {
    "iso:country":"US",
    "sg:address":"6123 Truax Ln",
    "sg:city":"Eau Claire",
    "sg:classifiers":[
        {
            "category":"Restaurant",
            "type":"Food & Drink"
        }
    ],
    "sg:menulink":"http://www.allmenus.com/wi/eau-claire/145456-subway/menu/",
    "sg:phone":"+1 715 874 6945",
    "sg:postcode":"54703",
    "sg:province":"WI",
    "sg:tags":[
        "american",
        "sandwich"
    ],
    "wof:name":"Subway",
    "wof:placetype":"venue"
},
  "geometry": {"coordinates":[-91.594352,44.842979],"type":"Point"}
}