{
  "type": "Feature",
  "properties": {
    "iso:country":"US",
    "sg:address":"1476 Willow Dr",
    "sg:city":"Delafield",
    "sg:classifiers":[
        {
            "category":"Wholesale",
            "subcategory":"Durable Goods & Equipment",
            "type":"Manufacturing & Wholesale Goods"
        }
    ],
    "sg:phone":"+1 262 646 5271",
    "sg:postcode":"53018",
    "sg:province":"WI",
    "sg:tags":[
        "exporter"
    ],
    "wof:name":"Intertecno",
    "wof:placetype":"venue"
},
  "geometry": {"coordinates":[-88.417692,43.066215],"type":"Point"}
}