{
  "type": "Feature",
  "properties": {
    "iso:country":"US",
    "sg:address":"23 S Wisconsin St",
    "sg:city":"Elkhorn",
    "sg:classifiers":[
        {
            "category":"Professional",
            "subcategory":"Employment Agencies",
            "type":"Services"
        }
    ],
    "sg:phone":"+1 262 743 2121",
    "sg:postcode":"53121",
    "sg:province":"WI",
    "sg:tags":[
        "opportunity"
    ],
    "wof:name":"Staff Force Inc",
    "wof:placetype":"venue"
},
  "geometry": {"coordinates":[-88.543458,42.671542],"type":"Point"}
}