{
  "type": "Feature",
  "properties": {
    "iso:country":"US",
    "sg:address":"625 Browns Lake Dr",
    "sg:city":"Burlington",
    "sg:classifiers":[
        {
            "category":"Retail",
            "subcategory":"Funeral Services",
            "type":"Services"
        }
    ],
    "sg:phone":"+1 262 763 3541",
    "sg:postcode":"53105",
    "sg:province":"WI",
    "sg:tags":[
        "cemetery"
    ],
    "wof:name":"McCarthy-Koenig-Daniels Funeral Home",
    "wof:placetype":"venue"
},
  "geometry": {"coordinates":[-88.26300000000001,42.680698],"type":"Point"}
}