{
  "type": "Feature",
  "properties": {
    "addr:full":"2727 18th Ave Kenosha WI 53140",
    "addr:housenumber":"2727",
    "addr:postcode":"53140",
    "addr:street":"18Th Ave",
    "iso:country":"US",
    "sg:address":"2727 18th Ave",
    "sg:city":"Kenosha",
    "sg:classifiers":[
        {
            "category":"Shopping",
            "subcategory":"Catalog Store",
            "type":"Retail Goods"
        }
    ],
    "sg:phone":"+1 262 857 3587",
    "sg:postcode":"53140",
    "sg:province":"WI",
    "sg:tags":[
        "a",
        "operates",
        "as",
        "book",
        "mail",
        "order",
        "concern"
    ],
    "wof:name":"Practcal Pblctns/Prctical Pdts",
    "wof:placetype":"venue"
},
  "geometry": {"coordinates":[-87.831239,42.637308],"type":"Point"}
}