{
  "type": "Feature",
  "properties": {
    "iso:country":"US",
    "sg:address":"2012 Dueholm Dr",
    "sg:city":"Milltown",
    "sg:classifiers":[
        {
            "category":"Building & Trades",
            "subcategory":"Landscaping Services",
            "type":"Services"
        }
    ],
    "sg:phone":"+1 715 857 5471",
    "sg:postcode":"54858",
    "sg:province":"WI",
    "sg:tags":[
        "tree"
    ],
    "wof:name":"George J Haines",
    "wof:placetype":"venue"
},
  "geometry": {"coordinates":[-92.37751799999999,45.499845],"type":"Point"}
}