{
  "type": "Feature",
  "properties": {
    "addr:full":"403 Elm St Marshfield WI 54449",
    "addr:housenumber":"403",
    "addr:postcode":"54449",
    "addr:street":"Elm St",
    "iso:country":"US",
    "sg:address":"403 Elm St",
    "sg:city":"Marshfield",
    "sg:classifiers":[
        {
            "category":"Government",
            "subcategory":"Office",
            "type":"Public Place"
        }
    ],
    "sg:phone":"+1 715 389 1338",
    "sg:postcode":"54449",
    "sg:province":"WI",
    "sg:tags":[
        "city"
    ],
    "wof:name":"Mc Millan Town Hall",
    "wof:placetype":"venue"
},
  "geometry": {"coordinates":[-90.13970999999999,44.728333],"type":"Point"}
}