{
  "type": "Feature",
  "properties": {
    "addr:full":"37201 87th St Burlington WI 53105",
    "addr:housenumber":"37201",
    "addr:postcode":"53105",
    "addr:street":"87Th St",
    "iso:country":"US",
    "sg:address":"37201 87th St",
    "sg:city":"Burlington",
    "sg:classifiers":[
        {
            "category":"Recreation",
            "type":"Entertainment"
        }
    ],
    "sg:phone":"+1 262 537 4011",
    "sg:postcode":"53105",
    "sg:province":"WI",
    "sg:tags":[
        "club",
        "membership"
    ],
    "wof:name":"Twin Lakes Industry",
    "wof:placetype":"venue"
},
  "geometry": {"coordinates":[-88.260824,42.549235],"type":"Point"}
}