{
  "type": "Feature",
  "properties": {
    "addr:full":"5711 Willow Rd Plymouth WI 53073",
    "addr:housenumber":"5711",
    "addr:postcode":"53073",
    "addr:street":"Willow Rd",
    "iso:country":"US",
    "sg:address":"5711 Willow Rd",
    "sg:city":"Plymouth",
    "sg:classifiers":[
        {
            "category":"Professional",
            "type":"Services"
        }
    ],
    "sg:phone":"+1 920 893 3117",
    "sg:postcode":"53073",
    "sg:province":"WI",
    "sg:tags":[
        "establishment"
    ],
    "wof:name":"SBA Towers Inc",
    "wof:placetype":"venue"
},
  "geometry": {"coordinates":[-87.921233,43.746666],"type":"Point"}
}