{
  "type": "Feature",
  "properties": {
    "iso:country":"US",
    "sg:address":"1590 Fairview Ln",
    "sg:city":"Fort Atkinson",
    "sg:classifiers":[
        {
            "category":"Organizations",
            "subcategory":"Membership Organization",
            "type":"Services"
        }
    ],
    "sg:phone":"+1 920 563 8677",
    "sg:postcode":"53538",
    "sg:province":"WI",
    "wof:name":"National Niemann Pick Dis",
    "wof:placetype":"venue"
},
  "geometry": {"coordinates":[-88.847863,42.899742],"type":"Point"}
}