{
  "type": "Feature",
  "properties": {
    "addr:full":"115 E Main St Mt Horeb WI 53572",
    "addr:housenumber":"115",
    "addr:postcode":"53572",
    "addr:street":"E Main St",
    "iso:country":"US",
    "sg:address":"115 E Main St",
    "sg:city":"Mt Horeb",
    "sg:classifiers":[
        {
            "category":"Personal",
            "subcategory":"Barber",
            "type":"Services"
        }
    ],
    "sg:phone":"+1 608 437 5157",
    "sg:postcode":"53572",
    "sg:province":"WI",
    "sg:tags":[
        "shop"
    ],
    "wof:name":"Village Barber",
    "wof:placetype":"venue"
},
  "geometry": {"coordinates":[-89.73956,43.008583],"type":"Point"}
}