{
  "type": "Feature",
  "properties": {
    "iso:country":"US",
    "sg:address":"5890 Hearthstone Dr",
    "sg:city":"Appleton",
    "sg:classifiers":[
        {
            "category":"Professional",
            "subcategory":"Computer Services",
            "type":"Services"
        }
    ],
    "sg:phone":"+1 920 734 7324",
    "sg:postcode":"54915",
    "sg:province":"WI",
    "sg:tags":[
        "consultant",
        "designer",
        "related"
    ],
    "sg:website":"www.jungenconsulting.com",
    "wof:name":"Jungen Consulting Inc",
    "wof:placetype":"venue"
},
  "geometry": {"coordinates":[-88.332663,44.237657],"type":"Point"}
}