{
  "type": "Feature",
  "properties": {
    "iso:country":"US",
    "sg:address":"39 N Washington St",
    "sg:city":"Elkhorn",
    "sg:classifiers":[
        {
            "category":"Health Services",
            "subcategory":"Doctor",
            "type":"Services"
        }
    ],
    "sg:phone":"+1 262 723 7761",
    "sg:postcode":"53121",
    "sg:province":"WI",
    "sg:tags":[
        "medical"
    ],
    "wof:name":"Bridges To Health Inc",
    "wof:placetype":"venue"
},
  "geometry": {"coordinates":[-88.542247,42.672897],"type":"Point"}
}