{
  "type": "Feature",
  "properties": {
    "iso:country":"US",
    "sg:address":"2670 Packerland Dr",
    "sg:city":"Green Bay",
    "sg:classifiers":[
        {
            "category":"Professional",
            "subcategory":"Engineering",
            "type":"Services"
        },
        {
            "category":"Professional",
            "subcategory":"Management & Consulting",
            "type":"Services"
        }
    ],
    "sg:phone":"+1 920 490 7773",
    "sg:postcode":"54313",
    "sg:province":"WI",
    "sg:tags":[
        "consultant",
        "engineer"
    ],
    "wof:name":"Packerland Engineering Inc",
    "wof:placetype":"venue"
},
  "geometry": {"coordinates":[-88.10897900000001,44.488627],"type":"Point"}
}