{
  "type": "Feature",
  "properties": {
    "iso:country":"US",
    "sg:address":"1616 John Ave",
    "sg:city":"Superior",
    "sg:classifiers":[
        {
            "category":"Travel",
            "subcategory":"Hotels & Motels",
            "type":"Entertainment"
        }
    ],
    "sg:phone":"+1 715 394 7277",
    "sg:postcode":"54880",
    "sg:province":"WI",
    "sg:tags":[
        "operation"
    ],
    "wof:name":"Raspberry Inn",
    "wof:placetype":"venue"
},
  "geometry": {"coordinates":[-92.100864,46.718342],"type":"Point"}
}