{
  "type": "Feature",
  "properties": {
    "iso:country":"US",
    "sg:address":"5186 Ripple Ave",
    "sg:city":"Oshkosh",
    "sg:classifiers":[
        {
            "category":"Freight",
            "type":"Transportation"
        }
    ],
    "sg:phone":"+1 920 589 5551",
    "sg:postcode":"54904",
    "sg:province":"WI",
    "sg:tags":[
        "distance",
        "long",
        "trucking"
    ],
    "wof:name":"Tichonchik Paul A Trucking",
    "wof:placetype":"venue"
},
  "geometry": {"coordinates":[-88.65836299999999,43.967407],"type":"Point"}
}