{
  "type": "Feature",
  "properties": {
    "addr:full":"27984 Spiral Rd Richland Center WI 53581",
    "addr:postcode":"27984;53581",
    "addr:street":"Spiral Rd",
    "iso:country":"US",
    "sg:address":"27984 Spiral Rd",
    "sg:city":"Richland Center",
    "sg:classifiers":[
        {
            "category":"Retail",
            "subcategory":"Repair Shop",
            "type":"Services"
        }
    ],
    "sg:phone":"+1 608 585 4262",
    "sg:postcode":"53581",
    "sg:province":"WI",
    "sg:tags":[
        "equipment",
        "industrial",
        "supply"
    ],
    "wof:name":"Henning's Equipment Sales",
    "wof:placetype":"venue"
},
  "geometry": {"coordinates":[-90.31097800000001,43.345075],"type":"Point"}
}