{
  "type": "Feature",
  "properties": {
    "iso:country":"US",
    "sg:address":"703 Squirrel Ln",
    "sg:city":"Marathon",
    "sg:classifiers":[
        {
            "category":"Building & Trades",
            "subcategory":"Cleaning & Sanitation",
            "type":"Services"
        }
    ],
    "sg:phone":"+1 715 359 5359",
    "sg:postcode":"54448",
    "sg:province":"WI",
    "sg:tags":[
        "maintenance"
    ],
    "wof:name":"Jean M Schulrud",
    "wof:placetype":"venue"
},
  "geometry": {"coordinates":[-89.740155,44.889754],"type":"Point"}
}