{
  "type": "Feature",
  "properties": {
    "addr:full":"133 S 76th St Milwaukee WI 53214",
    "addr:housenumber":"133",
    "addr:postcode":"53214",
    "addr:street":"S 76Th St",
    "iso:country":"US",
    "sg:address":"133 S 76th St",
    "sg:city":"Milwaukee",
    "sg:classifiers":[
        {
            "category":"Building & Trades",
            "subcategory":"Plumbing",
            "type":"Services"
        }
    ],
    "sg:phone":"+1 414 771 7811",
    "sg:postcode":"53214",
    "sg:province":"WI",
    "sg:tags":[
        "plumbing",
        "contractor"
    ],
    "wof:name":"Martin Plumbing & Heating",
    "wof:placetype":"venue"
},
  "geometry": {"coordinates":[-88.007352,43.030905],"type":"Point"}
}