{
  "type": "Feature",
  "properties": {
    "addr:full":"206 Liberty St Deerfield WI 53531",
    "addr:housenumber":"206",
    "addr:postcode":"53531",
    "addr:street":"Liberty St",
    "iso:country":"US",
    "sg:address":"206 Liberty St",
    "sg:city":"Deerfield",
    "sg:classifiers":[
        {
            "category":"Utilities",
            "subcategory":"Refuse",
            "type":"Services"
        },
        {
            "category":"Wholesale",
            "subcategory":"Scrap",
            "type":"Manufacturing & Wholesale Goods"
        }
    ],
    "sg:phone":"+1 608 764 5358",
    "sg:postcode":"53531",
    "sg:province":"WI",
    "sg:tags":[
        "recycling",
        "material",
        "center",
        "system"
    ],
    "wof:name":"J & S Recycling & Surplus",
    "wof:placetype":"venue"
},
  "geometry": {"coordinates":[-89.080606,43.051934],"type":"Point"}
}