{
  "type": "Feature",
  "properties": {
    "iso:country":"US",
    "sg:address":"627 S Cambridge St",
    "sg:city":"Wautoma",
    "sg:classifiers":[
        {
            "category":"Home & Garden",
            "subcategory":"Garden Supply",
            "type":"Retail Goods"
        }
    ],
    "sg:phone":"+1 920 787 7229",
    "sg:postcode":"54982",
    "sg:province":"WI",
    "wof:name":"Grimms Tree Farms Inc",
    "wof:placetype":"venue"
},
  "geometry": {"coordinates":[-89.297389,44.06804],"type":"Point"}
}