{
  "type": "Feature",
  "properties": {
    "iso:country":"US",
    "sg:address":"6085 Twin Lane Rd",
    "sg:city":"Marshall",
    "sg:classifiers":[
        {
            "category":"Building & Trades",
            "subcategory":"Construction",
            "type":"Services"
        }
    ],
    "sg:phone":"+1 608 206 7942",
    "sg:postcode":"53559",
    "sg:province":"WI",
    "sg:tags":[
        "excavating",
        "contractor"
    ],
    "wof:name":"Keyes Trucking & Excavating",
    "wof:placetype":"venue"
},
  "geometry": {"coordinates":[-89.147337,43.178737],"type":"Point"}
}