{
  "type": "Feature",
  "properties": {
    "addr:full":"636 Milwaukee St Delafield WI 53018",
    "addr:housenumber":"636",
    "addr:postcode":"53018",
    "addr:street":"Milwaukee St",
    "iso:country":"US",
    "sg:address":"636 Milwaukee St",
    "sg:city":"Delafield",
    "sg:classifiers":[
        {
            "category":"Personal",
            "subcategory":"Beauty Salon",
            "type":"Services"
        }
    ],
    "sg:phone":"+1 262 646 5535",
    "sg:postcode":"53018",
    "sg:province":"WI",
    "wof:name":"Creative Flair Salon",
    "wof:placetype":"venue"
},
  "geometry": {"coordinates":[-88.40388799999999,43.061694],"type":"Point"}
}