{
  "type": "Feature",
  "properties": {
    "iso:country":"US",
    "sg:address":"2220 Donegal Ct",
    "sg:city":"Hudson",
    "sg:classifiers":[
        {
            "category":"Professional",
            "subcategory":"Research",
            "type":"Services"
        }
    ],
    "sg:phone":"+1 715 386 5690",
    "sg:postcode":"54016",
    "sg:province":"WI",
    "sg:tags":[
        "organization",
        "noncommercial"
    ],
    "wof:name":"Gv Consulting LLC",
    "wof:placetype":"venue"
},
  "geometry": {"coordinates":[-92.726882,44.985568],"type":"Point"}
}