{
  "type": "Feature",
  "properties": {
    "iso:country":"US",
    "sg:address":"5590 Otto Kerl Rd",
    "sg:city":"Cross Plains",
    "sg:classifiers":[
        {
            "category":"Real Estate",
            "subcategory":"Real Estate Operator",
            "type":"Services"
        }
    ],
    "sg:phone":"+1 608 798 2486",
    "sg:postcode":"53528",
    "sg:province":"WI",
    "sg:tags":[
        "property",
        "lessor"
    ],
    "wof:name":"Thomas Breuning",
    "wof:placetype":"venue"
},
  "geometry": {"coordinates":[-89.62357,43.158444],"type":"Point"}
}