{
  "type": "Feature",
  "properties": {
    "iso:country":"US",
    "sg:address":"120 Alfred St",
    "sg:city":"Athens",
    "sg:classifiers":[
        {
            "category":"Bars & Pubs",
            "type":"Food & Drink"
        }
    ],
    "sg:phone":"+1 715 257 1172",
    "sg:postcode":"54411",
    "sg:province":"WI",
    "sg:tags":[
        "drinking"
    ],
    "wof:name":"Gary & Sue's Hang Out",
    "wof:placetype":"venue"
},
  "geometry": {"coordinates":[-90.073628,45.035032],"type":"Point"}
}