{
  "type": "Feature",
  "properties": {
    "iso:country":"US",
    "sg:address":"6409 Odana Rd",
    "sg:city":"Madison",
    "sg:classifiers":[
        {
            "category":"Banks & Credit Unions",
            "subcategory":"Bank",
            "type":"Services"
        }
    ],
    "sg:phone":"+1 608 278 7710",
    "sg:postcode":"53719",
    "sg:province":"WI",
    "sg:tags":[
        "mortgage",
        "loan",
        "broker",
        "real estate"
    ],
    "wof:name":"Home Mortgage Solutions",
    "wof:placetype":"venue"
},
  "geometry": {"coordinates":[-89.4901,43.05479],"type":"Point"}
}