{
  "type": "Feature",
  "properties": {
    "addr:full":"1102 Grand Ave Wausau WI 54403",
    "addr:housenumber":"1102",
    "addr:postcode":"54403",
    "addr:street":"Grand Ave",
    "iso:country":"US",
    "sg:address":"1102 Grand Ave",
    "sg:city":"Wausau",
    "sg:classifiers":[
        {
            "category":"Real Estate",
            "subcategory":"Real Estate Operator",
            "type":"Services"
        }
    ],
    "sg:phone":"+1 715 848 1354",
    "sg:postcode":"54403",
    "sg:province":"WI",
    "sg:tags":[
        "apartment"
    ],
    "wof:name":"Easy Living Management",
    "wof:placetype":"venue"
},
  "geometry": {"coordinates":[-89.620783,44.946194],"type":"Point"}
}