{
  "type": "Feature",
  "properties": {
    "iso:country":"US",
    "sg:address":"5119 Hillwind Rd",
    "sg:city":"Plymouth",
    "sg:classifiers":[
        {
            "category":"Shopping",
            "subcategory":"Used Merchandise",
            "type":"Retail Goods"
        }
    ],
    "sg:phone":"+1 920 893 5442",
    "sg:postcode":"53073",
    "sg:province":"WI",
    "wof:name":"Traders Quest",
    "wof:placetype":"venue"
},
  "geometry": {"coordinates":[-87.980996,43.724095],"type":"Point"}
}