{
  "type": "Feature",
  "properties": {
    "iso:country":"US",
    "sg:address":"849 Warsaw St",
    "sg:city":"Menasha",
    "sg:classifiers":[
        {
            "category":"Banks & Credit Unions",
            "subcategory":"Investment Brokerage",
            "type":"Services"
        },
        {
            "category":"Banks & Credit Unions",
            "subcategory":"Bank",
            "type":"Services"
        }
    ],
    "sg:phone":"+1 920 727 0400",
    "sg:postcode":"54952",
    "sg:province":"WI",
    "sg:tags":[
        "consultant",
        "planning",
        "financial",
        "mortgage"
    ],
    "wof:name":"Financial Network Investment C",
    "wof:placetype":"venue"
},
  "geometry": {"coordinates":[-88.444388,44.214223],"type":"Point"}
}