{
  "type": "Feature",
  "properties": {
    "iso:country":"US",
    "sg:address":"729 N Webb Ave",
    "sg:city":"Reedsburg",
    "sg:classifiers":[
        {
            "category":"Education",
            "subcategory":"School",
            "type":"Public Place"
        }
    ],
    "sg:phone":"+1 608 524 6529",
    "sg:postcode":"53959",
    "sg:province":"WI",
    "wof:name":"Reedsburg District School",
    "wof:placetype":"venue"
},
  "geometry": {"coordinates":[-90.009674,43.541295],"type":"Point"}
}