{
  "type": "Feature",
  "properties": {
    "iso:country":"US",
    "sg:address":"6005 120th Ave",
    "sg:city":"Kenosha",
    "sg:classifiers":[
        {
            "category":"Banks & Credit Unions",
            "subcategory":"Investment Brokerage",
            "type":"Services"
        }
    ],
    "sg:phone":"+1 262 857 9922",
    "sg:postcode":"53142",
    "sg:province":"WI",
    "sg:tags":[
        "tape",
        "video",
        "sale",
        "dvds-rental"
    ],
    "sg:website":"http://www.wisconsinshottestvideos.com",
    "wof:name":"Superb Video",
    "wof:placetype":"venue"
},
  "geometry": {"coordinates":[-87.95236800000001,42.58066],"type":"Point"}
}