{
  "type": "Feature",
  "properties": {
    "iso:country":"US",
    "sg:address":"4127 N Richards St",
    "sg:city":"Milwaukee",
    "sg:classifiers":[
        {
            "category":"Organizations",
            "subcategory":"Religious Organization",
            "type":"Services"
        }
    ],
    "sg:phone":"+1 414 332 3456",
    "sg:postcode":"53212",
    "sg:province":"WI",
    "sg:tags":[
        "church"
    ],
    "wof:name":"Bride Of Christ Assembly-God",
    "wof:placetype":"venue"
},
  "geometry": {"coordinates":[-87.907293,43.092368],"type":"Point"}
}