{
  "type": "Feature",
  "properties": {
    "iso:country":"US",
    "sg:address":"411 E Leffler St",
    "sg:city":"Dodgeville",
    "sg:classifiers":[
        {
            "category":"Shopping",
            "type":"Retail Goods"
        }
    ],
    "sg:phone":"+1 608 935 3566",
    "sg:postcode":"53533",
    "sg:province":"WI",
    "sg:tags":[
        "monument"
    ],
    "wof:name":"Dodgeville Monument Co",
    "wof:placetype":"venue"
},
  "geometry": {"coordinates":[-90.125619,42.974427],"type":"Point"}
}