{
  "type": "Feature",
  "properties": {
    "iso:country":"US",
    "sg:address":"8700 Kent Rd",
    "sg:city":"Beaver Dam",
    "sg:classifiers":[
        {
            "category":"Building & Trades",
            "subcategory":"Construction",
            "type":"Services"
        }
    ],
    "sg:phone":"+1 920 887 9317",
    "sg:postcode":"53955",
    "sg:province":"WI",
    "sg:tags":[
        "excavating",
        "contractor"
    ],
    "wof:name":"Michael Schmitt Construction",
    "wof:placetype":"venue"
},
  "geometry": {"coordinates":[-89.432462,43.408625],"type":"Point"}
}