{
  "type": "Feature",
  "properties": {
    "iso:country":"US",
    "sg:address":"1850 Dousman St",
    "sg:city":"Green Bay",
    "sg:classifiers":[
        {
            "category":"Freight",
            "type":"Transportation"
        }
    ],
    "sg:phone":"+1 920 494 7695",
    "sg:postcode":"54303",
    "sg:province":"WI",
    "sg:tags":[
        "operator",
        "local",
        "trucking"
    ],
    "wof:name":"Real Schreiber Trucking",
    "wof:placetype":"venue"
},
  "geometry": {"coordinates":[-88.071758,44.536914],"type":"Point"}
}