{
  "type": "Feature",
  "properties": {
    "addr:full":"410 Douglas Ave Montello WI 53949",
    "addr:housenumber":"410",
    "addr:postcode":"53949",
    "addr:street":"Douglas Ave",
    "iso:country":"US",
    "sg:address":"410 Douglas Ave",
    "sg:city":"Montello",
    "sg:classifiers":[
        {
            "category":"Manufacturing",
            "subcategory":"Tools & Machinery",
            "type":"Manufacturing & Wholesale Goods"
        }
    ],
    "sg:phone":"+1 608 297 2299",
    "sg:postcode":"53949",
    "sg:province":"WI",
    "sg:tags":[
        "machine",
        "shop"
    ],
    "wof:name":"Component Manufacturing Corp",
    "wof:placetype":"venue"
},
  "geometry": {"coordinates":[-89.32642300000001,43.799713],"type":"Point"}
}