{
  "type": "Feature",
  "properties": {
    "iso:country":"US",
    "sg:address":"2950 Universal Ct",
    "sg:city":"Oshkosh",
    "sg:classifiers":[
        {
            "category":"Banks & Credit Unions",
            "subcategory":"Investment Brokerage",
            "type":"Services"
        }
    ],
    "sg:phone":"+1 920 231 4646",
    "sg:postcode":"54904",
    "sg:province":"WI",
    "sg:tags":[
        "consultant",
        "planning",
        "financial"
    ],
    "sg:website":"www.nolazymoney.com",
    "wof:name":"Fletcher Financial Network",
    "wof:placetype":"venue"
},
  "geometry": {"coordinates":[-88.58914,43.984191],"type":"Point"}
}