{
  "type": "Feature",
  "properties": {
    "iso:country":"US",
    "sg:address":"1725 W River Dr W",
    "sg:city":"Stevens Point",
    "sg:classifiers":[
        {
            "category":"Government",
            "subcategory":"Office",
            "type":"Public Place"
        }
    ],
    "sg:phone":"+1 715 343 7142",
    "sg:postcode":"54481",
    "sg:province":"WI",
    "sg:tags":[
        "village"
    ],
    "wof:name":"Stevens Point Housing Programs",
    "wof:placetype":"venue"
},
  "geometry": {"coordinates":[-89.64060000000001,44.68175],"type":"Point"}
}