{
  "type": "Feature",
  "properties": {
    "iso:country":"US",
    "sg:address":"2354 Commonwealth Ave",
    "sg:city":"Madison",
    "sg:classifiers":[
        {
            "category":"Professional",
            "subcategory":"Secretarial Services",
            "type":"Services"
        }
    ],
    "sg:phone":"+1 608 233 0061",
    "sg:postcode":"53711",
    "sg:province":"WI",
    "sg:tags":[
        "reporting"
    ],
    "wof:name":"Simplyshop Co LLC",
    "wof:placetype":"venue"
},
  "geometry": {"coordinates":[-89.426211,43.062157],"type":"Point"}
}