{
  "type": "Feature",
  "properties": {
    "iso:country":"US",
    "sg:address":"5425 Oakdale Ave",
    "sg:city":"Cashton",
    "sg:classifiers":[
        {
            "category":"Shopping",
            "subcategory":"Gifts & Souvenirs",
            "type":"Retail Goods"
        }
    ],
    "sg:phone":"+1 608 452 3375",
    "sg:postcode":"54619",
    "sg:province":"WI",
    "wof:name":"Tasha & Friends",
    "wof:placetype":"venue"
},
  "geometry": {"coordinates":[-90.871348,43.742014],"type":"Point"}
}