{
  "type": "Feature",
  "properties": {
    "iso:country":"US",
    "sg:address":"728 N 4th St",
    "sg:city":"Manitowoc",
    "sg:classifiers":[
        {
            "category":"Professional",
            "type":"Services"
        }
    ],
    "sg:phone":"+1 920 682 0907",
    "sg:postcode":"54220",
    "sg:province":"WI",
    "wof:name":"Close To Home",
    "wof:placetype":"venue"
},
  "geometry": {"coordinates":[-87.652142,44.101722],"type":"Point"}
}