{
  "type": "Feature",
  "properties": {
    "iso:country":"US",
    "sg:address":"5633 White Lake Rd",
    "sg:city":"Weyauwega",
    "sg:classifiers":[
        {
            "category":"Manufacturing",
            "subcategory":"Metals",
            "type":"Manufacturing & Wholesale Goods"
        }
    ],
    "sg:phone":"+1 920 867 3560",
    "sg:postcode":"54983",
    "sg:province":"WI",
    "sg:tags":[
        "die",
        "aluminum",
        "mfg"
    ],
    "wof:name":"A & B Diecasting",
    "wof:placetype":"venue"
},
  "geometry": {"coordinates":[-88.944844,44.351666],"type":"Point"}
}