{
  "type": "Feature",
  "properties": {
    "iso:country":"US",
    "sg:address":"445 E Oklahoma Ave",
    "sg:city":"Milwaukee",
    "sg:classifiers":[
        {
            "category":"Retail",
            "subcategory":"Auto Rental",
            "type":"Services"
        }
    ],
    "sg:phone":"+1 414 481 4274",
    "sg:postcode":"53207",
    "sg:province":"WI",
    "sg:tags":[
        "truck"
    ],
    "wof:name":"Bush Leasing",
    "wof:placetype":"venue"
},
  "geometry": {"coordinates":[-87.903189,42.988226],"type":"Point"}
}