{
  "type": "Feature",
  "properties": {
    "addr:full":"155 US Hwy 63 Clear Lake WI 54005",
    "addr:housenumber":"155",
    "addr:postcode":"54005",
    "addr:street":"Us Hwy 63",
    "iso:country":"US",
    "sg:address":"155 US Hwy 63",
    "sg:city":"Clear Lake",
    "sg:classifiers":[
        {
            "category":"Autos & Motor Vehicles",
            "subcategory":"Automobile Sales",
            "type":"Retail Goods"
        }
    ],
    "sg:phone":"+1 715 263 2244",
    "sg:postcode":"54005",
    "sg:province":"WI",
    "sg:tags":[
        "supply"
    ],
    "wof:name":"Lakeland Power Sports Inc",
    "wof:placetype":"venue"
},
  "geometry": {"coordinates":[-92.284464,45.223672],"type":"Point"}
}