{
  "type": "Feature",
  "properties": {
    "iso:country":"US",
    "sg:address":"2614 State Rd 64",
    "sg:city":"Glenwood City",
    "sg:classifiers":[
        {
            "category":"Farming",
            "subcategory":"Dairy Farm",
            "type":"Manufacturing & Wholesale Goods"
        }
    ],
    "sg:phone":"+1 715 263 2341",
    "sg:postcode":"54013",
    "sg:province":"WI",
    "wof:name":"Kuhn Farm",
    "wof:placetype":"venue"
},
  "geometry": {"coordinates":[-92.281563,45.136592],"type":"Point"}
}