{
  "type": "Feature",
  "properties": {
    "iso:country":"US",
    "sg:address":"110 E Well St",
    "sg:city":"Ridgeway",
    "sg:classifiers":[
        {
            "category":"Farming",
            "subcategory":"Farm & Veterinary Services",
            "type":"Manufacturing & Wholesale Goods"
        }
    ],
    "sg:phone":"+1 608 523 1688",
    "sg:postcode":"53582",
    "sg:province":"WI",
    "sg:tags":[
        "preparation",
        "soil"
    ],
    "wof:name":"Hogan Soil Service",
    "wof:placetype":"venue"
},
  "geometry": {"coordinates":[-89.988862,43.00454],"type":"Point"}
}