{
  "type": "Feature",
  "properties": {
    "iso:country":"US",
    "sg:address":"11983 Heafford Rd",
    "sg:city":"Tomahawk",
    "sg:classifiers":[
        {
            "category":"Building & Trades",
            "subcategory":"Construction",
            "type":"Services"
        }
    ],
    "sg:phone":"+1 715 453 7956",
    "sg:postcode":"54487",
    "sg:province":"WI",
    "sg:tags":[
        "dry wall",
        "contractor"
    ],
    "wof:name":"Professional Drywall Service",
    "wof:placetype":"venue"
},
  "geometry": {"coordinates":[-89.71373800000001,45.551051],"type":"Point"}
}