{
  "type": "Feature",
  "properties": {
    "addr:full":"3961 Sock Rd Reeseville WI 53579",
    "addr:housenumber":"3961",
    "addr:postcode":"53579",
    "addr:street":"Sock Rd",
    "iso:country":"US",
    "sg:address":"3961 Sock Rd",
    "sg:city":"Reeseville",
    "sg:classifiers":[
        {
            "category":"Farming",
            "subcategory":"Dairy Farm",
            "type":"Manufacturing & Wholesale Goods"
        }
    ],
    "sg:phone":"+1 920 927 3623",
    "sg:postcode":"53579",
    "sg:province":"WI",
    "wof:name":"William R Borth",
    "wof:placetype":"venue"
},
  "geometry": {"coordinates":[-88.833276,43.346844],"type":"Point"}
}