{
  "type": "Feature",
  "properties": {
    "addr:full":"3149 Co Rd M Dodgeville WI 53533",
    "addr:housenumber":"3149",
    "addr:postcode":"53533",
    "addr:street":"Co Rd M",
    "iso:country":"US",
    "sg:address":"3149 Co Rd M",
    "sg:city":"Dodgeville",
    "sg:classifiers":[
        {
            "category":"Farming",
            "subcategory":"Livestock Farm",
            "type":"Manufacturing & Wholesale Goods"
        }
    ],
    "sg:phone":"+1 608 935 5491",
    "sg:postcode":"53533",
    "sg:province":"WI",
    "sg:tags":[
        "beef",
        "feedlot",
        "cattle"
    ],
    "wof:name":"Keith Ray",
    "wof:placetype":"venue"
},
  "geometry": {"coordinates":[-90.22629499999999,43.033851],"type":"Point"}
}