{
  "type": "Feature",
  "properties": {
    "addr:full":"95 N Moorland Rd Brookfield WI 53005",
    "addr:housenumber":"95",
    "addr:postcode":"53005",
    "addr:street":"N Moorland Rd",
    "iso:country":"US",
    "sg:address":"95 N Moorland Rd",
    "sg:city":"Brookfield",
    "sg:classifiers":[
        {
            "category":"Retail",
            "subcategory":"Portrait Studio",
            "type":"Services"
        }
    ],
    "sg:phone":"+1 262 782 2019",
    "sg:postcode":"53005",
    "sg:province":"WI",
    "sg:tags":[
        "photo"
    ],
    "wof:name":"Lifetouch",
    "wof:placetype":"venue"
},
  "geometry": {"coordinates":[-88.106933,43.034839],"type":"Point"}
}