{
  "type": "Feature",
  "properties": {
    "iso:country":"US",
    "sg:address":"1514 Nauman Rd",
    "sg:city":"Cecil",
    "sg:classifiers":[
        {
            "category":"Farming",
            "subcategory":"Dairy Farm",
            "type":"Manufacturing & Wholesale Goods"
        }
    ],
    "sg:phone":"+1 715 745 2541",
    "sg:postcode":"54111",
    "sg:province":"WI",
    "wof:name":"Roger Kanzenbach",
    "wof:placetype":"venue"
},
  "geometry": {"coordinates":[-88.326361,44.802095],"type":"Point"}
}