{
  "type": "Feature",
  "properties": {
    "iso:country":"US",
    "sg:address":"1121 N 7th St",
    "sg:city":"Sheboygan",
    "sg:classifiers":[
        {
            "category":"Professional",
            "subcategory":"Lawyer & Legal Services",
            "type":"Services"
        }
    ],
    "sg:phone":"+1 920 457 2424",
    "sg:postcode":"53081",
    "sg:province":"WI",
    "wof:name":"Alan J Peek",
    "wof:placetype":"venue"
},
  "geometry": {"coordinates":[-87.711196,43.757207],"type":"Point"}
}