{
  "type": "Feature",
  "properties": {
    "addr:full":"527 S Oak Park Ct Milwaukee WI 53214",
    "addr:housenumber":"527",
    "addr:postcode":"53214",
    "addr:street":"S Oak Park Ct",
    "iso:country":"US",
    "sg:address":"527 S Oak Park Ct",
    "sg:city":"Milwaukee",
    "sg:classifiers":[
        {
            "category":"Building & Trades",
            "subcategory":"Construction",
            "type":"Services"
        }
    ],
    "sg:phone":"+1 414 727 2608",
    "sg:postcode":"53214",
    "sg:province":"WI",
    "sg:tags":[
        "contractor"
    ],
    "wof:name":"Melkas Roofing LLC",
    "wof:placetype":"venue"
},
  "geometry": {"coordinates":[-87.984486,43.025127],"type":"Point"}
}