{
  "type": "Feature",
  "properties": {
    "iso:country":"US",
    "sg:address":"8867 810th Ave",
    "sg:city":"Colfax",
    "sg:classifiers":[
        {
            "category":"Freight",
            "type":"Transportation"
        }
    ],
    "sg:phone":"+1 715 962 3179",
    "sg:postcode":"54730",
    "sg:province":"WI",
    "sg:tags":[
        "operator",
        "local",
        "trucking"
    ],
    "wof:name":"Styczinski Trucking",
    "wof:placetype":"venue"
},
  "geometry": {"coordinates":[-91.71464400000001,44.972427],"type":"Point"}
}