{
  "type": "Feature",
  "properties": {
    "iso:country":"US",
    "sg:address":"17 E Main St",
    "sg:city":"Evansville",
    "sg:classifiers":[
        {
            "category":"Banks & Credit Unions",
            "subcategory":"Financial Services",
            "type":"Services"
        }
    ],
    "sg:phone":"+1 608 882 2469",
    "sg:postcode":"53536",
    "sg:province":"WI",
    "sg:tags":[
        "company",
        "holding"
    ],
    "wof:name":"Kenyon Holdings",
    "wof:placetype":"venue"
},
  "geometry": {"coordinates":[-89.298369,42.780228],"type":"Point"}
}