{
  "type": "Feature",
  "properties": {
    "addr:full":"1001 W Glen Oaks Ln Thiensville WI 53092",
    "addr:housenumber":"1001",
    "addr:postcode":"53092",
    "addr:street":"W Glen Oaks Ln",
    "iso:country":"US",
    "sg:address":"1001 W Glen Oaks Ln",
    "sg:city":"Thiensville",
    "sg:classifiers":[
        {
            "category":"Wholesale",
            "subcategory":"Chemicals & Plastics",
            "type":"Manufacturing & Wholesale Goods"
        }
    ],
    "sg:phone":"+1 262 241 7559",
    "sg:postcode":"53092",
    "sg:province":"WI",
    "sg:tags":[
        "metalworking",
        "industrial",
        "product"
    ],
    "wof:name":"Falcon Industrial Inc",
    "wof:placetype":"venue"
},
  "geometry": {"coordinates":[-87.92136600000001,43.235767],"type":"Point"}
}