{
  "type": "Feature",
  "properties": {
    "iso:country":"US",
    "sg:address":"9447 N 45th St",
    "sg:city":"Milwaukee",
    "sg:classifiers":[
        {
            "category":"Banks & Credit Unions",
            "subcategory":"Financial Services",
            "type":"Services"
        }
    ],
    "sg:phone":"+1 414 362 0384",
    "sg:postcode":"53223",
    "sg:province":"WI",
    "sg:tags":[
        "investor"
    ],
    "wof:name":"C Adams Investments LLC",
    "wof:placetype":"venue"
},
  "geometry": {"coordinates":[-87.96638299999999,43.191097],"type":"Point"}
}