{
  "type": "Feature",
  "properties": {
    "addr:full":"709 Hewett St Neillsville WI 54456",
    "addr:housenumber":"709",
    "addr:postcode":"54456",
    "addr:street":"Hewett St",
    "iso:country":"US",
    "sg:address":"709 Hewett St",
    "sg:city":"Neillsville",
    "sg:classifiers":[
        {
            "category":"Bars & Pubs",
            "type":"Food & Drink"
        }
    ],
    "sg:phone":"+1 715 743 2807",
    "sg:postcode":"54456",
    "sg:province":"WI",
    "sg:tags":[
        "drinking",
        "eating"
    ],
    "wof:name":"Rooster Bar",
    "wof:placetype":"venue"
},
  "geometry": {"coordinates":[-90.59605500000001,44.561795],"type":"Point"}
}