{
  "type": "Feature",
  "properties": {
    "addr:full":"6329 N Parkview Dr Milton WI 53563",
    "addr:housenumber":"6329",
    "addr:postcode":"53563",
    "addr:street":"N Parkview Dr",
    "iso:country":"US",
    "sg:address":"6329 N Parkview Dr",
    "sg:city":"Milton",
    "sg:classifiers":[
        {
            "category":"Manufacturing",
            "subcategory":"Food",
            "type":"Manufacturing & Wholesale Goods"
        },
        {
            "category":"Farming",
            "subcategory":"Farm",
            "type":"Manufacturing & Wholesale Goods"
        }
    ],
    "sg:phone":"+1 608 868 2588",
    "sg:postcode":"53563",
    "sg:province":"WI",
    "sg:tags":[
        "corn",
        "product"
    ],
    "wof:name":"Michael Pierce",
    "wof:placetype":"venue"
},
  "geometry": {"coordinates":[-88.945059,42.762929],"type":"Point"}
}