{
  "type": "Feature",
  "properties": {
    "iso:country":"US",
    "sg:address":"115 Maple St",
    "sg:city":"Granton",
    "sg:classifiers":[
        {
            "category":"Retail",
            "subcategory":"Veterinary Services",
            "type":"Services"
        }
    ],
    "sg:phone":"+1 715 238 7686",
    "sg:postcode":"54436",
    "sg:province":"WI",
    "sg:tags":[
        "veterinarian"
    ],
    "wof:name":"Grassland Veterinary Svc",
    "wof:placetype":"venue"
},
  "geometry": {"coordinates":[-90.462655,44.588072],"type":"Point"}
}