{
  "type": "Feature",
  "properties": {
    "iso:country":"US",
    "sg:address":"11733 State Rd 48",
    "sg:city":"Frederic",
    "sg:classifiers":[
        {
            "category":"Insurance",
            "subcategory":"Insurance Agent",
            "type":"Services"
        }
    ],
    "sg:phone":"+1 715 327 4800",
    "sg:postcode":"54837",
    "sg:province":"WI",
    "wof:name":"Trade Lake Mutual Insurance Co",
    "wof:placetype":"venue"
},
  "geometry": {"coordinates":[-92.588148,45.671367],"type":"Point"}
}