{
  "type": "Feature",
  "properties": {
    "addr:full":"524 South St Green Lake WI 54941",
    "addr:housenumber":"524",
    "addr:postcode":"54941",
    "addr:street":"South St",
    "iso:country":"US",
    "sg:address":"524 South St",
    "sg:city":"Green Lake",
    "sg:classifiers":[
        {
            "category":"Shopping",
            "subcategory":"Used Merchandise",
            "type":"Retail Goods"
        }
    ],
    "sg:phone":"+1 920 294 0991",
    "sg:postcode":"54941",
    "sg:province":"WI",
    "sg:tags":[
        "antique"
    ],
    "wof:name":"Lake House",
    "wof:placetype":"venue"
},
  "geometry": {"coordinates":[-88.95793500000001,43.844348],"type":"Point"}
}