{
  "type": "Feature",
  "properties": {
    "addr:full":"113 Freeman St Genoa City WI 53128",
    "addr:housenumber":"113",
    "addr:postcode":"53128",
    "addr:street":"Freeman St",
    "iso:country":"US",
    "sg:address":"113 Freeman St",
    "sg:city":"Genoa City",
    "sg:classifiers":[
        {
            "category":"Retail",
            "subcategory":"Funeral Services",
            "type":"Services"
        }
    ],
    "sg:phone":"+1 262 279 5933",
    "sg:postcode":"53128",
    "sg:province":"WI",
    "sg:tags":[
        "director"
    ],
    "wof:name":"Haase Derrick Lockwood Funeral",
    "wof:placetype":"venue"
},
  "geometry": {"coordinates":[-88.329932,42.496179],"type":"Point"}
}