{
  "type": "Feature",
  "properties": {
    "iso:country":"US",
    "sg:address":"1905 Washington St",
    "sg:city":"Wisconsin Rapids",
    "sg:classifiers":[
        {
            "category":"Health Services",
            "subcategory":"Hospital",
            "type":"Services"
        }
    ],
    "sg:phone":"+1 715 421 0480",
    "sg:postcode":"54494",
    "sg:province":"WI",
    "sg:tags":[
        "mental"
    ],
    "wof:name":"Children's Service Society",
    "wof:placetype":"venue"
},
  "geometry": {"coordinates":[-89.802437,44.394451],"type":"Point"}
}