{
  "type": "Feature",
  "properties": {
    "iso:country":"US",
    "sg:address":"747 E Scott St",
    "sg:city":"Fond Du Lac",
    "sg:classifiers":[
        {
            "category":"Organizations",
            "subcategory":"Religious Organization",
            "type":"Services"
        }
    ],
    "sg:phone":"+1 920 922 0300",
    "sg:postcode":"54935",
    "sg:province":"WI",
    "sg:tags":[
        "church"
    ],
    "sg:website":"www.fonddulacchurch.com",
    "wof:name":"Church Of Christ Fond Du Lac",
    "wof:placetype":"venue"
},
  "geometry": {"coordinates":[-88.421236,43.791281],"type":"Point"}
}