{
  "type": "Feature",
  "properties": {
    "addr:full":"2779 Ledgemont St Madison WI 53711",
    "addr:housenumber":"2779",
    "addr:postcode":"53711",
    "addr:street":"Ledgemont St",
    "iso:country":"US",
    "sg:address":"2779 Ledgemont St",
    "sg:city":"Madison",
    "sg:classifiers":[
        {
            "category":"Shopping",
            "subcategory":"Clothing, Apparel, & Fashions",
            "type":"Retail Goods"
        }
    ],
    "sg:phone":"+1 608 288 8233",
    "sg:postcode":"53711",
    "sg:province":"WI",
    "wof:name":"Benoy Masonry",
    "wof:placetype":"venue"
},
  "geometry": {"coordinates":[-89.443094,43.004927],"type":"Point"}
}