{
  "type": "Feature",
  "properties": {
    "addr:full":"13643 Thunder Mountain Rd Crivitz WI 54114",
    "addr:housenumber":"13643",
    "addr:postcode":"54114",
    "addr:street":"Thunder Mountain Rd",
    "iso:country":"US",
    "sg:address":"13643 Thunder Mountain Rd",
    "sg:city":"Crivitz",
    "sg:classifiers":[
        {
            "category":"Shopping",
            "subcategory":"Gifts & Souvenirs",
            "type":"Retail Goods"
        }
    ],
    "sg:phone":"+1 715 757 3594",
    "sg:postcode":"54114",
    "sg:province":"WI",
    "wof:name":"Thunder Mountain Rock Shop",
    "wof:placetype":"venue"
},
  "geometry": {"coordinates":[-88.295947,45.301615],"type":"Point"}
}