{
  "type": "Feature",
  "properties": {
    "iso:country":"US",
    "sg:address":"647 W Main St",
    "sg:city":"Lake Geneva",
    "sg:classifiers":[
        {
            "category":"Shopping",
            "subcategory":"Stationery & Office Supplies",
            "type":"Retail Goods"
        }
    ],
    "sg:phone":"+1 262 249 0456",
    "sg:postcode":"53147",
    "sg:province":"WI",
    "sg:tags":[
        "rubber",
        "stamp",
        "plastic"
    ],
    "wof:name":"Best Stamps & Advertising",
    "wof:placetype":"venue"
},
  "geometry": {"coordinates":[-88.432912,42.591784],"type":"Point"}
}