{
  "type": "Feature",
  "properties": {
    "iso:country":"US",
    "sg:address":"306 S Barstow St",
    "sg:city":"Eau Claire",
    "sg:classifiers":[
        {
            "category":"Banks & Credit Unions",
            "subcategory":"Investment Brokerage",
            "type":"Services"
        }
    ],
    "sg:phone":"+1 715 836 9990",
    "sg:postcode":"54701",
    "sg:province":"WI",
    "sg:tags":[
        "stock",
        "bond"
    ],
    "sg:website":"www.rwbaird.com",
    "wof:name":"Robert W Baird & Co",
    "wof:placetype":"venue"
},
  "geometry": {"coordinates":[-91.49879900000001,44.810133],"type":"Point"}
}