{
  "type": "Feature",
  "properties": {
    "iso:country":"US",
    "sg:address":"306 S Raynor Ave",
    "sg:city":"Union Grove",
    "sg:classifiers":[
        {
            "category":"Building & Trades",
            "subcategory":"Construction",
            "type":"Services"
        }
    ],
    "sg:phone":"+1 262 878 1336",
    "sg:postcode":"53182",
    "sg:province":"WI",
    "sg:tags":[
        "excavating",
        "grading",
        "contractor"
    ],
    "wof:name":"O & M Excavating & Grading",
    "wof:placetype":"venue"
},
  "geometry": {"coordinates":[-88.07152600000001,42.726187],"type":"Point"}
}