{
  "type": "Feature",
  "properties": {
    "iso:country":"US",
    "sg:address":"105 E Pioneer St",
    "sg:city":"Crandon",
    "sg:classifiers":[
        {
            "category":"Shopping",
            "subcategory":"Computers & Home Electronics",
            "type":"Retail Goods"
        }
    ],
    "sg:phone":"+1 715 478 1125",
    "sg:postcode":"54520",
    "sg:province":"WI",
    "sg:tags":[
        "equipment",
        "dealer"
    ],
    "sg:website":"www.1prospect.com",
    "wof:name":"1PROSPECT.COM",
    "wof:placetype":"venue"
},
  "geometry": {"coordinates":[-88.902866,45.564785],"type":"Point"}
}