{
  "type": "Feature",
  "properties": {
    "iso:country":"US",
    "sg:address":"7862 Culp Ln",
    "sg:city":"Pembine",
    "sg:classifiers":[
        {
            "category":"Shopping",
            "subcategory":"Catalog Store",
            "type":"Retail Goods"
        }
    ],
    "sg:phone":"+1 715 324 5907",
    "sg:postcode":"54156",
    "sg:province":"WI",
    "sg:tags":[
        "mail",
        "house"
    ],
    "wof:name":"Independent Avon Distributor",
    "wof:placetype":"venue"
},
  "geometry": {"coordinates":[-87.97989,45.578081],"type":"Point"}
}