{
  "type": "Feature",
  "properties": {
    "iso:country":"US",
    "sg:address":"420 Augusta St",
    "sg:city":"Janesville",
    "sg:classifiers":[
        {
            "category":"Manufacturing",
            "subcategory":"Motor Vehicles & Parts",
            "type":"Manufacturing & Wholesale Goods"
        }
    ],
    "sg:phone":"+1 608 756 3822",
    "sg:postcode":"53545",
    "sg:province":"WI",
    "sg:tags":[
        "mfg"
    ],
    "wof:name":"T T Euro Moto Corp",
    "wof:placetype":"venue"
},
  "geometry": {"coordinates":[-89.014603,42.689244],"type":"Point"}
}