{
  "type": "Feature",
  "properties": {
    "iso:country":"US",
    "sg:address":"4936 Machicknee Ln",
    "sg:city":"Lena",
    "sg:classifiers":[
        {
            "category":"Organizations",
            "subcategory":"Non-profit Organization",
            "type":"Services"
        }
    ],
    "sg:phone":"+1 920 846 8416",
    "sg:postcode":"54139",
    "sg:province":"WI",
    "sg:tags":[
        "social"
    ],
    "wof:name":"Carriveau Health Care Inc",
    "wof:placetype":"venue"
},
  "geometry": {"coordinates":[-88.07884900000001,44.851288],"type":"Point"}
}