{
  "type": "Feature",
  "properties": {
    "addr:full":"125 Bennet St Mellen WI 54546",
    "addr:housenumber":"125",
    "addr:postcode":"54546",
    "addr:street":"Bennet St",
    "iso:country":"US",
    "sg:address":"125 Bennet St",
    "sg:city":"Mellen",
    "sg:classifiers":[
        {
            "category":"Organizations",
            "subcategory":"Professional Association",
            "type":"Services"
        }
    ],
    "sg:phone":"+1 715 274 2330",
    "sg:postcode":"54546",
    "sg:province":"WI",
    "sg:tags":[
        "chambers",
        "commerce"
    ],
    "wof:name":"Mellen Chamber Of Commerce",
    "wof:placetype":"venue"
},
  "geometry": {"coordinates":[-90.659462,46.32661],"type":"Point"}
}