{
  "type": "Feature",
  "properties": {
    "iso:country":"US",
    "sg:address":"2756 New Pinery Rd",
    "sg:city":"Portage",
    "sg:classifiers":[
        {
            "category":"Restaurant",
            "type":"Food & Drink"
        }
    ],
    "sg:phone":"+1 608 742 3930",
    "sg:postcode":"53901",
    "sg:province":"WI",
    "sg:tags":[
        "style",
        "buffet",
        "family"
    ],
    "wof:name":"World Buffet",
    "wof:placetype":"venue"
},
  "geometry": {"coordinates":[-89.46965,43.572689],"type":"Point"}
}