{
  "type": "Feature",
  "properties": {
    "iso:country":"US",
    "sg:address":"1924 Pleasant View Dr",
    "sg:city":"Stoughton",
    "sg:classifiers":[
        {
            "category":"Professional",
            "subcategory":"Art Services",
            "type":"Services"
        }
    ],
    "sg:phone":"+1 608 873 5694",
    "sg:postcode":"53589",
    "sg:province":"WI",
    "sg:tags":[
        "commercial",
        "design"
    ],
    "wof:name":"Memory Graphics Inc",
    "wof:placetype":"venue"
},
  "geometry": {"coordinates":[-89.24267399999999,42.916071],"type":"Point"}
}