{
  "type": "Feature",
  "properties": {
    "addr:full":"5419 N Gilbert Ln Abrams WI 54101",
    "addr:housenumber":"5419",
    "addr:postcode":"54101",
    "addr:street":"N Gilbert Ln",
    "iso:country":"US",
    "sg:address":"5419 N Gilbert Ln",
    "sg:city":"Abrams",
    "sg:classifiers":[
        {
            "category":"Building & Trades",
            "subcategory":"Construction",
            "type":"Services"
        }
    ],
    "sg:phone":"+1 920 826 7841",
    "sg:postcode":"54101",
    "sg:province":"WI",
    "sg:tags":[
        "house"
    ],
    "wof:name":"J & J Builders Inc",
    "wof:placetype":"venue"
},
  "geometry": {"coordinates":[-88.038088,44.813385],"type":"Point"}
}