{
  "type": "Feature",
  "properties": {
    "addr:full":"4316 N Oakland Ave Milwaukee WI 53211",
    "addr:housenumber":"4316",
    "addr:postcode":"53211",
    "addr:street":"N Oakland Ave",
    "iso:country":"US",
    "sg:address":"4316 N Oakland Ave",
    "sg:city":"Milwaukee",
    "sg:classifiers":[
        {
            "category":"Building & Trades",
            "subcategory":"Construction",
            "type":"Services"
        }
    ],
    "sg:phone":"+1 414 332 1000",
    "sg:postcode":"53211",
    "sg:province":"WI",
    "sg:tags":[
        "hanging",
        "painter",
        "contractor"
    ],
    "sg:website":"www.pichlerpainting.com",
    "wof:name":"Pichler Painting Corp",
    "wof:placetype":"venue"
},
  "geometry": {"coordinates":[-87.887361,43.095424],"type":"Point"}
}