{
  "type": "Feature",
  "properties": {
    "iso:country":"US",
    "sg:address":"423 24th St N",
    "sg:city":"La Crosse",
    "sg:classifiers":[
        {
            "category":"Professional",
            "subcategory":"Management & Consulting",
            "type":"Services"
        }
    ],
    "sg:phone":"+1 608 782 8350",
    "sg:postcode":"54601",
    "sg:province":"WI",
    "sg:tags":[
        "business"
    ],
    "wof:name":"Pk Wilson Inc",
    "wof:placetype":"venue"
},
  "geometry": {"coordinates":[-91.220771,43.816233],"type":"Point"}
}