{
  "type": "Feature",
  "properties": {
    "iso:country":"US",
    "sg:address":"2011 Barberry Ln",
    "sg:city":"Green Bay",
    "sg:classifiers":[
        {
            "category":"Building & Trades",
            "subcategory":"Construction",
            "type":"Services"
        }
    ],
    "sg:phone":"+1 920 496 1216",
    "sg:postcode":"54304",
    "sg:province":"WI",
    "sg:tags":[
        "house"
    ],
    "wof:name":"Wendell D Sagear",
    "wof:placetype":"venue"
},
  "geometry": {"coordinates":[-88.064785,44.498907],"type":"Point"}
}