{
  "type": "Feature",
  "properties": {
    "iso:country":"US",
    "sg:address":"802 River St",
    "sg:city":"Rhinelander",
    "sg:classifiers":[
        {
            "category":"Professional",
            "type":"Services"
        }
    ],
    "sg:phone":"+1 715 362 3323",
    "sg:postcode":"54501",
    "sg:province":"WI",
    "wof:name":"Bad Boy Bill Dj Service",
    "wof:placetype":"venue"
},
  "geometry": {"coordinates":[-89.426376,45.644804],"type":"Point"}
}