{
  "type": "Feature",
  "properties": {
    "iso:country":"US",
    "sg:address":"3811 55th Ave",
    "sg:city":"Kenosha",
    "sg:classifiers":[
        {
            "category":"Manufacturing",
            "subcategory":"Wood Products",
            "type":"Manufacturing & Wholesale Goods"
        }
    ],
    "sg:phone":"+1 262 652 1552",
    "sg:postcode":"53144",
    "sg:province":"WI",
    "sg:tags":[
        "pallet",
        "skid"
    ],
    "wof:name":"Wright Pallet",
    "wof:placetype":"venue"
},
  "geometry": {"coordinates":[-87.873493,42.603243],"type":"Point"}
}