{
  "type": "Feature",
  "properties": {
    "iso:country":"US",
    "sg:address":"16695 Brehon Ln",
    "sg:city":"Brookfield",
    "sg:classifiers":[
        {
            "category":"Travel",
            "subcategory":"Travel Agent",
            "type":"Entertainment"
        }
    ],
    "sg:phone":"+1 262 783 6847",
    "sg:postcode":"53005",
    "sg:province":"WI",
    "sg:tags":[
        "agency",
        "bureau"
    ],
    "sg:website":"www.darlingtravel.com",
    "wof:name":"Darling Co Inc",
    "wof:placetype":"venue"
},
  "geometry": {"coordinates":[-88.11895699999999,43.075994],"type":"Point"}
}