{
  "type": "Feature",
  "properties": {
    "iso:country":"US",
    "sg:address":"421 Oak Ave",
    "sg:city":"Menomonie",
    "sg:classifiers":[
        {
            "category":"Home & Garden",
            "subcategory":"Building Materials",
            "type":"Retail Goods"
        }
    ],
    "sg:phone":"+1 715 235 3491",
    "sg:postcode":"54751",
    "sg:province":"WI",
    "wof:name":"United Building Centers 753",
    "wof:placetype":"venue"
},
  "geometry": {"coordinates":[-91.92750100000001,44.90281],"type":"Point"}
}