{
  "type": "Feature",
  "properties": {
    "addr:full":"5304 61st St Kenosha WI 53142",
    "addr:housenumber":"5304",
    "addr:postcode":"53142",
    "addr:street":"61St St",
    "iso:country":"US",
    "sg:address":"5304 61st St",
    "sg:city":"Kenosha",
    "sg:classifiers":[
        {
            "category":"Professional",
            "type":"Services"
        }
    ],
    "sg:phone":"+1 262 653 9569",
    "sg:postcode":"53142",
    "sg:province":"WI",
    "wof:name":"Debs Inflatables LLC",
    "wof:placetype":"venue"
},
  "geometry": {"coordinates":[-87.871109,42.579896],"type":"Point"}
}