{
  "type": "Feature",
  "properties": {
    "iso:country":"US",
    "sg:address":"45 6th St",
    "sg:city":"Clintonville",
    "sg:classifiers":[
        {
            "category":"Professional",
            "subcategory":"Accounting & Tax Preparation",
            "type":"Services"
        }
    ],
    "sg:phone":"+1 715 823 7100",
    "sg:postcode":"54929",
    "sg:province":"WI",
    "sg:tags":[
        "accountant"
    ],
    "wof:name":"Tri-County Tax & Accounting",
    "wof:placetype":"venue"
},
  "geometry": {"coordinates":[-88.764106,44.617711],"type":"Point"}
}