{
  "type": "Feature",
  "properties": {
    "iso:country":"US",
    "sg:address":"315 Union St",
    "sg:city":"Rio",
    "sg:classifiers":[
        {
            "category":"Health Services",
            "subcategory":"Doctor",
            "type":"Services"
        }
    ],
    "sg:phone":"+1 920 992 3500",
    "sg:postcode":"53960",
    "sg:province":"WI",
    "wof:name":"James W Nelson DDS",
    "wof:placetype":"venue"
},
  "geometry": {"coordinates":[-89.238277,43.447179],"type":"Point"}
}