{
  "type": "Feature",
  "properties": {
    "addr:full":"5340 Locust Dr West Salem WI 54669",
    "addr:housenumber":"5340",
    "addr:postcode":"54669",
    "addr:street":"Locust Dr",
    "iso:country":"US",
    "sg:address":"5340 Locust Dr",
    "sg:city":"West Salem",
    "sg:classifiers":[
        {
            "category":"Building & Trades",
            "subcategory":"Construction",
            "type":"Services"
        }
    ],
    "sg:phone":"+1 608 786 1582",
    "sg:postcode":"54669",
    "sg:province":"WI",
    "sg:tags":[
        "house",
        "builder",
        "operative"
    ],
    "wof:name":"Raymer Construction",
    "wof:placetype":"venue"
},
  "geometry": {"coordinates":[-91.107275,43.91453],"type":"Point"}
}