{
  "type": "Feature",
  "properties": {
    "iso:country":"US",
    "sg:address":"310 Kane St",
    "sg:city":"Fall River",
    "sg:classifiers":[
        {
            "category":"Farming",
            "subcategory":"Dairy Farm",
            "type":"Manufacturing & Wholesale Goods"
        }
    ],
    "sg:phone":"+1 920 484 3118",
    "sg:postcode":"53932",
    "sg:province":"WI",
    "wof:name":"Ladwig Farms",
    "wof:placetype":"venue"
},
  "geometry": {"coordinates":[-89.042424,43.384708],"type":"Point"}
}