{
  "type": "Feature",
  "properties": {
    "iso:country":"US",
    "sg:address":"5525 River Oaks Dr",
    "sg:city":"De Pere",
    "sg:classifiers":[
        {
            "category":"Manufacturing",
            "subcategory":"Tools & Machinery",
            "type":"Manufacturing & Wholesale Goods"
        }
    ],
    "sg:phone":"+1 920 351 0152",
    "sg:postcode":"54115",
    "sg:province":"WI",
    "sg:tags":[
        "mfg"
    ],
    "wof:name":"River Oaks Die Engraving LLC",
    "wof:placetype":"venue"
},
  "geometry": {"coordinates":[-88.102454,44.359486],"type":"Point"}
}