{
  "type": "Feature",
  "properties": {
    "addr:full":"8497 Brazelton Dr Random Lake WI 53075",
    "addr:housenumber":"8497",
    "addr:postcode":"53075",
    "addr:street":"Brazelton Dr Random",
    "iso:country":"US",
    "sg:address":"8497 Brazelton Dr",
    "sg:city":"Random Lake",
    "sg:classifiers":[
        {
            "category":"Organizations",
            "subcategory":"Religious Organization",
            "type":"Services"
        }
    ],
    "sg:phone":"+1 920 994 9060",
    "sg:postcode":"53075",
    "sg:province":"WI",
    "sg:tags":[
        "lutheran",
        "church"
    ],
    "wof:name":"Immanuel Lutheran Church",
    "wof:placetype":"venue"
},
  "geometry": {"coordinates":[-88.10451500000001,43.571499],"type":"Point"}
}