{
  "type": "Feature",
  "properties": {
    "iso:country":"US",
    "sg:address":"101 N Ogden Rd",
    "sg:city":"Peshtigo",
    "sg:classifiers":[
        {
            "category":"Government",
            "subcategory":"Court House",
            "type":"Public Place"
        }
    ],
    "sg:phone":"+1 715 582 1194",
    "sg:postcode":"54157",
    "sg:province":"WI",
    "sg:tags":[
        "defender",
        "state"
    ],
    "wof:name":"Peshtigo Trial Office",
    "wof:placetype":"venue"
},
  "geometry": {"coordinates":[-87.733993,45.055456],"type":"Point"}
}