{
  "type": "Feature",
  "properties": {
    "addr:full":"3969 S Howell Ave Milwaukee WI 53207",
    "addr:housenumber":"3969",
    "addr:postcode":"53207",
    "addr:street":"S Howell Ave",
    "iso:country":"US",
    "sg:address":"3969 S Howell Ave",
    "sg:city":"Milwaukee",
    "sg:classifiers":[
        {
            "category":"Shopping",
            "subcategory":"Used Merchandise",
            "type":"Retail Goods"
        }
    ],
    "sg:phone":"+1 414 744 1374",
    "sg:postcode":"53207",
    "sg:province":"WI",
    "sg:tags":[
        "antique"
    ],
    "wof:name":"Travis Kevin",
    "wof:placetype":"venue"
},
  "geometry": {"coordinates":[-87.909614,42.972259],"type":"Point"}
}