{
  "type": "Feature",
  "properties": {
    "iso:country":"US",
    "sg:address":"6733 W North Ave",
    "sg:city":"Milwaukee",
    "sg:classifiers":[
        {
            "category":"Restaurant",
            "type":"Food & Drink"
        }
    ],
    "sg:menulink":"http://www.allmenus.com/wi/wauwatosa/145819-subway/menu/",
    "sg:phone":"+1 414 257 1070",
    "sg:postcode":"53213",
    "sg:province":"WI",
    "sg:tags":[
        "american",
        "sandwich"
    ],
    "wof:name":"Subway",
    "wof:placetype":"venue"
},
  "geometry": {"coordinates":[-87.997184,43.060758],"type":"Point"}
}