{
  "type": "Feature",
  "properties": {
    "iso:country":"US",
    "sg:address":"3712 Kettle Moraine Rd",
    "sg:city":"Hartford",
    "sg:classifiers":[
        {
            "category":"Manufacturing",
            "subcategory":"Lumber",
            "type":"Manufacturing & Wholesale Goods"
        }
    ],
    "sg:phone":"+1 262 644 6133",
    "sg:postcode":"53027",
    "sg:province":"WI",
    "sg:tags":[
        "operation",
        "timber",
        "tract"
    ],
    "wof:name":"Schaefers CHSe&hrvst Tree Farm",
    "wof:placetype":"venue"
},
  "geometry": {"coordinates":[-88.319228,43.325109],"type":"Point"}
}