{
  "type": "Feature",
  "properties": {
    "iso:country":"US",
    "sg:address":"8528 2nd St",
    "sg:city":"Burnett",
    "sg:classifiers":[
        {
            "category":"Government",
            "subcategory":"Post Office",
            "type":"Public Place"
        }
    ],
    "sg:phone":"+1 920 689 2432",
    "sg:postcode":"53922",
    "sg:province":"WI",
    "wof:name":"US Post Office",
    "wof:placetype":"venue"
},
  "geometry": {"coordinates":[-88.707278,43.504039],"type":"Point"}
}