{
  "type": "Feature",
  "properties": {
    "iso:country":"US",
    "sg:address":"4365 W Bradley Rd",
    "sg:city":"Milwaukee",
    "sg:classifiers":[
        {
            "category":"Recreation",
            "type":"Entertainment"
        }
    ],
    "sg:phone":"+1 414 355 9596",
    "sg:postcode":"53223",
    "sg:province":"WI",
    "sg:tags":[
        "club",
        "membership"
    ],
    "wof:name":"Bridge Center of Milwaukee",
    "wof:placetype":"venue"
},
  "geometry": {"coordinates":[-87.965863,43.163063],"type":"Point"}
}