{
  "type": "Feature",
  "properties": {
    "iso:country":"US",
    "sg:address":"6854 Wildwood Creek Ct",
    "sg:city":"Franklin",
    "sg:classifiers":[
        {
            "category":"Insurance",
            "subcategory":"Insurance Agent",
            "type":"Services"
        }
    ],
    "sg:phone":"+1 414 425 2601",
    "sg:postcode":"53132",
    "sg:province":"WI",
    "wof:name":"Edward J Wruck Jr",
    "wof:placetype":"venue"
},
  "geometry": {"coordinates":[-88.00083600000001,42.906404],"type":"Point"}
}