{
  "type": "Feature",
  "properties": {
    "iso:country":"US",
    "sg:address":"2111 W North Ave",
    "sg:city":"Milwaukee",
    "sg:classifiers":[
        {
            "category":"Health Services",
            "subcategory":"Clinic",
            "type":"Services"
        }
    ],
    "sg:phone":"+1 414 344 4468",
    "sg:postcode":"53205",
    "sg:province":"WI",
    "sg:tags":[
        "banks",
        "blood",
        "center"
    ],
    "sg:website":"www.internationalresources.com",
    "wof:name":"ZLB Plasma Svc",
    "wof:placetype":"venue"
},
  "geometry": {"coordinates":[-87.939948,43.060437],"type":"Point"}
}