{
  "type": "Feature",
  "properties": {
    "iso:country":"US",
    "sg:address":"6676 W Charles Ct",
    "sg:city":"Franklin",
    "sg:classifiers":[
        {
            "category":"Professional",
            "subcategory":"Business Services",
            "type":"Services"
        }
    ],
    "sg:phone":"+1 414 425 3522",
    "sg:postcode":"53132",
    "sg:province":"WI",
    "wof:name":"Three Jt Enterprises LLC",
    "wof:placetype":"venue"
},
  "geometry": {"coordinates":[-87.997588,42.902195],"type":"Point"}
}