{
  "type": "Feature",
  "properties": {
    "iso:country":"US",
    "sg:address":"8386 State Hwy 19",
    "sg:city":"Cross Plains",
    "sg:classifiers":[
        {
            "category":"Professional",
            "type":"Services"
        }
    ],
    "sg:phone":"+1 608 798 4380",
    "sg:postcode":"53528",
    "sg:province":"WI",
    "wof:name":"Arlans Bobcat Services LLC",
    "wof:placetype":"venue"
},
  "geometry": {"coordinates":[-89.63411499999999,43.19004],"type":"Point"}
}