{
  "type": "Feature",
  "properties": {
    "iso:country":"US",
    "sg:address":"590 N Church St",
    "sg:city":"Richland Center",
    "sg:classifiers":[
        {
            "category":"Organizations",
            "subcategory":"Religious Organization",
            "type":"Services"
        }
    ],
    "sg:phone":"+1 608 647 6003",
    "sg:postcode":"53581",
    "sg:province":"WI",
    "wof:name":"St Barnabas Episcopal Church",
    "wof:placetype":"venue"
},
  "geometry": {"coordinates":[-90.38412,43.339222],"type":"Point"}
}