{
  "type": "Feature",
  "properties": {
    "addr:full":"311 E Birch Ave Milwaukee WI 53217",
    "addr:housenumber":"311",
    "addr:postcode":"53217",
    "addr:street":"E Birch Ave",
    "iso:country":"US",
    "sg:address":"311 E Birch Ave",
    "sg:city":"Milwaukee",
    "sg:classifiers":[
        {
            "category":"Banks & Credit Unions",
            "subcategory":"Investment Brokerage",
            "type":"Services"
        }
    ],
    "sg:phone":"+1 414 962 6266",
    "sg:postcode":"53217",
    "sg:province":"WI",
    "sg:tags":[
        "trust"
    ],
    "wof:name":"Bonlender Trust",
    "wof:placetype":"venue"
},
  "geometry": {"coordinates":[-87.906578,43.115969],"type":"Point"}
}