{
  "type": "Feature",
  "properties": {
    "iso:country":"US",
    "sg:address":"5175 810th Ave",
    "sg:city":"Menomonie",
    "sg:classifiers":[
        {
            "category":"Building & Trades",
            "subcategory":"Construction",
            "type":"Services"
        }
    ],
    "sg:phone":"+1 715 235 8146",
    "sg:postcode":"54751",
    "sg:province":"WI",
    "sg:tags":[
        "house",
        "general",
        "contractor"
    ],
    "wof:name":"Bergelin Richard Construction",
    "wof:placetype":"venue"
},
  "geometry": {"coordinates":[-91.899294,44.973675],"type":"Point"}
}