{
  "type": "Feature",
  "properties": {
    "iso:country":"US",
    "sg:address":"6992 Timber Ridge Cir",
    "sg:city":"Eau Claire",
    "sg:classifiers":[
        {
            "category":"Wholesale",
            "subcategory":"Non-durable Goods",
            "type":"Manufacturing & Wholesale Goods"
        }
    ],
    "sg:phone":"+1 715 836 0176",
    "sg:postcode":"54701",
    "sg:province":"WI",
    "wof:name":"M&B Distributors of Menomonie",
    "wof:placetype":"venue"
},
  "geometry": {"coordinates":[-91.520825,44.729243],"type":"Point"}
}