{
  "type": "Feature",
  "properties": {
    "iso:country":"US",
    "sg:address":"7747 N Teutonia Ave",
    "sg:city":"Milwaukee",
    "sg:classifiers":[
        {
            "category":"Retail",
            "subcategory":"Auto Repair",
            "type":"Services"
        }
    ],
    "sg:phone":"+1 414 357 7510",
    "sg:postcode":"53209",
    "sg:province":"WI",
    "sg:tags":[
        "body"
    ],
    "wof:name":"Parkland Auto Body",
    "wof:placetype":"venue"
},
  "geometry": {"coordinates":[-87.95978100000001,43.158593],"type":"Point"}
}