{
  "type": "Feature",
  "properties": {
    "iso:country":"US",
    "sg:address":"1551 38th Ave",
    "sg:city":"Amery",
    "sg:classifiers":[
        {
            "category":"Shopping",
            "subcategory":"Florist",
            "type":"Retail Goods"
        }
    ],
    "sg:phone":"+1 715 268 6304",
    "sg:postcode":"54001",
    "sg:province":"WI",
    "wof:name":"Js Floral & Gifts",
    "wof:placetype":"venue"
},
  "geometry": {"coordinates":[-92.483337,45.263284],"type":"Point"}
}