{
  "type": "Feature",
  "properties": {
    "iso:country":"US",
    "sg:address":"406 2nd St",
    "sg:city":"Monroe",
    "sg:classifiers":[
        {
            "category":"Building & Trades",
            "subcategory":"Electrical",
            "type":"Services"
        }
    ],
    "sg:phone":"+1 608 325 7663",
    "sg:postcode":"53566",
    "sg:province":"WI",
    "sg:tags":[
        "electric",
        "contractor"
    ],
    "wof:name":"Gentz Electric",
    "wof:placetype":"venue"
},
  "geometry": {"coordinates":[-89.653402,42.610033],"type":"Point"}
}