{
  "type": "Feature",
  "properties": {
    "iso:country":"US",
    "sg:address":"1114 12th St",
    "sg:city":"Racine",
    "sg:classifiers":[
        {
            "category":"Personal",
            "subcategory":"Beauty Salon",
            "type":"Services"
        }
    ],
    "sg:phone":"+1 262 632 0969",
    "sg:postcode":"53403",
    "sg:province":"WI",
    "wof:name":"Unique Beauty & Style",
    "wof:placetype":"venue"
},
  "geometry": {"coordinates":[-87.793696,42.718551],"type":"Point"}
}