{
  "type": "Feature",
  "properties": {
    "iso:country":"US",
    "sg:address":"9125 Military Rd",
    "sg:city":"Kaukauna",
    "sg:classifiers":[
        {
            "category":"Organizations",
            "subcategory":"Religious Organization",
            "type":"Services"
        }
    ],
    "sg:phone":"+1 920 766 5838",
    "sg:postcode":"54130",
    "sg:province":"WI",
    "wof:name":"St Johns Evang Lutheran Church",
    "wof:placetype":"venue"
},
  "geometry": {"coordinates":[-88.226721,44.22467],"type":"Point"}
}