{
  "type": "Feature",
  "properties": {
    "addr:full":"5455 Butler St Sheldon WI 54766",
    "addr:housenumber":"5455",
    "addr:postcode":"54766",
    "addr:street":"Butler St",
    "iso:country":"US",
    "sg:address":"5455 Butler St",
    "sg:city":"Sheldon",
    "sg:classifiers":[
        {
            "category":"Food & Beverages",
            "subcategory":"Dairy",
            "type":"Retail Goods"
        }
    ],
    "sg:phone":"+1 715 452 5826",
    "sg:postcode":"54766",
    "sg:province":"WI",
    "sg:tags":[
        "product"
    ],
    "wof:name":"Cheese On Wheels",
    "wof:placetype":"venue"
},
  "geometry": {"coordinates":[-90.953344,45.313545],"type":"Point"}
}