{
  "type": "Feature",
  "properties": {
    "iso:country":"US",
    "sg:address":"3072 Cimarron Trl",
    "sg:city":"Madison",
    "sg:classifiers":[
        {
            "category":"Freight",
            "type":"Transportation"
        }
    ],
    "sg:phone":"+1 608 845 8404",
    "sg:postcode":"53719",
    "sg:province":"WI",
    "sg:tags":[
        "operator",
        "local",
        "trucking"
    ],
    "wof:name":"Moving Solutions Inc",
    "wof:placetype":"venue"
},
  "geometry": {"coordinates":[-89.50863,43.019458],"type":"Point"}
}