{
  "type": "Feature",
  "properties": {
    "iso:country":"US",
    "sg:address":"138 S Main St",
    "sg:city":"Jefferson",
    "sg:classifiers":[
        {
            "category":"Real Estate",
            "subcategory":"Architect",
            "type":"Services"
        }
    ],
    "sg:phone":"+1 920 674 3100",
    "sg:postcode":"53549",
    "sg:province":"WI",
    "wof:name":"Architectural Firm",
    "wof:placetype":"venue"
},
  "geometry": {"coordinates":[-88.80718,43.004966],"type":"Point"}
}