{
  "type": "Feature",
  "properties": {
    "iso:country":"US",
    "sg:address":"1200 3rd Ave",
    "sg:city":"Woodruff",
    "sg:classifiers":[
        {
            "category":"Organizations",
            "subcategory":"Religious Organization",
            "type":"Services"
        }
    ],
    "sg:phone":"+1 715 356 5015",
    "sg:postcode":"54568",
    "sg:province":"WI",
    "sg:tags":[
        "church"
    ],
    "wof:name":"Woodruff Baptist Church",
    "wof:placetype":"venue"
},
  "geometry": {"coordinates":[-89.695978,45.893944],"type":"Point"}
}