{
  "type": "Feature",
  "properties": {
    "iso:country":"US",
    "sg:address":"490 Bayview Ct",
    "sg:city":"Green Lake",
    "sg:classifiers":[
        {
            "category":"Professional",
            "subcategory":"Art Services",
            "type":"Services"
        }
    ],
    "sg:phone":"+1 920 294 3222",
    "sg:postcode":"54941",
    "sg:province":"WI",
    "sg:tags":[
        "photo",
        "photography",
        "commercial",
        "studio",
        "portrait"
    ],
    "wof:name":"Sleeping Gypsy Photography",
    "wof:placetype":"venue"
},
  "geometry": {"coordinates":[-88.96005,43.843893],"type":"Point"}
}