{
  "type": "Feature",
  "properties": {
    "iso:country":"US",
    "sg:address":"8512 Brown St",
    "sg:city":"Oconomowoc",
    "sg:classifiers":[
        {
            "category":"Organizations",
            "subcategory":"Religious Organization",
            "type":"Services"
        }
    ],
    "sg:phone":"+1 262 474 7000",
    "sg:postcode":"53066",
    "sg:province":"WI",
    "wof:name":"St Catherine Alexandria Parish",
    "wof:placetype":"venue"
},
  "geometry": {"coordinates":[-88.459054,43.175074],"type":"Point"}
}