{
  "type": "Feature",
  "properties": {
    "iso:country":"US",
    "sg:address":"2056 Co Rd C",
    "sg:city":"Somerset",
    "sg:classifiers":[
        {
            "category":"Retail",
            "subcategory":"Repair Shop",
            "type":"Services"
        },
        {
            "category":"Building & Trades",
            "subcategory":"Construction",
            "type":"Services"
        }
    ],
    "sg:phone":"+1 715 246 9665",
    "sg:postcode":"54025",
    "sg:province":"WI",
    "sg:tags":[
        "steel",
        "structural",
        "erection",
        "welding"
    ],
    "wof:name":"T N T Metals",
    "wof:placetype":"venue"
},
  "geometry": {"coordinates":[-92.608615,45.158456],"type":"Point"}
}