{
  "type": "Feature",
  "properties": {
    "iso:country":"US",
    "sg:address":"853 Cornelius Dr",
    "sg:city":"Green Bay",
    "sg:classifiers":[
        {
            "category":"Shopping",
            "subcategory":"Musical Instruments",
            "type":"Retail Goods"
        }
    ],
    "sg:phone":"+1 920 884 3702",
    "sg:postcode":"54311",
    "sg:province":"WI",
    "wof:name":"Mecca Music Inc",
    "wof:placetype":"venue"
},
  "geometry": {"coordinates":[-87.929986,44.515091],"type":"Point"}
}