{
  "type": "Feature",
  "properties": {
    "iso:country":"US",
    "sg:address":"9265 Hermanson Rd",
    "sg:city":"St Germain",
    "sg:classifiers":[
        {
            "category":"Building & Trades",
            "subcategory":"Construction",
            "type":"Services"
        }
    ],
    "sg:phone":"+1 715 542 2373",
    "sg:postcode":"54558",
    "sg:province":"WI",
    "sg:tags":[
        "maintenance",
        "contractor"
    ],
    "wof:name":"St Germain Maintenance Bldg",
    "wof:placetype":"venue"
},
  "geometry": {"coordinates":[-89.563249,45.935754],"type":"Point"}
}