{
  "type": "Feature",
  "properties": {
    "iso:country":"US",
    "sg:address":"9424 Cedar St",
    "sg:city":"Fish Creek",
    "sg:classifiers":[
        {
            "category":"Home & Garden",
            "subcategory":"Furniture",
            "type":"Retail Goods"
        }
    ],
    "sg:phone":"+1 920 868 1734",
    "sg:postcode":"54212",
    "sg:province":"WI",
    "sg:tags":[
        "clothing",
        "family"
    ],
    "wof:name":"Touch of World",
    "wof:placetype":"venue"
},
  "geometry": {"coordinates":[-87.247513,45.128424],"type":"Point"}
}