{
  "type": "Feature",
  "properties": {
    "iso:country":"US",
    "sg:address":"8227 1015th St",
    "sg:city":"River Falls",
    "sg:classifiers":[
        {
            "category":"Banks & Credit Unions",
            "subcategory":"Bank",
            "type":"Services"
        }
    ],
    "sg:phone":"+1 715 426 8978",
    "sg:postcode":"54022",
    "sg:province":"WI",
    "sg:tags":[
        "mortgage"
    ],
    "wof:name":"Aspen Mortgage Co Inc",
    "wof:placetype":"venue"
},
  "geometry": {"coordinates":[-92.648439,44.83837],"type":"Point"}
}