{
  "type": "Feature",
  "properties": {
    "iso:country":"US",
    "sg:address":"304 W Pine St",
    "sg:city":"Sturgeon Bay",
    "sg:classifiers":[
        {
            "category":"Professional",
            "type":"Services"
        }
    ],
    "sg:phone":"+1 920 743 3881",
    "sg:postcode":"54235",
    "sg:province":"WI",
    "sg:tags":[
        "establishment"
    ],
    "wof:name":"Hartman & Hartman",
    "wof:placetype":"venue"
},
  "geometry": {"coordinates":[-87.390459,44.826982],"type":"Point"}
}