{
  "type": "Feature",
  "properties": {
    "iso:country":"US",
    "sg:address":"1001 Perry St",
    "sg:city":"Algoma",
    "sg:classifiers":[
        {
            "category":"Manufacturing",
            "subcategory":"Building Materials",
            "type":"Manufacturing & Wholesale Goods"
        }
    ],
    "sg:phone":"+1 920 487 5221",
    "sg:postcode":"54201",
    "sg:province":"WI",
    "sg:tags":[
        "door"
    ],
    "sg:website":"www.appalachiandoor.com",
    "wof:name":"Algoma Hardwoods Inc",
    "wof:placetype":"venue"
},
  "geometry": {"coordinates":[-87.446936,44.613251],"type":"Point"}
}