{
  "type": "Feature",
  "properties": {
    "iso:country":"US",
    "sg:address":"622 Fairview Ave",
    "sg:city":"De Pere",
    "sg:classifiers":[
        {
            "category":"Freight",
            "type":"Transportation"
        }
    ],
    "sg:phone":"+1 920 336 9335",
    "sg:postcode":"54115",
    "sg:province":"WI",
    "sg:tags":[
        "distance",
        "local",
        "hauling",
        "long"
    ],
    "wof:name":"Tom Hoffman Trucking",
    "wof:placetype":"venue"
},
  "geometry": {"coordinates":[-88.072785,44.45924],"type":"Point"}
}