{
  "type": "Feature",
  "properties": {
    "iso:country":"US",
    "sg:address":"345 Lamers Clancy Rd",
    "sg:city":"Kaukauna",
    "sg:classifiers":[
        {
            "category":"Wholesale",
            "subcategory":"Durable Goods & Equipment",
            "type":"Manufacturing & Wholesale Goods"
        }
    ],
    "sg:phone":"+1 920 532 0296",
    "sg:postcode":"54130",
    "sg:province":"WI",
    "sg:tags":[
        "representative",
        "manufacturer"
    ],
    "wof:name":"Marty Huss Sales LLC",
    "wof:placetype":"venue"
},
  "geometry": {"coordinates":[-88.18887700000001,44.28513],"type":"Point"}
}