{
  "type": "Feature",
  "properties": {
    "iso:country":"US",
    "sg:address":"205 Hiawatha St",
    "sg:city":"Coon Valley",
    "sg:classifiers":[
        {
            "category":"Personal",
            "subcategory":"Beauty Salon",
            "type":"Services"
        }
    ],
    "sg:phone":"+1 608 452 3611",
    "sg:postcode":"54623",
    "sg:province":"WI",
    "wof:name":"Maripat's Beauty Shop",
    "wof:placetype":"venue"
},
  "geometry": {"coordinates":[-91.011976,43.701064],"type":"Point"}
}