{
  "type": "Feature",
  "properties": {
    "iso:country":"US",
    "sg:address":"236 W 23rd Ave",
    "sg:city":"Oshkosh",
    "sg:classifiers":[
        {
            "category":"Manufacturing",
            "subcategory":"Tools & Machinery",
            "type":"Manufacturing & Wholesale Goods"
        }
    ],
    "sg:phone":"+1 920 231 3540",
    "sg:postcode":"54902",
    "sg:province":"WI",
    "sg:tags":[
        "machine",
        "shop"
    ],
    "sg:website":"www.idealproducts.net",
    "wof:name":"Ideal Products Inc",
    "wof:placetype":"venue"
},
  "geometry": {"coordinates":[-88.54432,43.993153],"type":"Point"}
}