{
  "type": "Feature",
  "properties": {
    "addr:full":"6514 Schroeder Rd Madison WI 53711",
    "addr:housenumber":"6514",
    "addr:postcode":"53711",
    "addr:street":"Schroeder Rd",
    "iso:country":"US",
    "sg:address":"6514 Schroeder Rd",
    "sg:city":"Madison",
    "sg:classifiers":[
        {
            "category":"Social Services",
            "subcategory":"Child Care",
            "type":"Services"
        }
    ],
    "sg:phone":"+1 608 277 0076",
    "sg:postcode":"53711",
    "sg:province":"WI",
    "wof:name":"LA Petite Academy",
    "wof:placetype":"venue"
},
  "geometry": {"coordinates":[-89.493731,43.046352],"type":"Point"}
}