{
  "type": "Feature",
  "properties": {
    "addr:full":"442 E Wall St Ellsworth WI 54011",
    "addr:housenumber":"442",
    "addr:postcode":"54011",
    "addr:street":"E Wall St",
    "iso:country":"US",
    "sg:address":"442 E Wall St",
    "sg:city":"Ellsworth",
    "sg:classifiers":[
        {
            "category":"Sports & Exercise",
            "subcategory":"Gym",
            "type":"Entertainment"
        }
    ],
    "sg:phone":"+1 715 273 3222",
    "sg:postcode":"54011",
    "sg:province":"WI",
    "sg:tags":[
        "fitness",
        "facility"
    ],
    "wof:name":"Curves",
    "wof:placetype":"venue"
},
  "geometry": {"coordinates":[-92.46662499999999,44.735037],"type":"Point"}
}