{
  "type": "Feature",
  "properties": {
    "iso:country":"US",
    "sg:address":"924 N Main St",
    "sg:city":"Rice Lake",
    "sg:classifiers":[
        {
            "category":"Building & Trades",
            "subcategory":"Landscaping Services",
            "type":"Services"
        }
    ],
    "sg:phone":"+1 715 234 4962",
    "sg:postcode":"54868",
    "sg:province":"WI",
    "sg:tags":[
        "landscape",
        "contractor"
    ],
    "wof:name":"Cook's Landscaping N Bobcat",
    "wof:placetype":"venue"
},
  "geometry": {"coordinates":[-91.733777,45.512],"type":"Point"}
}