{
  "type": "Feature",
  "properties": {
    "addr:full":"2407 North Ln Eau Claire WI 54703",
    "addr:housenumber":"2407",
    "addr:postcode":"54703",
    "addr:street":"North Ln",
    "iso:country":"US",
    "sg:address":"2407 North Ln",
    "sg:city":"Eau Claire",
    "sg:classifiers":[
        {
            "category":"Education",
            "subcategory":"School",
            "type":"Public Place"
        }
    ],
    "sg:phone":"+1 715 830 2279",
    "sg:postcode":"54703",
    "sg:province":"WI",
    "sg:website":"www.case.k12.wi.us",
    "wof:name":"St Olaf School",
    "wof:placetype":"venue"
},
  "geometry": {"coordinates":[-91.476286,44.855745],"type":"Point"}
}