{
  "type": "Feature",
  "properties": {
    "iso:country":"US",
    "sg:address":"440 Mead St",
    "sg:city":"Wisconsin Rapids",
    "sg:classifiers":[
        {
            "category":"Education",
            "subcategory":"School",
            "type":"Public Place"
        }
    ],
    "sg:phone":"+1 715 422 0950",
    "sg:postcode":"54494",
    "sg:province":"WI",
    "wof:name":"Assumption Middle School",
    "wof:placetype":"venue"
},
  "geometry": {"coordinates":[-89.825745,44.384638],"type":"Point"}
}