{
  "type": "Feature",
  "properties": {
    "addr:full":"6341 Farmland Ave Sparta WI 54656",
    "addr:postcode":"6341;54656",
    "addr:street":"Farmland Ave",
    "iso:country":"US",
    "sg:address":"6341 Farmland Ave",
    "sg:city":"Sparta",
    "sg:classifiers":[
        {
            "category":"Retail",
            "subcategory":"Veterinary Services",
            "type":"Services"
        },
        {
            "category":"Building & Trades",
            "subcategory":"Construction",
            "type":"Services"
        }
    ],
    "sg:phone":"+1 608 269 5037",
    "sg:postcode":"54656",
    "sg:province":"WI",
    "sg:tags":[
        "veterinarian",
        "contractor"
    ],
    "wof:name":"Castle Rock Veterinary Service",
    "wof:placetype":"venue"
},
  "geometry": {"coordinates":[-90.86464599999999,43.985767],"type":"Point"}
}