{
  "type": "Feature",
  "properties": {
    "addr:full":"12800 US Hwy 53 Osseo WI 54758",
    "addr:housenumber":"12800",
    "addr:postcode":"54758",
    "addr:street":"Us Hwy 53",
    "iso:country":"US",
    "sg:address":"12800 US Hwy 53",
    "sg:city":"Osseo",
    "sg:classifiers":[
        {
            "category":"Bars & Pubs",
            "type":"Food & Drink"
        }
    ],
    "sg:phone":"+1 715 597 6627",
    "sg:postcode":"54758",
    "sg:province":"WI",
    "sg:tags":[
        "drinking"
    ],
    "wof:name":"Foster Bar & Grill",
    "wof:placetype":"venue"
},
  "geometry": {"coordinates":[-91.312243,44.642817],"type":"Point"}
}