{
  "type": "Feature",
  "properties": {
    "iso:country":"US",
    "sg:address":"520 Water St",
    "sg:city":"Sauk City",
    "sg:classifiers":[
        {
            "category":"Health Services",
            "subcategory":"Clinic",
            "type":"Services"
        }
    ],
    "sg:phone":"+1 608 643 8273",
    "sg:postcode":"53583",
    "sg:province":"WI",
    "sg:tags":[
        "hypnotherapy"
    ],
    "wof:name":"Receptive Learning Ctr",
    "wof:placetype":"venue"
},
  "geometry": {"coordinates":[-89.72006500000001,43.290264],"type":"Point"}
}