{
  "type": "Feature",
  "properties": {
    "iso:country":"US",
    "sg:address":"31311 Dillon Rd",
    "sg:city":"Lone Rock",
    "sg:classifiers":[
        {
            "category":"Farming",
            "subcategory":"Livestock Farm",
            "type":"Manufacturing & Wholesale Goods"
        }
    ],
    "sg:phone":"+1 608 583 3209",
    "sg:postcode":"53556",
    "sg:province":"WI",
    "sg:tags":[
        "beef",
        "feedlot",
        "cattle"
    ],
    "wof:name":"Kenneth Edgerly",
    "wof:placetype":"venue"
},
  "geometry": {"coordinates":[-90.236417,43.209668],"type":"Point"}
}