{
  "type": "Feature",
  "properties": {
    "iso:country":"US",
    "sg:address":"4944 4th St",
    "sg:city":"Leopolis",
    "sg:classifiers":[
        {
            "category":"Bars & Pubs",
            "type":"Food & Drink"
        }
    ],
    "sg:phone":"+1 715 787 4409",
    "sg:postcode":"54948",
    "sg:province":"WI",
    "sg:tags":[
        "drinking"
    ],
    "wof:name":"Old Ranch House",
    "wof:placetype":"venue"
},
  "geometry": {"coordinates":[-88.84612199999999,44.769076],"type":"Point"}
}