{
  "type": "Feature",
  "properties": {
    "iso:country":"US",
    "sg:address":"7186 Bluff Rd",
    "sg:city":"Whitewater",
    "sg:phone":"+1 262 473 3035",
    "sg:postcode":"53190",
    "sg:province":"WI",
    "sg:tags":[
        "farm",
        "corn",
        "soybean"
    ],
    "wof:name":"Coylehaven Farms Inc",
    "wof:placetype":"venue"
},
  "geometry": {"coordinates":[-88.645852,42.826141],"type":"Point"}
}