{
  "type": "Feature",
  "properties": {
    "iso:country":"US",
    "sg:address":"1417 N Wauwatosa Ave",
    "sg:city":"Milwaukee",
    "sg:classifiers":[
        {
            "category":"Wholesale",
            "subcategory":"Electrical",
            "type":"Manufacturing & Wholesale Goods"
        }
    ],
    "sg:phone":"+1 414 258 4100",
    "sg:postcode":"53213",
    "sg:province":"WI",
    "sg:tags":[
        "equipment"
    ],
    "wof:name":"Gille Engineering Sales Co",
    "wof:placetype":"venue"
},
  "geometry": {"coordinates":[-88.00749,43.050833],"type":"Point"}
}