{
  "type": "Feature",
  "properties": {
    "iso:country":"US",
    "sg:address":"1413 Tower Ave",
    "sg:city":"Superior",
    "sg:classifiers":[
        {
            "category":"Wholesale",
            "subcategory":"Hardware",
            "type":"Manufacturing & Wholesale Goods"
        }
    ],
    "sg:phone":"+1 715 394 5255",
    "sg:postcode":"54880",
    "sg:province":"WI",
    "sg:tags":[
        "equipment",
        "janitorial",
        "refrigerating",
        "supply"
    ],
    "wof:name":"Dunbar's Inc",
    "wof:placetype":"venue"
},
  "geometry": {"coordinates":[-92.103982,46.720843],"type":"Point"}
}