{
  "type": "Feature",
  "properties": {
    "iso:country":"US",
    "sg:address":"2107 Zeier Rd",
    "sg:city":"Madison",
    "sg:classifiers":[
        {
            "category":"Home & Garden",
            "subcategory":"Furniture",
            "type":"Retail Goods"
        }
    ],
    "sg:phone":"+1 608 442 1896",
    "sg:postcode":"53704",
    "sg:province":"WI",
    "wof:name":"Americas Mattress LLC",
    "wof:placetype":"venue"
},
  "geometry": {"coordinates":[-89.300007,43.125304],"type":"Point"}
}