{
  "type": "Feature",
  "properties": {
    "iso:country":"US",
    "sg:address":"3974 S 27th St",
    "sg:city":"Milwaukee",
    "sg:classifiers":[
        {
            "category":"Recreation",
            "type":"Entertainment"
        }
    ],
    "sg:phone":"+1 414 282 2220",
    "sg:postcode":"53221",
    "sg:province":"WI",
    "sg:tags":[
        "martial",
        "arts",
        "instruction"
    ],
    "wof:name":"United Tae KWON Do",
    "wof:placetype":"venue"
},
  "geometry": {"coordinates":[-87.94844399999999,42.970753],"type":"Point"}
}