{
  "type": "Feature",
  "properties": {
    "iso:country":"US",
    "sg:address":"1317 Menomonie St",
    "sg:city":"Eau Claire",
    "sg:classifiers":[
        {
            "category":"Retail",
            "subcategory":"Auto Repair",
            "type":"Services"
        }
    ],
    "sg:phone":"+1 715 838 8886",
    "sg:postcode":"54703",
    "sg:province":"WI",
    "sg:tags":[
        "wrecker"
    ],
    "wof:name":"Chad's Towing & Auto Repair",
    "wof:placetype":"venue"
},
  "geometry": {"coordinates":[-91.53027,44.799721],"type":"Point"}
}