{
  "type": "Feature",
  "properties": {
    "iso:country":"US",
    "sg:address":"2312 N Central Ave",
    "sg:city":"Marshfield",
    "sg:classifiers":[
        {
            "category":"Fast Food",
            "type":"Food & Drink"
        },
        {
            "category":"Restaurant",
            "type":"Food & Drink"
        }
    ],
    "sg:phone":"+1 715 384 6532",
    "sg:postcode":"54449",
    "sg:province":"WI",
    "sg:tags":[
        "dining",
        "mexican",
        "take",
        "fine"
    ],
    "wof:name":"El Mezcal",
    "wof:placetype":"venue"
},
  "geometry": {"coordinates":[-90.15472,44.691133],"type":"Point"}
}