{
  "type": "Feature",
  "properties": {
    "iso:country":"US",
    "sg:address":"2479 US Hwy 12",
    "sg:city":"Baraboo",
    "sg:classifiers":[
        {
            "category":"Retail",
            "subcategory":"Repair Shop",
            "type":"Services"
        }
    ],
    "sg:phone":"+1 608 356 5131",
    "sg:postcode":"53913",
    "sg:province":"WI",
    "sg:tags":[
        "lighting",
        "fixture"
    ],
    "wof:name":"Mobile Maintenance & Repair",
    "wof:placetype":"venue"
},
  "geometry": {"coordinates":[-89.778272,43.554324],"type":"Point"}
}