{
  "type": "Feature",
  "properties": {
    "iso:country":"US",
    "sg:address":"231 W Adams St",
    "sg:city":"Lake Delton",
    "sg:classifiers":[
        {
            "category":"Wholesale",
            "subcategory":"Machinery & Supplies",
            "type":"Manufacturing & Wholesale Goods"
        }
    ],
    "sg:phone":"+1 608 254 8158",
    "sg:postcode":"53965",
    "sg:province":"WI",
    "sg:tags":[
        "equipment",
        "welding"
    ],
    "sg:website":"www.drm-corp.com",
    "wof:name":"DRM Corp",
    "wof:placetype":"venue"
},
  "geometry": {"coordinates":[-89.79800899999999,43.590359],"type":"Point"}
}