{
  "type": "Feature",
  "properties": {
    "iso:country":"US",
    "sg:address":"4785 Greens Coulee Rd",
    "sg:city":"Onalaska",
    "sg:phone":"+1 608 783 3108",
    "sg:postcode":"54650",
    "sg:province":"WI",
    "sg:tags":[
        "farm",
        "soybean"
    ],
    "wof:name":"George Humfeld",
    "wof:placetype":"venue"
},
  "geometry": {"coordinates":[-91.20312800000001,43.894169],"type":"Point"}
}