{
  "type": "Feature",
  "properties": {
    "iso:country":"US",
    "sg:address":"225 Eagle Lake Ave",
    "sg:city":"Mukwonago",
    "sg:classifiers":[
        {
            "category":"Health Services",
            "subcategory":"Health Practitioner",
            "type":"Services"
        }
    ],
    "sg:phone":"+1 262 363 3360",
    "sg:postcode":"53149",
    "sg:province":"WI",
    "sg:tags":[
        "audiology",
        "aids",
        "provides",
        "hearing"
    ],
    "wof:name":"Hearing Services Limited",
    "wof:placetype":"venue"
},
  "geometry": {"coordinates":[-88.338127,42.866775],"type":"Point"}
}