{
  "type": "Feature",
  "properties": {
    "iso:country":"US",
    "sg:address":"1000 Fox St",
    "sg:city":"Mukwonago",
    "sg:classifiers":[
        {
            "category":"Banks & Credit Unions",
            "subcategory":"Bank",
            "type":"Services"
        }
    ],
    "sg:phone":"+1 262 363 3031",
    "sg:postcode":"53149",
    "sg:province":"WI",
    "wof:name":"Johnson Bank",
    "wof:placetype":"venue"
},
  "geometry": {"coordinates":[-88.324157,42.868444],"type":"Point"}
}