{
  "type": "Feature",
  "properties": {
    "addr:full":"10711 W Forest Home Ave Hales Corners WI 53130",
    "addr:housenumber":"10711",
    "addr:postcode":"53130",
    "addr:street":"W Forest Home Ave",
    "iso:country":"US",
    "sg:address":"10711 W Forest Home Ave",
    "sg:city":"Hales Corners",
    "sg:classifiers":[
        {
            "category":"Restaurant",
            "type":"Food & Drink"
        }
    ],
    "sg:phone":"+1 414 427 0088",
    "sg:postcode":"53130",
    "sg:province":"WI",
    "wof:name":"Takeout Taxi",
    "wof:placetype":"venue"
},
  "geometry": {"coordinates":[-88.048255,42.935884],"type":"Point"}
}