{
  "type": "Feature",
  "properties": {
    "iso:country":"US",
    "sg:address":"6857 Industrial Blvd",
    "sg:city":"Onalaska",
    "sg:classifiers":[
        {
            "category":"Retail",
            "subcategory":"Auto Repair",
            "type":"Services"
        }
    ],
    "sg:phone":"+1 608 781 4443",
    "sg:postcode":"54650",
    "sg:province":"WI",
    "sg:tags":[
        "transmission"
    ],
    "wof:name":"Don's Transmission Svc Inc",
    "wof:placetype":"venue"
},
  "geometry": {"coordinates":[-91.247277,43.921416],"type":"Point"}
}