{
  "type": "Feature",
  "properties": {
    "addr:full":"1803 US Hwy 12 Menomonie WI 54751",
    "addr:housenumber":"1803",
    "addr:postcode":"54751",
    "addr:street":"Us Hwy 12",
    "iso:country":"US",
    "sg:address":"1803 US Hwy 12",
    "sg:city":"Menomonie",
    "sg:classifiers":[
        {
            "category":"Retail",
            "subcategory":"Auto Repair",
            "type":"Services"
        }
    ],
    "sg:phone":"+1 715 235 9490",
    "sg:postcode":"54751",
    "sg:province":"WI",
    "sg:tags":[
        "truck"
    ],
    "sg:website":"www.northwesttrucks.com",
    "wof:name":"Northwest International Trucks",
    "wof:placetype":"venue"
},
  "geometry": {"coordinates":[-91.906199,44.880979],"type":"Point"}
}