{
  "type": "Feature",
  "properties": {
    "iso:country":"US",
    "sg:address":"125 S University Dr",
    "sg:city":"West Bend",
    "sg:classifiers":[
        {
            "category":"Organizations",
            "subcategory":"Community Association",
            "type":"Services"
        }
    ],
    "sg:phone":"+1 262 335 2114",
    "sg:postcode":"53095",
    "sg:province":"WI",
    "wof:name":"Embassy Condominium Homes Assn",
    "wof:placetype":"venue"
},
  "geometry": {"coordinates":[-88.211011,43.422283],"type":"Point"}
}