{
  "type": "Feature",
  "properties": {
    "addr:full":"411 19th St S Wisconsin Rapids WI 54494",
    "addr:housenumber":"411",
    "addr:postcode":"54494",
    "addr:street":"19Th St S",
    "iso:country":"US",
    "sg:address":"411 19th St S",
    "sg:city":"Wisconsin Rapids",
    "sg:classifiers":[
        {
            "category":"Personal",
            "type":"Services"
        }
    ],
    "sg:phone":"+1 715 424 3423",
    "sg:postcode":"54494",
    "sg:province":"WI",
    "sg:tags":[
        "health"
    ],
    "wof:name":"Primary Element",
    "wof:placetype":"venue"
},
  "geometry": {"coordinates":[-89.803029,44.386415],"type":"Point"}
}