{
  "type": "Feature",
  "properties": {
    "iso:country":"US",
    "sg:address":"112 E Clayton Ave",
    "sg:city":"Clayton",
    "sg:classifiers":[
        {
            "category":"Shopping",
            "subcategory":"Used Merchandise",
            "type":"Retail Goods"
        }
    ],
    "sg:phone":"+1 715 948 4201",
    "sg:postcode":"54004",
    "sg:province":"WI",
    "sg:tags":[
        "antique"
    ],
    "wof:name":"Wayne March Antiques",
    "wof:placetype":"venue"
},
  "geometry": {"coordinates":[-92.172079,45.331252],"type":"Point"}
}