{
  "type": "Feature",
  "properties": {
    "addr:full":"3298 State Hwy 13 Wisconsin Dells WI 53965",
    "addr:housenumber":"3298",
    "addr:postcode":"53965",
    "addr:street":"State Hwy 13",
    "iso:country":"US",
    "sg:address":"3298 State Hwy 13",
    "sg:city":"Wisconsin Dells",
    "sg:classifiers":[
        {
            "category":"Home & Garden",
            "subcategory":"Mobile Homes",
            "type":"Retail Goods"
        }
    ],
    "sg:phone":"+1 608 254 8346",
    "sg:postcode":"53965",
    "sg:province":"WI",
    "sg:website":"www.steenberghomes.com",
    "wof:name":"Steenberg Homes Inc",
    "wof:placetype":"venue"
},
  "geometry": {"coordinates":[-89.83768999999999,43.774575],"type":"Point"}
}