{
  "type": "Feature",
  "properties": {
    "addr:full":"221 Scott St Wausau WI 54403",
    "addr:housenumber":"221",
    "addr:postcode":"54403",
    "addr:street":"Scott St",
    "iso:country":"US",
    "sg:address":"221 Scott St",
    "sg:city":"Wausau",
    "sg:classifiers":[
        {
            "category":"Real Estate",
            "subcategory":"Real Estate Operator",
            "type":"Services"
        }
    ],
    "sg:phone":"+1 715 845 2267",
    "sg:postcode":"54403",
    "sg:province":"WI",
    "sg:tags":[
        "apartment"
    ],
    "wof:name":"Landmark Apartments",
    "wof:placetype":"venue"
},
  "geometry": {"coordinates":[-89.627979,44.960578],"type":"Point"}
}