{
  "type": "Feature",
  "properties": {
    "addr:full":"1369 12th St Barron WI 54812",
    "addr:housenumber":"1369",
    "addr:postcode":"54812",
    "addr:street":"12Th St",
    "iso:country":"US",
    "sg:address":"1369 12th St",
    "sg:city":"Barron",
    "sg:classifiers":[
        {
            "category":"Shopping",
            "type":"Retail Goods"
        }
    ],
    "sg:phone":"+1 715 637 6000",
    "sg:postcode":"54812",
    "sg:province":"WI",
    "sg:tags":[
        "merchandise"
    ],
    "wof:name":"Disabled Vets Enterprises",
    "wof:placetype":"venue"
},
  "geometry": {"coordinates":[-91.909649,45.403167],"type":"Point"}
}