{
  "type": "Feature",
  "properties": {
    "iso:country":"US",
    "sg:address":"4267 W Loomis Rd",
    "sg:city":"Milwaukee",
    "sg:classifiers":[
        {
            "category":"Home & Garden",
            "subcategory":"Building Materials",
            "type":"Retail Goods"
        }
    ],
    "sg:phone":"+1 414 281 3572",
    "sg:postcode":"53221",
    "sg:province":"WI",
    "sg:tags":[
        "lumber"
    ],
    "wof:name":"Ark Lumber",
    "wof:placetype":"venue"
},
  "geometry": {"coordinates":[-87.968675,42.961748],"type":"Point"}
}