{
  "type": "Feature",
  "properties": {
    "addr:full":"7121 118th Ave Kenosha WI 53142",
    "addr:housenumber":"7121",
    "addr:postcode":"53142",
    "addr:street":"118Th Ave",
    "iso:country":"US",
    "sg:address":"7121 118th Ave",
    "sg:city":"Kenosha",
    "sg:classifiers":[
        {
            "category":"Restaurant",
            "type":"Food & Drink"
        }
    ],
    "sg:menulink":"http://www.allmenus.com/wi/kenosha/10661-texas-roadhouse/menu/",
    "sg:phone":"+1 262 857 7700",
    "sg:postcode":"53142",
    "sg:province":"WI",
    "sg:tags":[
        "american",
        "steakhouse"
    ],
    "wof:name":"Texas Roadhouse",
    "wof:placetype":"venue"
},
  "geometry": {"coordinates":[-87.95107899999999,42.569344],"type":"Point"}
}