{
  "type": "Feature",
  "properties": {
    "iso:country":"US",
    "sg:address":"618 S 12th St",
    "sg:city":"Wausau",
    "sg:classifiers":[
        {
            "category":"Retail",
            "subcategory":"Portrait Studio",
            "type":"Services"
        }
    ],
    "sg:phone":"+1 715 842 1279",
    "sg:postcode":"54403",
    "sg:province":"WI",
    "sg:tags":[
        "photo"
    ],
    "wof:name":"Hasenberg Photography",
    "wof:placetype":"venue"
},
  "geometry": {"coordinates":[-89.612465,44.950911],"type":"Point"}
}