{
  "type": "Feature",
  "properties": {
    "iso:country":"US",
    "sg:address":"1541 Deane Blvd",
    "sg:city":"Racine",
    "sg:classifiers":[
        {
            "category":"Professional",
            "subcategory":"Business Services",
            "type":"Services"
        }
    ],
    "sg:phone":"+1 262 633 7783",
    "sg:postcode":"53405",
    "sg:province":"WI",
    "wof:name":"Dannys Group Home",
    "wof:placetype":"venue"
},
  "geometry": {"coordinates":[-87.814824,42.713],"type":"Point"}
}