{
  "type": "Feature",
  "properties": {
    "iso:country":"US",
    "sg:address":"6218 S Indiana Ave",
    "sg:city":"Cudahy",
    "sg:classifiers":[
        {
            "category":"Building & Trades",
            "subcategory":"Construction",
            "type":"Services"
        }
    ],
    "sg:phone":"+1 414 762 3521",
    "sg:postcode":"53110",
    "sg:province":"WI",
    "sg:tags":[
        "house"
    ],
    "wof:name":"Dittrich Construction LLC",
    "wof:placetype":"venue"
},
  "geometry": {"coordinates":[-87.87620099999999,42.933257],"type":"Point"}
}