{
  "type": "Feature",
  "properties": {
    "addr:full":"7822 Co Rd Mm Hortonville WI 54944",
    "addr:housenumber":"7822",
    "addr:postcode":"54944",
    "addr:street":"Co Rd",
    "iso:country":"US",
    "sg:address":"7822 Co Rd Mm",
    "sg:city":"Hortonville",
    "sg:classifiers":[
        {
            "category":"Insurance",
            "subcategory":"Insurance Agent",
            "type":"Services"
        }
    ],
    "sg:phone":"+1 920 757 5915",
    "sg:postcode":"54944",
    "sg:province":"WI",
    "wof:name":"Tony Lauer Insurance Agency",
    "wof:placetype":"venue"
},
  "geometry": {"coordinates":[-88.58459000000001,44.365683],"type":"Point"}
}