{
  "type": "Feature",
  "properties": {
    "iso:country":"US",
    "sg:address":"1609 Carver St",
    "sg:city":"Madison",
    "sg:classifiers":[
        {
            "category":"Real Estate",
            "subcategory":"Real Estate Agent",
            "type":"Services"
        }
    ],
    "sg:phone":"+1 608 251 1535",
    "sg:postcode":"53713",
    "sg:province":"WI",
    "wof:name":"Arboretum Real Estate Svc",
    "wof:placetype":"venue"
},
  "geometry": {"coordinates":[-89.409165,43.044563],"type":"Point"}
}