{
  "type": "Feature",
  "properties": {
    "iso:country":"US",
    "sg:address":"631 3rd St",
    "sg:city":"Luxemburg",
    "sg:classifiers":[
        {
            "category":"Sports & Exercise",
            "subcategory":"Race Track",
            "type":"Entertainment"
        }
    ],
    "sg:phone":"+1 920 845 2300",
    "sg:postcode":"54217",
    "sg:province":"WI",
    "sg:tags":[
        "operation",
        "racing",
        "or"
    ],
    "wof:name":"Luxemburg Tri Star Speedway",
    "wof:placetype":"venue"
},
  "geometry": {"coordinates":[-87.707618,44.540047],"type":"Point"}
}