{
  "type": "Feature",
  "properties": {
    "addr:full":"114 S Sheridan St Lancaster WI 53813",
    "addr:housenumber":"114",
    "addr:postcode":"53813",
    "addr:street":"S Sheridan St",
    "iso:country":"US",
    "sg:address":"114 S Sheridan St",
    "sg:city":"Lancaster",
    "sg:classifiers":[
        {
            "category":"Shopping",
            "subcategory":"Hobbies, Toys, & Games",
            "type":"Retail Goods"
        }
    ],
    "sg:phone":"+1 608 723 2657",
    "sg:postcode":"53813",
    "sg:province":"WI",
    "wof:name":"Wigwam Ceramics",
    "wof:placetype":"venue"
},
  "geometry": {"coordinates":[-90.700132,42.847919],"type":"Point"}
}