{
  "type": "Feature",
  "properties": {
    "iso:country":"US",
    "sg:address":"4350 W Greenville Dr",
    "sg:city":"Appleton",
    "sg:classifiers":[
        {
            "category":"Shopping",
            "subcategory":"Bicycles & Sporting Goods",
            "type":"Retail Goods"
        },
        {
            "category":"Shopping",
            "subcategory":"Clothing, Apparel, & Fashions",
            "type":"Retail Goods"
        }
    ],
    "sg:phone":"+1 920 954 9266",
    "sg:postcode":"54913",
    "sg:province":"WI",
    "sg:tags":[
        "sport"
    ],
    "sg:website":"www.dsportinggoods.com",
    "wof:name":"Dick's Sporting Goods Inc",
    "wof:placetype":"venue"
},
  "geometry": {"coordinates":[-88.47191599999999,44.273539],"type":"Point"}
}