{
  "type": "Feature",
  "properties": {
    "iso:country":"US",
    "sg:address":"2305 Savanna Dr",
    "sg:city":"Janesville",
    "sg:classifiers":[
        {
            "category":"Building & Trades",
            "subcategory":"Construction",
            "type":"Services"
        }
    ],
    "sg:phone":"+1 608 752 4331",
    "sg:postcode":"53546",
    "sg:province":"WI",
    "sg:tags":[
        "house"
    ],
    "wof:name":"Gunderson Construction",
    "wof:placetype":"venue"
},
  "geometry": {"coordinates":[-88.969024,42.710261],"type":"Point"}
}