{
  "type": "Feature",
  "properties": {
    "iso:country":"US",
    "sg:address":"3749 S Whitnall Ave",
    "sg:city":"Milwaukee",
    "sg:classifiers":[
        {
            "category":"Manufacturing",
            "subcategory":"Retail Goods",
            "type":"Manufacturing & Wholesale Goods"
        }
    ],
    "sg:phone":"+1 414 483 8534",
    "sg:postcode":"53207",
    "sg:province":"WI",
    "sg:tags":[
        "product",
        "mfg"
    ],
    "wof:name":"King Neptune",
    "wof:placetype":"venue"
},
  "geometry": {"coordinates":[-87.905827,42.976913],"type":"Point"}
}