{
  "type": "Feature",
  "properties": {
    "iso:country":"US",
    "sg:address":"100 W Fernau Ave",
    "sg:city":"Oshkosh",
    "sg:classifiers":[
        {
            "category":"Social Services",
            "subcategory":"Job Training",
            "type":"Services"
        }
    ],
    "sg:phone":"+1 920 231 0870",
    "sg:postcode":"54901",
    "sg:province":"WI",
    "sg:tags":[
        "child",
        "day",
        "care"
    ],
    "wof:name":"Lakeside Packaging Plus Inc",
    "wof:placetype":"venue"
},
  "geometry": {"coordinates":[-88.54003299999999,44.058523],"type":"Point"}
}