{
  "type": "Feature",
  "properties": {
    "iso:country":"US",
    "sg:address":"1893 Hilltop Rd",
    "sg:city":"Shell Lake",
    "sg:classifiers":[
        {
            "category":"Home & Garden",
            "subcategory":"Building Materials",
            "type":"Retail Goods"
        }
    ],
    "sg:phone":"+1 715 468 2589",
    "sg:postcode":"54871",
    "sg:province":"WI",
    "sg:tags":[
        "kitchen",
        "cabinet"
    ],
    "wof:name":"Kitchen Mercantile",
    "wof:placetype":"venue"
},
  "geometry": {"coordinates":[-92.090586,45.725513],"type":"Point"}
}