{
  "type": "Feature",
  "properties": {
    "addr:full":"830 N Jackson St Milwaukee WI 53202",
    "addr:housenumber":"830",
    "addr:postcode":"53202",
    "addr:street":"N Jackson St",
    "iso:country":"US",
    "sg:address":"830 N Jackson St",
    "sg:city":"Milwaukee",
    "sg:classifiers":[
        {
            "category":"Social Services",
            "type":"Services"
        }
    ],
    "sg:phone":"+1 414 223 5105",
    "sg:postcode":"53202",
    "sg:province":"WI",
    "wof:name":"Catholic Aids Ministry",
    "wof:placetype":"venue"
},
  "geometry": {"coordinates":[-87.904293,43.04224],"type":"Point"}
}