{
  "type": "Feature",
  "properties": {
    "iso:country":"US",
    "sg:address":"1924 Co Rd F",
    "sg:city":"Sullivan",
    "sg:classifiers":[
        {
            "category":"Shopping",
            "subcategory":"Crafts & Fabrics",
            "type":"Retail Goods"
        }
    ],
    "sg:phone":"+1 262 593 2424",
    "sg:postcode":"53178",
    "sg:province":"WI",
    "sg:tags":[
        "sewing",
        "novelty",
        "supply"
    ],
    "wof:name":"Sandys Corner",
    "wof:placetype":"venue"
},
  "geometry": {"coordinates":[-88.631633,42.979867],"type":"Point"}
}