{
  "type": "Feature",
  "properties": {
    "iso:country":"US",
    "sg:address":"5975 Lake Dr",
    "sg:city":"Shawano",
    "sg:classifiers":[
        {
            "category":"Freight",
            "type":"Transportation"
        }
    ],
    "sg:phone":"+1 715 526 9464",
    "sg:postcode":"54166",
    "sg:province":"WI",
    "sg:tags":[
        "local",
        "mover",
        "storage",
        "trucking"
    ],
    "wof:name":"J & K Carlstrom Trucking Inc",
    "wof:placetype":"venue"
},
  "geometry": {"coordinates":[-88.568942,44.799585],"type":"Point"}
}