{
  "type": "Feature",
  "properties": {
    "iso:country":"US",
    "sg:address":"15 N Pinckney St",
    "sg:city":"Madison",
    "sg:classifiers":[
        {
            "category":"Personal",
            "subcategory":"Beauty Salon",
            "type":"Services"
        }
    ],
    "sg:phone":"+1 608 251 1113",
    "sg:postcode":"53703",
    "sg:province":"WI",
    "sg:tags":[
        "shop"
    ],
    "wof:name":"Salon Solo",
    "wof:placetype":"venue"
},
  "geometry": {"coordinates":[-89.383885,43.076166],"type":"Point"}
}