{
  "type": "Feature",
  "properties": {
    "addr:full":"7635 W Oklahoma Ave Milwaukee WI 53219",
    "addr:housenumber":"7635",
    "addr:postcode":"53219",
    "addr:street":"W Oklahoma Ave",
    "iso:country":"US",
    "sg:address":"7635 W Oklahoma Ave",
    "sg:city":"Milwaukee",
    "sg:classifiers":[
        {
            "category":"Professional",
            "subcategory":"Business Services",
            "type":"Services"
        }
    ],
    "sg:phone":"+1 414 541 9191",
    "sg:postcode":"53219",
    "sg:province":"WI",
    "wof:name":"Domke Financial Services",
    "wof:placetype":"venue"
},
  "geometry": {"coordinates":[-88.008667,42.988209],"type":"Point"}
}