{
  "type": "Feature",
  "properties": {
    "iso:country":"US",
    "sg:address":"303 W State St",
    "sg:city":"Fox Lake",
    "sg:classifiers":[
        {
            "category":"Cinema",
            "subcategory":"Movie Rental",
            "type":"Entertainment"
        }
    ],
    "sg:phone":"+1 920 928 3200",
    "sg:postcode":"53933",
    "sg:province":"WI",
    "sg:tags":[
        "video",
        "tape"
    ],
    "wof:name":"After Hours Video",
    "wof:placetype":"venue"
},
  "geometry": {"coordinates":[-88.910455,43.565987],"type":"Point"}
}