{
  "type": "Feature",
  "properties": {
    "iso:country":"US",
    "sg:address":"350 W Green Tree Rd",
    "sg:city":"Milwaukee",
    "sg:classifiers":[
        {
            "category":"Professional",
            "subcategory":"Management & Consulting",
            "type":"Services"
        }
    ],
    "sg:phone":"+1 414 352 0970",
    "sg:postcode":"53217",
    "sg:province":"WI",
    "wof:name":"Lincoln Financial",
    "wof:placetype":"venue"
},
  "geometry": {"coordinates":[-87.911434,43.144107],"type":"Point"}
}