{
  "type": "Feature",
  "properties": {
    "iso:country":"US",
    "sg:address":"7745 Co Hwy Bc",
    "sg:city":"Sparta",
    "sg:classifiers":[
        {
            "category":"Building & Trades",
            "subcategory":"Construction",
            "type":"Services"
        }
    ],
    "sg:phone":"+1 608 269 3287",
    "sg:postcode":"54656",
    "sg:province":"WI",
    "sg:tags":[
        "contractor"
    ],
    "wof:name":"Oswald Insulating",
    "wof:placetype":"venue"
},
  "geometry": {"coordinates":[-90.834942,43.954154],"type":"Point"}
}