{
  "type": "Feature",
  "properties": {
    "iso:country":"US",
    "sg:address":"3026 N 63rd St",
    "sg:city":"Milwaukee",
    "sg:classifiers":[
        {
            "category":"Professional",
            "subcategory":"Business Services",
            "type":"Services"
        }
    ],
    "sg:phone":"+1 414 873 0595",
    "sg:postcode":"53210",
    "sg:province":"WI",
    "sg:tags":[
        "appraiser"
    ],
    "wof:name":"Next Day Appraisals Inc",
    "wof:placetype":"venue"
},
  "geometry": {"coordinates":[-87.990618,43.075322],"type":"Point"}
}