{
  "type": "Feature",
  "properties": {
    "addr:full":"211 Hendricks St Waterloo WI 53594",
    "addr:housenumber":"211",
    "addr:postcode":"53594",
    "addr:street":"Hendricks St",
    "iso:country":"US",
    "sg:address":"211 Hendricks St",
    "sg:city":"Waterloo",
    "sg:classifiers":[
        {
            "category":"Government",
            "subcategory":"Office",
            "type":"Public Place"
        }
    ],
    "sg:phone":"+1 920 478 9797",
    "sg:postcode":"53594",
    "sg:province":"WI",
    "sg:tags":[
        "village"
    ],
    "wof:name":"City Garage",
    "wof:placetype":"venue"
},
  "geometry": {"coordinates":[-88.984525,43.186582],"type":"Point"}
}