{
  "type": "Feature",
  "properties": {
    "iso:country":"US",
    "sg:address":"418 Woods End",
    "sg:city":"Viroqua",
    "sg:classifiers":[
        {
            "category":"Retail",
            "subcategory":"Veterinary Services",
            "type":"Services"
        }
    ],
    "sg:phone":"+1 608 637 7300",
    "sg:postcode":"54665",
    "sg:province":"WI",
    "wof:name":"David L Brown DVM",
    "wof:placetype":"venue"
},
  "geometry": {"coordinates":[-90.896018,43.554469],"type":"Point"}
}