{
  "type": "Feature",
  "properties": {
    "iso:country":"US",
    "sg:address":"1613 Walnut St",
    "sg:city":"Oshkosh",
    "sg:classifiers":[
        {
            "category":"Building & Trades",
            "subcategory":"Construction",
            "type":"Services"
        }
    ],
    "sg:phone":"+1 920 231 0699",
    "sg:postcode":"54901",
    "sg:province":"WI",
    "sg:tags":[
        "home",
        "improvement"
    ],
    "wof:name":"Home Improvement",
    "wof:placetype":"venue"
},
  "geometry": {"coordinates":[-88.55153199999999,44.038291],"type":"Point"}
}