{
  "type": "Feature",
  "properties": {
    "addr:full":"312 Wisconsin St Butternut WI 54514",
    "addr:housenumber":"312",
    "addr:postcode":"54514",
    "addr:street":"Wisconsin St",
    "iso:country":"US",
    "sg:address":"312 Wisconsin St",
    "sg:city":"Butternut",
    "sg:classifiers":[
        {
            "category":"Education",
            "subcategory":"School",
            "type":"Public Place"
        }
    ],
    "sg:phone":"+1 715 769 3434",
    "sg:postcode":"54514",
    "sg:province":"WI",
    "sg:website":"www.butternut.k12.wi.us",
    "wof:name":"Butternut High School",
    "wof:placetype":"venue"
},
  "geometry": {"coordinates":[-90.49583,46.015857],"type":"Point"}
}