{
  "type": "Feature",
  "properties": {
    "addr:full":"7186 S 27th St Oak Creek WI 53154",
    "addr:housenumber":"7186",
    "addr:postcode":"53154",
    "addr:street":"S 27Th St",
    "iso:country":"US",
    "sg:address":"7186 S 27th St",
    "sg:city":"Oak Creek",
    "sg:classifiers":[
        {
            "category":"Shopping",
            "type":"Retail Goods"
        }
    ],
    "sg:phone":"+1 414 761 0825",
    "sg:postcode":"53154",
    "sg:province":"WI",
    "sg:tags":[
        "equipment",
        "care",
        "health",
        "home"
    ],
    "wof:name":"Advacare Systems",
    "wof:placetype":"venue"
},
  "geometry": {"coordinates":[-87.94990300000001,42.914581],"type":"Point"}
}