{
  "type": "Feature",
  "properties": {
    "iso:country":"US",
    "sg:address":"1119 W Kennedy Ave",
    "sg:city":"Kimberly",
    "sg:classifiers":[
        {
            "category":"Wholesale",
            "subcategory":"Stationery",
            "type":"Manufacturing & Wholesale Goods"
        },
        {
            "category":"Wholesale",
            "subcategory":"Scrap",
            "type":"Manufacturing & Wholesale Goods"
        }
    ],
    "sg:phone":"+1 920 722 8225",
    "sg:postcode":"54136",
    "sg:province":"WI",
    "sg:tags":[
        "paper",
        "waste"
    ],
    "wof:name":"North American Paper Co",
    "wof:placetype":"venue"
},
  "geometry": {"coordinates":[-88.353194,44.261534],"type":"Point"}
}