{
  "type": "Feature",
  "properties": {
    "addr:full":"1575 Co Rd N N Neosho WI 53059",
    "addr:housenumber":"1575",
    "addr:postcode":"53059",
    "addr:street":"Co Rd N N",
    "iso:country":"US",
    "sg:address":"1575 Co Rd N N",
    "sg:city":"Neosho",
    "sg:classifiers":[
        {
            "category":"Professional",
            "subcategory":"Business Services",
            "type":"Services"
        }
    ],
    "sg:phone":"+1 920 625 2088",
    "sg:postcode":"53059",
    "sg:province":"WI",
    "sg:tags":[
        "tool",
        "designer",
        "design"
    ],
    "wof:name":"Simpson Design",
    "wof:placetype":"venue"
},
  "geometry": {"coordinates":[-88.469548,43.286764],"type":"Point"}
}