{
  "type": "Feature",
  "properties": {
    "iso:country":"US",
    "sg:address":"421 Nebraska St",
    "sg:city":"Sturgeon Bay",
    "sg:classifiers":[
        {
            "category":"Social Services",
            "type":"Services"
        }
    ],
    "sg:phone":"+1 920 746 2345",
    "sg:postcode":"54235",
    "sg:province":"WI",
    "sg:tags":[
        "counseling"
    ],
    "sg:website":"www.doorcounty.org",
    "wof:name":"Door County Community Programs",
    "wof:placetype":"venue"
},
  "geometry": {"coordinates":[-87.37327999999999,44.834371],"type":"Point"}
}