{
  "type": "Feature",
  "properties": {
    "iso:country":"US",
    "sg:address":"2138 Melody Ln",
    "sg:city":"Waukesha",
    "sg:classifiers":[
        {
            "category":"Shopping",
            "type":"Retail Goods"
        }
    ],
    "sg:phone":"+1 262 547 6079",
    "sg:postcode":"53186",
    "sg:province":"WI",
    "sg:tags":[
        "picture",
        "frame"
    ],
    "wof:name":"Cedar Springs Framing",
    "wof:placetype":"venue"
},
  "geometry": {"coordinates":[-88.195104,43.031597],"type":"Point"}
}