{
  "type": "Feature",
  "properties": {
    "iso:country":"US",
    "sg:address":"806 3rd St",
    "sg:city":"Pepin",
    "sg:classifiers":[
        {
            "category":"Museum",
            "type":"Entertainment"
        }
    ],
    "sg:phone":"+1 715 442 6501",
    "sg:postcode":"54759",
    "sg:province":"WI",
    "wof:name":"Pepin Depot Museum",
    "wof:placetype":"venue"
},
  "geometry": {"coordinates":[-92.15333,44.442436],"type":"Point"}
}