{
  "type": "Feature",
  "properties": {
    "iso:country":"US",
    "sg:address":"230 E Sumner St",
    "sg:city":"Hartford",
    "sg:classifiers":[
        {
            "category":"Arts & Performance",
            "subcategory":"Theater",
            "type":"Entertainment"
        }
    ],
    "sg:phone":"+1 262 673 5200",
    "sg:postcode":"53027",
    "sg:province":"WI",
    "sg:tags":[
        "bureau"
    ],
    "wof:name":"Heartbeat Entertainment",
    "wof:placetype":"venue"
},
  "geometry": {"coordinates":[-88.374488,43.317694],"type":"Point"}
}