{
  "type": "Feature",
  "properties": {
    "addr:full":"2608 Co Rd P Merrill WI 54452",
    "addr:housenumber":"2608",
    "addr:postcode":"54452",
    "addr:street":"Co Rd",
    "iso:country":"US",
    "sg:address":"2608 Co Rd P",
    "sg:city":"Merrill",
    "sg:classifiers":[
        {
            "category":"Organizations",
            "subcategory":"Religious Organization",
            "type":"Services"
        }
    ],
    "sg:phone":"+1 715 536 8459",
    "sg:postcode":"54452",
    "sg:province":"WI",
    "sg:tags":[
        "a",
        "lutheran",
        "as",
        "church",
        "operates"
    ],
    "wof:name":"St Pauls Evang Lutheran Church",
    "wof:placetype":"venue"
},
  "geometry": {"coordinates":[-89.565252,45.1343],"type":"Point"}
}