{
  "type": "Feature",
  "properties": {
    "addr:full":"1080 Eastman St Platteville WI 53818",
    "addr:housenumber":"1080",
    "addr:postcode":"53818",
    "addr:street":"Eastman St",
    "iso:country":"US",
    "sg:address":"1080 Eastman St",
    "sg:city":"Platteville",
    "sg:classifiers":[
        {
            "category":"Organizations",
            "subcategory":"Religious Organization",
            "type":"Services"
        }
    ],
    "sg:phone":"+1 608 348 7064",
    "sg:postcode":"53818",
    "sg:province":"WI",
    "wof:name":"Eternalist Foundation Inc",
    "wof:placetype":"venue"
},
  "geometry": {"coordinates":[-90.48884200000001,42.745177],"type":"Point"}
}