{
  "type": "Feature",
  "properties": {
    "iso:country":"US",
    "sg:address":"662 Capitol Dr",
    "sg:city":"Pewaukee",
    "sg:classifiers":[
        {
            "category":"Banks & Credit Unions",
            "subcategory":"Financial Services",
            "type":"Services"
        }
    ],
    "sg:phone":"+1 262 264 0045",
    "sg:postcode":"53072",
    "sg:province":"WI",
    "sg:tags":[
        "investor"
    ],
    "wof:name":"RMJ Investments",
    "wof:placetype":"venue"
},
  "geometry": {"coordinates":[-88.253478,43.08331],"type":"Point"}
}