{
  "type": "Feature",
  "properties": {
    "addr:full":"307 W Milwaukee St Watertown WI 53094",
    "addr:housenumber":"307",
    "addr:postcode":"53094",
    "addr:street":"W Milwaukee St",
    "iso:country":"US",
    "sg:address":"307 W Milwaukee St",
    "sg:city":"Watertown",
    "sg:classifiers":[
        {
            "category":"Social Services",
            "subcategory":"Child Care",
            "type":"Services"
        }
    ],
    "sg:phone":"+1 920 261 6557",
    "sg:postcode":"53094",
    "sg:province":"WI",
    "sg:tags":[
        "day"
    ],
    "wof:name":"Tender Loving Day Care",
    "wof:placetype":"venue"
},
  "geometry": {"coordinates":[-88.72938499999999,43.189961],"type":"Point"}
}