{
  "type": "Feature",
  "properties": {
    "iso:country":"US",
    "sg:address":"120 E Lakeside St",
    "sg:city":"Madison",
    "sg:classifiers":[
        {
            "category":"Professional",
            "type":"Services"
        }
    ],
    "sg:phone":"+1 608 294 4086",
    "sg:postcode":"53715",
    "sg:province":"WI",
    "wof:name":"Chris Armstrong",
    "wof:placetype":"venue"
},
  "geometry": {"coordinates":[-89.38394099999999,43.056003],"type":"Point"}
}