{
  "type": "Feature",
  "properties": {
    "iso:country":"US",
    "sg:address":"713 Riverside Dr N",
    "sg:city":"Hudson",
    "sg:classifiers":[
        {
            "category":"Professional",
            "subcategory":"Lawyer & Legal Services",
            "type":"Services"
        }
    ],
    "sg:phone":"+1 715 386 2955",
    "sg:postcode":"54016",
    "sg:province":"WI",
    "wof:name":"Thomas A Dahle",
    "wof:placetype":"venue"
},
  "geometry": {"coordinates":[-92.75097599999999,44.989631],"type":"Point"}
}