{
  "type": "Feature",
  "properties": {
    "iso:country":"US",
    "sg:address":"589 Schommer Dr",
    "sg:city":"Hudson",
    "sg:classifiers":[
        {
            "category":"Manufacturing",
            "subcategory":"Metals",
            "type":"Manufacturing & Wholesale Goods"
        }
    ],
    "sg:phone":"+1 715 386 7611",
    "sg:postcode":"54016",
    "sg:province":"WI",
    "sg:tags":[
        "steel"
    ],
    "wof:name":"St Croix Custom Fabrication",
    "wof:placetype":"venue"
},
  "geometry": {"coordinates":[-92.681128,44.990301],"type":"Point"}
}