{
  "type": "Feature",
  "properties": {
    "iso:country":"US",
    "sg:address":"2313 Pendleton Pl",
    "sg:city":"Waukesha",
    "sg:classifiers":[
        {
            "category":"Wholesale",
            "subcategory":"Stationery",
            "type":"Manufacturing & Wholesale Goods"
        }
    ],
    "sg:phone":"+1 262 650 1776",
    "sg:postcode":"53188",
    "sg:province":"WI",
    "sg:tags":[
        "packaging",
        "material"
    ],
    "wof:name":"Ro-Don Inc",
    "wof:placetype":"venue"
},
  "geometry": {"coordinates":[-88.266712,43.003336],"type":"Point"}
}