{
  "type": "Feature",
  "properties": {
    "iso:country":"US",
    "sg:address":"301 N Green Bay Ave",
    "sg:city":"Gillett",
    "sg:classifiers":[
        {
            "category":"Building & Trades",
            "subcategory":"Construction",
            "type":"Services"
        }
    ],
    "sg:phone":"+1 920 855 2649",
    "sg:postcode":"54124",
    "sg:province":"WI",
    "sg:tags":[
        "hanging",
        "contractor"
    ],
    "wof:name":"Spectrum Painting",
    "wof:placetype":"venue"
},
  "geometry": {"coordinates":[-88.297144,44.896083],"type":"Point"}
}