{
  "type": "Feature",
  "properties": {
    "addr:full":"9007 Thoroughfare Rd Minocqua WI 54548",
    "addr:postcode":"9007;54548",
    "addr:street":"Thoroughfare Rd",
    "iso:country":"US",
    "sg:address":"9007 Thoroughfare Rd",
    "sg:city":"Minocqua",
    "sg:classifiers":[
        {
            "category":"Professional",
            "subcategory":"Business Services",
            "type":"Services"
        }
    ],
    "sg:phone":"+1 715 356 3869",
    "sg:postcode":"54548",
    "sg:province":"WI",
    "wof:name":"Jidel Enterprises LLC",
    "wof:placetype":"venue"
},
  "geometry": {"coordinates":[-89.677201,45.855171],"type":"Point"}
}