{
  "type": "Feature",
  "properties": {
    "iso:country":"US",
    "sg:address":"601 S 8th St",
    "sg:city":"Sheboygan",
    "sg:classifiers":[
        {
            "category":"Social Services",
            "type":"Services"
        }
    ],
    "sg:phone":"+1 920 458 5062",
    "sg:postcode":"53081",
    "sg:province":"WI",
    "sg:tags":[
        "welfare"
    ],
    "wof:name":"Childrens Svc Soc Wisconsin",
    "wof:placetype":"venue"
},
  "geometry": {"coordinates":[-87.712943,43.747602],"type":"Point"}
}