{
  "type": "Feature",
  "properties": {
    "iso:country":"US",
    "sg:address":"1923 Northpoint St",
    "sg:city":"Oshkosh",
    "sg:classifiers":[
        {
            "category":"Professional",
            "subcategory":"Business Services",
            "type":"Services"
        }
    ],
    "sg:phone":"+1 920 426 0991",
    "sg:postcode":"54901",
    "sg:province":"WI",
    "wof:name":"MPW Financial Planning Inc",
    "wof:placetype":"venue"
},
  "geometry": {"coordinates":[-88.518405,44.042805],"type":"Point"}
}