{
  "type": "Feature",
  "properties": {
    "addr:full":"8804 Holtz Rd Oconto Falls WI 54154",
    "addr:postcode":"8804;54154",
    "addr:street":"Holtz Rd",
    "iso:country":"US",
    "sg:address":"8804 Holtz Rd",
    "sg:city":"Oconto Falls",
    "sg:classifiers":[
        {
            "category":"Farming",
            "subcategory":"Farm",
            "type":"Manufacturing & Wholesale Goods"
        }
    ],
    "sg:phone":"+1 920 846 2592",
    "sg:postcode":"54154",
    "sg:province":"WI",
    "wof:name":"H W Farms",
    "wof:placetype":"venue"
},
  "geometry": {"coordinates":[-88.197299,44.851574],"type":"Point"}
}