{
  "type": "Feature",
  "properties": {
    "iso:country":"US",
    "sg:address":"1275 Franklin Dr",
    "sg:city":"Cleveland",
    "sg:classifiers":[
        {
            "category":"Organizations",
            "subcategory":"Community Association",
            "type":"Services"
        }
    ],
    "sg:phone":"+1 920 693 3300",
    "sg:postcode":"53015",
    "sg:province":"WI",
    "wof:name":"Tpa",
    "wof:placetype":"venue"
},
  "geometry": {"coordinates":[-87.726725,43.917445],"type":"Point"}
}