{
  "type": "Feature",
  "properties": {
    "iso:country":"US",
    "sg:address":"201 N Main St",
    "sg:city":"Waupaca",
    "sg:classifiers":[
        {
            "category":"Professional",
            "subcategory":"Business Services",
            "type":"Services"
        }
    ],
    "sg:phone":"+1 715 256 1212",
    "sg:postcode":"54981",
    "sg:province":"WI",
    "sg:tags":[
        "embroidery"
    ],
    "wof:name":"New Direction Cstm Embroidery",
    "wof:placetype":"venue"
},
  "geometry": {"coordinates":[-89.08493799999999,44.359744],"type":"Point"}
}