{
  "type": "Feature",
  "properties": {
    "iso:country":"US",
    "sg:address":"900 Riverside Dr",
    "sg:city":"Waupaca",
    "sg:classifiers":[
        {
            "category":"Health Services",
            "subcategory":"Podiatrist",
            "type":"Services"
        }
    ],
    "sg:phone":"+1 715 258 5210",
    "sg:postcode":"54981",
    "sg:province":"WI",
    "wof:name":"Plaza Podiatry Assoc",
    "wof:placetype":"venue"
},
  "geometry": {"coordinates":[-89.075147,44.345327],"type":"Point"}
}