{
  "type": "Feature",
  "properties": {
    "iso:country":"US",
    "sg:address":"5309 12th St",
    "sg:city":"Kenosha",
    "sg:classifiers":[
        {
            "category":"Building & Trades",
            "subcategory":"Construction",
            "type":"Services"
        }
    ],
    "sg:phone":"+1 262 553 9841",
    "sg:postcode":"53144",
    "sg:province":"WI",
    "sg:tags":[
        "house"
    ],
    "wof:name":"Vanderhoef Construction",
    "wof:placetype":"venue"
},
  "geometry": {"coordinates":[-87.87378,42.639595],"type":"Point"}
}