{
  "type": "Feature",
  "properties": {
    "iso:country":"US",
    "sg:address":"251 Oconner Dr",
    "sg:city":"Elkhorn",
    "sg:classifiers":[
        {
            "category":"Manufacturing",
            "subcategory":"Metals",
            "type":"Manufacturing & Wholesale Goods"
        },
        {
            "category":"Wholesale",
            "subcategory":"Farm Supplies",
            "type":"Manufacturing & Wholesale Goods"
        }
    ],
    "sg:phone":"+1 262 743 1234",
    "sg:postcode":"53121",
    "sg:province":"WI",
    "sg:tags":[
        "equipment",
        "plastic",
        "greenhouse",
        "liner",
        "mfg"
    ],
    "wof:name":"Yunker Plastics Inc",
    "wof:placetype":"venue"
},
  "geometry": {"coordinates":[-88.53774300000001,42.650089],"type":"Point"}
}