{
  "type": "Feature",
  "properties": {
    "iso:country":"US",
    "sg:address":"20710 County Line Rd",
    "sg:city":"Kansasville",
    "sg:classifiers":[
        {
            "category":"Manufacturing",
            "subcategory":"Metals",
            "type":"Manufacturing & Wholesale Goods"
        }
    ],
    "sg:phone":"+1 262 878 0161",
    "sg:postcode":"53139",
    "sg:province":"WI",
    "sg:tags":[
        "machine",
        "shop"
    ],
    "wof:name":"Nkw Machine Inc",
    "wof:placetype":"venue"
},
  "geometry": {"coordinates":[-88.064998,42.66983],"type":"Point"}
}