{
  "type": "Feature",
  "properties": {
    "iso:country":"US",
    "sg:address":"1288 Rudy St",
    "sg:city":"Onalaska",
    "sg:classifiers":[
        {
            "category":"Government",
            "subcategory":"Office",
            "type":"Public Place"
        }
    ],
    "sg:phone":"+1 608 781 0777",
    "sg:postcode":"54650",
    "sg:province":"WI",
    "sg:tags":[
        "federal",
        "security"
    ],
    "wof:name":"US Army Corp Of Engineers",
    "wof:placetype":"venue"
},
  "geometry": {"coordinates":[-91.19774200000001,43.875854],"type":"Point"}
}