{
  "type": "Feature",
  "properties": {
    "iso:country":"US",
    "sg:address":"11931 W Bluemound Rd",
    "sg:city":"Milwaukee",
    "sg:classifiers":[
        {
            "category":"Personal",
            "type":"Services"
        }
    ],
    "sg:phone":"+1 414 257 3737",
    "sg:postcode":"53226",
    "sg:province":"WI",
    "wof:name":"Sun Kissed Tanning Salon",
    "wof:placetype":"venue"
},
  "geometry": {"coordinates":[-88.062476,43.036207],"type":"Point"}
}