{
  "type": "Feature",
  "properties": {
    "iso:country":"US",
    "sg:address":"1177 105th Ave",
    "sg:city":"Amery",
    "sg:classifiers":[
        {
            "category":"Farming",
            "subcategory":"Livestock Farm",
            "type":"Manufacturing & Wholesale Goods"
        }
    ],
    "sg:phone":"+1 715 268 8250",
    "sg:postcode":"54001",
    "sg:province":"WI",
    "sg:tags":[
        "dairy",
        "beef",
        "feedlot",
        "cattle"
    ],
    "wof:name":"George Weigang",
    "wof:placetype":"venue"
},
  "geometry": {"coordinates":[-92.403459,45.361273],"type":"Point"}
}