{
  "type": "Feature",
  "properties": {
    "iso:country":"US",
    "sg:address":"531 Commerce Pkwy",
    "sg:city":"Verona",
    "sg:classifiers":[
        {
            "category":"Building & Trades",
            "subcategory":"Construction",
            "type":"Services"
        }
    ],
    "sg:phone":"+1 608 845 8777",
    "sg:postcode":"53593",
    "sg:province":"WI",
    "sg:tags":[
        "railroad",
        "contractor"
    ],
    "wof:name":"ABC Rail System Inc",
    "wof:placetype":"venue"
},
  "geometry": {"coordinates":[-89.545224,42.98464],"type":"Point"}
}