{
  "type": "Feature",
  "properties": {
    "addr:full":"1206 Winn Trl Madison WI 53704",
    "addr:housenumber":"1206",
    "addr:postcode":"53704",
    "addr:street":"Winn Trl",
    "iso:country":"US",
    "sg:address":"1206 Winn Trl",
    "sg:city":"Madison",
    "sg:classifiers":[
        {
            "category":"Building & Trades",
            "subcategory":"Construction",
            "type":"Services"
        }
    ],
    "sg:phone":"+1 608 243 8475",
    "sg:postcode":"53704",
    "sg:province":"WI",
    "sg:tags":[
        "contractor"
    ],
    "wof:name":"Assoc Tile",
    "wof:placetype":"venue"
},
  "geometry": {"coordinates":[-89.37375299999999,43.143429],"type":"Point"}
}