{
  "type": "Feature",
  "properties": {
    "addr:full":"690 Washington St Prairie Du Sac WI 53578",
    "addr:housenumber":"690",
    "addr:postcode":"53578",
    "addr:street":"Washington St",
    "iso:country":"US",
    "sg:address":"690 Washington St",
    "sg:city":"Prairie Du Sac",
    "sg:classifiers":[
        {
            "category":"Retail",
            "subcategory":"Laundry & Dry Cleaning",
            "type":"Services"
        }
    ],
    "sg:phone":"+1 608 643 2141",
    "sg:postcode":"53578",
    "sg:province":"WI",
    "sg:tags":[
        "cleaners",
        "rug",
        "carpet"
    ],
    "wof:name":"Denny's Magic Carpet",
    "wof:placetype":"venue"
},
  "geometry": {"coordinates":[-89.72627,43.290707],"type":"Point"}
}