{
  "type": "Feature",
  "properties": {
    "iso:country":"US",
    "sg:address":"880 Frontage Rd",
    "sg:city":"Peshtigo",
    "sg:classifiers":[
        {
            "category":"Home & Garden",
            "subcategory":"Carpets & Floor Coverings",
            "type":"Retail Goods"
        }
    ],
    "sg:phone":"+1 715 582 9205",
    "sg:postcode":"54157",
    "sg:province":"WI",
    "sg:tags":[
        "dealer",
        "rug"
    ],
    "wof:name":"Northwoods Interiors",
    "wof:placetype":"venue"
},
  "geometry": {"coordinates":[-87.728278,45.053283],"type":"Point"}
}