{
  "type": "Feature",
  "properties": {
    "addr:full":"112 E 21st St Fond Du Lac WI 54935",
    "addr:housenumber":"112",
    "addr:postcode":"54935",
    "addr:street":"E 21St St",
    "iso:country":"US",
    "sg:address":"112 E 21st St",
    "sg:city":"Fond Du Lac",
    "sg:classifiers":[
        {
            "category":"Travel",
            "subcategory":"Hotels & Motels",
            "type":"Entertainment"
        }
    ],
    "sg:phone":"+1 920 921 8663",
    "sg:postcode":"54935",
    "sg:province":"WI",
    "sg:tags":[
        "operation"
    ],
    "wof:name":"Summerwind LLC",
    "wof:placetype":"venue"
},
  "geometry": {"coordinates":[-88.44354300000001,43.755906],"type":"Point"}
}