{
  "type": "Feature",
  "properties": {
    "addr:full":"1402 Regent St Madison WI 53711",
    "addr:housenumber":"1402",
    "addr:postcode":"53711",
    "addr:street":"Regent St",
    "iso:country":"US",
    "sg:address":"1402 Regent St",
    "sg:city":"Madison",
    "sg:classifiers":[
        {
            "category":"Real Estate",
            "subcategory":"Real Estate Operator",
            "type":"Services"
        }
    ],
    "sg:phone":"+1 608 258 4900",
    "sg:postcode":"53711",
    "sg:province":"WI",
    "sg:tags":[
        "apartment"
    ],
    "sg:website":"www.privatereshalls.com",
    "wof:name":"Regent Apartments",
    "wof:placetype":"venue"
},
  "geometry": {"coordinates":[-89.40922999999999,43.067832],"type":"Point"}
}