{
  "type": "Feature",
  "properties": {
    "iso:country":"US",
    "sg:address":"1024 Main St",
    "sg:city":"Stevens Point",
    "sg:classifiers":[
        {
            "category":"Food & Beverages",
            "subcategory":"Groceries & Convenience Stores",
            "type":"Retail Goods"
        }
    ],
    "sg:phone":"+1 715 343 5477",
    "sg:postcode":"54481",
    "sg:province":"WI",
    "wof:name":"Laylas Garden Deli",
    "wof:placetype":"venue"
},
  "geometry": {"coordinates":[-89.584731,44.523477],"type":"Point"}
}