{
  "type": "Feature",
  "properties": {
    "iso:country":"US",
    "sg:address":"202 S Park St",
    "sg:city":"Madison",
    "sg:classifiers":[
        {
            "category":"Health Services",
            "subcategory":"Hospital",
            "type":"Services"
        }
    ],
    "sg:phone":"+1 608 267 6000",
    "sg:postcode":"53715",
    "sg:province":"WI",
    "sg:tags":[
        "general"
    ],
    "sg:website":"www.meriterhomehealth.com",
    "wof:name":"Meriter Hospital",
    "wof:placetype":"venue"
},
  "geometry": {"coordinates":[-89.400873,43.065827],"type":"Point"}
}