{
  "type": "Feature",
  "properties": {
    "iso:country":"US",
    "sg:address":"6100 W Executive Dr",
    "sg:city":"Mequon",
    "sg:classifiers":[
        {
            "category":"Sports & Exercise",
            "subcategory":"Golf",
            "type":"Entertainment"
        },
        {
            "category":"Shopping",
            "subcategory":"Bicycles & Sporting Goods",
            "type":"Retail Goods"
        }
    ],
    "sg:phone":"+1 262 236 0330",
    "sg:postcode":"53092",
    "sg:province":"WI",
    "sg:tags":[
        "course",
        "promotional",
        "supply"
    ],
    "sg:website":"www.advantagegolf-wi.com",
    "wof:name":"Advantage Golf Wisconsin LLC",
    "wof:placetype":"venue"
},
  "geometry": {"coordinates":[-87.990719,43.20955],"type":"Point"}
}