{
  "type": "Feature",
  "properties": {
    "addr:full":"6892 Breneman Rd Pardeeville WI 53954",
    "addr:housenumber":"6892",
    "addr:postcode":"53954",
    "addr:street":"Breneman Rd",
    "iso:country":"US",
    "sg:address":"6892 Breneman Rd",
    "sg:city":"Pardeeville",
    "sg:classifiers":[
        {
            "category":"Retail",
            "subcategory":"Animal Services",
            "type":"Services"
        }
    ],
    "sg:phone":"+1 608 429 3176",
    "sg:postcode":"53954",
    "sg:province":"WI",
    "wof:name":"Swan Lake Kennels",
    "wof:placetype":"venue"
},
  "geometry": {"coordinates":[-89.345602,43.54032],"type":"Point"}
}