{
  "type": "Feature",
  "properties": {
    "addr:full":"1823 McKinley Rd Eau Claire WI 54703",
    "addr:housenumber":"1823",
    "addr:postcode":"54703",
    "addr:street":"Mckinley Rd",
    "iso:country":"US",
    "sg:address":"1823 McKinley Rd",
    "sg:city":"Eau Claire",
    "sg:classifiers":[
        {
            "category":"Professional",
            "type":"Services"
        }
    ],
    "sg:phone":"+1 715 830 0906",
    "sg:postcode":"54703",
    "sg:province":"WI",
    "sg:tags":[
        "establishment"
    ],
    "wof:name":"Productive Living Systems Inc",
    "wof:placetype":"venue"
},
  "geometry": {"coordinates":[-91.45795,44.833858],"type":"Point"}
}