{
  "type": "Feature",
  "properties": {
    "iso:country":"US",
    "sg:address":"6922 Jackson Rd",
    "sg:city":"Vesper",
    "sg:classifiers":[
        {
            "category":"Retail",
            "subcategory":"Auto Repair",
            "type":"Services"
        }
    ],
    "sg:phone":"+1 262 284 5601",
    "sg:postcode":"54489",
    "sg:province":"WI",
    "sg:tags":[
        "body",
        "automobile",
        "painting"
    ],
    "wof:name":"Prom's Auto Body Repair",
    "wof:placetype":"venue"
},
  "geometry": {"coordinates":[-90.064435,44.466238],"type":"Point"}
}