{
  "type": "Feature",
  "properties": {
    "iso:country":"US",
    "sg:address":"8289 Church St",
    "sg:city":"Mindoro",
    "sg:classifiers":[
        {
            "category":"Organizations",
            "subcategory":"Religious Organization",
            "type":"Services"
        }
    ],
    "sg:phone":"+1 608 857 3852",
    "sg:postcode":"54644",
    "sg:province":"WI",
    "wof:name":"Mindoro Presbyterian Church",
    "wof:placetype":"venue"
},
  "geometry": {"coordinates":[-91.100548,44.020616],"type":"Point"}
}