{
  "type": "Feature",
  "properties": {
    "iso:country":"US",
    "sg:address":"7674 141st St",
    "sg:city":"Chippewa Falls",
    "sg:classifiers":[
        {
            "category":"Professional",
            "type":"Services"
        }
    ],
    "sg:phone":"+1 715 726 1558",
    "sg:postcode":"54729",
    "sg:province":"WI",
    "wof:name":"Randal A Patten",
    "wof:placetype":"venue"
},
  "geometry": {"coordinates":[-91.387378,44.954673],"type":"Point"}
}