{
  "type": "Feature",
  "properties": {
    "iso:country":"US",
    "sg:address":"8509 W Oklahoma Ave",
    "sg:city":"Milwaukee",
    "sg:classifiers":[
        {
            "category":"Education",
            "subcategory":"School",
            "type":"Public Place"
        }
    ],
    "sg:phone":"+1 414 545 8159",
    "sg:postcode":"53227",
    "sg:province":"WI",
    "wof:name":"Hs Energy Services Inc",
    "wof:placetype":"venue"
},
  "geometry": {"coordinates":[-88.02153199999999,42.988148],"type":"Point"}
}