{
  "type": "Feature",
  "properties": {
    "iso:country":"US",
    "sg:address":"9587 58th Pl",
    "sg:city":"Kenosha",
    "sg:classifiers":[
        {
            "category":"Building & Trades",
            "subcategory":"Construction",
            "type":"Services"
        }
    ],
    "sg:phone":"+1 262 657 4171",
    "sg:postcode":"53144",
    "sg:province":"WI",
    "sg:tags":[
        "elevator"
    ],
    "wof:name":"Thyssenkrupp",
    "wof:placetype":"venue"
},
  "geometry": {"coordinates":[-87.921244,42.583376],"type":"Point"}
}