{
  "type": "Feature",
  "properties": {
    "iso:country":"US",
    "sg:address":"810 Grove St",
    "sg:city":"Beaver Dam",
    "sg:classifiers":[
        {
            "category":"Professional",
            "subcategory":"Business Services",
            "type":"Services"
        }
    ],
    "sg:phone":"+1 920 887 9015",
    "sg:postcode":"53916",
    "sg:province":"WI",
    "wof:name":"Global Solution Providers Inc",
    "wof:placetype":"venue"
},
  "geometry": {"coordinates":[-88.83806800000001,43.473217],"type":"Point"}
}