{
  "type": "Feature",
  "properties": {
    "addr:full":"211 Main St Darlington WI 53530",
    "addr:housenumber":"211",
    "addr:postcode":"53530",
    "addr:street":"Main St",
    "iso:country":"US",
    "sg:address":"211 Main St",
    "sg:city":"Darlington",
    "sg:classifiers":[
        {
            "category":"Bars & Pubs",
            "type":"Food & Drink"
        }
    ],
    "sg:phone":"+1 608 776 4135",
    "sg:postcode":"53530",
    "sg:province":"WI",
    "sg:tags":[
        "drinking"
    ],
    "wof:name":"Corner Bar & Grill",
    "wof:placetype":"venue"
},
  "geometry": {"coordinates":[-90.117712,42.678571],"type":"Point"}
}