{
  "type": "Feature",
  "properties": {
    "iso:country":"US",
    "sg:address":"101 N Main St",
    "sg:city":"Fond Du Lac",
    "sg:classifiers":[
        {
            "category":"Wholesale",
            "subcategory":"Sporting Goods",
            "type":"Manufacturing & Wholesale Goods"
        }
    ],
    "sg:phone":"+1 920 924 9949",
    "sg:postcode":"54935",
    "sg:province":"WI",
    "sg:tags":[
        "course",
        "golf",
        "public"
    ],
    "wof:name":"Shooters Club LTD",
    "wof:placetype":"venue"
},
  "geometry": {"coordinates":[-88.447,43.782284],"type":"Point"}
}