{
  "type": "Feature",
  "properties": {
    "iso:country":"US",
    "sg:address":"5939 210th St",
    "sg:city":"Cadott",
    "sg:classifiers":[
        {
            "category":"Retail",
            "subcategory":"Auto Repair",
            "type":"Services"
        }
    ],
    "sg:phone":"+1 715 723 8316",
    "sg:postcode":"54727",
    "sg:province":"WI",
    "sg:tags":[
        "body"
    ],
    "wof:name":"Cars Auto Body",
    "wof:placetype":"venue"
},
  "geometry": {"coordinates":[-91.247614,44.928927],"type":"Point"}
}