{
  "type": "Feature",
  "properties": {
    "iso:country":"US",
    "sg:address":"1000 W Cassidy Dr",
    "sg:city":"Wausau",
    "sg:classifiers":[
        {
            "category":"Wholesale",
            "subcategory":"Hardware",
            "type":"Manufacturing & Wholesale Goods"
        }
    ],
    "sg:phone":"+1 715 675 6723",
    "sg:postcode":"54401",
    "sg:province":"WI",
    "sg:tags":[
        "refrigeration",
        "refrigerating"
    ],
    "wof:name":"Hoffman's Refrigeration",
    "wof:placetype":"venue"
},
  "geometry": {"coordinates":[-89.64197,44.995467],"type":"Point"}
}