{
  "type": "Feature",
  "properties": {
    "iso:country":"US",
    "sg:address":"870 Larkspur Dr",
    "sg:city":"Brookfield",
    "sg:classifiers":[
        {
            "category":"Wholesale",
            "subcategory":"Scrap",
            "type":"Manufacturing & Wholesale Goods"
        }
    ],
    "sg:phone":"+1 414 645 6040",
    "sg:postcode":"53045",
    "sg:province":"WI",
    "sg:tags":[
        "metal",
        "iron"
    ],
    "wof:name":"Lewinsky Iron & Metal Co",
    "wof:placetype":"venue"
},
  "geometry": {"coordinates":[-88.16403,43.042865],"type":"Point"}
}