{
  "type": "Feature",
  "properties": {
    "iso:country":"US",
    "sg:address":"1529 Co Rd C",
    "sg:city":"Rio",
    "sg:classifiers":[
        {
            "category":"Home & Garden",
            "subcategory":"Carpets & Floor Coverings",
            "type":"Retail Goods"
        }
    ],
    "sg:phone":"+1 920 992 3718",
    "sg:postcode":"53960",
    "sg:province":"WI",
    "sg:tags":[
        "mfg"
    ],
    "wof:name":"Millwork & Floors",
    "wof:placetype":"venue"
},
  "geometry": {"coordinates":[-89.2449,43.333003],"type":"Point"}
}