{
  "type": "Feature",
  "properties": {
    "iso:country":"US",
    "sg:address":"1612 N High Point Rd",
    "sg:city":"Middleton",
    "sg:classifiers":[
        {
            "category":"Retail",
            "subcategory":"Veterinary Services",
            "type":"Services"
        }
    ],
    "sg:phone":"+1 608 831 1101",
    "sg:postcode":"53562",
    "sg:province":"WI",
    "sg:tags":[
        "veterinarian"
    ],
    "wof:name":"Veterinary Emergency Service L",
    "wof:placetype":"venue"
},
  "geometry": {"coordinates":[-89.51849,43.092277],"type":"Point"}
}