{
  "type": "Feature",
  "properties": {
    "iso:country":"US",
    "sg:address":"11707 W Dearborn Ave",
    "sg:city":"Milwaukee",
    "sg:classifiers":[
        {
            "category":"Building & Trades",
            "subcategory":"Electrical",
            "type":"Services"
        },
        {
            "category":"Wholesale",
            "subcategory":"Electrical",
            "type":"Manufacturing & Wholesale Goods"
        }
    ],
    "sg:phone":"+1 414 476 1011",
    "sg:postcode":"53226",
    "sg:province":"WI",
    "sg:tags":[
        "sound",
        "installation",
        "system",
        "equipment",
        "design",
        "video"
    ],
    "wof:name":"Professional Audio Designs Inc",
    "wof:placetype":"venue"
},
  "geometry": {"coordinates":[-88.05847,43.032302],"type":"Point"}
}