{
  "type": "Feature",
  "properties": {
    "iso:country":"US",
    "sg:address":"5295 12 Corners Rd",
    "sg:city":"Black Creek",
    "sg:classifiers":[
        {
            "category":"Wholesale",
            "subcategory":"Dairy",
            "type":"Manufacturing & Wholesale Goods"
        }
    ],
    "sg:phone":"+1 920 730 9345",
    "sg:postcode":"54106",
    "sg:province":"WI",
    "sg:tags":[
        "product"
    ],
    "wof:name":"Black Creek Packaging LLC",
    "wof:placetype":"venue"
},
  "geometry": {"coordinates":[-88.435205,44.387294],"type":"Point"}
}