{
  "type": "Feature",
  "properties": {
    "iso:country":"US",
    "sg:address":"2578 N 88th St",
    "sg:city":"Milwaukee",
    "sg:classifiers":[
        {
            "category":"Retail",
            "subcategory":"Self-service Laundry",
            "type":"Services"
        }
    ],
    "sg:phone":"+1 414 258 0618",
    "sg:postcode":"53226",
    "sg:province":"WI",
    "sg:tags":[
        "coin"
    ],
    "wof:name":"Bond Laundry Mat",
    "wof:placetype":"venue"
},
  "geometry": {"coordinates":[-88.022407,43.064536],"type":"Point"}
}