{
  "type": "Feature",
  "properties": {
    "addr:full":"1480 W Pleasant Valley Rd West Bend WI 53095",
    "addr:housenumber":"1480",
    "addr:postcode":"53095",
    "addr:street":"W Pleasant Valley Rd",
    "iso:country":"US",
    "sg:address":"1480 W Pleasant Valley Rd",
    "sg:city":"West Bend",
    "sg:classifiers":[
        {
            "category":"Building & Trades",
            "subcategory":"Construction",
            "type":"Services"
        }
    ],
    "sg:phone":"+1 262 675 5005",
    "sg:postcode":"53095",
    "sg:province":"WI",
    "sg:tags":[
        "hanging",
        "contractor"
    ],
    "wof:name":"Hovland Painting",
    "wof:placetype":"venue"
},
  "geometry": {"coordinates":[-88.11111,43.35204],"type":"Point"}
}