{
  "type": "Feature",
  "properties": {
    "iso:country":"US",
    "sg:address":"714 Lawe St",
    "sg:city":"Green Bay",
    "sg:classifiers":[
        {
            "category":"Professional",
            "subcategory":"Secretarial Services",
            "type":"Services"
        }
    ],
    "sg:phone":"+1 920 432 9023",
    "sg:postcode":"54301",
    "sg:province":"WI",
    "sg:tags":[
        "convention",
        "court",
        "reporter"
    ],
    "wof:name":"Francois & Baux Reporting",
    "wof:placetype":"venue"
},
  "geometry": {"coordinates":[-88.014007,44.502413],"type":"Point"}
}