{
  "type": "Feature",
  "properties": {
    "addr:full":"1917 S Main St West Bend WI 53095",
    "addr:housenumber":"1917",
    "addr:postcode":"53095",
    "addr:street":"S Main St",
    "iso:country":"US",
    "sg:address":"1917 S Main St",
    "sg:city":"West Bend",
    "sg:classifiers":[
        {
            "category":"Manufacturing",
            "subcategory":"Rubber & Plastics",
            "type":"Manufacturing & Wholesale Goods"
        }
    ],
    "sg:phone":"+1 262 334 7531",
    "sg:postcode":"53095",
    "sg:province":"WI",
    "sg:tags":[
        "product",
        "m",
        "jewelry",
        "merchandise",
        "mfg"
    ],
    "wof:name":"A & E Engraving",
    "wof:placetype":"venue"
},
  "geometry": {"coordinates":[-88.180907,43.397275],"type":"Point"}
}