{
  "type": "Feature",
  "properties": {
    "iso:country":"US",
    "sg:address":"2786 Main St",
    "sg:city":"East Troy",
    "sg:classifiers":[
        {
            "category":"Shopping",
            "subcategory":"Beauty & Cosmetics",
            "type":"Retail Goods"
        }
    ],
    "sg:phone":"+1 262 642 9627",
    "sg:postcode":"53120",
    "sg:province":"WI",
    "sg:tags":[
        "merchandise"
    ],
    "wof:name":"Merle J Shaffer",
    "wof:placetype":"venue"
},
  "geometry": {"coordinates":[-88.40136,42.787218],"type":"Point"}
}