{
  "type": "Feature",
  "properties": {
    "iso:country":"US",
    "sg:address":"2312 N Grandview Blvd",
    "sg:city":"Waukesha",
    "sg:classifiers":[
        {
            "category":"Wholesale",
            "subcategory":"Electrical",
            "type":"Manufacturing & Wholesale Goods"
        }
    ],
    "sg:phone":"+1 262 542 6550",
    "sg:postcode":"53188",
    "sg:province":"WI",
    "sg:tags":[
        "electronic"
    ],
    "wof:name":"Circuit Sales Inc",
    "wof:placetype":"venue"
},
  "geometry": {"coordinates":[-88.256083,43.033026],"type":"Point"}
}