{
  "type": "Feature",
  "properties": {
    "iso:country":"US",
    "sg:address":"2710 Prairie Ave",
    "sg:city":"Beloit",
    "sg:classifiers":[
        {
            "category":"Building & Trades",
            "subcategory":"Electrical",
            "type":"Services"
        }
    ],
    "sg:phone":"+1 608 364 4044",
    "sg:postcode":"53511",
    "sg:province":"IL",
    "sg:tags":[
        "electric",
        "contractor"
    ],
    "sg:website":"www.carrollelectric.com",
    "wof:name":"Carroll Electric",
    "wof:placetype":"venue"
},
  "geometry": {"coordinates":[-89.011699,42.54642],"type":"Point"}
}