{
  "type": "Feature",
  "properties": {
    "addr:full":"2800 Ward Ave La Crosse WI 54601",
    "addr:housenumber":"2800",
    "addr:postcode":"54601",
    "addr:street":"Ward Ave",
    "iso:country":"US",
    "sg:address":"2800 Ward Ave",
    "sg:city":"La Crosse",
    "sg:classifiers":[
        {
            "category":"Government",
            "subcategory":"Office",
            "type":"Public Place"
        }
    ],
    "sg:phone":"+1 608 788 1032",
    "sg:postcode":"54601",
    "sg:province":"WI",
    "sg:tags":[
        "city"
    ],
    "wof:name":"Shelby Town Hall",
    "wof:placetype":"venue"
},
  "geometry": {"coordinates":[-91.213503,43.783301],"type":"Point"}
}