{
  "type": "Feature",
  "properties": {
    "iso:country":"US",
    "sg:address":"7245 State Rd 37",
    "sg:city":"Eau Claire",
    "sg:classifiers":[
        {
            "category":"Building & Trades",
            "subcategory":"Landscaping Services",
            "type":"Services"
        }
    ],
    "sg:phone":"+1 715 271 3010",
    "sg:postcode":"54701",
    "sg:province":"WI",
    "sg:tags":[
        "lawn",
        "maintenance",
        "grounds"
    ],
    "wof:name":"Grasscapes",
    "wof:placetype":"venue"
},
  "geometry": {"coordinates":[-91.56961099999999,44.728471],"type":"Point"}
}