{
  "type": "Feature",
  "properties": {
    "iso:country":"US",
    "sg:address":"14337 Park Rd",
    "sg:city":"Grantsburg",
    "sg:classifiers":[
        {
            "category":"Professional",
            "subcategory":"Accounting & Tax Preparation",
            "type":"Services"
        }
    ],
    "sg:phone":"+1 715 463 3045",
    "sg:postcode":"54840",
    "sg:province":"WI",
    "sg:tags":[
        "accountant"
    ],
    "wof:name":"Mc Shane Tax & Acounting",
    "wof:placetype":"venue"
},
  "geometry": {"coordinates":[-92.71964800000001,45.769479],"type":"Point"}
}