{
  "type": "Feature",
  "properties": {
    "addr:full":"1345 97th Ave Kenosha WI 53144",
    "addr:housenumber":"1345",
    "addr:postcode":"53144",
    "addr:street":"97Th Ave",
    "iso:country":"US",
    "sg:address":"1345 97th Ave",
    "sg:city":"Kenosha",
    "sg:classifiers":[
        {
            "category":"Manufacturing",
            "subcategory":"Retail Goods",
            "type":"Manufacturing & Wholesale Goods"
        }
    ],
    "sg:phone":"+1 262 859 0308",
    "sg:postcode":"53144",
    "sg:province":"WI",
    "sg:tags":[
        "product",
        "mfg"
    ],
    "wof:name":"Paradise Mfg Inc",
    "wof:placetype":"venue"
},
  "geometry": {"coordinates":[-87.925639,42.637195],"type":"Point"}
}