{
  "type": "Feature",
  "properties": {
    "addr:full":"131 E Maple Ave Beaver Dam WI 53916",
    "addr:housenumber":"131",
    "addr:postcode":"53916",
    "addr:street":"E Maple Ave",
    "iso:country":"US",
    "sg:address":"131 E Maple Ave",
    "sg:city":"Beaver Dam",
    "sg:classifiers":[
        {
            "category":"Retail",
            "subcategory":"Funeral Services",
            "type":"Services"
        }
    ],
    "sg:phone":"+1 920 885 6600",
    "sg:postcode":"53916",
    "sg:province":"WI",
    "sg:tags":[
        "home"
    ],
    "wof:name":"Mu",
    "wof:placetype":"venue"
},
  "geometry": {"coordinates":[-88.835076,43.457283],"type":"Point"}
}