{
  "type": "Feature",
  "properties": {
    "iso:country":"US",
    "sg:address":"3251 Cardinal Ln",
    "sg:city":"Edgar",
    "sg:classifiers":[
        {
            "category":"Farming",
            "subcategory":"Dairy Farm",
            "type":"Manufacturing & Wholesale Goods"
        }
    ],
    "sg:phone":"+1 715 352 2089",
    "sg:postcode":"54426",
    "sg:province":"WI",
    "wof:name":"Marvin Skrzypcak",
    "wof:placetype":"venue"
},
  "geometry": {"coordinates":[-89.92689900000001,44.881969],"type":"Point"}
}