{
  "type": "Feature",
  "properties": {
    "addr:full":"33939 205th Ave Gilman WI 54433",
    "addr:housenumber":"33939",
    "addr:postcode":"54433",
    "addr:street":"205Th Ave",
    "iso:country":"US",
    "sg:address":"33939 205th Ave",
    "sg:city":"Gilman",
    "sg:classifiers":[
        {
            "category":"Farming",
            "subcategory":"Dairy Farm",
            "type":"Manufacturing & Wholesale Goods"
        }
    ],
    "sg:phone":"+1 715 447 5744",
    "sg:postcode":"54433",
    "sg:province":"WI",
    "wof:name":"Robert A Callahan",
    "wof:placetype":"venue"
},
  "geometry": {"coordinates":[-90.98908,45.141131],"type":"Point"}
}