{
  "type": "Feature",
  "properties": {
    "iso:country":"US",
    "sg:address":"2115 Cappaert Rd",
    "sg:city":"Manitowoc",
    "sg:classifiers":[
        {
            "category":"Health Services",
            "subcategory":"Nursing And Care Facility",
            "type":"Services"
        }
    ],
    "sg:phone":"+1 920 686 1797",
    "sg:postcode":"54220",
    "sg:province":"WI",
    "wof:name":"Harmony of Manitowoc",
    "wof:placetype":"venue"
},
  "geometry": {"coordinates":[-87.710846,44.123377],"type":"Point"}
}