{
  "type": "Feature",
  "properties": {
    "iso:country":"US",
    "sg:address":"19667 State Hwy 27",
    "sg:city":"Sparta",
    "sg:classifiers":[
        {
            "category":"Organizations",
            "subcategory":"Religious Organization",
            "type":"Services"
        }
    ],
    "sg:phone":"+1 608 269 8502",
    "sg:postcode":"54656",
    "sg:province":"WI",
    "sg:tags":[
        "clergy"
    ],
    "wof:name":"First Congregational Church",
    "wof:placetype":"venue"
},
  "geometry": {"coordinates":[-90.830305,43.888429],"type":"Point"}
}