{
  "type": "Feature",
  "properties": {
    "addr:full":"3051 Progress Way Kaukauna WI 54130",
    "addr:housenumber":"3051",
    "addr:postcode":"54130",
    "addr:street":"Progress Way",
    "iso:country":"US",
    "sg:address":"3051 Progress Way",
    "sg:city":"Kaukauna",
    "sg:classifiers":[
        {
            "category":"Shopping",
            "type":"Retail Goods"
        }
    ],
    "sg:phone":"+1 920 759 9409",
    "sg:postcode":"54130",
    "sg:province":"WI",
    "sg:tags":[
        "telephone",
        "cellular"
    ],
    "wof:name":"Mobile Solution Corp",
    "wof:placetype":"venue"
},
  "geometry": {"coordinates":[-88.258672,44.304746],"type":"Point"}
}