{
  "type": "Feature",
  "properties": {
    "addr:full":"131 S Oborn St Waupaca WI 54981",
    "addr:housenumber":"131",
    "addr:postcode":"54981",
    "addr:street":"S Oborn St",
    "iso:country":"US",
    "sg:address":"131 S Oborn St",
    "sg:city":"Waupaca",
    "sg:classifiers":[
        {
            "category":"Home & Garden",
            "subcategory":"Building Materials",
            "type":"Retail Goods"
        }
    ],
    "sg:phone":"+1 715 256 1277",
    "sg:postcode":"54981",
    "sg:province":"WI",
    "sg:tags":[
        "stone"
    ],
    "wof:name":"Paramount Research & Dev",
    "wof:placetype":"venue"
},
  "geometry": {"coordinates":[-89.074646,44.357632],"type":"Point"}
}