{
  "type": "Feature",
  "properties": {
    "iso:country":"US",
    "sg:address":"8338 Co Rd H",
    "sg:city":"Camp Douglas",
    "sg:classifiers":[
        {
            "category":"Retail",
            "subcategory":"Animal Services",
            "type":"Services"
        }
    ],
    "sg:phone":"+1 608 427 3789",
    "sg:postcode":"54618",
    "sg:province":"WI",
    "sg:tags":[
        "pet",
        "grooming",
        "washing"
    ],
    "wof:name":"Pretty Pet's Pet Grooming",
    "wof:placetype":"venue"
},
  "geometry": {"coordinates":[-90.28487199999999,43.94786],"type":"Point"}
}