{
  "type": "Feature",
  "properties": {
    "iso:country":"US",
    "sg:address":"639 State Rd 70",
    "sg:city":"Grantsburg",
    "sg:classifiers":[
        {
            "category":"Food & Beverages",
            "subcategory":"Groceries & Convenience Stores",
            "type":"Retail Goods"
        }
    ],
    "sg:phone":"+1 715 463 5000",
    "sg:postcode":"54840",
    "sg:province":"WI",
    "wof:name":"Stop A Sec Convenience Store",
    "wof:placetype":"venue"
},
  "geometry": {"coordinates":[-92.696411,45.772906],"type":"Point"}
}