{
  "type": "Feature",
  "properties": {
    "iso:country":"US",
    "sg:address":"1706 Ludden Dr",
    "sg:city":"Cross Plains",
    "sg:classifiers":[
        {
            "category":"Professional",
            "type":"Services"
        }
    ],
    "sg:phone":"+1 608 798 4255",
    "sg:postcode":"53528",
    "sg:province":"WI",
    "wof:name":"Living Out Loud LLC",
    "wof:placetype":"venue"
},
  "geometry": {"coordinates":[-89.656728,43.106383],"type":"Point"}
}