{
  "type": "Feature",
  "properties": {
    "iso:country":"US",
    "sg:address":"6088 Coddington Rd",
    "sg:city":"Bancroft",
    "sg:classifiers":[
        {
            "category":"Freight",
            "type":"Transportation"
        }
    ],
    "sg:phone":"+1 715 344 0087",
    "sg:postcode":"54921",
    "sg:province":"WI",
    "sg:tags":[
        "trucking"
    ],
    "wof:name":"Chris Noth Trucking Inc",
    "wof:placetype":"venue"
},
  "geometry": {"coordinates":[-89.497294,44.367483],"type":"Point"}
}