{
  "type": "Feature",
  "properties": {
    "iso:country":"US",
    "sg:address":"2515 W Princeton Ave",
    "sg:city":"Eau Claire",
    "sg:classifiers":[
        {
            "category":"Professional",
            "subcategory":"Business Services",
            "type":"Services"
        }
    ],
    "sg:phone":"+1 715 835 0811",
    "sg:postcode":"54703",
    "sg:province":"WI",
    "sg:tags":[
        "paper"
    ],
    "wof:name":"Shredaway",
    "wof:placetype":"venue"
},
  "geometry": {"coordinates":[-91.456938,44.842557],"type":"Point"}
}