{
  "type": "Feature",
  "properties": {
    "iso:country":"US",
    "sg:address":"6701 S 27th St",
    "sg:city":"Franklin",
    "sg:classifiers":[
        {
            "category":"Professional",
            "subcategory":"Accounting & Tax Preparation",
            "type":"Services"
        }
    ],
    "sg:phone":"+1 414 304 1605",
    "sg:postcode":"53132",
    "sg:province":"WI",
    "sg:tags":[
        "return",
        "filing"
    ],
    "wof:name":"H & R Block Tax Svc",
    "wof:placetype":"venue"
},
  "geometry": {"coordinates":[-87.949816,42.919036],"type":"Point"}
}