{
  "type": "Feature",
  "properties": {
    "iso:country":"US",
    "sg:address":"1117 Milwaukee Ave",
    "sg:city":"South Milwaukee",
    "sg:classifiers":[
        {
            "category":"Restaurant",
            "type":"Food & Drink"
        }
    ],
    "sg:phone":"+1 414 764 3777",
    "sg:postcode":"53172",
    "sg:province":"WI",
    "wof:name":"Antonio's Family Restaurant",
    "wof:placetype":"venue"
},
  "geometry": {"coordinates":[-87.864648,42.910699],"type":"Point"}
}