{
  "type": "Feature",
  "properties": {
    "iso:country":"US",
    "sg:address":"1408 Co Hwy Nn",
    "sg:city":"West Bend",
    "sg:classifiers":[
        {
            "category":"Manufacturing",
            "subcategory":"Tools & Machinery",
            "type":"Manufacturing & Wholesale Goods"
        }
    ],
    "sg:phone":"+1 262 675 0779",
    "sg:postcode":"53095",
    "sg:province":"WI",
    "sg:tags":[
        "devices",
        "point"
    ],
    "wof:name":"Preferred Products LLC",
    "wof:placetype":"venue"
},
  "geometry": {"coordinates":[-88.089894,43.367867],"type":"Point"}
}