{
  "type": "Feature",
  "properties": {
    "iso:country":"US",
    "sg:address":"6194 Co Rd K",
    "sg:city":"Rhinelander",
    "sg:classifiers":[
        {
            "category":"Building & Trades",
            "subcategory":"Construction",
            "type":"Services"
        }
    ],
    "sg:phone":"+1 715 362 5611",
    "sg:postcode":"54501",
    "sg:province":"WI",
    "sg:tags":[
        "hanging",
        "painter",
        "contractor"
    ],
    "wof:name":"Tom's Brushstroke",
    "wof:placetype":"venue"
},
  "geometry": {"coordinates":[-89.485017,45.645492],"type":"Point"}
}