{
  "type": "Feature",
  "properties": {
    "iso:country":"US",
    "sg:address":"4317 N Woodridge Dr",
    "sg:city":"Appleton",
    "sg:classifiers":[
        {
            "category":"Wholesale",
            "subcategory":"Electrical",
            "type":"Manufacturing & Wholesale Goods"
        }
    ],
    "sg:phone":"+1 920 991 9317",
    "sg:postcode":"54913",
    "sg:province":"WI",
    "sg:tags":[
        "equipment",
        "electronic",
        "supply"
    ],
    "wof:name":"Molex",
    "wof:placetype":"venue"
},
  "geometry": {"coordinates":[-88.409686,44.305096],"type":"Point"}
}