{
  "type": "Feature",
  "properties": {
    "iso:country":"US",
    "sg:address":"705 S Buchanan St",
    "sg:city":"Prairie Du Chien",
    "sg:classifiers":[
        {
            "category":"Social Services",
            "type":"Services"
        }
    ],
    "sg:phone":"+1 608 357 2083",
    "sg:postcode":"53821",
    "sg:province":"WI",
    "sg:tags":[
        "youth",
        "organization",
        "center"
    ],
    "wof:name":"Care Council",
    "wof:placetype":"venue"
},
  "geometry": {"coordinates":[-91.135425,43.043732],"type":"Point"}
}