{
  "type": "Feature",
  "properties": {
    "iso:country":"US",
    "sg:address":"6715 Parkedge Cir",
    "sg:city":"Franklin",
    "sg:classifiers":[
        {
            "category":"Professional",
            "type":"Services"
        }
    ],
    "sg:phone":"+1 414 529 3228",
    "sg:postcode":"53132",
    "sg:province":"WI",
    "wof:name":"Get Results Inc",
    "wof:placetype":"venue"
},
  "geometry": {"coordinates":[-88.040903,42.924579],"type":"Point"}
}