{
  "type": "Feature",
  "properties": {
    "iso:country":"US",
    "sg:address":"5200 N Port Washington Rd",
    "sg:city":"Milwaukee",
    "sg:classifiers":[
        {
            "category":"Autos & Motor Vehicles",
            "subcategory":"Automobile Sales",
            "type":"Retail Goods"
        },
        {
            "category":"Retail",
            "subcategory":"Auto Repair",
            "type":"Services"
        }
    ],
    "sg:phone":"+1 877 857 5252",
    "sg:postcode":"53217",
    "sg:province":"WI",
    "sg:tags":[
        "used",
        "leasing",
        "car",
        "truck",
        "new"
    ],
    "sg:website":"http://amatonissan.dealersight.com/",
    "wof:name":"John Amato Nissan",
    "wof:placetype":"venue"
},
  "geometry": {"coordinates":[-87.91670999999999,43.111359],"type":"Point"}
}