{
  "type": "Feature",
  "properties": {
    "iso:country":"US",
    "sg:address":"1064 Oconobanks Dr",
    "sg:city":"Colgate",
    "sg:classifiers":[
        {
            "category":"Building & Trades",
            "subcategory":"Construction",
            "type":"Services"
        }
    ],
    "sg:phone":"+1 262 628 2756",
    "sg:postcode":"53017",
    "sg:province":"WI",
    "sg:tags":[
        "carpentry",
        "contractor"
    ],
    "wof:name":"Naumann & Co",
    "wof:placetype":"venue"
},
  "geometry": {"coordinates":[-88.29196,43.223379],"type":"Point"}
}