{
  "type": "Feature",
  "properties": {
    "addr:full":"1094 S Koeller St Oshkosh WI 54902",
    "addr:housenumber":"1094",
    "addr:postcode":"54902",
    "addr:street":"S Koeller St",
    "iso:country":"US",
    "sg:address":"1094 S Koeller St",
    "sg:city":"Oshkosh",
    "sg:classifiers":[
        {
            "category":"Travel",
            "subcategory":"Travel Agent",
            "type":"Entertainment"
        }
    ],
    "sg:phone":"+1 920 236 7777",
    "sg:postcode":"54902",
    "sg:province":"WI",
    "sg:tags":[
        "agency"
    ],
    "sg:website":"www.ambassadortravelltd.com",
    "wof:name":"Ambassador Travel LTD",
    "wof:placetype":"venue"
},
  "geometry": {"coordinates":[-88.582089,43.999998],"type":"Point"}
}