{
  "type": "Feature",
  "properties": {
    "iso:country":"US",
    "sg:address":"214 High St",
    "sg:city":"Mineral Point",
    "sg:classifiers":[
        {
            "category":"Real Estate",
            "subcategory":"Real Estate Agent",
            "type":"Services"
        }
    ],
    "sg:phone":"+1 608 987 4477",
    "sg:postcode":"53565",
    "sg:province":"WI",
    "wof:name":"ERA",
    "wof:placetype":"venue"
},
  "geometry": {"coordinates":[-90.181432,42.860376],"type":"Point"}
}