{
  "type": "Feature",
  "properties": {
    "iso:country":"US",
    "sg:address":"3248 S Pennsylvania Ave",
    "sg:city":"Milwaukee",
    "sg:classifiers":[
        {
            "category":"Shopping",
            "subcategory":"Clothing, Apparel, & Fashions",
            "type":"Retail Goods"
        }
    ],
    "sg:phone":"+1 414 489 7602",
    "sg:postcode":"53207",
    "sg:province":"WI",
    "wof:name":"Seiferts Stix LLC",
    "wof:placetype":"venue"
},
  "geometry": {"coordinates":[-87.87941600000001,42.98665],"type":"Point"}
}