{
  "type": "Feature",
  "properties": {
    "iso:country":"US",
    "sg:address":"7010 Hillview Rd",
    "sg:city":"Greenville",
    "sg:classifiers":[
        {
            "category":"Wholesale",
            "subcategory":"Furniture",
            "type":"Manufacturing & Wholesale Goods"
        }
    ],
    "sg:phone":"+1 920 993 9152",
    "sg:postcode":"54942",
    "sg:province":"WI",
    "wof:name":"Hi-Tec Interior Walls Inc",
    "wof:placetype":"venue"
},
  "geometry": {"coordinates":[-88.55136299999999,44.317061],"type":"Point"}
}