{
  "type": "Feature",
  "properties": {
    "iso:country":"US",
    "sg:address":"207 S Cherry Ave",
    "sg:city":"Marshfield",
    "sg:classifiers":[
        {
            "category":"Social Services",
            "type":"Services"
        }
    ],
    "sg:phone":"+1 715 387 8914",
    "sg:postcode":"54449",
    "sg:province":"WI",
    "wof:name":"Lutheran Social Services",
    "wof:placetype":"venue"
},
  "geometry": {"coordinates":[-90.170052,44.664354],"type":"Point"}
}