{
  "type": "Feature",
  "properties": {
    "addr:full":"14311 Luebke Rd Baraboo WI 53913",
    "addr:housenumber":"14311",
    "addr:postcode":"53913",
    "addr:street":"Luebke Rd",
    "iso:country":"US",
    "sg:address":"14311 Luebke Rd",
    "sg:city":"Baraboo",
    "sg:classifiers":[
        {
            "category":"Wholesale",
            "subcategory":"Machinery & Supplies",
            "type":"Manufacturing & Wholesale Goods"
        }
    ],
    "sg:phone":"+1 608 356 3365",
    "sg:postcode":"53913",
    "sg:province":"WI",
    "sg:tags":[
        "contractor"
    ],
    "wof:name":"Jemrack Fleet Svc",
    "wof:placetype":"venue"
},
  "geometry": {"coordinates":[-89.608414,43.467189],"type":"Point"}
}