{
  "type": "Feature",
  "properties": {
    "iso:country":"US",
    "sg:address":"120 W Keefe Ave",
    "sg:city":"Milwaukee",
    "sg:classifiers":[
        {
            "category":"Organizations",
            "subcategory":"Religious Organization",
            "type":"Services"
        }
    ],
    "sg:phone":"+1 414 264 0535",
    "sg:postcode":"53212",
    "sg:province":"WI",
    "wof:name":"House Of David Ministry",
    "wof:placetype":"venue"
},
  "geometry": {"coordinates":[-87.911956,43.082147],"type":"Point"}
}