{
  "type": "Feature",
  "properties": {
    "addr:full":"2700 S Ashland Ave Green Bay WI 54304",
    "addr:housenumber":"2700",
    "addr:postcode":"54304",
    "addr:street":"S Ashland Ave",
    "iso:country":"US",
    "sg:address":"2700 S Ashland Ave",
    "sg:city":"Green Bay",
    "sg:classifiers":[
        {
            "category":"Home & Garden",
            "subcategory":"Garden Supply",
            "type":"Retail Goods"
        }
    ],
    "sg:phone":"+1 920 498 6640",
    "sg:postcode":"54304",
    "sg:province":"WI",
    "sg:tags":[
        "engine"
    ],
    "sg:website":"www.broadwayautomotive.com",
    "wof:name":"Parts Center-Medium Duty Truck",
    "wof:placetype":"venue"
},
  "geometry": {"coordinates":[-88.062956,44.474422],"type":"Point"}
}