{
  "type": "Feature",
  "properties": {
    "iso:country":"US",
    "sg:address":"33 W Davenport St",
    "sg:city":"Rhinelander",
    "sg:classifiers":[
        {
            "category":"Manufacturing",
            "subcategory":"Apparel",
            "type":"Manufacturing & Wholesale Goods"
        }
    ],
    "sg:phone":"+1 715 369 7600",
    "sg:postcode":"54501",
    "sg:province":"WI",
    "wof:name":"Northern Expressions",
    "wof:placetype":"venue"
},
  "geometry": {"coordinates":[-89.412432,45.637746],"type":"Point"}
}