{
  "type": "Feature",
  "properties": {
    "iso:country":"US",
    "sg:address":"830 N Water St",
    "sg:city":"Sheboygan",
    "sg:classifiers":[
        {
            "category":"Real Estate",
            "subcategory":"Real Estate Operator",
            "type":"Services"
        }
    ],
    "sg:phone":"+1 920 208 6044",
    "sg:postcode":"53081",
    "sg:province":"WI",
    "sg:tags":[
        "building",
        "apartment"
    ],
    "wof:name":"Garden Toy Factory APT Homes",
    "wof:placetype":"venue"
},
  "geometry": {"coordinates":[-87.719022,43.753436],"type":"Point"}
}