{
  "type": "Feature",
  "properties": {
    "iso:country":"US",
    "sg:address":"9150 S 96th St",
    "sg:city":"Franklin",
    "sg:classifiers":[
        {
            "category":"Building & Trades",
            "subcategory":"Plumbing",
            "type":"Services"
        }
    ],
    "sg:phone":"+1 414 425 6480",
    "sg:postcode":"53132",
    "sg:province":"WI",
    "sg:tags":[
        "plumbing",
        "contractor"
    ],
    "wof:name":"Chuck's Plumbing & Heating Co",
    "wof:placetype":"venue"
},
  "geometry": {"coordinates":[-88.03380199999999,42.877376],"type":"Point"}
}