{
  "type": "Feature",
  "properties": {
    "iso:country":"US",
    "sg:address":"311 Letendre Ave",
    "sg:city":"Port Edwards",
    "sg:classifiers":[
        {
            "category":"Retail",
            "subcategory":"Auto Repair",
            "type":"Services"
        }
    ],
    "sg:phone":"+1 715 887 4100",
    "sg:postcode":"54469",
    "sg:province":"WI",
    "sg:tags":[
        "repairing",
        "automobile"
    ],
    "wof:name":"John Henry's Auto Repair",
    "wof:placetype":"venue"
},
  "geometry": {"coordinates":[-89.86277699999999,44.34384],"type":"Point"}
}