{
  "type": "Feature",
  "properties": {
    "iso:country":"US",
    "sg:address":"1021 27th St",
    "sg:city":"Caledonia",
    "sg:classifiers":[
        {
            "category":"Retail",
            "subcategory":"Auto Repair",
            "type":"Services"
        }
    ],
    "sg:phone":"+1 262 835 4877",
    "sg:postcode":"53108",
    "sg:province":"WI",
    "sg:tags":[
        "truck"
    ],
    "wof:name":"R DS Truck Service Inc",
    "wof:placetype":"venue"
},
  "geometry": {"coordinates":[-87.95326,42.829306],"type":"Point"}
}