{
  "type": "Feature",
  "properties": {
    "iso:country":"US",
    "sg:address":"277 4th Ave N",
    "sg:city":"Park Falls",
    "sg:classifiers":[
        {
            "category":"Health Services",
            "subcategory":"Doctor",
            "type":"Services"
        }
    ],
    "sg:phone":"+1 715 762 4825",
    "sg:postcode":"54552",
    "sg:province":"WI",
    "wof:name":"Breen William DDS Inc",
    "wof:placetype":"venue"
},
  "geometry": {"coordinates":[-90.45189499999999,45.936902],"type":"Point"}
}