{
  "type": "Feature",
  "properties": {
    "iso:country":"US",
    "sg:address":"2992 Co Rd Y",
    "sg:city":"Lomira",
    "sg:classifiers":[
        {
            "category":"Farming",
            "subcategory":"Livestock Farm",
            "type":"Manufacturing & Wholesale Goods"
        }
    ],
    "sg:phone":"+1 920 583 4039",
    "sg:postcode":"53048",
    "sg:province":"WI",
    "sg:tags":[
        "beef",
        "feedlot",
        "cattle"
    ],
    "wof:name":"Bo Joe Farm",
    "wof:placetype":"venue"
},
  "geometry": {"coordinates":[-88.547715,43.573469],"type":"Point"}
}