{
  "type": "Feature",
  "properties": {
    "iso:country":"US",
    "sg:address":"11876 McLeisch Rd",
    "sg:city":"Baraboo",
    "sg:classifiers":[
        {
            "category":"Organizations",
            "subcategory":"Religious Organization",
            "type":"Services"
        }
    ],
    "sg:phone":"+1 608 356 8113",
    "sg:postcode":"53913",
    "sg:province":"WI",
    "sg:tags":[
        "house",
        "retreat"
    ],
    "wof:name":"Durward's Glen Retreat",
    "wof:placetype":"venue"
},
  "geometry": {"coordinates":[-89.591866,43.43534],"type":"Point"}
}