{
  "type": "Feature",
  "properties": {
    "iso:country":"US",
    "sg:address":"315 W Seminary St",
    "sg:city":"Richland Center",
    "sg:classifiers":[
        {
            "category":"Autos & Motor Vehicles",
            "subcategory":"Auto Supplies",
            "type":"Retail Goods"
        },
        {
            "category":"Wholesale",
            "subcategory":"Auto Parts",
            "type":"Manufacturing & Wholesale Goods"
        }
    ],
    "sg:phone":"+1 608 647 2140",
    "sg:postcode":"53581",
    "sg:province":"WI",
    "sg:tags":[
        "automobile"
    ],
    "wof:name":"United Auto Supply Inc",
    "wof:placetype":"venue"
},
  "geometry": {"coordinates":[-90.388739,43.334612],"type":"Point"}
}