{
  "type": "Feature",
  "properties": {
    "iso:country":"US",
    "sg:address":"421 Water St",
    "sg:city":"Prairie Du Sac",
    "sg:classifiers":[
        {
            "category":"Health Services",
            "subcategory":"Chiropractor",
            "type":"Services"
        }
    ],
    "sg:phone":"+1 608 643 5060",
    "sg:postcode":"53578",
    "sg:province":"WI",
    "wof:name":"Cody Chiropractic Wellness Ctr",
    "wof:placetype":"venue"
},
  "geometry": {"coordinates":[-89.719063,43.288912],"type":"Point"}
}