{
  "type": "Feature",
  "properties": {
    "iso:country":"US",
    "sg:address":"424 Orange St",
    "sg:city":"Hudson",
    "sg:classifiers":[
        {
            "category":"Shopping",
            "subcategory":"Crafts & Fabrics",
            "type":"Retail Goods"
        }
    ],
    "sg:phone":"+1 715 381 0466",
    "sg:postcode":"54016",
    "sg:province":"WI",
    "sg:tags":[
        "material",
        "needlework"
    ],
    "wof:name":"Carolynn's Needle Arts",
    "wof:placetype":"venue"
},
  "geometry": {"coordinates":[-92.75365,44.979177],"type":"Point"}
}