{
  "type": "Feature",
  "properties": {
    "addr:full":"105 S Ludington St Columbus WI 53925",
    "addr:housenumber":"105",
    "addr:postcode":"53925",
    "addr:street":"S Ludington St",
    "iso:country":"US",
    "sg:address":"105 S Ludington St",
    "sg:city":"Columbus",
    "sg:classifiers":[
        {
            "category":"Insurance",
            "subcategory":"Insurance Agent",
            "type":"Services"
        }
    ],
    "sg:phone":"+1 920 623 4488",
    "sg:postcode":"53925",
    "sg:province":"WI",
    "wof:name":"American Family Insurance",
    "wof:placetype":"venue"
},
  "geometry": {"coordinates":[-89.01489100000001,43.337851],"type":"Point"}
}