{
  "type": "Feature",
  "properties": {
    "iso:country":"US",
    "sg:address":"13195 Hampton Rd",
    "sg:city":"Butler",
    "sg:classifiers":[
        {
            "category":"Social Services",
            "type":"Services"
        }
    ],
    "sg:phone":"+1 262 781 4445",
    "sg:postcode":"53007",
    "sg:province":"WI",
    "sg:tags":[
        "individual",
        "family"
    ],
    "wof:name":"Make--wish Fundation Wisconsin",
    "wof:placetype":"venue"
},
  "geometry": {"coordinates":[-88.069711,43.104572],"type":"Point"}
}