{
  "type": "Feature",
  "properties": {
    "iso:country":"US",
    "sg:address":"31380 State Hwy 130",
    "sg:city":"Lone Rock",
    "sg:classifiers":[
        {
            "category":"Farming",
            "subcategory":"Dairy Farm",
            "type":"Manufacturing & Wholesale Goods"
        }
    ],
    "sg:phone":"+1 608 583 4965",
    "sg:postcode":"53556",
    "sg:province":"WI",
    "wof:name":"Lasebra Farms LLC",
    "wof:placetype":"venue"
},
  "geometry": {"coordinates":[-90.227273,43.242209],"type":"Point"}
}