{
  "type": "Feature",
  "properties": {
    "iso:country":"US",
    "sg:address":"1210 Allermann Dr",
    "sg:city":"Watertown",
    "sg:classifiers":[
        {
            "category":"Real Estate",
            "subcategory":"Real Estate Agent",
            "type":"Services"
        }
    ],
    "sg:phone":"+1 920 261 6950",
    "sg:postcode":"53094",
    "sg:province":"WI",
    "wof:name":"Sold Quick Homebuyers LLC",
    "wof:placetype":"venue"
},
  "geometry": {"coordinates":[-88.70281900000001,43.180615],"type":"Point"}
}