{
  "type": "Feature",
  "properties": {
    "addr:full":"19450 W Coffee Rd New Berlin WI 53146",
    "addr:housenumber":"19450",
    "addr:postcode":"53146",
    "addr:street":"W Coffee Rd",
    "iso:country":"US",
    "sg:address":"19450 W Coffee Rd",
    "sg:city":"New Berlin",
    "sg:classifiers":[
        {
            "category":"Banks & Credit Unions",
            "subcategory":"Investment Brokerage",
            "type":"Services"
        }
    ],
    "sg:phone":"+1 262 549 0503",
    "sg:postcode":"53146",
    "sg:province":"WI",
    "sg:tags":[
        "advisory"
    ],
    "wof:name":"Roger C Helms",
    "wof:placetype":"venue"
},
  "geometry": {"coordinates":[-88.15822900000001,42.981043],"type":"Point"}
}