{
  "type": "Feature",
  "properties": {
    "addr:full":"512 S Fond du Lac Ave Campbellsport WI 53010",
    "addr:housenumber":"512",
    "addr:postcode":"53010",
    "addr:street":"S Fond Du Lac Ave",
    "iso:country":"US",
    "sg:address":"512 S Fond du Lac Ave",
    "sg:city":"Campbellsport",
    "sg:classifiers":[
        {
            "category":"Retail",
            "subcategory":"Self-service Laundry",
            "type":"Services"
        }
    ],
    "sg:phone":"+1 920 533 3440",
    "sg:postcode":"53010",
    "sg:province":"WI",
    "wof:name":"All Washed Up",
    "wof:placetype":"venue"
},
  "geometry": {"coordinates":[-88.282796,43.593837],"type":"Point"}
}