{
  "type": "Feature",
  "properties": {
    "iso:country":"US",
    "sg:address":"2491 Co Rd B",
    "sg:city":"Kewaunee",
    "sg:classifiers":[
        {
            "category":"Building & Trades",
            "subcategory":"Construction",
            "type":"Services"
        }
    ],
    "sg:phone":"+1 920 388 3229",
    "sg:postcode":"54216",
    "sg:province":"WI",
    "sg:tags":[
        "contractor",
        "nonresidential"
    ],
    "wof:name":"U Brothers Masonry",
    "wof:placetype":"venue"
},
  "geometry": {"coordinates":[-87.596342,44.414374],"type":"Point"}
}