{
  "type": "Feature",
  "properties": {
    "iso:country":"US",
    "sg:address":"1243 E Lake St",
    "sg:city":"Horicon",
    "sg:classifiers":[
        {
            "category":"Restaurant",
            "type":"Food & Drink"
        }
    ],
    "sg:phone":"+1 920 485 2711",
    "sg:postcode":"53032",
    "sg:province":"WI",
    "wof:name":"Backyard Grille",
    "wof:placetype":"venue"
},
  "geometry": {"coordinates":[-88.61972299999999,43.447619],"type":"Point"}
}