{
  "type": "Feature",
  "properties": {
    "iso:country":"US",
    "sg:address":"602 Military Rd",
    "sg:city":"Rothschild",
    "sg:classifiers":[
        {
            "category":"Education",
            "subcategory":"School",
            "type":"Public Place"
        }
    ],
    "sg:phone":"+1 715 359 9662",
    "sg:postcode":"54474",
    "sg:province":"WI",
    "wof:name":"St Mark's Catholic School",
    "wof:placetype":"venue"
},
  "geometry": {"coordinates":[-89.617811,44.880113],"type":"Point"}
}