{
  "type": "Feature",
  "properties": {
    "iso:country":"US",
    "sg:address":"14302 US Hwy 14",
    "sg:city":"Richland Center",
    "sg:classifiers":[
        {
            "category":"Home & Garden",
            "subcategory":"Garden Supply",
            "type":"Retail Goods"
        }
    ],
    "sg:phone":"+1 608 536 3533",
    "sg:postcode":"53581",
    "sg:province":"WI",
    "sg:tags":[
        "landscape"
    ],
    "wof:name":"Lincolnway Nurs Lincoln Ldscpg",
    "wof:placetype":"venue"
},
  "geometry": {"coordinates":[-90.58044700000001,43.382541],"type":"Point"}
}