{
  "type": "Feature",
  "properties": {
    "iso:country":"US",
    "sg:address":"565 Milwaukee Ave",
    "sg:city":"Burlington",
    "sg:classifiers":[
        {
            "category":"Professional",
            "subcategory":"Accounting & Tax Preparation",
            "type":"Services"
        }
    ],
    "sg:phone":"+1 262 763 4605",
    "sg:postcode":"53105",
    "sg:province":"WI",
    "wof:name":"Wayne J Christman",
    "wof:placetype":"venue"
},
  "geometry": {"coordinates":[-88.277283,42.680456],"type":"Point"}
}