{
  "type": "Feature",
  "properties": {
    "addr:full":"8763 Main Rd Springbrook WI 54875",
    "addr:housenumber":"8763",
    "addr:postcode":"54875",
    "addr:street":"Main Rd",
    "iso:country":"US",
    "sg:address":"8763 Main Rd",
    "sg:city":"Springbrook",
    "sg:classifiers":[
        {
            "category":"Professional",
            "subcategory":"Management & Consulting",
            "type":"Services"
        }
    ],
    "sg:phone":"+1 715 766 2208",
    "sg:postcode":"54875",
    "sg:province":"WI",
    "sg:tags":[
        "business"
    ],
    "wof:name":"Guides Choice",
    "wof:placetype":"venue"
},
  "geometry": {"coordinates":[-91.65361900000001,45.946301],"type":"Point"}
}