{
  "type": "Feature",
  "properties": {
    "iso:country":"US",
    "sg:address":"5601 W Florist Ave",
    "sg:city":"Milwaukee",
    "sg:classifiers":[
        {
            "category":"Shopping",
            "subcategory":"Hobbies, Toys, & Games",
            "type":"Retail Goods"
        },
        {
            "category":"Shopping",
            "subcategory":"Crafts & Fabrics",
            "type":"Retail Goods"
        },
        {
            "category":"Wholesale",
            "subcategory":"Toys & Hobbies",
            "type":"Manufacturing & Wholesale Goods"
        }
    ],
    "sg:phone":"+1 414 461 1050",
    "sg:postcode":"53218",
    "sg:province":"WI",
    "sg:tags":[
        "shop",
        "art",
        "supply",
        "model",
        "supplies-wholesale",
        "store",
        "manufacturer"
    ],
    "sg:website":"http://www.walthers.com",
    "wof:name":"Walthers Terminal Hobby Shop",
    "wof:placetype":"venue"
},
  "geometry": {"coordinates":[-87.981945,43.126601],"type":"Point"}
}