{
  "type": "Feature",
  "properties": {
    "iso:country":"US",
    "sg:address":"332 Hatten Ave",
    "sg:city":"Rice Lake",
    "sg:classifiers":[
        {
            "category":"Building & Trades",
            "subcategory":"Construction",
            "type":"Services"
        }
    ],
    "sg:phone":"+1 715 234 4554",
    "sg:postcode":"54868",
    "sg:province":"WI",
    "sg:tags":[
        "house"
    ],
    "wof:name":"Boehm & Wampfler Construc",
    "wof:placetype":"venue"
},
  "geometry": {"coordinates":[-91.74159299999999,45.496782],"type":"Point"}
}