{
  "type": "Feature",
  "properties": {
    "iso:country":"US",
    "sg:address":"1561 River Highlands Dr",
    "sg:city":"Oconomowoc",
    "sg:classifiers":[
        {
            "category":"Manufacturing",
            "subcategory":"Toys & Sporting Goods",
            "type":"Manufacturing & Wholesale Goods"
        }
    ],
    "sg:phone":"+1 262 567 5341",
    "sg:postcode":"53066",
    "sg:province":"WI",
    "sg:tags":[
        "mfg"
    ],
    "wof:name":"Precision Aero",
    "wof:placetype":"venue"
},
  "geometry": {"coordinates":[-88.526018,43.098507],"type":"Point"}
}