{
  "type": "Feature",
  "properties": {
    "addr:full":"5711 Carnation Ct Greendale WI 53129",
    "addr:housenumber":"5711",
    "addr:postcode":"53129",
    "addr:street":"Carnation Ct",
    "iso:country":"US",
    "sg:address":"5711 Carnation Ct",
    "sg:city":"Greendale",
    "sg:classifiers":[
        {
            "category":"Travel",
            "subcategory":"Travel Agent",
            "type":"Entertainment"
        }
    ],
    "sg:phone":"+1 414 423 0963",
    "sg:postcode":"53129",
    "sg:province":"WI",
    "sg:tags":[
        "operator",
        "tour"
    ],
    "wof:name":"Original Pedal Cab Tours",
    "wof:placetype":"venue"
},
  "geometry": {"coordinates":[-87.992874,42.939695],"type":"Point"}
}