{
  "type": "Feature",
  "properties": {
    "iso:country":"US",
    "sg:address":"10401 W Lincoln Ave",
    "sg:city":"Milwaukee",
    "sg:classifiers":[
        {
            "category":"Health Services",
            "subcategory":"Doctor",
            "type":"Services"
        }
    ],
    "sg:phone":"+1 414 546 1900",
    "sg:postcode":"53227",
    "sg:province":"WI",
    "sg:tags":[
        "dentist"
    ],
    "wof:name":"Endodontics Specialists",
    "wof:placetype":"venue"
},
  "geometry": {"coordinates":[-88.04267400000001,43.002514],"type":"Point"}
}