{
  "type": "Feature",
  "properties": {
    "iso:country":"US",
    "sg:address":"6702 Stonefield Rd",
    "sg:city":"Middleton",
    "sg:classifiers":[
        {
            "category":"Health Services",
            "subcategory":"Clinic",
            "type":"Services"
        }
    ],
    "sg:phone":"+1 608 827 7100",
    "sg:postcode":"53562",
    "sg:province":"WI",
    "sg:tags":[
        "specialty",
        "outpatient"
    ],
    "sg:website":"www.communitycareresources.com",
    "wof:name":"Community Care Resources",
    "wof:placetype":"venue"
},
  "geometry": {"coordinates":[-89.50057,43.083233],"type":"Point"}
}