{
  "type": "Feature",
  "properties": {
    "iso:country":"US",
    "sg:address":"3801 Superior Ave",
    "sg:city":"Sheboygan",
    "sg:classifiers":[
        {
            "category":"Autos & Motor Vehicles",
            "subcategory":"Fuel & Gas Station",
            "type":"Retail Goods"
        }
    ],
    "sg:phone":"+1 920 457 0670",
    "sg:postcode":"53081",
    "sg:province":"WI",
    "sg:tags":[
        "gasoline",
        "product",
        "station",
        "petroleum",
        "al"
    ],
    "wof:name":"Petro Stopping Center",
    "wof:placetype":"venue"
},
  "geometry": {"coordinates":[-87.757365,43.760998],"type":"Point"}
}