{
  "type": "Feature",
  "properties": {
    "iso:country":"US",
    "sg:address":"1850 W Pointe Dr",
    "sg:city":"Oshkosh",
    "sg:classifiers":[
        {
            "category":"Health Services",
            "subcategory":"Doctor",
            "type":"Services"
        }
    ],
    "sg:phone":"+1 920 233 2222",
    "sg:postcode":"54902",
    "sg:province":"WI",
    "sg:tags":[
        "dentist"
    ],
    "wof:name":"Lawrence A Johnson DDS SC",
    "wof:placetype":"venue"
},
  "geometry": {"coordinates":[-88.581058,44.019365],"type":"Point"}
}