{
  "type": "Feature",
  "properties": {
    "iso:country":"US",
    "sg:address":"3918 N Bay Dr",
    "sg:city":"Racine",
    "sg:classifiers":[
        {
            "category":"Personal",
            "subcategory":"Beauty Salon",
            "type":"Services"
        }
    ],
    "sg:phone":"+1 262 752 0070",
    "sg:postcode":"53402",
    "sg:province":"WI",
    "wof:name":"Ultimate Looks Hair Salon",
    "wof:placetype":"venue"
},
  "geometry": {"coordinates":[-87.780615,42.769173],"type":"Point"}
}