{
  "type": "Feature",
  "properties": {
    "iso:country":"US",
    "sg:address":"1040 W Grand Ave",
    "sg:city":"Wisconsin Rapids",
    "sg:classifiers":[
        {
            "category":"Retail",
            "subcategory":"Self-service Laundry",
            "type":"Services"
        }
    ],
    "sg:phone":"+1 715 423 0438",
    "sg:postcode":"54495",
    "sg:province":"WI",
    "sg:tags":[
        "coin"
    ],
    "wof:name":"Coin Phone Management Co",
    "wof:placetype":"venue"
},
  "geometry": {"coordinates":[-89.83649800000001,44.395793],"type":"Point"}
}