{
  "type": "Feature",
  "properties": {
    "iso:country":"US",
    "sg:address":"3680 Kinsman Blvd",
    "sg:city":"Madison",
    "sg:classifiers":[
        {
            "category":"Shopping",
            "subcategory":"Stationery & Office Supplies",
            "type":"Retail Goods"
        }
    ],
    "sg:phone":"+1 608 257 2736",
    "sg:postcode":"53704",
    "sg:province":"WI",
    "sg:website":"www.jacksonofficesupply.com",
    "wof:name":"Jackson Office Supplies",
    "wof:placetype":"venue"
},
  "geometry": {"coordinates":[-89.326238,43.125772],"type":"Point"}
}