{
  "type": "Feature",
  "properties": {
    "iso:country":"US",
    "sg:address":"2155 W Nordale Dr",
    "sg:city":"Appleton",
    "sg:classifiers":[
        {
            "category":"Home & Garden",
            "subcategory":"Building Materials",
            "type":"Retail Goods"
        }
    ],
    "sg:phone":"+1 920 739 7477",
    "sg:postcode":"54914",
    "sg:province":"WI",
    "sg:website":"www.bsnew.com",
    "wof:name":"Builders Supply Of Ne Wi",
    "wof:placetype":"venue"
},
  "geometry": {"coordinates":[-88.439907,44.286321],"type":"Point"}
}