{
  "type": "Feature",
  "properties": {
    "addr:full":"218 N Main St Brillion WI 54110",
    "addr:housenumber":"218",
    "addr:postcode":"54110",
    "addr:street":"N Main St",
    "iso:country":"US",
    "sg:address":"218 N Main St",
    "sg:city":"Brillion",
    "sg:classifiers":[
        {
            "category":"Insurance",
            "subcategory":"Insurance Agent",
            "type":"Services"
        }
    ],
    "sg:phone":"+1 920 756 2333",
    "sg:postcode":"54110",
    "sg:province":"WI",
    "wof:name":"Tom KEES Insurance",
    "wof:placetype":"venue"
},
  "geometry": {"coordinates":[-88.064302,44.17828],"type":"Point"}
}