{
  "type": "Feature",
  "properties": {
    "iso:country":"US",
    "sg:address":"813 N Jefferson St",
    "sg:city":"Milwaukee",
    "sg:classifiers":[
        {
            "category":"Shopping",
            "subcategory":"Jewelry",
            "type":"Retail Goods"
        }
    ],
    "sg:phone":"+1 414 276 1780",
    "sg:postcode":"53202",
    "sg:province":"WI",
    "wof:name":"Rohr Jewelers",
    "wof:placetype":"venue"
},
  "geometry": {"coordinates":[-87.90572299999999,43.042387],"type":"Point"}
}