{
  "type": "Feature",
  "properties": {
    "iso:country":"US",
    "sg:address":"1228 E Main St",
    "sg:city":"Reedsburg",
    "sg:classifiers":[
        {
            "category":"Real Estate",
            "subcategory":"Architect",
            "type":"Services"
        }
    ],
    "sg:phone":"+1 608 524 3488",
    "sg:postcode":"53959",
    "sg:province":"WI",
    "wof:name":"Blakeslee & Assoc",
    "wof:placetype":"venue"
},
  "geometry": {"coordinates":[-89.991771,43.532374],"type":"Point"}
}