{
  "type": "Feature",
  "properties": {
    "iso:country":"US",
    "sg:address":"1301 Erie Ave",
    "sg:city":"Sheboygan",
    "sg:classifiers":[
        {
            "category":"Professional",
            "subcategory":"Management & Consulting",
            "type":"Services"
        }
    ],
    "sg:phone":"+1 920 457 7493",
    "sg:postcode":"53081",
    "sg:province":"WI",
    "sg:tags":[
        "marketing",
        "program"
    ],
    "sg:website":"www.hyfab.com",
    "wof:name":"Clothcrafters",
    "wof:placetype":"venue"
},
  "geometry": {"coordinates":[-87.721351,43.756366],"type":"Point"}
}