{
  "type": "Feature",
  "properties": {
    "iso:country":"US",
    "sg:address":"4838 Co Rd Ff",
    "sg:city":"Oshkosh",
    "sg:classifiers":[
        {
            "category":"Farming",
            "subcategory":"Farm",
            "type":"Manufacturing & Wholesale Goods"
        }
    ],
    "sg:phone":"+1 920 589 3628",
    "sg:postcode":"54904",
    "sg:province":"WI",
    "sg:tags":[
        "crop",
        "animal",
        "general"
    ],
    "wof:name":"David Konrad",
    "wof:placetype":"venue"
},
  "geometry": {"coordinates":[-88.638946,43.894712],"type":"Point"}
}