{
  "type": "Feature",
  "properties": {
    "iso:country":"US",
    "sg:address":"1421 Broadway St S",
    "sg:city":"Menomonie",
    "sg:classifiers":[
        {
            "category":"Insurance",
            "subcategory":"Insurance Agent",
            "type":"Services"
        }
    ],
    "sg:phone":"+1 715 235 4846",
    "sg:postcode":"54751",
    "sg:province":"WI",
    "sg:tags":[
        "life",
        "carrier"
    ],
    "wof:name":"Johnson Gary T & Andrea Insur",
    "wof:placetype":"venue"
},
  "geometry": {"coordinates":[-91.92983700000001,44.869928],"type":"Point"}
}