{
  "type": "Feature",
  "properties": {
    "addr:full":"2075 160th St Milltown WI 54858",
    "addr:housenumber":"2075",
    "addr:postcode":"54858",
    "addr:street":"160Th St",
    "iso:country":"US",
    "sg:address":"2075 160th St",
    "sg:city":"Milltown",
    "sg:phone":"+1 715 825 2507",
    "sg:postcode":"54858",
    "sg:province":"WI",
    "sg:tags":[
        "farm",
        "corn"
    ],
    "wof:name":"Arnold Herwick",
    "wof:placetype":"venue"
},
  "geometry": {"coordinates":[-92.48878499999999,45.508728],"type":"Point"}
}