{
  "type": "Feature",
  "properties": {
    "addr:full":"4312 US Hwy 151 Oakfield WI 53065",
    "addr:housenumber":"4312",
    "addr:postcode":"53065",
    "addr:street":"Us Hwy 151",
    "iso:country":"US",
    "sg:address":"4312 US Hwy 151",
    "sg:city":"Oakfield",
    "sg:classifiers":[
        {
            "category":"Farming",
            "subcategory":"Dairy Farm",
            "type":"Manufacturing & Wholesale Goods"
        }
    ],
    "sg:phone":"+1 920 583 4086",
    "sg:postcode":"53065",
    "sg:province":"WI",
    "wof:name":"Daniel Flood",
    "wof:placetype":"venue"
},
  "geometry": {"coordinates":[-88.608079,43.694638],"type":"Point"}
}