{
  "type": "Feature",
  "properties": {
    "iso:country":"US",
    "sg:address":"610 E Longview Dr",
    "sg:city":"Appleton",
    "sg:classifiers":[
        {
            "category":"Health Services",
            "subcategory":"Doctor",
            "type":"Services"
        }
    ],
    "sg:phone":"+1 920 734 1646",
    "sg:postcode":"54911",
    "sg:province":"WI",
    "sg:tags":[
        "medical"
    ],
    "wof:name":"Mark J Scherer MD",
    "wof:placetype":"venue"
},
  "geometry": {"coordinates":[-88.39586799999999,44.28642],"type":"Point"}
}