{
  "type": "Feature",
  "properties": {
    "iso:country":"US",
    "sg:address":"10149 State Hwy 16",
    "sg:city":"Sparta",
    "sg:classifiers":[
        {
            "category":"Autos & Motor Vehicles",
            "subcategory":"Automobile Sales",
            "type":"Retail Goods"
        }
    ],
    "sg:phone":"+1 608 269 4023",
    "sg:postcode":"54656",
    "sg:province":"WI",
    "sg:tags":[
        "used"
    ],
    "wof:name":"Dash Motors",
    "wof:placetype":"venue"
},
  "geometry": {"coordinates":[-90.789114,43.940302],"type":"Point"}
}