{
  "type": "Feature",
  "properties": {
    "iso:country":"US",
    "sg:address":"2478 Co Hwy Gg",
    "sg:city":"Brodhead",
    "sg:classifiers":[
        {
            "category":"Retail",
            "subcategory":"Auto Repair",
            "type":"Services"
        }
    ],
    "sg:phone":"+1 608 897 2296",
    "sg:postcode":"53520",
    "sg:province":"WI",
    "sg:tags":[
        "body",
        "automobile",
        "painting"
    ],
    "wof:name":"Ultra Autobody",
    "wof:placetype":"venue"
},
  "geometry": {"coordinates":[-89.398215,42.594948],"type":"Point"}
}