{
  "type": "Feature",
  "properties": {
    "iso:country":"US",
    "sg:address":"433 McKinley Ave",
    "sg:city":"Omro",
    "sg:classifiers":[
        {
            "category":"Building & Trades",
            "subcategory":"Landscaping Services",
            "type":"Services"
        }
    ],
    "sg:phone":"+1 920 685 6664",
    "sg:postcode":"54963",
    "sg:province":"WI",
    "sg:tags":[
        "lawn",
        "maintenance",
        "grounds"
    ],
    "wof:name":"A Z Lawn Care",
    "wof:placetype":"venue"
},
  "geometry": {"coordinates":[-88.731365,44.035819],"type":"Point"}
}