{
  "type": "Feature",
  "properties": {
    "iso:country":"US",
    "sg:address":"3767 S 76th St Apt 3",
    "sg:city":"Milwaukee",
    "sg:classifiers":[
        {
            "category":"Farming",
            "subcategory":"Livestock Farm",
            "type":"Manufacturing & Wholesale Goods"
        }
    ],
    "sg:phone":"+1 414 455 8416",
    "sg:postcode":"53220",
    "sg:province":"WI",
    "sg:tags":[
        "horse"
    ],
    "wof:name":"Hagers Horses",
    "wof:placetype":"venue"
},
  "geometry": {"coordinates":[-88.00824,42.974322],"type":"Point"}
}