{
  "type": "Feature",
  "properties": {
    "iso:country":"US",
    "sg:address":"1844 Superior Ave",
    "sg:city":"Tomah",
    "sg:classifiers":[
        {
            "category":"Food & Beverages",
            "subcategory":"Groceries & Convenience Stores",
            "type":"Retail Goods"
        }
    ],
    "sg:phone":"+1 608 374 2064",
    "sg:postcode":"54660",
    "sg:province":"WI",
    "wof:name":"Aldi Store",
    "wof:placetype":"venue"
},
  "geometry": {"coordinates":[-90.504718,43.969348],"type":"Point"}
}