{
  "type": "Feature",
  "properties": {
    "iso:country":"US",
    "sg:address":"328 Grand Ave",
    "sg:city":"Little Chute",
    "sg:classifiers":[
        {
            "category":"Social Services",
            "subcategory":"Child Care",
            "type":"Services"
        }
    ],
    "sg:phone":"+1 920 788 8779",
    "sg:postcode":"54140",
    "sg:province":"WI",
    "sg:tags":[
        "day"
    ],
    "wof:name":"Cinder-Care",
    "wof:placetype":"venue"
},
  "geometry": {"coordinates":[-88.31551,44.278152],"type":"Point"}
}