{
  "type": "Feature",
  "properties": {
    "addr:full":"1500 Elm St Boscobel WI 53805",
    "addr:housenumber":"1500",
    "addr:postcode":"53805",
    "addr:street":"Elm St",
    "iso:country":"US",
    "sg:address":"1500 Elm St",
    "sg:city":"Boscobel",
    "sg:classifiers":[
        {
            "category":"Restaurant",
            "type":"Food & Drink"
        }
    ],
    "sg:menulink":"http://www.allmenus.com/wi/boscobel/225074-caseys-general-store/menu/",
    "sg:phone":"+1 608 375 4114",
    "sg:postcode":"53805",
    "sg:province":"WI",
    "sg:tags":[
        "american",
        "pizza"
    ],
    "wof:name":"Casey's General Store",
    "wof:placetype":"venue"
},
  "geometry": {"coordinates":[-90.71064200000001,43.132884],"type":"Point"}
}