{
  "type": "Feature",
  "properties": {
    "addr:full":"10847 Cardinal Ave Loyal WI 54446",
    "addr:housenumber":"10847",
    "addr:postcode":"54446",
    "addr:street":"Cardinal Ave",
    "iso:country":"US",
    "sg:address":"10847 Cardinal Ave",
    "sg:city":"Loyal",
    "sg:classifiers":[
        {
            "category":"Farming",
            "subcategory":"Dairy Farm",
            "type":"Manufacturing & Wholesale Goods"
        }
    ],
    "sg:phone":"+1 715 267 6674",
    "sg:postcode":"54446",
    "sg:province":"WI",
    "wof:name":"Timothy Milz",
    "wof:placetype":"venue"
},
  "geometry": {"coordinates":[-90.536818,44.811526],"type":"Point"}
}