{
  "type": "Feature",
  "properties": {
    "iso:country":"US",
    "sg:address":"302 N Spring St",
    "sg:city":"Beaver Dam",
    "sg:classifiers":[
        {
            "category":"Insurance",
            "subcategory":"Health Insurance",
            "type":"Services"
        }
    ],
    "sg:phone":"+1 920 887 1200",
    "sg:postcode":"53916",
    "sg:province":"WI",
    "sg:tags":[
        "plan"
    ],
    "wof:name":"John Deere",
    "wof:placetype":"venue"
},
  "geometry": {"coordinates":[-88.837039,43.459489],"type":"Point"}
}