{
  "type": "Feature",
  "properties": {
    "iso:country":"US",
    "sg:address":"10010 State Hwy 133",
    "sg:city":"Cassville",
    "sg:phone":"+1 608 725 5407",
    "sg:postcode":"53806",
    "sg:province":"WI",
    "sg:tags":[
        "farm",
        "corn"
    ],
    "wof:name":"Dennis Bausch",
    "wof:placetype":"venue"
},
  "geometry": {"coordinates":[-90.90992199999999,42.720171],"type":"Point"}
}