{
  "type": "Feature",
  "properties": {
    "iso:country":"US",
    "sg:address":"210 S Academy St",
    "sg:city":"Janesville",
    "sg:classifiers":[
        {
            "category":"Retail",
            "subcategory":"Repair Shop",
            "type":"Services"
        }
    ],
    "sg:phone":"+1 608 757 1717",
    "sg:postcode":"53548",
    "sg:province":"WI",
    "wof:name":"Sounds Of Music",
    "wof:placetype":"venue"
},
  "geometry": {"coordinates":[-89.02808899999999,42.676634],"type":"Point"}
}