{
  "type": "Feature",
  "properties": {
    "iso:country":"US",
    "sg:address":"425 George St",
    "sg:city":"Green Bay",
    "sg:classifiers":[
        {
            "category":"Shopping",
            "subcategory":"Clothing, Apparel, & Fashions",
            "type":"Retail Goods"
        }
    ],
    "sg:phone":"+1 920 884 7984",
    "sg:postcode":"54302",
    "sg:province":"WI",
    "wof:name":"Perfect Bride",
    "wof:placetype":"venue"
},
  "geometry": {"coordinates":[-87.987808,44.499325],"type":"Point"}
}