{
  "type": "Feature",
  "properties": {
    "iso:country":"US",
    "sg:address":"36620 89th St",
    "sg:city":"Twin Lakes",
    "sg:classifiers":[
        {
            "category":"Manufacturing",
            "subcategory":"Tools & Machinery",
            "type":"Manufacturing & Wholesale Goods"
        }
    ],
    "sg:phone":"+1 262 877 2171",
    "sg:postcode":"53181",
    "sg:province":"WI",
    "sg:tags":[
        "body",
        "automobile",
        "shop",
        "equipment"
    ],
    "sg:website":"www.fivestarbodies.com",
    "wof:name":"Five Star Fabricating",
    "wof:placetype":"venue"
},
  "geometry": {"coordinates":[-88.25410599999999,42.54557],"type":"Point"}
}