{
  "type": "Feature",
  "properties": {
    "iso:country":"US",
    "sg:address":"2635 S 134th St",
    "sg:city":"New Berlin",
    "sg:classifiers":[
        {
            "category":"Manufacturing",
            "subcategory":"Tools & Machinery",
            "type":"Manufacturing & Wholesale Goods"
        }
    ],
    "sg:phone":"+1 262 782 4442",
    "sg:postcode":"53151",
    "sg:province":"WI",
    "sg:tags":[
        "test",
        "equipment",
        "mfg"
    ],
    "wof:name":"Control Electronics",
    "wof:placetype":"venue"
},
  "geometry": {"coordinates":[-88.079975,42.995864],"type":"Point"}
}