{
  "type": "Feature",
  "properties": {
    "iso:country":"US",
    "sg:address":"510 N 3rd St",
    "sg:city":"Abbotsford",
    "sg:classifiers":[
        {
            "category":"Professional",
            "subcategory":"Secretarial Services",
            "type":"Services"
        }
    ],
    "sg:phone":"+1 715 223 4147",
    "sg:postcode":"54405",
    "sg:province":"WI",
    "sg:tags":[
        "reporting"
    ],
    "wof:name":"Kathy Knight",
    "wof:placetype":"venue"
},
  "geometry": {"coordinates":[-90.318292,44.952798],"type":"Point"}
}