{
  "type": "Feature",
  "properties": {
    "iso:country":"US",
    "sg:address":"201 Frontenac Ave",
    "sg:city":"Stevens Point",
    "sg:classifiers":[
        {
            "category":"Professional",
            "subcategory":"Accounting & Tax Preparation",
            "type":"Services"
        }
    ],
    "sg:phone":"+1 715 344 4984",
    "sg:postcode":"54481",
    "sg:province":"WI",
    "sg:tags":[
        "accountant"
    ],
    "sg:website":"www.cliftoncpa.com",
    "wof:name":"Clifton Gunderson & Co",
    "wof:placetype":"venue"
},
  "geometry": {"coordinates":[-89.555737,44.533007],"type":"Point"}
}