{
  "type": "Feature",
  "properties": {
    "iso:country":"US",
    "sg:address":"6931 W North Ave",
    "sg:city":"Wauwatosa",
    "sg:classifiers":[
        {
            "category":"Shopping",
            "subcategory":"Gifts & Souvenirs",
            "type":"Retail Goods"
        }
    ],
    "sg:phone":"+1 414 453 5252",
    "sg:postcode":"53213",
    "sg:province":"WI",
    "sg:tags":[
        "party",
        "supply"
    ],
    "wof:name":"Bartz's The Party Store",
    "wof:placetype":"venue"
},
  "geometry": {"coordinates":[-87.999438,43.060664],"type":"Point"}
}