{
  "type": "Feature",
  "properties": {
    "iso:country":"US",
    "sg:address":"11326 Lakeland Rd",
    "sg:city":"Fox Lake",
    "sg:classifiers":[
        {
            "category":"Building & Trades",
            "subcategory":"Construction",
            "type":"Services"
        }
    ],
    "sg:phone":"+1 920 928 2079",
    "sg:postcode":"53933",
    "sg:province":"WI",
    "sg:tags":[
        "excavation",
        "contractor"
    ],
    "wof:name":"Gullys Digging Service",
    "wof:placetype":"venue"
},
  "geometry": {"coordinates":[-88.85624199999999,43.613898],"type":"Point"}
}