{
  "type": "Feature",
  "properties": {
    "iso:country":"US",
    "sg:address":"2646 Carnie Rd",
    "sg:city":"Monroe",
    "sg:classifiers":[
        {
            "category":"Wholesale",
            "subcategory":"Machinery & Supplies",
            "type":"Manufacturing & Wholesale Goods"
        }
    ],
    "sg:phone":"+1 608 325 9473",
    "sg:postcode":"53566",
    "sg:province":"WI",
    "sg:tags":[
        "fire",
        "equipment",
        "fighting",
        "extinguisher"
    ],
    "wof:name":"Wisconsin Fire Apparatus",
    "wof:placetype":"venue"
},
  "geometry": {"coordinates":[-89.682945,42.600865],"type":"Point"}
}