{
  "type": "Feature",
  "properties": {
    "iso:country":"US",
    "sg:address":"106 E Washington St",
    "sg:city":"Tomah",
    "sg:classifiers":[
        {
            "category":"Professional",
            "subcategory":"Business Services",
            "type":"Services"
        }
    ],
    "sg:phone":"+1 608 372 6254",
    "sg:postcode":"54660",
    "sg:province":"WI",
    "wof:name":"Northstar",
    "wof:placetype":"venue"
},
  "geometry": {"coordinates":[-90.504575,43.98545],"type":"Point"}
}