{
  "type": "Feature",
  "properties": {
    "addr:full":"8101 22nd Ave Kenosha WI 53143",
    "addr:housenumber":"8101",
    "addr:postcode":"53143",
    "addr:street":"22Nd Ave",
    "iso:country":"US",
    "sg:address":"8101 22nd Ave",
    "sg:city":"Kenosha",
    "sg:classifiers":[
        {
            "category":"Food & Beverages",
            "subcategory":"Groceries & Convenience Stores",
            "type":"Retail Goods"
        }
    ],
    "sg:phone":"+1 262 657 1125",
    "sg:postcode":"53143",
    "sg:province":"WI",
    "wof:name":"7-Eleven",
    "wof:placetype":"venue"
},
  "geometry": {"coordinates":[-87.835054,42.554638],"type":"Point"}
}