{
  "type": "Feature",
  "properties": {
    "addr:full":"518 Hagar St La Crosse WI 54603",
    "addr:housenumber":"518",
    "addr:postcode":"54603",
    "addr:street":"Hagar St",
    "iso:country":"US",
    "sg:address":"518 Hagar St",
    "sg:city":"La Crosse",
    "sg:classifiers":[
        {
            "category":"Bars & Pubs",
            "type":"Food & Drink"
        }
    ],
    "sg:phone":"+1 608 784 6760",
    "sg:postcode":"54603",
    "sg:province":"WI",
    "wof:name":"Krazy L",
    "wof:placetype":"venue"
},
  "geometry": {"coordinates":[-91.248344,43.834566],"type":"Point"}
}