{
  "type": "Feature",
  "properties": {
    "iso:country":"US",
    "sg:address":"12160 Hillcrest Dr",
    "sg:city":"Lodi",
    "sg:classifiers":[
        {
            "category":"Real Estate",
            "subcategory":"Real Estate Agent",
            "type":"Services"
        }
    ],
    "sg:phone":"+1 608 592 5258",
    "sg:postcode":"53555",
    "sg:province":"WI",
    "wof:name":"Lakepoint Realty",
    "wof:placetype":"venue"
},
  "geometry": {"coordinates":[-89.60449699999999,43.351736],"type":"Point"}
}