{
  "type": "Feature",
  "properties": {
    "iso:country":"US",
    "sg:address":"309 2nd Ave S",
    "sg:city":"Wausau",
    "sg:classifiers":[
        {
            "category":"Professional",
            "subcategory":"Secretarial Services",
            "type":"Services"
        }
    ],
    "sg:phone":"+1 715 845 8255",
    "sg:postcode":"54401",
    "sg:province":"WI",
    "sg:tags":[
        "convention",
        "reporting",
        "court",
        "reporter"
    ],
    "wof:name":"Kraemer & Associates",
    "wof:placetype":"venue"
},
  "geometry": {"coordinates":[-89.63806099999999,44.96012],"type":"Point"}
}