{
  "type": "Feature",
  "properties": {
    "iso:country":"US",
    "sg:address":"2563 N 39th St",
    "sg:city":"Milwaukee",
    "sg:classifiers":[
        {
            "category":"Banks & Credit Unions",
            "subcategory":"Investment Brokerage",
            "type":"Services"
        },
        {
            "category":"Banks & Credit Unions",
            "subcategory":"Financial Services",
            "type":"Services"
        }
    ],
    "sg:phone":"+1 414 873 0522",
    "sg:postcode":"53210",
    "sg:province":"WI",
    "sg:tags":[
        "investor"
    ],
    "wof:name":"Ford K & R Investments",
    "wof:placetype":"venue"
},
  "geometry": {"coordinates":[-87.962305,43.064921],"type":"Point"}
}