{
  "type": "Feature",
  "properties": {
    "addr:full":"8716 N Granville Rd Milwaukee WI 53224",
    "addr:housenumber":"8716",
    "addr:postcode":"53224",
    "addr:street":"N Granville Rd",
    "iso:country":"US",
    "sg:address":"8716 N Granville Rd",
    "sg:city":"Milwaukee",
    "sg:classifiers":[
        {
            "category":"Retail",
            "subcategory":"Auto Repair",
            "type":"Services"
        }
    ],
    "sg:phone":"+1 414 365 2699",
    "sg:postcode":"53224",
    "sg:province":"WI",
    "sg:tags":[
        "repairing",
        "automobile"
    ],
    "wof:name":"SGS Automotive Svc Inc",
    "wof:placetype":"venue"
},
  "geometry": {"coordinates":[-88.041905,43.175033],"type":"Point"}
}