{
  "type": "Feature",
  "properties": {
    "iso:country":"US",
    "sg:address":"202 S Park St",
    "sg:city":"Madison",
    "sg:classifiers":[
        {
            "category":"Professional",
            "subcategory":"Business Services",
            "type":"Services"
        }
    ],
    "sg:phone":"+1 608 267 5300",
    "sg:postcode":"53715",
    "sg:province":"WI",
    "sg:tags":[
        "retirement",
        "for",
        "hospital",
        "fund",
        "home",
        "raising"
    ],
    "wof:name":"Meriter Foundation Inc",
    "wof:placetype":"venue"
},
  "geometry": {"coordinates":[-89.400873,43.065827],"type":"Point"}
}