{
  "type": "Feature",
  "properties": {
    "iso:country":"US",
    "sg:address":"8021 22nd Ave",
    "sg:city":"Kenosha",
    "sg:classifiers":[
        {
            "category":"Restaurant",
            "type":"Food & Drink"
        }
    ],
    "sg:phone":"+1 262 652 0010",
    "sg:postcode":"53143",
    "sg:province":"WI",
    "sg:tags":[
        "chinese"
    ],
    "wof:name":"Panda Szechwan Restaurant",
    "wof:placetype":"venue"
},
  "geometry": {"coordinates":[-87.835083,42.557994],"type":"Point"}
}