{
  "type": "Feature",
  "properties": {
    "iso:country":"US",
    "sg:address":"7903 Co Rd P",
    "sg:city":"Beaver",
    "sg:classifiers":[
        {
            "category":"Home & Garden",
            "subcategory":"Garden Supply",
            "type":"Retail Goods"
        }
    ],
    "sg:phone":"+1 920 680 9663",
    "sg:postcode":"54114",
    "sg:province":"WI",
    "sg:tags":[
        "landscaping",
        "equipment"
    ],
    "sg:website":"www.beavercreekoutfitter.com",
    "wof:name":"Beaver Creek Mulch & Firewood",
    "wof:placetype":"venue"
},
  "geometry": {"coordinates":[-88.002126,45.137174],"type":"Point"}
}