{
  "type": "Feature",
  "properties": {
    "addr:full":"118 N Stafford St Plymouth WI 53073",
    "addr:housenumber":"118",
    "addr:postcode":"53073",
    "addr:street":"N Stafford St",
    "iso:country":"US",
    "sg:address":"118 N Stafford St",
    "sg:city":"Plymouth",
    "sg:classifiers":[
        {
            "category":"Insurance",
            "subcategory":"Insurance Agent",
            "type":"Services"
        }
    ],
    "sg:phone":"+1 920 893 6677",
    "sg:postcode":"53073",
    "sg:province":"WI",
    "wof:name":"Founders Insurance",
    "wof:placetype":"venue"
},
  "geometry": {"coordinates":[-87.977388,43.747745],"type":"Point"}
}