{
  "type": "Feature",
  "properties": {
    "iso:country":"US",
    "sg:address":"116 Bridge St",
    "sg:city":"Mayville",
    "sg:classifiers":[
        {
            "category":"Food & Beverages",
            "subcategory":"Bakery",
            "type":"Retail Goods"
        }
    ],
    "sg:phone":"+1 920 387 2612",
    "sg:postcode":"53050",
    "sg:province":"WI",
    "wof:name":"Nadim and Jasmine",
    "wof:placetype":"venue"
},
  "geometry": {"coordinates":[-88.545303,43.495808],"type":"Point"}
}