{
  "type": "Feature",
  "properties": {
    "iso:country":"US",
    "sg:address":"231 W Wisconsin Ave",
    "sg:city":"Milwaukee",
    "sg:classifiers":[
        {
            "category":"Real Estate",
            "subcategory":"Real Estate Operator",
            "type":"Services"
        }
    ],
    "sg:phone":"+1 414 289 9519",
    "sg:postcode":"53233",
    "sg:province":"WI",
    "sg:tags":[
        "building",
        "apartment"
    ],
    "wof:name":"Majestic Loft Apartments",
    "wof:placetype":"venue"
},
  "geometry": {"coordinates":[-87.914133,43.038673],"type":"Point"}
}