{
  "type": "Feature",
  "properties": {
    "iso:country":"US",
    "sg:address":"205 Oak St",
    "sg:city":"Stoddard",
    "sg:classifiers":[
        {
            "category":"Insurance",
            "subcategory":"Insurance Agent",
            "type":"Services"
        }
    ],
    "sg:phone":"+1 608 457 2400",
    "sg:postcode":"54658",
    "sg:province":"WI",
    "wof:name":"Stoddard Insurance",
    "wof:placetype":"venue"
},
  "geometry": {"coordinates":[-91.21667600000001,43.664522],"type":"Point"}
}