{
  "type": "Feature",
  "properties": {
    "addr:full":"1290 Lombardi Ave Green Bay WI 54304",
    "addr:housenumber":"1290",
    "addr:postcode":"54304",
    "addr:street":"Lombardi Ave",
    "iso:country":"US",
    "sg:address":"1290 Lombardi Ave",
    "sg:city":"Green Bay",
    "sg:classifiers":[
        {
            "category":"Social Services",
            "type":"Services"
        }
    ],
    "sg:phone":"+1 920 497 2207",
    "sg:postcode":"54304",
    "sg:province":"WI",
    "sg:tags":[
        "counselor",
        "marriage",
        "family"
    ],
    "wof:name":"Children's Service Society-Wi",
    "wof:placetype":"venue"
},
  "geometry": {"coordinates":[-88.058869,44.501791],"type":"Point"}
}