{
  "type": "Feature",
  "properties": {
    "iso:country":"US",
    "sg:address":"2424 S Stoughton Rd",
    "sg:city":"Madison",
    "sg:classifiers":[
        {
            "category":"Autos & Motor Vehicles",
            "subcategory":"Automobile Sales",
            "type":"Retail Goods"
        }
    ],
    "sg:phone":"+1 608 221 0000",
    "sg:postcode":"53716",
    "sg:province":"WI",
    "sg:tags":[
        "car",
        "used",
        "dealer"
    ],
    "wof:name":"Schoepp Motors Inc",
    "wof:placetype":"venue"
},
  "geometry": {"coordinates":[-89.309337,43.055865],"type":"Point"}
}