{
  "type": "Feature",
  "properties": {
    "iso:country":"US",
    "sg:address":"70 White Oaks Ln",
    "sg:city":"Madison",
    "sg:classifiers":[
        {
            "category":"Professional",
            "subcategory":"Management & Consulting",
            "type":"Services"
        }
    ],
    "sg:phone":"+1 608 274 0766",
    "sg:postcode":"53711",
    "sg:province":"WI",
    "sg:tags":[
        "retail",
        "direct",
        "sales"
    ],
    "wof:name":"Burman Consulting",
    "wof:placetype":"venue"
},
  "geometry": {"coordinates":[-89.485131,43.04438],"type":"Point"}
}