{
  "type": "Feature",
  "properties": {
    "iso:country":"US",
    "sg:address":"7880 Chapel Hill Ct E",
    "sg:city":"Franklin",
    "sg:classifiers":[
        {
            "category":"Freight",
            "type":"Transportation"
        }
    ],
    "sg:phone":"+1 414 305 1214",
    "sg:postcode":"53132",
    "sg:province":"WI",
    "sg:tags":[
        "trucking"
    ],
    "wof:name":"Schultz Transfer Systems Inc",
    "wof:placetype":"venue"
},
  "geometry": {"coordinates":[-88.044839,42.902097],"type":"Point"}
}