{
  "type": "Feature",
  "properties": {
    "addr:full":"1060 Tanney Ln Hudson WI 54016",
    "addr:housenumber":"1060",
    "addr:postcode":"54016",
    "addr:street":"Tanney Ln",
    "iso:country":"US",
    "sg:address":"1060 Tanney Ln",
    "sg:city":"Hudson",
    "sg:classifiers":[
        {
            "category":"Manufacturing",
            "subcategory":"Metals",
            "type":"Manufacturing & Wholesale Goods"
        }
    ],
    "sg:phone":"+1 715 386 8044",
    "sg:postcode":"54016",
    "sg:province":"WI",
    "sg:tags":[
        "plumbing",
        "fitting",
        "fixture",
        "mfg"
    ],
    "wof:name":"Great Outdoors Midwest Inc",
    "wof:placetype":"venue"
},
  "geometry": {"coordinates":[-92.643439,45.016157],"type":"Point"}
}