{
  "type": "Feature",
  "properties": {
    "iso:country":"US",
    "sg:address":"479 Sycamore St",
    "sg:city":"Onalaska",
    "sg:classifiers":[
        {
            "category":"Professional",
            "subcategory":"Engineering",
            "type":"Services"
        }
    ],
    "sg:phone":"+1 608 783 7245",
    "sg:postcode":"54650",
    "sg:province":"WI",
    "wof:name":"Midwest Structural Consulting",
    "wof:placetype":"venue"
},
  "geometry": {"coordinates":[-91.204138,43.87193],"type":"Point"}
}