{
  "type": "Feature",
  "properties": {
    "iso:country":"US",
    "sg:address":"1102 Waban Hill",
    "sg:city":"Madison",
    "sg:classifiers":[
        {
            "category":"Professional",
            "subcategory":"Management & Consulting",
            "type":"Services"
        }
    ],
    "sg:phone":"+1 608 274 0006",
    "sg:postcode":"53711",
    "sg:province":"WI",
    "sg:tags":[
        "business"
    ],
    "wof:name":"David E Foster",
    "wof:placetype":"venue"
},
  "geometry": {"coordinates":[-89.445335,43.039149],"type":"Point"}
}