{
  "type": "Feature",
  "properties": {
    "addr:full":"8127 203rd Ave Bristol WI 53104",
    "addr:housenumber":"8127",
    "addr:postcode":"53104",
    "addr:street":"203Rd Ave",
    "iso:country":"US",
    "sg:address":"8127 203rd Ave",
    "sg:city":"Bristol",
    "sg:classifiers":[
        {
            "category":"Manufacturing",
            "subcategory":"Printing",
            "type":"Manufacturing & Wholesale Goods"
        }
    ],
    "sg:phone":"+1 262 857 7436",
    "sg:postcode":"53104",
    "sg:province":"WI",
    "sg:tags":[
        "book"
    ],
    "wof:name":"Travis Enterprises",
    "wof:placetype":"venue"
},
  "geometry": {"coordinates":[-88.055117,42.559752],"type":"Point"}
}