{
  "type": "Feature",
  "properties": {
    "addr:full":"1709 17th Ave South Milwaukee WI 53172",
    "addr:housenumber":"1709",
    "addr:postcode":"53172",
    "addr:street":"17Th Ave",
    "iso:country":"US",
    "sg:address":"1709 17th Ave",
    "sg:city":"South Milwaukee",
    "sg:classifiers":[
        {
            "category":"Professional",
            "type":"Services"
        }
    ],
    "sg:phone":"+1 414 762 5726",
    "sg:postcode":"53172",
    "sg:province":"WI",
    "wof:name":"Walleye Warrior Guide Service",
    "wof:placetype":"venue"
},
  "geometry": {"coordinates":[-87.876024,42.913671],"type":"Point"}
}