{
  "type": "Feature",
  "properties": {
    "iso:country":"US",
    "sg:address":"4238 N 76th St",
    "sg:city":"Milwaukee",
    "sg:classifiers":[
        {
            "category":"Building & Trades",
            "subcategory":"Construction",
            "type":"Services"
        }
    ],
    "sg:phone":"+1 414 536 8655",
    "sg:postcode":"53222",
    "sg:province":"WI",
    "sg:tags":[
        "roofing",
        "contractor"
    ],
    "wof:name":"Homecare Exteriors Inc",
    "wof:placetype":"venue"
},
  "geometry": {"coordinates":[-88.00706599999999,43.094751],"type":"Point"}
}