{
  "type": "Feature",
  "properties": {
    "addr:full":"41 Sherman Ave W Fort Atkinson WI 53538",
    "addr:housenumber":"41",
    "addr:postcode":"53538",
    "addr:street":"Sherman Ave W",
    "iso:country":"US",
    "sg:address":"41 Sherman Ave W",
    "sg:city":"Fort Atkinson",
    "sg:classifiers":[
        {
            "category":"Restaurant",
            "type":"Food & Drink"
        }
    ],
    "sg:phone":"+1 920 568 1582",
    "sg:postcode":"53538",
    "sg:province":"WI",
    "sg:tags":[
        "eating"
    ],
    "wof:name":"Ken & Betty's Steaks & Hoagies",
    "wof:placetype":"venue"
},
  "geometry": {"coordinates":[-88.838043,42.929807],"type":"Point"}
}