{
  "type": "Feature",
  "properties": {
    "iso:country":"US",
    "sg:address":"207 Water St",
    "sg:city":"Sauk City",
    "sg:classifiers":[
        {
            "category":"Professional",
            "type":"Services"
        }
    ],
    "sg:phone":"+1 608 643 6763",
    "sg:postcode":"53583",
    "sg:province":"WI",
    "sg:tags":[
        "establishment"
    ],
    "wof:name":"Enchanting Designs",
    "wof:placetype":"venue"
},
  "geometry": {"coordinates":[-89.727841,43.296183],"type":"Point"}
}