{
  "type": "Feature",
  "properties": {
    "iso:country":"US",
    "sg:address":"1721 Main St",
    "sg:city":"Cross Plains",
    "sg:classifiers":[
        {
            "category":"Sports & Exercise",
            "subcategory":"Bowling",
            "type":"Entertainment"
        }
    ],
    "sg:phone":"+1 608 798 4900",
    "sg:postcode":"53528",
    "sg:province":"WI",
    "sg:tags":[
        "center"
    ],
    "wof:name":"Main Street Lanes",
    "wof:placetype":"venue"
},
  "geometry": {"coordinates":[-89.65166,43.11396],"type":"Point"}
}