{
  "type": "Feature",
  "properties": {
    "addr:full":"2017 Green Meadow Dr Delavan WI 53115",
    "addr:housenumber":"2017",
    "addr:postcode":"53115",
    "addr:street":"Green Meadow Dr",
    "iso:country":"US",
    "sg:address":"2017 Green Meadow Dr",
    "sg:city":"Delavan",
    "sg:classifiers":[
        {
            "category":"Banks & Credit Unions",
            "subcategory":"Bank",
            "type":"Services"
        }
    ],
    "sg:phone":"+1 262 740 0161",
    "sg:postcode":"53115",
    "sg:province":"WI",
    "sg:tags":[
        "loan",
        "real estate"
    ],
    "wof:name":"Flagstar Bank Home Loan Ctr",
    "wof:placetype":"venue"
},
  "geometry": {"coordinates":[-88.622728,42.610718],"type":"Point"}
}