{
  "type": "Feature",
  "properties": {
    "iso:country":"US",
    "sg:address":"13400 Bishops Ln",
    "sg:city":"Brookfield",
    "sg:classifiers":[
        {
            "category":"Real Estate",
            "subcategory":"Real Estate Agent",
            "type":"Services"
        }
    ],
    "sg:phone":"+1 262 797 9400",
    "sg:postcode":"53005",
    "sg:province":"WI",
    "sg:tags":[
        "brokerage"
    ],
    "wof:name":"M L G Commerical LLC",
    "wof:placetype":"venue"
},
  "geometry": {"coordinates":[-88.07915199999999,43.034455],"type":"Point"}
}