{
  "type": "Feature",
  "properties": {
    "iso:country":"US",
    "sg:address":"509 Main St",
    "sg:city":"Wilton",
    "sg:classifiers":[
        {
            "category":"Retail",
            "subcategory":"Repair Shop",
            "type":"Services"
        }
    ],
    "sg:phone":"+1 608 435 6806",
    "sg:postcode":"54670",
    "sg:province":"WI",
    "sg:tags":[
        "clocks",
        "parts"
    ],
    "wof:name":"Country Clocksmith",
    "wof:placetype":"venue"
},
  "geometry": {"coordinates":[-90.52829199999999,43.814913],"type":"Point"}
}