{
  "type": "Feature",
  "properties": {
    "iso:country":"US",
    "sg:address":"7611 Hickory Dr",
    "sg:city":"Fredonia",
    "sg:classifiers":[
        {
            "category":"Professional",
            "subcategory":"Computer Services",
            "type":"Services"
        }
    ],
    "sg:phone":"+1 262 692 6679",
    "sg:postcode":"53021",
    "sg:province":"WI",
    "sg:tags":[
        "datum"
    ],
    "wof:name":"Digital Art Factory",
    "wof:placetype":"venue"
},
  "geometry": {"coordinates":[-88.040804,43.463152],"type":"Point"}
}