{
  "type": "Feature",
  "properties": {
    "iso:country":"US",
    "sg:address":"3869 Jefferson St",
    "sg:city":"Sullivan",
    "sg:classifiers":[
        {
            "category":"Building & Trades",
            "subcategory":"Construction",
            "type":"Services"
        }
    ],
    "sg:phone":"+1 262 593 2135",
    "sg:postcode":"53178",
    "sg:province":"WI",
    "sg:tags":[
        "contractor"
    ],
    "wof:name":"Geiger Enterprises",
    "wof:placetype":"venue"
},
  "geometry": {"coordinates":[-88.63114,42.98072],"type":"Point"}
}