{
  "type": "Feature",
  "properties": {
    "iso:country":"US",
    "sg:address":"310 E Applecreek Rd",
    "sg:city":"Appleton",
    "sg:classifiers":[
        {
            "category":"Building & Trades",
            "subcategory":"Construction",
            "type":"Services"
        }
    ],
    "sg:phone":"+1 920 739 8055",
    "sg:postcode":"54913",
    "sg:province":"WI",
    "sg:tags":[
        "specializing",
        "family",
        "builder",
        "general",
        "home",
        "contractor"
    ],
    "wof:name":"Jeff Heiting Builders",
    "wof:placetype":"venue"
},
  "geometry": {"coordinates":[-88.396124,44.311296],"type":"Point"}
}