{
  "type": "Feature",
  "properties": {
    "addr:full":"12525 N Island Dr Thiensville WI 53092",
    "addr:housenumber":"12525",
    "addr:postcode":"53092",
    "addr:street":"N Island Dr",
    "iso:country":"US",
    "sg:address":"12525 N Island Dr",
    "sg:city":"Thiensville",
    "sg:classifiers":[
        {
            "category":"Building & Trades",
            "subcategory":"Landscaping Services",
            "type":"Services"
        }
    ],
    "sg:phone":"+1 262 243 5749",
    "sg:postcode":"53092",
    "sg:province":"WI",
    "wof:name":"Clean Cut Lawn Care",
    "wof:placetype":"venue"
},
  "geometry": {"coordinates":[-87.934837,43.245923],"type":"Point"}
}