{
  "type": "Feature",
  "properties": {
    "iso:country":"US",
    "sg:address":"2062 Covered Bridge Rd",
    "sg:city":"Cedarburg",
    "sg:classifiers":[
        {
            "category":"Professional",
            "subcategory":"Engineering",
            "type":"Services"
        }
    ],
    "sg:phone":"+1 920 897 2462",
    "sg:postcode":"53012",
    "sg:province":"WI",
    "sg:tags":[
        "engineer"
    ],
    "wof:name":"Cebe & Associates Inc",
    "wof:placetype":"venue"
},
  "geometry": {"coordinates":[-88.003849,43.345687],"type":"Point"}
}