{
  "type": "Feature",
  "properties": {
    "iso:country":"US",
    "sg:address":"10155 W Cleveland Ave",
    "sg:city":"Milwaukee",
    "sg:classifiers":[
        {
            "category":"Building & Trades",
            "subcategory":"Landscaping Services",
            "type":"Services"
        }
    ],
    "sg:phone":"+1 414 327 6456",
    "sg:postcode":"53227",
    "sg:province":"WI",
    "wof:name":"Excel Landscape Management",
    "wof:placetype":"venue"
},
  "geometry": {"coordinates":[-88.041315,42.995268],"type":"Point"}
}