{
  "type": "Feature",
  "properties": {
    "iso:country":"US",
    "sg:address":"202 N 4th Ave",
    "sg:city":"St Nazianz",
    "sg:classifiers":[
        {
            "category":"Government",
            "subcategory":"Fire Station",
            "type":"Public Place"
        }
    ],
    "sg:phone":"+1 920 773 2311",
    "sg:postcode":"54232",
    "sg:province":"WI",
    "sg:tags":[
        "department"
    ],
    "wof:name":"St Nazianz Fire Station",
    "wof:placetype":"venue"
},
  "geometry": {"coordinates":[-87.92237299999999,44.009808],"type":"Point"}
}