{
  "type": "Feature",
  "properties": {
    "iso:country":"US",
    "sg:address":"506 Gehres Ct",
    "sg:city":"Oshkosh",
    "sg:classifiers":[
        {
            "category":"Shopping",
            "subcategory":"Gifts & Souvenirs",
            "type":"Retail Goods"
        }
    ],
    "sg:phone":"+1 920 231 8010",
    "sg:postcode":"54901",
    "sg:province":"WI",
    "wof:name":"Blue Barn Gifts LLC",
    "wof:placetype":"venue"
},
  "geometry": {"coordinates":[-88.530255,44.031594],"type":"Point"}
}