{
  "type": "Feature",
  "properties": {
    "addr:full":"2800 Pioneer Ave Rice Lake WI 54868",
    "addr:housenumber":"2800",
    "addr:postcode":"54868",
    "addr:street":"Pioneer Ave",
    "iso:country":"US",
    "sg:address":"2800 Pioneer Ave",
    "sg:city":"Rice Lake",
    "sg:classifiers":[
        {
            "category":"Restaurant",
            "type":"Food & Drink"
        }
    ],
    "sg:phone":"+1 715 234 5020",
    "sg:postcode":"54868",
    "sg:province":"WI",
    "sg:website":"www.mcwisconsin.com",
    "wof:name":"Mc Donald's",
    "wof:placetype":"venue"
},
  "geometry": {"coordinates":[-91.741283,45.468165],"type":"Point"}
}