{
  "type": "Feature",
  "properties": {
    "iso:country":"US",
    "sg:address":"1033 Schallock Rd",
    "sg:city":"Crandon",
    "sg:classifiers":[
        {
            "category":"Manufacturing",
            "subcategory":"Lumber",
            "type":"Manufacturing & Wholesale Goods"
        }
    ],
    "sg:phone":"+1 715 478 2154",
    "sg:postcode":"54520",
    "sg:province":"WI",
    "sg:tags":[
        "company",
        "logging"
    ],
    "wof:name":"Jack D Fraley",
    "wof:placetype":"venue"
},
  "geometry": {"coordinates":[-88.917706,45.55191],"type":"Point"}
}