{
  "type": "Feature",
  "properties": {
    "addr:full":"612 E Center St Milwaukee WI 53212",
    "addr:housenumber":"612",
    "addr:postcode":"53212",
    "addr:street":"E Center St",
    "iso:country":"US",
    "sg:address":"612 E Center St",
    "sg:city":"Milwaukee",
    "sg:classifiers":[
        {
            "category":"Professional",
            "subcategory":"Business Services",
            "type":"Services"
        }
    ],
    "sg:phone":"+1 414 374 7408",
    "sg:postcode":"53212",
    "sg:province":"WI",
    "wof:name":"Lucky Writing Service",
    "wof:placetype":"venue"
},
  "geometry": {"coordinates":[-87.902897,43.067554],"type":"Point"}
}