{
  "type": "Feature",
  "properties": {
    "iso:country":"US",
    "sg:address":"13202 Cutoff Rd",
    "sg:city":"Melrose",
    "sg:classifiers":[
        {
            "category":"Farming",
            "subcategory":"Dairy Farm",
            "type":"Manufacturing & Wholesale Goods"
        }
    ],
    "sg:phone":"+1 608 488 2056",
    "sg:postcode":"54642",
    "sg:province":"WI",
    "wof:name":"Tony A Gilbertson",
    "wof:placetype":"venue"
},
  "geometry": {"coordinates":[-90.974706,44.157819],"type":"Point"}
}