{
  "type": "Feature",
  "properties": {
    "iso:country":"US",
    "sg:address":"2338 Huntington Dr",
    "sg:city":"Star Prairie",
    "sg:classifiers":[
        {
            "category":"Real Estate",
            "subcategory":"Real Estate Agent",
            "type":"Services"
        }
    ],
    "sg:phone":"+1 715 248 3999",
    "sg:postcode":"54026",
    "sg:province":"WI",
    "wof:name":"Marylizs",
    "wof:placetype":"venue"
},
  "geometry": {"coordinates":[-92.554998,45.196882],"type":"Point"}
}