{
  "type": "Feature",
  "properties": {
    "addr:full":"227 E Silver Spring Dr Milwaukee WI 53217",
    "addr:housenumber":"227",
    "addr:postcode":"53217",
    "addr:street":"E Silver Spring Dr",
    "iso:country":"US",
    "sg:address":"227 E Silver Spring Dr",
    "sg:city":"Milwaukee",
    "sg:classifiers":[
        {
            "category":"Health Services",
            "subcategory":"Doctor",
            "type":"Services"
        }
    ],
    "sg:phone":"+1 414 964 8424",
    "sg:postcode":"53217",
    "sg:province":"WI",
    "sg:tags":[
        "physician",
        "surgeon",
        "medical"
    ],
    "wof:name":"Suson Eye Specialists  MD SC",
    "wof:placetype":"venue"
},
  "geometry": {"coordinates":[-87.907061,43.118453],"type":"Point"}
}