{
  "type": "Feature",
  "properties": {
    "iso:country":"US",
    "sg:address":"2102 Ogden Ave",
    "sg:city":"Superior",
    "sg:classifiers":[
        {
            "category":"Professional",
            "subcategory":"Detective & Security Services",
            "type":"Services"
        }
    ],
    "sg:phone":"+1 715 392 3510",
    "sg:postcode":"54880",
    "sg:province":"WI",
    "sg:tags":[
        "system"
    ],
    "wof:name":"Superior Security Center",
    "wof:placetype":"venue"
},
  "geometry": {"coordinates":[-92.102379,46.712158],"type":"Point"}
}