{
  "type": "Feature",
  "properties": {
    "iso:country":"US",
    "sg:address":"2200 Wisconsin Ave",
    "sg:city":"Plover",
    "sg:classifiers":[
        {
            "category":"Education",
            "subcategory":"School",
            "type":"Public Place"
        }
    ],
    "sg:phone":"+1 715 345 5425",
    "sg:postcode":"54467",
    "sg:province":"WI",
    "wof:name":"Roosevelt Elementary School",
    "wof:placetype":"venue"
},
  "geometry": {"coordinates":[-89.541798,44.464577],"type":"Point"}
}