{
  "type": "Feature",
  "properties": {
    "iso:country":"US",
    "sg:address":"5308 US Hwy 151",
    "sg:city":"Columbus",
    "sg:classifiers":[
        {
            "category":"Real Estate",
            "subcategory":"Real Estate Operator",
            "type":"Services"
        }
    ],
    "sg:phone":"+1 920 623 5017",
    "sg:postcode":"53925",
    "sg:province":"WI",
    "sg:tags":[
        "property",
        "lessor"
    ],
    "wof:name":"Diane Tiedt",
    "wof:placetype":"venue"
},
  "geometry": {"coordinates":[-88.943564,43.388547],"type":"Point"}
}