{
  "type": "Feature",
  "properties": {
    "iso:country":"US",
    "sg:address":"2003 W Bender Rd",
    "sg:city":"Milwaukee",
    "sg:classifiers":[
        {
            "category":"Wholesale",
            "subcategory":"Metals & Minerals",
            "type":"Manufacturing & Wholesale Goods"
        }
    ],
    "sg:phone":"+1 414 540 1235",
    "sg:postcode":"53209",
    "sg:province":"WI",
    "sg:tags":[
        "center"
    ],
    "wof:name":"Wisconsin Steel Services LLC",
    "wof:placetype":"venue"
},
  "geometry": {"coordinates":[-87.937397,43.1306],"type":"Point"}
}