{
  "type": "Feature",
  "properties": {
    "iso:country":"US",
    "sg:address":"11514 N Port Washington Rd",
    "sg:city":"Mequon",
    "sg:classifiers":[
        {
            "category":"Professional",
            "subcategory":"Advertising",
            "type":"Services"
        }
    ],
    "sg:phone":"+1 262 241 9996",
    "sg:postcode":"53092",
    "sg:province":"WI",
    "sg:tags":[
        "medium",
        "buying"
    ],
    "sg:website":"www.outdoorfirst.com",
    "wof:name":"Outdoor First",
    "wof:placetype":"venue"
},
  "geometry": {"coordinates":[-87.923987,43.228008],"type":"Point"}
}