{
  "type": "Feature",
  "properties": {
    "addr:full":"8940 N 85th St Milwaukee WI 53224",
    "addr:housenumber":"8940",
    "addr:postcode":"53224",
    "addr:street":"N 85Th St",
    "iso:country":"US",
    "sg:address":"8940 N 85th St",
    "sg:city":"Milwaukee",
    "sg:classifiers":[
        {
            "category":"Education",
            "subcategory":"Special Training",
            "type":"Public Place"
        }
    ],
    "sg:phone":"+1 414 355 1449",
    "sg:postcode":"53224",
    "sg:province":"WI",
    "sg:tags":[
        "educational",
        "fitness"
    ],
    "wof:name":"Fassi Inc",
    "wof:placetype":"venue"
},
  "geometry": {"coordinates":[-88.015545,43.182446],"type":"Point"}
}