{
  "type": "Feature",
  "properties": {
    "addr:full":"1507 S Oakwood Rd Oshkosh WI 54904",
    "addr:housenumber":"1507",
    "addr:postcode":"54904",
    "addr:street":"S Oakwood Rd",
    "iso:country":"US",
    "sg:address":"1507 S Oakwood Rd",
    "sg:city":"Oshkosh",
    "sg:classifiers":[
        {
            "category":"Real Estate",
            "subcategory":"Real Estate Agent",
            "type":"Services"
        }
    ],
    "sg:phone":"+1 920 235 3319",
    "sg:postcode":"54904",
    "sg:province":"WI",
    "wof:name":"Barbco LLC",
    "wof:placetype":"venue"
},
  "geometry": {"coordinates":[-88.6032,44.002688],"type":"Point"}
}