{
  "type": "Feature",
  "properties": {
    "iso:country":"US",
    "sg:address":"5900 Christine Ct",
    "sg:city":"Burlington",
    "sg:classifiers":[
        {
            "category":"Real Estate",
            "subcategory":"Real Estate Operator",
            "type":"Services"
        }
    ],
    "sg:phone":"+1 262 763 7863",
    "sg:postcode":"53105",
    "sg:province":"WI",
    "sg:tags":[
        "building",
        "apartment"
    ],
    "wof:name":"Finke Properties LLC",
    "wof:placetype":"venue"
},
  "geometry": {"coordinates":[-88.35074299999999,42.646004],"type":"Point"}
}