{
  "type": "Feature",
  "properties": {
    "addr:full":"800 Wisconsin St Eau Claire WI 54703",
    "addr:housenumber":"800",
    "addr:postcode":"54703",
    "addr:street":"Wisconsin St",
    "iso:country":"US",
    "sg:address":"800 Wisconsin St",
    "sg:city":"Eau Claire",
    "sg:classifiers":[
        {
            "category":"Communications",
            "subcategory":"Television Station",
            "type":"Services"
        }
    ],
    "sg:phone":"+1 715 839 5067",
    "sg:postcode":"54703",
    "sg:province":"WI",
    "sg:tags":[
        "broadcasting",
        "co"
    ],
    "sg:website":"www.cvctv.org",
    "wof:name":"Public Access Ctr",
    "wof:placetype":"venue"
},
  "geometry": {"coordinates":[-91.49755399999999,44.815965],"type":"Point"}
}