{
  "type": "Feature",
  "properties": {
    "iso:country":"US",
    "sg:address":"2168 US Hwy 12",
    "sg:city":"Baldwin",
    "sg:classifiers":[
        {
            "category":"Freight",
            "type":"Transportation"
        }
    ],
    "sg:phone":"+1 715 684 2597",
    "sg:postcode":"54002",
    "sg:province":"WI",
    "sg:tags":[
        "operator",
        "cartage",
        "local",
        "trucking"
    ],
    "wof:name":"Shefland Trucking Service",
    "wof:placetype":"venue"
},
  "geometry": {"coordinates":[-92.362788,44.967198],"type":"Point"}
}