{
  "type": "Feature",
  "properties": {
    "iso:country":"US",
    "sg:address":"1302 Marina Dr",
    "sg:city":"Grafton",
    "sg:classifiers":[
        {
            "category":"Professional",
            "subcategory":"Business Services",
            "type":"Services"
        }
    ],
    "sg:phone":"+1 262 376 8788",
    "sg:postcode":"53024",
    "sg:province":"WI",
    "wof:name":"Bst Technologies Inc",
    "wof:placetype":"venue"
},
  "geometry": {"coordinates":[-87.892771,43.323395],"type":"Point"}
}