{
  "type": "Feature",
  "properties": {
    "iso:country":"US",
    "sg:address":"3847 State Hwy 33",
    "sg:city":"Cambria",
    "sg:phone":"+1 920 348 5543",
    "sg:postcode":"53923",
    "sg:province":"WI",
    "sg:tags":[
        "farm",
        "corn",
        "soybean"
    ],
    "wof:name":"Sommers Farm",
    "wof:placetype":"venue"
},
  "geometry": {"coordinates":[-89.19747,43.570513],"type":"Point"}
}