{
  "type": "Feature",
  "properties": {
    "iso:country":"US",
    "sg:address":"1166 Co Rd Cw",
    "sg:city":"Watertown",
    "sg:classifiers":[
        {
            "category":"Farming",
            "subcategory":"Livestock Farm",
            "type":"Manufacturing & Wholesale Goods"
        }
    ],
    "sg:phone":"+1 920 261 2984",
    "sg:postcode":"53094",
    "sg:province":"WI",
    "sg:tags":[
        "corn",
        "beef",
        "feedlot",
        "cattle"
    ],
    "wof:name":"Rohrer John",
    "wof:placetype":"venue"
},
  "geometry": {"coordinates":[-88.588511,43.191557],"type":"Point"}
}