{
  "type": "Feature",
  "properties": {
    "addr:full":"8790 State Rd 82 Oxford WI 53952",
    "addr:housenumber":"8790;82",
    "addr:postcode":"53952",
    "addr:street":"State Rd",
    "iso:country":"US",
    "sg:address":"8790 State Rd 82",
    "sg:city":"Oxford",
    "sg:classifiers":[
        {
            "category":"Restaurant",
            "type":"Food & Drink"
        }
    ],
    "sg:phone":"+1 608 586 6550",
    "sg:postcode":"53952",
    "sg:province":"WI",
    "wof:name":"Tuffy's Corner",
    "wof:placetype":"venue"
},
  "geometry": {"coordinates":[-89.597008,43.78129],"type":"Point"}
}