{
  "type": "Feature",
  "properties": {
    "iso:country":"US",
    "sg:address":"1800 S Lawe St",
    "sg:city":"Appleton",
    "sg:classifiers":[
        {
            "category":"Shopping",
            "subcategory":"Computers & Home Electronics",
            "type":"Retail Goods"
        }
    ],
    "sg:phone":"+1 920 725 4566",
    "sg:postcode":"54915",
    "sg:province":"WI",
    "wof:name":"Fox Laser Toner Company",
    "wof:placetype":"venue"
},
  "geometry": {"coordinates":[-88.396118,44.24493],"type":"Point"}
}