{
  "type": "Feature",
  "properties": {
    "iso:country":"US",
    "sg:address":"1060 43rd St",
    "sg:city":"Caledonia",
    "sg:classifiers":[
        {
            "category":"Banks & Credit Unions",
            "subcategory":"Financial Services",
            "type":"Services"
        }
    ],
    "sg:phone":"+1 262 835 1128",
    "sg:postcode":"53108",
    "sg:province":"WI",
    "sg:tags":[
        "investor"
    ],
    "wof:name":"Marjan Investments LLC",
    "wof:placetype":"venue"
},
  "geometry": {"coordinates":[-87.972106,42.827403],"type":"Point"}
}