{
  "type": "Feature",
  "properties": {
    "addr:full":"7989 Wake Forest Dr Oak Creek WI 53154",
    "addr:housenumber":"7989",
    "addr:postcode":"53154",
    "addr:street":"Wake Forest Dr",
    "iso:country":"US",
    "sg:address":"7989 Wake Forest Dr",
    "sg:city":"Oak Creek",
    "sg:classifiers":[
        {
            "category":"Banks & Credit Unions",
            "subcategory":"Financial Services",
            "type":"Services"
        }
    ],
    "sg:phone":"+1 414 570 6017",
    "sg:postcode":"53154",
    "sg:province":"WI",
    "sg:tags":[
        "investor"
    ],
    "wof:name":"Limitless Investments LLC",
    "wof:placetype":"venue"
},
  "geometry": {"coordinates":[-87.92797299999999,42.898501],"type":"Point"}
}