{
  "type": "Feature",
  "properties": {
    "addr:full":"1301 State Hwy 69 Belleville WI 53508",
    "addr:housenumber":"1301",
    "addr:postcode":"53508",
    "addr:street":"State Hwy 69",
    "iso:country":"US",
    "sg:address":"1301 State Hwy 69",
    "sg:city":"Belleville",
    "sg:classifiers":[
        {
            "category":"Farming",
            "subcategory":"Dairy Farm",
            "type":"Manufacturing & Wholesale Goods"
        }
    ],
    "sg:phone":"+1 608 424 3068",
    "sg:postcode":"53508",
    "sg:province":"WI",
    "sg:tags":[
        "beef",
        "far",
        "corn",
        "crop",
        "field",
        "cattle",
        "feedlot"
    ],
    "wof:name":"Fisherdale Holsteins",
    "wof:placetype":"venue"
},
  "geometry": {"coordinates":[-89.51909499999999,42.921813],"type":"Point"}
}