{
  "type": "Feature",
  "properties": {
    "iso:country":"US",
    "sg:address":"2030 Gaynor Ave",
    "sg:city":"Wisconsin Rapids",
    "sg:classifiers":[
        {
            "category":"Shopping",
            "subcategory":"Used Merchandise",
            "type":"Retail Goods"
        }
    ],
    "sg:phone":"+1 715 423 0956",
    "sg:postcode":"54495",
    "sg:province":"WI",
    "wof:name":"Warehouse Furniture Outlet",
    "wof:placetype":"venue"
},
  "geometry": {"coordinates":[-89.85033300000001,44.380352],"type":"Point"}
}