{
  "type": "Feature",
  "properties": {
    "iso:country":"US",
    "sg:address":"924 Ohio St",
    "sg:city":"Oshkosh",
    "sg:classifiers":[
        {
            "category":"Building & Trades",
            "subcategory":"Plumbing",
            "type":"Services"
        }
    ],
    "sg:phone":"+1 920 236 8770",
    "sg:postcode":"54902",
    "sg:province":"WI",
    "sg:tags":[
        "air",
        "heating",
        "conditioning",
        "contractor"
    ],
    "wof:name":"Tenth Street Station Inc",
    "wof:placetype":"venue"
},
  "geometry": {"coordinates":[-88.552364,44.009636],"type":"Point"}
}