{
  "type": "Feature",
  "properties": {
    "iso:country":"US",
    "sg:address":"2561 Havey Ln",
    "sg:city":"Stoughton",
    "sg:classifiers":[
        {
            "category":"Manufacturing",
            "subcategory":"Printing",
            "type":"Manufacturing & Wholesale Goods"
        }
    ],
    "sg:phone":"+1 608 205 9262",
    "sg:postcode":"53589",
    "sg:province":"WI",
    "sg:tags":[
        "lithographic",
        "commercial"
    ],
    "wof:name":"Print Tech Inc",
    "wof:placetype":"venue"
},
  "geometry": {"coordinates":[-89.204157,42.958545],"type":"Point"}
}