{
  "type": "Feature",
  "properties": {
    "iso:country":"US",
    "sg:address":"1507 Jefferson St",
    "sg:city":"Oshkosh",
    "sg:classifiers":[
        {
            "category":"Building & Trades",
            "subcategory":"Construction",
            "type":"Services"
        }
    ],
    "sg:phone":"+1 920 303 6853",
    "sg:postcode":"54901",
    "sg:province":"WI",
    "sg:tags":[
        "house"
    ],
    "wof:name":"Excalibur Construction",
    "wof:placetype":"venue"
},
  "geometry": {"coordinates":[-88.536458,44.038112],"type":"Point"}
}