{
  "type": "Feature",
  "properties": {
    "iso:country":"US",
    "sg:address":"350 E Washington St",
    "sg:city":"Slinger",
    "sg:classifiers":[
        {
            "category":"Government",
            "subcategory":"Post Office",
            "type":"Public Place"
        }
    ],
    "sg:phone":"+1 262 644 0217",
    "sg:postcode":"53086",
    "sg:province":"WI",
    "sg:tags":[
        "postal",
        "us"
    ],
    "wof:name":"US Post Office",
    "wof:placetype":"venue"
},
  "geometry": {"coordinates":[-88.28097699999999,43.331652],"type":"Point"}
}