{
  "type": "Feature",
  "properties": {
    "addr:full":"720 Lake Shore Dr W Ashland WI 54806",
    "addr:housenumber":"720",
    "addr:postcode":"54806",
    "addr:street":"Lake Shore Dr W",
    "iso:country":"US",
    "sg:address":"720 Lake Shore Dr W",
    "sg:city":"Ashland",
    "sg:classifiers":[
        {
            "category":"Restaurant",
            "type":"Food & Drink"
        }
    ],
    "sg:phone":"+1 715 682 5455",
    "sg:postcode":"54806",
    "sg:province":"WI",
    "wof:name":"Mc Donald's",
    "wof:placetype":"venue"
},
  "geometry": {"coordinates":[-90.89163000000001,46.588957],"type":"Point"}
}