{
  "type": "Feature",
  "properties": {
    "addr:full":"4793 Cloverdale Rd Black River Falls WI 54615",
    "addr:housenumber":"4793",
    "addr:postcode":"54615",
    "addr:street":"Cloverdale Rd",
    "iso:country":"US",
    "sg:address":"4793 Cloverdale Rd",
    "sg:city":"Black River Falls",
    "sg:classifiers":[
        {
            "category":"Farming",
            "subcategory":"Dairy Farm",
            "type":"Manufacturing & Wholesale Goods"
        }
    ],
    "sg:phone":"+1 715 284 5996",
    "sg:postcode":"54615",
    "sg:province":"WI",
    "wof:name":"Andrew Anderson",
    "wof:placetype":"venue"
},
  "geometry": {"coordinates":[-90.93960800000001,44.24281],"type":"Point"}
}