{
  "type": "Feature",
  "properties": {
    "iso:country":"US",
    "sg:address":"1205 N Walnut Ave",
    "sg:city":"Marshfield",
    "sg:classifiers":[
        {
            "category":"Restaurant",
            "type":"Food & Drink"
        }
    ],
    "sg:phone":"+1 715 389 2087",
    "sg:postcode":"54449",
    "sg:province":"WI",
    "wof:name":"Victory Lane Sports Grill",
    "wof:placetype":"venue"
},
  "geometry": {"coordinates":[-90.172197,44.679544],"type":"Point"}
}