{
  "type": "Feature",
  "properties": {
    "iso:country":"US",
    "sg:address":"7982 State Rd 133",
    "sg:city":"Potosi",
    "sg:classifiers":[
        {
            "category":"Building & Trades",
            "subcategory":"Construction",
            "type":"Services"
        }
    ],
    "sg:phone":"+1 608 763 2185",
    "sg:postcode":"53820",
    "sg:province":"WI",
    "sg:tags":[
        "house"
    ],
    "wof:name":"Williams Construction",
    "wof:placetype":"venue"
},
  "geometry": {"coordinates":[-90.817999,42.692486],"type":"Point"}
}