{
  "type": "Feature",
  "properties": {
    "iso:country":"US",
    "sg:address":"132 W Chestnut St",
    "sg:city":"Burlington",
    "sg:classifiers":[
        {
            "category":"Social Services",
            "type":"Services"
        }
    ],
    "sg:phone":"+1 262 763 8012",
    "sg:postcode":"53105",
    "sg:province":"WI",
    "wof:name":"Racine County Opportunity Ctr",
    "wof:placetype":"venue"
},
  "geometry": {"coordinates":[-88.277993,42.680418],"type":"Point"}
}