{
  "type": "Feature",
  "properties": {
    "iso:country":"US",
    "sg:address":"566 Grand Canyon Dr",
    "sg:city":"Madison",
    "sg:classifiers":[
        {
            "category":"Health Services",
            "subcategory":"Hospital",
            "type":"Services"
        }
    ],
    "sg:phone":"+1 608 829 3565",
    "sg:postcode":"53705",
    "sg:province":"WI",
    "sg:tags":[
        "mental"
    ],
    "wof:name":"Northstar Day Hospital",
    "wof:placetype":"venue"
},
  "geometry": {"coordinates":[-89.496696,43.054422],"type":"Point"}
}