{
  "type": "Feature",
  "properties": {
    "iso:country":"US",
    "sg:address":"1129 Grandview Ave",
    "sg:city":"Tomah",
    "sg:classifiers":[
        {
            "category":"Building & Trades",
            "subcategory":"Construction",
            "type":"Services"
        }
    ],
    "sg:phone":"+1 608 372 2080",
    "sg:postcode":"54660",
    "sg:province":"WI",
    "sg:tags":[
        "general",
        "contractor"
    ],
    "wof:name":"Mc Cann Construction Co",
    "wof:placetype":"venue"
},
  "geometry": {"coordinates":[-90.501191,44.003897],"type":"Point"}
}