{
  "type": "Feature",
  "properties": {
    "iso:country":"US",
    "sg:address":"11000 W Heather Ave",
    "sg:city":"Milwaukee",
    "sg:classifiers":[
        {
            "category":"Freight",
            "type":"Transportation"
        }
    ],
    "sg:phone":"+1 414 354 5552",
    "sg:postcode":"53224",
    "sg:province":"WI",
    "wof:name":"Ryan & Sons Inc",
    "wof:placetype":"venue"
},
  "geometry": {"coordinates":[-88.05229,43.175116],"type":"Point"}
}