{
  "type": "Feature",
  "properties": {
    "addr:full":"2005 Lathrop Ave Racine WI 53405",
    "addr:housenumber":"2005",
    "addr:postcode":"53405",
    "addr:street":"Lathrop Ave",
    "iso:country":"US",
    "sg:address":"2005 Lathrop Ave",
    "sg:city":"Racine",
    "sg:classifiers":[
        {
            "category":"Autos & Motor Vehicles",
            "subcategory":"Motorcycle Sales",
            "type":"Retail Goods"
        }
    ],
    "sg:phone":"+1 262 632 4000",
    "sg:postcode":"53405",
    "sg:province":"WI",
    "sg:tags":[
        "repair",
        "scooter"
    ],
    "wof:name":"Racine Motor Sports Ltd",
    "wof:placetype":"venue"
},
  "geometry": {"coordinates":[-87.825897,42.704211],"type":"Point"}
}