{
  "type": "Feature",
  "properties": {
    "iso:country":"US",
    "sg:address":"4224 S 91st St",
    "sg:city":"Milwaukee",
    "sg:classifiers":[
        {
            "category":"Shopping",
            "type":"Retail Goods"
        },
        {
            "category":"Manufacturing",
            "subcategory":"Rubber & Plastics",
            "type":"Manufacturing & Wholesale Goods"
        }
    ],
    "sg:phone":"+1 414 329 1925",
    "sg:postcode":"53228",
    "sg:province":"WI",
    "sg:tags":[
        "product",
        "mfg"
    ],
    "sg:website":"www.bc-plastic.com",
    "wof:name":"B & C Plastics Inc",
    "wof:placetype":"venue"
},
  "geometry": {"coordinates":[-88.02578800000001,42.967008],"type":"Point"}
}