{
  "type": "Feature",
  "properties": {
    "iso:country":"US",
    "sg:address":"423 W Center St",
    "sg:city":"Milwaukee",
    "sg:classifiers":[
        {
            "category":"Personal",
            "subcategory":"Shoe Repair & Shine",
            "type":"Services"
        }
    ],
    "sg:phone":"+1 414 263 9908",
    "sg:postcode":"53212",
    "sg:province":"WI",
    "sg:tags":[
        "parlor",
        "shining"
    ],
    "wof:name":"Brown's Shoe Shine Parlor",
    "wof:placetype":"venue"
},
  "geometry": {"coordinates":[-87.916691,43.067496],"type":"Point"}
}