{
  "type": "Feature",
  "properties": {
    "iso:country":"US",
    "sg:address":"2304 Co Rd Ab",
    "sg:city":"Mc Farland",
    "sg:classifiers":[
        {
            "category":"Professional",
            "subcategory":"Business Services",
            "type":"Services"
        }
    ],
    "sg:phone":"+1 608 833 5516",
    "sg:postcode":"53558",
    "sg:province":"WI",
    "wof:name":"Groth Design LLC",
    "wof:placetype":"venue"
},
  "geometry": {"coordinates":[-89.27783599999999,42.975562],"type":"Point"}
}