{
  "type": "Feature",
  "properties": {
    "addr:full":"21870 Watertown Rd Waukesha WI 53186",
    "addr:postcode":"21870;53186",
    "addr:street":"Watertown Rd",
    "iso:country":"US",
    "sg:address":"21870 Watertown Rd",
    "sg:city":"Waukesha",
    "sg:classifiers":[
        {
            "category":"Professional",
            "subcategory":"Management & Consulting",
            "type":"Services"
        }
    ],
    "sg:phone":"+1 262 860 8900",
    "sg:postcode":"53186",
    "sg:province":"WI",
    "sg:tags":[
        "business"
    ],
    "wof:name":"Catalyst Production Resources",
    "wof:placetype":"venue"
},
  "geometry": {"coordinates":[-88.183734,43.048148],"type":"Point"}
}