{
  "type": "Feature",
  "properties": {
    "iso:country":"US",
    "sg:address":"940 Goodnow Ave",
    "sg:city":"Wisconsin Rapids",
    "sg:classifiers":[
        {
            "category":"Personal",
            "subcategory":"Beauty Salon",
            "type":"Services"
        }
    ],
    "sg:phone":"+1 715 424 4333",
    "sg:postcode":"54494",
    "sg:province":"WI",
    "sg:tags":[
        "shop",
        "spa",
        "day"
    ],
    "wof:name":"Inner Peace Day Spa LLC",
    "wof:placetype":"venue"
},
  "geometry": {"coordinates":[-89.815558,44.374824],"type":"Point"}
}