{
  "type": "Feature",
  "properties": {
    "addr:full":"1110 Fourier Dr Madison WI 53717",
    "addr:housenumber":"1110",
    "addr:postcode":"53717",
    "addr:street":"Fourier Dr",
    "iso:country":"US",
    "sg:address":"1110 Fourier Dr",
    "sg:city":"Madison",
    "sg:classifiers":[
        {
            "category":"Insurance",
            "subcategory":"Insurance Agent",
            "type":"Services"
        }
    ],
    "sg:phone":"+1 608 827 9480",
    "sg:postcode":"53717",
    "sg:province":"WI",
    "wof:name":"Bill Benisch Disability Ins",
    "wof:placetype":"venue"
},
  "geometry": {"coordinates":[-89.524322,43.080878],"type":"Point"}
}