{
  "type": "Feature",
  "properties": {
    "addr:full":"2170 Velp Ave Green Bay WI 54303",
    "addr:postcode":"2170;54303",
    "addr:street":"Velp Ave",
    "iso:country":"US",
    "sg:address":"2170 Velp Ave",
    "sg:city":"Green Bay",
    "sg:classifiers":[
        {
            "category":"Professional",
            "subcategory":"Employment Agencies",
            "type":"Services"
        }
    ],
    "sg:phone":"+1 920 662 1477",
    "sg:postcode":"54303",
    "sg:province":"WI",
    "sg:tags":[
        "opportunity"
    ],
    "sg:website":"www.techemp.com",
    "wof:name":"Technical Employment Service",
    "wof:placetype":"venue"
},
  "geometry": {"coordinates":[-88.06858,44.559913],"type":"Point"}
}