{
  "type": "Feature",
  "properties": {
    "addr:full":"3665 Buckeye Way Green Bay WI 54311",
    "addr:housenumber":"3665",
    "addr:postcode":"54311",
    "addr:street":"Buckeye Way",
    "iso:country":"US",
    "sg:address":"3665 Buckeye Way",
    "sg:city":"Green Bay",
    "sg:classifiers":[
        {
            "category":"Professional",
            "type":"Services"
        }
    ],
    "sg:phone":"+1 920 469 8415",
    "sg:postcode":"54311",
    "sg:province":"WI",
    "sg:tags":[
        "establishment"
    ],
    "wof:name":"Doucette & Doucette",
    "wof:placetype":"venue"
},
  "geometry": {"coordinates":[-87.90422700000001,44.535681],"type":"Point"}
}