{
  "type": "Feature",
  "properties": {
    "iso:country":"US",
    "sg:address":"4960 Morning Glory Dr",
    "sg:city":"West Bend",
    "sg:classifiers":[
        {
            "category":"Building & Trades",
            "subcategory":"Cleaning & Sanitation",
            "type":"Services"
        }
    ],
    "sg:phone":"+1 262 689 1191",
    "sg:postcode":"53095",
    "sg:province":"WI",
    "sg:tags":[
        "house"
    ],
    "wof:name":"Sparkling Homes",
    "wof:placetype":"venue"
},
  "geometry": {"coordinates":[-88.218905,43.370062],"type":"Point"}
}