{
  "type": "Feature",
  "properties": {
    "iso:country":"US",
    "sg:address":"403 Summer St",
    "sg:city":"Delavan",
    "sg:classifiers":[
        {
            "category":"Professional",
            "subcategory":"Business Services",
            "type":"Services"
        }
    ],
    "sg:phone":"+1 262 728 1844",
    "sg:postcode":"53115",
    "sg:province":"WI",
    "wof:name":"A Plus Antiques & Auctions",
    "wof:placetype":"venue"
},
  "geometry": {"coordinates":[-88.585403,42.627986],"type":"Point"}
}