{
  "type": "Feature",
  "properties": {
    "iso:country":"US",
    "sg:address":"130 S Main St",
    "sg:city":"Lodi",
    "sg:classifiers":[
        {
            "category":"Government",
            "subcategory":"Office",
            "type":"Public Place"
        }
    ],
    "sg:phone":"+1 608 592 3246",
    "sg:postcode":"53555",
    "sg:province":"WI",
    "sg:tags":[
        "govt",
        "city"
    ],
    "wof:name":"Lodi City Light & Water Svc",
    "wof:placetype":"venue"
},
  "geometry": {"coordinates":[-89.526654,43.313751],"type":"Point"}
}