{
  "type": "Feature",
  "properties": {
    "addr:full":"108 W Spring Dr Twin Lakes WI 53181",
    "addr:housenumber":"108",
    "addr:postcode":"53181",
    "addr:street":"W Spring Dr",
    "iso:country":"US",
    "sg:address":"108 W Spring Dr",
    "sg:city":"Twin Lakes",
    "sg:classifiers":[
        {
            "category":"Real Estate",
            "subcategory":"Real Estate Agent",
            "type":"Services"
        }
    ],
    "sg:phone":"+1 262 877 8346",
    "sg:postcode":"53181",
    "sg:province":"WI",
    "sg:tags":[
        "appraiser"
    ],
    "wof:name":"A C T Enterprises Inc",
    "wof:placetype":"venue"
},
  "geometry": {"coordinates":[-88.25891,42.515783],"type":"Point"}
}