{
  "type": "Feature",
  "properties": {
    "iso:country":"US",
    "sg:address":"2225 Westbrook Ln",
    "sg:city":"Madison",
    "sg:classifiers":[
        {
            "category":"Professional",
            "subcategory":"Business Services",
            "type":"Services"
        }
    ],
    "sg:phone":"+1 608 661 0554",
    "sg:postcode":"53711",
    "sg:province":"WI",
    "sg:tags":[
        "building",
        "inspection"
    ],
    "wof:name":"Ron Miller Inspections LLC",
    "wof:placetype":"venue"
},
  "geometry": {"coordinates":[-89.48998899999999,43.026376],"type":"Point"}
}