{
  "type": "Feature",
  "properties": {
    "addr:full":"3131 Hubertus Rd Hubertus WI 53033",
    "addr:postcode":"3131;53033",
    "addr:street":"Hubertus Rd",
    "iso:country":"US",
    "sg:address":"3131 Hubertus Rd",
    "sg:city":"Hubertus",
    "sg:classifiers":[
        {
            "category":"Building & Trades",
            "subcategory":"Construction",
            "type":"Services"
        }
    ],
    "sg:phone":"+1 262 628 1000",
    "sg:postcode":"53033",
    "sg:province":"WI",
    "sg:tags":[
        "general",
        "contractor"
    ],
    "wof:name":"Licitar Excavating Contractors",
    "wof:placetype":"venue"
},
  "geometry": {"coordinates":[-88.201584,43.236298],"type":"Point"}
}