{
  "type": "Feature",
  "properties": {
    "iso:country":"US",
    "sg:address":"3995 26th Ln",
    "sg:city":"Redgranite",
    "sg:classifiers":[
        {
            "category":"Building & Trades",
            "subcategory":"Construction",
            "type":"Services"
        }
    ],
    "sg:phone":"+1 920 566 2586",
    "sg:postcode":"54970",
    "sg:province":"WI",
    "sg:tags":[
        "house"
    ],
    "wof:name":"M Safford Construction",
    "wof:placetype":"venue"
},
  "geometry": {"coordinates":[-89.092569,44.119586],"type":"Point"}
}