{
  "type": "Feature",
  "properties": {
    "addr:full":"2566 S Kinnickinnic Ave Milwaukee WI 53207",
    "addr:housenumber":"2566",
    "addr:postcode":"53207",
    "addr:street":"S Kinnickinnic Ave",
    "iso:country":"US",
    "sg:address":"2566 S Kinnickinnic Ave",
    "sg:city":"Milwaukee",
    "sg:classifiers":[
        {
            "category":"Education",
            "subcategory":"Library",
            "type":"Public Place"
        },
        {
            "category":"Government",
            "subcategory":"Office",
            "type":"Public Place"
        }
    ],
    "sg:phone":"+1 414 286 3019",
    "sg:postcode":"53207",
    "sg:province":"WI",
    "sg:tags":[
        "township",
        "government-city",
        "village"
    ],
    "sg:website":"http://www.ci.mil.wi.us",
    "wof:name":"Bay View Library",
    "wof:placetype":"venue"
},
  "geometry": {"coordinates":[-87.90055099999999,42.998531],"type":"Point"}
}