{
  "type": "Feature",
  "properties": {
    "iso:country":"US",
    "sg:address":"12400 W Hampton Ave",
    "sg:city":"Butler",
    "sg:classifiers":[
        {
            "category":"Restaurant",
            "type":"Food & Drink"
        }
    ],
    "sg:menulink":"http://www.allmenus.com/wi/butler/114304-butler-inn/menu/",
    "sg:phone":"+1 262 783 5899",
    "sg:postcode":"53007",
    "sg:province":"WI",
    "sg:tags":[
        "american"
    ],
    "wof:name":"Butler Inn",
    "wof:placetype":"venue"
},
  "geometry": {"coordinates":[-88.066237,43.104807],"type":"Point"}
}