{
  "type": "Feature",
  "properties": {
    "iso:country":"US",
    "sg:address":"1000 Lone Tree Rd",
    "sg:city":"Elm Grove",
    "sg:classifiers":[
        {
            "category":"Wholesale",
            "subcategory":"Machinery & Supplies",
            "type":"Manufacturing & Wholesale Goods"
        }
    ],
    "sg:phone":"+1 262 789 5208",
    "sg:postcode":"53122",
    "sg:province":"WI",
    "sg:tags":[
        "equipment",
        "industrial"
    ],
    "wof:name":"Process Machine & Automation",
    "wof:placetype":"venue"
},
  "geometry": {"coordinates":[-88.099911,43.043471],"type":"Point"}
}