{
  "type": "Feature",
  "properties": {
    "iso:country":"US",
    "sg:address":"11243 N Oriole Ln",
    "sg:city":"Thiensville",
    "sg:classifiers":[
        {
            "category":"Wholesale",
            "subcategory":"Medical Equipment & Supplies",
            "type":"Manufacturing & Wholesale Goods"
        }
    ],
    "sg:phone":"+1 262 242 6225",
    "sg:postcode":"53092",
    "sg:province":"WI",
    "wof:name":"JM Medical LLC",
    "wof:placetype":"venue"
},
  "geometry": {"coordinates":[-87.93403600000001,43.222915],"type":"Point"}
}