{
  "type": "Feature",
  "properties": {
    "iso:country":"US",
    "sg:address":"12770 W North Ave",
    "sg:city":"Brookfield",
    "sg:classifiers":[
        {
            "category":"Health Services",
            "subcategory":"Doctor",
            "type":"Services"
        }
    ],
    "sg:phone":"+1 262 782 8576",
    "sg:postcode":"53005",
    "sg:province":"WI",
    "wof:name":"Mark Hackbarth",
    "wof:placetype":"venue"
},
  "geometry": {"coordinates":[-88.069222,43.060152],"type":"Point"}
}