{
  "type": "Feature",
  "properties": {
    "iso:country":"US",
    "sg:address":"6889 State Hwy 146",
    "sg:city":"Cambria",
    "sg:classifiers":[
        {
            "category":"Manufacturing",
            "subcategory":"Food",
            "type":"Manufacturing & Wholesale Goods"
        }
    ],
    "sg:phone":"+1 920 348 2200",
    "sg:postcode":"53923",
    "sg:province":"WI",
    "sg:tags":[
        "canned",
        "mfg"
    ],
    "wof:name":"Chiquita",
    "wof:placetype":"venue"
},
  "geometry": {"coordinates":[-89.10203,43.529751],"type":"Point"}
}