{
  "type": "Feature",
  "properties": {
    "iso:country":"US",
    "sg:address":"105 W Main St",
    "sg:city":"Arcadia",
    "sg:classifiers":[
        {
            "category":"Restaurant",
            "type":"Food & Drink"
        }
    ],
    "sg:phone":"+1 608 323 7455",
    "sg:postcode":"54612",
    "sg:province":"WI",
    "wof:name":"KOZY Kitchen",
    "wof:placetype":"venue"
},
  "geometry": {"coordinates":[-91.500484,44.252539],"type":"Point"}
}