{
  "type": "Feature",
  "properties": {
    "addr:full":"117 Rittenhouse Ave Bayfield WI 54814",
    "addr:housenumber":"117",
    "addr:postcode":"54814",
    "addr:street":"Rittenhouse Ave",
    "iso:country":"US",
    "sg:address":"117 Rittenhouse Ave",
    "sg:city":"Bayfield",
    "sg:classifiers":[
        {
            "category":"Restaurant",
            "type":"Food & Drink"
        }
    ],
    "sg:phone":"+1 715 779 9619",
    "sg:postcode":"54814",
    "sg:province":"WI",
    "sg:tags":[
        "shop",
        "coffee"
    ],
    "wof:name":"Blue Horizons Cafe",
    "wof:placetype":"venue"
},
  "geometry": {"coordinates":[-90.81461400000001,46.810967],"type":"Point"}
}