{
  "type": "Feature",
  "properties": {
    "iso:country":"US",
    "sg:address":"4700 710th St",
    "sg:city":"Ellsworth",
    "sg:classifiers":[
        {
            "category":"Shopping",
            "subcategory":"Bicycles & Sporting Goods",
            "type":"Retail Goods"
        }
    ],
    "sg:phone":"+1 715 273 0700",
    "sg:postcode":"54011",
    "sg:province":"WI",
    "wof:name":"Traynor Paintball",
    "wof:placetype":"venue"
},
  "geometry": {"coordinates":[-92.486909,44.710364],"type":"Point"}
}