{
  "type": "Feature",
  "properties": {
    "iso:country":"US",
    "sg:address":"1400 W Oklahoma Ave",
    "sg:city":"Milwaukee",
    "sg:classifiers":[
        {
            "category":"Professional",
            "subcategory":"Lawyer & Legal Services",
            "type":"Services"
        }
    ],
    "sg:phone":"+1 262 521 2257",
    "sg:postcode":"53215",
    "sg:province":"WI",
    "sg:tags":[
        "attorney"
    ],
    "wof:name":"David C Mirhoseini",
    "wof:placetype":"venue"
},
  "geometry": {"coordinates":[-87.93150799999999,42.988299],"type":"Point"}
}