{
  "type": "Feature",
  "properties": {
    "iso:country":"US",
    "sg:address":"3472 S 12th St",
    "sg:city":"Milwaukee",
    "sg:classifiers":[
        {
            "category":"Building & Trades",
            "subcategory":"Construction",
            "type":"Services"
        }
    ],
    "sg:phone":"+1 414 744 7597",
    "sg:postcode":"53215",
    "sg:province":"WI",
    "sg:tags":[
        "house"
    ],
    "wof:name":"Ed Hintz and Son Inc",
    "wof:placetype":"venue"
},
  "geometry": {"coordinates":[-87.927628,42.982401],"type":"Point"}
}