{
  "type": "Feature",
  "properties": {
    "iso:country":"US",
    "sg:address":"224 E Jefferson St",
    "sg:city":"Burlington",
    "sg:classifiers":[
        {
            "category":"Government",
            "subcategory":"Police Station",
            "type":"Public Place"
        }
    ],
    "sg:phone":"+1 262 763 2406",
    "sg:postcode":"53105",
    "sg:province":"WI",
    "sg:tags":[
        "department"
    ],
    "wof:name":"Burlington Chief Of Police",
    "wof:placetype":"venue"
},
  "geometry": {"coordinates":[-88.275377,42.678428],"type":"Point"}
}