{
  "type": "Feature",
  "properties": {
    "iso:country":"US",
    "sg:address":"1028 220th St",
    "sg:city":"Baldwin",
    "sg:classifiers":[
        {
            "category":"Wholesale",
            "subcategory":"Scrap",
            "type":"Manufacturing & Wholesale Goods"
        }
    ],
    "sg:phone":"+1 715 684 3043",
    "sg:postcode":"54002",
    "sg:province":"WI",
    "sg:tags":[
        "material"
    ],
    "wof:name":"Nelson Scrap",
    "wof:placetype":"venue"
},
  "geometry": {"coordinates":[-92.359699,45.007983],"type":"Point"}
}