{
  "type": "Feature",
  "properties": {
    "iso:country":"US",
    "sg:address":"2979 Hall Dr",
    "sg:city":"Medford",
    "sg:classifiers":[
        {
            "category":"Retail",
            "subcategory":"Portrait Studio",
            "type":"Services"
        }
    ],
    "sg:phone":"+1 715 748 5246",
    "sg:postcode":"54451",
    "sg:province":"WI",
    "sg:tags":[
        "photo"
    ],
    "wof:name":"Holmes Studio East",
    "wof:placetype":"venue"
},
  "geometry": {"coordinates":[-90.24946,45.139493],"type":"Point"}
}