{
  "type": "Feature",
  "properties": {
    "iso:country":"US",
    "sg:address":"7371 State Hwy 76",
    "sg:city":"Neenah",
    "sg:classifiers":[
        {
            "category":"Retail",
            "subcategory":"Animal Services",
            "type":"Services"
        }
    ],
    "sg:phone":"+1 920 722 9696",
    "sg:postcode":"54956",
    "sg:province":"WI",
    "wof:name":"Schultz Boarding Kennels",
    "wof:placetype":"venue"
},
  "geometry": {"coordinates":[-88.543971,44.158731],"type":"Point"}
}