{
  "type": "Feature",
  "properties": {
    "addr:full":"8437 Foote Dr Portage WI 53901",
    "addr:housenumber":"8437",
    "addr:postcode":"53901",
    "addr:street":"Foote Dr",
    "iso:country":"US",
    "sg:address":"8437 Foote Dr",
    "sg:city":"Portage",
    "sg:classifiers":[
        {
            "category":"Building & Trades",
            "subcategory":"Construction",
            "type":"Services"
        }
    ],
    "sg:phone":"+1 608 742 6313",
    "sg:postcode":"53901",
    "sg:province":"WI",
    "sg:tags":[
        "hanging",
        "contractor"
    ],
    "wof:name":"Portage Painting & Decorating",
    "wof:placetype":"venue"
},
  "geometry": {"coordinates":[-89.419695,43.555863],"type":"Point"}
}