{
  "type": "Feature",
  "properties": {
    "iso:country":"US",
    "sg:address":"2330 Knoll Terrace Dr",
    "sg:city":"Waterford",
    "sg:classifiers":[
        {
            "category":"Building & Trades",
            "subcategory":"Construction",
            "type":"Services"
        }
    ],
    "sg:phone":"+1 262 534 4315",
    "sg:postcode":"53185",
    "sg:province":"WI",
    "sg:tags":[
        "house"
    ],
    "wof:name":"Beronja Construction",
    "wof:placetype":"venue"
},
  "geometry": {"coordinates":[-88.215457,42.748393],"type":"Point"}
}