{
  "type": "Feature",
  "properties": {
    "addr:full":"1032 S Westland Dr Appleton WI 54914",
    "addr:housenumber":"1032",
    "addr:postcode":"54914",
    "addr:street":"S Westland Dr",
    "iso:country":"US",
    "sg:address":"1032 S Westland Dr",
    "sg:city":"Appleton",
    "sg:classifiers":[
        {
            "category":"Bars & Pubs",
            "type":"Food & Drink"
        }
    ],
    "sg:phone":"+1 920 734 5110",
    "sg:postcode":"54914",
    "sg:province":"WI",
    "sg:tags":[
        "drinking"
    ],
    "wof:name":"Paradise Club",
    "wof:placetype":"venue"
},
  "geometry": {"coordinates":[-88.465872,44.256446],"type":"Point"}
}