{
  "type": "Feature",
  "properties": {
    "addr:full":"7500 Green Bay Rd Kenosha WI 53142",
    "addr:housenumber":"7500",
    "addr:postcode":"53142",
    "addr:street":"Green Bay Rd",
    "iso:country":"US",
    "sg:address":"7500 Green Bay Rd",
    "sg:city":"Kenosha",
    "sg:classifiers":[
        {
            "category":"Education",
            "subcategory":"College",
            "type":"Public Place"
        }
    ],
    "sg:phone":"+1 262 697 8260",
    "sg:postcode":"53142",
    "sg:province":"WI",
    "sg:tags":[
        "four",
        "arts",
        "liberal"
    ],
    "wof:name":"Concordia",
    "wof:placetype":"venue"
},
  "geometry": {"coordinates":[-87.887562,42.566707],"type":"Point"}
}