{
  "type": "Feature",
  "properties": {
    "iso:country":"US",
    "sg:address":"130 N 7th Ave",
    "sg:city":"Sturgeon Bay",
    "sg:classifiers":[
        {
            "category":"Building & Trades",
            "subcategory":"Landscaping Services",
            "type":"Services"
        }
    ],
    "sg:phone":"+1 920 743 6206",
    "sg:postcode":"54235",
    "sg:province":"WI",
    "sg:tags":[
        "landscape",
        "contractor"
    ],
    "wof:name":"Five Star Landscape",
    "wof:placetype":"venue"
},
  "geometry": {"coordinates":[-87.373047,44.838138],"type":"Point"}
}