{
  "type": "Feature",
  "properties": {
    "iso:country":"US",
    "sg:address":"662 State St",
    "sg:city":"Madison",
    "sg:classifiers":[
        {
            "category":"Restaurant",
            "type":"Food & Drink"
        }
    ],
    "sg:phone":"+1 608 251 0440",
    "sg:postcode":"53703",
    "sg:province":"WI",
    "sg:tags":[
        "eating"
    ],
    "wof:name":"Pizza Hut",
    "wof:placetype":"venue"
},
  "geometry": {"coordinates":[-89.397266,43.074974],"type":"Point"}
}