{
  "type": "Feature",
  "properties": {
    "iso:country":"US",
    "sg:address":"6022 Sycamore St",
    "sg:city":"Greendale",
    "sg:classifiers":[
        {
            "category":"Professional",
            "subcategory":"Business Services",
            "type":"Services"
        }
    ],
    "sg:phone":"+1 414 421 3834",
    "sg:postcode":"53129",
    "sg:province":"WI",
    "wof:name":"Innovated Mediums LLC",
    "wof:placetype":"venue"
},
  "geometry": {"coordinates":[-87.97830999999999,42.9325],"type":"Point"}
}