{
  "type": "Feature",
  "properties": {
    "iso:country":"US",
    "sg:address":"306 S Main St",
    "sg:city":"Blanchardville",
    "sg:classifiers":[
        {
            "category":"Real Estate",
            "subcategory":"Real Estate Agent",
            "type":"Services"
        }
    ],
    "sg:phone":"+1 608 523 4225",
    "sg:postcode":"53516",
    "sg:province":"WI",
    "wof:name":"Chandler Realty",
    "wof:placetype":"venue"
},
  "geometry": {"coordinates":[-89.86219199999999,42.810283],"type":"Point"}
}