{
  "type": "Feature",
  "properties": {
    "addr:full":"112 E Huron St Berlin WI 54923",
    "addr:housenumber":"112",
    "addr:postcode":"54923",
    "addr:street":"E Huron St",
    "iso:country":"US",
    "sg:address":"112 E Huron St",
    "sg:city":"Berlin",
    "sg:classifiers":[
        {
            "category":"Shopping",
            "subcategory":"Florist",
            "type":"Retail Goods"
        }
    ],
    "sg:phone":"+1 920 361 9006",
    "sg:postcode":"54923",
    "sg:province":"WI",
    "sg:tags":[
        "gift"
    ],
    "wof:name":"Ladybug Floral & Gift LLC",
    "wof:placetype":"venue"
},
  "geometry": {"coordinates":[-88.94642399999999,43.968297],"type":"Point"}
}