{
  "type": "Feature",
  "properties": {
    "iso:country":"US",
    "sg:address":"1000 W Campus Dr",
    "sg:city":"Wausau",
    "sg:classifiers":[
        {
            "category":"Restaurant",
            "type":"Food & Drink"
        }
    ],
    "sg:phone":"+1 715 675 0057",
    "sg:postcode":"54401",
    "sg:province":"WI",
    "sg:tags":[
        "eating"
    ],
    "wof:name":"Consolidated Management Co",
    "wof:placetype":"venue"
},
  "geometry": {"coordinates":[-89.649836,44.988056],"type":"Point"}
}