{
  "type": "Feature",
  "properties": {
    "addr:full":"432 W Ryan St Brillion WI 54110",
    "addr:housenumber":"432",
    "addr:postcode":"54110",
    "addr:street":"W Ryan St",
    "iso:country":"US",
    "sg:address":"432 W Ryan St",
    "sg:city":"Brillion",
    "sg:classifiers":[
        {
            "category":"Insurance",
            "subcategory":"Insurance Agent",
            "type":"Services"
        }
    ],
    "sg:phone":"+1 920 756 5333",
    "sg:postcode":"54110",
    "sg:province":"WI",
    "sg:website":"www.hometownbrillion.com",
    "wof:name":"Hometown Insurance",
    "wof:placetype":"venue"
},
  "geometry": {"coordinates":[-88.07436800000001,44.182459],"type":"Point"}
}