{
  "type": "Feature",
  "properties": {
    "iso:country":"US",
    "sg:address":"4555 N 37th St",
    "sg:city":"Milwaukee",
    "sg:classifiers":[
        {
            "category":"Insurance",
            "subcategory":"Insurance Agent",
            "type":"Services"
        }
    ],
    "sg:phone":"+1 414 357 8508",
    "sg:postcode":"53209",
    "sg:province":"WI",
    "wof:name":"Johnny Triplett Insurance Agcy",
    "wof:placetype":"venue"
},
  "geometry": {"coordinates":[-87.959298,43.099761],"type":"Point"}
}