{
  "type": "Feature",
  "properties": {
    "iso:country":"US",
    "sg:address":"225 Regency Ct",
    "sg:city":"Brookfield",
    "sg:classifiers":[
        {
            "category":"Health Services",
            "subcategory":"Chiropractor",
            "type":"Services"
        }
    ],
    "sg:phone":"+1 262 641 4110",
    "sg:postcode":"53045",
    "sg:province":"WI",
    "sg:tags":[
        "chiropractic"
    ],
    "wof:name":"Dunn Chiropractic Office",
    "wof:placetype":"venue"
},
  "geometry": {"coordinates":[-88.149518,43.034184],"type":"Point"}
}