{
  "type": "Feature",
  "properties": {
    "iso:country":"US",
    "sg:address":"300 Audubon Rd",
    "sg:city":"Howards Grove",
    "sg:classifiers":[
        {
            "category":"Health Services",
            "subcategory":"Optometrist",
            "type":"Services"
        }
    ],
    "sg:phone":"+1 920 565 3991",
    "sg:postcode":"53083",
    "sg:province":"WI",
    "wof:name":"Kisiolek Eye Ctr",
    "wof:placetype":"venue"
},
  "geometry": {"coordinates":[-87.819046,43.827701],"type":"Point"}
}