{
  "type": "Feature",
  "properties": {
    "iso:country":"US",
    "sg:address":"8979 Co Rd U",
    "sg:city":"Cassville",
    "sg:classifiers":[
        {
            "category":"Farming",
            "subcategory":"Dairy Farm",
            "type":"Manufacturing & Wholesale Goods"
        }
    ],
    "sg:phone":"+1 608 794 2120",
    "sg:postcode":"53806",
    "sg:province":"WI",
    "wof:name":"Kenneth Raisbeck",
    "wof:placetype":"venue"
},
  "geometry": {"coordinates":[-90.855532,42.760825],"type":"Point"}
}