{
  "type": "Feature",
  "properties": {
    "iso:country":"US",
    "sg:address":"17718 Mercury Ave",
    "sg:city":"Norwalk",
    "sg:classifiers":[
        {
            "category":"Farming",
            "subcategory":"Dairy Farm",
            "type":"Manufacturing & Wholesale Goods"
        }
    ],
    "sg:phone":"+1 608 823 7975",
    "sg:postcode":"54648",
    "sg:province":"WI",
    "sg:tags":[
        "operates"
    ],
    "wof:name":"Haldeman Farms",
    "wof:placetype":"venue"
},
  "geometry": {"coordinates":[-90.64208600000001,43.803533],"type":"Point"}
}