{
  "type": "Feature",
  "properties": {
    "iso:country":"US",
    "sg:address":"1016 Newbury St",
    "sg:city":"Ripon",
    "sg:classifiers":[
        {
            "category":"Building & Trades",
            "subcategory":"Construction",
            "type":"Services"
        }
    ],
    "sg:phone":"+1 920 748 9314",
    "sg:postcode":"54971",
    "sg:province":"WI",
    "sg:tags":[
        "floor",
        "laying",
        "contractor"
    ],
    "wof:name":"Stretchs Flooring Installatio",
    "wof:placetype":"venue"
},
  "geometry": {"coordinates":[-88.837565,43.832847],"type":"Point"}
}