{
  "type": "Feature",
  "properties": {
    "iso:country":"US",
    "sg:address":"2425 Seymour Rd",
    "sg:city":"Eau Claire",
    "sg:classifiers":[
        {
            "category":"Home & Garden",
            "subcategory":"Furniture",
            "type":"Retail Goods"
        }
    ],
    "sg:phone":"+1 715 839 9335",
    "sg:postcode":"54703",
    "sg:province":"WI",
    "wof:name":"Northwoods Spec Furniture Co",
    "wof:placetype":"venue"
},
  "geometry": {"coordinates":[-91.474973,44.826437],"type":"Point"}
}