{
  "type": "Feature",
  "properties": {
    "iso:country":"US",
    "sg:address":"6924 Co Rd F",
    "sg:city":"Brownsville",
    "sg:classifiers":[
        {
            "category":"Retail",
            "subcategory":"Animal Services",
            "type":"Services"
        }
    ],
    "sg:phone":"+1 920 583 2203",
    "sg:postcode":"53006",
    "sg:province":"WI",
    "sg:tags":[
        "pet",
        "boarding",
        "sitting"
    ],
    "wof:name":"Sand Hill Kennels",
    "wof:placetype":"venue"
},
  "geometry": {"coordinates":[-88.505475,43.660927],"type":"Point"}
}