{
  "type": "Feature",
  "properties": {
    "iso:country":"US",
    "sg:address":"3919 S Clover Dr",
    "sg:city":"New Berlin",
    "sg:classifiers":[
        {
            "category":"Insurance",
            "subcategory":"Insurance Agent",
            "type":"Services"
        }
    ],
    "sg:phone":"+1 262 786 0447",
    "sg:postcode":"53146",
    "sg:province":"WI",
    "wof:name":"John Romppainen Insurance",
    "wof:placetype":"venue"
},
  "geometry": {"coordinates":[-88.130698,42.973368],"type":"Point"}
}