{
  "type": "Feature",
  "properties": {
    "iso:country":"US",
    "sg:address":"6483 Design Dr",
    "sg:city":"Greenville",
    "sg:classifiers":[
        {
            "category":"Manufacturing",
            "subcategory":"Metals",
            "type":"Manufacturing & Wholesale Goods"
        }
    ],
    "sg:phone":"+1 920 757 1503",
    "sg:postcode":"54942",
    "sg:province":"WI",
    "sg:tags":[
        "engraver"
    ],
    "wof:name":"Write-On BAKEWARE LLC",
    "wof:placetype":"venue"
},
  "geometry": {"coordinates":[-88.51537999999999,44.28055],"type":"Point"}
}