{
  "type": "Feature",
  "properties": {
    "addr:full":"9867 171st St Chippewa Falls WI 54729",
    "addr:housenumber":"9867",
    "addr:postcode":"54729",
    "addr:street":"171St St",
    "iso:country":"US",
    "sg:address":"9867 171st St",
    "sg:city":"Chippewa Falls",
    "sg:classifiers":[
        {
            "category":"Professional",
            "subcategory":"Business Services",
            "type":"Services"
        }
    ],
    "sg:phone":"+1 715 382 5242",
    "sg:postcode":"54729",
    "sg:province":"WI",
    "wof:name":"Dr Consulting",
    "wof:placetype":"venue"
},
  "geometry": {"coordinates":[-91.325074,44.985843],"type":"Point"}
}