{
  "type": "Feature",
  "properties": {
    "iso:country":"US",
    "sg:address":"2400 W Leonard St",
    "sg:city":"Appleton",
    "sg:classifiers":[
        {
            "category":"Shopping",
            "type":"Retail Goods"
        }
    ],
    "sg:phone":"+1 920 739 1288",
    "sg:postcode":"54914",
    "sg:province":"WI",
    "sg:tags":[
        "equipment",
        "telephone",
        "supply"
    ],
    "sg:website":"www.unitelinc.com",
    "wof:name":"Unitel",
    "wof:placetype":"venue"
},
  "geometry": {"coordinates":[-88.443422,44.250978],"type":"Point"}
}