{
  "type": "Feature",
  "properties": {
    "iso:country":"US",
    "sg:address":"1075 Spring Prairie Rd",
    "sg:city":"Burlington",
    "sg:classifiers":[
        {
            "category":"Freight",
            "type":"Transportation"
        }
    ],
    "sg:phone":"+1 262 763 6323",
    "sg:postcode":"53105",
    "sg:province":"WI",
    "sg:tags":[
        "operator",
        "trucking"
    ],
    "wof:name":"Stowell Trucking Inc",
    "wof:placetype":"venue"
},
  "geometry": {"coordinates":[-88.35194300000001,42.697993],"type":"Point"}
}