{
  "type": "Feature",
  "properties": {
    "addr:full":"209 Railroad St Menasha WI 54952",
    "addr:housenumber":"209",
    "addr:postcode":"54952",
    "addr:street":"Railroad St",
    "iso:country":"US",
    "sg:address":"209 Railroad St",
    "sg:city":"Menasha",
    "sg:classifiers":[
        {
            "category":"Building & Trades",
            "subcategory":"Construction",
            "type":"Services"
        },
        {
            "category":"Building & Trades",
            "subcategory":"Landscaping Services",
            "type":"Services"
        }
    ],
    "sg:phone":"+1 920 727 9865",
    "sg:postcode":"54952",
    "sg:province":"WI",
    "sg:tags":[
        "lawn",
        "contractor",
        "maintenance",
        "grounds"
    ],
    "wof:name":"J & M Lawn Maintenance",
    "wof:placetype":"venue"
},
  "geometry": {"coordinates":[-88.457134,44.193961],"type":"Point"}
}