{
  "type": "Feature",
  "properties": {
    "iso:country":"US",
    "sg:address":"2580 N Oakland Ave",
    "sg:city":"Milwaukee",
    "sg:classifiers":[
        {
            "category":"Real Estate",
            "subcategory":"Real Estate Services",
            "type":"Services"
        },
        {
            "category":"Real Estate",
            "subcategory":"Real Estate Agent",
            "type":"Services"
        }
    ],
    "sg:phone":"+1 414 963 9102",
    "sg:postcode":"53211",
    "sg:province":"WI",
    "sg:tags":[
        "buyer",
        "broker"
    ],
    "wof:name":"Wellston Co",
    "wof:placetype":"venue"
},
  "geometry": {"coordinates":[-87.88799899999999,43.065678],"type":"Point"}
}