{
  "type": "Feature",
  "properties": {
    "addr:full":"115 E Main St Reedsburg WI 53959",
    "addr:housenumber":"115",
    "addr:postcode":"53959",
    "addr:street":"E Main St",
    "iso:country":"US",
    "sg:address":"115 E Main St",
    "sg:city":"Reedsburg",
    "sg:classifiers":[
        {
            "category":"Banks & Credit Unions",
            "subcategory":"Bank",
            "type":"Services"
        }
    ],
    "sg:phone":"+1 608 524 5395",
    "sg:postcode":"53959",
    "sg:province":"WI",
    "sg:website":"www.cfbank.com",
    "wof:name":"Bank Of The West",
    "wof:placetype":"venue"
},
  "geometry": {"coordinates":[-90.00990899999999,43.532577],"type":"Point"}
}