{
  "type": "Feature",
  "properties": {
    "addr:full":"4648 Edgewater Beach Rd Green Bay WI 54311",
    "addr:housenumber":"4648",
    "addr:postcode":"54311",
    "addr:street":"Edgewater Beach Rd",
    "iso:country":"US",
    "sg:address":"4648 Edgewater Beach Rd",
    "sg:city":"Green Bay",
    "sg:classifiers":[
        {
            "category":"Freight",
            "type":"Transportation"
        }
    ],
    "sg:phone":"+1 920 866 3646",
    "sg:postcode":"54311",
    "sg:province":"WI",
    "sg:tags":[
        "operator",
        "trucking"
    ],
    "wof:name":"Steven L Debruin",
    "wof:placetype":"venue"
},
  "geometry": {"coordinates":[-87.84632499999999,44.617395],"type":"Point"}
}