{
  "type": "Feature",
  "properties": {
    "iso:country":"US",
    "sg:address":"936 Beetown Rd",
    "sg:city":"Lancaster",
    "sg:classifiers":[
        {
            "category":"Real Estate",
            "subcategory":"Real Estate Operator",
            "type":"Services"
        }
    ],
    "sg:phone":"+1 608 723 2620",
    "sg:postcode":"53813",
    "sg:province":"WI",
    "sg:tags":[
        "feedlot",
        "property",
        "beef",
        "lessor",
        "cattle"
    ],
    "wof:name":"Dorothy Macke",
    "wof:placetype":"venue"
},
  "geometry": {"coordinates":[-90.718858,42.842188],"type":"Point"}
}