{
  "type": "Feature",
  "properties": {
    "iso:country":"US",
    "sg:address":"316 Hewett St",
    "sg:city":"Neillsville",
    "sg:classifiers":[
        {
            "category":"Organizations",
            "subcategory":"Religious Organization",
            "type":"Services"
        }
    ],
    "sg:phone":"+1 715 743 3535",
    "sg:postcode":"54456",
    "sg:province":"WI",
    "sg:tags":[
        "church"
    ],
    "wof:name":"Assembly Of God Church",
    "wof:placetype":"venue"
},
  "geometry": {"coordinates":[-90.596371,44.556816],"type":"Point"}
}