{
  "type": "Feature",
  "properties": {
    "iso:country":"US",
    "sg:address":"135 E Pulaski St",
    "sg:city":"Pulaski",
    "sg:classifiers":[
        {
            "category":"Retail",
            "subcategory":"Veterinary Services",
            "type":"Services"
        }
    ],
    "sg:phone":"+1 920 822 8575",
    "sg:postcode":"54162",
    "sg:province":"WI",
    "wof:name":"Veterinary House Calls",
    "wof:placetype":"venue"
},
  "geometry": {"coordinates":[-88.241979,44.672474],"type":"Point"}
}