{
  "type": "Feature",
  "properties": {
    "iso:country":"US",
    "sg:address":"3221 60th St",
    "sg:city":"Kenosha",
    "sg:classifiers":[
        {
            "category":"Bars & Pubs",
            "type":"Food & Drink"
        }
    ],
    "sg:phone":"+1 262 657 5712",
    "sg:postcode":"53144",
    "sg:province":"WI",
    "sg:tags":[
        "drinking"
    ],
    "wof:name":"Our Kenosha Tap",
    "wof:placetype":"venue"
},
  "geometry": {"coordinates":[-87.848929,42.580836],"type":"Point"}
}