{
  "type": "Feature",
  "properties": {
    "addr:full":"8194 N Riley Rd Verona WI 53593",
    "addr:housenumber":"8194",
    "addr:postcode":"53593",
    "addr:street":"N Riley Rd",
    "iso:country":"US",
    "sg:address":"8194 N Riley Rd",
    "sg:city":"Verona",
    "sg:classifiers":[
        {
            "category":"Real Estate",
            "subcategory":"Architect",
            "type":"Services"
        }
    ],
    "sg:phone":"+1 608 335 8159",
    "sg:postcode":"53593",
    "sg:province":"WI",
    "wof:name":"Arch Aide LLC",
    "wof:placetype":"venue"
},
  "geometry": {"coordinates":[-89.62594,43.031456],"type":"Point"}
}