{
  "type": "Feature",
  "properties": {
    "iso:country":"US",
    "sg:address":"8361 N Cedarburg Rd",
    "sg:city":"Milwaukee",
    "sg:classifiers":[
        {
            "category":"Mining & Drilling",
            "type":"Manufacturing & Wholesale Goods"
        }
    ],
    "sg:phone":"+1 414 464 5550",
    "sg:postcode":"53209",
    "sg:province":"WI",
    "sg:tags":[
        "jacking",
        "mud",
        "contractor"
    ],
    "wof:name":"Atlas Mudjacking LLC",
    "wof:placetype":"venue"
},
  "geometry": {"coordinates":[-87.961277,43.168937],"type":"Point"}
}