{
  "type": "Feature",
  "properties": {
    "iso:country":"US",
    "sg:address":"2872 Charleston Dr",
    "sg:city":"Madison",
    "sg:classifiers":[
        {
            "category":"Building & Trades",
            "subcategory":"Construction",
            "type":"Services"
        }
    ],
    "sg:phone":"+1 608 271 4441",
    "sg:postcode":"53711",
    "sg:province":"WI",
    "sg:tags":[
        "carpentry",
        "contractor"
    ],
    "wof:name":"Wood Doctors Rx LLC",
    "wof:placetype":"venue"
},
  "geometry": {"coordinates":[-89.437558,43.010705],"type":"Point"}
}