{
  "type": "Feature",
  "properties": {
    "addr:full":"585 Washington Dr West Bend WI 53095",
    "addr:housenumber":"585",
    "addr:postcode":"53095",
    "addr:street":"Washington Dr",
    "iso:country":"US",
    "sg:address":"585 Washington Dr",
    "sg:city":"West Bend",
    "sg:classifiers":[
        {
            "category":"Building & Trades",
            "subcategory":"Landscaping Services",
            "type":"Services"
        }
    ],
    "sg:phone":"+1 262 675 5001",
    "sg:postcode":"53095",
    "sg:province":"WI",
    "sg:tags":[
        "lawn",
        "snowplowing",
        "care"
    ],
    "wof:name":"Lawn Systems Inc",
    "wof:placetype":"venue"
},
  "geometry": {"coordinates":[-88.064617,43.374493],"type":"Point"}
}