{
  "type": "Feature",
  "properties": {
    "iso:country":"US",
    "sg:address":"8134 W Keefe Ave",
    "sg:city":"Milwaukee",
    "sg:classifiers":[
        {
            "category":"Social Services",
            "subcategory":"Child Care",
            "type":"Services"
        }
    ],
    "sg:phone":"+1 414 463 9616",
    "sg:postcode":"53222",
    "sg:province":"WI",
    "wof:name":"Laura's Little Angels",
    "wof:placetype":"venue"
},
  "geometry": {"coordinates":[-88.014624,43.082613],"type":"Point"}
}