{
  "type": "Feature",
  "properties": {
    "iso:country":"US",
    "sg:address":"3336 Co Rd K",
    "sg:city":"Hartford",
    "sg:classifiers":[
        {
            "category":"Retail",
            "subcategory":"Veterinary Services",
            "type":"Services"
        }
    ],
    "sg:phone":"+1 262 673 5355",
    "sg:postcode":"53027",
    "sg:province":"WI",
    "sg:tags":[
        "veterinarian"
    ],
    "wof:name":"Animal Doctors The",
    "wof:placetype":"venue"
},
  "geometry": {"coordinates":[-88.35432900000001,43.312722],"type":"Point"}
}