{
  "type": "Feature",
  "properties": {
    "iso:country":"US",
    "sg:address":"4135 State Hwy 55",
    "sg:city":"Kaukauna",
    "sg:classifiers":[
        {
            "category":"Autos & Motor Vehicles",
            "subcategory":"Fuel & Gas Station",
            "type":"Retail Goods"
        }
    ],
    "sg:phone":"+1 920 788 3337",
    "sg:postcode":"54130",
    "sg:province":"WI",
    "sg:tags":[
        "convenience",
        "station",
        "store",
        "oil"
    ],
    "wof:name":"Dairyland Depot Inc",
    "wof:placetype":"venue"
},
  "geometry": {"coordinates":[-88.291507,44.387532],"type":"Point"}
}