{
  "type": "Feature",
  "properties": {
    "iso:country":"US",
    "sg:address":"1977 American Dr",
    "sg:city":"Neenah",
    "sg:classifiers":[
        {
            "category":"Banks & Credit Unions",
            "subcategory":"Investment Brokerage",
            "type":"Services"
        }
    ],
    "sg:phone":"+1 920 720 5678",
    "sg:postcode":"54956",
    "sg:province":"WI",
    "sg:tags":[
        "consultant",
        "planning",
        "financial",
        "planner"
    ],
    "sg:website":"www.retainedearnings.com",
    "wof:name":"Retained Earnings Co",
    "wof:placetype":"venue"
},
  "geometry": {"coordinates":[-88.469529,44.228683],"type":"Point"}
}