{
  "type": "Feature",
  "properties": {
    "iso:country":"US",
    "sg:address":"142 Poplar St",
    "sg:city":"Turtle Lake",
    "sg:classifiers":[
        {
            "category":"Shopping",
            "type":"Retail Goods"
        }
    ],
    "sg:phone":"+1 715 986 4367",
    "sg:postcode":"54889",
    "sg:province":"WI",
    "sg:tags":[
        "merchandise"
    ],
    "wof:name":"Fire Extinguishers Sales Svc",
    "wof:placetype":"venue"
},
  "geometry": {"coordinates":[-92.133961,45.396912],"type":"Point"}
}