{
  "type": "Feature",
  "properties": {
    "iso:country":"US",
    "sg:address":"2250 Woodview Rd",
    "sg:city":"Oconto",
    "sg:classifiers":[
        {
            "category":"Retail",
            "subcategory":"Repair Shop",
            "type":"Services"
        }
    ],
    "sg:phone":"+1 920 834 4995",
    "sg:postcode":"54153",
    "sg:province":"WI",
    "sg:tags":[
        "television",
        "radio"
    ],
    "wof:name":"Jim's TV & Stereo",
    "wof:placetype":"venue"
},
  "geometry": {"coordinates":[-87.87198600000001,44.961434],"type":"Point"}
}