{
  "type": "Feature",
  "properties": {
    "addr:full":"2881 Driftwood Beach Rd Chilton WI 53014",
    "addr:housenumber":"2881",
    "addr:postcode":"53014",
    "addr:street":"Driftwood Beach Rd",
    "iso:country":"US",
    "sg:address":"2881 Driftwood Beach Rd",
    "sg:city":"Chilton",
    "sg:classifiers":[
        {
            "category":"Retail",
            "subcategory":"Auto Repair",
            "type":"Services"
        }
    ],
    "sg:phone":"+1 920 849 9611",
    "sg:postcode":"53014",
    "sg:province":"WI",
    "sg:tags":[
        "automobile",
        "top",
        "upholstery"
    ],
    "wof:name":"Color Rite Inc",
    "wof:placetype":"venue"
},
  "geometry": {"coordinates":[-88.324629,43.992216],"type":"Point"}
}