{
  "type": "Feature",
  "properties": {
    "iso:country":"US",
    "sg:address":"4714 70th Ave",
    "sg:city":"Kenosha",
    "sg:classifiers":[
        {
            "category":"Manufacturing",
            "subcategory":"Tools & Machinery",
            "type":"Manufacturing & Wholesale Goods"
        }
    ],
    "sg:phone":"+1 262 657 7044",
    "sg:postcode":"53144",
    "sg:province":"WI",
    "sg:tags":[
        "machine",
        "screw",
        "product",
        "shop",
        "mfg"
    ],
    "wof:name":"Badger Automatic Products Inc",
    "wof:placetype":"venue"
},
  "geometry": {"coordinates":[-87.893923,42.594017],"type":"Point"}
}