{
  "type": "Feature",
  "properties": {
    "addr:full":"2040 S Memorial Dr Racine WI 53403",
    "addr:housenumber":"2040",
    "addr:postcode":"53403",
    "addr:street":"S Memorial Dr",
    "iso:country":"US",
    "sg:address":"2040 S Memorial Dr",
    "sg:city":"Racine",
    "sg:classifiers":[
        {
            "category":"Retail",
            "subcategory":"Auto Repair",
            "type":"Services"
        }
    ],
    "sg:phone":"+1 262 637 6153",
    "sg:postcode":"53403",
    "sg:province":"WI",
    "sg:tags":[
        "body"
    ],
    "wof:name":"A-1 Auto Body of Racine Inc",
    "wof:placetype":"venue"
},
  "geometry": {"coordinates":[-87.79859,42.705082],"type":"Point"}
}