{
  "type": "Feature",
  "properties": {
    "iso:country":"US",
    "sg:address":"615 Phillips Blvd",
    "sg:city":"Sauk City",
    "sg:classifiers":[
        {
            "category":"Shopping",
            "type":"Retail Goods"
        }
    ],
    "sg:phone":"+1 608 643 8241",
    "sg:postcode":"53583",
    "sg:province":"WI",
    "sg:tags":[
        "monument"
    ],
    "wof:name":"Spellman Monument Co Inc",
    "wof:placetype":"venue"
},
  "geometry": {"coordinates":[-89.728545,43.271287],"type":"Point"}
}