{
  "type": "Feature",
  "properties": {
    "addr:full":"8360 State Rd Chippewa Falls WI 54729",
    "addr:housenumber":"8360",
    "addr:postcode":"54729",
    "addr:street":"State Rd",
    "iso:country":"US",
    "sg:address":"8360 State Rd",
    "sg:city":"Chippewa Falls",
    "sg:classifiers":[
        {
            "category":"Building & Trades",
            "subcategory":"Equipment Rental",
            "type":"Services"
        }
    ],
    "sg:phone":"+1 715 726 8630",
    "sg:postcode":"54729",
    "sg:province":"WI",
    "sg:tags":[
        "heavy",
        "construction",
        "w",
        "business"
    ],
    "sg:website":"www.dawescrane.com",
    "wof:name":"Dawes Rigging & Crane Rental",
    "wof:placetype":"venue"
},
  "geometry": {"coordinates":[-91.388693,44.956539],"type":"Point"}
}