{
  "type": "Feature",
  "properties": {
    "iso:country":"US",
    "sg:address":"3952 N 76th St",
    "sg:city":"Milwaukee",
    "sg:classifiers":[
        {
            "category":"Retail",
            "subcategory":"Repair Shop",
            "type":"Services"
        }
    ],
    "sg:phone":"+1 414 466 4230",
    "sg:postcode":"53222",
    "sg:province":"WI",
    "sg:tags":[
        "furniture"
    ],
    "wof:name":"Bix Service Co",
    "wof:placetype":"venue"
},
  "geometry": {"coordinates":[-88.00717,43.088942],"type":"Point"}
}