{
  "type": "Feature",
  "properties": {
    "iso:country":"US",
    "sg:address":"11222 State Hwy 95",
    "sg:city":"Blair",
    "sg:classifiers":[
        {
            "category":"Farming",
            "subcategory":"Dairy Farm",
            "type":"Manufacturing & Wholesale Goods"
        }
    ],
    "sg:phone":"+1 608 989 2398",
    "sg:postcode":"54616",
    "sg:province":"WI",
    "wof:name":"Paul & Keith Nestingen",
    "wof:placetype":"venue"
},
  "geometry": {"coordinates":[-91.171027,44.308908],"type":"Point"}
}