{
  "type": "Feature",
  "properties": {
    "iso:country":"US",
    "sg:address":"1140 Main St",
    "sg:city":"La Crosse",
    "sg:classifiers":[
        {
            "category":"Social Services",
            "type":"Services"
        }
    ],
    "sg:phone":"+1 608 782 9622",
    "sg:postcode":"54601",
    "sg:province":"WI",
    "sg:tags":[
        "organization",
        "welfare"
    ],
    "sg:website":"www.laxymca.org",
    "wof:name":"LA Crosse Family Ymca",
    "wof:placetype":"venue"
},
  "geometry": {"coordinates":[-91.239681,43.811604],"type":"Point"}
}