{
  "type": "Feature",
  "properties": {
    "addr:full":"304 Keller Ave N Amery WI 54001",
    "addr:housenumber":"304",
    "addr:postcode":"54001",
    "addr:street":"Keller Ave N",
    "iso:country":"US",
    "sg:address":"304 Keller Ave N",
    "sg:city":"Amery",
    "sg:classifiers":[
        {
            "category":"Real Estate",
            "subcategory":"Real Estate Agent",
            "type":"Services"
        }
    ],
    "sg:phone":"+1 715 265 7592",
    "sg:postcode":"54001",
    "sg:province":"WI",
    "sg:website":"www.21homesearch.com",
    "wof:name":"Premier Group",
    "wof:placetype":"venue"
},
  "geometry": {"coordinates":[-92.362128,45.314668],"type":"Point"}
}