{
  "type": "Feature",
  "properties": {
    "iso:country":"US",
    "sg:address":"3311 Evergreen Ln",
    "sg:city":"Eau Claire",
    "sg:classifiers":[
        {
            "category":"Professional",
            "subcategory":"Business Services",
            "type":"Services"
        }
    ],
    "sg:phone":"+1 715 835 0789",
    "sg:postcode":"54701",
    "sg:province":"WI",
    "wof:name":"My Receptionist Inc",
    "wof:placetype":"venue"
},
  "geometry": {"coordinates":[-91.50094900000001,44.783804],"type":"Point"}
}