{
  "type": "Feature",
  "properties": {
    "iso:country":"US",
    "sg:address":"2006 N 21st St",
    "sg:city":"Sheboygan",
    "sg:classifiers":[
        {
            "category":"Insurance",
            "subcategory":"Insurance Agent",
            "type":"Services"
        }
    ],
    "sg:phone":"+1 920 803 0337",
    "sg:postcode":"53081",
    "sg:province":"WI",
    "wof:name":"Heitzmann Insurance",
    "wof:placetype":"venue"
},
  "geometry": {"coordinates":[-87.733969,43.766376],"type":"Point"}
}