{
  "type": "Feature",
  "properties": {
    "iso:country":"US",
    "sg:address":"5343 N 118th Ct",
    "sg:city":"Milwaukee",
    "sg:classifiers":[
        {
            "category":"Personal",
            "subcategory":"Psychics & Astrologers",
            "type":"Services"
        }
    ],
    "sg:phone":"+1 414 476 2520",
    "sg:postcode":"53225",
    "sg:province":"WI",
    "sg:tags":[
        "therapist",
        "respiratory"
    ],
    "wof:name":"Ahs Respiratory Inc",
    "wof:placetype":"venue"
},
  "geometry": {"coordinates":[-88.05935599999999,43.114607],"type":"Point"}
}