{
  "type": "Feature",
  "properties": {
    "iso:country":"US",
    "sg:address":"1130 Park Ave",
    "sg:city":"Columbus",
    "sg:classifiers":[
        {
            "category":"Insurance",
            "subcategory":"Insurance Agent",
            "type":"Services"
        }
    ],
    "sg:phone":"+1 920 887 8668",
    "sg:postcode":"53925",
    "sg:province":"WI",
    "wof:name":"Quamme Insurance Services LLC",
    "wof:placetype":"venue"
},
  "geometry": {"coordinates":[-89.024699,43.33055],"type":"Point"}
}