{
  "type": "Feature",
  "properties": {
    "iso:country":"US",
    "sg:address":"4739 Co Rd T",
    "sg:city":"Watertown",
    "sg:classifiers":[
        {
            "category":"Shopping",
            "subcategory":"Clothing, Apparel, & Fashions",
            "type":"Retail Goods"
        }
    ],
    "sg:phone":"+1 920 261 7440",
    "sg:postcode":"53094",
    "sg:province":"WI",
    "sg:tags":[
        "shop",
        "picture",
        "bridal",
        "framing",
        "custom"
    ],
    "wof:name":"Bridal Fair Unlimited",
    "wof:placetype":"venue"
},
  "geometry": {"coordinates":[-88.766985,43.189966],"type":"Point"}
}