{
  "type": "Feature",
  "properties": {
    "iso:country":"US",
    "sg:address":"126 Slazing Rd",
    "sg:city":"Potosi",
    "sg:classifiers":[
        {
            "category":"Building & Trades",
            "subcategory":"Cleaning & Sanitation",
            "type":"Services"
        }
    ],
    "sg:phone":"+1 608 763 2008",
    "sg:postcode":"53820",
    "sg:province":"WI",
    "sg:tags":[
        "maintenance"
    ],
    "wof:name":"New House Exterior Svcs",
    "wof:placetype":"venue"
},
  "geometry": {"coordinates":[-90.70159,42.68215],"type":"Point"}
}