{
  "type": "Feature",
  "properties": {
    "addr:full":"1900 Aviation Rd Waukesha WI 53188",
    "addr:housenumber":"1900",
    "addr:postcode":"53188",
    "addr:street":"Aviation Rd",
    "iso:country":"US",
    "sg:address":"1900 Aviation Rd",
    "sg:city":"Waukesha",
    "sg:classifiers":[
        {
            "category":"Community Center",
            "type":"Public Place"
        }
    ],
    "sg:phone":"+1 262 524 3737",
    "sg:postcode":"53188",
    "sg:province":"WI",
    "sg:tags":[
        "recreation"
    ],
    "sg:website":"http://www.lcmunict.com",
    "wof:name":"Saratoga Softball Complex",
    "wof:placetype":"venue"
},
  "geometry": {"coordinates":[-88.233467,43.026821],"type":"Point"}
}