{
  "type": "Feature",
  "properties": {
    "iso:country":"US",
    "sg:address":"112 Walnut St",
    "sg:city":"Hudson",
    "sg:classifiers":[
        {
            "category":"Sports & Exercise",
            "subcategory":"Gym",
            "type":"Entertainment"
        }
    ],
    "sg:phone":"+1 715 386 3230",
    "sg:postcode":"54016",
    "sg:province":"WI",
    "sg:tags":[
        "club",
        "health",
        "studio",
        "gymnasium"
    ],
    "wof:name":"Embody Health",
    "wof:placetype":"venue"
},
  "geometry": {"coordinates":[-92.75703,44.974797],"type":"Point"}
}