{
  "type": "Feature",
  "properties": {
    "iso:country":"US",
    "sg:address":"2940 US Hwy 51",
    "sg:city":"Janesville",
    "sg:classifiers":[
        {
            "category":"Personal",
            "subcategory":"Tattoo Parlor",
            "type":"Services"
        }
    ],
    "sg:phone":"+1 608 754 7554",
    "sg:postcode":"53546",
    "sg:province":"WI",
    "sg:tags":[
        "tattooing"
    ],
    "wof:name":"Area 51 Tattoo & Piercing",
    "wof:placetype":"venue"
},
  "geometry": {"coordinates":[-89.03118499999999,42.640147],"type":"Point"}
}