{
  "type": "Feature",
  "properties": {
    "iso:country":"US",
    "sg:address":"1830 Tower Ave",
    "sg:city":"Superior",
    "sg:classifiers":[
        {
            "category":"Shopping",
            "subcategory":"Florist",
            "type":"Retail Goods"
        }
    ],
    "sg:phone":"+1 715 394 2255",
    "sg:postcode":"54880",
    "sg:province":"WI",
    "wof:name":"Candy Expressions & Gift Shpp",
    "wof:placetype":"venue"
},
  "geometry": {"coordinates":[-92.10387799999999,46.716216],"type":"Point"}
}