{
  "type": "Feature",
  "properties": {
    "addr:full":"7256 Outlet Rd Crivitz WI 54114",
    "addr:housenumber":"7256",
    "addr:postcode":"54114",
    "addr:street":"Outlet Rd",
    "iso:country":"US",
    "sg:address":"7256 Outlet Rd",
    "sg:city":"Crivitz",
    "sg:classifiers":[
        {
            "category":"Retail",
            "subcategory":"Animal Services",
            "type":"Services"
        }
    ],
    "sg:phone":"+1 715 854 3655",
    "sg:postcode":"54114",
    "sg:province":"WI",
    "wof:name":"Kandis Custom Dog Grooming",
    "wof:placetype":"venue"
},
  "geometry": {"coordinates":[-87.962659,45.223187],"type":"Point"}
}