{
  "type": "Feature",
  "properties": {
    "iso:country":"US",
    "sg:address":"10353 Co Rd P",
    "sg:city":"Iola",
    "sg:classifiers":[
        {
            "category":"Wholesale",
            "subcategory":"Sporting Goods",
            "type":"Manufacturing & Wholesale Goods"
        }
    ],
    "sg:phone":"+1 715 677 3434",
    "sg:postcode":"54945",
    "sg:province":"WI",
    "wof:name":"Cass Genetics",
    "wof:placetype":"venue"
},
  "geometry": {"coordinates":[-89.21360900000001,44.614891],"type":"Point"}
}