{
  "type": "Feature",
  "properties": {
    "iso:country":"US",
    "sg:address":"1712 E Marion St",
    "sg:city":"Milwaukee",
    "sg:classifiers":[
        {
            "category":"Professional",
            "subcategory":"Management & Consulting",
            "type":"Services"
        }
    ],
    "sg:phone":"+1 414 332 0043",
    "sg:postcode":"53211",
    "sg:province":"WI",
    "wof:name":"Left Brain Marketing",
    "wof:placetype":"venue"
},
  "geometry": {"coordinates":[-87.888571,43.094693],"type":"Point"}
}