{
  "type": "Feature",
  "properties": {
    "iso:country":"US",
    "sg:address":"13635 W Crawford Dr",
    "sg:city":"New Berlin",
    "sg:classifiers":[
        {
            "category":"Manufacturing",
            "subcategory":"Wood Products",
            "type":"Manufacturing & Wholesale Goods"
        }
    ],
    "sg:phone":"+1 262 821 9676",
    "sg:postcode":"53151",
    "sg:province":"WI",
    "sg:tags":[
        "mfg"
    ],
    "wof:name":"Northwood Designs",
    "wof:placetype":"venue"
},
  "geometry": {"coordinates":[-88.082665,42.980431],"type":"Point"}
}