{
  "type": "Feature",
  "properties": {
    "iso:country":"US",
    "sg:address":"18252 75th Ave",
    "sg:city":"Chippewa Falls",
    "sg:classifiers":[
        {
            "category":"Building & Trades",
            "subcategory":"Construction",
            "type":"Services"
        }
    ],
    "sg:phone":"+1 715 723 9708",
    "sg:postcode":"54729",
    "sg:province":"WI",
    "sg:tags":[
        "bridges",
        "highway",
        "structure",
        "contractor"
    ],
    "wof:name":"Larson Construction Co",
    "wof:placetype":"venue"
},
  "geometry": {"coordinates":[-91.301488,44.951801],"type":"Point"}
}