{
  "type": "Feature",
  "properties": {
    "iso:country":"US",
    "sg:address":"602 N High Point Rd",
    "sg:city":"Madison",
    "sg:classifiers":[
        {
            "category":"Banks & Credit Unions",
            "subcategory":"Bank",
            "type":"Services"
        }
    ],
    "sg:phone":"+1 608 829 4650",
    "sg:postcode":"53717",
    "sg:province":"WI",
    "sg:tags":[
        "state",
        "commercial"
    ],
    "wof:name":"Bank One",
    "wof:placetype":"venue"
},
  "geometry": {"coordinates":[-89.51871,43.074978],"type":"Point"}
}