{
  "type": "Feature",
  "properties": {
    "iso:country":"US",
    "sg:address":"2341 S Kinnickinnic Ave",
    "sg:city":"Milwaukee",
    "sg:classifiers":[
        {
            "category":"Building & Trades",
            "subcategory":"Construction",
            "type":"Services"
        }
    ],
    "sg:phone":"+1 414 481 5505",
    "sg:postcode":"53207",
    "sg:province":"WI",
    "sg:tags":[
        "contractor",
        "mfg"
    ],
    "wof:name":"Bay View Enterprises Inc",
    "wof:placetype":"venue"
},
  "geometry": {"coordinates":[-87.904133,43.002684],"type":"Point"}
}