{
  "type": "Feature",
  "properties": {
    "iso:country":"US",
    "sg:address":"319 Cedar Ave E",
    "sg:city":"Menomonie",
    "sg:classifiers":[
        {
            "category":"Retail",
            "subcategory":"Portrait Studio",
            "type":"Services"
        }
    ],
    "sg:phone":"+1 715 235 8777",
    "sg:postcode":"54751",
    "sg:province":"WI",
    "sg:tags":[
        "laboratory",
        "photofinishing",
        "photo"
    ],
    "sg:website":"www.hybben.com",
    "wof:name":"Hybben Photography",
    "wof:placetype":"venue"
},
  "geometry": {"coordinates":[-91.928414,44.902007],"type":"Point"}
}