{
  "type": "Feature",
  "properties": {
    "addr:full":"4411 W Wisconsin Ave Appleton WI 54913",
    "addr:housenumber":"4411",
    "addr:postcode":"54913",
    "addr:street":"W Wisconsin Ave",
    "iso:country":"US",
    "sg:address":"4411 W Wisconsin Ave",
    "sg:city":"Appleton",
    "sg:classifiers":[
        {
            "category":"Shopping",
            "subcategory":"Hobbies, Toys, & Games",
            "type":"Retail Goods"
        }
    ],
    "sg:phone":"+1 920 734 6041",
    "sg:postcode":"54913",
    "sg:province":"WI",
    "wof:name":"Foucus Pocus",
    "wof:placetype":"venue"
},
  "geometry": {"coordinates":[-88.472335,44.272997],"type":"Point"}
}