{
  "type": "Feature",
  "properties": {
    "iso:country":"US",
    "sg:address":"2201 Regent St",
    "sg:city":"Madison",
    "sg:classifiers":[
        {
            "category":"Personal",
            "subcategory":"Beauty Salon",
            "type":"Services"
        }
    ],
    "sg:phone":"+1 608 231 1644",
    "sg:postcode":"53726",
    "sg:province":"WI",
    "sg:tags":[
        "shop"
    ],
    "wof:name":"LA Mop Hair Studio",
    "wof:placetype":"venue"
},
  "geometry": {"coordinates":[-89.425587,43.067923],"type":"Point"}
}