{
  "type": "Feature",
  "properties": {
    "iso:country":"US",
    "sg:address":"5125 Co Hwy G",
    "sg:city":"West Bend",
    "sg:classifiers":[
        {
            "category":"Freight",
            "type":"Transportation"
        }
    ],
    "sg:phone":"+1 262 338 4001",
    "sg:postcode":"53095",
    "sg:province":"WI",
    "sg:tags":[
        "warehouse",
        "self",
        "storage"
    ],
    "wof:name":"West Bend Commercial Warehouse",
    "wof:placetype":"venue"
},
  "geometry": {"coordinates":[-88.161148,43.368841],"type":"Point"}
}