{
  "type": "Feature",
  "properties": {
    "iso:country":"US",
    "sg:address":"3200 Plover Rd",
    "sg:city":"Plover",
    "sg:classifiers":[
        {
            "category":"Organizations",
            "subcategory":"Religious Organization",
            "type":"Services"
        }
    ],
    "sg:phone":"+1 715 344 4326",
    "sg:postcode":"54467",
    "sg:province":"WI",
    "sg:tags":[
        "church"
    ],
    "sg:website":"www.stbrons.com",
    "wof:name":"St Bronislava Church",
    "wof:placetype":"venue"
},
  "geometry": {"coordinates":[-89.555179,44.453691],"type":"Point"}
}