{
  "type": "Feature",
  "properties": {
    "iso:country":"US",
    "sg:address":"1543 Co Rd K N",
    "sg:city":"Custer",
    "sg:classifiers":[
        {
            "category":"Building & Trades",
            "subcategory":"Construction",
            "type":"Services"
        }
    ],
    "sg:phone":"+1 715 592 3635",
    "sg:postcode":"54423",
    "sg:province":"WI",
    "sg:tags":[
        "sandblasting"
    ],
    "wof:name":"Tomorrow River Powder Coating",
    "wof:placetype":"venue"
},
  "geometry": {"coordinates":[-89.415491,44.566013],"type":"Point"}
}