{
  "type": "Feature",
  "properties": {
    "iso:country":"US",
    "sg:address":"1023 E Capitol Dr",
    "sg:city":"Hartland",
    "sg:classifiers":[
        {
            "category":"Education",
            "subcategory":"School",
            "type":"Public Place"
        }
    ],
    "sg:phone":"+1 262 367 3617",
    "sg:postcode":"53029",
    "sg:province":"WI",
    "sg:tags":[
        "elementary"
    ],
    "wof:name":"Zion Lutheran School",
    "wof:placetype":"venue"
},
  "geometry": {"coordinates":[-88.332095,43.104488],"type":"Point"}
}