{
  "type": "Feature",
  "properties": {
    "iso:country":"US",
    "sg:address":"1509 Rapids Dr",
    "sg:city":"Racine",
    "sg:classifiers":[
        {
            "category":"Wholesale",
            "subcategory":"Stationery",
            "type":"Manufacturing & Wholesale Goods"
        }
    ],
    "sg:phone":"+1 262 632 5200",
    "sg:postcode":"53404",
    "sg:province":"WI",
    "sg:tags":[
        "business",
        "form",
        "supply"
    ],
    "wof:name":"Midwest Financial Supply",
    "wof:placetype":"venue"
},
  "geometry": {"coordinates":[-87.800246,42.744603],"type":"Point"}
}