{
  "type": "Feature",
  "properties": {
    "iso:country":"US",
    "sg:address":"165 W Washington St",
    "sg:city":"Burlington",
    "sg:classifiers":[
        {
            "category":"Government",
            "subcategory":"Fire Station",
            "type":"Public Place"
        }
    ],
    "sg:phone":"+1 262 763 7842",
    "sg:postcode":"53105",
    "sg:province":"WI",
    "sg:tags":[
        "department",
        "protection"
    ],
    "wof:name":"City Burlington Fire Dept",
    "wof:placetype":"venue"
},
  "geometry": {"coordinates":[-88.279619,42.677822],"type":"Point"}
}