{
  "type": "Feature",
  "properties": {
    "iso:country":"US",
    "sg:address":"807 N 25th St",
    "sg:city":"Wausau",
    "sg:classifiers":[
        {
            "category":"Wholesale",
            "subcategory":"Auto Parts",
            "type":"Manufacturing & Wholesale Goods"
        }
    ],
    "sg:phone":"+1 715 842 3636",
    "sg:postcode":"54403",
    "sg:province":"WI",
    "sg:tags":[
        "retail",
        "truck",
        "trailer"
    ],
    "sg:website":"www.zientaraco.com",
    "wof:name":"Zientara Fleet Equipment Inc",
    "wof:placetype":"venue"
},
  "geometry": {"coordinates":[-89.593488,44.967002],"type":"Point"}
}