{
  "type": "Feature",
  "properties": {
    "iso:country":"US",
    "sg:address":"7555 N Teutonia Ave",
    "sg:city":"Milwaukee",
    "sg:classifiers":[
        {
            "category":"Health Services",
            "subcategory":"Doctor",
            "type":"Services"
        }
    ],
    "sg:phone":"+1 414 351 1130",
    "sg:postcode":"53209",
    "sg:province":"WI",
    "wof:name":"R W Schroeder DDS",
    "wof:placetype":"venue"
},
  "geometry": {"coordinates":[-87.958917,43.155304],"type":"Point"}
}