{
  "type": "Feature",
  "properties": {
    "iso:country":"US",
    "sg:address":"1184 W Main St",
    "sg:city":"Whitewater",
    "sg:classifiers":[
        {
            "category":"Banks & Credit Unions",
            "subcategory":"Bank",
            "type":"Services"
        }
    ],
    "sg:phone":"+1 262 473 5643",
    "sg:postcode":"53190",
    "sg:province":"WI",
    "wof:name":"Norwest Bank WIS NA",
    "wof:placetype":"venue"
},
  "geometry": {"coordinates":[-88.751802,42.834904],"type":"Point"}
}