{
  "type": "Feature",
  "properties": {
    "addr:full":"1475 N Lake St Neenah WI 54956",
    "addr:housenumber":"1475",
    "addr:postcode":"54956",
    "addr:street":"N Lake St",
    "iso:country":"US",
    "sg:address":"1475 N Lake St",
    "sg:city":"Neenah",
    "sg:classifiers":[
        {
            "category":"Professional",
            "subcategory":"Engineering",
            "type":"Services"
        }
    ],
    "sg:phone":"+1 920 725 1127",
    "sg:postcode":"54956",
    "sg:province":"WI",
    "sg:tags":[
        "engineer"
    ],
    "wof:name":"CH2M Hill",
    "wof:placetype":"venue"
},
  "geometry": {"coordinates":[-88.46990599999999,44.21645],"type":"Point"}
}