{
  "type": "Feature",
  "properties": {
    "iso:country":"US",
    "sg:address":"1926 Froelich Rd",
    "sg:city":"Sullivan",
    "sg:classifiers":[
        {
            "category":"Farming",
            "subcategory":"Dairy Farm",
            "type":"Manufacturing & Wholesale Goods"
        }
    ],
    "sg:phone":"+1 262 593 8496",
    "sg:postcode":"53178",
    "sg:province":"WI",
    "wof:name":"Roman Holiday Dairy",
    "wof:placetype":"venue"
},
  "geometry": {"coordinates":[-88.634654,42.995564],"type":"Point"}
}