{
  "type": "Feature",
  "properties": {
    "iso:country":"US",
    "sg:address":"616 9th St",
    "sg:city":"Prairie Farm",
    "sg:classifiers":[
        {
            "category":"Farming",
            "subcategory":"Dairy Farm",
            "type":"Manufacturing & Wholesale Goods"
        }
    ],
    "sg:phone":"+1 715 455 1858",
    "sg:postcode":"54762",
    "sg:province":"WI",
    "wof:name":"Russell Bruder",
    "wof:placetype":"venue"
},
  "geometry": {"coordinates":[-91.972507,45.301643],"type":"Point"}
}