{
  "type": "Feature",
  "properties": {
    "iso:country":"US",
    "sg:address":"3188 London Rd",
    "sg:city":"Eau Claire",
    "sg:classifiers":[
        {
            "category":"Shopping",
            "subcategory":"Hobbies, Toys, & Games",
            "type":"Retail Goods"
        }
    ],
    "sg:phone":"+1 715 838 7277",
    "sg:postcode":"54701",
    "sg:province":"WI",
    "sg:tags":[
        "supply"
    ],
    "sg:website":"www.foygames.com",
    "wof:name":"Tabletop Games",
    "wof:placetype":"venue"
},
  "geometry": {"coordinates":[-91.46324300000001,44.788205],"type":"Point"}
}