{
  "type": "Feature",
  "properties": {
    "addr:full":"1914 W Co Rd Y Oshkosh WI 54904",
    "addr:housenumber":"1914",
    "addr:postcode":"54904",
    "addr:street":"W Co Rd Y",
    "iso:country":"US",
    "sg:address":"1914 W Co Rd Y",
    "sg:city":"Oshkosh",
    "sg:classifiers":[
        {
            "category":"Manufacturing",
            "subcategory":"Tools & Machinery",
            "type":"Manufacturing & Wholesale Goods"
        }
    ],
    "sg:phone":"+1 920 233 3556",
    "sg:postcode":"54904",
    "sg:province":"WI",
    "sg:tags":[
        "equipment",
        "refrigeration"
    ],
    "wof:name":"Jim's Refrigeration & Heating",
    "wof:placetype":"venue"
},
  "geometry": {"coordinates":[-88.578349,44.082754],"type":"Point"}
}