{
  "type": "Feature",
  "properties": {
    "iso:country":"US",
    "sg:address":"30858 Co Hwy I",
    "sg:city":"Cazenovia",
    "sg:classifiers":[
        {
            "category":"Bars & Pubs",
            "type":"Food & Drink"
        }
    ],
    "sg:phone":"+1 608 983 2756",
    "sg:postcode":"53924",
    "sg:province":"WI",
    "sg:tags":[
        "drinking"
    ],
    "wof:name":"Bunker Hill Saloon Inc",
    "wof:placetype":"venue"
},
  "geometry": {"coordinates":[-90.2474,43.496596],"type":"Point"}
}