{
  "type": "Feature",
  "properties": {
    "iso:country":"US",
    "sg:address":"1600 Co Rd A",
    "sg:city":"Mindoro",
    "sg:classifiers":[
        {
            "category":"Manufacturing",
            "subcategory":"Toys & Sporting Goods",
            "type":"Manufacturing & Wholesale Goods"
        }
    ],
    "sg:phone":"+1 608 857 9990",
    "sg:postcode":"54644",
    "sg:province":"WI",
    "sg:tags":[
        "mfg"
    ],
    "wof:name":"Wyndwalkr",
    "wof:placetype":"venue"
},
  "geometry": {"coordinates":[-90.997585,44.052019],"type":"Point"}
}