{
  "type": "Feature",
  "properties": {
    "iso:country":"US",
    "sg:address":"5328 S 27th St",
    "sg:city":"Milwaukee",
    "sg:classifiers":[
        {
            "category":"Utilities",
            "subcategory":"Mobile Phone",
            "type":"Services"
        }
    ],
    "sg:phone":"+1 414 281 0918",
    "sg:postcode":"53221",
    "sg:province":"WI",
    "sg:tags":[
        "telephone",
        "cellular"
    ],
    "wof:name":"Wireless",
    "wof:placetype":"venue"
},
  "geometry": {"coordinates":[-87.948891,42.948364],"type":"Point"}
}