{
  "type": "Feature",
  "properties": {
    "iso:country":"US",
    "sg:address":"21952 Co Hwy S R",
    "sg:city":"Richland Center",
    "sg:classifiers":[
        {
            "category":"Building & Trades",
            "subcategory":"Construction",
            "type":"Services"
        }
    ],
    "sg:phone":"+1 608 647 5007",
    "sg:postcode":"53581",
    "sg:province":"WI",
    "sg:tags":[
        "woodworker"
    ],
    "wof:name":"Pine River Woodcraft",
    "wof:placetype":"venue"
},
  "geometry": {"coordinates":[-90.37392699999999,43.380855],"type":"Point"}
}