{
  "type": "Feature",
  "properties": {
    "iso:country":"US",
    "sg:address":"9625 Darboy Dr",
    "sg:city":"Appleton",
    "sg:classifiers":[
        {
            "category":"Professional",
            "subcategory":"Business Services",
            "type":"Services"
        }
    ],
    "sg:phone":"+1 920 735 9069",
    "sg:postcode":"54915",
    "sg:province":"WI",
    "wof:name":"Equitable Reserve Assoc",
    "wof:placetype":"venue"
},
  "geometry": {"coordinates":[-88.329885,44.240428],"type":"Point"}
}