{
  "type": "Feature",
  "properties": {
    "iso:country":"US",
    "sg:address":"2441 100th Ave",
    "sg:city":"Kenosha",
    "sg:phone":"+1 262 859 3045",
    "sg:postcode":"53144",
    "sg:province":"WI",
    "sg:tags":[
        "farm",
        "wheat",
        "soybean"
    ],
    "wof:name":"Gitzlaff Farms Inc",
    "wof:placetype":"venue"
},
  "geometry": {"coordinates":[-87.92999500000001,42.618968],"type":"Point"}
}