{
  "type": "Feature",
  "properties": {
    "iso:country":"US",
    "sg:address":"3033 Prill Rd",
    "sg:city":"Eau Claire",
    "sg:classifiers":[
        {
            "category":"Farming",
            "subcategory":"Nursery",
            "type":"Manufacturing & Wholesale Goods"
        }
    ],
    "sg:phone":"+1 715 839 8448",
    "sg:postcode":"54701",
    "sg:province":"WI",
    "sg:tags":[
        "ornamental",
        "greenhouse"
    ],
    "wof:name":"Chippewa Valley Growers Inc",
    "wof:placetype":"venue"
},
  "geometry": {"coordinates":[-91.43159300000001,44.778423],"type":"Point"}
}