{
  "type": "Feature",
  "properties": {
    "iso:country":"US",
    "sg:address":"11520 N Port Washington Rd R",
    "sg:city":"Mequon",
    "sg:classifiers":[
        {
            "category":"Professional",
            "subcategory":"Lawyer & Legal Services",
            "type":"Services"
        }
    ],
    "sg:phone":"+1 262 240 2256",
    "sg:postcode":"53092",
    "sg:province":"WI",
    "sg:tags":[
        "attorney",
        "criminal",
        "law"
    ],
    "wof:name":"Luck & Rosenthal",
    "wof:placetype":"venue"
},
  "geometry": {"coordinates":[-87.924097,43.226845],"type":"Point"}
}