{
  "type": "Feature",
  "properties": {
    "addr:full":"7075 W Beckett Ave Milwaukee WI 53216",
    "addr:housenumber":"7075",
    "addr:postcode":"53216",
    "addr:street":"W Beckett Ave",
    "iso:country":"US",
    "sg:address":"7075 W Beckett Ave",
    "sg:city":"Milwaukee",
    "sg:classifiers":[
        {
            "category":"Health Services",
            "subcategory":"Chiropractor",
            "type":"Services"
        }
    ],
    "sg:phone":"+1 414 461 2727",
    "sg:postcode":"53216",
    "sg:province":"WI",
    "sg:tags":[
        "chiropractic"
    ],
    "wof:name":"Rohloff, Gene C",
    "wof:placetype":"venue"
},
  "geometry": {"coordinates":[-88.00034599999999,43.087179],"type":"Point"}
}