{
  "type": "Feature",
  "properties": {
    "iso:country":"US",
    "sg:address":"2220 Stonebridge Rd",
    "sg:city":"West Bend",
    "sg:classifiers":[
        {
            "category":"Wholesale",
            "subcategory":"Non-durable Goods",
            "type":"Manufacturing & Wholesale Goods"
        }
    ],
    "sg:phone":"+1 262 335 2677",
    "sg:postcode":"53095",
    "sg:province":"WI",
    "sg:tags":[
        "advertising"
    ],
    "wof:name":"CMS Motivational Group",
    "wof:placetype":"venue"
},
  "geometry": {"coordinates":[-88.170143,43.401144],"type":"Point"}
}