{
  "type": "Feature",
  "properties": {
    "iso:country":"US",
    "sg:address":"105 S Main St",
    "sg:city":"Lodi",
    "sg:classifiers":[
        {
            "category":"Personal",
            "subcategory":"Beauty Salon",
            "type":"Services"
        }
    ],
    "sg:phone":"+1 608 592 3055",
    "sg:postcode":"53555",
    "sg:province":"WI",
    "sg:tags":[
        "shop"
    ],
    "wof:name":"Country Clipper",
    "wof:placetype":"venue"
},
  "geometry": {"coordinates":[-89.526589,43.313943],"type":"Point"}
}