{
  "type": "Feature",
  "properties": {
    "addr:full":"2920 Superior Ave Sheboygan WI 53081",
    "addr:housenumber":"2920",
    "addr:postcode":"53081",
    "addr:street":"Superior Ave",
    "iso:country":"US",
    "sg:address":"2920 Superior Ave",
    "sg:city":"Sheboygan",
    "sg:classifiers":[
        {
            "category":"Health Services",
            "subcategory":"Doctor",
            "type":"Services"
        }
    ],
    "sg:phone":"+1 920 458 3791",
    "sg:postcode":"53081",
    "sg:province":"WI",
    "wof:name":"Orthopaedic Sheboygan Assoc SC",
    "wof:placetype":"venue"
},
  "geometry": {"coordinates":[-87.74570199999999,43.761207],"type":"Point"}
}