{
  "type": "Feature",
  "properties": {
    "iso:country":"US",
    "sg:address":"1649 7th St",
    "sg:city":"Green Bay",
    "sg:classifiers":[
        {
            "category":"Social Services",
            "subcategory":"Child Care",
            "type":"Services"
        }
    ],
    "sg:phone":"+1 920 499 3344",
    "sg:postcode":"54304",
    "sg:province":"WI",
    "wof:name":"Learning Years",
    "wof:placetype":"venue"
},
  "geometry": {"coordinates":[-88.070572,44.519415],"type":"Point"}
}