{
  "type": "Feature",
  "properties": {
    "iso:country":"US",
    "sg:address":"1457 Mansion Dr",
    "sg:city":"Monroe",
    "sg:classifiers":[
        {
            "category":"Retail",
            "subcategory":"Funeral Services",
            "type":"Services"
        }
    ],
    "sg:phone":"+1 608 325 1286",
    "sg:postcode":"53566",
    "sg:province":"WI",
    "sg:tags":[
        "crematory"
    ],
    "wof:name":"Southern Wi Cremation Svc",
    "wof:placetype":"venue"
},
  "geometry": {"coordinates":[-89.636719,42.611924],"type":"Point"}
}