{
  "type": "Feature",
  "properties": {
    "iso:country":"US",
    "sg:address":"3300 E Forest St",
    "sg:city":"Appleton",
    "sg:classifiers":[
        {
            "category":"Manufacturing",
            "subcategory":"Printing",
            "type":"Manufacturing & Wholesale Goods"
        }
    ],
    "sg:phone":"+1 920 733 9007",
    "sg:postcode":"54915",
    "sg:province":"WI",
    "sg:tags":[
        "miscellaneous",
        "publishing"
    ],
    "wof:name":"Proquest Company",
    "wof:placetype":"venue"
},
  "geometry": {"coordinates":[-88.359122,44.255627],"type":"Point"}
}