{
  "type": "Feature",
  "properties": {
    "iso:country":"US",
    "sg:address":"4930 S 33rd St",
    "sg:city":"Milwaukee",
    "sg:classifiers":[
        {
            "category":"Travel",
            "subcategory":"Travel Agent",
            "type":"Entertainment"
        }
    ],
    "sg:phone":"+1 414 281 0624",
    "sg:postcode":"53221",
    "sg:province":"WI",
    "sg:tags":[
        "agency",
        "bureau"
    ],
    "wof:name":"David Mooney",
    "wof:placetype":"venue"
},
  "geometry": {"coordinates":[-87.955353,42.95486],"type":"Point"}
}