{
  "type": "Feature",
  "properties": {
    "iso:country":"US",
    "sg:address":"229 Oak St",
    "sg:city":"Madison",
    "sg:classifiers":[
        {
            "category":"Manufacturing",
            "subcategory":"Glass & Minerals",
            "type":"Manufacturing & Wholesale Goods"
        }
    ],
    "sg:phone":"+1 608 243 0274",
    "sg:postcode":"53704",
    "sg:province":"WI",
    "sg:tags":[
        "ready",
        "concrete",
        "mfg"
    ],
    "wof:name":"Ready Graphics",
    "wof:placetype":"venue"
},
  "geometry": {"coordinates":[-89.34320200000001,43.101933],"type":"Point"}
}