{
  "type": "Feature",
  "properties": {
    "iso:country":"US",
    "sg:address":"51 W Walnut St",
    "sg:city":"Sturgeon Bay",
    "sg:classifiers":[
        {
            "category":"Professional",
            "type":"Services"
        }
    ],
    "sg:phone":"+1 920 743 3030",
    "sg:postcode":"54235",
    "sg:province":"WI",
    "wof:name":"Decor Services",
    "wof:placetype":"venue"
},
  "geometry": {"coordinates":[-87.387171,44.820679],"type":"Point"}
}