{
  "type": "Feature",
  "properties": {
    "iso:country":"US",
    "sg:address":"25140 75th St",
    "sg:city":"Salem",
    "sg:classifiers":[
        {
            "category":"Insurance",
            "subcategory":"Insurance Agent",
            "type":"Services"
        }
    ],
    "sg:phone":"+1 262 843 4221",
    "sg:postcode":"53168",
    "sg:province":"WI",
    "wof:name":"AFLAC",
    "wof:placetype":"venue"
},
  "geometry": {"coordinates":[-88.11369000000001,42.568357],"type":"Point"}
}