{
  "type": "Feature",
  "properties": {
    "iso:country":"US",
    "sg:address":"401 Wisconsin Ave",
    "sg:city":"Madison",
    "sg:classifiers":[
        {
            "category":"Professional",
            "subcategory":"Engineering",
            "type":"Services"
        }
    ],
    "sg:phone":"+1 608 229 2270",
    "sg:postcode":"53703",
    "sg:province":"WI",
    "sg:tags":[
        "engineer"
    ],
    "wof:name":"El Paso Corp",
    "wof:placetype":"venue"
},
  "geometry": {"coordinates":[-89.388691,43.078151],"type":"Point"}
}