{
  "type": "Feature",
  "properties": {
    "addr:full":"1837 Hall Rd Woodruff WI 54568",
    "addr:housenumber":"1837",
    "addr:postcode":"54568",
    "addr:street":"Hall Rd",
    "iso:country":"US",
    "sg:address":"1837 Hall Rd",
    "sg:city":"Woodruff",
    "sg:classifiers":[
        {
            "category":"Professional",
            "subcategory":"Business Services",
            "type":"Services"
        }
    ],
    "sg:phone":"+1 715 356 4415",
    "sg:postcode":"54568",
    "sg:province":"WI",
    "sg:tags":[
        "embroidery"
    ],
    "wof:name":"Helterhoff's Inc",
    "wof:placetype":"venue"
},
  "geometry": {"coordinates":[-89.73755,45.941892],"type":"Point"}
}