{
  "type": "Feature",
  "properties": {
    "addr:full":"104 E Washington St Tomah WI 54660",
    "addr:housenumber":"104",
    "addr:postcode":"54660",
    "addr:street":"E Washington St",
    "iso:country":"US",
    "sg:address":"104 E Washington St",
    "sg:city":"Tomah",
    "sg:classifiers":[
        {
            "category":"Wholesale",
            "subcategory":"Machinery & Supplies",
            "type":"Manufacturing & Wholesale Goods"
        }
    ],
    "sg:phone":"+1 608 374 2030",
    "sg:postcode":"54660",
    "sg:province":"WI",
    "sg:tags":[
        "construction",
        "fastener",
        "industrial",
        "suppl",
        "threaded"
    ],
    "wof:name":"Fastenal Company",
    "wof:placetype":"venue"
},
  "geometry": {"coordinates":[-90.504604,43.985461],"type":"Point"}
}