{
  "type": "Feature",
  "properties": {
    "iso:country":"US",
    "sg:address":"152 Bogert St",
    "sg:city":"Beaver Dam",
    "sg:classifiers":[
        {
            "category":"Building & Trades",
            "subcategory":"Landscaping Services",
            "type":"Services"
        }
    ],
    "sg:phone":"+1 920 887 9855",
    "sg:postcode":"53916",
    "sg:province":"WI",
    "sg:tags":[
        "lawn",
        "maintenance",
        "grounds"
    ],
    "wof:name":"Larry's Lawn Care",
    "wof:placetype":"venue"
},
  "geometry": {"coordinates":[-88.82767200000001,43.463091],"type":"Point"}
}