{
  "type": "Feature",
  "properties": {
    "iso:country":"US",
    "sg:address":"4517 W Burnham St",
    "sg:city":"Milwaukee",
    "sg:classifiers":[
        {
            "category":"Government",
            "subcategory":"Office",
            "type":"Public Place"
        }
    ],
    "sg:phone":"+1 414 645 6238",
    "sg:postcode":"53219",
    "sg:province":"WI",
    "sg:tags":[
        "transportation"
    ],
    "wof:name":"Department Of Public Works",
    "wof:placetype":"venue"
},
  "geometry": {"coordinates":[-87.97036,43.01008],"type":"Point"}
}