{
  "type": "Feature",
  "properties": {
    "addr:full":"25 8th St Clintonville WI 54929",
    "addr:housenumber":"25",
    "addr:postcode":"54929",
    "addr:street":"8Th St",
    "iso:country":"US",
    "sg:address":"25 8th St",
    "sg:city":"Clintonville",
    "sg:classifiers":[
        {
            "category":"Education",
            "subcategory":"School",
            "type":"Public Place"
        }
    ],
    "sg:phone":"+1 715 823 7245",
    "sg:postcode":"54929",
    "sg:province":"WI",
    "wof:name":"Clintonville Jr High School",
    "wof:placetype":"venue"
},
  "geometry": {"coordinates":[-88.762095,44.620152],"type":"Point"}
}