{
  "type": "Feature",
  "properties": {
    "addr:full":"700 6th St Racine WI 53403",
    "addr:housenumber":"700",
    "addr:postcode":"53403",
    "addr:street":"6Th St",
    "iso:country":"US",
    "sg:address":"700 6th St",
    "sg:city":"Racine",
    "sg:classifiers":[
        {
            "category":"Museum",
            "type":"Entertainment"
        }
    ],
    "sg:phone":"+1 262 637 7395",
    "sg:postcode":"53403",
    "sg:province":"WI",
    "sg:tags":[
        "gallery"
    ],
    "wof:name":"Racine Firebells",
    "wof:placetype":"venue"
},
  "geometry": {"coordinates":[-87.78939699999999,42.72615],"type":"Point"}
}