{
  "type": "Feature",
  "properties": {
    "addr:full":"3710 S Beaumont Ave Kansasville WI 53139",
    "addr:housenumber":"3710",
    "addr:postcode":"53139",
    "addr:street":"S Beaumont Ave",
    "iso:country":"US",
    "sg:address":"3710 S Beaumont Ave",
    "sg:city":"Kansasville",
    "sg:classifiers":[
        {
            "category":"Professional",
            "subcategory":"Accounting & Tax Preparation",
            "type":"Services"
        }
    ],
    "sg:phone":"+1 262 878 0108",
    "sg:postcode":"53139",
    "sg:province":"WI",
    "wof:name":"James W Carlson",
    "wof:placetype":"venue"
},
  "geometry": {"coordinates":[-88.110968,42.699885],"type":"Point"}
}