{
  "type": "Feature",
  "properties": {
    "addr:full":"5431 N 131st St Butler WI 53007",
    "addr:housenumber":"5431",
    "addr:postcode":"53007",
    "addr:street":"N 131St St",
    "iso:country":"US",
    "sg:address":"5431 N 131st St",
    "sg:city":"Butler",
    "sg:classifiers":[
        {
            "category":"Professional",
            "subcategory":"Advertising",
            "type":"Services"
        }
    ],
    "sg:phone":"+1 262 373 1630",
    "sg:postcode":"53007",
    "sg:province":"WI",
    "sg:tags":[
        "distribution"
    ],
    "wof:name":"Polyak Distributors",
    "wof:placetype":"venue"
},
  "geometry": {"coordinates":[-88.074155,43.116905],"type":"Point"}
}