{
  "type": "Feature",
  "properties": {
    "addr:full":"6776 Nehrbass Rd Athens WI 54411",
    "addr:housenumber":"6776",
    "addr:postcode":"54411",
    "addr:street":"Nehrbass Rd",
    "iso:country":"US",
    "sg:address":"6776 Nehrbass Rd",
    "sg:city":"Athens",
    "sg:classifiers":[
        {
            "category":"Building & Trades",
            "subcategory":"Construction",
            "type":"Services"
        }
    ],
    "sg:phone":"+1 715 257 7876",
    "sg:postcode":"54411",
    "sg:province":"WI",
    "sg:tags":[
        "contractor"
    ],
    "wof:name":"A-Ok",
    "wof:placetype":"venue"
},
  "geometry": {"coordinates":[-90.045464,45.082397],"type":"Point"}
}