{
  "type": "Feature",
  "properties": {
    "iso:country":"US",
    "sg:address":"320 Oak Ave",
    "sg:city":"Menomonie",
    "sg:classifiers":[
        {
            "category":"Travel",
            "subcategory":"Hotels & Motels",
            "type":"Entertainment"
        }
    ],
    "sg:phone":"+1 715 235 5664",
    "sg:postcode":"54751",
    "sg:province":"WI",
    "wof:name":"Country Inn & Suites",
    "wof:placetype":"venue"
},
  "geometry": {"coordinates":[-91.92879600000001,44.90296],"type":"Point"}
}