{
  "type": "Feature",
  "properties": {
    "iso:country":"US",
    "sg:address":"8320 Co Rd Es",
    "sg:city":"East Troy",
    "sg:classifiers":[
        {
            "category":"Autos & Motor Vehicles",
            "subcategory":"Fuel & Gas Station",
            "type":"Retail Goods"
        }
    ],
    "sg:phone":"+1 262 642 5744",
    "sg:postcode":"53120",
    "sg:province":"WI",
    "sg:tags":[
        "oil"
    ],
    "wof:name":"Troy Amoco",
    "wof:placetype":"venue"
},
  "geometry": {"coordinates":[-88.37677,42.804891],"type":"Point"}
}