{
  "type": "Feature",
  "properties": {
    "addr:full":"7806 Betsy Ln Verona WI 53593",
    "addr:housenumber":"7806",
    "addr:postcode":"53593",
    "addr:street":"Betsy Ln",
    "iso:country":"US",
    "sg:address":"7806 Betsy Ln",
    "sg:city":"Verona",
    "sg:classifiers":[
        {
            "category":"Health Services",
            "subcategory":"Clinic",
            "type":"Services"
        }
    ],
    "sg:phone":"+1 608 833 1713",
    "sg:postcode":"53593",
    "sg:province":"WI",
    "sg:tags":[
        "management"
    ],
    "wof:name":"Oak Park Place",
    "wof:placetype":"venue"
},
  "geometry": {"coordinates":[-89.59307699999999,43.063123],"type":"Point"}
}