{
  "type": "Feature",
  "properties": {
    "iso:country":"US",
    "sg:address":"213 E Madison St",
    "sg:city":"Dodgeville",
    "sg:classifiers":[
        {
            "category":"Building & Trades",
            "subcategory":"Electrical",
            "type":"Services"
        }
    ],
    "sg:phone":"+1 608 935 2564",
    "sg:postcode":"53533",
    "sg:province":"WI",
    "sg:tags":[
        "electrical",
        "contractor"
    ],
    "wof:name":"Johanning Electric",
    "wof:placetype":"venue"
},
  "geometry": {"coordinates":[-90.12857200000001,42.968257],"type":"Point"}
}