{
  "type": "Feature",
  "properties": {
    "iso:country":"US",
    "sg:address":"10944 Wauwatosa Rd",
    "sg:city":"Mequon",
    "sg:classifiers":[
        {
            "category":"Building & Trades",
            "subcategory":"Construction",
            "type":"Services"
        }
    ],
    "sg:phone":"+1 262 242 7550",
    "sg:postcode":"53097",
    "sg:province":"WI",
    "sg:tags":[
        "carpenter",
        "carpentry"
    ],
    "wof:name":"Kugel Custom Carpentry Inc",
    "wof:placetype":"venue"
},
  "geometry": {"coordinates":[-88.00358300000001,43.21473],"type":"Point"}
}