{
  "type": "Feature",
  "properties": {
    "iso:country":"US",
    "sg:address":"325 S Eagle St",
    "sg:city":"Oshkosh",
    "sg:classifiers":[
        {
            "category":"Education",
            "subcategory":"School",
            "type":"Public Place"
        }
    ],
    "sg:phone":"+1 920 424 0320",
    "sg:postcode":"54902",
    "sg:province":"WI",
    "sg:tags":[
        "middle"
    ],
    "wof:name":"Perry Tipler Middle",
    "wof:placetype":"venue"
},
  "geometry": {"coordinates":[-88.57314,44.014545],"type":"Point"}
}