{
  "type": "Feature",
  "properties": {
    "iso:country":"US",
    "sg:address":"10872 US Hwy 151",
    "sg:city":"Malone",
    "sg:classifiers":[
        {
            "category":"Restaurant",
            "type":"Food & Drink"
        }
    ],
    "sg:phone":"+1 920 795 4574",
    "sg:postcode":"53049",
    "sg:province":"WI",
    "wof:name":"Cedar Lodge Supper Club",
    "wof:placetype":"venue"
},
  "geometry": {"coordinates":[-88.302994,43.937704],"type":"Point"}
}