{
  "type": "Feature",
  "properties": {
    "addr:full":"749 Edison Ave Janesville WI 53546",
    "addr:housenumber":"749",
    "addr:postcode":"53546",
    "addr:street":"Edison Ave",
    "iso:country":"US",
    "sg:address":"749 Edison Ave",
    "sg:city":"Janesville",
    "sg:classifiers":[
        {
            "category":"Building & Trades",
            "subcategory":"Construction",
            "type":"Services"
        }
    ],
    "sg:phone":"+1 608 754 3438",
    "sg:postcode":"53546",
    "sg:province":"WI",
    "sg:tags":[
        "house",
        "c",
        "hanging",
        "contractor"
    ],
    "wof:name":"Anthony S Painting",
    "wof:placetype":"venue"
},
  "geometry": {"coordinates":[-89.026009,42.647769],"type":"Point"}
}