{
  "type": "Feature",
  "properties": {
    "iso:country":"US",
    "sg:address":"1617 N Stoughton Rd",
    "sg:city":"Madison",
    "sg:classifiers":[
        {
            "category":"Professional",
            "subcategory":"Management & Consulting",
            "type":"Services"
        }
    ],
    "sg:phone":"+1 608 244 8677",
    "sg:postcode":"53704",
    "sg:province":"WI",
    "sg:tags":[
        "food",
        "liquor"
    ],
    "wof:name":"Amigos Mxcan S Amercn Rest Bar",
    "wof:placetype":"venue"
},
  "geometry": {"coordinates":[-89.324835,43.118516],"type":"Point"}
}