{
  "type": "Feature",
  "properties": {
    "addr:full":"128 S Broadway Green Bay WI 54303",
    "addr:housenumber":"128",
    "addr:postcode":"54303",
    "addr:street":"S Broadway",
    "iso:country":"US",
    "sg:address":"128 S Broadway",
    "sg:city":"Green Bay",
    "sg:classifiers":[
        {
            "category":"Bars & Pubs",
            "type":"Food & Drink"
        }
    ],
    "sg:phone":"+1 920 433 0898",
    "sg:postcode":"54303",
    "sg:province":"WI",
    "sg:tags":[
        "drinking"
    ],
    "wof:name":"Connies Bowery",
    "wof:placetype":"venue"
},
  "geometry": {"coordinates":[-88.022471,44.515571],"type":"Point"}
}