{
  "type": "Feature",
  "properties": {
    "iso:country":"US",
    "sg:address":"7219 Sherry Ln",
    "sg:city":"Waterford",
    "sg:classifiers":[
        {
            "category":"Professional",
            "type":"Services"
        }
    ],
    "sg:phone":"+1 262 662 3198",
    "sg:postcode":"53185",
    "sg:province":"WI",
    "wof:name":"Shawn Tomas",
    "wof:placetype":"venue"
},
  "geometry": {"coordinates":[-88.199133,42.817781],"type":"Point"}
}