{
  "type": "Feature",
  "properties": {
    "addr:full":"1307 W Packard St Appleton WI 54914",
    "addr:housenumber":"1307",
    "addr:postcode":"54914",
    "addr:street":"W Packard St",
    "iso:country":"US",
    "sg:address":"1307 W Packard St",
    "sg:city":"Appleton",
    "sg:classifiers":[
        {
            "category":"Health Services",
            "subcategory":"Chiropractor",
            "type":"Services"
        }
    ],
    "sg:phone":"+1 920 739 4229",
    "sg:postcode":"54914",
    "sg:province":"WI",
    "wof:name":"Christopher E Matt Dr",
    "wof:placetype":"venue"
},
  "geometry": {"coordinates":[-88.428152,44.265745],"type":"Point"}
}