{
  "type": "Feature",
  "properties": {
    "iso:country":"US",
    "sg:address":"603 Hollister Ave",
    "sg:city":"Tomah",
    "sg:classifiers":[
        {
            "category":"Building & Trades",
            "subcategory":"Construction",
            "type":"Services"
        }
    ],
    "sg:phone":"+1 608 374 2811",
    "sg:postcode":"54660",
    "sg:province":"WI",
    "sg:tags":[
        "carpenter"
    ],
    "wof:name":"RAN Contruction",
    "wof:placetype":"venue"
},
  "geometry": {"coordinates":[-90.509216,43.981233],"type":"Point"}
}