{
  "type": "Feature",
  "properties": {
    "addr:full":"2410 Daniels St Madison WI 53718",
    "addr:housenumber":"2410",
    "addr:postcode":"53718",
    "addr:street":"Daniels St",
    "iso:country":"US",
    "sg:address":"2410 Daniels St",
    "sg:city":"Madison",
    "sg:classifiers":[
        {
            "category":"Building & Trades",
            "subcategory":"Construction",
            "type":"Services"
        }
    ],
    "sg:phone":"+1 608 223 0153",
    "sg:postcode":"53718",
    "sg:province":"WI",
    "sg:tags":[
        "resurfacing",
        "laying",
        "refinishing",
        "floor"
    ],
    "wof:name":"Traditional Wood Floors",
    "wof:placetype":"venue"
},
  "geometry": {"coordinates":[-89.297718,43.064793],"type":"Point"}
}