{
  "type": "Feature",
  "properties": {
    "iso:country":"US",
    "sg:address":"104 Co Rd Cb",
    "sg:city":"Neenah",
    "sg:classifiers":[
        {
            "category":"Social Services",
            "subcategory":"Child Care",
            "type":"Services"
        }
    ],
    "sg:phone":"+1 920 727 1540",
    "sg:postcode":"54956",
    "sg:province":"WI",
    "sg:tags":[
        "day"
    ],
    "wof:name":"A Childs Imagination",
    "wof:placetype":"venue"
},
  "geometry": {"coordinates":[-88.505025,44.172799],"type":"Point"}
}