{
  "type": "Feature",
  "properties": {
    "iso:country":"US",
    "sg:address":"2759 State Rd 67",
    "sg:city":"Delavan",
    "sg:classifiers":[
        {
            "category":"Manufacturing",
            "subcategory":"Printing",
            "type":"Manufacturing & Wholesale Goods"
        }
    ],
    "sg:phone":"+1 262 245 1877",
    "sg:postcode":"53115",
    "sg:province":"WI",
    "sg:tags":[
        "newspaper"
    ],
    "wof:name":"Beacon",
    "wof:placetype":"venue"
},
  "geometry": {"coordinates":[-88.54094000000001,42.592387],"type":"Point"}
}