{
  "type": "Feature",
  "properties": {
    "addr:full":"805 Cedar St Hartford WI 53027",
    "addr:housenumber":"805",
    "addr:postcode":"53027",
    "addr:street":"Cedar St",
    "iso:country":"US",
    "sg:address":"805 Cedar St",
    "sg:city":"Hartford",
    "sg:classifiers":[
        {
            "category":"Education",
            "subcategory":"School",
            "type":"Public Place"
        }
    ],
    "sg:phone":"+1 262 673 8950",
    "sg:postcode":"53027",
    "sg:province":"WI",
    "sg:tags":[
        "district"
    ],
    "wof:name":"Hartford Union High School Dst",
    "wof:placetype":"venue"
},
  "geometry": {"coordinates":[-88.38533700000001,43.307808],"type":"Point"}
}