{
  "type": "Feature",
  "properties": {
    "addr:full":"778 Albion Rd Edgerton WI 53534",
    "addr:housenumber":"778",
    "addr:postcode":"53534",
    "addr:street":"Albion Rd",
    "iso:country":"US",
    "sg:address":"778 Albion Rd",
    "sg:city":"Edgerton",
    "sg:phone":"+1 608 884 3684",
    "sg:postcode":"53534",
    "sg:province":"WI",
    "sg:tags":[
        "farm",
        "tobacco"
    ],
    "wof:name":"Melvin Becker",
    "wof:placetype":"venue"
},
  "geometry": {"coordinates":[-89.07172300000001,42.883168],"type":"Point"}
}