{
  "type": "Feature",
  "properties": {
    "iso:country":"US",
    "sg:address":"101 W 8th St",
    "sg:city":"Monroe",
    "sg:classifiers":[
        {
            "category":"Autos & Motor Vehicles",
            "subcategory":"Automobile Sales",
            "type":"Retail Goods"
        },
        {
            "category":"Retail",
            "subcategory":"Auto Repair",
            "type":"Services"
        }
    ],
    "sg:phone":"+1 608 328 2100",
    "sg:postcode":"53566",
    "sg:province":"WI",
    "sg:tags":[
        "used",
        "automotive",
        "dealers-used",
        "car",
        "new",
        "cars-wholesale",
        "tune"
    ],
    "sg:website":"http://www.napaautocare.com/",
    "wof:name":"Monroe Auto Sales",
    "wof:placetype":"venue"
},
  "geometry": {"coordinates":[-89.6614,42.603561],"type":"Point"}
}