{
  "type": "Feature",
  "properties": {
    "iso:country":"US",
    "sg:address":"5030 Co Rd T T",
    "sg:city":"Columbus",
    "sg:classifiers":[
        {
            "category":"Home & Garden",
            "subcategory":"Home Furnishings",
            "type":"Retail Goods"
        }
    ],
    "sg:phone":"+1 920 885 6164",
    "sg:postcode":"53925",
    "sg:province":"WI",
    "wof:name":"Recovery Room",
    "wof:placetype":"venue"
},
  "geometry": {"coordinates":[-88.924129,43.369324],"type":"Point"}
}