{
  "type": "Feature",
  "properties": {
    "iso:country":"US",
    "sg:address":"2615 Coplien Rd",
    "sg:city":"Monroe",
    "sg:classifiers":[
        {
            "category":"Retail",
            "subcategory":"Repair Shop",
            "type":"Services"
        }
    ],
    "sg:phone":"+1 608 325 1300",
    "sg:postcode":"53566",
    "sg:province":"WI",
    "sg:tags":[
        "scooter",
        "motorcycle",
        "motor"
    ],
    "wof:name":"Brunkow's Performance V-Twin",
    "wof:placetype":"venue"
},
  "geometry": {"coordinates":[-89.61782700000001,42.598995],"type":"Point"}
}