{
  "type": "Feature",
  "properties": {
    "addr:full":"9 N Brown St Rhinelander WI 54501",
    "addr:housenumber":"9",
    "addr:postcode":"54501",
    "addr:street":"N Brown St",
    "iso:country":"US",
    "sg:address":"9 N Brown St",
    "sg:city":"Rhinelander",
    "sg:classifiers":[
        {
            "category":"Shopping",
            "subcategory":"Department Store",
            "type":"Retail Goods"
        }
    ],
    "sg:phone":"+1 715 362 5657",
    "sg:postcode":"54501",
    "sg:province":"WI",
    "sg:website":"www.gliks.com",
    "wof:name":"Glik's",
    "wof:placetype":"venue"
},
  "geometry": {"coordinates":[-89.412834,45.638892],"type":"Point"}
}