{
  "type": "Feature",
  "properties": {
    "addr:full":"2430 9th Ave Bloomer WI 54724",
    "addr:housenumber":"2430",
    "addr:postcode":"54724",
    "addr:street":"9Th Ave",
    "iso:country":"US",
    "sg:address":"2430 9th Ave",
    "sg:city":"Bloomer",
    "sg:classifiers":[
        {
            "category":"Real Estate",
            "subcategory":"Real Estate Operator",
            "type":"Services"
        }
    ],
    "sg:phone":"+1 715 568 3796",
    "sg:postcode":"54724",
    "sg:province":"WI",
    "sg:tags":[
        "building",
        "apartment"
    ],
    "wof:name":"North Lakeview APT Office",
    "wof:placetype":"venue"
},
  "geometry": {"coordinates":[-91.504592,45.111271],"type":"Point"}
}