{
  "type": "Feature",
  "properties": {
    "iso:country":"US",
    "sg:address":"2024 Mason St",
    "sg:city":"New Holstein",
    "sg:classifiers":[
        {
            "category":"Building & Trades",
            "subcategory":"Construction",
            "type":"Services"
        }
    ],
    "sg:phone":"+1 920 898 1440",
    "sg:postcode":"53061",
    "sg:province":"WI",
    "sg:tags":[
        "contractor"
    ],
    "wof:name":"Benzschawel Roofing",
    "wof:placetype":"venue"
},
  "geometry": {"coordinates":[-88.082382,43.951604],"type":"Point"}
}