{
  "type": "Feature",
  "properties": {
    "addr:full":"315 N Washington St Berlin WI 54923",
    "addr:housenumber":"315",
    "addr:postcode":"54923",
    "addr:street":"N Washington St",
    "iso:country":"US",
    "sg:address":"315 N Washington St",
    "sg:city":"Berlin",
    "sg:classifiers":[
        {
            "category":"Home & Garden",
            "subcategory":"Garden Supply",
            "type":"Retail Goods"
        }
    ],
    "sg:phone":"+1 920 361 2363",
    "sg:postcode":"54923",
    "sg:province":"WI",
    "sg:tags":[
        "equipment",
        "lawn"
    ],
    "wof:name":"Huser Implement Sales & Svc",
    "wof:placetype":"venue"
},
  "geometry": {"coordinates":[-88.956969,43.977095],"type":"Point"}
}