{
  "type": "Feature",
  "properties": {
    "iso:country":"US",
    "sg:address":"35913 Geneva Rd",
    "sg:city":"Burlington",
    "sg:classifiers":[
        {
            "category":"Building & Trades",
            "subcategory":"Equipment Rental",
            "type":"Services"
        }
    ],
    "sg:phone":"+1 262 537 2687",
    "sg:postcode":"53105",
    "sg:province":"WI",
    "sg:tags":[
        "leasing"
    ],
    "wof:name":"Mellon Bank Leasing",
    "wof:placetype":"venue"
},
  "geometry": {"coordinates":[-88.239921,42.575286],"type":"Point"}
}