{
  "type": "Feature",
  "properties": {
    "iso:country":"US",
    "sg:address":"17919 W Lincoln Ave",
    "sg:city":"New Berlin",
    "sg:classifiers":[
        {
            "category":"Manufacturing",
            "subcategory":"Printing",
            "type":"Manufacturing & Wholesale Goods"
        }
    ],
    "sg:phone":"+1 262 797 8499",
    "sg:postcode":"53146",
    "sg:province":"WI",
    "sg:tags":[
        "screen"
    ],
    "sg:website":"www.imagegear.net",
    "wof:name":"Image Gear Inc",
    "wof:placetype":"venue"
},
  "geometry": {"coordinates":[-88.142044,43.002371],"type":"Point"}
}