{
  "type": "Feature",
  "properties": {
    "iso:country":"US",
    "sg:address":"818 Wolff St",
    "sg:city":"Racine",
    "sg:classifiers":[
        {
            "category":"Building & Trades",
            "subcategory":"Construction",
            "type":"Services"
        }
    ],
    "sg:phone":"+1 262 639 4122",
    "sg:postcode":"53402",
    "sg:province":"WI",
    "sg:tags":[
        "hanging",
        "painter",
        "contractor"
    ],
    "wof:name":"Madisen Jay Painting Contr",
    "wof:placetype":"venue"
},
  "geometry": {"coordinates":[-87.791878,42.753072],"type":"Point"}
}