{
  "type": "Feature",
  "properties": {
    "iso:country":"US",
    "sg:address":"1570 Co Rd A",
    "sg:city":"Mindoro",
    "sg:classifiers":[
        {
            "category":"Shopping",
            "subcategory":"Clothing, Apparel, & Fashions",
            "type":"Retail Goods"
        }
    ],
    "sg:phone":"+1 608 857 3366",
    "sg:postcode":"54644",
    "sg:province":"WI",
    "sg:tags":[
        "mfg",
        "jewelry",
        "costume"
    ],
    "wof:name":"West Elegance",
    "wof:placetype":"venue"
},
  "geometry": {"coordinates":[-90.994861,44.052613],"type":"Point"}
}