{
  "type": "Feature",
  "properties": {
    "iso:country":"US",
    "sg:address":"5553 N Waterford Dr",
    "sg:city":"Appleton",
    "sg:classifiers":[
        {
            "category":"Health Services",
            "subcategory":"Doctor",
            "type":"Services"
        }
    ],
    "sg:phone":"+1 920 738 2740",
    "sg:postcode":"54913",
    "sg:province":"WI",
    "sg:tags":[
        "clinic",
        "orthopedic"
    ],
    "wof:name":"Gmeiner James G MD",
    "wof:placetype":"venue"
},
  "geometry": {"coordinates":[-88.399538,44.316303],"type":"Point"}
}