{
  "type": "Feature",
  "properties": {
    "iso:country":"US",
    "sg:address":"6614 Odana Rd",
    "sg:city":"Madison",
    "sg:classifiers":[
        {
            "category":"Utilities",
            "subcategory":"Mobile Phone",
            "type":"Services"
        }
    ],
    "sg:phone":"+1 608 446 1111",
    "sg:postcode":"53719",
    "sg:province":"WI",
    "sg:tags":[
        "telephone",
        "cellular"
    ],
    "wof:name":"Einstein Personal Comms",
    "wof:placetype":"venue"
},
  "geometry": {"coordinates":[-89.493252,43.055066],"type":"Point"}
}