{
  "type": "Feature",
  "properties": {
    "iso:country":"US",
    "sg:address":"7269 State Road 60",
    "sg:city":"Cedarburg",
    "sg:classifiers":[
        {
            "category":"Professional",
            "subcategory":"Lawyer & Legal Services",
            "type":"Services"
        }
    ],
    "sg:phone":"+1 262 376 9449",
    "sg:postcode":"53012",
    "sg:province":"WI",
    "wof:name":"Fleck Kenneth M Atty",
    "wof:placetype":"venue"
},
  "geometry": {"coordinates":[-87.99720000000001,43.3228],"type":"Point"}
}