{
  "type": "Feature",
  "properties": {
    "iso:country":"US",
    "sg:address":"6055 S Ace Industrial Dr",
    "sg:city":"Cudahy",
    "sg:classifiers":[
        {
            "category":"Retail",
            "subcategory":"Auto Rental",
            "type":"Services"
        }
    ],
    "sg:phone":"+1 414 769 5640",
    "sg:postcode":"53110",
    "sg:province":"WI",
    "sg:tags":[
        "leasing",
        "vehicle"
    ],
    "wof:name":"Gsa/Fleet Management Center",
    "wof:placetype":"venue"
},
  "geometry": {"coordinates":[-87.883309,42.935117],"type":"Point"}
}