{
  "type": "Feature",
  "properties": {
    "iso:country":"US",
    "sg:address":"721 S Lake Ave",
    "sg:city":"Phillips",
    "sg:classifiers":[
        {
            "category":"Government",
            "subcategory":"Office",
            "type":"Public Place"
        }
    ],
    "sg:phone":"+1 715 339 3192",
    "sg:postcode":"54555",
    "sg:province":"WI",
    "sg:tags":[
        "village"
    ],
    "wof:name":"Phillips Disposal Plant",
    "wof:placetype":"venue"
},
  "geometry": {"coordinates":[-90.39089,45.680589],"type":"Point"}
}