{
  "type": "Feature",
  "properties": {
    "addr:full":"14700 Watertown Plank Rd Elm Grove WI 53122",
    "addr:postcode":"14700;53122",
    "addr:street":"Plank Rd",
    "iso:country":"US",
    "sg:address":"14700 Watertown Plank Rd",
    "sg:city":"Elm Grove",
    "sg:classifiers":[
        {
            "category":"Organizations",
            "subcategory":"Religious Organization",
            "type":"Services"
        }
    ],
    "sg:phone":"+1 262 782 4060",
    "sg:postcode":"53122",
    "sg:province":"WI",
    "wof:name":"Community Untd Methdst Church",
    "wof:placetype":"venue"
},
  "geometry": {"coordinates":[-88.096699,43.039363],"type":"Point"}
}