{
  "type": "Feature",
  "properties": {
    "iso:country":"US",
    "sg:address":"1014 Green Ridge Dr",
    "sg:city":"Green Bay",
    "sg:classifiers":[
        {
            "category":"Professional",
            "subcategory":"Computer Services",
            "type":"Services"
        }
    ],
    "sg:phone":"+1 920 366 8422",
    "sg:postcode":"54313",
    "sg:province":"WI",
    "sg:tags":[
        "repair"
    ],
    "wof:name":"Nova-K Computer Svc",
    "wof:placetype":"venue"
},
  "geometry": {"coordinates":[-88.125153,44.525034],"type":"Point"}
}