{
  "type": "Feature",
  "properties": {
    "addr:full":"420 Bruce Ln Wisconsin Rapids WI 54494",
    "addr:housenumber":"420",
    "addr:postcode":"54494",
    "addr:street":"Bruce Ln",
    "iso:country":"US",
    "sg:address":"420 Bruce Ln",
    "sg:city":"Wisconsin Rapids",
    "sg:classifiers":[
        {
            "category":"Building & Trades",
            "subcategory":"Construction",
            "type":"Services"
        }
    ],
    "sg:phone":"+1 715 424 3075",
    "sg:postcode":"54494",
    "sg:province":"WI",
    "sg:tags":[
        "dry wall",
        "contractor"
    ],
    "wof:name":"Palmquist Drywall",
    "wof:placetype":"venue"
},
  "geometry": {"coordinates":[-89.824381,44.356321],"type":"Point"}
}