{
  "type": "Feature",
  "properties": {
    "addr:full":"5140 N 20th St Milwaukee WI 53209",
    "addr:housenumber":"5140",
    "addr:postcode":"53209",
    "addr:street":"N 20Th St",
    "iso:country":"US",
    "sg:address":"5140 N 20th St",
    "sg:city":"Milwaukee",
    "sg:classifiers":[
        {
            "category":"Building & Trades",
            "subcategory":"Landscaping Services",
            "type":"Services"
        }
    ],
    "sg:phone":"+1 414 352 6401",
    "sg:postcode":"53209",
    "sg:province":"WI",
    "sg:tags":[
        "lawn",
        "maintenance",
        "grounds"
    ],
    "wof:name":"Magic Touch Lawn & Garden Inc",
    "wof:placetype":"venue"
},
  "geometry": {"coordinates":[-87.936442,43.109266],"type":"Point"}
}