{
  "type": "Feature",
  "properties": {
    "iso:country":"US",
    "sg:address":"1001 Truman St",
    "sg:city":"Kimberly",
    "sg:classifiers":[
        {
            "category":"Insurance",
            "subcategory":"Life Insurance",
            "type":"Services"
        }
    ],
    "sg:phone":"+1 920 734 3159",
    "sg:postcode":"54136",
    "sg:province":"WI",
    "sg:tags":[
        "carrier",
        "carrie"
    ],
    "wof:name":"Diamond Financial Services",
    "wof:placetype":"venue"
},
  "geometry": {"coordinates":[-88.349511,44.259578],"type":"Point"}
}