{
  "type": "Feature",
  "properties": {
    "iso:country":"US",
    "sg:address":"3927 Risseeuw Rd",
    "sg:city":"Cedar Grove",
    "sg:classifiers":[
        {
            "category":"Farming",
            "subcategory":"Livestock Farm",
            "type":"Manufacturing & Wholesale Goods"
        }
    ],
    "sg:phone":"+1 920 564 3416",
    "sg:postcode":"53013",
    "sg:province":"WI",
    "sg:tags":[
        "real",
        "property",
        "specialty",
        "lessor",
        "animal"
    ],
    "wof:name":"Alan & Beverly Garside",
    "wof:placetype":"venue"
},
  "geometry": {"coordinates":[-87.89110700000001,43.601552],"type":"Point"}
}