{
  "type": "Feature",
  "properties": {
    "iso:country":"US",
    "sg:address":"2847 Coventry Ln",
    "sg:city":"Waukesha",
    "sg:classifiers":[
        {
            "category":"Real Estate",
            "subcategory":"Real Estate Agent",
            "type":"Services"
        }
    ],
    "sg:phone":"+1 262 542 2929",
    "sg:postcode":"53188",
    "sg:province":"WI",
    "wof:name":"CJ Realty",
    "wof:placetype":"venue"
},
  "geometry": {"coordinates":[-88.283174,43.044382],"type":"Point"}
}