{
  "type": "Feature",
  "properties": {
    "addr:full":"9045 N Northridge Mall Rd Milwaukee WI 53223",
    "addr:housenumber":"9045",
    "addr:postcode":"53223",
    "addr:street":"N Northridge Mall Rd",
    "iso:country":"US",
    "sg:address":"9045 N Northridge Mall Rd",
    "sg:city":"Milwaukee",
    "sg:classifiers":[
        {
            "category":"Freight",
            "type":"Transportation"
        }
    ],
    "sg:phone":"+1 414 365 5572",
    "sg:postcode":"53223",
    "sg:province":"WI",
    "wof:name":"Anthony's Transportation Svc",
    "wof:placetype":"venue"
},
  "geometry": {"coordinates":[-88.012929,43.183668],"type":"Point"}
}