{
  "type": "Feature",
  "properties": {
    "addr:full":"134 Plastic Ave Tomah WI 54660",
    "addr:housenumber":"134",
    "addr:postcode":"54660",
    "addr:street":"Plastic Ave",
    "iso:country":"US",
    "sg:address":"134 Plastic Ave",
    "sg:city":"Tomah",
    "sg:classifiers":[
        {
            "category":"Retail",
            "subcategory":"Repair Shop",
            "type":"Services"
        }
    ],
    "sg:phone":"+1 608 372 4400",
    "sg:postcode":"54660",
    "sg:province":"WI",
    "sg:tags":[
        "welding"
    ],
    "wof:name":"Tomah Welding & Steel Supply",
    "wof:placetype":"venue"
},
  "geometry": {"coordinates":[-90.489963,43.984171],"type":"Point"}
}