{
  "type": "Feature",
  "properties": {
    "addr:full":"106 W State St Westby WI 54667",
    "addr:housenumber":"106",
    "addr:postcode":"54667",
    "addr:street":"W State St",
    "iso:country":"US",
    "sg:address":"106 W State St",
    "sg:city":"Westby",
    "sg:classifiers":[
        {
            "category":"Utilities",
            "subcategory":"Natural Gas",
            "type":"Services"
        }
    ],
    "sg:phone":"+1 608 634 4617",
    "sg:postcode":"54667",
    "sg:province":"WI",
    "sg:tags":[
        "company"
    ],
    "wof:name":"Midwest Natural Gas",
    "wof:placetype":"venue"
},
  "geometry": {"coordinates":[-90.85788100000001,43.653582],"type":"Point"}
}