{
  "type": "Feature",
  "properties": {
    "iso:country":"US",
    "sg:address":"9498 Townline Rd",
    "sg:city":"Van Dyne",
    "sg:classifiers":[
        {
            "category":"Building & Trades",
            "subcategory":"Construction",
            "type":"Services"
        }
    ],
    "sg:phone":"+1 920 688 5181",
    "sg:postcode":"54979",
    "sg:province":"WI",
    "sg:tags":[
        "contractor"
    ],
    "wof:name":"Rjt Exteriors LLC",
    "wof:placetype":"venue"
},
  "geometry": {"coordinates":[-88.523832,43.885499],"type":"Point"}
}