{
  "type": "Feature",
  "properties": {
    "iso:country":"US",
    "sg:address":"4806 51st St",
    "sg:city":"Mauston",
    "sg:classifiers":[
        {
            "category":"Building & Trades",
            "subcategory":"Construction",
            "type":"Services"
        }
    ],
    "sg:phone":"+1 608 835 7732",
    "sg:postcode":"53948",
    "sg:province":"WI",
    "sg:tags":[
        "house"
    ],
    "wof:name":"F&H Homes Inc",
    "wof:placetype":"venue"
},
  "geometry": {"coordinates":[-90.010418,43.803338],"type":"Point"}
}