{
  "type": "Feature",
  "properties": {
    "iso:country":"US",
    "sg:address":"1428 Wisconsin Ave",
    "sg:city":"Beloit",
    "sg:classifiers":[
        {
            "category":"Organizations",
            "subcategory":"Community Association",
            "type":"Services"
        }
    ],
    "sg:phone":"+1 608 365 1488",
    "sg:postcode":"53511",
    "sg:province":"WI",
    "wof:name":"Merrill Community Ctr",
    "wof:placetype":"venue"
},
  "geometry": {"coordinates":[-89.024199,42.51556],"type":"Point"}
}