{
  "type": "Feature",
  "properties": {
    "addr:full":"5285 Peterson Rd Scandinavia WI 54977",
    "addr:housenumber":"5285",
    "addr:postcode":"54977",
    "addr:street":"Peterson Rd",
    "iso:country":"US",
    "sg:address":"5285 Peterson Rd",
    "sg:city":"Scandinavia",
    "sg:classifiers":[
        {
            "category":"Farming",
            "subcategory":"Dairy Farm",
            "type":"Manufacturing & Wholesale Goods"
        }
    ],
    "sg:phone":"+1 715 467 2427",
    "sg:postcode":"54977",
    "sg:province":"WI",
    "sg:tags":[
        "field",
        "corn",
        "soybean",
        "crop"
    ],
    "wof:name":"Gor Low Acres",
    "wof:placetype":"venue"
},
  "geometry": {"coordinates":[-89.176154,44.429893],"type":"Point"}
}