{
  "type": "Feature",
  "properties": {
    "addr:full":"2706 W Deer Path Trl Janesville WI 53545",
    "addr:housenumber":"2706",
    "addr:postcode":"53545",
    "addr:street":"W Deer Path Trl",
    "iso:country":"US",
    "sg:address":"2706 W Deer Path Trl",
    "sg:city":"Janesville",
    "sg:classifiers":[
        {
            "category":"Freight",
            "type":"Transportation"
        }
    ],
    "sg:phone":"+1 608 755 9910",
    "sg:postcode":"53545",
    "sg:province":"WI",
    "sg:tags":[
        "operator",
        "trucking"
    ],
    "wof:name":"Bothuns Tree Transplant",
    "wof:placetype":"venue"
},
  "geometry": {"coordinates":[-89.054894,42.737482],"type":"Point"}
}