{
  "type": "Feature",
  "properties": {
    "iso:country":"US",
    "sg:address":"5600 W Florist Ave",
    "sg:city":"Milwaukee",
    "sg:classifiers":[
        {
            "category":"Manufacturing",
            "subcategory":"Tools & Machinery",
            "type":"Manufacturing & Wholesale Goods"
        }
    ],
    "sg:phone":"+1 414 462 8200",
    "sg:postcode":"53218",
    "sg:province":"WI",
    "sg:tags":[
        "compressor",
        "gas",
        "meter",
        "mfg"
    ],
    "sg:website":"www.waukeemeters.com",
    "wof:name":"Waukee Engineering Company",
    "wof:placetype":"venue"
},
  "geometry": {"coordinates":[-87.984905,43.126696],"type":"Point"}
}