{
  "type": "Feature",
  "properties": {
    "iso:country":"US",
    "sg:address":"16270 Shore Line Dr",
    "sg:city":"Brookfield",
    "sg:classifiers":[
        {
            "category":"Professional",
            "subcategory":"Business Services",
            "type":"Services"
        }
    ],
    "sg:phone":"+1 262 783 4354",
    "sg:postcode":"53005",
    "sg:province":"WI",
    "wof:name":"Fur Replicas Rentals & Sales",
    "wof:placetype":"venue"
},
  "geometry": {"coordinates":[-88.115346,43.084255],"type":"Point"}
}