{
  "type": "Feature",
  "properties": {
    "addr:full":"2801 S Webster Ave Green Bay WI 54301",
    "addr:housenumber":"2801",
    "addr:postcode":"54301",
    "addr:street":"S Webster Ave",
    "iso:country":"US",
    "sg:address":"2801 S Webster Ave",
    "sg:city":"Green Bay",
    "sg:classifiers":[
        {
            "category":"Health Services",
            "subcategory":"Clinic",
            "type":"Services"
        }
    ],
    "sg:phone":"+1 920 337 1122",
    "sg:postcode":"54301",
    "sg:province":"WI",
    "sg:tags":[
        "outpatient",
        "rehabilitation"
    ],
    "sg:website":"www.cp-center.org",
    "wof:name":"Cerebral Palsy Inc",
    "wof:placetype":"venue"
},
  "geometry": {"coordinates":[-88.033337,44.467831],"type":"Point"}
}