{
  "type": "Feature",
  "properties": {
    "iso:country":"US",
    "sg:address":"5014 W Howard Ave",
    "sg:city":"Milwaukee",
    "sg:classifiers":[
        {
            "category":"Sports & Exercise",
            "subcategory":"Bowling",
            "type":"Entertainment"
        }
    ],
    "sg:phone":"+1 414 543 7110",
    "sg:postcode":"53220",
    "sg:province":"WI",
    "sg:tags":[
        "drinking",
        "center"
    ],
    "wof:name":"Holiday Lanes",
    "wof:placetype":"venue"
},
  "geometry": {"coordinates":[-87.977975,42.973986],"type":"Point"}
}