{
  "type": "Feature",
  "properties": {
    "addr:full":"703 3rd St Marathon WI 54448",
    "addr:housenumber":"703",
    "addr:postcode":"54448",
    "addr:street":"3Rd St",
    "iso:country":"US",
    "sg:address":"703 3rd St",
    "sg:city":"Marathon",
    "sg:classifiers":[
        {
            "category":"Health Services",
            "subcategory":"Optometrist",
            "type":"Services"
        }
    ],
    "sg:phone":"+1 715 443 2248",
    "sg:postcode":"54448",
    "sg:province":"WI",
    "wof:name":"Family Vision Ctr",
    "wof:placetype":"venue"
},
  "geometry": {"coordinates":[-89.842578,44.931432],"type":"Point"}
}