{
  "type": "Feature",
  "properties": {
    "iso:country":"US",
    "sg:address":"26378 170th Ave",
    "sg:city":"Cadott",
    "sg:classifiers":[
        {
            "category":"Manufacturing",
            "subcategory":"Wood Products",
            "type":"Manufacturing & Wholesale Goods"
        }
    ],
    "sg:phone":"+1 715 289 4044",
    "sg:postcode":"54727",
    "sg:province":"WI",
    "sg:tags":[
        "mfg"
    ],
    "wof:name":"Padded Caps",
    "wof:placetype":"venue"
},
  "geometry": {"coordinates":[-91.146973,45.089199],"type":"Point"}
}