{
  "type": "Feature",
  "properties": {
    "iso:country":"US",
    "sg:address":"1121 W Valley Rd",
    "sg:city":"Appleton",
    "sg:classifiers":[
        {
            "category":"Banks & Credit Unions",
            "subcategory":"Investment Brokerage",
            "type":"Services"
        }
    ],
    "sg:phone":"+1 920 739 7757",
    "sg:postcode":"54915",
    "sg:province":"WI",
    "sg:tags":[
        "consultant",
        "planning",
        "financial"
    ],
    "wof:name":"Sentra Securities",
    "wof:placetype":"venue"
},
  "geometry": {"coordinates":[-88.426058,44.237019],"type":"Point"}
}