{
  "type": "Feature",
  "properties": {
    "addr:full":"305 S Bedford St Madison WI 53703",
    "addr:housenumber":"305",
    "addr:postcode":"53703",
    "addr:street":"S Bedford St",
    "iso:country":"US",
    "sg:address":"305 S Bedford St",
    "sg:city":"Madison",
    "sg:classifiers":[
        {
            "category":"Wholesale",
            "subcategory":"Toys & Hobbies",
            "type":"Manufacturing & Wholesale Goods"
        }
    ],
    "sg:phone":"+1 608 280 0912",
    "sg:postcode":"53703",
    "sg:province":"WI",
    "wof:name":"C L N Gallerys LLC",
    "wof:placetype":"venue"
},
  "geometry": {"coordinates":[-89.388587,43.06602],"type":"Point"}
}