{
  "type": "Feature",
  "properties": {
    "iso:country":"US",
    "sg:address":"5347 Portland Rd",
    "sg:city":"Cedarburg",
    "sg:classifiers":[
        {
            "category":"Building & Trades",
            "subcategory":"Construction",
            "type":"Services"
        }
    ],
    "sg:phone":"+1 262 375 1994",
    "sg:postcode":"53012",
    "sg:province":"WI",
    "sg:tags":[
        "carpentry",
        "contractor"
    ],
    "wof:name":"Knuth & Co Carpentry",
    "wof:placetype":"venue"
},
  "geometry": {"coordinates":[-87.978707,43.293897],"type":"Point"}
}