{
  "type": "Feature",
  "properties": {
    "iso:country":"US",
    "sg:address":"1403 State Rd 70",
    "sg:city":"Spooner",
    "sg:classifiers":[
        {
            "category":"Farming",
            "subcategory":"Livestock Farm",
            "type":"Manufacturing & Wholesale Goods"
        }
    ],
    "sg:phone":"+1 715 468 7382",
    "sg:postcode":"54801",
    "sg:province":"WI",
    "sg:tags":[
        "beef",
        "feedlot",
        "cattle"
    ],
    "wof:name":"Bernice Stock",
    "wof:placetype":"venue"
},
  "geometry": {"coordinates":[-92.052627,45.815291],"type":"Point"}
}