{
  "type": "Feature",
  "properties": {
    "iso:country":"US",
    "sg:address":"811 Ellen Ct",
    "sg:city":"Fond Du Lac",
    "sg:classifiers":[
        {
            "category":"Organizations",
            "subcategory":"Religious Organization",
            "type":"Services"
        }
    ],
    "sg:phone":"+1 920 922 3480",
    "sg:postcode":"54935",
    "sg:province":"WI",
    "sg:tags":[
        "monastery",
        "convent"
    ],
    "wof:name":"Sisters Of Agnes",
    "wof:placetype":"venue"
},
  "geometry": {"coordinates":[-88.43491899999999,43.756793],"type":"Point"}
}