{
  "type": "Feature",
  "properties": {
    "iso:country":"US",
    "sg:address":"7657 E Main St",
    "sg:city":"Siren",
    "sg:classifiers":[
        {
            "category":"Retail",
            "subcategory":"Repair Shop",
            "type":"Services"
        }
    ],
    "sg:phone":"+1 715 349 5730",
    "sg:postcode":"54872",
    "sg:province":"WI",
    "sg:tags":[
        "upholsterer"
    ],
    "wof:name":"Fern's Upholstery",
    "wof:placetype":"venue"
},
  "geometry": {"coordinates":[-92.378611,45.787349],"type":"Point"}
}