{
  "type": "Feature",
  "properties": {
    "iso:country":"US",
    "sg:address":"446 Main St",
    "sg:city":"Union Center",
    "sg:classifiers":[
        {
            "category":"Wholesale",
            "subcategory":"Dairy",
            "type":"Manufacturing & Wholesale Goods"
        }
    ],
    "sg:phone":"+1 608 462 5745",
    "sg:postcode":"53962",
    "sg:province":"WI",
    "sg:tags":[
        "product"
    ],
    "wof:name":"D & T Delights",
    "wof:placetype":"venue"
},
  "geometry": {"coordinates":[-90.26481,43.684683],"type":"Point"}
}