{
  "type": "Feature",
  "properties": {
    "iso:country":"US",
    "sg:address":"8137 S Steepleview Dr",
    "sg:city":"Franklin",
    "sg:classifiers":[
        {
            "category":"Building & Trades",
            "subcategory":"Construction",
            "type":"Services"
        }
    ],
    "sg:phone":"+1 414 529 2351",
    "sg:postcode":"53132",
    "sg:province":"WI",
    "sg:tags":[
        "house"
    ],
    "wof:name":"Westview Terrace",
    "wof:placetype":"venue"
},
  "geometry": {"coordinates":[-88.043239,42.896423],"type":"Point"}
}