{
  "type": "Feature",
  "properties": {
    "iso:country":"US",
    "sg:address":"529 N 32nd St",
    "sg:city":"Milwaukee",
    "sg:classifiers":[
        {
            "category":"Professional",
            "type":"Services"
        }
    ],
    "sg:phone":"+1 414 934 9114",
    "sg:postcode":"53208",
    "sg:province":"WI",
    "wof:name":"Ew Mettle Co LLC",
    "wof:placetype":"venue"
},
  "geometry": {"coordinates":[-87.954086,43.037132],"type":"Point"}
}