{
  "type": "Feature",
  "properties": {
    "iso:country":"US",
    "sg:address":"8020 Fielding Ln",
    "sg:city":"Greendale",
    "sg:classifiers":[
        {
            "category":"Bars & Pubs",
            "type":"Food & Drink"
        }
    ],
    "sg:phone":"+1 414 423 7973",
    "sg:postcode":"53129",
    "sg:province":"WI",
    "sg:tags":[
        "drinking"
    ],
    "wof:name":"Silver Spur Texas Smokehouse",
    "wof:placetype":"venue"
},
  "geometry": {"coordinates":[-88.012089,42.935688],"type":"Point"}
}