{
  "type": "Feature",
  "properties": {
    "iso:country":"US",
    "sg:address":"9404 N Dun Rovin Rd",
    "sg:city":"Hayward",
    "sg:classifiers":[
        {
            "category":"Travel",
            "subcategory":"Hotels & Motels",
            "type":"Entertainment"
        }
    ],
    "sg:phone":"+1 715 462 3834",
    "sg:postcode":"54843",
    "sg:province":"WI",
    "sg:tags":[
        "resort"
    ],
    "wof:name":"Dun Rovin Lodge",
    "wof:placetype":"venue"
},
  "geometry": {"coordinates":[-91.16929399999999,45.976956],"type":"Point"}
}