{
  "type": "Feature",
  "properties": {
    "iso:country":"US",
    "sg:address":"2840 Hidden Farm Rd",
    "sg:city":"Mc Farland",
    "sg:classifiers":[
        {
            "category":"Retail",
            "subcategory":"Animal Services",
            "type":"Services"
        }
    ],
    "sg:phone":"+1 608 838 9400",
    "sg:postcode":"53558",
    "sg:province":"WI",
    "sg:tags":[
        "dog",
        "kennel"
    ],
    "wof:name":"Windyhill Kennel",
    "wof:placetype":"venue"
},
  "geometry": {"coordinates":[-89.280099,43.003038],"type":"Point"}
}