{
  "type": "Feature",
  "properties": {
    "iso:country":"US",
    "sg:address":"428 Cleveland St",
    "sg:city":"Sheboygan Falls",
    "sg:classifiers":[
        {
            "category":"Manufacturing",
            "subcategory":"Metals",
            "type":"Manufacturing & Wholesale Goods"
        }
    ],
    "sg:phone":"+1 920 467 0599",
    "sg:postcode":"53085",
    "sg:province":"WI",
    "sg:tags":[
        "stamping"
    ],
    "sg:website":"www.htt-inc.com",
    "wof:name":"HTT Inc",
    "wof:placetype":"venue"
},
  "geometry": {"coordinates":[-87.80624400000001,43.726476],"type":"Point"}
}