{
  "type": "Feature",
  "properties": {
    "iso:country":"US",
    "sg:address":"1460 Co Hwy K",
    "sg:city":"Juda",
    "sg:phone":"+1 608 897 2293",
    "sg:postcode":"53550",
    "sg:province":"WI",
    "sg:tags":[
        "farm",
        "corn",
        "soybean"
    ],
    "wof:name":"Rodney Ehlert",
    "wof:placetype":"venue"
},
  "geometry": {"coordinates":[-89.574493,42.556188],"type":"Point"}
}