{
  "type": "Feature",
  "properties": {
    "iso:country":"US",
    "sg:address":"8082 N 76th St",
    "sg:city":"Milwaukee",
    "sg:classifiers":[
        {
            "category":"Food & Beverages",
            "subcategory":"Liquor & Beverages",
            "type":"Retail Goods"
        }
    ],
    "sg:phone":"+1 414 353 1950",
    "sg:postcode":"53223",
    "sg:province":"WI",
    "wof:name":"Sundeep Liquor & Video",
    "wof:placetype":"venue"
},
  "geometry": {"coordinates":[-88.004589,43.163602],"type":"Point"}
}