{
  "type": "Feature",
  "properties": {
    "iso:country":"US",
    "sg:address":"13831 W Capitol Dr",
    "sg:city":"Brookfield",
    "sg:classifiers":[
        {
            "category":"Building & Trades",
            "subcategory":"Construction",
            "type":"Services"
        }
    ],
    "sg:phone":"+1 262 781 7302",
    "sg:postcode":"53005",
    "sg:province":"WI",
    "sg:tags":[
        "maker",
        "cabinet"
    ],
    "wof:name":"Custom Cabinet Shop",
    "wof:placetype":"venue"
},
  "geometry": {"coordinates":[-88.08658800000001,43.089597],"type":"Point"}
}