{
  "type": "Feature",
  "properties": {
    "iso:country":"US",
    "sg:address":"5001 Voges Rd",
    "sg:city":"Madison",
    "sg:classifiers":[
        {
            "category":"Building & Trades",
            "subcategory":"Plumbing",
            "type":"Services"
        }
    ],
    "sg:phone":"+1 608 271 7500",
    "sg:postcode":"53718",
    "sg:province":"WI",
    "sg:tags":[
        "conditioning",
        "air",
        "system",
        "contractor"
    ],
    "sg:website":"www.tsihvac.com",
    "wof:name":"Temperature Systems Inc",
    "wof:placetype":"venue"
},
  "geometry": {"coordinates":[-89.298278,43.040489],"type":"Point"}
}