{
  "type": "Feature",
  "properties": {
    "iso:country":"US",
    "sg:address":"102 W Main St",
    "sg:city":"Cambridge",
    "sg:classifiers":[
        {
            "category":"Organizations",
            "subcategory":"Professional Association",
            "type":"Services"
        }
    ],
    "sg:phone":"+1 608 423 3780",
    "sg:postcode":"53523",
    "sg:province":"WI",
    "sg:tags":[
        "chambers",
        "business",
        "commerce"
    ],
    "wof:name":"Cambridge Chamber of Commerce",
    "wof:placetype":"venue"
},
  "geometry": {"coordinates":[-89.019624,43.004226],"type":"Point"}
}