{
  "type": "Feature",
  "properties": {
    "iso:country":"US",
    "sg:address":"39110 Valley Rd",
    "sg:city":"Oconomowoc",
    "sg:classifiers":[
        {
            "category":"Building & Trades",
            "subcategory":"Landscaping Services",
            "type":"Services"
        }
    ],
    "sg:phone":"+1 262 567 2713",
    "sg:postcode":"53066",
    "sg:province":"WI",
    "sg:tags":[
        "tree"
    ],
    "wof:name":"Mdz Enterprises",
    "wof:placetype":"venue"
},
  "geometry": {"coordinates":[-88.522469,43.084502],"type":"Point"}
}