{
  "type": "Feature",
  "properties": {
    "iso:country":"US",
    "sg:address":"5931 N 91st St",
    "sg:city":"Milwaukee",
    "sg:classifiers":[
        {
            "category":"Food & Beverages",
            "subcategory":"Groceries & Convenience Stores",
            "type":"Retail Goods"
        }
    ],
    "sg:phone":"+1 414 461 3100",
    "sg:postcode":"53225",
    "sg:province":"WI",
    "wof:name":"Kaul Oil Co",
    "wof:placetype":"venue"
},
  "geometry": {"coordinates":[-88.025767,43.125506],"type":"Point"}
}