{
  "type": "Feature",
  "properties": {
    "iso:country":"US",
    "sg:address":"760 Pilgrim Way",
    "sg:city":"Green Bay",
    "sg:classifiers":[
        {
            "category":"Health Services",
            "subcategory":"Doctor",
            "type":"Services"
        }
    ],
    "sg:phone":"+1 920 496 4777",
    "sg:postcode":"54304",
    "sg:province":"WI",
    "sg:tags":[
        "medical"
    ],
    "wof:name":"Alessandra M Gadsby MD",
    "wof:placetype":"venue"
},
  "geometry": {"coordinates":[-88.064427,44.481105],"type":"Point"}
}