{
  "type": "Feature",
  "properties": {
    "iso:country":"US",
    "sg:address":"3351 N 49th St",
    "sg:city":"Milwaukee",
    "sg:classifiers":[
        {
            "category":"Building & Trades",
            "subcategory":"Construction",
            "type":"Services"
        }
    ],
    "sg:phone":"+1 414 445 6943",
    "sg:postcode":"53216",
    "sg:province":"WI",
    "sg:tags":[
        "roofing",
        "contractor"
    ],
    "wof:name":"Cicero's Roofing Contractors",
    "wof:placetype":"venue"
},
  "geometry": {"coordinates":[-87.974864,43.080157],"type":"Point"}
}