{
  "type": "Feature",
  "properties": {
    "addr:full":"101 School St Lodi WI 53555",
    "addr:housenumber":"101",
    "addr:postcode":"53555",
    "addr:street":"School St",
    "iso:country":"US",
    "sg:address":"101 School St",
    "sg:city":"Lodi",
    "sg:classifiers":[
        {
            "category":"Education",
            "subcategory":"School",
            "type":"Public Place"
        }
    ],
    "sg:phone":"+1 608 592 3842",
    "sg:postcode":"53555",
    "sg:province":"WI",
    "sg:website":"www.lodi.k12.wi.us",
    "wof:name":"Lodi Elementary School",
    "wof:placetype":"venue"
},
  "geometry": {"coordinates":[-89.523984,43.318051],"type":"Point"}
}