{
  "type": "Feature",
  "properties": {
    "iso:country":"US",
    "sg:address":"6110 S Howell Ave",
    "sg:city":"Milwaukee",
    "sg:classifiers":[
        {
            "category":"Manufacturing",
            "subcategory":"Leather Goods",
            "type":"Manufacturing & Wholesale Goods"
        }
    ],
    "sg:phone":"+1 414 764 6820",
    "sg:postcode":"53207",
    "sg:province":"WI",
    "wof:name":"Willie's Custom Leather",
    "wof:placetype":"venue"
},
  "geometry": {"coordinates":[-87.909986,42.930235],"type":"Point"}
}