{
  "type": "Feature",
  "properties": {
    "iso:country":"US",
    "sg:address":"306 Grand Ave",
    "sg:city":"Merrill",
    "sg:classifiers":[
        {
            "category":"Personal",
            "subcategory":"Barber",
            "type":"Services"
        }
    ],
    "sg:phone":"+1 715 536 8821",
    "sg:postcode":"54452",
    "sg:province":"WI",
    "sg:tags":[
        "shop"
    ],
    "wof:name":"Mike's West Side Barber Shop",
    "wof:placetype":"venue"
},
  "geometry": {"coordinates":[-89.70485,45.179659],"type":"Point"}
}