{
  "type": "Feature",
  "properties": {
    "iso:country":"US",
    "sg:address":"1283 Link St",
    "sg:city":"Watertown",
    "sg:classifiers":[
        {
            "category":"Building & Trades",
            "subcategory":"Construction",
            "type":"Services"
        }
    ],
    "sg:phone":"+1 920 261 1717",
    "sg:postcode":"53098",
    "sg:province":"WI",
    "sg:tags":[
        "restoration",
        "preservation"
    ],
    "wof:name":"Mayer's Restoration & Painting",
    "wof:placetype":"venue"
},
  "geometry": {"coordinates":[-88.783163,43.240056],"type":"Point"}
}