{
  "type": "Feature",
  "properties": {
    "iso:country":"US",
    "sg:address":"7711 State Hwy 54",
    "sg:city":"Shiocton",
    "sg:classifiers":[
        {
            "category":"Restaurant",
            "type":"Food & Drink"
        }
    ],
    "sg:phone":"+1 920 986 9100",
    "sg:postcode":"54170",
    "sg:province":"WI",
    "sg:tags":[
        "eating"
    ],
    "wof:name":"Dick & Jeannis",
    "wof:placetype":"venue"
},
  "geometry": {"coordinates":[-88.575646,44.445755],"type":"Point"}
}