{
  "type": "Feature",
  "properties": {
    "iso:country":"US",
    "sg:address":"310 Allen St",
    "sg:city":"Chippewa Falls",
    "sg:classifiers":[
        {
            "category":"Bars & Pubs",
            "type":"Food & Drink"
        }
    ],
    "sg:phone":"+1 715 723 8211",
    "sg:postcode":"54729",
    "sg:province":"WI",
    "sg:tags":[
        "drinking"
    ],
    "wof:name":"Tip Top",
    "wof:placetype":"venue"
},
  "geometry": {"coordinates":[-91.38494300000001,44.937352],"type":"Point"}
}