{
  "type": "Feature",
  "properties": {
    "iso:country":"US",
    "sg:address":"1693 College Ave",
    "sg:city":"South Milwaukee",
    "sg:classifiers":[
        {
            "category":"Building & Trades",
            "subcategory":"Plumbing",
            "type":"Services"
        }
    ],
    "sg:phone":"+1 414 571 0700",
    "sg:postcode":"53172",
    "sg:province":"WI",
    "sg:tags":[
        "heating",
        "contractor"
    ],
    "wof:name":"A A BEST Choice LLC",
    "wof:placetype":"venue"
},
  "geometry": {"coordinates":[-87.87646100000001,42.92995],"type":"Point"}
}