{
  "type": "Feature",
  "properties": {
    "iso:country":"US",
    "sg:address":"5403 Middleton Dr",
    "sg:city":"Greendale",
    "sg:classifiers":[
        {
            "category":"Recreation",
            "type":"Entertainment"
        }
    ],
    "sg:phone":"+1 414 421 8427",
    "sg:postcode":"53129",
    "sg:province":"WI",
    "wof:name":"Ther-Ed",
    "wof:placetype":"venue"
},
  "geometry": {"coordinates":[-87.992092,42.945884],"type":"Point"}
}