{
  "type": "Feature",
  "properties": {
    "addr:full":"101 N Webster Ave Green Bay WI 54301",
    "addr:housenumber":"101",
    "addr:postcode":"54301",
    "addr:street":"N Webster Ave",
    "iso:country":"US",
    "sg:address":"101 N Webster Ave",
    "sg:city":"Green Bay",
    "sg:classifiers":[
        {
            "category":"Government",
            "subcategory":"Office",
            "type":"Public Place"
        }
    ],
    "sg:phone":"+1 920 433 3904",
    "sg:postcode":"54301",
    "sg:province":"WI",
    "sg:tags":[
        "federal",
        "human"
    ],
    "wof:name":"US Social Security Adm",
    "wof:placetype":"venue"
},
  "geometry": {"coordinates":[-88.00416,44.511283],"type":"Point"}
}