{
  "type": "Feature",
  "properties": {
    "iso:country":"US",
    "sg:address":"5810 W Oklahoma Ave",
    "sg:city":"Milwaukee",
    "sg:classifiers":[
        {
            "category":"Real Estate",
            "subcategory":"Real Estate Agent",
            "type":"Services"
        },
        {
            "category":"Real Estate",
            "subcategory":"Real Estate Operator",
            "type":"Services"
        }
    ],
    "sg:phone":"+1 414 545 9801",
    "sg:postcode":"53219",
    "sg:province":"WI",
    "sg:tags":[
        "company",
        "apartment",
        "leasing"
    ],
    "wof:name":"L J Rentals LLC",
    "wof:placetype":"venue"
},
  "geometry": {"coordinates":[-87.987473,42.988489],"type":"Point"}
}