{
  "type": "Feature",
  "properties": {
    "iso:country":"US",
    "sg:address":"5495 State Rd 120",
    "sg:city":"Elkhorn",
    "sg:classifiers":[
        {
            "category":"Food & Beverages",
            "subcategory":"Groceries & Convenience Stores",
            "type":"Retail Goods"
        }
    ],
    "sg:phone":"+1 262 723 6333",
    "sg:postcode":"53121",
    "sg:province":"WI",
    "sg:tags":[
        "gas"
    ],
    "wof:name":"Shaver's General Store",
    "wof:placetype":"venue"
},
  "geometry": {"coordinates":[-88.404766,42.691033],"type":"Point"}
}