{
  "type": "Feature",
  "properties": {
    "iso:country":"US",
    "sg:address":"2175 Pine Ridge Ct",
    "sg:city":"Grafton",
    "sg:classifiers":[
        {
            "category":"Banks & Credit Unions",
            "subcategory":"Investment Brokerage",
            "type":"Services"
        }
    ],
    "sg:phone":"+1 262 474 0100",
    "sg:postcode":"53024",
    "sg:province":"WI",
    "sg:tags":[
        "advisory",
        "financial"
    ],
    "wof:name":"Actual Financial Solutions",
    "wof:placetype":"venue"
},
  "geometry": {"coordinates":[-87.969819,43.30222],"type":"Point"}
}