{
  "type": "Feature",
  "properties": {
    "iso:country":"US",
    "sg:address":"3630 Grass Lake Rd",
    "sg:city":"Shawano",
    "sg:classifiers":[
        {
            "category":"Manufacturing",
            "subcategory":"Apparel",
            "type":"Manufacturing & Wholesale Goods"
        }
    ],
    "sg:phone":"+1 715 524 2406",
    "sg:postcode":"54166",
    "sg:province":"WI",
    "sg:tags":[
        "sewing",
        "contractor"
    ],
    "wof:name":"Wiscon Sew Inc",
    "wof:placetype":"venue"
},
  "geometry": {"coordinates":[-88.641553,44.717582],"type":"Point"}
}