{
  "type": "Feature",
  "properties": {
    "iso:country":"US",
    "sg:address":"12894 Romadka Ave",
    "sg:city":"Curtiss",
    "sg:classifiers":[
        {
            "category":"Personal",
            "subcategory":"Beauty Salon",
            "type":"Services"
        }
    ],
    "sg:phone":"+1 715 223 2666",
    "sg:postcode":"54422",
    "sg:province":"WI",
    "wof:name":"Untiedt & Untiedt",
    "wof:placetype":"venue"
},
  "geometry": {"coordinates":[-90.454926,44.892274],"type":"Point"}
}