{
  "type": "Feature",
  "properties": {
    "iso:country":"US",
    "sg:address":"4908 Meinders Rd",
    "sg:city":"Mc Farland",
    "sg:classifiers":[
        {
            "category":"Utilities",
            "type":"Services"
        }
    ],
    "sg:phone":"+1 608 819 0572",
    "sg:postcode":"53558",
    "sg:province":"WI",
    "wof:name":"Orin Remediation Tech LLC",
    "wof:placetype":"venue"
},
  "geometry": {"coordinates":[-89.296876,43.035454],"type":"Point"}
}