{
  "type": "Feature",
  "properties": {
    "iso:country":"US",
    "sg:address":"23808 Co Rd K",
    "sg:city":"Brillion",
    "sg:classifiers":[
        {
            "category":"Freight",
            "type":"Transportation"
        }
    ],
    "sg:phone":"+1 920 864 3373",
    "sg:postcode":"54110",
    "sg:province":"WI",
    "sg:tags":[
        "general"
    ],
    "wof:name":"Grove Storage LLC",
    "wof:placetype":"venue"
},
  "geometry": {"coordinates":[-88.042539,44.225974],"type":"Point"}
}