{
  "type": "Feature",
  "properties": {
    "iso:country":"US",
    "sg:address":"2159 Eastridge Ctr",
    "sg:city":"Eau Claire",
    "sg:classifiers":[
        {
            "category":"Restaurant",
            "type":"Food & Drink"
        }
    ],
    "sg:menulink":"http://www.allmenus.com/wi/eau-claire/23690-toppers-pizza/menu/",
    "sg:phone":"+1 608 833 1111",
    "sg:postcode":"54701",
    "sg:province":"WI",
    "sg:tags":[
        "american",
        "pizza"
    ],
    "wof:name":"Topper's Pizza",
    "wof:placetype":"venue"
},
  "geometry": {"coordinates":[-91.463953,44.796243],"type":"Point"}
}