{
  "type": "Feature",
  "properties": {
    "addr:full":"614 Central Ave Deerfield WI 53531",
    "addr:housenumber":"614",
    "addr:postcode":"53531",
    "addr:street":"Central Ave",
    "iso:country":"US",
    "sg:address":"614 Central Ave",
    "sg:city":"Deerfield",
    "sg:classifiers":[
        {
            "category":"Shopping",
            "subcategory":"Gifts & Souvenirs",
            "type":"Retail Goods"
        }
    ],
    "sg:phone":"+1 608 764 8455",
    "sg:postcode":"53531",
    "sg:province":"WI",
    "wof:name":"Fun Lites",
    "wof:placetype":"venue"
},
  "geometry": {"coordinates":[-89.07466100000001,43.06228],"type":"Point"}
}