{
  "type": "Feature",
  "properties": {
    "iso:country":"US",
    "sg:address":"7932 Windermere Ct",
    "sg:city":"Cross Plains",
    "sg:classifiers":[
        {
            "category":"Building & Trades",
            "subcategory":"Construction",
            "type":"Services"
        }
    ],
    "sg:phone":"+1 608 833 4853",
    "sg:postcode":"53528",
    "sg:province":"WI",
    "sg:tags":[
        "house"
    ],
    "wof:name":"Pellett Construction",
    "wof:placetype":"venue"
},
  "geometry": {"coordinates":[-89.599636,43.07893],"type":"Point"}
}