{
  "type": "Feature",
  "properties": {
    "iso:country":"US",
    "sg:address":"34111 Washington Ave",
    "sg:city":"Burlington",
    "sg:classifiers":[
        {
            "category":"Autos & Motor Vehicles",
            "subcategory":"Boat Sales",
            "type":"Retail Goods"
        }
    ],
    "sg:phone":"+1 262 534 4440",
    "sg:postcode":"53105",
    "sg:province":"WI",
    "sg:tags":[
        "propeller"
    ],
    "wof:name":"Pro-Pellers",
    "wof:placetype":"venue"
},
  "geometry": {"coordinates":[-88.288252,42.746411],"type":"Point"}
}