{
  "type": "Feature",
  "properties": {
    "addr:full":"600 W Paradise Dr West Bend WI 53095",
    "addr:housenumber":"600",
    "addr:postcode":"53095",
    "addr:street":"W Paradise Dr",
    "iso:country":"US",
    "sg:address":"600 W Paradise Dr",
    "sg:city":"West Bend",
    "sg:classifiers":[
        {
            "category":"Banks & Credit Unions",
            "subcategory":"Bank",
            "type":"Services"
        }
    ],
    "sg:phone":"+1 262 335 7191",
    "sg:postcode":"53095",
    "sg:province":"WI",
    "wof:name":"Chase",
    "wof:placetype":"venue"
},
  "geometry": {"coordinates":[-88.183036,43.3977],"type":"Point"}
}