{
  "type": "Feature",
  "properties": {
    "addr:full":"106 Dane St Dane WI 53529",
    "addr:housenumber":"106",
    "addr:postcode":"53529",
    "addr:street":"Dane St",
    "iso:country":"US",
    "sg:address":"106 Dane St",
    "sg:city":"Dane",
    "sg:classifiers":[
        {
            "category":"Bars & Pubs",
            "type":"Food & Drink"
        }
    ],
    "sg:phone":"+1 608 849 6275",
    "sg:postcode":"53529",
    "sg:province":"WI",
    "sg:tags":[
        "drinking"
    ],
    "wof:name":"Peg & Doc's Sports Bar & Grill",
    "wof:placetype":"venue"
},
  "geometry": {"coordinates":[-89.499953,43.252075],"type":"Point"}
}