{
  "type": "Feature",
  "properties": {
    "iso:country":"US",
    "sg:address":"647 Lakeland Rd",
    "sg:city":"Shawano",
    "sg:classifiers":[
        {
            "category":"Government",
            "subcategory":"Office",
            "type":"Public Place"
        }
    ],
    "sg:phone":"+1 715 524 2183",
    "sg:postcode":"54166",
    "sg:province":"WI",
    "sg:tags":[
        "forestry"
    ],
    "wof:name":"Forestry Service",
    "wof:placetype":"venue"
},
  "geometry": {"coordinates":[-88.583675,44.775486],"type":"Point"}
}