{
  "type": "Feature",
  "properties": {
    "iso:country":"US",
    "sg:address":"821 W Moreland Blvd",
    "sg:city":"Waukesha",
    "sg:classifiers":[
        {
            "category":"Building & Trades",
            "subcategory":"Landscaping Services",
            "type":"Services"
        }
    ],
    "sg:phone":"+1 262 513 8899",
    "sg:postcode":"53188",
    "sg:province":"WI",
    "sg:tags":[
        "landscape",
        "contractor"
    ],
    "wof:name":"Spring Garden",
    "wof:placetype":"venue"
},
  "geometry": {"coordinates":[-88.24313100000001,43.024798],"type":"Point"}
}