{
  "type": "Feature",
  "properties": {
    "iso:country":"US",
    "sg:address":"2900 Curry Ln",
    "sg:city":"Green Bay",
    "sg:classifiers":[
        {
            "category":"Government",
            "subcategory":"Office",
            "type":"Public Place"
        }
    ],
    "sg:phone":"+1 920 965 0001",
    "sg:postcode":"54311",
    "sg:province":"WI",
    "sg:tags":[
        "federal",
        "affairs",
        "govt",
        "admin"
    ],
    "wof:name":"Us Veterans Affairs Dept",
    "wof:placetype":"venue"
},
  "geometry": {"coordinates":[-87.933435,44.524423],"type":"Point"}
}