{
  "type": "Feature",
  "properties": {
    "iso:country":"US",
    "sg:address":"8010 N 76th St",
    "sg:city":"Milwaukee",
    "sg:classifiers":[
        {
            "category":"Wholesale",
            "subcategory":"Hardware",
            "type":"Manufacturing & Wholesale Goods"
        },
        {
            "category":"Home & Garden",
            "subcategory":"Garden Supply",
            "type":"Retail Goods"
        },
        {
            "category":"Retail",
            "subcategory":"Repair Shop",
            "type":"Services"
        }
    ],
    "sg:phone":"+1 414 355 2900",
    "sg:postcode":"53223",
    "sg:province":"WI",
    "sg:tags":[
        "renting",
        "lawn",
        "outdoor",
        "power",
        "landscaping",
        "equipment-sales",
        "equipment",
        "saw"
    ],
    "sg:website":"http://www.stihldealer.net/default-dealer-007043.aspx",
    "wof:name":"MARTENS RELIABLE TRUE VALUE",
    "wof:placetype":"venue"
},
  "geometry": {"coordinates":[-88.004561,43.163409],"type":"Point"}
}