{
  "type": "Feature",
  "properties": {
    "addr:full":"735 W Wisconsin Ave Milwaukee WI 53233",
    "addr:housenumber":"735",
    "addr:postcode":"53233",
    "addr:street":"W Wisconsin Ave",
    "iso:country":"US",
    "sg:address":"735 W Wisconsin Ave",
    "sg:city":"Milwaukee",
    "sg:classifiers":[
        {
            "category":"Professional",
            "subcategory":"Lawyer & Legal Services",
            "type":"Services"
        }
    ],
    "sg:phone":"+1 414 276 1233",
    "sg:postcode":"53233",
    "sg:province":"WI",
    "sg:tags":[
        "attorney"
    ],
    "wof:name":"Kostich Lebell Dobroski Morgan",
    "wof:placetype":"venue"
},
  "geometry": {"coordinates":[-87.921285,43.038737],"type":"Point"}
}