{
  "type": "Feature",
  "properties": {
    "iso:country":"US",
    "sg:address":"111 N Pioneer Park Rd",
    "sg:city":"Westfield",
    "sg:classifiers":[
        {
            "category":"Autos & Motor Vehicles",
            "subcategory":"Fuel & Gas Station",
            "type":"Retail Goods"
        }
    ],
    "sg:phone":"+1 608 296 2726",
    "sg:postcode":"53964",
    "sg:province":"WI",
    "sg:tags":[
        "station",
        "gasoline"
    ],
    "wof:name":"Amoco",
    "wof:placetype":"venue"
},
  "geometry": {"coordinates":[-89.48522199999999,43.888785],"type":"Point"}
}