{
  "type": "Feature",
  "properties": {
    "addr:full":"15624 Hickory Rd Tomah WI 54660",
    "addr:housenumber":"15624",
    "addr:postcode":"54660",
    "addr:street":"Hickory Rd",
    "iso:country":"US",
    "sg:address":"15624 Hickory Rd",
    "sg:city":"Tomah",
    "sg:classifiers":[
        {
            "category":"Farming",
            "subcategory":"Dairy Farm",
            "type":"Manufacturing & Wholesale Goods"
        }
    ],
    "sg:phone":"+1 608 372 9332",
    "sg:postcode":"54660",
    "sg:province":"WI",
    "wof:name":"Clearview Farms Inc",
    "wof:placetype":"venue"
},
  "geometry": {"coordinates":[-90.474508,43.953265],"type":"Point"}
}