{
  "type": "Feature",
  "properties": {
    "addr:full":"4551 N 41st St Milwaukee WI 53209",
    "addr:housenumber":"4551",
    "addr:postcode":"53209",
    "addr:street":"N 41St St",
    "iso:country":"US",
    "sg:address":"4551 N 41st St",
    "sg:city":"Milwaukee",
    "sg:classifiers":[
        {
            "category":"Social Services",
            "subcategory":"Child Care",
            "type":"Services"
        }
    ],
    "sg:phone":"+1 414 447 9155",
    "sg:postcode":"53209",
    "sg:province":"WI",
    "wof:name":"My Little Stars",
    "wof:placetype":"venue"
},
  "geometry": {"coordinates":[-87.964028,43.099837],"type":"Point"}
}