{
  "type": "Feature",
  "properties": {
    "addr:full":"3136 Hickory Ridge Rd Madison WI 53719",
    "addr:housenumber":"3136",
    "addr:postcode":"53719",
    "addr:street":"Hickory Ridge Rd",
    "iso:country":"US",
    "sg:address":"3136 Hickory Ridge Rd",
    "sg:city":"Madison",
    "sg:classifiers":[
        {
            "category":"Shopping",
            "subcategory":"Bicycles & Sporting Goods",
            "type":"Retail Goods"
        }
    ],
    "sg:phone":"+1 608 848 3750",
    "sg:postcode":"53719",
    "sg:province":"WI",
    "sg:tags":[
        "equipment",
        "golf",
        "supply"
    ],
    "wof:name":"Ages Golf",
    "wof:placetype":"venue"
},
  "geometry": {"coordinates":[-89.52169499999999,43.025015],"type":"Point"}
}