{
  "type": "Feature",
  "properties": {
    "iso:country":"US",
    "sg:address":"215 Martin Luther King Jr Blvd",
    "sg:city":"Madison",
    "sg:classifiers":[
        {
            "category":"Government",
            "subcategory":"Office",
            "type":"Public Place"
        }
    ],
    "sg:phone":"+1 608 267 4933",
    "sg:postcode":"53703",
    "sg:province":"WI",
    "sg:tags":[
        "city",
        "program",
        "adm"
    ],
    "wof:name":"Madison Economic Development",
    "wof:placetype":"venue"
},
  "geometry": {"coordinates":[-89.381372,43.072684],"type":"Point"}
}