{
  "type": "Feature",
  "properties": {
    "iso:country":"US",
    "sg:address":"1900 S Park St",
    "sg:city":"Madison",
    "sg:classifiers":[
        {
            "category":"Shopping",
            "subcategory":"Department Store",
            "type":"Retail Goods"
        }
    ],
    "sg:phone":"+1 608 250 6370",
    "sg:postcode":"53715",
    "sg:province":"WI",
    "wof:name":"St Vincet Depual",
    "wof:placetype":"venue"
},
  "geometry": {"coordinates":[-89.394132,43.046239],"type":"Point"}
}