{
  "type": "Feature",
  "properties": {
    "iso:country":"US",
    "sg:address":"1207 Oak St",
    "sg:city":"Beloit",
    "sg:classifiers":[
        {
            "category":"Building & Trades",
            "subcategory":"Construction",
            "type":"Services"
        }
    ],
    "sg:phone":"+1 608 362 1591",
    "sg:postcode":"53511",
    "sg:province":"WI",
    "sg:tags":[
        "contractor"
    ],
    "wof:name":"Moldenhauer A-1 Plastering",
    "wof:placetype":"venue"
},
  "geometry": {"coordinates":[-89.044392,42.514444],"type":"Point"}
}