{
  "type": "Feature",
  "properties": {
    "iso:country":"US",
    "sg:address":"9863 N Callahan Lake Rd",
    "sg:city":"Hayward",
    "sg:classifiers":[
        {
            "category":"Travel",
            "subcategory":"Hotels & Motels",
            "type":"Entertainment"
        }
    ],
    "sg:phone":"+1 715 462 3244",
    "sg:postcode":"54843",
    "sg:province":"WI",
    "sg:tags":[
        "operation"
    ],
    "wof:name":"Callahan Lake Resort",
    "wof:placetype":"venue"
},
  "geometry": {"coordinates":[-91.235009,45.985681],"type":"Point"}
}