{
  "type": "Feature",
  "properties": {
    "addr:full":"1501 W Main Ave De Pere WI 54115",
    "addr:housenumber":"1501",
    "addr:postcode":"54115",
    "addr:street":"W Main Ave",
    "iso:country":"US",
    "sg:address":"1501 W Main Ave",
    "sg:city":"De Pere",
    "sg:classifiers":[
        {
            "category":"Restaurant",
            "type":"Food & Drink"
        }
    ],
    "sg:menulink":"http://www.allmenus.com/wi/ashwaubenon/204607-taco-bell/menu/",
    "sg:phone":"+1 920 983 0430",
    "sg:postcode":"54115",
    "sg:province":"WI",
    "sg:tags":[
        "mexican"
    ],
    "wof:name":"Taco Bell",
    "wof:placetype":"venue"
},
  "geometry": {"coordinates":[-88.117323,44.462654],"type":"Point"}
}