{
  "type": "Feature",
  "properties": {
    "addr:full":"10787 Co Rd Id Blue Mounds WI 53517",
    "addr:housenumber":"10787",
    "addr:postcode":"53517",
    "addr:street":"Co",
    "iso:country":"US",
    "sg:address":"10787 Co Rd Id",
    "sg:city":"Blue Mounds",
    "sg:classifiers":[
        {
            "category":"Real Estate",
            "subcategory":"Real Estate Agent",
            "type":"Services"
        }
    ],
    "sg:phone":"+1 608 437 2029",
    "sg:postcode":"53517",
    "sg:province":"WI",
    "sg:tags":[
        "appraiser"
    ],
    "wof:name":"J C Ferrill Co",
    "wof:placetype":"venue"
},
  "geometry": {"coordinates":[-89.81734400000001,43.013314],"type":"Point"}
}