{
  "type": "Feature",
  "properties": {
    "iso:country":"US",
    "sg:address":"213 W Main St",
    "sg:city":"Watertown",
    "sg:classifiers":[
        {
            "category":"Personal",
            "subcategory":"Beauty Salon",
            "type":"Services"
        }
    ],
    "sg:phone":"+1 920 261 7372",
    "sg:postcode":"53094",
    "sg:province":"WI",
    "sg:tags":[
        "shop"
    ],
    "wof:name":"American Hairlines",
    "wof:placetype":"venue"
},
  "geometry": {"coordinates":[-88.727036,43.19454],"type":"Point"}
}