{
  "type": "Feature",
  "properties": {
    "iso:country":"US",
    "sg:address":"7896 Ripco Rd",
    "sg:city":"Eagle River",
    "sg:classifiers":[
        {
            "category":"Recreation",
            "type":"Entertainment"
        }
    ],
    "sg:phone":"+1 715 479 1552",
    "sg:postcode":"54521",
    "sg:province":"WI",
    "sg:tags":[
        "animal"
    ],
    "wof:name":"Bits & Wheels Ranch",
    "wof:placetype":"venue"
},
  "geometry": {"coordinates":[-89.2927,45.836119],"type":"Point"}
}