{
  "type": "Feature",
  "properties": {
    "iso:country":"US",
    "sg:address":"3701 Portage Rd",
    "sg:city":"Madison",
    "sg:classifiers":[
        {
            "category":"Professional",
            "type":"Services"
        }
    ],
    "sg:phone":"+1 608 246 0958",
    "sg:postcode":"53704",
    "sg:province":"WI",
    "wof:name":"AG Drew Dist Inc",
    "wof:placetype":"venue"
},
  "geometry": {"coordinates":[-89.308061,43.141494],"type":"Point"}
}