{
  "type": "Feature",
  "properties": {
    "addr:full":"1488 S 84th St Milwaukee WI 53214",
    "addr:housenumber":"1488",
    "addr:postcode":"53214",
    "addr:street":"S 84Th St",
    "iso:country":"US",
    "sg:address":"1488 S 84th St",
    "sg:city":"Milwaukee",
    "sg:classifiers":[
        {
            "category":"Wholesale",
            "subcategory":"Medical Equipment & Supplies",
            "type":"Manufacturing & Wholesale Goods"
        },
        {
            "category":"Health Services",
            "subcategory":"Hospital",
            "type":"Services"
        },
        {
            "category":"Shopping",
            "subcategory":"Pharmacy",
            "type":"Retail Goods"
        }
    ],
    "sg:phone":"+1 414 321 6494",
    "sg:postcode":"53214",
    "sg:province":"WI",
    "sg:tags":[
        "home",
        "wheelchair",
        "care"
    ],
    "wof:name":"Helping Aids Inc.",
    "wof:placetype":"venue"
},
  "geometry": {"coordinates":[-88.017099,43.014232],"type":"Point"}
}