{
  "type": "Feature",
  "properties": {
    "iso:country":"US",
    "sg:address":"6704 Gurnsey Ln",
    "sg:city":"Rhinelander",
    "sg:classifiers":[
        {
            "category":"Freight",
            "type":"Transportation"
        }
    ],
    "sg:phone":"+1 715 272 1566",
    "sg:postcode":"54501",
    "sg:province":"WI",
    "sg:tags":[
        "fixed",
        "motor",
        "facility"
    ],
    "wof:name":"Nicolet Home Inspection",
    "wof:placetype":"venue"
},
  "geometry": {"coordinates":[-89.338484,45.792515],"type":"Point"}
}