{
  "type": "Feature",
  "properties": {
    "iso:country":"US",
    "sg:address":"113 E Towne Mall",
    "sg:city":"Madison",
    "sg:classifiers":[
        {
            "category":"Shopping",
            "subcategory":"Clothing, Apparel, & Fashions",
            "type":"Retail Goods"
        }
    ],
    "sg:phone":"+1 608 246 2115",
    "sg:postcode":"53704",
    "sg:province":"WI",
    "wof:name":"Gadzooks",
    "wof:placetype":"venue"
},
  "geometry": {"coordinates":[-89.30427,43.128088],"type":"Point"}
}