{
  "type": "Feature",
  "properties": {
    "iso:country":"US",
    "sg:address":"8196 Galaxy Dr",
    "sg:city":"Neenah",
    "sg:classifiers":[
        {
            "category":"Building & Trades",
            "subcategory":"Electrical",
            "type":"Services"
        }
    ],
    "sg:phone":"+1 920 836 2032",
    "sg:postcode":"54956",
    "sg:province":"WI",
    "sg:tags":[
        "electrical",
        "contractor"
    ],
    "wof:name":"Electrical Contracting Spec LL",
    "wof:placetype":"venue"
},
  "geometry": {"coordinates":[-88.573245,44.189111],"type":"Point"}
}