{
  "type": "Feature",
  "properties": {
    "addr:full":"1725 S Shore Dr Delavan WI 53115",
    "addr:housenumber":"1725",
    "addr:postcode":"53115",
    "addr:street":"S Shore Dr",
    "iso:country":"US",
    "sg:address":"1725 S Shore Dr",
    "sg:city":"Delavan",
    "sg:classifiers":[
        {
            "category":"Restaurant",
            "type":"Food & Drink"
        }
    ],
    "sg:phone":"+1 262 728 6360",
    "sg:postcode":"53115",
    "sg:province":"WI",
    "sg:tags":[
        "tavern",
        "gift"
    ],
    "wof:name":"Village Supper Club The",
    "wof:placetype":"venue"
},
  "geometry": {"coordinates":[-88.585522,42.614311],"type":"Point"}
}