{
  "type": "Feature",
  "properties": {
    "addr:full":"36185 Abrams St Whitehall WI 54773",
    "addr:housenumber":"36185",
    "addr:postcode":"54773",
    "addr:street":"Abrams St",
    "iso:country":"US",
    "sg:address":"36185 Abrams St",
    "sg:city":"Whitehall",
    "sg:classifiers":[
        {
            "category":"Organizations",
            "subcategory":"Religious Organization",
            "type":"Services"
        }
    ],
    "sg:phone":"+1 715 538 4246",
    "sg:postcode":"54773",
    "sg:province":"WI",
    "sg:tags":[
        "church"
    ],
    "sg:website":"www.fbcwhtl.com",
    "wof:name":"First Baptist Church",
    "wof:placetype":"venue"
},
  "geometry": {"coordinates":[-91.31556999999999,44.365697],"type":"Point"}
}