{
  "type": "Feature",
  "properties": {
    "iso:country":"US",
    "sg:address":"1914 Stewart Ave",
    "sg:city":"Wausau",
    "sg:classifiers":[
        {
            "category":"Restaurant",
            "type":"Food & Drink"
        }
    ],
    "sg:phone":"+1 715 843 6514",
    "sg:postcode":"54401",
    "sg:province":"WI",
    "sg:tags":[
        "shop",
        "coffee"
    ],
    "wof:name":"Krispy Kreme Doughnuts",
    "wof:placetype":"venue"
},
  "geometry": {"coordinates":[-89.660676,44.959083],"type":"Point"}
}