{
  "type": "Feature",
  "properties": {
    "iso:country":"US",
    "sg:address":"2335 Durand Ave",
    "sg:city":"Racine",
    "sg:classifiers":[
        {
            "category":"Manufacturing",
            "subcategory":"Building Materials",
            "type":"Manufacturing & Wholesale Goods"
        }
    ],
    "sg:phone":"+1 262 598 9090",
    "sg:postcode":"53403",
    "sg:province":"WI",
    "sg:tags":[
        "product",
        "mfg",
        "tv",
        "plastic",
        "wood",
        "cabinet",
        "kitchen"
    ],
    "sg:website":"www.sportshelves.com",
    "wof:name":"Laning Custom Design Inc",
    "wof:placetype":"venue"
},
  "geometry": {"coordinates":[-87.808374,42.6969],"type":"Point"}
}