{
  "type": "Feature",
  "properties": {
    "iso:country":"US",
    "sg:address":"648 US Hwy 51",
    "sg:city":"Arlington",
    "sg:classifiers":[
        {
            "category":"Farming",
            "subcategory":"Livestock Farm",
            "type":"Manufacturing & Wholesale Goods"
        }
    ],
    "sg:phone":"+1 608 846 5589",
    "sg:postcode":"53911",
    "sg:province":"WI",
    "wof:name":"Ronald Klahn",
    "wof:placetype":"venue"
},
  "geometry": {"coordinates":[-89.32473299999999,43.297329],"type":"Point"}
}