{
  "type": "Feature",
  "properties": {
    "iso:country":"US",
    "sg:address":"911 E Main St",
    "sg:city":"Merrill",
    "sg:classifiers":[
        {
            "category":"Personal",
            "subcategory":"Beauty Salon",
            "type":"Services"
        }
    ],
    "sg:phone":"+1 715 536 1345",
    "sg:postcode":"54452",
    "sg:province":"WI",
    "sg:tags":[
        "shop"
    ],
    "wof:name":"Images Hair and Tanning",
    "wof:placetype":"venue"
},
  "geometry": {"coordinates":[-89.686169,45.180041],"type":"Point"}
}