{
  "type": "Feature",
  "properties": {
    "iso:country":"US",
    "sg:address":"3947 N 11th St",
    "sg:city":"Milwaukee",
    "sg:classifiers":[
        {
            "category":"Building & Trades",
            "subcategory":"Construction",
            "type":"Services"
        }
    ],
    "sg:phone":"+1 414 562 0647",
    "sg:postcode":"53206",
    "sg:province":"WI",
    "sg:tags":[
        "home",
        "improvement"
    ],
    "wof:name":"Hughes Remodeling Co",
    "wof:placetype":"venue"
},
  "geometry": {"coordinates":[-87.92474199999999,43.087305],"type":"Point"}
}