{
  "type": "Feature",
  "properties": {
    "addr:full":"228 S 1st St Milwaukee WI 53204",
    "addr:housenumber":"228",
    "addr:postcode":"53204",
    "addr:street":"S 1St St",
    "iso:country":"US",
    "sg:address":"228 S 1st St",
    "sg:city":"Milwaukee",
    "sg:classifiers":[
        {
            "category":"Professional",
            "subcategory":"Art Services",
            "type":"Services"
        }
    ],
    "sg:phone":"+1 414 481 4461",
    "sg:postcode":"53204",
    "sg:province":"WI",
    "sg:tags":[
        "artist"
    ],
    "wof:name":"Jeff Raasch Studio",
    "wof:placetype":"venue"
},
  "geometry": {"coordinates":[-87.910933,43.02854],"type":"Point"}
}