{
  "type": "Feature",
  "properties": {
    "addr:full":"6324 Co Rd G Scandinavia WI 54977",
    "addr:housenumber":"6324",
    "addr:postcode":"54977",
    "addr:street":"Co Rd",
    "iso:country":"US",
    "sg:address":"6324 Co Rd G",
    "sg:city":"Scandinavia",
    "sg:classifiers":[
        {
            "category":"Home & Garden",
            "subcategory":"Garden Supply",
            "type":"Retail Goods"
        }
    ],
    "sg:phone":"+1 715 467 2801",
    "sg:postcode":"54977",
    "sg:province":"WI",
    "sg:tags":[
        "fertilizer",
        "organic",
        "natural",
        "cosmetic"
    ],
    "wof:name":"Center For Natural Living",
    "wof:placetype":"venue"
},
  "geometry": {"coordinates":[-89.15383,44.470964],"type":"Point"}
}