{
  "type": "Feature",
  "properties": {
    "iso:country":"US",
    "sg:address":"2014 Harrison St",
    "sg:city":"Oshkosh",
    "sg:classifiers":[
        {
            "category":"Utilities",
            "subcategory":"Fuel Oil & Lpg",
            "type":"Services"
        }
    ],
    "sg:phone":"+1 920 231 5210",
    "sg:postcode":"54901",
    "sg:province":"WI",
    "sg:tags":[
        "propane",
        "gas"
    ],
    "wof:name":"Thermogas Co",
    "wof:placetype":"venue"
},
  "geometry": {"coordinates":[-88.532616,44.042547],"type":"Point"}
}