{
  "type": "Feature",
  "properties": {
    "addr:full":"10923 W Lincoln Ave Milwaukee WI 53227",
    "addr:housenumber":"10923",
    "addr:postcode":"53227",
    "addr:street":"W Lincoln Ave",
    "iso:country":"US",
    "sg:address":"10923 W Lincoln Ave",
    "sg:city":"Milwaukee",
    "sg:classifiers":[
        {
            "category":"Personal",
            "subcategory":"Beauty Salon",
            "type":"Services"
        }
    ],
    "sg:phone":"+1 414 545 8180",
    "sg:postcode":"53227",
    "sg:province":"WI",
    "sg:tags":[
        "shop"
    ],
    "wof:name":"Capello",
    "wof:placetype":"venue"
},
  "geometry": {"coordinates":[-88.049161,43.002526],"type":"Point"}
}