{
  "type": "Feature",
  "properties": {
    "iso:country":"US",
    "sg:address":"207 S Broadway St",
    "sg:city":"Stanley",
    "sg:classifiers":[
        {
            "category":"Bars & Pubs",
            "type":"Food & Drink"
        }
    ],
    "sg:phone":"+1 715 644 5841",
    "sg:postcode":"54768",
    "sg:province":"WI",
    "sg:tags":[
        "drinking"
    ],
    "wof:name":"Buzzys Bar & Grille",
    "wof:placetype":"venue"
},
  "geometry": {"coordinates":[-90.937578,44.958704],"type":"Point"}
}