{
  "type": "Feature",
  "properties": {
    "iso:country":"US",
    "sg:address":"701 E High St",
    "sg:city":"Milton",
    "sg:classifiers":[
        {
            "category":"Professional",
            "subcategory":"Business Services",
            "type":"Services"
        }
    ],
    "sg:phone":"+1 608 868 7719",
    "sg:postcode":"53563",
    "sg:province":"WI",
    "sg:tags":[
        "management",
        "real estate"
    ],
    "wof:name":"Sommers Appraisal",
    "wof:placetype":"venue"
},
  "geometry": {"coordinates":[-88.939066,42.772805],"type":"Point"}
}