{
  "type": "Feature",
  "properties": {
    "iso:country":"US",
    "sg:address":"6991 US Hwy 10",
    "sg:city":"Arkansaw",
    "sg:classifiers":[
        {
            "category":"Building & Trades",
            "subcategory":"Construction",
            "type":"Services"
        }
    ],
    "sg:phone":"+1 715 672 5341",
    "sg:postcode":"54721",
    "sg:province":"WI",
    "sg:tags":[
        "residential"
    ],
    "wof:name":"Sievwright Construction Inc",
    "wof:placetype":"venue"
},
  "geometry": {"coordinates":[-91.999398,44.634588],"type":"Point"}
}