{
  "type": "Feature",
  "properties": {
    "iso:country":"US",
    "sg:address":"1024 W Burnett St",
    "sg:city":"Beaver Dam",
    "sg:classifiers":[
        {
            "category":"Real Estate",
            "subcategory":"Real Estate Agent",
            "type":"Services"
        }
    ],
    "sg:phone":"+1 920 887 0561",
    "sg:postcode":"53916",
    "sg:province":"WI",
    "wof:name":"Daniels Realty",
    "wof:placetype":"venue"
},
  "geometry": {"coordinates":[-88.850194,43.466111],"type":"Point"}
}