{
  "type": "Feature",
  "properties": {
    "addr:full":"14999 W Beloit Rd New Berlin WI 53151",
    "addr:housenumber":"14999",
    "addr:postcode":"53151",
    "addr:street":"W Beloit Rd",
    "iso:country":"US",
    "sg:address":"14999 W Beloit Rd",
    "sg:city":"New Berlin",
    "sg:classifiers":[
        {
            "category":"Restaurant",
            "type":"Food & Drink"
        }
    ],
    "sg:menulink":"http://www.allmenus.com/wi/new-berlin/145669-subway/menu/",
    "sg:phone":"+1 414 427 1100",
    "sg:postcode":"53151",
    "sg:province":"WI",
    "sg:tags":[
        "american",
        "sandwich"
    ],
    "wof:name":"Subway",
    "wof:placetype":"venue"
},
  "geometry": {"coordinates":[-88.10245,42.954017],"type":"Point"}
}