{
  "type": "Feature",
  "properties": {
    "iso:country":"US",
    "sg:address":"3203 S 54th St",
    "sg:city":"Milwaukee",
    "sg:classifiers":[
        {
            "category":"Building & Trades",
            "subcategory":"Cleaning & Sanitation",
            "type":"Services"
        }
    ],
    "sg:phone":"+1 414 545 3691",
    "sg:postcode":"53219",
    "sg:province":"WI",
    "sg:tags":[
        "maintenance"
    ],
    "wof:name":"Cleaner Corners",
    "wof:placetype":"venue"
},
  "geometry": {"coordinates":[-87.981705,42.984828],"type":"Point"}
}