{
  "type": "Feature",
  "properties": {
    "iso:country":"US",
    "sg:address":"113 W Fulton St",
    "sg:city":"Waupaca",
    "sg:classifiers":[
        {
            "category":"Personal",
            "subcategory":"Barber",
            "type":"Services"
        }
    ],
    "sg:phone":"+1 715 258 3662",
    "sg:postcode":"54981",
    "sg:province":"WI",
    "wof:name":"Charlie's Barber Shop",
    "wof:placetype":"venue"
},
  "geometry": {"coordinates":[-89.085021,44.357871],"type":"Point"}
}