{
  "type": "Feature",
  "properties": {
    "iso:country":"US",
    "sg:address":"3609 N Maryland Ave",
    "sg:city":"Milwaukee",
    "sg:classifiers":[
        {
            "category":"Shopping",
            "subcategory":"Musical Instruments",
            "type":"Retail Goods"
        }
    ],
    "sg:phone":"+1 414 332 2988",
    "sg:postcode":"53211",
    "sg:province":"WI",
    "wof:name":"Thomas Miller & Assoc",
    "wof:placetype":"venue"
},
  "geometry": {"coordinates":[-87.882693,43.084977],"type":"Point"}
}