{
  "type": "Feature",
  "properties": {
    "iso:country":"US",
    "sg:address":"2845 11th Dr",
    "sg:city":"Adams",
    "sg:classifiers":[
        {
            "category":"Building & Trades",
            "subcategory":"Construction",
            "type":"Services"
        }
    ],
    "sg:phone":"+1 608 339 7014",
    "sg:postcode":"53910",
    "sg:province":"WI",
    "sg:tags":[
        "concrete",
        "contractor"
    ],
    "wof:name":"Douglas Sunderlage Constr",
    "wof:placetype":"venue"
},
  "geometry": {"coordinates":[-89.80717,43.841324],"type":"Point"}
}