{
  "type": "Feature",
  "properties": {
    "addr:full":"2115 Co Rd A Baraboo WI 53913",
    "addr:housenumber":"2115",
    "addr:postcode":"53913",
    "addr:street":"Co Rd",
    "iso:country":"US",
    "sg:address":"2115 Co Rd A",
    "sg:city":"Baraboo",
    "sg:phone":"+1 608 356 6830",
    "sg:postcode":"53913",
    "sg:province":"WI",
    "sg:tags":[
        "farm",
        "field",
        "crop",
        "soybean"
    ],
    "wof:name":"Ronald Wormet",
    "wof:placetype":"venue"
},
  "geometry": {"coordinates":[-89.742587,43.589309],"type":"Point"}
}