{
  "type": "Feature",
  "properties": {
    "iso:country":"US",
    "sg:address":"2841 Mecca Dr",
    "sg:city":"Plover",
    "sg:classifiers":[
        {
            "category":"Building & Trades",
            "subcategory":"Construction",
            "type":"Services"
        }
    ],
    "sg:phone":"+1 715 345 0705",
    "sg:postcode":"54467",
    "sg:province":"WI",
    "sg:tags":[
        "contractor"
    ],
    "wof:name":"Lepak Builders Inc",
    "wof:placetype":"venue"
},
  "geometry": {"coordinates":[-89.536513,44.460402],"type":"Point"}
}