{
  "type": "Feature",
  "properties": {
    "iso:country":"US",
    "sg:address":"1116 N Jackson St",
    "sg:city":"Milwaukee",
    "sg:classifiers":[
        {
            "category":"Personal",
            "subcategory":"Beauty Salon",
            "type":"Services"
        }
    ],
    "sg:phone":"+1 414 276 1188",
    "sg:postcode":"53202",
    "sg:province":"WI",
    "wof:name":"Emmy's Studio 101",
    "wof:placetype":"venue"
},
  "geometry": {"coordinates":[-87.90470000000001,43.045285],"type":"Point"}
}