{
  "type": "Feature",
  "properties": {
    "iso:country":"US",
    "sg:address":"6076 Lake Rd",
    "sg:city":"Oshkosh",
    "sg:classifiers":[
        {
            "category":"Utilities",
            "subcategory":"Cable",
            "type":"Services"
        }
    ],
    "sg:phone":"+1 920 688 3400",
    "sg:postcode":"54902",
    "sg:province":"WI",
    "sg:tags":[
        "television"
    ],
    "wof:name":"Americable Media Group Inc",
    "wof:placetype":"venue"
},
  "geometry": {"coordinates":[-88.480057,43.931302],"type":"Point"}
}