{
  "type": "Feature",
  "properties": {
    "iso:country":"US",
    "sg:address":"603 N Water St",
    "sg:city":"Sparta",
    "sg:classifiers":[
        {
            "category":"Travel",
            "subcategory":"Hotels & Motels",
            "type":"Entertainment"
        }
    ],
    "sg:phone":"+1 608 269 7878",
    "sg:postcode":"54656",
    "sg:province":"WI",
    "sg:tags":[
        "breakfast",
        "accommodation",
        "bed"
    ],
    "wof:name":"Strawberry Lace Inn B & B",
    "wof:placetype":"venue"
},
  "geometry": {"coordinates":[-90.81084,43.950796],"type":"Point"}
}