{
  "type": "Feature",
  "properties": {
    "iso:country":"US",
    "sg:address":"7 S 1st St",
    "sg:city":"Barron",
    "sg:classifiers":[
        {
            "category":"Restaurant",
            "type":"Food & Drink"
        }
    ],
    "sg:phone":"+1 715 537 6600",
    "sg:postcode":"54812",
    "sg:province":"WI",
    "sg:tags":[
        "eating"
    ],
    "wof:name":"Subway",
    "wof:placetype":"venue"
},
  "geometry": {"coordinates":[-91.85667599999999,45.401388],"type":"Point"}
}