{
  "type": "Feature",
  "properties": {
    "iso:country":"US",
    "sg:address":"4823 W Bradley Rd",
    "sg:city":"Milwaukee",
    "sg:classifiers":[
        {
            "category":"Personal",
            "subcategory":"Beauty Salon",
            "type":"Services"
        }
    ],
    "sg:phone":"+1 414 362 0345",
    "sg:postcode":"53223",
    "sg:province":"WI",
    "wof:name":"Jeanette's Total Creations",
    "wof:placetype":"venue"
},
  "geometry": {"coordinates":[-87.974448,43.163057],"type":"Point"}
}