{
  "type": "Feature",
  "properties": {
    "iso:country":"US",
    "sg:address":"3388 Bay Ridge Ct",
    "sg:city":"Oneida",
    "sg:classifiers":[
        {
            "category":"Professional",
            "type":"Services"
        }
    ],
    "sg:phone":"+1 920 869 1451",
    "sg:postcode":"54155",
    "sg:province":"WI",
    "wof:name":"Cellcom Bcmsa",
    "wof:placetype":"venue"
},
  "geometry": {"coordinates":[-88.164009,44.510139],"type":"Point"}
}