{
  "type": "Feature",
  "properties": {
    "iso:country":"US",
    "sg:address":"805 Maple Dr",
    "sg:city":"Campbellsport",
    "sg:classifiers":[
        {
            "category":"Building & Trades",
            "subcategory":"Construction",
            "type":"Services"
        }
    ],
    "sg:phone":"+1 920 533 8804",
    "sg:postcode":"53010",
    "sg:province":"WI",
    "sg:tags":[
        "excavation",
        "contractor"
    ],
    "wof:name":"Flasch Excavating and Cnstr",
    "wof:placetype":"venue"
},
  "geometry": {"coordinates":[-88.260261,43.568524],"type":"Point"}
}