{
  "type": "Feature",
  "properties": {
    "addr:full":"1417 Parkview Dr Kewaskum WI 53040",
    "addr:housenumber":"1417",
    "addr:postcode":"53040",
    "addr:street":"Parkview Dr",
    "iso:country":"US",
    "sg:address":"1417 Parkview Dr",
    "sg:city":"Kewaskum",
    "sg:classifiers":[
        {
            "category":"Education",
            "subcategory":"School",
            "type":"Public Place"
        }
    ],
    "sg:phone":"+1 262 626 2680",
    "sg:postcode":"53040",
    "sg:province":"WI",
    "wof:name":"St Lucas Lutheran Church-Schl",
    "wof:placetype":"venue"
},
  "geometry": {"coordinates":[-88.22311999999999,43.522267],"type":"Point"}
}