{
  "type": "Feature",
  "properties": {
    "addr:full":"1317 E Academy St Stoughton WI 53589",
    "addr:housenumber":"1317",
    "addr:postcode":"53589",
    "addr:street":"E Academy St",
    "iso:country":"US",
    "sg:address":"1317 E Academy St",
    "sg:city":"Stoughton",
    "sg:classifiers":[
        {
            "category":"Wholesale",
            "subcategory":"Auto Parts",
            "type":"Manufacturing & Wholesale Goods"
        }
    ],
    "sg:phone":"+1 608 873 1212",
    "sg:postcode":"53589",
    "sg:province":"WI",
    "sg:tags":[
        "automobile",
        "wrecking"
    ],
    "wof:name":"Schmidt's Auto Inc",
    "wof:placetype":"venue"
},
  "geometry": {"coordinates":[-89.20251,42.911232],"type":"Point"}
}