{
  "type": "Feature",
  "properties": {
    "iso:country":"US",
    "sg:address":"108 N Park Rd",
    "sg:city":"Stanley",
    "sg:classifiers":[
        {
            "category":"Autos & Motor Vehicles",
            "subcategory":"Auto Supplies",
            "type":"Retail Goods"
        }
    ],
    "sg:phone":"+1 715 644 5849",
    "sg:postcode":"54768",
    "sg:province":"WI",
    "wof:name":"Stanley Tire Center",
    "wof:placetype":"venue"
},
  "geometry": {"coordinates":[-90.941892,44.967711],"type":"Point"}
}