{
  "type": "Feature",
  "properties": {
    "iso:country":"US",
    "sg:address":"2606 N Packerland Dr",
    "sg:city":"Green Bay",
    "sg:classifiers":[
        {
            "category":"Autos & Motor Vehicles",
            "subcategory":"Automobile Sales",
            "type":"Retail Goods"
        }
    ],
    "sg:phone":"+1 920 499 8000",
    "sg:postcode":"54303",
    "sg:province":"WI",
    "sg:tags":[
        "car",
        "dealer"
    ],
    "wof:name":"West Town Auto",
    "wof:placetype":"venue"
},
  "geometry": {"coordinates":[-88.090549,44.542315],"type":"Point"}
}