{
  "type": "Feature",
  "properties": {
    "addr:full":"2688 Packerland Dr Green Bay WI 54313",
    "addr:housenumber":"2688",
    "addr:postcode":"54313",
    "addr:street":"Packerland Dr",
    "iso:country":"US",
    "sg:address":"2688 Packerland Dr",
    "sg:city":"Green Bay",
    "sg:classifiers":[
        {
            "category":"Autos & Motor Vehicles",
            "subcategory":"Automobile Sales",
            "type":"Retail Goods"
        }
    ],
    "sg:phone":"+1 920 496 3400",
    "sg:postcode":"54313",
    "sg:province":"WI",
    "sg:tags":[
        "car",
        "dealer"
    ],
    "wof:name":"M-R Sales",
    "wof:placetype":"venue"
},
  "geometry": {"coordinates":[-88.10879300000001,44.489298],"type":"Point"}
}