{
  "type": "Feature",
  "properties": {
    "addr:full":"3410 Skylark Ln Wausau WI 54401",
    "addr:housenumber":"3410",
    "addr:postcode":"54401",
    "addr:street":"Skylark Ln",
    "iso:country":"US",
    "sg:address":"3410 Skylark Ln",
    "sg:city":"Wausau",
    "sg:classifiers":[
        {
            "category":"Wholesale",
            "subcategory":"Chemicals & Plastics",
            "type":"Manufacturing & Wholesale Goods"
        }
    ],
    "sg:phone":"+1 715 849 1320",
    "sg:postcode":"54401",
    "sg:province":"WI",
    "sg:tags":[
        "product",
        "mfg"
    ],
    "wof:name":"Eaton Aeroquip Inc",
    "wof:placetype":"venue"
},
  "geometry": {"coordinates":[-89.68068599999999,44.939719],"type":"Point"}
}