{
  "type": "Feature",
  "properties": {
    "iso:country":"US",
    "sg:address":"2222 63rd St",
    "sg:city":"Kenosha",
    "sg:classifiers":[
        {
            "category":"Professional",
            "subcategory":"Computer Services",
            "type":"Services"
        }
    ],
    "sg:phone":"+1 262 652 2727",
    "sg:postcode":"53143",
    "sg:province":"WI",
    "sg:tags":[
        "consultant",
        "designer",
        "design",
        "system"
    ],
    "wof:name":"Omnicadd Inc",
    "wof:placetype":"venue"
},
  "geometry": {"coordinates":[-87.83656999999999,42.577723],"type":"Point"}
}