{
  "type": "Feature",
  "properties": {
    "iso:country":"US",
    "sg:address":"655 Trumpeter Trl",
    "sg:city":"De Pere",
    "sg:classifiers":[
        {
            "category":"Real Estate",
            "subcategory":"Real Estate Services",
            "type":"Services"
        }
    ],
    "sg:phone":"+1 920 330 0475",
    "sg:postcode":"54115",
    "sg:province":"WI",
    "sg:tags":[
        "company",
        "title"
    ],
    "wof:name":"Mark Porter",
    "wof:placetype":"venue"
},
  "geometry": {"coordinates":[-88.033408,44.435073],"type":"Point"}
}