{
  "type": "Feature",
  "properties": {
    "iso:country":"US",
    "sg:address":"6410 Enterprise Ln",
    "sg:city":"Madison",
    "sg:classifiers":[
        {
            "category":"Insurance",
            "subcategory":"Insurance Agent",
            "type":"Services"
        }
    ],
    "sg:phone":"+1 608 298 8000",
    "sg:postcode":"53719",
    "sg:province":"WI",
    "wof:name":"National Specialty Insurance",
    "wof:placetype":"venue"
},
  "geometry": {"coordinates":[-89.490568,43.057802],"type":"Point"}
}