{
  "type": "Feature",
  "properties": {
    "iso:country":"US",
    "sg:address":"8008 Wilson Lake Rd",
    "sg:city":"Phillips",
    "sg:classifiers":[
        {
            "category":"Shopping",
            "subcategory":"Computers & Home Electronics",
            "type":"Retail Goods"
        }
    ],
    "sg:phone":"+1 715 339 3132",
    "sg:postcode":"54555",
    "sg:province":"WI",
    "sg:tags":[
        "equipment",
        "video"
    ],
    "wof:name":"Eagle Video Svc",
    "wof:placetype":"venue"
},
  "geometry": {"coordinates":[-90.467269,45.658077],"type":"Point"}
}