{
  "type": "Feature",
  "properties": {
    "iso:country":"US",
    "sg:address":"103 Owen Rd",
    "sg:city":"Madison",
    "sg:classifiers":[
        {
            "category":"Shopping",
            "subcategory":"Gifts & Souvenirs",
            "type":"Retail Goods"
        }
    ],
    "sg:phone":"+1 608 222 7666",
    "sg:postcode":"53716",
    "sg:province":"WI",
    "wof:name":"Youngers Bllons Cstm Imprnting",
    "wof:placetype":"venue"
},
  "geometry": {"coordinates":[-89.327123,43.057096],"type":"Point"}
}