{
  "type": "Feature",
  "properties": {
    "addr:full":"123 S Falls St River Falls WI 54022",
    "addr:housenumber":"123",
    "addr:postcode":"54022",
    "addr:street":"S Falls St",
    "iso:country":"US",
    "sg:address":"123 S Falls St",
    "sg:city":"River Falls",
    "sg:classifiers":[
        {
            "category":"Health Services",
            "subcategory":"Health Practitioner",
            "type":"Services"
        }
    ],
    "sg:phone":"+1 715 426 4967",
    "sg:postcode":"54022",
    "sg:province":"WI",
    "sg:tags":[
        "psychologist"
    ],
    "wof:name":"Loretta P Henson PHD",
    "wof:placetype":"venue"
},
  "geometry": {"coordinates":[-92.63362100000001,44.858616],"type":"Point"}
}