{
  "type": "Feature",
  "properties": {
    "addr:full":"1906 Northview Rd Waukesha WI 53188",
    "addr:housenumber":"1906",
    "addr:postcode":"53188",
    "addr:street":"Northview Rd",
    "iso:country":"US",
    "sg:address":"1906 Northview Rd",
    "sg:city":"Waukesha",
    "sg:classifiers":[
        {
            "category":"Professional",
            "subcategory":"Business Services",
            "type":"Services"
        }
    ],
    "sg:phone":"+1 262 446 2089",
    "sg:postcode":"53188",
    "sg:province":"WI",
    "wof:name":"AMP Enterprises LLC",
    "wof:placetype":"venue"
},
  "geometry": {"coordinates":[-88.258619,43.032107],"type":"Point"}
}