{
  "type": "Feature",
  "properties": {
    "iso:country":"US",
    "sg:address":"401 N Pelham St",
    "sg:city":"Rhinelander",
    "sg:classifiers":[
        {
            "category":"Health Services",
            "subcategory":"Chiropractor",
            "type":"Services"
        }
    ],
    "sg:phone":"+1 715 362 2300",
    "sg:postcode":"54501",
    "sg:province":"WI",
    "sg:website":"www.advancedhealth.topchiro.com",
    "wof:name":"Advanced Health-Bergman Kopp",
    "wof:placetype":"venue"
},
  "geometry": {"coordinates":[-89.409874,45.643573],"type":"Point"}
}