{
  "type": "Feature",
  "properties": {
    "iso:country":"US",
    "sg:address":"2205 Wisconsin Ave",
    "sg:city":"New Holstein",
    "sg:classifiers":[
        {
            "category":"Banks & Credit Unions",
            "subcategory":"Bank",
            "type":"Services"
        }
    ],
    "sg:phone":"+1 920 898 5737",
    "sg:postcode":"53061",
    "sg:province":"WI",
    "sg:tags":[
        "mortgage"
    ],
    "wof:name":"Bank Mutual",
    "wof:placetype":"venue"
},
  "geometry": {"coordinates":[-88.096705,43.949665],"type":"Point"}
}