{
  "type": "Feature",
  "properties": {
    "iso:country":"US",
    "sg:address":"1200 Washington Rd",
    "sg:city":"Stoughton",
    "sg:classifiers":[
        {
            "category":"Building & Trades",
            "subcategory":"Construction",
            "type":"Services"
        }
    ],
    "sg:phone":"+1 608 873 6396",
    "sg:postcode":"53589",
    "sg:province":"WI",
    "sg:tags":[
        "residential"
    ],
    "wof:name":"Reinstad Construction",
    "wof:placetype":"venue"
},
  "geometry": {"coordinates":[-89.13187499999999,42.912572],"type":"Point"}
}