{
  "type": "Feature",
  "properties": {
    "addr:full":"2325 S Kinnickinnic Ave Milwaukee WI 53207",
    "addr:housenumber":"2325",
    "addr:postcode":"53207",
    "addr:street":"S Kinnickinnic Ave",
    "iso:country":"US",
    "sg:address":"2325 S Kinnickinnic Ave",
    "sg:city":"Milwaukee",
    "sg:classifiers":[
        {
            "category":"Shopping",
            "subcategory":"Bicycles & Sporting Goods",
            "type":"Retail Goods"
        }
    ],
    "sg:phone":"+1 414 486 1641",
    "sg:postcode":"53207",
    "sg:province":"WI",
    "sg:tags":[
        "equipment",
        "skateboard"
    ],
    "wof:name":"Cheepsk8s",
    "wof:placetype":"venue"
},
  "geometry": {"coordinates":[-87.903756,43.002315],"type":"Point"}
}