{
  "type": "Feature",
  "properties": {
    "iso:country":"US",
    "sg:address":"8815 Brian Dr",
    "sg:city":"Rothschild",
    "sg:classifiers":[
        {
            "category":"Real Estate",
            "subcategory":"Real Estate Agent",
            "type":"Services"
        }
    ],
    "sg:phone":"+1 715 359 0800",
    "sg:postcode":"54474",
    "sg:province":"WI",
    "wof:name":"Smart Move Realty",
    "wof:placetype":"venue"
},
  "geometry": {"coordinates":[-89.603691,44.877156],"type":"Point"}
}