{
  "type": "Feature",
  "properties": {
    "iso:country":"US",
    "sg:address":"105 Lyons St",
    "sg:city":"Marquette",
    "sg:classifiers":[
        {
            "category":"Restaurant",
            "type":"Food & Drink"
        }
    ],
    "sg:phone":"+1 920 394 3800",
    "sg:postcode":"53947",
    "sg:province":"WI",
    "wof:name":"Pub N Prime",
    "wof:placetype":"venue"
},
  "geometry": {"coordinates":[-89.139394,43.746018],"type":"Point"}
}