{
  "type": "Feature",
  "properties": {
    "iso:country":"US",
    "sg:address":"34009 118th St",
    "sg:city":"Twin Lakes",
    "sg:classifiers":[
        {
            "category":"Shopping",
            "subcategory":"Florist",
            "type":"Retail Goods"
        }
    ],
    "sg:phone":"+1 262 877 3630",
    "sg:postcode":"53181",
    "sg:province":"WI",
    "wof:name":"Flowers by Design",
    "wof:placetype":"venue"
},
  "geometry": {"coordinates":[-88.22192099999999,42.507055],"type":"Point"}
}