{
  "type": "Feature",
  "properties": {
    "addr:full":"2781 N 71st St Milwaukee WI 53210",
    "addr:housenumber":"2781",
    "addr:postcode":"53210",
    "addr:street":"N 71St St",
    "iso:country":"US",
    "sg:address":"2781 N 71st St",
    "sg:city":"Milwaukee",
    "sg:classifiers":[
        {
            "category":"Professional",
            "subcategory":"Management & Consulting",
            "type":"Services"
        }
    ],
    "sg:phone":"+1 414 456 8778",
    "sg:postcode":"53210",
    "sg:province":"WI",
    "wof:name":"Owen W Griffith",
    "wof:placetype":"venue"
},
  "geometry": {"coordinates":[-88.000685,43.07062],"type":"Point"}
}