{
  "type": "Feature",
  "properties": {
    "iso:country":"US",
    "sg:address":"26858 Marshall Rd",
    "sg:city":"Cashton",
    "sg:classifiers":[
        {
            "category":"Recreation",
            "type":"Entertainment"
        }
    ],
    "sg:phone":"+1 608 654 7401",
    "sg:postcode":"54619",
    "sg:province":"WI",
    "wof:name":"Flavor Trip Concessions",
    "wof:placetype":"venue"
},
  "geometry": {"coordinates":[-90.767247,43.794003],"type":"Point"}
}