{
  "type": "Feature",
  "properties": {
    "iso:country":"US",
    "sg:address":"926 Ann Ct",
    "sg:city":"Belleville",
    "sg:classifiers":[
        {
            "category":"Communications",
            "type":"Services"
        }
    ],
    "sg:phone":"+1 608 424 6174",
    "sg:postcode":"53508",
    "sg:province":"WI",
    "sg:tags":[
        "communication"
    ],
    "wof:name":"Excel Communications",
    "wof:placetype":"venue"
},
  "geometry": {"coordinates":[-89.538082,42.874577],"type":"Point"}
}