{
  "type": "Feature",
  "properties": {
    "iso:country":"US",
    "sg:address":"690 W 3rd Ave",
    "sg:city":"Oshkosh",
    "sg:classifiers":[
        {
            "category":"Building & Trades",
            "subcategory":"Electrical",
            "type":"Services"
        }
    ],
    "sg:phone":"+1 920 233 7191",
    "sg:postcode":"54902",
    "sg:province":"WI",
    "sg:tags":[
        "electrical",
        "contractor"
    ],
    "wof:name":"T Ruck Electric Inc",
    "wof:placetype":"venue"
},
  "geometry": {"coordinates":[-88.553629,44.015496],"type":"Point"}
}