{
  "type": "Feature",
  "properties": {
    "addr:full":"7615 Strauss Ct Shawano WI 54166",
    "addr:housenumber":"7615",
    "addr:postcode":"54166",
    "addr:street":"Strauss Ct",
    "iso:country":"US",
    "sg:address":"7615 Strauss Ct",
    "sg:city":"Shawano",
    "sg:classifiers":[
        {
            "category":"Personal",
            "type":"Services"
        }
    ],
    "sg:phone":"+1 715 526 5923",
    "sg:postcode":"54166",
    "sg:province":"WI",
    "wof:name":"Natural Body Works",
    "wof:placetype":"venue"
},
  "geometry": {"coordinates":[-88.62677100000001,44.847539],"type":"Point"}
}