{
  "type": "Feature",
  "properties": {
    "addr:full":"130 E Blackhawk Ave Prairie Du Chien WI 53821",
    "addr:housenumber":"130",
    "addr:postcode":"53821",
    "addr:street":"E Blackhawk Ave",
    "iso:country":"US",
    "sg:address":"130 E Blackhawk Ave",
    "sg:city":"Prairie Du Chien",
    "sg:classifiers":[
        {
            "category":"Shopping",
            "subcategory":"Gifts & Souvenirs",
            "type":"Retail Goods"
        }
    ],
    "sg:phone":"+1 608 326 2315",
    "sg:postcode":"53821",
    "sg:province":"WI",
    "sg:tags":[
        "shop"
    ],
    "wof:name":"Country Roads",
    "wof:placetype":"venue"
},
  "geometry": {"coordinates":[-91.145405,43.051787],"type":"Point"}
}