{
  "type": "Feature",
  "properties": {
    "addr:full":"5970 Humboldt Rd Luxemburg WI 54217",
    "addr:housenumber":"5970",
    "addr:postcode":"54217",
    "addr:street":"Humboldt Rd",
    "iso:country":"US",
    "sg:address":"5970 Humboldt Rd",
    "sg:city":"Luxemburg",
    "sg:classifiers":[
        {
            "category":"Restaurant",
            "type":"Food & Drink"
        }
    ],
    "sg:phone":"+1 920 845 2881",
    "sg:postcode":"54217",
    "sg:province":"WI",
    "sg:tags":[
        "tavern"
    ],
    "wof:name":"Davister Whipp Bar & Food",
    "wof:placetype":"venue"
},
  "geometry": {"coordinates":[-87.775301,44.501812],"type":"Point"}
}