{
  "type": "Feature",
  "properties": {
    "iso:country":"US",
    "sg:address":"96 E Geneva Sq",
    "sg:city":"Lake Geneva",
    "sg:classifiers":[
        {
            "category":"Restaurant",
            "type":"Food & Drink"
        }
    ],
    "sg:menulink":"http://www.allmenus.com/wi/lake-geneva/85799-dominos-pizza/menu/",
    "sg:phone":"+1 262 248 5050",
    "sg:postcode":"53147",
    "sg:province":"WI",
    "sg:tags":[
        "american",
        "wing",
        "pizza"
    ],
    "wof:name":"Domino's Pizza",
    "wof:placetype":"venue"
},
  "geometry": {"coordinates":[-88.42437,42.606109],"type":"Point"}
}