{
  "type": "Feature",
  "properties": {
    "iso:country":"US",
    "sg:address":"2201 N Dr Martin Luther King Dr",
    "sg:city":"Milwaukee",
    "sg:classifiers":[
        {
            "category":"Social Services",
            "type":"Services"
        }
    ],
    "sg:phone":"+1 414 963 2683",
    "sg:postcode":"53212",
    "sg:province":"WI",
    "sg:tags":[
        "program",
        "services-information",
        "referral"
    ],
    "wof:name":"Victims Assistance Program",
    "wof:placetype":"venue"
},
  "geometry": {"coordinates":[-87.914154,43.059116],"type":"Point"}
}