{
  "type": "Feature",
  "properties": {
    "iso:country":"US",
    "sg:address":"19833 E Gale Ave",
    "sg:city":"Galesville",
    "sg:classifiers":[
        {
            "category":"Bars & Pubs",
            "type":"Food & Drink"
        }
    ],
    "sg:phone":"+1 608 582 2517",
    "sg:postcode":"54630",
    "sg:province":"WI",
    "wof:name":"Mike's Bar",
    "wof:placetype":"venue"
},
  "geometry": {"coordinates":[-91.348609,44.082448],"type":"Point"}
}