{
  "type": "Feature",
  "properties": {
    "iso:country":"US",
    "sg:address":"6766 W Lincoln Ave",
    "sg:city":"Milwaukee",
    "sg:classifiers":[
        {
            "category":"Shopping",
            "subcategory":"Used Merchandise",
            "type":"Retail Goods"
        },
        {
            "category":"Home & Garden",
            "subcategory":"Household Appliances",
            "type":"Retail Goods"
        }
    ],
    "sg:phone":"+1 414 543 9181",
    "sg:postcode":"53219",
    "sg:province":"WI",
    "sg:tags":[
        "cleaners",
        "vacuum"
    ],
    "wof:name":"West Allis Vacuum Center",
    "wof:placetype":"venue"
},
  "geometry": {"coordinates":[-87.99794900000001,43.002949],"type":"Point"}
}