{
  "type": "Feature",
  "properties": {
    "iso:country":"US",
    "sg:address":"145 E North St",
    "sg:city":"Waukesha",
    "sg:classifiers":[
        {
            "category":"Shopping",
            "subcategory":"Bicycles & Sporting Goods",
            "type":"Retail Goods"
        }
    ],
    "sg:phone":"+1 262 544 5040",
    "sg:postcode":"53188",
    "sg:province":"WI",
    "sg:tags":[
        "equipment",
        "tennis",
        "supply"
    ],
    "wof:name":"Spring City Sporting Goods",
    "wof:placetype":"venue"
},
  "geometry": {"coordinates":[-88.23539599999999,43.013328],"type":"Point"}
}