{
  "type": "Feature",
  "properties": {
    "iso:country":"US",
    "sg:address":"2600 S Kerry Ln",
    "sg:city":"Appleton",
    "sg:classifiers":[
        {
            "category":"Recreation",
            "type":"Entertainment"
        }
    ],
    "sg:phone":"+1 920 734 5687",
    "sg:postcode":"54915",
    "sg:province":"WI",
    "sg:tags":[
        "parks"
    ],
    "wof:name":"Wisconsin Nuisance Wildlife",
    "wof:placetype":"venue"
},
  "geometry": {"coordinates":[-88.406631,44.23895],"type":"Point"}
}