{
  "type": "Feature",
  "properties": {
    "iso:country":"US",
    "sg:address":"2650 Foxfire Dr",
    "sg:city":"Green Bay",
    "sg:classifiers":[
        {
            "category":"Professional",
            "subcategory":"Computer Services",
            "type":"Services"
        }
    ],
    "sg:phone":"+1 920 406 9490",
    "sg:postcode":"54311",
    "sg:province":"WI",
    "sg:tags":[
        "datum"
    ],
    "wof:name":"Synercomm Inc",
    "wof:placetype":"venue"
},
  "geometry": {"coordinates":[-87.951104,44.456975],"type":"Point"}
}