{
  "type": "Feature",
  "properties": {
    "addr:full":"3730 Western Ct Oshkosh WI 54901",
    "addr:housenumber":"3730",
    "addr:postcode":"54901",
    "addr:street":"Western Ct",
    "iso:country":"US",
    "sg:address":"3730 Western Ct",
    "sg:city":"Oshkosh",
    "sg:classifiers":[
        {
            "category":"Professional",
            "subcategory":"Management & Consulting",
            "type":"Services"
        }
    ],
    "sg:phone":"+1 920 233 9113",
    "sg:postcode":"54901",
    "sg:province":"WI",
    "sg:tags":[
        "public",
        "relations"
    ],
    "wof:name":"Big Dogz Promotions LLC",
    "wof:placetype":"venue"
},
  "geometry": {"coordinates":[-88.547551,44.069087],"type":"Point"}
}