{
  "type": "Feature",
  "properties": {
    "iso:country":"US",
    "sg:address":"2960 Golf Rd",
    "sg:city":"Sarona",
    "sg:classifiers":[
        {
            "category":"Travel",
            "subcategory":"Hotels & Motels",
            "type":"Entertainment"
        }
    ],
    "sg:phone":"+1 715 635 6070",
    "sg:postcode":"54870",
    "sg:province":"WI",
    "sg:tags":[
        "operation"
    ],
    "wof:name":"One Tee Inn",
    "wof:placetype":"venue"
},
  "geometry": {"coordinates":[-91.693431,45.741644],"type":"Point"}
}