{
  "type": "Feature",
  "properties": {
    "addr:full":"121 N Madison St Lancaster WI 53813",
    "addr:housenumber":"121",
    "addr:postcode":"53813",
    "addr:street":"N Madison St",
    "iso:country":"US",
    "sg:address":"121 N Madison St",
    "sg:city":"Lancaster",
    "sg:classifiers":[
        {
            "category":"Professional",
            "subcategory":"Accounting & Tax Preparation",
            "type":"Services"
        }
    ],
    "sg:phone":"+1 608 723 6429",
    "sg:postcode":"53813",
    "sg:province":"WI",
    "sg:tags":[
        "return"
    ],
    "wof:name":"H & R Block",
    "wof:placetype":"venue"
},
  "geometry": {"coordinates":[-90.70956700000001,42.8488],"type":"Point"}
}