{
  "type": "Feature",
  "properties": {
    "addr:full":"1511 Monroe St Madison WI 53711",
    "addr:housenumber":"1511",
    "addr:postcode":"53711",
    "addr:street":"Monroe St",
    "iso:country":"US",
    "sg:address":"1511 Monroe St",
    "sg:city":"Madison",
    "sg:classifiers":[
        {
            "category":"Restaurant",
            "type":"Food & Drink"
        }
    ],
    "sg:phone":"+1 608 256 9476",
    "sg:postcode":"53711",
    "sg:province":"WI",
    "sg:tags":[
        "eating"
    ],
    "wof:name":"Mickies Dairy Bar",
    "wof:placetype":"venue"
},
  "geometry": {"coordinates":[-89.413281,43.067387],"type":"Point"}
}