{
  "type": "Feature",
  "properties": {
    "iso:country":"US",
    "sg:address":"54 E Towne Mall",
    "sg:city":"Madison",
    "sg:classifiers":[
        {
            "category":"Shopping",
            "subcategory":"Computers & Home Electronics",
            "type":"Retail Goods"
        }
    ],
    "sg:phone":"+1 608 249 3114",
    "sg:postcode":"53704",
    "sg:province":"WI",
    "sg:tags":[
        "game",
        "video",
        "software"
    ],
    "wof:name":"Electronics Boutique",
    "wof:placetype":"venue"
},
  "geometry": {"coordinates":[-89.30443200000001,43.128016],"type":"Point"}
}