{
  "type": "Feature",
  "properties": {
    "iso:country":"US",
    "sg:address":"452 Greenwood Dr",
    "sg:city":"Wisconsin Rapids",
    "sg:classifiers":[
        {
            "category":"Utilities",
            "type":"Services"
        }
    ],
    "sg:phone":"+1 715 423 5233",
    "sg:postcode":"54494",
    "sg:province":"WI",
    "sg:tags":[
        "sanitary"
    ],
    "wof:name":"Central Wisconsin Clean Sweep",
    "wof:placetype":"venue"
},
  "geometry": {"coordinates":[-89.82395200000001,44.361196],"type":"Point"}
}