{
  "type": "Feature",
  "properties": {
    "iso:country":"US",
    "sg:address":"111 N Superior Ave",
    "sg:city":"Tomah",
    "sg:classifiers":[
        {
            "category":"Home & Garden",
            "subcategory":"Building Materials",
            "type":"Retail Goods"
        }
    ],
    "sg:phone":"+1 608 372 2111",
    "sg:postcode":"54660",
    "sg:province":"WI",
    "sg:tags":[
        "lumber"
    ],
    "wof:name":"Tomah Lumber",
    "wof:placetype":"venue"
},
  "geometry": {"coordinates":[-90.50461,43.988181],"type":"Point"}
}