{
  "type": "Feature",
  "properties": {
    "iso:country":"US",
    "sg:address":"1020 N 12th St",
    "sg:city":"Milwaukee",
    "sg:classifiers":[
        {
            "category":"Health Services",
            "subcategory":"Doctor",
            "type":"Services"
        }
    ],
    "sg:phone":"+1 414 219 5000",
    "sg:postcode":"53233",
    "sg:province":"WI",
    "sg:tags":[
        "physician",
        "surgeon"
    ],
    "wof:name":"Aurora Behavioral Health Svc",
    "wof:placetype":"venue"
},
  "geometry": {"coordinates":[-87.927065,43.044144],"type":"Point"}
}