{
  "type": "Feature",
  "properties": {
    "addr:full":"6325 Odana Rd Madison WI 53719",
    "addr:housenumber":"6325",
    "addr:postcode":"53719",
    "addr:street":"Odana Rd",
    "iso:country":"US",
    "sg:address":"6325 Odana Rd",
    "sg:city":"Madison",
    "sg:classifiers":[
        {
            "category":"Insurance",
            "subcategory":"Life Insurance",
            "type":"Services"
        }
    ],
    "sg:phone":"+1 608 757 2701",
    "sg:postcode":"53719",
    "sg:province":"WI",
    "sg:tags":[
        "carrier"
    ],
    "wof:name":"MetLife",
    "wof:placetype":"venue"
},
  "geometry": {"coordinates":[-89.48644899999999,43.053512],"type":"Point"}
}