{
  "type": "Feature",
  "properties": {
    "addr:full":"7900 Durand Ave Sturtevant WI 53177",
    "addr:housenumber":"7900",
    "addr:postcode":"53177",
    "addr:street":"Durand Ave",
    "iso:country":"US",
    "sg:address":"7900 Durand Ave",
    "sg:city":"Sturtevant",
    "sg:classifiers":[
        {
            "category":"Manufacturing",
            "subcategory":"Metals",
            "type":"Manufacturing & Wholesale Goods"
        }
    ],
    "sg:phone":"+1 262 554 2929",
    "sg:postcode":"53177",
    "sg:province":"WI",
    "sg:tags":[
        "forging"
    ],
    "wof:name":"Walker Forge Inc",
    "wof:placetype":"venue"
},
  "geometry": {"coordinates":[-87.87956200000001,42.697741],"type":"Point"}
}