{
  "type": "Feature",
  "properties": {
    "addr:full":"101 E Madison St Clintonville WI 54929",
    "addr:housenumber":"101",
    "addr:postcode":"54929",
    "addr:street":"E Madison St",
    "iso:country":"US",
    "sg:address":"101 E Madison St",
    "sg:city":"Clintonville",
    "sg:classifiers":[
        {
            "category":"Home & Garden",
            "subcategory":"Building Materials",
            "type":"Retail Goods"
        }
    ],
    "sg:phone":"+1 715 823 3970",
    "sg:postcode":"54929",
    "sg:province":"WI",
    "wof:name":"Brick & Supply Co",
    "wof:placetype":"venue"
},
  "geometry": {"coordinates":[-88.757818,44.614478],"type":"Point"}
}