{
  "type": "Feature",
  "properties": {
    "iso:country":"US",
    "sg:address":"5607 State Hwy 52",
    "sg:city":"Wausau",
    "sg:classifiers":[
        {
            "category":"Building & Trades",
            "subcategory":"Construction",
            "type":"Services"
        }
    ],
    "sg:phone":"+1 715 842 8941",
    "sg:postcode":"54403",
    "sg:province":"WI",
    "sg:tags":[
        "concrete",
        "contractor"
    ],
    "wof:name":"B Krall Masonry Contr Inc",
    "wof:placetype":"venue"
},
  "geometry": {"coordinates":[-89.552828,45.001042],"type":"Point"}
}