{
  "type": "Feature",
  "properties": {
    "iso:country":"US",
    "sg:address":"15 Mill St",
    "sg:city":"Hartford",
    "sg:classifiers":[
        {
            "category":"Home & Garden",
            "subcategory":"Carpets & Floor Coverings",
            "type":"Retail Goods"
        }
    ],
    "sg:phone":"+1 262 673 4020",
    "sg:postcode":"53027",
    "sg:province":"WI",
    "sg:tags":[
        "material"
    ],
    "sg:website":"www.schnorenbergsfloor.com",
    "wof:name":"Schnorenberg's Floor Covering",
    "wof:placetype":"venue"
},
  "geometry": {"coordinates":[-88.377861,43.31825],"type":"Point"}
}