{
  "type": "Feature",
  "properties": {
    "addr:full":"1509 Carney Blvd Marinette WI 54143",
    "addr:housenumber":"1509",
    "addr:postcode":"54143",
    "addr:street":"Carney Blvd",
    "iso:country":"US",
    "sg:address":"1509 Carney Blvd",
    "sg:city":"Marinette",
    "sg:classifiers":[
        {
            "category":"Retail",
            "subcategory":"Laundry & Dry Cleaning",
            "type":"Services"
        }
    ],
    "sg:phone":"+1 715 735 3823",
    "sg:postcode":"54143",
    "sg:province":"WI",
    "sg:tags":[
        "drycleaning",
        "plant"
    ],
    "wof:name":"Le Roy Cleaners",
    "wof:placetype":"venue"
},
  "geometry": {"coordinates":[-87.62650499999999,45.092518],"type":"Point"}
}