{
  "type": "Feature",
  "properties": {
    "addr:full":"132 N 2nd Ave Sturgeon Bay WI 54235",
    "addr:housenumber":"132",
    "addr:postcode":"54235",
    "addr:street":"N 2Nd Ave",
    "iso:country":"US",
    "sg:address":"132 N 2nd Ave",
    "sg:city":"Sturgeon Bay",
    "sg:classifiers":[
        {
            "category":"Travel",
            "subcategory":"Hotels & Motels",
            "type":"Entertainment"
        }
    ],
    "sg:phone":"+1 920 743 4854",
    "sg:postcode":"54235",
    "sg:province":"WI",
    "sg:tags":[
        "operation"
    ],
    "wof:name":"Barbican",
    "wof:placetype":"venue"
},
  "geometry": {"coordinates":[-87.378817,44.835114],"type":"Point"}
}