{
  "type": "Feature",
  "properties": {
    "iso:country":"US",
    "sg:address":"3704 W Country Club Ln",
    "sg:city":"Altoona",
    "sg:classifiers":[
        {
            "category":"Shopping",
            "subcategory":"Computers & Home Electronics",
            "type":"Retail Goods"
        }
    ],
    "sg:phone":"+1 715 835 8254",
    "sg:postcode":"54720",
    "sg:province":"WI",
    "wof:name":"User- Friendly Computing",
    "wof:placetype":"venue"
},
  "geometry": {"coordinates":[-91.469027,44.810258],"type":"Point"}
}