{
  "type": "Feature",
  "properties": {
    "addr:full":"7495 W Layton Ave Milwaukee WI 53220",
    "addr:housenumber":"7495",
    "addr:postcode":"53220",
    "addr:street":"W Layton Ave",
    "iso:country":"US",
    "sg:address":"7495 W Layton Ave",
    "sg:city":"Milwaukee",
    "sg:classifiers":[
        {
            "category":"Restaurant",
            "type":"Food & Drink"
        }
    ],
    "sg:menulink":"http://www.allmenus.com/wi/greenfield/101287-cousins-subs/menu/",
    "sg:phone":"+1 414 282 6900",
    "sg:postcode":"53220",
    "sg:province":"WI",
    "sg:tags":[
        "wrap",
        "american",
        "sandwich"
    ],
    "wof:name":"Cousin's Subs",
    "wof:placetype":"venue"
},
  "geometry": {"coordinates":[-88.007533,42.959189],"type":"Point"}
}