{
  "type": "Feature",
  "properties": {
    "iso:country":"US",
    "sg:address":"2476 S Oneida St",
    "sg:city":"Green Bay",
    "sg:classifiers":[
        {
            "category":"Restaurant",
            "type":"Food & Drink"
        }
    ],
    "sg:phone":"+1 920 498 1005",
    "sg:postcode":"54304",
    "sg:province":"WI",
    "sg:tags":[
        "steakhouse"
    ],
    "wof:name":"Timber Lodge Steakhouse Inc",
    "wof:placetype":"venue"
},
  "geometry": {"coordinates":[-88.06931,44.483835],"type":"Point"}
}