{
  "type": "Feature",
  "properties": {
    "iso:country":"US",
    "sg:address":"515 E North Ave",
    "sg:city":"Luck",
    "sg:classifiers":[
        {
            "category":"Wholesale",
            "subcategory":"Groceries",
            "type":"Manufacturing & Wholesale Goods"
        }
    ],
    "sg:phone":"+1 715 472 4218",
    "sg:postcode":"54853",
    "sg:province":"WI",
    "wof:name":"High Path Sugar Bush",
    "wof:placetype":"venue"
},
  "geometry": {"coordinates":[-92.47640199999999,45.57686],"type":"Point"}
}