{
  "type": "Feature",
  "properties": {
    "iso:country":"US",
    "sg:address":"29 Pleasant Oak Ct",
    "sg:city":"Oregon",
    "sg:classifiers":[
        {
            "category":"Real Estate",
            "subcategory":"Real Estate Operator",
            "type":"Services"
        }
    ],
    "sg:phone":"+1 608 835 9118",
    "sg:postcode":"53575",
    "sg:province":"WI",
    "sg:tags":[
        "property",
        "lessor"
    ],
    "wof:name":"M & M of Oregon",
    "wof:placetype":"venue"
},
  "geometry": {"coordinates":[-89.383182,42.912741],"type":"Point"}
}