{
  "type": "Feature",
  "properties": {
    "iso:country":"US",
    "sg:address":"10034 N Brookdale Dr",
    "sg:city":"Mequon",
    "sg:classifiers":[
        {
            "category":"Building & Trades",
            "subcategory":"Landscaping Services",
            "type":"Services"
        }
    ],
    "sg:phone":"+1 262 241 3683",
    "sg:postcode":"53092",
    "sg:province":"WI",
    "sg:tags":[
        "landscape",
        "contractor"
    ],
    "wof:name":"Garden Escapes",
    "wof:placetype":"venue"
},
  "geometry": {"coordinates":[-87.926965,43.201684],"type":"Point"}
}