{
  "type": "Feature",
  "properties": {
    "addr:full":"3686 US Hwy 14 Spring Green WI 53588",
    "addr:housenumber":"3686",
    "addr:postcode":"53588",
    "addr:street":"Us Hwy 14",
    "iso:country":"US",
    "sg:address":"3686 US Hwy 14",
    "sg:city":"Spring Green",
    "sg:phone":"+1 608 588 2051",
    "sg:postcode":"53588",
    "sg:province":"WI",
    "sg:tags":[
        "farm",
        "corn",
        "soybean"
    ],
    "wof:name":"Lane Cross Farms Inc",
    "wof:placetype":"venue"
},
  "geometry": {"coordinates":[-90.133966,43.189707],"type":"Point"}
}