{
  "type": "Feature",
  "properties": {
    "iso:country":"US",
    "sg:address":"5308 55th Ave",
    "sg:city":"Kenosha",
    "sg:classifiers":[
        {
            "category":"Retail",
            "subcategory":"Auto Repair",
            "type":"Services"
        }
    ],
    "sg:phone":"+1 262 654 6750",
    "sg:postcode":"53144",
    "sg:province":"WI",
    "sg:tags":[
        "general"
    ],
    "wof:name":"Jeffs Auto Service",
    "wof:placetype":"venue"
},
  "geometry": {"coordinates":[-87.873876,42.586083],"type":"Point"}
}