{
  "type": "Feature",
  "properties": {
    "addr:full":"3544 110th Ave Maiden Rock WI 54750",
    "addr:housenumber":"3544",
    "addr:postcode":"54750",
    "addr:street":"110Th Ave",
    "iso:country":"US",
    "sg:address":"3544 110th Ave",
    "sg:city":"Maiden Rock",
    "sg:classifiers":[
        {
            "category":"Shopping",
            "type":"Retail Goods"
        }
    ],
    "sg:phone":"+1 715 448 2107",
    "sg:postcode":"54750",
    "sg:province":"WI",
    "sg:tags":[
        "pet",
        "food",
        "supply"
    ],
    "wof:name":"Carson Ridge Kennel",
    "wof:placetype":"venue"
},
  "geometry": {"coordinates":[-92.30892299999999,44.574217],"type":"Point"}
}