{
  "type": "Feature",
  "properties": {
    "addr:full":"317 N Central Ave Marshfield WI 54449",
    "addr:housenumber":"317",
    "addr:postcode":"54449",
    "addr:street":"N Central Ave",
    "iso:country":"US",
    "sg:address":"317 N Central Ave",
    "sg:city":"Marshfield",
    "sg:classifiers":[
        {
            "category":"Bars & Pubs",
            "type":"Food & Drink"
        }
    ],
    "sg:phone":"+1 715 384 5535",
    "sg:postcode":"54449",
    "sg:province":"WI",
    "sg:tags":[
        "drinking"
    ],
    "wof:name":"Jacks",
    "wof:placetype":"venue"
},
  "geometry": {"coordinates":[-90.170958,44.670324],"type":"Point"}
}