{
  "type": "Feature",
  "properties": {
    "iso:country":"US",
    "sg:address":"6289 Willow Rd",
    "sg:city":"Withee",
    "sg:classifiers":[
        {
            "category":"Professional",
            "type":"Services"
        }
    ],
    "sg:phone":"+1 715 229 9550",
    "sg:postcode":"54498",
    "sg:province":"WI",
    "sg:tags":[
        "establishment"
    ],
    "wof:name":"Blue Ridge Svc",
    "wof:placetype":"venue"
},
  "geometry": {"coordinates":[-90.62553699999999,44.958693],"type":"Point"}
}