{
  "type": "Feature",
  "properties": {
    "iso:country":"US",
    "sg:address":"19150 Jungle Rd",
    "sg:city":"Tomah",
    "sg:classifiers":[
        {
            "category":"Farming",
            "subcategory":"Farm",
            "type":"Manufacturing & Wholesale Goods"
        }
    ],
    "sg:phone":"+1 608 372 5606",
    "sg:postcode":"54660",
    "sg:province":"WI",
    "sg:tags":[
        "crop",
        "general"
    ],
    "wof:name":"Wenzel Designs",
    "wof:placetype":"venue"
},
  "geometry": {"coordinates":[-90.42047599999999,43.881824],"type":"Point"}
}