{
  "type": "Feature",
  "properties": {
    "iso:country":"US",
    "sg:address":"549 Boulder Rd",
    "sg:city":"Watertown",
    "sg:classifiers":[
        {
            "category":"Shopping",
            "subcategory":"Computers & Home Electronics",
            "type":"Retail Goods"
        }
    ],
    "sg:phone":"+1 920 261 2819",
    "sg:postcode":"53098",
    "sg:province":"WI",
    "sg:tags":[
        "equipment",
        "electronic",
        "supply"
    ],
    "wof:name":"Electronic Processing",
    "wof:placetype":"venue"
},
  "geometry": {"coordinates":[-88.71507699999999,43.212247],"type":"Point"}
}