{
  "type": "Feature",
  "properties": {
    "iso:country":"US",
    "sg:address":"2404 Sycamore Dr",
    "sg:city":"Green Bay",
    "sg:classifiers":[
        {
            "category":"Shopping",
            "type":"Retail Goods"
        }
    ],
    "sg:phone":"+1 920 469 5418",
    "sg:postcode":"54311",
    "sg:province":"WI",
    "sg:tags":[
        "merchandise"
    ],
    "wof:name":"Almost Home",
    "wof:placetype":"venue"
},
  "geometry": {"coordinates":[-87.964754,44.477505],"type":"Point"}
}