{
  "type": "Feature",
  "properties": {
    "iso:country":"US",
    "sg:address":"351 Mineral St",
    "sg:city":"Mineral Point",
    "sg:classifiers":[
        {
            "category":"Farming",
            "subcategory":"Livestock Farm",
            "type":"Manufacturing & Wholesale Goods"
        }
    ],
    "sg:phone":"+1 608 943 6913",
    "sg:postcode":"53565",
    "sg:province":"WI",
    "sg:tags":[
        "animal",
        "general"
    ],
    "wof:name":"Kevin Butteris",
    "wof:placetype":"venue"
},
  "geometry": {"coordinates":[-90.184705,42.86503],"type":"Point"}
}