{
  "type": "Feature",
  "properties": {
    "iso:country":"US",
    "sg:address":"334 W Jefferson St",
    "sg:city":"West Salem",
    "sg:classifiers":[
        {
            "category":"Manufacturing",
            "subcategory":"Tools & Machinery",
            "type":"Manufacturing & Wholesale Goods"
        }
    ],
    "sg:phone":"+1 608 786 1104",
    "sg:postcode":"54669",
    "sg:province":"WI",
    "sg:tags":[
        "die",
        "maker"
    ],
    "wof:name":"West Salem Tool & Die Inc",
    "wof:placetype":"venue"
},
  "geometry": {"coordinates":[-91.084654,43.894397],"type":"Point"}
}