{
  "type": "Feature",
  "properties": {
    "iso:country":"US",
    "sg:address":"506 Valley Rd",
    "sg:city":"Madison",
    "sg:classifiers":[
        {
            "category":"Professional",
            "type":"Services"
        }
    ],
    "sg:phone":"+1 608 222 1005",
    "sg:postcode":"53714",
    "sg:province":"WI",
    "sg:tags":[
        "establishment"
    ],
    "wof:name":"Lewis Lewis",
    "wof:placetype":"venue"
},
  "geometry": {"coordinates":[-89.294884,43.089532],"type":"Point"}
}