{
  "type": "Feature",
  "properties": {
    "addr:full":"1717 96th Ave Hammond WI 54015",
    "addr:housenumber":"1717",
    "addr:postcode":"54015",
    "addr:street":"96Th Ave",
    "iso:country":"US",
    "sg:address":"1717 96th Ave",
    "sg:city":"Hammond",
    "sg:classifiers":[
        {
            "category":"Professional",
            "subcategory":"Lawyer & Legal Services",
            "type":"Services"
        }
    ],
    "sg:phone":"+1 715 796 2539",
    "sg:postcode":"54015",
    "sg:province":"WI",
    "sg:tags":[
        "planning",
        "estate"
    ],
    "wof:name":"Johnson & Assoc",
    "wof:placetype":"venue"
},
  "geometry": {"coordinates":[-92.452836,45.000753],"type":"Point"}
}