{
  "type": "Feature",
  "properties": {
    "iso:country":"US",
    "sg:address":"5616 Townline Rd",
    "sg:city":"Athens",
    "sg:classifiers":[
        {
            "category":"Social Services",
            "subcategory":"Child Care",
            "type":"Services"
        }
    ],
    "sg:phone":"+1 715 654 5378",
    "sg:postcode":"54411",
    "sg:province":"WI",
    "sg:tags":[
        "day"
    ],
    "wof:name":"MA & PA Country Daycare",
    "wof:placetype":"venue"
},
  "geometry": {"coordinates":[-90.197604,44.995147],"type":"Point"}
}