{
  "type": "Feature",
  "properties": {
    "addr:full":"708 Sylvan Ter Waukesha WI 53188",
    "addr:housenumber":"708",
    "addr:postcode":"53188",
    "addr:street":"Sylvan Ter",
    "iso:country":"US",
    "sg:address":"708 Sylvan Ter",
    "sg:city":"Waukesha",
    "sg:classifiers":[
        {
            "category":"Real Estate",
            "subcategory":"Real Estate Agent",
            "type":"Services"
        }
    ],
    "sg:phone":"+1 262 574 9270",
    "sg:postcode":"53188",
    "sg:province":"WI",
    "wof:name":"National Furniture Services",
    "wof:placetype":"venue"
},
  "geometry": {"coordinates":[-88.253958,43.022133],"type":"Point"}
}