{
  "type": "Feature",
  "properties": {
    "iso:country":"US",
    "sg:address":"1210 Co Rd D",
    "sg:city":"Glenwood City",
    "sg:classifiers":[
        {
            "category":"Farming",
            "subcategory":"Dairy Farm",
            "type":"Manufacturing & Wholesale Goods"
        }
    ],
    "sg:phone":"+1 715 265 7603",
    "sg:postcode":"54013",
    "sg:province":"WI",
    "wof:name":"Jerry Frederick",
    "wof:placetype":"venue"
},
  "geometry": {"coordinates":[-92.257942,45.045252],"type":"Point"}
}