{
  "type": "Feature",
  "properties": {
    "addr:full":"65 White Oaks Ln Madison WI 53711",
    "addr:housenumber":"65",
    "addr:postcode":"53711",
    "addr:street":"White Oaks Ln",
    "iso:country":"US",
    "sg:address":"65 White Oaks Ln",
    "sg:city":"Madison",
    "sg:classifiers":[
        {
            "category":"Real Estate",
            "subcategory":"Real Estate Operator",
            "type":"Services"
        }
    ],
    "sg:phone":"+1 608 273 4390",
    "sg:postcode":"53711",
    "sg:province":"WI",
    "sg:tags":[
        "property",
        "lessor"
    ],
    "wof:name":"Flury Landon",
    "wof:placetype":"venue"
},
  "geometry": {"coordinates":[-89.484797,43.044215],"type":"Point"}
}