{
  "type": "Feature",
  "properties": {
    "iso:country":"US",
    "sg:address":"20035 Junco Rd",
    "sg:city":"Tomah",
    "sg:classifiers":[
        {
            "category":"Social Services",
            "subcategory":"Adult Care",
            "type":"Services"
        }
    ],
    "sg:phone":"+1 608 372 0570",
    "sg:postcode":"54660",
    "sg:province":"WI",
    "sg:tags":[
        "residential"
    ],
    "wof:name":"Sunset Ridge Estates",
    "wof:placetype":"venue"
},
  "geometry": {"coordinates":[-90.5719,43.884918],"type":"Point"}
}