{
  "type": "Feature",
  "properties": {
    "addr:full":"2400 Wright St Madison WI 53704",
    "addr:housenumber":"2400",
    "addr:postcode":"53704",
    "addr:street":"Wright St",
    "iso:country":"US",
    "sg:address":"2400 Wright St",
    "sg:city":"Madison",
    "sg:classifiers":[
        {
            "category":"Shopping",
            "subcategory":"Pharmacy",
            "type":"Retail Goods"
        }
    ],
    "sg:phone":"+1 608 242 3542",
    "sg:postcode":"53704",
    "sg:province":"WI",
    "wof:name":"Drug Control Program",
    "wof:placetype":"venue"
},
  "geometry": {"coordinates":[-89.329994,43.130838],"type":"Point"}
}