{
  "type": "Feature",
  "properties": {
    "iso:country":"US",
    "sg:address":"7387 Co Rd V",
    "sg:city":"Holmen",
    "sg:classifiers":[
        {
            "category":"Farming",
            "subcategory":"Dairy Farm",
            "type":"Manufacturing & Wholesale Goods"
        }
    ],
    "sg:phone":"+1 608 526 3879",
    "sg:postcode":"54636",
    "sg:province":"WI",
    "wof:name":"Thomas Hale",
    "wof:placetype":"venue"
},
  "geometry": {"coordinates":[-91.255595,43.985506],"type":"Point"}
}