{
  "type": "Feature",
  "properties": {
    "addr:full":"2978 Voyager Dr Green Bay WI 54311",
    "addr:housenumber":"2978",
    "addr:postcode":"54311",
    "addr:street":"Voyager Dr",
    "iso:country":"US",
    "sg:address":"2978 Voyager Dr",
    "sg:city":"Green Bay",
    "sg:classifiers":[
        {
            "category":"Professional",
            "type":"Services"
        }
    ],
    "sg:phone":"+1 920 406 0001",
    "sg:postcode":"54311",
    "sg:province":"WI",
    "sg:tags":[
        "establishment"
    ],
    "wof:name":"Todd Wiese Home Saling Syst",
    "wof:placetype":"venue"
},
  "geometry": {"coordinates":[-87.93284800000001,44.48593],"type":"Point"}
}