{
  "type": "Feature",
  "properties": {
    "iso:country":"US",
    "sg:address":"4760 N 76th St",
    "sg:city":"Milwaukee",
    "sg:classifiers":[
        {
            "category":"Personal",
            "subcategory":"Beauty Salon",
            "type":"Services"
        }
    ],
    "sg:phone":"+1 414 535 7602",
    "sg:postcode":"53218",
    "sg:province":"WI",
    "sg:tags":[
        "shop",
        "cosmetologist"
    ],
    "wof:name":"Studio 76 Barber & Beauty",
    "wof:placetype":"venue"
},
  "geometry": {"coordinates":[-88.00678600000001,43.103769],"type":"Point"}
}