{
  "type": "Feature",
  "properties": {
    "iso:country":"US",
    "sg:address":"6624 Seybold Rd",
    "sg:city":"Madison",
    "sg:classifiers":[
        {
            "category":"Autos & Motor Vehicles",
            "subcategory":"Automobile Sales",
            "type":"Retail Goods"
        }
    ],
    "sg:phone":"+1 608 443 3600",
    "sg:postcode":"53719",
    "sg:province":"WI",
    "sg:tags":[
        "car",
        "dealer"
    ],
    "wof:name":"Jaguar Landrover Madison",
    "wof:placetype":"venue"
},
  "geometry": {"coordinates":[-89.496884,43.051854],"type":"Point"}
}