{
  "type": "Feature",
  "properties": {
    "addr:full":"3456 25th St Frederic WI 54837",
    "addr:housenumber":"3456",
    "addr:postcode":"54837",
    "addr:street":"25Th St",
    "iso:country":"US",
    "sg:address":"3456 25th St",
    "sg:city":"Frederic",
    "sg:classifiers":[
        {
            "category":"Bars & Pubs",
            "type":"Food & Drink"
        }
    ],
    "sg:phone":"+1 715 653 2671",
    "sg:postcode":"54837",
    "sg:province":"WI",
    "wof:name":"Indian Creek Tavern",
    "wof:placetype":"venue"
},
  "geometry": {"coordinates":[-92.20603,45.71878],"type":"Point"}
}