{
  "type": "Feature",
  "properties": {
    "iso:country":"US",
    "sg:address":"3566 E Fitzsimmons Rd",
    "sg:city":"Oak Creek",
    "sg:classifiers":[
        {
            "category":"Manufacturing",
            "subcategory":"Apparel",
            "type":"Manufacturing & Wholesale Goods"
        }
    ],
    "sg:phone":"+1 414 762 7068",
    "sg:postcode":"53154",
    "sg:province":"WI",
    "sg:tags":[
        "textile",
        "product",
        "fabricated",
        "mfg"
    ],
    "wof:name":"Tent-A-Pen",
    "wof:placetype":"venue"
},
  "geometry": {"coordinates":[-87.863783,42.864381],"type":"Point"}
}