{
  "type": "Feature",
  "properties": {
    "iso:country":"US",
    "sg:address":"423 5th St",
    "sg:city":"Centuria",
    "sg:classifiers":[
        {
            "category":"Autos & Motor Vehicles",
            "subcategory":"Boat Sales",
            "type":"Retail Goods"
        }
    ],
    "sg:phone":"+1 715 640 6000",
    "sg:postcode":"54824",
    "sg:province":"WI",
    "sg:tags":[
        "equipment",
        "supplies-wholesale",
        "manufacturer"
    ],
    "sg:website":"http://www.kennedypontoons.com",
    "wof:name":"Kennedy Pontoons Inc",
    "wof:placetype":"venue"
},
  "geometry": {"coordinates":[-92.554192,45.450158],"type":"Point"}
}