{
  "type": "Feature",
  "properties": {
    "iso:country":"US",
    "sg:address":"6957 Hillside Rd",
    "sg:city":"Pickett",
    "sg:classifiers":[
        {
            "category":"Farming",
            "subcategory":"Dairy Farm",
            "type":"Manufacturing & Wholesale Goods"
        }
    ],
    "sg:phone":"+1 920 589 6312",
    "sg:postcode":"54964",
    "sg:province":"WI",
    "wof:name":"Gary Koplitz",
    "wof:placetype":"venue"
},
  "geometry": {"coordinates":[-88.749641,43.902002],"type":"Point"}
}