{
  "type": "Feature",
  "properties": {
    "iso:country":"US",
    "sg:address":"159 W Main St",
    "sg:city":"Stoughton",
    "sg:classifiers":[
        {
            "category":"Shopping",
            "type":"Retail Goods"
        }
    ],
    "sg:phone":"+1 608 873 5513",
    "sg:postcode":"53589",
    "sg:province":"WI",
    "sg:tags":[
        "monument"
    ],
    "wof:name":"Wisconsin Monument & Vault Co",
    "wof:placetype":"venue"
},
  "geometry": {"coordinates":[-89.220929,42.916693],"type":"Point"}
}