{
  "type": "Feature",
  "properties": {
    "iso:country":"US",
    "sg:address":"5810 Schofield Ave",
    "sg:city":"Schofield",
    "sg:classifiers":[
        {
            "category":"Travel",
            "subcategory":"Hotels & Motels",
            "type":"Entertainment"
        }
    ],
    "sg:phone":"+1 715 359 1990",
    "sg:postcode":"54476",
    "sg:province":"WI",
    "sg:tags":[
        "operation"
    ],
    "wof:name":"Inn Weston & Suites",
    "wof:placetype":"venue"
},
  "geometry": {"coordinates":[-89.551343,44.904312],"type":"Point"}
}