{
  "type": "Feature",
  "properties": {
    "iso:country":"US",
    "sg:address":"3618 N Lake Dr",
    "sg:city":"Milwaukee",
    "sg:classifiers":[
        {
            "category":"Professional",
            "subcategory":"Lawyer & Legal Services",
            "type":"Services"
        }
    ],
    "sg:phone":"+1 414 962 4240",
    "sg:postcode":"53211",
    "sg:province":"WI",
    "wof:name":"Harold & Touraine Nash Fo",
    "wof:placetype":"venue"
},
  "geometry": {"coordinates":[-87.873119,43.085031],"type":"Point"}
}