{
  "type": "Feature",
  "properties": {
    "iso:country":"US",
    "sg:address":"701 E 1st St",
    "sg:city":"Merrill",
    "sg:classifiers":[
        {
            "category":"Government",
            "subcategory":"Fire Station",
            "type":"Public Place"
        }
    ],
    "sg:phone":"+1 715 536 2233",
    "sg:postcode":"54452",
    "sg:province":"WI",
    "sg:tags":[
        "protection"
    ],
    "wof:name":"Merrill Fire & Ambulance Svc",
    "wof:placetype":"venue"
},
  "geometry": {"coordinates":[-89.688833,45.180436],"type":"Point"}
}