{
  "type": "Feature",
  "properties": {
    "iso:country":"US",
    "sg:address":"11735 Mossy Cliff Trl",
    "sg:city":"Sister Bay",
    "sg:classifiers":[
        {
            "category":"Professional",
            "type":"Services"
        }
    ],
    "sg:phone":"+1 920 854 9630",
    "sg:postcode":"54234",
    "sg:province":"WI",
    "sg:tags":[
        "establishment"
    ],
    "wof:name":"Translink",
    "wof:placetype":"venue"
},
  "geometry": {"coordinates":[-87.117853,45.231193],"type":"Point"}
}