{
  "type": "Feature",
  "properties": {
    "iso:country":"US",
    "sg:address":"102 N Main St",
    "sg:city":"Oconomowoc",
    "sg:classifiers":[
        {
            "category":"Building & Trades",
            "subcategory":"Equipment Rental",
            "type":"Services"
        }
    ],
    "sg:phone":"+1 262 567 4123",
    "sg:postcode":"53066",
    "sg:province":"WI",
    "wof:name":"Beihoff Music Corp",
    "wof:placetype":"venue"
},
  "geometry": {"coordinates":[-88.499677,43.113877],"type":"Point"}
}