{
  "type": "Feature",
  "properties": {
    "addr:full":"5005 376th Ave Burlington WI 53105",
    "addr:housenumber":"5005",
    "addr:postcode":"53105",
    "addr:street":"376Th Ave",
    "iso:country":"US",
    "sg:address":"5005 376th Ave",
    "sg:city":"Burlington",
    "sg:classifiers":[
        {
            "category":"Building & Trades",
            "subcategory":"Construction",
            "type":"Services"
        }
    ],
    "sg:phone":"+1 262 537 4721",
    "sg:postcode":"53105",
    "sg:province":"WI",
    "sg:tags":[
        "house"
    ],
    "wof:name":"Moran Builders LLC",
    "wof:placetype":"venue"
},
  "geometry": {"coordinates":[-88.266582,42.591891],"type":"Point"}
}