{
  "type": "Feature",
  "properties": {
    "iso:country":"US",
    "sg:address":"405 W Walnut St",
    "sg:city":"Green Bay",
    "sg:classifiers":[
        {
            "category":"Cinema",
            "subcategory":"Movie Theater",
            "type":"Entertainment"
        }
    ],
    "sg:phone":"+1 920 433 0611",
    "sg:postcode":"54303",
    "sg:province":"WI",
    "sg:tags":[
        "motion",
        "picture",
        "eating"
    ],
    "wof:name":"West Theater Llc",
    "wof:placetype":"venue"
},
  "geometry": {"coordinates":[-88.022955,44.516651],"type":"Point"}
}