{
  "type": "Feature",
  "properties": {
    "addr:full":"6891 Hollander Ln Pickett WI 54964",
    "addr:housenumber":"6891",
    "addr:postcode":"54964",
    "addr:street":"Hollander Ln",
    "iso:country":"US",
    "sg:address":"6891 Hollander Ln",
    "sg:city":"Pickett",
    "sg:classifiers":[
        {
            "category":"Restaurant",
            "type":"Food & Drink"
        }
    ],
    "sg:phone":"+1 920 589 4010",
    "sg:postcode":"54964",
    "sg:province":"WI",
    "sg:tags":[
        "eating"
    ],
    "wof:name":"Aldo S Pizzeria",
    "wof:placetype":"venue"
},
  "geometry": {"coordinates":[-88.744519,43.909225],"type":"Point"}
}