{
  "type": "Feature",
  "properties": {
    "addr:full":"1109 N High Point Rd Madison WI 53717",
    "addr:housenumber":"1109",
    "addr:postcode":"53717",
    "addr:street":"N High Point Rd",
    "iso:country":"US",
    "sg:address":"1109 N High Point Rd",
    "sg:city":"Madison",
    "sg:classifiers":[
        {
            "category":"Professional",
            "subcategory":"Management & Consulting",
            "type":"Services"
        }
    ],
    "sg:phone":"+1 608 242 4100",
    "sg:postcode":"53717",
    "sg:province":"WI",
    "sg:tags":[
        "business"
    ],
    "wof:name":"Compel Consulting Inc",
    "wof:placetype":"venue"
},
  "geometry": {"coordinates":[-89.519702,43.082559],"type":"Point"}
}