{
  "type": "Feature",
  "properties": {
    "addr:full":"402 Mandan Dr Waukesha WI 53188",
    "addr:housenumber":"402",
    "addr:postcode":"53188",
    "addr:street":"Mandan Dr",
    "iso:country":"US",
    "sg:address":"402 Mandan Dr",
    "sg:city":"Waukesha",
    "sg:classifiers":[
        {
            "category":"Professional",
            "type":"Services"
        }
    ],
    "sg:phone":"+1 262 544 9111",
    "sg:postcode":"53188",
    "sg:province":"WI",
    "wof:name":"Lorriel L L C",
    "wof:placetype":"venue"
},
  "geometry": {"coordinates":[-88.267399,43.009225],"type":"Point"}
}