{
  "type": "Feature",
  "properties": {
    "iso:country":"US",
    "sg:address":"2550 E Main St",
    "sg:city":"Reedsburg",
    "sg:classifiers":[
        {
            "category":"Home & Garden",
            "subcategory":"Building Materials",
            "type":"Retail Goods"
        },
        {
            "category":"Building & Trades",
            "subcategory":"Construction",
            "type":"Services"
        }
    ],
    "sg:phone":"+1 608 524 1444",
    "sg:postcode":"53959",
    "sg:province":"WI",
    "sg:tags":[
        "glass",
        "window",
        "replacement",
        "plate"
    ],
    "wof:name":"Wisconsin Glass LLC",
    "wof:placetype":"venue"
},
  "geometry": {"coordinates":[-89.970911,43.532475],"type":"Point"}
}