{
  "type": "Feature",
  "properties": {
    "iso:country":"US",
    "sg:address":"440 S Wall St",
    "sg:city":"Denmark",
    "sg:classifiers":[
        {
            "category":"Retail",
            "subcategory":"Auto Repair",
            "type":"Services"
        }
    ],
    "sg:phone":"+1 920 863 6040",
    "sg:postcode":"54208",
    "sg:province":"WI",
    "sg:tags":[
        "repairing",
        "automobile"
    ],
    "wof:name":"Randy's Service Ctr",
    "wof:placetype":"venue"
},
  "geometry": {"coordinates":[-87.82664699999999,44.34414],"type":"Point"}
}