{
  "type": "Feature",
  "properties": {
    "addr:full":"522 16th St Racine WI 53403",
    "addr:housenumber":"522",
    "addr:postcode":"53403",
    "addr:street":"16Th St",
    "iso:country":"US",
    "sg:address":"522 16th St",
    "sg:city":"Racine",
    "sg:classifiers":[
        {
            "category":"Food & Beverages",
            "subcategory":"Groceries & Convenience Stores",
            "type":"Retail Goods"
        }
    ],
    "sg:phone":"+1 262 634 6133",
    "sg:postcode":"53403",
    "sg:province":"WI",
    "wof:name":"Bell City Food",
    "wof:placetype":"venue"
},
  "geometry": {"coordinates":[-87.78681899999999,42.71262],"type":"Point"}
}