{
  "type": "Feature",
  "properties": {
    "iso:country":"US",
    "sg:address":"31000 Namekagon Rd",
    "sg:city":"Danbury",
    "sg:classifiers":[
        {
            "category":"Government",
            "subcategory":"Police Station",
            "type":"Public Place"
        }
    ],
    "sg:phone":"+1 715 259 7139",
    "sg:postcode":"54830",
    "sg:province":"WI",
    "sg:tags":[
        "protection"
    ],
    "wof:name":"Webblake Police Department",
    "wof:placetype":"venue"
},
  "geometry": {"coordinates":[-92.112535,46.039933],"type":"Point"}
}