{
  "type": "Feature",
  "properties": {
    "iso:country":"US",
    "sg:address":"301 Fremont St",
    "sg:city":"Fond Du Lac",
    "sg:classifiers":[
        {
            "category":"Manufacturing",
            "subcategory":"Retail Goods",
            "type":"Manufacturing & Wholesale Goods"
        }
    ],
    "sg:phone":"+1 920 922 0520",
    "sg:postcode":"54935",
    "sg:province":"WI",
    "sg:tags":[
        "broom",
        "brush"
    ],
    "wof:name":"Regal Manufacturing Co",
    "wof:placetype":"venue"
},
  "geometry": {"coordinates":[-88.458217,43.764017],"type":"Point"}
}