{
  "type": "Feature",
  "properties": {
    "iso:country":"US",
    "sg:address":"624 Bakertown Rd",
    "sg:city":"Sullivan",
    "sg:classifiers":[
        {
            "category":"Building & Trades",
            "subcategory":"Construction",
            "type":"Services"
        }
    ],
    "sg:phone":"+1 262 593 8833",
    "sg:postcode":"53178",
    "sg:province":"WI",
    "sg:tags":[
        "marking",
        "maintenance",
        "parking"
    ],
    "wof:name":"Sullivan Village Public Works",
    "wof:placetype":"venue"
},
  "geometry": {"coordinates":[-88.59618399999999,43.019161],"type":"Point"}
}