{
  "type": "Feature",
  "properties": {
    "iso:country":"US",
    "sg:address":"13183 Neuman Rd",
    "sg:city":"Baraboo",
    "sg:classifiers":[
        {
            "category":"Autos & Motor Vehicles",
            "subcategory":"Motorcycle Sales",
            "type":"Retail Goods"
        }
    ],
    "sg:phone":"+1 608 356 3146",
    "sg:postcode":"53913",
    "sg:province":"WI",
    "sg:tags":[
        "scooter"
    ],
    "wof:name":"JNS Cycle LLC",
    "wof:placetype":"venue"
},
  "geometry": {"coordinates":[-89.66790899999999,43.447062],"type":"Point"}
}