{
  "type": "Feature",
  "properties": {
    "iso:country":"US",
    "sg:address":"465 South Blvd",
    "sg:city":"Baraboo",
    "sg:classifiers":[
        {
            "category":"Retail",
            "subcategory":"Auto Repair",
            "type":"Services"
        }
    ],
    "sg:phone":"+1 800 800 2727",
    "sg:postcode":"53913",
    "sg:province":"WI",
    "sg:tags":[
        "glass",
        "replacement"
    ],
    "wof:name":"Safelite Autoglass",
    "wof:placetype":"venue"
},
  "geometry": {"coordinates":[-89.749042,43.461511],"type":"Point"}
}