{
  "type": "Feature",
  "properties": {
    "iso:country":"US",
    "sg:address":"27989 Mitchell Hollow Rd",
    "sg:city":"Belmont",
    "sg:classifiers":[
        {
            "category":"Farming",
            "subcategory":"Dairy Farm",
            "type":"Manufacturing & Wholesale Goods"
        }
    ],
    "sg:phone":"+1 608 348 9428",
    "sg:postcode":"53510",
    "sg:province":"WI",
    "wof:name":"David Nodolf",
    "wof:placetype":"venue"
},
  "geometry": {"coordinates":[-90.367254,42.747924],"type":"Point"}
}