{
  "type": "Feature",
  "properties": {
    "iso:country":"US",
    "sg:address":"5727 Riverside Dr",
    "sg:city":"Shawano",
    "sg:classifiers":[
        {
            "category":"Insurance",
            "subcategory":"Insurance Agent",
            "type":"Services"
        }
    ],
    "sg:phone":"+1 715 524 3969",
    "sg:postcode":"54166",
    "sg:province":"WI",
    "wof:name":"Vannes Financial Svc",
    "wof:placetype":"venue"
},
  "geometry": {"coordinates":[-88.615097,44.798211],"type":"Point"}
}