{
  "type": "Feature",
  "properties": {
    "iso:country":"US",
    "sg:address":"1024 Forest Lake Dr",
    "sg:city":"Plover",
    "sg:classifiers":[
        {
            "category":"Wholesale",
            "subcategory":"Non-durable Goods",
            "type":"Manufacturing & Wholesale Goods"
        }
    ],
    "sg:phone":"+1 715 344 3632",
    "sg:postcode":"54467",
    "sg:province":"WI",
    "wof:name":"Wolosek Christmas Trees",
    "wof:placetype":"venue"
},
  "geometry": {"coordinates":[-89.632929,44.440879],"type":"Point"}
}