{
  "type": "Feature",
  "properties": {
    "iso:country":"US",
    "sg:address":"620 S Main St",
    "sg:city":"Shawano",
    "sg:classifiers":[
        {
            "category":"Shopping",
            "subcategory":"Bicycles & Sporting Goods",
            "type":"Retail Goods"
        }
    ],
    "sg:phone":"+1 715 526 2216",
    "sg:postcode":"54166",
    "sg:province":"WI",
    "wof:name":"Joe Bikeler's Bike Shop",
    "wof:placetype":"venue"
},
  "geometry": {"coordinates":[-88.609031,44.774372],"type":"Point"}
}