{
  "type": "Feature",
  "properties": {
    "iso:country":"US",
    "sg:address":"211 E Franklin St",
    "sg:city":"Appleton",
    "sg:classifiers":[
        {
            "category":"Professional",
            "subcategory":"Business Services",
            "type":"Services"
        },
        {
            "category":"Professional",
            "subcategory":"Management & Consulting",
            "type":"Services"
        }
    ],
    "sg:phone":"+1 920 882 1833",
    "sg:postcode":"54911",
    "sg:province":"WI",
    "sg:tags":[
        "consultant"
    ],
    "wof:name":"A Va Advisors LLC",
    "wof:placetype":"venue"
},
  "geometry": {"coordinates":[-88.402862,44.263943],"type":"Point"}
}