{
  "type": "Feature",
  "properties": {
    "iso:country":"US",
    "sg:address":"302 Prairie St",
    "sg:city":"Reeseville",
    "sg:classifiers":[
        {
            "category":"Organizations",
            "subcategory":"Religious Organization",
            "type":"Services"
        }
    ],
    "sg:phone":"+1 920 927 3102",
    "sg:postcode":"53579",
    "sg:province":"WI",
    "sg:tags":[
        "church"
    ],
    "wof:name":"Tri-Parish Catholic Ctr",
    "wof:placetype":"venue"
},
  "geometry": {"coordinates":[-88.84345,43.307014],"type":"Point"}
}