{
  "type": "Feature",
  "properties": {
    "addr:full":"2820 22nd Pl Kenosha WI 53140",
    "addr:housenumber":"2820",
    "addr:postcode":"53140",
    "addr:street":"22Nd Pl",
    "iso:country":"US",
    "sg:address":"2820 22nd Pl",
    "sg:city":"Kenosha",
    "sg:classifiers":[
        {
            "category":"Building & Trades",
            "subcategory":"Equipment Rental",
            "type":"Services"
        }
    ],
    "sg:phone":"+1 262 551 7505",
    "sg:postcode":"53140",
    "sg:province":"WI",
    "wof:name":"Rentals Unlimited LLC",
    "wof:placetype":"venue"
},
  "geometry": {"coordinates":[-87.842382,42.617426],"type":"Point"}
}