{
  "type": "Feature",
  "properties": {
    "iso:country":"US",
    "sg:address":"1740 Wisconsin St",
    "sg:city":"Sturtevant",
    "sg:classifiers":[
        {
            "category":"Manufacturing",
            "subcategory":"Printing",
            "type":"Manufacturing & Wholesale Goods"
        }
    ],
    "sg:phone":"+1 262 886 6749",
    "sg:postcode":"53177",
    "sg:province":"WI",
    "sg:tags":[
        "newspaper"
    ],
    "wof:name":"Milwaukee Journal Sentinel",
    "wof:placetype":"venue"
},
  "geometry": {"coordinates":[-87.904808,42.715613],"type":"Point"}
}