{
  "type": "Feature",
  "properties": {
    "iso:country":"US",
    "sg:address":"103 N Leonard St",
    "sg:city":"West Salem",
    "sg:classifiers":[
        {
            "category":"Retail",
            "subcategory":"Auto Repair",
            "type":"Services"
        }
    ],
    "sg:phone":"+1 608 786 4100",
    "sg:postcode":"54669",
    "sg:province":"WI",
    "sg:tags":[
        "body",
        "automobile",
        "painting"
    ],
    "wof:name":"First Class Auto Body",
    "wof:placetype":"venue"
},
  "geometry": {"coordinates":[-91.08122,43.89797],"type":"Point"}
}