{
  "type": "Feature",
  "properties": {
    "iso:country":"US",
    "sg:address":"402 E Main St",
    "sg:city":"Sun Prairie",
    "sg:classifiers":[
        {
            "category":"Retail",
            "subcategory":"Auto Repair",
            "type":"Services"
        }
    ],
    "sg:phone":"+1 608 834 3330",
    "sg:postcode":"53590",
    "sg:province":"WI",
    "sg:tags":[
        "automotive",
        "general"
    ],
    "wof:name":"Crawley Automotive",
    "wof:placetype":"venue"
},
  "geometry": {"coordinates":[-89.20972500000001,43.182863],"type":"Point"}
}