{
  "type": "Feature",
  "properties": {
    "iso:country":"US",
    "sg:address":"4346 Fond du Lac Dr",
    "sg:city":"Slinger",
    "sg:classifiers":[
        {
            "category":"Building & Trades",
            "subcategory":"Landscaping Services",
            "type":"Services"
        }
    ],
    "sg:phone":"+1 262 644 8885",
    "sg:postcode":"53086",
    "sg:province":"WI",
    "sg:tags":[
        "landscape",
        "contractor"
    ],
    "sg:website":"www.outdoordesign.net",
    "wof:name":"Outdoor Design Inc",
    "wof:placetype":"venue"
},
  "geometry": {"coordinates":[-88.247606,43.30263],"type":"Point"}
}