{
  "type": "Feature",
  "properties": {
    "iso:country":"US",
    "sg:address":"6909 Village Park Dr",
    "sg:city":"Madison",
    "sg:classifiers":[
        {
            "category":"Building & Trades",
            "subcategory":"Construction",
            "type":"Services"
        }
    ],
    "sg:phone":"+1 608 219 1807",
    "sg:postcode":"53718",
    "sg:province":"WI",
    "sg:tags":[
        "floor",
        "laying",
        "contractor"
    ],
    "wof:name":"Daego Flooring",
    "wof:placetype":"venue"
},
  "geometry": {"coordinates":[-89.287115,43.164334],"type":"Point"}
}