{
  "type": "Feature",
  "properties": {
    "iso:country":"US",
    "sg:address":"1702 Robach St",
    "sg:city":"Cochrane",
    "sg:classifiers":[
        {
            "category":"Manufacturing",
            "subcategory":"Lumber",
            "type":"Manufacturing & Wholesale Goods"
        }
    ],
    "sg:phone":"+1 608 248 2388",
    "sg:postcode":"54622",
    "sg:province":"WI",
    "sg:tags":[
        "logging"
    ],
    "wof:name":"D & S Pallet Products Inc",
    "wof:placetype":"venue"
},
  "geometry": {"coordinates":[-91.874168,44.251],"type":"Point"}
}