{
  "type": "Feature",
  "properties": {
    "addr:full":"211 Scenic Cir Marshall WI 53559",
    "addr:housenumber":"211",
    "addr:postcode":"53559",
    "addr:street":"Scenic Cir",
    "iso:country":"US",
    "sg:address":"211 Scenic Cir",
    "sg:city":"Marshall",
    "sg:classifiers":[
        {
            "category":"Professional",
            "subcategory":"Management & Consulting",
            "type":"Services"
        }
    ],
    "sg:phone":"+1 608 655 4628",
    "sg:postcode":"53559",
    "sg:province":"WI",
    "wof:name":"J & B Management",
    "wof:placetype":"venue"
},
  "geometry": {"coordinates":[-89.068307,43.177115],"type":"Point"}
}