{
  "type": "Feature",
  "properties": {
    "iso:country":"US",
    "sg:address":"644 Hillcrest Dr",
    "sg:city":"Waupaca",
    "sg:classifiers":[
        {
            "category":"Personal",
            "type":"Services"
        }
    ],
    "sg:phone":"+1 715 256 4900",
    "sg:postcode":"54981",
    "sg:province":"WI",
    "wof:name":"Art of Massage & Wellness",
    "wof:placetype":"venue"
},
  "geometry": {"coordinates":[-89.096616,44.3588],"type":"Point"}
}