{
  "type": "Feature",
  "properties": {
    "iso:country":"US",
    "sg:address":"125 W Glenview Ct",
    "sg:city":"Thiensville",
    "sg:classifiers":[
        {
            "category":"Retail",
            "subcategory":"Animal Services",
            "type":"Services"
        }
    ],
    "sg:phone":"+1 262 241 5001",
    "sg:postcode":"53092",
    "sg:province":"WI",
    "wof:name":"Glennsdale Group",
    "wof:placetype":"venue"
},
  "geometry": {"coordinates":[-87.909104,43.197888],"type":"Point"}
}