{
  "type": "Feature",
  "properties": {
    "iso:country":"US",
    "sg:address":"112 Aster Ave",
    "sg:city":"Genoa City",
    "sg:classifiers":[
        {
            "category":"Insurance",
            "subcategory":"Insurance Agent",
            "type":"Services"
        }
    ],
    "sg:phone":"+1 262 279 5973",
    "sg:postcode":"53128",
    "sg:province":"WI",
    "wof:name":"Travelers",
    "wof:placetype":"venue"
},
  "geometry": {"coordinates":[-88.305446,42.524091],"type":"Point"}
}