{
  "type": "Feature",
  "properties": {
    "addr:full":"15 Walworth Ct Madison WI 53705",
    "addr:housenumber":"15",
    "addr:postcode":"53705",
    "addr:street":"Walworth Ct",
    "iso:country":"US",
    "sg:address":"15 Walworth Ct",
    "sg:city":"Madison",
    "sg:classifiers":[
        {
            "category":"Restaurant",
            "type":"Food & Drink"
        }
    ],
    "sg:phone":"+1 608 233 3165",
    "sg:postcode":"53705",
    "sg:province":"WI",
    "sg:tags":[
        "eating"
    ],
    "wof:name":"Hong Kong Wok",
    "wof:placetype":"venue"
},
  "geometry": {"coordinates":[-89.46163300000001,43.062327],"type":"Point"}
}