{
  "type": "Feature",
  "properties": {
    "addr:full":"10365 Hillview Rd Eleva WI 54738",
    "addr:housenumber":"10365",
    "addr:postcode":"54738",
    "addr:street":"Hillview Rd",
    "iso:country":"US",
    "sg:address":"10365 Hillview Rd",
    "sg:city":"Eleva",
    "sg:classifiers":[
        {
            "category":"Professional",
            "type":"Services"
        }
    ],
    "sg:phone":"+1 715 878 4540",
    "sg:postcode":"54738",
    "sg:province":"WI",
    "wof:name":"American Federation of St",
    "wof:placetype":"venue"
},
  "geometry": {"coordinates":[-91.40709699999999,44.676633],"type":"Point"}
}