{
  "type": "Feature",
  "properties": {
    "iso:country":"US",
    "sg:address":"606 N Genesee St",
    "sg:city":"Delafield",
    "sg:classifiers":[
        {
            "category":"Shopping",
            "subcategory":"Stationery & Office Supplies",
            "type":"Retail Goods"
        }
    ],
    "sg:phone":"+1 262 646 4158",
    "sg:postcode":"53018",
    "sg:province":"WI",
    "sg:tags":[
        "stationer"
    ],
    "wof:name":"Lang Co Store",
    "wof:placetype":"venue"
},
  "geometry": {"coordinates":[-88.4041,43.060503],"type":"Point"}
}