{
  "type": "Feature",
  "properties": {
    "iso:country":"US",
    "sg:address":"4781 Hayes Rd",
    "sg:city":"Madison",
    "sg:classifiers":[
        {
            "category":"Shopping",
            "type":"Retail Goods"
        }
    ],
    "sg:phone":"+1 608 245 0546",
    "sg:postcode":"53704",
    "sg:province":"WI",
    "sg:tags":[
        "laboratory",
        "medical",
        "merchandise"
    ],
    "wof:name":"Herslof Ocular Prosthetics",
    "wof:placetype":"venue"
},
  "geometry": {"coordinates":[-89.29952299999999,43.139034],"type":"Point"}
}