{
  "type": "Feature",
  "properties": {
    "iso:country":"US",
    "sg:address":"10398 State Hwy 13",
    "sg:city":"Marshfield",
    "sg:classifiers":[
        {
            "category":"Farming",
            "subcategory":"Dairy Farm",
            "type":"Manufacturing & Wholesale Goods"
        }
    ],
    "sg:phone":"+1 715 384 5723",
    "sg:postcode":"54449",
    "sg:province":"WI",
    "wof:name":"Chinas Angels Farm",
    "wof:placetype":"venue"
},
  "geometry": {"coordinates":[-90.180025,44.616102],"type":"Point"}
}