{
  "type": "Feature",
  "properties": {
    "iso:country":"US",
    "sg:address":"13885 Mission Rd",
    "sg:city":"Stone Lake",
    "sg:classifiers":[
        {
            "category":"Organizations",
            "subcategory":"Religious Organization",
            "type":"Services"
        }
    ],
    "sg:phone":"+1 715 865 3662",
    "sg:postcode":"54876",
    "sg:province":"WI",
    "wof:name":"St Francis Solanus Church",
    "wof:placetype":"venue"
},
  "geometry": {"coordinates":[-91.38671600000001,45.889502],"type":"Point"}
}