{
  "type": "Feature",
  "properties": {
    "addr:full":"1115 S Main St West Bend WI 53095",
    "addr:housenumber":"1115",
    "addr:postcode":"53095",
    "addr:street":"S Main St",
    "iso:country":"US",
    "sg:address":"1115 S Main St",
    "sg:city":"West Bend",
    "sg:classifiers":[
        {
            "category":"Wholesale",
            "subcategory":"Books, Periodicals, & Newspapers",
            "type":"Manufacturing & Wholesale Goods"
        }
    ],
    "sg:phone":"+1 800 759 6397",
    "sg:postcode":"53095",
    "sg:province":"WI",
    "wof:name":"Circulation Department",
    "wof:placetype":"venue"
},
  "geometry": {"coordinates":[-88.181066,43.406071],"type":"Point"}
}