{
  "type": "Feature",
  "properties": {
    "iso:country":"US",
    "sg:address":"105 E Main St",
    "sg:city":"Campbellsport",
    "sg:classifiers":[
        {
            "category":"Personal",
            "type":"Services"
        }
    ],
    "sg:phone":"+1 920 533 3635",
    "sg:postcode":"53010",
    "sg:province":"WI",
    "wof:name":"Tanning Zone",
    "wof:placetype":"venue"
},
  "geometry": {"coordinates":[-88.28238,43.597991],"type":"Point"}
}