{
  "type": "Feature",
  "properties": {
    "iso:country":"US",
    "sg:address":"1626 Lenwood Ave",
    "sg:city":"Green Bay",
    "sg:classifiers":[
        {
            "category":"Freight",
            "type":"Transportation"
        }
    ],
    "sg:phone":"+1 920 490 7690",
    "sg:postcode":"54303",
    "sg:province":"WI",
    "sg:tags":[
        "warehouse"
    ],
    "wof:name":"Clear Stream Co  Inc",
    "wof:placetype":"venue"
},
  "geometry": {"coordinates":[-88.052666,44.548019],"type":"Point"}
}