{
  "type": "Feature",
  "properties": {
    "iso:country":"US",
    "sg:address":"501 Maple Ave",
    "sg:city":"Waukesha",
    "sg:classifiers":[
        {
            "category":"Manufacturing",
            "subcategory":"Retail Goods",
            "type":"Manufacturing & Wholesale Goods"
        }
    ],
    "sg:phone":"+1 262 646 9000",
    "sg:postcode":"53188",
    "sg:province":"WI",
    "sg:tags":[
        "brush"
    ],
    "sg:website":"www.tanisinc.com",
    "wof:name":"Tanis Brush Mfg",
    "wof:placetype":"venue"
},
  "geometry": {"coordinates":[-88.353185,43.040078],"type":"Point"}
}