{
  "type": "Feature",
  "properties": {
    "iso:country":"US",
    "sg:address":"15300 W Capitol Dr",
    "sg:city":"Brookfield",
    "sg:classifiers":[
        {
            "category":"Personal",
            "subcategory":"Beauty Salon",
            "type":"Services"
        }
    ],
    "sg:phone":"+1 262 790 9507",
    "sg:postcode":"53005",
    "sg:province":"WI",
    "sg:tags":[
        "shop"
    ],
    "wof:name":"Creative Sports & Event Mktg",
    "wof:placetype":"venue"
},
  "geometry": {"coordinates":[-88.105864,43.089591],"type":"Point"}
}