{
  "type": "Feature",
  "properties": {
    "addr:full":"8495 State Hwy 21 Omro WI 54963",
    "addr:housenumber":"8495",
    "addr:postcode":"54963",
    "addr:street":"State Hwy 21",
    "iso:country":"US",
    "sg:address":"8495 State Hwy 21",
    "sg:city":"Omro",
    "sg:classifiers":[
        {
            "category":"Farming",
            "subcategory":"Farm",
            "type":"Manufacturing & Wholesale Goods"
        }
    ],
    "sg:phone":"+1 920 685 5205",
    "sg:postcode":"54963",
    "sg:province":"WI",
    "sg:tags":[
        "crop",
        "general"
    ],
    "wof:name":"Joseph Roycraft",
    "wof:placetype":"venue"
},
  "geometry": {"coordinates":[-88.822132,44.048209],"type":"Point"}
}