{
  "type": "Feature",
  "properties": {
    "iso:country":"US",
    "sg:address":"136 Walmar Dr",
    "sg:city":"Sun Prairie",
    "sg:classifiers":[
        {
            "category":"Wholesale",
            "subcategory":"Durable Goods & Equipment",
            "type":"Manufacturing & Wholesale Goods"
        }
    ],
    "sg:phone":"+1 608 837 6219",
    "sg:postcode":"53590",
    "sg:province":"WI",
    "wof:name":"City Limits Neon",
    "wof:placetype":"venue"
},
  "geometry": {"coordinates":[-89.24995800000001,43.182805],"type":"Point"}
}