{
  "type": "Feature",
  "properties": {
    "addr:full":"16686 Co Hwy Dd Bloomer WI 54724",
    "addr:housenumber":"16686",
    "addr:postcode":"54724",
    "addr:street":"Co Hwy Dd",
    "iso:country":"US",
    "sg:address":"16686 Co Hwy Dd",
    "sg:city":"Bloomer",
    "sg:classifiers":[
        {
            "category":"Building & Trades",
            "subcategory":"Construction",
            "type":"Services"
        }
    ],
    "sg:phone":"+1 715 568 1187",
    "sg:postcode":"54724",
    "sg:province":"WI",
    "sg:tags":[
        "barn"
    ],
    "wof:name":"Tony Barn",
    "wof:placetype":"venue"
},
  "geometry": {"coordinates":[-91.611615,45.084203],"type":"Point"}
}