{
  "type": "Feature",
  "properties": {
    "iso:country":"US",
    "sg:address":"1193 Saint Albert the Great Dr",
    "sg:city":"Sun Prairie",
    "sg:classifiers":[
        {
            "category":"Restaurant",
            "type":"Food & Drink"
        }
    ],
    "sg:phone":"+1 608 837 2496",
    "sg:postcode":"53590",
    "sg:province":"WI",
    "sg:tags":[
        "eating"
    ],
    "wof:name":"Secret Kitchen Catering",
    "wof:placetype":"venue"
},
  "geometry": {"coordinates":[-89.240888,43.195939],"type":"Point"}
}