{
  "type": "Feature",
  "properties": {
    "addr:full":"1634 Lakeshore Dr Campbellsport WI 53010",
    "addr:housenumber":"1634",
    "addr:postcode":"53010",
    "addr:street":"Lakeshore Dr",
    "iso:country":"US",
    "sg:address":"1634 Lakeshore Dr",
    "sg:city":"Campbellsport",
    "sg:classifiers":[
        {
            "category":"Wholesale",
            "subcategory":"Non-durable Goods",
            "type":"Manufacturing & Wholesale Goods"
        }
    ],
    "sg:phone":"+1 920 533 8880",
    "sg:postcode":"53010",
    "sg:province":"WI",
    "wof:name":"Weeping Heart Trading Company",
    "wof:placetype":"venue"
},
  "geometry": {"coordinates":[-88.209092,43.598697],"type":"Point"}
}