{
  "type": "Feature",
  "properties": {
    "addr:full":"327 S Pine St Burlington WI 53105",
    "addr:housenumber":"327",
    "addr:postcode":"53105",
    "addr:street":"S Pine St",
    "iso:country":"US",
    "sg:address":"327 S Pine St",
    "sg:city":"Burlington",
    "sg:classifiers":[
        {
            "category":"Restaurant",
            "type":"Food & Drink"
        }
    ],
    "sg:phone":"+1 262 763 7185",
    "sg:postcode":"53105",
    "sg:province":"WI",
    "sg:tags":[
        "flavor",
        "local"
    ],
    "sg:website":"www.chocolatefest.com",
    "wof:name":"Chocolate Fest",
    "wof:placetype":"venue"
},
  "geometry": {"coordinates":[-88.270827,42.672572],"type":"Point"}
}