{
  "type": "Feature",
  "properties": {
    "iso:country":"US",
    "sg:address":"101 Cedar St W",
    "sg:city":"Frederic",
    "sg:classifiers":[
        {
            "category":"Retail",
            "subcategory":"Funeral Services",
            "type":"Services"
        }
    ],
    "sg:phone":"+1 715 327 4475",
    "sg:postcode":"54837",
    "sg:province":"WI",
    "sg:tags":[
        "director"
    ],
    "wof:name":"Carlson-Rowe Funeral Home",
    "wof:placetype":"venue"
},
  "geometry": {"coordinates":[-92.468318,45.664386],"type":"Point"}
}