{
  "type": "Feature",
  "properties": {
    "iso:country":"US",
    "sg:address":"9174 Co Rd C",
    "sg:city":"Eldorado",
    "sg:classifiers":[
        {
            "category":"Farming",
            "subcategory":"Dairy Farm",
            "type":"Manufacturing & Wholesale Goods"
        }
    ],
    "sg:phone":"+1 920 872 2372",
    "sg:postcode":"54932",
    "sg:province":"WI",
    "wof:name":"Brian Westphal",
    "wof:placetype":"venue"
},
  "geometry": {"coordinates":[-88.624741,43.876038],"type":"Point"}
}