{
  "type": "Feature",
  "properties": {
    "iso:country":"US",
    "sg:address":"18155 W Bluemound Rd",
    "sg:city":"Brookfield",
    "sg:classifiers":[
        {
            "category":"Travel",
            "subcategory":"Hotels & Motels",
            "type":"Entertainment"
        }
    ],
    "sg:phone":"+1 262 792 1212",
    "sg:postcode":"53045",
    "sg:province":"WI",
    "sg:website":"http://milwaukeebrookfield.doubletree.com",
    "wof:name":"Doubletree Milwaukee Brookfield",
    "wof:placetype":"venue"
},
  "geometry": {"coordinates":[-88.13967100000001,43.036282],"type":"Point"}
}