{
  "type": "Feature",
  "properties": {
    "addr:full":"3935 S 76th St Milwaukee WI 53220",
    "addr:housenumber":"3935",
    "addr:postcode":"53220",
    "addr:street":"S 76Th St",
    "iso:country":"US",
    "sg:address":"3935 S 76th St",
    "sg:city":"Milwaukee",
    "sg:classifiers":[
        {
            "category":"Shopping",
            "subcategory":"Department Store",
            "type":"Retail Goods"
        }
    ],
    "sg:phone":"+1 414 541 8389",
    "sg:postcode":"53220",
    "sg:province":"WI",
    "sg:tags":[
        "shop"
    ],
    "wof:name":"Family Dollar Store",
    "wof:placetype":"venue"
},
  "geometry": {"coordinates":[-88.008067,42.973123],"type":"Point"}
}