{
  "type": "Feature",
  "properties": {
    "iso:country":"US",
    "sg:address":"7011 Voyager Dr",
    "sg:city":"Fond Du Lac",
    "sg:classifiers":[
        {
            "category":"Taxi",
            "type":"Transportation"
        }
    ],
    "sg:phone":"+1 920 322 8864",
    "sg:postcode":"54937",
    "sg:province":"WI",
    "sg:tags":[
        "taxicab"
    ],
    "wof:name":"Ben's Budget Cab",
    "wof:placetype":"venue"
},
  "geometry": {"coordinates":[-88.510377,43.814983],"type":"Point"}
}