{
  "type": "Feature",
  "properties": {
    "addr:full":"301 W Wisconsin Ave Ste 600 Milwaukee WI 53203",
    "addr:housenumber":"301",
    "addr:postcode":"53203",
    "addr:street":"W Wisconsin Ave Ste 600",
    "iso:country":"US",
    "sg:address":"301 W Wisconsin Ave Ste 600",
    "sg:city":"Milwaukee",
    "sg:classifiers":[
        {
            "category":"Utilities",
            "subcategory":"Electric",
            "type":"Services"
        },
        {
            "category":"Manufacturing",
            "subcategory":"Electronics",
            "type":"Manufacturing & Wholesale Goods"
        }
    ],
    "sg:phone":"+1 414 274 4437",
    "sg:postcode":"53203",
    "sg:province":"WI",
    "sg:tags":[
        "equipment-testing"
    ],
    "wof:name":"Port Washington Generating Station",
    "wof:placetype":"venue"
},
  "geometry": {"coordinates":[-87.914528,43.038799],"type":"Point"}
}