{
  "type": "Feature",
  "properties": {
    "iso:country":"US",
    "sg:address":"126 N Jefferson St",
    "sg:city":"Milwaukee",
    "sg:classifiers":[
        {
            "category":"Professional",
            "subcategory":"Management & Consulting",
            "type":"Services"
        }
    ],
    "sg:phone":"+1 414 273 2627",
    "sg:postcode":"53202",
    "sg:province":"WI",
    "wof:name":"Properties I Pettibone LL",
    "wof:placetype":"venue"
},
  "geometry": {"coordinates":[-87.904074,43.028817],"type":"Point"}
}