{
  "type": "Feature",
  "properties": {
    "iso:country":"US",
    "sg:address":"8561 State Hwy 40",
    "sg:city":"Colfax",
    "sg:classifiers":[
        {
            "category":"Farming",
            "subcategory":"Dairy Farm",
            "type":"Manufacturing & Wholesale Goods"
        }
    ],
    "sg:phone":"+1 715 962 3849",
    "sg:postcode":"54730",
    "sg:province":"WI",
    "sg:tags":[
        "field",
        "corn",
        "soybean",
        "crop"
    ],
    "wof:name":"Donald Henderson",
    "wof:placetype":"venue"
},
  "geometry": {"coordinates":[-91.72909199999999,44.986177],"type":"Point"}
}