{
  "type": "Feature",
  "properties": {
    "iso:country":"US",
    "sg:address":"333 W College Ave",
    "sg:city":"Appleton",
    "sg:classifiers":[
        {
            "category":"Shopping",
            "subcategory":"Gifts & Souvenirs",
            "type":"Retail Goods"
        }
    ],
    "sg:phone":"+1 920 882 3076",
    "sg:postcode":"54911",
    "sg:province":"WI",
    "wof:name":"Trends & Traditions",
    "wof:placetype":"venue"
},
  "geometry": {"coordinates":[-88.410319,44.261744],"type":"Point"}
}