{
  "type": "Feature",
  "properties": {
    "addr:full":"304 W Elm St Abbotsford WI 54405",
    "addr:housenumber":"304",
    "addr:postcode":"54405",
    "addr:street":"W Elm St",
    "iso:country":"US",
    "sg:address":"304 W Elm St",
    "sg:city":"Abbotsford",
    "sg:classifiers":[
        {
            "category":"Organizations",
            "subcategory":"Religious Organization",
            "type":"Services"
        }
    ],
    "sg:phone":"+1 715 223 6200",
    "sg:postcode":"54405",
    "sg:province":"WI",
    "wof:name":"Keith E Jones Rev",
    "wof:placetype":"venue"
},
  "geometry": {"coordinates":[-90.326954,44.944684],"type":"Point"}
}