{
  "type": "Feature",
  "properties": {
    "iso:country":"US",
    "sg:address":"24157 State Rd 35",
    "sg:city":"Siren",
    "sg:classifiers":[
        {
            "category":"Real Estate",
            "subcategory":"Real Estate Agent",
            "type":"Services"
        }
    ],
    "sg:phone":"+1 715 349 7035",
    "sg:postcode":"54872",
    "sg:province":"WI",
    "sg:website":"www.edinarealty.com",
    "wof:name":"Edina Realty Inc",
    "wof:placetype":"venue"
},
  "geometry": {"coordinates":[-92.381068,45.789981],"type":"Point"}
}