{
  "type": "Feature",
  "properties": {
    "iso:country":"US",
    "sg:address":"2695 Badger Ave",
    "sg:city":"Oshkosh",
    "sg:classifiers":[
        {
            "category":"Wholesale",
            "subcategory":"Electrical",
            "type":"Manufacturing & Wholesale Goods"
        }
    ],
    "sg:phone":"+1 920 235 3880",
    "sg:postcode":"54904",
    "sg:province":"WI",
    "sg:tags":[
        "electric",
        "motor"
    ],
    "wof:name":"W W Electric Motors Inc",
    "wof:placetype":"venue"
},
  "geometry": {"coordinates":[-88.589398,43.991826],"type":"Point"}
}