{
  "type": "Feature",
  "properties": {
    "addr:full":"5400 W Forest Home Ave Milwaukee WI 53220",
    "addr:housenumber":"5400",
    "addr:postcode":"53220",
    "addr:street":"W Forest Home Ave",
    "iso:country":"US",
    "sg:address":"5400 W Forest Home Ave",
    "sg:city":"Milwaukee",
    "sg:classifiers":[
        {
            "category":"Banks & Credit Unions",
            "subcategory":"Bank",
            "type":"Services"
        }
    ],
    "sg:phone":"+1 414 328 5960",
    "sg:postcode":"53220",
    "sg:province":"WI",
    "wof:name":"M&M Services",
    "wof:placetype":"venue"
},
  "geometry": {"coordinates":[-87.98223900000001,42.980433],"type":"Point"}
}