{
  "type": "Feature",
  "properties": {
    "addr:full":"115 State St Madison WI 53703",
    "addr:housenumber":"115",
    "addr:postcode":"53703",
    "addr:street":"State St",
    "iso:country":"US",
    "sg:address":"115 State St",
    "sg:city":"Madison",
    "sg:classifiers":[
        {
            "category":"Restaurant",
            "type":"Food & Drink"
        }
    ],
    "sg:menulink":"http://www.allmenus.com/wi/madison/261023-ians-pizza/menu/",
    "sg:phone":"+1 608 257 0597",
    "sg:postcode":"53703",
    "sg:province":"WI",
    "sg:tags":[
        "american",
        "pizza"
    ],
    "wof:name":"Ian's Pizza",
    "wof:placetype":"venue"
},
  "geometry": {"coordinates":[-89.386627,43.074526],"type":"Point"}
}