{
  "type": "Feature",
  "properties": {
    "iso:country":"US",
    "sg:address":"4333 Co Rd J",
    "sg:city":"Tigerton",
    "sg:phone":"+1 715 535 2915",
    "sg:postcode":"54486",
    "sg:province":"WI",
    "sg:tags":[
        "farm",
        "field",
        "corn",
        "crop"
    ],
    "wof:name":"Paul Schultz",
    "wof:placetype":"venue"
},
  "geometry": {"coordinates":[-89.056343,44.747562],"type":"Point"}
}