{
  "type": "Feature",
  "properties": {
    "iso:country":"US",
    "sg:address":"1557 Loon Lake Dr",
    "sg:city":"Birchwood",
    "sg:classifiers":[
        {
            "category":"Professional",
            "subcategory":"Business Services",
            "type":"Services"
        }
    ],
    "sg:phone":"+1 715 354 9798",
    "sg:postcode":"54817",
    "sg:province":"WI",
    "sg:tags":[
        "interior",
        "consultant",
        "design",
        "decorator"
    ],
    "wof:name":"Design In Mind",
    "wof:placetype":"venue"
},
  "geometry": {"coordinates":[-91.61554099999999,45.692885],"type":"Point"}
}