{
  "type": "Feature",
  "properties": {
    "iso:country":"US",
    "sg:address":"1131 Milwaukee Ave",
    "sg:city":"South Milwaukee",
    "sg:classifiers":[
        {
            "category":"Building & Trades",
            "subcategory":"Plumbing",
            "type":"Services"
        }
    ],
    "sg:phone":"+1 414 766 1674",
    "sg:postcode":"53172",
    "sg:province":"WI",
    "sg:tags":[
        "contractor"
    ],
    "wof:name":"Air Experts",
    "wof:placetype":"venue"
},
  "geometry": {"coordinates":[-87.864441,42.910695],"type":"Point"}
}