{
  "type": "Feature",
  "properties": {
    "iso:country":"US",
    "sg:address":"1436 182nd Ave",
    "sg:city":"New Richmond",
    "sg:classifiers":[
        {
            "category":"Building & Trades",
            "subcategory":"Equipment Rental",
            "type":"Services"
        }
    ],
    "sg:phone":"+1 715 246 4034",
    "sg:postcode":"54017",
    "sg:province":"WI",
    "sg:tags":[
        "person",
        "nursery",
        "ornamental"
    ],
    "wof:name":"Powers Portable Toilets",
    "wof:placetype":"venue"
},
  "geometry": {"coordinates":[-92.521005,45.125899],"type":"Point"}
}