{
  "type": "Feature",
  "properties": {
    "iso:country":"US",
    "sg:address":"215 N Silver St",
    "sg:city":"La Farge",
    "sg:classifiers":[
        {
            "category":"Government",
            "subcategory":"Office",
            "type":"Public Place"
        }
    ],
    "sg:phone":"+1 608 625 2332",
    "sg:postcode":"54639",
    "sg:province":"WI",
    "sg:tags":[
        "village"
    ],
    "wof:name":"LA Farge Village Shop",
    "wof:placetype":"venue"
},
  "geometry": {"coordinates":[-90.638915,43.576055],"type":"Point"}
}