{
  "type": "Feature",
  "properties": {
    "addr:full":"21415 W Greenfield Ave New Berlin WI 53146",
    "addr:housenumber":"21415",
    "addr:postcode":"53146",
    "addr:street":"W Greenfield Ave",
    "iso:country":"US",
    "sg:address":"21415 W Greenfield Ave",
    "sg:city":"New Berlin",
    "sg:classifiers":[
        {
            "category":"Manufacturing",
            "subcategory":"Tools & Machinery",
            "type":"Manufacturing & Wholesale Goods"
        }
    ],
    "sg:phone":"+1 262 548 9871",
    "sg:postcode":"53146",
    "sg:province":"WI",
    "sg:tags":[
        "equipment",
        "medical",
        "mfg",
        "rent",
        "instrument"
    ],
    "wof:name":"Orthologic Corp",
    "wof:placetype":"venue"
},
  "geometry": {"coordinates":[-88.180769,43.013694],"type":"Point"}
}