{
  "type": "Feature",
  "properties": {
    "iso:country":"US",
    "sg:address":"102 W Madison Ave",
    "sg:city":"Grantsburg",
    "sg:classifiers":[
        {
            "category":"Restaurant",
            "type":"Food & Drink"
        }
    ],
    "sg:phone":"+1 715 463 5570",
    "sg:postcode":"54840",
    "sg:province":"WI",
    "wof:name":"Jade Dragon Restaurant & Gifts",
    "wof:placetype":"venue"
},
  "geometry": {"coordinates":[-92.68408100000001,45.778994],"type":"Point"}
}