{
  "type": "Feature",
  "properties": {
    "iso:country":"US",
    "sg:address":"4451 S 27th St",
    "sg:city":"Franksville",
    "sg:classifiers":[
        {
            "category":"Professional",
            "subcategory":"Research",
            "type":"Services"
        }
    ],
    "sg:phone":"+1 262 835 9500",
    "sg:postcode":"53126",
    "sg:province":"WI",
    "sg:tags":[
        "environmental",
        "ecological"
    ],
    "wof:name":"Underground Power Corp",
    "wof:placetype":"venue"
},
  "geometry": {"coordinates":[-87.95469,42.768834],"type":"Point"}
}