{
  "type": "Feature",
  "properties": {
    "addr:full":"4915 Monona Dr Monona WI 53716",
    "addr:housenumber":"4915",
    "addr:postcode":"53716",
    "addr:street":"Monona Dr",
    "iso:country":"US",
    "sg:address":"4915 Monona Dr",
    "sg:city":"Monona",
    "sg:classifiers":[
        {
            "category":"Professional",
            "subcategory":"Lawyer & Legal Services",
            "type":"Services"
        }
    ],
    "sg:phone":"+1 608 222 7977",
    "sg:postcode":"53716",
    "sg:province":"WI",
    "sg:tags":[
        "attorney"
    ],
    "wof:name":"Able Low-Cost Legal Svc",
    "wof:placetype":"venue"
},
  "geometry": {"coordinates":[-89.326212,43.065984],"type":"Point"}
}