{
  "type": "Feature",
  "properties": {
    "addr:full":"6604 Odana Rd Madison WI 53719",
    "addr:housenumber":"6604",
    "addr:postcode":"53719",
    "addr:street":"Odana Rd",
    "iso:country":"US",
    "sg:address":"6604 Odana Rd",
    "sg:city":"Madison",
    "sg:classifiers":[
        {
            "category":"Cinema",
            "subcategory":"Movie Theater",
            "type":"Entertainment"
        }
    ],
    "sg:phone":"+1 608 833 1500",
    "sg:postcode":"53719",
    "sg:province":"WI",
    "wof:name":"Market Square Theatres Inc",
    "wof:placetype":"venue"
},
  "geometry": {"coordinates":[-89.493416,43.05507],"type":"Point"}
}