{
  "type": "Feature",
  "properties": {
    "iso:country":"US",
    "sg:address":"420 Higgins Dr",
    "sg:city":"Evansville",
    "sg:classifiers":[
        {
            "category":"Shopping",
            "type":"Retail Goods"
        }
    ],
    "sg:phone":"+1 608 302 9912",
    "sg:postcode":"53536",
    "sg:province":"WI",
    "sg:tags":[
        "merchandise"
    ],
    "wof:name":"L & A Global Enterprises, Inc.",
    "wof:placetype":"venue"
},
  "geometry": {"coordinates":[-89.312319,42.774015],"type":"Point"}
}