{
  "type": "Feature",
  "properties": {
    "addr:full":"8023 W Scranton Pl Milwaukee WI 53218",
    "addr:housenumber":"8023",
    "addr:postcode":"53218",
    "addr:street":"W Scranton Pl",
    "iso:country":"US",
    "sg:address":"8023 W Scranton Pl",
    "sg:city":"Milwaukee",
    "sg:classifiers":[
        {
            "category":"Professional",
            "subcategory":"Lawyer & Legal Services",
            "type":"Services"
        }
    ],
    "sg:phone":"+1 414 462 8537",
    "sg:postcode":"53218",
    "sg:province":"WI",
    "wof:name":"Evelyn Lim Ang SC",
    "wof:placetype":"venue"
},
  "geometry": {"coordinates":[-88.012749,43.115598],"type":"Point"}
}