{
  "type": "Feature",
  "properties": {
    "iso:country":"US",
    "sg:address":"926 7th Ave",
    "sg:city":"Grafton",
    "sg:classifiers":[
        {
            "category":"Real Estate",
            "subcategory":"Real Estate Agent",
            "type":"Services"
        }
    ],
    "sg:phone":"+1 414 530 6960",
    "sg:postcode":"53024",
    "sg:province":"WI",
    "sg:tags":[
        "inspection"
    ],
    "wof:name":"C-J Midwest",
    "wof:placetype":"venue"
},
  "geometry": {"coordinates":[-87.957437,43.32416],"type":"Point"}
}