{
  "type": "Feature",
  "properties": {
    "iso:country":"US",
    "sg:address":"816 N Bay Shore Dr",
    "sg:city":"Sister Bay",
    "sg:classifiers":[
        {
            "category":"Food & Beverages",
            "subcategory":"Groceries & Convenience Stores",
            "type":"Retail Goods"
        }
    ],
    "sg:phone":"+1 920 854 2215",
    "sg:postcode":"54234",
    "sg:province":"WI",
    "wof:name":"Bhirdo's By The Bay",
    "wof:placetype":"venue"
},
  "geometry": {"coordinates":[-87.118913,45.19286],"type":"Point"}
}