{
  "type": "Feature",
  "properties": {
    "iso:country":"US",
    "sg:address":"6095 N Green Bay Ave",
    "sg:city":"Milwaukee",
    "sg:classifiers":[
        {
            "category":"Utilities",
            "subcategory":"Telephone",
            "type":"Services"
        }
    ],
    "sg:phone":"+1 414 732 0516",
    "sg:postcode":"53209",
    "sg:province":"WI",
    "sg:tags":[
        "communications"
    ],
    "wof:name":"Harker Online",
    "wof:placetype":"venue"
},
  "geometry": {"coordinates":[-87.93317399999999,43.129304],"type":"Point"}
}