{
  "type": "Feature",
  "properties": {
    "addr:full":"104 S East St Colby WI 54421",
    "addr:housenumber":"104",
    "addr:postcode":"54421",
    "addr:street":"S East St",
    "iso:country":"US",
    "sg:address":"104 S East St",
    "sg:city":"Colby",
    "sg:classifiers":[
        {
            "category":"Utilities",
            "subcategory":"Water",
            "type":"Services"
        }
    ],
    "sg:phone":"+1 715 223 6615",
    "sg:postcode":"54421",
    "sg:province":"WI",
    "sg:tags":[
        "company",
        "sewage"
    ],
    "wof:name":"Colby City Water Dept",
    "wof:placetype":"venue"
},
  "geometry": {"coordinates":[-90.31275599999999,44.907454],"type":"Point"}
}