{
  "type": "Feature",
  "properties": {
    "iso:country":"US",
    "sg:address":"1492 E Division Ave",
    "sg:city":"Barron",
    "sg:classifiers":[
        {
            "category":"Travel",
            "subcategory":"Hotels & Motels",
            "type":"Entertainment"
        }
    ],
    "sg:phone":"+1 715 537 3489",
    "sg:postcode":"54812",
    "sg:province":"WI",
    "sg:tags":[
        "operation"
    ],
    "wof:name":"Ramblers Rest Motel",
    "wof:placetype":"venue"
},
  "geometry": {"coordinates":[-91.835635,45.401199],"type":"Point"}
}