{
  "type": "Feature",
  "properties": {
    "addr:full":"5056 Cloverdale Rd Black River Falls WI 54615",
    "addr:housenumber":"5056",
    "addr:postcode":"54615",
    "addr:street":"Cloverdale Rd",
    "iso:country":"US",
    "sg:address":"5056 Cloverdale Rd",
    "sg:city":"Black River Falls",
    "sg:classifiers":[
        {
            "category":"Mining & Drilling",
            "type":"Manufacturing & Wholesale Goods"
        }
    ],
    "sg:phone":"+1 715 284 5859",
    "sg:postcode":"54615",
    "sg:province":"WI",
    "sg:tags":[
        "field"
    ],
    "wof:name":"Johns Pulling Sled Services",
    "wof:placetype":"venue"
},
  "geometry": {"coordinates":[-90.96449200000001,44.256879],"type":"Point"}
}