{
  "type": "Feature",
  "properties": {
    "addr:full":"505 Urban St Rothschild WI 54474",
    "addr:housenumber":"505",
    "addr:postcode":"54474",
    "addr:street":"Urban St",
    "iso:country":"US",
    "sg:address":"505 Urban St",
    "sg:city":"Rothschild",
    "sg:classifiers":[
        {
            "category":"Retail",
            "subcategory":"Repair Shop",
            "type":"Services"
        }
    ],
    "sg:phone":"+1 715 355 4321",
    "sg:postcode":"54474",
    "sg:province":"WI",
    "sg:tags":[
        "electrical",
        "business"
    ],
    "wof:name":"Barker Enterprises",
    "wof:placetype":"venue"
},
  "geometry": {"coordinates":[-89.614374,44.882742],"type":"Point"}
}