{
  "type": "Feature",
  "properties": {
    "iso:country":"US",
    "sg:address":"1907 Co Rd T",
    "sg:city":"Marshall",
    "sg:classifiers":[
        {
            "category":"Farming",
            "subcategory":"Livestock Farm",
            "type":"Manufacturing & Wholesale Goods"
        }
    ],
    "sg:phone":"+1 608 837 5580",
    "sg:postcode":"53559",
    "sg:province":"WI",
    "sg:tags":[
        "grain",
        "beef"
    ],
    "wof:name":"Yelk Farms Llp",
    "wof:placetype":"venue"
},
  "geometry": {"coordinates":[-89.151039,43.15235],"type":"Point"}
}