{
  "type": "Feature",
  "properties": {
    "iso:country":"US",
    "sg:address":"508 E Lincoln Ave",
    "sg:city":"Lancaster",
    "sg:classifiers":[
        {
            "category":"Organizations",
            "subcategory":"Religious Organization",
            "type":"Services"
        }
    ],
    "sg:phone":"+1 608 723 6553",
    "sg:postcode":"53813",
    "sg:province":"WI",
    "wof:name":"Books Bible Christan Book Str",
    "wof:placetype":"venue"
},
  "geometry": {"coordinates":[-90.704875,42.842649],"type":"Point"}
}