{
  "type": "Feature",
  "properties": {
    "iso:country":"US",
    "sg:address":"905 Waube Ln",
    "sg:city":"Green Bay",
    "sg:classifiers":[
        {
            "category":"Home & Garden",
            "subcategory":"Building Materials",
            "type":"Retail Goods"
        }
    ],
    "sg:phone":"+1 920 336 0023",
    "sg:postcode":"54304",
    "sg:province":"WI",
    "sg:tags":[
        "lumber"
    ],
    "wof:name":"Menard Inc",
    "wof:placetype":"venue"
},
  "geometry": {"coordinates":[-88.083675,44.468255],"type":"Point"}
}