{
  "type": "Feature",
  "properties": {
    "addr:full":"102 Central Bridge St Wausau WI 54401",
    "addr:housenumber":"102",
    "addr:postcode":"54401",
    "addr:street":"Central Bridge St",
    "iso:country":"US",
    "sg:address":"102 Central Bridge St",
    "sg:city":"Wausau",
    "sg:classifiers":[
        {
            "category":"Home & Garden",
            "subcategory":"Building Materials",
            "type":"Retail Goods"
        }
    ],
    "sg:phone":"+1 715 842 3036",
    "sg:postcode":"54401",
    "sg:province":"WI",
    "wof:name":"Stone's Building Ctr",
    "wof:placetype":"venue"
},
  "geometry": {"coordinates":[-89.63260699999999,44.969654],"type":"Point"}
}