{
  "type": "Feature",
  "properties": {
    "iso:country":"US",
    "sg:address":"5340 S 121st St",
    "sg:city":"Hales Corners",
    "sg:classifiers":[
        {
            "category":"Building & Trades",
            "subcategory":"Construction",
            "type":"Services"
        }
    ],
    "sg:phone":"+1 414 427 4321",
    "sg:postcode":"53130",
    "sg:province":"WI",
    "sg:tags":[
        "tile",
        "dealer"
    ],
    "wof:name":"Bartolotta Tile Co",
    "wof:placetype":"venue"
},
  "geometry": {"coordinates":[-88.065563,42.947572],"type":"Point"}
}