{
  "type": "Feature",
  "properties": {
    "addr:full":"5053 Timmers Bay Rd West Bend WI 53095",
    "addr:postcode":"5053;53095",
    "addr:street":"Timmers Bay Rd",
    "iso:country":"US",
    "sg:address":"5053 Timmers Bay Rd",
    "sg:city":"West Bend",
    "sg:classifiers":[
        {
            "category":"Autos & Motor Vehicles",
            "subcategory":"Boat Sales",
            "type":"Retail Goods"
        }
    ],
    "sg:phone":"+1 262 644 8200",
    "sg:postcode":"53095",
    "sg:province":"WI",
    "wof:name":"Kasten Marine LLC",
    "wof:placetype":"venue"
},
  "geometry": {"coordinates":[-88.254453,43.375707],"type":"Point"}
}