{
  "type": "Feature",
  "properties": {
    "iso:country":"US",
    "sg:address":"101 S Main St",
    "sg:city":"Iron Ridge",
    "sg:classifiers":[
        {
            "category":"Restaurant",
            "type":"Food & Drink"
        }
    ],
    "sg:phone":"+1 920 387 0288",
    "sg:postcode":"53035",
    "sg:province":"WI",
    "wof:name":"Lee's Chinese Restaurant",
    "wof:placetype":"venue"
},
  "geometry": {"coordinates":[-88.532101,43.399432],"type":"Point"}
}