{
  "type": "Feature",
  "properties": {
    "addr:full":"2501 W Silver Spring Dr Milwaukee WI 53209",
    "addr:housenumber":"2501",
    "addr:postcode":"53209",
    "addr:street":"W Silver Spring Dr",
    "iso:country":"US",
    "sg:address":"2501 W Silver Spring Dr",
    "sg:city":"Milwaukee",
    "sg:classifiers":[
        {
            "category":"Health Services",
            "subcategory":"Clinic",
            "type":"Services"
        },
        {
            "category":"Health Services",
            "subcategory":"Medical Lab",
            "type":"Services"
        },
        {
            "category":"Personal",
            "type":"Services"
        }
    ],
    "sg:phone":"+1 866 867 0393",
    "sg:postcode":"53209",
    "sg:province":"WI",
    "sg:tags":[
        "laboratory",
        "testing",
        "paternity",
        "drug"
    ],
    "sg:website":"http://www.rapidstdtesting.com",
    "wof:name":"Rapid STD DNA Drug Testing GLENDALE",
    "wof:placetype":"venue"
},
  "geometry": {"coordinates":[-87.943764,43.11903],"type":"Point"}
}