{
  "type": "Feature",
  "properties": {
    "addr:full":"3303 W College Ave Appleton WI 54914",
    "addr:housenumber":"3303",
    "addr:postcode":"54914",
    "addr:street":"W College Ave",
    "iso:country":"US",
    "sg:address":"3303 W College Ave",
    "sg:city":"Appleton",
    "sg:classifiers":[
        {
            "category":"Manufacturing",
            "subcategory":"Printing",
            "type":"Manufacturing & Wholesale Goods"
        }
    ],
    "sg:phone":"+1 920 832 9300",
    "sg:postcode":"54914",
    "sg:province":"WI",
    "sg:tags":[
        "printer"
    ],
    "sg:website":"www.kinkos.com",
    "wof:name":"Fed Ex Kinko's Ofc & Print Ctr",
    "wof:placetype":"venue"
},
  "geometry": {"coordinates":[-88.45319000000001,44.261674],"type":"Point"}
}