{
  "type": "Feature",
  "properties": {
    "iso:country":"US",
    "sg:address":"921 Grove St",
    "sg:city":"Oshkosh",
    "sg:classifiers":[
        {
            "category":"Social Services",
            "subcategory":"Adult Care",
            "type":"Services"
        }
    ],
    "sg:phone":"+1 920 426 1011",
    "sg:postcode":"54901",
    "sg:province":"WI",
    "sg:tags":[
        "home"
    ],
    "wof:name":"Casa Cara Home",
    "wof:placetype":"venue"
},
  "geometry": {"coordinates":[-88.52512900000001,44.027863],"type":"Point"}
}