{
  "type": "Feature",
  "properties": {
    "addr:full":"3204 Churchill Dr Madison WI 53713",
    "addr:housenumber":"3204",
    "addr:postcode":"53713",
    "addr:street":"Churchill Dr",
    "iso:country":"US",
    "sg:address":"3204 Churchill Dr",
    "sg:city":"Madison",
    "sg:classifiers":[
        {
            "category":"Organizations",
            "subcategory":"Labor Organization",
            "type":"Services"
        }
    ],
    "sg:phone":"+1 608 274 4755",
    "sg:postcode":"53713",
    "sg:province":"WI",
    "wof:name":"Afl-Cio International Laundry",
    "wof:placetype":"venue"
},
  "geometry": {"coordinates":[-89.422256,43.030012],"type":"Point"}
}