{
  "type": "Feature",
  "properties": {
    "iso:country":"US",
    "sg:address":"3202 River Ave",
    "sg:city":"Neillsville",
    "sg:classifiers":[
        {
            "category":"Farming",
            "subcategory":"Nursery",
            "type":"Manufacturing & Wholesale Goods"
        }
    ],
    "sg:phone":"+1 715 743 2234",
    "sg:postcode":"54456",
    "sg:province":"WI",
    "sg:tags":[
        "ornamental"
    ],
    "wof:name":"Maggies Greenery",
    "wof:placetype":"venue"
},
  "geometry": {"coordinates":[-90.61928,44.533715],"type":"Point"}
}