{
  "type": "Feature",
  "properties": {
    "addr:full":"7347 Co Hwy X Albany WI 53502",
    "addr:housenumber":"7347",
    "addr:postcode":"53502",
    "addr:street":"Co Hwy X",
    "iso:country":"US",
    "sg:address":"7347 Co Hwy X",
    "sg:city":"Albany",
    "sg:classifiers":[
        {
            "category":"Food & Beverages",
            "subcategory":"Groceries & Convenience Stores",
            "type":"Retail Goods"
        }
    ],
    "sg:phone":"+1 608 862 3715",
    "sg:postcode":"53502",
    "sg:province":"WI",
    "sg:tags":[
        "business"
    ],
    "wof:name":"Wayne Albertson Auctioneer",
    "wof:placetype":"venue"
},
  "geometry": {"coordinates":[-89.481238,42.773945],"type":"Point"}
}