{
  "type": "Feature",
  "properties": {
    "addr:full":"1025 N Sherman Ave Madison WI 53704",
    "addr:housenumber":"1025",
    "addr:postcode":"53704",
    "addr:street":"N Sherman Ave",
    "iso:country":"US",
    "sg:address":"1025 N Sherman Ave",
    "sg:city":"Madison",
    "sg:classifiers":[
        {
            "category":"Restaurant",
            "type":"Food & Drink"
        }
    ],
    "sg:menulink":"http://www.allmenus.com/wi/madison/261227-esquire-club/menu/",
    "sg:phone":"+1 608 249 0193",
    "sg:postcode":"53704",
    "sg:province":"WI",
    "sg:tags":[
        "american",
        "steakhouse"
    ],
    "wof:name":"Esquire Club",
    "wof:placetype":"venue"
},
  "geometry": {"coordinates":[-89.36344,43.111278],"type":"Point"}
}