{
  "type": "Feature",
  "properties": {
    "iso:country":"US",
    "sg:address":"2915 N Oakland Ave",
    "sg:city":"Milwaukee",
    "sg:classifiers":[
        {
            "category":"Professional",
            "subcategory":"Printing & Photocopies",
            "type":"Services"
        }
    ],
    "sg:phone":"+1 414 962 4633",
    "sg:postcode":"53211",
    "sg:province":"WI",
    "sg:tags":[
        "photocopying",
        "offset"
    ],
    "wof:name":"Clark Graphics",
    "wof:placetype":"venue"
},
  "geometry": {"coordinates":[-87.887968,43.072554],"type":"Point"}
}