{
  "type": "Feature",
  "properties": {
    "iso:country":"US",
    "sg:address":"6302 McKee Rd",
    "sg:city":"Fitchburg",
    "sg:classifiers":[
        {
            "category":"Retail",
            "subcategory":"Portrait Studio",
            "type":"Services"
        },
        {
            "category":"Shopping",
            "subcategory":"Photographic Equipment",
            "type":"Retail Goods"
        }
    ],
    "sg:phone":"+1 608 298 9669",
    "sg:postcode":"53719",
    "sg:province":"WI",
    "sg:tags":[
        "photographer",
        "supply"
    ],
    "wof:name":"Camera Creation Madison LLC",
    "wof:placetype":"venue"
},
  "geometry": {"coordinates":[-89.479732,43.015739],"type":"Point"}
}