{
  "type": "Feature",
  "properties": {
    "addr:full":"511 Main St Friendship WI 53934",
    "addr:housenumber":"511",
    "addr:postcode":"53934",
    "addr:street":"Main St",
    "iso:country":"US",
    "sg:address":"511 Main St",
    "sg:city":"Friendship",
    "sg:classifiers":[
        {
            "category":"Government",
            "subcategory":"Court House",
            "type":"Public Place"
        }
    ],
    "sg:phone":"+1 608 339 6158",
    "sg:postcode":"53934",
    "sg:province":"WI",
    "sg:tags":[
        "county"
    ],
    "wof:name":"Raymond E Gieringer",
    "wof:placetype":"venue"
},
  "geometry": {"coordinates":[-89.816247,43.97031],"type":"Point"}
}