{
  "type": "Feature",
  "properties": {
    "iso:country":"US",
    "sg:address":"1500 E Moreland Blvd",
    "sg:city":"Waukesha",
    "sg:classifiers":[
        {
            "category":"Real Estate",
            "subcategory":"Real Estate Services",
            "type":"Services"
        },
        {
            "category":"Banks & Credit Unions",
            "subcategory":"Bank",
            "type":"Services"
        },
        {
            "category":"Banks & Credit Unions",
            "subcategory":"Financial Services",
            "type":"Services"
        }
    ],
    "sg:phone":"+1 262 798 0201",
    "sg:postcode":"53186",
    "sg:province":"WI",
    "sg:tags":[
        "commercial",
        "loan",
        "saving",
        "mortgage"
    ],
    "sg:website":"http://www.pyramaxbank.com",
    "wof:name":"Pyramax Bank",
    "wof:placetype":"venue"
},
  "geometry": {"coordinates":[-88.205353,43.025131],"type":"Point"}
}