{
  "type": "Feature",
  "properties": {
    "addr:full":"3194 Smith Creek Rd Maple WI 54854",
    "addr:housenumber":"3194",
    "addr:postcode":"54854",
    "addr:street":"Smith Creek Rd",
    "iso:country":"US",
    "sg:address":"3194 Smith Creek Rd",
    "sg:city":"Maple",
    "sg:classifiers":[
        {
            "category":"Wholesale",
            "subcategory":"Computers",
            "type":"Manufacturing & Wholesale Goods"
        }
    ],
    "sg:phone":"+1 715 372 5161",
    "sg:postcode":"54854",
    "sg:province":"WI",
    "sg:tags":[
        "water",
        "equipment",
        "safety",
        "filter"
    ],
    "sg:website":"www.archaeologyitm.com",
    "wof:name":"Lakota Scientific Inc",
    "wof:placetype":"venue"
},
  "geometry": {"coordinates":[-91.636661,46.633201],"type":"Point"}
}