{
  "type": "Feature",
  "properties": {
    "iso:country":"US",
    "sg:address":"1032 S Cesar E Chavez Dr",
    "sg:city":"Milwaukee",
    "sg:classifiers":[
        {
            "category":"Health Services",
            "subcategory":"Doctor",
            "type":"Services"
        }
    ],
    "sg:phone":"+1 414 385 0644",
    "sg:postcode":"53204",
    "sg:province":"WI",
    "sg:tags":[
        "medical"
    ],
    "wof:name":"Childrens Urgent Care",
    "wof:placetype":"venue"
},
  "geometry": {"coordinates":[-87.933002,43.020137],"type":"Point"}
}