{
  "type": "Feature",
  "properties": {
    "addr:full":"825 E Green Bay Ave Saukville WI 53080",
    "addr:housenumber":"825",
    "addr:postcode":"53080",
    "addr:street":"E Green Bay Ave",
    "iso:country":"US",
    "sg:address":"825 E Green Bay Ave",
    "sg:city":"Saukville",
    "sg:classifiers":[
        {
            "category":"Professional",
            "subcategory":"Accounting & Tax Preparation",
            "type":"Services"
        }
    ],
    "sg:phone":"+1 262 268 1474",
    "sg:postcode":"53080",
    "sg:province":"WI",
    "sg:tags":[
        "return",
        "filing"
    ],
    "wof:name":"H & R Block Tax Svc",
    "wof:placetype":"venue"
},
  "geometry": {"coordinates":[-87.92542299999999,43.385027],"type":"Point"}
}