{
  "type": "Feature",
  "properties": {
    "iso:country":"US",
    "sg:address":"8521 W Wisconsin Ave",
    "sg:city":"Milwaukee",
    "sg:classifiers":[
        {
            "category":"Cinema",
            "subcategory":"Movie Rental",
            "type":"Entertainment"
        }
    ],
    "sg:phone":"+1 414 443 6449",
    "sg:postcode":"53226",
    "sg:province":"WI",
    "sg:tags":[
        "electrical",
        "video",
        "tape",
        "contractor"
    ],
    "wof:name":"Livewire Data Video & Audio In",
    "wof:placetype":"venue"
},
  "geometry": {"coordinates":[-88.019046,43.038507],"type":"Point"}
}