{
  "type": "Feature",
  "properties": {
    "addr:full":"1101 N Market St Milwaukee WI 53202",
    "addr:housenumber":"1101",
    "addr:postcode":"53202",
    "addr:street":"N Market St",
    "iso:country":"US",
    "sg:address":"1101 N Market St",
    "sg:city":"Milwaukee",
    "sg:classifiers":[
        {
            "category":"Health Services",
            "subcategory":"Health Practitioner",
            "type":"Services"
        }
    ],
    "sg:phone":"+1 414 223 1191",
    "sg:postcode":"53202",
    "sg:province":"WI",
    "sg:tags":[
        "therapy",
        "rehabilitation",
        "physical"
    ],
    "wof:name":"Nova Care Otptent Rhbilitation",
    "wof:placetype":"venue"
},
  "geometry": {"coordinates":[-87.90978200000001,43.044034],"type":"Point"}
}