{
  "type": "Feature",
  "properties": {
    "iso:country":"US",
    "sg:address":"1140 2nd St N",
    "sg:city":"Wisconsin Rapids",
    "sg:classifiers":[
        {
            "category":"Health Services",
            "subcategory":"Hospital",
            "type":"Services"
        }
    ],
    "sg:phone":"+1 715 424 5040",
    "sg:postcode":"54494",
    "sg:province":"WI",
    "sg:tags":[
        "mental"
    ],
    "wof:name":"Northwest Counseling-Guidance",
    "wof:placetype":"venue"
},
  "geometry": {"coordinates":[-89.816856,44.397575],"type":"Point"}
}