{
  "type": "Feature",
  "properties": {
    "iso:country":"US",
    "sg:address":"1310 Rogers St",
    "sg:city":"Stevens Point",
    "sg:classifiers":[
        {
            "category":"Manufacturing",
            "subcategory":"Retail Goods",
            "type":"Manufacturing & Wholesale Goods"
        }
    ],
    "sg:phone":"+1 715 341 4480",
    "sg:postcode":"54481",
    "sg:province":"WI",
    "sg:tags":[
        "product",
        "mfg"
    ],
    "wof:name":"Steffen Industries LLC",
    "wof:placetype":"venue"
},
  "geometry": {"coordinates":[-89.576771,44.52342],"type":"Point"}
}