{
  "type": "Feature",
  "properties": {
    "iso:country":"US",
    "sg:address":"7746 W Becher St",
    "sg:city":"Milwaukee",
    "sg:classifiers":[
        {
            "category":"Insurance",
            "subcategory":"Insurance Agent",
            "type":"Services"
        }
    ],
    "sg:phone":"+1 414 329 1000",
    "sg:postcode":"53219",
    "sg:province":"WI",
    "wof:name":"Gary Hudson Insurance Agency",
    "wof:placetype":"venue"
},
  "geometry": {"coordinates":[-88.009563,43.006397],"type":"Point"}
}