{
  "type": "Feature",
  "properties": {
    "iso:country":"US",
    "sg:address":"1520 Vernon St",
    "sg:city":"Stoughton",
    "sg:classifiers":[
        {
            "category":"Health Services",
            "subcategory":"Medical Lab",
            "type":"Services"
        }
    ],
    "sg:phone":"+1 608 873 8754",
    "sg:postcode":"53589",
    "sg:province":"WI",
    "sg:tags":[
        "laboratory"
    ],
    "wof:name":"Premier Dental Prosthetics Inc",
    "wof:placetype":"venue"
},
  "geometry": {"coordinates":[-89.203285,42.916806],"type":"Point"}
}