{
  "type": "Feature",
  "properties": {
    "iso:country":"US",
    "sg:address":"7155 N 43rd St",
    "sg:city":"Milwaukee",
    "sg:classifiers":[
        {
            "category":"Bars & Pubs",
            "type":"Food & Drink"
        }
    ],
    "sg:phone":"+1 414 352 5287",
    "sg:postcode":"53209",
    "sg:province":"WI",
    "wof:name":"Just For Fun",
    "wof:placetype":"venue"
},
  "geometry": {"coordinates":[-87.96572399999999,43.143354],"type":"Point"}
}