{
  "type": "Feature",
  "properties": {
    "iso:country":"US",
    "sg:address":"417 Scott St",
    "sg:city":"Ripon",
    "sg:classifiers":[
        {
            "category":"Building & Trades",
            "subcategory":"Construction",
            "type":"Services"
        }
    ],
    "sg:phone":"+1 920 748 9771",
    "sg:postcode":"54971",
    "sg:province":"WI",
    "sg:tags":[
        "house",
        "general",
        "contractor"
    ],
    "sg:website":"www.pollesch.com",
    "wof:name":"Pollesch Construction LLC",
    "wof:placetype":"venue"
},
  "geometry": {"coordinates":[-88.831556,43.84526],"type":"Point"}
}