{
  "type": "Feature",
  "properties": {
    "iso:country":"US",
    "sg:address":"16165 Cumberland Trl",
    "sg:city":"Brookfield",
    "sg:classifiers":[
        {
            "category":"Professional",
            "subcategory":"Management & Consulting",
            "type":"Services"
        }
    ],
    "sg:phone":"+1 262 790 1731",
    "sg:postcode":"53005",
    "sg:province":"WI",
    "wof:name":"Preferred Property Management",
    "wof:placetype":"venue"
},
  "geometry": {"coordinates":[-88.115206,43.086797],"type":"Point"}
}