{
  "type": "Feature",
  "properties": {
    "iso:country":"US",
    "sg:address":"2588 State Hwy 53",
    "sg:city":"Chippewa Falls",
    "sg:classifiers":[
        {
            "category":"Organizations",
            "subcategory":"Community Association",
            "type":"Services"
        }
    ],
    "sg:phone":"+1 715 723 0172",
    "sg:postcode":"54729",
    "sg:province":"WI",
    "wof:name":"Foe 2213",
    "wof:placetype":"venue"
},
  "geometry": {"coordinates":[-91.473395,44.846368],"type":"Point"}
}