{
  "type": "Feature",
  "properties": {
    "addr:full":"2738 Scenic Dr Campbellsport WI 53010",
    "addr:housenumber":"2738",
    "addr:postcode":"53010",
    "addr:street":"Scenic Dr",
    "iso:country":"US",
    "sg:address":"2738 Scenic Dr",
    "sg:city":"Campbellsport",
    "sg:classifiers":[
        {
            "category":"Retail",
            "subcategory":"Animal Services",
            "type":"Services"
        }
    ],
    "sg:phone":"+1 920 533 8579",
    "sg:postcode":"53010",
    "sg:province":"WI",
    "sg:website":"www.cadenskennels.com",
    "wof:name":"Cadens Kennels & Hunt Club",
    "wof:placetype":"venue"
},
  "geometry": {"coordinates":[-88.291101,43.55737],"type":"Point"}
}