{
  "type": "Feature",
  "properties": {
    "iso:country":"US",
    "sg:address":"139 E Kilbourn Ave",
    "sg:city":"Milwaukee",
    "sg:classifiers":[
        {
            "category":"Restaurant",
            "type":"Food & Drink"
        }
    ],
    "sg:menulink":"http://www.allmenus.com/wi/milwaukee/268290-kil@wat/menu/",
    "sg:phone":"+1 414 291 4793",
    "sg:postcode":"53202",
    "sg:province":"WI",
    "sg:tags":[
        "new",
        "american"
    ],
    "wof:name":"Kil@Wat",
    "wof:placetype":"venue"
},
  "geometry": {"coordinates":[-87.910465,43.042196],"type":"Point"}
}