{
  "type": "Feature",
  "properties": {
    "iso:country":"US",
    "sg:address":"150 Front St",
    "sg:city":"Beaver Dam",
    "sg:classifiers":[
        {
            "category":"Restaurant",
            "type":"Food & Drink"
        }
    ],
    "sg:phone":"+1 920 887 3838",
    "sg:postcode":"53916",
    "sg:province":"WI",
    "wof:name":"Ming's Garden Chinese",
    "wof:placetype":"venue"
},
  "geometry": {"coordinates":[-88.837809,43.45631],"type":"Point"}
}