{
  "type": "Feature",
  "properties": {
    "iso:country":"US",
    "sg:address":"2215 Minnesota St",
    "sg:city":"Oshkosh",
    "sg:classifiers":[
        {
            "category":"Food & Beverages",
            "subcategory":"Bakery",
            "type":"Retail Goods"
        }
    ],
    "sg:phone":"+1 920 235 3411",
    "sg:postcode":"54902",
    "sg:province":"WI",
    "sg:tags":[
        "baker"
    ],
    "wof:name":"Interstate Brands Corp",
    "wof:placetype":"venue"
},
  "geometry": {"coordinates":[-88.545075,43.995048],"type":"Point"}
}