{
  "type": "Feature",
  "properties": {
    "iso:country":"US",
    "sg:address":"107 W Eau Claire St",
    "sg:city":"Rice Lake",
    "sg:classifiers":[
        {
            "category":"Manufacturing",
            "subcategory":"Printing",
            "type":"Manufacturing & Wholesale Goods"
        }
    ],
    "sg:phone":"+1 715 234 7123",
    "sg:postcode":"54868",
    "sg:province":"WI",
    "sg:tags":[
        "multimedia"
    ],
    "wof:name":"Rice Lake Media Duplication",
    "wof:placetype":"venue"
},
  "geometry": {"coordinates":[-91.73620699999999,45.503516],"type":"Point"}
}