{
  "type": "Feature",
  "properties": {
    "iso:country":"US",
    "sg:address":"8459 Seneca Dr",
    "sg:city":"Menomonee Falls",
    "sg:classifiers":[
        {
            "category":"Shopping",
            "subcategory":"Bicycles & Sporting Goods",
            "type":"Retail Goods"
        }
    ],
    "sg:phone":"+1 262 442 5092",
    "sg:postcode":"53051",
    "sg:province":"WI",
    "wof:name":"Right Gear LLC",
    "wof:placetype":"venue"
},
  "geometry": {"coordinates":[-88.140599,43.171159],"type":"Point"}
}