{
  "type": "Feature",
  "properties": {
    "iso:country":"US",
    "sg:address":"26566 Co Hwy X",
    "sg:city":"Cadott",
    "sg:classifiers":[
        {
            "category":"Bars & Pubs",
            "type":"Food & Drink"
        }
    ],
    "sg:phone":"+1 715 289 4955",
    "sg:postcode":"54727",
    "sg:province":"WI",
    "sg:tags":[
        "drinking"
    ],
    "wof:name":"J & J's Country Fest Inn",
    "wof:placetype":"venue"
},
  "geometry": {"coordinates":[-91.135258,44.944635],"type":"Point"}
}