{
  "type": "Feature",
  "properties": {
    "iso:country":"US",
    "sg:address":"700 N Main St",
    "sg:city":"Verona",
    "sg:classifiers":[
        {
            "category":"Education",
            "subcategory":"School",
            "type":"Public Place"
        }
    ],
    "sg:phone":"+1 608 845 4306",
    "sg:postcode":"53593",
    "sg:province":"WI",
    "wof:name":"Verona Community Education Ofc",
    "wof:placetype":"venue"
},
  "geometry": {"coordinates":[-89.533605,42.998235],"type":"Point"}
}