{
  "type": "Feature",
  "properties": {
    "iso:country":"US",
    "sg:address":"208 S Main St",
    "sg:city":"Fort Atkinson",
    "sg:classifiers":[
        {
            "category":"Shopping",
            "type":"Retail Goods"
        }
    ],
    "sg:phone":"+1 920 563 9959",
    "sg:postcode":"53538",
    "sg:province":"WI",
    "sg:tags":[
        "merchandise"
    ],
    "wof:name":"2d Framing",
    "wof:placetype":"venue"
},
  "geometry": {"coordinates":[-88.83708,42.926768],"type":"Point"}
}