{
  "type": "Feature",
  "properties": {
    "addr:full":"5006 Sunset St Schofield WI 54476",
    "addr:housenumber":"5006",
    "addr:postcode":"54476",
    "addr:street":"Sunset St",
    "iso:country":"US",
    "sg:address":"5006 Sunset St",
    "sg:city":"Schofield",
    "sg:classifiers":[
        {
            "category":"Building & Trades",
            "subcategory":"Construction",
            "type":"Services"
        }
    ],
    "sg:phone":"+1 715 359 6291",
    "sg:postcode":"54476",
    "sg:province":"WI",
    "sg:tags":[
        "contractor"
    ],
    "wof:name":"Central Wisconsin Roofing Inc",
    "wof:placetype":"venue"
},
  "geometry": {"coordinates":[-89.565302,44.911744],"type":"Point"}
}