{
  "type": "Feature",
  "properties": {
    "addr:full":"514 S Main St Markesan WI 53946",
    "addr:housenumber":"514",
    "addr:postcode":"53946",
    "addr:street":"S Main St",
    "iso:country":"US",
    "sg:address":"514 S Main St",
    "sg:city":"Markesan",
    "sg:classifiers":[
        {
            "category":"Building & Trades",
            "subcategory":"Plumbing",
            "type":"Services"
        }
    ],
    "sg:phone":"+1 920 398 2181",
    "sg:postcode":"53946",
    "sg:province":"WI",
    "sg:tags":[
        "conditioning",
        "air",
        "system",
        "contractor"
    ],
    "wof:name":"B J HTG & AC Contr",
    "wof:placetype":"venue"
},
  "geometry": {"coordinates":[-88.989384,43.701426],"type":"Point"}
}