{
  "type": "Feature",
  "properties": {
    "iso:country":"US",
    "sg:address":"4340 Galetka Ln",
    "sg:city":"Radisson",
    "sg:classifiers":[
        {
            "category":"Personal",
            "subcategory":"Beauty Salon",
            "type":"Services"
        }
    ],
    "sg:phone":"+1 715 266 8005",
    "sg:postcode":"54867",
    "sg:province":"WI",
    "wof:name":"Sandys Hair Affair",
    "wof:placetype":"venue"
},
  "geometry": {"coordinates":[-91.245626,45.788963],"type":"Point"}
}