{
  "type": "Feature",
  "properties": {
    "iso:country":"US",
    "sg:address":"10405 Little Bear Rd",
    "sg:city":"Spring Green",
    "sg:classifiers":[
        {
            "category":"Real Estate",
            "subcategory":"Real Estate Agent",
            "type":"Services"
        }
    ],
    "sg:phone":"+1 608 588 2496",
    "sg:postcode":"53588",
    "sg:province":"WI",
    "wof:name":"Koller Enterprises LLC",
    "wof:placetype":"venue"
},
  "geometry": {"coordinates":[-90.140046,43.268471],"type":"Point"}
}