{
  "type": "Feature",
  "properties": {
    "iso:country":"US",
    "sg:address":"35720 52nd St",
    "sg:city":"Burlington",
    "sg:classifiers":[
        {
            "category":"Personal",
            "subcategory":"Beauty Salon",
            "type":"Services"
        }
    ],
    "sg:phone":"+1 262 537 4971",
    "sg:postcode":"53105",
    "sg:province":"WI",
    "wof:name":"Tracy's Hair FX",
    "wof:placetype":"venue"
},
  "geometry": {"coordinates":[-88.245965,42.58946],"type":"Point"}
}