{
  "type": "Feature",
  "properties": {
    "iso:country":"US",
    "sg:address":"20583 Ridge Rd",
    "sg:city":"Jackson",
    "sg:classifiers":[
        {
            "category":"Real Estate",
            "subcategory":"Real Estate Agent",
            "type":"Services"
        }
    ],
    "sg:phone":"+1 262 677 4328",
    "sg:postcode":"53037",
    "sg:province":"WI",
    "wof:name":"Blakeslee Ltd 3 LLC",
    "wof:placetype":"venue"
},
  "geometry": {"coordinates":[-88.165133,43.328951],"type":"Point"}
}