{
  "type": "Feature",
  "properties": {
    "iso:country":"US",
    "sg:address":"666 S Thompson Rd",
    "sg:city":"Sun Prairie",
    "sg:classifiers":[
        {
            "category":"Wholesale",
            "subcategory":"Auto Parts",
            "type":"Manufacturing & Wholesale Goods"
        }
    ],
    "sg:phone":"+1 608 244 9146",
    "sg:postcode":"53590",
    "sg:province":"WI",
    "sg:tags":[
        "truck",
        "accessory"
    ],
    "sg:website":"www.jl4wd.com",
    "wof:name":"J & L4-WHEEL Drive Ctr Inc",
    "wof:placetype":"venue"
},
  "geometry": {"coordinates":[-89.25458999999999,43.172867],"type":"Point"}
}