{
  "type": "Feature",
  "properties": {
    "iso:country":"US",
    "sg:address":"4251 W Beltline Hwy",
    "sg:city":"Madison",
    "sg:classifiers":[
        {
            "category":"Professional",
            "subcategory":"Business Services",
            "type":"Services"
        }
    ],
    "sg:phone":"+1 608 276 8288",
    "sg:postcode":"53711",
    "sg:province":"WI",
    "wof:name":"Sleepless Nghts Rcrding Studio",
    "wof:placetype":"venue"
},
  "geometry": {"coordinates":[-89.44705999999999,43.034636],"type":"Point"}
}