{
  "type": "Feature",
  "properties": {
    "iso:country":"US",
    "sg:address":"2115 New Jersey Ave",
    "sg:city":"Sheboygan",
    "sg:classifiers":[
        {
            "category":"Retail",
            "subcategory":"Laundry & Dry Cleaning",
            "type":"Services"
        }
    ],
    "sg:phone":"+1 920 457 2508",
    "sg:postcode":"53081",
    "sg:province":"WI",
    "sg:tags":[
        "linen",
        "supply"
    ],
    "wof:name":"Wolf's Linen & Uniform Rental",
    "wof:placetype":"venue"
},
  "geometry": {"coordinates":[-87.73577899999999,43.746433],"type":"Point"}
}