{
  "type": "Feature",
  "properties": {
    "iso:country":"US",
    "sg:address":"410 N Falls St",
    "sg:city":"River Falls",
    "sg:classifiers":[
        {
            "category":"Health Services",
            "subcategory":"Health Practitioner",
            "type":"Services"
        }
    ],
    "sg:phone":"+1 715 425 3801",
    "sg:postcode":"54022",
    "sg:province":"WI",
    "wof:name":"Uw",
    "wof:placetype":"venue"
},
  "geometry": {"coordinates":[-92.63353,44.862253],"type":"Point"}
}