{
  "type": "Feature",
  "properties": {
    "iso:country":"US",
    "sg:address":"926 N 29th St",
    "sg:city":"Milwaukee",
    "sg:classifiers":[
        {
            "category":"Professional",
            "subcategory":"Engineering",
            "type":"Services"
        }
    ],
    "sg:phone":"+1 414 344 1718",
    "sg:postcode":"53208",
    "sg:province":"WI",
    "wof:name":"Dm Design Ltd",
    "wof:placetype":"venue"
},
  "geometry": {"coordinates":[-87.95061800000001,43.042385],"type":"Point"}
}