{
  "type": "Feature",
  "properties": {
    "iso:country":"US",
    "sg:address":"4738 S Fairview Dr",
    "sg:city":"New Berlin",
    "sg:classifiers":[
        {
            "category":"Building & Trades",
            "subcategory":"Construction",
            "type":"Services"
        }
    ],
    "sg:phone":"+1 262 679 3345",
    "sg:postcode":"53146",
    "sg:province":"WI",
    "sg:tags":[
        "residential"
    ],
    "wof:name":"Kroeninger Construction",
    "wof:placetype":"venue"
},
  "geometry": {"coordinates":[-88.144647,42.958379],"type":"Point"}
}