{
  "type": "Feature",
  "properties": {
    "iso:country":"US",
    "sg:address":"2121 Cleveland Ave",
    "sg:city":"Marinette",
    "sg:classifiers":[
        {
            "category":"Manufacturing",
            "subcategory":"Motor Vehicles & Parts",
            "type":"Manufacturing & Wholesale Goods"
        }
    ],
    "sg:phone":"+1 715 735 9311",
    "sg:postcode":"54143",
    "sg:province":"WI",
    "sg:tags":[
        "manufacture",
        "tank",
        "air"
    ],
    "sg:website":"www.silvanind.com",
    "wof:name":"Silvan Industries Inc",
    "wof:placetype":"venue"
},
  "geometry": {"coordinates":[-87.64143,45.084917],"type":"Point"}
}