{
  "type": "Feature",
  "properties": {
    "iso:country":"US",
    "sg:address":"1418 State Hwy 78",
    "sg:city":"Mount Horeb",
    "sg:phone":"+1 608 437 4940",
    "sg:postcode":"53572",
    "sg:province":"WI",
    "sg:tags":[
        "farm",
        "corn"
    ],
    "wof:name":"Kenneth Hefty",
    "wof:placetype":"venue"
},
  "geometry": {"coordinates":[-89.79595999999999,42.931847],"type":"Point"}
}