{
  "type": "Feature",
  "properties": {
    "iso:country":"US",
    "sg:address":"3720 Milwaukee St",
    "sg:city":"Madison",
    "sg:classifiers":[
        {
            "category":"Retail",
            "subcategory":"Auto Repair",
            "type":"Services"
        }
    ],
    "sg:phone":"+1 608 241 8880",
    "sg:postcode":"53714",
    "sg:province":"WI",
    "sg:tags":[
        "shop",
        "body",
        "automobile",
        "collision",
        "automotive",
        "painting"
    ],
    "wof:name":"M & M Auto Body Inc",
    "wof:placetype":"venue"
},
  "geometry": {"coordinates":[-89.321933,43.098314],"type":"Point"}
}