{
  "type": "Feature",
  "properties": {
    "iso:country":"US",
    "sg:address":"921 S Monroe St",
    "sg:city":"New Lisbon",
    "sg:classifiers":[
        {
            "category":"Retail",
            "subcategory":"Repair Shop",
            "type":"Services"
        }
    ],
    "sg:phone":"+1 608 562 3708",
    "sg:postcode":"53950",
    "sg:province":"WI",
    "wof:name":"Pettis Cycle Sales",
    "wof:placetype":"venue"
},
  "geometry": {"coordinates":[-90.166174,43.870831],"type":"Point"}
}