{
  "type": "Feature",
  "properties": {
    "iso:country":"US",
    "sg:address":"145 Kohler Dr",
    "sg:city":"Fredonia",
    "sg:classifiers":[
        {
            "category":"Retail",
            "subcategory":"Repair Shop",
            "type":"Services"
        }
    ],
    "sg:phone":"+1 262 692 6404",
    "sg:postcode":"53021",
    "sg:province":"WI",
    "wof:name":"Accurate Medical Electronic",
    "wof:placetype":"venue"
},
  "geometry": {"coordinates":[-88.042641,43.503406],"type":"Point"}
}