{
  "type": "Feature",
  "properties": {
    "iso:country":"US",
    "sg:address":"10610 W Folsom St",
    "sg:city":"Eau Claire",
    "sg:classifiers":[
        {
            "category":"Building & Trades",
            "subcategory":"Construction",
            "type":"Services"
        }
    ],
    "sg:phone":"+1 715 874 6824",
    "sg:postcode":"54703",
    "sg:province":"WI",
    "sg:tags":[
        "contractor"
    ],
    "wof:name":"Merrit Construction",
    "wof:placetype":"venue"
},
  "geometry": {"coordinates":[-91.64400000000001,44.828495],"type":"Point"}
}