{
  "type": "Feature",
  "properties": {
    "iso:country":"US",
    "sg:address":"3318 Washington Ave",
    "sg:city":"Racine",
    "sg:classifiers":[
        {
            "category":"Organizations",
            "subcategory":"Non-profit Organization",
            "type":"Services"
        }
    ],
    "sg:phone":"+1 262 637 3826",
    "sg:postcode":"53405",
    "sg:province":"WI",
    "wof:name":"Hand To Hand",
    "wof:placetype":"venue"
},
  "geometry": {"coordinates":[-87.819665,42.718768],"type":"Point"}
}