{
  "type": "Feature",
  "properties": {
    "iso:country":"US",
    "sg:address":"5143 Co Rd A",
    "sg:city":"Oregon",
    "sg:classifiers":[
        {
            "category":"Food & Beverages",
            "subcategory":"Groceries & Convenience Stores",
            "type":"Retail Goods"
        }
    ],
    "sg:phone":"+1 608 835 7191",
    "sg:postcode":"53575",
    "sg:province":"WI",
    "wof:name":"Starvin Marvins Inc",
    "wof:placetype":"venue"
},
  "geometry": {"coordinates":[-89.389029,42.892589],"type":"Point"}
}