{
  "type": "Feature",
  "properties": {
    "addr:full":"4606 W Johnson Ave Racine WI 53405",
    "addr:housenumber":"4606",
    "addr:postcode":"53405",
    "addr:street":"W Johnson Ave",
    "iso:country":"US",
    "sg:address":"4606 W Johnson Ave",
    "sg:city":"Racine",
    "sg:classifiers":[
        {
            "category":"Health Services",
            "subcategory":"Nursing And Care Facility",
            "type":"Services"
        }
    ],
    "sg:phone":"+1 262 639 4309",
    "sg:postcode":"53405",
    "sg:province":"WI",
    "wof:name":"Terrence Serenity",
    "wof:placetype":"venue"
},
  "geometry": {"coordinates":[-87.836061,42.780671],"type":"Point"}
}