{
  "type": "Feature",
  "properties": {
    "iso:country":"US",
    "sg:address":"928 W 10th St",
    "sg:city":"Kaukauna",
    "sg:classifiers":[
        {
            "category":"Real Estate",
            "subcategory":"Real Estate Agent",
            "type":"Services"
        }
    ],
    "sg:phone":"+1 920 759 9717",
    "sg:postcode":"54130",
    "sg:province":"WI",
    "sg:tags":[
        "inspection"
    ],
    "wof:name":"Brick Kicker",
    "wof:placetype":"venue"
},
  "geometry": {"coordinates":[-88.29109699999999,44.272076],"type":"Point"}
}