{
  "type": "Feature",
  "properties": {
    "iso:country":"US",
    "sg:address":"11065 Camp Ave",
    "sg:city":"Sparta",
    "sg:classifiers":[
        {
            "category":"Home & Garden",
            "subcategory":"Household Appliances",
            "type":"Retail Goods"
        }
    ],
    "sg:phone":"+1 608 272 3814",
    "sg:postcode":"54656",
    "sg:province":"WI",
    "wof:name":"Sand Country Woodworks",
    "wof:placetype":"venue"
},
  "geometry": {"coordinates":[-90.770263,44.100563],"type":"Point"}
}