{
  "type": "Feature",
  "properties": {
    "iso:country":"US",
    "sg:address":"1814 Grafton Rd",
    "sg:city":"Madison",
    "sg:classifiers":[
        {
            "category":"Professional",
            "subcategory":"Management & Consulting",
            "type":"Services"
        }
    ],
    "sg:phone":"+1 608 224 2104",
    "sg:postcode":"53716",
    "sg:province":"WI",
    "wof:name":"Corville Group",
    "wof:placetype":"venue"
},
  "geometry": {"coordinates":[-89.285132,43.072591],"type":"Point"}
}