{
  "type": "Feature",
  "properties": {
    "iso:country":"US",
    "sg:address":"12544 White Pine Dr",
    "sg:city":"Minong",
    "sg:classifiers":[
        {
            "category":"Professional",
            "subcategory":"Lawyer & Legal Services",
            "type":"Services"
        }
    ],
    "sg:phone":"+1 715 466 5396",
    "sg:postcode":"54859",
    "sg:province":"WI",
    "wof:name":"Andrew S Lawton",
    "wof:placetype":"venue"
},
  "geometry": {"coordinates":[-91.983878,46.087052],"type":"Point"}
}