{
  "type": "Feature",
  "properties": {
    "iso:country":"US",
    "sg:address":"202 E Union St",
    "sg:city":"Waupaca",
    "sg:classifiers":[
        {
            "category":"Professional",
            "subcategory":"Lawyer & Legal Services",
            "type":"Services"
        }
    ],
    "sg:phone":"+1 715 258 2227",
    "sg:postcode":"54981",
    "sg:province":"WI",
    "sg:tags":[
        "attorney"
    ],
    "wof:name":"Mark Morrow Law Offices",
    "wof:placetype":"venue"
},
  "geometry": {"coordinates":[-89.083585,44.357013],"type":"Point"}
}