{
  "type": "Feature",
  "properties": {
    "iso:country":"US",
    "sg:address":"7320 Noraire Dr",
    "sg:city":"Franksville",
    "sg:classifiers":[
        {
            "category":"Professional",
            "subcategory":"Business Services",
            "type":"Services"
        }
    ],
    "sg:phone":"+1 262 895 3795",
    "sg:postcode":"53126",
    "sg:province":"WI",
    "sg:tags":[
        "mobile",
        "marketing",
        "exhibit",
        "event"
    ],
    "wof:name":"Cad Industries LLC",
    "wof:placetype":"venue"
},
  "geometry": {"coordinates":[-88.079021,42.819822],"type":"Point"}
}