{
  "type": "Feature",
  "properties": {
    "addr:full":"3386 Morrissey Rd Mauston WI 53948",
    "addr:housenumber":"3386",
    "addr:postcode":"53948",
    "addr:street":"Morrissey Rd",
    "iso:country":"US",
    "sg:address":"3386 Morrissey Rd",
    "sg:city":"Mauston",
    "sg:classifiers":[
        {
            "category":"Farming",
            "subcategory":"Farm",
            "type":"Manufacturing & Wholesale Goods"
        }
    ],
    "sg:phone":"+1 608 847 7594",
    "sg:postcode":"53948",
    "sg:province":"WI",
    "sg:tags":[
        "crop",
        "general"
    ],
    "wof:name":"Pat Garrigan",
    "wof:placetype":"venue"
},
  "geometry": {"coordinates":[-90.004993,43.752651],"type":"Point"}
}