{
  "type": "Feature",
  "properties": {
    "iso:country":"US",
    "sg:address":"3013 E Puetz Rd",
    "sg:city":"Oak Creek",
    "sg:classifiers":[
        {
            "category":"Building & Trades",
            "subcategory":"Electrical",
            "type":"Services"
        }
    ],
    "sg:phone":"+1 414 764 7513",
    "sg:postcode":"53154",
    "sg:province":"WI",
    "sg:tags":[
        "electrical",
        "contractor"
    ],
    "wof:name":"EE Services",
    "wof:placetype":"venue"
},
  "geometry": {"coordinates":[-87.873653,42.886222],"type":"Point"}
}