{
  "type": "Feature",
  "properties": {
    "addr:full":"2917 Woodridge Ln Waukesha WI 53188",
    "addr:housenumber":"2917",
    "addr:postcode":"53188",
    "addr:street":"Woodridge Ln",
    "iso:country":"US",
    "sg:address":"2917 Woodridge Ln",
    "sg:city":"Waukesha",
    "sg:classifiers":[
        {
            "category":"Restaurant",
            "type":"Food & Drink"
        }
    ],
    "sg:phone":"+1 262 970 9420",
    "sg:postcode":"53188",
    "sg:province":"WI",
    "sg:tags":[
        "eating"
    ],
    "wof:name":"Bruce Brazier Sales LLC",
    "wof:placetype":"venue"
},
  "geometry": {"coordinates":[-88.279657,43.043596],"type":"Point"}
}