{
  "type": "Feature",
  "properties": {
    "iso:country":"US",
    "sg:address":"39866 US Hwy 53",
    "sg:city":"Whitehall",
    "sg:classifiers":[
        {
            "category":"Food & Beverages",
            "subcategory":"Groceries & Convenience Stores",
            "type":"Retail Goods"
        }
    ],
    "sg:phone":"+1 715 983 2141",
    "sg:postcode":"54773",
    "sg:province":"WI",
    "wof:name":"Cenex Convenience Store",
    "wof:placetype":"venue"
},
  "geometry": {"coordinates":[-91.216083,44.419574],"type":"Point"}
}