{
  "type": "Feature",
  "properties": {
    "addr:full":"1935 State St Racine WI 53404",
    "addr:housenumber":"1935",
    "addr:postcode":"53404",
    "addr:street":"State St",
    "iso:country":"US",
    "sg:address":"1935 State St",
    "sg:city":"Racine",
    "sg:classifiers":[
        {
            "category":"Professional",
            "subcategory":"Business Services",
            "type":"Services"
        }
    ],
    "sg:phone":"+1 262 898 2008",
    "sg:postcode":"53404",
    "sg:province":"WI",
    "wof:name":"Amica Business Solutions",
    "wof:placetype":"venue"
},
  "geometry": {"coordinates":[-87.80541100000001,42.735569],"type":"Point"}
}