{
  "type": "Feature",
  "properties": {
    "iso:country":"US",
    "sg:address":"2063 Co Rd G",
    "sg:city":"Livingston",
    "sg:classifiers":[
        {
            "category":"Farming",
            "subcategory":"Dairy Farm",
            "type":"Manufacturing & Wholesale Goods"
        }
    ],
    "sg:phone":"+1 608 623 2405",
    "sg:postcode":"53554",
    "sg:province":"WI",
    "wof:name":"Mark Caygill",
    "wof:placetype":"venue"
},
  "geometry": {"coordinates":[-90.35394100000001,42.906379],"type":"Point"}
}