{
  "type": "Feature",
  "properties": {
    "iso:country":"US",
    "sg:address":"3205 Co Rd Vv",
    "sg:city":"Seymour",
    "sg:phone":"+1 920 833 6663",
    "sg:postcode":"54165",
    "sg:province":"WI",
    "sg:tags":[
        "farm",
        "grain",
        "cash",
        "soybean"
    ],
    "wof:name":"Neal Krohlow",
    "wof:placetype":"venue"
},
  "geometry": {"coordinates":[-88.33190500000001,44.558263],"type":"Point"}
}