{
  "type": "Feature",
  "properties": {
    "iso:country":"US",
    "sg:address":"1009 W Lincoln Ave",
    "sg:city":"Milwaukee",
    "sg:classifiers":[
        {
            "category":"Building & Trades",
            "subcategory":"Construction",
            "type":"Services"
        }
    ],
    "sg:phone":"+1 414 383 5981",
    "sg:postcode":"53215",
    "sg:province":"WI",
    "sg:tags":[
        "contractor",
        "specialty",
        "mfg"
    ],
    "wof:name":"Studio One Signs",
    "wof:placetype":"venue"
},
  "geometry": {"coordinates":[-87.925157,43.002768],"type":"Point"}
}