{
  "type": "Feature",
  "properties": {
    "iso:country":"US",
    "sg:address":"16100 W Finnernan Rd",
    "sg:city":"Evansville",
    "sg:classifiers":[
        {
            "category":"Farming",
            "subcategory":"Dairy Farm",
            "type":"Manufacturing & Wholesale Goods"
        }
    ],
    "sg:phone":"+1 608 882 4465",
    "sg:postcode":"53536",
    "sg:province":"WI",
    "wof:name":"Keith Trow",
    "wof:placetype":"venue"
},
  "geometry": {"coordinates":[-89.31934200000001,42.717583],"type":"Point"}
}