{
  "type": "Feature",
  "properties": {
    "iso:country":"US",
    "sg:address":"7105 Mariner Cir",
    "sg:city":"Fond Du Lac",
    "sg:classifiers":[
        {
            "category":"Insurance",
            "subcategory":"Insurance Agent",
            "type":"Services"
        }
    ],
    "sg:phone":"+1 920 924 3810",
    "sg:postcode":"54937",
    "sg:province":"WI",
    "wof:name":"Wheels Insurance",
    "wof:placetype":"venue"
},
  "geometry": {"coordinates":[-88.514931,43.82012],"type":"Point"}
}