{
  "type": "Feature",
  "properties": {
    "addr:full":"7815 Dunn Lake Rd Spooner WI 54801",
    "addr:housenumber":"7815",
    "addr:postcode":"54801",
    "addr:street":"Dunn Lake Rd",
    "iso:country":"US",
    "sg:address":"7815 Dunn Lake Rd",
    "sg:city":"Spooner",
    "sg:classifiers":[
        {
            "category":"Travel",
            "subcategory":"Hotels & Motels",
            "type":"Entertainment"
        }
    ],
    "sg:phone":"+1 715 635 9557",
    "sg:postcode":"54801",
    "sg:province":"WI",
    "sg:tags":[
        "operation"
    ],
    "wof:name":"Persen Dunn Lake Resort",
    "wof:placetype":"venue"
},
  "geometry": {"coordinates":[-91.937583,45.928185],"type":"Point"}
}