{
  "type": "Feature",
  "properties": {
    "iso:country":"US",
    "sg:address":"7501 N Granville Rd",
    "sg:city":"Milwaukee",
    "sg:classifiers":[
        {
            "category":"Education",
            "subcategory":"School",
            "type":"Public Place"
        }
    ],
    "sg:phone":"+1 262 236 1200",
    "sg:postcode":"53224",
    "sg:province":"WI",
    "wof:name":"Vincent High School",
    "wof:placetype":"venue"
},
  "geometry": {"coordinates":[-88.02901199999999,43.15527],"type":"Point"}
}