{
  "type": "Feature",
  "properties": {
    "addr:full":"777 E Park Ave Chippewa Falls WI 54729",
    "addr:housenumber":"777",
    "addr:postcode":"54729",
    "addr:street":"E Park Ave",
    "iso:country":"US",
    "sg:address":"777 E Park Ave",
    "sg:city":"Chippewa Falls",
    "sg:classifiers":[
        {
            "category":"Health Services",
            "subcategory":"Doctor",
            "type":"Services"
        }
    ],
    "sg:phone":"+1 715 723 0366",
    "sg:postcode":"54729",
    "sg:province":"WI",
    "wof:name":"Snyder Patrick M DDS",
    "wof:placetype":"venue"
},
  "geometry": {"coordinates":[-91.372096,44.932095],"type":"Point"}
}