{
  "type": "Feature",
  "properties": {
    "iso:country":"US",
    "sg:address":"1110 E Main St",
    "sg:city":"Merrill",
    "sg:classifiers":[
        {
            "category":"Government",
            "subcategory":"Office",
            "type":"Public Place"
        }
    ],
    "sg:phone":"+1 715 536 0322",
    "sg:postcode":"54452",
    "sg:province":"WI",
    "wof:name":"Lincoln County Small Claims",
    "wof:placetype":"venue"
},
  "geometry": {"coordinates":[-89.683226,45.180905],"type":"Point"}
}