{
  "type": "Feature",
  "properties": {
    "iso:country":"US",
    "sg:address":"1310 Lake Shore Dr E",
    "sg:city":"Ashland",
    "sg:classifiers":[
        {
            "category":"Utilities",
            "subcategory":"Telephone",
            "type":"Services"
        }
    ],
    "sg:phone":"+1 715 682 0290",
    "sg:postcode":"54806",
    "sg:province":"WI",
    "sg:tags":[
        "local",
        "co"
    ],
    "wof:name":"Chequamegon Telephone Coop",
    "wof:placetype":"venue"
},
  "geometry": {"coordinates":[-90.8698,46.599869],"type":"Point"}
}