{
  "type": "Feature",
  "properties": {
    "iso:country":"US",
    "sg:address":"102 N Washington St",
    "sg:city":"St Croix Falls",
    "sg:classifiers":[
        {
            "category":"Banks & Credit Unions",
            "subcategory":"Bank",
            "type":"Services"
        }
    ],
    "sg:phone":"+1 715 483 3241",
    "sg:postcode":"54024",
    "sg:province":"WI",
    "sg:website":"www.eaglevalleybank.com",
    "wof:name":"Eagle Valley Bank",
    "wof:placetype":"venue"
},
  "geometry": {"coordinates":[-92.64476500000001,45.412059],"type":"Point"}
}