{
  "type": "Feature",
  "properties": {
    "iso:country":"US",
    "sg:address":"7414 Loy Rd",
    "sg:city":"Arena",
    "sg:phone":"+1 608 753 2273",
    "sg:postcode":"53503",
    "sg:province":"WI",
    "sg:tags":[
        "beef",
        "farm",
        "corn",
        "soybean",
        "cattle",
        "feedlot"
    ],
    "wof:name":"Don Winch",
    "wof:placetype":"venue"
},
  "geometry": {"coordinates":[-89.94471900000001,43.146914],"type":"Point"}
}