{
  "type": "Feature",
  "properties": {
    "iso:country":"US",
    "sg:address":"4494 440th St",
    "sg:city":"Menomonie",
    "sg:classifiers":[
        {
            "category":"Retail",
            "subcategory":"Repair Shop",
            "type":"Services"
        }
    ],
    "sg:phone":"+1 715 235 4222",
    "sg:postcode":"54751",
    "sg:province":"WI",
    "sg:tags":[
        "plumbing",
        "drain",
        "cleaning",
        "sewer"
    ],
    "wof:name":"Randy's Septic Svc",
    "wof:placetype":"venue"
},
  "geometry": {"coordinates":[-91.939768,44.840566],"type":"Point"}
}