{
  "type": "Feature",
  "properties": {
    "iso:country":"US",
    "sg:address":"3600 W Pierce St",
    "sg:city":"Milwaukee",
    "sg:classifiers":[
        {
            "category":"Retail",
            "subcategory":"Repair Shop",
            "type":"Services"
        },
        {
            "category":"Building & Trades",
            "subcategory":"Construction",
            "type":"Services"
        }
    ],
    "sg:phone":"+1 414 645 7550",
    "sg:postcode":"53215",
    "sg:province":"WI",
    "sg:tags":[
        "machine",
        "welder"
    ],
    "wof:name":"Metal Spraying Corp",
    "wof:placetype":"venue"
},
  "geometry": {"coordinates":[-87.958862,43.023609],"type":"Point"}
}