{
  "type": "Feature",
  "properties": {
    "addr:full":"2636 State Hwy 47 S Lac Du Flambeau WI 54538",
    "addr:housenumber":"2636",
    "addr:postcode":"54538",
    "addr:street":"State Hwy 47 S Lac Du Flambeau",
    "iso:country":"US",
    "sg:address":"2636 State Hwy 47 S",
    "sg:city":"Lac Du Flambeau",
    "sg:classifiers":[
        {
            "category":"Bars & Pubs",
            "type":"Food & Drink"
        }
    ],
    "sg:phone":"+1 715 588 3527",
    "sg:postcode":"54538",
    "sg:province":"WI",
    "sg:tags":[
        "drinking"
    ],
    "wof:name":"Legends Bar",
    "wof:placetype":"venue"
},
  "geometry": {"coordinates":[-89.860868,45.977981],"type":"Point"}
}