{
  "type": "Feature",
  "properties": {
    "iso:country":"US",
    "sg:address":"2555 Packerland Dr",
    "sg:city":"Green Bay",
    "sg:classifiers":[
        {
            "category":"Professional",
            "subcategory":"Business Services",
            "type":"Services"
        }
    ],
    "sg:phone":"+1 920 497 0781",
    "sg:postcode":"54313",
    "sg:province":"WI",
    "sg:tags":[
        "program",
        "incentive"
    ],
    "wof:name":"Oneida Tribe Of Indians",
    "wof:placetype":"venue"
},
  "geometry": {"coordinates":[-88.106984,44.491578],"type":"Point"}
}