{
  "type": "Feature",
  "properties": {
    "iso:country":"US",
    "sg:address":"5800 Broad St",
    "sg:city":"Greendale",
    "sg:classifiers":[
        {
            "category":"Professional",
            "subcategory":"Management & Consulting",
            "type":"Services"
        }
    ],
    "sg:phone":"+1 414 423 9977",
    "sg:postcode":"53129",
    "sg:province":"WI",
    "wof:name":"United Securities Alliance",
    "wof:placetype":"venue"
},
  "geometry": {"coordinates":[-87.99606799999999,42.938123],"type":"Point"}
}