{
  "type": "Feature",
  "properties": {
    "iso:country":"US",
    "sg:address":"7425 W Birch St",
    "sg:city":"Webster",
    "sg:classifiers":[
        {
            "category":"Organizations",
            "subcategory":"Religious Organization",
            "type":"Services"
        }
    ],
    "sg:phone":"+1 715 866 7157",
    "sg:postcode":"54893",
    "sg:province":"WI",
    "sg:tags":[
        "church"
    ],
    "wof:name":"Burnett County Church-Christ",
    "wof:placetype":"venue"
},
  "geometry": {"coordinates":[-92.366123,45.875251],"type":"Point"}
}