{
  "type": "Feature",
  "properties": {
    "addr:full":"3720 Stonebrook Ct Brookfield WI 53005",
    "addr:housenumber":"3720",
    "addr:postcode":"53005",
    "addr:street":"Stonebrook Ct",
    "iso:country":"US",
    "sg:address":"3720 Stonebrook Ct",
    "sg:city":"Brookfield",
    "sg:classifiers":[
        {
            "category":"Shopping",
            "subcategory":"Musical Instruments",
            "type":"Retail Goods"
        }
    ],
    "sg:phone":"+1 262 783 6612",
    "sg:postcode":"53005",
    "sg:province":"WI",
    "sg:tags":[
        "music",
        "dealer"
    ],
    "wof:name":"Choralyre Co",
    "wof:placetype":"venue"
},
  "geometry": {"coordinates":[-88.11368400000001,43.085835],"type":"Point"}
}