{
  "type": "Feature",
  "properties": {
    "iso:country":"US",
    "sg:address":"201 1st St",
    "sg:city":"Racine",
    "sg:classifiers":[
        {
            "category":"Utilities",
            "subcategory":"Natural Gas",
            "type":"Services"
        }
    ],
    "sg:phone":"+1 262 552 7500",
    "sg:postcode":"53403",
    "sg:province":"WI",
    "sg:tags":[
        "company"
    ],
    "sg:website":"www.we-energies.com",
    "wof:name":"We Energies",
    "wof:placetype":"venue"
},
  "geometry": {"coordinates":[-87.809302,42.667808],"type":"Point"}
}