{
  "type": "Feature",
  "properties": {
    "iso:country":"US",
    "sg:address":"31314 Fresno Ave",
    "sg:city":"Tomah",
    "sg:classifiers":[
        {
            "category":"Manufacturing",
            "subcategory":"Tools & Machinery",
            "type":"Manufacturing & Wholesale Goods"
        }
    ],
    "sg:phone":"+1 608 372 9175",
    "sg:postcode":"54660",
    "sg:province":"WI",
    "sg:tags":[
        "woodworking",
        "mfg"
    ],
    "wof:name":"Larson Machine Shop",
    "wof:placetype":"venue"
},
  "geometry": {"coordinates":[-90.363916,43.987331],"type":"Point"}
}