{
  "type": "Feature",
  "properties": {
    "iso:country":"US",
    "sg:address":"1350 W College Ave",
    "sg:city":"Appleton",
    "sg:classifiers":[
        {
            "category":"Home & Garden",
            "subcategory":"Home Furnishings",
            "type":"Retail Goods"
        },
        {
            "category":"Shopping",
            "subcategory":"Crafts & Fabrics",
            "type":"Retail Goods"
        }
    ],
    "sg:phone":"+1 920 749 1957",
    "sg:postcode":"54914",
    "sg:province":"WI",
    "sg:tags":[
        "household",
        "sewing",
        "appliance",
        "quilting"
    ],
    "wof:name":"Piece By Pieces",
    "wof:placetype":"venue"
},
  "geometry": {"coordinates":[-88.42736499999999,44.261894],"type":"Point"}
}