{
  "type": "Feature",
  "properties": {
    "addr:full":"4821 Rosemary Cir Wisconsin Rapids WI 54494",
    "addr:housenumber":"4821",
    "addr:postcode":"54494",
    "addr:street":"Rosemary Cir",
    "iso:country":"US",
    "sg:address":"4821 Rosemary Cir",
    "sg:city":"Wisconsin Rapids",
    "sg:classifiers":[
        {
            "category":"Professional",
            "subcategory":"Management & Consulting",
            "type":"Services"
        }
    ],
    "sg:phone":"+1 715 423 3266",
    "sg:postcode":"54494",
    "sg:province":"WI",
    "sg:tags":[
        "business"
    ],
    "wof:name":"Stuart Smith Consulting LLC",
    "wof:placetype":"venue"
},
  "geometry": {"coordinates":[-89.792452,44.350745],"type":"Point"}
}