{
  "type": "Feature",
  "properties": {
    "addr:full":"8611 Brunswick Rd Minocqua WI 54548",
    "addr:housenumber":"8611",
    "addr:postcode":"54548",
    "addr:street":"Brunswick Rd",
    "iso:country":"US",
    "sg:address":"8611 Brunswick Rd",
    "sg:city":"Minocqua",
    "sg:classifiers":[
        {
            "category":"Building & Trades",
            "subcategory":"Equipment Rental",
            "type":"Services"
        }
    ],
    "sg:phone":"+1 715 358 2892",
    "sg:postcode":"54548",
    "sg:province":"WI",
    "wof:name":"Ncsm Rentals LLC",
    "wof:placetype":"venue"
},
  "geometry": {"coordinates":[-89.676203,45.882414],"type":"Point"}
}