{
  "type": "Feature",
  "properties": {
    "iso:country":"US",
    "sg:address":"7497 Farmers Grove Rd",
    "sg:city":"Monticello",
    "sg:classifiers":[
        {
            "category":"Farming",
            "subcategory":"Dairy Farm",
            "type":"Manufacturing & Wholesale Goods"
        }
    ],
    "sg:phone":"+1 608 527 5732",
    "sg:postcode":"53570",
    "sg:province":"WI",
    "wof:name":"Jeff Nimtz",
    "wof:placetype":"venue"
},
  "geometry": {"coordinates":[-89.732776,42.785568],"type":"Point"}
}