{
  "type": "Feature",
  "properties": {
    "iso:country":"US",
    "sg:address":"8976 Co Hwy D",
    "sg:city":"Antigo",
    "sg:classifiers":[
        {
            "category":"Real Estate",
            "subcategory":"Real Estate Operator",
            "type":"Services"
        }
    ],
    "sg:phone":"+1 715 623 2959",
    "sg:postcode":"54409",
    "sg:province":"WI",
    "sg:tags":[
        "building",
        "nonresidential"
    ],
    "wof:name":"Tls Freedom Properties LLC",
    "wof:placetype":"venue"
},
  "geometry": {"coordinates":[-89.09592499999999,45.044104],"type":"Point"}
}