{
  "type": "Feature",
  "properties": {
    "iso:country":"US",
    "sg:address":"25110 75th St",
    "sg:city":"Salem",
    "sg:classifiers":[
        {
            "category":"Building & Trades",
            "subcategory":"Landscaping Services",
            "type":"Services"
        }
    ],
    "sg:phone":"+1 262 945 9831",
    "sg:postcode":"53168",
    "sg:province":"WI",
    "sg:tags":[
        "designer",
        "landscape"
    ],
    "wof:name":"Foss & Assoc",
    "wof:placetype":"venue"
},
  "geometry": {"coordinates":[-88.112325,42.568361],"type":"Point"}
}