{
  "type": "Feature",
  "properties": {
    "iso:country":"US",
    "sg:address":"525 S Whelen Ave",
    "sg:city":"Medford",
    "sg:classifiers":[
        {
            "category":"Recreation",
            "type":"Entertainment"
        },
        {
            "category":"Organizations",
            "subcategory":"Community Association",
            "type":"Services"
        }
    ],
    "sg:phone":"+1 715 748 4050",
    "sg:postcode":"54451",
    "sg:province":"WI",
    "sg:tags":[
        "club",
        "membership"
    ],
    "wof:name":"Medford Curling Club Inc",
    "wof:placetype":"venue"
},
  "geometry": {"coordinates":[-90.344682,45.134218],"type":"Point"}
}