{
  "type": "Feature",
  "properties": {
    "addr:full":"1412 State Hwy 47 Woodruff WI 54568",
    "addr:housenumber":"1412",
    "addr:postcode":"54568",
    "addr:street":"State Hwy 47",
    "iso:country":"US",
    "sg:address":"1412 State Hwy 47",
    "sg:city":"Woodruff",
    "sg:classifiers":[
        {
            "category":"Government",
            "subcategory":"Post Office",
            "type":"Public Place"
        }
    ],
    "sg:phone":"+1 715 356 5577",
    "sg:postcode":"54568",
    "sg:province":"WI",
    "sg:tags":[
        "postal",
        "us"
    ],
    "wof:name":"US Post Office",
    "wof:placetype":"venue"
},
  "geometry": {"coordinates":[-89.691281,45.894922],"type":"Point"}
}