{
  "type": "Feature",
  "properties": {
    "iso:country":"US",
    "sg:address":"1216 E Brady St",
    "sg:city":"Milwaukee",
    "sg:classifiers":[
        {
            "category":"Bars & Pubs",
            "type":"Food & Drink"
        }
    ],
    "sg:phone":"+1 414 276 2677",
    "sg:postcode":"53202",
    "sg:province":"WI",
    "wof:name":"Up & Under Pub",
    "wof:placetype":"venue"
},
  "geometry": {"coordinates":[-87.896052,43.053023],"type":"Point"}
}