{
  "type": "Feature",
  "properties": {
    "iso:country":"US",
    "sg:address":"3380 N 35th St",
    "sg:city":"Milwaukee",
    "sg:classifiers":[
        {
            "category":"Autos & Motor Vehicles",
            "subcategory":"Fuel & Gas Station",
            "type":"Retail Goods"
        }
    ],
    "sg:phone":"+1 414 442 8372",
    "sg:postcode":"53216",
    "sg:province":"WI",
    "sg:tags":[
        "oil"
    ],
    "wof:name":"Skynet Mobil",
    "wof:placetype":"venue"
},
  "geometry": {"coordinates":[-87.957167,43.079337],"type":"Point"}
}