{
  "type": "Feature",
  "properties": {
    "iso:country":"US",
    "sg:address":"6301 Offshore Dr",
    "sg:city":"Madison",
    "sg:classifiers":[
        {
            "category":"Insurance",
            "subcategory":"Insurance Agent",
            "type":"Services"
        }
    ],
    "sg:phone":"+1 608 310 8675",
    "sg:postcode":"53705",
    "sg:province":"WI",
    "wof:name":"Haas & Haas Insurance Agency",
    "wof:placetype":"venue"
},
  "geometry": {"coordinates":[-89.490337,43.063292],"type":"Point"}
}