{
  "type": "Feature",
  "properties": {
    "addr:full":"1914 N 13th St Superior WI 54880",
    "addr:housenumber":"1914",
    "addr:postcode":"54880",
    "addr:street":"N 13Th St",
    "iso:country":"US",
    "sg:address":"1914 N 13th St",
    "sg:city":"Superior",
    "sg:classifiers":[
        {
            "category":"Home & Garden",
            "subcategory":"Building Materials",
            "type":"Retail Goods"
        }
    ],
    "sg:phone":"+1 715 392 2238",
    "sg:postcode":"54880",
    "sg:province":"WI",
    "sg:tags":[
        "lumber"
    ],
    "wof:name":"H & H Lumber Co Inc",
    "wof:placetype":"venue"
},
  "geometry": {"coordinates":[-92.10678799999999,46.723043],"type":"Point"}
}