{
  "type": "Feature",
  "properties": {
    "iso:country":"US",
    "sg:address":"1418 S Layton Blvd",
    "sg:city":"Milwaukee",
    "sg:classifiers":[
        {
            "category":"Education",
            "subcategory":"School",
            "type":"Public Place"
        }
    ],
    "sg:phone":"+1 414 647 8035",
    "sg:postcode":"53215",
    "sg:province":"WI",
    "wof:name":"Hmong American Peace Academy",
    "wof:placetype":"venue"
},
  "geometry": {"coordinates":[-87.947734,43.016177],"type":"Point"}
}