{
  "type": "Feature",
  "properties": {
    "iso:country":"US",
    "sg:address":"4515 Rivord Rd",
    "sg:city":"Superior",
    "sg:classifiers":[
        {
            "category":"Retail",
            "subcategory":"Auto Repair",
            "type":"Services"
        }
    ],
    "sg:phone":"+1 715 399 8128",
    "sg:postcode":"54880",
    "sg:province":"WI",
    "sg:tags":[
        "repairing",
        "automobile"
    ],
    "wof:name":"B J's Auto Body LLP",
    "wof:placetype":"venue"
},
  "geometry": {"coordinates":[-92.05206,46.600329],"type":"Point"}
}