{
  "type": "Feature",
  "properties": {
    "addr:full":"410 S Washington St Cuba City WI 53807",
    "addr:housenumber":"410",
    "addr:postcode":"53807",
    "addr:street":"S Washington St",
    "iso:country":"US",
    "sg:address":"410 S Washington St",
    "sg:city":"Cuba City",
    "sg:classifiers":[
        {
            "category":"Building & Trades",
            "subcategory":"Construction",
            "type":"Services"
        }
    ],
    "sg:phone":"+1 608 744 3749",
    "sg:postcode":"53807",
    "sg:province":"WI",
    "sg:tags":[
        "contractor"
    ],
    "wof:name":"Clendenen Bros Roofg & Siding",
    "wof:placetype":"venue"
},
  "geometry": {"coordinates":[-90.429605,42.603402],"type":"Point"}
}