{
  "type": "Feature",
  "properties": {
    "iso:country":"US",
    "sg:address":"1140 S 30th St",
    "sg:city":"Manitowoc",
    "sg:classifiers":[
        {
            "category":"Food & Beverages",
            "subcategory":"Groceries & Convenience Stores",
            "type":"Retail Goods"
        }
    ],
    "sg:phone":"+1 920 683 6840",
    "sg:postcode":"54220",
    "sg:province":"WI",
    "wof:name":"Supersaver",
    "wof:placetype":"venue"
},
  "geometry": {"coordinates":[-87.685339,44.087596],"type":"Point"}
}