{
  "type": "Feature",
  "properties": {
    "iso:country":"US",
    "sg:address":"95 W Main St",
    "sg:city":"Platteville",
    "sg:classifiers":[
        {
            "category":"Real Estate",
            "subcategory":"Real Estate Services",
            "type":"Services"
        }
    ],
    "sg:phone":"+1 608 348 5700",
    "sg:postcode":"53818",
    "sg:province":"WI",
    "sg:tags":[
        "abstract",
        "title"
    ],
    "wof:name":"Tri County Title Services",
    "wof:placetype":"venue"
},
  "geometry": {"coordinates":[-90.47899200000001,42.734168],"type":"Point"}
}