{
  "type": "Feature",
  "properties": {
    "iso:country":"US",
    "sg:address":"12766 W Peninsula Rd",
    "sg:city":"Hayward",
    "sg:classifiers":[
        {
            "category":"Organizations",
            "subcategory":"Religious Organization",
            "type":"Services"
        }
    ],
    "sg:phone":"+1 715 634 5689",
    "sg:postcode":"54843",
    "sg:province":"WI",
    "sg:tags":[
        "church"
    ],
    "wof:name":"Church Of Christ",
    "wof:placetype":"venue"
},
  "geometry": {"coordinates":[-91.339778,46.015471],"type":"Point"}
}