{
  "type": "Feature",
  "properties": {
    "iso:country":"US",
    "sg:address":"1408 Country Club Ln",
    "sg:city":"Watertown",
    "sg:classifiers":[
        {
            "category":"Professional",
            "subcategory":"Management & Consulting",
            "type":"Services"
        }
    ],
    "sg:phone":"+1 920 261 7243",
    "sg:postcode":"53098",
    "sg:province":"WI",
    "sg:tags":[
        "retail",
        "direct",
        "sales"
    ],
    "wof:name":"Healthy Alternatives LLC",
    "wof:placetype":"venue"
},
  "geometry": {"coordinates":[-88.726206,43.229621],"type":"Point"}
}