{
  "type": "Feature",
  "properties": {
    "addr:full":"18326 W Co Rd B Brodhead WI 53520",
    "addr:housenumber":"18326",
    "addr:postcode":"53520",
    "addr:street":"W Co Rd B",
    "iso:country":"US",
    "sg:address":"18326 W Co Rd B",
    "sg:city":"Brodhead",
    "sg:phone":"+1 608 897 4500",
    "sg:postcode":"53520",
    "sg:province":"WI",
    "sg:tags":[
        "farm",
        "corn",
        "wheat"
    ],
    "wof:name":"Bettenhausen Farms Inc",
    "wof:placetype":"venue"
},
  "geometry": {"coordinates":[-89.362792,42.686675],"type":"Point"}
}