{
  "type": "Feature",
  "properties": {
    "iso:country":"US",
    "sg:address":"885 Arthur Dr",
    "sg:city":"Milton",
    "sg:classifiers":[
        {
            "category":"Real Estate",
            "subcategory":"Real Estate Operator",
            "type":"Services"
        }
    ],
    "sg:phone":"+1 608 868 2255",
    "sg:postcode":"53563",
    "sg:province":"WI",
    "sg:tags":[
        "apartment"
    ],
    "wof:name":"Meadow Ridge Apartments",
    "wof:placetype":"venue"
},
  "geometry": {"coordinates":[-88.938271,42.76881],"type":"Point"}
}