{
  "type": "Feature",
  "properties": {
    "iso:country":"US",
    "sg:address":"6263 County Line Blvd",
    "sg:city":"Burlington",
    "sg:classifiers":[
        {
            "category":"Building & Trades",
            "subcategory":"Electrical",
            "type":"Services"
        }
    ],
    "sg:phone":"+1 262 763 9388",
    "sg:postcode":"53105",
    "sg:province":"WI",
    "sg:tags":[
        "electric",
        "contractor"
    ],
    "wof:name":"KINK Electric",
    "wof:placetype":"venue"
},
  "geometry": {"coordinates":[-88.307208,42.717687],"type":"Point"}
}