{
  "type": "Feature",
  "properties": {
    "iso:country":"US",
    "sg:address":"4430 N 150th St",
    "sg:city":"Brookfield",
    "sg:classifiers":[
        {
            "category":"Real Estate",
            "subcategory":"Real Estate Agent",
            "type":"Services"
        }
    ],
    "sg:phone":"+1 262 783 4970",
    "sg:postcode":"53005",
    "sg:province":"WI",
    "wof:name":"ERI Properties",
    "wof:placetype":"venue"
},
  "geometry": {"coordinates":[-88.099819,43.099811],"type":"Point"}
}