{
  "type": "Feature",
  "properties": {
    "addr:full":"7004 Center Ave Medford WI 54451",
    "addr:housenumber":"7004",
    "addr:postcode":"54451",
    "addr:street":"Center Ave",
    "iso:country":"US",
    "sg:address":"7004 Center Ave",
    "sg:city":"Medford",
    "sg:classifiers":[
        {
            "category":"Organizations",
            "subcategory":"Non-profit Organization",
            "type":"Services"
        }
    ],
    "sg:phone":"+1 715 748 9246",
    "sg:postcode":"54451",
    "sg:province":"WI",
    "sg:tags":[
        "alternative",
        "abortion"
    ],
    "wof:name":"Wisconsin Right To Life",
    "wof:placetype":"venue"
},
  "geometry": {"coordinates":[-90.40545,45.162819],"type":"Point"}
}