{
  "type": "Feature",
  "properties": {
    "iso:country":"US",
    "sg:address":"4954 Sherman Rd",
    "sg:city":"Slinger",
    "sg:classifiers":[
        {
            "category":"Building & Trades",
            "subcategory":"Construction",
            "type":"Services"
        }
    ],
    "sg:phone":"+1 262 644 5662",
    "sg:postcode":"53086",
    "sg:province":"WI",
    "sg:tags":[
        "carpenter"
    ],
    "wof:name":"R & M Carpenter Contr Inc",
    "wof:placetype":"venue"
},
  "geometry": {"coordinates":[-88.283004,43.310303],"type":"Point"}
}