{
  "type": "Feature",
  "properties": {
    "iso:country":"US",
    "sg:address":"5574 Star Branch Rd",
    "sg:city":"Pardeeville",
    "sg:classifiers":[
        {
            "category":"Building & Trades",
            "subcategory":"Construction",
            "type":"Services"
        }
    ],
    "sg:phone":"+1 608 742 9307",
    "sg:postcode":"53954",
    "sg:province":"WI",
    "sg:tags":[
        "hanging",
        "contractor"
    ],
    "wof:name":"Big Sky Painting LLC",
    "wof:placetype":"venue"
},
  "geometry": {"coordinates":[-89.391716,43.478122],"type":"Point"}
}