{
  "type": "Feature",
  "properties": {
    "addr:full":"2310 W Creedy Rd Beloit WI 53511",
    "addr:housenumber":"2310",
    "addr:postcode":"53511",
    "addr:street":"W Creedy Rd",
    "iso:country":"US",
    "sg:address":"2310 W Creedy Rd",
    "sg:city":"Beloit",
    "sg:classifiers":[
        {
            "category":"Health Services",
            "subcategory":"Hospital",
            "type":"Services"
        }
    ],
    "sg:phone":"+1 815 601 8380",
    "sg:postcode":"53511",
    "sg:province":"WI",
    "sg:tags":[
        "sleep",
        "treatment",
        "disorders-information"
    ],
    "wof:name":"Profusion Solution",
    "wof:placetype":"venue"
},
  "geometry": {"coordinates":[-89.065664,42.56189],"type":"Point"}
}