{
  "type": "Feature",
  "properties": {
    "iso:country":"US",
    "sg:address":"603 Wisconsin St",
    "sg:city":"Merrill",
    "sg:classifiers":[
        {
            "category":"Retail",
            "subcategory":"Laundry & Dry Cleaning",
            "type":"Services"
        }
    ],
    "sg:phone":"+1 715 536 2793",
    "sg:postcode":"54452",
    "sg:province":"WI",
    "wof:name":"Meuniers Carpet & Uphl Clg",
    "wof:placetype":"venue"
},
  "geometry": {"coordinates":[-89.713555,45.18525],"type":"Point"}
}