{
  "type": "Feature",
  "properties": {
    "iso:country":"US",
    "sg:address":"463 E Mills St",
    "sg:city":"Cadott",
    "sg:classifiers":[
        {
            "category":"Education",
            "subcategory":"School",
            "type":"Public Place"
        }
    ],
    "sg:phone":"+1 715 289 4213",
    "sg:postcode":"54727",
    "sg:province":"WI",
    "sg:website":"www.cadott.k12.wi.us",
    "wof:name":"Cadott Elementary School",
    "wof:placetype":"venue"
},
  "geometry": {"coordinates":[-91.146158,44.951748],"type":"Point"}
}