{
  "type": "Feature",
  "properties": {
    "iso:country":"US",
    "sg:address":"235 S Dann St",
    "sg:city":"Whitewater",
    "sg:classifiers":[
        {
            "category":"Building & Trades",
            "subcategory":"Electrical",
            "type":"Services"
        }
    ],
    "sg:phone":"+1 262 473 3944",
    "sg:postcode":"53190",
    "sg:province":"WI",
    "sg:tags":[
        "electric",
        "contractor"
    ],
    "wof:name":"Sta-Lite Corp",
    "wof:placetype":"venue"
},
  "geometry": {"coordinates":[-88.722831,42.832125],"type":"Point"}
}