{
  "type": "Feature",
  "properties": {
    "iso:country":"US",
    "sg:address":"2158 US Hwy 63",
    "sg:city":"Deer Park",
    "sg:classifiers":[
        {
            "category":"Food & Beverages",
            "subcategory":"Bakery",
            "type":"Retail Goods"
        }
    ],
    "sg:phone":"+1 715 263 3431",
    "sg:postcode":"54007",
    "sg:province":"WI",
    "sg:tags":[
        "baker"
    ],
    "wof:name":"Cake Creators & Debbie",
    "wof:placetype":"venue"
},
  "geometry": {"coordinates":[-92.28396499999999,45.174499],"type":"Point"}
}