{
  "type": "Feature",
  "properties": {
    "iso:country":"US",
    "sg:address":"340 13th St",
    "sg:city":"Hudson",
    "sg:classifiers":[
        {
            "category":"Education",
            "subcategory":"School",
            "type":"Public Place"
        }
    ],
    "sg:phone":"+1 715 386 4237",
    "sg:postcode":"54016",
    "sg:province":"WI",
    "sg:website":"www.hudson.k12.wi.us",
    "wof:name":"E P Rock Elementary School",
    "wof:placetype":"venue"
},
  "geometry": {"coordinates":[-92.741281,44.967077],"type":"Point"}
}