{
  "type": "Feature",
  "properties": {
    "iso:country":"US",
    "sg:address":"614 Broad St",
    "sg:city":"Beloit",
    "sg:classifiers":[
        {
            "category":"Bars & Pubs",
            "type":"Food & Drink"
        }
    ],
    "sg:phone":"+1 608 365 2745",
    "sg:postcode":"53511",
    "sg:province":"IL",
    "sg:tags":[
        "drinking"
    ],
    "wof:name":"Outt Back",
    "wof:placetype":"venue"
},
  "geometry": {"coordinates":[-89.030695,42.49858],"type":"Point"}
}