{
  "type": "Feature",
  "properties": {
    "addr:full":"650 9th Ave Clayton WI 54004",
    "addr:housenumber":"650",
    "addr:postcode":"54004",
    "addr:street":"9Th Ave",
    "iso:country":"US",
    "sg:address":"650 9th Ave",
    "sg:city":"Clayton",
    "sg:classifiers":[
        {
            "category":"Government",
            "subcategory":"Office",
            "type":"Public Place"
        }
    ],
    "sg:phone":"+1 715 357 3919",
    "sg:postcode":"54004",
    "sg:province":"WI",
    "sg:tags":[
        "village"
    ],
    "wof:name":"Arland Town Shop",
    "wof:placetype":"venue"
},
  "geometry": {"coordinates":[-92.02127299999999,45.338322],"type":"Point"}
}