{
  "type": "Feature",
  "properties": {
    "addr:full":"924 4th Ave Antigo WI 54409",
    "addr:housenumber":"924",
    "addr:postcode":"54409",
    "addr:street":"4Th Ave",
    "iso:country":"US",
    "sg:address":"924 4th Ave",
    "sg:city":"Antigo",
    "sg:classifiers":[
        {
            "category":"Bars & Pubs",
            "type":"Food & Drink"
        }
    ],
    "sg:phone":"+1 715 627 0103",
    "sg:postcode":"54409",
    "sg:province":"WI",
    "sg:tags":[
        "drinking"
    ],
    "wof:name":"Head Inn",
    "wof:placetype":"venue"
},
  "geometry": {"coordinates":[-89.15731100000001,45.142084],"type":"Point"}
}