{
  "type": "Feature",
  "properties": {
    "iso:country":"US",
    "sg:address":"821 W College Ave",
    "sg:city":"Waukesha",
    "sg:classifiers":[
        {
            "category":"Wholesale",
            "subcategory":"Hardware",
            "type":"Manufacturing & Wholesale Goods"
        }
    ],
    "sg:phone":"+1 262 521 1047",
    "sg:postcode":"53186",
    "sg:province":"WI",
    "sg:tags":[
        "fastener"
    ],
    "wof:name":"Fastenal Co",
    "wof:placetype":"venue"
},
  "geometry": {"coordinates":[-88.247474,43.002714],"type":"Point"}
}