{
  "type": "Feature",
  "properties": {
    "iso:country":"US",
    "sg:address":"2222 London Rd",
    "sg:city":"Eau Claire",
    "sg:classifiers":[
        {
            "category":"Retail",
            "subcategory":"Funeral Services",
            "type":"Services"
        }
    ],
    "sg:phone":"+1 715 832 1141",
    "sg:postcode":"54701",
    "sg:province":"WI",
    "wof:name":"Eau Claire Mem Crematory Svc",
    "wof:placetype":"venue"
},
  "geometry": {"coordinates":[-91.463103,44.796015],"type":"Point"}
}