{
  "type": "Feature",
  "properties": {
    "addr:full":"1501 Meadowbreeze Cir Neenah WI 54956",
    "addr:housenumber":"1501",
    "addr:postcode":"54956",
    "addr:street":"Meadowbreeze Cir",
    "iso:country":"US",
    "sg:address":"1501 Meadowbreeze Cir",
    "sg:city":"Neenah",
    "sg:classifiers":[
        {
            "category":"Manufacturing",
            "subcategory":"Aerospace",
            "type":"Manufacturing & Wholesale Goods"
        }
    ],
    "sg:phone":"+1 920 720 7094",
    "sg:postcode":"54956",
    "sg:province":"WI",
    "sg:tags":[
        "modification",
        "aircraft",
        "engineering"
    ],
    "wof:name":"Thomas A Knott Pe",
    "wof:placetype":"venue"
},
  "geometry": {"coordinates":[-88.50308,44.152259],"type":"Point"}
}