{
  "type": "Feature",
  "properties": {
    "iso:country":"US",
    "sg:address":"2966 S Herman St",
    "sg:city":"Milwaukee",
    "sg:classifiers":[
        {
            "category":"Arts & Performance",
            "subcategory":"Theater",
            "type":"Entertainment"
        }
    ],
    "sg:phone":"+1 414 744 0056",
    "sg:postcode":"53207",
    "sg:province":"WI",
    "sg:tags":[
        "group"
    ],
    "wof:name":"Julie Sobanski",
    "wof:placetype":"venue"
},
  "geometry": {"coordinates":[-87.895517,42.99017],"type":"Point"}
}