{
  "type": "Feature",
  "properties": {
    "iso:country":"US",
    "sg:address":"635 S 66th St",
    "sg:city":"Milwaukee",
    "sg:classifiers":[
        {
            "category":"Professional",
            "subcategory":"Management & Consulting",
            "type":"Services"
        }
    ],
    "sg:phone":"+1 414 475 6998",
    "sg:postcode":"53214",
    "sg:province":"WI",
    "wof:name":"Glroggecom",
    "wof:placetype":"venue"
},
  "geometry": {"coordinates":[-87.99502,43.025089],"type":"Point"}
}