{
  "type": "Feature",
  "properties": {
    "iso:country":"US",
    "sg:address":"820 Tower Ave",
    "sg:city":"Superior",
    "sg:classifiers":[
        {
            "category":"Food & Beverages",
            "subcategory":"Liquor & Beverages",
            "type":"Retail Goods"
        },
        {
            "category":"Bars & Pubs",
            "type":"Food & Drink"
        }
    ],
    "sg:phone":"+1 715 392 5373",
    "sg:postcode":"54880",
    "sg:province":"WI",
    "sg:tags":[
        "alcoholic"
    ],
    "wof:name":"Bev's Jook Joint",
    "wof:placetype":"venue"
},
  "geometry": {"coordinates":[-92.103803,46.727968],"type":"Point"}
}