{
  "type": "Feature",
  "properties": {
    "iso:country":"US",
    "sg:address":"2645 Shore Ridge Ct",
    "sg:city":"Green Bay",
    "sg:classifiers":[
        {
            "category":"Building & Trades",
            "subcategory":"Landscaping Services",
            "type":"Services"
        }
    ],
    "sg:phone":"+1 920 468 9577",
    "sg:postcode":"54311",
    "sg:province":"WI",
    "wof:name":"Wetli Landscpg & Lawn Car",
    "wof:placetype":"venue"
},
  "geometry": {"coordinates":[-87.917913,44.540444],"type":"Point"}
}