{
  "type": "Feature",
  "properties": {
    "iso:country":"US",
    "sg:address":"925 W Maple St",
    "sg:city":"Lancaster",
    "sg:classifiers":[
        {
            "category":"Education",
            "subcategory":"School",
            "type":"Public Place"
        }
    ],
    "sg:phone":"+1 608 723 2175",
    "sg:postcode":"53813",
    "sg:province":"WI",
    "wof:name":"Lancaster Community School Dst",
    "wof:placetype":"venue"
},
  "geometry": {"coordinates":[-90.720183,42.848008],"type":"Point"}
}