{
  "type": "Feature",
  "properties": {
    "iso:country":"US",
    "sg:address":"2643 Co Rd B",
    "sg:city":"Hancock",
    "sg:classifiers":[
        {
            "category":"Building & Trades",
            "subcategory":"Construction",
            "type":"Services"
        }
    ],
    "sg:phone":"+1 715 228 5447",
    "sg:postcode":"54943",
    "sg:province":"WI",
    "sg:tags":[
        "excavating",
        "contractor"
    ],
    "wof:name":"G & D Trucking & Excavating",
    "wof:placetype":"venue"
},
  "geometry": {"coordinates":[-89.418165,44.07914],"type":"Point"}
}