{
  "type": "Feature",
  "properties": {
    "iso:country":"US",
    "sg:address":"8115 Hillcrest Dr",
    "sg:city":"Wauwatosa",
    "sg:classifiers":[
        {
            "category":"Professional",
            "subcategory":"Art Services",
            "type":"Services"
        }
    ],
    "sg:phone":"+1 414 445 6592",
    "sg:postcode":"53213",
    "sg:province":"WI",
    "sg:tags":[
        "photographer"
    ],
    "wof:name":"Wolfe Photography Inc",
    "wof:placetype":"venue"
},
  "geometry": {"coordinates":[-88.016041,43.055006],"type":"Point"}
}