{
  "type": "Feature",
  "properties": {
    "iso:country":"US",
    "sg:address":"721 Jefferson St",
    "sg:city":"Sturgeon Bay",
    "sg:classifiers":[
        {
            "category":"Home & Garden",
            "subcategory":"Furniture",
            "type":"Retail Goods"
        }
    ],
    "sg:phone":"+1 920 743 9595",
    "sg:postcode":"54235",
    "sg:province":"WI",
    "sg:tags":[
        "house",
        "furnishing"
    ],
    "wof:name":"Revisions",
    "wof:placetype":"venue"
},
  "geometry": {"coordinates":[-87.372508,44.839463],"type":"Point"}
}