{
  "type": "Feature",
  "properties": {
    "addr:full":"3214 N 105th St Milwaukee WI 53222",
    "addr:housenumber":"3214",
    "addr:postcode":"53222",
    "addr:street":"N 105Th St",
    "iso:country":"US",
    "sg:address":"3214 N 105th St",
    "sg:city":"Milwaukee",
    "sg:classifiers":[
        {
            "category":"Professional",
            "subcategory":"Art Services",
            "type":"Services"
        }
    ],
    "sg:phone":"+1 414 259 0005",
    "sg:postcode":"53222",
    "sg:province":"WI",
    "sg:tags":[
        "commercial",
        "design"
    ],
    "wof:name":"Design Plus Graphics",
    "wof:placetype":"venue"
},
  "geometry": {"coordinates":[-88.044211,43.078233],"type":"Point"}
}