{
  "type": "Feature",
  "properties": {
    "iso:country":"US",
    "sg:address":"3595 Bennett Pl",
    "sg:city":"Warrens",
    "sg:classifiers":[
        {
            "category":"Wholesale",
            "subcategory":"Fruits & Vegetables",
            "type":"Manufacturing & Wholesale Goods"
        }
    ],
    "sg:phone":"+1 608 378 4233",
    "sg:postcode":"54666",
    "sg:province":"WI",
    "sg:tags":[
        "shipper"
    ],
    "wof:name":"Northland Cranberries Inc",
    "wof:placetype":"venue"
},
  "geometry": {"coordinates":[-90.377582,44.195661],"type":"Point"}
}