{
  "type": "Feature",
  "properties": {
    "iso:country":"US",
    "sg:address":"810 W Main St",
    "sg:city":"Waupun",
    "sg:classifiers":[
        {
            "category":"Home & Garden",
            "subcategory":"Building Materials",
            "type":"Retail Goods"
        }
    ],
    "sg:phone":"+1 920 324 3200",
    "sg:postcode":"53963",
    "sg:province":"WI",
    "sg:tags":[
        "lumber"
    ],
    "wof:name":"Waupun Lumber",
    "wof:placetype":"venue"
},
  "geometry": {"coordinates":[-88.75013,43.633172],"type":"Point"}
}