{
  "type": "Feature",
  "properties": {
    "addr:full":"2491 Co Hwy J Chippewa Falls WI 54729",
    "addr:housenumber":"2491",
    "addr:postcode":"54729",
    "addr:street":"Co Hwy J Chippewa",
    "iso:country":"US",
    "sg:address":"2491 Co Hwy J",
    "sg:city":"Chippewa Falls",
    "sg:classifiers":[
        {
            "category":"Banks & Credit Unions",
            "subcategory":"Bank",
            "type":"Services"
        }
    ],
    "sg:phone":"+1 715 720 3983",
    "sg:postcode":"54729",
    "sg:province":"WI",
    "sg:tags":[
        "personal",
        "institution"
    ],
    "wof:name":"Froehlich Financial Svcs LLC",
    "wof:placetype":"venue"
},
  "geometry": {"coordinates":[-91.417906,44.896812],"type":"Point"}
}