{
  "type": "Feature",
  "properties": {
    "iso:country":"US",
    "sg:address":"2837 Main St",
    "sg:city":"East Troy",
    "sg:classifiers":[
        {
            "category":"Building & Trades",
            "subcategory":"Construction",
            "type":"Services"
        },
        {
            "category":"Wholesale",
            "subcategory":"Metals & Minerals",
            "type":"Manufacturing & Wholesale Goods"
        }
    ],
    "sg:phone":"+1 262 786 5559",
    "sg:postcode":"53120",
    "sg:province":"WI",
    "sg:tags":[
        "aluminum",
        "contractor"
    ],
    "wof:name":"New Berlin Aluminum Prod Inc",
    "wof:placetype":"venue"
},
  "geometry": {"coordinates":[-88.404841,42.785513],"type":"Point"}
}