{
  "type": "Feature",
  "properties": {
    "iso:country":"US",
    "sg:address":"501 E Broadway St",
    "sg:city":"Waukesha",
    "sg:classifiers":[
        {
            "category":"Professional",
            "subcategory":"Lawyer & Legal Services",
            "type":"Services"
        }
    ],
    "sg:phone":"+1 262 544 4046",
    "sg:postcode":"53186",
    "sg:province":"WI",
    "sg:tags":[
        "attorney"
    ],
    "wof:name":"Charles M Davies",
    "wof:placetype":"venue"
},
  "geometry": {"coordinates":[-88.220484,43.007332],"type":"Point"}
}