{
  "type": "Feature",
  "properties": {
    "addr:full":"4113 Co Rd Aa Fredonia WI 53021",
    "addr:housenumber":"4113",
    "addr:postcode":"53021",
    "addr:street":"Co Rd",
    "iso:country":"US",
    "sg:address":"4113 Co Rd Aa",
    "sg:city":"Fredonia",
    "sg:classifiers":[
        {
            "category":"Retail",
            "subcategory":"Portrait Studio",
            "type":"Services"
        }
    ],
    "sg:phone":"+1 262 692 3886",
    "sg:postcode":"53021",
    "sg:province":"WI",
    "sg:tags":[
        "photographer"
    ],
    "wof:name":"Jennifer's Photography",
    "wof:placetype":"venue"
},
  "geometry": {"coordinates":[-87.987264,43.476838],"type":"Point"}
}