{
  "type": "Feature",
  "properties": {
    "iso:country":"US",
    "sg:address":"516 Cass St",
    "sg:city":"La Crosse",
    "sg:classifiers":[
        {
            "category":"Personal",
            "subcategory":"Beauty Salon",
            "type":"Services"
        }
    ],
    "sg:phone":"+1 608 784 5577",
    "sg:postcode":"54601",
    "sg:province":"WI",
    "sg:tags":[
        "shop"
    ],
    "wof:name":"Looks Unlimited",
    "wof:placetype":"venue"
},
  "geometry": {"coordinates":[-91.24888,43.808646],"type":"Point"}
}