{
  "type": "Feature",
  "properties": {
    "iso:country":"US",
    "sg:address":"841 Riverfront Dr",
    "sg:city":"Sheboygan",
    "sg:classifiers":[
        {
            "category":"Banks & Credit Unions",
            "subcategory":"Investment Brokerage",
            "type":"Services"
        }
    ],
    "sg:phone":"+1 920 208 2287",
    "sg:postcode":"53081",
    "sg:province":"WI",
    "sg:tags":[
        "security"
    ],
    "wof:name":"Three Rvers Ctr For Ind Living",
    "wof:placetype":"venue"
},
  "geometry": {"coordinates":[-87.711321,43.74686],"type":"Point"}
}