{
  "type": "Feature",
  "properties": {
    "addr:full":"902 Belknap St Superior WI 54880",
    "addr:housenumber":"902",
    "addr:postcode":"54880",
    "addr:street":"Belknap St",
    "iso:country":"US",
    "sg:address":"902 Belknap St",
    "sg:city":"Superior",
    "sg:classifiers":[
        {
            "category":"Retail",
            "subcategory":"Laundry & Dry Cleaning",
            "type":"Services"
        }
    ],
    "sg:phone":"+1 715 394 4077",
    "sg:postcode":"54880",
    "sg:province":"WI",
    "sg:tags":[
        "garment",
        "agent"
    ],
    "wof:name":"Clothes Basket Dry Cleaners",
    "wof:placetype":"venue"
},
  "geometry": {"coordinates":[-92.091893,46.720543],"type":"Point"}
}