{
  "type": "Feature",
  "properties": {
    "iso:country":"US",
    "sg:address":"6130 W Donges Bay Rd",
    "sg:city":"Mequon",
    "sg:classifiers":[
        {
            "category":"Building & Trades",
            "subcategory":"Construction",
            "type":"Services"
        }
    ],
    "sg:phone":"+1 262 241 3258",
    "sg:postcode":"53092",
    "sg:province":"WI",
    "sg:tags":[
        "home",
        "improvement"
    ],
    "wof:name":"Mulligan & Assoc Inc",
    "wof:placetype":"venue"
},
  "geometry": {"coordinates":[-87.982608,43.207171],"type":"Point"}
}