{
  "type": "Feature",
  "properties": {
    "iso:country":"US",
    "sg:address":"1310 N 5th St",
    "sg:city":"Superior",
    "sg:classifiers":[
        {
            "category":"Taxi",
            "type":"Transportation"
        }
    ],
    "sg:phone":"+1 715 394 5555",
    "sg:postcode":"54880",
    "sg:province":"WI",
    "sg:tags":[
        "taxicab"
    ],
    "wof:name":"Badger Taxi Cab",
    "wof:placetype":"venue"
},
  "geometry": {"coordinates":[-92.09775,46.732465],"type":"Point"}
}