{
  "type": "Feature",
  "properties": {
    "addr:full":"2730 Pella Opening Rd Clintonville WI 54929",
    "addr:postcode":"2730;54929",
    "addr:street":"Opening Rd",
    "iso:country":"US",
    "sg:address":"2730 Pella Opening Rd",
    "sg:city":"Clintonville",
    "sg:classifiers":[
        {
            "category":"Organizations",
            "subcategory":"Religious Organization",
            "type":"Services"
        }
    ],
    "sg:phone":"+1 715 823 4459",
    "sg:postcode":"54929",
    "sg:province":"WI",
    "sg:tags":[
        "church"
    ],
    "wof:name":"St Peter's Pella Opening",
    "wof:placetype":"venue"
},
  "geometry": {"coordinates":[-88.741491,44.680877],"type":"Point"}
}