{
  "type": "Feature",
  "properties": {
    "iso:country":"US",
    "sg:address":"610 W Hadley St",
    "sg:city":"Milwaukee",
    "sg:classifiers":[
        {
            "category":"Organizations",
            "subcategory":"Religious Organization",
            "type":"Services"
        }
    ],
    "sg:phone":"+1 414 372 9166",
    "sg:postcode":"53212",
    "sg:province":"WI",
    "wof:name":"Elijah's House Of Peace",
    "wof:placetype":"venue"
},
  "geometry": {"coordinates":[-87.919711,43.069497],"type":"Point"}
}