{
  "type": "Feature",
  "properties": {
    "iso:country":"US",
    "sg:address":"5300 S 76th St",
    "sg:city":"Greendale",
    "sg:classifiers":[
        {
            "category":"Ice Cream",
            "type":"Food & Drink"
        }
    ],
    "sg:menulink":"http://www.allmenus.com/wi/greendale/192926-dairy-queen/menu/",
    "sg:phone":"+1 414 421 3162",
    "sg:postcode":"53129",
    "sg:province":"WI",
    "sg:tags":[
        "burger",
        "american"
    ],
    "wof:name":"Dairy Queen",
    "wof:placetype":"venue"
},
  "geometry": {"coordinates":[-88.00814699999999,42.948492],"type":"Point"}
}