{
  "type": "Feature",
  "properties": {
    "iso:country":"US",
    "sg:address":"1151 Valley Rd",
    "sg:city":"Appleton",
    "sg:classifiers":[
        {
            "category":"Insurance",
            "subcategory":"Insurance Agent",
            "type":"Services"
        }
    ],
    "sg:phone":"+1 920 733 7331",
    "sg:postcode":"54915",
    "sg:province":"WI",
    "sg:tags":[
        "life",
        "carrier"
    ],
    "wof:name":"Bob Walter Insurance Agcy LLC",
    "wof:placetype":"venue"
},
  "geometry": {"coordinates":[-88.42489999999999,44.237086],"type":"Point"}
}