{
  "type": "Feature",
  "properties": {
    "iso:country":"US",
    "sg:address":"205 N Main St",
    "sg:city":"Walworth",
    "sg:classifiers":[
        {
            "category":"Restaurant",
            "type":"Food & Drink"
        }
    ],
    "sg:phone":"+1 262 275 2071",
    "sg:postcode":"53184",
    "sg:province":"WI",
    "sg:tags":[
        "eating"
    ],
    "wof:name":"Sunrise Cafe",
    "wof:placetype":"venue"
},
  "geometry": {"coordinates":[-88.599681,42.53374],"type":"Point"}
}