{
  "type": "Feature",
  "properties": {
    "iso:country":"US",
    "sg:address":"6653 Cedar Dr",
    "sg:city":"Greenville",
    "sg:classifiers":[
        {
            "category":"Professional",
            "subcategory":"Business Services",
            "type":"Services"
        }
    ],
    "sg:phone":"+1 920 757 6760",
    "sg:postcode":"54942",
    "sg:province":"WI",
    "wof:name":"Business Process Science & Svc",
    "wof:placetype":"venue"
},
  "geometry": {"coordinates":[-88.52422199999999,44.295513],"type":"Point"}
}