{
  "type": "Feature",
  "properties": {
    "iso:country":"US",
    "sg:address":"1213 Gohres St",
    "sg:city":"La Crosse",
    "sg:classifiers":[
        {
            "category":"Shopping",
            "subcategory":"Used Merchandise",
            "type":"Retail Goods"
        }
    ],
    "sg:phone":"+1 608 782 8443",
    "sg:postcode":"54603",
    "sg:province":"WI",
    "sg:tags":[
        "business"
    ],
    "wof:name":"Caledonia Street Antique Mall",
    "wof:placetype":"venue"
},
  "geometry": {"coordinates":[-91.238477,43.849289],"type":"Point"}
}