{
  "type": "Feature",
  "properties": {
    "iso:country":"US",
    "sg:address":"4402 E Broadway",
    "sg:city":"Madison",
    "sg:classifiers":[
        {
            "category":"Travel",
            "subcategory":"Hotels & Motels",
            "type":"Entertainment"
        }
    ],
    "sg:phone":"+1 608 223 1800",
    "sg:postcode":"53716",
    "sg:province":"WI",
    "sg:tags":[
        "operation"
    ],
    "wof:name":"Ramada Limited-Canoga Park",
    "wof:placetype":"venue"
},
  "geometry": {"coordinates":[-89.309865,43.048156],"type":"Point"}
}