{
  "type": "Feature",
  "properties": {
    "addr:full":"11558 Kempton Rd Augusta WI 54722",
    "addr:housenumber":"11558",
    "addr:postcode":"54722",
    "addr:street":"Kempton Rd",
    "iso:country":"US",
    "sg:address":"11558 Kempton Rd",
    "sg:city":"Augusta",
    "sg:classifiers":[
        {
            "category":"Manufacturing",
            "subcategory":"Metals",
            "type":"Manufacturing & Wholesale Goods"
        }
    ],
    "sg:phone":"+1 715 286 2807",
    "sg:postcode":"54722",
    "sg:province":"WI",
    "sg:tags":[
        "fencing",
        "wire"
    ],
    "wof:name":"Eugene Vetterkind",
    "wof:placetype":"venue"
},
  "geometry": {"coordinates":[-91.033501,44.659792],"type":"Point"}
}