{
  "type": "Feature",
  "properties": {
    "addr:full":"523 State Hwy 82 Mauston WI 53948",
    "addr:housenumber":"523",
    "addr:postcode":"53948",
    "addr:street":"State Hwy 82",
    "iso:country":"US",
    "sg:address":"523 State Hwy 82",
    "sg:city":"Mauston",
    "sg:classifiers":[
        {
            "category":"Banks & Credit Unions",
            "subcategory":"Bank",
            "type":"Services"
        }
    ],
    "sg:phone":"+1 608 847 4500",
    "sg:postcode":"53948",
    "sg:province":"WI",
    "wof:name":"Acuity Bank",
    "wof:placetype":"venue"
},
  "geometry": {"coordinates":[-90.06696100000001,43.797658],"type":"Point"}
}