{
  "type": "Feature",
  "properties": {
    "iso:country":"US",
    "sg:address":"3777 S 108th St",
    "sg:city":"Milwaukee",
    "sg:classifiers":[
        {
            "category":"Banks & Credit Unions",
            "subcategory":"Bank",
            "type":"Services"
        }
    ],
    "sg:phone":"+1 414 546 1816",
    "sg:postcode":"53228",
    "sg:province":"WI",
    "sg:tags":[
        "loan"
    ],
    "wof:name":"Budgetline Cash Advance",
    "wof:placetype":"venue"
},
  "geometry": {"coordinates":[-88.047518,42.979087],"type":"Point"}
}