{
  "type": "Feature",
  "properties": {
    "iso:country":"US",
    "sg:address":"3400 S Business Dr",
    "sg:city":"Sheboygan",
    "sg:classifiers":[
        {
            "category":"Autos & Motor Vehicles",
            "subcategory":"Automobile Sales",
            "type":"Retail Goods"
        }
    ],
    "sg:phone":"+1 920 459 6840",
    "sg:postcode":"53081",
    "sg:province":"WI",
    "sg:tags":[
        "car",
        "used",
        "leasing",
        "passenger"
    ],
    "wof:name":"Sheboygan Cadillac",
    "wof:placetype":"venue"
},
  "geometry": {"coordinates":[-87.738264,43.718013],"type":"Point"}
}