{
  "type": "Feature",
  "properties": {
    "iso:country":"US",
    "sg:address":"6695 US Hwy 18",
    "sg:city":"Jefferson",
    "sg:classifiers":[
        {
            "category":"Building & Trades",
            "subcategory":"Landscaping Services",
            "type":"Services"
        }
    ],
    "sg:phone":"+1 920 674 2393",
    "sg:postcode":"53549",
    "sg:province":"WI",
    "sg:tags":[
        "sod",
        "sodding"
    ],
    "wof:name":"Long Sod Farms Inc",
    "wof:placetype":"venue"
},
  "geometry": {"coordinates":[-88.862326,43.00697],"type":"Point"}
}