{
  "type": "Feature",
  "properties": {
    "iso:country":"US",
    "sg:address":"5868 Kent Rd",
    "sg:city":"Bryant",
    "sg:phone":"+1 715 623 7386",
    "sg:postcode":"54418",
    "sg:province":"WI",
    "sg:tags":[
        "farm",
        "corn"
    ],
    "wof:name":"Calvin Hurlbert",
    "wof:placetype":"venue"
},
  "geometry": {"coordinates":[-88.91570400000001,45.255521],"type":"Point"}
}