{
  "type": "Feature",
  "properties": {
    "iso:country":"US",
    "sg:address":"2545 N Cramer St",
    "sg:city":"Milwaukee",
    "sg:classifiers":[
        {
            "category":"Professional",
            "subcategory":"Business Services",
            "type":"Services"
        }
    ],
    "sg:phone":"+1 414 332 3307",
    "sg:postcode":"53211",
    "sg:province":"WI",
    "wof:name":"B & B Services Co",
    "wof:placetype":"venue"
},
  "geometry": {"coordinates":[-87.886783,43.063732],"type":"Point"}
}