{
  "type": "Feature",
  "properties": {
    "iso:country":"US",
    "sg:address":"34900 Oak Knoll Rd",
    "sg:city":"Burlington",
    "sg:classifiers":[
        {
            "category":"Professional",
            "type":"Services"
        }
    ],
    "sg:phone":"+1 262 534 2675",
    "sg:postcode":"53105",
    "sg:province":"WI",
    "wof:name":"Marris Co",
    "wof:placetype":"venue"
},
  "geometry": {"coordinates":[-88.298421,42.728772],"type":"Point"}
}