{
  "type": "Feature",
  "properties": {
    "iso:country":"US",
    "sg:address":"3496 Co Rd H",
    "sg:city":"Lake Geneva",
    "sg:classifiers":[
        {
            "category":"Retail",
            "subcategory":"Auto Repair",
            "type":"Services"
        }
    ],
    "sg:phone":"+1 262 248 1973",
    "sg:postcode":"53147",
    "sg:province":"WI",
    "sg:tags":[
        "repairing",
        "automobile"
    ],
    "wof:name":"Badger Pump Svc",
    "wof:placetype":"venue"
},
  "geometry": {"coordinates":[-88.48693900000001,42.620599],"type":"Point"}
}