{
  "type": "Feature",
  "properties": {
    "iso:country":"US",
    "sg:address":"208 Wilson Ave",
    "sg:city":"Bayfield",
    "sg:classifiers":[
        {
            "category":"Manufacturing",
            "subcategory":"Food",
            "type":"Manufacturing & Wholesale Goods"
        }
    ],
    "sg:phone":"+1 715 779 3301",
    "sg:postcode":"54814",
    "sg:province":"WI",
    "sg:tags":[
        "seafood",
        "product",
        "fish",
        "prepared"
    ],
    "sg:website":"www.bodins.com",
    "wof:name":"Bodin Fisheries",
    "wof:placetype":"venue"
},
  "geometry": {"coordinates":[-90.816368,46.808404],"type":"Point"}
}