{
  "type": "Feature",
  "properties": {
    "addr:full":"905 Chicory Way Sun Prairie WI 53590",
    "addr:housenumber":"905",
    "addr:postcode":"53590",
    "addr:street":"Chicory Way",
    "iso:country":"US",
    "sg:address":"905 Chicory Way",
    "sg:city":"Sun Prairie",
    "sg:classifiers":[
        {
            "category":"Professional",
            "subcategory":"Accounting & Tax Preparation",
            "type":"Services"
        }
    ],
    "sg:phone":"+1 608 837 4143",
    "sg:postcode":"53590",
    "sg:province":"WI",
    "wof:name":"Money Matters",
    "wof:placetype":"venue"
},
  "geometry": {"coordinates":[-89.22713400000001,43.19275],"type":"Point"}
}