{
  "type": "Feature",
  "properties": {
    "iso:country":"US",
    "sg:address":"107 S Grove St",
    "sg:city":"Mt Horeb",
    "sg:classifiers":[
        {
            "category":"Social Services",
            "type":"Services"
        }
    ],
    "sg:phone":"+1 608 437 6902",
    "sg:postcode":"53572",
    "sg:province":"WI",
    "sg:tags":[
        "senior",
        "citizen"
    ],
    "wof:name":"Southwest Dane Senior Outreach",
    "wof:placetype":"venue"
},
  "geometry": {"coordinates":[-89.740324,43.008614],"type":"Point"}
}