{
  "type": "Feature",
  "properties": {
    "iso:country":"US",
    "sg:address":"13710 Oak St",
    "sg:city":"Argyle",
    "sg:classifiers":[
        {
            "category":"Farming",
            "subcategory":"Dairy Farm",
            "type":"Manufacturing & Wholesale Goods"
        }
    ],
    "sg:phone":"+1 608 543 3404",
    "sg:postcode":"53504",
    "sg:province":"WI",
    "wof:name":"Karl Stein",
    "wof:placetype":"venue"
},
  "geometry": {"coordinates":[-89.862128,42.695676],"type":"Point"}
}