{
  "type": "Feature",
  "properties": {
    "iso:country":"US",
    "sg:address":"23711 61st St",
    "sg:city":"Salem",
    "sg:classifiers":[
        {
            "category":"Professional",
            "type":"Services"
        }
    ],
    "sg:phone":"+1 262 843 2718",
    "sg:postcode":"53168",
    "sg:province":"WI",
    "wof:name":"Anthony Guzy",
    "wof:placetype":"venue"
},
  "geometry": {"coordinates":[-88.096632,42.581435],"type":"Point"}
}