{
  "type": "Feature",
  "properties": {
    "addr:full":"1004 Ontario Ave Sheboygan WI 53081",
    "addr:housenumber":"1004",
    "addr:postcode":"53081",
    "addr:street":"Ontario Ave",
    "iso:country":"US",
    "sg:address":"1004 Ontario Ave",
    "sg:city":"Sheboygan",
    "sg:classifiers":[
        {
            "category":"Autos & Motor Vehicles",
            "subcategory":"Auto Supplies",
            "type":"Retail Goods"
        }
    ],
    "sg:phone":"+1 920 459 2540",
    "sg:postcode":"53081",
    "sg:province":"WI",
    "sg:tags":[
        "automobile",
        "parts"
    ],
    "wof:name":"Menzer Supply Co",
    "wof:placetype":"venue"
},
  "geometry": {"coordinates":[-87.71789200000001,43.755342],"type":"Point"}
}