{
  "type": "Feature",
  "properties": {
    "addr:full":"950 Wilcox St Waupun WI 53963",
    "addr:housenumber":"950",
    "addr:postcode":"53963",
    "addr:street":"Wilcox St",
    "iso:country":"US",
    "sg:address":"950 Wilcox St",
    "sg:city":"Waupun",
    "sg:classifiers":[
        {
            "category":"Education",
            "subcategory":"School",
            "type":"Public Place"
        }
    ],
    "sg:phone":"+1 920 324 9341",
    "sg:postcode":"53963",
    "sg:province":"WI",
    "sg:tags":[
        "district"
    ],
    "wof:name":"School District of Waupun",
    "wof:placetype":"venue"
},
  "geometry": {"coordinates":[-88.71924300000001,43.630084],"type":"Point"}
}