{
  "type": "Feature",
  "properties": {
    "iso:country":"US",
    "sg:address":"76 E Johnson St",
    "sg:city":"Fond Du Lac",
    "sg:classifiers":[
        {
            "category":"Professional",
            "subcategory":"Business Services",
            "type":"Services"
        }
    ],
    "sg:phone":"+1 920 922 3546",
    "sg:postcode":"54935",
    "sg:province":"WI",
    "wof:name":"William Bump Jr",
    "wof:placetype":"venue"
},
  "geometry": {"coordinates":[-88.44419499999999,43.783471],"type":"Point"}
}