{
  "type": "Feature",
  "properties": {
    "iso:country":"US",
    "sg:address":"10 S 2nd St",
    "sg:city":"Black River Fls",
    "sg:classifiers":[
        {
            "category":"Real Estate",
            "subcategory":"Surveying",
            "type":"Services"
        }
    ],
    "sg:phone":"+1 715 284 2150",
    "sg:postcode":"54615",
    "sg:province":"WI",
    "sg:tags":[
        "surveyor"
    ],
    "wof:name":"Melichar Boundary Co",
    "wof:placetype":"venue"
},
  "geometry": {"coordinates":[-90.84966,44.295],"type":"Point"}
}