{
  "type": "Feature",
  "properties": {
    "iso:country":"US",
    "sg:address":"3420 Silver Creek Rd",
    "sg:city":"Manitowoc",
    "sg:classifiers":[
        {
            "category":"Building & Trades",
            "subcategory":"Construction",
            "type":"Services"
        }
    ],
    "sg:phone":"+1 920 682 2301",
    "sg:postcode":"54220",
    "sg:province":"WI",
    "sg:tags":[
        "house",
        "carpentry",
        "contractor"
    ],
    "wof:name":"Curt Johnson Remodeling",
    "wof:placetype":"venue"
},
  "geometry": {"coordinates":[-87.693945,44.052373],"type":"Point"}
}