{
  "type": "Feature",
  "properties": {
    "addr:full":"3857 US Hwy 12 Lyndon Station WI 53944",
    "addr:housenumber":"3857",
    "addr:postcode":"53944",
    "addr:street":"Us Hwy 12 Lyndon Station",
    "iso:country":"US",
    "sg:address":"3857 US Hwy 12",
    "sg:city":"Lyndon Station",
    "sg:classifiers":[
        {
            "category":"Wholesale",
            "subcategory":"Farm Supplies",
            "type":"Manufacturing & Wholesale Goods"
        }
    ],
    "sg:phone":"+1 608 339 2326",
    "sg:postcode":"53944",
    "sg:province":"WI",
    "sg:tags":[
        "feed"
    ],
    "wof:name":"Soy-Co",
    "wof:placetype":"venue"
},
  "geometry": {"coordinates":[-89.954869,43.715467],"type":"Point"}
}