{
  "type": "Feature",
  "properties": {
    "addr:full":"335 Saint Annes Pkwy Hudson WI 54016",
    "addr:housenumber":"335",
    "addr:postcode":"54016",
    "addr:street":"Saint Annes Pkwy",
    "iso:country":"US",
    "sg:address":"335 Saint Annes Pkwy",
    "sg:city":"Hudson",
    "sg:classifiers":[
        {
            "category":"Real Estate",
            "subcategory":"Real Estate Services",
            "type":"Services"
        },
        {
            "category":"Real Estate",
            "subcategory":"Real Estate Agent",
            "type":"Services"
        }
    ],
    "sg:phone":"+1 715 377 7680",
    "sg:postcode":"54016",
    "sg:province":"WI",
    "sg:tags":[
        "buyer",
        "broker"
    ],
    "wof:name":"Troy Realty",
    "wof:placetype":"venue"
},
  "geometry": {"coordinates":[-92.73584700000001,44.899586],"type":"Point"}
}