{
  "type": "Feature",
  "properties": {
    "iso:country":"US",
    "sg:address":"1110 W Heather Ln",
    "sg:city":"Milwaukee",
    "sg:classifiers":[
        {
            "category":"Shopping",
            "type":"Retail Goods"
        }
    ],
    "sg:phone":"+1 414 352 6594",
    "sg:postcode":"53217",
    "sg:province":"WI",
    "sg:tags":[
        "merchandise"
    ],
    "wof:name":"Amerimedica Inc",
    "wof:placetype":"venue"
},
  "geometry": {"coordinates":[-87.920498,43.173968],"type":"Point"}
}