{
  "type": "Feature",
  "properties": {
    "iso:country":"US",
    "sg:address":"2728 E Newton Ave",
    "sg:city":"Milwaukee",
    "sg:classifiers":[
        {
            "category":"Travel",
            "subcategory":"Campground",
            "type":"Entertainment"
        }
    ],
    "sg:phone":"+1 414 963 1862",
    "sg:postcode":"53211",
    "sg:province":"WI",
    "sg:tags":[
        "camp"
    ],
    "wof:name":"Akita Aquatics Association",
    "wof:placetype":"venue"
},
  "geometry": {"coordinates":[-87.876104,43.085115],"type":"Point"}
}