{
  "type": "Feature",
  "properties": {
    "addr:full":"2339 W Wisconsin Ave Appleton WI 54914",
    "addr:housenumber":"2339",
    "addr:postcode":"54914",
    "addr:street":"W Wisconsin Ave",
    "iso:country":"US",
    "sg:address":"2339 W Wisconsin Ave",
    "sg:city":"Appleton",
    "sg:classifiers":[
        {
            "category":"Education",
            "subcategory":"Special Training",
            "type":"Public Place"
        }
    ],
    "sg:phone":"+1 920 968 7799",
    "sg:postcode":"54914",
    "sg:province":"WI",
    "sg:tags":[
        "instruction",
        "driving"
    ],
    "wof:name":"Cornerstone Driving School",
    "wof:placetype":"venue"
},
  "geometry": {"coordinates":[-88.442921,44.273161],"type":"Point"}
}