{
  "type": "Feature",
  "properties": {
    "iso:country":"US",
    "sg:address":"222 Oak St",
    "sg:city":"Spooner",
    "sg:classifiers":[
        {
            "category":"Government",
            "subcategory":"Office",
            "type":"Public Place"
        }
    ],
    "sg:phone":"+1 715 635 4400",
    "sg:postcode":"54801",
    "sg:province":"WI",
    "sg:tags":[
        "county",
        "resource"
    ],
    "wof:name":"Washburn WIC Program",
    "wof:placetype":"venue"
},
  "geometry": {"coordinates":[-91.88993000000001,45.826185],"type":"Point"}
}