{
  "type": "Feature",
  "properties": {
    "iso:country":"US",
    "sg:address":"965 Co Hwy Ss",
    "sg:city":"Chetek",
    "sg:classifiers":[
        {
            "category":"Shopping",
            "subcategory":"Florist",
            "type":"Retail Goods"
        }
    ],
    "sg:phone":"+1 715 924 3127",
    "sg:postcode":"54728",
    "sg:province":"WI",
    "wof:name":"Northwest Growers",
    "wof:placetype":"venue"
},
  "geometry": {"coordinates":[-91.651349,45.317517],"type":"Point"}
}