{
  "type": "Feature",
  "properties": {
    "addr:full":"2916 Minnesota Ave Stevens Point WI 54481",
    "addr:housenumber":"2916",
    "addr:postcode":"54481",
    "addr:street":"Minnesota Ave",
    "iso:country":"US",
    "sg:address":"2916 Minnesota Ave",
    "sg:city":"Stevens Point",
    "sg:classifiers":[
        {
            "category":"Retail",
            "subcategory":"Auto Repair",
            "type":"Services"
        }
    ],
    "sg:phone":"+1 715 344 6707",
    "sg:postcode":"54481",
    "sg:province":"WI",
    "sg:tags":[
        "general"
    ],
    "wof:name":"D & D Auto Repair",
    "wof:placetype":"venue"
},
  "geometry": {"coordinates":[-89.55934000000001,44.508],"type":"Point"}
}