{
  "type": "Feature",
  "properties": {
    "iso:country":"US",
    "sg:address":"201 16th Ct",
    "sg:city":"Wautoma",
    "sg:classifiers":[
        {
            "category":"Government",
            "subcategory":"Office",
            "type":"Public Place"
        }
    ],
    "sg:phone":"+1 920 787 2116",
    "sg:postcode":"54982",
    "sg:province":"WI",
    "sg:tags":[
        "federal"
    ],
    "wof:name":"US Consolidated Farm Svc Agcy",
    "wof:placetype":"venue"
},
  "geometry": {"coordinates":[-89.30365500000001,44.076702],"type":"Point"}
}