{
  "type": "Feature",
  "properties": {
    "addr:full":"1630 Cliffview Dr Oshkosh WI 54901",
    "addr:housenumber":"1630",
    "addr:postcode":"54901",
    "addr:street":"Cliffview Dr",
    "iso:country":"US",
    "sg:address":"1630 Cliffview Dr",
    "sg:city":"Oshkosh",
    "sg:classifiers":[
        {
            "category":"Professional",
            "subcategory":"Management & Consulting",
            "type":"Services"
        }
    ],
    "sg:phone":"+1 920 426 9274",
    "sg:postcode":"54901",
    "sg:province":"WI",
    "sg:tags":[
        "business"
    ],
    "wof:name":"Networth Consulting",
    "wof:placetype":"venue"
},
  "geometry": {"coordinates":[-88.51749100000001,44.035947],"type":"Point"}
}