{
  "type": "Feature",
  "properties": {
    "iso:country":"US",
    "sg:address":"500 Elmberta St",
    "sg:city":"Mauston",
    "sg:classifiers":[
        {
            "category":"Personal",
            "subcategory":"Beauty Salon",
            "type":"Services"
        }
    ],
    "sg:phone":"+1 608 847 6777",
    "sg:postcode":"53948",
    "sg:province":"WI",
    "wof:name":"Mary Ellens Beauty Salon",
    "wof:placetype":"venue"
},
  "geometry": {"coordinates":[-90.08505700000001,43.789994],"type":"Point"}
}