{
  "type": "Feature",
  "properties": {
    "iso:country":"US",
    "sg:address":"6290 N Port Washington Rd",
    "sg:city":"Milwaukee",
    "sg:classifiers":[
        {
            "category":"Professional",
            "subcategory":"Lawyer & Legal Services",
            "type":"Services"
        }
    ],
    "sg:phone":"+1 414 831 7177",
    "sg:postcode":"53217",
    "sg:province":"WI",
    "sg:tags":[
        "attorney"
    ],
    "wof:name":"Jack E Keyes",
    "wof:placetype":"venue"
},
  "geometry": {"coordinates":[-87.912992,43.130775],"type":"Point"}
}