{
  "type": "Feature",
  "properties": {
    "iso:country":"US",
    "sg:address":"3210 W Southway Dr",
    "sg:city":"Franklin",
    "sg:classifiers":[
        {
            "category":"Manufacturing",
            "subcategory":"Glass & Minerals",
            "type":"Manufacturing & Wholesale Goods"
        }
    ],
    "sg:phone":"+1 414 761 3994",
    "sg:postcode":"53132",
    "sg:province":"WI",
    "wof:name":"David Braun Creative",
    "wof:placetype":"venue"
},
  "geometry": {"coordinates":[-87.954868,42.896982],"type":"Point"}
}