{
  "type": "Feature",
  "properties": {
    "iso:country":"US",
    "sg:address":"4832 Holtman Rd",
    "sg:city":"Stratford",
    "sg:classifiers":[
        {
            "category":"Retail",
            "subcategory":"Auto Repair",
            "type":"Services"
        }
    ],
    "sg:phone":"+1 715 687 2269",
    "sg:postcode":"54484",
    "sg:province":"WI",
    "sg:tags":[
        "body"
    ],
    "wof:name":"Bills Body & Paint",
    "wof:placetype":"venue"
},
  "geometry": {"coordinates":[-90.024548,44.858548],"type":"Point"}
}