{
  "type": "Feature",
  "properties": {
    "iso:country":"US",
    "sg:address":"4698 Elm Lawn Rd",
    "sg:city":"Oconto Falls",
    "sg:classifiers":[
        {
            "category":"Retail",
            "subcategory":"Animal Services",
            "type":"Services"
        }
    ],
    "sg:phone":"+1 920 846 2543",
    "sg:postcode":"54154",
    "sg:province":"WI",
    "sg:tags":[
        "pet",
        "boarding",
        "sitting"
    ],
    "wof:name":"K-9 Creations Country Resort",
    "wof:placetype":"venue"
},
  "geometry": {"coordinates":[-88.167706,44.841436],"type":"Point"}
}