{
  "type": "Feature",
  "properties": {
    "iso:country":"US",
    "sg:address":"603 Meadow Park Dr",
    "sg:city":"Clinton",
    "sg:classifiers":[
        {
            "category":"Food & Beverages",
            "subcategory":"Specialty",
            "type":"Retail Goods"
        }
    ],
    "sg:phone":"+1 608 676 4151",
    "sg:postcode":"53525",
    "sg:province":"WI",
    "wof:name":"Herbs For Health & Weight Ctrl",
    "wof:placetype":"venue"
},
  "geometry": {"coordinates":[-88.866415,42.563145],"type":"Point"}
}