{
  "type": "Feature",
  "properties": {
    "iso:country":"US",
    "sg:address":"3198 London Rd",
    "sg:city":"Eau Claire",
    "sg:classifiers":[
        {
            "category":"Sports & Exercise",
            "subcategory":"Gym",
            "type":"Entertainment"
        }
    ],
    "sg:phone":"+1 715 552 8783",
    "sg:postcode":"54701",
    "sg:province":"WI",
    "sg:tags":[
        "fitness",
        "physical",
        "facility"
    ],
    "wof:name":"Curves For Women",
    "wof:placetype":"venue"
},
  "geometry": {"coordinates":[-91.463244,44.788295],"type":"Point"}
}