{
  "type": "Feature",
  "properties": {
    "iso:country":"US",
    "sg:address":"2280 Co Rd C",
    "sg:city":"Bay City",
    "sg:phone":"+1 715 594 3858",
    "sg:postcode":"54723",
    "sg:province":"WI",
    "sg:tags":[
        "farm",
        "corn"
    ],
    "wof:name":"Jim Conway",
    "wof:placetype":"venue"
},
  "geometry": {"coordinates":[-92.48756899999999,44.626066],"type":"Point"}
}