{
  "type": "Feature",
  "properties": {
    "addr:full":"57 S Walworth Ave Williams Bay WI 53191",
    "addr:housenumber":"57",
    "addr:postcode":"53191",
    "addr:street":"S Walworth Ave",
    "iso:country":"US",
    "sg:address":"57 S Walworth Ave",
    "sg:city":"Williams Bay",
    "sg:classifiers":[
        {
            "category":"Freight",
            "type":"Transportation"
        }
    ],
    "sg:phone":"+1 262 245 1388",
    "sg:postcode":"53191",
    "sg:province":"WI",
    "sg:tags":[
        "dock"
    ],
    "wof:name":"Kirsch's Pier Slips",
    "wof:placetype":"venue"
},
  "geometry": {"coordinates":[-88.541073,42.572966],"type":"Point"}
}