{
  "type": "Feature",
  "properties": {
    "iso:country":"US",
    "sg:address":"2301 Church St",
    "sg:city":"Stevens Point",
    "sg:classifiers":[
        {
            "category":"Restaurant",
            "type":"Food & Drink"
        }
    ],
    "sg:phone":"+1 715 345 0578",
    "sg:postcode":"54481",
    "sg:province":"WI",
    "sg:tags":[
        "caterer"
    ],
    "wof:name":"Mobile Chef Catering",
    "wof:placetype":"venue"
},
  "geometry": {"coordinates":[-89.57478999999999,44.514753],"type":"Point"}
}