{
  "type": "Feature",
  "properties": {
    "iso:country":"US",
    "sg:address":"733 W Oklahoma Ave",
    "sg:city":"Milwaukee",
    "sg:classifiers":[
        {
            "category":"Bars & Pubs",
            "type":"Food & Drink"
        }
    ],
    "sg:phone":"+1 414 294 3899",
    "sg:postcode":"53215",
    "sg:province":"WI",
    "wof:name":"Fuzzy's",
    "wof:placetype":"venue"
},
  "geometry": {"coordinates":[-87.921169,42.988205],"type":"Point"}
}