{
  "type": "Feature",
  "properties": {
    "iso:country":"US",
    "sg:address":"568 26th Ave",
    "sg:city":"Cumberland",
    "sg:classifiers":[
        {
            "category":"Professional",
            "subcategory":"Accounting & Tax Preparation",
            "type":"Services"
        }
    ],
    "sg:phone":"+1 715 822 2083",
    "sg:postcode":"54829",
    "sg:province":"WI",
    "wof:name":"Thelma W Johnson",
    "wof:placetype":"venue"
},
  "geometry": {"coordinates":[-92.03779400000001,45.580861],"type":"Point"}
}