{
  "type": "Feature",
  "properties": {
    "iso:country":"US",
    "sg:address":"3807 Spring St",
    "sg:city":"Racine",
    "sg:classifiers":[
        {
            "category":"Health Services",
            "subcategory":"Doctor",
            "type":"Services"
        }
    ],
    "sg:phone":"+1 262 687 8288",
    "sg:postcode":"53405",
    "sg:province":"WI",
    "sg:tags":[
        "physician",
        "surgeon"
    ],
    "wof:name":"All Saints Asthma Program",
    "wof:placetype":"venue"
},
  "geometry": {"coordinates":[-87.825714,42.733599],"type":"Point"}
}