{
  "type": "Feature",
  "properties": {
    "iso:country":"US",
    "sg:address":"4252 Co Rd Dd",
    "sg:city":"Kaukauna",
    "sg:classifiers":[
        {
            "category":"Retail",
            "subcategory":"Auto Repair",
            "type":"Services"
        }
    ],
    "sg:phone":"+1 920 788 5538",
    "sg:postcode":"54130",
    "sg:province":"WI",
    "sg:tags":[
        "executive",
        "general"
    ],
    "wof:name":"Municipal Garage",
    "wof:placetype":"venue"
},
  "geometry": {"coordinates":[-88.181471,44.341361],"type":"Point"}
}