{
  "type": "Feature",
  "properties": {
    "iso:country":"US",
    "sg:address":"16522 Happy Hollow Dr",
    "sg:city":"Cazenovia",
    "sg:classifiers":[
        {
            "category":"Farming",
            "subcategory":"Dairy Farm",
            "type":"Manufacturing & Wholesale Goods"
        }
    ],
    "sg:phone":"+1 608 986 3935",
    "sg:postcode":"53924",
    "sg:province":"WI",
    "sg:tags":[
        "field",
        "crop"
    ],
    "wof:name":"Weeping Willow Farms",
    "wof:placetype":"venue"
},
  "geometry": {"coordinates":[-90.257908,43.46215],"type":"Point"}
}