{
  "type": "Feature",
  "properties": {
    "addr:full":"11963 Roberta Ln Marshfield WI 54449",
    "addr:housenumber":"11963",
    "addr:postcode":"54449",
    "addr:street":"Roberta Ln",
    "iso:country":"US",
    "sg:address":"11963 Roberta Ln",
    "sg:city":"Marshfield",
    "sg:classifiers":[
        {
            "category":"Building & Trades",
            "subcategory":"Electrical",
            "type":"Services"
        }
    ],
    "sg:phone":"+1 715 389 2880",
    "sg:postcode":"54449",
    "sg:province":"WI",
    "sg:tags":[
        "electric",
        "contractor"
    ],
    "wof:name":"Neuman Electric Inc",
    "wof:placetype":"venue"
},
  "geometry": {"coordinates":[-90.226139,44.680016],"type":"Point"}
}