{
  "type": "Feature",
  "properties": {
    "iso:country":"US",
    "sg:address":"1976 S 81st St",
    "sg:city":"Milwaukee",
    "sg:classifiers":[
        {
            "category":"Building & Trades",
            "subcategory":"Plumbing",
            "type":"Services"
        }
    ],
    "sg:phone":"+1 414 546 1322",
    "sg:postcode":"53219",
    "sg:province":"WI",
    "sg:tags":[
        "plumbing",
        "contractor"
    ],
    "wof:name":"HTG Plumbing Inc",
    "wof:placetype":"venue"
},
  "geometry": {"coordinates":[-88.013831,43.008781],"type":"Point"}
}