{
  "type": "Feature",
  "properties": {
    "addr:full":"1249 Madison St Beaver Dam WI 53916",
    "addr:housenumber":"1249",
    "addr:postcode":"53916",
    "addr:street":"Madison St",
    "iso:country":"US",
    "sg:address":"1249 Madison St",
    "sg:city":"Beaver Dam",
    "sg:classifiers":[
        {
            "category":"Retail",
            "subcategory":"Auto Repair",
            "type":"Services"
        }
    ],
    "sg:phone":"+1 920 887 8586",
    "sg:postcode":"53916",
    "sg:province":"WI",
    "sg:tags":[
        "transmission",
        "repairing",
        "automobile"
    ],
    "wof:name":"Don Cigelskes Transmissions",
    "wof:placetype":"venue"
},
  "geometry": {"coordinates":[-88.857376,43.440601],"type":"Point"}
}