{
  "type": "Feature",
  "properties": {
    "iso:country":"US",
    "sg:address":"2055 Southland Ln",
    "sg:city":"New London",
    "sg:classifiers":[
        {
            "category":"Recreation",
            "type":"Entertainment"
        }
    ],
    "sg:phone":"+1 920 982 2771",
    "sg:postcode":"54961",
    "sg:province":"WI",
    "sg:tags":[
        "guide"
    ],
    "wof:name":"Williams Award Winning Txdrmy",
    "wof:placetype":"venue"
},
  "geometry": {"coordinates":[-88.753992,44.374304],"type":"Point"}
}