{
  "type": "Feature",
  "properties": {
    "iso:country":"US",
    "sg:address":"1820 Alabama St",
    "sg:city":"Sturgeon Bay",
    "sg:classifiers":[
        {
            "category":"Cinema",
            "subcategory":"Movie Theater",
            "type":"Entertainment"
        }
    ],
    "sg:phone":"+1 920 746 8371",
    "sg:postcode":"54235",
    "sg:province":"WI",
    "sg:tags":[
        "motion",
        "picture"
    ],
    "wof:name":"Sturgeon Bay Cinema",
    "wof:placetype":"venue"
},
  "geometry": {"coordinates":[-87.346604,44.849736],"type":"Point"}
}