{
  "type": "Feature",
  "properties": {
    "iso:country":"US",
    "sg:address":"275 Bruce St",
    "sg:city":"Verona",
    "sg:classifiers":[
        {
            "category":"Manufacturing",
            "subcategory":"Printing",
            "type":"Manufacturing & Wholesale Goods"
        }
    ],
    "sg:phone":"+1 608 848 1701",
    "sg:postcode":"53593",
    "sg:province":"WI",
    "sg:tags":[
        "publisher",
        "periodical"
    ],
    "wof:name":"Planet Newsletter LLC",
    "wof:placetype":"venue"
},
  "geometry": {"coordinates":[-89.534617,42.976319],"type":"Point"}
}