{
  "type": "Feature",
  "properties": {
    "iso:country":"US",
    "sg:address":"1509 N 4th St",
    "sg:city":"Tomahawk",
    "sg:classifiers":[
        {
            "category":"Insurance",
            "subcategory":"Insurance Agent",
            "type":"Services"
        }
    ],
    "sg:phone":"+1 715 453 7134",
    "sg:postcode":"54487",
    "sg:province":"WI",
    "wof:name":"American Family Insurance",
    "wof:placetype":"venue"
},
  "geometry": {"coordinates":[-89.72936900000001,45.491235],"type":"Point"}
}