{
  "type": "Feature",
  "properties": {
    "iso:country":"US",
    "sg:address":"4902 W State St",
    "sg:city":"Milwaukee",
    "sg:classifiers":[
        {
            "category":"Autos & Motor Vehicles",
            "subcategory":"Automobile Sales",
            "type":"Retail Goods"
        },
        {
            "category":"Retail",
            "subcategory":"Auto Repair",
            "type":"Services"
        }
    ],
    "sg:phone":"+1 414 475 6388",
    "sg:postcode":"53208",
    "sg:province":"WI",
    "sg:tags":[
        "car",
        "used",
        "new"
    ],
    "wof:name":"Platinum Motors",
    "wof:placetype":"venue"
},
  "geometry": {"coordinates":[-87.974287,43.043845],"type":"Point"}
}