{
  "type": "Feature",
  "properties": {
    "iso:country":"US",
    "sg:address":"3299 Lekie Dr",
    "sg:city":"Medford",
    "sg:classifiers":[
        {
            "category":"Farming",
            "subcategory":"Dairy Farm",
            "type":"Manufacturing & Wholesale Goods"
        }
    ],
    "sg:phone":"+1 715 748 4793",
    "sg:postcode":"54451",
    "sg:province":"WI",
    "wof:name":"Brandner Dairy",
    "wof:placetype":"venue"
},
  "geometry": {"coordinates":[-90.209659,45.159833],"type":"Point"}
}