{
  "type": "Feature",
  "properties": {
    "addr:full":"20769 Co Hwy X Chippewa Falls WI 54729",
    "addr:housenumber":"20769",
    "addr:postcode":"54729",
    "addr:street":"Co Hwy X",
    "iso:country":"US",
    "sg:address":"20769 Co Hwy X",
    "sg:city":"Chippewa Falls",
    "sg:classifiers":[
        {
            "category":"Building & Trades",
            "subcategory":"Construction",
            "type":"Services"
        }
    ],
    "sg:phone":"+1 715 723 2394",
    "sg:postcode":"54729",
    "sg:province":"WI",
    "sg:tags":[
        "masonry",
        "contractor"
    ],
    "wof:name":"Larry Green Masonry Contractor",
    "wof:placetype":"venue"
},
  "geometry": {"coordinates":[-91.252364,44.929576],"type":"Point"}
}