{
  "type": "Feature",
  "properties": {
    "iso:country":"US",
    "sg:address":"1212 200th Ave",
    "sg:city":"New Richmond",
    "sg:classifiers":[
        {
            "category":"Building & Trades",
            "subcategory":"Construction",
            "type":"Services"
        }
    ],
    "sg:phone":"+1 715 246 6946",
    "sg:postcode":"54017",
    "sg:province":"WI",
    "sg:tags":[
        "carpentry",
        "contractor"
    ],
    "wof:name":"Langer Woodcraft",
    "wof:placetype":"venue"
},
  "geometry": {"coordinates":[-92.57162599999999,45.151563],"type":"Point"}
}