{
  "type": "Feature",
  "properties": {
    "iso:country":"US",
    "sg:address":"704 S Whitney Way",
    "sg:city":"Madison",
    "sg:classifiers":[
        {
            "category":"Restaurant",
            "type":"Food & Drink"
        }
    ],
    "sg:menulink":"http://www.allmenus.com/wi/madison/261422-cancun-mexican-restaurant/menu/",
    "sg:phone":"+1 608 277 0992",
    "sg:postcode":"53711",
    "sg:province":"WI",
    "sg:tags":[
        "mexican"
    ],
    "wof:name":"Cancun Mexican Restaurant",
    "wof:placetype":"venue"
},
  "geometry": {"coordinates":[-89.47358,43.049815],"type":"Point"}
}