{
  "type": "Feature",
  "properties": {
    "iso:country":"US",
    "sg:address":"69 Hoopen Rd",
    "sg:city":"Cambridge",
    "sg:classifiers":[
        {
            "category":"Building & Trades",
            "subcategory":"Construction",
            "type":"Services"
        }
    ],
    "sg:phone":"+1 608 423 3542",
    "sg:postcode":"53523",
    "sg:province":"WI",
    "sg:tags":[
        "concrete",
        "contractor"
    ],
    "wof:name":"Hausz Concrete Inc",
    "wof:placetype":"venue"
},
  "geometry": {"coordinates":[-89.01969,42.949721],"type":"Point"}
}