{
  "type": "Feature",
  "properties": {
    "iso:country":"US",
    "sg:address":"1315 Wisconsin Ave",
    "sg:city":"Grafton",
    "sg:classifiers":[
        {
            "category":"Restaurant",
            "type":"Food & Drink"
        }
    ],
    "sg:phone":"+1 262 377 4374",
    "sg:postcode":"53024",
    "sg:province":"WI",
    "sg:tags":[
        "shop",
        "coffee"
    ],
    "wof:name":"Painted Bean",
    "wof:placetype":"venue"
},
  "geometry": {"coordinates":[-87.951878,43.318407],"type":"Point"}
}