{
  "type": "Feature",
  "properties": {
    "addr:full":"1724 Regent St Madison WI 53726",
    "addr:housenumber":"1724",
    "addr:postcode":"53726",
    "addr:street":"Regent St",
    "iso:country":"US",
    "sg:address":"1724 Regent St",
    "sg:city":"Madison",
    "sg:classifiers":[
        {
            "category":"Real Estate",
            "subcategory":"Real Estate Agent",
            "type":"Services"
        }
    ],
    "sg:phone":"+1 608 233 0202",
    "sg:postcode":"53726",
    "sg:province":"WI",
    "wof:name":"Lathrop Properties LLC",
    "wof:placetype":"venue"
},
  "geometry": {"coordinates":[-89.416415,43.067913],"type":"Point"}
}