{
  "type": "Feature",
  "properties": {
    "iso:country":"US",
    "sg:address":"8025 Excelsior Dr.",
    "sg:city":"Madison",
    "sg:classifiers":[
        {
            "category":"Professional",
            "subcategory":"Computer Services",
            "type":"Services"
        }
    ],
    "sg:postcode":"53717",
    "sg:province":"WI",
    "sg:tags":[
        "social-media",
        "mapping",
        "interactive-mapping",
        "fishing",
        "outdoor-recreation",
        "fishing-data",
        "fishing-maps"
    ],
    "sg:website":"http://www.outdoorinsite.com",
    "wof:name":"Outdoor InSite",
    "wof:placetype":"venue"
},
  "geometry": {"coordinates":[-89.524292,43.079448],"type":"Point"}
}