{
  "type": "Feature",
  "properties": {
    "iso:country":"US",
    "sg:address":"1118 Grove Ave",
    "sg:city":"Racine",
    "sg:classifiers":[
        {
            "category":"Personal",
            "subcategory":"Beauty Salon",
            "type":"Services"
        }
    ],
    "sg:phone":"+1 262 634 6770",
    "sg:postcode":"53405",
    "sg:province":"WI",
    "sg:tags":[
        "shop"
    ],
    "wof:name":"Nail & Face Place",
    "wof:placetype":"venue"
},
  "geometry": {"coordinates":[-87.817442,42.718984],"type":"Point"}
}