{
  "type": "Feature",
  "properties": {
    "iso:country":"US",
    "sg:address":"1906 Melvin Ave",
    "sg:city":"Racine",
    "sg:classifiers":[
        {
            "category":"Home & Garden",
            "subcategory":"Furniture",
            "type":"Retail Goods"
        }
    ],
    "sg:phone":"+1 262 681 9460",
    "sg:postcode":"53404",
    "sg:province":"WI",
    "wof:name":"Nu-Wood Cabinet LTD",
    "wof:placetype":"venue"
},
  "geometry": {"coordinates":[-87.80446600000001,42.755523],"type":"Point"}
}