{
  "type": "Feature",
  "properties": {
    "addr:full":"1323 Michigan Ave Sheboygan WI 53081",
    "addr:housenumber":"1323",
    "addr:postcode":"53081",
    "addr:street":"Michigan Ave",
    "iso:country":"US",
    "sg:address":"1323 Michigan Ave",
    "sg:city":"Sheboygan",
    "sg:classifiers":[
        {
            "category":"Manufacturing",
            "subcategory":"Food",
            "type":"Manufacturing & Wholesale Goods"
        }
    ],
    "sg:phone":"+1 920 459 9833",
    "sg:postcode":"53081",
    "sg:province":"WI",
    "sg:tags":[
        "frozen",
        "dessert",
        "ice",
        "cream"
    ],
    "wof:name":"Angie's Subs & Ice Cream",
    "wof:placetype":"venue"
},
  "geometry": {"coordinates":[-87.72289600000001,43.758487],"type":"Point"}
}