{
  "type": "Feature",
  "properties": {
    "iso:country":"US",
    "sg:address":"941 N Perkins St",
    "sg:city":"Appleton",
    "sg:classifiers":[
        {
            "category":"Freight",
            "type":"Transportation"
        }
    ],
    "sg:phone":"+1 630 766 7121",
    "sg:postcode":"54914",
    "sg:province":"WI",
    "sg:tags":[
        "company",
        "trucking"
    ],
    "wof:name":"World Class Logistics Inc",
    "wof:placetype":"venue"
},
  "geometry": {"coordinates":[-88.44137000000001,44.27272],"type":"Point"}
}