{
  "type": "Feature",
  "properties": {
    "iso:country":"US",
    "sg:address":"201 W Main St",
    "sg:city":"Waterford",
    "sg:classifiers":[
        {
            "category":"Restaurant",
            "type":"Food & Drink"
        }
    ],
    "sg:phone":"+1 262 534 5200",
    "sg:postcode":"53185",
    "sg:province":"WI",
    "sg:tags":[
        "eating"
    ],
    "wof:name":"Marty's Diamond",
    "wof:placetype":"venue"
},
  "geometry": {"coordinates":[-88.214218,42.76321],"type":"Point"}
}