{
  "type": "Feature",
  "properties": {
    "addr:full":"612 Chippewa Ct Fort Atkinson WI 53538",
    "addr:housenumber":"612",
    "addr:postcode":"53538",
    "addr:street":"Chippewa Ct",
    "iso:country":"US",
    "sg:address":"612 Chippewa Ct",
    "sg:city":"Fort Atkinson",
    "sg:classifiers":[
        {
            "category":"Manufacturing",
            "subcategory":"Printing",
            "type":"Manufacturing & Wholesale Goods"
        }
    ],
    "sg:phone":"+1 920 568 1079",
    "sg:postcode":"53538",
    "sg:province":"WI",
    "sg:tags":[
        "child",
        "book",
        "day",
        "care"
    ],
    "wof:name":"Table Time Projects",
    "wof:placetype":"venue"
},
  "geometry": {"coordinates":[-88.846069,42.94077],"type":"Point"}
}