{
  "type": "Feature",
  "properties": {
    "addr:full":"5256 Dundee Rd Rhinelander WI 54501",
    "addr:housenumber":"5256",
    "addr:postcode":"54501",
    "addr:street":"Dundee Rd",
    "iso:country":"US",
    "sg:address":"5256 Dundee Rd",
    "sg:city":"Rhinelander",
    "sg:phone":"+1 715 369 3175",
    "sg:postcode":"54501",
    "sg:province":"WI",
    "sg:tags":[
        "equipment",
        "commercial"
    ],
    "wof:name":"Newbold Equipment & Tool",
    "wof:placetype":"venue"
},
  "geometry": {"coordinates":[-89.411277,45.679777],"type":"Point"}
}