{
  "type": "Feature",
  "properties": {
    "iso:country":"US",
    "sg:address":"645 Schwartz Rd",
    "sg:city":"Pulaski",
    "sg:classifiers":[
        {
            "category":"Farming",
            "subcategory":"Livestock Farm",
            "type":"Manufacturing & Wholesale Goods"
        }
    ],
    "sg:phone":"+1 920 822 8265",
    "sg:postcode":"54162",
    "sg:province":"WI",
    "sg:tags":[
        "beef",
        "feedlot",
        "cattle"
    ],
    "wof:name":"Gerald Nooyen",
    "wof:placetype":"venue"
},
  "geometry": {"coordinates":[-88.181636,44.69577],"type":"Point"}
}