{
  "type": "Feature",
  "properties": {
    "iso:country":"US",
    "sg:address":"2415 N 11th St",
    "sg:city":"Milwaukee",
    "sg:classifiers":[
        {
            "category":"Building & Trades",
            "subcategory":"Landscaping Services",
            "type":"Services"
        }
    ],
    "sg:phone":"+1 414 467 2689",
    "sg:postcode":"53206",
    "sg:province":"WI",
    "sg:tags":[
        "aged",
        "homes-institutional"
    ],
    "wof:name":"N E Individual & Family Services",
    "wof:placetype":"venue"
},
  "geometry": {"coordinates":[-87.925456,43.062424],"type":"Point"}
}