{
  "type": "Feature",
  "properties": {
    "iso:country":"US",
    "sg:address":"2367 E River Dr",
    "sg:city":"Green Bay",
    "sg:classifiers":[
        {
            "category":"Shopping",
            "subcategory":"Hobbies, Toys, & Games",
            "type":"Retail Goods"
        }
    ],
    "sg:phone":"+1 920 436 9762",
    "sg:postcode":"54301",
    "sg:province":"WI",
    "wof:name":"Shawano Hobbies LLC",
    "wof:placetype":"venue"
},
  "geometry": {"coordinates":[-88.011753,44.474846],"type":"Point"}
}