{
  "type": "Feature",
  "properties": {
    "addr:full":"132 Trowbridge Dr Fond Du Lac WI 54937",
    "addr:housenumber":"132",
    "addr:postcode":"54937",
    "addr:street":"Trowbridge Dr",
    "iso:country":"US",
    "sg:address":"132 Trowbridge Dr",
    "sg:city":"Fond Du Lac",
    "sg:classifiers":[
        {
            "category":"Manufacturing",
            "subcategory":"Metals",
            "type":"Manufacturing & Wholesale Goods"
        }
    ],
    "sg:phone":"+1 920 922 7207",
    "sg:postcode":"54937",
    "sg:province":"WI",
    "sg:tags":[
        "extruded",
        "product",
        "aluminum"
    ],
    "sg:website":"www.midstal.com",
    "wof:name":"Mid-States Aluminum Corp",
    "wof:placetype":"venue"
},
  "geometry": {"coordinates":[-88.47561399999999,43.74782],"type":"Point"}
}