{
  "type": "Feature",
  "properties": {
    "iso:country":"US",
    "sg:address":"5848 Park Ln",
    "sg:city":"Hartford",
    "sg:classifiers":[
        {
            "category":"Manufacturing",
            "subcategory":"Electronics",
            "type":"Manufacturing & Wholesale Goods"
        }
    ],
    "sg:phone":"+1 262 644 6276",
    "sg:postcode":"53027",
    "sg:province":"WI",
    "sg:tags":[
        "equipment",
        "mfg",
        "communication"
    ],
    "wof:name":"Motorola",
    "wof:placetype":"venue"
},
  "geometry": {"coordinates":[-88.32277499999999,43.302111],"type":"Point"}
}