{
  "type": "Feature",
  "properties": {
    "iso:country":"US",
    "sg:address":"1200 W Walnut St",
    "sg:city":"Milwaukee",
    "sg:classifiers":[
        {
            "category":"Organizations",
            "subcategory":"Religious Organization",
            "type":"Services"
        }
    ],
    "sg:phone":"+1 414 562 6972",
    "sg:postcode":"53205",
    "sg:province":"WI",
    "sg:tags":[
        "church"
    ],
    "wof:name":"Mt Sinai Community Baptist Chr",
    "wof:placetype":"venue"
},
  "geometry": {"coordinates":[-87.927848,43.052628],"type":"Point"}
}