{
  "type": "Feature",
  "properties": {
    "iso:country":"US",
    "sg:address":"9120 N 107th St",
    "sg:city":"Milwaukee",
    "sg:classifiers":[
        {
            "category":"Retail",
            "subcategory":"Auto Repair",
            "type":"Services"
        }
    ],
    "sg:phone":"+1 414 355 6662",
    "sg:postcode":"53224",
    "sg:province":"WI",
    "sg:tags":[
        "truck",
        "trailers-repair"
    ],
    "wof:name":"Custom Fleet Maintenance",
    "wof:placetype":"venue"
},
  "geometry": {"coordinates":[-88.044037,43.183522],"type":"Point"}
}