{
  "type": "Feature",
  "properties": {
    "iso:country":"US",
    "sg:address":"8548 Koeppler Rd",
    "sg:city":"Ojibwa",
    "sg:classifiers":[
        {
            "category":"Manufacturing",
            "subcategory":"Lumber",
            "type":"Manufacturing & Wholesale Goods"
        }
    ],
    "sg:phone":"+1 715 266 5402",
    "sg:postcode":"54862",
    "sg:province":"WI",
    "sg:tags":[
        "logging"
    ],
    "wof:name":"Anderson Rudolph Logging",
    "wof:placetype":"venue"
},
  "geometry": {"coordinates":[-91.113269,45.797199],"type":"Point"}
}