{
  "type": "Feature",
  "properties": {
    "iso:country":"US",
    "sg:address":"819 E Morgan Ave",
    "sg:city":"Milwaukee",
    "sg:classifiers":[
        {
            "category":"Wholesale",
            "subcategory":"Auto Parts",
            "type":"Manufacturing & Wholesale Goods"
        }
    ],
    "sg:phone":"+1 414 483 7423",
    "sg:postcode":"53207",
    "sg:province":"WI",
    "sg:tags":[
        "automobile",
        "wrecking"
    ],
    "wof:name":"Bower's Salvage",
    "wof:placetype":"venue"
},
  "geometry": {"coordinates":[-87.898309,42.980945],"type":"Point"}
}