{
  "type": "Feature",
  "properties": {
    "iso:country":"US",
    "sg:address":"16391 Co Hwy G",
    "sg:city":"Stanley",
    "sg:classifiers":[
        {
            "category":"Farming",
            "subcategory":"Dairy Farm",
            "type":"Manufacturing & Wholesale Goods"
        }
    ],
    "sg:phone":"+1 715 644 5390",
    "sg:postcode":"54768",
    "sg:province":"WI",
    "wof:name":"James Cox",
    "wof:placetype":"venue"
},
  "geometry": {"coordinates":[-90.984228,45.078401],"type":"Point"}
}