{
  "type": "Feature",
  "properties": {
    "iso:country":"US",
    "sg:address":"7060 Paoli Rd",
    "sg:city":"Verona",
    "sg:classifiers":[
        {
            "category":"Farming",
            "subcategory":"Dairy Farm",
            "type":"Manufacturing & Wholesale Goods"
        }
    ],
    "sg:phone":"+1 608 845 7476",
    "sg:postcode":"53593",
    "sg:province":"WI",
    "wof:name":"Erwin Himsel",
    "wof:placetype":"venue"
},
  "geometry": {"coordinates":[-89.538331,42.92949],"type":"Point"}
}