{
  "type": "Feature",
  "properties": {
    "iso:country":"US",
    "sg:address":"7942 Lodi Springfield Rd",
    "sg:city":"Lodi",
    "sg:classifiers":[
        {
            "category":"Building & Trades",
            "subcategory":"Construction",
            "type":"Services"
        }
    ],
    "sg:phone":"+1 608 592 3743",
    "sg:postcode":"53555",
    "sg:province":"WI",
    "sg:tags":[
        "contractor"
    ],
    "wof:name":"Margraf Roofing",
    "wof:placetype":"venue"
},
  "geometry": {"coordinates":[-89.547495,43.278621],"type":"Point"}
}