{
  "type": "Feature",
  "properties": {
    "iso:country":"US",
    "sg:address":"3703 Altoona Ave",
    "sg:city":"Altoona",
    "sg:classifiers":[
        {
            "category":"Restaurant",
            "type":"Food & Drink"
        }
    ],
    "sg:phone":"+1 715 832 0401",
    "sg:postcode":"54720",
    "sg:province":"WI",
    "sg:tags":[
        "eating"
    ],
    "wof:name":"Northwoods Lobster Co LLC",
    "wof:placetype":"venue"
},
  "geometry": {"coordinates":[-91.46507099999999,44.809164],"type":"Point"}
}