{
  "type": "Feature",
  "properties": {
    "addr:full":"511 S Railroad St Kimberly WI 54136",
    "addr:housenumber":"511",
    "addr:postcode":"54136",
    "addr:street":"S Railroad St",
    "iso:country":"US",
    "sg:address":"511 S Railroad St",
    "sg:city":"Kimberly",
    "sg:classifiers":[
        {
            "category":"Manufacturing",
            "subcategory":"Tools & Machinery",
            "type":"Manufacturing & Wholesale Goods"
        }
    ],
    "sg:phone":"+1 920 687 0158",
    "sg:postcode":"54136",
    "sg:province":"WI",
    "sg:tags":[
        "machine",
        "shop"
    ],
    "wof:name":"Black Dog Machine",
    "wof:placetype":"venue"
},
  "geometry": {"coordinates":[-88.339028,44.264669],"type":"Point"}
}