{
  "type": "Feature",
  "properties": {
    "iso:country":"US",
    "sg:address":"110 W Vinal St",
    "sg:city":"Wittenberg",
    "sg:classifiers":[
        {
            "category":"Manufacturing",
            "subcategory":"Printing",
            "type":"Manufacturing & Wholesale Goods"
        }
    ],
    "sg:phone":"+1 715 253 2737",
    "sg:postcode":"54499",
    "sg:province":"WI",
    "sg:tags":[
        "newspaper"
    ],
    "wof:name":"Wittenberg Enterprise News",
    "wof:placetype":"venue"
},
  "geometry": {"coordinates":[-89.168401,44.823717],"type":"Point"}
}