{
  "type": "Feature",
  "properties": {
    "addr:full":"227 E Main St Sun Prairie WI 53590",
    "addr:housenumber":"227",
    "addr:postcode":"53590",
    "addr:street":"E Main St",
    "iso:country":"US",
    "sg:address":"227 E Main St",
    "sg:city":"Sun Prairie",
    "sg:classifiers":[
        {
            "category":"Shopping",
            "subcategory":"Crafts & Fabrics",
            "type":"Retail Goods"
        }
    ],
    "sg:phone":"+1 608 837 8909",
    "sg:postcode":"53590",
    "sg:province":"WI",
    "sg:tags":[
        "sewing"
    ],
    "wof:name":"Prairie Junction",
    "wof:placetype":"venue"
},
  "geometry": {"coordinates":[-89.212355,43.183087],"type":"Point"}
}