{
  "type": "Feature",
  "properties": {
    "iso:country":"US",
    "sg:address":"4777 S 27th St",
    "sg:city":"Milwaukee",
    "sg:classifiers":[
        {
            "category":"Shopping",
            "subcategory":"Department Store",
            "type":"Retail Goods"
        }
    ],
    "sg:phone":"+1 414 282 1000",
    "sg:postcode":"53221",
    "sg:province":"WI",
    "wof:name":"Target",
    "wof:placetype":"venue"
},
  "geometry": {"coordinates":[-87.948812,42.958998],"type":"Point"}
}