{
  "type": "Feature",
  "properties": {
    "iso:country":"US",
    "sg:address":"1404 Center Ave",
    "sg:city":"Janesville",
    "sg:classifiers":[
        {
            "category":"Social Services",
            "subcategory":"Adult Care",
            "type":"Services"
        }
    ],
    "sg:phone":"+1 608 755 0923",
    "sg:postcode":"53546",
    "sg:province":"WI",
    "sg:tags":[
        "home",
        "group"
    ],
    "wof:name":"Lutheran Social Svc",
    "wof:placetype":"venue"
},
  "geometry": {"coordinates":[-89.031335,42.659061],"type":"Point"}
}