{
  "type": "Feature",
  "properties": {
    "iso:country":"US",
    "sg:address":"2146 E Johnson St",
    "sg:city":"Madison",
    "sg:classifiers":[
        {
            "category":"Recreation",
            "type":"Entertainment"
        }
    ],
    "sg:phone":"+1 608 223 0229",
    "sg:postcode":"53704",
    "sg:province":"WI",
    "sg:tags":[
        "martial",
        "arts",
        "instruction"
    ],
    "wof:name":"Madison Aikido Club",
    "wof:placetype":"venue"
},
  "geometry": {"coordinates":[-89.357876,43.097641],"type":"Point"}
}