{
  "type": "Feature",
  "properties": {
    "iso:country":"US",
    "sg:address":"405 Santa Maria Dr",
    "sg:city":"Arlington",
    "sg:classifiers":[
        {
            "category":"Building & Trades",
            "subcategory":"Cleaning & Sanitation",
            "type":"Services"
        }
    ],
    "sg:phone":"+1 608 635 4264",
    "sg:postcode":"53911",
    "sg:province":"WI",
    "sg:tags":[
        "maintenance"
    ],
    "wof:name":"Facility Concepts Plus LLC",
    "wof:placetype":"venue"
},
  "geometry": {"coordinates":[-89.378498,43.340724],"type":"Point"}
}