{
  "type": "Feature",
  "properties": {
    "iso:country":"US",
    "sg:address":"1255 Bell Ave",
    "sg:city":"Hartford",
    "sg:classifiers":[
        {
            "category":"Professional",
            "subcategory":"Management & Consulting",
            "type":"Services"
        }
    ],
    "sg:phone":"+1 262 670 9877",
    "sg:postcode":"53027",
    "sg:province":"WI",
    "sg:tags":[
        "consultant"
    ],
    "wof:name":"Dan Vogds Trading Co",
    "wof:placetype":"venue"
},
  "geometry": {"coordinates":[-88.36114499999999,43.316771],"type":"Point"}
}