{
  "type": "Feature",
  "properties": {
    "iso:country":"US",
    "sg:address":"1525 Coulee Rd",
    "sg:city":"Hudson",
    "sg:classifiers":[
        {
            "category":"Banks & Credit Unions",
            "subcategory":"Bank",
            "type":"Services"
        }
    ],
    "sg:phone":"+1 715 386 4480",
    "sg:postcode":"54016",
    "sg:province":"WI",
    "sg:tags":[
        "state",
        "commercial"
    ],
    "wof:name":"Citizens Bank",
    "wof:placetype":"venue"
},
  "geometry": {"coordinates":[-92.735832,44.963396],"type":"Point"}
}