{
  "type": "Feature",
  "properties": {
    "addr:full":"309 N Rutland Ave Brooklyn WI 53521",
    "addr:housenumber":"309",
    "addr:postcode":"53521",
    "addr:street":"N Rutland Ave",
    "iso:country":"US",
    "sg:address":"309 N Rutland Ave",
    "sg:city":"Brooklyn",
    "sg:classifiers":[
        {
            "category":"Building & Trades",
            "subcategory":"Construction",
            "type":"Services"
        }
    ],
    "sg:phone":"+1 608 455 6022",
    "sg:postcode":"53521",
    "sg:province":"WI",
    "sg:tags":[
        "residential"
    ],
    "wof:name":"Seidels Construction",
    "wof:placetype":"venue"
},
  "geometry": {"coordinates":[-89.369006,42.85427],"type":"Point"}
}