{
  "type": "Feature",
  "properties": {
    "iso:country":"US",
    "sg:address":"2989 W Spencer St",
    "sg:city":"Appleton",
    "sg:classifiers":[
        {
            "category":"Wholesale",
            "subcategory":"Non-durable Goods",
            "type":"Manufacturing & Wholesale Goods"
        }
    ],
    "sg:phone":"+1 920 739 7340",
    "sg:postcode":"54914",
    "sg:province":"WI",
    "wof:name":"Fox Valley Distributing",
    "wof:placetype":"venue"
},
  "geometry": {"coordinates":[-88.454339,44.258619],"type":"Point"}
}