{
  "type": "Feature",
  "properties": {
    "addr:full":"205 Maries Way Random Lake WI 53075",
    "addr:housenumber":"205",
    "addr:postcode":"53075",
    "addr:street":"Maries Way",
    "iso:country":"US",
    "sg:address":"205 Maries Way",
    "sg:city":"Random Lake",
    "sg:classifiers":[
        {
            "category":"Building & Trades",
            "subcategory":"Landscaping Services",
            "type":"Services"
        }
    ],
    "sg:phone":"+1 262 285 3593",
    "sg:postcode":"53075",
    "sg:province":"WI",
    "sg:tags":[
        "landscape",
        "contractor"
    ],
    "wof:name":"Green Valley Landscaping",
    "wof:placetype":"venue"
},
  "geometry": {"coordinates":[-87.943128,43.55367],"type":"Point"}
}