{
  "type": "Feature",
  "properties": {
    "iso:country":"US",
    "sg:address":"11377 Main St",
    "sg:city":"Trempealeau",
    "sg:classifiers":[
        {
            "category":"Bars & Pubs",
            "type":"Food & Drink"
        }
    ],
    "sg:phone":"+1 608 534 5235",
    "sg:postcode":"54661",
    "sg:province":"WI",
    "sg:tags":[
        "drinking"
    ],
    "wof:name":"Linda's Place",
    "wof:placetype":"venue"
},
  "geometry": {"coordinates":[-91.442477,44.004785],"type":"Point"}
}