{
  "type": "Feature",
  "properties": {
    "iso:country":"US",
    "sg:address":"442 Forest St",
    "sg:city":"Downing",
    "sg:classifiers":[
        {
            "category":"Building & Trades",
            "subcategory":"Construction",
            "type":"Services"
        }
    ],
    "sg:phone":"+1 715 265 4523",
    "sg:postcode":"54734",
    "sg:province":"WI",
    "sg:tags":[
        "house"
    ],
    "wof:name":"Zielsdorf Construction",
    "wof:placetype":"venue"
},
  "geometry": {"coordinates":[-92.133835,45.044071],"type":"Point"}
}