{
  "type": "Feature",
  "properties": {
    "iso:country":"US",
    "sg:address":"5706 W Vliet St",
    "sg:city":"Milwaukee",
    "sg:classifiers":[
        {
            "category":"Shopping",
            "subcategory":"Clothing, Apparel, & Fashions",
            "type":"Retail Goods"
        }
    ],
    "sg:phone":"+1 414 771 9222",
    "sg:postcode":"53208",
    "sg:province":"WI",
    "sg:tags":[
        "item",
        "boutique"
    ],
    "wof:name":"Mermaid Alley LLC",
    "wof:placetype":"venue"
},
  "geometry": {"coordinates":[-87.98524399999999,43.049825],"type":"Point"}
}