{
  "type": "Feature",
  "properties": {
    "iso:country":"US",
    "sg:address":"20373 Chicken Ridge Rd",
    "sg:city":"Richland Center",
    "sg:classifiers":[
        {
            "category":"Farming",
            "subcategory":"Farm",
            "type":"Manufacturing & Wholesale Goods"
        }
    ],
    "sg:phone":"+1 608 647 8329",
    "sg:postcode":"53581",
    "sg:province":"WI",
    "sg:tags":[
        "crop",
        "general"
    ],
    "wof:name":"Matt Ottesen",
    "wof:placetype":"venue"
},
  "geometry": {"coordinates":[-90.453624,43.316911],"type":"Point"}
}