{
  "type": "Feature",
  "properties": {
    "iso:country":"US",
    "sg:address":"11940 S Maxworthy Rd",
    "sg:city":"Clinton",
    "sg:classifiers":[
        {
            "category":"Wholesale",
            "subcategory":"Furniture",
            "type":"Manufacturing & Wholesale Goods"
        },
        {
            "category":"Home & Garden",
            "subcategory":"Furniture",
            "type":"Retail Goods"
        }
    ],
    "sg:phone":"+1 608 365 5520",
    "sg:postcode":"53525",
    "sg:province":"WI",
    "sg:tags":[
        "store",
        "furniture-wholesale",
        "manufacturer"
    ],
    "wof:name":"Ross Services",
    "wof:placetype":"venue"
},
  "geometry": {"coordinates":[-88.923979,42.505804],"type":"Point"}
}