{
  "type": "Feature",
  "properties": {
    "addr:full":"529 N River Rd West Bend WI 53090",
    "addr:housenumber":"529",
    "addr:postcode":"53090",
    "addr:street":"N River Rd",
    "iso:country":"US",
    "sg:address":"529 N River Rd",
    "sg:city":"West Bend",
    "sg:classifiers":[
        {
            "category":"Manufacturing",
            "subcategory":"Building Materials",
            "type":"Manufacturing & Wholesale Goods"
        }
    ],
    "sg:phone":"+1 262 338 4480",
    "sg:postcode":"53090",
    "sg:province":"WI",
    "sg:tags":[
        "door"
    ],
    "wof:name":"Milliken Millwork Inc",
    "wof:placetype":"venue"
},
  "geometry": {"coordinates":[-88.161343,43.428325],"type":"Point"}
}