{
  "type": "Feature",
  "properties": {
    "iso:country":"US",
    "sg:address":"8725 W North Ave",
    "sg:city":"Milwaukee",
    "sg:classifiers":[
        {
            "category":"Restaurant",
            "type":"Food & Drink"
        }
    ],
    "sg:menulink":"http://www.allmenus.com/wi/wauwatosa/141655-the-city-market/menu/",
    "sg:phone":"+1 414 453 0000",
    "sg:postcode":"53226",
    "sg:province":"WI",
    "sg:tags":[
        "american",
        "diner"
    ],
    "wof:name":"The City Market",
    "wof:placetype":"venue"
},
  "geometry": {"coordinates":[-88.02189799999999,43.060286],"type":"Point"}
}