{
  "type": "Feature",
  "properties": {
    "addr:full":"4801 Washington Ave Racine WI 53406",
    "addr:housenumber":"4801",
    "addr:postcode":"53406",
    "addr:street":"Washington Ave",
    "iso:country":"US",
    "sg:address":"4801 Washington Ave",
    "sg:city":"Racine",
    "sg:classifiers":[
        {
            "category":"Shopping",
            "subcategory":"Department Store",
            "type":"Retail Goods"
        }
    ],
    "sg:phone":"+1 262 637 7333",
    "sg:postcode":"53406",
    "sg:province":"WI",
    "sg:tags":[
        "discount",
        "optical",
        "center",
        "pharmacy"
    ],
    "wof:name":"Shopko",
    "wof:placetype":"venue"
},
  "geometry": {"coordinates":[-87.83644,42.718528],"type":"Point"}
}