{
  "type": "Feature",
  "properties": {
    "addr:full":"5300 N Hollywood Ave Milwaukee WI 53217",
    "addr:housenumber":"5300",
    "addr:postcode":"53217",
    "addr:street":"N Hollywood Ave",
    "iso:country":"US",
    "sg:address":"5300 N Hollywood Ave",
    "sg:city":"Milwaukee",
    "sg:classifiers":[
        {
            "category":"Airline",
            "type":"Transportation"
        }
    ],
    "sg:phone":"+1 414 747 4574",
    "sg:postcode":"53217",
    "sg:province":"WI",
    "sg:tags":[
        "scheduled",
        "air"
    ],
    "wof:name":"Continental Airlines",
    "wof:placetype":"venue"
},
  "geometry": {"coordinates":[-87.90311199999999,43.115939],"type":"Point"}
}