{
  "type": "Feature",
  "properties": {
    "iso:country":"US",
    "sg:address":"304 Locust St",
    "sg:city":"Hudson",
    "sg:classifiers":[
        {
            "category":"Professional",
            "subcategory":"Lawyer & Legal Services",
            "type":"Services"
        }
    ],
    "sg:phone":"+1 715 386 8482",
    "sg:postcode":"54016",
    "sg:province":"WI",
    "wof:name":"Zilz Estreen & Oglend",
    "wof:placetype":"venue"
},
  "geometry": {"coordinates":[-92.755408,44.975886],"type":"Point"}
}