{
  "type": "Feature",
  "properties": {
    "iso:country":"US",
    "sg:address":"220 Walnut St",
    "sg:city":"Spooner",
    "sg:classifiers":[
        {
            "category":"Shopping",
            "subcategory":"Catalog Store",
            "type":"Retail Goods"
        }
    ],
    "sg:phone":"+1 715 635 2195",
    "sg:postcode":"54801",
    "sg:province":"WI",
    "wof:name":"JC Penney",
    "wof:placetype":"venue"
},
  "geometry": {"coordinates":[-91.889295,45.827136],"type":"Point"}
}