{
  "type": "Feature",
  "properties": {
    "addr:full":"1007 S 12th St Watertown WI 53094",
    "addr:housenumber":"1007",
    "addr:postcode":"53094",
    "addr:street":"S 12Th St",
    "iso:country":"US",
    "sg:address":"1007 S 12th St",
    "sg:city":"Watertown",
    "sg:classifiers":[
        {
            "category":"Wholesale",
            "subcategory":"Electrical",
            "type":"Manufacturing & Wholesale Goods"
        }
    ],
    "sg:phone":"+1 920 261 6024",
    "sg:postcode":"53094",
    "sg:province":"WI",
    "sg:tags":[
        "control"
    ],
    "wof:name":"Nortel Networks",
    "wof:placetype":"venue"
},
  "geometry": {"coordinates":[-88.71368699999999,43.173794],"type":"Point"}
}