{
  "type": "Feature",
  "properties": {
    "iso:country":"US",
    "sg:address":"1314 Baxter Ave",
    "sg:city":"Superior",
    "sg:classifiers":[
        {
            "category":"Manufacturing",
            "subcategory":"Toys & Sporting Goods",
            "type":"Manufacturing & Wholesale Goods"
        }
    ],
    "sg:phone":"+1 715 392 1215",
    "sg:postcode":"54880",
    "sg:province":"WI",
    "sg:tags":[
        "mfg"
    ],
    "wof:name":"Jerrys Quality Tackle",
    "wof:placetype":"venue"
},
  "geometry": {"coordinates":[-92.094825,46.722103],"type":"Point"}
}