{
  "type": "Feature",
  "properties": {
    "addr:full":"6322 Pilgrim Rd Madison WI 53711",
    "addr:housenumber":"6322",
    "addr:postcode":"53711",
    "addr:street":"Pilgrim Rd",
    "iso:country":"US",
    "sg:address":"6322 Pilgrim Rd",
    "sg:city":"Madison",
    "sg:classifiers":[
        {
            "category":"Professional",
            "subcategory":"Management & Consulting",
            "type":"Services"
        }
    ],
    "sg:phone":"+1 608 271 3243",
    "sg:postcode":"53711",
    "sg:province":"WI",
    "wof:name":"Dd Moyer & Associates LLC",
    "wof:placetype":"venue"
},
  "geometry": {"coordinates":[-89.492003,43.026233],"type":"Point"}
}