{
  "type": "Feature",
  "properties": {
    "iso:country":"US",
    "sg:address":"2629 Bass Rd",
    "sg:city":"Cottage Grove",
    "sg:classifiers":[
        {
            "category":"Building & Trades",
            "subcategory":"Construction",
            "type":"Services"
        }
    ],
    "sg:phone":"+1 608 839 9531",
    "sg:postcode":"53527",
    "sg:province":"WI",
    "sg:tags":[
        "house"
    ],
    "wof:name":"Mk Enterprises",
    "wof:placetype":"venue"
},
  "geometry": {"coordinates":[-89.20953,43.050767],"type":"Point"}
}