{
  "type": "Feature",
  "properties": {
    "iso:country":"US",
    "sg:address":"701 Sand Lake Coulee Rd",
    "sg:city":"Onalaska",
    "sg:classifiers":[
        {
            "category":"Insurance",
            "subcategory":"Insurance Agent",
            "type":"Services"
        }
    ],
    "sg:phone":"+1 608 781 2159",
    "sg:postcode":"54650",
    "sg:province":"WI",
    "sg:tags":[
        "processing"
    ],
    "wof:name":"Benefits Design Group Inc",
    "wof:placetype":"venue"
},
  "geometry": {"coordinates":[-91.22010899999999,43.893497],"type":"Point"}
}