{
  "type": "Feature",
  "properties": {
    "iso:country":"US",
    "sg:address":"8311 W Howard Ave",
    "sg:city":"Milwaukee",
    "sg:classifiers":[
        {
            "category":"Banks & Credit Unions",
            "subcategory":"Financial Services",
            "type":"Services"
        }
    ],
    "sg:phone":"+1 414 543 9787",
    "sg:postcode":"53220",
    "sg:province":"WI",
    "sg:tags":[
        "investor"
    ],
    "wof:name":"Malich Investments Inc",
    "wof:placetype":"venue"
},
  "geometry": {"coordinates":[-88.017735,42.973654],"type":"Point"}
}