{
  "type": "Feature",
  "properties": {
    "iso:country":"US",
    "sg:address":"710 N Plankinton Ave",
    "sg:city":"Milwaukee",
    "sg:classifiers":[
        {
            "category":"Banks & Credit Unions",
            "subcategory":"Financial Services",
            "type":"Services"
        }
    ],
    "sg:phone":"+1 414 274 2534",
    "sg:postcode":"53203",
    "sg:province":"WI",
    "sg:tags":[
        "company",
        "investment",
        "holding",
        "except"
    ],
    "wof:name":"North Aurora Rlty Holdings Inc",
    "wof:placetype":"venue"
},
  "geometry": {"coordinates":[-87.9123,43.040037],"type":"Point"}
}