{
  "type": "Feature",
  "properties": {
    "iso:country":"US",
    "sg:address":"744 Simonet St",
    "sg:city":"Green Bay",
    "sg:classifiers":[
        {
            "category":"Autos & Motor Vehicles",
            "subcategory":"Automobile Sales",
            "type":"Retail Goods"
        }
    ],
    "sg:phone":"+1 920 437 1330",
    "sg:postcode":"54301",
    "sg:province":"WI",
    "sg:tags":[
        "car",
        "dealer"
    ],
    "wof:name":"Dorsch Ford",
    "wof:placetype":"venue"
},
  "geometry": {"coordinates":[-88.017116,44.466209],"type":"Point"}
}