{
  "type": "Feature",
  "properties": {
    "iso:country":"US",
    "sg:address":"3821 19th Ave",
    "sg:city":"Kenosha",
    "sg:classifiers":[
        {
            "category":"Personal",
            "type":"Services"
        }
    ],
    "sg:phone":"+1 262 914 9140",
    "sg:postcode":"53140",
    "sg:province":"WI",
    "sg:tags":[
        "therapist",
        "massage"
    ],
    "wof:name":"Feather's Touch",
    "wof:placetype":"venue"
},
  "geometry": {"coordinates":[-87.832465,42.60175],"type":"Point"}
}