{
  "type": "Feature",
  "properties": {
    "iso:country":"US",
    "sg:address":"3105 Cedar Rd",
    "sg:city":"Pulaski",
    "sg:classifiers":[
        {
            "category":"Wholesale",
            "subcategory":"Machinery & Supplies",
            "type":"Manufacturing & Wholesale Goods"
        }
    ],
    "sg:phone":"+1 920 822 5145",
    "sg:postcode":"54162",
    "sg:province":"WI",
    "sg:tags":[
        "farm",
        "equipment"
    ],
    "wof:name":"Patz Sales & Svc",
    "wof:placetype":"venue"
},
  "geometry": {"coordinates":[-88.346448,44.710092],"type":"Point"}
}