{
  "type": "Feature",
  "properties": {
    "iso:country":"US",
    "sg:address":"12201 W North Ave",
    "sg:city":"Wauwatosa",
    "sg:classifiers":[
        {
            "category":"Banks & Credit Unions",
            "subcategory":"Bank",
            "type":"Services"
        }
    ],
    "sg:phone":"+1 414 259 9200",
    "sg:postcode":"53226",
    "sg:province":"WI",
    "sg:tags":[
        "loan",
        "real estate"
    ],
    "wof:name":"First Financial Lending",
    "wof:placetype":"venue"
},
  "geometry": {"coordinates":[-88.06551399999999,43.059948],"type":"Point"}
}