{
  "type": "Feature",
  "properties": {
    "addr:full":"4090 Meadow Rd Catawba WI 54515",
    "addr:housenumber":"4090",
    "addr:postcode":"54515",
    "addr:street":"Meadow Rd",
    "iso:country":"US",
    "sg:address":"4090 Meadow Rd",
    "sg:city":"Catawba",
    "sg:classifiers":[
        {
            "category":"Wholesale",
            "subcategory":"Non-durable Goods",
            "type":"Manufacturing & Wholesale Goods"
        }
    ],
    "sg:phone":"+1 715 474 3463",
    "sg:postcode":"54515",
    "sg:province":"WI",
    "wof:name":"Lasee Crafts",
    "wof:placetype":"venue"
},
  "geometry": {"coordinates":[-90.482849,45.520219],"type":"Point"}
}