{
  "type": "Feature",
  "properties": {
    "addr:full":"523 Superior St Antigo WI 54409",
    "addr:housenumber":"523",
    "addr:postcode":"54409",
    "addr:street":"Superior St",
    "iso:country":"US",
    "sg:address":"523 Superior St",
    "sg:city":"Antigo",
    "sg:classifiers":[
        {
            "category":"Restaurant",
            "type":"Food & Drink"
        }
    ],
    "sg:phone":"+1 715 623 5611",
    "sg:postcode":"54409",
    "sg:province":"WI",
    "sg:tags":[
        "drinking",
        "eating"
    ],
    "wof:name":"B B Jacks",
    "wof:placetype":"venue"
},
  "geometry": {"coordinates":[-89.152187,45.140202],"type":"Point"}
}