{
  "type": "Feature",
  "properties": {
    "iso:country":"US",
    "sg:address":"1145 Main St",
    "sg:city":"Stevens Point",
    "sg:classifiers":[
        {
            "category":"Personal",
            "subcategory":"Beauty Salon",
            "type":"Services"
        }
    ],
    "sg:phone":"+1 715 344 4444",
    "sg:postcode":"54481",
    "sg:province":"WI",
    "sg:tags":[
        "shop"
    ],
    "wof:name":"A Cut Above",
    "wof:placetype":"venue"
},
  "geometry": {"coordinates":[-89.58377,44.523332],"type":"Point"}
}