{
  "type": "Feature",
  "properties": {
    "iso:country":"US",
    "sg:address":"890 Elm Grove Rd",
    "sg:city":"Elm Grove",
    "sg:classifiers":[
        {
            "category":"Professional",
            "subcategory":"Business Services",
            "type":"Services"
        },
        {
            "category":"Home & Garden",
            "subcategory":"Home Furnishings",
            "type":"Retail Goods"
        }
    ],
    "sg:phone":"+1 262 797 7883",
    "sg:postcode":"53122",
    "sg:province":"WI",
    "sg:tags":[
        "designer",
        "consultant",
        "retailing",
        "window",
        "design",
        "treatment",
        "interior",
        "decorator",
        "furniture"
    ],
    "wof:name":"Design Resource Center",
    "wof:placetype":"venue"
},
  "geometry": {"coordinates":[-88.078974,43.039592],"type":"Point"}
}