{
  "type": "Feature",
  "properties": {
    "iso:country":"US",
    "sg:address":"1169 N Bequette St",
    "sg:city":"Dodgeville",
    "sg:classifiers":[
        {
            "category":"Restaurant",
            "type":"Food & Drink"
        }
    ],
    "sg:phone":"+1 608 935 2420",
    "sg:postcode":"53533",
    "sg:province":"WI",
    "sg:tags":[
        "eating"
    ],
    "wof:name":"McDonalds",
    "wof:placetype":"venue"
},
  "geometry": {"coordinates":[-90.132775,42.972397],"type":"Point"}
}