{
  "type": "Feature",
  "properties": {
    "iso:country":"US",
    "sg:address":"9395 Tri County Rd",
    "sg:city":"Fremont",
    "sg:classifiers":[
        {
            "category":"Building & Trades",
            "subcategory":"Construction",
            "type":"Services"
        }
    ],
    "sg:phone":"+1 920 446 3769",
    "sg:postcode":"54940",
    "sg:province":"WI",
    "sg:tags":[
        "concrete",
        "contractor"
    ],
    "wof:name":"Wolf River Concrete",
    "wof:placetype":"venue"
},
  "geometry": {"coordinates":[-88.868621,44.242528],"type":"Point"}
}