{
  "type": "Feature",
  "properties": {
    "iso:country":"US",
    "sg:address":"3512 W Fond du Lac Ave",
    "sg:city":"Milwaukee",
    "sg:classifiers":[
        {
            "category":"Personal",
            "subcategory":"Beauty Salon",
            "type":"Services"
        }
    ],
    "sg:phone":"+1 414 447 5615",
    "sg:postcode":"53216",
    "sg:province":"WI",
    "sg:tags":[
        "provides",
        "manicure",
        "pedicure"
    ],
    "wof:name":"Magic Nails",
    "wof:placetype":"venue"
},
  "geometry": {"coordinates":[-87.958348,43.075963],"type":"Point"}
}