{
  "type": "Feature",
  "properties": {
    "iso:country":"US",
    "sg:address":"1226 W Marshall St",
    "sg:city":"Rice Lake",
    "sg:classifiers":[
        {
            "category":"Building & Trades",
            "subcategory":"Construction",
            "type":"Services"
        }
    ],
    "sg:phone":"+1 715 234 1973",
    "sg:postcode":"54868",
    "sg:province":"WI",
    "sg:tags":[
        "splicing",
        "cable"
    ],
    "wof:name":"Push Inc",
    "wof:placetype":"venue"
},
  "geometry": {"coordinates":[-91.75179,45.50455],"type":"Point"}
}