{
  "type": "Feature",
  "properties": {
    "iso:country":"US",
    "sg:address":"615 1st Ave E",
    "sg:city":"Holmen",
    "sg:classifiers":[
        {
            "category":"Professional",
            "type":"Services"
        }
    ],
    "sg:phone":"+1 608 526 9573",
    "sg:postcode":"54636",
    "sg:province":"WI",
    "wof:name":"Jason M Yeiter",
    "wof:placetype":"venue"
},
  "geometry": {"coordinates":[-91.254192,43.959678],"type":"Point"}
}