{
  "type": "Feature",
  "properties": {
    "iso:country":"US",
    "sg:address":"418 E Waterford Ave",
    "sg:city":"Milwaukee",
    "sg:classifiers":[
        {
            "category":"Freight",
            "type":"Transportation"
        }
    ],
    "sg:phone":"+1 414 481 2049",
    "sg:postcode":"53207",
    "sg:province":"WI",
    "sg:tags":[
        "operator",
        "trucking"
    ],
    "wof:name":"Wilinski Enterprises Inc",
    "wof:placetype":"venue"
},
  "geometry": {"coordinates":[-87.904831,42.970159],"type":"Point"}
}