{
  "type": "Feature",
  "properties": {
    "iso:country":"US",
    "sg:address":"3170 Parkside Dr",
    "sg:city":"Brookfield",
    "sg:classifiers":[
        {
            "category":"Real Estate",
            "subcategory":"Real Estate Agent",
            "type":"Services"
        }
    ],
    "sg:phone":"+1 262 781 0371",
    "sg:postcode":"53005",
    "sg:province":"WI",
    "wof:name":"Neustedter Realty",
    "wof:placetype":"venue"
},
  "geometry": {"coordinates":[-88.081097,43.078252],"type":"Point"}
}