{
  "type": "Feature",
  "properties": {
    "iso:country":"US",
    "sg:address":"7818 W Layton Ave",
    "sg:city":"Milwaukee",
    "sg:classifiers":[
        {
            "category":"Health Services",
            "subcategory":"Doctor",
            "type":"Services"
        }
    ],
    "sg:phone":"+1 414 281 1490",
    "sg:postcode":"53220",
    "sg:province":"WI",
    "sg:tags":[
        "medical",
        "imaging"
    ],
    "wof:name":"Open Advanced MRI-Milwaukee",
    "wof:placetype":"venue"
},
  "geometry": {"coordinates":[-88.011151,42.959324],"type":"Point"}
}