{
  "type": "Feature",
  "properties": {
    "iso:country":"US",
    "sg:address":"1349 S 108th St",
    "sg:city":"Milwaukee",
    "sg:classifiers":[
        {
            "category":"Insurance",
            "subcategory":"Insurance Agent",
            "type":"Services"
        }
    ],
    "sg:phone":"+1 414 774 2000",
    "sg:postcode":"53214",
    "sg:province":"WI",
    "wof:name":"Dennis Wurch Insurance Agency",
    "wof:placetype":"venue"
},
  "geometry": {"coordinates":[-88.047106,43.017627],"type":"Point"}
}