{
  "type": "Feature",
  "properties": {
    "iso:country":"US",
    "sg:address":"4088 State Hwy 52",
    "sg:city":"Antigo",
    "sg:classifiers":[
        {
            "category":"Farming",
            "subcategory":"Dairy Farm",
            "type":"Manufacturing & Wholesale Goods"
        }
    ],
    "sg:phone":"+1 715 623 7966",
    "sg:postcode":"54409",
    "sg:province":"WI",
    "wof:name":"Lucky Ash Dairy Farm",
    "wof:placetype":"venue"
},
  "geometry": {"coordinates":[-89.097344,45.173421],"type":"Point"}
}