{
  "type": "Feature",
  "properties": {
    "addr:full":"100 S Mill St West Salem WI 54669",
    "addr:housenumber":"100",
    "addr:postcode":"54669",
    "addr:street":"S Mill St",
    "iso:country":"US",
    "sg:address":"100 S Mill St",
    "sg:city":"West Salem",
    "sg:classifiers":[
        {
            "category":"Government",
            "subcategory":"Fire Station",
            "type":"Public Place"
        }
    ],
    "sg:phone":"+1 608 786 0111",
    "sg:postcode":"54669",
    "sg:province":"WI",
    "sg:tags":[
        "department"
    ],
    "wof:name":"West Salem Fire Dept",
    "wof:placetype":"venue"
},
  "geometry": {"coordinates":[-91.07991,43.896996],"type":"Point"}
}