{
  "type": "Feature",
  "properties": {
    "iso:country":"US",
    "sg:address":"610 N Water St",
    "sg:city":"Milwaukee",
    "sg:classifiers":[
        {
            "category":"Wholesale",
            "subcategory":"Music Publishers",
            "type":"Manufacturing & Wholesale Goods"
        }
    ],
    "sg:phone":"+1 414 409 7815",
    "sg:postcode":"53202",
    "sg:province":"WI",
    "sg:tags":[
        "distribution"
    ],
    "wof:name":"Southwind Music Inc DBA Weasel Records",
    "wof:placetype":"venue"
},
  "geometry": {"coordinates":[-87.908964,43.037518],"type":"Point"}
}