{
  "type": "Feature",
  "properties": {
    "iso:country":"US",
    "sg:address":"214 Church St",
    "sg:city":"St Nazianz",
    "sg:classifiers":[
        {
            "category":"Organizations",
            "subcategory":"Religious Organization",
            "type":"Services"
        }
    ],
    "sg:phone":"+1 920 773 2511",
    "sg:postcode":"54232",
    "sg:province":"WI",
    "sg:tags":[
        "church"
    ],
    "wof:name":"St Gregory Parish Rectory",
    "wof:placetype":"venue"
},
  "geometry": {"coordinates":[-87.925816,44.005166],"type":"Point"}
}