{
  "type": "Feature",
  "properties": {
    "iso:country":"US",
    "sg:address":"10976 Railroad Rd",
    "sg:city":"Merrillan",
    "sg:classifiers":[
        {
            "category":"Professional",
            "type":"Services"
        }
    ],
    "sg:phone":"+1 715 333 8693",
    "sg:postcode":"54754",
    "sg:province":"WI",
    "wof:name":"Cs Services",
    "wof:placetype":"venue"
},
  "geometry": {"coordinates":[-90.86212,44.449889],"type":"Point"}
}