{
  "type": "Feature",
  "properties": {
    "iso:country":"US",
    "sg:address":"9149 State Hwy 57",
    "sg:city":"Luxemburg",
    "sg:classifiers":[
        {
            "category":"Retail",
            "subcategory":"Portrait Studio",
            "type":"Services"
        }
    ],
    "sg:phone":"+1 920 866 9589",
    "sg:postcode":"54217",
    "sg:province":"WI",
    "sg:tags":[
        "photographer"
    ],
    "wof:name":"Glamour Shot A",
    "wof:placetype":"venue"
},
  "geometry": {"coordinates":[-87.749807,44.654736],"type":"Point"}
}