{
  "type": "Feature",
  "properties": {
    "addr:full":"550 Gannon Rd Lodi WI 53555",
    "addr:housenumber":"550",
    "addr:postcode":"53555",
    "addr:street":"Gannon Rd",
    "iso:country":"US",
    "sg:address":"550 Gannon Rd",
    "sg:city":"Lodi",
    "sg:classifiers":[
        {
            "category":"Building & Trades",
            "subcategory":"Construction",
            "type":"Services"
        }
    ],
    "sg:phone":"+1 608 592 4313",
    "sg:postcode":"53555",
    "sg:province":"WI",
    "sg:tags":[
        "contractor"
    ],
    "wof:name":"Eberts Home Improvment",
    "wof:placetype":"venue"
},
  "geometry": {"coordinates":[-89.62944899999999,43.296449],"type":"Point"}
}