{
  "type": "Feature",
  "properties": {
    "addr:full":"415 E 3rd St Washburn WI 54891",
    "addr:housenumber":"415",
    "addr:postcode":"54891",
    "addr:street":"E 3Rd St",
    "iso:country":"US",
    "sg:address":"415 E 3rd St",
    "sg:city":"Washburn",
    "sg:classifiers":[
        {
            "category":"Restaurant",
            "type":"Food & Drink"
        }
    ],
    "sg:phone":"+1 715 373 5644",
    "sg:postcode":"54891",
    "sg:province":"WI",
    "wof:name":"Travelers",
    "wof:placetype":"venue"
},
  "geometry": {"coordinates":[-90.88539299999999,46.678057],"type":"Point"}
}