{
  "type": "Feature",
  "properties": {
    "iso:country":"US",
    "sg:address":"303 Cardinal Cir",
    "sg:city":"Mayville",
    "sg:classifiers":[
        {
            "category":"Insurance",
            "subcategory":"Insurance Agent",
            "type":"Services"
        }
    ],
    "sg:phone":"+1 920 387 1486",
    "sg:postcode":"53050",
    "sg:province":"WI",
    "wof:name":"State Farm Insurance",
    "wof:placetype":"venue"
},
  "geometry": {"coordinates":[-88.566565,43.499021],"type":"Point"}
}