{
  "type": "Feature",
  "properties": {
    "iso:country":"US",
    "sg:address":"566 Redbird Cir",
    "sg:city":"De Pere",
    "sg:classifiers":[
        {
            "category":"Organizations",
            "subcategory":"Religious Organization",
            "type":"Services"
        }
    ],
    "sg:phone":"+1 920 336 7418",
    "sg:postcode":"54115",
    "sg:province":"WI",
    "sg:tags":[
        "church"
    ],
    "wof:name":"Journey Community Church",
    "wof:placetype":"venue"
},
  "geometry": {"coordinates":[-88.037195,44.438208],"type":"Point"}
}