{
  "type": "Feature",
  "properties": {
    "iso:country":"US",
    "sg:address":"1027 Main St",
    "sg:city":"Union Grove",
    "sg:classifiers":[
        {
            "category":"Restaurant",
            "type":"Food & Drink"
        }
    ],
    "sg:phone":"+1 262 878 1150",
    "sg:postcode":"53182",
    "sg:province":"WI",
    "sg:tags":[
        "eating"
    ],
    "wof:name":"Callen S Restaurant",
    "wof:placetype":"venue"
},
  "geometry": {"coordinates":[-88.051802,42.687331],"type":"Point"}
}