{
  "type": "Feature",
  "properties": {
    "iso:country":"US",
    "sg:address":"626 N Bend Dr",
    "sg:city":"Melrose",
    "sg:classifiers":[
        {
            "category":"Retail",
            "subcategory":"Repair Shop",
            "type":"Services"
        }
    ],
    "sg:phone":"+1 608 488 6596",
    "sg:postcode":"54642",
    "sg:province":"WI",
    "sg:tags":[
        "farm",
        "equipment",
        "parts",
        "machinery"
    ],
    "wof:name":"North Bend Automotive Center",
    "wof:placetype":"venue"
},
  "geometry": {"coordinates":[-91.120995,44.089098],"type":"Point"}
}