{
  "type": "Feature",
  "properties": {
    "iso:country":"US",
    "sg:address":"4510 Stonefield Cir",
    "sg:city":"Sheboygan",
    "sg:classifiers":[
        {
            "category":"Professional",
            "type":"Services"
        }
    ],
    "sg:phone":"+1 920 208 7021",
    "sg:postcode":"53083",
    "sg:province":"WI",
    "wof:name":"Quilted Line",
    "wof:placetype":"venue"
},
  "geometry": {"coordinates":[-87.76663,43.77831],"type":"Point"}
}