{
  "type": "Feature",
  "properties": {
    "iso:country":"US",
    "sg:address":"217 N Main St",
    "sg:city":"Marion",
    "sg:classifiers":[
        {
            "category":"Government",
            "subcategory":"Office",
            "type":"Public Place"
        }
    ],
    "sg:phone":"+1 715 754 4611",
    "sg:postcode":"54950",
    "sg:province":"WI",
    "sg:tags":[
        "village"
    ],
    "wof:name":"Marion City Building Inspector",
    "wof:placetype":"venue"
},
  "geometry": {"coordinates":[-88.888706,44.672171],"type":"Point"}
}