{
  "type": "Feature",
  "properties": {
    "iso:country":"US",
    "sg:address":"21716 W Good Hope Rd",
    "sg:city":"Lannon",
    "sg:classifiers":[
        {
            "category":"Freight",
            "type":"Transportation"
        }
    ],
    "sg:phone":"+1 262 251 1159",
    "sg:postcode":"53046",
    "sg:province":"WI",
    "sg:tags":[
        "operator",
        "construction",
        "local",
        "trucking"
    ],
    "wof:name":"Tremmel Mike Trckg & Grading",
    "wof:placetype":"venue"
},
  "geometry": {"coordinates":[-88.17895300000001,43.148259],"type":"Point"}
}