{
  "type": "Feature",
  "properties": {
    "iso:country":"US",
    "sg:address":"2313 W 5th St",
    "sg:city":"Marshfield",
    "sg:classifiers":[
        {
            "category":"Real Estate",
            "subcategory":"Real Estate Operator",
            "type":"Services"
        }
    ],
    "sg:phone":"+1 715 387 8294",
    "sg:postcode":"54449",
    "sg:province":"WI",
    "sg:tags":[
        "apartment"
    ],
    "wof:name":"A A Affordable Apartments",
    "wof:placetype":"venue"
},
  "geometry": {"coordinates":[-90.20678,44.666505],"type":"Point"}
}