{
  "type": "Feature",
  "properties": {
    "addr:full":"1007 Monitor St La Crosse WI 54603",
    "addr:housenumber":"1007",
    "addr:postcode":"54603",
    "addr:street":"Monitor St",
    "iso:country":"US",
    "sg:address":"1007 Monitor St",
    "sg:city":"La Crosse",
    "sg:classifiers":[
        {
            "category":"Wholesale",
            "subcategory":"Machinery & Supplies",
            "type":"Manufacturing & Wholesale Goods"
        }
    ],
    "sg:phone":"+1 608 784 6228",
    "sg:postcode":"54603",
    "sg:province":"WI",
    "sg:tags":[
        "equipment",
        "industrial"
    ],
    "sg:website":"www.airgas.com",
    "wof:name":"Airgas",
    "wof:placetype":"venue"
},
  "geometry": {"coordinates":[-91.239786,43.82988],"type":"Point"}
}