{
  "type": "Feature",
  "properties": {
    "iso:country":"US",
    "sg:address":"71 Debbie Ln",
    "sg:city":"Holmen",
    "sg:classifiers":[
        {
            "category":"Shopping",
            "subcategory":"Catalog Store",
            "type":"Retail Goods"
        }
    ],
    "sg:phone":"+1 608 779 5606",
    "sg:postcode":"54636",
    "sg:province":"WI",
    "sg:tags":[
        "mail",
        "house"
    ],
    "wof:name":"This Dogg Hunts",
    "wof:placetype":"venue"
},
  "geometry": {"coordinates":[-91.248031,43.926042],"type":"Point"}
}