{
  "type": "Feature",
  "properties": {
    "addr:full":"515 22nd Ave Monroe WI 53566",
    "addr:housenumber":"515",
    "addr:postcode":"53566",
    "addr:street":"22Nd Ave",
    "iso:country":"US",
    "sg:address":"515 22nd Ave",
    "sg:city":"Monroe",
    "sg:classifiers":[
        {
            "category":"Health Services",
            "subcategory":"Doctor",
            "type":"Services"
        }
    ],
    "sg:phone":"+1 608 324 2204",
    "sg:postcode":"53566",
    "sg:province":"WI",
    "sg:tags":[
        "physician",
        "family",
        "practice",
        "surgeons",
        "medicine",
        "surgeon"
    ],
    "wof:name":"Levin James Md",
    "wof:placetype":"venue"
},
  "geometry": {"coordinates":[-89.632603,42.607456],"type":"Point"}
}