{
  "type": "Feature",
  "properties": {
    "iso:country":"US",
    "sg:address":"5922 W Burnham St",
    "sg:city":"Milwaukee",
    "sg:classifiers":[
        {
            "category":"Shopping",
            "subcategory":"Department Store",
            "type":"Retail Goods"
        }
    ],
    "sg:phone":"+1 414 604 1699",
    "sg:postcode":"53219",
    "sg:province":"WI",
    "wof:name":"This & That",
    "wof:placetype":"venue"
},
  "geometry": {"coordinates":[-87.987124,43.010255],"type":"Point"}
}