{
  "type": "Feature",
  "properties": {
    "iso:country":"US",
    "sg:address":"5450 S 124th St",
    "sg:city":"Hales Corners",
    "sg:classifiers":[
        {
            "category":"Retail",
            "subcategory":"Repair Shop",
            "type":"Services"
        }
    ],
    "sg:phone":"+1 414 525 4144",
    "sg:postcode":"53130",
    "sg:province":"WI",
    "wof:name":"Pro Billiard Co",
    "wof:placetype":"venue"
},
  "geometry": {"coordinates":[-88.069303,42.945364],"type":"Point"}
}