{
  "type": "Feature",
  "properties": {
    "iso:country":"US",
    "sg:address":"5088 370th Ave",
    "sg:city":"Menomonie",
    "sg:classifiers":[
        {
            "category":"Building & Trades",
            "subcategory":"Construction",
            "type":"Services"
        }
    ],
    "sg:phone":"+1 715 235 7966",
    "sg:postcode":"54751",
    "sg:province":"WI",
    "sg:tags":[
        "residential"
    ],
    "wof:name":"Lb Construction",
    "wof:placetype":"venue"
},
  "geometry": {"coordinates":[-91.90423199999999,44.814589],"type":"Point"}
}