{
  "type": "Feature",
  "properties": {
    "iso:country":"US",
    "sg:address":"13498 Springdale Dr",
    "sg:city":"Viola",
    "sg:phone":"+1 608 627 1982",
    "sg:postcode":"54664",
    "sg:province":"WI",
    "sg:tags":[
        "farm",
        "grain",
        "cash"
    ],
    "wof:name":"Y Rockin Ranch Inc",
    "wof:placetype":"venue"
},
  "geometry": {"coordinates":[-90.594523,43.502801],"type":"Point"}
}