{
  "type": "Feature",
  "properties": {
    "iso:country":"US",
    "sg:address":"S2876 Stellner Ln",
    "sg:city":"Viroqua",
    "sg:classifiers":[
        {
            "category":"Autos & Motor Vehicles",
            "subcategory":"Auto Supplies",
            "type":"Retail Goods"
        }
    ],
    "sg:phone":"+1 608 483 2900",
    "sg:postcode":"54665",
    "sg:province":"WI",
    "sg:tags":[
        "automobile",
        "part",
        "tire"
    ],
    "wof:name":"Hubcaps Rims & More",
    "wof:placetype":"venue"
},
  "geometry": {"coordinates":[-91.06913,43.62402],"type":"Point"}
}