{
  "type": "Feature",
  "properties": {
    "addr:full":"155 E 4th St New Richmond WI 54017",
    "addr:housenumber":"155",
    "addr:postcode":"54017",
    "addr:street":"E 4Th St",
    "iso:country":"US",
    "sg:address":"155 E 4th St",
    "sg:city":"New Richmond",
    "sg:classifiers":[
        {
            "category":"Organizations",
            "subcategory":"Community Association",
            "type":"Services"
        }
    ],
    "sg:phone":"+1 715 246 2744",
    "sg:postcode":"54017",
    "sg:province":"WI",
    "sg:tags":[
        "fraternal"
    ],
    "wof:name":"Knights Of Columbus",
    "wof:placetype":"venue"
},
  "geometry": {"coordinates":[-92.53683700000001,45.119449],"type":"Point"}
}