{
  "type": "Feature",
  "properties": {
    "iso:country":"US",
    "sg:address":"4096 Kropp Rd",
    "sg:city":"Black Creek",
    "sg:classifiers":[
        {
            "category":"Building & Trades",
            "subcategory":"Construction",
            "type":"Services"
        }
    ],
    "sg:phone":"+1 920 833 6595",
    "sg:postcode":"54106",
    "sg:province":"WI",
    "sg:tags":[
        "contractor"
    ],
    "wof:name":"Manka Drywall",
    "wof:placetype":"venue"
},
  "geometry": {"coordinates":[-88.39297,44.472981],"type":"Point"}
}