{
  "type": "Feature",
  "properties": {
    "iso:country":"US",
    "sg:address":"1135 S 70th St",
    "sg:city":"Milwaukee",
    "sg:classifiers":[
        {
            "category":"Education",
            "subcategory":"College",
            "type":"Public Place"
        }
    ],
    "sg:phone":"+1 414 476 6565",
    "sg:postcode":"53214",
    "sg:province":"WI",
    "sg:tags":[
        "academic",
        "school"
    ],
    "wof:name":"Lakeland College-Milwaukee",
    "wof:placetype":"venue"
},
  "geometry": {"coordinates":[-88.000091,43.018871],"type":"Point"}
}