{
  "type": "Feature",
  "properties": {
    "iso:country":"US",
    "sg:address":"13750 State Hwy 121",
    "sg:city":"Alma Center",
    "sg:classifiers":[
        {
            "category":"Government",
            "subcategory":"Office",
            "type":"Public Place"
        }
    ],
    "sg:phone":"+1 715 964 6410",
    "sg:postcode":"54611",
    "sg:province":"WI",
    "sg:tags":[
        "village"
    ],
    "wof:name":"Garden Valley Township",
    "wof:placetype":"venue"
},
  "geometry": {"coordinates":[-90.998535,44.439015],"type":"Point"}
}