{
  "type": "Feature",
  "properties": {
    "iso:country":"US",
    "sg:address":"8313 Murphy Dr",
    "sg:city":"Middleton",
    "sg:classifiers":[
        {
            "category":"Restaurant",
            "type":"Food & Drink"
        }
    ],
    "sg:menulink":"http://www.allmenus.com/wi/middleton/35974-applebees/menu/",
    "sg:phone":"+1 608 827 0556",
    "sg:postcode":"53562",
    "sg:province":"WI",
    "sg:tags":[
        "burger",
        "american",
        "sandwich",
        "soup"
    ],
    "wof:name":"Applebee's",
    "wof:placetype":"venue"
},
  "geometry": {"coordinates":[-89.524963,43.098475],"type":"Point"}
}