{
  "type": "Feature",
  "properties": {
    "iso:country":"US",
    "sg:address":"632 School St",
    "sg:city":"Kohler",
    "sg:classifiers":[
        {
            "category":"Professional",
            "subcategory":"Management & Consulting",
            "type":"Services"
        }
    ],
    "sg:phone":"+1 920 457 6393",
    "sg:postcode":"53044",
    "sg:province":"WI",
    "sg:tags":[
        "business"
    ],
    "wof:name":"Atkins Associates",
    "wof:placetype":"venue"
},
  "geometry": {"coordinates":[-87.79373,43.734443],"type":"Point"}
}