{
  "type": "Feature",
  "properties": {
    "iso:country":"US",
    "sg:address":"32200 45th St",
    "sg:city":"Burlington",
    "sg:classifiers":[
        {
            "category":"Home & Garden",
            "subcategory":"Mobile Homes",
            "type":"Retail Goods"
        }
    ],
    "sg:phone":"+1 262 537 2314",
    "sg:postcode":"53105",
    "sg:province":"WI",
    "sg:tags":[
        "operator",
        "site"
    ],
    "wof:name":"Wheatland Mobile Home Park",
    "wof:placetype":"venue"
},
  "geometry": {"coordinates":[-88.198099,42.596959],"type":"Point"}
}