{
  "type": "Feature",
  "properties": {
    "addr:full":"7441 W Greenfield Ave Milwaukee WI 53214",
    "addr:housenumber":"7441",
    "addr:postcode":"53214",
    "addr:street":"W Greenfield Ave",
    "iso:country":"US",
    "sg:address":"7441 W Greenfield Ave",
    "sg:city":"Milwaukee",
    "sg:classifiers":[
        {
            "category":"Social Services",
            "type":"Services"
        }
    ],
    "sg:phone":"+1 414 259 0640",
    "sg:postcode":"53214",
    "sg:province":"WI",
    "sg:tags":[
        "loss",
        "clinic",
        "weight"
    ],
    "wof:name":"Area Intergroup",
    "wof:placetype":"venue"
},
  "geometry": {"coordinates":[-88.00559699999999,43.016563],"type":"Point"}
}