{
  "type": "Feature",
  "properties": {
    "iso:country":"US",
    "sg:address":"525 Airport Dr",
    "sg:city":"Oneida",
    "sg:classifiers":[
        {
            "category":"Government",
            "subcategory":"Office",
            "type":"Public Place"
        }
    ],
    "sg:phone":"+1 920 869 2711",
    "sg:postcode":"54155",
    "sg:province":"WI",
    "wof:name":"Oneida Health Ctr",
    "wof:placetype":"venue"
},
  "geometry": {"coordinates":[-88.16919,44.498441],"type":"Point"}
}