{
  "type": "Feature",
  "properties": {
    "addr:full":"19100 W Capitol Dr Brookfield WI 53045",
    "addr:housenumber":"19100",
    "addr:postcode":"53045",
    "addr:street":"W Capitol Dr",
    "iso:country":"US",
    "sg:address":"19100 W Capitol Dr",
    "sg:city":"Brookfield",
    "sg:classifiers":[
        {
            "category":"Autos & Motor Vehicles",
            "subcategory":"Automobile Sales",
            "type":"Retail Goods"
        }
    ],
    "sg:phone":"+1 866 796 3685",
    "sg:postcode":"53045",
    "sg:province":"WI",
    "sg:tags":[
        "new",
        "car"
    ],
    "sg:website":"http://www.1dodgecity.com",
    "wof:name":"Dodge City Chrysler Jeep",
    "wof:placetype":"venue"
},
  "geometry": {"coordinates":[-88.15013500000001,43.090655],"type":"Point"}
}