{
  "type": "Feature",
  "properties": {
    "iso:country":"US",
    "sg:address":"7525 W Greenfield Ave",
    "sg:city":"Milwaukee",
    "sg:classifiers":[
        {
            "category":"Government",
            "subcategory":"Court House",
            "type":"Public Place"
        }
    ],
    "sg:phone":"+1 414 302 8450",
    "sg:postcode":"53214",
    "sg:province":"WI",
    "sg:tags":[
        "city",
        "counsel"
    ],
    "wof:name":"West Allis Attorney",
    "wof:placetype":"venue"
},
  "geometry": {"coordinates":[-88.00691999999999,43.016553],"type":"Point"}
}