{
  "type": "Feature",
  "properties": {
    "iso:country":"US",
    "sg:address":"160 S Brooke St",
    "sg:city":"Fond Du Lac",
    "sg:classifiers":[
        {
            "category":"Building & Trades",
            "subcategory":"Plumbing",
            "type":"Services"
        }
    ],
    "sg:phone":"+1 920 923 2500",
    "sg:postcode":"54935",
    "sg:province":"WI",
    "sg:tags":[
        "heating",
        "contractor"
    ],
    "wof:name":"Wesley Heating & Cooling Inc",
    "wof:placetype":"venue"
},
  "geometry": {"coordinates":[-88.454534,43.775009],"type":"Point"}
}