{
  "type": "Feature",
  "properties": {
    "addr:full":"132 E Wisconsin Ave Oconomowoc WI 53066",
    "addr:housenumber":"132",
    "addr:postcode":"53066",
    "addr:street":"E Wisconsin Ave",
    "iso:country":"US",
    "sg:address":"132 E Wisconsin Ave",
    "sg:city":"Oconomowoc",
    "sg:classifiers":[
        {
            "category":"Home & Garden",
            "subcategory":"Garden Supply",
            "type":"Retail Goods"
        }
    ],
    "sg:phone":"+1 262 567 6664",
    "sg:postcode":"53066",
    "sg:province":"WI",
    "sg:tags":[
        "pet"
    ],
    "wof:name":"May Garden Ctr",
    "wof:placetype":"venue"
},
  "geometry": {"coordinates":[-88.497688,43.110858],"type":"Point"}
}