{
  "type": "Feature",
  "properties": {
    "iso:country":"US",
    "sg:address":"1357 Green Bay Rd",
    "sg:city":"Sturgeon Bay",
    "sg:classifiers":[
        {
            "category":"Retail",
            "subcategory":"Auto Repair",
            "type":"Services"
        }
    ],
    "sg:phone":"+1 920 743 6094",
    "sg:postcode":"54235",
    "sg:province":"WI",
    "sg:tags":[
        "engine",
        "crankshaft",
        "grinding"
    ],
    "wof:name":"Engine Rebuilding Service",
    "wof:placetype":"venue"
},
  "geometry": {"coordinates":[-87.40116500000001,44.8207],"type":"Point"}
}