{
  "type": "Feature",
  "properties": {
    "addr:full":"13143 30th Ave Chippewa Falls WI 54729",
    "addr:housenumber":"13143",
    "addr:postcode":"54729",
    "addr:street":"30Th Ave",
    "iso:country":"US",
    "sg:address":"13143 30th Ave",
    "sg:city":"Chippewa Falls",
    "sg:classifiers":[
        {
            "category":"Government",
            "subcategory":"Fire Station",
            "type":"Public Place"
        }
    ],
    "sg:phone":"+1 715 723 5488",
    "sg:postcode":"54729",
    "sg:province":"WI",
    "sg:tags":[
        "department"
    ],
    "wof:name":"Chippewa Fire Protection Dist",
    "wof:placetype":"venue"
},
  "geometry": {"coordinates":[-91.404811,44.886197],"type":"Point"}
}