{
  "type": "Feature",
  "properties": {
    "iso:country":"US",
    "sg:address":"101 Grand Ave",
    "sg:city":"Wausau",
    "sg:classifiers":[
        {
            "category":"Insurance",
            "subcategory":"Insurance Agent",
            "type":"Services"
        }
    ],
    "sg:phone":"+1 715 848 5424",
    "sg:postcode":"54403",
    "sg:province":"WI",
    "wof:name":"Insurance Associates",
    "wof:placetype":"venue"
},
  "geometry": {"coordinates":[-89.62451,44.956258],"type":"Point"}
}