{
  "type": "Feature",
  "properties": {
    "iso:country":"US",
    "sg:address":"25 E Towne Mall",
    "sg:city":"Madison",
    "sg:classifiers":[
        {
            "category":"Food & Beverages",
            "subcategory":"Bakery",
            "type":"Retail Goods"
        },
        {
            "category":"Restaurant",
            "type":"Food & Drink"
        }
    ],
    "sg:phone":"+1 608 244 2232",
    "sg:postcode":"53704",
    "sg:province":"WI",
    "wof:name":"Cinnabon",
    "wof:placetype":"venue"
},
  "geometry": {"coordinates":[-89.30428499999999,43.127959],"type":"Point"}
}