{
  "type": "Feature",
  "properties": {
    "iso:country":"US",
    "sg:address":"345 Co Rd A",
    "sg:city":"Oxford",
    "sg:classifiers":[
        {
            "category":"Bars & Pubs",
            "type":"Food & Drink"
        }
    ],
    "sg:phone":"+1 608 584 5211",
    "sg:postcode":"53952",
    "sg:province":"WI",
    "sg:tags":[
        "drinking"
    ],
    "wof:name":"Brooks Pub",
    "wof:placetype":"venue"
},
  "geometry": {"coordinates":[-89.638846,43.825276],"type":"Point"}
}