{
  "type": "Feature",
  "properties": {
    "iso:country":"US",
    "sg:address":"117 E Main St",
    "sg:city":"Madison",
    "sg:classifiers":[
        {
            "category":"Bars & Pubs",
            "type":"Food & Drink"
        }
    ],
    "sg:phone":"+1 608 294 9371",
    "sg:postcode":"53703",
    "sg:province":"WI",
    "wof:name":"Maduro",
    "wof:placetype":"venue"
},
  "geometry": {"coordinates":[-89.381047,43.075134],"type":"Point"}
}