{
  "type": "Feature",
  "properties": {
    "iso:country":"US",
    "sg:address":"250 Swarthout Rd",
    "sg:city":"Fall River",
    "sg:classifiers":[
        {
            "category":"Manufacturing",
            "subcategory":"Metals",
            "type":"Manufacturing & Wholesale Goods"
        },
        {
            "category":"Building & Trades",
            "subcategory":"Construction",
            "type":"Services"
        }
    ],
    "sg:phone":"+1 920 484 6401",
    "sg:postcode":"53932",
    "sg:province":"WI",
    "sg:tags":[
        "steel",
        "contractor"
    ],
    "wof:name":"Sheet Metal Specialties Inc",
    "wof:placetype":"venue"
},
  "geometry": {"coordinates":[-89.064618,43.380961],"type":"Point"}
}