{
  "type": "Feature",
  "properties": {
    "iso:country":"US",
    "sg:address":"2105 N 58th St",
    "sg:city":"Superior",
    "sg:classifiers":[
        {
            "category":"Retail",
            "subcategory":"Repair Shop",
            "type":"Services"
        }
    ],
    "sg:phone":"+1 715 392 2215",
    "sg:postcode":"54880",
    "sg:province":"WI",
    "sg:tags":[
        "related"
    ],
    "wof:name":"General Electric Rail Car Rpr",
    "wof:placetype":"venue"
},
  "geometry": {"coordinates":[-92.108498,46.669561],"type":"Point"}
}