{
  "type": "Feature",
  "properties": {
    "iso:country":"US",
    "sg:address":"8754 Gohr Rd",
    "sg:city":"Krakow",
    "sg:classifiers":[
        {
            "category":"Farming",
            "subcategory":"Dairy Farm",
            "type":"Manufacturing & Wholesale Goods"
        }
    ],
    "sg:phone":"+1 920 899 3884",
    "sg:postcode":"54137",
    "sg:province":"WI",
    "wof:name":"Calvin Gohr",
    "wof:placetype":"venue"
},
  "geometry": {"coordinates":[-88.203649,44.751981],"type":"Point"}
}