{
  "type": "Feature",
  "properties": {
    "iso:country":"US",
    "sg:address":"397 Man Cal Rd",
    "sg:city":"Brillion",
    "sg:classifiers":[
        {
            "category":"Farming",
            "subcategory":"Dairy Farm",
            "type":"Manufacturing & Wholesale Goods"
        }
    ],
    "sg:phone":"+1 920 864 2735",
    "sg:postcode":"54110",
    "sg:province":"WI",
    "wof:name":"Homestead Dairy",
    "wof:placetype":"venue"
},
  "geometry": {"coordinates":[-88.061395,44.240972],"type":"Point"}
}