{
  "type": "Feature",
  "properties": {
    "addr:full":"2000 Lathrop Ave Racine WI 53405",
    "addr:housenumber":"2000",
    "addr:postcode":"53405",
    "addr:street":"Lathrop Ave",
    "iso:country":"US",
    "sg:address":"2000 Lathrop Ave",
    "sg:city":"Racine",
    "sg:classifiers":[
        {
            "category":"Retail",
            "subcategory":"Repair Shop",
            "type":"Services"
        }
    ],
    "sg:phone":"+1 262 633 7044",
    "sg:postcode":"53405",
    "sg:province":"WI",
    "wof:name":"A & A Door Lock Service Inc",
    "wof:placetype":"venue"
},
  "geometry": {"coordinates":[-87.82597199999999,42.704125],"type":"Point"}
}