{
  "type": "Feature",
  "properties": {
    "iso:country":"US",
    "sg:address":"1811 Okeefe Rd",
    "sg:city":"Hudson",
    "sg:classifiers":[
        {
            "category":"Building & Trades",
            "subcategory":"Construction",
            "type":"Services"
        }
    ],
    "sg:phone":"+1 715 386 2275",
    "sg:postcode":"54016",
    "sg:province":"WI",
    "sg:tags":[
        "mobile",
        "home"
    ],
    "wof:name":"Thomas Mobile Home Svc",
    "wof:placetype":"venue"
},
  "geometry": {"coordinates":[-92.731269,44.945102],"type":"Point"}
}