{
  "type": "Feature",
  "properties": {
    "addr:full":"2311 E Main St Merrill WI 54452",
    "addr:housenumber":"2311",
    "addr:postcode":"54452",
    "addr:street":"E Main St",
    "iso:country":"US",
    "sg:address":"2311 E Main St",
    "sg:city":"Merrill",
    "sg:classifiers":[
        {
            "category":"Autos & Motor Vehicles",
            "subcategory":"Fuel & Gas Station",
            "type":"Retail Goods"
        }
    ],
    "sg:phone":"+1 715 536 1819",
    "sg:postcode":"54452",
    "sg:province":"WI",
    "sg:tags":[
        "grocery",
        "station",
        "gasoline"
    ],
    "sg:website":"www.kwiktrip.com",
    "wof:name":"KWIK Trip",
    "wof:placetype":"venue"
},
  "geometry": {"coordinates":[-89.66832100000001,45.180688],"type":"Point"}
}