{
  "type": "Feature",
  "properties": {
    "addr:full":"1058 Matheson St Janesville WI 53545",
    "addr:housenumber":"1058",
    "addr:postcode":"53545",
    "addr:street":"Matheson St",
    "iso:country":"US",
    "sg:address":"1058 Matheson St",
    "sg:city":"Janesville",
    "sg:classifiers":[
        {
            "category":"Building & Trades",
            "subcategory":"Plumbing",
            "type":"Services"
        }
    ],
    "sg:phone":"+1 608 754 3484",
    "sg:postcode":"53545",
    "sg:province":"WI",
    "sg:tags":[
        "water",
        "plumbing",
        "hot",
        "heating",
        "contractor"
    ],
    "wof:name":"Lenz Plumbing & Heating Inc",
    "wof:placetype":"venue"
},
  "geometry": {"coordinates":[-89.01035400000001,42.699538],"type":"Point"}
}