{
  "type": "Feature",
  "properties": {
    "iso:country":"US",
    "sg:address":"16620 W Bluemound Rd",
    "sg:city":"Brookfield",
    "sg:classifiers":[
        {
            "category":"Insurance",
            "subcategory":"Insurance Agent",
            "type":"Services"
        }
    ],
    "sg:phone":"+1 262 780 4880",
    "sg:postcode":"53005",
    "sg:province":"WI",
    "wof:name":"Medical Protective Co-Fort",
    "wof:placetype":"venue"
},
  "geometry": {"coordinates":[-88.117649,43.036515],"type":"Point"}
}