{
  "type": "Feature",
  "properties": {
    "iso:country":"US",
    "sg:address":"1397 S Park Ave",
    "sg:city":"Neenah",
    "sg:classifiers":[
        {
            "category":"Health Services",
            "subcategory":"Doctor",
            "type":"Services"
        }
    ],
    "sg:phone":"+1 920 722 4222",
    "sg:postcode":"54956",
    "sg:province":"WI",
    "sg:tags":[
        "physician",
        "surgeon"
    ],
    "wof:name":"Neonatal Associates-Wisconsin",
    "wof:placetype":"venue"
},
  "geometry": {"coordinates":[-88.451872,44.160602],"type":"Point"}
}