{
  "type": "Feature",
  "properties": {
    "iso:country":"US",
    "sg:address":"6812 S 112th St",
    "sg:city":"Franklin",
    "sg:classifiers":[
        {
            "category":"Manufacturing",
            "subcategory":"Printing",
            "type":"Manufacturing & Wholesale Goods"
        }
    ],
    "sg:phone":"+1 414 427 8833",
    "sg:postcode":"53132",
    "sg:province":"WI",
    "sg:website":"www.flexprepress.com",
    "wof:name":"Flex Prepress",
    "wof:placetype":"venue"
},
  "geometry": {"coordinates":[-88.053362,42.920896],"type":"Point"}
}