{
  "type": "Feature",
  "properties": {
    "iso:country":"US",
    "sg:address":"2329 Sims Ave",
    "sg:city":"Stevens Point",
    "sg:classifiers":[
        {
            "category":"Building & Trades",
            "subcategory":"Construction",
            "type":"Services"
        }
    ],
    "sg:phone":"+1 715 341 1926",
    "sg:postcode":"54481",
    "sg:province":"WI",
    "sg:tags":[
        "hanging",
        "house",
        "c",
        "general",
        "contractor"
    ],
    "wof:name":"Spielman Construction",
    "wof:placetype":"venue"
},
  "geometry": {"coordinates":[-89.565856,44.52515],"type":"Point"}
}