{
  "type": "Feature",
  "properties": {
    "iso:country":"US",
    "sg:address":"202 Valorie Ln",
    "sg:city":"Monona",
    "sg:classifiers":[
        {
            "category":"Real Estate",
            "subcategory":"Real Estate Operator",
            "type":"Services"
        }
    ],
    "sg:phone":"+1 608 222 1186",
    "sg:postcode":"53716",
    "sg:province":"WI",
    "sg:tags":[
        "building",
        "apartment"
    ],
    "wof:name":"Monona Village Apartments",
    "wof:placetype":"venue"
},
  "geometry": {"coordinates":[-89.32840400000001,43.06328],"type":"Point"}
}