{
  "type": "Feature",
  "properties": {
    "addr:full":"130 N 4th Ave Sturgeon Bay WI 54235",
    "addr:housenumber":"130",
    "addr:postcode":"54235",
    "addr:street":"N 4Th Ave",
    "iso:country":"US",
    "sg:address":"130 N 4th Ave",
    "sg:city":"Sturgeon Bay",
    "sg:classifiers":[
        {
            "category":"Professional",
            "subcategory":"Printing & Photocopies",
            "type":"Services"
        },
        {
            "category":"Manufacturing",
            "subcategory":"Printing",
            "type":"Manufacturing & Wholesale Goods"
        }
    ],
    "sg:phone":"+1 920 746 1430",
    "sg:postcode":"54235",
    "sg:province":"WI",
    "sg:tags":[
        "commercial",
        "duplicating",
        "copying"
    ],
    "wof:name":"Copies Plus More Inc",
    "wof:placetype":"venue"
},
  "geometry": {"coordinates":[-87.37641000000001,44.836248],"type":"Point"}
}