{
  "type": "Feature",
  "properties": {
    "iso:country":"US",
    "sg:address":"419 Humboldt St",
    "sg:city":"Watertown",
    "sg:classifiers":[
        {
            "category":"Wholesale",
            "subcategory":"Hardware",
            "type":"Manufacturing & Wholesale Goods"
        }
    ],
    "sg:phone":"+1 920 261 9333",
    "sg:postcode":"53094",
    "sg:province":"WI",
    "sg:tags":[
        "beer",
        "cooling",
        "dispensing"
    ],
    "wof:name":"Pauli Cooling Systems Inc",
    "wof:placetype":"venue"
},
  "geometry": {"coordinates":[-88.704931,43.179531],"type":"Point"}
}