{
  "type": "Feature",
  "properties": {
    "iso:country":"US",
    "sg:address":"1815 Steven St",
    "sg:city":"Sun Prairie",
    "sg:classifiers":[
        {
            "category":"Wholesale",
            "subcategory":"Farm Supplies",
            "type":"Manufacturing & Wholesale Goods"
        }
    ],
    "sg:phone":"+1 608 825 3458",
    "sg:postcode":"53590",
    "sg:province":"WI",
    "sg:tags":[
        "research",
        "commercial",
        "physical",
        "mfg"
    ],
    "wof:name":"Pioneer",
    "wof:placetype":"venue"
},
  "geometry": {"coordinates":[-89.245427,43.191836],"type":"Point"}
}