{
  "type": "Feature",
  "properties": {
    "iso:country":"US",
    "sg:address":"221 Sanborn Ave",
    "sg:city":"Ashland",
    "sg:classifiers":[
        {
            "category":"Restaurant",
            "type":"Food & Drink"
        }
    ],
    "sg:phone":"+1 715 682 8202",
    "sg:postcode":"54806",
    "sg:province":"WI",
    "sg:tags":[
        "pizza"
    ],
    "wof:name":"Hugo's Pizza",
    "wof:placetype":"venue"
},
  "geometry": {"coordinates":[-90.906384,46.58113],"type":"Point"}
}