{
  "type": "Feature",
  "properties": {
    "addr:full":"31407 Hickory Hollow Rd Waterford WI 53185",
    "addr:housenumber":"31407",
    "addr:postcode":"53185",
    "addr:street":"Hickory Hollow Rd",
    "iso:country":"US",
    "sg:address":"31407 Hickory Hollow Rd",
    "sg:city":"Waterford",
    "sg:classifiers":[
        {
            "category":"Professional",
            "type":"Services"
        }
    ],
    "sg:phone":"+1 262 534 7787",
    "sg:postcode":"53185",
    "sg:province":"WI",
    "sg:tags":[
        "establishment"
    ],
    "wof:name":"Type Pro",
    "wof:placetype":"venue"
},
  "geometry": {"coordinates":[-88.237207,42.78197],"type":"Point"}
}