{
  "type": "Feature",
  "properties": {
    "addr:full":"5468 Easy St Waunakee WI 53597",
    "addr:housenumber":"5468",
    "addr:postcode":"53597",
    "addr:street":"Easy St",
    "iso:country":"US",
    "sg:address":"5468 Easy St",
    "sg:city":"Waunakee",
    "sg:classifiers":[
        {
            "category":"Shopping",
            "subcategory":"Florist",
            "type":"Retail Goods"
        }
    ],
    "sg:phone":"+1 608 849 4474",
    "sg:postcode":"53597",
    "sg:province":"WI",
    "wof:name":"Royal Arrangement",
    "wof:placetype":"venue"
},
  "geometry": {"coordinates":[-89.419259,43.206691],"type":"Point"}
}