{
  "type": "Feature",
  "properties": {
    "addr:full":"1027 S Main St Oshkosh WI 54902",
    "addr:housenumber":"1027",
    "addr:postcode":"54902",
    "addr:street":"S Main St",
    "iso:country":"US",
    "sg:address":"1027 S Main St",
    "sg:city":"Oshkosh",
    "sg:classifiers":[
        {
            "category":"Restaurant",
            "type":"Food & Drink"
        }
    ],
    "sg:phone":"+1 920 303 1675",
    "sg:postcode":"54902",
    "sg:province":"WI",
    "wof:name":"Garibaldi Italian Bistro",
    "wof:placetype":"venue"
},
  "geometry": {"coordinates":[-88.538124,44.009384],"type":"Point"}
}