{
  "type": "Feature",
  "properties": {
    "iso:country":"US",
    "sg:address":"230 12th Ave S",
    "sg:city":"Wisconsin Rapids",
    "sg:classifiers":[
        {
            "category":"Professional",
            "subcategory":"Computer Services",
            "type":"Services"
        }
    ],
    "sg:phone":"+1 715 424 2552",
    "sg:postcode":"54495",
    "sg:province":"WI",
    "sg:tags":[
        "consultant"
    ],
    "wof:name":"Byte Wise Consulting",
    "wof:placetype":"venue"
},
  "geometry": {"coordinates":[-89.838433,44.394381],"type":"Point"}
}