{
  "type": "Feature",
  "properties": {
    "iso:country":"US",
    "sg:address":"3664 E Munkwitz Ave",
    "sg:city":"Cudahy",
    "sg:classifiers":[
        {
            "category":"Building & Trades",
            "subcategory":"Construction",
            "type":"Services"
        }
    ],
    "sg:phone":"+1 414 483 1611",
    "sg:postcode":"53110",
    "sg:province":"WI",
    "sg:tags":[
        "resurfacing",
        "laying",
        "refinishing",
        "floor"
    ],
    "wof:name":"Classic Wood Floors",
    "wof:placetype":"venue"
},
  "geometry": {"coordinates":[-87.858896,42.956501],"type":"Point"}
}