{
  "type": "Feature",
  "properties": {
    "iso:country":"US",
    "sg:address":"7357 Winnebago Dr",
    "sg:city":"Fond Du Lac",
    "sg:classifiers":[
        {
            "category":"Shopping",
            "subcategory":"Computers & Home Electronics",
            "type":"Retail Goods"
        }
    ],
    "sg:phone":"+1 920 922 9209",
    "sg:postcode":"54935",
    "sg:province":"WI",
    "sg:website":"www.comdata.net",
    "wof:name":"Comdata Business Systems",
    "wof:placetype":"venue"
},
  "geometry": {"coordinates":[-88.40686100000001,43.803863],"type":"Point"}
}