{
  "type": "Feature",
  "properties": {
    "iso:country":"US",
    "sg:address":"1009 N Jackson St",
    "sg:city":"Milwaukee",
    "sg:classifiers":[
        {
            "category":"Wholesale",
            "subcategory":"Groceries",
            "type":"Manufacturing & Wholesale Goods"
        }
    ],
    "sg:phone":"+1 414 765 9768",
    "sg:postcode":"53202",
    "sg:province":"WI",
    "sg:tags":[
        "food"
    ],
    "wof:name":"Alemer Holdings LLC",
    "wof:placetype":"venue"
},
  "geometry": {"coordinates":[-87.904848,43.045651],"type":"Point"}
}