{
  "type": "Feature",
  "properties": {
    "iso:country":"US",
    "sg:address":"1069 18th Ave",
    "sg:city":"Wautoma",
    "sg:classifiers":[
        {
            "category":"Manufacturing",
            "subcategory":"Toys & Sporting Goods",
            "type":"Manufacturing & Wholesale Goods"
        }
    ],
    "sg:phone":"+1 920 787 3213",
    "sg:postcode":"54982",
    "sg:province":"WI",
    "sg:tags":[
        "mfg"
    ],
    "wof:name":"Xmas Year Round",
    "wof:placetype":"venue"
},
  "geometry": {"coordinates":[-89.267281,44.025923],"type":"Point"}
}