{
  "type": "Feature",
  "properties": {
    "iso:country":"US",
    "sg:address":"354 Ladwig St",
    "sg:city":"Campbellsport",
    "sg:classifiers":[
        {
            "category":"Farming",
            "subcategory":"Nursery",
            "type":"Manufacturing & Wholesale Goods"
        }
    ],
    "sg:phone":"+1 920 533 4341",
    "sg:postcode":"53010",
    "sg:province":"WI",
    "sg:tags":[
        "ornamental"
    ],
    "wof:name":"Midwest Ground Covers",
    "wof:placetype":"venue"
},
  "geometry": {"coordinates":[-88.280647,43.595022],"type":"Point"}
}