{
  "type": "Feature",
  "properties": {
    "addr:full":"2931 72nd Ave Kenosha WI 53144",
    "addr:housenumber":"2931",
    "addr:postcode":"53144",
    "addr:street":"72Nd Ave",
    "iso:country":"US",
    "sg:address":"2931 72nd Ave",
    "sg:city":"Kenosha",
    "sg:phone":"+1 262 658 4013",
    "sg:postcode":"53144",
    "sg:province":"WI",
    "sg:tags":[
        "farm",
        "corn",
        "soybean"
    ],
    "wof:name":"Fenske Farms",
    "wof:placetype":"venue"
},
  "geometry": {"coordinates":[-87.895196,42.613064],"type":"Point"}
}