{
  "type": "Feature",
  "properties": {
    "iso:country":"US",
    "sg:address":"630 Sumter Cir",
    "sg:city":"Sun Prairie",
    "sg:classifiers":[
        {
            "category":"Building & Trades",
            "subcategory":"Construction",
            "type":"Services"
        }
    ],
    "sg:phone":"+1 608 837 3550",
    "sg:postcode":"53590",
    "sg:province":"WI",
    "sg:tags":[
        "general",
        "contractor"
    ],
    "wof:name":"Glynn Construction",
    "wof:placetype":"venue"
},
  "geometry": {"coordinates":[-89.19571,43.187618],"type":"Point"}
}