{
  "type": "Feature",
  "properties": {
    "iso:country":"US",
    "sg:address":"8263 State Hwy 67",
    "sg:city":"Plymouth",
    "sg:classifiers":[
        {
            "category":"Wholesale",
            "subcategory":"Farm Supplies",
            "type":"Manufacturing & Wholesale Goods"
        }
    ],
    "sg:phone":"+1 920 526 3538",
    "sg:postcode":"53073",
    "sg:province":"WI",
    "sg:tags":[
        "raw",
        "product",
        "material"
    ],
    "wof:name":"J B K Intl Hrse Brding Stables",
    "wof:placetype":"venue"
},
  "geometry": {"coordinates":[-88.108839,43.720204],"type":"Point"}
}