{
  "type": "Feature",
  "properties": {
    "iso:country":"US",
    "sg:address":"234 W Main St",
    "sg:city":"Waukesha",
    "sg:classifiers":[
        {
            "category":"Shopping",
            "subcategory":"Crafts & Fabrics",
            "type":"Retail Goods"
        }
    ],
    "sg:phone":"+1 262 513 9920",
    "sg:postcode":"53186",
    "sg:province":"WI",
    "sg:tags":[
        "sewing"
    ],
    "wof:name":"Paulas Canvas & Cross Stitch",
    "wof:placetype":"venue"
},
  "geometry": {"coordinates":[-88.229081,43.012246],"type":"Point"}
}