{
  "type": "Feature",
  "properties": {
    "iso:country":"US",
    "sg:address":"604 E Main St",
    "sg:city":"Merrill",
    "sg:classifiers":[
        {
            "category":"Shopping",
            "subcategory":"Musical Instruments",
            "type":"Retail Goods"
        }
    ],
    "sg:phone":"+1 715 536 6329",
    "sg:postcode":"54452",
    "sg:province":"WI",
    "sg:tags":[
        "repair"
    ],
    "wof:name":"Mamer Piano Service",
    "wof:placetype":"venue"
},
  "geometry": {"coordinates":[-89.68986,45.179309],"type":"Point"}
}