{
  "type": "Feature",
  "properties": {
    "iso:country":"US",
    "sg:address":"505 Dapin Rd",
    "sg:city":"Madison",
    "sg:classifiers":[
        {
            "category":"Personal",
            "type":"Services"
        }
    ],
    "sg:phone":"+1 608 243 1729",
    "sg:postcode":"53704",
    "sg:province":"WI",
    "sg:tags":[
        "therapist",
        "massage"
    ],
    "wof:name":"A Healing Path",
    "wof:placetype":"venue"
},
  "geometry": {"coordinates":[-89.39052,43.142186],"type":"Point"}
}