{
  "type": "Feature",
  "properties": {
    "iso:country":"US",
    "sg:address":"412 E Grand Ave",
    "sg:city":"Beloit",
    "sg:classifiers":[
        {
            "category":"Professional",
            "subcategory":"Accounting & Tax Preparation",
            "type":"Services"
        }
    ],
    "sg:phone":"+1 608 364 0829",
    "sg:postcode":"53511",
    "sg:province":"WI",
    "sg:tags":[
        "return",
        "filing"
    ],
    "sg:website":"www.jacksonhewitt.com",
    "wof:name":"Jackson Hewitt Tax Svc",
    "wof:placetype":"venue"
},
  "geometry": {"coordinates":[-89.03537,42.499543],"type":"Point"}
}