{
  "type": "Feature",
  "properties": {
    "iso:country":"US",
    "sg:address":"6302 Church Rd",
    "sg:city":"Monticello",
    "sg:classifiers":[
        {
            "category":"Building & Trades",
            "subcategory":"Landscaping Services",
            "type":"Services"
        }
    ],
    "sg:phone":"+1 608 938 1226",
    "sg:postcode":"53570",
    "sg:province":"WI",
    "sg:tags":[
        "landscape",
        "contractor"
    ],
    "wof:name":"B K Landscaping",
    "wof:placetype":"venue"
},
  "geometry": {"coordinates":[-89.681364,42.737063],"type":"Point"}
}