{
  "type": "Feature",
  "properties": {
    "iso:country":"US",
    "sg:address":"2255 McCoy Rd",
    "sg:city":"Sun Prairie",
    "sg:classifiers":[
        {
            "category":"Wholesale",
            "subcategory":"Machinery & Supplies",
            "type":"Manufacturing & Wholesale Goods"
        }
    ],
    "sg:phone":"+1 608 837 2332",
    "sg:postcode":"53590",
    "sg:province":"WI",
    "sg:tags":[
        "industrial",
        "equipment",
        "material",
        "handling",
        "repair"
    ],
    "sg:website":"www.inlandmh.com",
    "wof:name":"Inland Material Handling Inc",
    "wof:placetype":"venue"
},
  "geometry": {"coordinates":[-89.24905099999999,43.174958],"type":"Point"}
}