{
  "type": "Feature",
  "properties": {
    "iso:country":"US",
    "sg:address":"2059 Herwig Rd",
    "sg:city":"Reedsburg",
    "sg:classifiers":[
        {
            "category":"Manufacturing",
            "subcategory":"Wood Products",
            "type":"Manufacturing & Wholesale Goods"
        }
    ],
    "sg:phone":"+1 608 254 8050",
    "sg:postcode":"53959",
    "sg:province":"WI",
    "sg:tags":[
        "boards",
        "particle"
    ],
    "wof:name":"Park Lane Model RR Museum",
    "wof:placetype":"venue"
},
  "geometry": {"coordinates":[-89.837136,43.567748],"type":"Point"}
}