{
  "type": "Feature",
  "properties": {
    "addr:full":"7673 Johnson St Siren WI 54872",
    "addr:housenumber":"7673",
    "addr:postcode":"54872",
    "addr:street":"Johnson St",
    "iso:country":"US",
    "sg:address":"7673 Johnson St",
    "sg:city":"Siren",
    "sg:classifiers":[
        {
            "category":"Organizations",
            "subcategory":"Non-profit Organization",
            "type":"Services"
        }
    ],
    "sg:phone":"+1 715 349 8717",
    "sg:postcode":"54872",
    "sg:province":"WI",
    "sg:tags":[
        "peer",
        "self",
        "support",
        "advocacy"
    ],
    "wof:name":"Bccmi Drop In Center",
    "wof:placetype":"venue"
},
  "geometry": {"coordinates":[-92.380413,45.78627],"type":"Point"}
}