{
  "type": "Feature",
  "properties": {
    "iso:country":"US",
    "sg:address":"507 6th St",
    "sg:city":"Racine",
    "sg:classifiers":[
        {
            "category":"Organizations",
            "subcategory":"Professional Association",
            "type":"Services"
        }
    ],
    "sg:phone":"+1 262 898 1840",
    "sg:postcode":"53403",
    "sg:province":"WI",
    "wof:name":"Historic 6th Street Assn",
    "wof:placetype":"venue"
},
  "geometry": {"coordinates":[-87.78709600000001,42.726335],"type":"Point"}
}