{
  "type": "Feature",
  "properties": {
    "iso:country":"US",
    "sg:address":"1522 Oconnor Rd",
    "sg:city":"Lodi",
    "sg:classifiers":[
        {
            "category":"Personal",
            "subcategory":"Beauty Salon",
            "type":"Services"
        }
    ],
    "sg:phone":"+1 608 592 7302",
    "sg:postcode":"53555",
    "sg:province":"WI",
    "sg:tags":[
        "shop"
    ],
    "wof:name":"Making Waves Hair Salon",
    "wof:placetype":"venue"
},
  "geometry": {"coordinates":[-89.640315,43.32832],"type":"Point"}
}