{
  "type": "Feature",
  "properties": {
    "addr:full":"2320 N Lake Dr Milwaukee WI 53211",
    "addr:housenumber":"2320",
    "addr:postcode":"53211",
    "addr:street":"N Lake Dr",
    "iso:country":"US",
    "sg:address":"2320 N Lake Dr",
    "sg:city":"Milwaukee",
    "sg:classifiers":[
        {
            "category":"Health Services",
            "subcategory":"Doctor",
            "type":"Services"
        }
    ],
    "sg:phone":"+1 414 267 6500",
    "sg:postcode":"53211",
    "sg:province":"WI",
    "sg:tags":[
        "physician",
        "surgeon"
    ],
    "wof:name":"St Mary's Family Practice Ctr",
    "wof:placetype":"venue"
},
  "geometry": {"coordinates":[-87.87829000000001,43.062105],"type":"Point"}
}