{
  "type": "Feature",
  "properties": {
    "addr:full":"3702 S 27th St Milwaukee WI 53221",
    "addr:housenumber":"3702",
    "addr:postcode":"53221",
    "addr:street":"S 27Th St",
    "iso:country":"US",
    "sg:address":"3702 S 27th St",
    "sg:city":"Milwaukee",
    "sg:classifiers":[
        {
            "category":"Restaurant",
            "type":"Food & Drink"
        }
    ],
    "sg:phone":"+1 414 281 0801",
    "sg:postcode":"53221",
    "sg:province":"WI",
    "sg:tags":[
        "fast"
    ],
    "wof:name":"Wong's Wok",
    "wof:placetype":"venue"
},
  "geometry": {"coordinates":[-87.948398,42.97951],"type":"Point"}
}