{
  "type": "Feature",
  "properties": {
    "iso:country":"US",
    "sg:address":"2708 Thomas Dr",
    "sg:city":"Eau Claire",
    "sg:classifiers":[
        {
            "category":"Insurance",
            "subcategory":"Insurance Agent",
            "type":"Services"
        }
    ],
    "sg:phone":"+1 715 834 4632",
    "sg:postcode":"54701",
    "sg:province":"WI",
    "wof:name":"Knights Of Columbus",
    "wof:placetype":"venue"
},
  "geometry": {"coordinates":[-91.506378,44.790246],"type":"Point"}
}