{
  "type": "Feature",
  "properties": {
    "iso:country":"US",
    "sg:address":"3440 S Herman St",
    "sg:city":"Milwaukee",
    "sg:classifiers":[
        {
            "category":"Cinema",
            "subcategory":"Movie Rental",
            "type":"Entertainment"
        }
    ],
    "sg:phone":"+1 414 514 0444",
    "sg:postcode":"53207",
    "sg:province":"WI",
    "sg:tags":[
        "picture",
        "exchange",
        "motion",
        "distributor",
        "film"
    ],
    "wof:name":"Entheos Productions",
    "wof:placetype":"venue"
},
  "geometry": {"coordinates":[-87.895674,42.981841],"type":"Point"}
}