{
  "type": "Feature",
  "properties": {
    "addr:full":"2122 Calumet Dr New Holstein WI 53061",
    "addr:housenumber":"2122",
    "addr:postcode":"53061",
    "addr:street":"Calumet Dr",
    "iso:country":"US",
    "sg:address":"2122 Calumet Dr",
    "sg:city":"New Holstein",
    "sg:classifiers":[
        {
            "category":"Building & Trades",
            "subcategory":"Construction",
            "type":"Services"
        }
    ],
    "sg:phone":"+1 920 898 4409",
    "sg:postcode":"53061",
    "sg:province":"WI",
    "sg:tags":[
        "contractor"
    ],
    "wof:name":"Gemini Installations LLC",
    "wof:placetype":"venue"
},
  "geometry": {"coordinates":[-88.10024199999999,43.951237],"type":"Point"}
}