{
  "type": "Feature",
  "properties": {
    "iso:country":"US",
    "sg:address":"18000 W Sarah Ln",
    "sg:city":"Brookfield",
    "sg:classifiers":[
        {
            "category":"Professional",
            "subcategory":"Employment Agencies",
            "type":"Services"
        }
    ],
    "sg:phone":"+1 414 771 8426",
    "sg:postcode":"53045",
    "sg:province":"WI",
    "sg:tags":[
        "opportunity"
    ],
    "wof:name":"Adecco",
    "wof:placetype":"venue"
},
  "geometry": {"coordinates":[-88.136504,43.033085],"type":"Point"}
}