{
  "type": "Feature",
  "properties": {
    "iso:country":"US",
    "sg:address":"534 Sugar Creek Rd",
    "sg:city":"Delavan",
    "sg:classifiers":[
        {
            "category":"Retail",
            "subcategory":"Animal Services",
            "type":"Services"
        }
    ],
    "sg:phone":"+1 262 728 6936",
    "sg:postcode":"53115",
    "sg:province":"WI",
    "sg:tags":[
        "pet",
        "boarding",
        "sitting"
    ],
    "wof:name":"Pet Nanny",
    "wof:placetype":"venue"
},
  "geometry": {"coordinates":[-88.628027,42.639702],"type":"Point"}
}