{
  "type": "Feature",
  "properties": {
    "addr:full":"319 Douglas St New London WI 54961",
    "addr:housenumber":"319",
    "addr:postcode":"54961",
    "addr:street":"Douglas St",
    "iso:country":"US",
    "sg:address":"319 Douglas St",
    "sg:city":"New London",
    "sg:classifiers":[
        {
            "category":"Organizations",
            "subcategory":"Religious Organization",
            "type":"Services"
        }
    ],
    "sg:phone":"+1 920 982 3700",
    "sg:postcode":"54961",
    "sg:province":"WI",
    "sg:tags":[
        "church"
    ],
    "wof:name":"New Life Community Church",
    "wof:placetype":"venue"
},
  "geometry": {"coordinates":[-88.736603,44.382622],"type":"Point"}
}