{
  "type": "Feature",
  "properties": {
    "iso:country":"US",
    "sg:address":"8427 Lewiston Station Rd",
    "sg:city":"Wisconsin Dells",
    "sg:classifiers":[
        {
            "category":"Insurance",
            "subcategory":"Insurance Agent",
            "type":"Services"
        }
    ],
    "sg:phone":"+1 608 742 5205",
    "sg:postcode":"53965",
    "sg:province":"WI",
    "wof:name":"Hohn Insurance Agency",
    "wof:placetype":"venue"
},
  "geometry": {"coordinates":[-89.64216999999999,43.584696],"type":"Point"}
}