{
  "type": "Feature",
  "properties": {
    "iso:country":"US",
    "sg:address":"179 State Rd 83",
    "sg:city":"Hartford",
    "sg:classifiers":[
        {
            "category":"Professional",
            "subcategory":"Computer Services",
            "type":"Services"
        }
    ],
    "sg:phone":"+1 262 966 7541",
    "sg:postcode":"53027",
    "sg:province":"WI",
    "sg:tags":[
        "related"
    ],
    "wof:name":"Lake Country Systems",
    "wof:placetype":"venue"
},
  "geometry": {"coordinates":[-88.379397,43.194842],"type":"Point"}
}