{
  "type": "Feature",
  "properties": {
    "iso:country":"US",
    "sg:address":"2502 Shopko Dr",
    "sg:city":"Madison",
    "sg:classifiers":[
        {
            "category":"Shopping",
            "subcategory":"Florist",
            "type":"Retail Goods"
        }
    ],
    "sg:phone":"+1 608 243 1122",
    "sg:postcode":"53704",
    "sg:province":"WI",
    "sg:website":"www.roundys.com",
    "wof:name":"Rose Petals",
    "wof:placetype":"venue"
},
  "geometry": {"coordinates":[-89.34710800000001,43.11149],"type":"Point"}
}