{
  "type": "Feature",
  "properties": {
    "iso:country":"US",
    "sg:address":"4669 State Hwy 42",
    "sg:city":"Kewaunee",
    "sg:classifiers":[
        {
            "category":"Building & Trades",
            "subcategory":"Construction",
            "type":"Services"
        }
    ],
    "sg:phone":"+1 920 660 7383",
    "sg:postcode":"54216",
    "sg:province":"WI",
    "sg:tags":[
        "concrete",
        "contractor"
    ],
    "wof:name":"Petes Conveying Services",
    "wof:placetype":"venue"
},
  "geometry": {"coordinates":[-87.527378,44.429076],"type":"Point"}
}