{
  "type": "Feature",
  "properties": {
    "iso:country":"US",
    "sg:address":"6134 22nd Ave",
    "sg:city":"Kenosha",
    "sg:classifiers":[
        {
            "category":"Restaurant",
            "type":"Food & Drink"
        }
    ],
    "sg:phone":"+1 262 652 3778",
    "sg:postcode":"53143",
    "sg:province":"WI",
    "wof:name":"Uptown Restaurant",
    "wof:placetype":"venue"
},
  "geometry": {"coordinates":[-87.835614,42.578827],"type":"Point"}
}