{
  "type": "Feature",
  "properties": {
    "iso:country":"US",
    "sg:address":"5645 State Hwy 21",
    "sg:city":"Necedah",
    "sg:classifiers":[
        {
            "category":"Travel",
            "subcategory":"Hotels & Motels",
            "type":"Entertainment"
        }
    ],
    "sg:phone":"+1 608 565 2263",
    "sg:postcode":"54646",
    "sg:province":"WI",
    "sg:tags":[
        "operation"
    ],
    "wof:name":"Necedah Motel",
    "wof:placetype":"venue"
},
  "geometry": {"coordinates":[-90.051955,44.029046],"type":"Point"}
}