{
  "type": "Feature",
  "properties": {
    "iso:country":"US",
    "sg:address":"9755 US Hwy 61",
    "sg:city":"Lancaster",
    "sg:classifiers":[
        {
            "category":"Insurance",
            "subcategory":"Insurance Agent",
            "type":"Services"
        }
    ],
    "sg:phone":"+1 608 723 2105",
    "sg:postcode":"53813",
    "sg:province":"WI",
    "wof:name":"Rural Insurance Co",
    "wof:placetype":"venue"
},
  "geometry": {"coordinates":[-90.704511,42.861097],"type":"Point"}
}