{
  "type": "Feature",
  "properties": {
    "iso:country":"US",
    "sg:address":"116 W Wisconsin Ave",
    "sg:city":"Milwaukee",
    "sg:classifiers":[
        {
            "category":"Arts & Performance",
            "subcategory":"Theater",
            "type":"Entertainment"
        }
    ],
    "sg:phone":"+1 414 224 3000",
    "sg:postcode":"53203",
    "sg:province":"WI",
    "wof:name":"Riverside Theatre",
    "wof:placetype":"venue"
},
  "geometry": {"coordinates":[-87.910858,43.038781],"type":"Point"}
}