{
  "type": "Feature",
  "properties": {
    "addr:full":"1240 Sunnyridge Rd Pewaukee WI 53072",
    "addr:housenumber":"1240",
    "addr:postcode":"53072",
    "addr:street":"Sunnyridge Rd",
    "iso:country":"US",
    "sg:address":"1240 Sunnyridge Rd",
    "sg:city":"Pewaukee",
    "sg:classifiers":[
        {
            "category":"Wholesale",
            "subcategory":"Machinery & Supplies",
            "type":"Manufacturing & Wholesale Goods"
        }
    ],
    "sg:phone":"+1 262 691 2512",
    "sg:postcode":"53072",
    "sg:province":"WI",
    "wof:name":"TPS Intl Inc",
    "wof:placetype":"venue"
},
  "geometry": {"coordinates":[-88.238018,43.081122],"type":"Point"}
}