{
  "type": "Feature",
  "properties": {
    "iso:country":"US",
    "sg:address":"19333 W North Ave",
    "sg:city":"Brookfield",
    "sg:classifiers":[
        {
            "category":"Health Services",
            "subcategory":"Clinic",
            "type":"Services"
        }
    ],
    "sg:phone":"+1 262 785 2187",
    "sg:postcode":"53045",
    "sg:province":"WI",
    "sg:tags":[
        "medical",
        "specialty",
        "outpatient"
    ],
    "wof:name":"Rehabilitation Institutes",
    "wof:placetype":"venue"
},
  "geometry": {"coordinates":[-88.153827,43.061317],"type":"Point"}
}