{
  "type": "Feature",
  "properties": {
    "iso:country":"US",
    "sg:address":"11600 W Lincoln Ave",
    "sg:city":"Milwaukee",
    "sg:classifiers":[
        {
            "category":"Real Estate",
            "subcategory":"Developer",
            "type":"Services"
        }
    ],
    "sg:phone":"+1 414 321 5300",
    "sg:postcode":"53227",
    "sg:province":"WI",
    "sg:tags":[
        "residential",
        "develops"
    ],
    "wof:name":"Kaerek Builders",
    "wof:placetype":"venue"
},
  "geometry": {"coordinates":[-88.05802300000001,43.0027],"type":"Point"}
}