{
  "type": "Feature",
  "properties": {
    "iso:country":"US",
    "sg:address":"118 Spring St",
    "sg:city":"Somerset",
    "sg:classifiers":[
        {
            "category":"Professional",
            "subcategory":"Computer Services",
            "type":"Services"
        }
    ],
    "sg:phone":"+1 715 247 3133",
    "sg:postcode":"54025",
    "sg:province":"WI",
    "sg:tags":[
        "programing",
        "custom"
    ],
    "wof:name":"Paragon Consulting Inc",
    "wof:placetype":"venue"
},
  "geometry": {"coordinates":[-92.674522,45.124255],"type":"Point"}
}