{
  "type": "Feature",
  "properties": {
    "iso:country":"US",
    "sg:address":"309 N Bartlett St",
    "sg:city":"Shawano",
    "sg:classifiers":[
        {
            "category":"Health Services",
            "subcategory":"Hospital",
            "type":"Services"
        }
    ],
    "sg:phone":"+1 715 526 2111",
    "sg:postcode":"54166",
    "sg:province":"WI",
    "sg:website":"www.shawanomed.org",
    "wof:name":"Shawano Medical Ctr",
    "wof:placetype":"venue"
},
  "geometry": {"coordinates":[-88.615847,44.784784],"type":"Point"}
}