{
  "type": "Feature",
  "properties": {
    "iso:country":"US",
    "sg:address":"23 S Hillock Dr",
    "sg:city":"Racine",
    "sg:classifiers":[
        {
            "category":"Manufacturing",
            "subcategory":"Retail Goods",
            "type":"Manufacturing & Wholesale Goods"
        }
    ],
    "sg:phone":"+1 262 884 4229",
    "sg:postcode":"53406",
    "sg:province":"WI",
    "sg:tags":[
        "product",
        "mfg"
    ],
    "wof:name":"Canaan Industries LLC",
    "wof:placetype":"venue"
},
  "geometry": {"coordinates":[-87.847988,42.733214],"type":"Point"}
}