{
  "type": "Feature",
  "properties": {
    "iso:country":"US",
    "sg:address":"3537 Femrite Dr",
    "sg:city":"Madison",
    "sg:classifiers":[
        {
            "category":"Retail",
            "subcategory":"Auto Repair",
            "type":"Services"
        }
    ],
    "sg:phone":"+1 608 222 4440",
    "sg:postcode":"53718",
    "sg:province":"WI",
    "sg:tags":[
        "general"
    ],
    "wof:name":"Cherokee Truck & Auto",
    "wof:placetype":"venue"
},
  "geometry": {"coordinates":[-89.27377799999999,43.051899],"type":"Point"}
}