{
  "type": "Feature",
  "properties": {
    "iso:country":"US",
    "sg:address":"3113 S Duluth Ave",
    "sg:city":"Sturgeon Bay",
    "sg:classifiers":[
        {
            "category":"Autos & Motor Vehicles",
            "subcategory":"Automobile Sales",
            "type":"Retail Goods"
        }
    ],
    "sg:phone":"+1 920 743 7297",
    "sg:postcode":"54235",
    "sg:province":"WI",
    "sg:tags":[
        "car",
        "dealer"
    ],
    "wof:name":"Door County Sales LTD",
    "wof:placetype":"venue"
},
  "geometry": {"coordinates":[-87.397468,44.821193],"type":"Point"}
}