{
  "type": "Feature",
  "properties": {
    "iso:country":"US",
    "sg:address":"6900 46th St",
    "sg:city":"Kenosha",
    "sg:classifiers":[
        {
            "category":"Manufacturing",
            "subcategory":"Tools & Machinery",
            "type":"Manufacturing & Wholesale Goods"
        }
    ],
    "sg:phone":"+1 262 656 7680",
    "sg:postcode":"53144",
    "sg:province":"WI",
    "sg:tags":[
        "control",
        "for",
        "mfg",
        "relate",
        "water",
        "equipment",
        "pollution"
    ],
    "sg:website":"www.beckart.com",
    "wof:name":"Beckart Environmental Inc",
    "wof:placetype":"venue"
},
  "geometry": {"coordinates":[-87.89118,42.595139],"type":"Point"}
}