{
  "type": "Feature",
  "properties": {
    "addr:full":"7137 Triple T Rd Mount Calvary WI 53057",
    "addr:housenumber":"7137",
    "addr:postcode":"53057",
    "addr:street":"Triple T Rd",
    "iso:country":"US",
    "sg:address":"7137 Triple T Rd",
    "sg:city":"Mount Calvary",
    "sg:classifiers":[
        {
            "category":"Farming",
            "subcategory":"Dairy Farm",
            "type":"Manufacturing & Wholesale Goods"
        }
    ],
    "sg:phone":"+1 920 753 3652",
    "sg:postcode":"53057",
    "sg:province":"WI",
    "sg:tags":[
        "field",
        "crop"
    ],
    "wof:name":"E Sippel",
    "wof:placetype":"venue"
},
  "geometry": {"coordinates":[-88.201071,43.802926],"type":"Point"}
}