{
  "type": "Feature",
  "properties": {
    "iso:country":"US",
    "sg:address":"18 Kings Mill Cir",
    "sg:city":"Madison",
    "sg:classifiers":[
        {
            "category":"Real Estate",
            "subcategory":"Real Estate Agent",
            "type":"Services"
        }
    ],
    "sg:phone":"+1 608 223 0501",
    "sg:postcode":"53718",
    "sg:province":"WI",
    "wof:name":"Richmond Hill Estates",
    "wof:placetype":"venue"
},
  "geometry": {"coordinates":[-89.278398,43.076514],"type":"Point"}
}