{
  "type": "Feature",
  "properties": {
    "iso:country":"US",
    "sg:address":"3073 Canary Rd",
    "sg:city":"Lake Geneva",
    "sg:classifiers":[
        {
            "category":"Building & Trades",
            "subcategory":"Cleaning & Sanitation",
            "type":"Services"
        }
    ],
    "sg:phone":"+1 262 248 0858",
    "sg:postcode":"53147",
    "sg:province":"WI",
    "sg:tags":[
        "janitor"
    ],
    "wof:name":"Home Cleaning Svc",
    "wof:placetype":"venue"
},
  "geometry": {"coordinates":[-88.505669,42.603527],"type":"Point"}
}