{
  "type": "Feature",
  "properties": {
    "addr:full":"1149 Grant St De Pere WI 54115",
    "addr:housenumber":"1149",
    "addr:postcode":"54115",
    "addr:street":"Grant St",
    "iso:country":"US",
    "sg:address":"1149 Grant St",
    "sg:city":"De Pere",
    "sg:classifiers":[
        {
            "category":"Retail",
            "subcategory":"Portrait Studio",
            "type":"Services"
        }
    ],
    "sg:phone":"+1 920 336 9232",
    "sg:postcode":"54115",
    "sg:province":"WI",
    "sg:tags":[
        "photo",
        "photography",
        "commercial"
    ],
    "wof:name":"Lewis Photography",
    "wof:placetype":"venue"
},
  "geometry": {"coordinates":[-88.088115,44.445005],"type":"Point"}
}