{
  "type": "Feature",
  "properties": {
    "iso:country":"US",
    "sg:address":"2613 Elm Ln",
    "sg:city":"Sturgeon Bay",
    "sg:phone":"+1 920 824 5752",
    "sg:postcode":"54235",
    "sg:province":"WI",
    "sg:tags":[
        "farm",
        "grain",
        "cash"
    ],
    "wof:name":"Peter Hansen",
    "wof:placetype":"venue"
},
  "geometry": {"coordinates":[-87.529032,44.799883],"type":"Point"}
}