{
  "type": "Feature",
  "properties": {
    "iso:country":"US",
    "sg:address":"817 E Johnson St",
    "sg:city":"Madison",
    "sg:classifiers":[
        {
            "category":"Professional",
            "type":"Services"
        }
    ],
    "sg:phone":"+1 608 256 5233",
    "sg:postcode":"53703",
    "sg:province":"WI",
    "wof:name":"Jade Mountain",
    "wof:placetype":"venue"
},
  "geometry": {"coordinates":[-89.376358,43.084183],"type":"Point"}
}