{
  "type": "Feature",
  "properties": {
    "addr:full":"611 Sweetbriar Ln Watertown WI 53098",
    "addr:housenumber":"611",
    "addr:postcode":"53098",
    "addr:street":"Sweetbriar Ln",
    "iso:country":"US",
    "sg:address":"611 Sweetbriar Ln",
    "sg:city":"Watertown",
    "sg:classifiers":[
        {
            "category":"Shopping",
            "subcategory":"Stationery & Office Supplies",
            "type":"Retail Goods"
        }
    ],
    "sg:phone":"+1 920 261 8980",
    "sg:postcode":"53098",
    "sg:province":"WI",
    "sg:tags":[
        "rubber",
        "stamp",
        "plastic"
    ],
    "wof:name":"Rubber Stamp Shop",
    "wof:placetype":"venue"
},
  "geometry": {"coordinates":[-88.74506,43.206828],"type":"Point"}
}