{
  "type": "Feature",
  "properties": {
    "iso:country":"US",
    "sg:address":"9155 W Lisbon Ave",
    "sg:city":"Milwaukee",
    "sg:classifiers":[
        {
            "category":"Personal",
            "subcategory":"Beauty Salon",
            "type":"Services"
        }
    ],
    "sg:phone":"+1 414 466 7470",
    "sg:postcode":"53222",
    "sg:province":"WI",
    "wof:name":"LA Belle Hair Designs",
    "wof:placetype":"venue"
},
  "geometry": {"coordinates":[-88.026859,43.08454],"type":"Point"}
}