{
  "type": "Feature",
  "properties": {
    "iso:country":"US",
    "sg:address":"10403 Maple Rd",
    "sg:city":"Phillips",
    "sg:classifiers":[
        {
            "category":"Personal",
            "type":"Services"
        }
    ],
    "sg:phone":"+1 715 339 4489",
    "sg:postcode":"54555",
    "sg:province":"WI",
    "wof:name":"Jesunas Alfons",
    "wof:placetype":"venue"
},
  "geometry": {"coordinates":[-90.491879,45.745948],"type":"Point"}
}