{
  "type": "Feature",
  "properties": {
    "iso:country":"US",
    "sg:address":"301 S Franklin St",
    "sg:city":"Verona",
    "sg:classifiers":[
        {
            "category":"Building & Trades",
            "subcategory":"Plumbing",
            "type":"Services"
        }
    ],
    "sg:phone":"+1 608 845 9353",
    "sg:postcode":"53593",
    "sg:province":"WI",
    "sg:tags":[
        "heating",
        "contractor"
    ],
    "wof:name":"Dale's Heating & Air Cond",
    "wof:placetype":"venue"
},
  "geometry": {"coordinates":[-89.532039,42.986075],"type":"Point"}
}