{
  "type": "Feature",
  "properties": {
    "iso:country":"US",
    "sg:address":"4309 Bay Shore Dr",
    "sg:city":"Sturgeon Bay",
    "sg:classifiers":[
        {
            "category":"Professional",
            "subcategory":"Advertising",
            "type":"Services"
        }
    ],
    "sg:phone":"+1 920 746 8337",
    "sg:postcode":"54235",
    "sg:province":"WI",
    "sg:tags":[
        "agency"
    ],
    "wof:name":"Add Magic",
    "wof:placetype":"venue"
},
  "geometry": {"coordinates":[-87.382775,44.879441],"type":"Point"}
}