{
  "type": "Feature",
  "properties": {
    "iso:country":"US",
    "sg:address":"810 N Central Ave",
    "sg:city":"Marshfield",
    "sg:classifiers":[
        {
            "category":"Banks & Credit Unions",
            "subcategory":"Bank",
            "type":"Services"
        }
    ],
    "sg:phone":"+1 715 387 3761",
    "sg:postcode":"54449",
    "sg:province":"WI",
    "wof:name":"Time Federal Savings Bank",
    "wof:placetype":"venue"
},
  "geometry": {"coordinates":[-90.167911,44.674953],"type":"Point"}
}