{
  "type": "Feature",
  "properties": {
    "iso:country":"US",
    "sg:address":"2623 S Stoughton Rd",
    "sg:city":"Madison",
    "sg:classifiers":[
        {
            "category":"Retail",
            "subcategory":"Auto Repair",
            "type":"Services"
        }
    ],
    "sg:phone":"+1 608 223 2088",
    "sg:postcode":"53716",
    "sg:province":"WI",
    "sg:tags":[
        "repairing",
        "automobile",
        "body"
    ],
    "wof:name":"Reece Auto & Restoration",
    "wof:placetype":"venue"
},
  "geometry": {"coordinates":[-89.309034,43.054324],"type":"Point"}
}