{
  "type": "Feature",
  "properties": {
    "addr:full":"823 Briar Ln Altoona WI 54720",
    "addr:housenumber":"823",
    "addr:postcode":"54720",
    "addr:street":"Briar Ln",
    "iso:country":"US",
    "sg:address":"823 Briar Ln",
    "sg:city":"Altoona",
    "sg:classifiers":[
        {
            "category":"Health Services",
            "subcategory":"Clinic",
            "type":"Services"
        }
    ],
    "sg:phone":"+1 715 552 1791",
    "sg:postcode":"54720",
    "sg:province":"WI",
    "sg:tags":[
        "home",
        "care"
    ],
    "wof:name":"J A E",
    "wof:placetype":"venue"
},
  "geometry": {"coordinates":[-91.429591,44.796872],"type":"Point"}
}