{
  "type": "Feature",
  "properties": {
    "iso:country":"US",
    "sg:address":"9110 Middle Rd",
    "sg:city":"Oostburg",
    "sg:classifiers":[
        {
            "category":"Professional",
            "subcategory":"Computer Services",
            "type":"Services"
        }
    ],
    "sg:phone":"+1 920 452 7008",
    "sg:postcode":"53070",
    "sg:province":"WI",
    "sg:tags":[
        "design",
        "system",
        "programing",
        "custom"
    ],
    "sg:website":"www.summ-tech.com",
    "wof:name":"Summ-Tech Inc",
    "wof:placetype":"venue"
},
  "geometry": {"coordinates":[-87.759126,43.644469],"type":"Point"}
}