{
  "type": "Feature",
  "properties": {
    "addr:full":"113 W Monowau St Tomah WI 54660",
    "addr:housenumber":"113",
    "addr:postcode":"54660",
    "addr:street":"W Monowau St",
    "iso:country":"US",
    "sg:address":"113 W Monowau St",
    "sg:city":"Tomah",
    "sg:classifiers":[
        {
            "category":"Manufacturing",
            "subcategory":"Printing",
            "type":"Manufacturing & Wholesale Goods"
        }
    ],
    "sg:phone":"+1 608 372 4350",
    "sg:postcode":"54660",
    "sg:province":"WI",
    "sg:tags":[
        "printer",
        "publishing",
        "mfg",
        "commercial",
        "industry",
        "m"
    ],
    "wof:name":"Town & Country Printers Inc",
    "wof:placetype":"venue"
},
  "geometry": {"coordinates":[-90.505319,43.976887],"type":"Point"}
}