{
  "type": "Feature",
  "properties": {
    "iso:country":"US",
    "sg:address":"610 Pine St",
    "sg:city":"Pepin",
    "sg:classifiers":[
        {
            "category":"Manufacturing",
            "subcategory":"Tools & Machinery",
            "type":"Manufacturing & Wholesale Goods"
        }
    ],
    "sg:phone":"+1 715 442 4111",
    "sg:postcode":"54759",
    "sg:province":"WI",
    "sg:tags":[
        "farm",
        "equipment"
    ],
    "wof:name":"Pepin Farm Implements",
    "wof:placetype":"venue"
},
  "geometry": {"coordinates":[-92.14733699999999,44.445461],"type":"Point"}
}