{
  "type": "Feature",
  "properties": {
    "iso:country":"US",
    "sg:address":"8023 Rangeline Rd",
    "sg:city":"Sheboygan",
    "sg:classifiers":[
        {
            "category":"Building & Trades",
            "subcategory":"Construction",
            "type":"Services"
        }
    ],
    "sg:phone":"+1 920 565 2594",
    "sg:postcode":"53083",
    "sg:province":"WI",
    "sg:tags":[
        "general",
        "industrial",
        "commercial",
        "contractor"
    ],
    "wof:name":"Badger Structures",
    "wof:placetype":"venue"
},
  "geometry": {"coordinates":[-87.80077799999999,43.823759],"type":"Point"}
}