{
  "type": "Feature",
  "properties": {
    "iso:country":"US",
    "sg:address":"810 Park Ave",
    "sg:city":"Beaver Dam",
    "sg:classifiers":[
        {
            "category":"Banks & Credit Unions",
            "subcategory":"Bank",
            "type":"Services"
        }
    ],
    "sg:phone":"+1 920 356 0427",
    "sg:postcode":"53916",
    "sg:province":"WI",
    "sg:tags":[
        "federal",
        "savings",
        "institution"
    ],
    "wof:name":"Beaver Dam",
    "wof:placetype":"venue"
},
  "geometry": {"coordinates":[-88.821605,43.456249],"type":"Point"}
}