{
  "type": "Feature",
  "properties": {
    "iso:country":"US",
    "sg:address":"4263 State Rd 49",
    "sg:city":"Poy Sippi",
    "sg:classifiers":[
        {
            "category":"Banks & Credit Unions",
            "subcategory":"Bank",
            "type":"Services"
        }
    ],
    "sg:phone":"+1 920 987 9000",
    "sg:postcode":"54967",
    "sg:province":"WI",
    "wof:name":"First National Bank",
    "wof:placetype":"venue"
},
  "geometry": {"coordinates":[-88.996911,44.134122],"type":"Point"}
}