{
  "type": "Feature",
  "properties": {
    "iso:country":"US",
    "sg:address":"1111 Industrial St",
    "sg:city":"Reedsburg",
    "sg:classifiers":[
        {
            "category":"Social Services",
            "subcategory":"Child Care",
            "type":"Services"
        },
        {
            "category":"Education",
            "subcategory":"School",
            "type":"Public Place"
        }
    ],
    "sg:phone":"+1 608 524 1657",
    "sg:postcode":"53959",
    "sg:province":"WI",
    "sg:tags":[
        "kindergarten",
        "academic"
    ],
    "wof:name":"Head Start Reedsburg II",
    "wof:placetype":"venue"
},
  "geometry": {"coordinates":[-89.990546,43.524381],"type":"Point"}
}