{
  "type": "Feature",
  "properties": {
    "iso:country":"US",
    "sg:address":"405 N Hastings Pl",
    "sg:city":"Eau Claire",
    "sg:classifiers":[
        {
            "category":"Retail",
            "subcategory":"Funeral Services",
            "type":"Services"
        }
    ],
    "sg:phone":"+1 715 834 2555",
    "sg:postcode":"54703",
    "sg:province":"WI",
    "wof:name":"Cremation Society Of Wisconsin",
    "wof:placetype":"venue"
},
  "geometry": {"coordinates":[-91.47409500000001,44.820078],"type":"Point"}
}