{
  "type": "Feature",
  "properties": {
    "iso:country":"US",
    "sg:address":"7601 Poplar Rd",
    "sg:city":"Shawano",
    "sg:classifiers":[
        {
            "category":"Bars & Pubs",
            "type":"Food & Drink"
        }
    ],
    "sg:phone":"+1 715 524 2975",
    "sg:postcode":"54166",
    "sg:province":"WI",
    "sg:tags":[
        "drinking"
    ],
    "wof:name":"Shack",
    "wof:placetype":"venue"
},
  "geometry": {"coordinates":[-88.624425,44.775624],"type":"Point"}
}