{
  "type": "Feature",
  "properties": {
    "iso:country":"US",
    "sg:address":"4862 Ridge Prairie School Rd",
    "sg:city":"Delavan",
    "sg:classifiers":[
        {
            "category":"Professional",
            "subcategory":"Lawyer & Legal Services",
            "type":"Services"
        }
    ],
    "sg:phone":"+1 262 728 8588",
    "sg:postcode":"53115",
    "sg:province":"WI",
    "sg:tags":[
        "attorney"
    ],
    "wof:name":"Carol Unger-Keizer Law Offices",
    "wof:placetype":"venue"
},
  "geometry": {"coordinates":[-88.678712,42.649811],"type":"Point"}
}