{
  "type": "Feature",
  "properties": {
    "addr:full":"2491 S Broadway Green Bay WI 54304",
    "addr:housenumber":"2491",
    "addr:postcode":"54304",
    "addr:street":"S Broadway",
    "iso:country":"US",
    "sg:address":"2491 S Broadway",
    "sg:city":"Green Bay",
    "sg:classifiers":[
        {
            "category":"Manufacturing",
            "subcategory":"Food",
            "type":"Manufacturing & Wholesale Goods"
        }
    ],
    "sg:phone":"+1 920 432 8776",
    "sg:postcode":"54304",
    "sg:province":"WI",
    "sg:tags":[
        "product",
        "mfg"
    ],
    "wof:name":"Pan-O-Gold Baking Co",
    "wof:placetype":"venue"
},
  "geometry": {"coordinates":[-88.051643,44.481446],"type":"Point"}
}