{
  "type": "Feature",
  "properties": {
    "iso:country":"US",
    "sg:address":"1830 W Hadley St",
    "sg:city":"Milwaukee",
    "sg:classifiers":[
        {
            "category":"Organizations",
            "subcategory":"Religious Organization",
            "type":"Services"
        }
    ],
    "sg:phone":"+1 414 263 6770",
    "sg:postcode":"53206",
    "sg:province":"WI",
    "sg:tags":[
        "church"
    ],
    "wof:name":"Ebenezer Baptist Church",
    "wof:placetype":"venue"
},
  "geometry": {"coordinates":[-87.936485,43.069676],"type":"Point"}
}