{
  "type": "Feature",
  "properties": {
    "iso:country":"US",
    "sg:address":"2921 Twin Towers Dr",
    "sg:city":"Plover",
    "sg:classifiers":[
        {
            "category":"Wholesale",
            "subcategory":"Medical Equipment & Supplies",
            "type":"Manufacturing & Wholesale Goods"
        }
    ],
    "sg:phone":"+1 715 341 0888",
    "sg:postcode":"54467",
    "sg:province":"WI",
    "sg:tags":[
        "optical"
    ],
    "wof:name":"Alpha Optical",
    "wof:placetype":"venue"
},
  "geometry": {"coordinates":[-89.49833599999999,44.456099],"type":"Point"}
}