{
  "type": "Feature",
  "properties": {
    "addr:full":"10321 Country Ln Sister Bay WI 54234",
    "addr:housenumber":"10321",
    "addr:postcode":"54234",
    "addr:street":"Country Ln",
    "iso:country":"US",
    "sg:address":"10321 Country Ln",
    "sg:city":"Sister Bay",
    "sg:classifiers":[
        {
            "category":"Building & Trades",
            "subcategory":"Construction",
            "type":"Services"
        }
    ],
    "sg:phone":"+1 920 854 2061",
    "sg:postcode":"54234",
    "sg:province":"WI",
    "sg:tags":[
        "house"
    ],
    "wof:name":"Laaksonen Builders",
    "wof:placetype":"venue"
},
  "geometry": {"coordinates":[-87.132644,45.170915],"type":"Point"}
}