{
  "type": "Feature",
  "properties": {
    "iso:country":"US",
    "sg:address":"2340 State Hwy 32",
    "sg:city":"Krakow",
    "sg:classifiers":[
        {
            "category":"Real Estate",
            "subcategory":"Real Estate Agent",
            "type":"Services"
        }
    ],
    "sg:phone":"+1 920 899 8900",
    "sg:postcode":"54137",
    "sg:province":"WI",
    "sg:website":"www.hearthsidehomesandrealty.com",
    "wof:name":"Hearthside Home & Realty",
    "wof:placetype":"venue"
},
  "geometry": {"coordinates":[-88.25138200000001,44.761276],"type":"Point"}
}