{
  "type": "Feature",
  "properties": {
    "iso:country":"US",
    "sg:address":"605 Main St",
    "sg:city":"Brownsville",
    "sg:classifiers":[
        {
            "category":"Restaurant",
            "type":"Food & Drink"
        }
    ],
    "sg:phone":"+1 920 583 2269",
    "sg:postcode":"53006",
    "sg:province":"WI",
    "sg:tags":[
        "eating",
        "caterer"
    ],
    "wof:name":"Karlen Catering LLC",
    "wof:placetype":"venue"
},
  "geometry": {"coordinates":[-88.492214,43.616228],"type":"Point"}
}