{
  "type": "Feature",
  "properties": {
    "iso:country":"US",
    "sg:address":"65 N 4th St",
    "sg:city":"Platteville",
    "sg:classifiers":[
        {
            "category":"Professional",
            "subcategory":"Accounting & Tax Preparation",
            "type":"Services"
        }
    ],
    "sg:phone":"+1 608 348 9472",
    "sg:postcode":"53818",
    "sg:province":"WI",
    "sg:tags":[
        "accountant"
    ],
    "wof:name":"LBS Inc",
    "wof:placetype":"venue"
},
  "geometry": {"coordinates":[-90.478076,42.734357],"type":"Point"}
}