{
  "type": "Feature",
  "properties": {
    "iso:country":"US",
    "sg:address":"5585 Robin Rd",
    "sg:city":"Edgar",
    "sg:classifiers":[
        {
            "category":"Farming",
            "subcategory":"Dairy Farm",
            "type":"Manufacturing & Wholesale Goods"
        }
    ],
    "sg:phone":"+1 715 352 2807",
    "sg:postcode":"54426",
    "sg:province":"WI",
    "wof:name":"Ronald Meyer",
    "wof:placetype":"venue"
},
  "geometry": {"coordinates":[-89.98396099999999,44.974098],"type":"Point"}
}