{
  "type": "Feature",
  "properties": {
    "addr:full":"216 15th Ave South Milwaukee WI 53172",
    "addr:housenumber":"216",
    "addr:postcode":"53172",
    "addr:street":"15Th Ave",
    "iso:country":"US",
    "sg:address":"216 15th Ave",
    "sg:city":"South Milwaukee",
    "sg:classifiers":[
        {
            "category":"Retail",
            "subcategory":"Repair Shop",
            "type":"Services"
        }
    ],
    "sg:phone":"+1 414 571 7020",
    "sg:postcode":"53172",
    "sg:province":"WI",
    "sg:tags":[
        "equipment",
        "printing"
    ],
    "wof:name":"Astech Inc",
    "wof:placetype":"venue"
},
  "geometry": {"coordinates":[-87.870745,42.928652],"type":"Point"}
}