{
  "type": "Feature",
  "properties": {
    "iso:country":"US",
    "sg:address":"1511 Main Ave",
    "sg:city":"Sheboygan",
    "sg:classifiers":[
        {
            "category":"Manufacturing",
            "subcategory":"Tools & Machinery",
            "type":"Manufacturing & Wholesale Goods"
        }
    ],
    "sg:phone":"+1 920 452 3622",
    "sg:postcode":"53083",
    "sg:province":"WI",
    "sg:tags":[
        "machine",
        "shop",
        "job",
        "ind",
        "general"
    ],
    "wof:name":"H Dahler Machine Co Inc",
    "wof:placetype":"venue"
},
  "geometry": {"coordinates":[-87.728292,43.772936],"type":"Point"}
}