{
  "type": "Feature",
  "properties": {
    "addr:full":"10520 Grant St Wisconsin Rapids WI 54494",
    "addr:housenumber":"10520",
    "addr:postcode":"54494",
    "addr:street":"Grant St",
    "iso:country":"US",
    "sg:address":"10520 Grant St",
    "sg:city":"Wisconsin Rapids",
    "sg:classifiers":[
        {
            "category":"Farming",
            "subcategory":"Livestock Farm",
            "type":"Manufacturing & Wholesale Goods"
        }
    ],
    "sg:phone":"+1 715 421 0470",
    "sg:postcode":"54494",
    "sg:province":"WI",
    "sg:tags":[
        "beef",
        "feedlot",
        "cattle"
    ],
    "wof:name":"Vernon Steinke",
    "wof:placetype":"venue"
},
  "geometry": {"coordinates":[-89.677334,44.373532],"type":"Point"}
}