{
  "type": "Feature",
  "properties": {
    "addr:full":"6333 Odana Rd Madison WI 53719",
    "addr:housenumber":"6333",
    "addr:postcode":"53719",
    "addr:street":"Odana Rd",
    "iso:country":"US",
    "sg:address":"6333 Odana Rd",
    "sg:city":"Madison",
    "sg:classifiers":[
        {
            "category":"Freight",
            "type":"Transportation"
        }
    ],
    "sg:phone":"+1 608 274 7454",
    "sg:postcode":"53719",
    "sg:province":"WI",
    "sg:tags":[
        "truck"
    ],
    "wof:name":"Transportation Consultants Inc",
    "wof:placetype":"venue"
},
  "geometry": {"coordinates":[-89.486367,43.053496],"type":"Point"}
}