{
  "type": "Feature",
  "properties": {
    "iso:country":"US",
    "sg:address":"530 W Parkway Blvd",
    "sg:city":"Appleton",
    "sg:classifiers":[
        {
            "category":"Organizations",
            "subcategory":"Religious Organization",
            "type":"Services"
        }
    ],
    "sg:phone":"+1 920 733 9561",
    "sg:postcode":"54911",
    "sg:province":"WI",
    "sg:tags":[
        "church"
    ],
    "wof:name":"Bethany Evang Lutheran Church",
    "wof:placetype":"venue"
},
  "geometry": {"coordinates":[-88.41434099999999,44.278246],"type":"Point"}
}