{
  "type": "Feature",
  "properties": {
    "iso:country":"US",
    "sg:address":"640 Park Ln",
    "sg:city":"Hazel Green",
    "sg:classifiers":[
        {
            "category":"Building & Trades",
            "subcategory":"Construction",
            "type":"Services"
        }
    ],
    "sg:phone":"+1 608 854 2145",
    "sg:postcode":"53811",
    "sg:province":"WI",
    "sg:tags":[
        "concrete",
        "contractor"
    ],
    "wof:name":"Burkholder Concrete",
    "wof:placetype":"venue"
},
  "geometry": {"coordinates":[-90.465578,42.52706],"type":"Point"}
}