{
  "type": "Feature",
  "properties": {
    "iso:country":"US",
    "sg:address":"1486 US Hwy 12",
    "sg:city":"Roberts",
    "sg:classifiers":[
        {
            "category":"Farming",
            "subcategory":"Dairy Farm",
            "type":"Manufacturing & Wholesale Goods"
        }
    ],
    "sg:phone":"+1 715 796 2605",
    "sg:postcode":"54023",
    "sg:province":"WI",
    "wof:name":"Gillis Farm Inc",
    "wof:placetype":"venue"
},
  "geometry": {"coordinates":[-92.498971,44.992601],"type":"Point"}
}