{
  "type": "Feature",
  "properties": {
    "addr:full":"5510 Lucas Ln Boulder Junction WI 54512",
    "addr:housenumber":"5510",
    "addr:postcode":"54512",
    "addr:street":"Lucas Ln",
    "iso:country":"US",
    "sg:address":"5510 Lucas Ln",
    "sg:city":"Boulder Junction",
    "sg:classifiers":[
        {
            "category":"Travel",
            "subcategory":"Hotels & Motels",
            "type":"Entertainment"
        }
    ],
    "sg:phone":"+1 715 385 2900",
    "sg:postcode":"54512",
    "sg:province":"WI",
    "sg:tags":[
        "resort"
    ],
    "wof:name":"Libby's Bear Trap Lodge",
    "wof:placetype":"venue"
},
  "geometry": {"coordinates":[-89.69068799999999,46.11553],"type":"Point"}
}