{
  "type": "Feature",
  "properties": {
    "iso:country":"US",
    "sg:address":"2040 W Wisconsin Ave",
    "sg:city":"Milwaukee",
    "sg:classifiers":[
        {
            "category":"Professional",
            "subcategory":"Employment Agencies",
            "type":"Services"
        }
    ],
    "sg:phone":"+1 414 931 8759",
    "sg:postcode":"53233",
    "sg:province":"WI",
    "wof:name":"Nurses 4 Footcare",
    "wof:placetype":"venue"
},
  "geometry": {"coordinates":[-87.938862,43.038757],"type":"Point"}
}