{
  "type": "Feature",
  "properties": {
    "addr:full":"204 W Main St Hortonville WI 54944",
    "addr:housenumber":"204",
    "addr:postcode":"54944",
    "addr:street":"W Main St",
    "iso:country":"US",
    "sg:address":"204 W Main St",
    "sg:city":"Hortonville",
    "sg:classifiers":[
        {
            "category":"Insurance",
            "subcategory":"Insurance Agent",
            "type":"Services"
        }
    ],
    "sg:phone":"+1 920 779 6000",
    "sg:postcode":"54944",
    "sg:province":"WI",
    "wof:name":"Mark Pribbenow Agency",
    "wof:placetype":"venue"
},
  "geometry": {"coordinates":[-88.640472,44.335203],"type":"Point"}
}