{
  "type": "Feature",
  "properties": {
    "iso:country":"US",
    "sg:address":"1002 W Center St",
    "sg:city":"Chetek",
    "sg:classifiers":[
        {
            "category":"Manufacturing",
            "subcategory":"Tools & Machinery",
            "type":"Manufacturing & Wholesale Goods"
        }
    ],
    "sg:phone":"+1 715 924 3009",
    "sg:postcode":"54728",
    "sg:province":"WI",
    "sg:tags":[
        "machine",
        "shop"
    ],
    "wof:name":"Lake Country Tool & Design",
    "wof:placetype":"venue"
},
  "geometry": {"coordinates":[-91.663933,45.31811],"type":"Point"}
}