{
  "type": "Feature",
  "properties": {
    "iso:country":"US",
    "sg:address":"340 W Main St",
    "sg:city":"Waukesha",
    "sg:classifiers":[
        {
            "category":"Professional",
            "subcategory":"Employment Agencies",
            "type":"Services"
        }
    ],
    "sg:phone":"+1 262 544 1651",
    "sg:postcode":"53186",
    "sg:province":"WI",
    "sg:tags":[
        "temporary"
    ],
    "wof:name":"Kelly Services",
    "wof:placetype":"venue"
},
  "geometry": {"coordinates":[-88.23191300000001,43.011579],"type":"Point"}
}