{
  "type": "Feature",
  "properties": {
    "addr:full":"3592 N Oakland Ave Milwaukee WI 53211",
    "addr:housenumber":"3592",
    "addr:postcode":"53211",
    "addr:street":"N Oakland Ave",
    "iso:country":"US",
    "sg:address":"3592 N Oakland Ave",
    "sg:city":"Milwaukee",
    "sg:classifiers":[
        {
            "category":"Restaurant",
            "type":"Food & Drink"
        }
    ],
    "sg:phone":"+1 414 967 1100",
    "sg:postcode":"53211",
    "sg:province":"WI",
    "wof:name":"Mama Mia-Felicci's",
    "wof:placetype":"venue"
},
  "geometry": {"coordinates":[-87.887776,43.082241],"type":"Point"}
}