{
  "type": "Feature",
  "properties": {
    "iso:country":"US",
    "sg:address":"1527 195th Ave",
    "sg:city":"Centuria",
    "sg:classifiers":[
        {
            "category":"Professional",
            "subcategory":"Business Services",
            "type":"Services"
        }
    ],
    "sg:phone":"+1 715 825 2030",
    "sg:postcode":"54824",
    "sg:province":"WI",
    "wof:name":"Custom Outfitters",
    "wof:placetype":"venue"
},
  "geometry": {"coordinates":[-92.476481,45.490658],"type":"Point"}
}