{
  "type": "Feature",
  "properties": {
    "addr:full":"2715 N Colony Ave Franksville WI 53126",
    "addr:housenumber":"2715",
    "addr:postcode":"53126",
    "addr:street":"N Colony Ave",
    "iso:country":"US",
    "sg:address":"2715 N Colony Ave",
    "sg:city":"Franksville",
    "sg:classifiers":[
        {
            "category":"Wholesale",
            "subcategory":"Drugs",
            "type":"Manufacturing & Wholesale Goods"
        }
    ],
    "sg:phone":"+1 262 878 3449",
    "sg:postcode":"53126",
    "sg:province":"WI",
    "wof:name":"Melaleuca Inc",
    "wof:placetype":"venue"
},
  "geometry": {"coordinates":[-88.052109,42.752388],"type":"Point"}
}