{
  "type": "Feature",
  "properties": {
    "addr:full":"2600 S Heritage Woods Dr Appleton WI 54915",
    "addr:housenumber":"2600",
    "addr:postcode":"54915",
    "addr:street":"S Heritage Woods Dr",
    "iso:country":"US",
    "sg:address":"2600 S Heritage Woods Dr",
    "sg:city":"Appleton",
    "sg:classifiers":[
        {
            "category":"Health Services",
            "subcategory":"Hospital",
            "type":"Services"
        }
    ],
    "sg:phone":"+1 920 738 3003",
    "sg:postcode":"54915",
    "sg:province":"WI",
    "sg:tags":[
        "residential",
        "care"
    ],
    "wof:name":"Heritage Living Retirement Ctr",
    "wof:placetype":"venue"
},
  "geometry": {"coordinates":[-88.415948,44.238078],"type":"Point"}
}