{
  "type": "Feature",
  "properties": {
    "iso:country":"US",
    "sg:address":"2200 W Cornell St",
    "sg:city":"Milwaukee",
    "sg:classifiers":[
        {
            "category":"Manufacturing",
            "subcategory":"Metals",
            "type":"Manufacturing & Wholesale Goods"
        }
    ],
    "sg:phone":"+1 414 445 8787",
    "sg:postcode":"53209",
    "sg:province":"WI",
    "sg:tags":[
        "metal-wholesale",
        "stamping",
        "manufacturer"
    ],
    "sg:website":"http://www.acrometalstamping.com",
    "wof:name":"Acro Metal Stamping",
    "wof:placetype":"venue"
},
  "geometry": {"coordinates":[-87.939362,43.100719],"type":"Point"}
}