{
  "type": "Feature",
  "properties": {
    "addr:full":"15224 US Hwy 8 Goodman WI 54125",
    "addr:housenumber":"15224",
    "addr:postcode":"54125",
    "addr:street":"Us Hwy 8",
    "iso:country":"US",
    "sg:address":"15224 US Hwy 8",
    "sg:city":"Goodman",
    "sg:classifiers":[
        {
            "category":"Personal",
            "type":"Services"
        }
    ],
    "sg:phone":"+1 715 336 2747",
    "sg:postcode":"54125",
    "sg:province":"WI",
    "sg:tags":[
        "program",
        "physical",
        "exercise",
        "fitness"
    ],
    "wof:name":"Fitness Factor",
    "wof:placetype":"venue"
},
  "geometry": {"coordinates":[-88.360964,45.636745],"type":"Point"}
}