{
  "type": "Feature",
  "properties": {
    "iso:country":"US",
    "sg:address":"2891 Lehman Rd",
    "sg:city":"Neosho",
    "sg:classifiers":[
        {
            "category":"Farming",
            "subcategory":"Dairy Farm",
            "type":"Manufacturing & Wholesale Goods"
        }
    ],
    "sg:phone":"+1 920 625 3084",
    "sg:postcode":"53059",
    "sg:province":"WI",
    "wof:name":"Bernard Wolter",
    "wof:placetype":"venue"
},
  "geometry": {"coordinates":[-88.54547700000001,43.333989],"type":"Point"}
}