{
  "type": "Feature",
  "properties": {
    "iso:country":"US",
    "sg:address":"8836 Co Rd J",
    "sg:city":"Woodruff",
    "sg:classifiers":[
        {
            "category":"Building & Trades",
            "subcategory":"Construction",
            "type":"Services"
        }
    ],
    "sg:phone":"+1 715 356 6524",
    "sg:postcode":"54568",
    "sg:province":"WI",
    "sg:tags":[
        "contractor"
    ],
    "wof:name":"Dennys Masonry",
    "wof:placetype":"venue"
},
  "geometry": {"coordinates":[-89.65476700000001,45.887799],"type":"Point"}
}