{
  "type": "Feature",
  "properties": {
    "iso:country":"US",
    "sg:address":"15315 State Hwy 32",
    "sg:city":"Lakewood",
    "sg:classifiers":[
        {
            "category":"Bars & Pubs",
            "type":"Food & Drink"
        }
    ],
    "sg:phone":"+1 715 276 3073",
    "sg:postcode":"54138",
    "sg:province":"WI",
    "wof:name":"Paul Bunyan's Corner Pub",
    "wof:placetype":"venue"
},
  "geometry": {"coordinates":[-88.52327200000001,45.300657],"type":"Point"}
}