{
  "type": "Feature",
  "properties": {
    "addr:full":"1730 16th St Eau Claire WI 54703",
    "addr:housenumber":"1730",
    "addr:postcode":"54703",
    "addr:street":"16Th St",
    "iso:country":"US",
    "sg:address":"1730 16th St",
    "sg:city":"Eau Claire",
    "sg:classifiers":[
        {
            "category":"Freight",
            "type":"Transportation"
        }
    ],
    "sg:phone":"+1 715 552 0164",
    "sg:postcode":"54703",
    "sg:province":"WI",
    "sg:tags":[
        "operator",
        "local",
        "trucking"
    ],
    "wof:name":"Whitetail Express Delivery",
    "wof:placetype":"venue"
},
  "geometry": {"coordinates":[-91.53047100000001,44.816823],"type":"Point"}
}