{
  "type": "Feature",
  "properties": {
    "addr:full":"2215 510th St Menomonie WI 54751",
    "addr:housenumber":"2215",
    "addr:postcode":"54751",
    "addr:street":"510Th St",
    "iso:country":"US",
    "sg:address":"2215 510th St",
    "sg:city":"Menomonie",
    "sg:classifiers":[
        {
            "category":"Farming",
            "subcategory":"Dairy Farm",
            "type":"Manufacturing & Wholesale Goods"
        }
    ],
    "sg:phone":"+1 715 664 8858",
    "sg:postcode":"54751",
    "sg:province":"WI",
    "sg:tags":[
        "corn"
    ],
    "wof:name":"Creaser John",
    "wof:placetype":"venue"
},
  "geometry": {"coordinates":[-91.903346,44.752745],"type":"Point"}
}