{
  "type": "Feature",
  "properties": {
    "iso:country":"US",
    "sg:address":"1459 1st Ave N",
    "sg:city":"Park Falls",
    "sg:classifiers":[
        {
            "category":"Building & Trades",
            "subcategory":"Landscaping Services",
            "type":"Services"
        }
    ],
    "sg:phone":"+1 715 762 2907",
    "sg:postcode":"54552",
    "sg:province":"WI",
    "sg:tags":[
        "landscape"
    ],
    "wof:name":"Mastercare Services LLC",
    "wof:placetype":"venue"
},
  "geometry": {"coordinates":[-90.447665,45.937236],"type":"Point"}
}