{
  "type": "Feature",
  "properties": {
    "iso:country":"US",
    "sg:address":"202 S Park St",
    "sg:city":"Madison",
    "sg:classifiers":[
        {
            "category":"Banks & Credit Unions",
            "subcategory":"Bank",
            "type":"Services"
        }
    ],
    "sg:phone":"+1 608 267 6019",
    "sg:postcode":"53715",
    "sg:province":"WI",
    "wof:name":"Park Bank",
    "wof:placetype":"venue"
},
  "geometry": {"coordinates":[-89.400873,43.065827],"type":"Point"}
}