{
  "type": "Feature",
  "properties": {
    "addr:full":"821 1st Ave Woodruff WI 54568",
    "addr:housenumber":"821",
    "addr:postcode":"54568",
    "addr:street":"1St Ave",
    "iso:country":"US",
    "sg:address":"821 1st Ave",
    "sg:city":"Woodruff",
    "sg:classifiers":[
        {
            "category":"Retail",
            "subcategory":"Car Wash",
            "type":"Services"
        }
    ],
    "sg:phone":"+1 715 356 3855",
    "sg:postcode":"54568",
    "sg:province":"WI",
    "sg:tags":[
        "automobile",
        "detail",
        "clean"
    ],
    "wof:name":"Tender Wash",
    "wof:placetype":"venue"
},
  "geometry": {"coordinates":[-89.700238,45.896984],"type":"Point"}
}