{
  "type": "Feature",
  "properties": {
    "iso:country":"US",
    "sg:address":"901 Main St",
    "sg:city":"Union Grove",
    "sg:classifiers":[
        {
            "category":"Insurance",
            "subcategory":"Insurance Agent",
            "type":"Services"
        }
    ],
    "sg:phone":"+1 262 878 5300",
    "sg:postcode":"53182",
    "sg:province":"WI",
    "wof:name":"Lisa Johnson Agency",
    "wof:placetype":"venue"
},
  "geometry": {"coordinates":[-88.051889,42.689175],"type":"Point"}
}