{
  "type": "Feature",
  "properties": {
    "iso:country":"US",
    "sg:address":"251 W Althea Dr",
    "sg:city":"Grafton",
    "sg:classifiers":[
        {
            "category":"Professional",
            "subcategory":"Detective & Security Services",
            "type":"Services"
        }
    ],
    "sg:phone":"+1 262 375 9992",
    "sg:postcode":"53024",
    "sg:province":"WI",
    "sg:tags":[
        "car"
    ],
    "wof:name":"Alliance Investigation",
    "wof:placetype":"venue"
},
  "geometry": {"coordinates":[-87.96857,43.312326],"type":"Point"}
}