{
  "type": "Feature",
  "properties": {
    "addr:full":"46 N Brown St Rhinelander WI 54501",
    "addr:housenumber":"46",
    "addr:postcode":"54501",
    "addr:street":"N Brown St",
    "iso:country":"US",
    "sg:address":"46 N Brown St",
    "sg:city":"Rhinelander",
    "sg:classifiers":[
        {
            "category":"Restaurant",
            "type":"Food & Drink"
        }
    ],
    "sg:phone":"+1 715 369 5333",
    "sg:postcode":"54501",
    "sg:province":"WI",
    "sg:tags":[
        "eating"
    ],
    "wof:name":"Garden Of Eatin' Restaurant",
    "wof:placetype":"venue"
},
  "geometry": {"coordinates":[-89.412685,45.638453],"type":"Point"}
}