{
  "type": "Feature",
  "properties": {
    "iso:country":"US",
    "sg:address":"5017 S 110th St",
    "sg:city":"Milwaukee",
    "sg:classifiers":[
        {
            "category":"Health Services",
            "subcategory":"Hospital",
            "type":"Services"
        }
    ],
    "sg:phone":"+1 414 425 0432",
    "sg:postcode":"53228",
    "sg:province":"WI",
    "sg:tags":[
        "dialysis"
    ],
    "wof:name":"Midwest Dialysis Center Acute Center",
    "wof:placetype":"venue"
},
  "geometry": {"coordinates":[-88.05025999999999,42.953104],"type":"Point"}
}