{
  "type": "Feature",
  "properties": {
    "addr:full":"219 Wisconsin St Oshkosh WI 54901",
    "addr:housenumber":"219",
    "addr:postcode":"54901",
    "addr:street":"Wisconsin St",
    "iso:country":"US",
    "sg:address":"219 Wisconsin St",
    "sg:city":"Oshkosh",
    "sg:classifiers":[
        {
            "category":"Bars & Pubs",
            "type":"Food & Drink"
        }
    ],
    "sg:phone":"+1 920 233 1510",
    "sg:postcode":"54901",
    "sg:province":"WI",
    "sg:tags":[
        "drinking",
        "eating"
    ],
    "sg:website":"www.kellysbarosh.com",
    "wof:name":"Kelly's Bar",
    "wof:placetype":"venue"
},
  "geometry": {"coordinates":[-88.547017,44.021704],"type":"Point"}
}