{
  "type": "Feature",
  "properties": {
    "iso:country":"US",
    "sg:address":"11715 N Port Washington Rd",
    "sg:city":"Mequon",
    "sg:classifiers":[
        {
            "category":"Banks & Credit Unions",
            "subcategory":"Bank",
            "type":"Services"
        },
        {
            "category":"Banks & Credit Unions",
            "subcategory":"Financial Services",
            "type":"Services"
        }
    ],
    "sg:phone":"+1 262 292 0014",
    "sg:postcode":"53092",
    "sg:province":"WI",
    "sg:tags":[
        "broker",
        "mortgage"
    ],
    "sg:website":"www.theequitablebank.com",
    "wof:name":"Equitable Bank Ssb",
    "wof:placetype":"venue"
},
  "geometry": {"coordinates":[-87.924239,43.231137],"type":"Point"}
}