{
  "type": "Feature",
  "properties": {
    "iso:country":"US",
    "sg:address":"2431 Sunrise Ct",
    "sg:city":"Plover",
    "sg:classifiers":[
        {
            "category":"Shopping",
            "subcategory":"Catalog Store",
            "type":"Retail Goods"
        }
    ],
    "sg:phone":"+1 715 344 4924",
    "sg:postcode":"54467",
    "sg:province":"WI",
    "sg:tags":[
        "mfg",
        "house",
        "trade",
        "printing",
        "stationery",
        "mail"
    ],
    "wof:name":"Center For Excellence",
    "wof:placetype":"venue"
},
  "geometry": {"coordinates":[-89.524569,44.461697],"type":"Point"}
}