{
  "type": "Feature",
  "properties": {
    "iso:country":"US",
    "sg:address":"15121 145th St",
    "sg:city":"Bloomer",
    "sg:classifiers":[
        {
            "category":"Organizations",
            "subcategory":"Religious Organization",
            "type":"Services"
        }
    ],
    "sg:phone":"+1 715 288 6523",
    "sg:postcode":"54724",
    "sg:province":"WI",
    "sg:tags":[
        "church"
    ],
    "wof:name":"St John's Ev Lutheran Church",
    "wof:placetype":"venue"
},
  "geometry": {"coordinates":[-91.379057,45.062849],"type":"Point"}
}