{
  "type": "Feature",
  "properties": {
    "iso:country":"US",
    "sg:address":"91 S Main St",
    "sg:city":"Fond Du Lac",
    "sg:classifiers":[
        {
            "category":"Restaurant",
            "type":"Food & Drink"
        }
    ],
    "sg:phone":"+1 920 907 1368",
    "sg:postcode":"54935",
    "sg:province":"WI",
    "sg:tags":[
        "eating"
    ],
    "wof:name":"Panda House Chinese Buffet",
    "wof:placetype":"venue"
},
  "geometry": {"coordinates":[-88.44684599999999,43.77693],"type":"Point"}
}