{
  "type": "Feature",
  "properties": {
    "addr:full":"711 Main St Wrightstown WI 54180",
    "addr:housenumber":"711",
    "addr:postcode":"54180",
    "addr:street":"Main St",
    "iso:country":"US",
    "sg:address":"711 Main St",
    "sg:city":"Wrightstown",
    "sg:classifiers":[
        {
            "category":"Retail",
            "subcategory":"Funeral Services",
            "type":"Services"
        }
    ],
    "sg:phone":"+1 920 532 4366",
    "sg:postcode":"54180",
    "sg:province":"WI",
    "sg:tags":[
        "director"
    ],
    "wof:name":"De Wane-Cotter Funeral Home",
    "wof:placetype":"venue"
},
  "geometry": {"coordinates":[-88.170304,44.326307],"type":"Point"}
}