{
  "type": "Feature",
  "properties": {
    "iso:country":"US",
    "sg:address":"178 University Dr",
    "sg:city":"Fond Du Lac",
    "sg:classifiers":[
        {
            "category":"Wholesale",
            "subcategory":"Machinery & Supplies",
            "type":"Manufacturing & Wholesale Goods"
        }
    ],
    "sg:phone":"+1 920 921 1067",
    "sg:postcode":"54935",
    "sg:province":"WI",
    "sg:tags":[
        "janitorial"
    ],
    "wof:name":"Palmer Company Inc",
    "wof:placetype":"venue"
},
  "geometry": {"coordinates":[-88.415001,43.783404],"type":"Point"}
}