{
  "type": "Feature",
  "properties": {
    "iso:country":"US",
    "sg:address":"13133 N Port Washington Rd",
    "sg:city":"Mequon",
    "sg:classifiers":[
        {
            "category":"Health Services",
            "subcategory":"Doctor",
            "type":"Services"
        }
    ],
    "sg:phone":"+1 262 243 3660",
    "sg:postcode":"53097",
    "sg:province":"WI",
    "sg:tags":[
        "physician",
        "surgeon"
    ],
    "wof:name":"ENT Assoc",
    "wof:placetype":"venue"
},
  "geometry": {"coordinates":[-87.924246,43.259003],"type":"Point"}
}