{
  "type": "Feature",
  "properties": {
    "iso:country":"US",
    "sg:address":"14332 Town Hall Rd",
    "sg:city":"Fairchild",
    "sg:classifiers":[
        {
            "category":"Farming",
            "subcategory":"Livestock Farm",
            "type":"Manufacturing & Wholesale Goods"
        }
    ],
    "sg:phone":"+1 715 334 5699",
    "sg:postcode":"54741",
    "sg:province":"WI",
    "sg:tags":[
        "feedlot",
        "corn",
        "soybean",
        "beef",
        "cattle"
    ],
    "wof:name":"Orville Olsen",
    "wof:placetype":"venue"
},
  "geometry": {"coordinates":[-90.983182,44.587782],"type":"Point"}
}