{
  "type": "Feature",
  "properties": {
    "iso:country":"US",
    "sg:address":"2454 Co Rd Hh",
    "sg:city":"Lyndon Station",
    "sg:classifiers":[
        {
            "category":"Shopping",
            "subcategory":"Stationery & Office Supplies",
            "type":"Retail Goods"
        }
    ],
    "sg:phone":"+1 608 666 3331",
    "sg:postcode":"53944",
    "sg:province":"WI",
    "sg:tags":[
        "map"
    ],
    "wof:name":"County Maps",
    "wof:placetype":"venue"
},
  "geometry": {"coordinates":[-89.88227500000001,43.725304],"type":"Point"}
}