{
  "type": "Feature",
  "properties": {
    "addr:full":"210 N Main St Potosi WI 53820",
    "addr:housenumber":"210",
    "addr:postcode":"53820",
    "addr:street":"N Main St",
    "iso:country":"US",
    "sg:address":"210 N Main St",
    "sg:city":"Potosi",
    "sg:classifiers":[
        {
            "category":"Professional",
            "type":"Services"
        }
    ],
    "sg:phone":"+1 608 763 4304",
    "sg:postcode":"53820",
    "sg:province":"WI",
    "sg:tags":[
        "establishment"
    ],
    "wof:name":"Potosi Fire & Rescue",
    "wof:placetype":"venue"
},
  "geometry": {"coordinates":[-90.694271,42.696619],"type":"Point"}
}