{
  "type": "Feature",
  "properties": {
    "iso:country":"US",
    "sg:address":"7017 W Greenfield Ave",
    "sg:city":"Milwaukee",
    "sg:classifiers":[
        {
            "category":"Shopping",
            "subcategory":"Hobbies, Toys, & Games",
            "type":"Retail Goods"
        }
    ],
    "sg:phone":"+1 414 259 0532",
    "sg:postcode":"53214",
    "sg:province":"WI",
    "sg:tags":[
        "supply"
    ],
    "wof:name":"Zajal & Jypsys Game Castle",
    "wof:placetype":"venue"
},
  "geometry": {"coordinates":[-88.00117299999999,43.016594],"type":"Point"}
}