{
  "type": "Feature",
  "properties": {
    "iso:country":"US",
    "sg:address":"1022 Michigan Ave",
    "sg:city":"Sheboygan",
    "sg:classifiers":[
        {
            "category":"Arts & Performance",
            "subcategory":"Theater",
            "type":"Entertainment"
        }
    ],
    "sg:phone":"+1 920 694 0300",
    "sg:postcode":"53081",
    "sg:province":"WI",
    "sg:tags":[
        "group",
        "eating"
    ],
    "sg:website":"www.wonderfulworldcoffeehouse.com",
    "wof:name":"Wonderful World",
    "wof:placetype":"venue"
},
  "geometry": {"coordinates":[-87.717676,43.758619],"type":"Point"}
}