{
  "type": "Feature",
  "properties": {
    "iso:country":"US",
    "sg:address":"810 4th Ave N",
    "sg:city":"Onalaska",
    "sg:classifiers":[
        {
            "category":"Building & Trades",
            "subcategory":"Construction",
            "type":"Services"
        }
    ],
    "sg:phone":"+1 608 783 4619",
    "sg:postcode":"54650",
    "sg:province":"WI",
    "sg:tags":[
        "house"
    ],
    "wof:name":"Quality Builders LLC",
    "wof:placetype":"venue"
},
  "geometry": {"coordinates":[-91.236476,43.894746],"type":"Point"}
}