{
  "type": "Feature",
  "properties": {
    "iso:country":"US",
    "sg:address":"1713 S Wacouta Ave",
    "sg:city":"Prairie Du Chien",
    "sg:classifiers":[
        {
            "category":"Home & Garden",
            "subcategory":"Garden Supply",
            "type":"Retail Goods"
        }
    ],
    "sg:phone":"+1 608 326 6224",
    "sg:postcode":"53821",
    "sg:province":"WI",
    "sg:tags":[
        "landscape"
    ],
    "wof:name":"Garden City South",
    "wof:placetype":"venue"
},
  "geometry": {"coordinates":[-91.141762,43.030419],"type":"Point"}
}