{
  "type": "Feature",
  "properties": {
    "addr:full":"1439 Dayton St Mayville WI 53050",
    "addr:housenumber":"1439",
    "addr:postcode":"53050",
    "addr:street":"Dayton St",
    "iso:country":"US",
    "sg:address":"1439 Dayton St",
    "sg:city":"Mayville",
    "sg:classifiers":[
        {
            "category":"Real Estate",
            "subcategory":"Real Estate Operator",
            "type":"Services"
        }
    ],
    "sg:phone":"+1 920 387 3166",
    "sg:postcode":"53050",
    "sg:province":"WI",
    "sg:tags":[
        "apartment"
    ],
    "wof:name":"Mayville Heights",
    "wof:placetype":"venue"
},
  "geometry": {"coordinates":[-88.55876499999999,43.497627],"type":"Point"}
}