{
  "type": "Feature",
  "properties": {
    "iso:country":"US",
    "sg:address":"1705 US Hwy 14",
    "sg:city":"Richland Center",
    "sg:classifiers":[
        {
            "category":"Home & Garden",
            "subcategory":"Building Materials",
            "type":"Retail Goods"
        }
    ],
    "sg:phone":"+1 608 647 8722",
    "sg:postcode":"53581",
    "sg:province":"WI",
    "sg:tags":[
        "mixed",
        "concrete"
    ],
    "wof:name":"Richland Center Redi-Mix",
    "wof:placetype":"venue"
},
  "geometry": {"coordinates":[-90.37478900000001,43.320799],"type":"Point"}
}