{
  "type": "Feature",
  "properties": {
    "iso:country":"US",
    "sg:address":"4110 Brookhaven Trce",
    "sg:city":"Wisconsin Rapids",
    "sg:classifiers":[
        {
            "category":"Autos & Motor Vehicles",
            "subcategory":"Automobile Sales",
            "type":"Retail Goods"
        }
    ],
    "sg:phone":"+1 715 424 0706",
    "sg:postcode":"54494",
    "sg:province":"WI",
    "sg:tags":[
        "used"
    ],
    "wof:name":"Tjs Auto and Body Inc",
    "wof:placetype":"venue"
},
  "geometry": {"coordinates":[-89.771738,44.357115],"type":"Point"}
}