{
  "type": "Feature",
  "properties": {
    "iso:country":"US",
    "sg:address":"2535 Greenbrier Rd",
    "sg:city":"Green Bay",
    "sg:classifiers":[
        {
            "category":"Manufacturing",
            "subcategory":"Toys & Sporting Goods",
            "type":"Manufacturing & Wholesale Goods"
        }
    ],
    "sg:phone":"+1 920 406 9616",
    "sg:postcode":"54311",
    "sg:province":"WI",
    "sg:tags":[
        "mfg"
    ],
    "wof:name":"Sigma Game Inc",
    "wof:placetype":"venue"
},
  "geometry": {"coordinates":[-87.95585699999999,44.473506],"type":"Point"}
}