{
  "type": "Feature",
  "properties": {
    "addr:full":"6329 W Greenfield Ave Milwaukee WI 53214",
    "addr:housenumber":"6329",
    "addr:postcode":"53214",
    "addr:street":"W Greenfield Ave",
    "iso:country":"US",
    "sg:address":"6329 W Greenfield Ave",
    "sg:city":"Milwaukee",
    "sg:classifiers":[
        {
            "category":"Personal",
            "subcategory":"Beauty Salon",
            "type":"Services"
        }
    ],
    "sg:phone":"+1 414 302 1019",
    "sg:postcode":"53214",
    "sg:province":"WI",
    "sg:tags":[
        "shop"
    ],
    "wof:name":"Basic Nails",
    "wof:placetype":"venue"
},
  "geometry": {"coordinates":[-87.99185900000001,43.016655],"type":"Point"}
}