{
  "type": "Feature",
  "properties": {
    "iso:country":"US",
    "sg:address":"3915 Durand Ave",
    "sg:city":"Racine",
    "sg:classifiers":[
        {
            "category":"Food & Beverages",
            "subcategory":"Groceries & Convenience Stores",
            "type":"Retail Goods"
        }
    ],
    "sg:phone":"+1 262 554 8696",
    "sg:postcode":"53405",
    "sg:province":"WI",
    "sg:tags":[
        "grocer"
    ],
    "wof:name":"Kohl's Food Store",
    "wof:placetype":"venue"
},
  "geometry": {"coordinates":[-87.827046,42.696786],"type":"Point"}
}