{
  "type": "Feature",
  "properties": {
    "iso:country":"US",
    "sg:address":"5 W Walworth St",
    "sg:city":"Elkhorn",
    "sg:classifiers":[
        {
            "category":"Real Estate",
            "subcategory":"Real Estate Services",
            "type":"Services"
        }
    ],
    "sg:phone":"+1 262 743 1515",
    "sg:postcode":"53121",
    "sg:province":"WI",
    "sg:tags":[
        "company",
        "title"
    ],
    "wof:name":"Landmark Title Of Walworth",
    "wof:placetype":"venue"
},
  "geometry": {"coordinates":[-88.543544,42.671903],"type":"Point"}
}