{
  "type": "Feature",
  "properties": {
    "iso:country":"US",
    "sg:address":"22660 State Rd 48",
    "sg:city":"Grantsburg",
    "sg:classifiers":[
        {
            "category":"Farming",
            "subcategory":"Dairy Farm",
            "type":"Manufacturing & Wholesale Goods"
        }
    ],
    "sg:phone":"+1 715 463 5685",
    "sg:postcode":"54840",
    "sg:province":"WI",
    "sg:tags":[
        "feedlot",
        "grain",
        "cash",
        "beef",
        "cattle"
    ],
    "wof:name":"Bevan Branstad",
    "wof:placetype":"venue"
},
  "geometry": {"coordinates":[-92.681879,45.743727],"type":"Point"}
}