{
  "type": "Feature",
  "properties": {
    "iso:country":"US",
    "sg:address":"2819 Washington Ave",
    "sg:city":"Racine",
    "sg:classifiers":[
        {
            "category":"Retail",
            "subcategory":"Portrait Studio",
            "type":"Services"
        }
    ],
    "sg:phone":"+1 262 637 7502",
    "sg:postcode":"53405",
    "sg:province":"WI",
    "sg:tags":[
        "photographer"
    ],
    "wof:name":"J C Penney Co",
    "wof:placetype":"venue"
},
  "geometry": {"coordinates":[-87.813599,42.716733],"type":"Point"}
}