{
  "type": "Feature",
  "properties": {
    "iso:country":"US",
    "sg:address":"325 Lois St",
    "sg:city":"Rhinelander",
    "sg:classifiers":[
        {
            "category":"Shopping",
            "subcategory":"Clothing, Apparel, & Fashions",
            "type":"Retail Goods"
        }
    ],
    "sg:phone":"+1 715 362 5452",
    "sg:postcode":"54501",
    "sg:province":"WI",
    "sg:tags":[
        "association"
    ],
    "wof:name":"Nicolet Male Chorus",
    "wof:placetype":"venue"
},
  "geometry": {"coordinates":[-89.434489,45.642005],"type":"Point"}
}