{
  "type": "Feature",
  "properties": {
    "addr:full":"730 Houston St Minong WI 54859",
    "addr:housenumber":"730",
    "addr:postcode":"54859",
    "addr:street":"Houston St",
    "iso:country":"US",
    "sg:address":"730 Houston St",
    "sg:city":"Minong",
    "sg:classifiers":[
        {
            "category":"Manufacturing",
            "subcategory":"Watercraft",
            "type":"Manufacturing & Wholesale Goods"
        }
    ],
    "sg:phone":"+1 715 466 5247",
    "sg:postcode":"54859",
    "sg:province":"WI",
    "sg:tags":[
        "boat"
    ],
    "wof:name":"Smoker-Craft",
    "wof:placetype":"venue"
},
  "geometry": {"coordinates":[-91.831368,46.097008],"type":"Point"}
}