{
  "type": "Feature",
  "properties": {
    "addr:full":"7501 N 81st St Milwaukee WI 53223",
    "addr:housenumber":"7501",
    "addr:postcode":"53223",
    "addr:street":"N 81St St",
    "iso:country":"US",
    "sg:address":"7501 N 81st St",
    "sg:city":"Milwaukee",
    "sg:classifiers":[
        {
            "category":"Professional",
            "subcategory":"Advertising",
            "type":"Services"
        }
    ],
    "sg:phone":"+1 414 586 0605",
    "sg:postcode":"53223",
    "sg:province":"WI",
    "sg:tags":[
        "distributing",
        "sample",
        "service-circular"
    ],
    "wof:name":"Almo Distributing Wisconsin",
    "wof:placetype":"venue"
},
  "geometry": {"coordinates":[-88.01129899999999,43.15395],"type":"Point"}
}