{
  "type": "Feature",
  "properties": {
    "iso:country":"US",
    "sg:address":"241 5th St",
    "sg:city":"Hartford",
    "sg:classifiers":[
        {
            "category":"Shopping",
            "subcategory":"Catalog Store",
            "type":"Retail Goods"
        }
    ],
    "sg:phone":"+1 262 673 4733",
    "sg:postcode":"53027",
    "sg:province":"WI",
    "sg:tags":[
        "mail",
        "house"
    ],
    "wof:name":"Judy Weed",
    "wof:placetype":"venue"
},
  "geometry": {"coordinates":[-88.372971,43.321086],"type":"Point"}
}