{
  "type": "Feature",
  "properties": {
    "iso:country":"US",
    "sg:address":"1914 Co Rd Q",
    "sg:city":"Montfort",
    "sg:classifiers":[
        {
            "category":"Farming",
            "subcategory":"Livestock Farm",
            "type":"Manufacturing & Wholesale Goods"
        }
    ],
    "sg:phone":"+1 608 822 6876",
    "sg:postcode":"53569",
    "sg:province":"WI",
    "sg:tags":[
        "feedlot",
        "field",
        "crop",
        "beef",
        "cattle"
    ],
    "wof:name":"Michael Hrubes",
    "wof:placetype":"venue"
},
  "geometry": {"coordinates":[-90.50126400000001,43.048657],"type":"Point"}
}