{
  "type": "Feature",
  "properties": {
    "iso:country":"US",
    "sg:address":"1879 W Bone Lake Dr",
    "sg:city":"Balsam Lake",
    "sg:classifiers":[
        {
            "category":"Bars & Pubs",
            "type":"Food & Drink"
        }
    ],
    "sg:phone":"+1 715 857 5679",
    "sg:postcode":"54810",
    "sg:province":"WI",
    "sg:tags":[
        "drinking",
        "eating",
        "operation"
    ],
    "wof:name":"Blacksmith Shop Motel",
    "wof:placetype":"venue"
},
  "geometry": {"coordinates":[-92.38375600000001,45.48083],"type":"Point"}
}