{
  "type": "Feature",
  "properties": {
    "iso:country":"US",
    "sg:address":"514 Jefferson Ave",
    "sg:city":"Lake Geneva",
    "sg:classifiers":[
        {
            "category":"Building & Trades",
            "subcategory":"Construction",
            "type":"Services"
        }
    ],
    "sg:phone":"+1 262 248 9227",
    "sg:postcode":"53147",
    "sg:province":"WI",
    "sg:tags":[
        "house"
    ],
    "wof:name":"J&J Construction Southern WI",
    "wof:placetype":"venue"
},
  "geometry": {"coordinates":[-88.445076,42.596923],"type":"Point"}
}