{
  "type": "Feature",
  "properties": {
    "iso:country":"US",
    "sg:address":"3416 S 27th St",
    "sg:city":"Milwaukee",
    "sg:classifiers":[
        {
            "category":"Health Services",
            "subcategory":"Optometrist",
            "type":"Services"
        }
    ],
    "sg:phone":"+1 414 384 2020",
    "sg:postcode":"53215",
    "sg:province":"WI",
    "wof:name":"Darwin Eye Care LLC",
    "wof:placetype":"venue"
},
  "geometry": {"coordinates":[-87.948281,42.981566],"type":"Point"}
}