{
  "type": "Feature",
  "properties": {
    "iso:country":"US",
    "sg:address":"7535 Bramer Rd",
    "sg:city":"Trego",
    "sg:classifiers":[
        {
            "category":"Building & Trades",
            "subcategory":"Construction",
            "type":"Services"
        }
    ],
    "sg:phone":"+1 715 466 4570",
    "sg:postcode":"54888",
    "sg:province":"WI",
    "sg:tags":[
        "excavation",
        "contractor"
    ],
    "wof:name":"Tractor Service",
    "wof:placetype":"venue"
},
  "geometry": {"coordinates":[-91.928241,45.99799],"type":"Point"}
}