{
  "type": "Feature",
  "properties": {
    "iso:country":"US",
    "sg:address":"129 N Main St",
    "sg:city":"Oconto Falls",
    "sg:classifiers":[
        {
            "category":"Manufacturing",
            "subcategory":"Textiles",
            "type":"Manufacturing & Wholesale Goods"
        }
    ],
    "sg:phone":"+1 920 846 2355",
    "sg:postcode":"54154",
    "sg:province":"WI",
    "sg:tags":[
        "screen",
        "printing",
        "embroidery"
    ],
    "wof:name":"Topline Graphics",
    "wof:placetype":"venue"
},
  "geometry": {"coordinates":[-88.14372,44.875086],"type":"Point"}
}