{
  "type": "Feature",
  "properties": {
    "iso:country":"US",
    "sg:address":"313 Harriman Ave N",
    "sg:city":"Amery",
    "sg:classifiers":[
        {
            "category":"Retail",
            "subcategory":"Repair Shop",
            "type":"Services"
        }
    ],
    "sg:phone":"+1 715 268 9183",
    "sg:postcode":"54001",
    "sg:province":"WI",
    "sg:tags":[
        "lock",
        "locksmith"
    ],
    "wof:name":"Swanberg Security & Invstgtns",
    "wof:placetype":"venue"
},
  "geometry": {"coordinates":[-92.363677,45.314373],"type":"Point"}
}