{
  "type": "Feature",
  "properties": {
    "addr:full":"1829 Cherry Ave Brantwood WI 54513",
    "addr:housenumber":"1829",
    "addr:postcode":"54513",
    "addr:street":"Cherry Ave",
    "iso:country":"US",
    "sg:address":"1829 Cherry Ave",
    "sg:city":"Brantwood",
    "sg:phone":"+1 715 564 2474",
    "sg:postcode":"54513",
    "sg:province":"WI",
    "sg:tags":[
        "farm",
        "field",
        "crop"
    ],
    "wof:name":"Peter Peterson",
    "wof:placetype":"venue"
},
  "geometry": {"coordinates":[-90.128308,45.523464],"type":"Point"}
}