{
  "type": "Feature",
  "properties": {
    "iso:country":"US",
    "sg:address":"1911 Green St",
    "sg:city":"Racine",
    "sg:classifiers":[
        {
            "category":"Organizations",
            "subcategory":"Religious Organization",
            "type":"Services"
        }
    ],
    "sg:phone":"+1 262 637 6296",
    "sg:postcode":"53402",
    "sg:province":"WI",
    "wof:name":"School Sisters of St Frances",
    "wof:placetype":"venue"
},
  "geometry": {"coordinates":[-87.789788,42.745672],"type":"Point"}
}