{
  "type": "Feature",
  "properties": {
    "iso:country":"US",
    "sg:address":"5446 Park St",
    "sg:city":"Boulder Junction",
    "sg:classifiers":[
        {
            "category":"Professional",
            "subcategory":"Lawyer & Legal Services",
            "type":"Services"
        }
    ],
    "sg:phone":"+1 715 385 2047",
    "sg:postcode":"54512",
    "sg:province":"WI",
    "wof:name":"Obrien Anderson Garbowicz &",
    "wof:placetype":"venue"
},
  "geometry": {"coordinates":[-89.640524,46.111591],"type":"Point"}
}