{
  "type": "Feature",
  "properties": {
    "iso:country":"US",
    "sg:address":"615 South Blvd",
    "sg:city":"Baraboo",
    "sg:classifiers":[
        {
            "category":"Autos & Motor Vehicles",
            "subcategory":"Automobile Sales",
            "type":"Retail Goods"
        }
    ],
    "sg:phone":"+1 608 356 2222",
    "sg:postcode":"53913",
    "sg:province":"WI",
    "sg:tags":[
        "car",
        "dealer"
    ],
    "wof:name":"Glacier Valley Ford-Mercury",
    "wof:placetype":"venue"
},
  "geometry": {"coordinates":[-89.75202899999999,43.460208],"type":"Point"}
}