{
  "type": "Feature",
  "properties": {
    "iso:country":"US",
    "sg:address":"817 N 8th St",
    "sg:city":"Sheboygan",
    "sg:classifiers":[
        {
            "category":"Social Services",
            "type":"Services"
        }
    ],
    "sg:phone":"+1 920 452 6875",
    "sg:postcode":"53081",
    "sg:province":"WI",
    "sg:tags":[
        "support",
        "group"
    ],
    "wof:name":"Open Door",
    "wof:placetype":"venue"
},
  "geometry": {"coordinates":[-87.712858,43.753982],"type":"Point"}
}