{
  "type": "Feature",
  "properties": {
    "iso:country":"US",
    "sg:address":"615 McLean Ave",
    "sg:city":"Tomah",
    "sg:classifiers":[
        {
            "category":"Professional",
            "subcategory":"Management & Consulting",
            "type":"Services"
        }
    ],
    "sg:phone":"+1 608 372 9557",
    "sg:postcode":"54660",
    "sg:province":"WI",
    "wof:name":"Larson Jay Aid Assoc For Luthe",
    "wof:placetype":"venue"
},
  "geometry": {"coordinates":[-90.506259,43.981377],"type":"Point"}
}