{
  "type": "Feature",
  "properties": {
    "iso:country":"US",
    "sg:address":"4202 Amberidge Dr",
    "sg:city":"Franklin",
    "sg:classifiers":[
        {
            "category":"Social Services",
            "type":"Services"
        }
    ],
    "sg:phone":"+1 414 423 5362",
    "sg:postcode":"53132",
    "sg:province":"WI",
    "sg:tags":[
        "organization",
        "welfare"
    ],
    "wof:name":"Community Options",
    "wof:placetype":"venue"
},
  "geometry": {"coordinates":[-87.967744,42.912226],"type":"Point"}
}