{
  "type": "Feature",
  "properties": {
    "addr:full":"529 Franklin St Wausau WI 54403",
    "addr:housenumber":"529",
    "addr:postcode":"54403",
    "addr:street":"Franklin St",
    "iso:country":"US",
    "sg:address":"529 Franklin St",
    "sg:city":"Wausau",
    "sg:classifiers":[
        {
            "category":"Professional",
            "subcategory":"Lawyer & Legal Services",
            "type":"Services"
        }
    ],
    "sg:phone":"+1 715 843 7547",
    "sg:postcode":"54403",
    "sg:province":"WI",
    "sg:tags":[
        "attorney"
    ],
    "wof:name":"Corbett Law Office",
    "wof:placetype":"venue"
},
  "geometry": {"coordinates":[-89.623617,44.962993],"type":"Point"}
}