{
  "type": "Feature",
  "properties": {
    "iso:country":"US",
    "sg:address":"22 E Franklin Ave",
    "sg:city":"Barron",
    "sg:classifiers":[
        {
            "category":"Real Estate",
            "subcategory":"Real Estate Agent",
            "type":"Services"
        }
    ],
    "sg:phone":"+1 715 637 5713",
    "sg:postcode":"54812",
    "sg:province":"WI",
    "wof:name":"M & M Asset Ventures LLC",
    "wof:placetype":"venue"
},
  "geometry": {"coordinates":[-91.857949,45.402332],"type":"Point"}
}