{
  "type": "Feature",
  "properties": {
    "iso:country":"US",
    "sg:address":"2809 Maple Rd",
    "sg:city":"Pulaski",
    "sg:classifiers":[
        {
            "category":"Building & Trades",
            "subcategory":"Construction",
            "type":"Services"
        }
    ],
    "sg:phone":"+1 920 822 3988",
    "sg:postcode":"54162",
    "sg:province":"WI",
    "sg:tags":[
        "concrete",
        "contractor"
    ],
    "wof:name":"Bath Concrete Construction",
    "wof:placetype":"venue"
},
  "geometry": {"coordinates":[-88.293397,44.686674],"type":"Point"}
}