{
  "type": "Feature",
  "properties": {
    "addr:full":"818 Whispering Oaks Rd Oregon WI 53575",
    "addr:housenumber":"818",
    "addr:postcode":"53575",
    "addr:street":"Whispering Oaks Rd",
    "iso:country":"US",
    "sg:address":"818 Whispering Oaks Rd",
    "sg:city":"Oregon",
    "sg:classifiers":[
        {
            "category":"Education",
            "subcategory":"Special Training",
            "type":"Public Place"
        }
    ],
    "sg:phone":"+1 608 263 8610",
    "sg:postcode":"53575",
    "sg:province":"WI",
    "sg:tags":[
        "educational"
    ],
    "wof:name":"Donna Alberti",
    "wof:placetype":"venue"
},
  "geometry": {"coordinates":[-89.42479,42.897857],"type":"Point"}
}