{
  "type": "Feature",
  "properties": {
    "iso:country":"US",
    "sg:address":"5673 King James Ct",
    "sg:city":"Fitchburg",
    "sg:classifiers":[
        {
            "category":"Education",
            "subcategory":"School",
            "type":"Public Place"
        }
    ],
    "sg:phone":"+1 608 273 4932",
    "sg:postcode":"53719",
    "sg:province":"WI",
    "wof:name":"Verona Area School",
    "wof:placetype":"venue"
},
  "geometry": {"coordinates":[-89.477121,43.020192],"type":"Point"}
}