{
  "type": "Feature",
  "properties": {
    "iso:country":"US",
    "sg:address":"1000 Log Lodge Ct",
    "sg:city":"Baraboo",
    "sg:classifiers":[
        {
            "category":"Government",
            "subcategory":"Office",
            "type":"Public Place"
        }
    ],
    "sg:phone":"+1 608 355 3178",
    "sg:postcode":"53913",
    "sg:province":"WI",
    "sg:tags":[
        "state",
        "resource"
    ],
    "wof:name":"Unemployment Compensation",
    "wof:placetype":"venue"
},
  "geometry": {"coordinates":[-89.76953399999999,43.480064],"type":"Point"}
}