{
  "type": "Feature",
  "properties": {
    "iso:country":"US",
    "sg:address":"1203 N Main St",
    "sg:city":"Oshkosh",
    "sg:classifiers":[
        {
            "category":"Shopping",
            "subcategory":"Computers & Home Electronics",
            "type":"Retail Goods"
        }
    ],
    "sg:phone":"+1 920 231 2653",
    "sg:postcode":"54901",
    "sg:province":"WI",
    "sg:tags":[
        "repair"
    ],
    "wof:name":"Bobs TV & CB Repair",
    "wof:placetype":"venue"
},
  "geometry": {"coordinates":[-88.53767000000001,44.033347],"type":"Point"}
}