{
  "type": "Feature",
  "properties": {
    "iso:country":"US",
    "sg:address":"1680 Sharon Ln",
    "sg:city":"Grafton",
    "sg:classifiers":[
        {
            "category":"Real Estate",
            "subcategory":"Real Estate Operator",
            "type":"Services"
        },
        {
            "category":"Building & Trades",
            "subcategory":"Construction",
            "type":"Services"
        }
    ],
    "sg:phone":"+1 262 377 6878",
    "sg:postcode":"53024",
    "sg:province":"WI",
    "sg:tags":[
        "apartment",
        "contractor"
    ],
    "wof:name":"Hoffmann Robert G Co Bldg Contr",
    "wof:placetype":"venue"
},
  "geometry": {"coordinates":[-87.9487,43.345299],"type":"Point"}
}