{
  "type": "Feature",
  "properties": {
    "iso:country":"US",
    "sg:address":"10695 Co Rd Zz",
    "sg:city":"Sister Bay",
    "sg:classifiers":[
        {
            "category":"Building & Trades",
            "subcategory":"Construction",
            "type":"Services"
        }
    ],
    "sg:phone":"+1 920 854 2116",
    "sg:postcode":"54234",
    "sg:province":"WI",
    "sg:tags":[
        "excavation",
        "marine",
        "contractor"
    ],
    "wof:name":"Hockers Excavating Inc",
    "wof:placetype":"venue"
},
  "geometry": {"coordinates":[-87.061075,45.190251],"type":"Point"}
}