{
  "type": "Feature",
  "properties": {
    "addr:full":"426 W Sunset Dr Waukesha WI 53189",
    "addr:housenumber":"426",
    "addr:postcode":"53189",
    "addr:street":"W Sunset Dr",
    "iso:country":"US",
    "sg:address":"426 W Sunset Dr",
    "sg:city":"Waukesha",
    "sg:classifiers":[
        {
            "category":"Food & Beverages",
            "subcategory":"Groceries & Convenience Stores",
            "type":"Retail Goods"
        },
        {
            "category":"Autos & Motor Vehicles",
            "subcategory":"Fuel & Gas Station",
            "type":"Retail Goods"
        }
    ],
    "sg:phone":"+1 262 547 2381",
    "sg:postcode":"53189",
    "sg:province":"WI",
    "sg:tags":[
        "station",
        "gasoline"
    ],
    "wof:name":"PDQ Food Stores Inc",
    "wof:placetype":"venue"
},
  "geometry": {"coordinates":[-88.23648300000001,42.988354],"type":"Point"}
}