{
  "type": "Feature",
  "properties": {
    "iso:country":"US",
    "sg:address":"222 N Midvale Blvd",
    "sg:city":"Madison",
    "sg:classifiers":[
        {
            "category":"Professional",
            "subcategory":"Lawyer & Legal Services",
            "type":"Services"
        }
    ],
    "sg:phone":"+1 608 231 9060",
    "sg:postcode":"53705",
    "sg:province":"WI",
    "sg:tags":[
        "attorney"
    ],
    "wof:name":"Lauren R Brown-Perry",
    "wof:placetype":"venue"
},
  "geometry": {"coordinates":[-89.451202,43.069251],"type":"Point"}
}