{
  "type": "Feature",
  "properties": {
    "addr:full":"501 Lake Ave Florence WI 54121",
    "addr:housenumber":"501",
    "addr:postcode":"54121",
    "addr:street":"Lake Ave",
    "iso:country":"US",
    "sg:address":"501 Lake Ave",
    "sg:city":"Florence",
    "sg:classifiers":[
        {
            "category":"Professional",
            "subcategory":"Business Services",
            "type":"Services"
        }
    ],
    "sg:phone":"+1 715 528 4927",
    "sg:postcode":"54121",
    "sg:province":"WI",
    "sg:tags":[
        "information",
        "referral"
    ],
    "wof:name":"Information Technology",
    "wof:placetype":"venue"
},
  "geometry": {"coordinates":[-88.24982199999999,45.921459],"type":"Point"}
}