{
  "type": "Feature",
  "properties": {
    "addr:full":"1127 W Harris St Appleton WI 54914",
    "addr:housenumber":"1127",
    "addr:postcode":"54914",
    "addr:street":"W Harris St",
    "iso:country":"US",
    "sg:address":"1127 W Harris St",
    "sg:city":"Appleton",
    "sg:classifiers":[
        {
            "category":"Building & Trades",
            "subcategory":"Plumbing",
            "type":"Services"
        }
    ],
    "sg:phone":"+1 920 954 9855",
    "sg:postcode":"54914",
    "sg:province":"WI",
    "sg:tags":[
        "contractor"
    ],
    "wof:name":"A & K Sheet Metal",
    "wof:placetype":"venue"
},
  "geometry": {"coordinates":[-88.424498,44.264824],"type":"Point"}
}