{
  "type": "Feature",
  "properties": {
    "addr:full":"3304 Falcon Dr Wausau WI 54401",
    "addr:housenumber":"3304",
    "addr:postcode":"54401",
    "addr:street":"Falcon Dr",
    "iso:country":"US",
    "sg:address":"3304 Falcon Dr",
    "sg:city":"Wausau",
    "sg:classifiers":[
        {
            "category":"Building & Trades",
            "subcategory":"Construction",
            "type":"Services"
        }
    ],
    "sg:phone":"+1 715 675 0505",
    "sg:postcode":"54401",
    "sg:province":"WI",
    "sg:tags":[
        "contractor"
    ],
    "wof:name":"Gilge Siding & Windows",
    "wof:placetype":"venue"
},
  "geometry": {"coordinates":[-89.678563,45.01733],"type":"Point"}
}