{
  "type": "Feature",
  "properties": {
    "iso:country":"US",
    "sg:address":"506 W Garland St",
    "sg:city":"West Salem",
    "sg:classifiers":[
        {
            "category":"Freight",
            "type":"Transportation"
        }
    ],
    "sg:phone":"+1 608 786 0562",
    "sg:postcode":"54669",
    "sg:province":"WI",
    "sg:tags":[
        "operator",
        "local",
        "trucking"
    ],
    "wof:name":"Gilbertson Milk Hauling Inc",
    "wof:placetype":"venue"
},
  "geometry": {"coordinates":[-91.090507,43.899164],"type":"Point"}
}