{
  "type": "Feature",
  "properties": {
    "iso:country":"US",
    "sg:address":"5593 State Rd 49",
    "sg:city":"Waupun",
    "sg:classifiers":[
        {
            "category":"Building & Trades",
            "subcategory":"Construction",
            "type":"Services"
        }
    ],
    "sg:phone":"+1 920 324 3311",
    "sg:postcode":"53963",
    "sg:province":"WI",
    "sg:tags":[
        "wallpaper"
    ],
    "wof:name":"Laurie's Wallpaper Svc",
    "wof:placetype":"venue"
},
  "geometry": {"coordinates":[-88.691267,43.633131],"type":"Point"}
}