{
  "type": "Feature",
  "properties": {
    "iso:country":"US",
    "sg:address":"614 Janssen St",
    "sg:city":"Horicon",
    "sg:classifiers":[
        {
            "category":"Home & Garden",
            "subcategory":"Carpets & Floor Coverings",
            "type":"Retail Goods"
        }
    ],
    "sg:phone":"+1 920 485 0601",
    "sg:postcode":"53032",
    "sg:province":"WI",
    "wof:name":"Four On Floor",
    "wof:placetype":"venue"
},
  "geometry": {"coordinates":[-88.62963,43.44241],"type":"Point"}
}