{
  "type": "Feature",
  "properties": {
    "iso:country":"US",
    "sg:address":"3471 Co Rd C",
    "sg:city":"Stevens Point",
    "sg:classifiers":[
        {
            "category":"Wholesale",
            "subcategory":"Farm Supplies",
            "type":"Manufacturing & Wholesale Goods"
        }
    ],
    "sg:phone":"+1 715 344 2421",
    "sg:postcode":"54481",
    "sg:province":"WI",
    "sg:tags":[
        "livestock"
    ],
    "wof:name":"Ron Zinda Livestock",
    "wof:placetype":"venue"
},
  "geometry": {"coordinates":[-89.74178999999999,44.518462],"type":"Point"}
}