{
  "type": "Feature",
  "properties": {
    "addr:full":"1205 N Sherman Ave Madison WI 53704",
    "addr:housenumber":"1205",
    "addr:postcode":"53704",
    "addr:street":"N Sherman Ave",
    "iso:country":"US",
    "sg:address":"1205 N Sherman Ave",
    "sg:city":"Madison",
    "sg:classifiers":[
        {
            "category":"Professional",
            "subcategory":"Accounting & Tax Preparation",
            "type":"Services"
        }
    ],
    "sg:phone":"+1 608 241 2323",
    "sg:postcode":"53704",
    "sg:province":"WI",
    "sg:tags":[
        "return",
        "filing"
    ],
    "wof:name":"H & R Block Tax Svc",
    "wof:placetype":"venue"
},
  "geometry": {"coordinates":[-89.363722,43.11316],"type":"Point"}
}