{
  "type": "Feature",
  "properties": {
    "iso:country":"US",
    "sg:address":"4015 David Rd",
    "sg:city":"Madison",
    "sg:classifiers":[
        {
            "category":"Building & Trades",
            "subcategory":"Construction",
            "type":"Services"
        }
    ],
    "sg:phone":"+1 608 240 1440",
    "sg:postcode":"53704",
    "sg:province":"WI",
    "sg:tags":[
        "home",
        "builder",
        "operative"
    ],
    "wof:name":"Leo Cox Construction",
    "wof:placetype":"venue"
},
  "geometry": {"coordinates":[-89.314463,43.134891],"type":"Point"}
}