{
  "type": "Feature",
  "properties": {
    "iso:country":"US",
    "sg:address":"10545 Blackhawk Trl",
    "sg:city":"Fox Lake",
    "sg:classifiers":[
        {
            "category":"Building & Trades",
            "subcategory":"Construction",
            "type":"Services"
        }
    ],
    "sg:phone":"+1 262 689 9671",
    "sg:postcode":"53933",
    "sg:province":"WI",
    "sg:tags":[
        "house"
    ],
    "wof:name":"Viennawoods",
    "wof:placetype":"venue"
},
  "geometry": {"coordinates":[-88.926641,43.598963],"type":"Point"}
}