{
  "type": "Feature",
  "properties": {
    "iso:country":"US",
    "sg:address":"2945 Landing Rd",
    "sg:city":"Weyauwega",
    "sg:classifiers":[
        {
            "category":"Manufacturing",
            "subcategory":"Lumber",
            "type":"Manufacturing & Wholesale Goods"
        }
    ],
    "sg:phone":"+1 920 867 3645",
    "sg:postcode":"54983",
    "sg:province":"WI",
    "sg:tags":[
        "mill"
    ],
    "wof:name":"Deys Lumber Inc",
    "wof:placetype":"venue"
},
  "geometry": {"coordinates":[-88.878468,44.348816],"type":"Point"}
}