{
  "type": "Feature",
  "properties": {
    "iso:country":"US",
    "sg:address":"5021 28th St",
    "sg:city":"Kenosha",
    "sg:classifiers":[
        {
            "category":"Building & Trades",
            "subcategory":"Construction",
            "type":"Services"
        }
    ],
    "sg:phone":"+1 262 658 0700",
    "sg:postcode":"53144",
    "sg:province":"WI",
    "sg:tags":[
        "contractor"
    ],
    "wof:name":"Master Craft Builders",
    "wof:placetype":"venue"
},
  "geometry": {"coordinates":[-87.854609,42.612911],"type":"Point"}
}