{
  "type": "Feature",
  "properties": {
    "iso:country":"US",
    "sg:address":"14154 de la Tour Dr",
    "sg:city":"South Beloit",
    "sg:classifiers":[
        {
            "category":"Building & Trades",
            "subcategory":"Equipment Rental",
            "type":"Services"
        }
    ],
    "sg:phone":"+1 815 624 2411",
    "sg:postcode":"61080",
    "sg:province":"WI",
    "wof:name":"Sb Rentals",
    "wof:placetype":"venue"
},
  "geometry": {"coordinates":[-89.045475,42.464927],"type":"Point"}
}