{
  "type": "Feature",
  "properties": {
    "iso:country":"US",
    "sg:address":"1254 Meadow Ln",
    "sg:city":"Racine",
    "sg:classifiers":[
        {
            "category":"Professional",
            "subcategory":"Business Services",
            "type":"Services"
        }
    ],
    "sg:phone":"+1 262 886 1624",
    "sg:postcode":"53406",
    "sg:province":"WI",
    "wof:name":"Oglesby Enterprises Inc",
    "wof:placetype":"venue"
},
  "geometry": {"coordinates":[-87.85738,42.713399],"type":"Point"}
}