{
  "type": "Feature",
  "properties": {
    "iso:country":"US",
    "sg:address":"10001 64th St",
    "sg:city":"Kenosha",
    "sg:classifiers":[
        {
            "category":"Professional",
            "subcategory":"Business Services",
            "type":"Services"
        }
    ],
    "sg:phone":"+1 262 857 2489",
    "sg:postcode":"53142",
    "sg:province":"WI",
    "wof:name":"Dks Enterprise LLC",
    "wof:placetype":"venue"
},
  "geometry": {"coordinates":[-87.929832,42.576625],"type":"Point"}
}