{
  "type": "Feature",
  "properties": {
    "iso:country":"US",
    "sg:address":"814 Mullet Pl",
    "sg:city":"Green Bay",
    "sg:classifiers":[
        {
            "category":"Wholesale",
            "subcategory":"Non-durable Goods",
            "type":"Manufacturing & Wholesale Goods"
        }
    ],
    "sg:phone":"+1 920 432 0256",
    "sg:postcode":"54304",
    "sg:province":"WI",
    "wof:name":"Moonbeams LLC",
    "wof:placetype":"venue"
},
  "geometry": {"coordinates":[-88.039145,44.501739],"type":"Point"}
}