{
  "type": "Feature",
  "properties": {
    "addr:full":"12038 Westrom Rd Grantsburg WI 54840",
    "addr:housenumber":"12038",
    "addr:postcode":"54840",
    "addr:street":"Westrom Rd",
    "iso:country":"US",
    "sg:address":"12038 Westrom Rd",
    "sg:city":"Grantsburg",
    "sg:classifiers":[
        {
            "category":"Professional",
            "type":"Services"
        }
    ],
    "sg:phone":"+1 715 463 5096",
    "sg:postcode":"54840",
    "sg:province":"WI",
    "wof:name":"Arlu L Ames",
    "wof:placetype":"venue"
},
  "geometry": {"coordinates":[-92.610417,45.736502],"type":"Point"}
}