{
  "type": "Feature",
  "properties": {
    "addr:full":"201 W Mifflin St Madison WI 53703",
    "addr:housenumber":"201",
    "addr:postcode":"53703",
    "addr:street":"W Mifflin St",
    "iso:country":"US",
    "sg:address":"201 W Mifflin St",
    "sg:city":"Madison",
    "sg:classifiers":[
        {
            "category":"Education",
            "subcategory":"Library",
            "type":"Public Place"
        },
        {
            "category":"Government",
            "subcategory":"Office",
            "type":"Public Place"
        }
    ],
    "sg:phone":"+1 608 266 6388",
    "sg:postcode":"53703",
    "sg:province":"WI",
    "sg:tags":[
        "parish",
        "township",
        "government-city",
        "government-county",
        "village"
    ],
    "sg:website":"http://www.bookmobile.com",
    "wof:name":"Dane County Library Service",
    "wof:placetype":"venue"
},
  "geometry": {"coordinates":[-89.38732899999999,43.074059],"type":"Point"}
}