{
  "type": "Feature",
  "properties": {
    "addr:full":"415 Main St Marathon WI 54448",
    "addr:housenumber":"415",
    "addr:postcode":"54448",
    "addr:street":"Main St",
    "iso:country":"US",
    "sg:address":"415 Main St",
    "sg:city":"Marathon",
    "sg:classifiers":[
        {
            "category":"Food & Beverages",
            "subcategory":"Specialty",
            "type":"Retail Goods"
        }
    ],
    "sg:phone":"+1 715 443 2255",
    "sg:postcode":"54448",
    "sg:province":"WI",
    "sg:tags":[
        "health",
        "diet"
    ],
    "wof:name":"Sugar N Spice",
    "wof:placetype":"venue"
},
  "geometry": {"coordinates":[-89.84028600000001,44.931216],"type":"Point"}
}