{
  "type": "Feature",
  "properties": {
    "iso:country":"US",
    "sg:address":"15042 Pinewood Dr",
    "sg:city":"Thorp",
    "sg:classifiers":[
        {
            "category":"Retail",
            "subcategory":"Repair Shop",
            "type":"Services"
        }
    ],
    "sg:phone":"+1 715 669 7298",
    "sg:postcode":"54771",
    "sg:province":"WI",
    "sg:tags":[
        "welding"
    ],
    "wof:name":"Dans Welding & Machine T",
    "wof:placetype":"venue"
},
  "geometry": {"coordinates":[-90.810242,45.046233],"type":"Point"}
}