{
  "type": "Feature",
  "properties": {
    "iso:country":"US",
    "sg:address":"4594 Castle Rd",
    "sg:city":"Medford",
    "sg:classifiers":[
        {
            "category":"Professional",
            "subcategory":"Business Services",
            "type":"Services"
        }
    ],
    "sg:phone":"+1 715 785 7248",
    "sg:postcode":"54451",
    "sg:province":"WI",
    "wof:name":"Wilmark Industrial",
    "wof:placetype":"venue"
},
  "geometry": {"coordinates":[-90.39391500000001,45.198367],"type":"Point"}
}