{
  "type": "Feature",
  "properties": {
    "iso:country":"US",
    "sg:address":"321 Milwaukee St",
    "sg:city":"Menasha",
    "sg:classifiers":[
        {
            "category":"Government",
            "subcategory":"Office",
            "type":"Public Place"
        }
    ],
    "sg:phone":"+1 920 967 5186",
    "sg:postcode":"54952",
    "sg:province":"WI",
    "sg:tags":[
        "village"
    ],
    "wof:name":"Menasha Water & Electric",
    "wof:placetype":"venue"
},
  "geometry": {"coordinates":[-88.449045,44.205999],"type":"Point"}
}