{
  "type": "Feature",
  "properties": {
    "iso:country":"US",
    "sg:address":"204 N Mill St",
    "sg:city":"West Salem",
    "sg:classifiers":[
        {
            "category":"Freight",
            "type":"Transportation"
        }
    ],
    "sg:phone":"+1 608 786 9947",
    "sg:postcode":"54669",
    "sg:province":"WI",
    "sg:tags":[
        "operator",
        "local",
        "trucking"
    ],
    "wof:name":"Levendoski Trucking Inc",
    "wof:placetype":"venue"
},
  "geometry": {"coordinates":[-91.08001400000001,43.899],"type":"Point"}
}