{
  "type": "Feature",
  "properties": {
    "iso:country":"US",
    "sg:address":"21 E 2nd St",
    "sg:city":"Fond Du Lac",
    "sg:classifiers":[
        {
            "category":"Banks & Credit Unions",
            "subcategory":"Bank",
            "type":"Services"
        }
    ],
    "sg:phone":"+1 920 922 7705",
    "sg:postcode":"54935",
    "sg:province":"WI",
    "sg:tags":[
        "mortgage"
    ],
    "wof:name":"Assured Mortgage",
    "wof:placetype":"venue"
},
  "geometry": {"coordinates":[-88.44465,43.775328],"type":"Point"}
}