{
  "type": "Feature",
  "properties": {
    "iso:country":"US",
    "sg:address":"116 E Towne Mall",
    "sg:city":"Madison",
    "sg:classifiers":[
        {
            "category":"Shopping",
            "subcategory":"Clothing, Apparel, & Fashions",
            "type":"Retail Goods"
        }
    ],
    "sg:phone":"+1 608 242 1810",
    "sg:postcode":"53704",
    "sg:province":"WI",
    "sg:tags":[
        "family"
    ],
    "wof:name":"Disney Store Inc",
    "wof:placetype":"venue"
},
  "geometry": {"coordinates":[-89.30441399999999,43.128132],"type":"Point"}
}