{
  "type": "Feature",
  "properties": {
    "addr:full":"205 W Main St Mt Horeb WI 53572",
    "addr:housenumber":"205",
    "addr:postcode":"53572",
    "addr:street":"W Main St",
    "iso:country":"US",
    "sg:address":"205 W Main St",
    "sg:city":"Mt Horeb",
    "sg:classifiers":[
        {
            "category":"Shopping",
            "subcategory":"Clothing, Apparel, & Fashions",
            "type":"Retail Goods"
        }
    ],
    "sg:phone":"+1 608 437 8073",
    "sg:postcode":"53572",
    "sg:province":"WI",
    "wof:name":"Her Closet",
    "wof:placetype":"venue"
},
  "geometry": {"coordinates":[-89.740449,43.008582],"type":"Point"}
}