{
  "type": "Feature",
  "properties": {
    "iso:country":"US",
    "sg:address":"5707 7th Ave",
    "sg:city":"Kenosha",
    "sg:classifiers":[
        {
            "category":"Health Services",
            "subcategory":"Clinic",
            "type":"Services"
        }
    ],
    "sg:phone":"+1 262 657 8467",
    "sg:postcode":"53140",
    "sg:province":"WI",
    "sg:tags":[
        "home"
    ],
    "wof:name":"Home Health Care Int",
    "wof:placetype":"venue"
},
  "geometry": {"coordinates":[-87.819356,42.58318],"type":"Point"}
}