{
  "type": "Feature",
  "properties": {
    "addr:full":"430 Chippewa Mall Dr Chippewa Falls WI 54729",
    "addr:housenumber":"430",
    "addr:postcode":"54729",
    "addr:street":"Chippewa Mall Dr",
    "iso:country":"US",
    "sg:address":"430 Chippewa Mall Dr",
    "sg:city":"Chippewa Falls",
    "sg:classifiers":[
        {
            "category":"Autos & Motor Vehicles",
            "subcategory":"Auto Supplies",
            "type":"Retail Goods"
        }
    ],
    "sg:phone":"+1 715 720 1960",
    "sg:postcode":"54729",
    "sg:province":"WI",
    "wof:name":"Champion Auto Stores Inc",
    "wof:placetype":"venue"
},
  "geometry": {"coordinates":[-91.381539,44.924184],"type":"Point"}
}