{
  "type": "Feature",
  "properties": {
    "iso:country":"US",
    "sg:address":"1750 Dousman St",
    "sg:city":"Green Bay",
    "sg:classifiers":[
        {
            "category":"Social Services",
            "subcategory":"Child Care",
            "type":"Services"
        }
    ],
    "sg:phone":"+1 920 494 7808",
    "sg:postcode":"54303",
    "sg:province":"WI",
    "sg:tags":[
        "kindergarten",
        "academic",
        "school"
    ],
    "wof:name":"Sonshine Christian Pre-School",
    "wof:placetype":"venue"
},
  "geometry": {"coordinates":[-88.063012,44.534144],"type":"Point"}
}