{
  "type": "Feature",
  "properties": {
    "addr:full":"5531 6th Ave Kenosha WI 53140",
    "addr:housenumber":"5531",
    "addr:postcode":"53140",
    "addr:street":"6Th Ave",
    "iso:country":"US",
    "sg:address":"5531 6th Ave",
    "sg:city":"Kenosha",
    "sg:classifiers":[
        {
            "category":"Shopping",
            "type":"Retail Goods"
        },
        {
            "category":"Shopping",
            "subcategory":"Bicycles & Sporting Goods",
            "type":"Retail Goods"
        }
    ],
    "sg:phone":"+1 262 652 7227",
    "sg:postcode":"53140",
    "sg:province":"WI",
    "sg:tags":[
        "equipment",
        "soccer",
        "merchandise",
        "supply"
    ],
    "wof:name":"Just For Kicks Soccer Store LL",
    "wof:placetype":"venue"
},
  "geometry": {"coordinates":[-87.81857599999999,42.585366],"type":"Point"}
}