{
  "type": "Feature",
  "properties": {
    "addr:full":"3345 Lake Dr Hartford WI 53027",
    "addr:housenumber":"3345",
    "addr:postcode":"53027",
    "addr:street":"Lake Dr",
    "iso:country":"US",
    "sg:address":"3345 Lake Dr",
    "sg:city":"Hartford",
    "sg:classifiers":[
        {
            "category":"Professional",
            "subcategory":"Computer Services",
            "type":"Services"
        }
    ],
    "sg:phone":"+1 262 673 6469",
    "sg:postcode":"53027",
    "sg:province":"WI",
    "sg:tags":[
        "programing",
        "custom"
    ],
    "wof:name":"Picture Perfect Designs",
    "wof:placetype":"venue"
},
  "geometry": {"coordinates":[-88.34191,43.312438],"type":"Point"}
}