{
  "type": "Feature",
  "properties": {
    "iso:country":"US",
    "sg:address":"6620 Plover Rd",
    "sg:city":"Wisconsin Rapids",
    "sg:classifiers":[
        {
            "category":"Building & Trades",
            "subcategory":"Construction",
            "type":"Services"
        }
    ],
    "sg:phone":"+1 715 421 2296",
    "sg:postcode":"54494",
    "sg:province":"WI",
    "sg:tags":[
        "contractor"
    ],
    "wof:name":"V S F Drywall",
    "wof:placetype":"venue"
},
  "geometry": {"coordinates":[-89.736602,44.420504],"type":"Point"}
}