{
  "type": "Feature",
  "properties": {
    "addr:full":"8075 Tower Rd Malone WI 53049",
    "addr:housenumber":"8075",
    "addr:postcode":"53049",
    "addr:street":"Tower Rd",
    "iso:country":"US",
    "sg:address":"8075 Tower Rd",
    "sg:city":"Malone",
    "sg:classifiers":[
        {
            "category":"Retail",
            "subcategory":"Auto Repair",
            "type":"Services"
        }
    ],
    "sg:phone":"+1 920 922 4177",
    "sg:postcode":"53049",
    "sg:province":"WI",
    "sg:tags":[
        "general"
    ],
    "wof:name":"K & K Auto Repair",
    "wof:placetype":"venue"
},
  "geometry": {"coordinates":[-88.32195,43.832982],"type":"Point"}
}