{
  "type": "Feature",
  "properties": {
    "iso:country":"US",
    "sg:address":"603 S Jackson St",
    "sg:city":"Cuba City",
    "sg:classifiers":[
        {
            "category":"Building & Trades",
            "subcategory":"Construction",
            "type":"Services"
        }
    ],
    "sg:phone":"+1 608 744 3238",
    "sg:postcode":"53807",
    "sg:province":"WI",
    "sg:tags":[
        "heavy"
    ],
    "wof:name":"Don Bubach Construction Co",
    "wof:placetype":"venue"
},
  "geometry": {"coordinates":[-90.433264,42.602054],"type":"Point"}
}