{
  "type": "Feature",
  "properties": {
    "iso:country":"US",
    "sg:address":"7938 Green Tree Ln",
    "sg:city":"Oconomowoc",
    "sg:classifiers":[
        {
            "category":"Professional",
            "subcategory":"Accounting & Tax Preparation",
            "type":"Services"
        }
    ],
    "sg:phone":"+1 262 567 7157",
    "sg:postcode":"53066",
    "sg:province":"WI",
    "sg:tags":[
        "return"
    ],
    "wof:name":"Robert Q Rothe",
    "wof:placetype":"venue"
},
  "geometry": {"coordinates":[-88.541736,43.131166],"type":"Point"}
}