{
  "type": "Feature",
  "properties": {
    "iso:country":"US",
    "sg:address":"8394 Gohr Rd",
    "sg:city":"Sobieski",
    "sg:classifiers":[
        {
            "category":"Farming",
            "subcategory":"Dairy Farm",
            "type":"Manufacturing & Wholesale Goods"
        }
    ],
    "sg:phone":"+1 920 899 3889",
    "sg:postcode":"54171",
    "sg:province":"WI",
    "wof:name":"Sleepy Hollow Dairy Farm",
    "wof:placetype":"venue"
},
  "geometry": {"coordinates":[-88.18594,44.752714],"type":"Point"}
}