{
  "type": "Feature",
  "properties": {
    "iso:country":"US",
    "sg:address":"3623 W Anita Ln",
    "sg:city":"Franklin",
    "sg:classifiers":[
        {
            "category":"Real Estate",
            "subcategory":"Real Estate Agent",
            "type":"Services"
        }
    ],
    "sg:phone":"+1 414 423 8976",
    "sg:postcode":"53132",
    "sg:province":"WI",
    "wof:name":"Jina Realty",
    "wof:placetype":"venue"
},
  "geometry": {"coordinates":[-87.96568000000001,42.893875],"type":"Point"}
}