{
  "type": "Feature",
  "properties": {
    "iso:country":"US",
    "sg:address":"2701 Co Rd Ee",
    "sg:city":"Baileys Harbor",
    "sg:classifiers":[
        {
            "category":"Travel",
            "subcategory":"Campground",
            "type":"Entertainment"
        }
    ],
    "sg:phone":"+1 920 839 2109",
    "sg:postcode":"54202",
    "sg:province":"WI",
    "wof:name":"Bailey's Bluff",
    "wof:placetype":"venue"
},
  "geometry": {"coordinates":[-87.144621,45.070997],"type":"Point"}
}