{
  "type": "Feature",
  "properties": {
    "iso:country":"US",
    "sg:address":"1246 S 34th St",
    "sg:city":"Milwaukee",
    "sg:classifiers":[
        {
            "category":"Farming",
            "subcategory":"Fish & Marine Products",
            "type":"Manufacturing & Wholesale Goods"
        },
        {
            "category":"Recreation",
            "subcategory":"Fishing",
            "type":"Entertainment"
        }
    ],
    "sg:phone":"+1 414 305 9196",
    "sg:postcode":"53215",
    "sg:province":"WI",
    "sg:tags":[
        "tackle",
        "fishermen's",
        "supply"
    ],
    "wof:name":"Wishin N Fishin",
    "wof:placetype":"venue"
},
  "geometry": {"coordinates":[-87.95639,43.018504],"type":"Point"}
}