{
  "type": "Feature",
  "properties": {
    "addr:full":"422 6th St Menasha WI 54952",
    "addr:housenumber":"422",
    "addr:postcode":"54952",
    "addr:street":"6Th St",
    "iso:country":"US",
    "sg:address":"422 6th St",
    "sg:city":"Menasha",
    "sg:classifiers":[
        {
            "category":"Bars & Pubs",
            "type":"Food & Drink"
        }
    ],
    "sg:phone":"+1 920 722 3356",
    "sg:postcode":"54952",
    "sg:province":"WI",
    "sg:tags":[
        "drinking"
    ],
    "wof:name":"Beck's Home Plate",
    "wof:placetype":"venue"
},
  "geometry": {"coordinates":[-88.44605199999999,44.208268],"type":"Point"}
}