{
  "type": "Feature",
  "properties": {
    "addr:full":"615 5th St Haugen WI 54868",
    "addr:housenumber":"615",
    "addr:postcode":"54868",
    "addr:street":"5Th St",
    "iso:country":"US",
    "sg:address":"615 5th St",
    "sg:city":"Haugen",
    "sg:classifiers":[
        {
            "category":"Education",
            "subcategory":"School",
            "type":"Public Place"
        }
    ],
    "sg:phone":"+1 715 234 7341",
    "sg:postcode":"54868",
    "sg:province":"WI",
    "wof:name":"Haugen Elementary School",
    "wof:placetype":"venue"
},
  "geometry": {"coordinates":[-91.783863,45.609974],"type":"Point"}
}