{
  "type": "Feature",
  "properties": {
    "addr:full":"2312 Crest View Dr Hudson WI 54016",
    "addr:housenumber":"2312",
    "addr:postcode":"54016",
    "addr:street":"Crest View Dr",
    "iso:country":"US",
    "sg:address":"2312 Crest View Dr",
    "sg:city":"Hudson",
    "sg:classifiers":[
        {
            "category":"Restaurant",
            "type":"Food & Drink"
        }
    ],
    "sg:phone":"+1 715 377 0300",
    "sg:postcode":"54016",
    "sg:province":"WI",
    "sg:tags":[
        "eating"
    ],
    "wof:name":"Kingdom Buffet",
    "wof:placetype":"venue"
},
  "geometry": {"coordinates":[-92.723923,44.960715],"type":"Point"}
}