{
  "type": "Feature",
  "properties": {
    "iso:country":"US",
    "sg:address":"104 Pine St",
    "sg:city":"Eden",
    "sg:classifiers":[
        {
            "category":"Government",
            "subcategory":"Office",
            "type":"Public Place"
        }
    ],
    "sg:phone":"+1 920 477 4304",
    "sg:postcode":"53019",
    "sg:province":"WI",
    "sg:tags":[
        "village"
    ],
    "wof:name":"Eden Village Office",
    "wof:placetype":"venue"
},
  "geometry": {"coordinates":[-88.356694,43.691236],"type":"Point"}
}