{
  "type": "Feature",
  "properties": {
    "iso:country":"US",
    "sg:address":"1140 Eastern Trl",
    "sg:city":"Mukwonago",
    "sg:classifiers":[
        {
            "category":"Insurance",
            "subcategory":"Insurance Agent",
            "type":"Services"
        }
    ],
    "sg:phone":"+1 262 363 3660",
    "sg:postcode":"53149",
    "sg:province":"WI",
    "wof:name":"Lr Siix & Associotes Inc",
    "wof:placetype":"venue"
},
  "geometry": {"coordinates":[-88.315012,42.879503],"type":"Point"}
}