{
  "type": "Feature",
  "properties": {
    "iso:country":"US",
    "sg:address":"9579 Englehart Rd",
    "sg:city":"Watertown",
    "sg:classifiers":[
        {
            "category":"Farming",
            "subcategory":"Dairy Farm",
            "type":"Manufacturing & Wholesale Goods"
        }
    ],
    "sg:phone":"+1 920 206 2703",
    "sg:postcode":"53094",
    "sg:province":"WI",
    "wof:name":"Zimmerman Dairy",
    "wof:placetype":"venue"
},
  "geometry": {"coordinates":[-88.857316,43.192953],"type":"Point"}
}