{
  "type": "Feature",
  "properties": {
    "addr:full":"409 N Jefferson St Lancaster WI 53813",
    "addr:housenumber":"409",
    "addr:postcode":"53813",
    "addr:street":"N Jefferson St",
    "iso:country":"US",
    "sg:address":"409 N Jefferson St",
    "sg:city":"Lancaster",
    "sg:classifiers":[
        {
            "category":"Health Services",
            "subcategory":"Health Practitioner",
            "type":"Services"
        }
    ],
    "sg:phone":"+1 608 723 6432",
    "sg:postcode":"53813",
    "sg:province":"WI",
    "wof:name":"Family Massage Therapy",
    "wof:placetype":"venue"
},
  "geometry": {"coordinates":[-90.710832,42.85183],"type":"Point"}
}