{
  "type": "Feature",
  "properties": {
    "addr:full":"109 N Main St Hartford WI 53027",
    "addr:housenumber":"109",
    "addr:postcode":"53027",
    "addr:street":"N Main St",
    "iso:country":"US",
    "sg:address":"109 N Main St",
    "sg:city":"Hartford",
    "sg:classifiers":[
        {
            "category":"Government",
            "subcategory":"Office",
            "type":"Public Place"
        }
    ],
    "sg:phone":"+1 262 673 8202",
    "sg:postcode":"53027",
    "sg:province":"WI",
    "sg:tags":[
        "village"
    ],
    "wof:name":"Hartford Clerk",
    "wof:placetype":"venue"
},
  "geometry": {"coordinates":[-88.378942,43.319183],"type":"Point"}
}