{
  "type": "Feature",
  "properties": {
    "iso:country":"US",
    "sg:address":"875 Lawrence Dr",
    "sg:city":"De Pere",
    "sg:classifiers":[
        {
            "category":"Manufacturing",
            "subcategory":"Tools & Machinery",
            "type":"Manufacturing & Wholesale Goods"
        }
    ],
    "sg:phone":"+1 920 337 9750",
    "sg:postcode":"54115",
    "sg:province":"WI",
    "sg:tags":[
        "generator"
    ],
    "wof:name":"Cummins Npower",
    "wof:placetype":"venue"
},
  "geometry": {"coordinates":[-88.106565,44.426685],"type":"Point"}
}