{
  "type": "Feature",
  "properties": {
    "iso:country":"US",
    "sg:address":"2700 State Rd",
    "sg:city":"La Crosse",
    "sg:classifiers":[
        {
            "category":"Retail",
            "subcategory":"Auto Repair",
            "type":"Services"
        }
    ],
    "sg:phone":"+1 608 788 4161",
    "sg:postcode":"54601",
    "sg:province":"WI",
    "sg:tags":[
        "repairing",
        "automobile",
        "general"
    ],
    "wof:name":"Happy's Garage",
    "wof:placetype":"venue"
},
  "geometry": {"coordinates":[-91.215082,43.794368],"type":"Point"}
}