{
  "type": "Feature",
  "properties": {
    "iso:country":"US",
    "sg:address":"102 Village Walk Ln",
    "sg:city":"Johnson Creek",
    "sg:classifiers":[
        {
            "category":"Personal",
            "subcategory":"Beauty Salon",
            "type":"Services"
        }
    ],
    "sg:phone":"+1 920 699 2300",
    "sg:postcode":"53038",
    "sg:province":"WI",
    "sg:tags":[
        "manicuring"
    ],
    "wof:name":"Oasis Creations",
    "wof:placetype":"venue"
},
  "geometry": {"coordinates":[-88.764688,43.083088],"type":"Point"}
}