{
  "type": "Feature",
  "properties": {
    "addr:full":"401 Edward St Burlington WI 53105",
    "addr:housenumber":"401",
    "addr:postcode":"53105",
    "addr:street":"Edward St",
    "iso:country":"US",
    "sg:address":"401 Edward St",
    "sg:city":"Burlington",
    "sg:classifiers":[
        {
            "category":"Real Estate",
            "subcategory":"Real Estate Agent",
            "type":"Services"
        }
    ],
    "sg:phone":"+1 262 763 5838",
    "sg:postcode":"53105",
    "sg:province":"WI",
    "wof:name":"Re/Max",
    "wof:placetype":"venue"
},
  "geometry": {"coordinates":[-88.27552300000001,42.671391],"type":"Point"}
}