{
  "type": "Feature",
  "properties": {
    "addr:full":"2105 Brackett Ave Eau Claire WI 54701",
    "addr:housenumber":"2105",
    "addr:postcode":"54701",
    "addr:street":"Brackett Ave",
    "iso:country":"US",
    "sg:address":"2105 Brackett Ave",
    "sg:city":"Eau Claire",
    "sg:classifiers":[
        {
            "category":"Local Transit",
            "type":"Transportation"
        }
    ],
    "sg:phone":"+1 715 834 0842",
    "sg:postcode":"54701",
    "sg:province":"WI",
    "sg:tags":[
        "passenger"
    ],
    "wof:name":"A+ Limosine Service",
    "wof:placetype":"venue"
},
  "geometry": {"coordinates":[-91.469472,44.800022],"type":"Point"}
}