{
  "type": "Feature",
  "properties": {
    "addr:full":"21 S Barstow St Eau Claire WI 54701",
    "addr:housenumber":"21",
    "addr:postcode":"54701",
    "addr:street":"S Barstow St",
    "iso:country":"US",
    "sg:address":"21 S Barstow St",
    "sg:city":"Eau Claire",
    "sg:classifiers":[
        {
            "category":"Government",
            "subcategory":"Court House",
            "type":"Public Place"
        }
    ],
    "sg:phone":"+1 715 836 2006",
    "sg:postcode":"54701",
    "sg:province":"WI",
    "sg:tags":[
        "defender",
        "state"
    ],
    "wof:name":"Eau Claire Trial Office",
    "wof:placetype":"venue"
},
  "geometry": {"coordinates":[-91.50068400000001,44.812398],"type":"Point"}
}