{
  "type": "Feature",
  "properties": {
    "addr:full":"2749 S 108th St Milwaukee WI 53227",
    "addr:housenumber":"2749",
    "addr:postcode":"53227",
    "addr:street":"S 108Th St",
    "iso:country":"US",
    "sg:address":"2749 S 108th St",
    "sg:city":"Milwaukee",
    "sg:classifiers":[
        {
            "category":"Home & Garden",
            "subcategory":"Home Furnishings",
            "type":"Retail Goods"
        }
    ],
    "sg:phone":"+1 414 543 6000",
    "sg:postcode":"53227",
    "sg:province":"WI",
    "sg:tags":[
        "blind",
        "window"
    ],
    "wof:name":"Eddie ZS Blinds & Drapery",
    "wof:placetype":"venue"
},
  "geometry": {"coordinates":[-88.04711,42.99447],"type":"Point"}
}