{
  "type": "Feature",
  "properties": {
    "iso:country":"US",
    "sg:address":"222 W Main St",
    "sg:city":"Madison",
    "sg:classifiers":[
        {
            "category":"Organizations",
            "subcategory":"Religious Organization",
            "type":"Services"
        }
    ],
    "sg:phone":"+1 608 256 5614",
    "sg:postcode":"53703",
    "sg:province":"WI",
    "sg:tags":[
        "church"
    ],
    "sg:website":"www.straphaelmsn.org",
    "wof:name":"St Raphael Cathedral",
    "wof:placetype":"venue"
},
  "geometry": {"coordinates":[-89.385892,43.071957],"type":"Point"}
}