{
  "type": "Feature",
  "properties": {
    "iso:country":"US",
    "sg:address":"2058 N Wisconsin St",
    "sg:city":"Racine",
    "sg:classifiers":[
        {
            "category":"Building & Trades",
            "subcategory":"Construction",
            "type":"Services"
        }
    ],
    "sg:phone":"+1 262 637 9178",
    "sg:postcode":"53402",
    "sg:province":"WI",
    "sg:tags":[
        "concrete",
        "contractor"
    ],
    "wof:name":"B&G Asphalt Sealcoating LLC",
    "wof:placetype":"venue"
},
  "geometry": {"coordinates":[-87.78599800000001,42.745821],"type":"Point"}
}