{
  "type": "Feature",
  "properties": {
    "iso:country":"US",
    "sg:address":"430 E Division St",
    "sg:city":"Fond Du Lac",
    "sg:classifiers":[
        {
            "category":"Banks & Credit Unions",
            "subcategory":"Bank",
            "type":"Services"
        }
    ],
    "sg:phone":"+1 920 926 4980",
    "sg:postcode":"54935",
    "sg:province":"WI",
    "sg:tags":[
        "state"
    ],
    "wof:name":"St Agnes Employers Credit Un",
    "wof:placetype":"venue"
},
  "geometry": {"coordinates":[-88.430481,43.77861],"type":"Point"}
}