{
  "type": "Feature",
  "properties": {
    "iso:country":"US",
    "sg:address":"1401 W Hadley St",
    "sg:city":"Milwaukee",
    "sg:classifiers":[
        {
            "category":"Place Of Worship",
            "subcategory":"Church",
            "type":"Public Place"
        },
        {
            "category":"Place Of Worship",
            "type":"Public Place"
        }
    ],
    "sg:phone":"+1 414 265 2725",
    "sg:postcode":"53206",
    "sg:province":"WI",
    "sg:tags":[
        "churches-baptist-general",
        "churches-baptist"
    ],
    "wof:name":"Way Of Cross Mssnary Baptst Ch",
    "wof:placetype":"venue"
},
  "geometry": {"coordinates":[-87.92959999999999,43.069515],"type":"Point"}
}