{
  "type": "Feature",
  "properties": {
    "iso:country":"US",
    "sg:address":"1719 S Balsam Lake Ct",
    "sg:city":"Balsam Lake",
    "sg:classifiers":[
        {
            "category":"Freight",
            "type":"Transportation"
        }
    ],
    "sg:phone":"+1 715 268 2522",
    "sg:postcode":"54810",
    "sg:province":"WI",
    "sg:tags":[
        "special"
    ],
    "wof:name":"East Balsam Self Storage",
    "wof:placetype":"venue"
},
  "geometry": {"coordinates":[-92.399311,45.455409],"type":"Point"}
}