{
  "type": "Feature",
  "properties": {
    "iso:country":"US",
    "sg:address":"2544 N 48th St",
    "sg:city":"Milwaukee",
    "sg:classifiers":[
        {
            "category":"Professional",
            "subcategory":"Business Services",
            "type":"Services"
        }
    ],
    "sg:phone":"+1 414 444 9460",
    "sg:postcode":"53210",
    "sg:province":"WI",
    "wof:name":"City Home Inspection LLC",
    "wof:placetype":"venue"
},
  "geometry": {"coordinates":[-87.97366599999999,43.065283],"type":"Point"}
}