{
  "type": "Feature",
  "properties": {
    "iso:country":"US",
    "sg:address":"1815 N 6th St",
    "sg:city":"Wausau",
    "sg:classifiers":[
        {
            "category":"Retail",
            "subcategory":"Auto Repair",
            "type":"Services"
        }
    ],
    "sg:phone":"+1 715 842 3982",
    "sg:postcode":"54403",
    "sg:province":"WI",
    "sg:tags":[
        "repairing",
        "automobile"
    ],
    "wof:name":"Lloyd's Auto Repair Inc",
    "wof:placetype":"venue"
},
  "geometry": {"coordinates":[-89.623305,44.971811],"type":"Point"}
}