{
  "type": "Feature",
  "properties": {
    "iso:country":"US",
    "sg:address":"4384 N 27th St",
    "sg:city":"Milwaukee",
    "sg:classifiers":[
        {
            "category":"Personal",
            "subcategory":"Beauty Salon",
            "type":"Services"
        }
    ],
    "sg:phone":"+1 414 871 5833",
    "sg:postcode":"53216",
    "sg:province":"WI",
    "sg:tags":[
        "shop"
    ],
    "wof:name":"Hair Masters Beauty Salon",
    "wof:placetype":"venue"
},
  "geometry": {"coordinates":[-87.946815,43.097618],"type":"Point"}
}