{
  "type": "Feature",
  "properties": {
    "iso:country":"US",
    "sg:address":"14260 W Greenfield Ave",
    "sg:city":"Brookfield",
    "sg:classifiers":[
        {
            "category":"Real Estate",
            "subcategory":"Real Estate Agent",
            "type":"Services"
        }
    ],
    "sg:phone":"+1 262 784 2727",
    "sg:postcode":"53005",
    "sg:province":"WI",
    "wof:name":"Phillips Agency Inc",
    "wof:placetype":"venue"
},
  "geometry": {"coordinates":[-88.092079,43.016664],"type":"Point"}
}