{
  "type": "Feature",
  "properties": {
    "iso:country":"US",
    "sg:address":"1016 S Main St",
    "sg:city":"Jefferson",
    "sg:classifiers":[
        {
            "category":"Insurance",
            "subcategory":"Insurance Agent",
            "type":"Services"
        }
    ],
    "sg:phone":"+1 920 674 4944",
    "sg:postcode":"53549",
    "sg:province":"WI",
    "wof:name":"American Family Insurance",
    "wof:placetype":"venue"
},
  "geometry": {"coordinates":[-88.807142,42.994166],"type":"Point"}
}