{
  "type": "Feature",
  "properties": {
    "iso:country":"US",
    "sg:address":"295 N Center St",
    "sg:city":"Livingston",
    "sg:classifiers":[
        {
            "category":"Government",
            "subcategory":"Post Office",
            "type":"Public Place"
        }
    ],
    "sg:phone":"+1 608 943 8136",
    "sg:postcode":"53554",
    "sg:province":"WI",
    "wof:name":"US Post Office",
    "wof:placetype":"venue"
},
  "geometry": {"coordinates":[-90.43100200000001,42.901092],"type":"Point"}
}