{
  "type": "Feature",
  "properties": {
    "iso:country":"US",
    "sg:address":"5768 US Hwy 45",
    "sg:city":"Fond Du Lac",
    "sg:classifiers":[
        {
            "category":"Freight",
            "type":"Transportation"
        }
    ],
    "sg:phone":"+1 920 922 2299",
    "sg:postcode":"54935",
    "sg:province":"WI",
    "sg:tags":[
        "commercial",
        "storage"
    ],
    "wof:name":"Avenue Self Storage",
    "wof:placetype":"venue"
},
  "geometry": {"coordinates":[-88.393778,43.742934],"type":"Point"}
}