{
  "type": "Feature",
  "properties": {
    "addr:full":"111 Vermont St Beaver Dam WI 53916",
    "addr:housenumber":"111",
    "addr:postcode":"53916",
    "addr:street":"Vermont St",
    "iso:country":"US",
    "sg:address":"111 Vermont St",
    "sg:city":"Beaver Dam",
    "sg:classifiers":[
        {
            "category":"Personal",
            "subcategory":"Beauty Salon",
            "type":"Services"
        }
    ],
    "sg:phone":"+1 920 887 8770",
    "sg:postcode":"53916",
    "sg:province":"WI",
    "sg:tags":[
        "shop"
    ],
    "wof:name":"Sue's Snip & Curl Beauty Salon",
    "wof:placetype":"venue"
},
  "geometry": {"coordinates":[-88.828946,43.462012],"type":"Point"}
}