{
  "type": "Feature",
  "properties": {
    "iso:country":"US",
    "sg:address":"3852 Heritage Rd",
    "sg:city":"De Pere",
    "sg:classifiers":[
        {
            "category":"Utilities",
            "subcategory":"Refuse",
            "type":"Services"
        }
    ],
    "sg:phone":"+1 920 336 6383",
    "sg:postcode":"54115",
    "sg:province":"WI",
    "sg:tags":[
        "system"
    ],
    "wof:name":"Sexton John Sand & Gravel Corp",
    "wof:placetype":"venue"
},
  "geometry": {"coordinates":[-88.052234,44.427978],"type":"Point"}
}