{
  "type": "Feature",
  "properties": {
    "iso:country":"US",
    "sg:address":"7233 Bradley St",
    "sg:city":"Lake Tomahawk",
    "sg:classifiers":[
        {
            "category":"Bars & Pubs",
            "type":"Food & Drink"
        }
    ],
    "sg:phone":"+1 715 277 2632",
    "sg:postcode":"54539",
    "sg:province":"WI",
    "sg:tags":[
        "drinking"
    ],
    "wof:name":"Lake Tomahawk Pub",
    "wof:placetype":"venue"
},
  "geometry": {"coordinates":[-89.59389400000001,45.81516],"type":"Point"}
}