{
  "type": "Feature",
  "properties": {
    "iso:country":"US",
    "sg:address":"2302 Radtke Ave",
    "sg:city":"Schofield",
    "sg:classifiers":[
        {
            "category":"Real Estate",
            "subcategory":"Real Estate Operator",
            "type":"Services"
        }
    ],
    "sg:phone":"+1 715 359 8548",
    "sg:postcode":"54476",
    "sg:province":"WI",
    "sg:tags":[
        "manages",
        "apartment",
        "owns"
    ],
    "wof:name":"Bornheimer Apartments",
    "wof:placetype":"venue"
},
  "geometry": {"coordinates":[-89.593447,44.911133],"type":"Point"}
}