{
  "type": "Feature",
  "properties": {
    "iso:country":"US",
    "sg:address":"513 W North St",
    "sg:city":"Poynette",
    "sg:classifiers":[
        {
            "category":"Professional",
            "type":"Services"
        }
    ],
    "sg:phone":"+1 608 635 7644",
    "sg:postcode":"53955",
    "sg:province":"WI",
    "wof:name":"Positive Place",
    "wof:placetype":"venue"
},
  "geometry": {"coordinates":[-89.40282500000001,43.395579],"type":"Point"}
}