{
  "type": "Feature",
  "properties": {
    "addr:full":"1012 Martin Rd Bloomer WI 54724",
    "addr:housenumber":"1012",
    "addr:postcode":"54724",
    "addr:street":"Martin Rd",
    "iso:country":"US",
    "sg:address":"1012 Martin Rd",
    "sg:city":"Bloomer",
    "sg:classifiers":[
        {
            "category":"Retail",
            "subcategory":"Auto Repair",
            "type":"Services"
        }
    ],
    "sg:phone":"+1 715 568 5381",
    "sg:postcode":"54724",
    "sg:province":"WI",
    "sg:tags":[
        "repairing",
        "automobile"
    ],
    "wof:name":"Day's Tire Svc",
    "wof:placetype":"venue"
},
  "geometry": {"coordinates":[-91.485494,45.1053],"type":"Point"}
}