{
  "type": "Feature",
  "properties": {
    "iso:country":"US",
    "sg:address":"2707 Golf Ave",
    "sg:city":"Racine",
    "sg:classifiers":[
        {
            "category":"Wholesale",
            "subcategory":"Office Equipment",
            "type":"Manufacturing & Wholesale Goods"
        }
    ],
    "sg:phone":"+1 262 632 4550",
    "sg:postcode":"53404",
    "sg:province":"WI",
    "wof:name":"J & L Microfilm Svc",
    "wof:placetype":"venue"
},
  "geometry": {"coordinates":[-87.81667400000001,42.753722],"type":"Point"}
}