{
  "type": "Feature",
  "properties": {
    "iso:country":"US",
    "sg:address":"307 S Main St",
    "sg:city":"Fountain City",
    "sg:classifiers":[
        {
            "category":"Retail",
            "subcategory":"Funeral Services",
            "type":"Services"
        }
    ],
    "sg:phone":"+1 608 687 4201",
    "sg:postcode":"54629",
    "sg:province":"WI",
    "sg:tags":[
        "director"
    ],
    "wof:name":"Fawcett & Junker Funeral Home",
    "wof:placetype":"venue"
},
  "geometry": {"coordinates":[-91.713454,44.126535],"type":"Point"}
}