{
  "type": "Feature",
  "properties": {
    "iso:country":"US",
    "sg:address":"1077 Sunlite Dr",
    "sg:city":"Oneida",
    "sg:classifiers":[
        {
            "category":"Wholesale",
            "subcategory":"Non-durable Goods",
            "type":"Manufacturing & Wholesale Goods"
        },
        {
            "category":"Professional",
            "subcategory":"Advertising",
            "type":"Services"
        }
    ],
    "sg:phone":"+1 920 662 1722",
    "sg:postcode":"54155",
    "sg:province":"WI",
    "sg:tags":[
        "agency"
    ],
    "wof:name":"National Merchandising Corp",
    "wof:placetype":"venue"
},
  "geometry": {"coordinates":[-88.14180899999999,44.564521],"type":"Point"}
}