{
  "type": "Feature",
  "properties": {
    "iso:country":"US",
    "sg:address":"7441 W Greenfield Ave",
    "sg:city":"Milwaukee",
    "sg:classifiers":[
        {
            "category":"Social Services",
            "type":"Services"
        }
    ],
    "sg:phone":"+1 414 771 0322",
    "sg:postcode":"53214",
    "sg:province":"WI",
    "sg:tags":[
        "counseling",
        "counselor",
        "marriage",
        "family"
    ],
    "wof:name":"Temenos Counseling Center",
    "wof:placetype":"venue"
},
  "geometry": {"coordinates":[-88.00532,43.016672],"type":"Point"}
}