{
  "type": "Feature",
  "properties": {
    "addr:full":"1102 Bridge St Grafton WI 53024",
    "addr:housenumber":"1102",
    "addr:postcode":"53024",
    "addr:street":"Bridge St",
    "iso:country":"US",
    "sg:address":"1102 Bridge St",
    "sg:city":"Grafton",
    "sg:classifiers":[
        {
            "category":"Government",
            "subcategory":"Office",
            "type":"Public Place"
        }
    ],
    "sg:phone":"+1 262 377 8500",
    "sg:postcode":"53024",
    "sg:province":"WI",
    "sg:tags":[
        "village"
    ],
    "wof:name":"Town Of Grafton",
    "wof:placetype":"venue"
},
  "geometry": {"coordinates":[-87.951734,43.318585],"type":"Point"}
}