{
  "type": "Feature",
  "properties": {
    "iso:country":"US",
    "sg:address":"225 Scholl St",
    "sg:city":"Amery",
    "sg:classifiers":[
        {
            "category":"Health Services",
            "subcategory":"Hospital",
            "type":"Services"
        }
    ],
    "sg:phone":"+1 715 268 7151",
    "sg:postcode":"54001",
    "sg:province":"WI",
    "wof:name":"Amery Regional Medical Center",
    "wof:placetype":"venue"
},
  "geometry": {"coordinates":[-92.364966,45.303036],"type":"Point"}
}