{
  "type": "Feature",
  "properties": {
    "iso:country":"US",
    "sg:address":"708 55th St",
    "sg:city":"Kenosha",
    "sg:classifiers":[
        {
            "category":"Shopping",
            "subcategory":"Optical Goods",
            "type":"Retail Goods"
        }
    ],
    "sg:phone":"+1 262 656 0101",
    "sg:postcode":"53140",
    "sg:province":"WI",
    "wof:name":"We Opticians Inc",
    "wof:placetype":"venue"
},
  "geometry": {"coordinates":[-87.821166,42.585754],"type":"Point"}
}