{
  "type": "Feature",
  "properties": {
    "iso:country":"US",
    "sg:address":"6102 W North Ave",
    "sg:city":"Milwaukee",
    "sg:classifiers":[
        {
            "category":"Cinema",
            "subcategory":"Movie Rental",
            "type":"Entertainment"
        }
    ],
    "sg:phone":"+1 414 475 0772",
    "sg:postcode":"53213",
    "sg:province":"WI",
    "sg:tags":[
        "leasing",
        "video",
        "disc",
        "tape"
    ],
    "sg:website":"www.blockbuster.com",
    "wof:name":"Blockbuster Video",
    "wof:placetype":"venue"
},
  "geometry": {"coordinates":[-87.989783,43.060786],"type":"Point"}
}