{
  "type": "Feature",
  "properties": {
    "iso:country":"US",
    "sg:address":"1230 Sumner St",
    "sg:city":"Wausau",
    "sg:classifiers":[
        {
            "category":"Building & Trades",
            "subcategory":"Pest Control",
            "type":"Services"
        }
    ],
    "sg:phone":"+1 715 842 5544",
    "sg:postcode":"54403",
    "sg:province":"WI",
    "wof:name":"Central Wisconsin Pest Control",
    "wof:placetype":"venue"
},
  "geometry": {"coordinates":[-89.610438,44.947827],"type":"Point"}
}