{
  "type": "Feature",
  "properties": {
    "addr:full":"175 Patrick Blvd Brookfield WI 53045",
    "addr:housenumber":"175",
    "addr:postcode":"53045",
    "addr:street":"Patrick Blvd",
    "iso:country":"US",
    "sg:address":"175 Patrick Blvd",
    "sg:city":"Brookfield",
    "sg:classifiers":[
        {
            "category":"Insurance",
            "subcategory":"Insurance Agent",
            "type":"Services"
        }
    ],
    "sg:phone":"+1 262 794 9004",
    "sg:postcode":"53045",
    "sg:province":"WI",
    "sg:tags":[
        "adjuster"
    ],
    "wof:name":"Crawford & Co",
    "wof:placetype":"venue"
},
  "geometry": {"coordinates":[-88.135109,43.033835],"type":"Point"}
}