{
  "type": "Feature",
  "properties": {
    "iso:country":"US",
    "sg:address":"19120 Eton Ct",
    "sg:city":"Brookfield",
    "sg:classifiers":[
        {
            "category":"Professional",
            "subcategory":"Management & Consulting",
            "type":"Services"
        },
        {
            "category":"Banks & Credit Unions",
            "subcategory":"Financial Services",
            "type":"Services"
        }
    ],
    "sg:phone":"+1 262 790 6863",
    "sg:postcode":"53045",
    "sg:province":"WI",
    "sg:tags":[
        "consultant",
        "financing",
        "planning"
    ],
    "wof:name":"Dbrok Group",
    "wof:placetype":"venue"
},
  "geometry": {"coordinates":[-88.149702,43.103686],"type":"Point"}
}