{
  "type": "Feature",
  "properties": {
    "iso:country":"US",
    "sg:address":"4178 Ridge Rd",
    "sg:city":"Deerfield",
    "sg:classifiers":[
        {
            "category":"Shopping",
            "subcategory":"Gifts & Souvenirs",
            "type":"Retail Goods"
        }
    ],
    "sg:phone":"+1 608 839 9813",
    "sg:postcode":"53531",
    "sg:province":"WI",
    "sg:tags":[
        "shop"
    ],
    "wof:name":"Windmill Of Craft USA",
    "wof:placetype":"venue"
},
  "geometry": {"coordinates":[-89.152669,43.07893],"type":"Point"}
}