{
  "type": "Feature",
  "properties": {
    "iso:country":"US",
    "sg:address":"1831 Capital Ave",
    "sg:city":"Madison",
    "sg:classifiers":[
        {
            "category":"Bars & Pubs",
            "type":"Food & Drink"
        }
    ],
    "sg:phone":"+1 608 238 2838",
    "sg:postcode":"53705",
    "sg:province":"WI",
    "sg:tags":[
        "drinking"
    ],
    "wof:name":"Isthmus Properties",
    "wof:placetype":"venue"
},
  "geometry": {"coordinates":[-89.473654,43.086576],"type":"Point"}
}