{
  "type": "Feature",
  "properties": {
    "iso:country":"US",
    "sg:address":"10863 W Bluemound Rd",
    "sg:city":"Milwaukee",
    "sg:classifiers":[
        {
            "category":"Health Services",
            "subcategory":"Doctor",
            "type":"Services"
        }
    ],
    "sg:phone":"+1 414 258 0120",
    "sg:postcode":"53226",
    "sg:province":"WI",
    "wof:name":"Dentist The",
    "wof:placetype":"venue"
},
  "geometry": {"coordinates":[-88.04865100000001,43.035126],"type":"Point"}
}