{
  "type": "Feature",
  "properties": {
    "addr:full":"1417 N 88th Ave Wausau WI 54401",
    "addr:housenumber":"1417",
    "addr:postcode":"54401",
    "addr:street":"N 88Th Ave",
    "iso:country":"US",
    "sg:address":"1417 N 88th Ave",
    "sg:city":"Wausau",
    "sg:classifiers":[
        {
            "category":"Wholesale",
            "subcategory":"Chemicals & Plastics",
            "type":"Manufacturing & Wholesale Goods"
        }
    ],
    "sg:phone":"+1 715 845 1682",
    "sg:postcode":"54401",
    "sg:province":"WI",
    "wof:name":"Amway Products Distributor",
    "wof:placetype":"venue"
},
  "geometry": {"coordinates":[-89.74717800000001,44.980295],"type":"Point"}
}