{
  "type": "Feature",
  "properties": {
    "iso:country":"US",
    "sg:address":"600 S Main St",
    "sg:city":"Oshkosh",
    "sg:classifiers":[
        {
            "category":"Professional",
            "subcategory":"Lawyer & Legal Services",
            "type":"Services"
        }
    ],
    "sg:phone":"+1 920 235 0748",
    "sg:postcode":"54902",
    "sg:province":"WI",
    "sg:tags":[
        "attorney"
    ],
    "wof:name":"William Wilde Law Offices",
    "wof:placetype":"venue"
},
  "geometry": {"coordinates":[-88.538134,44.01169],"type":"Point"}
}