{
  "type": "Feature",
  "properties": {
    "iso:country":"US",
    "sg:address":"10586 Main St",
    "sg:city":"Hayward",
    "sg:classifiers":[
        {
            "category":"Real Estate",
            "subcategory":"Real Estate Agent",
            "type":"Services"
        }
    ],
    "sg:phone":"+1 715 634 8988",
    "sg:postcode":"54843",
    "sg:province":"WI",
    "wof:name":"Northern Pines Realty Inc",
    "wof:placetype":"venue"
},
  "geometry": {"coordinates":[-91.484524,46.014461],"type":"Point"}
}