{
  "type": "Feature",
  "properties": {
    "addr:full":"1380 Gruber Rd Green Bay WI 54313",
    "addr:housenumber":"1380",
    "addr:postcode":"54313",
    "addr:street":"Gruber Rd",
    "iso:country":"US",
    "sg:address":"1380 Gruber Rd",
    "sg:city":"Green Bay",
    "sg:classifiers":[
        {
            "category":"Building & Trades",
            "subcategory":"Construction",
            "type":"Services"
        }
    ],
    "sg:phone":"+1 920 661 9270",
    "sg:postcode":"54313",
    "sg:province":"WI",
    "sg:tags":[
        "painter"
    ],
    "wof:name":"Lessuise Inc Paint Prfnshng",
    "wof:placetype":"venue"
},
  "geometry": {"coordinates":[-88.07224100000001,44.580669],"type":"Point"}
}