{
  "type": "Feature",
  "properties": {
    "iso:country":"US",
    "sg:address":"2601 Lost Dauphin Rd",
    "sg:city":"De Pere",
    "sg:classifiers":[
        {
            "category":"Building & Trades",
            "subcategory":"Construction",
            "type":"Services"
        }
    ],
    "sg:phone":"+1 920 336 2046",
    "sg:postcode":"54115",
    "sg:province":"WI",
    "sg:tags":[
        "home",
        "residential",
        "general",
        "family",
        "contractor"
    ],
    "wof:name":"Able Construction LLC",
    "wof:placetype":"venue"
},
  "geometry": {"coordinates":[-88.11421199999999,44.397861],"type":"Point"}
}