{
  "type": "Feature",
  "properties": {
    "addr:full":"6804 University Ave Middleton WI 53562",
    "addr:housenumber":"6804",
    "addr:postcode":"53562",
    "addr:street":"University Ave",
    "iso:country":"US",
    "sg:address":"6804 University Ave",
    "sg:city":"Middleton",
    "sg:classifiers":[
        {
            "category":"Social Services",
            "subcategory":"Child Care",
            "type":"Services"
        }
    ],
    "sg:phone":"+1 608 836 4433",
    "sg:postcode":"53562",
    "sg:province":"WI",
    "sg:tags":[
        "day"
    ],
    "wof:name":"Cullen Nursery and Day Care",
    "wof:placetype":"venue"
},
  "geometry": {"coordinates":[-89.49842200000001,43.097075],"type":"Point"}
}