{
  "type": "Feature",
  "properties": {
    "iso:country":"US",
    "sg:address":"2215 Johanson Rd",
    "sg:city":"Iola",
    "sg:classifiers":[
        {
            "category":"Real Estate",
            "subcategory":"Real Estate Agent",
            "type":"Services"
        }
    ],
    "sg:phone":"+1 715 445 3358",
    "sg:postcode":"54945",
    "sg:province":"WI",
    "wof:name":"Rice & Rice",
    "wof:placetype":"venue"
},
  "geometry": {"coordinates":[-89.119317,44.491336],"type":"Point"}
}