{
  "type": "Feature",
  "properties": {
    "iso:country":"US",
    "sg:address":"19372 Dayton Ridge Rd",
    "sg:city":"Richland Center",
    "sg:classifiers":[
        {
            "category":"Real Estate",
            "subcategory":"Real Estate Agent",
            "type":"Services"
        }
    ],
    "sg:phone":"+1 608 647 8664",
    "sg:postcode":"53581",
    "sg:province":"WI",
    "wof:name":"Granger Enterprises",
    "wof:placetype":"venue"
},
  "geometry": {"coordinates":[-90.494548,43.333077],"type":"Point"}
}