{
  "type": "Feature",
  "properties": {
    "addr:full":"11736 Mink River Rd Ellison Bay WI 54210",
    "addr:housenumber":"11736",
    "addr:postcode":"54210",
    "addr:street":"Mink River Rd",
    "iso:country":"US",
    "sg:address":"11736 Mink River Rd",
    "sg:city":"Ellison Bay",
    "sg:classifiers":[
        {
            "category":"Wholesale",
            "subcategory":"Non-durable Goods",
            "type":"Manufacturing & Wholesale Goods"
        }
    ],
    "sg:phone":"+1 920 854 4839",
    "sg:postcode":"54210",
    "sg:province":"WI",
    "wof:name":"Mary Ellen Sisulak",
    "wof:placetype":"venue"
},
  "geometry": {"coordinates":[-87.061442,45.24322],"type":"Point"}
}