{
  "type": "Feature",
  "properties": {
    "addr:full":"242 McKay Ave Spring Valley WI 54767",
    "addr:housenumber":"242",
    "addr:postcode":"54767",
    "addr:street":"Mckay Ave",
    "iso:country":"US",
    "sg:address":"242 McKay Ave",
    "sg:city":"Spring Valley",
    "sg:classifiers":[
        {
            "category":"Social Services",
            "type":"Services"
        }
    ],
    "sg:phone":"+1 715 778 5790",
    "sg:postcode":"54767",
    "sg:province":"WI",
    "sg:tags":[
        "senior",
        "citizen"
    ],
    "wof:name":"Senior Citizen Ctr",
    "wof:placetype":"venue"
},
  "geometry": {"coordinates":[-92.238477,44.848486],"type":"Point"}
}