{
  "type": "Feature",
  "properties": {
    "iso:country":"US",
    "sg:address":"14408 W Kostner Ln",
    "sg:city":"New Berlin",
    "sg:classifiers":[
        {
            "category":"Manufacturing",
            "subcategory":"Electronics",
            "type":"Manufacturing & Wholesale Goods"
        }
    ],
    "sg:phone":"+1 262 786 6410",
    "sg:postcode":"53151",
    "sg:province":"WI",
    "sg:tags":[
        "control",
        "mfr",
        "electronic",
        "panel"
    ],
    "wof:name":"Powertronics Industries Inc",
    "wof:placetype":"venue"
},
  "geometry": {"coordinates":[-88.093935,43.011551],"type":"Point"}
}