{
  "type": "Feature",
  "properties": {
    "iso:country":"US",
    "sg:address":"1960 62nd St",
    "sg:city":"Somerset",
    "sg:classifiers":[
        {
            "category":"Building & Trades",
            "subcategory":"Construction",
            "type":"Services"
        }
    ],
    "sg:phone":"+1 715 247 5337",
    "sg:postcode":"54025",
    "sg:province":"WI",
    "sg:tags":[
        "house"
    ],
    "wof:name":"Hartman Homes Inc",
    "wof:placetype":"venue"
},
  "geometry": {"coordinates":[-92.688198,45.147825],"type":"Point"}
}