{
  "type": "Feature",
  "properties": {
    "iso:country":"US",
    "sg:address":"229 2nd St",
    "sg:city":"Gays Mills",
    "sg:classifiers":[
        {
            "category":"Manufacturing",
            "subcategory":"Wood Products",
            "type":"Manufacturing & Wholesale Goods"
        }
    ],
    "sg:phone":"+1 608 735 4245",
    "sg:postcode":"54631",
    "sg:province":"WI",
    "sg:tags":[
        "mfg"
    ],
    "wof:name":"Classic Designs Woodworking",
    "wof:placetype":"venue"
},
  "geometry": {"coordinates":[-90.827462,43.291557],"type":"Point"}
}