{
  "type": "Feature",
  "properties": {
    "addr:full":"407 S 2nd St Alma WI 54610",
    "addr:housenumber":"407",
    "addr:postcode":"54610",
    "addr:street":"S 2Nd St",
    "iso:country":"US",
    "sg:address":"407 S 2nd St",
    "sg:city":"Alma",
    "sg:classifiers":[
        {
            "category":"Professional",
            "subcategory":"Employment Agencies",
            "type":"Services"
        }
    ],
    "sg:phone":"+1 608 685 6246",
    "sg:postcode":"54610",
    "sg:province":"WI",
    "sg:tags":[
        "leasing"
    ],
    "wof:name":"Gemini Employee Leasing",
    "wof:placetype":"venue"
},
  "geometry": {"coordinates":[-91.91330000000001,44.31888],"type":"Point"}
}