{
  "type": "Feature",
  "properties": {
    "iso:country":"US",
    "sg:address":"30 W Central St",
    "sg:city":"Chippewa Falls",
    "sg:classifiers":[
        {
            "category":"Government",
            "subcategory":"Office",
            "type":"Public Place"
        }
    ],
    "sg:phone":"+1 715 726 2734",
    "sg:postcode":"54729",
    "sg:province":"WI",
    "sg:tags":[
        "city"
    ],
    "wof:name":"Chippewa Falls Mayors Office",
    "wof:placetype":"venue"
},
  "geometry": {"coordinates":[-91.393477,44.935825],"type":"Point"}
}