{
  "type": "Feature",
  "properties": {
    "iso:country":"US",
    "sg:address":"9419 N 49th St",
    "sg:city":"Milwaukee",
    "sg:classifiers":[
        {
            "category":"Building & Trades",
            "subcategory":"Construction",
            "type":"Services"
        }
    ],
    "sg:phone":"+1 414 460 1966",
    "sg:postcode":"53223",
    "sg:province":"WI",
    "sg:tags":[
        "roofing",
        "contractor",
        "automotive"
    ],
    "wof:name":"Tuff Shield Exterior",
    "wof:placetype":"venue"
},
  "geometry": {"coordinates":[-87.971783,43.192345],"type":"Point"}
}