{
  "type": "Feature",
  "properties": {
    "iso:country":"US",
    "sg:address":"2702 Monroe St",
    "sg:city":"Madison",
    "sg:classifiers":[
        {
            "category":"Organizations",
            "subcategory":"Non-profit Organization",
            "type":"Services"
        }
    ],
    "sg:phone":"+1 608 233 5440",
    "sg:postcode":"53711",
    "sg:province":"WI",
    "sg:tags":[
        "charitable",
        "institution"
    ],
    "wof:name":"Wisconsin Right To Life Dane",
    "wof:placetype":"venue"
},
  "geometry": {"coordinates":[-89.429677,43.056751],"type":"Point"}
}