{
  "type": "Feature",
  "properties": {
    "addr:full":"10050 Dardis Lake Ln Phillips WI 54555",
    "addr:housenumber":"10050",
    "addr:postcode":"54555",
    "addr:street":"Dardis Lake Ln",
    "iso:country":"US",
    "sg:address":"10050 Dardis Lake Ln",
    "sg:city":"Phillips",
    "sg:classifiers":[
        {
            "category":"Shopping",
            "subcategory":"Gifts & Souvenirs",
            "type":"Retail Goods"
        }
    ],
    "sg:phone":"+1 715 339 2035",
    "sg:postcode":"54555",
    "sg:province":"WI",
    "sg:tags":[
        "shop"
    ],
    "wof:name":"Minnow Lake Loft",
    "wof:placetype":"venue"
},
  "geometry": {"coordinates":[-90.324237,45.740371],"type":"Point"}
}