{
  "type": "Feature",
  "properties": {
    "iso:country":"US",
    "sg:address":"1224 King St",
    "sg:city":"La Crosse",
    "sg:classifiers":[
        {
            "category":"Building & Trades",
            "subcategory":"Construction",
            "type":"Services"
        }
    ],
    "sg:phone":"+1 608 780 4672",
    "sg:postcode":"54601",
    "sg:province":"WI",
    "sg:tags":[
        "general",
        "nonresidential",
        "contractor"
    ],
    "wof:name":"Jim WEBB Engineering & Constr",
    "wof:placetype":"venue"
},
  "geometry": {"coordinates":[-91.23784999999999,43.809999],"type":"Point"}
}