{
  "type": "Feature",
  "properties": {
    "iso:country":"US",
    "sg:address":"424 Fremont St",
    "sg:city":"Kiel",
    "sg:classifiers":[
        {
            "category":"Organizations",
            "subcategory":"Religious Organization",
            "type":"Services"
        }
    ],
    "sg:phone":"+1 920 894 2404",
    "sg:postcode":"53042",
    "sg:province":"WI",
    "sg:tags":[
        "church"
    ],
    "sg:website":"www.tcei.com/spucc",
    "wof:name":"St Peters United Church Christ",
    "wof:placetype":"venue"
},
  "geometry": {"coordinates":[-88.035601,43.912585],"type":"Point"}
}