{
  "type": "Feature",
  "properties": {
    "addr:full":"4905 Substation Rd Lancaster WI 53813",
    "addr:housenumber":"4905",
    "addr:postcode":"53813",
    "addr:street":"Substation Rd",
    "iso:country":"US",
    "sg:address":"4905 Substation Rd",
    "sg:city":"Lancaster",
    "sg:phone":"+1 608 723 2368",
    "sg:postcode":"53813",
    "sg:province":"WI",
    "sg:tags":[
        "farm",
        "corn"
    ],
    "wof:name":"Harold Wiederholt",
    "wof:placetype":"venue"
},
  "geometry": {"coordinates":[-90.66719399999999,42.77055],"type":"Point"}
}