{
  "type": "Feature",
  "properties": {
    "iso:country":"US",
    "sg:address":"200 S Madison St",
    "sg:city":"Waupun",
    "sg:classifiers":[
        {
            "category":"Government",
            "subcategory":"Jail",
            "type":"Public Place"
        }
    ],
    "sg:phone":"+1 920 324 5571",
    "sg:postcode":"53963",
    "sg:province":"WI",
    "sg:tags":[
        "govt",
        "state",
        "institution"
    ],
    "wof:name":"Waupun Correctional Institute",
    "wof:placetype":"venue"
},
  "geometry": {"coordinates":[-88.729734,43.628415],"type":"Point"}
}