{
  "type": "Feature",
  "properties": {
    "iso:country":"US",
    "sg:address":"5 E Monico St",
    "sg:city":"Rhinelander",
    "sg:classifiers":[
        {
            "category":"Autos & Motor Vehicles",
            "subcategory":"Fuel & Gas Station",
            "type":"Retail Goods"
        }
    ],
    "sg:phone":"+1 715 369 2972",
    "sg:postcode":"54501",
    "sg:province":"WI",
    "sg:tags":[
        "repair",
        "station",
        "gasoline",
        "general"
    ],
    "wof:name":"Northwoods Auto Techs",
    "wof:placetype":"venue"
},
  "geometry": {"coordinates":[-89.404712,45.651431],"type":"Point"}
}