{
  "type": "Feature",
  "properties": {
    "addr:full":"2011 State Hwy 40 Colfax WI 54730",
    "addr:housenumber":"2011",
    "addr:postcode":"54730",
    "addr:street":"State Hwy 40",
    "iso:country":"US",
    "sg:address":"2011 State Hwy 40",
    "sg:city":"Colfax",
    "sg:classifiers":[
        {
            "category":"Bars & Pubs",
            "type":"Food & Drink"
        }
    ],
    "sg:phone":"+1 715 962 4695",
    "sg:postcode":"54730",
    "sg:province":"WI",
    "wof:name":"Club 40",
    "wof:placetype":"venue"
},
  "geometry": {"coordinates":[-91.631343,45.0085],"type":"Point"}
}