{
  "type": "Feature",
  "properties": {
    "iso:country":"US",
    "sg:address":"514 S Main St",
    "sg:city":"Westby",
    "sg:classifiers":[
        {
            "category":"Organizations",
            "subcategory":"Professional Association",
            "type":"Services"
        }
    ],
    "sg:phone":"+1 608 634 4011",
    "sg:postcode":"54667",
    "sg:province":"WI",
    "sg:tags":[
        "chambers",
        "commerce"
    ],
    "wof:name":"Westby Chamber Of Commerce",
    "wof:placetype":"venue"
},
  "geometry": {"coordinates":[-90.859813,43.649755],"type":"Point"}
}