{
  "type": "Feature",
  "properties": {
    "iso:country":"US",
    "sg:address":"5748 Nasturtium Ave",
    "sg:city":"Cashton",
    "sg:classifiers":[
        {
            "category":"Professional",
            "subcategory":"Business Services",
            "type":"Services"
        }
    ],
    "sg:phone":"+1 608 654 5777",
    "sg:postcode":"54619",
    "sg:province":"WI",
    "wof:name":"Dickson Enterprises",
    "wof:placetype":"venue"
},
  "geometry": {"coordinates":[-90.877004,43.755765],"type":"Point"}
}