{
  "type": "Feature",
  "properties": {
    "iso:country":"US",
    "sg:address":"2059 Linway Dr",
    "sg:city":"Beloit",
    "sg:classifiers":[
        {
            "category":"Real Estate",
            "subcategory":"Real Estate Operator",
            "type":"Services"
        }
    ],
    "sg:phone":"+1 608 346 3722",
    "sg:postcode":"53511",
    "sg:province":"IL",
    "sg:tags":[
        "sales"
    ],
    "wof:name":"McFall Real Estate",
    "wof:placetype":"venue"
},
  "geometry": {"coordinates":[-89.075304,42.527356],"type":"Point"}
}