{
  "type": "Feature",
  "properties": {
    "iso:country":"US",
    "sg:address":"311 E Main St",
    "sg:city":"Mt Horeb",
    "sg:classifiers":[
        {
            "category":"Insurance",
            "subcategory":"Insurance Agent",
            "type":"Services"
        }
    ],
    "sg:phone":"+1 608 437 8492",
    "sg:postcode":"53572",
    "sg:province":"WI",
    "wof:name":"Marty Insurance & Financial",
    "wof:placetype":"venue"
},
  "geometry": {"coordinates":[-89.736603,43.008591],"type":"Point"}
}