{
  "type": "Feature",
  "properties": {
    "iso:country":"US",
    "sg:address":"1658 State Hwy 42",
    "sg:city":"Maplewood",
    "sg:classifiers":[
        {
            "category":"Building & Trades",
            "subcategory":"Construction",
            "type":"Services"
        }
    ],
    "sg:phone":"+1 920 856 6977",
    "sg:postcode":"54201",
    "sg:province":"WI",
    "sg:tags":[
        "house",
        "carpentry",
        "contractor"
    ],
    "wof:name":"Heartland Builders",
    "wof:placetype":"venue"
},
  "geometry": {"coordinates":[-87.44124600000001,44.597802],"type":"Point"}
}