{
  "type": "Feature",
  "properties": {
    "addr:full":"1625 Maple Ln Ashland WI 54806",
    "addr:housenumber":"1625",
    "addr:postcode":"54806",
    "addr:street":"Maple Ln",
    "iso:country":"US",
    "sg:address":"1625 Maple Ln",
    "sg:city":"Ashland",
    "sg:classifiers":[
        {
            "category":"Health Services",
            "subcategory":"Doctor",
            "type":"Services"
        }
    ],
    "sg:phone":"+1 715 682 9311",
    "sg:postcode":"54806",
    "sg:province":"WI",
    "sg:tags":[
        "physician",
        "surgeon",
        "medical"
    ],
    "sg:website":"www.drhamp.com",
    "wof:name":"Ent Professional Assoc SC",
    "wof:placetype":"venue"
},
  "geometry": {"coordinates":[-90.89031799999999,46.566954],"type":"Point"}
}