{
  "type": "Feature",
  "properties": {
    "iso:country":"US",
    "sg:address":"469 Clifton Rd",
    "sg:city":"Sherwood",
    "sg:classifiers":[
        {
            "category":"Government",
            "subcategory":"Fire Station",
            "type":"Public Place"
        }
    ],
    "sg:phone":"+1 920 989 1066",
    "sg:postcode":"54169",
    "sg:province":"WI",
    "sg:tags":[
        "protection"
    ],
    "wof:name":"Harrison Fire Dept",
    "wof:placetype":"venue"
},
  "geometry": {"coordinates":[-88.263031,44.17356],"type":"Point"}
}