{
  "type": "Feature",
  "properties": {
    "iso:country":"US",
    "sg:address":"903 N 2nd St",
    "sg:city":"Wausau",
    "sg:classifiers":[
        {
            "category":"Real Estate",
            "subcategory":"Real Estate Operator",
            "type":"Services"
        }
    ],
    "sg:phone":"+1 715 842 3343",
    "sg:postcode":"54403",
    "sg:province":"WI",
    "sg:tags":[
        "building",
        "nonresidential"
    ],
    "wof:name":"Community Service Center",
    "wof:placetype":"venue"
},
  "geometry": {"coordinates":[-89.62839099999999,44.964908],"type":"Point"}
}