{
  "type": "Feature",
  "properties": {
    "iso:country":"US",
    "sg:address":"600 21st Ave",
    "sg:city":"Bloomer",
    "sg:classifiers":[
        {
            "category":"Manufacturing",
            "subcategory":"Metals",
            "type":"Manufacturing & Wholesale Goods"
        }
    ],
    "sg:phone":"+1 715 568 1700",
    "sg:postcode":"54724",
    "sg:province":"WI",
    "sg:tags":[
        "stampings",
        "mfg"
    ],
    "wof:name":"PMI",
    "wof:placetype":"venue"
},
  "geometry": {"coordinates":[-91.479973,45.095614],"type":"Point"}
}