{
  "type": "Feature",
  "properties": {
    "addr:full":"5805 Anchorage Ave Madison WI 53705",
    "addr:housenumber":"5805",
    "addr:postcode":"53705",
    "addr:street":"Anchorage Ave",
    "iso:country":"US",
    "sg:address":"5805 Anchorage Ave",
    "sg:city":"Madison",
    "sg:classifiers":[
        {
            "category":"Organizations",
            "subcategory":"Membership Organization",
            "type":"Services"
        }
    ],
    "sg:phone":"+1 608 232 7044",
    "sg:postcode":"53705",
    "sg:province":"WI",
    "sg:tags":[
        "society",
        "humane"
    ],
    "wof:name":"House Rabbit Society",
    "wof:placetype":"venue"
},
  "geometry": {"coordinates":[-89.4812,43.06732],"type":"Point"}
}