{
  "type": "Feature",
  "properties": {
    "iso:country":"US",
    "sg:address":"1840 Dickinson Rd",
    "sg:city":"De Pere",
    "sg:classifiers":[
        {
            "category":"Food & Beverages",
            "subcategory":"Bakery",
            "type":"Retail Goods"
        }
    ],
    "sg:phone":"+1 920 330 0300",
    "sg:postcode":"54115",
    "sg:province":"WI",
    "sg:tags":[
        "baker"
    ],
    "wof:name":"Uncle Mikes Bake Shoppe LLC",
    "wof:placetype":"venue"
},
  "geometry": {"coordinates":[-88.037569,44.44],"type":"Point"}
}