{
  "type": "Feature",
  "properties": {
    "iso:country":"US",
    "sg:address":"5925 Haase Rd",
    "sg:city":"De Forest",
    "sg:classifiers":[
        {
            "category":"Retail",
            "subcategory":"Animal Services",
            "type":"Services"
        }
    ],
    "sg:phone":"+1 608 242 8824",
    "sg:postcode":"53532",
    "sg:province":"WI",
    "sg:tags":[
        "cat",
        "dog",
        "kennel"
    ],
    "wof:name":"Badger Kennel Club",
    "wof:placetype":"venue"
},
  "geometry": {"coordinates":[-89.32112100000001,43.173925],"type":"Point"}
}