{
  "type": "Feature",
  "properties": {
    "iso:country":"US",
    "sg:address":"6713 Odana Rd",
    "sg:city":"Madison",
    "sg:classifiers":[
        {
            "category":"Personal",
            "subcategory":"Tattoo Parlor",
            "type":"Services"
        }
    ],
    "sg:phone":"+1 608 833 3310",
    "sg:postcode":"53719",
    "sg:province":"WI",
    "sg:tags":[
        "tattooing"
    ],
    "sg:website":"www.tattoomadison.com",
    "wof:name":"Blue Lotus Tattoo & Body Prcng",
    "wof:placetype":"venue"
},
  "geometry": {"coordinates":[-89.501277,43.056523],"type":"Point"}
}