{
  "type": "Feature",
  "properties": {
    "iso:country":"US",
    "sg:address":"112 W Court St",
    "sg:city":"Viroqua",
    "sg:classifiers":[
        {
            "category":"Shopping",
            "subcategory":"Used Merchandise",
            "type":"Retail Goods"
        },
        {
            "category":"Shopping",
            "subcategory":"Bicycles & Sporting Goods",
            "type":"Retail Goods"
        }
    ],
    "sg:phone":"+1 608 637 3992",
    "sg:postcode":"54665",
    "sg:province":"WI",
    "sg:tags":[
        "gun",
        "gunsmith"
    ],
    "wof:name":"Dave's Gun & Pawn Shop",
    "wof:placetype":"venue"
},
  "geometry": {"coordinates":[-90.890473,43.556275],"type":"Point"}
}