{
  "type": "Feature",
  "properties": {
    "addr:full":"705 State Road 70 Grantsburg WI 54840",
    "addr:housenumber":"705",
    "addr:postcode":"54840",
    "addr:street":"State Road 70",
    "iso:country":"US",
    "sg:address":"705 State Road 70",
    "sg:city":"Grantsburg",
    "sg:classifiers":[
        {
            "category":"Health Services",
            "subcategory":"Chiropractor",
            "type":"Services"
        }
    ],
    "sg:phone":"+1 715 463 5766",
    "sg:postcode":"54840",
    "sg:province":"WI",
    "sg:tags":[
        "chiropractic"
    ],
    "sg:website":"http://www.bontchiropractic.com",
    "wof:name":"Bont Chiropractic Clinic",
    "wof:placetype":"venue"
},
  "geometry": {"coordinates":[-92.70298699999999,45.772996],"type":"Point"}
}