{
  "type": "Feature",
  "properties": {
    "addr:full":"305 E Madison Ave Milton WI 53563",
    "addr:housenumber":"305",
    "addr:postcode":"53563",
    "addr:street":"E Madison Ave",
    "iso:country":"US",
    "sg:address":"305 E Madison Ave",
    "sg:city":"Milton",
    "sg:classifiers":[
        {
            "category":"Manufacturing",
            "subcategory":"Apparel",
            "type":"Manufacturing & Wholesale Goods"
        }
    ],
    "sg:phone":"+1 608 868 4089",
    "sg:postcode":"53563",
    "sg:province":"WI",
    "sg:tags":[
        "merchandise",
        "mfg"
    ],
    "wof:name":"Undercover Shop",
    "wof:placetype":"venue"
},
  "geometry": {"coordinates":[-88.94575399999999,42.778609],"type":"Point"}
}