{
  "type": "Feature",
  "properties": {
    "iso:country":"US",
    "sg:address":"776 Vanguard Way",
    "sg:city":"Green Bay",
    "sg:classifiers":[
        {
            "category":"Insurance",
            "subcategory":"Insurance Agent",
            "type":"Services"
        }
    ],
    "sg:phone":"+1 920 434 9529",
    "sg:postcode":"54313",
    "sg:province":"WI",
    "wof:name":"Maple Valley Insurance",
    "wof:placetype":"venue"
},
  "geometry": {"coordinates":[-88.10272,44.561608],"type":"Point"}
}