{
  "type": "Feature",
  "properties": {
    "iso:country":"US",
    "sg:address":"5400 S Lake Dr",
    "sg:city":"Cudahy",
    "sg:classifiers":[
        {
            "category":"Sports & Exercise",
            "subcategory":"Golf",
            "type":"Entertainment"
        }
    ],
    "sg:phone":"+1 414 481 1400",
    "sg:postcode":"53110",
    "sg:province":"WI",
    "sg:tags":[
        "course",
        "instruction"
    ],
    "wof:name":"Park Warnimont Golf Course",
    "wof:placetype":"venue"
},
  "geometry": {"coordinates":[-87.849937,42.94656],"type":"Point"}
}