{
  "type": "Feature",
  "properties": {
    "addr:full":"154 N 4th Ave Sturgeon Bay WI 54235",
    "addr:housenumber":"154",
    "addr:postcode":"54235",
    "addr:street":"N 4Th Ave",
    "iso:country":"US",
    "sg:address":"154 N 4th Ave",
    "sg:city":"Sturgeon Bay",
    "sg:classifiers":[
        {
            "category":"Autos & Motor Vehicles",
            "subcategory":"Fuel & Gas Station",
            "type":"Retail Goods"
        }
    ],
    "sg:phone":"+1 920 743 1508",
    "sg:postcode":"54235",
    "sg:province":"WI",
    "sg:tags":[
        "grocery",
        "station",
        "gasoline"
    ],
    "wof:name":"Speedway Superamerica LLC",
    "wof:placetype":"venue"
},
  "geometry": {"coordinates":[-87.376276,44.836044],"type":"Point"}
}