{
  "type": "Feature",
  "properties": {
    "iso:country":"US",
    "sg:address":"314 Broadway St",
    "sg:city":"Baraboo",
    "sg:classifiers":[
        {
            "category":"Autos & Motor Vehicles",
            "subcategory":"Fuel & Gas Station",
            "type":"Retail Goods"
        }
    ],
    "sg:phone":"+1 608 356 8466",
    "sg:postcode":"53913",
    "sg:province":"WI",
    "sg:tags":[
        "gasoline",
        "station",
        "truck"
    ],
    "wof:name":"U-Haul",
    "wof:placetype":"venue"
},
  "geometry": {"coordinates":[-89.744203,43.468837],"type":"Point"}
}