{
  "type": "Feature",
  "properties": {
    "iso:country":"US",
    "sg:address":"1322 Mid Valley Dr",
    "sg:city":"De Pere",
    "sg:classifiers":[
        {
            "category":"Building & Trades",
            "subcategory":"Construction",
            "type":"Services"
        }
    ],
    "sg:phone":"+1 920 983 1607",
    "sg:postcode":"54115",
    "sg:province":"WI",
    "sg:tags":[
        "cabinet",
        "carpentry",
        "maker",
        "contractor"
    ],
    "wof:name":"Hilltop Woodworking Inc",
    "wof:placetype":"venue"
},
  "geometry": {"coordinates":[-88.09618,44.444367],"type":"Point"}
}