{
  "type": "Feature",
  "properties": {
    "addr:full":"501 Jefferson St Oregon WI 53575",
    "addr:housenumber":"501",
    "addr:postcode":"53575",
    "addr:street":"Jefferson St",
    "iso:country":"US",
    "sg:address":"501 Jefferson St",
    "sg:city":"Oregon",
    "sg:classifiers":[
        {
            "category":"Professional",
            "type":"Services"
        }
    ],
    "sg:phone":"+1 608 835 5295",
    "sg:postcode":"53575",
    "sg:province":"WI",
    "wof:name":"Stanley Wright",
    "wof:placetype":"venue"
},
  "geometry": {"coordinates":[-89.38988999999999,42.928233],"type":"Point"}
}