{
  "type": "Feature",
  "properties": {
    "iso:country":"US",
    "sg:address":"6827 Airport Rd",
    "sg:city":"Three Lakes",
    "sg:phone":"+1 715 546 2691",
    "sg:postcode":"54562",
    "sg:province":"WI",
    "sg:tags":[
        "equipment",
        "station"
    ],
    "wof:name":"Northland Petroleum Corp",
    "wof:placetype":"venue"
},
  "geometry": {"coordinates":[-89.122777,45.791814],"type":"Point"}
}