{
  "type": "Feature",
  "properties": {
    "iso:country":"US",
    "sg:address":"3009 Zuehlke Dr",
    "sg:city":"Appleton",
    "sg:classifiers":[
        {
            "category":"Wholesale",
            "subcategory":"Hardware",
            "type":"Manufacturing & Wholesale Goods"
        }
    ],
    "sg:phone":"+1 920 830 2378",
    "sg:postcode":"54911",
    "sg:province":"WI",
    "sg:tags":[
        "plumbing",
        "fixture",
        "heating",
        "supply"
    ],
    "wof:name":"Able Distributing Co Inc",
    "wof:placetype":"venue"
},
  "geometry": {"coordinates":[-88.35848799999999,44.289179],"type":"Point"}
}