{
  "type": "Feature",
  "properties": {
    "addr:full":"600 University St Elk Mound WI 54739",
    "addr:housenumber":"600",
    "addr:postcode":"54739",
    "addr:street":"University St",
    "iso:country":"US",
    "sg:address":"600 University St",
    "sg:city":"Elk Mound",
    "sg:classifiers":[
        {
            "category":"Farming",
            "subcategory":"Livestock Farm",
            "type":"Manufacturing & Wholesale Goods"
        },
        {
            "category":"Farming",
            "subcategory":"Farm",
            "type":"Manufacturing & Wholesale Goods"
        }
    ],
    "sg:phone":"+1 715 874 5441",
    "sg:postcode":"54739",
    "sg:province":"WI",
    "sg:tags":[
        "feedlot",
        "hog",
        "corn",
        "or",
        "soybean"
    ],
    "wof:name":"E & L Harrison Enterprises Inc",
    "wof:placetype":"venue"
},
  "geometry": {"coordinates":[-91.681597,44.874685],"type":"Point"}
}