{
  "type": "Feature",
  "properties": {
    "iso:country":"US",
    "sg:address":"808 Smith St",
    "sg:city":"Stevens Point",
    "sg:classifiers":[
        {
            "category":"Building & Trades",
            "subcategory":"Construction",
            "type":"Services"
        }
    ],
    "sg:phone":"+1 715 342 4275",
    "sg:postcode":"54481",
    "sg:province":"WI",
    "sg:tags":[
        "concrete",
        "contractor"
    ],
    "wof:name":"Alchemy Concrete Inc",
    "wof:placetype":"venue"
},
  "geometry": {"coordinates":[-89.57883,44.527893],"type":"Point"}
}