{
  "type": "Feature",
  "properties": {
    "iso:country":"US",
    "sg:address":"3332 N 7th St",
    "sg:city":"Sheboygan",
    "sg:classifiers":[
        {
            "category":"Building & Trades",
            "subcategory":"Landscaping Services",
            "type":"Services"
        }
    ],
    "sg:phone":"+1 920 452 3695",
    "sg:postcode":"53083",
    "sg:province":"WI",
    "sg:tags":[
        "landscape"
    ],
    "wof:name":"Crocker Design",
    "wof:placetype":"venue"
},
  "geometry": {"coordinates":[-87.71212199999999,43.781521],"type":"Point"}
}