{
  "type": "Feature",
  "properties": {
    "iso:country":"US",
    "sg:address":"3651 State Hwy 149",
    "sg:city":"Malone",
    "sg:classifiers":[
        {
            "category":"Banks & Credit Unions",
            "subcategory":"Investment Brokerage",
            "type":"Services"
        }
    ],
    "sg:phone":"+1 920 926 0198",
    "sg:postcode":"53049",
    "sg:province":"WI",
    "sg:tags":[
        "consultant",
        "planning",
        "financial"
    ],
    "sg:website":"www.vestech.com",
    "wof:name":"Vesper Technologies",
    "wof:placetype":"venue"
},
  "geometry": {"coordinates":[-88.340486,43.8339],"type":"Point"}
}