{
  "type": "Feature",
  "properties": {
    "addr:full":"1115 W Green Tree Rd Milwaukee WI 53217",
    "addr:housenumber":"1115",
    "addr:postcode":"53217",
    "addr:street":"W Green Tree Rd",
    "iso:country":"US",
    "sg:address":"1115 W Green Tree Rd",
    "sg:city":"Milwaukee",
    "sg:classifiers":[
        {
            "category":"Shopping",
            "subcategory":"Used Merchandise",
            "type":"Retail Goods"
        }
    ],
    "sg:phone":"+1 414 352 1521",
    "sg:postcode":"53217",
    "sg:province":"WI",
    "sg:tags":[
        "antique"
    ],
    "wof:name":"Elizabeth Bradley Antiques",
    "wof:placetype":"venue"
},
  "geometry": {"coordinates":[-87.924592,43.144198],"type":"Point"}
}