{
  "type": "Feature",
  "properties": {
    "iso:country":"US",
    "sg:address":"8222 Lincoln Rd",
    "sg:city":"Van Dyne",
    "sg:classifiers":[
        {
            "category":"Farming",
            "subcategory":"Livestock Farm",
            "type":"Manufacturing & Wholesale Goods"
        }
    ],
    "sg:phone":"+1 920 688 5157",
    "sg:postcode":"54979",
    "sg:province":"WI",
    "sg:tags":[
        "beef",
        "feedlot",
        "cattle"
    ],
    "wof:name":"Harold Hinz",
    "wof:placetype":"venue"
},
  "geometry": {"coordinates":[-88.580052,43.879463],"type":"Point"}
}