{
  "type": "Feature",
  "properties": {
    "iso:country":"US",
    "sg:address":"1115 21st Ave N",
    "sg:city":"Wisconsin Rapids",
    "sg:classifiers":[
        {
            "category":"Wholesale",
            "subcategory":"Machinery & Supplies",
            "type":"Manufacturing & Wholesale Goods"
        }
    ],
    "sg:phone":"+1 715 421 3453",
    "sg:postcode":"54495",
    "sg:province":"WI",
    "sg:tags":[
        "equipment",
        "veterinarian"
    ],
    "wof:name":"W A Butler Co",
    "wof:placetype":"venue"
},
  "geometry": {"coordinates":[-89.84976,44.404273],"type":"Point"}
}