{
  "type": "Feature",
  "properties": {
    "iso:country":"US",
    "sg:address":"303 McKay Ave",
    "sg:city":"Spring Valley",
    "sg:classifiers":[
        {
            "category":"Manufacturing",
            "subcategory":"Chemicals & Compounds",
            "type":"Manufacturing & Wholesale Goods"
        }
    ],
    "sg:phone":"+1 715 778 5928",
    "sg:postcode":"54767",
    "sg:province":"WI",
    "sg:tags":[
        "preparation",
        "pharmaceutical"
    ],
    "sg:website":"www.veterinaryconcepts.com",
    "wof:name":"Veterinary Concepts Inc",
    "wof:placetype":"venue"
},
  "geometry": {"coordinates":[-92.23859,44.849167],"type":"Point"}
}