{
  "type": "Feature",
  "properties": {
    "iso:country":"US",
    "sg:address":"15805 N 1st St",
    "sg:city":"Hayward",
    "sg:classifiers":[
        {
            "category":"Professional",
            "subcategory":"Business Services",
            "type":"Services"
        }
    ],
    "sg:phone":"+1 715 634 4801",
    "sg:postcode":"54843",
    "sg:province":"WI",
    "sg:tags":[
        "operation"
    ],
    "wof:name":"Hayward Lakes Resort Assn",
    "wof:placetype":"venue"
},
  "geometry": {"coordinates":[-91.493228,46.020685],"type":"Point"}
}