{
  "type": "Feature",
  "properties": {
    "iso:country":"US",
    "sg:address":"6153 N Santa Monica Blvd",
    "sg:city":"Milwaukee",
    "sg:classifiers":[
        {
            "category":"Real Estate",
            "subcategory":"Real Estate Operator",
            "type":"Services"
        }
    ],
    "sg:phone":"+1 414 332 2439",
    "sg:postcode":"53217",
    "sg:province":"WI",
    "sg:tags":[
        "building",
        "nonresidential"
    ],
    "wof:name":"62nd Street Property LLC",
    "wof:placetype":"venue"
},
  "geometry": {"coordinates":[-87.906527,43.128489],"type":"Point"}
}