{
  "type": "Feature",
  "properties": {
    "iso:country":"US",
    "sg:address":"1044 Pleasant Ave",
    "sg:city":"Arcadia",
    "sg:classifiers":[
        {
            "category":"Personal",
            "subcategory":"Beauty Salon",
            "type":"Services"
        }
    ],
    "sg:phone":"+1 608 323 3403",
    "sg:postcode":"54612",
    "sg:province":"WI",
    "sg:tags":[
        "shop"
    ],
    "wof:name":"Lady JS",
    "wof:placetype":"venue"
},
  "geometry": {"coordinates":[-91.486798,44.247724],"type":"Point"}
}