{
  "type": "Feature",
  "properties": {
    "iso:country":"US",
    "sg:address":"334 N Cherry St",
    "sg:city":"Whitewater",
    "sg:classifiers":[
        {
            "category":"Freight",
            "type":"Transportation"
        }
    ],
    "sg:phone":"+1 262 473 1183",
    "sg:postcode":"53190",
    "sg:province":"WI",
    "sg:tags":[
        "pier"
    ],
    "wof:name":"Summerset Pier Service",
    "wof:placetype":"venue"
},
  "geometry": {"coordinates":[-88.726652,42.838429],"type":"Point"}
}