{
  "type": "Feature",
  "properties": {
    "addr:full":"111 Shanghai Ridge Rd Eastman WI 54626",
    "addr:housenumber":"111",
    "addr:postcode":"54626",
    "addr:street":"Shanghai Ridge Rd",
    "iso:country":"US",
    "sg:address":"111 Shanghai Ridge Rd",
    "sg:city":"Eastman",
    "sg:classifiers":[
        {
            "category":"Wholesale",
            "subcategory":"Machinery & Supplies",
            "type":"Manufacturing & Wholesale Goods"
        }
    ],
    "sg:phone":"+1 608 874 4644",
    "sg:postcode":"54626",
    "sg:province":"WI",
    "sg:tags":[
        "farm",
        "equipment"
    ],
    "wof:name":"Shedivy's Agri-Svc",
    "wof:placetype":"venue"
},
  "geometry": {"coordinates":[-91.016755,43.166509],"type":"Point"}
}