{
  "type": "Feature",
  "properties": {
    "iso:country":"US",
    "sg:address":"106 S Mound Ave",
    "sg:city":"Belmont",
    "sg:classifiers":[
        {
            "category":"Personal",
            "subcategory":"Massage",
            "type":"Services"
        },
        {
            "category":"Health Services",
            "subcategory":"Health Practitioner",
            "type":"Services"
        }
    ],
    "sg:phone":"+1 608 762 5635",
    "sg:postcode":"53510",
    "sg:province":"WI",
    "wof:name":"Massage Works",
    "wof:placetype":"venue"
},
  "geometry": {"coordinates":[-90.33390300000001,42.738437],"type":"Point"}
}