{
  "type": "Feature",
  "properties": {
    "iso:country":"US",
    "sg:address":"102 4th Ave",
    "sg:city":"Baraboo",
    "sg:classifiers":[
        {
            "category":"Banks & Credit Unions",
            "subcategory":"Bank",
            "type":"Services"
        }
    ],
    "sg:phone":"+1 608 355 2055",
    "sg:postcode":"53913",
    "sg:province":"WI",
    "sg:tags":[
        "financing"
    ],
    "wof:name":"G M Funding",
    "wof:placetype":"venue"
},
  "geometry": {"coordinates":[-89.744212,43.470972],"type":"Point"}
}