{
  "type": "Feature",
  "properties": {
    "iso:country":"US",
    "sg:address":"5015 Sheboygan Ave",
    "sg:city":"Madison",
    "sg:classifiers":[
        {
            "category":"Real Estate",
            "subcategory":"Real Estate Operator",
            "type":"Services"
        }
    ],
    "sg:phone":"+1 608 233 9299",
    "sg:postcode":"53705",
    "sg:province":"WI",
    "sg:tags":[
        "building",
        "apartment"
    ],
    "wof:name":"Monticello Apartments",
    "wof:placetype":"venue"
},
  "geometry": {"coordinates":[-89.465532,43.072675],"type":"Point"}
}