{
  "type": "Feature",
  "properties": {
    "addr:full":"1345 S Riverside Dr Beloit WI 53511",
    "addr:housenumber":"1345",
    "addr:postcode":"53511",
    "addr:street":"S Riverside Dr",
    "iso:country":"US",
    "sg:address":"1345 S Riverside Dr",
    "sg:city":"Beloit",
    "sg:classifiers":[
        {
            "category":"Wholesale",
            "subcategory":"Construction Materials",
            "type":"Manufacturing & Wholesale Goods"
        }
    ],
    "sg:phone":"+1 608 368 2301",
    "sg:postcode":"53511",
    "sg:province":"WI",
    "sg:tags":[
        "carwash"
    ],
    "wof:name":"Amcraft Building Products",
    "wof:placetype":"venue"
},
  "geometry": {"coordinates":[-89.03262599999999,42.51614],"type":"Point"}
}