{
  "type": "Feature",
  "properties": {
    "iso:country":"US",
    "sg:address":"2900 Deerfield Dr",
    "sg:city":"Janesville",
    "sg:classifiers":[
        {
            "category":"Shopping",
            "subcategory":"Department Store",
            "type":"Retail Goods"
        }
    ],
    "sg:phone":"+1 608 758 2708",
    "sg:postcode":"53546",
    "sg:province":"WI",
    "wof:name":"T J Maxx",
    "wof:placetype":"venue"
},
  "geometry": {"coordinates":[-88.980256,42.714698],"type":"Point"}
}