{
  "type": "Feature",
  "properties": {
    "iso:country":"US",
    "sg:address":"1526 Shore Dr",
    "sg:city":"Marinette",
    "sg:classifiers":[
        {
            "category":"Wholesale",
            "subcategory":"Medical Equipment & Supplies",
            "type":"Manufacturing & Wholesale Goods"
        }
    ],
    "sg:phone":"+1 715 735 5900",
    "sg:postcode":"54143",
    "sg:province":"WI",
    "sg:tags":[
        "dental"
    ],
    "sg:website":"www.thedentalassistant.net",
    "wof:name":"Dental Assistant",
    "wof:placetype":"venue"
},
  "geometry": {"coordinates":[-87.619202,45.089775],"type":"Point"}
}