{
  "type": "Feature",
  "properties": {
    "addr:full":"3554 Lake Farm Rd Madison WI 53711",
    "addr:housenumber":"3554",
    "addr:postcode":"53711",
    "addr:street":"Lake Farm Rd",
    "iso:country":"US",
    "sg:address":"3554 Lake Farm Rd",
    "sg:city":"Madison",
    "sg:classifiers":[
        {
            "category":"Building & Trades",
            "subcategory":"Landscaping Services",
            "type":"Services"
        }
    ],
    "sg:phone":"+1 608 222 8132",
    "sg:postcode":"53711",
    "sg:province":"WI",
    "wof:name":"J & B Lawn Services",
    "wof:placetype":"venue"
},
  "geometry": {"coordinates":[-89.345743,43.016669],"type":"Point"}
}