{
  "type": "Feature",
  "properties": {
    "iso:country":"US",
    "sg:address":"1120 State St",
    "sg:city":"Green Bay",
    "sg:classifiers":[
        {
            "category":"Retail",
            "subcategory":"Laundry & Dry Cleaning",
            "type":"Services"
        }
    ],
    "sg:phone":"+1 920 433 0246",
    "sg:postcode":"54304",
    "sg:province":"WI",
    "sg:tags":[
        "cleaners",
        "rug",
        "carpet"
    ],
    "wof:name":"Stanley Steamer Carpet Cleaner",
    "wof:placetype":"venue"
},
  "geometry": {"coordinates":[-88.028527,44.503989],"type":"Point"}
}