{
  "type": "Feature",
  "properties": {
    "iso:country":"US",
    "sg:address":"418 N 27th St",
    "sg:city":"Milwaukee",
    "sg:classifiers":[
        {
            "category":"Freight",
            "type":"Transportation"
        }
    ],
    "sg:phone":"+1 414 344 3300",
    "sg:postcode":"53208",
    "sg:province":"WI",
    "sg:tags":[
        "delivery"
    ],
    "wof:name":"Home Delivery Inc",
    "wof:placetype":"venue"
},
  "geometry": {"coordinates":[-87.947659,43.035885],"type":"Point"}
}