{
  "type": "Feature",
  "properties": {
    "iso:country":"US",
    "sg:address":"2830 Village Rd",
    "sg:city":"Portage",
    "sg:classifiers":[
        {
            "category":"Real Estate",
            "subcategory":"Real Estate Operator",
            "type":"Services"
        }
    ],
    "sg:phone":"+1 608 742 2131",
    "sg:postcode":"53901",
    "sg:province":"WI",
    "sg:tags":[
        "apartment"
    ],
    "wof:name":"Village House Apartments",
    "wof:placetype":"venue"
},
  "geometry": {"coordinates":[-89.472593,43.564887],"type":"Point"}
}