{
  "type": "Feature",
  "properties": {
    "iso:country":"US",
    "sg:address":"27510 Cherryville Rd",
    "sg:city":"Ashland",
    "sg:classifiers":[
        {
            "category":"Professional",
            "subcategory":"Accounting & Tax Preparation",
            "type":"Services"
        }
    ],
    "sg:phone":"+1 715 682 3127",
    "sg:postcode":"54806",
    "sg:province":"WI",
    "wof:name":"Diane L Foris CPA",
    "wof:placetype":"venue"
},
  "geometry": {"coordinates":[-91.004707,46.594416],"type":"Point"}
}