{
  "type": "Feature",
  "properties": {
    "iso:country":"US",
    "sg:address":"361 Hillside Rd",
    "sg:city":"Colgate",
    "sg:classifiers":[
        {
            "category":"Retail",
            "subcategory":"Auto Repair",
            "type":"Services"
        }
    ],
    "sg:phone":"+1 262 628 4672",
    "sg:postcode":"53017",
    "sg:province":"WI",
    "sg:tags":[
        "repairing",
        "automobile",
        "automotive"
    ],
    "wof:name":"Timmy's Automotive",
    "wof:placetype":"venue"
},
  "geometry": {"coordinates":[-88.24174499999999,43.202218],"type":"Point"}
}