{
  "type": "Feature",
  "properties": {
    "iso:country":"US",
    "sg:address":"11610 E Lake Shore Rd",
    "sg:city":"Clinton",
    "sg:classifiers":[
        {
            "category":"Farming",
            "subcategory":"Livestock Farm",
            "type":"Manufacturing & Wholesale Goods"
        }
    ],
    "sg:phone":"+1 608 676 4589",
    "sg:postcode":"53525",
    "sg:province":"WI",
    "sg:tags":[
        "real",
        "hog",
        "lessor",
        "property",
        "or",
        "feedlot"
    ],
    "wof:name":"Raymond Ibeling",
    "wof:placetype":"venue"
},
  "geometry": {"coordinates":[-88.805896,42.547807],"type":"Point"}
}