{
  "type": "Feature",
  "properties": {
    "iso:country":"US",
    "sg:address":"132 S Harmony Dr",
    "sg:city":"Janesville",
    "sg:classifiers":[
        {
            "category":"Professional",
            "subcategory":"Engineering",
            "type":"Services"
        }
    ],
    "sg:phone":"+1 608 757 1248",
    "sg:postcode":"53545",
    "sg:province":"WI",
    "wof:name":"Infratek Engineers Inc",
    "wof:placetype":"venue"
},
  "geometry": {"coordinates":[-88.997153,42.683722],"type":"Point"}
}