{
  "type": "Feature",
  "properties": {
    "iso:country":"US",
    "sg:address":"2467 N 58th St",
    "sg:city":"Milwaukee",
    "sg:classifiers":[
        {
            "category":"Building & Trades",
            "subcategory":"Construction",
            "type":"Services"
        }
    ],
    "sg:phone":"+1 414 447 8090",
    "sg:postcode":"53210",
    "sg:province":"WI",
    "sg:tags":[
        "hanging",
        "contractor"
    ],
    "wof:name":"Byes Painting",
    "wof:placetype":"venue"
},
  "geometry": {"coordinates":[-87.985343,43.063115],"type":"Point"}
}