{
  "type": "Feature",
  "properties": {
    "iso:country":"US",
    "sg:address":"2930 Co Rd G",
    "sg:city":"Marinette",
    "sg:classifiers":[
        {
            "category":"Restaurant",
            "type":"Food & Drink"
        }
    ],
    "sg:phone":"+1 715 735 9121",
    "sg:postcode":"54143",
    "sg:province":"WI",
    "sg:tags":[
        "out"
    ],
    "wof:name":"Mc Guires Restaurant",
    "wof:placetype":"venue"
},
  "geometry": {"coordinates":[-87.74889400000001,45.179128],"type":"Point"}
}