{
  "type": "Feature",
  "properties": {
    "addr:full":"103 W Jefferson St Oconomowoc WI 53066",
    "addr:housenumber":"103",
    "addr:postcode":"53066",
    "addr:street":"W Jefferson St",
    "iso:country":"US",
    "sg:address":"103 W Jefferson St",
    "sg:city":"Oconomowoc",
    "sg:classifiers":[
        {
            "category":"Museum",
            "type":"Entertainment"
        }
    ],
    "sg:phone":"+1 262 569 0740",
    "sg:postcode":"53066",
    "sg:province":"WI",
    "wof:name":"Oconomowoc Historical Museum",
    "wof:placetype":"venue"
},
  "geometry": {"coordinates":[-88.499116,43.105019],"type":"Point"}
}