{
  "type": "Feature",
  "properties": {
    "iso:country":"US",
    "sg:address":"10787 Minnie Ave",
    "sg:city":"Hayward",
    "sg:classifiers":[
        {
            "category":"Health Services",
            "subcategory":"Chiropractor",
            "type":"Services"
        }
    ],
    "sg:phone":"+1 715 934 3344",
    "sg:postcode":"54843",
    "sg:province":"WI",
    "wof:name":"Hansen Family Chiropractic",
    "wof:placetype":"venue"
},
  "geometry": {"coordinates":[-91.48313899999999,46.01949],"type":"Point"}
}