{
  "type": "Feature",
  "properties": {
    "iso:country":"US",
    "sg:address":"4001 S 68th St",
    "sg:city":"Milwaukee",
    "sg:classifiers":[
        {
            "category":"Education",
            "subcategory":"School",
            "type":"Public Place"
        }
    ],
    "sg:phone":"+1 414 541 5881",
    "sg:postcode":"53220",
    "sg:province":"WI",
    "sg:tags":[
        "a",
        "as",
        "operates"
    ],
    "wof:name":"St Johns Lutheran School",
    "wof:placetype":"venue"
},
  "geometry": {"coordinates":[-87.99810100000001,42.97249],"type":"Point"}
}