{
  "type": "Feature",
  "properties": {
    "iso:country":"US",
    "sg:address":"725 N 22nd St",
    "sg:city":"Milwaukee",
    "sg:classifiers":[
        {
            "category":"Travel",
            "subcategory":"Hotels & Motels",
            "type":"Entertainment"
        }
    ],
    "sg:phone":"+1 414 933 6000",
    "sg:postcode":"53233",
    "sg:province":"WI",
    "wof:name":"Biller Hotel LTD",
    "wof:placetype":"venue"
},
  "geometry": {"coordinates":[-87.940573,43.039865],"type":"Point"}
}