{
  "type": "Feature",
  "properties": {
    "iso:country":"US",
    "sg:address":"W62n281 Washington Ave",
    "sg:city":"Cedarburg",
    "sg:classifiers":[
        {
            "category":"Health Services",
            "subcategory":"Doctor",
            "type":"Services"
        },
        {
            "category":"Health Services",
            "subcategory":"Health Practitioner",
            "type":"Services"
        }
    ],
    "sg:phone":"+1 262 377 6440",
    "sg:postcode":"53012",
    "sg:province":"WI",
    "sg:tags":[
        "physician",
        "surgeon",
        "therapist",
        "physical"
    ],
    "wof:name":"A Healing Spirit",
    "wof:placetype":"venue"
},
  "geometry": {"coordinates":[-87.98634,43.28623],"type":"Point"}
}