{
  "type": "Feature",
  "properties": {
    "iso:country":"US",
    "sg:address":"100 E Towne Mall",
    "sg:city":"Madison",
    "sg:classifiers":[
        {
            "category":"Shopping",
            "type":"Retail Goods"
        }
    ],
    "sg:phone":"+1 608 244 1151",
    "sg:postcode":"53704",
    "sg:province":"WI",
    "sg:tags":[
        "art",
        "gallery",
        "dealer"
    ],
    "wof:name":"Thomas Kinkade Signature Gllry",
    "wof:placetype":"venue"
},
  "geometry": {"coordinates":[-89.30442600000001,43.128092],"type":"Point"}
}