{
  "type": "Feature",
  "properties": {
    "iso:country":"US",
    "sg:address":"1952 N 36th St",
    "sg:city":"Milwaukee",
    "sg:classifiers":[
        {
            "category":"Government",
            "subcategory":"Office",
            "type":"Public Place"
        }
    ],
    "sg:phone":"+1 414 344 1214",
    "sg:postcode":"53208",
    "sg:province":"WI",
    "sg:tags":[
        "development",
        "economic",
        "community"
    ],
    "wof:name":"Land",
    "wof:placetype":"venue"
},
  "geometry": {"coordinates":[-87.95869,43.055567],"type":"Point"}
}