{
  "type": "Feature",
  "properties": {
    "addr:full":"13845 Bishops Dr Brookfield WI 53005",
    "addr:housenumber":"13845",
    "addr:postcode":"53005",
    "addr:street":"Bishops Dr",
    "iso:country":"US",
    "sg:address":"13845 Bishops Dr",
    "sg:city":"Brookfield",
    "sg:classifiers":[
        {
            "category":"Wholesale",
            "subcategory":"Machinery & Supplies",
            "type":"Manufacturing & Wholesale Goods"
        }
    ],
    "sg:phone":"+1 414 443 5180",
    "sg:postcode":"53005",
    "sg:province":"WI",
    "sg:tags":[
        "equipment",
        "printing"
    ],
    "sg:website":"www.lanier.com",
    "wof:name":"Lanier Worldwide Inc",
    "wof:placetype":"venue"
},
  "geometry": {"coordinates":[-88.084171,43.028718],"type":"Point"}
}