{
  "type": "Feature",
  "properties": {
    "iso:country":"US",
    "sg:address":"611 E Geneva St",
    "sg:city":"Elkhorn",
    "sg:classifiers":[
        {
            "category":"Banks & Credit Unions",
            "subcategory":"Bank",
            "type":"Services"
        }
    ],
    "sg:phone":"+1 262 743 1906",
    "sg:postcode":"53121",
    "sg:province":"WI",
    "sg:tags":[
        "federal",
        "personal",
        "institution"
    ],
    "wof:name":"Educators Credit Union",
    "wof:placetype":"venue"
},
  "geometry": {"coordinates":[-88.52787499999999,42.669955],"type":"Point"}
}