{
  "type": "Feature",
  "properties": {
    "addr:full":"2518 S 16th St Milwaukee WI 53215",
    "addr:housenumber":"2518",
    "addr:postcode":"53215",
    "addr:street":"S 16Th St",
    "iso:country":"US",
    "sg:address":"2518 S 16th St",
    "sg:city":"Milwaukee",
    "sg:classifiers":[
        {
            "category":"Wholesale",
            "subcategory":"Office Equipment",
            "type":"Manufacturing & Wholesale Goods"
        },
        {
            "category":"Shopping",
            "subcategory":"Stationery & Office Supplies",
            "type":"Retail Goods"
        },
        {
            "category":"Shopping",
            "subcategory":"Computers & Home Electronics",
            "type":"Retail Goods"
        },
        {
            "category":"Professional",
            "subcategory":"Printing & Photocopies",
            "type":"Services"
        },
        {
            "category":"Wholesale",
            "subcategory":"Computers",
            "type":"Manufacturing & Wholesale Goods"
        }
    ],
    "sg:phone":"+1 414 672 5206",
    "sg:postcode":"53215",
    "sg:province":"WI",
    "sg:tags":[
        "register",
        "autographic",
        "duplicating",
        "copying",
        "typewriter",
        "furniture"
    ],
    "sg:website":"http://www.officedepot.com",
    "wof:name":"Office Depot",
    "wof:placetype":"venue"
},
  "geometry": {"coordinates":[-87.933525,42.998962],"type":"Point"}
}