{
  "type": "Feature",
  "properties": {
    "iso:country":"US",
    "sg:address":"3450 W Spencer St",
    "sg:city":"Appleton",
    "sg:classifiers":[
        {
            "category":"Home & Garden",
            "subcategory":"Furniture",
            "type":"Retail Goods"
        }
    ],
    "sg:phone":"+1 920 735 6500",
    "sg:postcode":"54914",
    "sg:province":"WI",
    "wof:name":"Furniture Warehouse Fox Cities",
    "wof:placetype":"venue"
},
  "geometry": {"coordinates":[-88.457394,44.258774],"type":"Point"}
}