{
  "type": "Feature",
  "properties": {
    "iso:country":"US",
    "sg:address":"5888 N Port Washington Rd",
    "sg:city":"Milwaukee",
    "sg:classifiers":[
        {
            "category":"Banks & Credit Unions",
            "subcategory":"Bank",
            "type":"Services"
        }
    ],
    "sg:phone":"+1 414 332 7030",
    "sg:postcode":"53217",
    "sg:province":"WI",
    "wof:name":"US Bank",
    "wof:placetype":"venue"
},
  "geometry": {"coordinates":[-87.91652499999999,43.118938],"type":"Point"}
}