{
  "type": "Feature",
  "properties": {
    "iso:country":"US",
    "sg:address":"404 Main St W",
    "sg:city":"Ashland",
    "sg:classifiers":[
        {
            "category":"Professional",
            "subcategory":"Lawyer & Legal Services",
            "type":"Services"
        }
    ],
    "sg:phone":"+1 715 682 6442",
    "sg:postcode":"54806",
    "sg:province":"WI",
    "sg:tags":[
        "attorney"
    ],
    "wof:name":"Ashland County Family Court",
    "wof:placetype":"venue"
},
  "geometry": {"coordinates":[-90.886934,46.589744],"type":"Point"}
}