{
  "type": "Feature",
  "properties": {
    "addr:full":"540 Coe St Cashton WI 54619",
    "addr:housenumber":"540",
    "addr:postcode":"54619",
    "addr:street":"Coe St",
    "iso:country":"US",
    "sg:address":"540 Coe St",
    "sg:city":"Cashton",
    "sg:classifiers":[
        {
            "category":"Education",
            "subcategory":"School",
            "type":"Public Place"
        }
    ],
    "sg:phone":"+1 608 654 5131",
    "sg:postcode":"54619",
    "sg:province":"WI",
    "wof:name":"Cashton High School",
    "wof:placetype":"venue"
},
  "geometry": {"coordinates":[-90.78017800000001,43.740736],"type":"Point"}
}