{
  "type": "Feature",
  "properties": {
    "iso:country":"US",
    "sg:address":"1033 Ridgewood Dr",
    "sg:city":"Stoughton",
    "sg:classifiers":[
        {
            "category":"Building & Trades",
            "subcategory":"Construction",
            "type":"Services"
        }
    ],
    "sg:phone":"+1 608 873 5757",
    "sg:postcode":"53589",
    "sg:province":"WI",
    "sg:tags":[
        "house"
    ],
    "wof:name":"Plumb Construction",
    "wof:placetype":"venue"
},
  "geometry": {"coordinates":[-89.21487,42.90108],"type":"Point"}
}