{
  "type": "Feature",
  "properties": {
    "addr:full":"1516 S 3rd Ave Wausau WI 54401",
    "addr:housenumber":"1516",
    "addr:postcode":"54401",
    "addr:street":"S 3Rd Ave",
    "iso:country":"US",
    "sg:address":"1516 S 3rd Ave",
    "sg:city":"Wausau",
    "sg:classifiers":[
        {
            "category":"Building & Trades",
            "subcategory":"Construction",
            "type":"Services"
        }
    ],
    "sg:phone":"+1 715 845 5768",
    "sg:postcode":"54401",
    "sg:province":"WI",
    "sg:tags":[
        "contractor"
    ],
    "wof:name":"T Lonsdorf Agency",
    "wof:placetype":"venue"
},
  "geometry": {"coordinates":[-89.63944499999999,44.941029],"type":"Point"}
}