{
  "type": "Feature",
  "properties": {
    "iso:country":"US",
    "sg:address":"8508 W Montana Ave",
    "sg:city":"Milwaukee",
    "sg:classifiers":[
        {
            "category":"Freight",
            "type":"Transportation"
        }
    ],
    "sg:phone":"+1 414 541 6123",
    "sg:postcode":"53227",
    "sg:province":"WI",
    "sg:tags":[
        "trucking"
    ],
    "wof:name":"D & L Schultz Trucking Inc",
    "wof:placetype":"venue"
},
  "geometry": {"coordinates":[-88.02038899999999,42.994433],"type":"Point"}
}