{
  "type": "Feature",
  "properties": {
    "iso:country":"US",
    "sg:address":"112 E Mineral St",
    "sg:city":"Milwaukee",
    "sg:classifiers":[
        {
            "category":"Shopping",
            "type":"Retail Goods"
        },
        {
            "category":"Professional",
            "subcategory":"Business Services",
            "type":"Services"
        }
    ],
    "sg:phone":"+1 414 672 6910",
    "sg:postcode":"53204",
    "sg:province":"WI",
    "sg:tags":[
        "art",
        "gallery",
        "dealer"
    ],
    "wof:name":"Artamation Inc",
    "wof:placetype":"venue"
},
  "geometry": {"coordinates":[-87.90996699999999,43.021197],"type":"Point"}
}