{
  "type": "Feature",
  "properties": {
    "iso:country":"US",
    "sg:address":"515 Oak St",
    "sg:city":"Baraboo",
    "sg:classifiers":[
        {
            "category":"Government",
            "subcategory":"Court House",
            "type":"Public Place"
        }
    ],
    "sg:phone":"+1 608 355 3246",
    "sg:postcode":"53913",
    "sg:province":"WI",
    "sg:tags":[
        "county"
    ],
    "wof:name":"Sauk County Court Commissioner",
    "wof:placetype":"venue"
},
  "geometry": {"coordinates":[-89.742555,43.470758],"type":"Point"}
}