{
  "type": "Feature",
  "properties": {
    "iso:country":"US",
    "sg:address":"6606 Woodland Dr",
    "sg:city":"Waunakee",
    "sg:classifiers":[
        {
            "category":"Building & Trades",
            "subcategory":"Construction",
            "type":"Services"
        }
    ],
    "sg:phone":"+1 608 849 4352",
    "sg:postcode":"53597",
    "sg:province":"WI",
    "sg:tags":[
        "house",
        "nonresidential"
    ],
    "wof:name":"Remedelers",
    "wof:placetype":"venue"
},
  "geometry": {"coordinates":[-89.50224900000001,43.177336],"type":"Point"}
}