{
  "type": "Feature",
  "properties": {
    "iso:country":"US",
    "sg:address":"403 Mill St",
    "sg:city":"Wilton",
    "sg:classifiers":[
        {
            "category":"Organizations",
            "subcategory":"Religious Organization",
            "type":"Services"
        }
    ],
    "sg:phone":"+1 608 435 6703",
    "sg:postcode":"54670",
    "sg:province":"WI",
    "wof:name":"Dan R & Beth Dibbert Rev",
    "wof:placetype":"venue"
},
  "geometry": {"coordinates":[-90.531001,43.813652],"type":"Point"}
}