{
  "type": "Feature",
  "properties": {
    "iso:country":"US",
    "sg:address":"551 Upper Rd",
    "sg:city":"Kohler",
    "sg:classifiers":[
        {
            "category":"Professional",
            "subcategory":"Employment Agencies",
            "type":"Services"
        }
    ],
    "sg:phone":"+1 920 452 6447",
    "sg:postcode":"53044",
    "sg:province":"WI",
    "sg:tags":[
        "modeling"
    ],
    "wof:name":"Oreck-Madson Talent Agency",
    "wof:placetype":"venue"
},
  "geometry": {"coordinates":[-87.788959,43.738981],"type":"Point"}
}