{
  "type": "Feature",
  "properties": {
    "iso:country":"US",
    "sg:address":"5799 River Rd",
    "sg:city":"Waunakee",
    "sg:classifiers":[
        {
            "category":"Professional",
            "subcategory":"Engineering",
            "type":"Services"
        }
    ],
    "sg:phone":"+1 608 849 4180",
    "sg:postcode":"53597",
    "sg:province":"WI",
    "wof:name":"Socon Engineering Inc",
    "wof:placetype":"venue"
},
  "geometry": {"coordinates":[-89.381785,43.177496],"type":"Point"}
}