{
  "type": "Feature",
  "properties": {
    "addr:full":"3526 Co Rd Nn Elkhorn WI 53121",
    "addr:housenumber":"3526",
    "addr:postcode":"53121",
    "addr:street":"Co Rd Nn",
    "iso:country":"US",
    "sg:address":"3526 Co Rd Nn",
    "sg:city":"Elkhorn",
    "sg:classifiers":[
        {
            "category":"Professional",
            "subcategory":"Business Services",
            "type":"Services"
        }
    ],
    "sg:phone":"+1 262 723 7996",
    "sg:postcode":"53121",
    "sg:province":"WI",
    "wof:name":"Isle of Decor",
    "wof:placetype":"venue"
},
  "geometry": {"coordinates":[-88.48781700000001,42.662599],"type":"Point"}
}