{
  "type": "Feature",
  "properties": {
    "iso:country":"US",
    "sg:address":"1202 Drake St",
    "sg:city":"Madison",
    "sg:classifiers":[
        {
            "category":"Building & Trades",
            "subcategory":"Landscaping Services",
            "type":"Services"
        }
    ],
    "sg:phone":"+1 608 259 9078",
    "sg:postcode":"53715",
    "sg:province":"WI",
    "wof:name":"Johnson Tree Care LLC",
    "wof:placetype":"venue"
},
  "geometry": {"coordinates":[-89.407178,43.062134],"type":"Point"}
}