{
  "type": "Feature",
  "properties": {
    "iso:country":"US",
    "sg:address":"6876 S 13th St",
    "sg:city":"Oak Creek",
    "sg:classifiers":[
        {
            "category":"Retail",
            "subcategory":"Auto Repair",
            "type":"Services"
        }
    ],
    "sg:phone":"+1 414 788 5464",
    "sg:postcode":"53154",
    "sg:province":"WI",
    "sg:tags":[
        "automobile",
        "co",
        "drive",
        "transporter"
    ],
    "wof:name":"Ram Auto Transport",
    "wof:placetype":"venue"
},
  "geometry": {"coordinates":[-87.930561,42.919783],"type":"Point"}
}