{
  "type": "Feature",
  "properties": {
    "iso:country":"US",
    "sg:address":"2291 Church Rd",
    "sg:city":"Mosinee",
    "sg:classifiers":[
        {
            "category":"Organizations",
            "subcategory":"Religious Organization",
            "type":"Services"
        }
    ],
    "sg:phone":"+1 715 457 3053",
    "sg:postcode":"54455",
    "sg:province":"WI",
    "wof:name":"Saint Jhns Evang Lthran Church",
    "wof:placetype":"venue"
},
  "geometry": {"coordinates":[-89.714814,44.691589],"type":"Point"}
}