{
  "type": "Feature",
  "properties": {
    "iso:country":"US",
    "sg:address":"621 N Lynndale Dr",
    "sg:city":"Appleton",
    "sg:classifiers":[
        {
            "category":"Travel",
            "subcategory":"Travel Agent",
            "type":"Entertainment"
        }
    ],
    "sg:phone":"+1 920 739 8851",
    "sg:postcode":"54914",
    "sg:province":"WI",
    "sg:tags":[
        "agency",
        "bureau"
    ],
    "sg:website":"www.creativegroupinc.com",
    "wof:name":"Creative Group Travel",
    "wof:placetype":"venue"
},
  "geometry": {"coordinates":[-88.44597,44.262442],"type":"Point"}
}