{
  "type": "Feature",
  "properties": {
    "iso:country":"US",
    "sg:address":"9460 S 96th St",
    "sg:city":"Franklin",
    "sg:classifiers":[
        {
            "category":"Shopping",
            "type":"Retail Goods"
        }
    ],
    "sg:phone":"+1 414 425 6780",
    "sg:postcode":"53132",
    "sg:province":"WI",
    "sg:tags":[
        "merchandise"
    ],
    "wof:name":"New Beginnings",
    "wof:placetype":"venue"
},
  "geometry": {"coordinates":[-88.033428,42.873961],"type":"Point"}
}