{
  "type": "Feature",
  "properties": {
    "iso:country":"US",
    "sg:address":"205 N Spring St",
    "sg:city":"Beaver Dam",
    "sg:classifiers":[
        {
            "category":"Wholesale",
            "subcategory":"Computers",
            "type":"Manufacturing & Wholesale Goods"
        }
    ],
    "sg:phone":"+1 920 356 9410",
    "sg:postcode":"53916",
    "sg:province":"WI",
    "sg:tags":[
        "repair"
    ],
    "wof:name":"Total Computer Solutions Inc",
    "wof:placetype":"venue"
},
  "geometry": {"coordinates":[-88.836872,43.458376],"type":"Point"}
}