{
  "type": "Feature",
  "properties": {
    "iso:country":"US",
    "sg:address":"105 7th St S",
    "sg:city":"La Crosse",
    "sg:classifiers":[
        {
            "category":"Insurance",
            "subcategory":"Insurance Agent",
            "type":"Services"
        }
    ],
    "sg:phone":"+1 608 784 9004",
    "sg:postcode":"54601",
    "sg:province":"WI",
    "wof:name":"Irv Hougom Agency",
    "wof:placetype":"venue"
},
  "geometry": {"coordinates":[-91.24669299999999,43.810034],"type":"Point"}
}