{
  "type": "Feature",
  "properties": {
    "iso:country":"US",
    "sg:address":"1133 W Mount Vernon Ave",
    "sg:city":"Milwaukee",
    "sg:classifiers":[
        {
            "category":"Retail",
            "subcategory":"Auto Repair",
            "type":"Services"
        }
    ],
    "sg:phone":"+1 414 291 9100",
    "sg:postcode":"53233",
    "sg:province":"WI",
    "sg:tags":[
        "wrecker"
    ],
    "wof:name":"Vehicle Towing Dispatch",
    "wof:placetype":"venue"
},
  "geometry": {"coordinates":[-87.92418600000001,43.033774],"type":"Point"}
}