{
  "type": "Feature",
  "properties": {
    "addr:full":"10606 N Port Washington Rd Mequon WI 53092",
    "addr:housenumber":"10606",
    "addr:postcode":"53092",
    "addr:street":"N Port Washington Rd",
    "iso:country":"US",
    "sg:address":"10606 N Port Washington Rd",
    "sg:city":"Mequon",
    "sg:classifiers":[
        {
            "category":"Organizations",
            "subcategory":"Religious Organization",
            "type":"Services"
        }
    ],
    "sg:phone":"+1 262 241 3980",
    "sg:postcode":"53092",
    "sg:province":"WI",
    "sg:tags":[
        "church"
    ],
    "sg:website":"www.christchurchmequon.org",
    "wof:name":"Christ Church",
    "wof:placetype":"venue"
},
  "geometry": {"coordinates":[-87.924092,43.211269],"type":"Point"}
}