{
  "type": "Feature",
  "properties": {
    "iso:country":"US",
    "sg:address":"1851 Franklin St",
    "sg:city":"Wisconsin Rapids",
    "sg:classifiers":[
        {
            "category":"Education",
            "subcategory":"Library",
            "type":"Public Place"
        }
    ],
    "sg:phone":"+1 715 424 2988",
    "sg:postcode":"54494",
    "sg:province":"WI",
    "wof:name":"Christian Library",
    "wof:placetype":"venue"
},
  "geometry": {"coordinates":[-89.803799,44.395508],"type":"Point"}
}