{
  "type": "Feature",
  "properties": {
    "iso:country":"US",
    "sg:address":"125 Day Ave",
    "sg:city":"Marshfield",
    "sg:classifiers":[
        {
            "category":"Building & Trades",
            "subcategory":"Construction",
            "type":"Services"
        }
    ],
    "sg:phone":"+1 715 384 9975",
    "sg:postcode":"54449",
    "sg:province":"WI",
    "wof:name":"C & M Construction Inc",
    "wof:placetype":"venue"
},
  "geometry": {"coordinates":[-90.079446,44.691043],"type":"Point"}
}