{
  "type": "Feature",
  "properties": {
    "iso:country":"US",
    "sg:address":"3321 W Parnell Ave",
    "sg:city":"Milwaukee",
    "sg:classifiers":[
        {
            "category":"Real Estate",
            "subcategory":"Real Estate Agent",
            "type":"Services"
        },
        {
            "category":"Real Estate",
            "subcategory":"Real Estate Operator",
            "type":"Services"
        }
    ],
    "sg:phone":"+1 414 282 6922",
    "sg:postcode":"53221",
    "sg:province":"WI",
    "sg:tags":[
        "rental",
        "agency",
        "dwelling"
    ],
    "wof:name":"Veley Enterprises LLC",
    "wof:placetype":"venue"
},
  "geometry": {"coordinates":[-87.95719800000001,42.941669],"type":"Point"}
}