{
  "type": "Feature",
  "properties": {
    "iso:country":"US",
    "sg:address":"10848 Isaacson Rd",
    "sg:city":"Scandinavia",
    "sg:classifiers":[
        {
            "category":"Farming",
            "subcategory":"Dairy Farm",
            "type":"Manufacturing & Wholesale Goods"
        }
    ],
    "sg:phone":"+1 715 824 2406",
    "sg:postcode":"54977",
    "sg:province":"WI",
    "wof:name":"Peterson Dairy Farms 2",
    "wof:placetype":"venue"
},
  "geometry": {"coordinates":[-89.238214,44.475442],"type":"Point"}
}