{
  "type": "Feature",
  "properties": {
    "iso:country":"US",
    "sg:address":"1550 Engineering Dr",
    "sg:city":"Madison",
    "sg:classifiers":[
        {
            "category":"Education",
            "subcategory":"College",
            "type":"Public Place"
        }
    ],
    "sg:phone":"+1 608 262 3471",
    "sg:postcode":"53706",
    "sg:province":"WI",
    "sg:tags":[
        "academic",
        "school"
    ],
    "wof:name":"University Of Wi Engineering",
    "wof:placetype":"venue"
},
  "geometry": {"coordinates":[-89.41327200000001,43.072388],"type":"Point"}
}