{
  "type": "Feature",
  "properties": {
    "addr:full":"29218 Raab Dr Waterford WI 53185",
    "addr:postcode":"29218;53185",
    "addr:street":"Raab Dr",
    "iso:country":"US",
    "sg:address":"29218 Raab Dr",
    "sg:city":"Waterford",
    "sg:classifiers":[
        {
            "category":"Building & Trades",
            "subcategory":"Landscaping Services",
            "type":"Services"
        }
    ],
    "sg:phone":"+1 262 662 2653",
    "sg:postcode":"53185",
    "sg:province":"WI",
    "wof:name":"Busy Bees Contracting Inc",
    "wof:placetype":"venue"
},
  "geometry": {"coordinates":[-88.216415,42.836047],"type":"Point"}
}