{
  "type": "Feature",
  "properties": {
    "iso:country":"US",
    "sg:address":"3791 W Rib Rd",
    "sg:city":"Westboro",
    "sg:classifiers":[
        {
            "category":"Freight",
            "type":"Transportation"
        }
    ],
    "sg:phone":"+1 715 427 3853",
    "sg:postcode":"54490",
    "sg:province":"WI",
    "sg:tags":[
        "special"
    ],
    "wof:name":"Kk Storage Inc",
    "wof:placetype":"venue"
},
  "geometry": {"coordinates":[-90.241651,45.308928],"type":"Point"}
}