{
  "type": "Feature",
  "properties": {
    "iso:country":"US",
    "sg:address":"118 S Main St",
    "sg:city":"Lodi",
    "sg:classifiers":[
        {
            "category":"Restaurant",
            "type":"Food & Drink"
        },
        {
            "category":"Bars & Pubs",
            "type":"Food & Drink"
        }
    ],
    "sg:phone":"+1 608 592 3965",
    "sg:postcode":"53555",
    "sg:province":"WI",
    "sg:tags":[
        "drinking"
    ],
    "wof:name":"Willie & Teddie's",
    "wof:placetype":"venue"
},
  "geometry": {"coordinates":[-89.526684,43.313805],"type":"Point"}
}