{
  "type": "Feature",
  "properties": {
    "addr:full":"517 E Wisconsin Ave Milwaukee WI 53202",
    "addr:housenumber":"517",
    "addr:postcode":"53202",
    "addr:street":"E Wisconsin Ave",
    "iso:country":"US",
    "sg:address":"517 E Wisconsin Ave",
    "sg:city":"Milwaukee",
    "sg:classifiers":[
        {
            "category":"Professional",
            "subcategory":"Management & Consulting",
            "type":"Services"
        }
    ],
    "sg:phone":"+1 414 224 0592",
    "sg:postcode":"53202",
    "sg:province":"WI",
    "sg:tags":[
        "construction"
    ],
    "wof:name":"Jacobs Engineering Milwaukee",
    "wof:placetype":"venue"
},
  "geometry": {"coordinates":[-87.904156,43.038799],"type":"Point"}
}