{
  "type": "Feature",
  "properties": {
    "iso:country":"US",
    "sg:address":"2261 16th Ave",
    "sg:city":"Cameron",
    "sg:classifiers":[
        {
            "category":"Building & Trades",
            "subcategory":"Equipment Rental",
            "type":"Services"
        }
    ],
    "sg:phone":"+1 715 458 2227",
    "sg:postcode":"54822",
    "sg:province":"WI",
    "sg:tags":[
        "heavy",
        "construction"
    ],
    "wof:name":"Big Tool Rental",
    "wof:placetype":"venue"
},
  "geometry": {"coordinates":[-91.693,45.437056],"type":"Point"}
}