{
  "type": "Feature",
  "properties": {
    "iso:country":"US",
    "sg:address":"3826 Timber Lane Rd",
    "sg:city":"Granton",
    "sg:classifiers":[
        {
            "category":"Farming",
            "subcategory":"Livestock Farm",
            "type":"Manufacturing & Wholesale Goods"
        }
    ],
    "sg:phone":"+1 715 238 7435",
    "sg:postcode":"54436",
    "sg:province":"WI",
    "sg:tags":[
        "beef",
        "feedlot",
        "cattle"
    ],
    "wof:name":"Donald Rowe",
    "wof:placetype":"venue"
},
  "geometry": {"coordinates":[-90.515788,44.618339],"type":"Point"}
}