{
  "type": "Feature",
  "properties": {
    "addr:full":"51173 Old Gays Rd Gays Mills WI 54631",
    "addr:housenumber":"51173",
    "addr:postcode":"54631",
    "addr:street":"Old Gays Rd",
    "iso:country":"US",
    "sg:address":"51173 Old Gays Rd",
    "sg:city":"Gays Mills",
    "sg:classifiers":[
        {
            "category":"Retail",
            "subcategory":"Veterinary Services",
            "type":"Services"
        }
    ],
    "sg:phone":"+1 608 735 4141",
    "sg:postcode":"54631",
    "sg:province":"WI",
    "sg:tags":[
        "veterinarian"
    ],
    "wof:name":"Lee Way Veterinary Svc",
    "wof:placetype":"venue"
},
  "geometry": {"coordinates":[-90.887294,43.318987],"type":"Point"}
}