{
  "type": "Feature",
  "properties": {
    "iso:country":"US",
    "sg:address":"404 Main St",
    "sg:city":"Fair Water",
    "sg:classifiers":[
        {
            "category":"Professional",
            "type":"Services"
        }
    ],
    "sg:phone":"+1 920 346 2889",
    "sg:postcode":"53931",
    "sg:province":"WI",
    "wof:name":"Remos",
    "wof:placetype":"venue"
},
  "geometry": {"coordinates":[-88.865572,43.742173],"type":"Point"}
}