{
  "type": "Feature",
  "properties": {
    "iso:country":"US",
    "sg:address":"1637 Main St",
    "sg:city":"La Crosse",
    "sg:classifiers":[
        {
            "category":"Autos & Motor Vehicles",
            "subcategory":"Automobile Sales",
            "type":"Retail Goods"
        }
    ],
    "sg:phone":"+1 608 783 5595",
    "sg:postcode":"54601",
    "sg:province":"WI",
    "sg:tags":[
        "car",
        "dealer"
    ],
    "wof:name":"Premier Auto Group",
    "wof:placetype":"venue"
},
  "geometry": {"coordinates":[-91.231503,43.811792],"type":"Point"}
}