{
  "type": "Feature",
  "properties": {
    "iso:country":"US",
    "sg:address":"8090 Co Rd K",
    "sg:city":"Cross Plains",
    "sg:classifiers":[
        {
            "category":"Building & Trades",
            "subcategory":"Construction",
            "type":"Services"
        }
    ],
    "sg:phone":"+1 608 836 6600",
    "sg:postcode":"53528",
    "sg:province":"WI",
    "sg:tags":[
        "roofing",
        "contractor"
    ],
    "wof:name":"Middleton Roofing Co",
    "wof:placetype":"venue"
},
  "geometry": {"coordinates":[-89.6118,43.158532],"type":"Point"}
}