{
  "type": "Feature",
  "properties": {
    "iso:country":"US",
    "sg:address":"1814 Talen St",
    "sg:city":"Menomonie",
    "sg:classifiers":[
        {
            "category":"Retail",
            "subcategory":"Auto Repair",
            "type":"Services"
        }
    ],
    "sg:phone":"+1 715 235 7045",
    "sg:postcode":"54751",
    "sg:province":"WI",
    "sg:tags":[
        "repairing",
        "automobile",
        "general"
    ],
    "wof:name":"Transmotive Auto Repair Svc",
    "wof:placetype":"venue"
},
  "geometry": {"coordinates":[-91.926197,44.905211],"type":"Point"}
}