{
  "type": "Feature",
  "properties": {
    "addr:full":"1157 Redwood Dr Green Bay WI 54304",
    "addr:housenumber":"1157",
    "addr:postcode":"54304",
    "addr:street":"Redwood Dr",
    "iso:country":"US",
    "sg:address":"1157 Redwood Dr",
    "sg:city":"Green Bay",
    "sg:classifiers":[
        {
            "category":"Health Services",
            "subcategory":"Nursing And Care Facility",
            "type":"Services"
        },
        {
            "category":"Social Services",
            "subcategory":"Job Training",
            "type":"Services"
        }
    ],
    "sg:phone":"+1 920 494 1345",
    "sg:postcode":"54304",
    "sg:province":"WI",
    "sg:tags":[
        "mental",
        "skilled",
        "dev",
        "disabled",
        "intermediate",
        "retardation"
    ],
    "wof:name":"Redwood House",
    "wof:placetype":"venue"
},
  "geometry": {"coordinates":[-88.048615,44.511963],"type":"Point"}
}