{
  "type": "Feature",
  "properties": {
    "iso:country":"US",
    "sg:address":"1424 S Town Hall Rd",
    "sg:city":"Chilton",
    "sg:classifiers":[
        {
            "category":"Personal",
            "subcategory":"Beauty Salon",
            "type":"Services"
        }
    ],
    "sg:phone":"+1 920 795 4017",
    "sg:postcode":"53014",
    "sg:province":"WI",
    "sg:tags":[
        "shop"
    ],
    "wof:name":"Chilton Hair Design",
    "wof:placetype":"venue"
},
  "geometry": {"coordinates":[-88.250578,43.941368],"type":"Point"}
}