{
  "type": "Feature",
  "properties": {
    "iso:country":"US",
    "sg:address":"507 Linn St",
    "sg:city":"Baraboo",
    "sg:classifiers":[
        {
            "category":"Professional",
            "subcategory":"Employment Agencies",
            "type":"Services"
        }
    ],
    "sg:phone":"+1 608 356 0300",
    "sg:postcode":"53913",
    "sg:province":"WI",
    "sg:tags":[
        "opportunity"
    ],
    "wof:name":"Adecco",
    "wof:placetype":"venue"
},
  "geometry": {"coordinates":[-89.76712499999999,43.474871],"type":"Point"}
}