{
  "type": "Feature",
  "properties": {
    "addr:full":"1131 Co Rd A Mindoro WI 54644",
    "addr:housenumber":"1131",
    "addr:postcode":"54644",
    "addr:street":"Co Rd",
    "iso:country":"US",
    "sg:address":"1131 Co Rd A",
    "sg:city":"Mindoro",
    "sg:classifiers":[
        {
            "category":"Retail",
            "subcategory":"Repair Shop",
            "type":"Services"
        }
    ],
    "sg:phone":"+1 608 857 3400",
    "sg:postcode":"54644",
    "sg:province":"WI",
    "sg:tags":[
        "taxidermist"
    ],
    "wof:name":"Broken Arrow Taxidermy",
    "wof:placetype":"venue"
},
  "geometry": {"coordinates":[-90.957454,44.061186],"type":"Point"}
}