{
  "type": "Feature",
  "properties": {
    "iso:country":"US",
    "sg:address":"1619 Co Rd I",
    "sg:city":"Somerset",
    "sg:classifiers":[
        {
            "category":"Retail",
            "subcategory":"Repair Shop",
            "type":"Services"
        }
    ],
    "sg:phone":"+1 715 247 5106",
    "sg:postcode":"54025",
    "sg:province":"WI",
    "sg:tags":[
        "scheduled",
        "transportation",
        "air"
    ],
    "wof:name":"Irlbeck Aviation",
    "wof:placetype":"venue"
},
  "geometry": {"coordinates":[-92.675095,45.104821],"type":"Point"}
}