{
  "type": "Feature",
  "properties": {
    "addr:full":"631 E Franklin St Sparta WI 54656",
    "addr:housenumber":"631",
    "addr:postcode":"54656",
    "addr:street":"E Franklin St",
    "iso:country":"US",
    "sg:address":"631 E Franklin St",
    "sg:city":"Sparta",
    "sg:classifiers":[
        {
            "category":"Manufacturing",
            "subcategory":"Tools & Machinery",
            "type":"Manufacturing & Wholesale Goods"
        }
    ],
    "sg:phone":"+1 608 269 7844",
    "sg:postcode":"54656",
    "sg:province":"WI",
    "sg:tags":[
        "equipment",
        "system",
        "automation"
    ],
    "wof:name":"R J Gross",
    "wof:placetype":"venue"
},
  "geometry": {"coordinates":[-90.802982,43.945861],"type":"Point"}
}