{
  "type": "Feature",
  "properties": {
    "iso:country":"US",
    "sg:address":"1710 W Mckinley Ave",
    "sg:city":"Milwaukee",
    "sg:classifiers":[
        {
            "category":"Personal",
            "subcategory":"Beauty Salon",
            "type":"Services"
        }
    ],
    "sg:phone":"+1 414 342 0245",
    "sg:postcode":"53205",
    "sg:province":"WI",
    "wof:name":"Joyce Ann Kelly",
    "wof:placetype":"venue"
},
  "geometry": {"coordinates":[-87.93463,43.047206],"type":"Point"}
}