{
  "type": "Feature",
  "properties": {
    "iso:country":"US",
    "sg:address":"6089 State Hwy 16",
    "sg:city":"Sparta",
    "sg:classifiers":[
        {
            "category":"Wholesale",
            "subcategory":"Farm Supplies",
            "type":"Manufacturing & Wholesale Goods"
        }
    ],
    "sg:phone":"+1 608 269 3104",
    "sg:postcode":"54656",
    "sg:province":"WI",
    "sg:tags":[
        "buyer",
        "livestock"
    ],
    "wof:name":"Equity Co-Op Livestock Sales",
    "wof:placetype":"venue"
},
  "geometry": {"coordinates":[-90.867993,43.932734],"type":"Point"}
}