{
  "type": "Feature",
  "properties": {
    "iso:country":"US",
    "sg:address":"630 Bluegrass Ln",
    "sg:city":"Pulaski",
    "sg:classifiers":[
        {
            "category":"Real Estate",
            "subcategory":"Real Estate Operator",
            "type":"Services"
        }
    ],
    "sg:phone":"+1 920 822 5991",
    "sg:postcode":"54162",
    "sg:province":"WI",
    "sg:tags":[
        "property",
        "lessor"
    ],
    "wof:name":"Charles Kientop",
    "wof:placetype":"venue"
},
  "geometry": {"coordinates":[-88.23106799999999,44.686781],"type":"Point"}
}