{
  "type": "Feature",
  "properties": {
    "iso:country":"US",
    "sg:address":"515 Farwell Ave",
    "sg:city":"Fond Du Lac",
    "sg:classifiers":[
        {
            "category":"Building & Trades",
            "subcategory":"Construction",
            "type":"Services"
        }
    ],
    "sg:phone":"+1 920 921 9081",
    "sg:postcode":"54935",
    "sg:province":"WI",
    "sg:tags":[
        "painter"
    ],
    "wof:name":"Scheberl Brothers Painting",
    "wof:placetype":"venue"
},
  "geometry": {"coordinates":[-88.459599,43.765262],"type":"Point"}
}