{
  "type": "Feature",
  "properties": {
    "iso:country":"US",
    "sg:address":"8107 Busy Nook Rd",
    "sg:city":"Oconto Falls",
    "sg:classifiers":[
        {
            "category":"Farming",
            "subcategory":"Farm & Veterinary Services",
            "type":"Manufacturing & Wholesale Goods"
        }
    ],
    "sg:phone":"+1 920 846 3394",
    "sg:postcode":"54154",
    "sg:province":"WI",
    "sg:tags":[
        "professional",
        "livestock",
        "organization"
    ],
    "wof:name":"Great Northern Texas Longhorn",
    "wof:placetype":"venue"
},
  "geometry": {"coordinates":[-88.185759,44.908833],"type":"Point"}
}