{
  "type": "Feature",
  "properties": {
    "iso:country":"US",
    "sg:address":"9810 Hynek Rd",
    "sg:city":"Whitelaw",
    "sg:classifiers":[
        {
            "category":"Farming",
            "subcategory":"Dairy Farm",
            "type":"Manufacturing & Wholesale Goods"
        }
    ],
    "sg:phone":"+1 920 732 4548",
    "sg:postcode":"54247",
    "sg:province":"WI",
    "wof:name":"Gary Hynek",
    "wof:placetype":"venue"
},
  "geometry": {"coordinates":[-87.811862,44.212538],"type":"Point"}
}