{
  "type": "Feature",
  "properties": {
    "addr:full":"8790 Co Rd X Forestville WI 54213",
    "addr:housenumber":"8790",
    "addr:postcode":"54213",
    "addr:street":"Co Rd X",
    "iso:country":"US",
    "sg:address":"8790 Co Rd X",
    "sg:city":"Forestville",
    "sg:classifiers":[
        {
            "category":"Real Estate",
            "subcategory":"Real Estate Operator",
            "type":"Services"
        }
    ],
    "sg:phone":"+1 920 856 6478",
    "sg:postcode":"54213",
    "sg:province":"WI",
    "sg:tags":[
        "property",
        "lessor"
    ],
    "wof:name":"Francis Charles",
    "wof:placetype":"venue"
},
  "geometry": {"coordinates":[-87.558201,44.67543],"type":"Point"}
}