{
  "type": "Feature",
  "properties": {
    "iso:country":"US",
    "sg:address":"7102 S Woelfel Rd",
    "sg:city":"Franklin",
    "sg:classifiers":[
        {
            "category":"Retail",
            "subcategory":"Laundry & Dry Cleaning",
            "type":"Services"
        }
    ],
    "sg:phone":"+1 414 448 0066",
    "sg:postcode":"53132",
    "sg:province":"WI",
    "sg:tags":[
        "drycleaning",
        "plant"
    ],
    "wof:name":"X & L Drycleaning LLC",
    "wof:placetype":"venue"
},
  "geometry": {"coordinates":[-88.028963,42.913026],"type":"Point"}
}