{
  "type": "Feature",
  "properties": {
    "addr:full":"2069 S Koeller St Oshkosh WI 54902",
    "addr:housenumber":"2069",
    "addr:postcode":"54902",
    "addr:street":"S Koeller St",
    "iso:country":"US",
    "sg:address":"2069 S Koeller St",
    "sg:city":"Oshkosh",
    "sg:classifiers":[
        {
            "category":"Building & Trades",
            "subcategory":"Equipment Rental",
            "type":"Services"
        }
    ],
    "sg:phone":"+1 920 233 8922",
    "sg:postcode":"54902",
    "sg:province":"WI",
    "wof:name":"Rent-A-Center",
    "wof:placetype":"venue"
},
  "geometry": {"coordinates":[-88.581912,44.002201],"type":"Point"}
}