{
  "type": "Feature",
  "properties": {
    "iso:country":"US",
    "sg:address":"509 Carroll St",
    "sg:city":"Beaver Dam",
    "sg:classifiers":[
        {
            "category":"Personal",
            "type":"Services"
        }
    ],
    "sg:phone":"+1 920 356 9358",
    "sg:postcode":"53916",
    "sg:province":"WI",
    "sg:tags":[
        "therapist",
        "massage"
    ],
    "wof:name":"First Retreat",
    "wof:placetype":"venue"
},
  "geometry": {"coordinates":[-88.837974,43.471591],"type":"Point"}
}