{
  "type": "Feature",
  "properties": {
    "iso:country":"US",
    "sg:address":"131 E Washington Ave",
    "sg:city":"Hartford",
    "sg:classifiers":[
        {
            "category":"Freight",
            "type":"Transportation"
        }
    ],
    "sg:phone":"+1 262 670 5081",
    "sg:postcode":"53027",
    "sg:province":"WI",
    "sg:tags":[
        "trucking"
    ],
    "wof:name":"Southport Auto Transport",
    "wof:placetype":"venue"
},
  "geometry": {"coordinates":[-88.378781,43.311943],"type":"Point"}
}