{
  "type": "Feature",
  "properties": {
    "addr:full":"5801 W North Ave Milwaukee WI 53208",
    "addr:housenumber":"5801",
    "addr:postcode":"53208",
    "addr:street":"W North Ave",
    "iso:country":"US",
    "sg:address":"5801 W North Ave",
    "sg:city":"Milwaukee",
    "sg:classifiers":[
        {
            "category":"Retail",
            "subcategory":"Repair Shop",
            "type":"Services"
        }
    ],
    "sg:phone":"+1 414 777 0447",
    "sg:postcode":"53208",
    "sg:province":"WI",
    "sg:tags":[
        "lock",
        "locksmith"
    ],
    "wof:name":"Bonded Safe & Lock",
    "wof:placetype":"venue"
},
  "geometry": {"coordinates":[-87.986412,43.060697],"type":"Point"}
}