{
  "type": "Feature",
  "properties": {
    "addr:full":"1905 Huebbe Pkwy Beloit WI 53511",
    "addr:housenumber":"1905",
    "addr:postcode":"53511",
    "addr:street":"Huebbe Pkwy",
    "iso:country":"US",
    "sg:address":"1905 Huebbe Pkwy",
    "sg:city":"Beloit",
    "sg:classifiers":[
        {
            "category":"Health Services",
            "subcategory":"Doctor",
            "type":"Services"
        }
    ],
    "sg:phone":"+1 608 364 2400",
    "sg:postcode":"53511",
    "sg:province":"WI",
    "sg:tags":[
        "medical"
    ],
    "wof:name":"Lim Roger G",
    "wof:placetype":"venue"
},
  "geometry": {"coordinates":[-89.00669000000001,42.549708],"type":"Point"}
}