{
  "type": "Feature",
  "properties": {
    "iso:country":"US",
    "sg:address":"525 Marshall St",
    "sg:city":"Eau Claire",
    "sg:classifiers":[
        {
            "category":"Wholesale",
            "subcategory":"Non-durable Goods",
            "type":"Manufacturing & Wholesale Goods"
        }
    ],
    "sg:phone":"+1 715 838 9394",
    "sg:postcode":"54703",
    "sg:province":"WI",
    "wof:name":"Black Hills Imprinters",
    "wof:placetype":"venue"
},
  "geometry": {"coordinates":[-91.518231,44.824146],"type":"Point"}
}