{
  "type": "Feature",
  "properties": {
    "iso:country":"US",
    "sg:address":"122 Green Bay Rd",
    "sg:city":"Thiensville",
    "sg:classifiers":[
        {
            "category":"Professional",
            "subcategory":"Art Services",
            "type":"Services"
        },
        {
            "category":"Professional",
            "subcategory":"Advertising",
            "type":"Services"
        }
    ],
    "sg:phone":"+1 262 236 4228",
    "sg:postcode":"53092",
    "sg:province":"WI",
    "sg:tags":[
        "commercial",
        "medium",
        "design",
        "interactive"
    ],
    "wof:name":"Strong Interactive Media Inc",
    "wof:placetype":"venue"
},
  "geometry": {"coordinates":[-87.98246,43.23163],"type":"Point"}
}