{
  "type": "Feature",
  "properties": {
    "iso:country":"US",
    "sg:address":"732 US Hwy 12",
    "sg:city":"Hudson",
    "sg:classifiers":[
        {
            "category":"Professional",
            "type":"Services"
        }
    ],
    "sg:phone":"+1 715 381 2880",
    "sg:postcode":"54016",
    "sg:province":"WI",
    "wof:name":"Liquid Bean",
    "wof:placetype":"venue"
},
  "geometry": {"coordinates":[-92.653755,44.988974],"type":"Point"}
}