{
  "type": "Feature",
  "properties": {
    "iso:country":"US",
    "sg:address":"162 E Wisconsin Ave",
    "sg:city":"Oconomowoc",
    "sg:classifiers":[
        {
            "category":"Cafe",
            "type":"Food & Drink"
        }
    ],
    "sg:menulink":"http://www.allmenus.com/wi/oconomowoc/261651-golosi-gelato-cafe/menu/",
    "sg:phone":"+1 262 527 0950",
    "sg:postcode":"53066",
    "sg:province":"WI",
    "wof:name":"Golosi Gelato Cafe'",
    "wof:placetype":"venue"
},
  "geometry": {"coordinates":[-88.497812,43.110938],"type":"Point"}
}