{
  "type": "Feature",
  "properties": {
    "addr:full":"161 Goehl Rd Waterloo WI 53594",
    "addr:housenumber":"161",
    "addr:postcode":"53594",
    "addr:street":"Goehl Rd",
    "iso:country":"US",
    "sg:address":"161 Goehl Rd",
    "sg:city":"Waterloo",
    "sg:classifiers":[
        {
            "category":"Social Services",
            "subcategory":"Adult Care",
            "type":"Services"
        }
    ],
    "sg:phone":"+1 920 478 4193",
    "sg:postcode":"53594",
    "sg:province":"WI",
    "sg:tags":[
        "residential"
    ],
    "wof:name":"Highland House",
    "wof:placetype":"venue"
},
  "geometry": {"coordinates":[-88.98579599999999,43.19668],"type":"Point"}
}