{
  "type": "Feature",
  "properties": {
    "iso:country":"US",
    "sg:address":"426 Railroad St",
    "sg:city":"Allenton",
    "sg:classifiers":[
        {
            "category":"Home & Garden",
            "subcategory":"Building Materials",
            "type":"Retail Goods"
        }
    ],
    "sg:phone":"+1 262 629 5551",
    "sg:postcode":"53002",
    "sg:province":"WI",
    "sg:tags":[
        "lumber"
    ],
    "sg:website":"www.zuerns.com",
    "wof:name":"Zuern Building Products Inc",
    "wof:placetype":"venue"
},
  "geometry": {"coordinates":[-88.341192,43.416721],"type":"Point"}
}