{
  "type": "Feature",
  "properties": {
    "iso:country":"US",
    "sg:address":"713 Willow Creek Pkwy",
    "sg:city":"Watertown",
    "sg:classifiers":[
        {
            "category":"Real Estate",
            "subcategory":"Real Estate Agent",
            "type":"Services"
        }
    ],
    "sg:phone":"+1 920 261 9159",
    "sg:postcode":"53094",
    "sg:province":"WI",
    "wof:name":"Merter LLC",
    "wof:placetype":"venue"
},
  "geometry": {"coordinates":[-88.741665,43.186428],"type":"Point"}
}