{
  "type": "Feature",
  "properties": {
    "addr:full":"11475 Bay Dr Lodi WI 53555",
    "addr:housenumber":"11475",
    "addr:postcode":"53555",
    "addr:street":"Bay Dr",
    "iso:country":"US",
    "sg:address":"11475 Bay Dr",
    "sg:city":"Lodi",
    "sg:classifiers":[
        {
            "category":"Building & Trades",
            "subcategory":"Construction",
            "type":"Services"
        }
    ],
    "sg:phone":"+1 608 592 4040",
    "sg:postcode":"53555",
    "sg:province":"WI",
    "sg:tags":[
        "house",
        "floor",
        "laying",
        "contractor"
    ],
    "wof:name":"Interior Design",
    "wof:placetype":"venue"
},
  "geometry": {"coordinates":[-89.561712,43.366158],"type":"Point"}
}