{
  "type": "Feature",
  "properties": {
    "addr:full":"907 S Andrews St Shawano WI 54166",
    "addr:housenumber":"907",
    "addr:postcode":"54166",
    "addr:street":"S Andrews St",
    "iso:country":"US",
    "sg:address":"907 S Andrews St",
    "sg:city":"Shawano",
    "sg:classifiers":[
        {
            "category":"Building & Trades",
            "subcategory":"Construction",
            "type":"Services"
        }
    ],
    "sg:phone":"+1 715 526 6161",
    "sg:postcode":"54166",
    "sg:province":"WI",
    "sg:tags":[
        "hanging",
        "painter",
        "contractor"
    ],
    "wof:name":"Dan's Painting",
    "wof:placetype":"venue"
},
  "geometry": {"coordinates":[-88.605306,44.770902],"type":"Point"}
}