{
  "type": "Feature",
  "properties": {
    "addr:full":"9507 W National Ave Milwaukee WI 53227",
    "addr:housenumber":"9507",
    "addr:postcode":"53227",
    "addr:street":"W National Ave",
    "iso:country":"US",
    "sg:address":"9507 W National Ave",
    "sg:city":"Milwaukee",
    "sg:classifiers":[
        {
            "category":"Retail",
            "subcategory":"Laundry & Dry Cleaning",
            "type":"Services"
        }
    ],
    "sg:phone":"+1 414 329 8439",
    "sg:postcode":"53227",
    "sg:province":"WI",
    "sg:tags":[
        "cleaners",
        "rug",
        "carpet"
    ],
    "wof:name":"Specialized Cleaning Svc",
    "wof:placetype":"venue"
},
  "geometry": {"coordinates":[-88.030947,43.002743],"type":"Point"}
}