{
  "type": "Feature",
  "properties": {
    "iso:country":"US",
    "sg:address":"457 N Main St",
    "sg:city":"Oshkosh",
    "sg:classifiers":[
        {
            "category":"Shopping",
            "subcategory":"Gifts & Souvenirs",
            "type":"Retail Goods"
        }
    ],
    "sg:phone":"+1 920 303 9230",
    "sg:postcode":"54901",
    "sg:province":"WI",
    "wof:name":"Starseed",
    "wof:placetype":"venue"
},
  "geometry": {"coordinates":[-88.53759700000001,44.019154],"type":"Point"}
}