{
  "type": "Feature",
  "properties": {
    "iso:country":"US",
    "sg:address":"4143 Fern Ln",
    "sg:city":"Oxford",
    "sg:classifiers":[
        {
            "category":"Wholesale",
            "subcategory":"Auto Parts",
            "type":"Manufacturing & Wholesale Goods"
        }
    ],
    "sg:phone":"+1 608 586 4901",
    "sg:postcode":"53952",
    "sg:province":"WI",
    "sg:tags":[
        "automotive",
        "supply"
    ],
    "wof:name":"RPM Distributing of Wisconsin",
    "wof:placetype":"venue"
},
  "geometry": {"coordinates":[-89.591798,43.788694],"type":"Point"}
}