{
  "type": "Feature",
  "properties": {
    "iso:country":"US",
    "sg:address":"2901 University Ave",
    "sg:city":"Madison",
    "sg:classifiers":[
        {
            "category":"Food & Beverages",
            "subcategory":"Liquor & Beverages",
            "type":"Retail Goods"
        }
    ],
    "sg:phone":"+1 608 233 2328",
    "sg:postcode":"53705",
    "sg:province":"WI",
    "sg:tags":[
        "beer",
        "ale"
    ],
    "wof:name":"Party Port",
    "wof:placetype":"venue"
},
  "geometry": {"coordinates":[-89.441347,43.075247],"type":"Point"}
}