{
  "type": "Feature",
  "properties": {
    "iso:country":"US",
    "sg:address":"135 S Main St",
    "sg:city":"Oregon",
    "sg:classifiers":[
        {
            "category":"Health Services",
            "subcategory":"Nursing And Care Facility",
            "type":"Services"
        },
        {
            "category":"Home & Garden",
            "subcategory":"Mobile Homes",
            "type":"Retail Goods"
        }
    ],
    "sg:phone":"+1 608 835 7713",
    "sg:postcode":"53575",
    "sg:province":"WI",
    "sg:tags":[
        "retirement",
        "community"
    ],
    "wof:name":"Rolling Meadows Homes Inc",
    "wof:placetype":"venue"
},
  "geometry": {"coordinates":[-89.384771,42.925196],"type":"Point"}
}