{
  "type": "Feature",
  "properties": {
    "iso:country":"US",
    "sg:address":"3827 Theiler Rd",
    "sg:city":"Monroe",
    "sg:classifiers":[
        {
            "category":"Farming",
            "subcategory":"Dairy Farm",
            "type":"Manufacturing & Wholesale Goods"
        }
    ],
    "sg:phone":"+1 608 325 2987",
    "sg:postcode":"53566",
    "sg:province":"WI",
    "wof:name":"Rick Devoe",
    "wof:placetype":"venue"
},
  "geometry": {"coordinates":[-89.56298,42.50984],"type":"Point"}
}