{
  "type": "Feature",
  "properties": {
    "addr:full":"7225 Thoma Rd New London WI 54961",
    "addr:housenumber":"7225",
    "addr:postcode":"54961",
    "addr:street":"Thoma Rd",
    "iso:country":"US",
    "sg:address":"7225 Thoma Rd",
    "sg:city":"New London",
    "sg:classifiers":[
        {
            "category":"Farming",
            "subcategory":"Dairy Farm",
            "type":"Manufacturing & Wholesale Goods"
        }
    ],
    "sg:phone":"+1 920 982 2925",
    "sg:postcode":"54961",
    "sg:province":"WI",
    "wof:name":"Maple Grove Farm",
    "wof:placetype":"venue"
},
  "geometry": {"coordinates":[-88.77748699999999,44.500486],"type":"Point"}
}