{
  "type": "Feature",
  "properties": {
    "iso:country":"US",
    "sg:address":"6930 N Teutonia Ave",
    "sg:city":"Milwaukee",
    "sg:classifiers":[
        {
            "category":"Banks & Credit Unions",
            "subcategory":"Bank",
            "type":"Services"
        }
    ],
    "sg:phone":"+1 414 352 2900",
    "sg:postcode":"53209",
    "sg:province":"WI",
    "sg:tags":[
        "institution",
        "business"
    ],
    "wof:name":"Payday Loan Store Wisconsin",
    "wof:placetype":"venue"
},
  "geometry": {"coordinates":[-87.955503,43.144981],"type":"Point"}
}