{
  "type": "Feature",
  "properties": {
    "addr:full":"125 Rowell St Beaver Dam WI 53916",
    "addr:housenumber":"125",
    "addr:postcode":"53916",
    "addr:street":"Rowell St",
    "iso:country":"US",
    "sg:address":"125 Rowell St",
    "sg:city":"Beaver Dam",
    "sg:classifiers":[
        {
            "category":"Manufacturing",
            "subcategory":"Metals",
            "type":"Manufacturing & Wholesale Goods"
        }
    ],
    "sg:phone":"+1 920 887 0395",
    "sg:postcode":"53916",
    "sg:province":"WI",
    "sg:tags":[
        "gray",
        "ductile",
        "casting",
        "mfg",
        "malleable",
        "iron"
    ],
    "sg:website":"www.kirshfoundry.com",
    "wof:name":"Kirsh Foundry Inc",
    "wof:placetype":"venue"
},
  "geometry": {"coordinates":[-88.84160900000001,43.454045],"type":"Point"}
}