{
  "type": "Feature",
  "properties": {
    "iso:country":"US",
    "sg:address":"717 Rose St",
    "sg:city":"La Crosse",
    "sg:classifiers":[
        {
            "category":"Bars & Pubs",
            "type":"Food & Drink"
        }
    ],
    "sg:phone":"+1 608 796 1161",
    "sg:postcode":"54603",
    "sg:province":"WI",
    "sg:tags":[
        "drinking"
    ],
    "wof:name":"Rose Ramblin Inc",
    "wof:placetype":"venue"
},
  "geometry": {"coordinates":[-91.248242,43.835581],"type":"Point"}
}