{
  "type": "Feature",
  "properties": {
    "addr:full":"2705 Packers Ave Madison WI 53704",
    "addr:housenumber":"2705",
    "addr:postcode":"53704",
    "addr:street":"Packers Ave",
    "iso:country":"US",
    "sg:address":"2705 Packers Ave",
    "sg:city":"Madison",
    "sg:classifiers":[
        {
            "category":"Retail",
            "subcategory":"Auto Rental",
            "type":"Services"
        }
    ],
    "sg:phone":"+1 608 249 4551",
    "sg:postcode":"53704",
    "sg:province":"WI",
    "sg:tags":[
        "renting",
        "truck",
        "leasing"
    ],
    "wof:name":"Budget Truck Rental",
    "wof:placetype":"venue"
},
  "geometry": {"coordinates":[-89.355073,43.128526],"type":"Point"}
}