{
  "type": "Feature",
  "properties": {
    "addr:full":"608 Rockshire Dr Janesville WI 53546",
    "addr:housenumber":"608",
    "addr:postcode":"53546",
    "addr:street":"Rockshire Dr",
    "iso:country":"US",
    "sg:address":"608 Rockshire Dr",
    "sg:city":"Janesville",
    "sg:classifiers":[
        {
            "category":"Professional",
            "subcategory":"Management & Consulting",
            "type":"Services"
        }
    ],
    "sg:phone":"+1 608 754 4278",
    "sg:postcode":"53546",
    "sg:province":"WI",
    "wof:name":"Richard A Murray",
    "wof:placetype":"venue"
},
  "geometry": {"coordinates":[-88.954779,42.689306],"type":"Point"}
}