{
  "type": "Feature",
  "properties": {
    "iso:country":"US",
    "sg:address":"3020 Washington Ave",
    "sg:city":"Plover",
    "sg:classifiers":[
        {
            "category":"Health Services",
            "subcategory":"Nursing And Care Facility",
            "type":"Services"
        }
    ],
    "sg:phone":"+1 715 341 7301",
    "sg:postcode":"54467",
    "sg:province":"WI",
    "sg:tags":[
        "association"
    ],
    "sg:website":"www.c2change.com",
    "wof:name":"Choices To Change",
    "wof:placetype":"venue"
},
  "geometry": {"coordinates":[-89.540115,44.453636],"type":"Point"}
}