{
  "type": "Feature",
  "properties": {
    "iso:country":"US",
    "sg:address":"5823 W Burnham St",
    "sg:city":"Milwaukee",
    "sg:phone":"+1 414 321 5775",
    "sg:postcode":"53219",
    "sg:province":"WI",
    "sg:website":"http://www.antiguamilwaukee.com",
    "wof:name":"Antigua Latin Restaurant",
    "wof:placetype":"venue"
},
  "geometry": {"coordinates":[-87.98522199999999,43.010173],"type":"Point"}
}