{
  "type": "Feature",
  "properties": {
    "addr:full":"6025 Monona Dr Monona WI 53716",
    "addr:housenumber":"6025",
    "addr:postcode":"53716",
    "addr:street":"Monona Dr",
    "iso:country":"US",
    "sg:address":"6025 Monona Dr",
    "sg:city":"Monona",
    "sg:classifiers":[
        {
            "category":"Shopping",
            "subcategory":"Jewelry",
            "type":"Retail Goods"
        }
    ],
    "sg:phone":"+1 608 221 0140",
    "sg:postcode":"53716",
    "sg:province":"WI",
    "sg:tags":[
        "coin",
        "jeweler"
    ],
    "wof:name":"Capital City Coins and Jewelry",
    "wof:placetype":"venue"
},
  "geometry": {"coordinates":[-89.32536,43.053304],"type":"Point"}
}