{
  "type": "Feature",
  "properties": {
    "iso:country":"US",
    "sg:address":"2410 State Hwy 107",
    "sg:city":"Merrill",
    "sg:classifiers":[
        {
            "category":"Bars & Pubs",
            "type":"Food & Drink"
        }
    ],
    "sg:phone":"+1 715 539 1170",
    "sg:postcode":"54452",
    "sg:province":"WI",
    "wof:name":"Club 107",
    "wof:placetype":"venue"
},
  "geometry": {"coordinates":[-89.74506,45.177984],"type":"Point"}
}