{
  "type": "Feature",
  "properties": {
    "iso:country":"US",
    "sg:address":"3900 Park Rd",
    "sg:city":"Marathon",
    "sg:classifiers":[
        {
            "category":"Manufacturing",
            "subcategory":"Lumber",
            "type":"Manufacturing & Wholesale Goods"
        }
    ],
    "sg:phone":"+1 715 443 3863",
    "sg:postcode":"54448",
    "sg:province":"WI",
    "sg:tags":[
        "track",
        "timber"
    ],
    "wof:name":"David Matis Forest Products",
    "wof:placetype":"venue"
},
  "geometry": {"coordinates":[-89.798479,44.913024],"type":"Point"}
}