{
  "type": "Feature",
  "properties": {
    "iso:country":"US",
    "sg:address":"105 Elm St",
    "sg:city":"Oakfield",
    "sg:classifiers":[
        {
            "category":"Real Estate",
            "subcategory":"Real Estate Operator",
            "type":"Services"
        }
    ],
    "sg:phone":"+1 920 583 3833",
    "sg:postcode":"53065",
    "sg:province":"WI",
    "sg:tags":[
        "building",
        "apartment"
    ],
    "wof:name":"Wild Goose Landing-Sr Housing",
    "wof:placetype":"venue"
},
  "geometry": {"coordinates":[-88.551683,43.68618],"type":"Point"}
}