{
  "type": "Feature",
  "properties": {
    "iso:country":"US",
    "sg:address":"632 Eastview Dr",
    "sg:city":"Antigo",
    "sg:classifiers":[
        {
            "category":"Freight",
            "type":"Transportation"
        }
    ],
    "sg:phone":"+1 715 623 4713",
    "sg:postcode":"54409",
    "sg:province":"WI",
    "sg:tags":[
        "cartage",
        "trucking"
    ],
    "wof:name":"Melzer Trucking",
    "wof:placetype":"venue"
},
  "geometry": {"coordinates":[-89.131889,45.141619],"type":"Point"}
}