{
  "type": "Feature",
  "properties": {
    "iso:country":"US",
    "sg:address":"5502 Co Rd C",
    "sg:city":"Cecil",
    "sg:classifiers":[
        {
            "category":"Bars & Pubs",
            "type":"Food & Drink"
        }
    ],
    "sg:phone":"+1 715 745 2155",
    "sg:postcode":"54111",
    "sg:province":"WI",
    "wof:name":"Pete & Barb's Landmark",
    "wof:placetype":"venue"
},
  "geometry": {"coordinates":[-88.332056,44.793162],"type":"Point"}
}