{
  "type": "Feature",
  "properties": {
    "iso:country":"US",
    "sg:address":"3131 Pierce Blvd",
    "sg:city":"Racine",
    "sg:classifiers":[
        {
            "category":"Professional",
            "type":"Services"
        }
    ],
    "sg:phone":"+1 262 634 4369",
    "sg:postcode":"53405",
    "sg:province":"WI",
    "wof:name":"Eric R Sabol",
    "wof:placetype":"venue"
},
  "geometry": {"coordinates":[-87.816919,42.698829],"type":"Point"}
}