{
  "type": "Feature",
  "properties": {
    "iso:country":"US",
    "sg:address":"226 W 3rd St",
    "sg:city":"New Richmond",
    "sg:classifiers":[
        {
            "category":"Wholesale",
            "subcategory":"Non-durable Goods",
            "type":"Manufacturing & Wholesale Goods"
        }
    ],
    "sg:phone":"+1 715 246 4634",
    "sg:postcode":"54017",
    "sg:province":"WI",
    "sg:tags":[
        "advertising"
    ],
    "wof:name":"Lowe Advertising Specialties",
    "wof:placetype":"venue"
},
  "geometry": {"coordinates":[-92.539739,45.12044],"type":"Point"}
}