{
  "type": "Feature",
  "properties": {
    "addr:full":"3915 N Richards St Milwaukee WI 53212",
    "addr:housenumber":"3915",
    "addr:postcode":"53212",
    "addr:street":"N Richards St",
    "iso:country":"US",
    "sg:address":"3915 N Richards St",
    "sg:city":"Milwaukee",
    "sg:classifiers":[
        {
            "category":"Sports & Exercise",
            "subcategory":"Gym",
            "type":"Entertainment"
        }
    ],
    "sg:phone":"+1 414 961 2333",
    "sg:postcode":"53212",
    "sg:province":"WI",
    "sg:tags":[
        "club",
        "health",
        "studio",
        "gymnasium"
    ],
    "wof:name":"Victory Lady Fitness Ctr",
    "wof:placetype":"venue"
},
  "geometry": {"coordinates":[-87.907382,43.088242],"type":"Point"}
}