{
  "type": "Feature",
  "properties": {
    "addr:full":"928 Loring St Altoona WI 54720",
    "addr:housenumber":"928",
    "addr:postcode":"54720",
    "addr:street":"Loring St",
    "iso:country":"US",
    "sg:address":"928 Loring St",
    "sg:city":"Altoona",
    "sg:classifiers":[
        {
            "category":"Personal",
            "subcategory":"Beauty Salon",
            "type":"Services"
        }
    ],
    "sg:phone":"+1 715 832 8044",
    "sg:postcode":"54720",
    "sg:province":"WI",
    "sg:tags":[
        "shop"
    ],
    "wof:name":"Pic-A-Style",
    "wof:placetype":"venue"
},
  "geometry": {"coordinates":[-91.46648,44.800131],"type":"Point"}
}