{
  "type": "Feature",
  "properties": {
    "addr:full":"5454 Park St Boulder Junction WI 54512",
    "addr:housenumber":"5454",
    "addr:postcode":"54512",
    "addr:street":"Park St",
    "iso:country":"US",
    "sg:address":"5454 Park St",
    "sg:city":"Boulder Junction",
    "sg:classifiers":[
        {
            "category":"Shopping",
            "subcategory":"Bicycles & Sporting Goods",
            "type":"Retail Goods"
        }
    ],
    "sg:phone":"+1 715 385 3398",
    "sg:postcode":"54512",
    "sg:province":"WI",
    "wof:name":"Coontail Too",
    "wof:placetype":"venue"
},
  "geometry": {"coordinates":[-89.640636,46.111234],"type":"Point"}
}