{
  "type": "Feature",
  "properties": {
    "iso:country":"US",
    "sg:address":"2116 Harris Highland Dr",
    "sg:city":"Waukesha",
    "sg:classifiers":[
        {
            "category":"Retail",
            "subcategory":"Repair Shop",
            "type":"Services"
        }
    ],
    "sg:phone":"+1 262 548 0699",
    "sg:postcode":"53188",
    "sg:province":"WI",
    "sg:tags":[
        "bathtub",
        "sink",
        "refinishing"
    ],
    "wof:name":"Surface Specialists",
    "wof:placetype":"venue"
},
  "geometry": {"coordinates":[-88.263417,43.003835],"type":"Point"}
}