{
  "type": "Feature",
  "properties": {
    "addr:full":"1406 Springdale Ln Green Bay WI 54304",
    "addr:housenumber":"1406",
    "addr:postcode":"54304",
    "addr:street":"Springdale Ln",
    "iso:country":"US",
    "sg:address":"1406 Springdale Ln",
    "sg:city":"Green Bay",
    "sg:classifiers":[
        {
            "category":"Real Estate",
            "subcategory":"Real Estate Agent",
            "type":"Services"
        }
    ],
    "sg:phone":"+1 920 494 4999",
    "sg:postcode":"54304",
    "sg:province":"WI",
    "sg:tags":[
        "appraisal"
    ],
    "wof:name":"NEW Appraisal Co",
    "wof:placetype":"venue"
},
  "geometry": {"coordinates":[-88.086217,44.518118],"type":"Point"}
}