{
  "type": "Feature",
  "properties": {
    "iso:country":"US",
    "sg:address":"3431 N Cramer St",
    "sg:city":"Milwaukee",
    "sg:classifiers":[
        {
            "category":"Professional",
            "subcategory":"Art Services",
            "type":"Services"
        }
    ],
    "sg:phone":"+1 414 961 9130",
    "sg:postcode":"53211",
    "sg:province":"WI",
    "sg:tags":[
        "photography",
        "commercial"
    ],
    "wof:name":"Purcell Imaging Ltd",
    "wof:placetype":"venue"
},
  "geometry": {"coordinates":[-87.886531,43.081178],"type":"Point"}
}