{
  "type": "Feature",
  "properties": {
    "iso:country":"US",
    "sg:address":"206 E Lincoln Ave",
    "sg:city":"Milwaukee",
    "sg:classifiers":[
        {
            "category":"Home & Garden",
            "subcategory":"Household Appliances",
            "type":"Retail Goods"
        },
        {
            "category":"Building & Trades",
            "subcategory":"Construction",
            "type":"Services"
        }
    ],
    "sg:phone":"+1 414 744 4424",
    "sg:postcode":"53207",
    "sg:province":"WI",
    "sg:tags":[
        "major",
        "system",
        "appliances-small",
        "specialty",
        "heating",
        "contractor",
        "air conditioning"
    ],
    "wof:name":"Magnum Services",
    "wof:placetype":"venue"
},
  "geometry": {"coordinates":[-87.907877,43.0029],"type":"Point"}
}