{
  "type": "Feature",
  "properties": {
    "iso:country":"US",
    "sg:address":"5908 Willow Rd",
    "sg:city":"Plymouth",
    "sg:classifiers":[
        {
            "category":"Autos & Motor Vehicles",
            "subcategory":"Automobile Sales",
            "type":"Retail Goods"
        }
    ],
    "sg:phone":"+1 920 893 0311",
    "sg:postcode":"53073",
    "sg:province":"WI",
    "sg:tags":[
        "car",
        "dealer"
    ],
    "wof:name":"Wolf's Chrysler-Plymouth Jeep",
    "wof:placetype":"venue"
},
  "geometry": {"coordinates":[-87.921453,43.755559],"type":"Point"}
}