{
  "type": "Feature",
  "properties": {
    "iso:country":"US",
    "sg:address":"1310 Liberty St",
    "sg:city":"La Crosse",
    "sg:classifiers":[
        {
            "category":"Social Services",
            "subcategory":"Child Care",
            "type":"Services"
        }
    ],
    "sg:phone":"+1 608 785 7450",
    "sg:postcode":"54603",
    "sg:province":"WI",
    "sg:tags":[
        "day"
    ],
    "wof:name":"Laurie Rose Daycare",
    "wof:placetype":"venue"
},
  "geometry": {"coordinates":[-91.243817,43.842899],"type":"Point"}
}