{
  "type": "Feature",
  "properties": {
    "iso:country":"US",
    "sg:address":"2047 22nd Ave",
    "sg:city":"Kenosha",
    "sg:classifiers":[
        {
            "category":"Health Services",
            "subcategory":"Clinic",
            "type":"Services"
        }
    ],
    "sg:phone":"+1 262 551 9400",
    "sg:postcode":"53140",
    "sg:province":"WI",
    "sg:tags":[
        "specialty",
        "outpatient"
    ],
    "wof:name":"Post Rehabilitation Inc",
    "wof:placetype":"venue"
},
  "geometry": {"coordinates":[-87.835782,42.618497],"type":"Point"}
}