{
  "type": "Feature",
  "properties": {
    "iso:country":"US",
    "sg:address":"6881 Division Rd",
    "sg:city":"Egg Harbor",
    "sg:phone":"+1 920 868 3117",
    "sg:postcode":"54209",
    "sg:province":"WI",
    "sg:tags":[
        "farm",
        "grain",
        "cash"
    ],
    "wof:name":"Mark Sawyer",
    "wof:placetype":"venue"
},
  "geometry": {"coordinates":[-87.275507,44.993915],"type":"Point"}
}