{
  "type": "Feature",
  "properties": {
    "addr:full":"15330 Watertown Plank Rd Elm Grove WI 53122",
    "addr:postcode":"15330;53122",
    "addr:street":"Plank Rd",
    "iso:country":"US",
    "sg:address":"15330 Watertown Plank Rd",
    "sg:city":"Elm Grove",
    "sg:classifiers":[
        {
            "category":"Organizations",
            "subcategory":"Non-profit Organization",
            "type":"Services"
        },
        {
            "category":"Organizations",
            "subcategory":"Religious Organization",
            "type":"Services"
        }
    ],
    "sg:phone":"+1 262 782 3140",
    "sg:postcode":"53122",
    "sg:province":"WI",
    "wof:name":"American Baptist Churches WI",
    "wof:placetype":"venue"
},
  "geometry": {"coordinates":[-88.10589899999999,43.037004],"type":"Point"}
}