{
  "type": "Feature",
  "properties": {
    "iso:country":"US",
    "sg:address":"186 S Central Ave",
    "sg:city":"Richland Center",
    "sg:classifiers":[
        {
            "category":"Shopping",
            "subcategory":"Computers & Home Electronics",
            "type":"Retail Goods"
        }
    ],
    "sg:phone":"+1 608 647 6350",
    "sg:postcode":"53581",
    "sg:province":"WI",
    "sg:tags":[
        "equipment"
    ],
    "wof:name":"Advanced Technology Solutions",
    "wof:placetype":"venue"
},
  "geometry": {"coordinates":[-90.385513,43.334746],"type":"Point"}
}