{
  "type": "Feature",
  "properties": {
    "iso:country":"US",
    "sg:address":"21 Crestwood Dr",
    "sg:city":"Elkhart Lake",
    "sg:classifiers":[
        {
            "category":"Building & Trades",
            "subcategory":"Construction",
            "type":"Services"
        }
    ],
    "sg:phone":"+1 920 876 4604",
    "sg:postcode":"53020",
    "sg:province":"WI",
    "sg:tags":[
        "house"
    ],
    "wof:name":"J&A Builders",
    "wof:placetype":"venue"
},
  "geometry": {"coordinates":[-88.00735,43.835015],"type":"Point"}
}