{
  "type": "Feature",
  "properties": {
    "iso:country":"US",
    "sg:address":"6955 N Port Washington Rd",
    "sg:city":"Milwaukee",
    "sg:classifiers":[
        {
            "category":"Shopping",
            "subcategory":"Bicycles & Sporting Goods",
            "type":"Retail Goods"
        }
    ],
    "sg:phone":"+1 414 247 8100",
    "sg:postcode":"53217",
    "sg:province":"WI",
    "wof:name":"Wheel & Sprocket Inc",
    "wof:placetype":"venue"
},
  "geometry": {"coordinates":[-87.912937,43.140939],"type":"Point"}
}