{
  "type": "Feature",
  "properties": {
    "addr:full":"4301 Lien Rd Madison WI 53704",
    "addr:housenumber":"4301",
    "addr:postcode":"53704",
    "addr:street":"Lien Rd",
    "iso:country":"US",
    "sg:address":"4301 Lien Rd",
    "sg:city":"Madison",
    "sg:classifiers":[
        {
            "category":"Retail",
            "subcategory":"Photofinishing",
            "type":"Services"
        }
    ],
    "sg:phone":"+1 608 240 0340",
    "sg:postcode":"53704",
    "sg:province":"WI",
    "sg:tags":[
        "photo",
        "finishing"
    ],
    "wof:name":"Qualex Inc",
    "wof:placetype":"venue"
},
  "geometry": {"coordinates":[-89.310863,43.121131],"type":"Point"}
}