{
  "type": "Feature",
  "properties": {
    "iso:country":"US",
    "sg:address":"322 E Main St",
    "sg:city":"Little Chute",
    "sg:classifiers":[
        {
            "category":"Insurance",
            "subcategory":"Insurance Agent",
            "type":"Services"
        }
    ],
    "sg:phone":"+1 920 788 2200",
    "sg:postcode":"54140",
    "sg:province":"WI",
    "wof:name":"Jerry Sherwood Insurance",
    "wof:placetype":"venue"
},
  "geometry": {"coordinates":[-88.31175500000001,44.280768],"type":"Point"}
}