{
  "type": "Feature",
  "properties": {
    "addr:full":"5511 Dearhamer Rd Bruce WI 54819",
    "addr:housenumber":"5511",
    "addr:postcode":"54819",
    "addr:street":"Dearhamer Rd",
    "iso:country":"US",
    "sg:address":"5511 Dearhamer Rd",
    "sg:city":"Bruce",
    "sg:classifiers":[
        {
            "category":"Farming",
            "subcategory":"Dairy Farm",
            "type":"Manufacturing & Wholesale Goods"
        }
    ],
    "sg:phone":"+1 715 868 5884",
    "sg:postcode":"54819",
    "sg:province":"WI",
    "wof:name":"Richard A Benson",
    "wof:placetype":"venue"
},
  "geometry": {"coordinates":[-91.318105,45.491268],"type":"Point"}
}