{
  "type": "Feature",
  "properties": {
    "iso:country":"US",
    "sg:address":"4189 Brue Rd",
    "sg:city":"Dodgeville",
    "sg:classifiers":[
        {
            "category":"Local Transit",
            "type":"Transportation"
        }
    ],
    "sg:phone":"+1 608 935 5255",
    "sg:postcode":"53533",
    "sg:province":"WI",
    "sg:tags":[
        "bus",
        "line"
    ],
    "wof:name":"First Student Bus Lines Inc",
    "wof:placetype":"venue"
},
  "geometry": {"coordinates":[-90.157558,42.967364],"type":"Point"}
}