{
  "type": "Feature",
  "properties": {
    "iso:country":"US",
    "sg:address":"10810 W Fairmount Ave",
    "sg:city":"Milwaukee",
    "sg:classifiers":[
        {
            "category":"Building & Trades",
            "subcategory":"Construction",
            "type":"Services"
        }
    ],
    "sg:phone":"+1 414 527 3140",
    "sg:postcode":"53225",
    "sg:province":"WI",
    "sg:tags":[
        "hanging",
        "contractor"
    ],
    "wof:name":"Deans Painting Contractor",
    "wof:placetype":"venue"
},
  "geometry": {"coordinates":[-88.048923,43.10912],"type":"Point"}
}