{
  "type": "Feature",
  "properties": {
    "iso:country":"US",
    "sg:address":"5823 State Hwy 85",
    "sg:city":"Durand",
    "sg:classifiers":[
        {
            "category":"Food & Beverages",
            "subcategory":"Meat & Fish",
            "type":"Retail Goods"
        },
        {
            "category":"Personal",
            "type":"Services"
        }
    ],
    "sg:phone":"+1 715 672 8073",
    "sg:postcode":"54736",
    "sg:province":"WI",
    "wof:name":"Butch's Country Market",
    "wof:placetype":"venue"
},
  "geometry": {"coordinates":[-91.93822299999999,44.641168],"type":"Point"}
}