{
  "type": "Feature",
  "properties": {
    "addr:full":"1848 Liberty St Marinette WI 54143",
    "addr:housenumber":"1848",
    "addr:postcode":"54143",
    "addr:street":"Liberty St",
    "iso:country":"US",
    "sg:address":"1848 Liberty St",
    "sg:city":"Marinette",
    "sg:classifiers":[
        {
            "category":"Shopping",
            "subcategory":"Bicycles & Sporting Goods",
            "type":"Retail Goods"
        }
    ],
    "sg:phone":"+1 715 735 0542",
    "sg:postcode":"54143",
    "sg:province":"WI",
    "wof:name":"Storys Athletics",
    "wof:placetype":"venue"
},
  "geometry": {"coordinates":[-87.632451,45.097751],"type":"Point"}
}