{
  "type": "Feature",
  "properties": {
    "iso:country":"US",
    "sg:address":"33 S Water St E",
    "sg:city":"Fort Atkinson",
    "sg:classifiers":[
        {
            "category":"Personal",
            "subcategory":"Beauty Salon",
            "type":"Services"
        }
    ],
    "sg:phone":"+1 920 563 3366",
    "sg:postcode":"53538",
    "sg:province":"WI",
    "wof:name":"Crimson Salon & Spa",
    "wof:placetype":"venue"
},
  "geometry": {"coordinates":[-88.836521,42.927483],"type":"Point"}
}