{
  "type": "Feature",
  "properties": {
    "iso:country":"US",
    "sg:address":"1250 S Post Rd",
    "sg:city":"Brookfield",
    "sg:classifiers":[
        {
            "category":"Food & Beverages",
            "subcategory":"Specialty",
            "type":"Retail Goods"
        }
    ],
    "sg:phone":"+1 262 786 6897",
    "sg:postcode":"53005",
    "sg:province":"WI",
    "wof:name":"Cornerstone Nutrition LLC",
    "wof:placetype":"venue"
},
  "geometry": {"coordinates":[-88.117017,43.017854],"type":"Point"}
}