{
  "type": "Feature",
  "properties": {
    "addr:full":"232 S Courtney St Rhinelander WI 54501",
    "addr:housenumber":"232",
    "addr:postcode":"54501",
    "addr:street":"S Courtney St",
    "iso:country":"US",
    "sg:address":"232 S Courtney St",
    "sg:city":"Rhinelander",
    "sg:classifiers":[
        {
            "category":"Shopping",
            "type":"Retail Goods"
        }
    ],
    "sg:phone":"+1 715 362 1544",
    "sg:postcode":"54501",
    "sg:province":"WI",
    "sg:tags":[
        "merchandise"
    ],
    "wof:name":"Miracle-Ear",
    "wof:placetype":"venue"
},
  "geometry": {"coordinates":[-89.413541,45.635604],"type":"Point"}
}