{
  "type": "Feature",
  "properties": {
    "addr:full":"8112 State Hwy 22 Bear Creek WI 54922",
    "addr:housenumber":"8112",
    "addr:postcode":"54922",
    "addr:street":"State Hwy 22",
    "iso:country":"US",
    "sg:address":"8112 State Hwy 22",
    "sg:city":"Bear Creek",
    "sg:classifiers":[
        {
            "category":"Building & Trades",
            "subcategory":"Construction",
            "type":"Services"
        }
    ],
    "sg:phone":"+1 715 752 3003",
    "sg:postcode":"54922",
    "sg:province":"WI",
    "wof:name":"Shamrock Construction Inc",
    "wof:placetype":"venue"
},
  "geometry": {"coordinates":[-88.81792,44.531895],"type":"Point"}
}