{
  "type": "Feature",
  "properties": {
    "iso:country":"US",
    "sg:address":"560 N Rolling Meadows Dr",
    "sg:city":"Fond Du Lac",
    "sg:classifiers":[
        {
            "category":"Wholesale",
            "subcategory":"Vending Machines",
            "type":"Manufacturing & Wholesale Goods"
        }
    ],
    "sg:phone":"+1 920 929 8040",
    "sg:postcode":"54937",
    "sg:province":"WI",
    "sg:tags":[
        "operator"
    ],
    "sg:website":"www.a-zvending.com",
    "wof:name":"A To Z Vending & Food Service",
    "wof:placetype":"venue"
},
  "geometry": {"coordinates":[-88.48659000000001,43.791263],"type":"Point"}
}