{
  "type": "Feature",
  "properties": {
    "iso:country":"US",
    "sg:address":"4241 8th St S",
    "sg:city":"Wisconsin Rapids",
    "sg:classifiers":[
        {
            "category":"Autos & Motor Vehicles",
            "subcategory":"Automobile Sales",
            "type":"Retail Goods"
        }
    ],
    "sg:phone":"+1 715 421 2277",
    "sg:postcode":"54494",
    "sg:province":"WI",
    "sg:tags":[
        "car",
        "dealer"
    ],
    "wof:name":"Greg Ellious Motors Pre-Owned",
    "wof:placetype":"venue"
},
  "geometry": {"coordinates":[-89.816711,44.355501],"type":"Point"}
}