{
  "type": "Feature",
  "properties": {
    "iso:country":"US",
    "sg:address":"204 Valorie Ln",
    "sg:city":"Madison",
    "sg:classifiers":[
        {
            "category":"Communications",
            "type":"Services"
        }
    ],
    "sg:phone":"+1 608 224 0181",
    "sg:postcode":"53716",
    "sg:province":"WI",
    "sg:tags":[
        "communication"
    ],
    "wof:name":"Veit Communications LLC",
    "wof:placetype":"venue"
},
  "geometry": {"coordinates":[-89.328387,43.06328],"type":"Point"}
}