{
  "type": "Feature",
  "properties": {
    "addr:full":"601 Wildwood Rd West Bend WI 53090",
    "addr:housenumber":"601",
    "addr:postcode":"53090",
    "addr:street":"Wildwood Rd",
    "iso:country":"US",
    "sg:address":"601 Wildwood Rd",
    "sg:city":"West Bend",
    "sg:classifiers":[
        {
            "category":"Home & Garden",
            "subcategory":"Garden Supply",
            "type":"Retail Goods"
        }
    ],
    "sg:phone":"+1 262 338 5252",
    "sg:postcode":"53090",
    "sg:province":"WI",
    "sg:tags":[
        "center"
    ],
    "wof:name":"Stein Garden & Gifts",
    "wof:placetype":"venue"
},
  "geometry": {"coordinates":[-88.21599999999999,43.429521],"type":"Point"}
}