{
  "type": "Feature",
  "properties": {
    "iso:country":"US",
    "sg:address":"2811 8th St S",
    "sg:city":"Wisconsin Rapids",
    "sg:classifiers":[
        {
            "category":"Health Services",
            "subcategory":"Health Practitioner",
            "type":"Services"
        }
    ],
    "sg:phone":"+1 715 423 1295",
    "sg:postcode":"54494",
    "sg:province":"WI",
    "sg:tags":[
        "nutritionist"
    ],
    "wof:name":"Nutritional Dynamics",
    "wof:placetype":"venue"
},
  "geometry": {"coordinates":[-89.816842,44.369434],"type":"Point"}
}