{
  "type": "Feature",
  "properties": {
    "iso:country":"US",
    "sg:address":"10575 Lakeshore Rd",
    "sg:city":"Clintonville",
    "sg:classifiers":[
        {
            "category":"Autos & Motor Vehicles",
            "subcategory":"Automobile Sales",
            "type":"Retail Goods"
        }
    ],
    "sg:phone":"+1 715 823 7800",
    "sg:postcode":"54929",
    "sg:province":"WI",
    "sg:tags":[
        "car",
        "used",
        "dealer"
    ],
    "wof:name":"West Town Motors",
    "wof:placetype":"venue"
},
  "geometry": {"coordinates":[-88.77227499999999,44.621448],"type":"Point"}
}