{
  "type": "Feature",
  "properties": {
    "iso:country":"US",
    "sg:address":"312 S Western Ave",
    "sg:city":"Waupaca",
    "sg:classifiers":[
        {
            "category":"Building & Trades",
            "subcategory":"Construction",
            "type":"Services"
        }
    ],
    "sg:phone":"+1 920 867 4946",
    "sg:postcode":"54981",
    "sg:province":"WI",
    "sg:tags":[
        "house"
    ],
    "wof:name":"A & F Roofing Inc",
    "wof:placetype":"venue"
},
  "geometry": {"coordinates":[-89.103144,44.35212],"type":"Point"}
}