{
  "type": "Feature",
  "properties": {
    "iso:country":"US",
    "sg:address":"813 Monroe St",
    "sg:city":"Sheboygan Falls",
    "sg:classifiers":[
        {
            "category":"Restaurant",
            "type":"Food & Drink"
        }
    ],
    "sg:phone":"+1 920 467 1454",
    "sg:postcode":"53085",
    "sg:province":"WI",
    "sg:tags":[
        "eating"
    ],
    "wof:name":"Park View Restaurant",
    "wof:placetype":"venue"
},
  "geometry": {"coordinates":[-87.81620599999999,43.727176],"type":"Point"}
}