{
  "type": "Feature",
  "properties": {
    "iso:country":"US",
    "sg:address":"1548 Deckner Ave",
    "sg:city":"Green Bay",
    "sg:classifiers":[
        {
            "category":"Manufacturing",
            "subcategory":"Food",
            "type":"Manufacturing & Wholesale Goods"
        }
    ],
    "sg:phone":"+1 920 336 6464",
    "sg:postcode":"54302",
    "sg:province":"WI",
    "sg:tags":[
        "frozen",
        "mfg",
        "pizza"
    ],
    "wof:name":"Badger Best Pizza",
    "wof:placetype":"venue"
},
  "geometry": {"coordinates":[-87.98833399999999,44.502393],"type":"Point"}
}