{
  "type": "Feature",
  "properties": {
    "iso:country":"US",
    "sg:address":"2331 State Hwy 22",
    "sg:city":"Waupaca",
    "sg:classifiers":[
        {
            "category":"Freight",
            "type":"Transportation"
        }
    ],
    "sg:phone":"+1 715 258 7776",
    "sg:postcode":"54981",
    "sg:province":"WI",
    "sg:tags":[
        "special"
    ],
    "wof:name":"Highway 22 Storage",
    "wof:placetype":"venue"
},
  "geometry": {"coordinates":[-89.152127,44.315838],"type":"Point"}
}