{
  "type": "Feature",
  "properties": {
    "addr:full":"15500 W Cleveland Ave New Berlin WI 53151",
    "addr:housenumber":"15500",
    "addr:postcode":"53151",
    "addr:street":"W Cleveland Ave",
    "iso:country":"US",
    "sg:address":"15500 W Cleveland Ave",
    "sg:city":"New Berlin",
    "sg:classifiers":[
        {
            "category":"Freight",
            "type":"Transportation"
        }
    ],
    "sg:phone":"+1 262 860 1608",
    "sg:postcode":"53151",
    "sg:province":"WI",
    "sg:tags":[
        "operator",
        "local",
        "trucking"
    ],
    "wof:name":"Pakula Trucking LLC",
    "wof:placetype":"venue"
},
  "geometry": {"coordinates":[-88.106894,42.995614],"type":"Point"}
}