{
  "type": "Feature",
  "properties": {
    "iso:country":"US",
    "sg:address":"4775 Co Rd A",
    "sg:city":"Oregon",
    "sg:classifiers":[
        {
            "category":"Manufacturing",
            "subcategory":"Building Materials",
            "type":"Manufacturing & Wholesale Goods"
        }
    ],
    "sg:phone":"+1 608 835 5584",
    "sg:postcode":"53575",
    "sg:province":"WI",
    "sg:tags":[
        "wood",
        "door",
        "molding"
    ],
    "wof:name":"Madison Pre-Hung Doors Inc",
    "wof:placetype":"venue"
},
  "geometry": {"coordinates":[-89.37135600000001,42.895383],"type":"Point"}
}