{
  "type": "Feature",
  "properties": {
    "iso:country":"US",
    "sg:address":"1926 S Van Dyke Rd",
    "sg:city":"Appleton",
    "sg:classifiers":[
        {
            "category":"Manufacturing",
            "subcategory":"Tools & Machinery",
            "type":"Manufacturing & Wholesale Goods"
        }
    ],
    "sg:phone":"+1 920 725 7951",
    "sg:postcode":"54914",
    "sg:province":"WI",
    "sg:tags":[
        "shop",
        "machine",
        "machining"
    ],
    "wof:name":"Machining & Repair Svcs LLC",
    "wof:placetype":"venue"
},
  "geometry": {"coordinates":[-88.470031,44.244795],"type":"Point"}
}