{
  "type": "Feature",
  "properties": {
    "iso:country":"US",
    "sg:address":"368 40th St",
    "sg:city":"Clear Lake",
    "sg:classifiers":[
        {
            "category":"Building & Trades",
            "subcategory":"Construction",
            "type":"Services"
        }
    ],
    "sg:phone":"+1 715 263 2977",
    "sg:postcode":"54005",
    "sg:province":"WI",
    "sg:tags":[
        "house"
    ],
    "wof:name":"Dodge Construction",
    "wof:placetype":"venue"
},
  "geometry": {"coordinates":[-92.23939,45.264069],"type":"Point"}
}