{
  "type": "Feature",
  "properties": {
    "iso:country":"US",
    "sg:address":"118 Forest Ave",
    "sg:city":"Kewaskum",
    "sg:classifiers":[
        {
            "category":"Wholesale",
            "subcategory":"Meat",
            "type":"Manufacturing & Wholesale Goods"
        }
    ],
    "sg:phone":"+1 262 626 2710",
    "sg:postcode":"53040",
    "sg:province":"WI",
    "sg:tags":[
        "packer"
    ],
    "wof:name":"Kewaskum Frozen Foods Inc",
    "wof:placetype":"venue"
},
  "geometry": {"coordinates":[-88.22948100000001,43.521378],"type":"Point"}
}