{
  "type": "Feature",
  "properties": {
    "iso:country":"US",
    "sg:address":"2523 Post Rd",
    "sg:city":"Stevens Point",
    "sg:classifiers":[
        {
            "category":"Real Estate",
            "subcategory":"Surveying",
            "type":"Services"
        }
    ],
    "sg:phone":"+1 715 340 5314",
    "sg:postcode":"54481",
    "sg:province":"WI",
    "sg:tags":[
        "surveyor"
    ],
    "wof:name":"Central Staking",
    "wof:placetype":"venue"
},
  "geometry": {"coordinates":[-89.551178,44.488277],"type":"Point"}
}