{
  "type": "Feature",
  "properties": {
    "iso:country":"US",
    "sg:address":"635 S Fancher Rd",
    "sg:city":"Racine",
    "sg:classifiers":[
        {
            "category":"Building & Trades",
            "subcategory":"Construction",
            "type":"Services"
        }
    ],
    "sg:phone":"+1 262 886 4563",
    "sg:postcode":"53406",
    "sg:province":"WI",
    "sg:tags":[
        "carpentry",
        "contractor"
    ],
    "wof:name":"Houdek Contracting",
    "wof:placetype":"venue"
},
  "geometry": {"coordinates":[-87.904758,42.722708],"type":"Point"}
}