{
  "type": "Feature",
  "properties": {
    "iso:country":"US",
    "sg:address":"526 W National Ave",
    "sg:city":"Milwaukee",
    "sg:classifiers":[
        {
            "category":"Structure",
            "subcategory":"Office Building",
            "type":"Public Place"
        }
    ],
    "sg:phone":"+1 414 324 7705",
    "sg:postcode":"53204",
    "sg:province":"WI",
    "sg:tags":[
        "park"
    ],
    "wof:name":"Pachefsky Property",
    "wof:placetype":"venue"
},
  "geometry": {"coordinates":[-87.917168,43.023223],"type":"Point"}
}