{
  "type": "Feature",
  "properties": {
    "iso:country":"US",
    "sg:address":"2201 E Springs Dr",
    "sg:city":"Madison",
    "sg:classifiers":[
        {
            "category":"Home & Garden",
            "subcategory":"Furniture",
            "type":"Retail Goods"
        }
    ],
    "sg:phone":"+1 608 240 0200",
    "sg:postcode":"53704",
    "sg:province":"WI",
    "wof:name":"Slumberland Furniture Inc",
    "wof:placetype":"venue"
},
  "geometry": {"coordinates":[-89.29477300000001,43.126453],"type":"Point"}
}