{
  "type": "Feature",
  "properties": {
    "iso:country":"US",
    "sg:address":"2475 University Ave",
    "sg:city":"Green Bay",
    "sg:classifiers":[
        {
            "category":"Banks & Credit Unions",
            "subcategory":"Bank",
            "type":"Services"
        }
    ],
    "sg:phone":"+1 920 288 0190",
    "sg:postcode":"54302",
    "sg:province":"WI",
    "sg:tags":[
        "financing"
    ],
    "wof:name":"Citi Financial",
    "wof:placetype":"venue"
},
  "geometry": {"coordinates":[-87.959599,44.513334],"type":"Point"}
}