{
  "type": "Feature",
  "properties": {
    "addr:full":"33 Winter St Superior WI 54880",
    "addr:housenumber":"33",
    "addr:postcode":"54880",
    "addr:street":"Winter St",
    "iso:country":"US",
    "sg:address":"33 Winter St",
    "sg:city":"Superior",
    "sg:phone":"+1 715 394 5618",
    "sg:postcode":"54880",
    "sg:province":"WI",
    "sg:tags":[
        "product",
        "petroleum"
    ],
    "sg:website":"www.jefffostertrucking.com",
    "wof:name":"Jeff Foster Trucking",
    "wof:placetype":"venue"
},
  "geometry": {"coordinates":[-92.07990599999999,46.727895],"type":"Point"}
}