{
  "type": "Feature",
  "properties": {
    "addr:full":"3725 N 126th St Brookfield WI 53005",
    "addr:housenumber":"3725",
    "addr:postcode":"53005",
    "addr:street":"N 126Th St",
    "iso:country":"US",
    "sg:address":"3725 N 126th St",
    "sg:city":"Brookfield",
    "sg:classifiers":[
        {
            "category":"Retail",
            "subcategory":"Repair Shop",
            "type":"Services"
        }
    ],
    "sg:phone":"+1 262 781 7550",
    "sg:postcode":"53005",
    "sg:province":"WI",
    "sg:tags":[
        "installs",
        "equipment"
    ],
    "wof:name":"Refrigeration Svc Installation",
    "wof:placetype":"venue"
},
  "geometry": {"coordinates":[-88.069034,43.085104],"type":"Point"}
}