{
  "type": "Feature",
  "properties": {
    "iso:country":"US",
    "sg:address":"368 Pond St",
    "sg:city":"Amherst",
    "sg:classifiers":[
        {
            "category":"Home & Garden",
            "subcategory":"Garden Supply",
            "type":"Retail Goods"
        }
    ],
    "sg:phone":"+1 715 824 5532",
    "sg:postcode":"54406",
    "sg:province":"WI",
    "sg:tags":[
        "florist"
    ],
    "wof:name":"Mittelstedt Floral",
    "wof:placetype":"venue"
},
  "geometry": {"coordinates":[-89.28115200000001,44.4524],"type":"Point"}
}