{
  "type": "Feature",
  "properties": {
    "iso:country":"US",
    "sg:address":"9011 Co Rd Ww",
    "sg:city":"Wisconsin Rapids",
    "sg:classifiers":[
        {
            "category":"Government",
            "subcategory":"Office",
            "type":"Public Place"
        }
    ],
    "sg:phone":"+1 715 424 4880",
    "sg:postcode":"54494",
    "sg:province":"WI",
    "sg:tags":[
        "town"
    ],
    "wof:name":"Town of Grant",
    "wof:placetype":"venue"
},
  "geometry": {"coordinates":[-89.687878,44.359047],"type":"Point"}
}