{
  "type": "Feature",
  "properties": {
    "addr:full":"7996 Co Rd Y Lodi WI 53555",
    "addr:housenumber":"7996",
    "addr:postcode":"53555",
    "addr:street":"Co Rd Y",
    "iso:country":"US",
    "sg:address":"7996 Co Rd Y",
    "sg:city":"Lodi",
    "sg:classifiers":[
        {
            "category":"Shopping",
            "subcategory":"Bicycles & Sporting Goods",
            "type":"Retail Goods"
        }
    ],
    "sg:phone":"+1 608 592 4757",
    "sg:postcode":"53555",
    "sg:province":"WI",
    "wof:name":"Johns Gun Shop",
    "wof:placetype":"venue"
},
  "geometry": {"coordinates":[-89.610786,43.265654],"type":"Point"}
}