{
  "type": "Feature",
  "properties": {
    "addr:full":"900 N 46th St Milwaukee WI 53208",
    "addr:housenumber":"900",
    "addr:postcode":"53208",
    "addr:street":"N 46Th St",
    "iso:country":"US",
    "sg:address":"900 N 46th St",
    "sg:city":"Milwaukee",
    "sg:phone":"+1 414 257 3188",
    "sg:postcode":"53208",
    "sg:province":"WI",
    "sg:tags":[
        "equipment",
        "rental"
    ],
    "wof:name":"American Restaurant Equipment",
    "wof:placetype":"venue"
},
  "geometry": {"coordinates":[-87.971597,43.040963],"type":"Point"}
}