{
  "type": "Feature",
  "properties": {
    "addr:full":"5401 Dorsett Dr Madison WI 53711",
    "addr:housenumber":"5401",
    "addr:postcode":"53711",
    "addr:street":"Dorsett Dr",
    "iso:country":"US",
    "sg:address":"5401 Dorsett Dr",
    "sg:city":"Madison",
    "sg:classifiers":[
        {
            "category":"Real Estate",
            "subcategory":"Real Estate Operator",
            "type":"Services"
        }
    ],
    "sg:phone":"+1 608 271 3445",
    "sg:postcode":"53711",
    "sg:province":"WI",
    "sg:tags":[
        "building",
        "nonresidential"
    ],
    "wof:name":"Oak Park Properties",
    "wof:placetype":"venue"
},
  "geometry": {"coordinates":[-89.46930399999999,43.037839],"type":"Point"}
}