{
  "type": "Feature",
  "properties": {
    "iso:country":"US",
    "sg:address":"820 17th Ave E",
    "sg:city":"Menomonie",
    "sg:classifiers":[
        {
            "category":"Health Services",
            "subcategory":"Nursing And Care Facility",
            "type":"Services"
        }
    ],
    "sg:phone":"+1 715 232 8181",
    "sg:postcode":"54751",
    "sg:province":"WI",
    "sg:tags":[
        "intermediate"
    ],
    "sg:website":"www.ourhouseassisted.com",
    "wof:name":"Our House Assisted Living",
    "wof:placetype":"venue"
},
  "geometry": {"coordinates":[-91.920753,44.867386],"type":"Point"}
}