{
  "type": "Feature",
  "properties": {
    "iso:country":"US",
    "sg:address":"2046 US Hwy 8",
    "sg:city":"St Croix Falls",
    "sg:classifiers":[
        {
            "category":"Building & Trades",
            "subcategory":"Construction",
            "type":"Services"
        }
    ],
    "sg:phone":"+1 715 483 9265",
    "sg:postcode":"54024",
    "sg:province":"WI",
    "sg:tags":[
        "general",
        "contractor"
    ],
    "wof:name":"Valley Custom Homes",
    "wof:placetype":"venue"
},
  "geometry": {"coordinates":[-92.577583,45.397383],"type":"Point"}
}