{
  "type": "Feature",
  "properties": {
    "iso:country":"US",
    "sg:address":"6019 7th Ave",
    "sg:city":"Kenosha",
    "sg:classifiers":[
        {
            "category":"Professional",
            "subcategory":"Management & Consulting",
            "type":"Services"
        },
        {
            "category":"Retail",
            "subcategory":"Funeral Services",
            "type":"Services"
        },
        {
            "category":"Cemetery",
            "type":"Public Place"
        }
    ],
    "sg:phone":"+1 262 654 2136",
    "sg:postcode":"53143",
    "sg:province":"WI",
    "sg:tags":[
        "supply",
        "consultant",
        "crematory",
        "director",
        "plans-pre-arranged",
        "embalmer"
    ],
    "sg:website":"http://www.hansen-lendmanfuneralhome.com",
    "wof:name":"Hansen-Lendman Funeral Home Inc",
    "wof:placetype":"venue"
},
  "geometry": {"coordinates":[-87.818701,42.580646],"type":"Point"}
}