{
  "type": "Feature",
  "properties": {
    "iso:country":"US",
    "sg:address":"911 Sunset Ln",
    "sg:city":"River Falls",
    "sg:classifiers":[
        {
            "category":"Professional",
            "subcategory":"Detective & Security Services",
            "type":"Services"
        }
    ],
    "sg:phone":"+1 715 426 1126",
    "sg:postcode":"54022",
    "sg:province":"WI",
    "wof:name":"Discreet Investigations",
    "wof:placetype":"venue"
},
  "geometry": {"coordinates":[-92.63943,44.865885],"type":"Point"}
}