{
  "type": "Feature",
  "properties": {
    "iso:country":"US",
    "sg:address":"150 E Jefferson St",
    "sg:city":"Spring Green",
    "sg:classifiers":[
        {
            "category":"Personal",
            "subcategory":"Beauty Salon",
            "type":"Services"
        }
    ],
    "sg:phone":"+1 608 588 7449",
    "sg:postcode":"53588",
    "sg:province":"WI",
    "sg:tags":[
        "shop"
    ],
    "wof:name":"Style Station",
    "wof:placetype":"venue"
},
  "geometry": {"coordinates":[-90.06766500000001,43.176767],"type":"Point"}
}