{
  "type": "Feature",
  "properties": {
    "iso:country":"US",
    "sg:address":"3346 State Hwy 13",
    "sg:city":"Wisconsin Dells",
    "sg:classifiers":[
        {
            "category":"Professional",
            "subcategory":"Management & Consulting",
            "type":"Services"
        }
    ],
    "sg:phone":"+1 608 254 8606",
    "sg:postcode":"53965",
    "sg:province":"WI",
    "sg:tags":[
        "manufacturing"
    ],
    "wof:name":"JB Die & Manufacturing",
    "wof:placetype":"venue"
},
  "geometry": {"coordinates":[-89.837569,43.769141],"type":"Point"}
}