{
  "type": "Feature",
  "properties": {
    "iso:country":"US",
    "sg:address":"3541 State Hwy 35",
    "sg:city":"Maiden Rock",
    "sg:classifiers":[
        {
            "category":"Autos & Motor Vehicles",
            "subcategory":"Fuel & Gas Station",
            "type":"Retail Goods"
        }
    ],
    "sg:phone":"+1 715 448 3000",
    "sg:postcode":"54750",
    "sg:province":"WI",
    "sg:tags":[
        "oil"
    ],
    "wof:name":"Park Service & Convenience",
    "wof:placetype":"venue"
},
  "geometry": {"coordinates":[-92.303039,44.555254],"type":"Point"}
}