{
  "type": "Feature",
  "properties": {
    "iso:country":"US",
    "sg:address":"850 Sunnyside Rd",
    "sg:city":"Green Lake",
    "sg:classifiers":[
        {
            "category":"Social Services",
            "subcategory":"Adult Care",
            "type":"Services"
        }
    ],
    "sg:phone":"+1 920 294 1000",
    "sg:postcode":"54941",
    "sg:province":"WI",
    "sg:tags":[
        "residential",
        "real estate"
    ],
    "sg:website":"www.greenlakemanor.com",
    "wof:name":"Green Lake Manor",
    "wof:placetype":"venue"
},
  "geometry": {"coordinates":[-88.92527200000001,43.843959],"type":"Point"}
}