{
  "type": "Feature",
  "properties": {
    "addr:full":"2244 Bluemound Rd Waukesha WI 53186",
    "addr:housenumber":"2244",
    "addr:postcode":"53186",
    "addr:street":"Bluemound Rd",
    "iso:country":"US",
    "sg:address":"2244 Bluemound Rd",
    "sg:city":"Waukesha",
    "sg:classifiers":[
        {
            "category":"Professional",
            "subcategory":"Engineering",
            "type":"Services"
        }
    ],
    "sg:phone":"+1 262 717 9898",
    "sg:postcode":"53186",
    "sg:province":"WI",
    "wof:name":"Precast Engineering Company",
    "wof:placetype":"venue"
},
  "geometry": {"coordinates":[-88.184252,43.036275],"type":"Point"}
}