{
  "type": "Feature",
  "properties": {
    "iso:country":"US",
    "sg:address":"1565 Harrison St",
    "sg:city":"Oshkosh",
    "sg:classifiers":[
        {
            "category":"Building & Trades",
            "subcategory":"Plumbing",
            "type":"Services"
        }
    ],
    "sg:phone":"+1 920 235 6670",
    "sg:postcode":"54901",
    "sg:province":"WI",
    "sg:tags":[
        "conditioning",
        "air",
        "system",
        "contractor"
    ],
    "wof:name":"Central Heating Svc Inc",
    "wof:placetype":"venue"
},
  "geometry": {"coordinates":[-88.53453399999999,44.036477],"type":"Point"}
}