{
  "type": "Feature",
  "properties": {
    "iso:country":"US",
    "sg:address":"202 S Main St",
    "sg:city":"Medford",
    "sg:classifiers":[
        {
            "category":"Retail",
            "subcategory":"Portrait Studio",
            "type":"Services"
        }
    ],
    "sg:phone":"+1 715 748 3779",
    "sg:postcode":"54451",
    "sg:province":"WI",
    "sg:tags":[
        "photo",
        "photography"
    ],
    "wof:name":"Haasenbach Photography",
    "wof:placetype":"venue"
},
  "geometry": {"coordinates":[-90.34436,45.137252],"type":"Point"}
}