{
  "type": "Feature",
  "properties": {
    "addr:full":"181 2nd St S Wisconsin Rapids WI 54494",
    "addr:housenumber":"181",
    "addr:postcode":"54494",
    "addr:street":"2Nd St S",
    "iso:country":"US",
    "sg:address":"181 2nd St S",
    "sg:city":"Wisconsin Rapids",
    "sg:classifiers":[
        {
            "category":"Banks & Credit Unions",
            "subcategory":"Bank",
            "type":"Services"
        }
    ],
    "sg:phone":"+1 715 423 7600",
    "sg:postcode":"54494",
    "sg:province":"WI",
    "sg:website":"www.wcnbank.com",
    "wof:name":"Wood County National Bank",
    "wof:placetype":"venue"
},
  "geometry": {"coordinates":[-89.824698,44.391067],"type":"Point"}
}