{
  "type": "Feature",
  "properties": {
    "addr:full":"735 825th St Hager City WI 54014",
    "addr:housenumber":"735",
    "addr:postcode":"54014",
    "addr:street":"825Th St",
    "iso:country":"US",
    "sg:address":"735 825th St",
    "sg:city":"Hager City",
    "sg:classifiers":[
        {
            "category":"Wholesale",
            "subcategory":"Toys & Hobbies",
            "type":"Manufacturing & Wholesale Goods"
        }
    ],
    "sg:phone":"+1 715 792 5513",
    "sg:postcode":"54014",
    "sg:province":"WI",
    "sg:tags":[
        "firework",
        "merchandise"
    ],
    "wof:name":"Island Fireworks Inc",
    "wof:placetype":"venue"
},
  "geometry": {"coordinates":[-92.54746799999999,44.576952],"type":"Point"}
}