{
  "type": "Feature",
  "properties": {
    "iso:country":"US",
    "sg:address":"780 Packer Dr",
    "sg:city":"Green Bay",
    "sg:classifiers":[
        {
            "category":"Restaurant",
            "type":"Food & Drink"
        }
    ],
    "sg:phone":"+1 920 499 3110",
    "sg:postcode":"54304",
    "sg:province":"WI",
    "sg:tags":[
        "eating"
    ],
    "wof:name":"Bay City Smkhouse In Midway Ht",
    "wof:placetype":"venue"
},
  "geometry": {"coordinates":[-88.057705,44.49938],"type":"Point"}
}