{
  "type": "Feature",
  "properties": {
    "iso:country":"US",
    "sg:address":"126 N Madison St",
    "sg:city":"Green Bay",
    "sg:classifiers":[
        {
            "category":"Professional",
            "subcategory":"Computer Services",
            "type":"Services"
        }
    ],
    "sg:phone":"+1 920 436 4984",
    "sg:postcode":"54301",
    "sg:province":"WI",
    "sg:tags":[
        "related"
    ],
    "wof:name":"Lake Group",
    "wof:placetype":"venue"
},
  "geometry": {"coordinates":[-88.011272,44.513488],"type":"Point"}
}