{
  "type": "Feature",
  "properties": {
    "iso:country":"US",
    "sg:address":"1015 Industrial Dr",
    "sg:city":"Fort Atkinson",
    "sg:classifiers":[
        {
            "category":"Manufacturing",
            "subcategory":"Food",
            "type":"Manufacturing & Wholesale Goods"
        }
    ],
    "sg:phone":"+1 920 674 9700",
    "sg:postcode":"53538",
    "sg:province":"WI",
    "sg:tags":[
        "product",
        "manufacturer"
    ],
    "wof:name":"L D Foods",
    "wof:placetype":"venue"
},
  "geometry": {"coordinates":[-88.850877,42.916008],"type":"Point"}
}