{
  "type": "Feature",
  "properties": {
    "iso:country":"US",
    "sg:address":"2881 N Ridge Rd",
    "sg:city":"Genoa",
    "sg:classifiers":[
        {
            "category":"Wholesale",
            "subcategory":"Farm Supplies",
            "type":"Manufacturing & Wholesale Goods"
        }
    ],
    "sg:phone":"+1 608 689 2930",
    "sg:postcode":"54632",
    "sg:province":"WI",
    "wof:name":"Full Circle Feed",
    "wof:placetype":"venue"
},
  "geometry": {"coordinates":[-91.14308699999999,43.565768],"type":"Point"}
}