{
  "type": "Feature",
  "properties": {
    "iso:country":"US",
    "sg:address":"2312 N Grandview Blvd",
    "sg:city":"Waukesha",
    "sg:classifiers":[
        {
            "category":"Social Services",
            "subcategory":"Adult Care",
            "type":"Services"
        }
    ],
    "sg:phone":"+1 262 547 9550",
    "sg:postcode":"53188",
    "sg:province":"WI",
    "sg:tags":[
        "home",
        "residential"
    ],
    "wof:name":"Christian Familycare Homes Inc",
    "wof:placetype":"venue"
},
  "geometry": {"coordinates":[-88.256083,43.033026],"type":"Point"}
}