{
  "type": "Feature",
  "properties": {
    "addr:full":"4555 Douglas Ave Caledonia WI 53108",
    "addr:housenumber":"4555",
    "addr:postcode":"53108",
    "addr:street":"Douglas Ave",
    "iso:country":"US",
    "sg:address":"4555 Douglas Ave",
    "sg:city":"Caledonia",
    "sg:classifiers":[
        {
            "category":"Restaurant",
            "type":"Food & Drink"
        }
    ],
    "sg:phone":"+1 262 639 6612",
    "sg:postcode":"53108",
    "sg:province":"WI",
    "wof:name":"George Webb Restaurants",
    "wof:placetype":"venue"
},
  "geometry": {"coordinates":[-87.933998,42.816898],"type":"Point"}
}