{
  "type": "Feature",
  "properties": {
    "addr:full":"1822 Keehan Ln Green Bay WI 54311",
    "addr:housenumber":"1822",
    "addr:postcode":"54311",
    "addr:street":"Keehan Ln",
    "iso:country":"US",
    "sg:address":"1822 Keehan Ln",
    "sg:city":"Green Bay",
    "sg:classifiers":[
        {
            "category":"Shopping",
            "subcategory":"Catalog Store",
            "type":"Retail Goods"
        }
    ],
    "sg:phone":"+1 920 469 1185",
    "sg:postcode":"54311",
    "sg:province":"WI",
    "sg:tags":[
        "mail",
        "house"
    ],
    "wof:name":"Victoriana Forever",
    "wof:placetype":"venue"
},
  "geometry": {"coordinates":[-87.96622499999999,44.4686],"type":"Point"}
}