{
  "type": "Feature",
  "properties": {
    "iso:country":"US",
    "sg:address":"3470 N Oakland Ave",
    "sg:city":"Shorewood",
    "sg:classifiers":[
        {
            "category":"Education",
            "subcategory":"Special Training",
            "type":"Public Place"
        }
    ],
    "sg:phone":"+1 262 789 0300",
    "sg:postcode":"53211",
    "sg:province":"WI",
    "sg:tags":[
        "instruction",
        "driving"
    ],
    "wof:name":"Assurance Drivers School",
    "wof:placetype":"venue"
},
  "geometry": {"coordinates":[-87.887587,43.081742],"type":"Point"}
}