{
  "type": "Feature",
  "properties": {
    "iso:country":"US",
    "sg:address":"1800 Patton Pl",
    "sg:city":"Janesville",
    "sg:classifiers":[
        {
            "category":"Wholesale",
            "subcategory":"Machinery & Supplies",
            "type":"Manufacturing & Wholesale Goods"
        }
    ],
    "sg:phone":"+1 608 756 4470",
    "sg:postcode":"53546",
    "sg:province":"WI",
    "sg:tags":[
        "equipment",
        "plastic"
    ],
    "wof:name":"Die-Sep",
    "wof:placetype":"venue"
},
  "geometry": {"coordinates":[-89.053147,42.653151],"type":"Point"}
}