{
  "type": "Feature",
  "properties": {
    "iso:country":"US",
    "sg:address":"4278 Oriole Dr",
    "sg:city":"Lake Geneva",
    "sg:classifiers":[
        {
            "category":"Professional",
            "subcategory":"Business Services",
            "type":"Services"
        }
    ],
    "sg:phone":"+1 262 245 5489",
    "sg:postcode":"53147",
    "sg:province":"WI",
    "wof:name":"Robin Kasson",
    "wof:placetype":"venue"
},
  "geometry": {"coordinates":[-88.51078200000001,42.576558],"type":"Point"}
}