{
  "type": "Feature",
  "properties": {
    "iso:country":"US",
    "sg:address":"1100 W Historic Mitchell St",
    "sg:city":"Milwaukee",
    "sg:classifiers":[
        {
            "category":"Shopping",
            "type":"Retail Goods"
        }
    ],
    "sg:phone":"+1 414 672 1830",
    "sg:postcode":"53204",
    "sg:province":"WI",
    "sg:tags":[
        "wedding",
        "supply"
    ],
    "wof:name":"Lopez Bakery",
    "wof:placetype":"venue"
},
  "geometry": {"coordinates":[-87.926926,43.012288],"type":"Point"}
}