{
  "type": "Feature",
  "properties": {
    "iso:country":"US",
    "sg:address":"2997 10th Ave",
    "sg:city":"Spring Valley",
    "sg:classifiers":[
        {
            "category":"Farming",
            "subcategory":"Dairy Farm",
            "type":"Manufacturing & Wholesale Goods"
        }
    ],
    "sg:phone":"+1 715 772 4596",
    "sg:postcode":"54767",
    "sg:province":"WI",
    "wof:name":"Howard Brahmer",
    "wof:placetype":"venue"
},
  "geometry": {"coordinates":[-92.198089,44.872369],"type":"Point"}
}