{
  "type": "Feature",
  "properties": {
    "addr:full":"1850 Deckner Ave Green Bay WI 54302",
    "addr:housenumber":"1850",
    "addr:postcode":"54302",
    "addr:street":"Deckner Ave",
    "iso:country":"US",
    "sg:address":"1850 Deckner Ave",
    "sg:city":"Green Bay",
    "sg:classifiers":[
        {
            "category":"Home & Garden",
            "subcategory":"Hardware",
            "type":"Retail Goods"
        }
    ],
    "sg:phone":"+1 920 465 6515",
    "sg:postcode":"54302",
    "sg:province":"WI",
    "sg:tags":[
        "pressure",
        "washer",
        "sales"
    ],
    "wof:name":"Pressure Systems Inc",
    "wof:placetype":"venue"
},
  "geometry": {"coordinates":[-87.975956,44.502338],"type":"Point"}
}