{
  "type": "Feature",
  "properties": {
    "iso:country":"US",
    "sg:address":"8329 Jackson Park Blvd",
    "sg:city":"Milwaukee",
    "sg:classifiers":[
        {
            "category":"Real Estate",
            "subcategory":"Real Estate Services",
            "type":"Services"
        },
        {
            "category":"Professional",
            "subcategory":"Business Services",
            "type":"Services"
        },
        {
            "category":"Real Estate",
            "subcategory":"Surveying",
            "type":"Services"
        }
    ],
    "sg:phone":"+1 414 476 9449",
    "sg:postcode":"53213",
    "sg:province":"WI",
    "sg:tags":[
        "commercial",
        "appraisers-business",
        "industrial",
        "appraisers-commercial",
        "appraiser"
    ],
    "wof:name":"Davis Appraisals Inc",
    "wof:placetype":"venue"
},
  "geometry": {"coordinates":[-88.016536,43.059534],"type":"Point"}
}