{
  "type": "Feature",
  "properties": {
    "iso:country":"US",
    "sg:address":"3381 E Puetz Rd",
    "sg:city":"Oak Creek",
    "sg:classifiers":[
        {
            "category":"Social Services",
            "subcategory":"Child Care",
            "type":"Services"
        }
    ],
    "sg:phone":"+1 414 762 8755",
    "sg:postcode":"53154",
    "sg:province":"WI",
    "wof:name":"Grace Luthren Early Chldhd Ctr",
    "wof:placetype":"venue"
},
  "geometry": {"coordinates":[-87.867967,42.886135],"type":"Point"}
}