{
  "type": "Feature",
  "properties": {
    "iso:country":"US",
    "sg:address":"307 Ridge View Trl",
    "sg:city":"Verona",
    "sg:classifiers":[
        {
            "category":"Professional",
            "subcategory":"Business Services",
            "type":"Services"
        }
    ],
    "sg:phone":"+1 608 845 7420",
    "sg:postcode":"53593",
    "sg:province":"WI",
    "sg:tags":[
        "interior",
        "consultant",
        "design",
        "decorator"
    ],
    "wof:name":"Blue Door Interiors LLC",
    "wof:placetype":"venue"
},
  "geometry": {"coordinates":[-89.556313,42.991167],"type":"Point"}
}