{
  "type": "Feature",
  "properties": {
    "addr:full":"1470 E Main St Reedsburg WI 53959",
    "addr:housenumber":"1470",
    "addr:postcode":"53959",
    "addr:street":"E Main St",
    "iso:country":"US",
    "sg:address":"1470 E Main St",
    "sg:city":"Reedsburg",
    "sg:classifiers":[
        {
            "category":"Travel",
            "subcategory":"Hotels & Motels",
            "type":"Entertainment"
        }
    ],
    "sg:phone":"+1 608 524 2888",
    "sg:postcode":"53959",
    "sg:province":"WI",
    "wof:name":"Super 8 Motel",
    "wof:placetype":"venue"
},
  "geometry": {"coordinates":[-89.988017,43.532384],"type":"Point"}
}