{
  "type": "Feature",
  "properties": {
    "iso:country":"US",
    "sg:address":"740 N Randall Ave",
    "sg:city":"Janesville",
    "sg:classifiers":[
        {
            "category":"Social Services",
            "type":"Services"
        }
    ],
    "sg:phone":"+1 608 741 6434",
    "sg:postcode":"53545",
    "sg:province":"WI",
    "sg:tags":[
        "care",
        "center",
        "day"
    ],
    "wof:name":"LSS-Cedar Acres Adult Day",
    "wof:placetype":"venue"
},
  "geometry": {"coordinates":[-89.002931,42.690956],"type":"Point"}
}