{
  "type": "Feature",
  "properties": {
    "iso:country":"US",
    "sg:address":"617 W Pine St",
    "sg:city":"Baraboo",
    "sg:classifiers":[
        {
            "category":"Food & Beverages",
            "subcategory":"Groceries & Convenience Stores",
            "type":"Retail Goods"
        }
    ],
    "sg:phone":"+1 608 356 1067",
    "sg:postcode":"53913",
    "sg:province":"WI",
    "wof:name":"M & G Travel Mart Shell",
    "wof:placetype":"venue"
},
  "geometry": {"coordinates":[-89.768907,43.477078],"type":"Point"}
}