{
  "type": "Feature",
  "properties": {
    "iso:country":"US",
    "sg:address":"802 South St",
    "sg:city":"Plymouth",
    "sg:classifiers":[
        {
            "category":"Professional",
            "type":"Services"
        }
    ],
    "sg:phone":"+1 920 893 1351",
    "sg:postcode":"53073",
    "sg:province":"WI",
    "wof:name":"Fun Cheese Co",
    "wof:placetype":"venue"
},
  "geometry": {"coordinates":[-87.971233,43.738515],"type":"Point"}
}