{
  "type": "Feature",
  "properties": {
    "addr:full":"2840 S Oneida St Green Bay WI 54304",
    "addr:housenumber":"2840",
    "addr:postcode":"54304",
    "addr:street":"S Oneida St",
    "iso:country":"US",
    "sg:address":"2840 S Oneida St",
    "sg:city":"Green Bay",
    "sg:classifiers":[
        {
            "category":"Travel",
            "subcategory":"Hotels & Motels",
            "type":"Entertainment"
        }
    ],
    "sg:phone":"+1 920 494 7887",
    "sg:postcode":"54304",
    "sg:province":"WI",
    "sg:tags":[
        "operation"
    ],
    "wof:name":"Baymont Inns & Suites",
    "wof:placetype":"venue"
},
  "geometry": {"coordinates":[-88.07506600000001,44.473473],"type":"Point"}
}