{
  "type": "Feature",
  "properties": {
    "addr:full":"1233 N Mayfair Rd Ste 211 Milwaukee WI 53226",
    "addr:housenumber":"1233",
    "addr:postcode":"53226",
    "addr:street":"N Mayfair Rd Ste 211",
    "iso:country":"US",
    "sg:address":"1233 N Mayfair Rd Ste 211",
    "sg:city":"Milwaukee",
    "sg:classifiers":[
        {
            "category":"Banks & Credit Unions",
            "subcategory":"Investment Brokerage",
            "type":"Services"
        },
        {
            "category":"Banks & Credit Unions",
            "subcategory":"Bank",
            "type":"Services"
        },
        {
            "category":"Banks & Credit Unions",
            "subcategory":"Financial Services",
            "type":"Services"
        }
    ],
    "sg:phone":"+1 414 778 1091",
    "sg:postcode":"53226",
    "sg:province":"WI",
    "sg:tags":[
        "retirement",
        "transfer",
        "broker",
        "agent",
        "plan",
        "annuity",
        "stock",
        "insurance",
        "bond"
    ],
    "wof:name":"The Investment Company Inc",
    "wof:placetype":"venue"
},
  "geometry": {"coordinates":[-88.04741300000001,43.04571],"type":"Point"}
}