{
  "type": "Feature",
  "properties": {
    "addr:full":"2740 Davids Star Dr Jackson WI 53037",
    "addr:housenumber":"2740",
    "addr:postcode":"53037",
    "addr:street":"Davids Star Dr",
    "iso:country":"US",
    "sg:address":"2740 Davids Star Dr",
    "sg:city":"Jackson",
    "sg:classifiers":[
        {
            "category":"Organizations",
            "subcategory":"Religious Organization",
            "type":"Services"
        }
    ],
    "sg:phone":"+1 262 375 1843",
    "sg:postcode":"53037",
    "sg:province":"WI",
    "sg:tags":[
        "church"
    ],
    "wof:name":"David's Star Ev Lutheran Chr",
    "wof:placetype":"venue"
},
  "geometry": {"coordinates":[-88.107426,43.288792],"type":"Point"}
}