{
  "type": "Feature",
  "properties": {
    "iso:country":"US",
    "sg:address":"12506 Spring St",
    "sg:city":"Sturtevant",
    "sg:classifiers":[
        {
            "category":"Building & Trades",
            "subcategory":"Construction",
            "type":"Services"
        }
    ],
    "sg:phone":"+1 262 884 6892",
    "sg:postcode":"53177",
    "sg:province":"WI",
    "sg:tags":[
        "home",
        "family"
    ],
    "wof:name":"Kyle Construction",
    "wof:placetype":"venue"
},
  "geometry": {"coordinates":[-87.93657899999999,42.736704],"type":"Point"}
}