{
  "type": "Feature",
  "properties": {
    "iso:country":"US",
    "sg:address":"1220 E Locust St Apt 209",
    "sg:city":"Milwaukee",
    "sg:classifiers":[
        {
            "category":"Wholesale",
            "subcategory":"Books, Periodicals, & Newspapers",
            "type":"Manufacturing & Wholesale Goods"
        }
    ],
    "sg:phone":"+1 515 988 5790",
    "sg:postcode":"53212",
    "sg:province":"WI",
    "sg:tags":[
        "publisher",
        "book"
    ],
    "wof:name":"Rescue Press",
    "wof:placetype":"venue"
},
  "geometry": {"coordinates":[-87.895776,43.071128],"type":"Point"}
}