{
  "type": "Feature",
  "properties": {
    "iso:country":"US",
    "sg:address":"83 Warbler Way",
    "sg:city":"Watertown",
    "sg:classifiers":[
        {
            "category":"Building & Trades",
            "subcategory":"Cleaning & Sanitation",
            "type":"Services"
        }
    ],
    "sg:phone":"+1 920 988 5468",
    "sg:postcode":"53098",
    "sg:province":"WI",
    "sg:tags":[
        "maintenance"
    ],
    "wof:name":"St John Maintance & Repair Svc",
    "wof:placetype":"venue"
},
  "geometry": {"coordinates":[-88.613563,43.202422],"type":"Point"}
}