{
  "type": "Feature",
  "properties": {
    "iso:country":"US",
    "sg:address":"20808 State Hwy 58",
    "sg:city":"Cazenovia",
    "sg:classifiers":[
        {
            "category":"Farming",
            "subcategory":"Dairy Farm",
            "type":"Manufacturing & Wholesale Goods"
        }
    ],
    "sg:phone":"+1 608 585 3702",
    "sg:postcode":"53924",
    "sg:province":"WI",
    "wof:name":"Rodney Gochenaur Farm",
    "wof:placetype":"venue"
},
  "geometry": {"coordinates":[-90.241955,43.396285],"type":"Point"}
}