{
  "type": "Feature",
  "properties": {
    "addr:full":"175 E Wisconsin Ave Oconomowoc WI 53066",
    "addr:housenumber":"175",
    "addr:postcode":"53066",
    "addr:street":"E Wisconsin Ave",
    "iso:country":"US",
    "sg:address":"175 E Wisconsin Ave",
    "sg:city":"Oconomowoc",
    "sg:classifiers":[
        {
            "category":"Banks & Credit Unions",
            "subcategory":"Bank",
            "type":"Services"
        }
    ],
    "sg:phone":"+1 262 560 9790",
    "sg:postcode":"53066",
    "sg:province":"WI",
    "sg:tags":[
        "loan"
    ],
    "wof:name":"Lake & Country Financial Svc",
    "wof:placetype":"venue"
},
  "geometry": {"coordinates":[-88.498644,43.111208],"type":"Point"}
}