{
  "type": "Feature",
  "properties": {
    "iso:country":"US",
    "sg:address":"120 Main St",
    "sg:city":"Camp Douglas",
    "sg:classifiers":[
        {
            "category":"Bars & Pubs",
            "type":"Food & Drink"
        }
    ],
    "sg:phone":"+1 608 427 3221",
    "sg:postcode":"54618",
    "sg:province":"WI",
    "wof:name":"End Zone",
    "wof:placetype":"venue"
},
  "geometry": {"coordinates":[-90.26864999999999,43.920111],"type":"Point"}
}