{
  "type": "Feature",
  "properties": {
    "addr:full":"215 N 28th Ave Wausau WI 54401",
    "addr:housenumber":"215",
    "addr:postcode":"54401",
    "addr:street":"N 28Th Ave",
    "iso:country":"US",
    "sg:address":"215 N 28th Ave",
    "sg:city":"Wausau",
    "sg:classifiers":[
        {
            "category":"Health Services",
            "subcategory":"Doctor",
            "type":"Services"
        }
    ],
    "sg:phone":"+1 715 847 2866",
    "sg:postcode":"54401",
    "sg:province":"WI",
    "sg:tags":[
        "physician",
        "surgeon"
    ],
    "wof:name":"U W Cancer Ctr",
    "wof:placetype":"venue"
},
  "geometry": {"coordinates":[-89.670783,44.96287],"type":"Point"}
}