{
  "type": "Feature",
  "properties": {
    "addr:full":"800 Park Ave Beaver Dam WI 53916",
    "addr:housenumber":"800",
    "addr:postcode":"53916",
    "addr:street":"Park Ave",
    "iso:country":"US",
    "sg:address":"800 Park Ave",
    "sg:city":"Beaver Dam",
    "sg:classifiers":[
        {
            "category":"Shopping",
            "subcategory":"Shoes",
            "type":"Retail Goods"
        }
    ],
    "sg:phone":"+1 920 887 3530",
    "sg:postcode":"53916",
    "sg:province":"WI",
    "sg:tags":[
        "shoe",
        "store"
    ],
    "wof:name":"Payless Shoe Source",
    "wof:placetype":"venue"
},
  "geometry": {"coordinates":[-88.82167099999999,43.45625],"type":"Point"}
}