{
  "type": "Feature",
  "properties": {
    "iso:country":"US",
    "sg:address":"1601 Airport Rd",
    "sg:city":"Waukesha",
    "sg:classifiers":[
        {
            "category":"Wholesale",
            "subcategory":"Machinery & Supplies",
            "type":"Manufacturing & Wholesale Goods"
        },
        {
            "category":"Manufacturing",
            "subcategory":"Motor Vehicles & Parts",
            "type":"Manufacturing & Wholesale Goods"
        }
    ],
    "sg:phone":"+1 262 896 3500",
    "sg:postcode":"53188",
    "sg:province":"WI",
    "sg:tags":[
        "equipment",
        "industrial",
        "truck",
        "auto"
    ],
    "sg:website":"www.forceamerica.com",
    "wof:name":"Force America Inc",
    "wof:placetype":"venue"
},
  "geometry": {"coordinates":[-88.233378,43.027063],"type":"Point"}
}