{
  "type": "Feature",
  "properties": {
    "iso:country":"US",
    "sg:address":"220 N Francis St",
    "sg:city":"Brillion",
    "sg:classifiers":[
        {
            "category":"Banks & Credit Unions",
            "subcategory":"Bank",
            "type":"Services"
        }
    ],
    "sg:phone":"+1 920 756 2119",
    "sg:postcode":"54110",
    "sg:province":"WI",
    "sg:website":"www.bacu.com",
    "wof:name":"Best Advantage Credit Union",
    "wof:placetype":"venue"
},
  "geometry": {"coordinates":[-88.06158499999999,44.178026],"type":"Point"}
}