{
  "type": "Feature",
  "properties": {
    "iso:country":"US",
    "sg:address":"3443 S 58th St",
    "sg:city":"Milwaukee",
    "sg:classifiers":[
        {
            "category":"Government",
            "subcategory":"Office",
            "type":"Public Place"
        }
    ],
    "sg:phone":"+1 414 321 5672",
    "sg:postcode":"53219",
    "sg:province":"WI",
    "sg:tags":[
        "general"
    ],
    "wof:name":"Lola Administrative Services",
    "wof:placetype":"venue"
},
  "geometry": {"coordinates":[-87.986611,42.981926],"type":"Point"}
}