{
  "type": "Feature",
  "properties": {
    "iso:country":"US",
    "sg:address":"6631 Church St",
    "sg:city":"Vesper",
    "sg:classifiers":[
        {
            "category":"Organizations",
            "subcategory":"Religious Organization",
            "type":"Services"
        }
    ],
    "sg:phone":"+1 715 569 4412",
    "sg:postcode":"54489",
    "sg:province":"WI",
    "sg:tags":[
        "church"
    ],
    "wof:name":"St James Catholic Church",
    "wof:placetype":"venue"
},
  "geometry": {"coordinates":[-89.973549,44.4854],"type":"Point"}
}