{
  "type": "Feature",
  "properties": {
    "iso:country":"US",
    "sg:address":"8617 N Port Washington Rd",
    "sg:city":"Milwaukee",
    "sg:classifiers":[
        {
            "category":"Restaurant",
            "type":"Food & Drink"
        }
    ],
    "sg:menulink":"http://www.allmenus.com/wi/fox-point/97852-outback-steakhouse/menu/",
    "sg:phone":"+1 414 228 8859",
    "sg:postcode":"53217",
    "sg:province":"WI",
    "sg:tags":[
        "american",
        "steakhouse"
    ],
    "wof:name":"Outback Steakhouse",
    "wof:placetype":"venue"
},
  "geometry": {"coordinates":[-87.91246599999999,43.173456],"type":"Point"}
}