{
  "type": "Feature",
  "properties": {
    "iso:country":"US",
    "sg:address":"6566 Rio Rd",
    "sg:city":"Sheboygan Falls",
    "sg:classifiers":[
        {
            "category":"Shopping",
            "subcategory":"Bicycles & Sporting Goods",
            "type":"Retail Goods"
        }
    ],
    "sg:phone":"+1 920 892 4699",
    "sg:postcode":"53085",
    "sg:province":"WI",
    "sg:tags":[
        "outfitter"
    ],
    "wof:name":"Ridge Runner Outfitters",
    "wof:placetype":"venue"
},
  "geometry": {"coordinates":[-87.911459,43.778886],"type":"Point"}
}