{
  "type": "Feature",
  "properties": {
    "addr:full":"308 E Main St Twin Lakes WI 53181",
    "addr:housenumber":"308",
    "addr:postcode":"53181",
    "addr:street":"E Main St",
    "iso:country":"US",
    "sg:address":"308 E Main St",
    "sg:city":"Twin Lakes",
    "sg:classifiers":[
        {
            "category":"Shopping",
            "subcategory":"Optical Goods",
            "type":"Retail Goods"
        }
    ],
    "sg:phone":"+1 262 877 3999",
    "sg:postcode":"53181",
    "sg:province":"WI",
    "sg:tags":[
        "optician"
    ],
    "wof:name":"Eye Site",
    "wof:placetype":"venue"
},
  "geometry": {"coordinates":[-88.25094900000001,42.53175],"type":"Point"}
}