{
  "type": "Feature",
  "properties": {
    "iso:country":"US",
    "sg:address":"24231 4th St",
    "sg:city":"Trempealeau",
    "sg:classifiers":[
        {
            "category":"Education",
            "subcategory":"School",
            "type":"Public Place"
        }
    ],
    "sg:phone":"+1 608 534 6391",
    "sg:postcode":"54661",
    "sg:province":"WI",
    "sg:website":"www.getschools.k12.wi.us",
    "wof:name":"Gale-Ettrick-Trempealeau Middl",
    "wof:placetype":"venue"
},
  "geometry": {"coordinates":[-91.437147,44.005629],"type":"Point"}
}