{
  "type": "Feature",
  "properties": {
    "iso:country":"US",
    "sg:address":"9041 N Deerwood Dr",
    "sg:city":"Milwaukee",
    "sg:classifiers":[
        {
            "category":"Professional",
            "type":"Services"
        }
    ],
    "sg:phone":"+1 414 355 5935",
    "sg:postcode":"53209",
    "sg:province":"WI",
    "wof:name":"Javis Timbers LLC",
    "wof:placetype":"venue"
},
  "geometry": {"coordinates":[-87.964415,43.179374],"type":"Point"}
}