{
  "type": "Feature",
  "properties": {
    "iso:country":"US",
    "sg:address":"1821 Conde St",
    "sg:city":"Janesville",
    "sg:classifiers":[
        {
            "category":"Education",
            "subcategory":"School",
            "type":"Public Place"
        }
    ],
    "sg:phone":"+1 608 743 6700",
    "sg:postcode":"53546",
    "sg:province":"WI",
    "wof:name":"Lincoln Elementary School",
    "wof:placetype":"venue"
},
  "geometry": {"coordinates":[-89.043393,42.653419],"type":"Point"}
}