{
  "type": "Feature",
  "properties": {
    "addr:full":"2533 Jefferson Rd Neosho WI 53059",
    "addr:housenumber":"2533",
    "addr:postcode":"53059",
    "addr:street":"Jefferson Rd",
    "iso:country":"US",
    "sg:address":"2533 Jefferson Rd",
    "sg:city":"Neosho",
    "sg:classifiers":[
        {
            "category":"Retail",
            "subcategory":"Laundry & Dry Cleaning",
            "type":"Services"
        }
    ],
    "sg:phone":"+1 920 625 2290",
    "sg:postcode":"53059",
    "sg:province":"WI",
    "sg:tags":[
        "cleaners",
        "rug",
        "carpet"
    ],
    "wof:name":"Carpet Care Assoc",
    "wof:placetype":"venue"
},
  "geometry": {"coordinates":[-88.478779,43.289735],"type":"Point"}
}