{
  "type": "Feature",
  "properties": {
    "iso:country":"US",
    "sg:address":"321 E College Ave",
    "sg:city":"Appleton",
    "sg:classifiers":[
        {
            "category":"Restaurant",
            "type":"Food & Drink"
        }
    ],
    "sg:phone":"+1 920 830 2030",
    "sg:postcode":"54911",
    "sg:province":"WI",
    "wof:name":"Taste Of Thai",
    "wof:placetype":"venue"
},
  "geometry": {"coordinates":[-88.401235,44.261741],"type":"Point"}
}