{
  "type": "Feature",
  "properties": {
    "iso:country":"US",
    "sg:address":"1259 Wayland St",
    "sg:city":"Beaver Dam",
    "sg:classifiers":[
        {
            "category":"Building & Trades",
            "subcategory":"Construction",
            "type":"Services"
        }
    ],
    "sg:phone":"+1 920 420 5857",
    "sg:postcode":"53916",
    "sg:province":"WI",
    "sg:tags":[
        "contractor"
    ],
    "wof:name":"C A B Construction",
    "wof:placetype":"venue"
},
  "geometry": {"coordinates":[-88.826295,43.472345],"type":"Point"}
}