{
  "type": "Feature",
  "properties": {
    "iso:country":"US",
    "sg:address":"5920 S Oak Rd",
    "sg:city":"West Bend",
    "sg:classifiers":[
        {
            "category":"Professional",
            "subcategory":"Management & Consulting",
            "type":"Services"
        }
    ],
    "sg:phone":"+1 262 438 0041",
    "sg:postcode":"53095",
    "sg:province":"WI",
    "sg:tags":[
        "roofing",
        "consultant"
    ],
    "wof:name":"Rams",
    "wof:placetype":"venue"
},
  "geometry": {"coordinates":[-88.120695,43.403912],"type":"Point"}
}