{
  "type": "Feature",
  "properties": {
    "iso:country":"US",
    "sg:address":"64 State Hwy 139",
    "sg:city":"Long Lake",
    "sg:classifiers":[
        {
            "category":"Home & Garden",
            "subcategory":"Building Materials",
            "type":"Retail Goods"
        }
    ],
    "sg:phone":"+1 715 674 3448",
    "sg:postcode":"54542",
    "sg:province":"WI",
    "wof:name":"Mel's General Store",
    "wof:placetype":"venue"
},
  "geometry": {"coordinates":[-88.653678,45.975691],"type":"Point"}
}