{
  "type": "Feature",
  "properties": {
    "iso:country":"US",
    "sg:address":"3921 S 76th St",
    "sg:city":"Milwaukee",
    "sg:classifiers":[
        {
            "category":"Health Services",
            "subcategory":"Chiropractor",
            "type":"Services"
        }
    ],
    "sg:phone":"+1 414 545 2121",
    "sg:postcode":"53220",
    "sg:province":"WI",
    "wof:name":"LA Blanc Chiropractic Clinic",
    "wof:placetype":"venue"
},
  "geometry": {"coordinates":[-88.00807,42.972984],"type":"Point"}
}