{
  "type": "Feature",
  "properties": {
    "iso:country":"US",
    "sg:address":"2670 S Ashland Ave",
    "sg:city":"Green Bay",
    "sg:classifiers":[
        {
            "category":"Professional",
            "subcategory":"Employment Agencies",
            "type":"Services"
        }
    ],
    "sg:phone":"+1 920 884 7070",
    "sg:postcode":"54304",
    "sg:province":"WI",
    "sg:tags":[
        "opportunity"
    ],
    "wof:name":"Dell Technical Group",
    "wof:placetype":"venue"
},
  "geometry": {"coordinates":[-88.06374599999999,44.47303],"type":"Point"}
}