{
  "type": "Feature",
  "properties": {
    "iso:country":"US",
    "sg:address":"3143 Southwood Dr",
    "sg:city":"Racine",
    "sg:classifiers":[
        {
            "category":"Arts & Performance",
            "subcategory":"Theater",
            "type":"Entertainment"
        }
    ],
    "sg:phone":"+1 262 554 1506",
    "sg:postcode":"53406",
    "sg:province":"WI",
    "sg:tags":[
        "bureau"
    ],
    "wof:name":"Zeahl Entertainment Prdctns",
    "wof:placetype":"venue"
},
  "geometry": {"coordinates":[-87.841734,42.695159],"type":"Point"}
}