{
  "type": "Feature",
  "properties": {
    "iso:country":"US",
    "sg:address":"1956 Energy Dr",
    "sg:city":"East Troy",
    "sg:classifiers":[
        {
            "category":"Freight",
            "type":"Transportation"
        }
    ],
    "sg:phone":"+1 262 642 3366",
    "sg:postcode":"53120",
    "sg:province":"WI",
    "sg:tags":[
        "commercial",
        "storage",
        "special"
    ],
    "wof:name":"S & G Self Storage",
    "wof:placetype":"venue"
},
  "geometry": {"coordinates":[-88.39001,42.790748],"type":"Point"}
}