{
  "type": "Feature",
  "properties": {
    "iso:country":"US",
    "sg:address":"634 Mayflower Ave",
    "sg:city":"Sheboygan",
    "sg:classifiers":[
        {
            "category":"Organizations",
            "subcategory":"Membership Organization",
            "type":"Services"
        }
    ],
    "sg:phone":"+1 920 452 7909",
    "sg:postcode":"53083",
    "sg:province":"WI",
    "wof:name":"United States Power Squad",
    "wof:placetype":"venue"
},
  "geometry": {"coordinates":[-87.71085100000001,43.777107],"type":"Point"}
}