{
  "type": "Feature",
  "properties": {
    "iso:country":"US",
    "sg:address":"31417 Lake St",
    "sg:city":"Burlington",
    "sg:classifiers":[
        {
            "category":"Professional",
            "subcategory":"Business Services",
            "type":"Services"
        }
    ],
    "sg:phone":"+1 262 767 9670",
    "sg:postcode":"53105",
    "sg:province":"WI",
    "sg:tags":[
        "appraiser"
    ],
    "wof:name":"De Rosia Appraisal Svc",
    "wof:placetype":"venue"
},
  "geometry": {"coordinates":[-88.251223,42.685378],"type":"Point"}
}