{
  "type": "Feature",
  "properties": {
    "iso:country":"US",
    "sg:address":"1250 E Prospect Ave",
    "sg:city":"Marion",
    "sg:classifiers":[
        {
            "category":"Restaurant",
            "type":"Food & Drink"
        }
    ],
    "sg:phone":"+1 715 754 2200",
    "sg:postcode":"54950",
    "sg:province":"WI",
    "wof:name":"Zig's Hide-Away",
    "wof:placetype":"venue"
},
  "geometry": {"coordinates":[-88.867514,44.671167],"type":"Point"}
}