{
  "type": "Feature",
  "properties": {
    "addr:full":"213 S Central Ave Richland Center WI 53581",
    "addr:housenumber":"213",
    "addr:postcode":"53581",
    "addr:street":"S Central Ave",
    "iso:country":"US",
    "sg:address":"213 S Central Ave",
    "sg:city":"Richland Center",
    "sg:classifiers":[
        {
            "category":"Real Estate",
            "subcategory":"Real Estate Operator",
            "type":"Services"
        }
    ],
    "sg:phone":"+1 608 647 6676",
    "sg:postcode":"53581",
    "sg:province":"WI",
    "sg:tags":[
        "apartment"
    ],
    "wof:name":"Park Apartments",
    "wof:placetype":"venue"
},
  "geometry": {"coordinates":[-90.385374,43.334523],"type":"Point"}
}