{
  "type": "Feature",
  "properties": {
    "iso:country":"US",
    "sg:address":"1818 S Park St",
    "sg:city":"Madison",
    "sg:classifiers":[
        {
            "category":"Home & Garden",
            "subcategory":"Garden Supply",
            "type":"Retail Goods"
        }
    ],
    "sg:phone":"+1 608 251 1659",
    "sg:postcode":"53715",
    "sg:province":"WI",
    "sg:tags":[
        "landscaping",
        "equipment"
    ],
    "wof:name":"Tri-Star Mulch",
    "wof:placetype":"venue"
},
  "geometry": {"coordinates":[-89.39412900000001,43.046727],"type":"Point"}
}