{
  "type": "Feature",
  "properties": {
    "iso:country":"US",
    "sg:address":"1862 State Hwy 54",
    "sg:city":"Luxemburg",
    "sg:classifiers":[
        {
            "category":"Home & Garden",
            "subcategory":"Building Materials",
            "type":"Retail Goods"
        }
    ],
    "sg:phone":"+1 920 845 5463",
    "sg:postcode":"54217",
    "sg:province":"WI",
    "sg:tags":[
        "lumber"
    ],
    "wof:name":"Weidner Hardwood Lumber",
    "wof:placetype":"venue"
},
  "geometry": {"coordinates":[-87.66323,44.555988],"type":"Point"}
}