{
  "type": "Feature",
  "properties": {
    "iso:country":"US",
    "sg:address":"5623 Broad St",
    "sg:city":"Greendale",
    "sg:classifiers":[
        {
            "category":"Real Estate",
            "subcategory":"Developer",
            "type":"Services"
        }
    ],
    "sg:phone":"+1 414 423 1187",
    "sg:postcode":"53129",
    "sg:province":"WI",
    "wof:name":"Grandhaven LLC",
    "wof:placetype":"venue"
},
  "geometry": {"coordinates":[-87.996084,42.940994],"type":"Point"}
}