{
  "type": "Feature",
  "properties": {
    "iso:country":"US",
    "sg:address":"320 E Main St",
    "sg:city":"Gilman",
    "sg:classifiers":[
        {
            "category":"Health Services",
            "subcategory":"Doctor",
            "type":"Services"
        }
    ],
    "sg:phone":"+1 715 447 8293",
    "sg:postcode":"54433",
    "sg:province":"WI",
    "sg:tags":[
        "clinic"
    ],
    "wof:name":"Gilman Clinic",
    "wof:placetype":"venue"
},
  "geometry": {"coordinates":[-90.810588,45.166446],"type":"Point"}
}