{
  "type": "Feature",
  "properties": {
    "iso:country":"US",
    "sg:address":"1040 Village Green Ct",
    "sg:city":"Green Bay",
    "sg:classifiers":[
        {
            "category":"Building & Trades",
            "subcategory":"Construction",
            "type":"Services"
        }
    ],
    "sg:phone":"+1 920 494 0198",
    "sg:postcode":"54313",
    "sg:province":"WI",
    "sg:tags":[
        "hanging",
        "contractor"
    ],
    "wof:name":"Fisher Ralph Wallpaper & Pntg",
    "wof:placetype":"venue"
},
  "geometry": {"coordinates":[-88.127747,44.524522],"type":"Point"}
}