{
  "type": "Feature",
  "properties": {
    "iso:country":"US",
    "sg:address":"1445 Yates Ave",
    "sg:city":"Beloit",
    "sg:classifiers":[
        {
            "category":"Professional",
            "type":"Services"
        }
    ],
    "sg:phone":"+1 608 313 9145",
    "sg:postcode":"53511",
    "sg:province":"IL",
    "wof:name":"Blackhawk Machine Tool LLC",
    "wof:placetype":"venue"
},
  "geometry": {"coordinates":[-89.017835,42.515705],"type":"Point"}
}