{
  "type": "Feature",
  "properties": {
    "iso:country":"US",
    "sg:address":"5480 Co Rd Tt",
    "sg:city":"Sheboygan Falls",
    "sg:classifiers":[
        {
            "category":"Government",
            "subcategory":"Fire Station",
            "type":"Public Place"
        }
    ],
    "sg:phone":"+1 920 467 4876",
    "sg:postcode":"53085",
    "sg:province":"WI",
    "sg:tags":[
        "department"
    ],
    "wof:name":"Sheboygan Falls Fire Dept",
    "wof:placetype":"venue"
},
  "geometry": {"coordinates":[-87.850318,43.739134],"type":"Point"}
}