{
  "type": "Feature",
  "properties": {
    "iso:country":"US",
    "sg:address":"1000 Grove St",
    "sg:city":"Bangor",
    "sg:classifiers":[
        {
            "category":"Wholesale",
            "subcategory":"Machinery & Supplies",
            "type":"Manufacturing & Wholesale Goods"
        }
    ],
    "sg:phone":"+1 608 486 2535",
    "sg:postcode":"54614",
    "sg:province":"WI",
    "sg:tags":[
        "contractor"
    ],
    "wof:name":"Thicke's Heavy Equipment Sales",
    "wof:placetype":"venue"
},
  "geometry": {"coordinates":[-90.980952,43.891218],"type":"Point"}
}