{
  "type": "Feature",
  "properties": {
    "addr:full":"2273 Orchard Dr Pulaski WI 54162",
    "addr:housenumber":"2273",
    "addr:postcode":"54162",
    "addr:street":"Orchard Dr",
    "iso:country":"US",
    "sg:address":"2273 Orchard Dr",
    "sg:city":"Pulaski",
    "sg:phone":"+1 920 822 5203",
    "sg:postcode":"54162",
    "sg:province":"WI",
    "sg:tags":[
        "farm",
        "corn"
    ],
    "wof:name":"Tyczkowski Teofil",
    "wof:placetype":"venue"
},
  "geometry": {"coordinates":[-88.344629,44.659036],"type":"Point"}
}