{
  "type": "Feature",
  "properties": {
    "iso:country":"US",
    "sg:address":"2685 Maple Ridge Rd",
    "sg:city":"Platteville",
    "sg:classifiers":[
        {
            "category":"Farming",
            "subcategory":"Dairy Farm",
            "type":"Manufacturing & Wholesale Goods"
        }
    ],
    "sg:phone":"+1 608 348 9021",
    "sg:postcode":"53818",
    "sg:province":"WI",
    "wof:name":"A Klar Dairy Inc",
    "wof:placetype":"venue"
},
  "geometry": {"coordinates":[-90.545034,42.709032],"type":"Point"}
}