{
  "type": "Feature",
  "properties": {
    "iso:country":"US",
    "sg:address":"1113 Rockdale St",
    "sg:city":"Green Bay",
    "sg:classifiers":[
        {
            "category":"Building & Trades",
            "subcategory":"Cleaning & Sanitation",
            "type":"Services"
        }
    ],
    "sg:phone":"+1 920 499 5505",
    "sg:postcode":"54304",
    "sg:province":"WI",
    "sg:tags":[
        "janitor"
    ],
    "wof:name":"Masterkleen",
    "wof:placetype":"venue"
},
  "geometry": {"coordinates":[-88.050465,44.506414],"type":"Point"}
}