{
  "type": "Feature",
  "properties": {
    "iso:country":"US",
    "sg:address":"730 N Old World 3rd St",
    "sg:city":"Milwaukee",
    "sg:classifiers":[
        {
            "category":"Restaurant",
            "type":"Food & Drink"
        }
    ],
    "sg:phone":"+1 414 319 1190",
    "sg:postcode":"53203",
    "sg:province":"WI",
    "sg:tags":[
        "middle",
        "american",
        "mediterranean",
        "eastern"
    ],
    "sg:website":"http://www.velvetroommilwaukee.com",
    "wof:name":"The Velvet Room",
    "wof:placetype":"venue"
},
  "geometry": {"coordinates":[-87.914513,43.039644],"type":"Point"}
}