{
  "type": "Feature",
  "properties": {
    "iso:country":"US",
    "sg:address":"1096 Windsong Ln",
    "sg:city":"Onalaska",
    "sg:classifiers":[
        {
            "category":"Building & Trades",
            "subcategory":"Cleaning & Sanitation",
            "type":"Services"
        }
    ],
    "sg:phone":"+1 608 781 4919",
    "sg:postcode":"54650",
    "sg:province":"WI",
    "sg:tags":[
        "residential",
        "commercial"
    ],
    "wof:name":"BMW Cleaning",
    "wof:placetype":"venue"
},
  "geometry": {"coordinates":[-91.16186999999999,43.873345],"type":"Point"}
}