{
  "type": "Feature",
  "properties": {
    "addr:full":"1309 4th Ave Stevens Point WI 54481",
    "addr:housenumber":"1309",
    "addr:postcode":"54481",
    "addr:street":"4Th Ave",
    "iso:country":"US",
    "sg:address":"1309 4th Ave",
    "sg:city":"Stevens Point",
    "sg:classifiers":[
        {
            "category":"Building & Trades",
            "subcategory":"Construction",
            "type":"Services"
        }
    ],
    "sg:phone":"+1 715 342 0359",
    "sg:postcode":"54481",
    "sg:province":"WI",
    "sg:tags":[
        "general",
        "contractor"
    ],
    "wof:name":"Tessen Construction",
    "wof:placetype":"venue"
},
  "geometry": {"coordinates":[-89.579784,44.528761],"type":"Point"}
}