{
  "type": "Feature",
  "properties": {
    "addr:full":"1044 Meadow St Watertown WI 53094",
    "addr:housenumber":"1044",
    "addr:postcode":"53094",
    "addr:street":"Meadow St",
    "iso:country":"US",
    "sg:address":"1044 Meadow St",
    "sg:city":"Watertown",
    "sg:classifiers":[
        {
            "category":"Manufacturing",
            "subcategory":"Jewelry",
            "type":"Manufacturing & Wholesale Goods"
        }
    ],
    "sg:phone":"+1 920 206 1385",
    "sg:postcode":"53094",
    "sg:province":"WI",
    "sg:tags":[
        "precious",
        "metal",
        "mfg"
    ],
    "wof:name":"Sheikh Corparate",
    "wof:placetype":"venue"
},
  "geometry": {"coordinates":[-88.74936700000001,43.195675],"type":"Point"}
}