{
  "type": "Feature",
  "properties": {
    "addr:full":"6150 Mineral Point Rd Madison WI 53705",
    "addr:housenumber":"6150",
    "addr:postcode":"53705",
    "addr:street":"Mineral Point Rd",
    "iso:country":"US",
    "sg:address":"6150 Mineral Point Rd",
    "sg:city":"Madison",
    "sg:classifiers":[
        {
            "category":"Deli",
            "type":"Food & Drink"
        },
        {
            "category":"Bagels",
            "type":"Food & Drink"
        },
        {
            "category":"Coffee & Tea",
            "type":"Food & Drink"
        }
    ],
    "sg:menulink":"http://www.allmenus.com/wi/madison/41010-brueggers/menu/",
    "sg:phone":"+1 608 236 0607",
    "sg:postcode":"53705",
    "sg:province":"WI",
    "sg:tags":[
        "wrap",
        "soup",
        "american",
        "sandwich",
        "salad"
    ],
    "wof:name":"Bruegger's",
    "wof:placetype":"venue"
},
  "geometry": {"coordinates":[-89.485631,43.060882],"type":"Point"}
}