{
  "type": "Feature",
  "properties": {
    "iso:country":"US",
    "sg:address":"1525 Sun Valley Dr",
    "sg:city":"Beloit",
    "sg:classifiers":[
        {
            "category":"Shopping",
            "type":"Retail Goods"
        }
    ],
    "sg:phone":"+1 608 362 0353",
    "sg:postcode":"53511",
    "sg:province":"WI",
    "sg:tags":[
        "merchandise"
    ],
    "wof:name":"J & S Pet Store Inc",
    "wof:placetype":"venue"
},
  "geometry": {"coordinates":[-89.065094,42.518928],"type":"Point"}
}