{
  "type": "Feature",
  "properties": {
    "iso:country":"US",
    "sg:address":"200 State St",
    "sg:city":"Beloit",
    "sg:classifiers":[
        {
            "category":"Manufacturing",
            "subcategory":"Tools & Machinery",
            "type":"Manufacturing & Wholesale Goods"
        },
        {
            "category":"Autos & Motor Vehicles",
            "subcategory":"Auto Supplies",
            "type":"Retail Goods"
        },
        {
            "category":"Wholesale",
            "subcategory":"Machinery & Supplies",
            "type":"Manufacturing & Wholesale Goods"
        },
        {
            "category":"Building & Trades",
            "subcategory":"Electrical",
            "type":"Services"
        }
    ],
    "sg:phone":"+1 608 364 8800",
    "sg:postcode":"53511",
    "sg:province":"WI",
    "sg:tags":[
        "gear",
        "power",
        "transmission",
        "automobile",
        "generator",
        "equipment",
        "cutting",
        "part"
    ],
    "sg:website":"http://www.grovegear.com",
    "wof:name":"Regal-Beloit Corporation",
    "wof:placetype":"venue"
},
  "geometry": {"coordinates":[-89.036171,42.49778],"type":"Point"}
}