{
  "type": "Feature",
  "properties": {
    "iso:country":"US",
    "sg:address":"301 S College Ave",
    "sg:city":"Fox Lake",
    "sg:classifiers":[
        {
            "category":"Social Services",
            "subcategory":"Child Care",
            "type":"Services"
        }
    ],
    "sg:phone":"+1 920 928 6700",
    "sg:postcode":"53933",
    "sg:province":"WI",
    "sg:tags":[
        "day"
    ],
    "wof:name":"Punkin Patch",
    "wof:placetype":"venue"
},
  "geometry": {"coordinates":[-88.90935899999999,43.563185],"type":"Point"}
}