{
  "type": "Feature",
  "properties": {
    "addr:full":"5151 Co Rd J Bangor WI 54614",
    "addr:housenumber":"5151",
    "addr:postcode":"54614",
    "addr:street":"Co Rd J",
    "iso:country":"US",
    "sg:address":"5151 Co Rd J",
    "sg:city":"Bangor",
    "sg:classifiers":[
        {
            "category":"Building & Trades",
            "subcategory":"Plumbing",
            "type":"Services"
        }
    ],
    "sg:phone":"+1 608 486 2234",
    "sg:postcode":"54614",
    "sg:province":"WI",
    "sg:tags":[
        "contractor"
    ],
    "wof:name":"Schmitz Services",
    "wof:placetype":"venue"
},
  "geometry": {"coordinates":[-90.920069,43.909506],"type":"Point"}
}