{
  "type": "Feature",
  "properties": {
    "iso:country":"US",
    "sg:address":"11575 W Theodore Trecker Way",
    "sg:city":"Milwaukee",
    "sg:classifiers":[
        {
            "category":"Professional",
            "subcategory":"Management & Consulting",
            "type":"Services"
        },
        {
            "category":"Professional",
            "subcategory":"Employment Agencies",
            "type":"Services"
        }
    ],
    "sg:phone":"+1 414 453 9545",
    "sg:postcode":"53214",
    "sg:province":"WI",
    "sg:tags":[
        "consultant",
        "search",
        "executive",
        "opportunity",
        "contractor"
    ],
    "sg:website":"http://www.eagleinc.net",
    "wof:name":"Eagle Technology Group, Inc.",
    "wof:placetype":"venue"
},
  "geometry": {"coordinates":[-88.056679,43.023652],"type":"Point"}
}