{
  "type": "Feature",
  "properties": {
    "iso:country":"US",
    "sg:address":"5826 W Lincoln Ave",
    "sg:city":"Milwaukee",
    "sg:classifiers":[
        {
            "category":"Personal",
            "subcategory":"Beauty Salon",
            "type":"Services"
        }
    ],
    "sg:phone":"+1 414 541 5060",
    "sg:postcode":"53219",
    "sg:province":"WI",
    "sg:tags":[
        "shop"
    ],
    "wof:name":"Image Oasis Salon",
    "wof:placetype":"venue"
},
  "geometry": {"coordinates":[-87.98598200000001,43.003007],"type":"Point"}
}