{
  "type": "Feature",
  "properties": {
    "iso:country":"US",
    "sg:address":"17540 Mariner Ct",
    "sg:city":"Brookfield",
    "sg:classifiers":[
        {
            "category":"Building & Trades",
            "subcategory":"Construction",
            "type":"Services"
        }
    ],
    "sg:phone":"+1 262 783 5033",
    "sg:postcode":"53045",
    "sg:province":"WI",
    "sg:tags":[
        "home",
        "builder"
    ],
    "wof:name":"Dale G Mierow Homes LTD",
    "wof:placetype":"venue"
},
  "geometry": {"coordinates":[-88.130335,43.084507],"type":"Point"}
}