{
  "type": "Feature",
  "properties": {
    "iso:country":"US",
    "sg:address":"14725 Walpine Ln",
    "sg:city":"Blue River",
    "sg:classifiers":[
        {
            "category":"Farming",
            "subcategory":"Dairy Farm",
            "type":"Manufacturing & Wholesale Goods"
        }
    ],
    "sg:phone":"+1 608 536 3714",
    "sg:postcode":"53518",
    "sg:province":"WI",
    "wof:name":"Steve Walther Farm",
    "wof:placetype":"venue"
},
  "geometry": {"coordinates":[-90.574137,43.322897],"type":"Point"}
}