{
  "type": "Feature",
  "properties": {
    "iso:country":"US",
    "sg:address":"1147 Alex Ct",
    "sg:city":"Hubertus",
    "sg:classifiers":[
        {
            "category":"Real Estate",
            "subcategory":"Real Estate Agent",
            "type":"Services"
        }
    ],
    "sg:phone":"+1 262 628 1847",
    "sg:postcode":"53033",
    "sg:province":"WI",
    "wof:name":"Fieldstone Realty",
    "wof:placetype":"venue"
},
  "geometry": {"coordinates":[-88.245131,43.229029],"type":"Point"}
}