{
  "type": "Feature",
  "properties": {
    "iso:country":"US",
    "sg:address":"6219 Kilpatrick Ln",
    "sg:city":"Madison",
    "sg:classifiers":[
        {
            "category":"Professional",
            "subcategory":"Employment Agencies",
            "type":"Services"
        }
    ],
    "sg:phone":"+1 608 222 0014",
    "sg:postcode":"53718",
    "sg:province":"WI",
    "wof:name":"Auby & Associates",
    "wof:placetype":"venue"
},
  "geometry": {"coordinates":[-89.270958,43.085381],"type":"Point"}
}