{
  "type": "Feature",
  "properties": {
    "iso:country":"US",
    "sg:address":"1803 Truax Blvd",
    "sg:city":"Eau Claire",
    "sg:classifiers":[
        {
            "category":"Real Estate",
            "subcategory":"Real Estate Operator",
            "type":"Services"
        }
    ],
    "sg:phone":"+1 715 552 3424",
    "sg:postcode":"54703",
    "sg:province":"WI",
    "sg:tags":[
        "building",
        "apartment"
    ],
    "wof:name":"Horizon Management Group",
    "wof:placetype":"venue"
},
  "geometry": {"coordinates":[-91.532861,44.836563],"type":"Point"}
}