{
  "type": "Feature",
  "properties": {
    "iso:country":"US",
    "sg:address":"1702 Birchwood St",
    "sg:city":"Delavan",
    "sg:classifiers":[
        {
            "category":"Organizations",
            "subcategory":"Religious Organization",
            "type":"Services"
        }
    ],
    "sg:phone":"+1 262 728 9237",
    "sg:postcode":"53115",
    "sg:province":"WI",
    "wof:name":"Living World Assembly of God",
    "wof:placetype":"venue"
},
  "geometry": {"coordinates":[-88.677717,42.628507],"type":"Point"}
}