{
  "type": "Feature",
  "properties": {
    "iso:country":"US",
    "sg:address":"2909 Sheridan Rd",
    "sg:city":"Kenosha",
    "sg:classifiers":[
        {
            "category":"Retail",
            "subcategory":"Funeral Services",
            "type":"Services"
        }
    ],
    "sg:phone":"+1 262 657 3442",
    "sg:postcode":"53140",
    "sg:province":"WI",
    "sg:tags":[
        "cemetery"
    ],
    "wof:name":"St George Cemetery",
    "wof:placetype":"venue"
},
  "geometry": {"coordinates":[-87.825401,42.611318],"type":"Point"}
}