{
  "type": "Feature",
  "properties": {
    "addr:full":"419 W Olson St Blanchardville WI 53516",
    "addr:housenumber":"419",
    "addr:postcode":"53516",
    "addr:street":"W Olson St",
    "iso:country":"US",
    "sg:address":"419 W Olson St",
    "sg:city":"Blanchardville",
    "sg:classifiers":[
        {
            "category":"Farming",
            "subcategory":"Livestock Farm",
            "type":"Manufacturing & Wholesale Goods"
        }
    ],
    "sg:phone":"+1 608 523 4251",
    "sg:postcode":"53516",
    "sg:province":"WI",
    "sg:tags":[
        "beef",
        "feedlot",
        "cattle"
    ],
    "wof:name":"Meade John",
    "wof:placetype":"venue"
},
  "geometry": {"coordinates":[-89.86750499999999,42.809667],"type":"Point"}
}