{
  "type": "Feature",
  "properties": {
    "addr:full":"713 N Summit St Spooner WI 54801",
    "addr:housenumber":"713",
    "addr:postcode":"54801",
    "addr:street":"N Summit St",
    "iso:country":"US",
    "sg:address":"713 N Summit St",
    "sg:city":"Spooner",
    "sg:classifiers":[
        {
            "category":"Government",
            "subcategory":"Office",
            "type":"Public Place"
        }
    ],
    "sg:phone":"+1 715 635 2808",
    "sg:postcode":"54801",
    "sg:province":"WI",
    "sg:tags":[
        "housing",
        "program"
    ],
    "wof:name":"Housing Athrty of Cty Sponner",
    "wof:placetype":"venue"
},
  "geometry": {"coordinates":[-91.887703,45.829807],"type":"Point"}
}