{
  "type": "Feature",
  "properties": {
    "iso:country":"US",
    "sg:address":"1477 Ashley Ct",
    "sg:city":"Green Bay",
    "sg:classifiers":[
        {
            "category":"Building & Trades",
            "subcategory":"Construction",
            "type":"Services"
        }
    ],
    "sg:phone":"+1 920 499 8947",
    "sg:postcode":"54313",
    "sg:province":"WI",
    "sg:tags":[
        "house"
    ],
    "wof:name":"Oleniczak Construction",
    "wof:placetype":"venue"
},
  "geometry": {"coordinates":[-88.08714500000001,44.506669],"type":"Point"}
}