{
  "type": "Feature",
  "properties": {
    "iso:country":"US",
    "sg:address":"229 Hillcrest Ct",
    "sg:city":"Sheboygan Falls",
    "sg:classifiers":[
        {
            "category":"Building & Trades",
            "subcategory":"Construction",
            "type":"Services"
        }
    ],
    "sg:phone":"+1 920 467 9994",
    "sg:postcode":"53085",
    "sg:province":"WI",
    "sg:tags":[
        "house"
    ],
    "wof:name":"JC Home Improvements",
    "wof:placetype":"venue"
},
  "geometry": {"coordinates":[-87.811576,43.723034],"type":"Point"}
}