{
  "type": "Feature",
  "properties": {
    "iso:country":"US",
    "sg:address":"5921 Tower Ave",
    "sg:city":"Superior",
    "sg:classifiers":[
        {
            "category":"Manufacturing",
            "subcategory":"Printing",
            "type":"Manufacturing & Wholesale Goods"
        }
    ],
    "sg:phone":"+1 715 392 4600",
    "sg:postcode":"54880",
    "sg:province":"WI",
    "sg:tags":[
        "commercial"
    ],
    "wof:name":"Rich Designs",
    "wof:placetype":"venue"
},
  "geometry": {"coordinates":[-92.104367,46.667197],"type":"Point"}
}