{
  "type": "Feature",
  "properties": {
    "iso:country":"US",
    "sg:address":"2713 Sleepy Hollow Rd",
    "sg:city":"Kewaunee",
    "sg:classifiers":[
        {
            "category":"Building & Trades",
            "subcategory":"Construction",
            "type":"Services"
        }
    ],
    "sg:phone":"+1 920 388 4263",
    "sg:postcode":"54216",
    "sg:province":"WI",
    "sg:tags":[
        "insulation",
        "contractor"
    ],
    "wof:name":"Insulators Inc",
    "wof:placetype":"venue"
},
  "geometry": {"coordinates":[-87.66413,44.423552],"type":"Point"}
}