{
  "type": "Feature",
  "properties": {
    "addr:full":"4971 Lakeview Ave Hubertus WI 53033",
    "addr:housenumber":"4971",
    "addr:postcode":"53033",
    "addr:street":"Lakeview Ave",
    "iso:country":"US",
    "sg:address":"4971 Lakeview Ave",
    "sg:city":"Hubertus",
    "sg:classifiers":[
        {
            "category":"Building & Trades",
            "subcategory":"Construction",
            "type":"Services"
        }
    ],
    "sg:phone":"+1 262 628 8292",
    "sg:postcode":"53033",
    "sg:province":"WI",
    "sg:tags":[
        "tile",
        "dealer"
    ],
    "wof:name":"Ramzyn Interiors",
    "wof:placetype":"venue"
},
  "geometry": {"coordinates":[-88.283331,43.244239],"type":"Point"}
}