{
  "type": "Feature",
  "properties": {
    "iso:country":"US",
    "sg:address":"995 Badger Cir",
    "sg:city":"Grafton",
    "sg:classifiers":[
        {
            "category":"Wholesale",
            "subcategory":"Machinery & Supplies",
            "type":"Manufacturing & Wholesale Goods"
        }
    ],
    "sg:phone":"+1 262 375 4100",
    "sg:postcode":"53024",
    "sg:province":"WI",
    "sg:tags":[
        "food",
        "equipment",
        "processing",
        "packaging"
    ],
    "sg:website":"www.stockamerica.com",
    "wof:name":"Stock America Inc",
    "wof:placetype":"venue"
},
  "geometry": {"coordinates":[-87.93502599999999,43.32396],"type":"Point"}
}