{
  "type": "Feature",
  "properties": {
    "iso:country":"US",
    "sg:address":"705 Grand Ave",
    "sg:city":"Random Lake",
    "sg:classifiers":[
        {
            "category":"Organizations",
            "subcategory":"Religious Organization",
            "type":"Services"
        }
    ],
    "sg:phone":"+1 920 994 4043",
    "sg:postcode":"53075",
    "sg:province":"WI",
    "wof:name":"Random Lake",
    "wof:placetype":"venue"
},
  "geometry": {"coordinates":[-87.970816,43.553235],"type":"Point"}
}