{
  "type": "Feature",
  "properties": {
    "iso:country":"US",
    "sg:address":"12 Marina Dr",
    "sg:city":"Superior",
    "sg:classifiers":[
        {
            "category":"Shopping",
            "subcategory":"Gifts & Souvenirs",
            "type":"Retail Goods"
        }
    ],
    "sg:phone":"+1 715 394 5550",
    "sg:postcode":"54880",
    "sg:province":"WI",
    "sg:tags":[
        "shop"
    ],
    "wof:name":"Gifts Galore",
    "wof:placetype":"venue"
},
  "geometry": {"coordinates":[-92.066592,46.722303],"type":"Point"}
}