{
  "type": "Feature",
  "properties": {
    "iso:country":"US",
    "sg:address":"2678 S 108th St",
    "sg:city":"Milwaukee",
    "sg:classifiers":[
        {
            "category":"Restaurant",
            "type":"Food & Drink"
        }
    ],
    "sg:menulink":"http://www.allmenus.com/wi/west-allis/137870-boston-market/menu/",
    "sg:phone":"+1 414 329 0909",
    "sg:postcode":"53227",
    "sg:province":"WI",
    "sg:tags":[
        "barbecue",
        "american",
        "soup"
    ],
    "wof:name":"Boston Market",
    "wof:placetype":"venue"
},
  "geometry": {"coordinates":[-88.04636499999999,42.995934],"type":"Point"}
}