{
  "type": "Feature",
  "properties": {
    "addr:full":"1132 Gohres St La Crosse WI 54603",
    "addr:housenumber":"1132",
    "addr:postcode":"54603",
    "addr:street":"Gohres St",
    "iso:country":"US",
    "sg:address":"1132 Gohres St",
    "sg:city":"La Crosse",
    "sg:classifiers":[
        {
            "category":"Home & Garden",
            "subcategory":"Furniture",
            "type":"Retail Goods"
        }
    ],
    "sg:phone":"+1 608 304 2337",
    "sg:postcode":"54603",
    "sg:province":"WI",
    "wof:name":"Bed & Mattress Wholesale",
    "wof:placetype":"venue"
},
  "geometry": {"coordinates":[-91.240168,43.849122],"type":"Point"}
}