{
  "type": "Feature",
  "properties": {
    "iso:country":"US",
    "sg:address":"734 S Shore Dr",
    "sg:city":"Hubertus",
    "sg:classifiers":[
        {
            "category":"Retail",
            "subcategory":"Repair Shop",
            "type":"Services"
        }
    ],
    "sg:phone":"+1 262 628 1139",
    "sg:postcode":"53033",
    "sg:province":"WI",
    "sg:tags":[
        "television"
    ],
    "wof:name":"Town & Country TV",
    "wof:placetype":"venue"
},
  "geometry": {"coordinates":[-88.203992,43.217025],"type":"Point"}
}