{
  "type": "Feature",
  "properties": {
    "iso:country":"US",
    "sg:address":"214 Diedrich St",
    "sg:city":"Kaukauna",
    "sg:classifiers":[
        {
            "category":"Professional",
            "type":"Services"
        }
    ],
    "sg:phone":"+1 920 759 9445",
    "sg:postcode":"54130",
    "sg:province":"WI",
    "wof:name":"Telsmith",
    "wof:placetype":"venue"
},
  "geometry": {"coordinates":[-88.277652,44.286268],"type":"Point"}
}