{
  "type": "Feature",
  "properties": {
    "addr:full":"1701 N Spring St Beaver Dam WI 53916",
    "addr:housenumber":"1701",
    "addr:postcode":"53916",
    "addr:street":"N Spring St",
    "iso:country":"US",
    "sg:address":"1701 N Spring St",
    "sg:city":"Beaver Dam",
    "sg:classifiers":[
        {
            "category":"Insurance",
            "subcategory":"Insurance Agent",
            "type":"Services"
        }
    ],
    "sg:phone":"+1 920 885 9115",
    "sg:postcode":"53916",
    "sg:province":"WI",
    "wof:name":"State Farm Insurance",
    "wof:placetype":"venue"
},
  "geometry": {"coordinates":[-88.819104,43.482616],"type":"Point"}
}