{
  "type": "Feature",
  "properties": {
    "addr:full":"739 N Harding St Oconomowoc WI 53066",
    "addr:housenumber":"739",
    "addr:postcode":"53066",
    "addr:street":"N Harding St",
    "iso:country":"US",
    "sg:address":"739 N Harding St",
    "sg:city":"Oconomowoc",
    "sg:classifiers":[
        {
            "category":"Social Services",
            "subcategory":"Child Care",
            "type":"Services"
        }
    ],
    "sg:phone":"+1 262 569 9109",
    "sg:postcode":"53066",
    "sg:province":"WI",
    "wof:name":"Great Beginnings",
    "wof:placetype":"venue"
},
  "geometry": {"coordinates":[-88.487268,43.118884],"type":"Point"}
}