{
  "type": "Feature",
  "properties": {
    "iso:country":"US",
    "sg:address":"9 Rustic Ct",
    "sg:city":"Appleton",
    "sg:classifiers":[
        {
            "category":"Health Services",
            "subcategory":"Doctor",
            "type":"Services"
        }
    ],
    "sg:phone":"+1 920 727 8040",
    "sg:postcode":"54911",
    "sg:province":"WI",
    "sg:tags":[
        "medical"
    ],
    "wof:name":"William D Moore MD Inc",
    "wof:placetype":"venue"
},
  "geometry": {"coordinates":[-88.384998,44.296426],"type":"Point"}
}