{
  "type": "Feature",
  "properties": {
    "iso:country":"US",
    "sg:address":"11425 W Lake Park Dr",
    "sg:city":"Milwaukee",
    "sg:classifiers":[
        {
            "category":"Professional",
            "subcategory":"Computer Services",
            "type":"Services"
        }
    ],
    "sg:phone":"+1 414 973 4300",
    "sg:postcode":"53224",
    "sg:province":"WI",
    "sg:tags":[
        "electronic",
        "datum",
        "business",
        "interchange"
    ],
    "wof:name":"ARI Network Services Inc",
    "wof:placetype":"venue"
},
  "geometry": {"coordinates":[-88.060119,43.158266],"type":"Point"}
}