{
  "type": "Feature",
  "properties": {
    "iso:country":"US",
    "sg:address":"843 Taft St",
    "sg:city":"Oregon",
    "sg:classifiers":[
        {
            "category":"Building & Trades",
            "subcategory":"Construction",
            "type":"Services"
        }
    ],
    "sg:phone":"+1 608 835 9799",
    "sg:postcode":"53575",
    "sg:province":"WI",
    "sg:tags":[
        "roofing",
        "contractor"
    ],
    "wof:name":"Blatterman Roofing Inc",
    "wof:placetype":"venue"
},
  "geometry": {"coordinates":[-89.369584,42.898574],"type":"Point"}
}