{
  "type": "Feature",
  "properties": {
    "iso:country":"US",
    "sg:address":"4845 S Brookdale Dr",
    "sg:city":"Milwaukee",
    "sg:classifiers":[
        {
            "category":"Social Services",
            "type":"Services"
        }
    ],
    "sg:phone":"+1 414 858 9400",
    "sg:postcode":"53228",
    "sg:province":"WI",
    "sg:website":"www.comfortkeepers.com",
    "wof:name":"Comfort Keepers",
    "wof:placetype":"venue"
},
  "geometry": {"coordinates":[-88.03530499999999,42.957009],"type":"Point"}
}