{
  "type": "Feature",
  "properties": {
    "addr:full":"28171 Epic Ave Tomah WI 54660",
    "addr:housenumber":"28171",
    "addr:postcode":"54660",
    "addr:street":"Epic Ave",
    "iso:country":"US",
    "sg:address":"28171 Epic Ave",
    "sg:city":"Tomah",
    "sg:classifiers":[
        {
            "category":"Retail",
            "subcategory":"Repair Shop",
            "type":"Services"
        }
    ],
    "sg:phone":"+1 608 372 3838",
    "sg:postcode":"54660",
    "sg:province":"WI",
    "wof:name":"R & R Lock Shop",
    "wof:placetype":"venue"
},
  "geometry": {"coordinates":[-90.43407999999999,44.037405],"type":"Point"}
}