{
  "type": "Feature",
  "properties": {
    "iso:country":"US",
    "sg:address":"510 Lincoln St",
    "sg:city":"Nelson",
    "sg:classifiers":[
        {
            "category":"Autos & Motor Vehicles",
            "subcategory":"Automobile Sales",
            "type":"Retail Goods"
        }
    ],
    "sg:phone":"+1 715 673 4894",
    "sg:postcode":"54756",
    "sg:province":"WI",
    "sg:tags":[
        "snowmobile"
    ],
    "wof:name":"R J's Fast Track",
    "wof:placetype":"venue"
},
  "geometry": {"coordinates":[-92.00791700000001,44.424148],"type":"Point"}
}