{
  "type": "Feature",
  "properties": {
    "iso:country":"US",
    "sg:address":"5609 N Co Rd F",
    "sg:city":"Janesville",
    "sg:classifiers":[
        {
            "category":"Building & Trades",
            "subcategory":"Construction",
            "type":"Services"
        }
    ],
    "sg:phone":"+1 608 756 5665",
    "sg:postcode":"53545",
    "sg:province":"WI",
    "sg:tags":[
        "contractor"
    ],
    "wof:name":"Jak Builders",
    "wof:placetype":"venue"
},
  "geometry": {"coordinates":[-89.066403,42.749055],"type":"Point"}
}