{
  "type": "Feature",
  "properties": {
    "iso:country":"US",
    "sg:address":"5585 Guilford Rd",
    "sg:city":"Madison",
    "sg:classifiers":[
        {
            "category":"Restaurant",
            "type":"Food & Drink"
        }
    ],
    "sg:phone":"+1 608 848 7828",
    "sg:postcode":"53711",
    "sg:province":"WI",
    "sg:tags":[
        "eating"
    ],
    "wof:name":"Big Mikes Super Subs",
    "wof:placetype":"venue"
},
  "geometry": {"coordinates":[-89.427658,43.019164],"type":"Point"}
}