{
  "type": "Feature",
  "properties": {
    "iso:country":"US",
    "sg:address":"413 Charles St",
    "sg:city":"De Pere",
    "sg:classifiers":[
        {
            "category":"Organizations",
            "subcategory":"Religious Organization",
            "type":"Services"
        }
    ],
    "sg:phone":"+1 920 347 9047",
    "sg:postcode":"54115",
    "sg:province":"WI",
    "sg:tags":[
        "church"
    ],
    "sg:website":"www.calvarydepere.lifewaylink.com",
    "wof:name":"Calvary Baptist Church",
    "wof:placetype":"venue"
},
  "geometry": {"coordinates":[-88.059355,44.447834],"type":"Point"}
}