{
  "type": "Feature",
  "properties": {
    "iso:country":"US",
    "sg:address":"9825 Saratoga Dr",
    "sg:city":"Caledonia",
    "sg:classifiers":[
        {
            "category":"Freight",
            "type":"Transportation"
        }
    ],
    "sg:phone":"+1 414 762 0685",
    "sg:postcode":"53108",
    "sg:province":"WI",
    "sg:tags":[
        "trucking"
    ],
    "wof:name":"Seager Trucking",
    "wof:placetype":"venue"
},
  "geometry": {"coordinates":[-87.906711,42.837886],"type":"Point"}
}