{
  "type": "Feature",
  "properties": {
    "addr:full":"2540 Co Rd Mn Cottage Grove WI 53527",
    "addr:housenumber":"2540",
    "addr:postcode":"53527",
    "addr:street":"Co Rd",
    "iso:country":"US",
    "sg:address":"2540 Co Rd Mn",
    "sg:city":"Cottage Grove",
    "sg:classifiers":[
        {
            "category":"Retail",
            "subcategory":"Animal Services",
            "type":"Services"
        }
    ],
    "sg:phone":"+1 608 839 3411",
    "sg:postcode":"53527",
    "sg:province":"WI",
    "sg:tags":[
        "pet",
        "boarding",
        "sitting"
    ],
    "wof:name":"Rose-Run Kennels",
    "wof:placetype":"venue"
},
  "geometry": {"coordinates":[-89.204976,43.021566],"type":"Point"}
}