{
  "type": "Feature",
  "properties": {
    "addr:full":"3381 Basil Dr Madison WI 53704",
    "addr:housenumber":"3381",
    "addr:postcode":"53704",
    "addr:street":"Basil Dr",
    "iso:country":"US",
    "sg:address":"3381 Basil Dr",
    "sg:city":"Madison",
    "sg:classifiers":[
        {
            "category":"Professional",
            "subcategory":"Art Services",
            "type":"Services"
        }
    ],
    "sg:phone":"+1 608 245 1859",
    "sg:postcode":"53704",
    "sg:province":"WI",
    "sg:tags":[
        "commercial",
        "design"
    ],
    "wof:name":"Studio427",
    "wof:placetype":"venue"
},
  "geometry": {"coordinates":[-89.31607200000001,43.139826],"type":"Point"}
}