{
  "type": "Feature",
  "properties": {
    "addr:full":"1127 E Oklahoma Ave Milwaukee WI 53207",
    "addr:housenumber":"1127",
    "addr:postcode":"53207",
    "addr:street":"E Oklahoma Ave",
    "iso:country":"US",
    "sg:address":"1127 E Oklahoma Ave",
    "sg:city":"Milwaukee",
    "sg:classifiers":[
        {
            "category":"Autos & Motor Vehicles",
            "subcategory":"Fuel & Gas Station",
            "type":"Retail Goods"
        },
        {
            "category":"Retail",
            "subcategory":"Car Wash",
            "type":"Services"
        }
    ],
    "sg:phone":"+1 414 489 0101",
    "sg:postcode":"53207",
    "sg:province":"WI",
    "sg:website":"http://www.mobil.com",
    "wof:name":"Sunrise Mobile # 2 & Carwash",
    "wof:placetype":"venue"
},
  "geometry": {"coordinates":[-87.895233,42.988306],"type":"Point"}
}