{
  "type": "Feature",
  "properties": {
    "iso:country":"US",
    "sg:address":"1104 Washington St",
    "sg:city":"Manitowoc",
    "sg:classifiers":[
        {
            "category":"Wholesale",
            "subcategory":"Sporting Goods",
            "type":"Manufacturing & Wholesale Goods"
        },
        {
            "category":"Shopping",
            "subcategory":"Bicycles & Sporting Goods",
            "type":"Retail Goods"
        }
    ],
    "sg:phone":"+1 920 683 1764",
    "sg:postcode":"54220",
    "sg:province":"WI",
    "sg:tags":[
        "paint",
        "game",
        "ball"
    ],
    "wof:name":"Paul's Paintball",
    "wof:placetype":"venue"
},
  "geometry": {"coordinates":[-87.66332,44.088965],"type":"Point"}
}