{
  "type": "Feature",
  "properties": {
    "iso:country":"US",
    "sg:address":"913 Madison Ave",
    "sg:city":"Fort Atkinson",
    "sg:classifiers":[
        {
            "category":"Personal",
            "subcategory":"Beauty Salon",
            "type":"Services"
        }
    ],
    "sg:phone":"+1 920 563 7656",
    "sg:postcode":"53538",
    "sg:province":"WI",
    "sg:tags":[
        "shop"
    ],
    "wof:name":"Hair It Is",
    "wof:placetype":"venue"
},
  "geometry": {"coordinates":[-88.84997,42.934539],"type":"Point"}
}