{
  "type": "Feature",
  "properties": {
    "iso:country":"US",
    "sg:address":"419 W Cottage Grove Rd",
    "sg:city":"Cottage Grove",
    "sg:classifiers":[
        {
            "category":"Banks & Credit Unions",
            "subcategory":"Bank",
            "type":"Services"
        }
    ],
    "sg:phone":"+1 608 839 3977",
    "sg:postcode":"53527",
    "sg:province":"WI",
    "wof:name":"Bank Of Sun Prairie",
    "wof:placetype":"venue"
},
  "geometry": {"coordinates":[-89.208727,43.086714],"type":"Point"}
}