{
  "type": "Feature",
  "properties": {
    "iso:country":"US",
    "sg:address":"8276 State Hwy 73",
    "sg:city":"Greenwood",
    "sg:classifiers":[
        {
            "category":"Farming",
            "subcategory":"Dairy Farm",
            "type":"Manufacturing & Wholesale Goods"
        }
    ],
    "sg:phone":"+1 715 267 7315",
    "sg:postcode":"54437",
    "sg:province":"WI",
    "wof:name":"Charaden Farms",
    "wof:placetype":"venue"
},
  "geometry": {"coordinates":[-90.598854,44.71576],"type":"Point"}
}