{
  "type": "Feature",
  "properties": {
    "iso:country":"US",
    "sg:address":"2722 Highland Dr",
    "sg:city":"Cambridge",
    "sg:classifiers":[
        {
            "category":"Professional",
            "subcategory":"Business Services",
            "type":"Services"
        }
    ],
    "sg:phone":"+1 608 423 3097",
    "sg:postcode":"53523",
    "sg:province":"WI",
    "wof:name":"Country Comforts",
    "wof:placetype":"venue"
},
  "geometry": {"coordinates":[-89.032249,42.998931],"type":"Point"}
}