{
  "type": "Feature",
  "properties": {
    "iso:country":"US",
    "sg:address":"5601 Odana Rd",
    "sg:city":"Madison",
    "sg:classifiers":[
        {
            "category":"Arts & Performance",
            "subcategory":"Theater",
            "type":"Entertainment"
        }
    ],
    "sg:phone":"+1 608 271 1190",
    "sg:postcode":"53719",
    "sg:province":"WI",
    "sg:tags":[
        "live",
        "music"
    ],
    "sg:website":"www.openbooking.com",
    "wof:name":"A Open Booking Entertainment",
    "wof:placetype":"venue"
},
  "geometry": {"coordinates":[-89.474024,43.049917],"type":"Point"}
}