{
  "type": "Feature",
  "properties": {
    "iso:country":"US",
    "sg:address":"7360 540th St",
    "sg:city":"Menomonie",
    "sg:classifiers":[
        {
            "category":"Freight",
            "type":"Transportation"
        }
    ],
    "sg:phone":"+1 715 834 2337",
    "sg:postcode":"54751",
    "sg:province":"WI",
    "wof:name":"H T Transport Inc",
    "wof:placetype":"venue"
},
  "geometry": {"coordinates":[-91.888327,44.945258],"type":"Point"}
}