{
  "type": "Feature",
  "properties": {
    "addr:full":"223 W Grand Ave Port Washington WI 53074",
    "addr:housenumber":"223",
    "addr:postcode":"53074",
    "addr:street":"W Grand Ave",
    "iso:country":"US",
    "sg:address":"223 W Grand Ave",
    "sg:city":"Port Washington",
    "sg:classifiers":[
        {
            "category":"Autos & Motor Vehicles",
            "subcategory":"Fuel & Gas Station",
            "type":"Retail Goods"
        }
    ],
    "sg:phone":"+1 262 375 4666",
    "sg:postcode":"53074",
    "sg:province":"WI",
    "sg:tags":[
        "oil"
    ],
    "wof:name":"Port Amoco Svc",
    "wof:placetype":"venue"
},
  "geometry": {"coordinates":[-87.87288100000001,43.387482],"type":"Point"}
}