{
  "type": "Feature",
  "properties": {
    "iso:country":"US",
    "sg:address":"300 Travis Ln",
    "sg:city":"Waukesha",
    "sg:classifiers":[
        {
            "category":"Building & Trades",
            "subcategory":"Construction",
            "type":"Services"
        }
    ],
    "sg:phone":"+1 262 521 1083",
    "sg:postcode":"53189",
    "sg:province":"WI",
    "sg:tags":[
        "general",
        "contractor"
    ],
    "wof:name":"Superior Flooring Of Waukesha",
    "wof:placetype":"venue"
},
  "geometry": {"coordinates":[-88.23084799999999,42.975966],"type":"Point"}
}