{
  "type": "Feature",
  "properties": {
    "addr:full":"7230 W Sandy Point Rd Couderay WI 54828",
    "addr:housenumber":"7230",
    "addr:postcode":"54828",
    "addr:street":"W Sandy Point Rd",
    "iso:country":"US",
    "sg:address":"7230 W Sandy Point Rd",
    "sg:city":"Couderay",
    "sg:classifiers":[
        {
            "category":"Travel",
            "subcategory":"Hotels & Motels",
            "type":"Entertainment"
        }
    ],
    "sg:phone":"+1 715 945 2776",
    "sg:postcode":"54828",
    "sg:province":"WI",
    "sg:tags":[
        "resort",
        "operation"
    ],
    "wof:name":"Chippewa Pines Resort Inc",
    "wof:placetype":"venue"
},
  "geometry": {"coordinates":[-91.240433,45.896061],"type":"Point"}
}