{
  "type": "Feature",
  "properties": {
    "addr:full":"3231 E Hamilton Ave Eau Claire WI 54701",
    "addr:housenumber":"3231",
    "addr:postcode":"54701",
    "addr:street":"E Hamilton Ave",
    "iso:country":"US",
    "sg:address":"3231 E Hamilton Ave",
    "sg:city":"Eau Claire",
    "sg:classifiers":[
        {
            "category":"Wholesale",
            "subcategory":"Machinery & Supplies",
            "type":"Manufacturing & Wholesale Goods"
        }
    ],
    "sg:phone":"+1 715 835 9914",
    "sg:postcode":"54701",
    "sg:province":"WI",
    "sg:tags":[
        "equipment",
        "industrial",
        "business"
    ],
    "wof:name":"Northern Paint Company Inc",
    "wof:placetype":"venue"
},
  "geometry": {"coordinates":[-91.45866700000001,44.785641],"type":"Point"}
}