{
  "type": "Feature",
  "properties": {
    "iso:country":"US",
    "sg:address":"24161 State Rd 35",
    "sg:city":"Siren",
    "sg:classifiers":[
        {
            "category":"Professional",
            "subcategory":"Lawyer & Legal Services",
            "type":"Services"
        }
    ],
    "sg:phone":"+1 715 349 5215",
    "sg:postcode":"54872",
    "sg:province":"WI",
    "sg:tags":[
        "attorney"
    ],
    "wof:name":"Benson Law Office",
    "wof:placetype":"venue"
},
  "geometry": {"coordinates":[-92.380988,45.789818],"type":"Point"}
}