{
  "type": "Feature",
  "properties": {
    "iso:country":"US",
    "sg:address":"1828 Duncan Rd",
    "sg:city":"Bloomer",
    "sg:classifiers":[
        {
            "category":"Professional",
            "type":"Services"
        }
    ],
    "sg:phone":"+1 715 568 3215",
    "sg:postcode":"54724",
    "sg:province":"WI",
    "wof:name":"Gregory A Miller",
    "wof:placetype":"venue"
},
  "geometry": {"coordinates":[-91.496959,45.103152],"type":"Point"}
}