{
  "type": "Feature",
  "properties": {
    "iso:country":"US",
    "sg:address":"4145 N Oakland Ave",
    "sg:city":"Milwaukee",
    "sg:classifiers":[
        {
            "category":"Food & Beverages",
            "subcategory":"Groceries & Convenience Stores",
            "type":"Retail Goods"
        }
    ],
    "sg:phone":"+1 414 967 9218",
    "sg:postcode":"53211",
    "sg:province":"WI",
    "sg:tags":[
        "grocer"
    ],
    "wof:name":"Pick'n Save",
    "wof:placetype":"venue"
},
  "geometry": {"coordinates":[-87.887522,43.093482],"type":"Point"}
}