{
  "type": "Feature",
  "properties": {
    "iso:country":"US",
    "sg:address":"3901 N Humboldt Blvd # 304",
    "sg:city":"Milwaukee",
    "sg:classifiers":[
        {
            "category":"Education",
            "subcategory":"Music School",
            "type":"Public Place"
        }
    ],
    "sg:phone":"+1 414 763 8049",
    "sg:postcode":"53212",
    "sg:province":"WI",
    "sg:tags":[
        "instruction-instrumental"
    ],
    "wof:name":"Musical Gifts Violin Studio",
    "wof:placetype":"venue"
},
  "geometry": {"coordinates":[-87.89907100000001,43.08849],"type":"Point"}
}