{
  "type": "Feature",
  "properties": {
    "iso:country":"US",
    "sg:address":"301 N Century Ave",
    "sg:city":"Waunakee",
    "sg:classifiers":[
        {
            "category":"Restaurant",
            "type":"Food & Drink"
        }
    ],
    "sg:phone":"+1 608 849 5011",
    "sg:postcode":"53597",
    "sg:province":"WI",
    "wof:name":"Rex's Innkeeper",
    "wof:placetype":"venue"
},
  "geometry": {"coordinates":[-89.461789,43.195792],"type":"Point"}
}