{
  "type": "Feature",
  "properties": {
    "iso:country":"US",
    "sg:address":"9309 W Fairlane Ct",
    "sg:city":"Milwaukee",
    "sg:classifiers":[
        {
            "category":"Shopping",
            "type":"Retail Goods"
        }
    ],
    "sg:phone":"+1 414 355 6990",
    "sg:postcode":"53224",
    "sg:province":"WI",
    "sg:tags":[
        "pet",
        "food",
        "supply"
    ],
    "wof:name":"Pet Pantry",
    "wof:placetype":"venue"
},
  "geometry": {"coordinates":[-88.02909,43.169138],"type":"Point"}
}