{
  "type": "Feature",
  "properties": {
    "iso:country":"US",
    "sg:address":"929 8th St",
    "sg:city":"Kiel",
    "sg:classifiers":[
        {
            "category":"School Buses",
            "type":"Transportation"
        }
    ],
    "sg:phone":"+1 920 894 2013",
    "sg:postcode":"53042",
    "sg:province":"WI",
    "wof:name":"Kiel Transportation Inc",
    "wof:placetype":"venue"
},
  "geometry": {"coordinates":[-88.041836,43.917495],"type":"Point"}
}