{
  "type": "Feature",
  "properties": {
    "iso:country":"US",
    "sg:address":"2293 Boland Valley Rd",
    "sg:city":"Arcadia",
    "sg:classifiers":[
        {
            "category":"Shopping",
            "subcategory":"Computers & Home Electronics",
            "type":"Retail Goods"
        }
    ],
    "sg:phone":"+1 608 323 3235",
    "sg:postcode":"54612",
    "sg:province":"WI",
    "wof:name":"Dart Computers",
    "wof:placetype":"venue"
},
  "geometry": {"coordinates":[-91.569792,44.261493],"type":"Point"}
}