{
  "type": "Feature",
  "properties": {
    "iso:country":"US",
    "sg:address":"4162 Whitefish Bay Rd",
    "sg:city":"Sturgeon Bay",
    "sg:classifiers":[
        {
            "category":"Building & Trades",
            "subcategory":"Construction",
            "type":"Services"
        },
        {
            "category":"Wholesale",
            "subcategory":"Durable Goods & Equipment",
            "type":"Manufacturing & Wholesale Goods"
        }
    ],
    "sg:phone":"+1 920 743 9120",
    "sg:postcode":"54235",
    "sg:province":"WI",
    "sg:tags":[
        "fuel",
        "masonry",
        "logging",
        "dealer",
        "contractor"
    ],
    "wof:name":"Mann Enterprises",
    "wof:placetype":"venue"
},
  "geometry": {"coordinates":[-87.250031,44.908299],"type":"Point"}
}