{
  "type": "Feature",
  "properties": {
    "iso:country":"US",
    "sg:address":"615 Wisconsin Ave",
    "sg:city":"Racine",
    "sg:classifiers":[
        {
            "category":"Retail",
            "subcategory":"Repair Shop",
            "type":"Services"
        }
    ],
    "sg:phone":"+1 262 632 6670",
    "sg:postcode":"53403",
    "sg:province":"WI",
    "sg:tags":[
        "picture",
        "framing"
    ],
    "wof:name":"Avenue Frame Shop Inc",
    "wof:placetype":"venue"
},
  "geometry": {"coordinates":[-87.78368399999999,42.726088],"type":"Point"}
}