{
  "type": "Feature",
  "properties": {
    "iso:country":"US",
    "sg:address":"2374 250th St",
    "sg:city":"Deer Park",
    "sg:classifiers":[
        {
            "category":"Utilities",
            "subcategory":"Fuel Oil & Lpg",
            "type":"Services"
        }
    ],
    "sg:phone":"+1 715 684 5502",
    "sg:postcode":"54007",
    "sg:province":"WI",
    "sg:tags":[
        "dealer"
    ],
    "wof:name":"Black Bear Firewood",
    "wof:placetype":"venue"
},
  "geometry": {"coordinates":[-92.304182,45.197956],"type":"Point"}
}