{
  "type": "Feature",
  "properties": {
    "iso:country":"US",
    "sg:address":"1311 Spring St",
    "sg:city":"Manitowoc",
    "sg:classifiers":[
        {
            "category":"Manufacturing",
            "subcategory":"Metals",
            "type":"Manufacturing & Wholesale Goods"
        }
    ],
    "sg:phone":"+1 920 682 4613",
    "sg:postcode":"54220",
    "sg:province":"WI",
    "sg:tags":[
        "plate",
        "structural",
        "m",
        "fabricated",
        "mfg"
    ],
    "sg:website":"www.consumersinc.com",
    "wof:name":"Consumers Inc",
    "wof:placetype":"venue"
},
  "geometry": {"coordinates":[-87.66441399999999,44.102147],"type":"Point"}
}