{
  "type": "Feature",
  "properties": {
    "iso:country":"US",
    "sg:address":"10324 Bighorn Ln",
    "sg:city":"Hancock",
    "sg:classifiers":[
        {
            "category":"Retail",
            "subcategory":"Repair Shop",
            "type":"Services"
        }
    ],
    "sg:phone":"+1 715 249 5233",
    "sg:postcode":"54943",
    "sg:province":"WI",
    "sg:tags":[
        "farm",
        "agricultural",
        "machine",
        "equipment"
    ],
    "wof:name":"Marl Lake Power Eqp & Mar",
    "wof:placetype":"venue"
},
  "geometry": {"coordinates":[-89.397661,44.114366],"type":"Point"}
}