{
  "type": "Feature",
  "properties": {
    "addr:full":"4295 W Bradley Rd Milwaukee WI 53209",
    "addr:housenumber":"4295",
    "addr:postcode":"53209",
    "addr:street":"W Bradley Rd",
    "iso:country":"US",
    "sg:address":"4295 W Bradley Rd",
    "sg:city":"Milwaukee",
    "sg:classifiers":[
        {
            "category":"Banks & Credit Unions",
            "subcategory":"Bank",
            "type":"Services"
        }
    ],
    "sg:phone":"+1 414 357 1323",
    "sg:postcode":"53209",
    "sg:province":"WI",
    "sg:website":"http://www.tcnb.com",
    "wof:name":"Tri City National Bank",
    "wof:placetype":"venue"
},
  "geometry": {"coordinates":[-87.964716,43.163158],"type":"Point"}
}