{
  "type": "Feature",
  "properties": {
    "iso:country":"US",
    "sg:address":"12039 508th Ave",
    "sg:city":"Prescott",
    "sg:classifiers":[
        {
            "category":"Professional",
            "subcategory":"Accounting & Tax Preparation",
            "type":"Services"
        }
    ],
    "sg:phone":"+1 715 262 3604",
    "sg:postcode":"54021",
    "sg:province":"WI",
    "wof:name":"Bremali Inc",
    "wof:placetype":"venue"
},
  "geometry": {"coordinates":[-92.742079,44.722563],"type":"Point"}
}