{
  "type": "Feature",
  "properties": {
    "iso:country":"US",
    "sg:address":"4554 Golf Dr",
    "sg:city":"Fennimore",
    "sg:classifiers":[
        {
            "category":"Professional",
            "type":"Services"
        }
    ],
    "sg:phone":"+1 608 822 7660",
    "sg:postcode":"53809",
    "sg:province":"WI",
    "wof:name":"Michael J Birchman",
    "wof:placetype":"venue"
},
  "geometry": {"coordinates":[-90.654371,43.037122],"type":"Point"}
}