{
  "type": "Feature",
  "properties": {
    "iso:country":"US",
    "sg:address":"922 Churchill St",
    "sg:city":"Waupaca",
    "sg:classifiers":[
        {
            "category":"Social Services",
            "type":"Services"
        }
    ],
    "sg:phone":"+1 715 258 6480",
    "sg:postcode":"54981",
    "sg:province":"WI",
    "sg:tags":[
        "probation"
    ],
    "wof:name":"Probation & Parole Office",
    "wof:placetype":"venue"
},
  "geometry": {"coordinates":[-89.072045,44.347968],"type":"Point"}
}