{
  "type": "Feature",
  "properties": {
    "iso:country":"US",
    "sg:address":"500 Everett Dr",
    "sg:city":"Waukesha",
    "sg:classifiers":[
        {
            "category":"Real Estate",
            "subcategory":"Real Estate Agent",
            "type":"Services"
        }
    ],
    "sg:phone":"+1 262 547 2851",
    "sg:postcode":"53188",
    "sg:province":"WI",
    "wof:name":"Becker Group LLC",
    "wof:placetype":"venue"
},
  "geometry": {"coordinates":[-88.265648,43.00827],"type":"Point"}
}