{
  "type": "Feature",
  "properties": {
    "iso:country":"US",
    "sg:address":"11831 Buckbee Rd",
    "sg:city":"Marion",
    "sg:classifiers":[
        {
            "category":"Wholesale",
            "subcategory":"Electrical",
            "type":"Manufacturing & Wholesale Goods"
        }
    ],
    "sg:phone":"+1 715 754 5974",
    "sg:postcode":"54950",
    "sg:province":"WI",
    "sg:tags":[
        "electric",
        "motor"
    ],
    "wof:name":"Hangartner Electric",
    "wof:placetype":"venue"
},
  "geometry": {"coordinates":[-88.86071,44.669036],"type":"Point"}
}