{
  "type": "Feature",
  "properties": {
    "iso:country":"US",
    "sg:address":"4344 N 27th St",
    "sg:city":"Milwaukee",
    "sg:classifiers":[
        {
            "category":"Organizations",
            "subcategory":"Religious Organization",
            "type":"Services"
        }
    ],
    "sg:phone":"+1 414 442 2234",
    "sg:postcode":"53216",
    "sg:province":"WI",
    "sg:tags":[
        "god",
        "churches-pentecostal",
        "church"
    ],
    "wof:name":"Powerhouse of Deliverance Church of God",
    "wof:placetype":"venue"
},
  "geometry": {"coordinates":[-87.946809,43.096388],"type":"Point"}
}