{
  "type": "Feature",
  "properties": {
    "iso:country":"US",
    "sg:address":"8303 Co Rd A",
    "sg:city":"Superior",
    "sg:classifiers":[
        {
            "category":"Shopping",
            "subcategory":"Bicycles & Sporting Goods",
            "type":"Retail Goods"
        }
    ],
    "sg:phone":"+1 715 399 0104",
    "sg:postcode":"54880",
    "sg:province":"WI",
    "sg:tags":[
        "gun",
        "gunsmith"
    ],
    "wof:name":"J R Gunworks",
    "wof:placetype":"venue"
},
  "geometry": {"coordinates":[-92.071577,46.465098],"type":"Point"}
}