{
  "type": "Feature",
  "properties": {
    "iso:country":"US",
    "sg:address":"419 E Broadway",
    "sg:city":"Waukesha",
    "sg:classifiers":[
        {
            "category":"Health Services",
            "subcategory":"Dentist",
            "type":"Services"
        }
    ],
    "sg:phone":"+1 262 549 6850",
    "sg:postcode":"53186",
    "sg:province":"WI",
    "sg:tags":[
        "product",
        "dentists-cosmetic",
        "teeth",
        "dentists-periodontists",
        "whitening",
        "dentistry",
        "dentists-orthodontists"
    ],
    "sg:website":"http://www.cfdonbroadway.com",
    "wof:name":"Complete Family Dentistry",
    "wof:placetype":"venue"
},
  "geometry": {"coordinates":[-88.222165,43.007963],"type":"Point"}
}