{
  "type": "Feature",
  "properties": {
    "iso:country":"US",
    "sg:address":"1434 Progress Ln",
    "sg:city":"Omro",
    "sg:classifiers":[
        {
            "category":"Manufacturing",
            "subcategory":"Printing",
            "type":"Manufacturing & Wholesale Goods"
        }
    ],
    "sg:phone":"+1 920 685 5662",
    "sg:postcode":"54963",
    "sg:province":"WI",
    "sg:tags":[
        "printer"
    ],
    "sg:website":"www.printco.com",
    "wof:name":"Printco Inc",
    "wof:placetype":"venue"
},
  "geometry": {"coordinates":[-88.725682,44.038502],"type":"Point"}
}