{
  "type": "Feature",
  "properties": {
    "iso:country":"US",
    "sg:address":"402 Herman St",
    "sg:city":"Iron Ridge",
    "sg:classifiers":[
        {
            "category":"Organizations",
            "subcategory":"Religious Organization",
            "type":"Services"
        }
    ],
    "sg:phone":"+1 920 625 2042",
    "sg:postcode":"53035",
    "sg:province":"WI",
    "sg:tags":[
        "church"
    ],
    "wof:name":"Our Savior's Lutheran Church",
    "wof:placetype":"venue"
},
  "geometry": {"coordinates":[-88.52831500000001,43.39662],"type":"Point"}
}