{
  "type": "Feature",
  "properties": {
    "addr:full":"5900 7th Ave Kenosha WI 53140",
    "addr:housenumber":"5900",
    "addr:postcode":"53140",
    "addr:street":"7Th Ave",
    "iso:country":"US",
    "sg:address":"5900 7th Ave",
    "sg:city":"Kenosha",
    "sg:classifiers":[
        {
            "category":"Social Services",
            "subcategory":"Child Care",
            "type":"Services"
        }
    ],
    "sg:phone":"+1 262 656 1202",
    "sg:postcode":"53140",
    "sg:province":"WI",
    "sg:tags":[
        "school",
        "nursery"
    ],
    "wof:name":"Wonderful World Of Kids Castle",
    "wof:placetype":"venue"
},
  "geometry": {"coordinates":[-87.819114,42.581593],"type":"Point"}
}