{
  "type": "Feature",
  "properties": {
    "iso:country":"US",
    "sg:address":"5406 N Shore Rd",
    "sg:city":"Weyauwega",
    "sg:classifiers":[
        {
            "category":"Bars & Pubs",
            "type":"Food & Drink"
        }
    ],
    "sg:phone":"+1 920 867 3096",
    "sg:postcode":"54983",
    "sg:province":"WI",
    "sg:tags":[
        "drinking"
    ],
    "wof:name":"Crossings Supper Club",
    "wof:placetype":"venue"
},
  "geometry": {"coordinates":[-88.952206,44.373623],"type":"Point"}
}