{
  "type": "Feature",
  "properties": {
    "iso:country":"US",
    "sg:address":"400 S Fisk St",
    "sg:city":"Green Bay",
    "sg:classifiers":[
        {
            "category":"Building & Trades",
            "subcategory":"Landscaping Services",
            "type":"Services"
        }
    ],
    "sg:phone":"+1 920 498 8266",
    "sg:postcode":"54303",
    "sg:province":"WI",
    "sg:tags":[
        "landscape",
        "contractor"
    ],
    "wof:name":"Custom Landscaping & Lawncare",
    "wof:placetype":"venue"
},
  "geometry": {"coordinates":[-88.058363,44.523879],"type":"Point"}
}