{
  "type": "Feature",
  "properties": {
    "iso:country":"US",
    "sg:address":"790 Main St",
    "sg:city":"Baldwin",
    "sg:classifiers":[
        {
            "category":"Retail",
            "subcategory":"Photofinishing",
            "type":"Services"
        }
    ],
    "sg:phone":"+1 715 684 5180",
    "sg:postcode":"54002",
    "sg:province":"WI",
    "sg:tags":[
        "laboratory"
    ],
    "wof:name":"K J S Photo",
    "wof:placetype":"venue"
},
  "geometry": {"coordinates":[-92.371658,44.966693],"type":"Point"}
}