{
  "type": "Feature",
  "properties": {
    "iso:country":"US",
    "sg:address":"440 US Hwy 14",
    "sg:city":"Janesville",
    "sg:classifiers":[
        {
            "category":"Government",
            "subcategory":"Office",
            "type":"Public Place"
        }
    ],
    "sg:phone":"+1 608 754 6617",
    "sg:postcode":"53545",
    "sg:province":"WI",
    "sg:tags":[
        "county"
    ],
    "wof:name":"Rock County Land Conservation",
    "wof:placetype":"venue"
},
  "geometry": {"coordinates":[-89.020546,42.726859],"type":"Point"}
}