{
  "type": "Feature",
  "properties": {
    "iso:country":"US",
    "sg:address":"6021 W Stevenson St",
    "sg:city":"Milwaukee",
    "sg:classifiers":[
        {
            "category":"Building & Trades",
            "subcategory":"Construction",
            "type":"Services"
        }
    ],
    "sg:phone":"+1 414 778 1166",
    "sg:postcode":"53213",
    "sg:province":"WI",
    "sg:tags":[
        "house"
    ],
    "wof:name":"Alumicraft Unlimited",
    "wof:placetype":"venue"
},
  "geometry": {"coordinates":[-87.989676,43.03202],"type":"Point"}
}