{
  "type": "Feature",
  "properties": {
    "iso:country":"US",
    "sg:address":"1336 E Sumner St",
    "sg:city":"Hartford",
    "sg:classifiers":[
        {
            "category":"Shopping",
            "subcategory":"Photographic Equipment",
            "type":"Retail Goods"
        },
        {
            "category":"Shopping",
            "subcategory":"Computers & Home Electronics",
            "type":"Retail Goods"
        }
    ],
    "sg:phone":"+1 262 673 3190",
    "sg:postcode":"53027",
    "sg:province":"WI",
    "sg:tags":[
        "stereo",
        "television",
        "also",
        "camera",
        "radio",
        "electronic",
        "other"
    ],
    "wof:name":"Camera Case & TV Inc",
    "wof:placetype":"venue"
},
  "geometry": {"coordinates":[-88.357614,43.317706],"type":"Point"}
}