{
  "type": "Feature",
  "properties": {
    "iso:country":"US",
    "sg:address":"5542 S 45th St",
    "sg:city":"Milwaukee",
    "sg:classifiers":[
        {
            "category":"Professional",
            "subcategory":"Management & Consulting",
            "type":"Services"
        }
    ],
    "sg:phone":"+1 414 421 0275",
    "sg:postcode":"53220",
    "sg:province":"WI",
    "wof:name":"Laura V Orlowski",
    "wof:placetype":"venue"
},
  "geometry": {"coordinates":[-87.971684,42.94352],"type":"Point"}
}