{
  "type": "Feature",
  "properties": {
    "iso:country":"US",
    "sg:address":"9353 Co Rd Ff",
    "sg:city":"Ripon",
    "sg:phone":"+1 920 748 2620",
    "sg:postcode":"54971",
    "sg:province":"WI",
    "sg:tags":[
        "farm",
        "corn",
        "dairy"
    ],
    "wof:name":"Gerald Schulz Inc",
    "wof:placetype":"venue"
},
  "geometry": {"coordinates":[-88.881484,43.874808],"type":"Point"}
}