{
  "type": "Feature",
  "properties": {
    "iso:country":"US",
    "sg:address":"12100 W Park Pl",
    "sg:city":"Milwaukee",
    "sg:classifiers":[
        {
            "category":"Professional",
            "subcategory":"Research",
            "type":"Services"
        }
    ],
    "sg:phone":"+1 414 359 4200",
    "sg:postcode":"53224",
    "sg:province":"WI",
    "sg:tags":[
        "development"
    ],
    "wof:name":"A O Smith Water Products",
    "wof:placetype":"venue"
},
  "geometry": {"coordinates":[-88.06134299999999,43.158951],"type":"Point"}
}