{
  "type": "Feature",
  "properties": {
    "iso:country":"US",
    "sg:address":"1348 Edgewood Rd N",
    "sg:city":"Custer",
    "sg:classifiers":[
        {
            "category":"Farming",
            "subcategory":"Dairy Farm",
            "type":"Manufacturing & Wholesale Goods"
        }
    ],
    "sg:phone":"+1 715 592 4201",
    "sg:postcode":"54423",
    "sg:province":"WI",
    "wof:name":"Robert & Celia Rozek",
    "wof:placetype":"venue"
},
  "geometry": {"coordinates":[-89.400548,44.556028],"type":"Point"}
}