{
  "type": "Feature",
  "properties": {
    "iso:country":"US",
    "sg:address":"6665 W Mill Rd",
    "sg:city":"Milwaukee",
    "sg:classifiers":[
        {
            "category":"Wholesale",
            "subcategory":"Machinery & Supplies",
            "type":"Manufacturing & Wholesale Goods"
        }
    ],
    "sg:phone":"+1 414 353 7903",
    "sg:postcode":"53218",
    "sg:province":"WI",
    "sg:tags":[
        "equipment",
        "industrial"
    ],
    "wof:name":"Progressive Machinery Inc",
    "wof:placetype":"venue"
},
  "geometry": {"coordinates":[-87.99119399999999,43.133914],"type":"Point"}
}