{
  "type": "Feature",
  "properties": {
    "iso:country":"US",
    "sg:address":"4724 Co Rd G",
    "sg:city":"Saint Cloud",
    "sg:classifiers":[
        {
            "category":"Farming",
            "subcategory":"Dairy Farm",
            "type":"Manufacturing & Wholesale Goods"
        }
    ],
    "sg:phone":"+1 920 477 2500",
    "sg:postcode":"53079",
    "sg:province":"WI",
    "wof:name":"Robert Twohig",
    "wof:placetype":"venue"
},
  "geometry": {"coordinates":[-88.180809,43.713156],"type":"Point"}
}