{
  "type": "Feature",
  "properties": {
    "iso:country":"US",
    "sg:address":"7549 F & W Ct",
    "sg:city":"Lannon",
    "sg:classifiers":[
        {
            "category":"Manufacturing",
            "subcategory":"Metals",
            "type":"Manufacturing & Wholesale Goods"
        }
    ],
    "sg:phone":"+1 262 251 5063",
    "sg:postcode":"53046",
    "sg:province":"WI",
    "wof:name":"Fence Erectors Inc",
    "wof:placetype":"venue"
},
  "geometry": {"coordinates":[-88.155124,43.155488],"type":"Point"}
}