{
  "type": "Feature",
  "properties": {
    "iso:country":"US",
    "sg:address":"350 Winnebago St",
    "sg:city":"N Fond Du Lac",
    "sg:classifiers":[
        {
            "category":"Real Estate",
            "subcategory":"Real Estate Operator",
            "type":"Services"
        }
    ],
    "sg:phone":"+1 920 929 9270",
    "sg:postcode":"54937",
    "sg:province":"WI",
    "sg:tags":[
        "apartment"
    ],
    "wof:name":"Northgate Senior Apartments",
    "wof:placetype":"venue"
},
  "geometry": {"coordinates":[-88.48969,43.80647],"type":"Point"}
}