{
  "type": "Feature",
  "properties": {
    "iso:country":"US",
    "sg:address":"102 W Willow St",
    "sg:city":"Bear Creek",
    "sg:classifiers":[
        {
            "category":"Professional",
            "subcategory":"Lawyer & Legal Services",
            "type":"Services"
        }
    ],
    "sg:phone":"+1 715 752 4474",
    "sg:postcode":"54922",
    "sg:province":"WI",
    "sg:tags":[
        "attorney"
    ],
    "wof:name":"Gerald D Lorge",
    "wof:placetype":"venue"
},
  "geometry": {"coordinates":[-88.726216,44.531394],"type":"Point"}
}