{
  "type": "Feature",
  "properties": {
    "iso:country":"US",
    "sg:address":"5380 Farmco Dr",
    "sg:city":"Madison",
    "sg:classifiers":[
        {
            "category":"Recreation",
            "subcategory":"Marina",
            "type":"Entertainment"
        }
    ],
    "sg:phone":"+1 608 246 8122",
    "sg:postcode":"53704",
    "sg:province":"WI",
    "sg:tags":[
        "operation"
    ],
    "wof:name":"Bright Work Boat Repair",
    "wof:placetype":"venue"
},
  "geometry": {"coordinates":[-89.410403,43.153455],"type":"Point"}
}