{
  "type": "Feature",
  "properties": {
    "iso:country":"US",
    "sg:address":"3316 Ableman Rd",
    "sg:city":"Reedsburg",
    "sg:phone":"+1 608 524 3503",
    "sg:postcode":"53959",
    "sg:province":"WI",
    "sg:tags":[
        "farm",
        "field",
        "crop"
    ],
    "wof:name":"Carl Beth",
    "wof:placetype":"venue"
},
  "geometry": {"coordinates":[-89.916837,43.524779],"type":"Point"}
}