{
  "type": "Feature",
  "properties": {
    "iso:country":"US",
    "sg:address":"815 Water Ave",
    "sg:city":"Hillsboro",
    "sg:classifiers":[
        {
            "category":"Home & Garden",
            "subcategory":"Hardware",
            "type":"Retail Goods"
        }
    ],
    "sg:phone":"+1 608 489 2588",
    "sg:postcode":"54634",
    "sg:province":"WI",
    "wof:name":"Hillsboro Hardware Hank",
    "wof:placetype":"venue"
},
  "geometry": {"coordinates":[-90.33961,43.651047],"type":"Point"}
}