{
  "type": "Feature",
  "properties": {
    "addr:full":"6115 Washington Ave Racine WI 53406",
    "addr:housenumber":"6115",
    "addr:postcode":"53406",
    "addr:street":"Washington Ave",
    "iso:country":"US",
    "sg:address":"6115 Washington Ave",
    "sg:city":"Racine",
    "sg:classifiers":[
        {
            "category":"Banks & Credit Unions",
            "subcategory":"Bank",
            "type":"Services"
        }
    ],
    "sg:phone":"+1 262 886 1514",
    "sg:postcode":"53406",
    "sg:province":"WI",
    "sg:tags":[
        "federal",
        "savings"
    ],
    "wof:name":"TCF Bank",
    "wof:placetype":"venue"
},
  "geometry": {"coordinates":[-87.855355,42.719096],"type":"Point"}
}