{
  "type": "Feature",
  "properties": {
    "iso:country":"US",
    "sg:address":"13018 W Forest Dr",
    "sg:city":"New Berlin",
    "sg:classifiers":[
        {
            "category":"Professional",
            "type":"Services"
        }
    ],
    "sg:phone":"+1 262 796 0768",
    "sg:postcode":"53151",
    "sg:province":"WI",
    "wof:name":"Kirk J Noll",
    "wof:placetype":"venue"
},
  "geometry": {"coordinates":[-88.075309,43.011805],"type":"Point"}
}