{
  "type": "Feature",
  "properties": {
    "addr:full":"181 State Rd 108 Melrose WI 54642",
    "addr:housenumber":"181",
    "addr:postcode":"54642",
    "addr:street":"State Rd 108",
    "iso:country":"US",
    "sg:address":"181 State Rd 108",
    "sg:city":"Melrose",
    "sg:classifiers":[
        {
            "category":"Education",
            "subcategory":"School",
            "type":"Public Place"
        }
    ],
    "sg:phone":"+1 608 488 2201",
    "sg:postcode":"54642",
    "sg:province":"WI",
    "sg:tags":[
        "educational",
        "administrative"
    ],
    "wof:name":"Melrose Mindoro School Dst",
    "wof:placetype":"venue"
},
  "geometry": {"coordinates":[-91.023414,44.071371],"type":"Point"}
}