{
  "type": "Feature",
  "properties": {
    "iso:country":"US",
    "sg:address":"1020 W Historic Mitchell St",
    "sg:city":"Milwaukee",
    "sg:classifiers":[
        {
            "category":"Shopping",
            "subcategory":"Clothing, Apparel, & Fashions",
            "type":"Retail Goods"
        }
    ],
    "sg:phone":"+1 414 384 8059",
    "sg:postcode":"53204",
    "sg:province":"WI",
    "sg:tags":[
        "hat"
    ],
    "wof:name":"J M Caps",
    "wof:placetype":"venue"
},
  "geometry": {"coordinates":[-87.925236,43.012366],"type":"Point"}
}