{
  "type": "Feature",
  "properties": {
    "iso:country":"US",
    "sg:address":"219 S 2nd St",
    "sg:city":"Milwaukee",
    "sg:classifiers":[
        {
            "category":"Bars & Pubs",
            "type":"Food & Drink"
        }
    ],
    "sg:phone":"+1 414 276 2711",
    "sg:postcode":"53204",
    "sg:province":"WI",
    "sg:tags":[
        "drinking"
    ],
    "wof:name":"BRC Enterprises Inc",
    "wof:placetype":"venue"
},
  "geometry": {"coordinates":[-87.91264200000001,43.028581],"type":"Point"}
}