{
  "type": "Feature",
  "properties": {
    "addr:full":"527 W Bender Rd Milwaukee WI 53217",
    "addr:housenumber":"527",
    "addr:postcode":"53217",
    "addr:street":"W Bender Rd",
    "iso:country":"US",
    "sg:address":"527 W Bender Rd",
    "sg:city":"Milwaukee",
    "sg:classifiers":[
        {
            "category":"Professional",
            "subcategory":"Advertising",
            "type":"Services"
        }
    ],
    "sg:phone":"+1 414 332 5670",
    "sg:postcode":"53217",
    "sg:province":"WI",
    "sg:tags":[
        "agency"
    ],
    "wof:name":"Street Smart Marketing",
    "wof:placetype":"venue"
},
  "geometry": {"coordinates":[-87.91656,43.129481],"type":"Point"}
}