{
  "type": "Feature",
  "properties": {
    "iso:country":"US",
    "sg:address":"2501 N Mountain Rd",
    "sg:city":"Wausau",
    "sg:classifiers":[
        {
            "category":"Shopping",
            "subcategory":"Bicycles & Sporting Goods",
            "type":"Retail Goods"
        }
    ],
    "sg:phone":"+1 715 355 4844",
    "sg:postcode":"54401",
    "sg:province":"WI",
    "wof:name":"Split Second Sports",
    "wof:placetype":"venue"
},
  "geometry": {"coordinates":[-89.668514,44.933378],"type":"Point"}
}