{
  "type": "Feature",
  "properties": {
    "addr:full":"415 Co Rd A Briggsville WI 53952",
    "addr:housenumber":"415",
    "addr:postcode":"53952",
    "addr:street":"Co Rd A Briggsville",
    "iso:country":"US",
    "sg:address":"415 Co Rd A",
    "sg:city":"Briggsville",
    "sg:classifiers":[
        {
            "category":"Restaurant",
            "type":"Food & Drink"
        }
    ],
    "sg:phone":"+1 608 981 2012",
    "sg:postcode":"53952",
    "sg:province":"WI",
    "wof:name":"Pheasant Inn",
    "wof:placetype":"venue"
},
  "geometry": {"coordinates":[-89.68625900000001,43.828309],"type":"Point"}
}