{
  "type": "Feature",
  "properties": {
    "iso:country":"US",
    "sg:address":"8530 W McMyron St",
    "sg:city":"Milwaukee",
    "sg:classifiers":[
        {
            "category":"Travel",
            "subcategory":"Travel Agent",
            "type":"Entertainment"
        }
    ],
    "sg:phone":"+1 414 257 1032",
    "sg:postcode":"53214",
    "sg:province":"WI",
    "sg:tags":[
        "agency"
    ],
    "wof:name":"American Dream Vacations",
    "wof:placetype":"venue"
},
  "geometry": {"coordinates":[-88.018237,43.023084],"type":"Point"}
}