{
  "type": "Feature",
  "properties": {
    "iso:country":"US",
    "sg:address":"1828 Wisconsin Ave",
    "sg:city":"New Holstein",
    "sg:classifiers":[
        {
            "category":"Insurance",
            "subcategory":"Insurance Agent",
            "type":"Services"
        }
    ],
    "sg:phone":"+1 920 898 4488",
    "sg:postcode":"53061",
    "sg:province":"WI",
    "wof:name":"Calumet Equity Mutual Insur Co",
    "wof:placetype":"venue"
},
  "geometry": {"coordinates":[-88.089623,43.949841],"type":"Point"}
}