{
  "type": "Feature",
  "properties": {
    "addr:full":"1209 S Silverbrook Dr West Bend WI 53095",
    "addr:housenumber":"1209",
    "addr:postcode":"53095",
    "addr:street":"S Silverbrook Dr",
    "iso:country":"US",
    "sg:address":"1209 S Silverbrook Dr",
    "sg:city":"West Bend",
    "sg:classifiers":[
        {
            "category":"Shopping",
            "subcategory":"Crafts & Fabrics",
            "type":"Retail Goods"
        }
    ],
    "sg:phone":"+1 262 334 9751",
    "sg:postcode":"53095",
    "sg:province":"WI",
    "sg:tags":[
        "sewing"
    ],
    "wof:name":"Art of Needle",
    "wof:placetype":"venue"
},
  "geometry": {"coordinates":[-88.191211,43.403011],"type":"Point"}
}