{
  "type": "Feature",
  "properties": {
    "iso:country":"US",
    "sg:address":"444 W Prairie St",
    "sg:city":"Columbus",
    "sg:classifiers":[
        {
            "category":"Professional",
            "subcategory":"Management & Consulting",
            "type":"Services"
        }
    ],
    "sg:phone":"+1 920 623 3937",
    "sg:postcode":"53925",
    "sg:province":"WI",
    "sg:tags":[
        "business"
    ],
    "wof:name":"Sneath R A Associates LLC",
    "wof:placetype":"venue"
},
  "geometry": {"coordinates":[-89.020338,43.339339],"type":"Point"}
}