{
  "type": "Feature",
  "properties": {
    "iso:country":"US",
    "sg:address":"1812 W State St",
    "sg:city":"Milwaukee",
    "sg:classifiers":[
        {
            "category":"Food & Beverages",
            "subcategory":"Groceries & Convenience Stores",
            "type":"Retail Goods"
        }
    ],
    "sg:phone":"+1 414 342 3303",
    "sg:postcode":"53233",
    "sg:province":"WI",
    "sg:tags":[
        "juice"
    ],
    "wof:name":"Badger Distributing Of Milwaukee",
    "wof:placetype":"venue"
},
  "geometry": {"coordinates":[-87.935531,43.043251],"type":"Point"}
}