{
  "type": "Feature",
  "properties": {
    "iso:country":"US",
    "sg:address":"1011 N Broadway",
    "sg:city":"De Pere",
    "sg:classifiers":[
        {
            "category":"Banks & Credit Unions",
            "subcategory":"Bank",
            "type":"Services"
        }
    ],
    "sg:phone":"+1 920 425 1400",
    "sg:postcode":"54115",
    "sg:province":"WI",
    "wof:name":"Nicolet National Bank",
    "wof:placetype":"venue"
},
  "geometry": {"coordinates":[-88.055037,44.459173],"type":"Point"}
}