{
  "type": "Feature",
  "properties": {
    "iso:country":"US",
    "sg:address":"168 Proudfit St",
    "sg:city":"Madison",
    "sg:classifiers":[
        {
            "category":"Building & Trades",
            "subcategory":"Construction",
            "type":"Services"
        }
    ],
    "sg:phone":"+1 608 255 3600",
    "sg:postcode":"53715",
    "sg:province":"WI",
    "sg:tags":[
        "general",
        "contractor"
    ],
    "wof:name":"Mainstreet Co",
    "wof:placetype":"venue"
},
  "geometry": {"coordinates":[-89.39304199999999,43.065638],"type":"Point"}
}