{
  "type": "Feature",
  "properties": {
    "addr:full":"3210 Jordan Rd Stevens Point WI 54481",
    "addr:housenumber":"3210",
    "addr:postcode":"54481",
    "addr:street":"Jordan Rd",
    "iso:country":"US",
    "sg:address":"3210 Jordan Rd",
    "sg:city":"Stevens Point",
    "sg:classifiers":[
        {
            "category":"Retail",
            "subcategory":"Repair Shop",
            "type":"Services"
        }
    ],
    "sg:phone":"+1 715 341 2111",
    "sg:postcode":"54481",
    "sg:province":"WI",
    "sg:tags":[
        "appliance",
        "electrical"
    ],
    "wof:name":"Jim's Service & Appliance Rpr",
    "wof:placetype":"venue"
},
  "geometry": {"coordinates":[-89.563973,44.577576],"type":"Point"}
}