{
  "type": "Feature",
  "properties": {
    "iso:country":"US",
    "sg:address":"7835 W Burleigh St",
    "sg:city":"Milwaukee",
    "sg:classifiers":[
        {
            "category":"Restaurant",
            "type":"Food & Drink"
        }
    ],
    "sg:phone":"+1 414 445 1141",
    "sg:postcode":"53222",
    "sg:province":"WI",
    "sg:tags":[
        "eating"
    ],
    "wof:name":"Z Cafe",
    "wof:placetype":"venue"
},
  "geometry": {"coordinates":[-88.010723,43.075208],"type":"Point"}
}