{
  "type": "Feature",
  "properties": {
    "addr:full":"10080 Water St N Sister Bay WI 54234",
    "addr:housenumber":"10080",
    "addr:postcode":"54234",
    "addr:street":"Water St N",
    "iso:country":"US",
    "sg:address":"10080 Water St N",
    "sg:city":"Sister Bay",
    "sg:classifiers":[
        {
            "category":"Travel",
            "subcategory":"Hotels & Motels",
            "type":"Entertainment"
        }
    ],
    "sg:phone":"+1 920 854 2321",
    "sg:postcode":"54234",
    "sg:province":"WI",
    "sg:tags":[
        "operation"
    ],
    "wof:name":"Pine Grove Motel",
    "wof:placetype":"venue"
},
  "geometry": {"coordinates":[-87.171829,45.161428],"type":"Point"}
}