{
  "type": "Feature",
  "properties": {
    "iso:country":"US",
    "sg:address":"10712 W Hampton Ave",
    "sg:city":"Milwaukee",
    "sg:classifiers":[
        {
            "category":"Autos & Motor Vehicles",
            "subcategory":"Automobile Sales",
            "type":"Retail Goods"
        }
    ],
    "sg:phone":"+1 414 461 3661",
    "sg:postcode":"53225",
    "sg:province":"WI",
    "sg:tags":[
        "car",
        "used",
        "dealer"
    ],
    "wof:name":"Super Service Inc",
    "wof:placetype":"venue"
},
  "geometry": {"coordinates":[-88.049044,43.104903],"type":"Point"}
}