{
  "type": "Feature",
  "properties": {
    "iso:country":"US",
    "sg:address":"3013 W North Ave",
    "sg:city":"Milwaukee",
    "sg:classifiers":[
        {
            "category":"Food & Beverages",
            "subcategory":"Liquor & Beverages",
            "type":"Retail Goods"
        }
    ],
    "sg:phone":"+1 414 264 2222",
    "sg:postcode":"53208",
    "sg:province":"WI",
    "sg:tags":[
        "alcoholic"
    ],
    "wof:name":"Love Child Liquor",
    "wof:placetype":"venue"
},
  "geometry": {"coordinates":[-87.95165799999999,43.06053],"type":"Point"}
}