{
  "type": "Feature",
  "properties": {
    "iso:country":"US",
    "sg:address":"212 Iroquois Ave",
    "sg:city":"Green Bay",
    "sg:classifiers":[
        {
            "category":"Organizations",
            "subcategory":"Religious Organization",
            "type":"Services"
        }
    ],
    "sg:phone":"+1 920 431 0367",
    "sg:postcode":"54301",
    "sg:province":"WI",
    "wof:name":"CPE Ministry Program",
    "wof:placetype":"venue"
},
  "geometry": {"coordinates":[-88.02990699999999,44.476132],"type":"Point"}
}