{
  "type": "Feature",
  "properties": {
    "iso:country":"US",
    "sg:address":"4575 S 5th St",
    "sg:city":"Milwaukee",
    "sg:classifiers":[
        {
            "category":"Organizations",
            "subcategory":"Professional Association",
            "type":"Services"
        }
    ],
    "sg:phone":"+1 414 482 4620",
    "sg:postcode":"53207",
    "sg:province":"WI",
    "sg:website":"www.tops.org",
    "wof:name":"Tops Club Inc",
    "wof:placetype":"venue"
},
  "geometry": {"coordinates":[-87.917087,42.961238],"type":"Point"}
}