{
  "type": "Feature",
  "properties": {
    "iso:country":"US",
    "sg:address":"7325 W Forest Home Ave",
    "sg:city":"Milwaukee",
    "sg:classifiers":[
        {
            "category":"Government",
            "subcategory":"Office",
            "type":"Public Place"
        }
    ],
    "sg:phone":"+1 414 543 5500",
    "sg:postcode":"53220",
    "sg:province":"WI",
    "sg:tags":[
        "city"
    ],
    "wof:name":"Greenfield City Hall",
    "wof:placetype":"venue"
},
  "geometry": {"coordinates":[-88.005313,42.966029],"type":"Point"}
}