{
  "type": "Feature",
  "properties": {
    "iso:country":"US",
    "sg:address":"753 10th Ave Ct",
    "sg:city":"Monroe",
    "sg:classifiers":[
        {
            "category":"Shopping",
            "type":"Retail Goods"
        }
    ],
    "sg:phone":"+1 608 325 6606",
    "sg:postcode":"53566",
    "sg:province":"WI",
    "sg:tags":[
        "hearing",
        "equipment",
        "supply",
        "impaired"
    ],
    "wof:name":"Hearing Aid Ctr",
    "wof:placetype":"venue"
},
  "geometry": {"coordinates":[-89.646525,42.603792],"type":"Point"}
}