{
  "type": "Feature",
  "properties": {
    "iso:country":"US",
    "sg:address":"310 4th St",
    "sg:city":"Algoma",
    "sg:classifiers":[
        {
            "category":"Personal",
            "subcategory":"Beauty Salon",
            "type":"Services"
        }
    ],
    "sg:phone":"+1 920 487 9700",
    "sg:postcode":"54201",
    "sg:province":"WI",
    "wof:name":"Top Of The Plaza Boutique",
    "wof:placetype":"venue"
},
  "geometry": {"coordinates":[-87.438478,44.610367],"type":"Point"}
}