{
  "type": "Feature",
  "properties": {
    "iso:country":"US",
    "sg:address":"5303 28th St",
    "sg:city":"Kenosha",
    "sg:classifiers":[
        {
            "category":"Professional",
            "subcategory":"Accounting & Tax Preparation",
            "type":"Services"
        },
        {
            "category":"Professional",
            "subcategory":"Management & Consulting",
            "type":"Services"
        },
        {
            "category":"Banks & Credit Unions",
            "subcategory":"Financial Services",
            "type":"Services"
        }
    ],
    "sg:phone":"+1 262 652 6767",
    "sg:postcode":"53144",
    "sg:province":"WI",
    "sg:tags":[
        "consultant",
        "financing",
        "planning",
        "return",
        "preparation-business"
    ],
    "wof:name":"Barter Financial Planning Services",
    "wof:placetype":"venue"
},
  "geometry": {"coordinates":[-87.87272400000001,42.613671],"type":"Point"}
}