{
  "type": "Feature",
  "properties": {
    "addr:full":"348 W Madison St Waterloo WI 53594",
    "addr:housenumber":"348",
    "addr:postcode":"53594",
    "addr:street":"W Madison St",
    "iso:country":"US",
    "sg:address":"348 W Madison St",
    "sg:city":"Waterloo",
    "sg:classifiers":[
        {
            "category":"Organizations",
            "subcategory":"Religious Organization",
            "type":"Services"
        }
    ],
    "sg:phone":"+1 920 478 2520",
    "sg:postcode":"53594",
    "sg:province":"WI",
    "sg:tags":[
        "church"
    ],
    "wof:name":"United Methodist Church",
    "wof:placetype":"venue"
},
  "geometry": {"coordinates":[-88.992682,43.18369],"type":"Point"}
}