{
  "type": "Feature",
  "properties": {
    "iso:country":"US",
    "sg:address":"535 State Hwy 70",
    "sg:city":"Park Falls",
    "sg:classifiers":[
        {
            "category":"Building & Trades",
            "subcategory":"Construction",
            "type":"Services"
        }
    ],
    "sg:phone":"+1 715 762 4220",
    "sg:postcode":"54552",
    "sg:province":"WI",
    "sg:tags":[
        "dry wall",
        "contractor"
    ],
    "wof:name":"Chuck's Drywall",
    "wof:placetype":"venue"
},
  "geometry": {"coordinates":[-90.063848,45.88473],"type":"Point"}
}