{
  "type": "Feature",
  "properties": {
    "addr:full":"591 115th St Amery WI 54001",
    "addr:housenumber":"591",
    "addr:postcode":"54001",
    "addr:street":"115Th St",
    "iso:country":"US",
    "sg:address":"591 115th St",
    "sg:city":"Amery",
    "sg:classifiers":[
        {
            "category":"Farming",
            "subcategory":"Livestock Farm",
            "type":"Manufacturing & Wholesale Goods"
        }
    ],
    "sg:phone":"+1 715 268 6317",
    "sg:postcode":"54001",
    "sg:province":"WI",
    "sg:tags":[
        "beef",
        "feedlot",
        "cattle"
    ],
    "wof:name":"Mark Roberts",
    "wof:placetype":"venue"
},
  "geometry": {"coordinates":[-92.397886,45.295455],"type":"Point"}
}