{
  "type": "Feature",
  "properties": {
    "iso:country":"US",
    "sg:address":"2409 Jacato Dr",
    "sg:city":"Racine",
    "sg:classifiers":[
        {
            "category":"Social Services",
            "subcategory":"Child Care",
            "type":"Services"
        },
        {
            "category":"Professional",
            "type":"Services"
        }
    ],
    "sg:phone":"+1 262 634 2853",
    "sg:postcode":"53404",
    "sg:province":"WI",
    "wof:name":"D N Wilson",
    "wof:placetype":"venue"
},
  "geometry": {"coordinates":[-87.811643,42.751219],"type":"Point"}
}