{
  "type": "Feature",
  "properties": {
    "iso:country":"US",
    "sg:address":"9335 Co Rd I",
    "sg:city":"Eleva",
    "sg:classifiers":[
        {
            "category":"Farming",
            "subcategory":"Livestock Farm",
            "type":"Manufacturing & Wholesale Goods"
        }
    ],
    "sg:phone":"+1 715 878 4251",
    "sg:postcode":"54738",
    "sg:province":"WI",
    "sg:tags":[
        "beef",
        "feedlot",
        "cattle"
    ],
    "wof:name":"Karl Kinderman",
    "wof:placetype":"venue"
},
  "geometry": {"coordinates":[-91.427693,44.697433],"type":"Point"}
}