{
  "type": "Feature",
  "properties": {
    "addr:full":"541 288th Ave Burlington WI 53105",
    "addr:housenumber":"541",
    "addr:postcode":"53105",
    "addr:street":"288Th Ave",
    "iso:country":"US",
    "sg:address":"541 288th Ave",
    "sg:city":"Burlington",
    "sg:classifiers":[
        {
            "category":"Farming",
            "subcategory":"Dairy Farm",
            "type":"Manufacturing & Wholesale Goods"
        }
    ],
    "sg:phone":"+1 262 878 3739",
    "sg:postcode":"53105",
    "sg:province":"WI",
    "wof:name":"Andrew Dorn",
    "wof:placetype":"venue"
},
  "geometry": {"coordinates":[-88.159302,42.664589],"type":"Point"}
}