{
  "type": "Feature",
  "properties": {
    "iso:country":"US",
    "sg:address":"2413 Ravenswood Rd",
    "sg:city":"Madison",
    "sg:classifiers":[
        {
            "category":"Personal",
            "type":"Services"
        }
    ],
    "sg:phone":"+1 608 271 6047",
    "sg:postcode":"53711",
    "sg:province":"WI",
    "wof:name":"Creative Quilting By Sandra",
    "wof:placetype":"venue"
},
  "geometry": {"coordinates":[-89.491164,43.028357],"type":"Point"}
}