{
  "type": "Feature",
  "properties": {
    "iso:country":"US",
    "sg:address":"5131 32nd St S",
    "sg:city":"Wisconsin Rapids",
    "sg:classifiers":[
        {
            "category":"Building & Trades",
            "subcategory":"Construction",
            "type":"Services"
        }
    ],
    "sg:phone":"+1 715 424 4979",
    "sg:postcode":"54494",
    "sg:province":"WI",
    "sg:tags":[
        "carpentry",
        "contractor"
    ],
    "wof:name":"Wisen Woods",
    "wof:placetype":"venue"
},
  "geometry": {"coordinates":[-89.78559199999999,44.347796],"type":"Point"}
}