{
  "type": "Feature",
  "properties": {
    "iso:country":"US",
    "sg:address":"246 Lincoln St",
    "sg:city":"Amherst",
    "sg:classifiers":[
        {
            "category":"Building & Trades",
            "subcategory":"Construction",
            "type":"Services"
        }
    ],
    "sg:phone":"+1 715 824 3298",
    "sg:postcode":"54406",
    "sg:province":"WI",
    "sg:tags":[
        "hanging",
        "contractor"
    ],
    "wof:name":"Central Wsconsin Pntg Papering",
    "wof:placetype":"venue"
},
  "geometry": {"coordinates":[-89.289027,44.44962],"type":"Point"}
}