{
  "type": "Feature",
  "properties": {
    "iso:country":"US",
    "sg:address":"5301 22nd Ave",
    "sg:city":"Kenosha",
    "sg:classifiers":[
        {
            "category":"Bars & Pubs",
            "type":"Food & Drink"
        }
    ],
    "sg:phone":"+1 262 605 6900",
    "sg:postcode":"53140",
    "sg:province":"WI",
    "wof:name":"Slim's",
    "wof:placetype":"venue"
},
  "geometry": {"coordinates":[-87.835706,42.586123],"type":"Point"}
}