{
  "type": "Feature",
  "properties": {
    "iso:country":"US",
    "sg:address":"7260 S Clement Ave",
    "sg:city":"Oak Creek",
    "sg:classifiers":[
        {
            "category":"Professional",
            "subcategory":"Accounting & Tax Preparation",
            "type":"Services"
        }
    ],
    "sg:phone":"+1 414 764 3631",
    "sg:postcode":"53154",
    "sg:province":"WI",
    "wof:name":"G & S Enterprises",
    "wof:placetype":"venue"
},
  "geometry": {"coordinates":[-87.896046,42.91322],"type":"Point"}
}