{
  "type": "Feature",
  "properties": {
    "addr:full":"2166 South Ave Lomira WI 53048",
    "addr:housenumber":"2166",
    "addr:postcode":"53048",
    "addr:street":"South Ave",
    "iso:country":"US",
    "sg:address":"2166 South Ave",
    "sg:city":"Lomira",
    "sg:classifiers":[
        {
            "category":"Government",
            "subcategory":"Fire Station",
            "type":"Public Place"
        }
    ],
    "sg:phone":"+1 920 583 3900",
    "sg:postcode":"53048",
    "sg:province":"WI",
    "sg:tags":[
        "volunteer"
    ],
    "wof:name":"Knowles Volunteer Fire Dept",
    "wof:placetype":"venue"
},
  "geometry": {"coordinates":[-88.50208499999999,43.571949],"type":"Point"}
}