{
  "type": "Feature",
  "properties": {
    "addr:full":"214 Spring St Oregon WI 53575",
    "addr:housenumber":"214",
    "addr:postcode":"53575",
    "addr:street":"Spring St",
    "iso:country":"US",
    "sg:address":"214 Spring St",
    "sg:city":"Oregon",
    "sg:classifiers":[
        {
            "category":"Sports & Exercise",
            "subcategory":"Bowling",
            "type":"Entertainment"
        }
    ],
    "sg:phone":"+1 608 835 3133",
    "sg:postcode":"53575",
    "sg:province":"WI",
    "sg:tags":[
        "lounge",
        "center"
    ],
    "wof:name":"Oregon Bowl LLC",
    "wof:placetype":"venue"
},
  "geometry": {"coordinates":[-89.38306900000001,42.926278],"type":"Point"}
}