{
  "type": "Feature",
  "properties": {
    "iso:country":"US",
    "sg:address":"911 Cove Rd",
    "sg:city":"Sturgeon Bay",
    "sg:classifiers":[
        {
            "category":"Shopping",
            "subcategory":"Clothing, Apparel, & Fashions",
            "type":"Retail Goods"
        }
    ],
    "sg:phone":"+1 920 743 4121",
    "sg:postcode":"54235",
    "sg:province":"WI",
    "sg:tags":[
        "shop",
        "drinking",
        "barber"
    ],
    "wof:name":"Orams Barber Shop",
    "wof:placetype":"venue"
},
  "geometry": {"coordinates":[-87.341285,44.825522],"type":"Point"}
}