{
  "type": "Feature",
  "properties": {
    "iso:country":"US",
    "sg:address":"30728 93rd St",
    "sg:city":"Burlington",
    "sg:classifiers":[
        {
            "category":"Home & Garden",
            "subcategory":"Garden Supply",
            "type":"Retail Goods"
        }
    ],
    "sg:phone":"+1 262 889 4301",
    "sg:postcode":"53105",
    "sg:province":"WI",
    "sg:tags":[
        "nursery",
        "gardening"
    ],
    "wof:name":"Paul Swartz Nursery & Garden Shop Inc",
    "wof:placetype":"venue"
},
  "geometry": {"coordinates":[-88.226997,42.580399],"type":"Point"}
}