{
  "type": "Feature",
  "properties": {
    "iso:country":"US",
    "sg:address":"1605 Monroe St",
    "sg:city":"Madison",
    "sg:classifiers":[
        {
            "category":"Education",
            "subcategory":"Special Training",
            "type":"Public Place"
        }
    ],
    "sg:phone":"+1 608 257 6699",
    "sg:postcode":"53711",
    "sg:province":"WI",
    "sg:tags":[
        "instruction",
        "music"
    ],
    "wof:name":"Guitar Studio",
    "wof:placetype":"venue"
},
  "geometry": {"coordinates":[-89.41369299999999,43.067133],"type":"Point"}
}