{
  "type": "Feature",
  "properties": {
    "iso:country":"US",
    "sg:address":"1405 S Coachlight Dr",
    "sg:city":"New Berlin",
    "sg:classifiers":[
        {
            "category":"Real Estate",
            "subcategory":"Real Estate Agent",
            "type":"Services"
        }
    ],
    "sg:phone":"+1 262 782 0041",
    "sg:postcode":"53151",
    "sg:province":"WI",
    "sg:tags":[
        "management"
    ],
    "wof:name":"Bell Property Management",
    "wof:placetype":"venue"
},
  "geometry": {"coordinates":[-88.113022,43.01438],"type":"Point"}
}