{
  "type": "Feature",
  "properties": {
    "iso:country":"US",
    "sg:address":"180 Cove Ct",
    "sg:city":"Nekoosa",
    "sg:classifiers":[
        {
            "category":"Building & Trades",
            "subcategory":"Cleaning & Sanitation",
            "type":"Services"
        }
    ],
    "sg:phone":"+1 715 325 7579",
    "sg:postcode":"54457",
    "sg:province":"WI",
    "sg:tags":[
        "maintenance"
    ],
    "wof:name":"B E Clean Janitorial Service",
    "wof:placetype":"venue"
},
  "geometry": {"coordinates":[-89.765314,44.231618],"type":"Point"}
}