{
  "type": "Feature",
  "properties": {
    "iso:country":"US",
    "sg:address":"301 Bukolt Ave",
    "sg:city":"Stevens Point",
    "sg:classifiers":[
        {
            "category":"Local Transit",
            "type":"Transportation"
        }
    ],
    "sg:phone":"+1 715 341 6901",
    "sg:postcode":"54481",
    "sg:province":"WI",
    "sg:tags":[
        "passenger"
    ],
    "wof:name":"Celebrity Limousine",
    "wof:placetype":"venue"
},
  "geometry": {"coordinates":[-89.593407,44.530533],"type":"Point"}
}