{
  "type": "Feature",
  "properties": {
    "iso:country":"US",
    "sg:address":"229 Rose St",
    "sg:city":"La Crosse",
    "sg:classifiers":[
        {
            "category":"Autos & Motor Vehicles",
            "subcategory":"Automobile Sales",
            "type":"Retail Goods"
        }
    ],
    "sg:phone":"+1 608 785 2277",
    "sg:postcode":"54603",
    "sg:province":"WI",
    "sg:tags":[
        "car",
        "dealer"
    ],
    "wof:name":"Auto 5000",
    "wof:placetype":"venue"
},
  "geometry": {"coordinates":[-91.24817299999999,43.829207],"type":"Point"}
}