{
  "type": "Feature",
  "properties": {
    "iso:country":"US",
    "sg:address":"1235 Apache Trl",
    "sg:city":"Brookfield",
    "sg:classifiers":[
        {
            "category":"Professional",
            "subcategory":"Employment Agencies",
            "type":"Services"
        }
    ],
    "sg:phone":"+1 262 814 1003",
    "sg:postcode":"53005",
    "sg:province":"WI",
    "wof:name":"Mackenzie Associates Inc",
    "wof:placetype":"venue"
},
  "geometry": {"coordinates":[-88.115793,43.04594],"type":"Point"}
}