{
  "type": "Feature",
  "properties": {
    "addr:full":"1523 24th St Two Rivers WI 54241",
    "addr:housenumber":"1523",
    "addr:postcode":"54241",
    "addr:street":"24Th St",
    "iso:country":"US",
    "sg:address":"1523 24th St",
    "sg:city":"Two Rivers",
    "sg:classifiers":[
        {
            "category":"Organizations",
            "subcategory":"Non-profit Organization",
            "type":"Services"
        }
    ],
    "sg:phone":"+1 920 793 1678",
    "sg:postcode":"54241",
    "sg:province":"WI",
    "sg:tags":[
        "social"
    ],
    "wof:name":"Candlelighters Lakeshore Cnty",
    "wof:placetype":"venue"
},
  "geometry": {"coordinates":[-87.56975199999999,44.155562],"type":"Point"}
}