{
  "type": "Feature",
  "properties": {
    "addr:full":"3121 13th St Kenosha WI 53144",
    "addr:housenumber":"3121",
    "addr:postcode":"53144",
    "addr:street":"13Th St",
    "iso:country":"US",
    "sg:address":"3121 13th St",
    "sg:city":"Kenosha",
    "sg:classifiers":[
        {
            "category":"Freight",
            "type":"Transportation"
        }
    ],
    "sg:phone":"+1 262 552 8942",
    "sg:postcode":"53144",
    "sg:province":"WI",
    "wof:name":"Buckos Ambulatory Transport",
    "wof:placetype":"venue"
},
  "geometry": {"coordinates":[-87.846425,42.636464],"type":"Point"}
}