{
  "type": "Feature",
  "properties": {
    "iso:country":"US",
    "sg:address":"12711 Bristol Rd",
    "sg:city":"Kenosha",
    "sg:classifiers":[
        {
            "category":"Bars & Pubs",
            "type":"Food & Drink"
        },
        {
            "category":"Food & Beverages",
            "subcategory":"Liquor & Beverages",
            "type":"Retail Goods"
        }
    ],
    "sg:phone":"+1 262 857 2682",
    "sg:postcode":"53142",
    "sg:province":"WI",
    "sg:tags":[
        "tavern",
        "bartending"
    ],
    "wof:name":"Grizzly Saloon",
    "wof:placetype":"venue"
},
  "geometry": {"coordinates":[-88.02524200000001,42.496449],"type":"Point"}
}