{
  "type": "Feature",
  "properties": {
    "iso:country":"US",
    "sg:address":"857 3rd St",
    "sg:city":"Menasha",
    "sg:classifiers":[
        {
            "category":"Building & Trades",
            "subcategory":"Construction",
            "type":"Services"
        }
    ],
    "sg:phone":"+1 920 722 4388",
    "sg:postcode":"54952",
    "sg:province":"WI",
    "sg:tags":[
        "resurfacing",
        "laying",
        "refinishing",
        "floor"
    ],
    "wof:name":"Andrea Camozzi Hardwood Flrng",
    "wof:placetype":"venue"
},
  "geometry": {"coordinates":[-88.43141199999999,44.204571],"type":"Point"}
}