{
  "type": "Feature",
  "properties": {
    "addr:full":"28 Langdon St Madison WI 53703",
    "addr:housenumber":"28",
    "addr:postcode":"53703",
    "addr:street":"Langdon St",
    "iso:country":"US",
    "sg:address":"28 Langdon St",
    "sg:city":"Madison",
    "sg:classifiers":[
        {
            "category":"Travel",
            "subcategory":"Hotels & Motels",
            "type":"Entertainment"
        }
    ],
    "sg:phone":"+1 608 257 2519",
    "sg:postcode":"53703",
    "sg:province":"WI",
    "sg:tags":[
        "membership",
        "lodging"
    ],
    "wof:name":"Alpha Phi",
    "wof:placetype":"venue"
},
  "geometry": {"coordinates":[-89.39055,43.078261],"type":"Point"}
}