{
  "type": "Feature",
  "properties": {
    "addr:full":"2994 State Hwy 23 Superior WI 54880",
    "addr:housenumber":"2994",
    "addr:postcode":"54880",
    "addr:street":"State Hwy 23",
    "iso:country":"US",
    "sg:address":"2994 State Hwy 23",
    "sg:city":"Superior",
    "sg:classifiers":[
        {
            "category":"Retail",
            "subcategory":"Auto Repair",
            "type":"Services"
        }
    ],
    "sg:phone":"+1 218 626 3535",
    "sg:postcode":"54880",
    "sg:province":"WI",
    "sg:tags":[
        "body"
    ],
    "wof:name":"Vine Body Shop",
    "wof:placetype":"venue"
},
  "geometry": {"coordinates":[-92.287541,46.656411],"type":"Point"}
}