{
  "type": "Feature",
  "properties": {
    "iso:country":"US",
    "sg:address":"1113 N Sherman Ave",
    "sg:city":"Madison",
    "sg:classifiers":[
        {
            "category":"Professional",
            "subcategory":"Business Services",
            "type":"Services"
        }
    ],
    "sg:phone":"+1 608 245 1443",
    "sg:postcode":"53704",
    "sg:province":"WI",
    "wof:name":"Wizards Wyeth Digital",
    "wof:placetype":"venue"
},
  "geometry": {"coordinates":[-89.363725,43.112591],"type":"Point"}
}