{
  "type": "Feature",
  "properties": {
    "iso:country":"US",
    "sg:address":"6353 Co Rd K",
    "sg:city":"Phillips",
    "sg:classifiers":[
        {
            "category":"Shopping",
            "subcategory":"Used Merchandise",
            "type":"Retail Goods"
        }
    ],
    "sg:phone":"+1 715 339 3291",
    "sg:postcode":"54556",
    "sg:province":"WI",
    "wof:name":"Riverside Antiques",
    "wof:placetype":"venue"
},
  "geometry": {"coordinates":[-90.290971,45.605383],"type":"Point"}
}