{
  "type": "Feature",
  "properties": {
    "iso:country":"US",
    "sg:address":"3210 Watford Way",
    "sg:city":"Madison",
    "sg:classifiers":[
        {
            "category":"Wholesale",
            "subcategory":"Non-durable Goods",
            "type":"Manufacturing & Wholesale Goods"
        }
    ],
    "sg:phone":"+1 608 273 4400",
    "sg:postcode":"53713",
    "sg:province":"WI",
    "sg:tags":[
        "advertising"
    ],
    "sg:website":"www.cummingspromotions.com",
    "wof:name":"Cummings Enterprises Inc",
    "wof:placetype":"venue"
},
  "geometry": {"coordinates":[-89.400565,43.027803],"type":"Point"}
}