{
  "type": "Feature",
  "properties": {
    "addr:full":"28678 120th Ave Cadott WI 54727",
    "addr:housenumber":"28678",
    "addr:postcode":"54727",
    "addr:street":"120Th Ave",
    "iso:country":"US",
    "sg:address":"28678 120th Ave",
    "sg:city":"Cadott",
    "sg:classifiers":[
        {
            "category":"Farming",
            "subcategory":"Dairy Farm",
            "type":"Manufacturing & Wholesale Goods"
        }
    ],
    "sg:phone":"+1 715 289 3873",
    "sg:postcode":"54727",
    "sg:province":"WI",
    "wof:name":"Scott Pozarski",
    "wof:placetype":"venue"
},
  "geometry": {"coordinates":[-91.092895,45.016727],"type":"Point"}
}