{
  "type": "Feature",
  "properties": {
    "iso:country":"US",
    "sg:address":"7572 Co Rd Vv",
    "sg:city":"Cassville",
    "sg:classifiers":[
        {
            "category":"Farming",
            "subcategory":"Livestock Farm",
            "type":"Manufacturing & Wholesale Goods"
        }
    ],
    "sg:phone":"+1 608 794 2146",
    "sg:postcode":"53806",
    "sg:province":"WI",
    "sg:tags":[
        "corn",
        "beef",
        "feedlot",
        "cattle"
    ],
    "wof:name":"Hochhausen Brothers",
    "wof:placetype":"venue"
},
  "geometry": {"coordinates":[-91.032408,42.783919],"type":"Point"}
}