{
  "type": "Feature",
  "properties": {
    "iso:country":"US",
    "sg:address":"3357 N 36th St",
    "sg:city":"Milwaukee",
    "sg:classifiers":[
        {
            "category":"Social Services",
            "subcategory":"Child Care",
            "type":"Services"
        }
    ],
    "sg:phone":"+1 414 444 2611",
    "sg:postcode":"53216",
    "sg:province":"WI",
    "wof:name":"Shenika's Loving Hands",
    "wof:placetype":"venue"
},
  "geometry": {"coordinates":[-87.958512,43.079984],"type":"Point"}
}