{
  "type": "Feature",
  "properties": {
    "iso:country":"US",
    "sg:address":"10845 Moore Ave",
    "sg:city":"Upson",
    "sg:classifiers":[
        {
            "category":"Government",
            "subcategory":"Office",
            "type":"Public Place"
        }
    ],
    "sg:phone":"+1 715 561 3501",
    "sg:postcode":"54565",
    "sg:province":"WI",
    "sg:tags":[
        "village"
    ],
    "wof:name":"Upson Town Garage",
    "wof:placetype":"venue"
},
  "geometry": {"coordinates":[-90.406081,46.367304],"type":"Point"}
}