{
  "type": "Feature",
  "properties": {
    "iso:country":"US",
    "sg:address":"325 Curtis Ave",
    "sg:city":"Hatley",
    "sg:classifiers":[
        {
            "category":"Recreation",
            "type":"Entertainment"
        }
    ],
    "sg:phone":"+1 715 446 3596",
    "sg:postcode":"54440",
    "sg:province":"WI",
    "sg:tags":[
        "sporting"
    ],
    "wof:name":"Plover River Outfitters",
    "wof:placetype":"venue"
},
  "geometry": {"coordinates":[-89.340311,44.885847],"type":"Point"}
}