{
  "type": "Feature",
  "properties": {
    "iso:country":"US",
    "sg:address":"2238 N Dr Martin Luther King Dr",
    "sg:city":"Milwaukee",
    "sg:classifiers":[
        {
            "category":"Shopping",
            "subcategory":"Tobacco",
            "type":"Retail Goods"
        }
    ],
    "sg:phone":"+1 414 265 5033",
    "sg:postcode":"53212",
    "sg:province":"WI",
    "sg:tags":[
        "cigarette",
        "cigar"
    ],
    "wof:name":"SH Tobacco-North Ave",
    "wof:placetype":"venue"
},
  "geometry": {"coordinates":[-87.914151,43.059572],"type":"Point"}
}