{
  "type": "Feature",
  "properties": {
    "addr:full":"999 S Wells St Lake Geneva WI 53147",
    "addr:housenumber":"999",
    "addr:postcode":"53147",
    "addr:street":"S Wells St",
    "iso:country":"US",
    "sg:address":"999 S Wells St",
    "sg:city":"Lake Geneva",
    "sg:classifiers":[
        {
            "category":"Professional",
            "type":"Services"
        }
    ],
    "sg:phone":"+1 262 248 1925",
    "sg:postcode":"53147",
    "sg:province":"WI",
    "sg:tags":[
        "establishment"
    ],
    "wof:name":"Trostel Seg Inc",
    "wof:placetype":"venue"
},
  "geometry": {"coordinates":[-88.42355499999999,42.581281],"type":"Point"}
}