{
  "type": "Feature",
  "properties": {
    "addr:full":"114 E Center St South Wayne WI 53587",
    "addr:housenumber":"114",
    "addr:postcode":"53587",
    "addr:street":"E Center St",
    "iso:country":"US",
    "sg:address":"114 E Center St",
    "sg:city":"South Wayne",
    "sg:classifiers":[
        {
            "category":"Banks & Credit Unions",
            "subcategory":"Bank",
            "type":"Services"
        }
    ],
    "sg:phone":"+1 608 439 5391",
    "sg:postcode":"53587",
    "sg:province":"WI",
    "sg:tags":[
        "state",
        "commercial"
    ],
    "wof:name":"F & M Bank-Wisconsin",
    "wof:placetype":"venue"
},
  "geometry": {"coordinates":[-89.879825,42.569013],"type":"Point"}
}