{
  "type": "Feature",
  "properties": {
    "addr:full":"435 State Hwy 32 Sheboygan Falls WI 53085",
    "addr:housenumber":"435",
    "addr:postcode":"53085",
    "addr:street":"State Hwy 32",
    "iso:country":"US",
    "sg:address":"435 State Hwy 32",
    "sg:city":"Sheboygan Falls",
    "sg:classifiers":[
        {
            "category":"Freight",
            "type":"Transportation"
        }
    ],
    "sg:phone":"+1 920 467 2876",
    "sg:postcode":"53085",
    "sg:province":"WI",
    "sg:tags":[
        "commercial",
        "storage",
        "special"
    ],
    "wof:name":"Highway 32 Storage",
    "wof:placetype":"venue"
},
  "geometry": {"coordinates":[-87.81977500000001,43.742557],"type":"Point"}
}