{
  "type": "Feature",
  "properties": {
    "addr:full":"212 S Main St Waupaca WI 54981",
    "addr:housenumber":"212",
    "addr:postcode":"54981",
    "addr:street":"S Main St",
    "iso:country":"US",
    "sg:address":"212 S Main St",
    "sg:city":"Waupaca",
    "sg:classifiers":[
        {
            "category":"Personal",
            "subcategory":"Beauty Salon",
            "type":"Services"
        }
    ],
    "sg:phone":"+1 715 258 0212",
    "sg:postcode":"54981",
    "sg:province":"WI",
    "sg:tags":[
        "shop"
    ],
    "wof:name":"Studio 212 Hair Salon",
    "wof:placetype":"venue"
},
  "geometry": {"coordinates":[-89.08496700000001,44.356946],"type":"Point"}
}