{
  "type": "Feature",
  "properties": {
    "iso:country":"US",
    "sg:address":"16363 W Ryerson Rd",
    "sg:city":"New Berlin",
    "sg:classifiers":[
        {
            "category":"Professional",
            "subcategory":"Computer Services",
            "type":"Services"
        }
    ],
    "sg:phone":"+1 262 787 0387",
    "sg:postcode":"53151",
    "sg:province":"WI",
    "sg:tags":[
        "processing",
        "datum"
    ],
    "wof:name":"E Funds Corp",
    "wof:placetype":"venue"
},
  "geometry": {"coordinates":[-88.119547,42.989611],"type":"Point"}
}