{
  "type": "Feature",
  "properties": {
    "iso:country":"US",
    "sg:address":"6333 N Green Bay Ave",
    "sg:city":"Milwaukee",
    "sg:classifiers":[
        {
            "category":"Building & Trades",
            "subcategory":"Landscaping Services",
            "type":"Services"
        }
    ],
    "sg:phone":"+1 414 540 6791",
    "sg:postcode":"53209",
    "sg:province":"WI",
    "sg:tags":[
        "landscape",
        "contractor"
    ],
    "wof:name":"Paul Conway Landscaping",
    "wof:placetype":"venue"
},
  "geometry": {"coordinates":[-87.93249900000001,43.132185],"type":"Point"}
}