{
  "type": "Feature",
  "properties": {
    "addr:full":"34085 Hidden Valley Dr Dousman WI 53118",
    "addr:housenumber":"34085",
    "addr:postcode":"53118",
    "addr:street":"Hidden Valley Dr",
    "iso:country":"US",
    "sg:address":"34085 Hidden Valley Dr",
    "sg:city":"Dousman",
    "sg:classifiers":[
        {
            "category":"Professional",
            "subcategory":"Management & Consulting",
            "type":"Services"
        }
    ],
    "sg:phone":"+1 262 392 3166",
    "sg:postcode":"53118",
    "sg:province":"WI",
    "wof:name":"Thorsten Consulting Group",
    "wof:placetype":"venue"
},
  "geometry": {"coordinates":[-88.425962,42.968444],"type":"Point"}
}