{
  "type": "Feature",
  "properties": {
    "addr:full":"9378 State Hwy 55 Kaukauna WI 54130",
    "addr:housenumber":"9378",
    "addr:postcode":"54130",
    "addr:street":"State Hwy 55",
    "iso:country":"US",
    "sg:address":"9378 State Hwy 55",
    "sg:city":"Kaukauna",
    "sg:classifiers":[
        {
            "category":"Retail",
            "subcategory":"Auto Repair",
            "type":"Services"
        }
    ],
    "sg:phone":"+1 920 766 5746",
    "sg:postcode":"54130",
    "sg:province":"WI",
    "sg:tags":[
        "repairing",
        "automobile"
    ],
    "wof:name":"Hiway 55 Auto Svc",
    "wof:placetype":"venue"
},
  "geometry": {"coordinates":[-88.283193,44.234119],"type":"Point"}
}