{
  "type": "Feature",
  "properties": {
    "iso:country":"US",
    "sg:address":"8632 Co Rd I",
    "sg:city":"Oxford",
    "sg:classifiers":[
        {
            "category":"Travel",
            "subcategory":"Hotels & Motels",
            "type":"Entertainment"
        }
    ],
    "sg:phone":"+1 608 586 5489",
    "sg:postcode":"53952",
    "sg:province":"WI",
    "sg:tags":[
        "operation"
    ],
    "wof:name":"Oxford House Bed & Breakfast",
    "wof:placetype":"venue"
},
  "geometry": {"coordinates":[-89.588756,43.772923],"type":"Point"}
}