{
  "type": "Feature",
  "properties": {
    "addr:full":"344 N Washington St St Croix Falls WI 54024",
    "addr:housenumber":"344",
    "addr:postcode":"54024",
    "addr:street":"N Washington St St",
    "iso:country":"US",
    "sg:address":"344 N Washington St",
    "sg:city":"St Croix Falls",
    "sg:classifiers":[
        {
            "category":"Building & Trades",
            "subcategory":"Plumbing",
            "type":"Services"
        }
    ],
    "sg:phone":"+1 715 483 3448",
    "sg:postcode":"54024",
    "sg:province":"WI",
    "sg:tags":[
        "heating",
        "contractor"
    ],
    "wof:name":"St Croix Plumbing Htg & AC",
    "wof:placetype":"venue"
},
  "geometry": {"coordinates":[-92.644746,45.415017],"type":"Point"}
}