{
  "type": "Feature",
  "properties": {
    "iso:country":"US",
    "sg:address":"106 S Fremont St",
    "sg:city":"Whitewater",
    "sg:classifiers":[
        {
            "category":"Shopping",
            "type":"Retail Goods"
        }
    ],
    "sg:phone":"+1 262 473 5561",
    "sg:postcode":"53190",
    "sg:province":"WI",
    "sg:tags":[
        "hearing",
        "equipment",
        "supply",
        "impaired"
    ],
    "wof:name":"Beltone Hearing Aid Ctr",
    "wof:placetype":"venue"
},
  "geometry": {"coordinates":[-88.73372000000001,42.834383],"type":"Point"}
}