{
  "type": "Feature",
  "properties": {
    "iso:country":"US",
    "sg:address":"12460 Skaugum Rd",
    "sg:city":"Ellison Bay",
    "sg:classifiers":[
        {
            "category":"Real Estate",
            "subcategory":"Real Estate Agent",
            "type":"Services"
        }
    ],
    "sg:phone":"+1 920 854 5167",
    "sg:postcode":"54210",
    "sg:province":"WI",
    "wof:name":"Ludwigsen Realty Venture",
    "wof:placetype":"venue"
},
  "geometry": {"coordinates":[-86.972866,45.276095],"type":"Point"}
}