{
  "type": "Feature",
  "properties": {
    "iso:country":"US",
    "sg:address":"6778 Co Rd B",
    "sg:city":"Menomonie",
    "sg:classifiers":[
        {
            "category":"Retail",
            "subcategory":"Repair Shop",
            "type":"Services"
        }
    ],
    "sg:phone":"+1 715 235 5557",
    "sg:postcode":"54751",
    "sg:province":"WI",
    "sg:tags":[
        "repairing",
        "saw"
    ],
    "wof:name":"Mike's Small Engines",
    "wof:placetype":"venue"
},
  "geometry": {"coordinates":[-91.854497,44.926224],"type":"Point"}
}