{
  "type": "Feature",
  "properties": {
    "iso:country":"US",
    "sg:address":"1940 Stephenson St",
    "sg:city":"Marinette",
    "sg:classifiers":[
        {
            "category":"Building & Trades",
            "subcategory":"Construction",
            "type":"Services"
        }
    ],
    "sg:phone":"+1 715 735 9564",
    "sg:postcode":"54143",
    "sg:province":"WI",
    "sg:tags":[
        "home",
        "builder"
    ],
    "wof:name":"Home Helpers",
    "wof:placetype":"venue"
},
  "geometry": {"coordinates":[-87.634269,45.10209],"type":"Point"}
}