{
  "type": "Feature",
  "properties": {
    "iso:country":"US",
    "sg:address":"6114 Hurd St",
    "sg:city":"Marshall",
    "sg:classifiers":[
        {
            "category":"Farming",
            "subcategory":"Dairy Farm",
            "type":"Manufacturing & Wholesale Goods"
        }
    ],
    "sg:phone":"+1 608 655 3924",
    "sg:postcode":"53559",
    "sg:province":"WI",
    "wof:name":"James Krause",
    "wof:placetype":"venue"
},
  "geometry": {"coordinates":[-89.056387,43.183021],"type":"Point"}
}