{
  "type": "Feature",
  "properties": {
    "iso:country":"US",
    "sg:address":"4510 Patzke Rd",
    "sg:city":"Racine",
    "sg:classifiers":[
        {
            "category":"Building & Trades",
            "subcategory":"Plumbing",
            "type":"Services"
        }
    ],
    "sg:phone":"+1 262 637 6300",
    "sg:postcode":"53405",
    "sg:province":"WI",
    "sg:tags":[
        "ventilating",
        "air",
        "heating",
        "conditioning",
        "contractor"
    ],
    "wof:name":"Temperature Controls of Racing",
    "wof:placetype":"venue"
},
  "geometry": {"coordinates":[-87.832747,42.76153],"type":"Point"}
}