{
  "type": "Feature",
  "properties": {
    "iso:country":"US",
    "sg:address":"11939 Macarthur Rd",
    "sg:city":"Chili",
    "sg:classifiers":[
        {
            "category":"Farming",
            "subcategory":"Farm",
            "type":"Manufacturing & Wholesale Goods"
        }
    ],
    "sg:phone":"+1 715 676 2169",
    "sg:postcode":"54420",
    "sg:province":"WI",
    "sg:tags":[
        "crop",
        "general"
    ],
    "wof:name":"Summer Vale Farm LLC",
    "wof:placetype":"venue"
},
  "geometry": {"coordinates":[-90.30997600000001,44.584853],"type":"Point"}
}