{
  "type": "Feature",
  "properties": {
    "iso:country":"US",
    "sg:address":"253 N Washington St",
    "sg:city":"Spring Green",
    "sg:classifiers":[
        {
            "category":"Organizations",
            "subcategory":"Religious Organization",
            "type":"Services"
        }
    ],
    "sg:phone":"+1 608 588 2028",
    "sg:postcode":"53588",
    "sg:province":"WI",
    "sg:tags":[
        "church"
    ],
    "wof:name":"St John's Catholic Church",
    "wof:placetype":"venue"
},
  "geometry": {"coordinates":[-90.06960100000001,43.178858],"type":"Point"}
}