{
  "type": "Feature",
  "properties": {
    "iso:country":"US",
    "sg:address":"6661 University Ave",
    "sg:city":"Middleton",
    "sg:classifiers":[
        {
            "category":"Utilities",
            "subcategory":"Mobile Phone",
            "type":"Services"
        }
    ],
    "sg:phone":"+1 608 446 1111",
    "sg:postcode":"53562",
    "sg:province":"WI",
    "sg:tags":[
        "communication",
        "electronic",
        "radiotelephone"
    ],
    "wof:name":"Einstein Pcs",
    "wof:placetype":"venue"
},
  "geometry": {"coordinates":[-89.494251,43.095315],"type":"Point"}
}