{
  "type": "Feature",
  "properties": {
    "addr:full":"136 W Grand Ave Beloit WI 53511",
    "addr:housenumber":"136",
    "addr:postcode":"53511",
    "addr:street":"W Grand Ave",
    "iso:country":"US",
    "sg:address":"136 W Grand Ave",
    "sg:city":"Beloit",
    "sg:classifiers":[
        {
            "category":"Building & Trades",
            "subcategory":"Construction",
            "type":"Services"
        },
        {
            "category":"Home & Garden",
            "subcategory":"Carpets & Floor Coverings",
            "type":"Retail Goods"
        }
    ],
    "sg:phone":"+1 608 363 8650",
    "sg:postcode":"53511",
    "sg:province":"WI",
    "sg:tags":[
        "dealer",
        "laying",
        "rug",
        "contractor"
    ],
    "wof:name":"Canyon Contract Flooring",
    "wof:placetype":"venue"
},
  "geometry": {"coordinates":[-89.037785,42.501405],"type":"Point"}
}