{
  "type": "Feature",
  "properties": {
    "iso:country":"US",
    "sg:address":"2010 W Moholt Dr",
    "sg:city":"Eau Claire",
    "sg:classifiers":[
        {
            "category":"Organizations",
            "subcategory":"Religious Organization",
            "type":"Services"
        }
    ],
    "sg:phone":"+1 715 835 5475",
    "sg:postcode":"54703",
    "sg:province":"WI",
    "wof:name":"Plymouth United Church Christ",
    "wof:placetype":"venue"
},
  "geometry": {"coordinates":[-91.53587,44.823881],"type":"Point"}
}