{
  "type": "Feature",
  "properties": {
    "iso:country":"US",
    "sg:address":"11423 Mine Rd",
    "sg:city":"Baraboo",
    "sg:classifiers":[
        {
            "category":"Manufacturing",
            "subcategory":"Watercraft",
            "type":"Manufacturing & Wholesale Goods"
        }
    ],
    "sg:phone":"+1 608 356 6476",
    "sg:postcode":"53913",
    "sg:province":"WI",
    "wof:name":"Freedom Boat Works",
    "wof:placetype":"venue"
},
  "geometry": {"coordinates":[-89.752555,43.449121],"type":"Point"}
}