{
  "type": "Feature",
  "properties": {
    "iso:country":"US",
    "sg:address":"2199 Lime Kiln Rd",
    "sg:city":"Baileys Harbor",
    "sg:classifiers":[
        {
            "category":"Building & Trades",
            "subcategory":"Landscaping Services",
            "type":"Services"
        }
    ],
    "sg:phone":"+1 920 854 5993",
    "sg:postcode":"54202",
    "sg:province":"WI",
    "sg:tags":[
        "landscape",
        "contractor"
    ],
    "wof:name":"Bridenhagen Tree & Landscape",
    "wof:placetype":"venue"
},
  "geometry": {"coordinates":[-87.105811,45.134581],"type":"Point"}
}