{
  "type": "Feature",
  "properties": {
    "iso:country":"US",
    "sg:address":"477 S Nicolet Rd",
    "sg:city":"Appleton",
    "sg:classifiers":[
        {
            "category":"Professional",
            "subcategory":"Management & Consulting",
            "type":"Services"
        },
        {
            "category":"Professional",
            "subcategory":"Accounting & Tax Preparation",
            "type":"Services"
        }
    ],
    "sg:phone":"+1 920 954 8526",
    "sg:postcode":"54914",
    "sg:province":"WI",
    "sg:tags":[
        "accountant"
    ],
    "wof:name":"Herrling Fisk & Co Ltd Inc",
    "wof:placetype":"venue"
},
  "geometry": {"coordinates":[-88.469281,44.260376],"type":"Point"}
}