{
  "type": "Feature",
  "properties": {
    "iso:country":"US",
    "sg:address":"5448 Co Rd D M",
    "sg:city":"De Forest",
    "sg:classifiers":[
        {
            "category":"Organizations",
            "subcategory":"Religious Organization",
            "type":"Services"
        }
    ],
    "sg:phone":"+1 608 846 4163",
    "sg:postcode":"53532",
    "sg:province":"WI",
    "wof:name":"Church",
    "wof:placetype":"venue"
},
  "geometry": {"coordinates":[-89.272674,43.29604],"type":"Point"}
}