{
  "type": "Feature",
  "properties": {
    "iso:country":"US",
    "sg:address":"6175 S 1st St",
    "sg:city":"Milwaukee",
    "sg:classifiers":[
        {
            "category":"Recreation",
            "type":"Entertainment"
        }
    ],
    "sg:phone":"+1 414 764 8640",
    "sg:postcode":"53207",
    "sg:province":"WI",
    "sg:tags":[
        "club",
        "membership"
    ],
    "wof:name":"Mike Heating & AC",
    "wof:placetype":"venue"
},
  "geometry": {"coordinates":[-87.911662,42.930738],"type":"Point"}
}