{
  "type": "Feature",
  "properties": {
    "addr:full":"3350 Lathrop Ave Racine WI 53405",
    "addr:housenumber":"3350",
    "addr:postcode":"53405",
    "addr:street":"Lathrop Ave",
    "iso:country":"US",
    "sg:address":"3350 Lathrop Ave",
    "sg:city":"Racine",
    "sg:classifiers":[
        {
            "category":"Organizations",
            "subcategory":"Religious Organization",
            "type":"Services"
        }
    ],
    "sg:phone":"+1 262 554 7010",
    "sg:postcode":"53405",
    "sg:province":"WI",
    "wof:name":"Holy Cross Lutheran Church",
    "wof:placetype":"venue"
},
  "geometry": {"coordinates":[-87.825997,42.692389],"type":"Point"}
}