{
  "type": "Feature",
  "properties": {
    "iso:country":"US",
    "sg:address":"1300 S Main St",
    "sg:city":"River Falls",
    "sg:classifiers":[
        {
            "category":"Travel",
            "subcategory":"Hotels & Motels",
            "type":"Entertainment"
        }
    ],
    "sg:phone":"+1 715 425 8181",
    "sg:postcode":"54022",
    "sg:province":"WI",
    "sg:tags":[
        "operation"
    ],
    "wof:name":"Motel River Falls",
    "wof:placetype":"venue"
},
  "geometry": {"coordinates":[-92.629371,44.842768],"type":"Point"}
}