{
  "type": "Feature",
  "properties": {
    "iso:country":"US",
    "sg:address":"1002 6th St E",
    "sg:city":"Menomonie",
    "sg:classifiers":[
        {
            "category":"Organizations",
            "subcategory":"Religious Organization",
            "type":"Services"
        }
    ],
    "sg:phone":"+1 715 235 7072",
    "sg:postcode":"54751",
    "sg:province":"WI",
    "wof:name":"Grace Episcopal Church",
    "wof:placetype":"venue"
},
  "geometry": {"coordinates":[-91.92338700000001,44.873737],"type":"Point"}
}