{
  "type": "Feature",
  "properties": {
    "addr:full":"739 Phillips Blvd Sauk City WI 53583",
    "addr:housenumber":"739",
    "addr:postcode":"53583",
    "addr:street":"Phillips Blvd",
    "iso:country":"US",
    "sg:address":"739 Phillips Blvd",
    "sg:city":"Sauk City",
    "sg:classifiers":[
        {
            "category":"Ice Cream",
            "type":"Food & Drink"
        }
    ],
    "sg:menulink":"http://www.allmenus.com/wi/sauk-city/192825-dairy-queen/menu/",
    "sg:phone":"+1 608 643 3872",
    "sg:postcode":"53583",
    "sg:province":"WI",
    "sg:tags":[
        "burger",
        "american"
    ],
    "wof:name":"Dairy Queen",
    "wof:placetype":"venue"
},
  "geometry": {"coordinates":[-89.73111900000001,43.271257],"type":"Point"}
}