{
  "type": "Feature",
  "properties": {
    "iso:country":"US",
    "sg:address":"2517 N 47th St",
    "sg:city":"Milwaukee",
    "sg:classifiers":[
        {
            "category":"Education",
            "subcategory":"School",
            "type":"Public Place"
        }
    ],
    "sg:phone":"+1 414 444 0434",
    "sg:postcode":"53210",
    "sg:province":"WI",
    "sg:tags":[
        "charter"
    ],
    "wof:name":"Central City Cyberschool of ML",
    "wof:placetype":"venue"
},
  "geometry": {"coordinates":[-87.97251300000001,43.065799],"type":"Point"}
}