{
  "type": "Feature",
  "properties": {
    "iso:country":"US",
    "sg:address":"13444 Mud Lake Rd",
    "sg:city":"New Auburn",
    "sg:classifiers":[
        {
            "category":"Manufacturing",
            "subcategory":"Tools & Machinery",
            "type":"Manufacturing & Wholesale Goods"
        }
    ],
    "sg:phone":"+1 715 967 2350",
    "sg:postcode":"54757",
    "sg:province":"WI",
    "sg:tags":[
        "industry",
        "mfg"
    ],
    "wof:name":"Walter Huse Bulldozing",
    "wof:placetype":"venue"
},
  "geometry": {"coordinates":[-91.354034,45.316439],"type":"Point"}
}