{
  "type": "Feature",
  "properties": {
    "iso:country":"US",
    "sg:address":"11430 W Bluemound Rd",
    "sg:city":"Milwaukee",
    "sg:classifiers":[
        {
            "category":"Banks & Credit Unions",
            "subcategory":"Bank",
            "type":"Services"
        }
    ],
    "sg:phone":"+1 414 453 6115",
    "sg:postcode":"53226",
    "sg:province":"WI",
    "sg:tags":[
        "banker",
        "mortgage"
    ],
    "wof:name":"Accepted Mortgage Finance",
    "wof:placetype":"venue"
},
  "geometry": {"coordinates":[-88.055819,43.035851],"type":"Point"}
}