{
  "type": "Feature",
  "properties": {
    "iso:country":"US",
    "sg:address":"4528 W Eau Claire Rd",
    "sg:city":"Janesville",
    "sg:classifiers":[
        {
            "category":"Utilities",
            "subcategory":"Telephone",
            "type":"Services"
        }
    ],
    "sg:phone":"+1 608 752 4244",
    "sg:postcode":"53548",
    "sg:province":"WI",
    "sg:tags":[
        "company"
    ],
    "wof:name":"Mrc Telecommunications Inc",
    "wof:placetype":"venue"
},
  "geometry": {"coordinates":[-89.07815,42.613534],"type":"Point"}
}