{
  "type": "Feature",
  "properties": {
    "iso:country":"US",
    "sg:address":"2116 Hunters Ln",
    "sg:city":"Grafton",
    "sg:classifiers":[
        {
            "category":"Freight",
            "type":"Transportation"
        }
    ],
    "sg:phone":"+1 262 983 6466",
    "sg:postcode":"53024",
    "sg:province":"WI",
    "sg:tags":[
        "operator",
        "local",
        "trucking"
    ],
    "wof:name":"Branch Trucking Inc",
    "wof:placetype":"venue"
},
  "geometry": {"coordinates":[-87.934066,43.314957],"type":"Point"}
}