{
  "type": "Feature",
  "properties": {
    "iso:country":"US",
    "sg:address":"2241 Main St",
    "sg:city":"Green Bay",
    "sg:classifiers":[
        {
            "category":"Banks & Credit Unions",
            "subcategory":"Bank",
            "type":"Services"
        }
    ],
    "sg:phone":"+1 920 431 8849",
    "sg:postcode":"54302",
    "sg:province":"WI",
    "wof:name":"Associated Bank",
    "wof:placetype":"venue"
},
  "geometry": {"coordinates":[-87.970794,44.484583],"type":"Point"}
}