{
  "type": "Feature",
  "properties": {
    "iso:country":"US",
    "sg:address":"4350 S 116th St",
    "sg:city":"Milwaukee",
    "sg:classifiers":[
        {
            "category":"Professional",
            "subcategory":"Business Services",
            "type":"Services"
        }
    ],
    "sg:phone":"+1 414 427 8115",
    "sg:postcode":"53228",
    "sg:province":"WI",
    "wof:name":"Nec Technologies",
    "wof:placetype":"venue"
},
  "geometry": {"coordinates":[-88.057607,42.965426],"type":"Point"}
}