{
  "type": "Feature",
  "properties": {
    "addr:full":"2033 W Congress St Milwaukee WI 53209",
    "addr:housenumber":"2033",
    "addr:postcode":"53209",
    "addr:street":"W Congress St",
    "iso:country":"US",
    "sg:address":"2033 W Congress St",
    "sg:city":"Milwaukee",
    "sg:classifiers":[
        {
            "category":"Organizations",
            "subcategory":"Religious Organization",
            "type":"Services"
        }
    ],
    "sg:phone":"+1 414 445 3303",
    "sg:postcode":"53209",
    "sg:province":"WI",
    "sg:tags":[
        "church"
    ],
    "wof:name":"Antioch Missionary Baptist Chr",
    "wof:placetype":"venue"
},
  "geometry": {"coordinates":[-87.937972,43.096914],"type":"Point"}
}