{
  "type": "Feature",
  "properties": {
    "iso:country":"US",
    "sg:address":"8520 W Arthur Ave",
    "sg:city":"Milwaukee",
    "sg:classifiers":[
        {
            "category":"Professional",
            "subcategory":"Business Services",
            "type":"Services"
        }
    ],
    "sg:phone":"+1 414 541 3213",
    "sg:postcode":"53227",
    "sg:province":"WI",
    "wof:name":"Fusion Partnered Solutions",
    "wof:placetype":"venue"
},
  "geometry": {"coordinates":[-88.02213,42.999259],"type":"Point"}
}