{
  "type": "Feature",
  "properties": {
    "addr:full":"815 1st St Plum City WI 54761",
    "addr:housenumber":"815",
    "addr:postcode":"54761",
    "addr:street":"1St St",
    "iso:country":"US",
    "sg:address":"815 1st St",
    "sg:city":"Plum City",
    "sg:classifiers":[
        {
            "category":"Farming",
            "subcategory":"Dairy Farm",
            "type":"Manufacturing & Wholesale Goods"
        }
    ],
    "sg:phone":"+1 715 647 3178",
    "sg:postcode":"54761",
    "sg:province":"WI",
    "wof:name":"Kenneth Holmstadt",
    "wof:placetype":"venue"
},
  "geometry": {"coordinates":[-92.190068,44.635294],"type":"Point"}
}