{
  "type": "Feature",
  "properties": {
    "iso:country":"US",
    "sg:address":"2727 E Layton Ave",
    "sg:city":"Cudahy",
    "sg:classifiers":[
        {
            "category":"Autos & Motor Vehicles",
            "subcategory":"Automobile Sales",
            "type":"Retail Goods"
        }
    ],
    "sg:phone":"+1 414 481 8500",
    "sg:postcode":"53110",
    "sg:province":"WI",
    "sg:tags":[
        "a",
        "car",
        "used",
        "dealer",
        "general"
    ],
    "sg:website":"www.venusford.com",
    "wof:name":"Ed Witt's Venus Ford",
    "wof:placetype":"venue"
},
  "geometry": {"coordinates":[-87.87134,42.959007],"type":"Point"}
}