{
  "type": "Feature",
  "properties": {
    "iso:country":"US",
    "sg:address":"918 W Moreland Blvd",
    "sg:city":"Waukesha",
    "sg:classifiers":[
        {
            "category":"Shopping",
            "subcategory":"Florist",
            "type":"Retail Goods"
        }
    ],
    "sg:phone":"+1 262 521 2205",
    "sg:postcode":"53188",
    "sg:province":"WI",
    "wof:name":"Waukesha Greenhouse",
    "wof:placetype":"venue"
},
  "geometry": {"coordinates":[-88.244626,43.025086],"type":"Point"}
}