{
  "type": "Feature",
  "properties": {
    "iso:country":"US",
    "sg:address":"789 Keup Rd",
    "sg:city":"Cedarburg",
    "sg:classifiers":[
        {
            "category":"Manufacturing",
            "subcategory":"Metals",
            "type":"Manufacturing & Wholesale Goods"
        }
    ],
    "sg:phone":"+1 262 375 9075",
    "sg:postcode":"53012",
    "sg:province":"WI",
    "sg:tags":[
        "tool",
        "mfg"
    ],
    "wof:name":"Snap-On Tools",
    "wof:placetype":"venue"
},
  "geometry": {"coordinates":[-87.97466300000001,43.304309],"type":"Point"}
}