{
  "type": "Feature",
  "properties": {
    "iso:country":"US",
    "sg:address":"9034 Co Hwy A",
    "sg:city":"Delavan",
    "sg:classifiers":[
        {
            "category":"Shopping",
            "subcategory":"Crafts & Fabrics",
            "type":"Retail Goods"
        }
    ],
    "sg:phone":"+1 608 883 9922",
    "sg:postcode":"53115",
    "sg:province":"WI",
    "sg:tags":[
        "sewing",
        "yarn"
    ],
    "wof:name":"Needles n Pins",
    "wof:placetype":"venue"
},
  "geometry": {"coordinates":[-88.746363,42.715107],"type":"Point"}
}