{
  "type": "Feature",
  "properties": {
    "iso:country":"US",
    "sg:address":"1202 5th Ave",
    "sg:city":"Antigo",
    "sg:classifiers":[
        {
            "category":"Personal",
            "type":"Services"
        }
    ],
    "sg:phone":"+1 715 623 6874",
    "sg:postcode":"54409",
    "sg:province":"WI",
    "wof:name":"Genz John",
    "wof:placetype":"venue"
},
  "geometry": {"coordinates":[-89.162855,45.140552],"type":"Point"}
}