{
  "type": "Feature",
  "properties": {
    "addr:full":"1175 Tanglewood Ct Brookfield WI 53005",
    "addr:housenumber":"1175",
    "addr:postcode":"53005",
    "addr:street":"Tanglewood Ct",
    "iso:country":"US",
    "sg:address":"1175 Tanglewood Ct",
    "sg:city":"Brookfield",
    "sg:classifiers":[
        {
            "category":"Wholesale",
            "subcategory":"Sporting Goods",
            "type":"Manufacturing & Wholesale Goods"
        }
    ],
    "sg:phone":"+1 262 821 2878",
    "sg:postcode":"53005",
    "sg:province":"WI",
    "wof:name":"North Country Marketing LTD",
    "wof:placetype":"venue"
},
  "geometry": {"coordinates":[-88.126098,43.020294],"type":"Point"}
}