{
  "type": "Feature",
  "properties": {
    "addr:full":"4639 W Forest Home Ave Milwaukee WI 53219",
    "addr:housenumber":"4639",
    "addr:postcode":"53219",
    "addr:street":"W Forest Home Ave",
    "iso:country":"US",
    "sg:address":"4639 W Forest Home Ave",
    "sg:city":"Milwaukee",
    "sg:classifiers":[
        {
            "category":"Health Services",
            "subcategory":"Doctor",
            "type":"Services"
        }
    ],
    "sg:phone":"+1 414 321 3444",
    "sg:postcode":"53219",
    "sg:province":"WI",
    "sg:tags":[
        "dentist"
    ],
    "wof:name":"Roberta K Brown DDS",
    "wof:placetype":"venue"
},
  "geometry": {"coordinates":[-87.972433,42.986223],"type":"Point"}
}