{
  "type": "Feature",
  "properties": {
    "iso:country":"US",
    "sg:address":"2113 Fitchrona Rd",
    "sg:city":"Verona",
    "sg:classifiers":[
        {
            "category":"Real Estate",
            "subcategory":"Real Estate Operator",
            "type":"Services"
        }
    ],
    "sg:phone":"+1 608 845 7807",
    "sg:postcode":"53593",
    "sg:province":"WI",
    "sg:tags":[
        "property",
        "lessor"
    ],
    "wof:name":"Hageman John",
    "wof:placetype":"venue"
},
  "geometry": {"coordinates":[-89.485154,42.964985],"type":"Point"}
}