{
  "type": "Feature",
  "properties": {
    "iso:country":"US",
    "sg:address":"N6829 Briggs Rd",
    "sg:city":"Holmen",
    "sg:classifiers":[
        {
            "category":"Building & Trades",
            "subcategory":"Construction",
            "type":"Services"
        }
    ],
    "sg:phone":"+1 608 526 3934",
    "sg:postcode":"54636",
    "sg:province":"WI",
    "sg:tags":[
        "industrial",
        "contractors-commercial"
    ],
    "wof:name":"La Crosse Buildings",
    "wof:placetype":"venue"
},
  "geometry": {"coordinates":[-91.280327,43.949221],"type":"Point"}
}