{
  "type": "Feature",
  "properties": {
    "addr:full":"1697 690th St Mondovi WI 54755",
    "addr:housenumber":"1697",
    "addr:postcode":"54755",
    "addr:street":"690Th St",
    "iso:country":"US",
    "sg:address":"1697 690th St",
    "sg:city":"Mondovi",
    "sg:classifiers":[
        {
            "category":"Professional",
            "type":"Services"
        }
    ],
    "sg:phone":"+1 715 875 4998",
    "sg:postcode":"54755",
    "sg:province":"WI",
    "sg:tags":[
        "establishment"
    ],
    "wof:name":"Five Eagles",
    "wof:placetype":"venue"
},
  "geometry": {"coordinates":[-91.812528,44.748407],"type":"Point"}
}