{
  "type": "Feature",
  "properties": {
    "iso:country":"US",
    "sg:address":"1332 Scenic Dr",
    "sg:city":"Kewaskum",
    "sg:classifiers":[
        {
            "category":"Organizations",
            "subcategory":"Religious Organization",
            "type":"Services"
        }
    ],
    "sg:phone":"+1 262 690 6444",
    "sg:postcode":"53040",
    "sg:province":"WI",
    "sg:tags":[
        "church"
    ],
    "wof:name":"Saint John's United Church",
    "wof:placetype":"venue"
},
  "geometry": {"coordinates":[-88.10589899999999,43.527292],"type":"Point"}
}