{
  "type": "Feature",
  "properties": {
    "iso:country":"US",
    "sg:address":"9922 N Arrowwood Rd",
    "sg:city":"Thiensville",
    "sg:classifiers":[
        {
            "category":"Professional",
            "subcategory":"Business Services",
            "type":"Services"
        }
    ],
    "sg:phone":"+1 262 242 0947",
    "sg:postcode":"53092",
    "sg:province":"WI",
    "wof:name":"Klumb Automotive",
    "wof:placetype":"venue"
},
  "geometry": {"coordinates":[-87.973876,43.198089],"type":"Point"}
}