{
  "type": "Feature",
  "properties": {
    "iso:country":"US",
    "sg:address":"20347 Main St",
    "sg:city":"Jackson",
    "sg:classifiers":[
        {
            "category":"Real Estate",
            "subcategory":"Real Estate Agent",
            "type":"Services"
        }
    ],
    "sg:phone":"+1 262 677 0691",
    "sg:postcode":"53037",
    "sg:province":"WI",
    "wof:name":"Applied Inventoryand Valuation",
    "wof:placetype":"venue"
},
  "geometry": {"coordinates":[-88.161713,43.32382],"type":"Point"}
}