{
  "type": "Feature",
  "properties": {
    "iso:country":"US",
    "sg:address":"11380 W Line Rd",
    "sg:city":"Brownsville",
    "sg:classifiers":[
        {
            "category":"Farming",
            "subcategory":"Orchard",
            "type":"Manufacturing & Wholesale Goods"
        }
    ],
    "sg:phone":"+1 920 583 3065",
    "sg:postcode":"53006",
    "sg:province":"WI",
    "sg:tags":[
        "farm",
        "fruit",
        "tree",
        "berry",
        "crop"
    ],
    "wof:name":"Rosenkranz Farms",
    "wof:placetype":"venue"
},
  "geometry": {"coordinates":[-88.521551,43.613175],"type":"Point"}
}