{
  "type": "Feature",
  "properties": {
    "iso:country":"US",
    "sg:address":"7923 Co Rd B",
    "sg:city":"Westfield",
    "sg:classifiers":[
        {
            "category":"Freight",
            "type":"Transportation"
        }
    ],
    "sg:phone":"+1 608 296 2145",
    "sg:postcode":"53964",
    "sg:province":"WI",
    "wof:name":"Rjb Trucking",
    "wof:placetype":"venue"
},
  "geometry": {"coordinates":[-89.43440699999999,43.926797],"type":"Point"}
}