{
  "type": "Feature",
  "properties": {
    "iso:country":"US",
    "sg:address":"65 Hollander Ct",
    "sg:city":"Fond Du Lac",
    "sg:classifiers":[
        {
            "category":"Freight",
            "type":"Transportation"
        }
    ],
    "sg:phone":"+1 920 922 0230",
    "sg:postcode":"54937",
    "sg:province":"WI",
    "sg:tags":[
        "trucking"
    ],
    "sg:website":"www.osborntrucking.com",
    "wof:name":"Osborn & Son Trucking Co Inc",
    "wof:placetype":"venue"
},
  "geometry": {"coordinates":[-88.469714,43.751169],"type":"Point"}
}