{
  "type": "Feature",
  "properties": {
    "addr:full":"3806 Oakwood Hills Pkwy Eau Claire WI 54701",
    "addr:housenumber":"3806",
    "addr:postcode":"54701",
    "addr:street":"Oakwood Hills Pkwy",
    "iso:country":"US",
    "sg:address":"3806 Oakwood Hills Pkwy",
    "sg:city":"Eau Claire",
    "sg:classifiers":[
        {
            "category":"Insurance",
            "subcategory":"Insurance Agent",
            "type":"Services"
        }
    ],
    "sg:phone":"+1 715 831 5959",
    "sg:postcode":"54701",
    "sg:province":"WI",
    "wof:name":"Isaksson Insurance",
    "wof:placetype":"venue"
},
  "geometry": {"coordinates":[-91.44344100000001,44.772324],"type":"Point"}
}