{
  "type": "Feature",
  "properties": {
    "iso:country":"US",
    "sg:address":"2079 State Hwy 64",
    "sg:city":"Marinette",
    "sg:classifiers":[
        {
            "category":"Manufacturing",
            "subcategory":"Watercraft",
            "type":"Manufacturing & Wholesale Goods"
        }
    ],
    "sg:phone":"+1 715 735 5089",
    "sg:postcode":"54143",
    "sg:province":"WI",
    "wof:name":"Voyaguer Canoes",
    "wof:placetype":"venue"
},
  "geometry": {"coordinates":[-87.69856,45.099941],"type":"Point"}
}