{
  "type": "Feature",
  "properties": {
    "addr:full":"13730 W Greenfield Ave Brookfield WI 53005",
    "addr:housenumber":"13730",
    "addr:postcode":"53005",
    "addr:street":"W Greenfield Ave",
    "iso:country":"US",
    "sg:address":"13730 W Greenfield Ave",
    "sg:city":"Brookfield",
    "sg:classifiers":[
        {
            "category":"Communications",
            "subcategory":"Film & Video Production",
            "type":"Services"
        }
    ],
    "sg:phone":"+1 262 784 1988",
    "sg:postcode":"53005",
    "sg:province":"WI",
    "sg:tags":[
        "taping"
    ],
    "wof:name":"Creative Images Video Prdctns",
    "wof:placetype":"venue"
},
  "geometry": {"coordinates":[-88.084183,43.016607],"type":"Point"}
}