{
  "type": "Feature",
  "properties": {
    "iso:country":"US",
    "sg:address":"3139 N Oakland Ave",
    "sg:city":"Milwaukee",
    "sg:classifiers":[
        {
            "category":"Shopping",
            "subcategory":"Books",
            "type":"Retail Goods"
        }
    ],
    "sg:phone":"+1 414 332 2665",
    "sg:postcode":"53211",
    "sg:province":"WI",
    "sg:tags":[
        "textbook"
    ],
    "wof:name":"Follett College Bookstore 363",
    "wof:placetype":"venue"
},
  "geometry": {"coordinates":[-87.887918,43.075266],"type":"Point"}
}