{
  "type": "Feature",
  "properties": {
    "iso:country":"US",
    "sg:address":"1978 US Hwy 8",
    "sg:city":"Saint Croix Falls",
    "sg:classifiers":[
        {
            "category":"Home & Garden",
            "subcategory":"Household Appliances",
            "type":"Retail Goods"
        }
    ],
    "sg:phone":"+1 715 483 5526",
    "sg:postcode":"54024",
    "sg:province":"WI",
    "wof:name":"Appliances and More",
    "wof:placetype":"venue"
},
  "geometry": {"coordinates":[-92.565737,45.397517],"type":"Point"}
}