{
  "type": "Feature",
  "properties": {
    "iso:country":"US",
    "sg:address":"7635 Magolski Rd",
    "sg:city":"Marion",
    "sg:classifiers":[
        {
            "category":"Farming",
            "subcategory":"Livestock Farm",
            "type":"Manufacturing & Wholesale Goods"
        }
    ],
    "sg:phone":"+1 715 754 2461",
    "sg:postcode":"54950",
    "sg:province":"WI",
    "sg:tags":[
        "beef",
        "feedlot",
        "cattle"
    ],
    "wof:name":"Leon Vollmer",
    "wof:placetype":"venue"
},
  "geometry": {"coordinates":[-88.842841,44.670811],"type":"Point"}
}