{
  "type": "Feature",
  "properties": {
    "iso:country":"US",
    "sg:address":"17507 Birch Ln",
    "sg:city":"Wittenberg",
    "sg:classifiers":[
        {
            "category":"Building & Trades",
            "subcategory":"Construction",
            "type":"Services"
        }
    ],
    "sg:phone":"+1 715 253 2525",
    "sg:postcode":"54499",
    "sg:province":"WI",
    "sg:tags":[
        "floor",
        "laying",
        "contractor"
    ],
    "wof:name":"Refined Refinishers",
    "wof:placetype":"venue"
},
  "geometry": {"coordinates":[-89.134831,44.840783],"type":"Point"}
}