{
  "type": "Feature",
  "properties": {
    "iso:country":"US",
    "sg:address":"548 Prairie Rd",
    "sg:city":"Fond Du Lac",
    "sg:classifiers":[
        {
            "category":"Professional",
            "subcategory":"Engineering",
            "type":"Services"
        }
    ],
    "sg:phone":"+1 920 922 5703",
    "sg:postcode":"54935",
    "sg:province":"WI",
    "sg:tags":[
        "engineer"
    ],
    "wof:name":"J E Arthur & Assoc Inc",
    "wof:placetype":"venue"
},
  "geometry": {"coordinates":[-88.41200000000001,43.786128],"type":"Point"}
}