{
  "type": "Feature",
  "properties": {
    "iso:country":"US",
    "sg:address":"259 W Main St",
    "sg:city":"Waukesha",
    "sg:classifiers":[
        {
            "category":"Shopping",
            "subcategory":"Used Merchandise",
            "type":"Retail Goods"
        }
    ],
    "sg:phone":"+1 262 522 7636",
    "sg:postcode":"53186",
    "sg:province":"WI",
    "sg:tags":[
        "antique"
    ],
    "sg:website":"www.foxantiques.com",
    "wof:name":"Fox Main Street Antiques",
    "wof:placetype":"venue"
},
  "geometry": {"coordinates":[-88.230812,43.011718],"type":"Point"}
}