{
  "type": "Feature",
  "properties": {
    "iso:country":"US",
    "sg:address":"1371 Cedar St",
    "sg:city":"Green Bay",
    "sg:classifiers":[
        {
            "category":"Professional",
            "subcategory":"Business Services",
            "type":"Services"
        }
    ],
    "sg:phone":"+1 920 437 2236",
    "sg:postcode":"54302",
    "sg:province":"WI",
    "wof:name":"Y & E Creations",
    "wof:placetype":"venue"
},
  "geometry": {"coordinates":[-87.993757,44.511513],"type":"Point"}
}