{
  "type": "Feature",
  "properties": {
    "iso:country":"US",
    "sg:address":"102 E Gorham St",
    "sg:city":"Madison",
    "sg:classifiers":[
        {
            "category":"Building & Trades",
            "subcategory":"Plumbing",
            "type":"Services"
        }
    ],
    "sg:phone":"+1 608 284 9495",
    "sg:postcode":"53703",
    "sg:province":"WI",
    "sg:tags":[
        "contractor"
    ],
    "wof:name":"Light Energy Systems",
    "wof:placetype":"venue"
},
  "geometry": {"coordinates":[-89.384962,43.079596],"type":"Point"}
}