{
  "type": "Feature",
  "properties": {
    "iso:country":"US",
    "sg:address":"8002 198th Ave",
    "sg:city":"Bristol",
    "sg:classifiers":[
        {
            "category":"Real Estate",
            "subcategory":"Real Estate Agent",
            "type":"Services"
        }
    ],
    "sg:phone":"+1 262 857 3172",
    "sg:postcode":"53104",
    "sg:province":"WI",
    "sg:tags":[
        "inspection"
    ],
    "wof:name":"Capstone Home Inspections",
    "wof:placetype":"venue"
},
  "geometry": {"coordinates":[-88.04805399999999,42.558774],"type":"Point"}
}