{
  "type": "Feature",
  "properties": {
    "iso:country":"US",
    "sg:address":"153 E 3rd St",
    "sg:city":"Kaukauna",
    "sg:classifiers":[
        {
            "category":"Restaurant",
            "type":"Food & Drink"
        }
    ],
    "sg:menulink":"http://www.allmenus.com/wi/kaukauna/145539-subway/menu/",
    "sg:phone":"+1 920 759 0998",
    "sg:postcode":"54130",
    "sg:province":"WI",
    "sg:tags":[
        "american",
        "sandwich"
    ],
    "wof:name":"Subway",
    "wof:placetype":"venue"
},
  "geometry": {"coordinates":[-88.27232600000001,44.277011],"type":"Point"}
}