{
  "type": "Feature",
  "properties": {
    "iso:country":"US",
    "sg:address":"4080 Park Rd",
    "sg:city":"Brodhead",
    "sg:phone":"+1 608 897 2967",
    "sg:postcode":"53520",
    "sg:province":"WI",
    "sg:tags":[
        "farm",
        "corn"
    ],
    "wof:name":"Carlyle Porterfield",
    "wof:placetype":"venue"
},
  "geometry": {"coordinates":[-89.43215600000001,42.654674],"type":"Point"}
}