{
  "type": "Feature",
  "properties": {
    "iso:country":"US",
    "sg:address":"100 W Lawrence St",
    "sg:city":"Appleton",
    "sg:classifiers":[
        {
            "category":"Professional",
            "subcategory":"Management & Consulting",
            "type":"Services"
        }
    ],
    "sg:phone":"+1 920 830 9999",
    "sg:postcode":"54911",
    "sg:province":"WI",
    "sg:tags":[
        "consultant"
    ],
    "wof:name":"Rugland Water",
    "wof:placetype":"venue"
},
  "geometry": {"coordinates":[-88.405946,44.260715],"type":"Point"}
}