{
  "type": "Feature",
  "properties": {
    "iso:country":"US",
    "sg:address":"8242 N Ridge Trl",
    "sg:city":"Milton",
    "sg:classifiers":[
        {
            "category":"Building & Trades",
            "subcategory":"Plumbing",
            "type":"Services"
        }
    ],
    "sg:phone":"+1 608 868 3278",
    "sg:postcode":"53563",
    "sg:province":"WI",
    "sg:tags":[
        "plumbing",
        "contractor"
    ],
    "wof:name":"Ron's Plumbing",
    "wof:placetype":"venue"
},
  "geometry": {"coordinates":[-88.952732,42.791096],"type":"Point"}
}