{
  "type": "Feature",
  "properties": {
    "iso:country":"US",
    "sg:address":"372 W Jackson Ave",
    "sg:city":"Grantsburg",
    "sg:classifiers":[
        {
            "category":"Retail",
            "subcategory":"Repair Shop",
            "type":"Services"
        }
    ],
    "sg:phone":"+1 715 463 5554",
    "sg:postcode":"54840",
    "sg:province":"WI",
    "wof:name":"Grantsburg Upholstery",
    "wof:placetype":"venue"
},
  "geometry": {"coordinates":[-92.688247,45.783815],"type":"Point"}
}