{
  "type": "Feature",
  "properties": {
    "iso:country":"US",
    "sg:address":"24665 State Rd 35 70",
    "sg:city":"Siren",
    "sg:classifiers":[
        {
            "category":"Home & Garden",
            "subcategory":"Home Furnishings",
            "type":"Retail Goods"
        }
    ],
    "sg:phone":"+1 715 349 2250",
    "sg:postcode":"54872",
    "sg:province":"WI",
    "sg:tags":[
        "quilting"
    ],
    "wof:name":"Bear Den Quilt Co",
    "wof:placetype":"venue"
},
  "geometry": {"coordinates":[-92.36787,45.813476],"type":"Point"}
}