{
  "type": "Feature",
  "properties": {
    "iso:country":"US",
    "sg:address":"8120 900th St",
    "sg:city":"River Falls",
    "sg:phone":"+1 715 425 5395",
    "sg:postcode":"54022",
    "sg:province":"WI",
    "sg:tags":[
        "farm",
        "field",
        "crop"
    ],
    "wof:name":"Arthur Dolan",
    "wof:placetype":"venue"
},
  "geometry": {"coordinates":[-92.56510900000001,44.834481],"type":"Point"}
}