{
  "type": "Feature",
  "properties": {
    "iso:country":"US",
    "sg:address":"115 E Main St",
    "sg:city":"Sun Prairie",
    "sg:classifiers":[
        {
            "category":"Museum",
            "type":"Entertainment"
        }
    ],
    "sg:phone":"+1 608 837 2915",
    "sg:postcode":"53590",
    "sg:province":"WI",
    "sg:tags":[
        "gallery"
    ],
    "wof:name":"Sun Prairie Historical Museum",
    "wof:placetype":"venue"
},
  "geometry": {"coordinates":[-89.213539,43.183226],"type":"Point"}
}