{
  "type": "Feature",
  "properties": {
    "addr:full":"1165 250th St Woodville WI 54028",
    "addr:housenumber":"1165",
    "addr:postcode":"54028",
    "addr:street":"250Th St",
    "iso:country":"US",
    "sg:address":"1165 250th St",
    "sg:city":"Woodville",
    "sg:classifiers":[
        {
            "category":"Farming",
            "subcategory":"Dairy Farm",
            "type":"Manufacturing & Wholesale Goods"
        }
    ],
    "sg:phone":"+1 715 684 2232",
    "sg:postcode":"54028",
    "sg:province":"WI",
    "wof:name":"Mike Dorwin Farms",
    "wof:placetype":"venue"
},
  "geometry": {"coordinates":[-92.29857,45.030048],"type":"Point"}
}