{
  "type": "Feature",
  "properties": {
    "addr:full":"7430 Harwood Ave Milwaukee WI 53213",
    "addr:housenumber":"7430",
    "addr:postcode":"53213",
    "addr:street":"Harwood Ave",
    "iso:country":"US",
    "sg:address":"7430 Harwood Ave",
    "sg:city":"Milwaukee",
    "sg:classifiers":[
        {
            "category":"Professional",
            "subcategory":"Lawyer & Legal Services",
            "type":"Services"
        }
    ],
    "sg:phone":"+1 414 453 5555",
    "sg:postcode":"53213",
    "sg:province":"WI",
    "wof:name":"Mark Murphy Attorney",
    "wof:placetype":"venue"
},
  "geometry": {"coordinates":[-88.006484,43.050541],"type":"Point"}
}