{
  "type": "Feature",
  "properties": {
    "iso:country":"US",
    "sg:address":"5749 Turner Rd",
    "sg:city":"Pardeeville",
    "sg:classifiers":[
        {
            "category":"Real Estate",
            "subcategory":"Developer",
            "type":"Services"
        }
    ],
    "sg:phone":"+1 608 429 2008",
    "sg:postcode":"53954",
    "sg:province":"WI",
    "wof:name":"Rainbow Ridge Inc",
    "wof:placetype":"venue"
},
  "geometry": {"coordinates":[-89.289249,43.628518],"type":"Point"}
}