{
  "type": "Feature",
  "properties": {
    "iso:country":"US",
    "sg:address":"11604 Spreeman Rd",
    "sg:city":"Suring",
    "sg:classifiers":[
        {
            "category":"Real Estate",
            "subcategory":"Architect",
            "type":"Services"
        }
    ],
    "sg:phone":"+1 920 842 2647",
    "sg:postcode":"54174",
    "sg:province":"WI",
    "sg:tags":[
        "building",
        "designer",
        "architectural"
    ],
    "wof:name":"Erb Enterprises Ltd",
    "wof:placetype":"venue"
},
  "geometry": {"coordinates":[-88.403379,45.095042],"type":"Point"}
}