{
  "type": "Feature",
  "properties": {
    "iso:country":"US",
    "sg:address":"456 E Tilson St",
    "sg:city":"West Salem",
    "sg:phone":"+1 608 786 0243",
    "sg:postcode":"54669",
    "sg:province":"WI",
    "sg:tags":[
        "farm",
        "field",
        "crop"
    ],
    "wof:name":"Kenneth Piper",
    "wof:placetype":"venue"
},
  "geometry": {"coordinates":[-91.078885,43.905936],"type":"Point"}
}