{
  "type": "Feature",
  "properties": {
    "addr:full":"13 N Bird St Sun Prairie WI 53590",
    "addr:housenumber":"13",
    "addr:postcode":"53590",
    "addr:street":"N Bird St",
    "iso:country":"US",
    "sg:address":"13 N Bird St",
    "sg:city":"Sun Prairie",
    "sg:classifiers":[
        {
            "category":"Shopping",
            "subcategory":"Computers & Home Electronics",
            "type":"Retail Goods"
        }
    ],
    "sg:phone":"+1 608 825 7226",
    "sg:postcode":"53590",
    "sg:province":"WI",
    "sg:tags":[
        "equipment",
        "dealer"
    ],
    "wof:name":"Com Link Computers Inc",
    "wof:placetype":"venue"
},
  "geometry": {"coordinates":[-89.22646,43.182174],"type":"Point"}
}