{
  "type": "Feature",
  "properties": {
    "iso:country":"US",
    "sg:address":"6647 Hillendale Dr",
    "sg:city":"Muskego",
    "sg:classifiers":[
        {
            "category":"Real Estate",
            "subcategory":"Real Estate Agent",
            "type":"Services"
        }
    ],
    "sg:phone":"+1 262 679 7826",
    "sg:postcode":"53150",
    "sg:province":"WI",
    "wof:name":"Advanced Appraisal Services LL",
    "wof:placetype":"venue"
},
  "geometry": {"coordinates":[-88.155018,42.924023],"type":"Point"}
}