{
  "type": "Feature",
  "properties": {
    "iso:country":"US",
    "sg:address":"7047 Oriole Ln",
    "sg:city":"Fredonia",
    "sg:classifiers":[
        {
            "category":"Recreation",
            "type":"Entertainment"
        }
    ],
    "sg:phone":"+1 262 334 3003",
    "sg:postcode":"53021",
    "sg:province":"WI",
    "wof:name":"Lignite Stables Ltd",
    "wof:placetype":"venue"
},
  "geometry": {"coordinates":[-88.010752,43.532146],"type":"Point"}
}