{
  "type": "Feature",
  "properties": {
    "iso:country":"US",
    "sg:address":"4108 E M H Townline Rd",
    "sg:city":"Milton",
    "sg:phone":"+1 608 868 2595",
    "sg:postcode":"53563",
    "sg:province":"WI",
    "sg:tags":[
        "farm",
        "corn",
        "soybean"
    ],
    "wof:name":"Pierce Farms",
    "wof:placetype":"venue"
},
  "geometry": {"coordinates":[-88.967446,42.758913],"type":"Point"}
}