{
  "type": "Feature",
  "properties": {
    "iso:country":"US",
    "sg:address":"810 17th Ave",
    "sg:city":"Bloomer",
    "sg:classifiers":[
        {
            "category":"Home & Garden",
            "subcategory":"Building Materials",
            "type":"Retail Goods"
        }
    ],
    "sg:phone":"+1 715 568 1220",
    "sg:postcode":"54724",
    "sg:province":"WI",
    "sg:tags":[
        "lumber"
    ],
    "wof:name":"United Building Ctr",
    "wof:placetype":"venue"
},
  "geometry": {"coordinates":[-91.482902,45.099611],"type":"Point"}
}