{
  "type": "Feature",
  "properties": {
    "iso:country":"US",
    "sg:address":"5606 Spring Valley Rd",
    "sg:city":"Burlington",
    "sg:phone":"+1 262 763 8913",
    "sg:postcode":"53105",
    "sg:province":"WI",
    "sg:tags":[
        "beef",
        "farm",
        "cash",
        "grain",
        "cattle",
        "feedlot"
    ],
    "wof:name":"Harold Reich",
    "wof:placetype":"venue"
},
  "geometry": {"coordinates":[-88.333821,42.646321],"type":"Point"}
}