{
  "type": "Feature",
  "properties": {
    "addr:full":"436 College Ave De Pere WI 54115",
    "addr:housenumber":"436",
    "addr:postcode":"54115",
    "addr:street":"College Ave",
    "iso:country":"US",
    "sg:address":"436 College Ave",
    "sg:city":"De Pere",
    "sg:classifiers":[
        {
            "category":"Banks & Credit Unions",
            "subcategory":"Investment Brokerage",
            "type":"Services"
        }
    ],
    "sg:phone":"+1 920 339 9035",
    "sg:postcode":"54115",
    "sg:province":"WI",
    "wof:name":"Garot Investments",
    "wof:placetype":"venue"
},
  "geometry": {"coordinates":[-88.072948,44.444747],"type":"Point"}
}