{
  "type": "Feature",
  "properties": {
    "iso:country":"US",
    "sg:address":"126 Cherry St",
    "sg:city":"Phillips",
    "sg:classifiers":[
        {
            "category":"Government",
            "subcategory":"Office",
            "type":"Public Place"
        }
    ],
    "sg:phone":"+1 715 339 2515",
    "sg:postcode":"54555",
    "sg:province":"WI",
    "wof:name":"Price County Register Of Deeds",
    "wof:placetype":"venue"
},
  "geometry": {"coordinates":[-90.398028,45.690366],"type":"Point"}
}