{
  "type": "Feature",
  "properties": {
    "iso:country":"US",
    "sg:address":"1220 Janesville Ave",
    "sg:city":"Fort Atkinson",
    "sg:classifiers":[
        {
            "category":"Food & Beverages",
            "subcategory":"Specialty",
            "type":"Retail Goods"
        }
    ],
    "sg:phone":"+1 920 563 0900",
    "sg:postcode":"53538",
    "sg:province":"WI",
    "sg:tags":[
        "salon",
        "tanning"
    ],
    "wof:name":"Tuckers Inc of Fort Atkinson",
    "wof:placetype":"venue"
},
  "geometry": {"coordinates":[-88.849947,42.912278],"type":"Point"}
}