{
  "type": "Feature",
  "properties": {
    "iso:country":"US",
    "sg:address":"2219 Eagle Dr",
    "sg:city":"Middleton",
    "sg:classifiers":[
        {
            "category":"Professional",
            "subcategory":"Engineering",
            "type":"Services"
        }
    ],
    "sg:phone":"+1 608 836 8180",
    "sg:postcode":"53562",
    "sg:province":"WI",
    "sg:tags":[
        "company"
    ],
    "wof:name":"Inspire Design Group LLC",
    "wof:placetype":"venue"
},
  "geometry": {"coordinates":[-89.52768500000001,43.100604],"type":"Point"}
}