{
  "type": "Feature",
  "properties": {
    "iso:country":"US",
    "sg:address":"275 N Beaver Creek Rd",
    "sg:city":"Park Falls",
    "sg:classifiers":[
        {
            "category":"Building & Trades",
            "subcategory":"Construction",
            "type":"Services"
        }
    ],
    "sg:phone":"+1 715 583 4476",
    "sg:postcode":"54552",
    "sg:province":"WI",
    "sg:tags":[
        "contractor"
    ],
    "wof:name":"Al Schlitz Builders",
    "wof:placetype":"venue"
},
  "geometry": {"coordinates":[-90.17295300000001,45.990268],"type":"Point"}
}