{
  "type": "Feature",
  "properties": {
    "iso:country":"US",
    "sg:address":"422 Oneida St",
    "sg:city":"Minocqua",
    "sg:classifiers":[
        {
            "category":"Shopping",
            "subcategory":"Clothing, Apparel, & Fashions",
            "type":"Retail Goods"
        }
    ],
    "sg:phone":"+1 715 356 3030",
    "sg:postcode":"54548",
    "sg:province":"WI",
    "wof:name":"Omni Clothing LTD",
    "wof:placetype":"venue"
},
  "geometry": {"coordinates":[-89.709869,45.870577],"type":"Point"}
}