{
  "type": "Feature",
  "properties": {
    "iso:country":"US",
    "sg:address":"9250 N Green Bay Rd",
    "sg:city":"Milwaukee",
    "sg:classifiers":[
        {
            "category":"Shopping",
            "type":"Retail Goods"
        },
        {
            "category":"Shopping",
            "subcategory":"Clothing, Apparel, & Fashions",
            "type":"Retail Goods"
        }
    ],
    "sg:phone":"+1 414 365 2868",
    "sg:postcode":"53209",
    "sg:province":"WI",
    "sg:tags":[
        "swim",
        "swimwear",
        "accessory"
    ],
    "wof:name":"Wharf Swim Shop LLC",
    "wof:placetype":"venue"
},
  "geometry": {"coordinates":[-87.9636,43.18309],"type":"Point"}
}