{
  "type": "Feature",
  "properties": {
    "iso:country":"US",
    "sg:address":"1504 E North Ave",
    "sg:city":"Milwaukee",
    "sg:classifiers":[
        {
            "category":"Professional",
            "subcategory":"Computer Services",
            "type":"Services"
        }
    ],
    "sg:phone":"+1 414 908 4316",
    "sg:postcode":"53202",
    "sg:province":"WI",
    "sg:tags":[
        "information"
    ],
    "wof:name":"Tier X Solutions Inc",
    "wof:placetype":"venue"
},
  "geometry": {"coordinates":[-87.890524,43.060215],"type":"Point"}
}