{
  "type": "Feature",
  "properties": {
    "iso:country":"US",
    "sg:address":"1801 E Wyndmere Dr",
    "sg:city":"Appleton",
    "sg:classifiers":[
        {
            "category":"Professional",
            "subcategory":"Employment Agencies",
            "type":"Services"
        }
    ],
    "sg:phone":"+1 920 954 1833",
    "sg:postcode":"54913",
    "sg:province":"WI",
    "sg:tags":[
        "opportunity"
    ],
    "sg:website":"www.wyndmeregroup.com",
    "wof:name":"Wyndmere Recruiting Group",
    "wof:placetype":"venue"
},
  "geometry": {"coordinates":[-88.377159,44.311295],"type":"Point"}
}