{
  "type": "Feature",
  "properties": {
    "iso:country":"US",
    "sg:address":"6948 Hillcrest Ave",
    "sg:city":"Rudolph",
    "sg:classifiers":[
        {
            "category":"Manufacturing",
            "subcategory":"Building Materials",
            "type":"Manufacturing & Wholesale Goods"
        }
    ],
    "sg:phone":"+1 715 435 3295",
    "sg:postcode":"54475",
    "sg:province":"WI",
    "sg:tags":[
        "mfg"
    ],
    "wof:name":"Slivers N Splinters",
    "wof:placetype":"venue"
},
  "geometry": {"coordinates":[-89.798969,44.499517],"type":"Point"}
}