{
  "type": "Feature",
  "properties": {
    "iso:country":"US",
    "sg:address":"1327 Sheridan Rd",
    "sg:city":"Kenosha",
    "sg:classifiers":[
        {
            "category":"Professional",
            "type":"Services"
        }
    ],
    "sg:phone":"+1 262 552 8694",
    "sg:postcode":"53140",
    "sg:province":"WI",
    "wof:name":"Ross Studios",
    "wof:placetype":"venue"
},
  "geometry": {"coordinates":[-87.819423,42.63589],"type":"Point"}
}