{
  "type": "Feature",
  "properties": {
    "iso:country":"US",
    "sg:address":"1701 N Spring St",
    "sg:city":"Beaver Dam",
    "sg:classifiers":[
        {
            "category":"Shopping",
            "type":"Retail Goods"
        }
    ],
    "sg:phone":"+1 920 887 9621",
    "sg:postcode":"53916",
    "sg:province":"WI",
    "sg:tags":[
        "hearing",
        "equipment",
        "supply",
        "impaired"
    ],
    "wof:name":"Beltone Hearing Aid Ctr",
    "wof:placetype":"venue"
},
  "geometry": {"coordinates":[-88.819104,43.482616],"type":"Point"}
}