{
  "type": "Feature",
  "properties": {
    "addr:full":"536 N Main St River Falls WI 54022",
    "addr:housenumber":"536",
    "addr:postcode":"54022",
    "addr:street":"N Main St",
    "iso:country":"US",
    "sg:address":"536 N Main St",
    "sg:city":"River Falls",
    "sg:classifiers":[
        {
            "category":"Education",
            "subcategory":"Special Training",
            "type":"Public Place"
        }
    ],
    "sg:phone":"+1 715 425 1874",
    "sg:postcode":"54022",
    "sg:province":"WI",
    "wof:name":"Saint Bridgets Parish Educatn",
    "wof:placetype":"venue"
},
  "geometry": {"coordinates":[-92.62316199999999,44.863812],"type":"Point"}
}