{
  "type": "Feature",
  "properties": {
    "addr:full":"15170 Christmas Tree Ln Sheldon WI 54766",
    "addr:housenumber":"15170",
    "addr:postcode":"54766",
    "addr:street":"Christmas Tree Ln",
    "iso:country":"US",
    "sg:address":"15170 Christmas Tree Ln",
    "sg:city":"Sheldon",
    "sg:classifiers":[
        {
            "category":"Building & Trades",
            "subcategory":"Landscaping Services",
            "type":"Services"
        }
    ],
    "sg:phone":"+1 715 668 5235",
    "sg:postcode":"54766",
    "sg:province":"WI",
    "sg:tags":[
        "landscape"
    ],
    "wof:name":"Kc Landscaping Inc",
    "wof:placetype":"venue"
},
  "geometry": {"coordinates":[-90.812038,45.338462],"type":"Point"}
}