{
  "type": "Feature",
  "properties": {
    "iso:country":"US",
    "sg:address":"9524 3rd Ave",
    "sg:city":"Almond",
    "sg:classifiers":[
        {
            "category":"Freight",
            "type":"Transportation"
        }
    ],
    "sg:phone":"+1 715 366 2763",
    "sg:postcode":"54909",
    "sg:province":"WI",
    "sg:tags":[
        "operator",
        "trucking"
    ],
    "wof:name":"Turner Services",
    "wof:placetype":"venue"
},
  "geometry": {"coordinates":[-89.312317,44.294496],"type":"Point"}
}