{
  "type": "Feature",
  "properties": {
    "addr:full":"4046 13th Ave Kenosha WI 53140",
    "addr:housenumber":"4046",
    "addr:postcode":"53140",
    "addr:street":"13Th Ave",
    "iso:country":"US",
    "sg:address":"4046 13th Ave",
    "sg:city":"Kenosha",
    "sg:classifiers":[
        {
            "category":"Retail",
            "subcategory":"Auto Repair",
            "type":"Services"
        }
    ],
    "sg:phone":"+1 262 652 5334",
    "sg:postcode":"53140",
    "sg:province":"WI",
    "sg:tags":[
        "general"
    ],
    "wof:name":"Autosport",
    "wof:placetype":"venue"
},
  "geometry": {"coordinates":[-87.826536,42.599754],"type":"Point"}
}