{
  "type": "Feature",
  "properties": {
    "iso:country":"US",
    "sg:address":"586 Schoepp Rd",
    "sg:city":"Sauk City",
    "sg:classifiers":[
        {
            "category":"Travel",
            "subcategory":"Hotels & Motels",
            "type":"Entertainment"
        }
    ],
    "sg:phone":"+1 608 643 6396",
    "sg:postcode":"53583",
    "sg:province":"WI",
    "sg:tags":[
        "resort",
        "operation"
    ],
    "wof:name":"Schoepp's Cottonwood Resort",
    "wof:placetype":"venue"
},
  "geometry": {"coordinates":[-89.64048200000001,43.302609],"type":"Point"}
}