{
  "type": "Feature",
  "properties": {
    "iso:country":"US",
    "sg:address":"601 Madison Ave",
    "sg:city":"Fort Atkinson",
    "sg:classifiers":[
        {
            "category":"Retail",
            "subcategory":"Veterinary Services",
            "type":"Services"
        }
    ],
    "sg:phone":"+1 920 563 0464",
    "sg:postcode":"53538",
    "sg:province":"WI",
    "wof:name":"Creature Comforts LLC",
    "wof:placetype":"venue"
},
  "geometry": {"coordinates":[-88.845723,42.933481],"type":"Point"}
}