{
  "type": "Feature",
  "properties": {
    "iso:country":"US",
    "sg:address":"2104 Queens Ct",
    "sg:city":"Waukesha",
    "sg:classifiers":[
        {
            "category":"Shopping",
            "type":"Retail Goods"
        }
    ],
    "sg:phone":"+1 262 549 3630",
    "sg:postcode":"53188",
    "sg:province":"WI",
    "sg:tags":[
        "cosmetic",
        "perfume"
    ],
    "wof:name":"Mary Kay Cosmetics",
    "wof:placetype":"venue"
},
  "geometry": {"coordinates":[-88.26143399999999,43.036548],"type":"Point"}
}