{
  "type": "Feature",
  "properties": {
    "iso:country":"US",
    "sg:address":"337 W Wisconsin Ave",
    "sg:city":"Appleton",
    "sg:classifiers":[
        {
            "category":"Shopping",
            "subcategory":"Used Merchandise",
            "type":"Retail Goods"
        }
    ],
    "sg:phone":"+1 920 832 8822",
    "sg:postcode":"54911",
    "sg:province":"WI",
    "sg:tags":[
        "shop",
        "thrift"
    ],
    "wof:name":"Bargain Garden Inc",
    "wof:placetype":"venue"
},
  "geometry": {"coordinates":[-88.4106,44.272861],"type":"Point"}
}