{
  "type": "Feature",
  "properties": {
    "addr:full":"204 E Main St Omro WI 54963",
    "addr:housenumber":"204",
    "addr:postcode":"54963",
    "addr:street":"E Main St",
    "iso:country":"US",
    "sg:address":"204 E Main St",
    "sg:city":"Omro",
    "sg:classifiers":[
        {
            "category":"Utilities",
            "subcategory":"Mobile Phone",
            "type":"Services"
        }
    ],
    "sg:phone":"+1 920 685 2848",
    "sg:postcode":"54963",
    "sg:province":"WI",
    "sg:tags":[
        "communication",
        "radiotelephone"
    ],
    "wof:name":"Fox Wireless",
    "wof:placetype":"venue"
},
  "geometry": {"coordinates":[-88.742464,44.039342],"type":"Point"}
}