{
  "type": "Feature",
  "properties": {
    "iso:country":"US",
    "sg:address":"7777 Blue Lake Point Rd",
    "sg:city":"Minocqua",
    "sg:classifiers":[
        {
            "category":"Banks & Credit Unions",
            "subcategory":"Financial Services",
            "type":"Services"
        }
    ],
    "sg:phone":"+1 715 356 1581",
    "sg:postcode":"54548",
    "sg:province":"WI",
    "sg:tags":[
        "investor"
    ],
    "wof:name":"Bella Brothers Investments LLC",
    "wof:placetype":"venue"
},
  "geometry": {"coordinates":[-89.750897,45.839541],"type":"Point"}
}