{
  "type": "Feature",
  "properties": {
    "addr:full":"7345 S Loomis Rd Wind Lake WI 53185",
    "addr:housenumber":"7345",
    "addr:postcode":"53185",
    "addr:street":"S Loomis Rd",
    "iso:country":"US",
    "sg:address":"7345 S Loomis Rd",
    "sg:city":"Wind Lake",
    "sg:classifiers":[
        {
            "category":"Social Services",
            "subcategory":"Child Care",
            "type":"Services"
        }
    ],
    "sg:phone":"+1 262 895 3880",
    "sg:postcode":"53185",
    "sg:province":"WI",
    "wof:name":"Lots For Tots",
    "wof:placetype":"venue"
},
  "geometry": {"coordinates":[-88.16149,42.820495],"type":"Point"}
}