{
  "type": "Feature",
  "properties": {
    "iso:country":"US",
    "sg:address":"3030 W Pierce St",
    "sg:city":"Milwaukee",
    "sg:classifiers":[
        {
            "category":"Professional",
            "type":"Services"
        }
    ],
    "sg:phone":"+1 414 672 6444",
    "sg:postcode":"53215",
    "sg:province":"WI",
    "wof:name":"Will Smith Father",
    "wof:placetype":"venue"
},
  "geometry": {"coordinates":[-87.95258,43.02392],"type":"Point"}
}