{
  "type": "Feature",
  "properties": {
    "iso:country":"US",
    "sg:address":"1461 Crestwood Dr",
    "sg:city":"Oconomowoc",
    "sg:classifiers":[
        {
            "category":"Manufacturing",
            "subcategory":"Rubber & Plastics",
            "type":"Manufacturing & Wholesale Goods"
        }
    ],
    "sg:phone":"+1 262 567 0012",
    "sg:postcode":"53066",
    "sg:province":"WI",
    "sg:tags":[
        "product",
        "mfg"
    ],
    "wof:name":"Holsen Corp International",
    "wof:placetype":"venue"
},
  "geometry": {"coordinates":[-88.48673700000001,43.129925],"type":"Point"}
}