{
  "type": "Feature",
  "properties": {
    "addr:full":"2215 Pennsylvania Ave Sun Prairie WI 53590",
    "addr:housenumber":"2215",
    "addr:postcode":"53590",
    "addr:street":"Pennsylvania Ave",
    "iso:country":"US",
    "sg:address":"2215 Pennsylvania Ave",
    "sg:city":"Sun Prairie",
    "sg:classifiers":[
        {
            "category":"Education",
            "subcategory":"School",
            "type":"Public Place"
        }
    ],
    "sg:phone":"+1 608 834 7200",
    "sg:postcode":"53590",
    "sg:province":"WI",
    "wof:name":"Royal Oaks Elementary School",
    "wof:placetype":"venue"
},
  "geometry": {"coordinates":[-89.252039,43.185021],"type":"Point"}
}