{
  "type": "Feature",
  "properties": {
    "addr:full":"12202 Western Ave Cedarburg WI 53012",
    "addr:housenumber":"12202",
    "addr:postcode":"53012",
    "addr:street":"Western Ave",
    "iso:country":"US",
    "sg:address":"12202 Western Ave",
    "sg:city":"Cedarburg",
    "sg:classifiers":[
        {
            "category":"Building & Trades",
            "subcategory":"Construction",
            "type":"Services"
        }
    ],
    "sg:phone":"+1 262 375 3635",
    "sg:postcode":"53012",
    "sg:province":"WI",
    "sg:tags":[
        "contractor"
    ],
    "wof:name":"Salvaggio Enterprises Inc",
    "wof:placetype":"venue"
},
  "geometry": {"coordinates":[-88.054703,43.2934],"type":"Point"}
}