{
  "type": "Feature",
  "properties": {
    "iso:country":"US",
    "sg:address":"2222 E 5th St",
    "sg:city":"Superior",
    "sg:classifiers":[
        {
            "category":"Banks & Credit Unions",
            "subcategory":"Bank",
            "type":"Services"
        }
    ],
    "sg:phone":"+1 715 398 8945",
    "sg:postcode":"54880",
    "sg:province":"WI",
    "sg:tags":[
        "state"
    ],
    "wof:name":"Superior Community Credit Un",
    "wof:placetype":"venue"
},
  "geometry": {"coordinates":[-92.049296,46.703922],"type":"Point"}
}