{
  "type": "Feature",
  "properties": {
    "iso:country":"US",
    "sg:address":"2340 Holly Rd",
    "sg:city":"Neenah",
    "sg:classifiers":[
        {
            "category":"Shopping",
            "subcategory":"Bicycles & Sporting Goods",
            "type":"Retail Goods"
        }
    ],
    "sg:phone":"+1 920 733 6824",
    "sg:postcode":"54956",
    "sg:province":"WI",
    "wof:name":"Archery Shack",
    "wof:placetype":"venue"
},
  "geometry": {"coordinates":[-88.465507,44.234596],"type":"Point"}
}