{
  "type": "Feature",
  "properties": {
    "addr:full":"6638 Sheridan Rd Kenosha WI 53143",
    "addr:housenumber":"6638",
    "addr:postcode":"53143",
    "addr:street":"Sheridan Rd",
    "iso:country":"US",
    "sg:address":"6638 Sheridan Rd",
    "sg:city":"Kenosha",
    "sg:classifiers":[
        {
            "category":"Health Services",
            "subcategory":"Doctor",
            "type":"Services"
        }
    ],
    "sg:phone":"+1 262 925 8800",
    "sg:postcode":"53143",
    "sg:province":"WI",
    "sg:tags":[
        "physician",
        "surgeon"
    ],
    "wof:name":"Pediatric Therapies LLC",
    "wof:placetype":"venue"
},
  "geometry": {"coordinates":[-87.822768,42.573269],"type":"Point"}
}