{
  "type": "Feature",
  "properties": {
    "addr:full":"400 W Grant St Crandon WI 54520",
    "addr:housenumber":"400",
    "addr:postcode":"54520",
    "addr:street":"W Grant St",
    "iso:country":"US",
    "sg:address":"400 W Grant St",
    "sg:city":"Crandon",
    "sg:classifiers":[
        {
            "category":"Real Estate",
            "subcategory":"Real Estate Operator",
            "type":"Services"
        }
    ],
    "sg:phone":"+1 715 478 5030",
    "sg:postcode":"54520",
    "sg:province":"WI",
    "sg:tags":[
        "building",
        "apartment"
    ],
    "wof:name":"Grant Apts Office",
    "wof:placetype":"venue"
},
  "geometry": {"coordinates":[-88.907169,45.570928],"type":"Point"}
}