{
  "type": "Feature",
  "properties": {
    "iso:country":"US",
    "sg:address":"3801 Tower Ave",
    "sg:city":"Superior",
    "sg:classifiers":[
        {
            "category":"Professional",
            "subcategory":"Management & Consulting",
            "type":"Services"
        }
    ],
    "sg:phone":"+1 715 392 3166",
    "sg:postcode":"54880",
    "sg:province":"WI",
    "wof:name":"Howard Immel Inc",
    "wof:placetype":"venue"
},
  "geometry": {"coordinates":[-92.104193,46.693855],"type":"Point"}
}