{
  "type": "Feature",
  "properties": {
    "addr:full":"1216 N 13th St Milwaukee WI 53205",
    "addr:housenumber":"1216",
    "addr:postcode":"53205",
    "addr:street":"N 13Th St",
    "iso:country":"US",
    "sg:address":"1216 N 13th St",
    "sg:city":"Milwaukee",
    "sg:classifiers":[
        {
            "category":"Health Services",
            "subcategory":"Doctor",
            "type":"Services"
        }
    ],
    "sg:phone":"+1 414 931 0261",
    "sg:postcode":"53205",
    "sg:province":"WI",
    "sg:tags":[
        "clinic"
    ],
    "wof:name":"Marquette Clinic For Women",
    "wof:placetype":"venue"
},
  "geometry": {"coordinates":[-87.928594,43.046933],"type":"Point"}
}