{
  "type": "Feature",
  "properties": {
    "iso:country":"US",
    "sg:address":"1814 Truax Blvd",
    "sg:city":"Eau Claire",
    "sg:classifiers":[
        {
            "category":"Retail",
            "subcategory":"Repair Shop",
            "type":"Services"
        }
    ],
    "sg:phone":"+1 715 830 9969",
    "sg:postcode":"54703",
    "sg:province":"WI",
    "sg:tags":[
        "armature",
        "rewinding"
    ],
    "wof:name":"Mallum Electric Motor Service",
    "wof:placetype":"venue"
},
  "geometry": {"coordinates":[-91.532844,44.836712],"type":"Point"}
}