{
  "type": "Feature",
  "properties": {
    "iso:country":"US",
    "sg:address":"8791 Co Hwy K",
    "sg:city":"Elcho",
    "sg:classifiers":[
        {
            "category":"Retail",
            "subcategory":"Auto Repair",
            "type":"Services"
        }
    ],
    "sg:phone":"+1 715 275 3049",
    "sg:postcode":"54428",
    "sg:province":"WI",
    "sg:tags":[
        "body",
        "automobile",
        "painting"
    ],
    "wof:name":"Blast Tech Enterprises",
    "wof:placetype":"venue"
},
  "geometry": {"coordinates":[-89.085746,45.440917],"type":"Point"}
}