{
  "type": "Feature",
  "properties": {
    "addr:full":"2548 Violet Ln Merrill WI 54452",
    "addr:housenumber":"2548",
    "addr:postcode":"54452",
    "addr:street":"Violet Ln",
    "iso:country":"US",
    "sg:address":"2548 Violet Ln",
    "sg:city":"Merrill",
    "sg:classifiers":[
        {
            "category":"Building & Trades",
            "subcategory":"Construction",
            "type":"Services"
        }
    ],
    "sg:phone":"+1 715 536 8411",
    "sg:postcode":"54452",
    "sg:province":"WI",
    "sg:tags":[
        "contractor"
    ],
    "wof:name":"A B G Masonry Inc",
    "wof:placetype":"venue"
},
  "geometry": {"coordinates":[-89.55156700000001,45.181552],"type":"Point"}
}