{
  "type": "Feature",
  "properties": {
    "iso:country":"US",
    "sg:address":"485 S Walnut St",
    "sg:city":"Janesville",
    "sg:classifiers":[
        {
            "category":"Personal",
            "subcategory":"Beauty Salon",
            "type":"Services"
        }
    ],
    "sg:phone":"+1 608 741 6076",
    "sg:postcode":"53548",
    "sg:province":"WI",
    "wof:name":"Shearz",
    "wof:placetype":"venue"
},
  "geometry": {"coordinates":[-89.040546,42.676448],"type":"Point"}
}