{
  "type": "Feature",
  "properties": {
    "iso:country":"US",
    "sg:address":"9223 Cemetery Rd",
    "sg:city":"Middle Inlet",
    "sg:classifiers":[
        {
            "category":"Building & Trades",
            "subcategory":"Construction",
            "type":"Services"
        }
    ],
    "sg:phone":"+1 715 854 7329",
    "sg:postcode":"54114",
    "sg:province":"WI",
    "sg:tags":[
        "general",
        "contractor"
    ],
    "wof:name":"Dale Atwood Construction",
    "wof:placetype":"venue"
},
  "geometry": {"coordinates":[-87.99373799999999,45.289186],"type":"Point"}
}