{
  "type": "Feature",
  "properties": {
    "iso:country":"US",
    "sg:address":"615 Center St",
    "sg:city":"Lake Geneva",
    "sg:classifiers":[
        {
            "category":"Building & Trades",
            "subcategory":"Construction",
            "type":"Services"
        }
    ],
    "sg:phone":"+1 262 348 9044",
    "sg:postcode":"53147",
    "sg:province":"WI",
    "sg:tags":[
        "nonresidential"
    ],
    "wof:name":"Mark Bench Buildings",
    "wof:placetype":"venue"
},
  "geometry": {"coordinates":[-88.43341700000001,42.597645],"type":"Point"}
}