{
  "type": "Feature",
  "properties": {
    "iso:country":"US",
    "sg:address":"2117 Parkfield Dr",
    "sg:city":"West Bend",
    "sg:classifiers":[
        {
            "category":"Building & Trades",
            "subcategory":"Construction",
            "type":"Services"
        }
    ],
    "sg:phone":"+1 262 334 6241",
    "sg:postcode":"53090",
    "sg:province":"WI",
    "sg:tags":[
        "house"
    ],
    "wof:name":"A Builders & Remodeling",
    "wof:placetype":"venue"
},
  "geometry": {"coordinates":[-88.18008399999999,43.447276],"type":"Point"}
}