{
  "type": "Feature",
  "properties": {
    "iso:country":"US",
    "sg:address":"9254 Campbell Lake Rd",
    "sg:city":"Ogdensburg",
    "sg:classifiers":[
        {
            "category":"Sports & Exercise",
            "subcategory":"Golf",
            "type":"Entertainment"
        }
    ],
    "sg:phone":"+1 920 244 4653",
    "sg:postcode":"54962",
    "sg:province":"WI",
    "sg:tags":[
        "course",
        "public"
    ],
    "wof:name":"Glen Cairn Golf Course Ltd",
    "wof:placetype":"venue"
},
  "geometry": {"coordinates":[-88.99086,44.58241],"type":"Point"}
}