{
  "type": "Feature",
  "properties": {
    "addr:full":"300 Audubon Rd Sheboygan WI 53083",
    "addr:housenumber":"300",
    "addr:postcode":"53083",
    "addr:street":"Audubon Rd",
    "iso:country":"US",
    "sg:address":"300 Audubon Rd",
    "sg:city":"Sheboygan",
    "sg:classifiers":[
        {
            "category":"Professional",
            "subcategory":"Management & Consulting",
            "type":"Services"
        }
    ],
    "sg:phone":"+1 920 565 3766",
    "sg:postcode":"53083",
    "sg:province":"WI",
    "sg:tags":[
        "insurance"
    ],
    "wof:name":"Eric Eickhoff",
    "wof:placetype":"venue"
},
  "geometry": {"coordinates":[-87.819046,43.827701],"type":"Point"}
}