{
  "type": "Feature",
  "properties": {
    "iso:country":"US",
    "sg:address":"1630 Chestnut St",
    "sg:city":"Wisconsin Rapids",
    "sg:classifiers":[
        {
            "category":"Building & Trades",
            "subcategory":"Construction",
            "type":"Services"
        }
    ],
    "sg:phone":"+1 715 424 6964",
    "sg:postcode":"54494",
    "sg:province":"WI",
    "sg:tags":[
        "hanging",
        "contractor"
    ],
    "wof:name":"Midstate Painting",
    "wof:placetype":"venue"
},
  "geometry": {"coordinates":[-89.806574,44.383781],"type":"Point"}
}