{
  "type": "Feature",
  "properties": {
    "iso:country":"US",
    "sg:address":"7143 E Plaza Dr",
    "sg:city":"Beaver Dam",
    "sg:classifiers":[
        {
            "category":"Home & Garden",
            "subcategory":"Home Furnishings",
            "type":"Retail Goods"
        }
    ],
    "sg:phone":"+1 920 887 7987",
    "sg:postcode":"53916",
    "sg:province":"WI",
    "sg:tags":[
        "plumbing"
    ],
    "sg:website":"www.fireplaceworks.com",
    "wof:name":"Fireplace Works",
    "wof:placetype":"venue"
},
  "geometry": {"coordinates":[-88.808249,43.452636],"type":"Point"}
}