{
  "type": "Feature",
  "properties": {
    "iso:country":"US",
    "sg:address":"21375 Birdseye Ln",
    "sg:city":"Waukesha",
    "sg:classifiers":[
        {
            "category":"Manufacturing",
            "subcategory":"Electronics",
            "type":"Manufacturing & Wholesale Goods"
        }
    ],
    "sg:phone":"+1 262 798 0203",
    "sg:postcode":"53186",
    "sg:province":"WI",
    "sg:tags":[
        "equipment",
        "electronic",
        "supply"
    ],
    "wof:name":"Bear Electronics Inc",
    "wof:placetype":"venue"
},
  "geometry": {"coordinates":[-88.179241,43.022862],"type":"Point"}
}