{
  "type": "Feature",
  "properties": {
    "iso:country":"US",
    "sg:address":"3215 Benrud Pkwy",
    "sg:city":"Eau Claire",
    "sg:classifiers":[
        {
            "category":"Home & Garden",
            "subcategory":"Hardware",
            "type":"Retail Goods"
        }
    ],
    "sg:phone":"+1 715 834 5645",
    "sg:postcode":"54701",
    "sg:province":"WI",
    "wof:name":"Elite Machine",
    "wof:placetype":"venue"
},
  "geometry": {"coordinates":[-91.455324,44.768349],"type":"Point"}
}