{
  "type": "Feature",
  "properties": {
    "iso:country":"US",
    "sg:address":"7754 Rasmusen St",
    "sg:city":"Siren",
    "sg:classifiers":[
        {
            "category":"Social Services",
            "subcategory":"Adult Care",
            "type":"Services"
        }
    ],
    "sg:phone":"+1 715 349 5871",
    "sg:postcode":"54872",
    "sg:province":"WI",
    "sg:tags":[
        "home"
    ],
    "wof:name":"Birchview",
    "wof:placetype":"venue"
},
  "geometry": {"coordinates":[-92.383281,45.774641],"type":"Point"}
}