{
  "type": "Feature",
  "properties": {
    "iso:country":"US",
    "sg:address":"2117 Lakeside Pl",
    "sg:city":"Green Bay",
    "sg:classifiers":[
        {
            "category":"Wholesale",
            "subcategory":"Electrical",
            "type":"Manufacturing & Wholesale Goods"
        }
    ],
    "sg:phone":"+1 920 468 1219",
    "sg:postcode":"54302",
    "sg:province":"WI",
    "sg:tags":[
        "electronic"
    ],
    "wof:name":"Monster Jamz Productions",
    "wof:placetype":"venue"
},
  "geometry": {"coordinates":[-87.963563,44.52871],"type":"Point"}
}