{
  "type": "Feature",
  "properties": {
    "addr:full":"424 College St Beloit WI 53511",
    "addr:housenumber":"424",
    "addr:postcode":"53511",
    "addr:street":"College St",
    "iso:country":"US",
    "sg:address":"424 College St",
    "sg:city":"Beloit",
    "sg:classifiers":[
        {
            "category":"Social Services",
            "type":"Services"
        }
    ],
    "sg:phone":"+1 608 362 3683",
    "sg:postcode":"53511",
    "sg:province":"WI",
    "sg:tags":[
        "food",
        "senior",
        "bank",
        "citizen"
    ],
    "sg:website":"http://www.mowaa.org",
    "wof:name":"Meals on Wheels Beloit",
    "wof:placetype":"venue"
},
  "geometry": {"coordinates":[-89.029563,42.500057],"type":"Point"}
}