{
  "type": "Feature",
  "properties": {
    "addr:full":"1 Ontario St Montreal WI 54550",
    "addr:housenumber":"1",
    "addr:postcode":"54550",
    "addr:street":"Ontario St",
    "iso:country":"US",
    "sg:address":"1 Ontario St",
    "sg:city":"Montreal",
    "sg:classifiers":[
        {
            "category":"Building & Trades",
            "subcategory":"Landscaping Services",
            "type":"Services"
        }
    ],
    "sg:phone":"+1 715 561 4358",
    "sg:postcode":"54550",
    "sg:province":"WI",
    "sg:tags":[
        "landscape",
        "contractor"
    ],
    "wof:name":"Klaus' Lawn & Garden Svc",
    "wof:placetype":"venue"
},
  "geometry": {"coordinates":[-90.23578999999999,46.431789],"type":"Point"}
}