{
  "type": "Feature",
  "properties": {
    "iso:country":"US",
    "sg:address":"16720 Victor Rd",
    "sg:city":"New Berlin",
    "sg:classifiers":[
        {
            "category":"Wholesale",
            "subcategory":"Machinery & Supplies",
            "type":"Manufacturing & Wholesale Goods"
        }
    ],
    "sg:phone":"+1 262 797 5730",
    "sg:postcode":"53151",
    "sg:province":"WI",
    "sg:tags":[
        "steel",
        "stainless",
        "valve"
    ],
    "sg:website":"www.definox-usa.com",
    "wof:name":"Defontaine Of America Inc",
    "wof:placetype":"venue"
},
  "geometry": {"coordinates":[-88.121421,42.986856],"type":"Point"}
}