{
  "type": "Feature",
  "properties": {
    "addr:full":"8422 W Capitol Dr Milwaukee WI 53222",
    "addr:housenumber":"8422",
    "addr:postcode":"53222",
    "addr:street":"W Capitol Dr",
    "iso:country":"US",
    "sg:address":"8422 W Capitol Dr",
    "sg:city":"Milwaukee",
    "sg:classifiers":[
        {
            "category":"Home & Garden",
            "subcategory":"Building Materials",
            "type":"Retail Goods"
        }
    ],
    "sg:phone":"+1 414 462 9150",
    "sg:postcode":"53222",
    "sg:province":"WI",
    "sg:tags":[
        "paint",
        "floor",
        "covering"
    ],
    "wof:name":"Sherwin-Williams Paints",
    "wof:placetype":"venue"
},
  "geometry": {"coordinates":[-88.01861599999999,43.089895],"type":"Point"}
}