{
  "type": "Feature",
  "properties": {
    "addr:full":"124 W Wisconsin Ave Neenah WI 54956",
    "addr:housenumber":"124",
    "addr:postcode":"54956",
    "addr:street":"W Wisconsin Ave",
    "iso:country":"US",
    "sg:address":"124 W Wisconsin Ave",
    "sg:city":"Neenah",
    "sg:classifiers":[
        {
            "category":"Banks & Credit Unions",
            "subcategory":"Investment Brokerage",
            "type":"Services"
        }
    ],
    "sg:phone":"+1 920 886 0220",
    "sg:postcode":"54956",
    "sg:province":"WI",
    "sg:tags":[
        "consultant",
        "planning",
        "financial"
    ],
    "sg:website":"www.marketplacefinancialgroup.com",
    "wof:name":"Marketplace Financial Group",
    "wof:placetype":"venue"
},
  "geometry": {"coordinates":[-88.463031,44.186993],"type":"Point"}
}