{
  "type": "Feature",
  "properties": {
    "addr:full":"9520 State Hwy 26 Burnett WI 53922",
    "addr:housenumber":"9520",
    "addr:postcode":"53922",
    "addr:street":"State Hwy 26",
    "iso:country":"US",
    "sg:address":"9520 State Hwy 26",
    "sg:city":"Burnett",
    "sg:classifiers":[
        {
            "category":"Organizations",
            "subcategory":"Religious Organization",
            "type":"Services"
        }
    ],
    "sg:phone":"+1 920 689 2361",
    "sg:postcode":"53922",
    "sg:province":"WI",
    "sg:tags":[
        "church"
    ],
    "wof:name":"Emmanuel Lutheran Church",
    "wof:placetype":"venue"
},
  "geometry": {"coordinates":[-88.709661,43.544304],"type":"Point"}
}