{
  "type": "Feature",
  "properties": {
    "iso:country":"US",
    "sg:address":"500 Co Rd K",
    "sg:city":"Waupaca",
    "sg:classifiers":[
        {
            "category":"Local Transit",
            "type":"Transportation"
        }
    ],
    "sg:phone":"+1 715 258 8103",
    "sg:postcode":"54981",
    "sg:province":"WI",
    "sg:tags":[
        "ambulance"
    ],
    "wof:name":"Waupaca Area Ambulance",
    "wof:placetype":"venue"
},
  "geometry": {"coordinates":[-89.079775,44.360676],"type":"Point"}
}