{
  "type": "Feature",
  "properties": {
    "iso:country":"US",
    "sg:address":"1631 N Main St",
    "sg:city":"West Bend",
    "sg:classifiers":[
        {
            "category":"Shopping",
            "subcategory":"Computers & Home Electronics",
            "type":"Retail Goods"
        }
    ],
    "sg:phone":"+1 262 338 6019",
    "sg:postcode":"53090",
    "sg:province":"WI",
    "sg:tags":[
        "mobile",
        "ca",
        "sales",
        "licensed",
        "radio",
        "common"
    ],
    "wof:name":"Moraine Radio",
    "wof:placetype":"venue"
},
  "geometry": {"coordinates":[-88.18713099999999,43.44237],"type":"Point"}
}