{
  "type": "Feature",
  "properties": {
    "iso:country":"US",
    "sg:address":"116 W Wisconsin Ave",
    "sg:city":"Tomahawk",
    "sg:classifiers":[
        {
            "category":"Personal",
            "subcategory":"Beauty Salon",
            "type":"Services"
        }
    ],
    "sg:phone":"+1 715 453 5199",
    "sg:postcode":"54487",
    "sg:province":"WI",
    "sg:tags":[
        "shop"
    ],
    "wof:name":"Radiant Nails",
    "wof:placetype":"venue"
},
  "geometry": {"coordinates":[-89.731948,45.471084],"type":"Point"}
}