{
  "type": "Feature",
  "properties": {
    "addr:full":"1880 N Casaloma Dr Appleton WI 54913",
    "addr:housenumber":"1880",
    "addr:postcode":"54913",
    "addr:street":"N Casaloma Dr",
    "iso:country":"US",
    "sg:address":"1880 N Casaloma Dr",
    "sg:city":"Appleton",
    "sg:classifiers":[
        {
            "category":"Restaurant",
            "type":"Food & Drink"
        }
    ],
    "sg:phone":"+1 920 968 0052",
    "sg:postcode":"54913",
    "sg:province":"WI",
    "sg:tags":[
        "caterer"
    ],
    "wof:name":"Cedar Creek West",
    "wof:placetype":"venue"
},
  "geometry": {"coordinates":[-88.476412,44.277457],"type":"Point"}
}