{
  "type": "Feature",
  "properties": {
    "iso:country":"US",
    "sg:address":"2353 S Ridge Rd",
    "sg:city":"Green Bay",
    "sg:classifiers":[
        {
            "category":"Health Services",
            "subcategory":"Doctor",
            "type":"Services"
        }
    ],
    "sg:phone":"+1 920 494 9685",
    "sg:postcode":"54304",
    "sg:province":"WI",
    "sg:tags":[
        "physician",
        "surgeon"
    ],
    "wof:name":"Ridgeview Medical Arts",
    "wof:placetype":"venue"
},
  "geometry": {"coordinates":[-88.073886,44.490832],"type":"Point"}
}