{
  "type": "Feature",
  "properties": {
    "iso:country":"US",
    "sg:address":"8844 Marsh Dr",
    "sg:city":"Sheldon",
    "sg:classifiers":[
        {
            "category":"Professional",
            "subcategory":"Art Services",
            "type":"Services"
        }
    ],
    "sg:phone":"+1 715 452 5216",
    "sg:postcode":"54766",
    "sg:province":"WI",
    "sg:tags":[
        "graphic",
        "designer"
    ],
    "wof:name":"Rich Tuisl Productions",
    "wof:placetype":"venue"
},
  "geometry": {"coordinates":[-90.88372,45.350944],"type":"Point"}
}