{
  "type": "Feature",
  "properties": {
    "addr:full":"101 Mill St Blanchardville WI 53516",
    "addr:housenumber":"101",
    "addr:postcode":"53516",
    "addr:street":"Mill St",
    "iso:country":"US",
    "sg:address":"101 Mill St",
    "sg:city":"Blanchardville",
    "sg:classifiers":[
        {
            "category":"Wholesale",
            "subcategory":"Machinery & Supplies",
            "type":"Manufacturing & Wholesale Goods"
        }
    ],
    "sg:phone":"+1 608 523 4713",
    "sg:postcode":"53516",
    "sg:province":"WI",
    "sg:tags":[
        "equipment",
        "dairy"
    ],
    "wof:name":"Ederer Dairy Supply & Hardware",
    "wof:placetype":"venue"
},
  "geometry": {"coordinates":[-89.86192699999999,42.810793],"type":"Point"}
}