{
  "type": "Feature",
  "properties": {
    "addr:full":"3433 Oakwood Hills Pkwy Eau Claire WI 54701",
    "addr:housenumber":"3433",
    "addr:postcode":"54701",
    "addr:street":"Oakwood Hills Pkwy",
    "iso:country":"US",
    "sg:address":"3433 Oakwood Hills Pkwy",
    "sg:city":"Eau Claire",
    "sg:classifiers":[
        {
            "category":"Professional",
            "subcategory":"Engineering",
            "type":"Services"
        }
    ],
    "sg:phone":"+1 715 834 3161",
    "sg:postcode":"54701",
    "sg:province":"WI",
    "sg:tags":[
        "engineer"
    ],
    "sg:website":"www.ayresassociates.com",
    "wof:name":"Ayres Associates",
    "wof:placetype":"venue"
},
  "geometry": {"coordinates":[-91.446673,44.782982],"type":"Point"}
}