{
  "type": "Feature",
  "properties": {
    "iso:country":"US",
    "sg:address":"1222 Main St",
    "sg:city":"Bloomer",
    "sg:classifiers":[
        {
            "category":"Organizations",
            "subcategory":"Religious Organization",
            "type":"Services"
        }
    ],
    "sg:phone":"+1 715 568 3255",
    "sg:postcode":"54724",
    "sg:province":"WI",
    "sg:tags":[
        "church"
    ],
    "wof:name":"St Pauls Catholic Church",
    "wof:placetype":"venue"
},
  "geometry": {"coordinates":[-91.488756,45.103408],"type":"Point"}
}