{
  "type": "Feature",
  "properties": {
    "iso:country":"US",
    "sg:address":"9650 150th St",
    "sg:city":"Downing",
    "sg:classifiers":[
        {
            "category":"Health Services",
            "subcategory":"Nursing And Care Facility",
            "type":"Services"
        }
    ],
    "sg:phone":"+1 715 643 3120",
    "sg:postcode":"54734",
    "sg:province":"WI",
    "sg:tags":[
        "skilled"
    ],
    "wof:name":"Triple Springs Country Ho",
    "wof:placetype":"venue"
},
  "geometry": {"coordinates":[-92.090447,45.027632],"type":"Point"}
}