{
  "type": "Feature",
  "properties": {
    "addr:full":"1334 Matchey Rd Independence WI 54747",
    "addr:housenumber":"1334",
    "addr:postcode":"54747",
    "addr:street":"Matchey Rd",
    "iso:country":"US",
    "sg:address":"1334 Matchey Rd",
    "sg:city":"Independence",
    "sg:classifiers":[
        {
            "category":"Building & Trades",
            "subcategory":"Construction",
            "type":"Services"
        }
    ],
    "sg:phone":"+1 715 985 3450",
    "sg:postcode":"54747",
    "sg:province":"WI",
    "wof:name":"JJJ Construction",
    "wof:placetype":"venue"
},
  "geometry": {"coordinates":[-91.533883,44.400068],"type":"Point"}
}