{
  "type": "Feature",
  "properties": {
    "addr:full":"2546 Omro Rd Oshkosh WI 54904",
    "addr:housenumber":"2546",
    "addr:postcode":"54904",
    "addr:street":"Omro Rd",
    "iso:country":"US",
    "sg:address":"2546 Omro Rd",
    "sg:city":"Oshkosh",
    "sg:classifiers":[
        {
            "category":"Home & Garden",
            "subcategory":"Garden Supply",
            "type":"Retail Goods"
        }
    ],
    "sg:phone":"+1 920 235 3827",
    "sg:postcode":"54904",
    "sg:province":"WI",
    "sg:tags":[
        "vehicle"
    ],
    "sg:website":"www.tpsales.net",
    "wof:name":"T-P Sales",
    "wof:placetype":"venue"
},
  "geometry": {"coordinates":[-88.597059,44.03282],"type":"Point"}
}