{
  "type": "Feature",
  "properties": {
    "addr:full":"908 Bertha St Wausau WI 54403",
    "addr:housenumber":"908",
    "addr:postcode":"54403",
    "addr:street":"Bertha St",
    "iso:country":"US",
    "sg:address":"908 Bertha St",
    "sg:city":"Wausau",
    "sg:classifiers":[
        {
            "category":"Organizations",
            "subcategory":"Community Association",
            "type":"Services"
        }
    ],
    "sg:phone":"+1 715 842 2601",
    "sg:postcode":"54403",
    "sg:province":"WI",
    "wof:name":"Catholic Order of Forester",
    "wof:placetype":"venue"
},
  "geometry": {"coordinates":[-89.63035499999999,44.93177],"type":"Point"}
}