{
  "type": "Feature",
  "properties": {
    "addr:full":"305 McKinley St Fond Du Lac WI 54937",
    "addr:housenumber":"305",
    "addr:postcode":"54937",
    "addr:street":"Mckinley St",
    "iso:country":"US",
    "sg:address":"305 McKinley St",
    "sg:city":"Fond Du Lac",
    "sg:classifiers":[
        {
            "category":"Education",
            "subcategory":"School",
            "type":"Public Place"
        }
    ],
    "sg:phone":"+1 920 929 3754",
    "sg:postcode":"54937",
    "sg:province":"WI",
    "sg:tags":[
        "middle"
    ],
    "wof:name":"Middle School",
    "wof:placetype":"venue"
},
  "geometry": {"coordinates":[-88.48912799999999,43.81326],"type":"Point"}
}