{
  "type": "Feature",
  "properties": {
    "iso:country":"US",
    "sg:address":"5532 Hamilton Ave",
    "sg:city":"Sparta",
    "sg:classifiers":[
        {
            "category":"Building & Trades",
            "subcategory":"Construction",
            "type":"Services"
        }
    ],
    "sg:phone":"+1 608 269 2605",
    "sg:postcode":"54656",
    "sg:province":"WI",
    "sg:tags":[
        "residential",
        "contractor"
    ],
    "wof:name":"Von Ruden/Schmitz Construction",
    "wof:placetype":"venue"
},
  "geometry": {"coordinates":[-90.883397,43.939935],"type":"Point"}
}