{
  "type": "Feature",
  "properties": {
    "iso:country":"US",
    "sg:address":"627 Bay Shore Dr",
    "sg:city":"Oshkosh",
    "sg:classifiers":[
        {
            "category":"Manufacturing",
            "subcategory":"Retail Goods",
            "type":"Manufacturing & Wholesale Goods"
        }
    ],
    "sg:phone":"+1 920 231 9620",
    "sg:postcode":"54901",
    "sg:province":"WI",
    "sg:tags":[
        "candle"
    ],
    "sg:website":"www.blythehomescents.com",
    "wof:name":"Blyth Homescents",
    "wof:placetype":"venue"
},
  "geometry": {"coordinates":[-88.529234,44.012041],"type":"Point"}
}