{
  "type": "Feature",
  "properties": {
    "iso:country":"US",
    "sg:address":"868 W Main St",
    "sg:city":"Brownsville",
    "sg:classifiers":[
        {
            "category":"Autos & Motor Vehicles",
            "subcategory":"Fuel & Gas Station",
            "type":"Retail Goods"
        }
    ],
    "sg:phone":"+1 920 583 3700",
    "sg:postcode":"53006",
    "sg:province":"WI",
    "sg:tags":[
        "oil"
    ],
    "wof:name":"Cole's Brownsville Amoco",
    "wof:placetype":"venue"
},
  "geometry": {"coordinates":[-88.49991199999999,43.61623],"type":"Point"}
}