{
  "type": "Feature",
  "properties": {
    "addr:full":"5181 McCarthy Rd Lena WI 54139",
    "addr:housenumber":"5181",
    "addr:postcode":"54139",
    "addr:street":"Mccarthy Rd",
    "iso:country":"US",
    "sg:address":"5181 McCarthy Rd",
    "sg:city":"Lena",
    "sg:classifiers":[
        {
            "category":"Freight",
            "type":"Transportation"
        }
    ],
    "sg:phone":"+1 920 834 4499",
    "sg:postcode":"54139",
    "sg:province":"WI",
    "sg:tags":[
        "operator",
        "trucking"
    ],
    "wof:name":"J H Fischer Transfer",
    "wof:placetype":"venue"
},
  "geometry": {"coordinates":[-88.030856,44.901444],"type":"Point"}
}