{
  "type": "Feature",
  "properties": {
    "iso:country":"US",
    "sg:address":"440 Cardinal Ln",
    "sg:city":"Hartland",
    "sg:classifiers":[
        {
            "category":"Communications",
            "subcategory":"Newspaper",
            "type":"Services"
        }
    ],
    "sg:phone":"+1 262 361 9119",
    "sg:postcode":"53029",
    "sg:province":"WI",
    "wof:name":"ICP Group",
    "wof:placetype":"venue"
},
  "geometry": {"coordinates":[-88.35007899999999,43.095875],"type":"Point"}
}