{
  "type": "Feature",
  "properties": {
    "iso:country":"US",
    "sg:address":"2724 Aquarius Rd",
    "sg:city":"Green Bay",
    "sg:classifiers":[
        {
            "category":"Professional",
            "subcategory":"Business Services",
            "type":"Services"
        }
    ],
    "sg:phone":"+1 920 435 7431",
    "sg:postcode":"54311",
    "sg:province":"WI",
    "wof:name":"Adams Homestead Partnership LL",
    "wof:placetype":"venue"
},
  "geometry": {"coordinates":[-87.946649,44.457809],"type":"Point"}
}