{
  "type": "Feature",
  "properties": {
    "iso:country":"US",
    "sg:address":"136 W Knapp St",
    "sg:city":"Rice Lake",
    "sg:classifiers":[
        {
            "category":"Building & Trades",
            "subcategory":"Plumbing",
            "type":"Services"
        }
    ],
    "sg:phone":"+1 715 234 2340",
    "sg:postcode":"54868",
    "sg:province":"WI",
    "sg:tags":[
        "contractor"
    ],
    "wof:name":"Lake Heating & Cooling",
    "wof:placetype":"venue"
},
  "geometry": {"coordinates":[-91.737854,45.50878],"type":"Point"}
}