{
  "type": "Feature",
  "properties": {
    "iso:country":"US",
    "sg:address":"1284 Lakeview Dr",
    "sg:city":"Hatley",
    "sg:classifiers":[
        {
            "category":"Building & Trades",
            "subcategory":"Equipment Rental",
            "type":"Services"
        }
    ],
    "sg:phone":"+1 715 446 3978",
    "sg:postcode":"54440",
    "sg:province":"WI",
    "wof:name":"North Country Rentals LLC",
    "wof:placetype":"venue"
},
  "geometry": {"coordinates":[-89.342488,44.815189],"type":"Point"}
}