{
  "type": "Feature",
  "properties": {
    "iso:country":"US",
    "sg:address":"18 Jewelers Park Dr",
    "sg:city":"Neenah",
    "sg:classifiers":[
        {
            "category":"Manufacturing",
            "subcategory":"Printing",
            "type":"Manufacturing & Wholesale Goods"
        }
    ],
    "sg:phone":"+1 920 722 6333",
    "sg:postcode":"54956",
    "sg:province":"WI",
    "sg:tags":[
        "commercial"
    ],
    "wof:name":"Teuteberg Inc",
    "wof:placetype":"venue"
},
  "geometry": {"coordinates":[-88.483868,44.156377],"type":"Point"}
}