{
  "type": "Feature",
  "properties": {
    "iso:country":"US",
    "sg:address":"2313 W Wells St",
    "sg:city":"Milwaukee",
    "sg:classifiers":[
        {
            "category":"Retail",
            "subcategory":"Auto Repair",
            "type":"Services"
        }
    ],
    "sg:phone":"+1 414 344 2740",
    "sg:postcode":"53233",
    "sg:province":"WI",
    "sg:tags":[
        "muffler",
        "exhaust",
        "system"
    ],
    "wof:name":"John The Muffler Man",
    "wof:placetype":"venue"
},
  "geometry": {"coordinates":[-87.942757,43.040176],"type":"Point"}
}