{
  "type": "Feature",
  "properties": {
    "iso:country":"US",
    "sg:address":"10407 W Concordia Ave",
    "sg:city":"Milwaukee",
    "sg:classifiers":[
        {
            "category":"Building & Trades",
            "subcategory":"Construction",
            "type":"Services"
        }
    ],
    "sg:phone":"+1 414 453 5900",
    "sg:postcode":"53222",
    "sg:province":"WI",
    "sg:tags":[
        "general",
        "contractor"
    ],
    "wof:name":"Schaefer Brothers Building Co",
    "wof:placetype":"venue"
},
  "geometry": {"coordinates":[-88.044177,43.079377],"type":"Point"}
}