{
  "type": "Feature",
  "properties": {
    "iso:country":"US",
    "sg:address":"1937 W Windsor Cir",
    "sg:city":"Milwaukee",
    "sg:classifiers":[
        {
            "category":"Building & Trades",
            "subcategory":"Cleaning & Sanitation",
            "type":"Services"
        }
    ],
    "sg:phone":"+1 414 828 7070",
    "sg:postcode":"53209",
    "sg:province":"WI",
    "wof:name":"Nishas Janitorial Services &",
    "wof:placetype":"venue"
},
  "geometry": {"coordinates":[-87.93545899999999,43.136652],"type":"Point"}
}