{
  "type": "Feature",
  "properties": {
    "iso:country":"US",
    "sg:address":"8780 S Howell Ave",
    "sg:city":"Oak Creek",
    "sg:classifiers":[
        {
            "category":"Banks & Credit Unions",
            "subcategory":"Bank",
            "type":"Services"
        }
    ],
    "sg:phone":"+1 414 764 3400",
    "sg:postcode":"53154",
    "sg:province":"WI",
    "sg:tags":[
        "federal",
        "savings",
        "institution"
    ],
    "sg:website":"www.mutualsavingsbank.com",
    "wof:name":"Bank Mutual",
    "wof:placetype":"venue"
},
  "geometry": {"coordinates":[-87.912201,42.884921],"type":"Point"}
}