{
  "type": "Feature",
  "properties": {
    "iso:country":"US",
    "sg:address":"4913 W Center St",
    "sg:city":"Milwaukee",
    "sg:classifiers":[
        {
            "category":"Personal",
            "subcategory":"Beauty Salon",
            "type":"Services"
        }
    ],
    "sg:phone":"+1 414 445 5525",
    "sg:postcode":"53210",
    "sg:province":"WI",
    "wof:name":"Le Bean's Barber & Stylists",
    "wof:placetype":"venue"
},
  "geometry": {"coordinates":[-87.976091,43.067884],"type":"Point"}
}