{
  "type": "Feature",
  "properties": {
    "iso:country":"US",
    "sg:address":"1444 Blake Ave",
    "sg:city":"Racine",
    "sg:classifiers":[
        {
            "category":"Restaurant",
            "type":"Food & Drink"
        }
    ],
    "sg:phone":"+1 262 632 3392",
    "sg:postcode":"53404",
    "sg:province":"WI",
    "wof:name":"De Rose Bar",
    "wof:placetype":"venue"
},
  "geometry": {"coordinates":[-87.801795,42.738599],"type":"Point"}
}