{
  "type": "Feature",
  "properties": {
    "iso:country":"US",
    "sg:address":"220 N Adams St",
    "sg:city":"Green Bay",
    "sg:classifiers":[
        {
            "category":"Shopping",
            "subcategory":"Jewelry",
            "type":"Retail Goods"
        }
    ],
    "sg:phone":"+1 920 432 4441",
    "sg:postcode":"54301",
    "sg:province":"WI",
    "sg:tags":[
        "diamond",
        "coin",
        "jeweler"
    ],
    "wof:name":"Reiser's Diamond Vault Inc",
    "wof:placetype":"venue"
},
  "geometry": {"coordinates":[-88.01339900000001,44.515508],"type":"Point"}
}