{
  "type": "Feature",
  "properties": {
    "addr:full":"5609 Star School Rd Fort Atkinson WI 53538",
    "addr:housenumber":"5609",
    "addr:postcode":"53538",
    "addr:street":"Star School Rd",
    "iso:country":"US",
    "sg:address":"5609 Star School Rd",
    "sg:city":"Fort Atkinson",
    "sg:classifiers":[
        {
            "category":"Government",
            "subcategory":"Office",
            "type":"Public Place"
        }
    ],
    "sg:phone":"+1 920 563 4510",
    "sg:postcode":"53538",
    "sg:province":"WI",
    "sg:tags":[
        "executive"
    ],
    "wof:name":"Koshkonong Town",
    "wof:placetype":"venue"
},
  "geometry": {"coordinates":[-88.826882,42.88003],"type":"Point"}
}