{
  "type": "Feature",
  "properties": {
    "iso:country":"US",
    "sg:address":"6302 Bluff Rd",
    "sg:city":"Whitewater",
    "sg:classifiers":[
        {
            "category":"Wholesale",
            "subcategory":"Computers",
            "type":"Manufacturing & Wholesale Goods"
        }
    ],
    "sg:phone":"+1 262 495 2111",
    "sg:postcode":"53190",
    "sg:province":"WI",
    "wof:name":"Datalink Corp",
    "wof:placetype":"venue"
},
  "geometry": {"coordinates":[-88.60717099999999,42.835689],"type":"Point"}
}