{
  "type": "Feature",
  "properties": {
    "iso:country":"US",
    "sg:address":"1750 N 118th St",
    "sg:city":"Milwaukee",
    "sg:classifiers":[
        {
            "category":"Building & Trades",
            "subcategory":"Construction",
            "type":"Services"
        }
    ],
    "sg:phone":"+1 414 774 1136",
    "sg:postcode":"53226",
    "sg:province":"WI",
    "sg:tags":[
        "framing",
        "contractor"
    ],
    "wof:name":"Wizco Construction LLC",
    "wof:placetype":"venue"
},
  "geometry": {"coordinates":[-88.05997000000001,43.05439],"type":"Point"}
}