{
  "type": "Feature",
  "properties": {
    "iso:country":"US",
    "sg:address":"7986 E Friesland Rd",
    "sg:city":"Randolph",
    "sg:classifiers":[
        {
            "category":"Farming",
            "subcategory":"Dairy Farm",
            "type":"Manufacturing & Wholesale Goods"
        }
    ],
    "sg:phone":"+1 920 326 3878",
    "sg:postcode":"53956",
    "sg:province":"WI",
    "wof:name":"Robert Koopmans",
    "wof:placetype":"venue"
},
  "geometry": {"coordinates":[-89.046968,43.569018],"type":"Point"}
}