{
  "type": "Feature",
  "properties": {
    "iso:country":"US",
    "sg:address":"3080 Nassau Dr",
    "sg:city":"Brookfield",
    "sg:classifiers":[
        {
            "category":"Professional",
            "subcategory":"Business Services",
            "type":"Services"
        }
    ],
    "sg:phone":"+1 262 784 2296",
    "sg:postcode":"53045",
    "sg:province":"WI",
    "wof:name":"Gcd Enterprises",
    "wof:placetype":"venue"
},
  "geometry": {"coordinates":[-88.13281000000001,43.075739],"type":"Point"}
}