{
  "type": "Feature",
  "properties": {
    "iso:country":"US",
    "sg:address":"1102 Western Ave",
    "sg:city":"Mosinee",
    "sg:classifiers":[
        {
            "category":"Retail",
            "subcategory":"Auto Repair",
            "type":"Services"
        }
    ],
    "sg:phone":"+1 715 693 2600",
    "sg:postcode":"54455",
    "sg:province":"WI",
    "sg:tags":[
        "automotive",
        "tune"
    ],
    "sg:website":"http://www.napaautocare.com/",
    "wof:name":"Kohnert Auto Repair",
    "wof:placetype":"venue"
},
  "geometry": {"coordinates":[-89.719615,44.788839],"type":"Point"}
}