{
  "type": "Feature",
  "properties": {
    "addr:full":"7903 W Capitol Dr Milwaukee WI 53222",
    "addr:housenumber":"7903",
    "addr:postcode":"53222",
    "addr:street":"W Capitol Dr",
    "iso:country":"US",
    "sg:address":"7903 W Capitol Dr",
    "sg:city":"Milwaukee",
    "sg:classifiers":[
        {
            "category":"Organizations",
            "subcategory":"Religious Organization",
            "type":"Services"
        }
    ],
    "sg:phone":"+1 414 464 8241",
    "sg:postcode":"53222",
    "sg:province":"WI",
    "sg:tags":[
        "church"
    ],
    "wof:name":"Highest Praise Records",
    "wof:placetype":"venue"
},
  "geometry": {"coordinates":[-88.012359,43.089803],"type":"Point"}
}