{
  "type": "Feature",
  "properties": {
    "addr:full":"2974 E Mertes Rd Superior WI 54880",
    "addr:housenumber":"2974",
    "addr:postcode":"54880",
    "addr:street":"E Mertes Rd",
    "iso:country":"US",
    "sg:address":"2974 E Mertes Rd",
    "sg:city":"Superior",
    "sg:classifiers":[
        {
            "category":"Autos & Motor Vehicles",
            "subcategory":"Automobile Sales",
            "type":"Retail Goods"
        }
    ],
    "sg:phone":"+1 715 399 2597",
    "sg:postcode":"54880",
    "sg:province":"WI",
    "sg:tags":[
        "car",
        "used",
        "dealer"
    ],
    "wof:name":"Country Road Auto Sales Inc",
    "wof:placetype":"venue"
},
  "geometry": {"coordinates":[-92.150065,46.597592],"type":"Point"}
}