{
  "type": "Feature",
  "properties": {
    "iso:country":"US",
    "sg:address":"257 N Hickory St",
    "sg:city":"Fond Du Lac",
    "sg:classifiers":[
        {
            "category":"Building & Trades",
            "subcategory":"Construction",
            "type":"Services"
        }
    ],
    "sg:phone":"+1 920 922 2910",
    "sg:postcode":"54935",
    "sg:province":"WI",
    "sg:tags":[
        "tile",
        "dealer"
    ],
    "wof:name":"Fond Du Lac Mosaic Tile Co Inc",
    "wof:placetype":"venue"
},
  "geometry": {"coordinates":[-88.462583,43.785169],"type":"Point"}
}