{
  "type": "Feature",
  "properties": {
    "iso:country":"US",
    "sg:address":"725 Gilmore St",
    "sg:city":"Madison",
    "sg:classifiers":[
        {
            "category":"Organizations",
            "subcategory":"Religious Organization",
            "type":"Services"
        }
    ],
    "sg:phone":"+1 608 233 8709",
    "sg:postcode":"53711",
    "sg:province":"WI",
    "sg:tags":[
        "church"
    ],
    "sg:website":"www.glenwoodmoravianchurch.org",
    "wof:name":"Glenwood Moravian Cmnty Church",
    "wof:placetype":"venue"
},
  "geometry": {"coordinates":[-89.433234,43.054813],"type":"Point"}
}