{
  "type": "Feature",
  "properties": {
    "iso:country":"US",
    "sg:address":"7915 N 66th St Ofc",
    "sg:city":"Milwaukee",
    "sg:classifiers":[
        {
            "category":"Place Of Worship",
            "subcategory":"Church",
            "type":"Public Place"
        },
        {
            "category":"Place Of Worship",
            "type":"Public Place"
        }
    ],
    "sg:phone":"+1 262 242 2878",
    "sg:postcode":"53223",
    "sg:province":"WI",
    "sg:tags":[
        "churches-pentecostal-independent",
        "churches-pentecostal"
    ],
    "wof:name":"Eternal Life Church Of God In Christ Inc",
    "wof:placetype":"venue"
},
  "geometry": {"coordinates":[-87.99177299999999,43.162338],"type":"Point"}
}