{
  "type": "Feature",
  "properties": {
    "iso:country":"US",
    "sg:address":"1521 Sheridan Rd",
    "sg:city":"Kenosha",
    "sg:classifiers":[
        {
            "category":"Personal",
            "subcategory":"Beauty Salon",
            "type":"Services"
        }
    ],
    "sg:phone":"+1 262 551 8795",
    "sg:postcode":"53140",
    "sg:province":"WI",
    "sg:tags":[
        "shop"
    ],
    "wof:name":"Cut N Dried",
    "wof:placetype":"venue"
},
  "geometry": {"coordinates":[-87.821551,42.629156],"type":"Point"}
}