{
  "type": "Feature",
  "properties": {
    "iso:country":"US",
    "sg:address":"8953 Beachnut Ln",
    "sg:city":"Algoma",
    "sg:classifiers":[
        {
            "category":"Real Estate",
            "subcategory":"Real Estate Operator",
            "type":"Services"
        }
    ],
    "sg:phone":"+1 920 837 7289",
    "sg:postcode":"54201",
    "sg:province":"WI",
    "sg:tags":[
        "property",
        "lessor"
    ],
    "wof:name":"Peter Buhr",
    "wof:placetype":"venue"
},
  "geometry": {"coordinates":[-87.555126,44.648292],"type":"Point"}
}