{
  "type": "Feature",
  "properties": {
    "addr:full":"1634 S 24th St Sheboygan WI 53081",
    "addr:housenumber":"1634",
    "addr:postcode":"53081",
    "addr:street":"S 24Th St",
    "iso:country":"US",
    "sg:address":"1634 S 24th St",
    "sg:city":"Sheboygan",
    "sg:classifiers":[
        {
            "category":"Social Services",
            "type":"Services"
        }
    ],
    "sg:phone":"+1 920 803 9545",
    "sg:postcode":"53081",
    "sg:province":"WI",
    "wof:name":"Diamonds Youth Baseball",
    "wof:placetype":"venue"
},
  "geometry": {"coordinates":[-87.736903,43.736318],"type":"Point"}
}