{
  "type": "Feature",
  "properties": {
    "iso:country":"US",
    "sg:address":"802 Michigan Ave",
    "sg:city":"Sheboygan",
    "sg:classifiers":[
        {
            "category":"Professional",
            "subcategory":"Lawyer & Legal Services",
            "type":"Services"
        }
    ],
    "sg:phone":"+1 920 803 6529",
    "sg:postcode":"53081",
    "sg:province":"WI",
    "wof:name":"Stephen M Seymour Attorney",
    "wof:placetype":"venue"
},
  "geometry": {"coordinates":[-87.713873,43.758608],"type":"Point"}
}