{
  "type": "Feature",
  "properties": {
    "iso:country":"US",
    "sg:address":"7498 Old Sauk Rd",
    "sg:city":"Madison",
    "sg:classifiers":[
        {
            "category":"Real Estate",
            "subcategory":"Real Estate Agent",
            "type":"Services"
        }
    ],
    "sg:phone":"+1 608 836 0191",
    "sg:postcode":"53717",
    "sg:province":"WI",
    "wof:name":"Schoer Co LLC",
    "wof:placetype":"venue"
},
  "geometry": {"coordinates":[-89.510713,43.075195],"type":"Point"}
}