{
  "type": "Feature",
  "properties": {
    "addr:full":"6411 Demarco Trl Verona WI 53593",
    "addr:housenumber":"6411",
    "addr:postcode":"53593",
    "addr:street":"Demarco Trl",
    "iso:country":"US",
    "sg:address":"6411 Demarco Trl",
    "sg:city":"Verona",
    "sg:classifiers":[
        {
            "category":"Wholesale",
            "subcategory":"Sporting Goods",
            "type":"Manufacturing & Wholesale Goods"
        }
    ],
    "sg:phone":"+1 608 848 8781",
    "sg:postcode":"53593",
    "sg:province":"WI",
    "sg:tags":[
        "recreation"
    ],
    "wof:name":"Commercial Recreation Supply",
    "wof:placetype":"venue"
},
  "geometry": {"coordinates":[-89.490044,42.997273],"type":"Point"}
}