{
  "type": "Feature",
  "properties": {
    "addr:full":"1367 State Hwy 160 Pulaski WI 54162",
    "addr:housenumber":"1367",
    "addr:postcode":"54162",
    "addr:street":"State Hwy 160",
    "iso:country":"US",
    "sg:address":"1367 State Hwy 160",
    "sg:city":"Pulaski",
    "sg:classifiers":[
        {
            "category":"Farming",
            "subcategory":"Dairy Farm",
            "type":"Manufacturing & Wholesale Goods"
        }
    ],
    "sg:phone":"+1 920 822 5939",
    "sg:postcode":"54162",
    "sg:province":"WI",
    "wof:name":"Werner Cheryl A",
    "wof:placetype":"venue"
},
  "geometry": {"coordinates":[-88.307498,44.673674],"type":"Point"}
}