{
  "type": "Feature",
  "properties": {
    "iso:country":"US",
    "sg:address":"6728 Lp Lake Rd",
    "sg:city":"Crivitz",
    "sg:classifiers":[
        {
            "category":"Manufacturing",
            "subcategory":"Metals",
            "type":"Manufacturing & Wholesale Goods"
        },
        {
            "category":"Building & Trades",
            "subcategory":"Plumbing",
            "type":"Services"
        }
    ],
    "sg:phone":"+1 715 854 7376",
    "sg:postcode":"54114",
    "sg:province":"WI",
    "sg:tags":[
        "contractor",
        "work",
        "sheet",
        "metalwork",
        "mfg"
    ],
    "wof:name":"Denny's Sheet Metal",
    "wof:placetype":"venue"
},
  "geometry": {"coordinates":[-88.044939,45.203518],"type":"Point"}
}