{
  "type": "Feature",
  "properties": {
    "iso:country":"US",
    "sg:address":"1122 N Sunnyslope Dr",
    "sg:city":"Racine",
    "sg:classifiers":[
        {
            "category":"Real Estate",
            "subcategory":"Real Estate Operator",
            "type":"Services"
        }
    ],
    "sg:phone":"+1 262 886 6011",
    "sg:postcode":"53406",
    "sg:province":"WI",
    "sg:tags":[
        "condominium"
    ],
    "wof:name":"Spring Creek Condominiums",
    "wof:placetype":"venue"
},
  "geometry": {"coordinates":[-87.86309199999999,42.734573],"type":"Point"}
}