{
  "type": "Feature",
  "properties": {
    "iso:country":"US",
    "sg:address":"2540 Dewey Ave",
    "sg:city":"Beloit",
    "sg:classifiers":[
        {
            "category":"Building & Trades",
            "subcategory":"Landscaping Services",
            "type":"Services"
        }
    ],
    "sg:phone":"+1 608 362 3337",
    "sg:postcode":"53511",
    "sg:province":"WI",
    "sg:tags":[
        "tree"
    ],
    "wof:name":"Baker Tree Service",
    "wof:placetype":"venue"
},
  "geometry": {"coordinates":[-89.022779,42.542564],"type":"Point"}
}