{
  "type": "Feature",
  "properties": {
    "addr:full":"110 2nd Ave N Park Falls WI 54552",
    "addr:housenumber":"110",
    "addr:postcode":"54552",
    "addr:street":"2Nd Ave N",
    "iso:country":"US",
    "sg:address":"110 2nd Ave N",
    "sg:city":"Park Falls",
    "sg:classifiers":[
        {
            "category":"Banks & Credit Unions",
            "subcategory":"Investment Brokerage",
            "type":"Services"
        }
    ],
    "sg:phone":"+1 715 762 3025",
    "sg:postcode":"54552",
    "sg:province":"WI",
    "sg:tags":[
        "advisory",
        "security"
    ],
    "wof:name":"Investment Centers Of America",
    "wof:placetype":"venue"
},
  "geometry": {"coordinates":[-90.44905300000001,45.935219],"type":"Point"}
}