{
  "type": "Feature",
  "properties": {
    "iso:country":"US",
    "sg:address":"1307 S Riverdale Dr",
    "sg:city":"Appleton",
    "sg:classifiers":[
        {
            "category":"Manufacturing",
            "subcategory":"Rubber & Plastics",
            "type":"Manufacturing & Wholesale Goods"
        }
    ],
    "sg:phone":"+1 920 954 8660",
    "sg:postcode":"54914",
    "sg:province":"WI",
    "sg:tags":[
        "product",
        "mfg"
    ],
    "wof:name":"Vangaurd Plastics Technol",
    "wof:placetype":"venue"
},
  "geometry": {"coordinates":[-88.43759799999999,44.249359],"type":"Point"}
}