{
  "type": "Feature",
  "properties": {
    "iso:country":"US",
    "sg:address":"102 W Linden St",
    "sg:city":"Abbotsford",
    "sg:classifiers":[
        {
            "category":"Wholesale",
            "subcategory":"Machinery & Supplies",
            "type":"Manufacturing & Wholesale Goods"
        }
    ],
    "sg:phone":"+1 715 223 6321",
    "sg:postcode":"54405",
    "sg:province":"WI",
    "sg:tags":[
        "equipment",
        "material",
        "handling"
    ],
    "sg:website":"www.creative-automation.com",
    "wof:name":"Creative Automation Inc",
    "wof:placetype":"venue"
},
  "geometry": {"coordinates":[-90.319434,44.942117],"type":"Point"}
}