{
  "type": "Feature",
  "properties": {
    "iso:country":"US",
    "sg:address":"2501 Camelot Blvd",
    "sg:city":"Sheboygan",
    "sg:classifiers":[
        {
            "category":"Restaurant",
            "type":"Food & Drink"
        }
    ],
    "sg:phone":"+1 920 208 3703",
    "sg:postcode":"53081",
    "sg:province":"WI",
    "sg:tags":[
        "eating"
    ],
    "wof:name":"Themars Cafe",
    "wof:placetype":"venue"
},
  "geometry": {"coordinates":[-87.737793,43.712971],"type":"Point"}
}