{
  "type": "Feature",
  "properties": {
    "addr:full":"334 W Lakeside St Madison WI 53715",
    "addr:housenumber":"334",
    "addr:postcode":"53715",
    "addr:street":"W Lakeside St",
    "iso:country":"US",
    "sg:address":"334 W Lakeside St",
    "sg:city":"Madison",
    "sg:classifiers":[
        {
            "category":"Food & Beverages",
            "subcategory":"Specialty",
            "type":"Retail Goods"
        }
    ],
    "sg:phone":"+1 608 251 6915",
    "sg:postcode":"53715",
    "sg:province":"WI",
    "sg:tags":[
        "herb"
    ],
    "wof:name":"Quintessence Inc",
    "wof:placetype":"venue"
},
  "geometry": {"coordinates":[-89.388784,43.056056],"type":"Point"}
}