{
  "type": "Feature",
  "properties": {
    "iso:country":"US",
    "sg:address":"2120 Chamberlain Ave",
    "sg:city":"Madison",
    "sg:classifiers":[
        {
            "category":"Professional",
            "subcategory":"Management & Consulting",
            "type":"Services"
        }
    ],
    "sg:phone":"+1 608 233 2810",
    "sg:postcode":"53726",
    "sg:province":"WI",
    "sg:tags":[
        "computer",
        "related"
    ],
    "wof:name":"Syntax Consulting Inc",
    "wof:placetype":"venue"
},
  "geometry": {"coordinates":[-89.421674,43.071235],"type":"Point"}
}