{
  "type": "Feature",
  "properties": {
    "iso:country":"US",
    "sg:address":"605 S Center Ave",
    "sg:city":"Jefferson",
    "sg:classifiers":[
        {
            "category":"Real Estate",
            "subcategory":"Real Estate Agent",
            "type":"Services"
        }
    ],
    "sg:phone":"+1 920 674 2028",
    "sg:postcode":"53549",
    "sg:province":"WI",
    "wof:name":"W & M Property Management LLP",
    "wof:placetype":"venue"
},
  "geometry": {"coordinates":[-88.806195,43.000503],"type":"Point"}
}