{
  "type": "Feature",
  "properties": {
    "iso:country":"US",
    "sg:address":"284 Park Dr",
    "sg:city":"New Auburn",
    "sg:classifiers":[
        {
            "category":"Real Estate",
            "subcategory":"Architect",
            "type":"Services"
        }
    ],
    "sg:phone":"+1 715 967 2504",
    "sg:postcode":"54757",
    "sg:province":"WI",
    "wof:name":"Paul Prince-Architectural Dtls",
    "wof:placetype":"venue"
},
  "geometry": {"coordinates":[-91.426726,45.29904],"type":"Point"}
}