{
  "type": "Feature",
  "properties": {
    "iso:country":"US",
    "sg:address":"1101 E Chestnut St",
    "sg:city":"Chilton",
    "sg:classifiers":[
        {
            "category":"Travel",
            "subcategory":"Hotels & Motels",
            "type":"Entertainment"
        }
    ],
    "sg:phone":"+1 920 849 3600",
    "sg:postcode":"53014",
    "sg:province":"WI",
    "sg:tags":[
        "operation"
    ],
    "wof:name":"Best Western Stanton Inn",
    "wof:placetype":"venue"
},
  "geometry": {"coordinates":[-88.153553,44.020562],"type":"Point"}
}