{
  "type": "Feature",
  "properties": {
    "iso:country":"US",
    "sg:address":"1883 State Rd 22",
    "sg:city":"Wautoma",
    "sg:classifiers":[
        {
            "category":"Retail",
            "subcategory":"Veterinary Services",
            "type":"Services"
        }
    ],
    "sg:phone":"+1 920 787 3991",
    "sg:postcode":"54982",
    "sg:province":"WI",
    "sg:tags":[
        "veterinarian"
    ],
    "wof:name":"Town & Country Veterinary Clnc",
    "wof:placetype":"venue"
},
  "geometry": {"coordinates":[-89.296616,44.044647],"type":"Point"}
}