{
  "type": "Feature",
  "properties": {
    "iso:country":"US",
    "sg:address":"2621 Elmira Ave",
    "sg:city":"Superior",
    "sg:classifiers":[
        {
            "category":"Retail",
            "subcategory":"Auto Repair",
            "type":"Services"
        }
    ],
    "sg:phone":"+1 715 392 7365",
    "sg:postcode":"54880",
    "sg:province":"WI",
    "sg:tags":[
        "general"
    ],
    "wof:name":"Moon Auto Service and Exhaust",
    "wof:placetype":"venue"
},
  "geometry": {"coordinates":[-92.114809,46.709069],"type":"Point"}
}