{
  "type": "Feature",
  "properties": {
    "iso:country":"US",
    "sg:address":"6215 State Hwy 33",
    "sg:city":"Pardeeville",
    "sg:classifiers":[
        {
            "category":"Professional",
            "type":"Services"
        }
    ],
    "sg:phone":"+1 608 429 4990",
    "sg:postcode":"53954",
    "sg:province":"WI",
    "wof:name":"High Calling",
    "wof:placetype":"venue"
},
  "geometry": {"coordinates":[-89.325476,43.570301],"type":"Point"}
}