{
  "type": "Feature",
  "properties": {
    "iso:country":"US",
    "sg:address":"1771 Co Rd P",
    "sg:city":"Merrill",
    "sg:classifiers":[
        {
            "category":"Shopping",
            "subcategory":"Hobbies, Toys, & Games",
            "type":"Retail Goods"
        }
    ],
    "sg:phone":"+1 715 536 4325",
    "sg:postcode":"54452",
    "sg:province":"WI",
    "sg:tags":[
        "used",
        "merchandise"
    ],
    "wof:name":"JSB Vending",
    "wof:placetype":"venue"
},
  "geometry": {"coordinates":[-89.51093,45.133984],"type":"Point"}
}