{
  "type": "Feature",
  "properties": {
    "iso:country":"US",
    "sg:address":"2747 Bartells Dr",
    "sg:city":"Beloit",
    "sg:classifiers":[
        {
            "category":"Communications",
            "type":"Services"
        }
    ],
    "sg:phone":"+1 608 365 5791",
    "sg:postcode":"53511",
    "sg:province":"WI",
    "wof:name":"Sight & Sound Commnctns Inc",
    "wof:placetype":"venue"
},
  "geometry": {"coordinates":[-89.02151000000001,42.548642],"type":"Point"}
}