{
  "type": "Feature",
  "properties": {
    "addr:full":"1033 N Breens Bay Rd Oconomowoc WI 53066",
    "addr:housenumber":"1033",
    "addr:postcode":"53066",
    "addr:street":"N Breens Bay Rd",
    "iso:country":"US",
    "sg:address":"1033 N Breens Bay Rd",
    "sg:city":"Oconomowoc",
    "sg:classifiers":[
        {
            "category":"Professional",
            "subcategory":"Business Services",
            "type":"Services"
        }
    ],
    "sg:phone":"+1 262 646 8401",
    "sg:postcode":"53066",
    "sg:province":"WI",
    "wof:name":"Foerster Inc",
    "wof:placetype":"venue"
},
  "geometry": {"coordinates":[-88.433455,43.044283],"type":"Point"}
}