{
  "type": "Feature",
  "properties": {
    "iso:country":"US",
    "sg:address":"14598 W Indies Rd",
    "sg:city":"Melrose",
    "sg:classifiers":[
        {
            "category":"Farming",
            "subcategory":"Dairy Farm",
            "type":"Manufacturing & Wholesale Goods"
        }
    ],
    "sg:phone":"+1 608 488 7794",
    "sg:postcode":"54642",
    "sg:province":"WI",
    "wof:name":"Garbers Farm",
    "wof:placetype":"venue"
},
  "geometry": {"coordinates":[-91.041,44.129072],"type":"Point"}
}