{
  "type": "Feature",
  "properties": {
    "iso:country":"US",
    "sg:address":"1433 W Main St",
    "sg:city":"Sun Prairie",
    "sg:classifiers":[
        {
            "category":"Recreation",
            "type":"Entertainment"
        }
    ],
    "sg:phone":"+1 608 834 9992",
    "sg:postcode":"53590",
    "sg:province":"WI",
    "sg:tags":[
        "martial",
        "arts",
        "instruction"
    ],
    "wof:name":"Kicks Unlimited LLC",
    "wof:placetype":"venue"
},
  "geometry": {"coordinates":[-89.237206,43.178891],"type":"Point"}
}