{
  "type": "Feature",
  "properties": {
    "iso:country":"US",
    "sg:address":"104 S 6th St",
    "sg:city":"Watertown",
    "sg:classifiers":[
        {
            "category":"Personal",
            "subcategory":"Barber",
            "type":"Services"
        }
    ],
    "sg:phone":"+1 920 261 7868",
    "sg:postcode":"53094",
    "sg:province":"WI",
    "sg:tags":[
        "shop",
        "beauty"
    ],
    "wof:name":"Genesis Hair Designs",
    "wof:placetype":"venue"
},
  "geometry": {"coordinates":[-88.71936100000001,43.193718],"type":"Point"}
}