{
  "type": "Feature",
  "properties": {
    "iso:country":"US",
    "sg:address":"8306 Schuster Rd",
    "sg:city":"Berlin",
    "sg:classifiers":[
        {
            "category":"Professional",
            "subcategory":"Management & Consulting",
            "type":"Services"
        }
    ],
    "sg:phone":"+1 920 685 2123",
    "sg:postcode":"54923",
    "sg:province":"WI",
    "sg:tags":[
        "consultant",
        "business"
    ],
    "wof:name":"Strongtree Consulting",
    "wof:placetype":"venue"
},
  "geometry": {"coordinates":[-88.824512,43.97873],"type":"Point"}
}