{
  "type": "Feature",
  "properties": {
    "iso:country":"US",
    "sg:address":"1421 Lake St",
    "sg:city":"Algoma",
    "sg:classifiers":[
        {
            "category":"Health Services",
            "subcategory":"Chiropractor",
            "type":"Services"
        }
    ],
    "sg:phone":"+1 920 487 3832",
    "sg:postcode":"54201",
    "sg:province":"WI",
    "wof:name":"Kenny Chiropractic Office",
    "wof:placetype":"venue"
},
  "geometry": {"coordinates":[-87.440274,44.600474],"type":"Point"}
}