{
  "type": "Feature",
  "properties": {
    "iso:country":"US",
    "sg:address":"10417 State Hwy 49",
    "sg:city":"Rosholt",
    "sg:classifiers":[
        {
            "category":"Freight",
            "type":"Transportation"
        }
    ],
    "sg:phone":"+1 715 677 6977",
    "sg:postcode":"54473",
    "sg:province":"WI",
    "sg:tags":[
        "trucking"
    ],
    "wof:name":"LJS Express",
    "wof:placetype":"venue"
},
  "geometry": {"coordinates":[-89.262919,44.627558],"type":"Point"}
}