{
  "type": "Feature",
  "properties": {
    "iso:country":"US",
    "sg:address":"514 Division St",
    "sg:city":"Madison",
    "sg:classifiers":[
        {
            "category":"Manufacturing",
            "subcategory":"Food",
            "type":"Manufacturing & Wholesale Goods"
        }
    ],
    "sg:phone":"+1 608 249 6411",
    "sg:postcode":"53704",
    "sg:province":"WI",
    "sg:tags":[
        "frozen",
        "dessert",
        "ice",
        "cream"
    ],
    "wof:name":"Schoep's Ice Cream Co",
    "wof:placetype":"venue"
},
  "geometry": {"coordinates":[-89.35113,43.090344],"type":"Point"}
}