{
  "type": "Feature",
  "properties": {
    "iso:country":"US",
    "sg:address":"1611 3rd Ave",
    "sg:city":"Cumberland",
    "sg:classifiers":[
        {
            "category":"Freight",
            "type":"Transportation"
        }
    ],
    "sg:phone":"+1 715 822 5382",
    "sg:postcode":"54829",
    "sg:province":"WI",
    "sg:tags":[
        "operator",
        "local",
        "trucking"
    ],
    "wof:name":"Jns Trucking",
    "wof:placetype":"venue"
},
  "geometry": {"coordinates":[-92.022839,45.537433],"type":"Point"}
}