{
  "type": "Feature",
  "properties": {
    "iso:country":"US",
    "sg:address":"27 E Racine St",
    "sg:city":"Janesville",
    "sg:classifiers":[
        {
            "category":"Professional",
            "subcategory":"Management & Consulting",
            "type":"Services"
        },
        {
            "category":"Insurance",
            "subcategory":"Insurance Agent",
            "type":"Services"
        }
    ],
    "sg:phone":"+1 608 758 2222",
    "sg:postcode":"53545",
    "sg:province":"WI",
    "wof:name":"Associates For Mature American",
    "wof:placetype":"venue"
},
  "geometry": {"coordinates":[-89.01643900000001,42.677168],"type":"Point"}
}