{
  "type": "Feature",
  "properties": {
    "iso:country":"US",
    "sg:address":"5920 Dale Ln",
    "sg:city":"Greendale",
    "sg:classifiers":[
        {
            "category":"Building & Trades",
            "subcategory":"Construction",
            "type":"Services"
        }
    ],
    "sg:phone":"+1 414 423 7991",
    "sg:postcode":"53129",
    "sg:province":"WI",
    "sg:tags":[
        "hanging",
        "contractor"
    ],
    "wof:name":"Kraftwerk Painting & Carpentry",
    "wof:placetype":"venue"
},
  "geometry": {"coordinates":[-87.996599,42.937901],"type":"Point"}
}