{
  "type": "Feature",
  "properties": {
    "iso:country":"US",
    "sg:address":"5145 N 124th St",
    "sg:city":"Butler",
    "sg:classifiers":[
        {
            "category":"Building & Trades",
            "subcategory":"Construction",
            "type":"Services"
        }
    ],
    "sg:phone":"+1 262 252 3470",
    "sg:postcode":"53007",
    "sg:province":"WI",
    "sg:tags":[
        "heavy",
        "engineering"
    ],
    "wof:name":"Foundation Solutions Inc",
    "wof:placetype":"venue"
},
  "geometry": {"coordinates":[-88.066163,43.110106],"type":"Point"}
}