{
  "type": "Feature",
  "properties": {
    "iso:country":"US",
    "sg:address":"6334 Ravine Ct",
    "sg:city":"Menasha",
    "sg:classifiers":[
        {
            "category":"Building & Trades",
            "subcategory":"Electrical",
            "type":"Services"
        }
    ],
    "sg:phone":"+1 920 731 2803",
    "sg:postcode":"54952",
    "sg:province":"WI",
    "sg:tags":[
        "electrical",
        "contractor"
    ],
    "wof:name":"Peterson Contracting",
    "wof:placetype":"venue"
},
  "geometry": {"coordinates":[-88.355057,44.205269],"type":"Point"}
}