{
  "type": "Feature",
  "properties": {
    "iso:country":"US",
    "sg:address":"300 W Market St",
    "sg:city":"Burlington",
    "sg:classifiers":[
        {
            "category":"Autos & Motor Vehicles",
            "subcategory":"Auto Supplies",
            "type":"Retail Goods"
        }
    ],
    "sg:phone":"+1 262 763 6000",
    "sg:postcode":"53105",
    "sg:province":"WI",
    "sg:tags":[
        "equipment",
        "racing",
        "car",
        "automobile"
    ],
    "wof:name":"S & P Motor Sports",
    "wof:placetype":"venue"
},
  "geometry": {"coordinates":[-88.283022,42.667928],"type":"Point"}
}