{
  "type": "Feature",
  "properties": {
    "iso:country":"US",
    "sg:address":"1940 4th Ave",
    "sg:city":"Chetek",
    "sg:classifiers":[
        {
            "category":"Manufacturing",
            "subcategory":"Tools & Machinery",
            "type":"Manufacturing & Wholesale Goods"
        }
    ],
    "sg:phone":"+1 715 837 1853",
    "sg:postcode":"54728",
    "sg:province":"WI",
    "sg:tags":[
        "machine",
        "shop",
        "industrial",
        "mfg"
    ],
    "wof:name":"Hessler Precision Tooling Mch",
    "wof:placetype":"venue"
},
  "geometry": {"coordinates":[-91.75993699999999,45.266132],"type":"Point"}
}