{
  "type": "Feature",
  "properties": {
    "iso:country":"US",
    "sg:address":"444 N Main St",
    "sg:city":"West Bend",
    "sg:classifiers":[
        {
            "category":"Retail",
            "subcategory":"Auto Repair",
            "type":"Services"
        }
    ],
    "sg:phone":"+1 262 334 7241",
    "sg:postcode":"53090",
    "sg:province":"WI",
    "sg:tags":[
        "repairing",
        "automobile",
        "automotive"
    ],
    "wof:name":"Auto Safety Center",
    "wof:placetype":"venue"
},
  "geometry": {"coordinates":[-88.186104,43.429354],"type":"Point"}
}