{
  "type": "Feature",
  "properties": {
    "iso:country":"US",
    "sg:address":"5790 Crown Ct",
    "sg:city":"Baraboo",
    "sg:classifiers":[
        {
            "category":"Building & Trades",
            "subcategory":"Cleaning & Sanitation",
            "type":"Services"
        },
        {
            "category":"Professional",
            "subcategory":"Employment Agencies",
            "type":"Services"
        }
    ],
    "sg:phone":"+1 608 355 9149",
    "sg:postcode":"53913",
    "sg:province":"WI",
    "sg:tags":[
        "janitor",
        "help",
        "supply"
    ],
    "wof:name":"Becki's Quality Cleaning Svc",
    "wof:placetype":"venue"
},
  "geometry": {"coordinates":[-89.64277,43.434413],"type":"Point"}
}