{
  "type": "Feature",
  "properties": {
    "iso:country":"US",
    "sg:address":"641 Sorenson Rd",
    "sg:city":"Waupaca",
    "sg:classifiers":[
        {
            "category":"Farming",
            "subcategory":"Dairy Farm",
            "type":"Manufacturing & Wholesale Goods"
        }
    ],
    "sg:phone":"+1 715 258 3988",
    "sg:postcode":"54981",
    "sg:province":"WI",
    "wof:name":"Richardson Art",
    "wof:placetype":"venue"
},
  "geometry": {"coordinates":[-89.054756,44.263732],"type":"Point"}
}