{
  "type": "Feature",
  "properties": {
    "iso:country":"US",
    "sg:address":"1333 N 22nd St",
    "sg:city":"Milwaukee",
    "sg:classifiers":[
        {
            "category":"Freight",
            "type":"Transportation"
        }
    ],
    "sg:phone":"+1 414 344 1073",
    "sg:postcode":"53205",
    "sg:province":"WI",
    "wof:name":"Sams Moving Company",
    "wof:placetype":"venue"
},
  "geometry": {"coordinates":[-87.940334,43.047988],"type":"Point"}
}