{
  "type": "Feature",
  "properties": {
    "iso:country":"US",
    "sg:address":"2520 W Dean Rd",
    "sg:city":"Milwaukee",
    "sg:classifiers":[
        {
            "category":"Professional",
            "subcategory":"Management & Consulting",
            "type":"Services"
        }
    ],
    "sg:phone":"+1 414 351 5388",
    "sg:postcode":"53217",
    "sg:province":"WI",
    "sg:tags":[
        "international",
        "consultant"
    ],
    "wof:name":"Marringa International Co Inc",
    "wof:placetype":"venue"
},
  "geometry": {"coordinates":[-87.942967,43.173069],"type":"Point"}
}