{
  "type": "Feature",
  "properties": {
    "iso:country":"US",
    "sg:address":"1016 16th Ave",
    "sg:city":"Monroe",
    "sg:classifiers":[
        {
            "category":"Government",
            "subcategory":"Court House",
            "type":"Public Place"
        }
    ],
    "sg:phone":"+1 608 328 9420",
    "sg:postcode":"53566",
    "sg:province":"WI",
    "sg:tags":[
        "county"
    ],
    "wof:name":"Green County Circuit Judge",
    "wof:placetype":"venue"
},
  "geometry": {"coordinates":[-89.639814,42.601962],"type":"Point"}
}