{
  "type": "Feature",
  "properties": {
    "iso:country":"US",
    "sg:address":"541 Kenosha St",
    "sg:city":"Walworth",
    "sg:classifiers":[
        {
            "category":"Shopping",
            "subcategory":"Jewelry",
            "type":"Retail Goods"
        }
    ],
    "sg:phone":"+1 262 275 5520",
    "sg:postcode":"53184",
    "sg:province":"WI",
    "sg:tags":[
        "jeweler"
    ],
    "wof:name":"Ulmer Jewelers",
    "wof:placetype":"venue"
},
  "geometry": {"coordinates":[-88.591193,42.531054],"type":"Point"}
}