{
  "type": "Feature",
  "properties": {
    "iso:country":"US",
    "sg:address":"1790 Superior St",
    "sg:city":"Three Lakes",
    "sg:classifiers":[
        {
            "category":"Shopping",
            "subcategory":"Pharmacy",
            "type":"Retail Goods"
        }
    ],
    "sg:phone":"+1 715 546 3266",
    "sg:postcode":"54562",
    "sg:province":"WI",
    "wof:name":"Three Lakes Pharmacy",
    "wof:placetype":"venue"
},
  "geometry": {"coordinates":[-89.16973,45.797914],"type":"Point"}
}