{
  "type": "Feature",
  "properties": {
    "addr:full":"1008 Randolph Dr Appleton WI 54913",
    "addr:housenumber":"1008",
    "addr:postcode":"54913",
    "addr:street":"Randolph Dr",
    "iso:country":"US",
    "sg:address":"1008 Randolph Dr",
    "sg:city":"Appleton",
    "sg:classifiers":[
        {
            "category":"Manufacturing",
            "subcategory":"Motor Vehicles & Parts",
            "type":"Manufacturing & Wholesale Goods"
        }
    ],
    "sg:phone":"+1 920 788 5749",
    "sg:postcode":"54913",
    "sg:province":"WI",
    "sg:tags":[
        "automobile",
        "car"
    ],
    "sg:website":"www.randercar.com",
    "wof:name":"Randercar Racing Enterprises",
    "wof:placetype":"venue"
},
  "geometry": {"coordinates":[-88.311589,44.299319],"type":"Point"}
}