{
  "type": "Feature",
  "properties": {
    "iso:country":"US",
    "sg:address":"2110 295th Ave",
    "sg:city":"Luck",
    "sg:classifiers":[
        {
            "category":"Organizations",
            "subcategory":"Religious Organization",
            "type":"Services"
        }
    ],
    "sg:phone":"+1 715 648 5387",
    "sg:postcode":"54853",
    "sg:province":"WI",
    "wof:name":"Atlas United Methodist Church",
    "wof:placetype":"venue"
},
  "geometry": {"coordinates":[-92.592182,45.635428],"type":"Point"}
}