{
  "type": "Feature",
  "properties": {
    "iso:country":"US",
    "sg:address":"1911 Taylor Ave",
    "sg:city":"Racine",
    "sg:classifiers":[
        {
            "category":"Shopping",
            "subcategory":"Clothing, Apparel, & Fashions",
            "type":"Retail Goods"
        }
    ],
    "sg:phone":"+1 262 634 4532",
    "sg:postcode":"53403",
    "sg:province":"WI",
    "sg:tags":[
        "sport",
        "printed",
        "custom"
    ],
    "wof:name":"Speed Textile Printing",
    "wof:placetype":"venue"
},
  "geometry": {"coordinates":[-87.809175,42.706533],"type":"Point"}
}