{
  "type": "Feature",
  "properties": {
    "iso:country":"US",
    "sg:address":"1509 Blue Mounds St",
    "sg:city":"Black Earth",
    "sg:classifiers":[
        {
            "category":"Social Services",
            "subcategory":"Child Care",
            "type":"Services"
        }
    ],
    "sg:phone":"+1 608 767 3601",
    "sg:postcode":"53515",
    "sg:province":"WI",
    "sg:tags":[
        "day"
    ],
    "wof:name":"Kidds Korner",
    "wof:placetype":"venue"
},
  "geometry": {"coordinates":[-89.74916399999999,43.135248],"type":"Point"}
}