{
  "type": "Feature",
  "properties": {
    "iso:country":"US",
    "sg:address":"1355 Gohres St",
    "sg:city":"La Crosse",
    "sg:classifiers":[
        {
            "category":"Shopping",
            "subcategory":"Used Merchandise",
            "type":"Retail Goods"
        }
    ],
    "sg:phone":"+1 608 782 2588",
    "sg:postcode":"54603",
    "sg:province":"WI",
    "sg:tags":[
        "book",
        "rare",
        "dealer"
    ],
    "wof:name":"Book Exchange",
    "wof:placetype":"venue"
},
  "geometry": {"coordinates":[-91.237573,43.849296],"type":"Point"}
}