{
  "type": "Feature",
  "properties": {
    "iso:country":"US",
    "sg:address":"230 N Milwaukee St",
    "sg:city":"Waterford",
    "sg:classifiers":[
        {
            "category":"Recreation",
            "subcategory":"Marina",
            "type":"Entertainment"
        }
    ],
    "sg:phone":"+1 262 534 5530",
    "sg:postcode":"53185",
    "sg:province":"WI",
    "wof:name":"River City Marina & Pets",
    "wof:placetype":"venue"
},
  "geometry": {"coordinates":[-88.209393,42.765848],"type":"Point"}
}