{
  "type": "Feature",
  "properties": {
    "iso:country":"US",
    "sg:address":"4069 Fox Hill Rd",
    "sg:city":"Baraboo",
    "sg:classifiers":[
        {
            "category":"Building & Trades",
            "subcategory":"Landscaping Services",
            "type":"Services"
        }
    ],
    "sg:phone":"+1 608 356 2415",
    "sg:postcode":"53913",
    "sg:province":"WI",
    "sg:tags":[
        "excavation",
        "contractor"
    ],
    "wof:name":"Fox Hill Enterprises",
    "wof:placetype":"venue"
},
  "geometry": {"coordinates":[-89.763735,43.497292],"type":"Point"}
}