{
  "type": "Feature",
  "properties": {
    "iso:country":"US",
    "sg:address":"1220 Rolling Hills Trl",
    "sg:city":"Hudson",
    "sg:classifiers":[
        {
            "category":"Building & Trades",
            "subcategory":"Construction",
            "type":"Services"
        }
    ],
    "sg:phone":"+1 715 549 6705",
    "sg:postcode":"54016",
    "sg:province":"WI",
    "sg:tags":[
        "house"
    ],
    "wof:name":"Blaiser Pools",
    "wof:placetype":"venue"
},
  "geometry": {"coordinates":[-92.70872,45.038847],"type":"Point"}
}