{
  "type": "Feature",
  "properties": {
    "iso:country":"US",
    "sg:address":"29 E Wilson St",
    "sg:city":"Madison",
    "sg:classifiers":[
        {
            "category":"Recreation",
            "type":"Entertainment"
        }
    ],
    "sg:phone":"+1 608 287 0339",
    "sg:postcode":"53703",
    "sg:province":"WI",
    "sg:tags":[
        "historical"
    ],
    "wof:name":"Frank Lloyd Wright Wisconsin",
    "wof:placetype":"venue"
},
  "geometry": {"coordinates":[-89.380371,43.073062],"type":"Point"}
}