{
  "type": "Feature",
  "properties": {
    "iso:country":"US",
    "sg:address":"544 Broadway St S",
    "sg:city":"Menomonie",
    "sg:classifiers":[
        {
            "category":"Insurance",
            "subcategory":"Insurance Agent",
            "type":"Services"
        }
    ],
    "sg:phone":"+1 715 235 7575",
    "sg:postcode":"54751",
    "sg:province":"WI",
    "sg:tags":[
        "consulting",
        "management"
    ],
    "wof:name":"Larry D Feiler & Associates",
    "wof:placetype":"venue"
},
  "geometry": {"coordinates":[-91.929658,44.877697],"type":"Point"}
}