{
  "type": "Feature",
  "properties": {
    "iso:country":"US",
    "sg:address":"202 S Thornton Ave",
    "sg:city":"Madison",
    "sg:classifiers":[
        {
            "category":"Building & Trades",
            "subcategory":"Cleaning & Sanitation",
            "type":"Services"
        }
    ],
    "sg:phone":"+1 608 251 1594",
    "sg:postcode":"53703",
    "sg:province":"WI",
    "sg:tags":[
        "janitor"
    ],
    "wof:name":"Clean Power Inc",
    "wof:placetype":"venue"
},
  "geometry": {"coordinates":[-89.359098,43.0881],"type":"Point"}
}