{
  "type": "Feature",
  "properties": {
    "iso:country":"US",
    "sg:address":"5040 Co Rd K",
    "sg:city":"South Range",
    "sg:classifiers":[
        {
            "category":"Home & Garden",
            "subcategory":"Building Materials",
            "type":"Retail Goods"
        }
    ],
    "sg:phone":"+1 715 399 2421",
    "sg:postcode":"54874",
    "sg:province":"WI",
    "sg:tags":[
        "center"
    ],
    "wof:name":"Range Builders Supply Inc",
    "wof:placetype":"venue"
},
  "geometry": {"coordinates":[-91.983599,46.57723],"type":"Point"}
}