{
  "type": "Feature",
  "properties": {
    "iso:country":"US",
    "sg:address":"3620 Pine Knoll Dr",
    "sg:city":"Baraboo",
    "sg:classifiers":[
        {
            "category":"Professional",
            "subcategory":"Management & Consulting",
            "type":"Services"
        }
    ],
    "sg:phone":"+1 608 356 5915",
    "sg:postcode":"53913",
    "sg:province":"WI",
    "wof:name":"Timothy P Stone Co",
    "wof:placetype":"venue"
},
  "geometry": {"coordinates":[-89.722438,43.51338],"type":"Point"}
}