{
  "type": "Feature",
  "properties": {
    "iso:country":"US",
    "sg:address":"74 Halbach Ct",
    "sg:city":"Fond Du Lac",
    "sg:classifiers":[
        {
            "category":"Manufacturing",
            "subcategory":"Chemicals & Compounds",
            "type":"Manufacturing & Wholesale Goods"
        }
    ],
    "sg:phone":"+1 920 922 1978",
    "sg:postcode":"54937",
    "sg:province":"WI",
    "sg:tags":[
        "mfg",
        "product",
        "trade",
        "exhibition",
        "show"
    ],
    "wof:name":"Versamount U S A",
    "wof:placetype":"venue"
},
  "geometry": {"coordinates":[-88.472809,43.753064],"type":"Point"}
}