{
  "type": "Feature",
  "properties": {
    "iso:country":"US",
    "sg:address":"1254 State Hwy 49",
    "sg:city":"Wittenberg",
    "sg:classifiers":[
        {
            "category":"Building & Trades",
            "subcategory":"Plumbing",
            "type":"Services"
        }
    ],
    "sg:phone":"+1 715 454 6827",
    "sg:postcode":"54499",
    "sg:province":"WI",
    "sg:tags":[
        "heating",
        "contractor"
    ],
    "wof:name":"A Groshek Electric & Heating",
    "wof:placetype":"venue"
},
  "geometry": {"coordinates":[-89.243998,44.724817],"type":"Point"}
}