{
  "type": "Feature",
  "properties": {
    "iso:country":"US",
    "sg:address":"707 3rd St",
    "sg:city":"Rothschild",
    "sg:classifiers":[
        {
            "category":"Organizations",
            "subcategory":"Religious Organization",
            "type":"Services"
        }
    ],
    "sg:phone":"+1 715 359 3919",
    "sg:postcode":"54474",
    "sg:province":"WI",
    "sg:tags":[
        "church"
    ],
    "wof:name":"Highland United Methodist Chr",
    "wof:placetype":"venue"
},
  "geometry": {"coordinates":[-89.615555,44.889286],"type":"Point"}
}