{
  "type": "Feature",
  "properties": {
    "iso:country":"US",
    "sg:address":"8017 State Hwy 101",
    "sg:city":"Armstrong Creek",
    "sg:classifiers":[
        {
            "category":"Autos & Motor Vehicles",
            "subcategory":"Fuel & Gas Station",
            "type":"Retail Goods"
        }
    ],
    "sg:phone":"+1 715 336 2424",
    "sg:postcode":"54103",
    "sg:province":"WI",
    "sg:tags":[
        "oil"
    ],
    "wof:name":"Gudowicz's Marathon & Store",
    "wof:placetype":"venue"
},
  "geometry": {"coordinates":[-88.446541,45.661351],"type":"Point"}
}