{
  "type": "Feature",
  "properties": {
    "addr:full":"245 S Century Ave Waunakee WI 53597",
    "addr:housenumber":"245",
    "addr:postcode":"53597",
    "addr:street":"S Century Ave",
    "iso:country":"US",
    "sg:address":"245 S Century Ave",
    "sg:city":"Waunakee",
    "sg:classifiers":[
        {
            "category":"Utilities",
            "subcategory":"Mobile Phone",
            "type":"Services"
        },
        {
            "category":"Wholesale",
            "subcategory":"Durable Goods & Equipment",
            "type":"Manufacturing & Wholesale Goods"
        }
    ],
    "sg:phone":"+1 608 850 4555",
    "sg:postcode":"53597",
    "sg:province":"WI",
    "sg:tags":[
        "electronic",
        "telephone",
        "cellular"
    ],
    "wof:name":"Quality Cellular",
    "wof:placetype":"venue"
},
  "geometry": {"coordinates":[-89.461691,43.190315],"type":"Point"}
}