{
  "type": "Feature",
  "properties": {
    "iso:country":"US",
    "sg:address":"16 Summit Ave",
    "sg:city":"Chippewa Falls",
    "sg:classifiers":[
        {
            "category":"Professional",
            "type":"Services"
        }
    ],
    "sg:phone":"+1 715 723 8662",
    "sg:postcode":"54729",
    "sg:province":"WI",
    "sg:tags":[
        "establishment"
    ],
    "wof:name":"Frenette & Frenette",
    "wof:placetype":"venue"
},
  "geometry": {"coordinates":[-91.388604,44.924235],"type":"Point"}
}