{
  "type": "Feature",
  "properties": {
    "iso:country":"US",
    "sg:address":"3548 Co Rd V",
    "sg:city":"De Forest",
    "sg:classifiers":[
        {
            "category":"Farming",
            "subcategory":"Dairy Farm",
            "type":"Manufacturing & Wholesale Goods"
        }
    ],
    "sg:phone":"+1 608 846 2620",
    "sg:postcode":"53532",
    "sg:province":"WI",
    "wof:name":"Cahpel View Dairy",
    "wof:placetype":"venue"
},
  "geometry": {"coordinates":[-89.271023,43.267621],"type":"Point"}
}