{
  "type": "Feature",
  "properties": {
    "iso:country":"US",
    "sg:address":"622 Highland Ave",
    "sg:city":"Kewaskum",
    "sg:classifiers":[
        {
            "category":"Retail",
            "subcategory":"Repair Shop",
            "type":"Services"
        }
    ],
    "sg:phone":"+1 262 626 4483",
    "sg:postcode":"53040",
    "sg:province":"WI",
    "sg:tags":[
        "repairing",
        "piano",
        "refinishing"
    ],
    "wof:name":"De Poms Piano Svc",
    "wof:placetype":"venue"
},
  "geometry": {"coordinates":[-88.219612,43.520018],"type":"Point"}
}