{
  "type": "Feature",
  "properties": {
    "iso:country":"US",
    "sg:address":"1210 Winged Foot Dr",
    "sg:city":"Twin Lakes",
    "sg:classifiers":[
        {
            "category":"Shopping",
            "type":"Retail Goods"
        }
    ],
    "sg:phone":"+1 262 877 8353",
    "sg:postcode":"53181",
    "sg:province":"WI",
    "sg:tags":[
        "merchandise"
    ],
    "wof:name":"Crystal Lake Petland",
    "wof:placetype":"venue"
},
  "geometry": {"coordinates":[-88.22973,42.527378],"type":"Point"}
}