{
  "type": "Feature",
  "properties": {
    "iso:country":"US",
    "sg:address":"2494 US Hwy 14",
    "sg:city":"Richland Center",
    "sg:classifiers":[
        {
            "category":"Utilities",
            "subcategory":"Cable",
            "type":"Services"
        }
    ],
    "sg:phone":"+1 608 647 6383",
    "sg:postcode":"53581",
    "sg:province":"WI",
    "sg:tags":[
        "television"
    ],
    "wof:name":"Dairyland Cable Systems Inc",
    "wof:placetype":"venue"
},
  "geometry": {"coordinates":[-90.360563,43.318211],"type":"Point"}
}