{
  "type": "Feature",
  "properties": {
    "iso:country":"US",
    "sg:address":"1120 Oakes Rd",
    "sg:city":"Racine",
    "sg:classifiers":[
        {
            "category":"Personal",
            "subcategory":"Barber",
            "type":"Services"
        }
    ],
    "sg:phone":"+1 262 886 5327",
    "sg:postcode":"53406",
    "sg:province":"WI",
    "wof:name":"Garys Barber",
    "wof:placetype":"venue"
},
  "geometry": {"coordinates":[-87.87044,42.720852],"type":"Point"}
}