{
  "type": "Feature",
  "properties": {
    "iso:country":"US",
    "sg:address":"234 Marguerite Ct",
    "sg:city":"Mayville",
    "sg:classifiers":[
        {
            "category":"Building & Trades",
            "subcategory":"Construction",
            "type":"Services"
        }
    ],
    "sg:phone":"+1 920 296 4310",
    "sg:postcode":"53050",
    "sg:province":"WI",
    "sg:tags":[
        "home",
        "improvement"
    ],
    "wof:name":"R R Construction",
    "wof:placetype":"venue"
},
  "geometry": {"coordinates":[-88.538681,43.499678],"type":"Point"}
}