{
  "type": "Feature",
  "properties": {
    "iso:country":"US",
    "sg:address":"8254 Bachelors Ave",
    "sg:city":"Willard",
    "sg:classifiers":[
        {
            "category":"Farming",
            "subcategory":"Farm",
            "type":"Manufacturing & Wholesale Goods"
        }
    ],
    "sg:phone":"+1 715 267 6472",
    "sg:postcode":"54493",
    "sg:province":"WI",
    "sg:tags":[
        "feedlot",
        "cattle",
        "crop",
        "beef",
        "general"
    ],
    "wof:name":"William Arch",
    "wof:placetype":"venue"
},
  "geometry": {"coordinates":[-90.740339,44.713043],"type":"Point"}
}