{
  "type": "Feature",
  "properties": {
    "addr:full":"8935 S 27th St Franklin WI 53132",
    "addr:housenumber":"8935",
    "addr:postcode":"53132",
    "addr:street":"S 27Th St",
    "iso:country":"US",
    "sg:address":"8935 S 27th St",
    "sg:city":"Franklin",
    "sg:classifiers":[
        {
            "category":"Personal",
            "type":"Services"
        }
    ],
    "sg:phone":"+1 414 698 6086",
    "sg:postcode":"53132",
    "sg:province":"WI",
    "sg:tags":[
        "cosmetic"
    ],
    "wof:name":"Perfect Brows Of Wisconsin",
    "wof:placetype":"venue"
},
  "geometry": {"coordinates":[-87.95107899999999,42.882631],"type":"Point"}
}