{
  "type": "Feature",
  "properties": {
    "addr:full":"3300 Commercial Ave Madison WI 53714",
    "addr:housenumber":"3300",
    "addr:postcode":"53714",
    "addr:street":"Commercial Ave",
    "iso:country":"US",
    "sg:address":"3300 Commercial Ave",
    "sg:city":"Madison",
    "sg:classifiers":[
        {
            "category":"Wholesale",
            "subcategory":"Sporting Goods",
            "type":"Manufacturing & Wholesale Goods"
        }
    ],
    "sg:phone":"+1 608 244 4758",
    "sg:postcode":"53714",
    "sg:province":"WI",
    "sg:tags":[
        "boat"
    ],
    "wof:name":"Lunenschloss Marine & Sptg Gds",
    "wof:placetype":"venue"
},
  "geometry": {"coordinates":[-89.330595,43.106983],"type":"Point"}
}