{
  "type": "Feature",
  "properties": {
    "iso:country":"US",
    "sg:address":"1402 Greenway Cross",
    "sg:city":"Madison",
    "sg:classifiers":[
        {
            "category":"Professional",
            "subcategory":"Art Services",
            "type":"Services"
        },
        {
            "category":"Professional",
            "subcategory":"Advertising",
            "type":"Services"
        }
    ],
    "sg:phone":"+1 608 268 5525",
    "sg:postcode":"53713",
    "sg:province":"WI",
    "sg:tags":[
        "commercial",
        "counselor",
        "design"
    ],
    "wof:name":"Tingalls Dzyn LLC",
    "wof:placetype":"venue"
},
  "geometry": {"coordinates":[-89.407741,43.03146],"type":"Point"}
}