{
  "type": "Feature",
  "properties": {
    "addr:full":"202 Park St Friendship WI 53934",
    "addr:housenumber":"202",
    "addr:postcode":"53934",
    "addr:street":"Park St",
    "iso:country":"US",
    "sg:address":"202 Park St",
    "sg:city":"Friendship",
    "sg:classifiers":[
        {
            "category":"Retail",
            "subcategory":"Laundry & Dry Cleaning",
            "type":"Services"
        }
    ],
    "sg:phone":"+1 608 339 4413",
    "sg:postcode":"53934",
    "sg:province":"WI",
    "wof:name":"Adams-Friendship Laundromat",
    "wof:placetype":"venue"
},
  "geometry": {"coordinates":[-89.827519,43.974133],"type":"Point"}
}