{
  "type": "Feature",
  "properties": {
    "iso:country":"US",
    "sg:address":"4146 Gust Rd",
    "sg:city":"Stratford",
    "sg:classifiers":[
        {
            "category":"Freight",
            "type":"Transportation"
        }
    ],
    "sg:phone":"+1 715 687 8520",
    "sg:postcode":"54484",
    "sg:province":"WI",
    "sg:tags":[
        "hauling",
        "trucking"
    ],
    "wof:name":"W-D's TRANSPORT LLC",
    "wof:placetype":"venue"
},
  "geometry": {"coordinates":[-90.024529,44.80324],"type":"Point"}
}