{
  "type": "Feature",
  "properties": {
    "iso:country":"US",
    "sg:address":"628 Wolff St",
    "sg:city":"Racine",
    "sg:classifiers":[
        {
            "category":"Professional",
            "subcategory":"Computer Services",
            "type":"Services"
        }
    ],
    "sg:phone":"+1 262 681 1724",
    "sg:postcode":"53402",
    "sg:province":"WI",
    "sg:tags":[
        "website",
        "design"
    ],
    "wof:name":"Curtin Com L L C",
    "wof:placetype":"venue"
},
  "geometry": {"coordinates":[-87.78933000000001,42.753074],"type":"Point"}
}