{
  "type": "Feature",
  "properties": {
    "iso:country":"US",
    "sg:address":"3702 Gateway Dr",
    "sg:city":"Eau Claire",
    "sg:classifiers":[
        {
            "category":"Food & Beverages",
            "subcategory":"Groceries & Convenience Stores",
            "type":"Retail Goods"
        }
    ],
    "sg:phone":"+1 715 833 0711",
    "sg:postcode":"54701",
    "sg:province":"WI",
    "wof:name":"Handy Mart",
    "wof:placetype":"venue"
},
  "geometry": {"coordinates":[-91.431668,44.778396],"type":"Point"}
}