{
  "type": "Feature",
  "properties": {
    "iso:country":"US",
    "sg:address":"811 Main Ave",
    "sg:city":"De Pere",
    "sg:classifiers":[
        {
            "category":"Shopping",
            "subcategory":"Department Store",
            "type":"Retail Goods"
        }
    ],
    "sg:phone":"+1 920 339 8082",
    "sg:postcode":"54115",
    "sg:province":"WI",
    "sg:tags":[
        "shop"
    ],
    "sg:website":"www.biglots.com",
    "wof:name":"Big Lots",
    "wof:placetype":"venue"
},
  "geometry": {"coordinates":[-88.083304,44.450295],"type":"Point"}
}