{
  "type": "Feature",
  "properties": {
    "addr:full":"1701 S 11th St Prairie Du Chien WI 53821",
    "addr:housenumber":"1701",
    "addr:postcode":"53821",
    "addr:street":"S 11Th St",
    "iso:country":"US",
    "sg:address":"1701 S 11th St",
    "sg:city":"Prairie Du Chien",
    "sg:classifiers":[
        {
            "category":"Retail",
            "subcategory":"Auto Repair",
            "type":"Services"
        }
    ],
    "sg:phone":"+1 608 326 6421",
    "sg:postcode":"53821",
    "sg:province":"WI",
    "sg:tags":[
        "body",
        "automobile",
        "painting"
    ],
    "sg:website":"www.southwestmotors.com",
    "wof:name":"Southwest Collision Ctr",
    "wof:placetype":"venue"
},
  "geometry": {"coordinates":[-91.134258,43.031372],"type":"Point"}
}