{
  "type": "Feature",
  "properties": {
    "iso:country":"US",
    "sg:address":"103 26th Ave",
    "sg:city":"Cumberland",
    "sg:classifiers":[
        {
            "category":"Bars & Pubs",
            "type":"Food & Drink"
        }
    ],
    "sg:phone":"+1 715 822 3512",
    "sg:postcode":"54829",
    "sg:province":"WI",
    "sg:tags":[
        "drinking"
    ],
    "wof:name":"County Line",
    "wof:placetype":"venue"
},
  "geometry": {"coordinates":[-92.133456,45.582299],"type":"Point"}
}