{
  "type": "Feature",
  "properties": {
    "iso:country":"US",
    "sg:address":"24714 Adams St",
    "sg:city":"Kansasville",
    "sg:classifiers":[
        {
            "category":"Professional",
            "type":"Services"
        }
    ],
    "sg:phone":"+1 262 878 2955",
    "sg:postcode":"53139",
    "sg:province":"WI",
    "wof:name":"Kenneth E Degroot",
    "wof:placetype":"venue"
},
  "geometry": {"coordinates":[-88.133171,42.695876],"type":"Point"}
}