{
  "type": "Feature",
  "properties": {
    "addr:full":"6454 Hunters Hollow Rd Fennimore WI 53809",
    "addr:housenumber":"6454",
    "addr:postcode":"53809",
    "addr:street":"Hunters Hollow Rd",
    "iso:country":"US",
    "sg:address":"6454 Hunters Hollow Rd",
    "sg:city":"Fennimore",
    "sg:phone":"+1 608 822 3569",
    "sg:postcode":"53809",
    "sg:province":"WI",
    "sg:tags":[
        "farm",
        "field",
        "corn",
        "crop"
    ],
    "wof:name":"Claire Adkins",
    "wof:placetype":"venue"
},
  "geometry": {"coordinates":[-90.73746199999999,42.995632],"type":"Point"}
}