{
  "type": "Feature",
  "properties": {
    "iso:country":"US",
    "sg:address":"6404 N 76th St",
    "sg:city":"Milwaukee",
    "sg:classifiers":[
        {
            "category":"Utilities",
            "subcategory":"Mobile Phone",
            "type":"Services"
        }
    ],
    "sg:phone":"+1 414 358 1890",
    "sg:postcode":"53223",
    "sg:province":"WI",
    "sg:tags":[
        "telephone",
        "cellular"
    ],
    "wof:name":"Service World Plus Inc",
    "wof:placetype":"venue"
},
  "geometry": {"coordinates":[-88.005663,43.135723],"type":"Point"}
}