{
  "type": "Feature",
  "properties": {
    "iso:country":"US",
    "sg:address":"3737 W River Ln",
    "sg:city":"Milwaukee",
    "sg:classifiers":[
        {
            "category":"Retail",
            "subcategory":"Car Wash",
            "type":"Services"
        }
    ],
    "sg:phone":"+1 414 354 7888",
    "sg:postcode":"53209",
    "sg:province":"WI",
    "sg:tags":[
        "carwash"
    ],
    "wof:name":"Roses Wash & Clean",
    "wof:placetype":"venue"
},
  "geometry": {"coordinates":[-87.960172,43.1776],"type":"Point"}
}