{
  "type": "Feature",
  "properties": {
    "iso:country":"US",
    "sg:address":"2054 Adams Rd",
    "sg:city":"Neosho",
    "sg:classifiers":[
        {
            "category":"Professional",
            "type":"Services"
        }
    ],
    "sg:phone":"+1 920 625 3307",
    "sg:postcode":"53059",
    "sg:province":"WI",
    "wof:name":"Performance Motor Sports",
    "wof:placetype":"venue"
},
  "geometry": {"coordinates":[-88.496128,43.28273],"type":"Point"}
}