{
  "type": "Feature",
  "properties": {
    "iso:country":"US",
    "sg:address":"1605 Autumn Dr",
    "sg:city":"Racine",
    "sg:classifiers":[
        {
            "category":"Wholesale",
            "subcategory":"Durable Goods & Equipment",
            "type":"Manufacturing & Wholesale Goods"
        }
    ],
    "sg:phone":"+1 262 752 1296",
    "sg:postcode":"53402",
    "sg:province":"WI",
    "wof:name":"McF International Sales Inc",
    "wof:placetype":"venue"
},
  "geometry": {"coordinates":[-87.801177,42.794557],"type":"Point"}
}