{
  "type": "Feature",
  "properties": {
    "addr:full":"209 E National Ave Milwaukee WI 53204",
    "addr:housenumber":"209",
    "addr:postcode":"53204",
    "addr:street":"E National Ave",
    "iso:country":"US",
    "sg:address":"209 E National Ave",
    "sg:city":"Milwaukee",
    "sg:classifiers":[
        {
            "category":"Bars & Pubs",
            "type":"Food & Drink"
        }
    ],
    "sg:phone":"+1 414 643 6900",
    "sg:postcode":"53204",
    "sg:province":"WI",
    "sg:tags":[
        "drinking"
    ],
    "wof:name":"Boot Camp Saloon",
    "wof:placetype":"venue"
},
  "geometry": {"coordinates":[-87.90940000000001,43.023127],"type":"Point"}
}