{
  "type": "Feature",
  "properties": {
    "iso:country":"US",
    "sg:address":"202 Racine St",
    "sg:city":"Waterford",
    "sg:classifiers":[
        {
            "category":"Travel",
            "subcategory":"Hotels & Motels",
            "type":"Entertainment"
        }
    ],
    "sg:phone":"+1 262 534 5049",
    "sg:postcode":"53185",
    "sg:province":"WI",
    "sg:tags":[
        "breakfast",
        "accommodation",
        "bed",
        "lodging"
    ],
    "wof:name":"River View Inn Bed & Breakfast",
    "wof:placetype":"venue"
},
  "geometry": {"coordinates":[-88.213745,42.764181],"type":"Point"}
}