{
  "type": "Feature",
  "properties": {
    "iso:country":"US",
    "sg:address":"1330 31st Ave",
    "sg:city":"Monroe",
    "sg:classifiers":[
        {
            "category":"Food & Beverages",
            "subcategory":"Meat & Fish",
            "type":"Retail Goods"
        }
    ],
    "sg:phone":"+1 608 325 3969",
    "sg:postcode":"53566",
    "sg:province":"WI",
    "sg:tags":[
        "frozen"
    ],
    "wof:name":"Schwan's Sales Enterprises",
    "wof:placetype":"venue"
},
  "geometry": {"coordinates":[-89.622084,42.598726],"type":"Point"}
}