{
  "type": "Feature",
  "properties": {
    "addr:full":"344 E Main St Twin Lakes WI 53181",
    "addr:housenumber":"344",
    "addr:postcode":"53181",
    "addr:street":"E Main St",
    "iso:country":"US",
    "sg:address":"344 E Main St",
    "sg:city":"Twin Lakes",
    "sg:classifiers":[
        {
            "category":"Shopping",
            "subcategory":"Bicycles & Sporting Goods",
            "type":"Retail Goods"
        }
    ],
    "sg:phone":"+1 262 877 3324",
    "sg:postcode":"53181",
    "sg:province":"WI",
    "sg:tags":[
        "bait",
        "fishing"
    ],
    "wof:name":"Twin Lakes Bait Shops",
    "wof:placetype":"venue"
},
  "geometry": {"coordinates":[-88.249094,42.532208],"type":"Point"}
}