{
  "type": "Feature",
  "properties": {
    "addr:full":"929 20th Ave Bloomer WI 54724",
    "addr:housenumber":"929",
    "addr:postcode":"54724",
    "addr:street":"20Th Ave",
    "iso:country":"US",
    "sg:address":"929 20th Ave",
    "sg:city":"Bloomer",
    "sg:classifiers":[
        {
            "category":"Freight",
            "type":"Transportation"
        }
    ],
    "sg:phone":"+1 715 568 1974",
    "sg:postcode":"54724",
    "sg:province":"WI",
    "sg:tags":[
        "company",
        "trucking"
    ],
    "wof:name":"Harms Way",
    "wof:placetype":"venue"
},
  "geometry": {"coordinates":[-91.485883,45.09623],"type":"Point"}
}