{
  "type": "Feature",
  "properties": {
    "iso:country":"US",
    "sg:address":"508 Country Walk Ln",
    "sg:city":"Sister Bay",
    "sg:classifiers":[
        {
            "category":"Professional",
            "subcategory":"Lawyer & Legal Services",
            "type":"Services"
        }
    ],
    "sg:phone":"+1 920 854 7400",
    "sg:postcode":"54234",
    "sg:province":"WI",
    "sg:tags":[
        "attorney"
    ],
    "wof:name":"Evan M Kjellenberg Law Office",
    "wof:placetype":"venue"
},
  "geometry": {"coordinates":[-87.127361,45.184841],"type":"Point"}
}