{
  "type": "Feature",
  "properties": {
    "iso:country":"US",
    "sg:address":"4951 State Hwy 117",
    "sg:city":"Bonduel",
    "sg:classifiers":[
        {
            "category":"Farming",
            "subcategory":"Dairy Farm",
            "type":"Manufacturing & Wholesale Goods"
        }
    ],
    "sg:phone":"+1 715 745 2478",
    "sg:postcode":"54107",
    "sg:province":"WI",
    "wof:name":"Keith Ebert",
    "wof:placetype":"venue"
},
  "geometry": {"coordinates":[-88.447463,44.766426],"type":"Point"}
}