{
  "type": "Feature",
  "properties": {
    "iso:country":"US",
    "sg:address":"10237 Shanks Rd",
    "sg:city":"Portage",
    "sg:classifiers":[
        {
            "category":"Farming",
            "subcategory":"Farm",
            "type":"Manufacturing & Wholesale Goods"
        }
    ],
    "sg:phone":"+1 608 742 3077",
    "sg:postcode":"53901",
    "sg:province":"WI",
    "sg:tags":[
        "crop",
        "general"
    ],
    "wof:name":"R & P Farms",
    "wof:placetype":"venue"
},
  "geometry": {"coordinates":[-89.50480899999999,43.45723],"type":"Point"}
}