{
  "type": "Feature",
  "properties": {
    "iso:country":"US",
    "sg:address":"3641 Soda Creek Rd",
    "sg:city":"Marathon",
    "sg:classifiers":[
        {
            "category":"Retail",
            "subcategory":"Repair Shop",
            "type":"Services"
        }
    ],
    "sg:phone":"+1 715 443 2868",
    "sg:postcode":"54448",
    "sg:province":"WI",
    "sg:tags":[
        "electrical"
    ],
    "wof:name":"Jl Machine Repair",
    "wof:placetype":"venue"
},
  "geometry": {"coordinates":[-89.878373,44.916153],"type":"Point"}
}