{
  "type": "Feature",
  "properties": {
    "addr:full":"120 W Mifflin St Madison WI 53703",
    "addr:housenumber":"120",
    "addr:postcode":"53703",
    "addr:street":"W Mifflin St",
    "iso:country":"US",
    "sg:address":"120 W Mifflin St",
    "sg:city":"Madison",
    "sg:classifiers":[
        {
            "category":"Shopping",
            "subcategory":"Stationery & Office Supplies",
            "type":"Retail Goods"
        }
    ],
    "sg:phone":"+1 608 256 5444",
    "sg:postcode":"53703",
    "sg:province":"WI",
    "sg:tags":[
        "supp"
    ],
    "wof:name":"Badger Office Supplies Inc",
    "wof:placetype":"venue"
},
  "geometry": {"coordinates":[-89.387308,43.07421],"type":"Point"}
}