{
  "type": "Feature",
  "properties": {
    "iso:country":"US",
    "sg:address":"3800 W Vliet St",
    "sg:city":"Milwaukee",
    "sg:classifiers":[
        {
            "category":"Social Services",
            "subcategory":"Child Care",
            "type":"Services"
        }
    ],
    "sg:phone":"+1 414 342 0964",
    "sg:postcode":"53208",
    "sg:province":"WI",
    "wof:name":"Charlotte's Web Crawlers",
    "wof:placetype":"venue"
},
  "geometry": {"coordinates":[-87.961113,43.048754],"type":"Point"}
}