{
  "type": "Feature",
  "properties": {
    "addr:full":"7636 N Teutonia Ave Milwaukee WI 53209",
    "addr:housenumber":"7636",
    "addr:postcode":"53209",
    "addr:street":"N Teutonia Ave",
    "iso:country":"US",
    "sg:address":"7636 N Teutonia Ave",
    "sg:city":"Milwaukee",
    "sg:classifiers":[
        {
            "category":"Autos & Motor Vehicles",
            "subcategory":"Auto Supplies",
            "type":"Retail Goods"
        },
        {
            "category":"Retail",
            "subcategory":"Auto Repair",
            "type":"Services"
        }
    ],
    "sg:phone":"+1 414 228 8470",
    "sg:postcode":"53209",
    "sg:province":"WI",
    "sg:tags":[
        "repairing",
        "automobile",
        "automotive"
    ],
    "wof:name":"Tom Butler Sales & Service",
    "wof:placetype":"venue"
},
  "geometry": {"coordinates":[-87.961512,43.161289],"type":"Point"}
}