{
  "type": "Feature",
  "properties": {
    "iso:country":"US",
    "sg:address":"8531 W Lincoln Ave",
    "sg:city":"Milwaukee",
    "sg:classifiers":[
        {
            "category":"Health Services",
            "subcategory":"Doctor",
            "type":"Services"
        }
    ],
    "sg:phone":"+1 414 327 2700",
    "sg:postcode":"53227",
    "sg:province":"WI",
    "sg:tags":[
        "dentist"
    ],
    "wof:name":"Todd R Krueger DDS",
    "wof:placetype":"venue"
},
  "geometry": {"coordinates":[-88.01949500000001,43.002654],"type":"Point"}
}