{
  "type": "Feature",
  "properties": {
    "iso:country":"US",
    "sg:address":"5325 Wall St",
    "sg:city":"Madison",
    "sg:classifiers":[
        {
            "category":"Banks & Credit Unions",
            "subcategory":"Bank",
            "type":"Services"
        }
    ],
    "sg:phone":"+1 608 301 0947",
    "sg:postcode":"53718",
    "sg:province":"WI",
    "sg:tags":[
        "short",
        "business",
        "loan",
        "real estate",
        "institution"
    ],
    "wof:name":"Prestige Funding LLC",
    "wof:placetype":"venue"
},
  "geometry": {"coordinates":[-89.288309,43.132578],"type":"Point"}
}