{
  "type": "Feature",
  "properties": {
    "addr:full":"523 9th St Green Bay WI 54304",
    "addr:housenumber":"523",
    "addr:postcode":"54304",
    "addr:street":"9Th St",
    "iso:country":"US",
    "sg:address":"523 9th St",
    "sg:city":"Green Bay",
    "sg:classifiers":[
        {
            "category":"Manufacturing",
            "subcategory":"Retail Goods",
            "type":"Manufacturing & Wholesale Goods"
        }
    ],
    "sg:phone":"+1 920 435 8485",
    "sg:postcode":"54304",
    "sg:province":"WI",
    "sg:tags":[
        "rubber",
        "stamp"
    ],
    "wof:name":"Rubber Stamp Mfg Co",
    "wof:placetype":"venue"
},
  "geometry": {"coordinates":[-88.033159,44.503317],"type":"Point"}
}