{
  "type": "Feature",
  "properties": {
    "iso:country":"US",
    "sg:address":"1109 Boomer St",
    "sg:city":"Watertown",
    "sg:classifiers":[
        {
            "category":"Building & Trades",
            "subcategory":"Plumbing",
            "type":"Services"
        }
    ],
    "sg:phone":"+1 920 261 1347",
    "sg:postcode":"53094",
    "sg:province":"WI",
    "sg:tags":[
        "specializing",
        "system",
        "air",
        "heating",
        "conditioning",
        "v",
        "contractor"
    ],
    "wof:name":"F W Zastrow Heating",
    "wof:placetype":"venue"
},
  "geometry": {"coordinates":[-88.715488,43.173959],"type":"Point"}
}