{
  "type": "Feature",
  "properties": {
    "iso:country":"US",
    "sg:address":"2846 Draper Rd",
    "sg:city":"Dorchester",
    "sg:classifiers":[
        {
            "category":"Farming",
            "subcategory":"Dairy Farm",
            "type":"Manufacturing & Wholesale Goods"
        }
    ],
    "sg:phone":"+1 715 654 5399",
    "sg:postcode":"54425",
    "sg:province":"WI",
    "wof:name":"Bartnik Farm",
    "wof:placetype":"venue"
},
  "geometry": {"coordinates":[-90.232314,45.017751],"type":"Point"}
}