{
  "type": "Feature",
  "properties": {
    "iso:country":"US",
    "sg:address":"5105 Caton Ln",
    "sg:city":"Waunakee",
    "sg:classifiers":[
        {
            "category":"Professional",
            "subcategory":"Business Services",
            "type":"Services"
        }
    ],
    "sg:phone":"+1 608 241 3437",
    "sg:postcode":"53597",
    "sg:province":"WI",
    "wof:name":"Blue Lotus Floatation Ctr LLC",
    "wof:placetype":"venue"
},
  "geometry": {"coordinates":[-89.389115,43.158545],"type":"Point"}
}