{
  "type": "Feature",
  "properties": {
    "iso:country":"US",
    "sg:address":"6069 Wipperfurth Rd",
    "sg:city":"Waunakee",
    "sg:classifiers":[
        {
            "category":"Banks & Credit Unions",
            "subcategory":"Investment Brokerage",
            "type":"Services"
        }
    ],
    "sg:phone":"+1 608 849 4589",
    "sg:postcode":"53597",
    "sg:province":"WI",
    "sg:tags":[
        "security"
    ],
    "wof:name":"Epping Financial Services",
    "wof:placetype":"venue"
},
  "geometry": {"coordinates":[-89.501516,43.202744],"type":"Point"}
}