{
  "type": "Feature",
  "properties": {
    "addr:full":"8520 University Green Middleton WI 53562",
    "addr:housenumber":"8520",
    "addr:postcode":"53562",
    "addr:street":"University Green",
    "iso:country":"US",
    "sg:address":"8520 University Green",
    "sg:city":"Middleton",
    "sg:classifiers":[
        {
            "category":"Professional",
            "subcategory":"Research",
            "type":"Services"
        }
    ],
    "sg:phone":"+1 608 836 7300",
    "sg:postcode":"53562",
    "sg:province":"WI",
    "sg:tags":[
        "development",
        "plant",
        "related"
    ],
    "sg:website":"www.monsanto.com",
    "wof:name":"Monsanto Co",
    "wof:placetype":"venue"
},
  "geometry": {"coordinates":[-89.53443799999999,43.097505],"type":"Point"}
}