{
  "type": "Feature",
  "properties": {
    "addr:full":"4755 W Beloit Rd Milwaukee WI 53214",
    "addr:housenumber":"4755",
    "addr:postcode":"53214",
    "addr:street":"W Beloit Rd",
    "iso:country":"US",
    "sg:address":"4755 W Beloit Rd",
    "sg:city":"Milwaukee",
    "sg:classifiers":[
        {
            "category":"Government",
            "subcategory":"City Hall",
            "type":"Public Place"
        },
        {
            "category":"Government",
            "subcategory":"Office",
            "type":"Public Place"
        }
    ],
    "sg:phone":"+1 414 645 5411",
    "sg:postcode":"53214",
    "sg:province":"WI",
    "sg:tags":[
        "town",
        "township",
        "planner",
        "government-city",
        "village"
    ],
    "wof:name":"Village Of West Milwaukee",
    "wof:placetype":"venue"
},
  "geometry": {"coordinates":[-87.97326700000001,43.017742],"type":"Point"}
}