{
  "type": "Feature",
  "properties": {
    "iso:country":"US",
    "sg:address":"141 S 12th Ave",
    "sg:city":"Sturgeon Bay",
    "sg:classifiers":[
        {
            "category":"Organizations",
            "subcategory":"Religious Organization",
            "type":"Services"
        }
    ],
    "sg:phone":"+1 920 743 2701",
    "sg:postcode":"54235",
    "sg:province":"WI",
    "wof:name":"Hope United Church Of Christ",
    "wof:placetype":"venue"
},
  "geometry": {"coordinates":[-87.36432000000001,44.834738],"type":"Point"}
}