{
  "type": "Feature",
  "properties": {
    "iso:country":"US",
    "sg:address":"1292 Capitol Dr",
    "sg:city":"Pewaukee",
    "sg:classifiers":[
        {
            "category":"Health Services",
            "subcategory":"Doctor",
            "type":"Services"
        }
    ],
    "sg:phone":"+1 414 443 6050",
    "sg:postcode":"53072",
    "sg:province":"WI",
    "sg:tags":[
        "physician",
        "surgeon"
    ],
    "wof:name":"Donald Beaver DO",
    "wof:placetype":"venue"
},
  "geometry": {"coordinates":[-88.23054999999999,43.08325],"type":"Point"}
}