{
  "type": "Feature",
  "properties": {
    "iso:country":"US",
    "sg:address":"4146 State Hwy 28",
    "sg:city":"Sheboygan Falls",
    "sg:classifiers":[
        {
            "category":"Freight",
            "type":"Transportation"
        }
    ],
    "sg:phone":"+1 920 467 0407",
    "sg:postcode":"53085",
    "sg:province":"WI",
    "sg:tags":[
        "operator",
        "local",
        "trucking"
    ],
    "wof:name":"Larry Suemnicht Trucking",
    "wof:placetype":"venue"
},
  "geometry": {"coordinates":[-87.91228,43.68935],"type":"Point"}
}