{
  "type": "Feature",
  "properties": {
    "iso:country":"US",
    "sg:address":"9950 Durand Ave",
    "sg:city":"Sturtevant",
    "sg:classifiers":[
        {
            "category":"Manufacturing",
            "subcategory":"Tools & Machinery",
            "type":"Manufacturing & Wholesale Goods"
        }
    ],
    "sg:phone":"+1 262 886 4402",
    "sg:postcode":"53177",
    "sg:province":"WI",
    "sg:tags":[
        "dry",
        "equipment",
        "filling",
        "mfg"
    ],
    "sg:website":"www.spee-dee.com",
    "wof:name":"Spee-Dee Packaging Machinery",
    "wof:placetype":"venue"
},
  "geometry": {"coordinates":[-87.914117,42.698344],"type":"Point"}
}