{
  "type": "Feature",
  "properties": {
    "iso:country":"US",
    "sg:address":"10096 Kings Rd",
    "sg:city":"Tomahawk",
    "sg:classifiers":[
        {
            "category":"Manufacturing",
            "subcategory":"Food",
            "type":"Manufacturing & Wholesale Goods"
        }
    ],
    "sg:phone":"+1 715 453 3800",
    "sg:postcode":"54487",
    "sg:province":"WI",
    "sg:tags":[
        "malt",
        "beverage",
        "brewer",
        "mfg"
    ],
    "wof:name":"Logjam Micro Brewery",
    "wof:placetype":"venue"
},
  "geometry": {"coordinates":[-89.685826,45.484008],"type":"Point"}
}