{
  "type": "Feature",
  "properties": {
    "addr:full":"4922 Columbia Rd Cedarburg WI 53012",
    "addr:housenumber":"4922",
    "addr:postcode":"53012",
    "addr:street":"Columbia Rd",
    "iso:country":"US",
    "sg:address":"4922 Columbia Rd",
    "sg:city":"Cedarburg",
    "sg:classifiers":[
        {
            "category":"Health Services",
            "subcategory":"Doctor",
            "type":"Services"
        }
    ],
    "sg:phone":"+1 262 377 4077",
    "sg:postcode":"53012",
    "sg:province":"WI",
    "sg:tags":[
        "medicine",
        "sport"
    ],
    "sg:website":"www.worc.net",
    "wof:name":"Homestead Physical Therapy",
    "wof:placetype":"venue"
},
  "geometry": {"coordinates":[-87.971603,43.301899],"type":"Point"}
}