{
  "type": "Feature",
  "properties": {
    "addr:full":"7945 N 76th St Milwaukee WI 53223",
    "addr:housenumber":"7945",
    "addr:postcode":"53223",
    "addr:street":"N 76Th St",
    "iso:country":"US",
    "sg:address":"7945 N 76th St",
    "sg:city":"Milwaukee",
    "sg:classifiers":[
        {
            "category":"Social Services",
            "type":"Services"
        }
    ],
    "sg:phone":"+1 414 586 9377",
    "sg:postcode":"53223",
    "sg:province":"WI",
    "sg:tags":[
        "counseling"
    ],
    "wof:name":"Current Initiative Counseling",
    "wof:placetype":"venue"
},
  "geometry": {"coordinates":[-88.004761,43.162796],"type":"Point"}
}