{
  "type": "Feature",
  "properties": {
    "iso:country":"US",
    "sg:address":"904 S Pierce Ave",
    "sg:city":"Appleton",
    "sg:classifiers":[
        {
            "category":"Professional",
            "type":"Services"
        }
    ],
    "sg:phone":"+1 920 991 0182",
    "sg:postcode":"54914",
    "sg:province":"WI",
    "wof:name":"Benefit Circle Foundation",
    "wof:placetype":"venue"
},
  "geometry": {"coordinates":[-88.41928299999999,44.253981],"type":"Point"}
}