{
  "type": "Feature",
  "properties": {
    "iso:country":"US",
    "sg:address":"757 Center Creek Rd",
    "sg:city":"Nelson",
    "sg:classifiers":[
        {
            "category":"Home & Garden",
            "subcategory":"Furniture",
            "type":"Retail Goods"
        }
    ],
    "sg:phone":"+1 715 673 4980",
    "sg:postcode":"54756",
    "sg:province":"WI",
    "wof:name":"Miller Custom Furnishings",
    "wof:placetype":"venue"
},
  "geometry": {"coordinates":[-91.953671,44.489252],"type":"Point"}
}