{
  "type": "Feature",
  "properties": {
    "addr:full":"302 N 57th St Wausau WI 54403",
    "addr:housenumber":"302",
    "addr:postcode":"54403",
    "addr:street":"N 57Th St",
    "iso:country":"US",
    "sg:address":"302 N 57th St",
    "sg:city":"Wausau",
    "sg:classifiers":[
        {
            "category":"Building & Trades",
            "subcategory":"Cleaning & Sanitation",
            "type":"Services"
        }
    ],
    "sg:phone":"+1 715 355 4739",
    "sg:postcode":"54403",
    "sg:province":"WI",
    "sg:tags":[
        "snow",
        "removal"
    ],
    "wof:name":"Osswald Lawncare & Maintenance",
    "wof:placetype":"venue"
},
  "geometry": {"coordinates":[-89.552967,44.956347],"type":"Point"}
}