{
  "type": "Feature",
  "properties": {
    "iso:country":"US",
    "sg:address":"1400 W Commercial St",
    "sg:city":"Appleton",
    "sg:classifiers":[
        {
            "category":"Building & Trades",
            "subcategory":"Construction",
            "type":"Services"
        }
    ],
    "sg:phone":"+1 920 731 8440",
    "sg:postcode":"54914",
    "sg:province":"WI",
    "sg:tags":[
        "tile",
        "dealer"
    ],
    "wof:name":"Grout Magic LLC",
    "wof:placetype":"venue"
},
  "geometry": {"coordinates":[-88.428168,44.270427],"type":"Point"}
}