{
  "type": "Feature",
  "properties": {
    "iso:country":"US",
    "sg:address":"525 E Division St",
    "sg:city":"Fond Du Lac",
    "sg:classifiers":[
        {
            "category":"Health Services",
            "subcategory":"Doctor",
            "type":"Services"
        }
    ],
    "sg:phone":"+1 920 923 6200",
    "sg:postcode":"54935",
    "sg:province":"WI",
    "sg:tags":[
        "medical"
    ],
    "wof:name":"K L Pennau MD",
    "wof:placetype":"venue"
},
  "geometry": {"coordinates":[-88.427718,43.778714],"type":"Point"}
}