{
  "type": "Feature",
  "properties": {
    "iso:country":"US",
    "sg:address":"2720 West 5 Mile Road",
    "sg:city":"Caledonia",
    "sg:classifiers":[
        {
            "category":"Shopping",
            "subcategory":"Party Supplies",
            "type":"Retail Goods"
        }
    ],
    "sg:phone":"+1 262 835 2227",
    "sg:postcode":"53108",
    "sg:province":"WI",
    "sg:website":"xfireworks.com/",
    "wof:name":"Xtreme Fireworks",
    "wof:placetype":"venue"
},
  "geometry": {"coordinates":[-87.954015,42.800531],"type":"Point"}
}