{
  "type": "Feature",
  "properties": {
    "addr:full":"3708 West Ln Cuba City WI 53807",
    "addr:housenumber":"3708",
    "addr:postcode":"53807",
    "addr:street":"West Ln",
    "iso:country":"US",
    "sg:address":"3708 West Ln",
    "sg:city":"Cuba City",
    "sg:classifiers":[
        {
            "category":"Farming",
            "subcategory":"Dairy Farm",
            "type":"Manufacturing & Wholesale Goods"
        }
    ],
    "sg:phone":"+1 608 568 7773",
    "sg:postcode":"53807",
    "sg:province":"WI",
    "wof:name":"Jerome Anthony",
    "wof:placetype":"venue"
},
  "geometry": {"coordinates":[-90.60502099999999,42.601935],"type":"Point"}
}