{
  "type": "Feature",
  "properties": {
    "addr:full":"200 US Hwy 14 Janesville WI 53545",
    "addr:housenumber":"200",
    "addr:postcode":"53545",
    "addr:street":"Us Hwy 14",
    "iso:country":"US",
    "sg:address":"200 US Hwy 14",
    "sg:city":"Janesville",
    "sg:classifiers":[
        {
            "category":"Manufacturing",
            "subcategory":"Toys & Sporting Goods",
            "type":"Manufacturing & Wholesale Goods"
        },
        {
            "category":"Government",
            "subcategory":"Police Station",
            "type":"Public Place"
        }
    ],
    "sg:phone":"+1 608 757 7945",
    "sg:postcode":"53545",
    "sg:province":"WI",
    "sg:tags":[
        "executive",
        "sheriff",
        "mfg"
    ],
    "wof:name":"Rock County Sheriff's Dept",
    "wof:placetype":"venue"
},
  "geometry": {"coordinates":[-89.03304300000001,42.730092],"type":"Point"}
}