{
  "type": "Feature",
  "properties": {
    "iso:country":"US",
    "sg:address":"345 W Liberty St",
    "sg:city":"Evansville",
    "sg:classifiers":[
        {
            "category":"Building & Trades",
            "subcategory":"Plumbing",
            "type":"Services"
        }
    ],
    "sg:phone":"+1 608 882 3918",
    "sg:postcode":"53536",
    "sg:province":"WI",
    "sg:tags":[
        "heating",
        "contractor"
    ],
    "wof:name":"Martin Don Heating & Cooling",
    "wof:placetype":"venue"
},
  "geometry": {"coordinates":[-89.307914,42.777704],"type":"Point"}
}