{
  "type": "Feature",
  "properties": {
    "iso:country":"US",
    "sg:address":"642 W 9th Ave",
    "sg:city":"Oshkosh",
    "sg:classifiers":[
        {
            "category":"Bars & Pubs",
            "type":"Food & Drink"
        }
    ],
    "sg:phone":"+1 920 235 3489",
    "sg:postcode":"54902",
    "sg:province":"WI",
    "wof:name":"RCR Split Level Bar",
    "wof:placetype":"venue"
},
  "geometry": {"coordinates":[-88.554937,44.010488],"type":"Point"}
}