{
  "type": "Feature",
  "properties": {
    "iso:country":"US",
    "sg:address":"212 9th St",
    "sg:city":"Cameron",
    "sg:classifiers":[
        {
            "category":"Autos & Motor Vehicles",
            "subcategory":"Auto Supplies",
            "type":"Retail Goods"
        }
    ],
    "sg:phone":"+1 715 458 4858",
    "sg:postcode":"54822",
    "sg:province":"WI",
    "sg:tags":[
        "repair",
        "general"
    ],
    "wof:name":"T JS Tire",
    "wof:placetype":"venue"
},
  "geometry": {"coordinates":[-91.74489699999999,45.407658],"type":"Point"}
}