{
  "type": "Feature",
  "properties": {
    "addr:full":"4135 Singing Hills Rd West Bend WI 53090",
    "addr:housenumber":"4135",
    "addr:postcode":"53090",
    "addr:street":"Singing Hills Rd",
    "iso:country":"US",
    "sg:address":"4135 Singing Hills Rd",
    "sg:city":"West Bend",
    "sg:classifiers":[
        {
            "category":"Freight",
            "type":"Transportation"
        }
    ],
    "sg:phone":"+1 262 675 2799",
    "sg:postcode":"53090",
    "sg:province":"WI",
    "sg:tags":[
        "operator",
        "local",
        "trucking"
    ],
    "wof:name":"Pw & Son Trucking",
    "wof:placetype":"venue"
},
  "geometry": {"coordinates":[-88.03091999999999,43.425186],"type":"Point"}
}