{
  "type": "Feature",
  "properties": {
    "iso:country":"US",
    "sg:address":"9823 Pioneer Rd",
    "sg:city":"Mequon",
    "sg:classifiers":[
        {
            "category":"Building & Trades",
            "subcategory":"Construction",
            "type":"Services"
        }
    ],
    "sg:phone":"+1 262 377 7993",
    "sg:postcode":"53012",
    "sg:province":"WI",
    "sg:tags":[
        "carpentry",
        "contractor"
    ],
    "wof:name":"Custom Cabinet Specialist",
    "wof:placetype":"venue"
},
  "geometry": {"coordinates":[-88.026822,43.278725],"type":"Point"}
}