{
  "type": "Feature",
  "properties": {
    "iso:country":"US",
    "sg:address":"411 Ridge St",
    "sg:city":"Stoughton",
    "sg:classifiers":[
        {
            "category":"Manufacturing",
            "subcategory":"Petroleum Products",
            "type":"Manufacturing & Wholesale Goods"
        }
    ],
    "sg:phone":"+1 608 873 7223",
    "sg:postcode":"53589",
    "sg:province":"WI",
    "sg:tags":[
        "lubricating",
        "oil",
        "grease"
    ],
    "sg:website":"www.ikimfg.com",
    "wof:name":"Stoughton Packaging Corp",
    "wof:placetype":"venue"
},
  "geometry": {"coordinates":[-89.2146,42.920255],"type":"Point"}
}