{
  "type": "Feature",
  "properties": {
    "addr:full":"420 Racine St Menasha WI 54952",
    "addr:housenumber":"420",
    "addr:postcode":"54952",
    "addr:street":"Racine St",
    "iso:country":"US",
    "sg:address":"420 Racine St",
    "sg:city":"Menasha",
    "sg:classifiers":[
        {
            "category":"Professional",
            "type":"Services"
        }
    ],
    "sg:phone":"+1 920 722 7744",
    "sg:postcode":"54952",
    "sg:province":"WI",
    "wof:name":"Dennis Barth",
    "wof:placetype":"venue"
},
  "geometry": {"coordinates":[-88.446147,44.207307],"type":"Point"}
}