{
  "type": "Feature",
  "properties": {
    "iso:country":"US",
    "sg:address":"17676 State Hwy 124",
    "sg:city":"Bloomer",
    "sg:classifiers":[
        {
            "category":"Autos & Motor Vehicles",
            "subcategory":"Automobile Sales",
            "type":"Retail Goods"
        }
    ],
    "sg:phone":"+1 715 288 6633",
    "sg:postcode":"54724",
    "sg:province":"WI",
    "sg:tags":[
        "used"
    ],
    "wof:name":"Eaglepoint Limo Servivice",
    "wof:placetype":"venue"
},
  "geometry": {"coordinates":[-91.388923,45.103875],"type":"Point"}
}