{
  "type": "Feature",
  "properties": {
    "iso:country":"US",
    "sg:address":"333 Bishops Way",
    "sg:city":"Brookfield",
    "sg:classifiers":[
        {
            "category":"Professional",
            "subcategory":"Business Services",
            "type":"Services"
        },
        {
            "category":"Professional",
            "subcategory":"Research",
            "type":"Services"
        }
    ],
    "sg:phone":"+1 262 789 5430",
    "sg:postcode":"53005",
    "sg:province":"WI",
    "sg:tags":[
        "development",
        "electronic"
    ],
    "wof:name":"Flextech Systems Inc",
    "wof:placetype":"venue"
},
  "geometry": {"coordinates":[-88.079422,43.033023],"type":"Point"}
}