{
  "type": "Feature",
  "properties": {
    "addr:full":"208 N 1st St Abbotsford WI 54405",
    "addr:housenumber":"208",
    "addr:postcode":"54405",
    "addr:street":"N 1St St",
    "iso:country":"US",
    "sg:address":"208 N 1st St",
    "sg:city":"Abbotsford",
    "sg:classifiers":[
        {
            "category":"Shopping",
            "subcategory":"Shoes",
            "type":"Retail Goods"
        }
    ],
    "sg:phone":"+1 715 223 4681",
    "sg:postcode":"54405",
    "sg:province":"WI",
    "wof:name":"Olson Shoes",
    "wof:placetype":"venue"
},
  "geometry": {"coordinates":[-90.319857,44.948639],"type":"Point"}
}