{
  "type": "Feature",
  "properties": {
    "iso:country":"US",
    "sg:address":"3092 Mill Rd",
    "sg:city":"Greenleaf",
    "sg:classifiers":[
        {
            "category":"Real Estate",
            "subcategory":"Real Estate Operator",
            "type":"Services"
        }
    ],
    "sg:phone":"+1 920 864 7438",
    "sg:postcode":"54126",
    "sg:province":"WI",
    "sg:tags":[
        "property",
        "lessor"
    ],
    "wof:name":"Theodore Lemke",
    "wof:placetype":"venue"
},
  "geometry": {"coordinates":[-88.000294,44.299102],"type":"Point"}
}