{
  "type": "Feature",
  "properties": {
    "iso:country":"US",
    "sg:address":"301 Alfred St",
    "sg:city":"Athens",
    "sg:classifiers":[
        {
            "category":"Restaurant",
            "type":"Food & Drink"
        }
    ],
    "sg:phone":"+1 715 257 7477",
    "sg:postcode":"54411",
    "sg:province":"WI",
    "wof:name":"Athens Country Cafe",
    "wof:placetype":"venue"
},
  "geometry": {"coordinates":[-90.073905,45.033108],"type":"Point"}
}