{
  "type": "Feature",
  "properties": {
    "addr:full":"5807 Aspen Ct Mc Farland WI 53558",
    "addr:housenumber":"5807",
    "addr:postcode":"53558",
    "addr:street":"Aspen Ct Mc Farland",
    "iso:country":"US",
    "sg:address":"5807 Aspen Ct",
    "sg:city":"Mc Farland",
    "sg:classifiers":[
        {
            "category":"Professional",
            "subcategory":"Computer Services",
            "type":"Services"
        }
    ],
    "sg:phone":"+1 608 873 6955",
    "sg:postcode":"53558",
    "sg:province":"WI",
    "sg:tags":[
        "repair"
    ],
    "wof:name":"Indigo Technology",
    "wof:placetype":"venue"
},
  "geometry": {"coordinates":[-89.280096,43.020172],"type":"Point"}
}