{
  "type": "Feature",
  "properties": {
    "iso:country":"US",
    "sg:address":"931 E Moreland Blvd",
    "sg:city":"Waukesha",
    "sg:classifiers":[
        {
            "category":"Shopping",
            "subcategory":"News",
            "type":"Retail Goods"
        }
    ],
    "sg:phone":"+1 262 547 9056",
    "sg:postcode":"53186",
    "sg:province":"WI",
    "wof:name":"Holts Variety Store",
    "wof:placetype":"venue"
},
  "geometry": {"coordinates":[-88.218015,43.02212],"type":"Point"}
}