{
  "type": "Feature",
  "properties": {
    "addr:full":"7829 N Evergreen Ave Hayward WI 54843",
    "addr:housenumber":"7829",
    "addr:postcode":"54843",
    "addr:street":"N Evergreen Ave",
    "iso:country":"US",
    "sg:address":"7829 N Evergreen Ave",
    "sg:city":"Hayward",
    "sg:classifiers":[
        {
            "category":"Government",
            "subcategory":"Fire Station",
            "type":"Public Place"
        }
    ],
    "sg:phone":"+1 715 634 2413",
    "sg:postcode":"54843",
    "sg:province":"WI",
    "sg:tags":[
        "department"
    ],
    "wof:name":"Bass Lake Fire Hall",
    "wof:placetype":"venue"
},
  "geometry": {"coordinates":[-91.411492,45.918294],"type":"Point"}
}