{
  "type": "Feature",
  "properties": {
    "iso:country":"US",
    "sg:address":"114 E Grand Ave",
    "sg:city":"Port Washington",
    "sg:classifiers":[
        {
            "category":"Personal",
            "subcategory":"Beauty Salon",
            "type":"Services"
        }
    ],
    "sg:phone":"+1 262 268 1192",
    "sg:postcode":"53074",
    "sg:province":"WI",
    "sg:tags":[
        "shop"
    ],
    "wof:name":"Lasting Impressions",
    "wof:placetype":"venue"
},
  "geometry": {"coordinates":[-87.869438,43.387668],"type":"Point"}
}