{
  "type": "Feature",
  "properties": {
    "addr:full":"321 S 4th St Stoughton WI 53589",
    "addr:housenumber":"321",
    "addr:postcode":"53589",
    "addr:street":"S 4Th St",
    "iso:country":"US",
    "sg:address":"321 S 4th St",
    "sg:city":"Stoughton",
    "sg:classifiers":[
        {
            "category":"Communications",
            "subcategory":"Film & Video Production",
            "type":"Services"
        }
    ],
    "sg:phone":"+1 608 873 7523",
    "sg:postcode":"53589",
    "sg:province":"WI",
    "sg:tags":[
        "motion"
    ],
    "wof:name":"Wsto Cable Access TV",
    "wof:placetype":"venue"
},
  "geometry": {"coordinates":[-89.217821,42.91655],"type":"Point"}
}