{
  "type": "Feature",
  "properties": {
    "iso:country":"US",
    "sg:address":"1110 S Marquette Rd",
    "sg:city":"Prairie Du Chien",
    "sg:classifiers":[
        {
            "category":"Organizations",
            "subcategory":"Religious Organization",
            "type":"Services"
        }
    ],
    "sg:phone":"+1 608 326 8559",
    "sg:postcode":"53821",
    "sg:province":"WI",
    "sg:tags":[
        "school"
    ],
    "wof:name":"Prairie Christian Academy",
    "wof:placetype":"venue"
},
  "geometry": {"coordinates":[-91.138887,43.037992],"type":"Point"}
}