{
  "type": "Feature",
  "properties": {
    "iso:country":"US",
    "sg:address":"1014 Wisconsin Ave",
    "sg:city":"Oostburg",
    "sg:classifiers":[
        {
            "category":"Retail",
            "subcategory":"Auto Repair",
            "type":"Services"
        }
    ],
    "sg:phone":"+1 920 564 4134",
    "sg:postcode":"53070",
    "sg:province":"WI",
    "sg:tags":[
        "general"
    ],
    "wof:name":"B P Mobile Service LLC",
    "wof:placetype":"venue"
},
  "geometry": {"coordinates":[-87.799385,43.62675],"type":"Point"}
}