{
  "type": "Feature",
  "properties": {
    "iso:country":"US",
    "sg:address":"5839 Sugar Creek Rd",
    "sg:city":"Elkhorn",
    "sg:classifiers":[
        {
            "category":"Retail",
            "subcategory":"Repair Shop",
            "type":"Services"
        }
    ],
    "sg:phone":"+1 262 723 4718",
    "sg:postcode":"53121",
    "sg:province":"WI",
    "sg:tags":[
        "welding"
    ],
    "wof:name":"RC Portable Wldg & Fabrication",
    "wof:placetype":"venue"
},
  "geometry": {"coordinates":[-88.587715,42.698559],"type":"Point"}
}