{
  "type": "Feature",
  "properties": {
    "iso:country":"US",
    "sg:address":"935 W Cecil St",
    "sg:city":"Neenah",
    "sg:classifiers":[
        {
            "category":"Shopping",
            "subcategory":"Florist",
            "type":"Retail Goods"
        }
    ],
    "sg:phone":"+1 920 727 9100",
    "sg:postcode":"54956",
    "sg:province":"WI",
    "wof:name":"Flower Case",
    "wof:placetype":"venue"
},
  "geometry": {"coordinates":[-88.485908,44.170959],"type":"Point"}
}