{
  "type": "Feature",
  "properties": {
    "iso:country":"US",
    "sg:address":"2871 University Ave",
    "sg:city":"Madison",
    "sg:classifiers":[
        {
            "category":"Restaurant",
            "type":"Food & Drink"
        }
    ],
    "sg:phone":"+1 608 238 6878",
    "sg:postcode":"53705",
    "sg:province":"WI",
    "sg:tags":[
        "eating"
    ],
    "wof:name":"Steep & Brew Inc",
    "wof:placetype":"venue"
},
  "geometry": {"coordinates":[-89.43700200000001,43.074296],"type":"Point"}
}