{
  "type": "Feature",
  "properties": {
    "iso:country":"US",
    "sg:address":"6242 W State St",
    "sg:city":"Milwaukee",
    "sg:classifiers":[
        {
            "category":"Retail",
            "subcategory":"Auto Repair",
            "type":"Services"
        }
    ],
    "sg:phone":"+1 414 475 5926",
    "sg:postcode":"53213",
    "sg:province":"WI",
    "sg:tags":[
        "body",
        "automobile",
        "painting"
    ],
    "wof:name":"D & T Restorations LTD",
    "wof:placetype":"venue"
},
  "geometry": {"coordinates":[-87.99072700000001,43.044622],"type":"Point"}
}