{
  "type": "Feature",
  "properties": {
    "addr:full":"1513 N 4th St Tomahawk WI 54487",
    "addr:housenumber":"1513",
    "addr:postcode":"54487",
    "addr:street":"N 4Th St",
    "iso:country":"US",
    "sg:address":"1513 N 4th St",
    "sg:city":"Tomahawk",
    "sg:classifiers":[
        {
            "category":"Autos & Motor Vehicles",
            "subcategory":"Auto Supplies",
            "type":"Retail Goods"
        }
    ],
    "sg:phone":"+1 715 453 5534",
    "sg:postcode":"54487",
    "sg:province":"WI",
    "sg:tags":[
        "automobile",
        "parts"
    ],
    "wof:name":"Carquest Auto Parts",
    "wof:placetype":"venue"
},
  "geometry": {"coordinates":[-89.72936900000001,45.491164],"type":"Point"}
}