{
  "type": "Feature",
  "properties": {
    "addr:full":"1200 Cedar St Merrill WI 54452",
    "addr:housenumber":"1200",
    "addr:postcode":"54452",
    "addr:street":"Cedar St",
    "iso:country":"US",
    "sg:address":"1200 Cedar St",
    "sg:city":"Merrill",
    "sg:classifiers":[
        {
            "category":"Professional",
            "subcategory":"Business Services",
            "type":"Services"
        }
    ],
    "sg:phone":"+1 715 536 5122",
    "sg:postcode":"54452",
    "sg:province":"WI",
    "wof:name":"Plautz Enterprises",
    "wof:placetype":"venue"
},
  "geometry": {"coordinates":[-89.681337,45.190706],"type":"Point"}
}