{
  "type": "Feature",
  "properties": {
    "iso:country":"US",
    "sg:address":"2851 New Pinery Rd",
    "sg:city":"Portage",
    "sg:classifiers":[
        {
            "category":"Manufacturing",
            "subcategory":"Glass & Minerals",
            "type":"Manufacturing & Wholesale Goods"
        }
    ],
    "sg:phone":"+1 608 745 4471",
    "sg:postcode":"53901",
    "sg:province":"WI",
    "sg:tags":[
        "manufacture",
        "pipe",
        "line"
    ],
    "wof:name":"Enbridge Energy Company Inc",
    "wof:placetype":"venue"
},
  "geometry": {"coordinates":[-89.46969900000001,43.569535],"type":"Point"}
}