{
  "type": "Feature",
  "properties": {
    "iso:country":"US",
    "sg:address":"828 State Hwy 26",
    "sg:city":"Milton",
    "sg:classifiers":[
        {
            "category":"Retail",
            "subcategory":"Funeral Services",
            "type":"Services"
        }
    ],
    "sg:phone":"+1 608 868 2542",
    "sg:postcode":"53563",
    "sg:province":"WI",
    "sg:tags":[
        "director"
    ],
    "wof:name":"Albrecht Funeral Home Inc",
    "wof:placetype":"venue"
},
  "geometry": {"coordinates":[-88.936777,42.765803],"type":"Point"}
}