{
  "type": "Feature",
  "properties": {
    "addr:full":"8170 E Pecatonica Rd Hollandale WI 53544",
    "addr:housenumber":"8170",
    "addr:postcode":"53544",
    "addr:street":"E Pecatonica Rd",
    "iso:country":"US",
    "sg:address":"8170 E Pecatonica Rd",
    "sg:city":"Hollandale",
    "sg:classifiers":[
        {
            "category":"Building & Trades",
            "subcategory":"Construction",
            "type":"Services"
        }
    ],
    "sg:phone":"+1 608 967 2512",
    "sg:postcode":"53544",
    "sg:province":"WI",
    "sg:tags":[
        "house"
    ],
    "wof:name":"JM Construction of Hollandale",
    "wof:placetype":"venue"
},
  "geometry": {"coordinates":[-89.911236,42.861928],"type":"Point"}
}