{
  "type": "Feature",
  "properties": {
    "addr:full":"1201 N 4th St Watertown WI 53098",
    "addr:housenumber":"1201",
    "addr:postcode":"53098",
    "addr:street":"N 4Th St",
    "iso:country":"US",
    "sg:address":"1201 N 4th St",
    "sg:city":"Watertown",
    "sg:classifiers":[
        {
            "category":"Shopping",
            "subcategory":"Bicycles & Sporting Goods",
            "type":"Retail Goods"
        }
    ],
    "sg:phone":"+1 920 261 9276",
    "sg:postcode":"53098",
    "sg:province":"WI",
    "sg:website":"www.trekbikes.com",
    "wof:name":"Trek Bicycle",
    "wof:placetype":"venue"
},
  "geometry": {"coordinates":[-88.706902,43.207214],"type":"Point"}
}