{
  "type": "Feature",
  "properties": {
    "iso:country":"US",
    "sg:address":"714 S 2nd St",
    "sg:city":"Milwaukee",
    "sg:classifiers":[
        {
            "category":"Professional",
            "type":"Services"
        }
    ],
    "sg:phone":"+1 414 347 9880",
    "sg:postcode":"53204",
    "sg:province":"WI",
    "wof:name":"Smag Media LLC",
    "wof:placetype":"venue"
},
  "geometry": {"coordinates":[-87.912558,43.02335],"type":"Point"}
}