{
  "type": "Feature",
  "properties": {
    "addr:full":"404 E Kimberly Ave Kimberly WI 54136",
    "addr:housenumber":"404",
    "addr:postcode":"54136",
    "addr:street":"E Kimberly Ave",
    "iso:country":"US",
    "sg:address":"404 E Kimberly Ave",
    "sg:city":"Kimberly",
    "sg:classifiers":[
        {
            "category":"Real Estate",
            "subcategory":"Real Estate Agent",
            "type":"Services"
        }
    ],
    "sg:phone":"+1 920 687 9613",
    "sg:postcode":"54136",
    "sg:province":"WI",
    "wof:name":"Dream Estates LLC",
    "wof:placetype":"venue"
},
  "geometry": {"coordinates":[-88.330366,44.272482],"type":"Point"}
}