{
  "type": "Feature",
  "properties": {
    "iso:country":"US",
    "sg:address":"2077 Airport Dr",
    "sg:city":"Green Bay",
    "sg:classifiers":[
        {
            "category":"Airport",
            "type":"Transportation"
        }
    ],
    "sg:phone":"+1 920 498 3662",
    "sg:postcode":"54313",
    "sg:province":"WI",
    "wof:name":"Gearbuck",
    "wof:placetype":"venue"
},
  "geometry": {"coordinates":[-88.123025,44.495779],"type":"Point"}
}