{
  "type": "Feature",
  "properties": {
    "iso:country":"US",
    "sg:address":"10509 Co Rd K",
    "sg:city":"Lancaster",
    "sg:classifiers":[
        {
            "category":"Farming",
            "subcategory":"Dairy Farm",
            "type":"Manufacturing & Wholesale Goods"
        }
    ],
    "sg:phone":"+1 608 723 7813",
    "sg:postcode":"53813",
    "sg:province":"WI",
    "wof:name":"Larry Udelhoven",
    "wof:placetype":"venue"
},
  "geometry": {"coordinates":[-90.74683,42.88529],"type":"Point"}
}