{
  "type": "Feature",
  "properties": {
    "iso:country":"US",
    "sg:address":"5544 N Port Washington Rd",
    "sg:city":"Milwaukee",
    "sg:classifiers":[
        {
            "category":"Food & Beverages",
            "subcategory":"Liquor & Beverages",
            "type":"Retail Goods"
        }
    ],
    "sg:phone":"+1 414 962 6220",
    "sg:postcode":"53217",
    "sg:province":"WI",
    "sg:tags":[
        "store"
    ],
    "wof:name":"North Shore Wine & Spirits",
    "wof:placetype":"venue"
},
  "geometry": {"coordinates":[-87.916618,43.11519],"type":"Point"}
}