{
  "type": "Feature",
  "properties": {
    "iso:country":"US",
    "sg:address":"9299 Deer Creek Rd",
    "sg:city":"Phillips",
    "sg:classifiers":[
        {
            "category":"Manufacturing",
            "subcategory":"Petroleum Products",
            "type":"Manufacturing & Wholesale Goods"
        }
    ],
    "sg:phone":"+1 715 339 6773",
    "sg:postcode":"54555",
    "sg:province":"WI",
    "sg:tags":[
        "concrete",
        "mfg",
        "asphalt",
        "contractor"
    ],
    "wof:name":"Tri State Asphalt Maintenance",
    "wof:placetype":"venue"
},
  "geometry": {"coordinates":[-90.451659,45.712509],"type":"Point"}
}