{
  "type": "Feature",
  "properties": {
    "addr:full":"264 S Grant St Ellsworth WI 54011",
    "addr:housenumber":"264",
    "addr:postcode":"54011",
    "addr:street":"S Grant St",
    "iso:country":"US",
    "sg:address":"264 S Grant St",
    "sg:city":"Ellsworth",
    "sg:classifiers":[
        {
            "category":"Organizations",
            "subcategory":"Religious Organization",
            "type":"Services"
        }
    ],
    "sg:phone":"+1 715 273 4774",
    "sg:postcode":"54011",
    "sg:province":"WI",
    "sg:tags":[
        "church"
    ],
    "wof:name":"St Francis Catholic Church",
    "wof:placetype":"venue"
},
  "geometry": {"coordinates":[-92.48175000000001,44.729081],"type":"Point"}
}