{
  "type": "Feature",
  "properties": {
    "iso:country":"US",
    "sg:address":"2018 Rae Ln",
    "sg:city":"Madison",
    "sg:classifiers":[
        {
            "category":"Social Services",
            "subcategory":"Child Care",
            "type":"Services"
        }
    ],
    "sg:phone":"+1 608 274 0939",
    "sg:postcode":"53711",
    "sg:province":"WI",
    "sg:tags":[
        "day"
    ],
    "wof:name":"Kay Sarkisian Family Day Care",
    "wof:placetype":"venue"
},
  "geometry": {"coordinates":[-89.48571099999999,43.030416],"type":"Point"}
}