{
  "type": "Feature",
  "properties": {
    "iso:country":"US",
    "sg:address":"7568 8th Ave",
    "sg:city":"New Lisbon",
    "sg:classifiers":[
        {
            "category":"Retail",
            "subcategory":"Auto Repair",
            "type":"Services"
        }
    ],
    "sg:phone":"+1 608 562 3417",
    "sg:postcode":"53950",
    "sg:province":"WI",
    "sg:tags":[
        "transmission",
        "general"
    ],
    "wof:name":"Transmission Plus",
    "wof:placetype":"venue"
},
  "geometry": {"coordinates":[-90.15248200000001,43.90921],"type":"Point"}
}