{
  "type": "Feature",
  "properties": {
    "iso:country":"US",
    "sg:address":"356 Dixie St",
    "sg:city":"Fond Du Lac",
    "sg:classifiers":[
        {
            "category":"Freight",
            "type":"Transportation"
        }
    ],
    "sg:phone":"+1 920 929 8088",
    "sg:postcode":"54935",
    "sg:province":"WI",
    "sg:tags":[
        "warehouse",
        "self",
        "storage"
    ],
    "wof:name":"Warehouse Specialists Inc",
    "wof:placetype":"venue"
},
  "geometry": {"coordinates":[-88.459017,43.762224],"type":"Point"}
}