{
  "type": "Feature",
  "properties": {
    "iso:country":"US",
    "sg:address":"1202 W Dayton St",
    "sg:city":"Madison",
    "sg:classifiers":[
        {
            "category":"Restaurant",
            "type":"Food & Drink"
        }
    ],
    "sg:phone":"+1 608 257 1126",
    "sg:postcode":"53715",
    "sg:province":"WI",
    "sg:tags":[
        "shop",
        "submarine",
        "sandwich"
    ],
    "wof:name":"Milans Dayton Street Sub Stn",
    "wof:placetype":"venue"
},
  "geometry": {"coordinates":[-89.40733,43.07114],"type":"Point"}
}