{
  "type": "Feature",
  "properties": {
    "iso:country":"US",
    "sg:address":"885 S Janesville St",
    "sg:city":"Whitewater",
    "sg:classifiers":[
        {
            "category":"Banks & Credit Unions",
            "subcategory":"Investment Brokerage",
            "type":"Services"
        }
    ],
    "sg:phone":"+1 262 473 3151",
    "sg:postcode":"53190",
    "sg:province":"WI",
    "sg:tags":[
        "security"
    ],
    "wof:name":"Edward Jones 21390",
    "wof:placetype":"venue"
},
  "geometry": {"coordinates":[-88.749088,42.820774],"type":"Point"}
}