{
  "type": "Feature",
  "properties": {
    "addr:full":"5648 Main St Auburndale WI 54412",
    "addr:housenumber":"5648",
    "addr:postcode":"54412",
    "addr:street":"Main St",
    "iso:country":"US",
    "sg:address":"5648 Main St",
    "sg:city":"Auburndale",
    "sg:classifiers":[
        {
            "category":"Health Services",
            "subcategory":"Doctor",
            "type":"Services"
        }
    ],
    "sg:phone":"+1 715 652 3100",
    "sg:postcode":"54412",
    "sg:province":"WI",
    "wof:name":"Auburndale Dental Clinic",
    "wof:placetype":"venue"
},
  "geometry": {"coordinates":[-89.994767,44.625208],"type":"Point"}
}