{
  "type": "Feature",
  "properties": {
    "iso:country":"US",
    "sg:address":"107 S Mound Ave",
    "sg:city":"Belmont",
    "sg:classifiers":[
        {
            "category":"Building & Trades",
            "subcategory":"Plumbing",
            "type":"Services"
        }
    ],
    "sg:phone":"+1 608 762 5306",
    "sg:postcode":"53510",
    "sg:province":"WI",
    "sg:tags":[
        "plumbing",
        "contractor"
    ],
    "wof:name":"Burke & Lovell Plumbing",
    "wof:placetype":"venue"
},
  "geometry": {"coordinates":[-90.334053,42.738438],"type":"Point"}
}