{
  "type": "Feature",
  "properties": {
    "iso:country":"US",
    "sg:address":"12505 Spring St",
    "sg:city":"Sturtevant",
    "sg:classifiers":[
        {
            "category":"Building & Trades",
            "subcategory":"Construction",
            "type":"Services"
        }
    ],
    "sg:phone":"+1 262 886 5374",
    "sg:postcode":"53177",
    "sg:province":"WI",
    "sg:tags":[
        "general",
        "contractor"
    ],
    "wof:name":"Reichl Construction Inc",
    "wof:placetype":"venue"
},
  "geometry": {"coordinates":[-87.936531,42.73656],"type":"Point"}
}