{
  "type": "Feature",
  "properties": {
    "iso:country":"US",
    "sg:address":"4174 Big Oak Dr",
    "sg:city":"Mauston",
    "sg:classifiers":[
        {
            "category":"Banks & Credit Unions",
            "subcategory":"Financial Services",
            "type":"Services"
        }
    ],
    "sg:phone":"+1 608 847 4005",
    "sg:postcode":"53948",
    "sg:province":"WI",
    "sg:tags":[
        "trust",
        "management"
    ],
    "wof:name":"Jay C Weldon Enterprises LLC",
    "wof:placetype":"venue"
},
  "geometry": {"coordinates":[-89.981181,43.892917],"type":"Point"}
}