{
  "type": "Feature",
  "properties": {
    "iso:country":"US",
    "sg:address":"9815 Bloch Ln",
    "sg:city":"Marshfield",
    "sg:classifiers":[
        {
            "category":"Freight",
            "type":"Transportation"
        }
    ],
    "sg:phone":"+1 715 676 3606",
    "sg:postcode":"54449",
    "sg:province":"WI",
    "sg:tags":[
        "operator",
        "local",
        "trucking"
    ],
    "wof:name":"Steven L Humphrey Trucking",
    "wof:placetype":"venue"
},
  "geometry": {"coordinates":[-90.268421,44.599129],"type":"Point"}
}