{
  "type": "Feature",
  "properties": {
    "iso:country":"US",
    "sg:address":"8654 Co Rd C",
    "sg:city":"Sturgeon Bay",
    "sg:classifiers":[
        {
            "category":"Autos & Motor Vehicles",
            "subcategory":"Fuel & Gas Station",
            "type":"Retail Goods"
        }
    ],
    "sg:phone":"+1 920 824 5222",
    "sg:postcode":"54235",
    "sg:province":"WI",
    "sg:tags":[
        "grocery",
        "station",
        "gasoline"
    ],
    "wof:name":"Stevenson Pier Mini Mart",
    "wof:placetype":"venue"
},
  "geometry": {"coordinates":[-87.552406,44.820002],"type":"Point"}
}