{
  "type": "Feature",
  "properties": {
    "iso:country":"US",
    "sg:address":"3103 Seymour Ln",
    "sg:city":"Wausau",
    "sg:classifiers":[
        {
            "category":"Organizations",
            "subcategory":"Religious Organization",
            "type":"Services"
        }
    ],
    "sg:phone":"+1 715 845 8241",
    "sg:postcode":"54401",
    "sg:province":"WI",
    "sg:tags":[
        "church"
    ],
    "sg:website":"www.nwdlcms.org",
    "wof:name":"Lutheran Church-Missouri Synod",
    "wof:placetype":"venue"
},
  "geometry": {"coordinates":[-89.674937,44.959014],"type":"Point"}
}