{
  "type": "Feature",
  "properties": {
    "iso:country":"US",
    "sg:address":"4506 30th St",
    "sg:city":"Kenosha",
    "sg:classifiers":[
        {
            "category":"Home & Garden",
            "subcategory":"Home Furnishings",
            "type":"Retail Goods"
        }
    ],
    "sg:phone":"+1 262 652 7432",
    "sg:postcode":"53144",
    "sg:province":"WI",
    "wof:name":"For Your Home",
    "wof:placetype":"venue"
},
  "geometry": {"coordinates":[-87.86395,42.611028],"type":"Point"}
}