{
  "type": "Feature",
  "properties": {
    "iso:country":"US",
    "sg:address":"16500 W Cleveland Ave",
    "sg:city":"New Berlin",
    "sg:classifiers":[
        {
            "category":"Wholesale",
            "subcategory":"Vending Machines",
            "type":"Manufacturing & Wholesale Goods"
        }
    ],
    "sg:phone":"+1 262 784 1200",
    "sg:postcode":"53151",
    "sg:province":"WI",
    "sg:tags":[
        "operator",
        "eating",
        "courier"
    ],
    "wof:name":"Compass Group USA Inc",
    "wof:placetype":"venue"
},
  "geometry": {"coordinates":[-88.118206,42.995418],"type":"Point"}
}