{
  "type": "Feature",
  "properties": {
    "iso:country":"US",
    "sg:address":"153 Tommys Tpke",
    "sg:city":"Stevens Point",
    "sg:classifiers":[
        {
            "category":"Professional",
            "subcategory":"Business Services",
            "type":"Services"
        }
    ],
    "sg:phone":"+1 715 344 8367",
    "sg:postcode":"54481",
    "sg:province":"WI",
    "wof:name":"ABC Home Inspection",
    "wof:placetype":"venue"
},
  "geometry": {"coordinates":[-89.55083399999999,44.481831],"type":"Point"}
}