{
  "type": "Feature",
  "properties": {
    "iso:country":"US",
    "sg:address":"6445 State Hwy 182",
    "sg:city":"Park Falls",
    "sg:classifiers":[
        {
            "category":"Building & Trades",
            "subcategory":"Electrical",
            "type":"Services"
        }
    ],
    "sg:phone":"+1 715 762 4085",
    "sg:postcode":"54552",
    "sg:province":"WI",
    "sg:tags":[
        "electric",
        "contractor"
    ],
    "wof:name":"Brandt Electric LLC",
    "wof:placetype":"venue"
},
  "geometry": {"coordinates":[-90.366654,45.941976],"type":"Point"}
}