{
  "type": "Feature",
  "properties": {
    "iso:country":"US",
    "sg:address":"200 E Richmond St",
    "sg:city":"Shawano",
    "sg:classifiers":[
        {
            "category":"Retail",
            "subcategory":"Auto Repair",
            "type":"Services"
        }
    ],
    "sg:phone":"+1 715 524 2590",
    "sg:postcode":"54166",
    "sg:province":"WI",
    "sg:tags":[
        "automotive"
    ],
    "wof:name":"Dr Gear LLC",
    "wof:placetype":"venue"
},
  "geometry": {"coordinates":[-88.607355,44.774629],"type":"Point"}
}