{
  "type": "Feature",
  "properties": {
    "iso:country":"US",
    "sg:address":"101 E 5th St",
    "sg:city":"Hayward",
    "sg:classifiers":[
        {
            "category":"Government",
            "subcategory":"Police Station",
            "type":"Public Place"
        }
    ],
    "sg:phone":"+1 715 634 4858",
    "sg:postcode":"54843",
    "sg:province":"WI",
    "sg:tags":[
        "sheriff"
    ],
    "wof:name":"Sawyer County Sheriff",
    "wof:placetype":"venue"
},
  "geometry": {"coordinates":[-91.484325,46.018712],"type":"Point"}
}