{
  "type": "Feature",
  "properties": {
    "iso:country":"US",
    "sg:address":"135 N Roosevelt Dr",
    "sg:city":"Beaver Dam",
    "sg:classifiers":[
        {
            "category":"Retail",
            "subcategory":"Repair Shop",
            "type":"Services"
        }
    ],
    "sg:phone":"+1 920 885 3775",
    "sg:postcode":"53916",
    "sg:province":"WI",
    "wof:name":"Lindert Sharpening & Sales",
    "wof:placetype":"venue"
},
  "geometry": {"coordinates":[-88.82323100000001,43.458038],"type":"Point"}
}