{
  "type": "Feature",
  "properties": {
    "iso:country":"US",
    "sg:address":"2765 Co Rd Q",
    "sg:city":"Markesan",
    "sg:phone":"+1 920 398 2031",
    "sg:postcode":"53946",
    "sg:province":"WI",
    "sg:tags":[
        "farm",
        "field",
        "corn",
        "crop"
    ],
    "wof:name":"Dennis Heine",
    "wof:placetype":"venue"
},
  "geometry": {"coordinates":[-88.905295,43.729202],"type":"Point"}
}