{
  "type": "Feature",
  "properties": {
    "iso:country":"US",
    "sg:address":"4823 Section Line Rd",
    "sg:city":"Dodgeville",
    "sg:classifiers":[
        {
            "category":"Manufacturing",
            "subcategory":"Pet Food",
            "type":"Manufacturing & Wholesale Goods"
        },
        {
            "category":"Manufacturing",
            "subcategory":"Chemicals & Compounds",
            "type":"Manufacturing & Wholesale Goods"
        }
    ],
    "sg:phone":"+1 608 935 3111",
    "sg:postcode":"53533",
    "sg:province":"WI",
    "sg:tags":[
        "feed",
        "product",
        "mfg",
        "prepared",
        "equipment",
        "biological"
    ],
    "wof:name":"Immuno Dynamics Inc",
    "wof:placetype":"venue"
},
  "geometry": {"coordinates":[-90.111521,42.959819],"type":"Point"}
}