{
  "type": "Feature",
  "properties": {
    "iso:country":"US",
    "sg:address":"18426 Durand Ave",
    "sg:city":"Union Grove",
    "sg:classifiers":[
        {
            "category":"Wholesale",
            "subcategory":"Construction Materials",
            "type":"Manufacturing & Wholesale Goods"
        }
    ],
    "sg:phone":"+1 262 878 2030",
    "sg:postcode":"53182",
    "sg:province":"WI",
    "sg:tags":[
        "tank",
        "system",
        "septic"
    ],
    "wof:name":"Grove Concrete & Supply Inc",
    "wof:placetype":"venue"
},
  "geometry": {"coordinates":[-88.038494,42.680941],"type":"Point"}
}