{
  "type": "Feature",
  "properties": {
    "iso:country":"US",
    "sg:address":"752 Alderson St",
    "sg:city":"Schofield",
    "sg:classifiers":[
        {
            "category":"Food & Beverages",
            "subcategory":"Meat & Fish",
            "type":"Retail Goods"
        }
    ],
    "sg:phone":"+1 715 241 7774",
    "sg:postcode":"54476",
    "sg:province":"WI",
    "wof:name":"Town & County Meats",
    "wof:placetype":"venue"
},
  "geometry": {"coordinates":[-89.596771,44.92201],"type":"Point"}
}