{
  "type": "Feature",
  "properties": {
    "iso:country":"US",
    "sg:address":"3411 Co Rd B",
    "sg:city":"Lake Geneva",
    "sg:classifiers":[
        {
            "category":"Building & Trades",
            "subcategory":"Construction",
            "type":"Services"
        }
    ],
    "sg:phone":"+1 262 248 9210",
    "sg:postcode":"53147",
    "sg:province":"WI",
    "sg:tags":[
        "house",
        "nonresidential",
        "general",
        "contractor"
    ],
    "wof:name":"Engerman Contracting Inc",
    "wof:placetype":"venue"
},
  "geometry": {"coordinates":[-88.46763199999999,42.516617],"type":"Point"}
}