{
  "type": "Feature",
  "properties": {
    "addr:full":"1101 W Ridgeview Dr Appleton WI 54914",
    "addr:housenumber":"1101",
    "addr:postcode":"54914",
    "addr:street":"W Ridgeview Dr",
    "iso:country":"US",
    "sg:address":"1101 W Ridgeview Dr",
    "sg:city":"Appleton",
    "sg:classifiers":[
        {
            "category":"Building & Trades",
            "subcategory":"Cleaning & Sanitation",
            "type":"Services"
        }
    ],
    "sg:phone":"+1 920 954 6726",
    "sg:postcode":"54914",
    "sg:province":"WI",
    "sg:tags":[
        "maintenance"
    ],
    "wof:name":"Pro Clean Janitorial Services",
    "wof:placetype":"venue"
},
  "geometry": {"coordinates":[-88.421919,44.290251],"type":"Point"}
}