{
  "type": "Feature",
  "properties": {
    "iso:country":"US",
    "sg:address":"3978 Co Hwy P",
    "sg:city":"Chippewa Falls",
    "sg:classifiers":[
        {
            "category":"Building & Trades",
            "subcategory":"Landscaping Services",
            "type":"Services"
        }
    ],
    "sg:phone":"+1 715 833 8373",
    "sg:postcode":"54729",
    "sg:province":"WI",
    "sg:tags":[
        "landscape",
        "contractor"
    ],
    "wof:name":"American Landscape",
    "wof:placetype":"venue"
},
  "geometry": {"coordinates":[-91.38891,44.900583],"type":"Point"}
}