{
  "type": "Feature",
  "properties": {
    "iso:country":"US",
    "sg:address":"1815 Jeffery Ln",
    "sg:city":"Waukesha",
    "sg:classifiers":[
        {
            "category":"Shopping",
            "subcategory":"Catalog Store",
            "type":"Retail Goods"
        }
    ],
    "sg:phone":"+1 262 970 8859",
    "sg:postcode":"53186",
    "sg:province":"WI",
    "sg:tags":[
        "mail",
        "house"
    ],
    "wof:name":"Solomon Pharmaceutical Supply",
    "wof:placetype":"venue"
},
  "geometry": {"coordinates":[-88.194462,43.035694],"type":"Point"}
}