{
  "type": "Feature",
  "properties": {
    "addr:full":"1430 Pershing Ave Sheboygan WI 53083",
    "addr:housenumber":"1430",
    "addr:postcode":"53083",
    "addr:street":"Pershing Ave",
    "iso:country":"US",
    "sg:address":"1430 Pershing Ave",
    "sg:city":"Sheboygan",
    "sg:classifiers":[
        {
            "category":"Home & Garden",
            "subcategory":"Household Appliances",
            "type":"Retail Goods"
        },
        {
            "category":"Home & Garden",
            "subcategory":"Furniture",
            "type":"Retail Goods"
        }
    ],
    "sg:phone":"+1 920 458 7485",
    "sg:postcode":"53083",
    "sg:province":"WI",
    "sg:tags":[
        "equipment",
        "kitchen",
        "cabinet"
    ],
    "wof:name":"T K Woodworking LLC",
    "wof:placetype":"venue"
},
  "geometry": {"coordinates":[-87.723192,43.779963],"type":"Point"}
}