{
  "type": "Feature",
  "properties": {
    "addr:full":"31518 High Dr Burlington WI 53105",
    "addr:housenumber":"31518",
    "addr:postcode":"53105",
    "addr:street":"High Dr",
    "iso:country":"US",
    "sg:address":"31518 High Dr",
    "sg:city":"Burlington",
    "sg:classifiers":[
        {
            "category":"Building & Trades",
            "subcategory":"Construction",
            "type":"Services"
        }
    ],
    "sg:phone":"+1 262 534 7146",
    "sg:postcode":"53105",
    "sg:province":"WI",
    "sg:tags":[
        "excavation",
        "excavating",
        "contractor"
    ],
    "wof:name":"Bennett Fairview Excavation",
    "wof:placetype":"venue"
},
  "geometry": {"coordinates":[-88.23698899999999,42.770402],"type":"Point"}
}