{
  "type": "Feature",
  "properties": {
    "iso:country":"US",
    "sg:address":"240 Walnut St",
    "sg:city":"Loganville",
    "sg:classifiers":[
        {
            "category":"Wholesale",
            "subcategory":"Farm Supplies",
            "type":"Manufacturing & Wholesale Goods"
        }
    ],
    "sg:phone":"+1 608 727 3431",
    "sg:postcode":"53943",
    "sg:province":"WI",
    "sg:tags":[
        "feed"
    ],
    "wof:name":"Co Op Country Partners",
    "wof:placetype":"venue"
},
  "geometry": {"coordinates":[-90.040349,43.440312],"type":"Point"}
}