{
  "type": "Feature",
  "properties": {
    "iso:country":"US",
    "sg:address":"3500 N Main St",
    "sg:city":"Racine",
    "sg:classifiers":[
        {
            "category":"Professional",
            "type":"Services"
        }
    ],
    "sg:phone":"+1 262 639 7737",
    "sg:postcode":"53402",
    "sg:province":"WI",
    "wof:name":"Paralax Aviation LLC",
    "wof:placetype":"venue"
},
  "geometry": {"coordinates":[-87.782469,42.763211],"type":"Point"}
}