{
  "type": "Feature",
  "properties": {
    "iso:country":"US",
    "sg:address":"3233 Highpointe Dr",
    "sg:city":"New Berlin",
    "sg:classifiers":[
        {
            "category":"Organizations",
            "subcategory":"Membership Organization",
            "type":"Services"
        }
    ],
    "sg:phone":"+1 262 796 9014",
    "sg:postcode":"53151",
    "sg:province":"WI",
    "wof:name":"Stephanie Central Inc",
    "wof:placetype":"venue"
},
  "geometry": {"coordinates":[-88.076582,42.985756],"type":"Point"}
}