{
  "type": "Feature",
  "properties": {
    "iso:country":"US",
    "sg:address":"4625 Pip Ln",
    "sg:city":"Oshkosh",
    "sg:classifiers":[
        {
            "category":"Farming",
            "subcategory":"Dairy Farm",
            "type":"Manufacturing & Wholesale Goods"
        }
    ],
    "sg:phone":"+1 920 231 7955",
    "sg:postcode":"54904",
    "sg:province":"WI",
    "sg:tags":[
        "beef",
        "feedlot",
        "cattle"
    ],
    "wof:name":"Grundy Farms Inc",
    "wof:placetype":"venue"
},
  "geometry": {"coordinates":[-88.576775,44.083326],"type":"Point"}
}