{
  "type": "Feature",
  "properties": {
    "iso:country":"US",
    "sg:address":"430 S Clay St",
    "sg:city":"Green Bay",
    "sg:classifiers":[
        {
            "category":"Health Services",
            "subcategory":"Nursing And Care Facility",
            "type":"Services"
        }
    ],
    "sg:phone":"+1 920 432 5231",
    "sg:postcode":"54301",
    "sg:province":"WI",
    "sg:tags":[
        "home",
        "rest"
    ],
    "wof:name":"Santa Maria Nursing Home",
    "wof:placetype":"venue"
},
  "geometry": {"coordinates":[-88.006704,44.505332],"type":"Point"}
}