{
  "type": "Feature",
  "properties": {
    "addr:full":"8032 Plantz Rd Ladysmith WI 54848",
    "addr:housenumber":"8032",
    "addr:postcode":"54848",
    "addr:street":"Plantz Rd",
    "iso:country":"US",
    "sg:address":"8032 Plantz Rd",
    "sg:city":"Ladysmith",
    "sg:classifiers":[
        {
            "category":"Farming",
            "subcategory":"Dairy Farm",
            "type":"Manufacturing & Wholesale Goods"
        }
    ],
    "sg:phone":"+1 715 532 6516",
    "sg:postcode":"54848",
    "sg:province":"WI",
    "sg:tags":[
        "a",
        "as",
        "operates"
    ],
    "wof:name":"Rusk Rose Holsteins Inc",
    "wof:placetype":"venue"
},
  "geometry": {"coordinates":[-91.08980699999999,45.407038],"type":"Point"}
}