{
  "type": "Feature",
  "properties": {
    "iso:country":"US",
    "sg:address":"2537 W Wisconsin Ave",
    "sg:city":"Milwaukee",
    "sg:classifiers":[
        {
            "category":"Banks & Credit Unions",
            "subcategory":"Bank",
            "type":"Services"
        }
    ],
    "sg:phone":"+1 414 931 0111",
    "sg:postcode":"53233",
    "sg:province":"WI",
    "sg:tags":[
        "full"
    ],
    "wof:name":"Wisconsin At 26th Office",
    "wof:placetype":"venue"
},
  "geometry": {"coordinates":[-87.94586,43.038619],"type":"Point"}
}