{
  "type": "Feature",
  "properties": {
    "addr:full":"4802 Najacht Rd Sheboygan WI 53083",
    "addr:housenumber":"4802",
    "addr:postcode":"53083",
    "addr:street":"Najacht Rd",
    "iso:country":"US",
    "sg:address":"4802 Najacht Rd",
    "sg:city":"Sheboygan",
    "sg:classifiers":[
        {
            "category":"Retail",
            "subcategory":"Animal Services",
            "type":"Services"
        }
    ],
    "sg:phone":"+1 920 452 8788",
    "sg:postcode":"53083",
    "sg:province":"WI",
    "sg:tags":[
        "pet",
        "training"
    ],
    "wof:name":"Sheboygan Dog Training Club",
    "wof:placetype":"venue"
},
  "geometry": {"coordinates":[-87.736907,43.797603],"type":"Point"}
}