{
  "type": "Feature",
  "properties": {
    "addr:full":"310 2nd St Hudson WI 54016",
    "addr:housenumber":"310",
    "addr:postcode":"54016",
    "addr:street":"2Nd St",
    "iso:country":"US",
    "sg:address":"310 2nd St",
    "sg:city":"Hudson",
    "sg:classifiers":[
        {
            "category":"Shopping",
            "type":"Retail Goods"
        }
    ],
    "sg:phone":"+1 715 381 2906",
    "sg:postcode":"54016",
    "sg:province":"WI",
    "sg:tags":[
        "art",
        "gallery",
        "dealer"
    ],
    "wof:name":"Seasons On St Croix",
    "wof:placetype":"venue"
},
  "geometry": {"coordinates":[-92.75668,44.972982],"type":"Point"}
}