{
  "type": "Feature",
  "properties": {
    "iso:country":"US",
    "sg:address":"332 W Wilson St",
    "sg:city":"Stoughton",
    "sg:classifiers":[
        {
            "category":"Professional",
            "subcategory":"Business Services",
            "type":"Services"
        }
    ],
    "sg:phone":"+1 608 205 9319",
    "sg:postcode":"53589",
    "sg:province":"WI",
    "wof:name":"Accent Business Communications",
    "wof:placetype":"venue"
},
  "geometry": {"coordinates":[-89.223705,42.923409],"type":"Point"}
}