{
  "type": "Feature",
  "properties": {
    "addr:full":"11101 W Lincoln Ave West Allis WI 53227",
    "addr:housenumber":"11101",
    "addr:postcode":"53227",
    "addr:street":"W Lincoln Ave",
    "iso:country":"US",
    "sg:address":"11101 W Lincoln Ave",
    "sg:city":"West Allis",
    "sg:classifiers":[
        {
            "category":"Health Services",
            "subcategory":"Doctor",
            "type":"Services"
        }
    ],
    "sg:phone":"+1 414 203 4500",
    "sg:postcode":"53227",
    "sg:province":"WI",
    "sg:tags":[
        "physician",
        "surgeon"
    ],
    "wof:name":"Crain H Bliwas MD",
    "wof:placetype":"venue"
},
  "geometry": {"coordinates":[-88.049707,43.002531],"type":"Point"}
}