{
  "type": "Feature",
  "properties": {
    "iso:country":"US",
    "sg:address":"1725 W 8th St",
    "sg:city":"Appleton",
    "sg:classifiers":[
        {
            "category":"Manufacturing",
            "subcategory":"Printing",
            "type":"Manufacturing & Wholesale Goods"
        }
    ],
    "sg:phone":"+1 920 968 0262",
    "sg:postcode":"54914",
    "sg:province":"WI",
    "sg:tags":[
        "label"
    ],
    "wof:name":"Xpanded Label Technology",
    "wof:placetype":"venue"
},
  "geometry": {"coordinates":[-88.433341,44.259611],"type":"Point"}
}