{
  "type": "Feature",
  "properties": {
    "iso:country":"US",
    "sg:address":"2399 Clear View Rd",
    "sg:city":"Monroe",
    "sg:classifiers":[
        {
            "category":"Wholesale",
            "subcategory":"Medical Equipment & Supplies",
            "type":"Manufacturing & Wholesale Goods"
        }
    ],
    "sg:phone":"+1 608 838 6676",
    "sg:postcode":"53523",
    "sg:province":"WI",
    "wof:name":"Alpine Dispensing Inc",
    "wof:placetype":"venue"
},
  "geometry": {"coordinates":[-89.052572,42.972524],"type":"Point"}
}