{
  "type": "Feature",
  "properties": {
    "iso:country":"US",
    "sg:address":"2411 Browning Dr",
    "sg:city":"Janesville",
    "sg:classifiers":[
        {
            "category":"Wholesale",
            "subcategory":"Durable Goods & Equipment",
            "type":"Manufacturing & Wholesale Goods"
        }
    ],
    "sg:phone":"+1 608 755 1597",
    "sg:postcode":"53546",
    "sg:province":"WI",
    "sg:tags":[
        "professional"
    ],
    "wof:name":"J & B Products Inc",
    "wof:placetype":"venue"
},
  "geometry": {"coordinates":[-88.976054,42.709702],"type":"Point"}
}