{
  "type": "Feature",
  "properties": {
    "iso:country":"US",
    "sg:address":"6865 Chadwick Rd",
    "sg:city":"Reedsburg",
    "sg:classifiers":[
        {
            "category":"Building & Trades",
            "subcategory":"Construction",
            "type":"Services"
        }
    ],
    "sg:phone":"+1 608 524 3131",
    "sg:postcode":"53959",
    "sg:province":"WI",
    "sg:tags":[
        "concrete",
        "contractor"
    ],
    "wof:name":"Alan's Concrete",
    "wof:placetype":"venue"
},
  "geometry": {"coordinates":[-89.97471,43.559964],"type":"Point"}
}