{
  "type": "Feature",
  "properties": {
    "iso:country":"US",
    "sg:address":"1538 Scott Rd",
    "sg:city":"Port Washington",
    "sg:classifiers":[
        {
            "category":"Recreation",
            "type":"Entertainment"
        }
    ],
    "sg:phone":"+1 262 284 4693",
    "sg:postcode":"53074",
    "sg:province":"WI",
    "wof:name":"Seahawk Charters",
    "wof:placetype":"venue"
},
  "geometry": {"coordinates":[-87.874656,43.40638],"type":"Point"}
}