{
  "type": "Feature",
  "properties": {
    "iso:country":"US",
    "sg:address":"607 Superior Ave",
    "sg:city":"Tomah",
    "sg:classifiers":[
        {
            "category":"Professional",
            "subcategory":"Business Services",
            "type":"Services"
        }
    ],
    "sg:phone":"+1 608 463 7198",
    "sg:postcode":"54660",
    "sg:province":"WI",
    "wof:name":"Brandau Hill Auction Service",
    "wof:placetype":"venue"
},
  "geometry": {"coordinates":[-90.50483,43.981452],"type":"Point"}
}