{
  "type": "Feature",
  "properties": {
    "iso:country":"US",
    "sg:address":"4520 W Burleigh St",
    "sg:city":"Milwaukee",
    "sg:classifiers":[
        {
            "category":"Shopping",
            "subcategory":"Used Merchandise",
            "type":"Retail Goods"
        }
    ],
    "sg:phone":"+1 414 445 7080",
    "sg:postcode":"53210",
    "sg:province":"WI",
    "wof:name":"Antiques By Loraine",
    "wof:placetype":"venue"
},
  "geometry": {"coordinates":[-87.97080200000001,43.075291],"type":"Point"}
}