{
  "type": "Feature",
  "properties": {
    "iso:country":"US",
    "sg:address":"700 Coronis Cir",
    "sg:city":"Green Bay",
    "sg:classifiers":[
        {
            "category":"Manufacturing",
            "subcategory":"Tools & Machinery",
            "type":"Manufacturing & Wholesale Goods"
        }
    ],
    "sg:phone":"+1 920 336 2400",
    "sg:postcode":"54304",
    "sg:province":"WI",
    "sg:tags":[
        "equipment",
        "industrial",
        "supply"
    ],
    "sg:website":"www.jonasservice.com",
    "wof:name":"Jonas Service & Supply Inc",
    "wof:placetype":"venue"
},
  "geometry": {"coordinates":[-88.078171,44.460318],"type":"Point"}
}