{
  "type": "Feature",
  "properties": {
    "iso:country":"US",
    "sg:address":"8426 Morgan Rd",
    "sg:city":"Almond",
    "sg:classifiers":[
        {
            "category":"Freight",
            "type":"Transportation"
        }
    ],
    "sg:phone":"+1 715 366 2841",
    "sg:postcode":"54909",
    "sg:province":"WI",
    "sg:tags":[
        "arrangement"
    ],
    "wof:name":"Sawyer Enterprises",
    "wof:placetype":"venue"
},
  "geometry": {"coordinates":[-89.346014,44.307017],"type":"Point"}
}