{
  "type": "Feature",
  "properties": {
    "addr:full":"501 S Nicolet Rd Appleton WI 54914",
    "addr:housenumber":"501",
    "addr:postcode":"54914",
    "addr:street":"S Nicolet Rd",
    "iso:country":"US",
    "sg:address":"501 S Nicolet Rd",
    "sg:city":"Appleton",
    "sg:classifiers":[
        {
            "category":"Health Services",
            "subcategory":"Clinic",
            "type":"Services"
        }
    ],
    "sg:phone":"+1 920 734 3054",
    "sg:postcode":"54914",
    "sg:province":"WI",
    "wof:name":"Biolife Plasma Services LP",
    "wof:placetype":"venue"
},
  "geometry": {"coordinates":[-88.46914599999999,44.257923],"type":"Point"}
}