{
  "type": "Feature",
  "properties": {
    "iso:country":"US",
    "sg:address":"307 Birch St",
    "sg:city":"Marshfield",
    "sg:classifiers":[
        {
            "category":"Retail",
            "subcategory":"Repair Shop",
            "type":"Services"
        }
    ],
    "sg:phone":"+1 715 387 4000",
    "sg:postcode":"54449",
    "sg:province":"WI",
    "sg:tags":[
        "electrical"
    ],
    "wof:name":"Jims Shaver Service",
    "wof:placetype":"venue"
},
  "geometry": {"coordinates":[-90.15113,44.714052],"type":"Point"}
}