{
  "type": "Feature",
  "properties": {
    "addr:full":"202 S Curtis Rd Milwaukee WI 53214",
    "addr:housenumber":"202",
    "addr:postcode":"53214",
    "addr:street":"S Curtis Rd",
    "iso:country":"US",
    "sg:address":"202 S Curtis Rd",
    "sg:city":"Milwaukee",
    "sg:classifiers":[
        {
            "category":"Wholesale",
            "subcategory":"Hardware",
            "type":"Manufacturing & Wholesale Goods"
        }
    ],
    "sg:phone":"+1 414 476 1598",
    "sg:postcode":"53214",
    "sg:province":"WI",
    "sg:tags":[
        "manufactured",
        "fastener"
    ],
    "wof:name":"Fastenal Company",
    "wof:placetype":"venue"
},
  "geometry": {"coordinates":[-88.06195700000001,43.028512],"type":"Point"}
}