{
  "type": "Feature",
  "properties": {
    "iso:country":"US",
    "sg:address":"302 State St",
    "sg:city":"Oshkosh",
    "sg:classifiers":[
        {
            "category":"Banks & Credit Unions",
            "subcategory":"Bank",
            "type":"Services"
        }
    ],
    "sg:phone":"+1 920 235 6363",
    "sg:postcode":"54901",
    "sg:province":"WI",
    "wof:name":"Pluswood Group Credit Union",
    "wof:placetype":"venue"
},
  "geometry": {"coordinates":[-88.536244,44.017692],"type":"Point"}
}