{
  "type": "Feature",
  "properties": {
    "addr:full":"2040 S Main St Hazel Green WI 53811",
    "addr:housenumber":"2040",
    "addr:postcode":"53811",
    "addr:street":"S Main St",
    "iso:country":"US",
    "sg:address":"2040 S Main St",
    "sg:city":"Hazel Green",
    "sg:classifiers":[
        {
            "category":"Bars & Pubs",
            "type":"Food & Drink"
        }
    ],
    "sg:phone":"+1 608 854 2131",
    "sg:postcode":"53811",
    "sg:province":"WI",
    "wof:name":"Wigwam",
    "wof:placetype":"venue"
},
  "geometry": {"coordinates":[-90.434774,42.532715],"type":"Point"}
}