{
  "type": "Feature",
  "properties": {
    "iso:country":"US",
    "sg:address":"5971 S 33rd St",
    "sg:city":"Milwaukee",
    "sg:classifiers":[
        {
            "category":"Real Estate",
            "subcategory":"Architect",
            "type":"Services"
        }
    ],
    "sg:phone":"+1 414 281 7513",
    "sg:postcode":"53221",
    "sg:province":"WI",
    "sg:tags":[
        "architectural"
    ],
    "wof:name":"Pacific Design LLC",
    "wof:placetype":"venue"
},
  "geometry": {"coordinates":[-87.956772,42.936981],"type":"Point"}
}