{
  "type": "Feature",
  "properties": {
    "addr:full":"149 S Falls St River Falls WI 54022",
    "addr:housenumber":"149",
    "addr:postcode":"54022",
    "addr:street":"S Falls St",
    "iso:country":"US",
    "sg:address":"149 S Falls St",
    "sg:city":"River Falls",
    "sg:classifiers":[
        {
            "category":"Social Services",
            "subcategory":"Child Care",
            "type":"Services"
        }
    ],
    "sg:phone":"+1 715 426 0409",
    "sg:postcode":"54022",
    "sg:province":"WI",
    "sg:tags":[
        "day"
    ],
    "wof:name":"Lollipop Land Child Care",
    "wof:placetype":"venue"
},
  "geometry": {"coordinates":[-92.633623,44.858367],"type":"Point"}
}