{
  "type": "Feature",
  "properties": {
    "addr:full":"1245 Waube Ln Green Bay WI 54304",
    "addr:housenumber":"1245",
    "addr:postcode":"54304",
    "addr:street":"Waube Ln",
    "iso:country":"US",
    "sg:address":"1245 Waube Ln",
    "sg:city":"Green Bay",
    "sg:classifiers":[
        {
            "category":"Professional",
            "subcategory":"Business Services",
            "type":"Services"
        }
    ],
    "sg:phone":"+1 920 339 0510",
    "sg:postcode":"54304",
    "sg:province":"WI",
    "sg:tags":[
        "liquidator"
    ],
    "sg:website":"www.futurapressurecooker.com",
    "wof:name":"Bay City Intl",
    "wof:placetype":"venue"
},
  "geometry": {"coordinates":[-88.09916699999999,44.473156],"type":"Point"}
}