{
  "type": "Feature",
  "properties": {
    "iso:country":"US",
    "sg:address":"5696 Substation Rd",
    "sg:city":"Lancaster",
    "sg:classifiers":[
        {
            "category":"Insurance",
            "subcategory":"Insurance Agent",
            "type":"Services"
        }
    ],
    "sg:phone":"+1 608 723 7541",
    "sg:postcode":"53813",
    "sg:province":"WI",
    "wof:name":"Wolf Farm Office",
    "wof:placetype":"venue"
},
  "geometry": {"coordinates":[-90.69802,42.769886],"type":"Point"}
}