{
  "type": "Feature",
  "properties": {
    "addr:full":"638 Water St Prairie Du Sac WI 53578",
    "addr:housenumber":"638",
    "addr:postcode":"53578",
    "addr:street":"Water St",
    "iso:country":"US",
    "sg:address":"638 Water St",
    "sg:city":"Prairie Du Sac",
    "sg:classifiers":[
        {
            "category":"Bars & Pubs",
            "type":"Food & Drink"
        }
    ],
    "sg:phone":"+1 608 643 3517",
    "sg:postcode":"53578",
    "sg:province":"WI",
    "sg:tags":[
        "drinking"
    ],
    "wof:name":"Coachs Place Inc",
    "wof:placetype":"venue"
},
  "geometry": {"coordinates":[-89.71813,43.287067],"type":"Point"}
}