{
  "type": "Feature",
  "properties": {
    "iso:country":"US",
    "sg:address":"8324 N 48th St",
    "sg:city":"Milwaukee",
    "sg:classifiers":[
        {
            "category":"Real Estate",
            "subcategory":"Real Estate Operator",
            "type":"Services"
        }
    ],
    "sg:phone":"+1 414 362 9575",
    "sg:postcode":"53223",
    "sg:province":"WI",
    "sg:tags":[
        "building",
        "nonresidential"
    ],
    "wof:name":"Avery Properties LLC",
    "wof:placetype":"venue"
},
  "geometry": {"coordinates":[-87.970374,43.168658],"type":"Point"}
}