{
  "type": "Feature",
  "properties": {
    "iso:country":"US",
    "sg:address":"51 Tower Dr",
    "sg:city":"Sun Prairie",
    "sg:classifiers":[
        {
            "category":"Organizations",
            "subcategory":"Religious Organization",
            "type":"Services"
        }
    ],
    "sg:phone":"+1 608 834 8855",
    "sg:postcode":"53590",
    "sg:province":"WI",
    "sg:tags":[
        "church"
    ],
    "wof:name":"Faith Hope & Love Family",
    "wof:placetype":"venue"
},
  "geometry": {"coordinates":[-89.21212199999999,43.198504],"type":"Point"}
}