{
  "type": "Feature",
  "properties": {
    "iso:country":"US",
    "sg:address":"18136 Fredrickson St",
    "sg:city":"Whitehall",
    "sg:classifiers":[
        {
            "category":"Real Estate",
            "subcategory":"Real Estate Operator",
            "type":"Services"
        }
    ],
    "sg:phone":"+1 715 538 4335",
    "sg:postcode":"54773",
    "sg:province":"WI",
    "sg:tags":[
        "property",
        "lessor"
    ],
    "wof:name":"Rufus Halama",
    "wof:placetype":"venue"
},
  "geometry": {"coordinates":[-91.309292,44.361301],"type":"Point"}
}