{
  "type": "Feature",
  "properties": {
    "iso:country":"US",
    "sg:address":"11248 Berlin Ln",
    "sg:city":"Athens",
    "sg:classifiers":[
        {
            "category":"Education",
            "subcategory":"School",
            "type":"Public Place"
        }
    ],
    "sg:phone":"+1 715 675 3773",
    "sg:postcode":"54411",
    "sg:province":"WI",
    "wof:name":"Berlin Elementary School",
    "wof:placetype":"venue"
},
  "geometry": {"coordinates":[-89.788576,45.062377],"type":"Point"}
}