{
  "type": "Feature",
  "properties": {
    "iso:country":"US",
    "sg:address":"2214 E Manogue Rd",
    "sg:city":"Milton",
    "sg:classifiers":[
        {
            "category":"Retail",
            "subcategory":"Repair Shop",
            "type":"Services"
        }
    ],
    "sg:phone":"+1 608 868 4022",
    "sg:postcode":"53563",
    "sg:province":"WI",
    "sg:tags":[
        "taxidermist"
    ],
    "wof:name":"Wegner's Taxidermy",
    "wof:placetype":"venue"
},
  "geometry": {"coordinates":[-88.999258,42.774223],"type":"Point"}
}