{
  "type": "Feature",
  "properties": {
    "iso:country":"US",
    "sg:address":"7071 School Rd",
    "sg:city":"Greenville",
    "sg:classifiers":[
        {
            "category":"Professional",
            "subcategory":"Art Services",
            "type":"Services"
        }
    ],
    "sg:phone":"+1 920 757 6499",
    "sg:postcode":"54942",
    "sg:province":"WI",
    "sg:tags":[
        "artist"
    ],
    "wof:name":"Bosetti Production Art & Dsgn",
    "wof:placetype":"venue"
},
  "geometry": {"coordinates":[-88.54429500000001,44.28731],"type":"Point"}
}