{
  "type": "Feature",
  "properties": {
    "addr:full":"627 Sheridan Dr Waupaca WI 54981",
    "addr:housenumber":"627",
    "addr:postcode":"54981",
    "addr:street":"Sheridan Dr",
    "iso:country":"US",
    "sg:address":"627 Sheridan Dr",
    "sg:city":"Waupaca",
    "sg:classifiers":[
        {
            "category":"Professional",
            "subcategory":"Testing Lab",
            "type":"Services"
        }
    ],
    "sg:phone":"+1 715 258 8083",
    "sg:postcode":"54981",
    "sg:province":"WI",
    "sg:tags":[
        "soil"
    ],
    "wof:name":"Sheridan Soil Svc",
    "wof:placetype":"venue"
},
  "geometry": {"coordinates":[-89.197029,44.395591],"type":"Point"}
}