{
  "type": "Feature",
  "properties": {
    "iso:country":"US",
    "sg:address":"9421 Union Valley Rd",
    "sg:city":"Black Earth",
    "sg:classifiers":[
        {
            "category":"Farming",
            "subcategory":"Dairy Farm",
            "type":"Manufacturing & Wholesale Goods"
        }
    ],
    "sg:phone":"+1 608 767 3637",
    "sg:postcode":"53515",
    "sg:province":"WI",
    "wof:name":"Ellis Spring Valley Dairy Farm",
    "wof:placetype":"venue"
},
  "geometry": {"coordinates":[-89.71643400000001,43.096897],"type":"Point"}
}