{
  "type": "Feature",
  "properties": {
    "addr:full":"503 S 22nd Ave Wausau WI 54401",
    "addr:housenumber":"503",
    "addr:postcode":"54401",
    "addr:street":"S 22Nd Ave",
    "iso:country":"US",
    "sg:address":"503 S 22nd Ave",
    "sg:city":"Wausau",
    "sg:classifiers":[
        {
            "category":"Organizations",
            "subcategory":"Community Association",
            "type":"Services"
        }
    ],
    "sg:phone":"+1 715 845 1315",
    "sg:postcode":"54401",
    "sg:province":"WI",
    "wof:name":"Disabled American Veterans",
    "wof:placetype":"venue"
},
  "geometry": {"coordinates":[-89.663197,44.957362],"type":"Point"}
}