{
  "type": "Feature",
  "properties": {
    "addr:full":"211 Town Rd Columbus WI 53925",
    "addr:housenumber":"211",
    "addr:postcode":"53925",
    "addr:street":"Town Rd",
    "iso:country":"US",
    "sg:address":"211 Town Rd",
    "sg:city":"Columbus",
    "sg:classifiers":[
        {
            "category":"Manufacturing",
            "subcategory":"Pet Food",
            "type":"Manufacturing & Wholesale Goods"
        }
    ],
    "sg:phone":"+1 920 623 3385",
    "sg:postcode":"53925",
    "sg:province":"WI",
    "sg:tags":[
        "feed"
    ],
    "wof:name":"Cenex Land O'Lakes",
    "wof:placetype":"venue"
},
  "geometry": {"coordinates":[-89.023809,43.34499],"type":"Point"}
}