{
  "type": "Feature",
  "properties": {
    "iso:country":"US",
    "sg:address":"614 School Pl",
    "sg:city":"West Bend",
    "sg:classifiers":[
        {
            "category":"Education",
            "subcategory":"School",
            "type":"Public Place"
        }
    ],
    "sg:phone":"+1 262 335 5510",
    "sg:postcode":"53090",
    "sg:province":"WI",
    "sg:website":"www.west-bend.k12.wi.us",
    "wof:name":"Barton Elementary School",
    "wof:placetype":"venue"
},
  "geometry": {"coordinates":[-88.186476,43.443014],"type":"Point"}
}