{
  "type": "Feature",
  "properties": {
    "iso:country":"US",
    "sg:address":"10680 State Hwy 33",
    "sg:city":"Baraboo",
    "sg:classifiers":[
        {
            "category":"Autos & Motor Vehicles",
            "subcategory":"Recreational Vehicle Sales",
            "type":"Retail Goods"
        }
    ],
    "sg:phone":"+1 608 524 2976",
    "sg:postcode":"53913",
    "sg:province":"WI",
    "sg:tags":[
        "parts",
        "trailer"
    ],
    "wof:name":"J & S Trailers",
    "wof:placetype":"venue"
},
  "geometry": {"coordinates":[-89.790072,43.514627],"type":"Point"}
}