{
  "type": "Feature",
  "properties": {
    "iso:country":"US",
    "sg:address":"602 W Vliet St",
    "sg:city":"Milwaukee",
    "sg:classifiers":[
        {
            "category":"Social Services",
            "subcategory":"Child Care",
            "type":"Services"
        }
    ],
    "sg:phone":"+1 414 765 1119",
    "sg:postcode":"53212",
    "sg:province":"WI",
    "wof:name":"Day Carl's Care",
    "wof:placetype":"venue"
},
  "geometry": {"coordinates":[-87.91882,43.048481],"type":"Point"}
}