{
  "type": "Feature",
  "properties": {
    "iso:country":"US",
    "sg:address":"208 N 7th St",
    "sg:city":"Waterford",
    "sg:classifiers":[
        {
            "category":"Retail",
            "subcategory":"Laundry & Dry Cleaning",
            "type":"Services"
        }
    ],
    "sg:phone":"+1 262 534 7272",
    "sg:postcode":"53185",
    "sg:province":"WI",
    "sg:tags":[
        "cleaners",
        "rug",
        "carpet"
    ],
    "wof:name":"Shroat's Carpet Cleaning",
    "wof:placetype":"venue"
},
  "geometry": {"coordinates":[-88.201512,42.763894],"type":"Point"}
}