{
  "type": "Feature",
  "properties": {
    "addr:full":"700 Regent St Madison WI 53715",
    "addr:housenumber":"700",
    "addr:postcode":"53715",
    "addr:street":"Regent St",
    "iso:country":"US",
    "sg:address":"700 Regent St",
    "sg:city":"Madison",
    "sg:classifiers":[
        {
            "category":"Professional",
            "subcategory":"Advertising",
            "type":"Services"
        }
    ],
    "sg:phone":"+1 608 284 1284",
    "sg:postcode":"53715",
    "sg:province":"WI",
    "sg:tags":[
        "agency"
    ],
    "wof:name":"Advisory Profiles",
    "wof:placetype":"venue"
},
  "geometry": {"coordinates":[-89.39645899999999,43.067461],"type":"Point"}
}