{
  "type": "Feature",
  "properties": {
    "iso:country":"US",
    "sg:address":"896 US Hwy 14",
    "sg:city":"Readstown",
    "sg:classifiers":[
        {
            "category":"Food & Beverages",
            "subcategory":"Liquor & Beverages",
            "type":"Retail Goods"
        }
    ],
    "sg:phone":"+1 608 629 5717",
    "sg:postcode":"54652",
    "sg:province":"WI",
    "sg:tags":[
        "convenience",
        "laundromat",
        "store"
    ],
    "wof:name":"Kickapoo Kwik Stop Inc",
    "wof:placetype":"venue"
},
  "geometry": {"coordinates":[-90.74825800000001,43.444384],"type":"Point"}
}