{
  "type": "Feature",
  "properties": {
    "iso:country":"US",
    "sg:address":"6310 240th Ave",
    "sg:city":"Salem",
    "sg:classifiers":[
        {
            "category":"Manufacturing",
            "subcategory":"Retail Goods",
            "type":"Manufacturing & Wholesale Goods"
        }
    ],
    "sg:phone":"+1 262 843 4616",
    "sg:postcode":"53168",
    "sg:province":"WI",
    "sg:tags":[
        "product",
        "mfg"
    ],
    "wof:name":"Alcalay Industries Inc",
    "wof:placetype":"venue"
},
  "geometry": {"coordinates":[-88.100076,42.579996],"type":"Point"}
}