{
  "type": "Feature",
  "properties": {
    "iso:country":"US",
    "sg:address":"813 Main St",
    "sg:city":"Union Grove",
    "sg:classifiers":[
        {
            "category":"Professional",
            "subcategory":"Lawyer & Legal Services",
            "type":"Services"
        }
    ],
    "sg:phone":"+1 262 878 4007",
    "sg:postcode":"53182",
    "sg:province":"WI",
    "sg:tags":[
        "attorney"
    ],
    "wof:name":"Koss Law Offices",
    "wof:placetype":"venue"
},
  "geometry": {"coordinates":[-88.051818,42.689936],"type":"Point"}
}