{
  "type": "Feature",
  "properties": {
    "iso:country":"US",
    "sg:address":"111 Hammond St",
    "sg:city":"Randolph",
    "sg:classifiers":[
        {
            "category":"Building & Trades",
            "subcategory":"Construction",
            "type":"Services"
        }
    ],
    "sg:phone":"+1 920 326 3836",
    "sg:postcode":"53956",
    "sg:province":"WI",
    "sg:tags":[
        "contractor"
    ],
    "wof:name":"Katsma Plastering",
    "wof:placetype":"venue"
},
  "geometry": {"coordinates":[-89.005173,43.543971],"type":"Point"}
}