{
  "type": "Feature",
  "properties": {
    "iso:country":"US",
    "sg:address":"2580 Washington Ave",
    "sg:city":"Plover",
    "sg:classifiers":[
        {
            "category":"Personal",
            "subcategory":"Beauty Salon",
            "type":"Services"
        }
    ],
    "sg:phone":"+1 715 341 8006",
    "sg:postcode":"54467",
    "sg:province":"WI",
    "sg:tags":[
        "shop"
    ],
    "wof:name":"Beach Side Tanning",
    "wof:placetype":"venue"
},
  "geometry": {"coordinates":[-89.53982499999999,44.457933],"type":"Point"}
}