{
  "type": "Feature",
  "properties": {
    "addr:full":"400 Cameron St Eau Claire WI 54703",
    "addr:housenumber":"400",
    "addr:postcode":"54703",
    "addr:street":"Cameron St",
    "iso:country":"US",
    "sg:address":"400 Cameron St",
    "sg:city":"Eau Claire",
    "sg:classifiers":[
        {
            "category":"Education",
            "subcategory":"School",
            "type":"Public Place"
        }
    ],
    "sg:phone":"+1 715 839 2816",
    "sg:postcode":"54703",
    "sg:province":"WI",
    "wof:name":"Lincoln Elementary School",
    "wof:placetype":"venue"
},
  "geometry": {"coordinates":[-91.513548,44.816354],"type":"Point"}
}