{
  "type": "Feature",
  "properties": {
    "iso:country":"US",
    "sg:address":"408 Highland Dr",
    "sg:city":"Grafton",
    "sg:classifiers":[
        {
            "category":"Social Services",
            "subcategory":"Adult Care",
            "type":"Services"
        }
    ],
    "sg:phone":"+1 262 375 2460",
    "sg:postcode":"53024",
    "sg:province":"WI",
    "sg:tags":[
        "residential"
    ],
    "wof:name":"Highland Home",
    "wof:placetype":"venue"
},
  "geometry": {"coordinates":[-87.960228,43.315004],"type":"Point"}
}