{
  "type": "Feature",
  "properties": {
    "addr:full":"300 Clark St Brandon WI 53959",
    "addr:housenumber":"300",
    "addr:postcode":"53959",
    "addr:street":"Clark St",
    "iso:country":"US",
    "sg:address":"300 Clark St",
    "sg:city":"Brandon",
    "sg:classifiers":[
        {
            "category":"Manufacturing",
            "subcategory":"Tools & Machinery",
            "type":"Manufacturing & Wholesale Goods"
        }
    ],
    "sg:phone":"+1 920 346 8205",
    "sg:postcode":"53959",
    "sg:province":"WI",
    "sg:tags":[
        "food",
        "process",
        "mfg"
    ],
    "wof:name":"Stainless Mfg & Design",
    "wof:placetype":"venue"
},
  "geometry": {"coordinates":[-90.018559,43.531465],"type":"Point"}
}