{
  "type": "Feature",
  "properties": {
    "iso:country":"US",
    "sg:address":"50525 Oak Grove Rd",
    "sg:city":"Osseo",
    "sg:classifiers":[
        {
            "category":"Food & Beverages",
            "subcategory":"Liquor & Beverages",
            "type":"Retail Goods"
        }
    ],
    "sg:phone":"+1 715 597 3194",
    "sg:postcode":"54758",
    "sg:province":"WI",
    "wof:name":"Loft Store",
    "wof:placetype":"venue"
},
  "geometry": {"coordinates":[-91.20009,44.576788],"type":"Point"}
}