{
  "type": "Feature",
  "properties": {
    "iso:country":"US",
    "sg:address":"507 N Main St",
    "sg:city":"Fond Du Lac",
    "sg:classifiers":[
        {
            "category":"Bars & Pubs",
            "type":"Food & Drink"
        }
    ],
    "sg:phone":"+1 920 922 1788",
    "sg:postcode":"54935",
    "sg:province":"WI",
    "wof:name":"Cheers",
    "wof:placetype":"venue"
},
  "geometry": {"coordinates":[-88.446362,43.794166],"type":"Point"}
}