{
  "type": "Feature",
  "properties": {
    "iso:country":"US",
    "sg:address":"6556 N 91st St",
    "sg:city":"Milwaukee",
    "sg:classifiers":[
        {
            "category":"Building & Trades",
            "subcategory":"Plumbing",
            "type":"Services"
        }
    ],
    "sg:phone":"+1 414 358 1679",
    "sg:postcode":"53224",
    "sg:province":"WI",
    "sg:tags":[
        "heating",
        "contractor"
    ],
    "wof:name":"Kummer's Heating & Air Cond",
    "wof:placetype":"venue"
},
  "geometry": {"coordinates":[-88.025308,43.1378],"type":"Point"}
}