{
  "type": "Feature",
  "properties": {
    "iso:country":"US",
    "sg:address":"2418 Crossroads Dr",
    "sg:city":"Madison",
    "sg:classifiers":[
        {
            "category":"Utilities",
            "subcategory":"Telephone",
            "type":"Services"
        }
    ],
    "sg:phone":"+1 608 241 4799",
    "sg:postcode":"53718",
    "sg:province":"WI",
    "sg:tags":[
        "company"
    ],
    "wof:name":"Telecorp Inc",
    "wof:placetype":"venue"
},
  "geometry": {"coordinates":[-89.290271,43.131736],"type":"Point"}
}