{
  "type": "Feature",
  "properties": {
    "iso:country":"US",
    "sg:address":"1420 Belknap St",
    "sg:city":"Superior",
    "sg:classifiers":[
        {
            "category":"Personal",
            "type":"Services"
        },
        {
            "category":"Sports & Exercise",
            "subcategory":"Gym",
            "type":"Entertainment"
        },
        {
            "category":"Health Services",
            "subcategory":"Health Practitioner",
            "type":"Services"
        },
        {
            "category":"Arena",
            "subcategory":"Sports Club",
            "type":"Entertainment"
        }
    ],
    "sg:phone":"+1 800 615 7352",
    "sg:postcode":"54880",
    "sg:province":"WI",
    "sg:tags":[
        "control",
        "trainer",
        "weight",
        "consultant",
        "program",
        "fitness",
        "physical"
    ],
    "sg:website":"http://duluth.citysearch.com/profile/external/35149059/superior_wi/curves.html?publisher=yellowpages&reference_id=1&placement=ypwebsitemip",
    "wof:name":"Curves",
    "wof:placetype":"venue"
},
  "geometry": {"coordinates":[-92.09823299999999,46.720631],"type":"Point"}
}