{
  "type": "Feature",
  "properties": {
    "iso:country":"US",
    "sg:address":"4926 Co Rd G",
    "sg:city":"Mauston",
    "sg:classifiers":[
        {
            "category":"Travel",
            "subcategory":"Hotels & Motels",
            "type":"Entertainment"
        }
    ],
    "sg:phone":"+1 608 847 7286",
    "sg:postcode":"53948",
    "sg:province":"WI",
    "sg:tags":[
        "operation"
    ],
    "wof:name":"Wells Lakeside Cottages",
    "wof:placetype":"venue"
},
  "geometry": {"coordinates":[-90.01665800000001,43.897689],"type":"Point"}
}