{
  "type": "Feature",
  "properties": {
    "iso:country":"US",
    "sg:address":"510 Market Ave",
    "sg:city":"Port Edwards",
    "sg:classifiers":[
        {
            "category":"Building & Trades",
            "subcategory":"Construction",
            "type":"Services"
        }
    ],
    "sg:phone":"+1 715 887 2372",
    "sg:postcode":"54469",
    "sg:province":"WI",
    "sg:tags":[
        "hanging",
        "contractor"
    ],
    "wof:name":"J T Wallpapering",
    "wof:placetype":"venue"
},
  "geometry": {"coordinates":[-89.866393,44.342967],"type":"Point"}
}