{
  "type": "Feature",
  "properties": {
    "iso:country":"US",
    "sg:address":"5304 42nd Ave",
    "sg:city":"Kenosha",
    "sg:classifiers":[
        {
            "category":"Building & Trades",
            "subcategory":"Construction",
            "type":"Services"
        }
    ],
    "sg:phone":"+1 262 657 5049",
    "sg:postcode":"53144",
    "sg:province":"WI",
    "sg:tags":[
        "concrete",
        "contractor"
    ],
    "wof:name":"Witt Concrete Construction LLC",
    "wof:placetype":"venue"
},
  "geometry": {"coordinates":[-87.85980600000001,42.585677],"type":"Point"}
}