{
  "type": "Feature",
  "properties": {
    "iso:country":"US",
    "sg:address":"407 S Church St",
    "sg:city":"Watertown",
    "sg:classifiers":[
        {
            "category":"Manufacturing",
            "subcategory":"Tools & Machinery",
            "type":"Manufacturing & Wholesale Goods"
        }
    ],
    "sg:phone":"+1 920 261 3504",
    "sg:postcode":"53094",
    "sg:province":"WI",
    "sg:tags":[
        "machine",
        "vending",
        "mfg"
    ],
    "wof:name":"Dandy Vending",
    "wof:placetype":"venue"
},
  "geometry": {"coordinates":[-88.729139,43.191436],"type":"Point"}
}