{
  "type": "Feature",
  "properties": {
    "iso:country":"US",
    "sg:address":"11251 Industrial Ln",
    "sg:city":"Elcho",
    "sg:classifiers":[
        {
            "category":"Manufacturing",
            "subcategory":"Metals",
            "type":"Manufacturing & Wholesale Goods"
        }
    ],
    "sg:phone":"+1 715 275 3155",
    "sg:postcode":"54428",
    "sg:province":"WI",
    "wof:name":"Pro-Weld Fabricating",
    "wof:placetype":"venue"
},
  "geometry": {"coordinates":[-89.192542,45.437011],"type":"Point"}
}