{
  "type": "Feature",
  "properties": {
    "iso:country":"US",
    "sg:address":"1815 Illinois Ave",
    "sg:city":"New Holstein",
    "sg:classifiers":[
        {
            "category":"Personal",
            "subcategory":"Shoe Repair & Shine",
            "type":"Services"
        }
    ],
    "sg:phone":"+1 920 898 5046",
    "sg:postcode":"53061",
    "sg:province":"WI",
    "sg:tags":[
        "leather"
    ],
    "wof:name":"Weber Shoe Service",
    "wof:placetype":"venue"
},
  "geometry": {"coordinates":[-88.089811,43.94863],"type":"Point"}
}