{
  "type": "Feature",
  "properties": {
    "iso:country":"US",
    "sg:address":"2093 Back Forty Rd",
    "sg:city":"Lodi",
    "sg:classifiers":[
        {
            "category":"Restaurant",
            "type":"Food & Drink"
        }
    ],
    "sg:phone":"+1 608 592 5400",
    "sg:postcode":"53555",
    "sg:province":"WI",
    "sg:tags":[
        "shop",
        "submarine",
        "sandwich"
    ],
    "wof:name":"Subway",
    "wof:placetype":"venue"
},
  "geometry": {"coordinates":[-89.563271,43.349854],"type":"Point"}
}