{
  "type": "Feature",
  "properties": {
    "iso:country":"US",
    "sg:address":"815 S Concord Rd",
    "sg:city":"Oconomowoc",
    "sg:classifiers":[
        {
            "category":"Social Services",
            "subcategory":"Child Care",
            "type":"Services"
        }
    ],
    "sg:phone":"+1 262 567 7334",
    "sg:postcode":"53066",
    "sg:province":"WI",
    "sg:tags":[
        "day"
    ],
    "wof:name":"Hearts & Hands Christian Pre K",
    "wof:placetype":"venue"
},
  "geometry": {"coordinates":[-88.517063,43.102401],"type":"Point"}
}