{
  "type": "Feature",
  "properties": {
    "addr:full":"7702 Sinawa Rd Valders WI 54245",
    "addr:housenumber":"7702",
    "addr:postcode":"54245",
    "addr:street":"Sinawa Rd",
    "iso:country":"US",
    "sg:address":"7702 Sinawa Rd",
    "sg:city":"Valders",
    "sg:classifiers":[
        {
            "category":"Manufacturing",
            "subcategory":"Lumber",
            "type":"Manufacturing & Wholesale Goods"
        }
    ],
    "sg:phone":"+1 920 758 2328",
    "sg:postcode":"54245",
    "sg:province":"WI",
    "sg:tags":[
        "forestry"
    ],
    "wof:name":"Wagner Woods & Wildlife",
    "wof:placetype":"venue"
},
  "geometry": {"coordinates":[-87.882006,44.00599],"type":"Point"}
}