{
  "type": "Feature",
  "properties": {
    "addr:full":"311 S Main St Granton WI 54436",
    "addr:housenumber":"311",
    "addr:postcode":"54436",
    "addr:street":"S Main St",
    "iso:country":"US",
    "sg:address":"311 S Main St",
    "sg:city":"Granton",
    "sg:classifiers":[
        {
            "category":"Building & Trades",
            "subcategory":"Plumbing",
            "type":"Services"
        }
    ],
    "sg:phone":"+1 715 238 7628",
    "sg:postcode":"54436",
    "sg:province":"WI",
    "sg:tags":[
        "heating",
        "contractor"
    ],
    "wof:name":"Kuehn's Appliance Svc",
    "wof:placetype":"venue"
},
  "geometry": {"coordinates":[-90.46132799999999,44.586673],"type":"Point"}
}