{
  "type": "Feature",
  "properties": {
    "iso:country":"US",
    "sg:address":"615 N Park St",
    "sg:city":"Grantsburg",
    "sg:classifiers":[
        {
            "category":"Manufacturing",
            "subcategory":"Tools & Machinery",
            "type":"Manufacturing & Wholesale Goods"
        }
    ],
    "sg:phone":"+1 715 463 5071",
    "sg:postcode":"54840",
    "sg:province":"WI",
    "sg:tags":[
        "machine",
        "shop"
    ],
    "wof:name":"MPC Inc",
    "wof:placetype":"venue"
},
  "geometry": {"coordinates":[-92.68732,45.78621],"type":"Point"}
}