{
  "type": "Feature",
  "properties": {
    "iso:country":"US",
    "sg:address":"611 E Albert St",
    "sg:city":"Portage",
    "sg:classifiers":[
        {
            "category":"Social Services",
            "subcategory":"Adult Care",
            "type":"Services"
        }
    ],
    "sg:phone":"+1 608 742 2147",
    "sg:postcode":"53901",
    "sg:province":"WI",
    "sg:tags":[
        "home",
        "residential"
    ],
    "wof:name":"Edeleweiss Gardens",
    "wof:placetype":"venue"
},
  "geometry": {"coordinates":[-89.446489,43.549408],"type":"Point"}
}