{
  "type": "Feature",
  "properties": {
    "addr:full":"1 Science Ct Madison WI 53711",
    "addr:postcode":"53711",
    "addr:street":"Science Ct",
    "iso:country":"US",
    "sg:address":"1 Science Ct",
    "sg:city":"Madison",
    "sg:classifiers":[
        {
            "category":"Professional",
            "subcategory":"Research",
            "type":"Services"
        }
    ],
    "sg:phone":"+1 608 218 7600",
    "sg:postcode":"53711",
    "sg:province":"WI",
    "sg:tags":[
        "biomedical"
    ],
    "wof:name":"Nimblegen Systems Inc",
    "wof:placetype":"venue"
},
  "geometry": {"coordinates":[-89.468119,43.059532],"type":"Point"}
}