{
  "type": "Feature",
  "properties": {
    "addr:full":"3370 Oak Grove Rd Waupun WI 53963",
    "addr:housenumber":"3370",
    "addr:postcode":"53963",
    "addr:street":"Oak Grove Rd",
    "iso:country":"US",
    "sg:address":"3370 Oak Grove Rd",
    "sg:city":"Waupun",
    "sg:classifiers":[
        {
            "category":"Freight",
            "type":"Transportation"
        }
    ],
    "sg:phone":"+1 920 346 5803",
    "sg:postcode":"53963",
    "sg:province":"WI",
    "sg:tags":[
        "operator",
        "local",
        "trucking"
    ],
    "wof:name":"Mitch Redeker Trucking LLC",
    "wof:placetype":"venue"
},
  "geometry": {"coordinates":[-88.815315,43.671064],"type":"Point"}
}