{
  "type": "Feature",
  "properties": {
    "iso:country":"US",
    "sg:address":"444 Evans Dr",
    "sg:city":"Evansville",
    "sg:classifiers":[
        {
            "category":"Building & Trades",
            "subcategory":"Construction",
            "type":"Services"
        }
    ],
    "sg:phone":"+1 608 882 6296",
    "sg:postcode":"53536",
    "sg:province":"WI",
    "sg:tags":[
        "house"
    ],
    "wof:name":"D & S Builders LLC",
    "wof:placetype":"venue"
},
  "geometry": {"coordinates":[-89.315004,42.774169],"type":"Point"}
}