{
  "type": "Feature",
  "properties": {
    "iso:country":"US",
    "sg:address":"17314 Maple Rd",
    "sg:city":"Wittenberg",
    "sg:classifiers":[
        {
            "category":"Farming",
            "subcategory":"Dairy Farm",
            "type":"Manufacturing & Wholesale Goods"
        }
    ],
    "sg:phone":"+1 715 253 2378",
    "sg:postcode":"54499",
    "sg:province":"WI",
    "wof:name":"J L Boreen Farms Inc",
    "wof:placetype":"venue"
},
  "geometry": {"coordinates":[-89.117722,44.848068],"type":"Point"}
}