{
  "type": "Feature",
  "properties": {
    "iso:country":"US",
    "sg:address":"8890 Forest Ln",
    "sg:city":"Westboro",
    "sg:classifiers":[
        {
            "category":"Travel",
            "subcategory":"Campground",
            "type":"Entertainment"
        }
    ],
    "sg:phone":"+1 715 427 5241",
    "sg:postcode":"54490",
    "sg:province":"WI",
    "sg:tags":[
        "camp",
        "christian"
    ],
    "wof:name":"Camp Forest Springs Inc",
    "wof:placetype":"venue"
},
  "geometry": {"coordinates":[-90.220826,45.357445],"type":"Point"}
}