{
  "type": "Feature",
  "properties": {
    "iso:country":"US",
    "sg:address":"635 Meadow Dr",
    "sg:city":"Green Lake",
    "sg:classifiers":[
        {
            "category":"Professional",
            "subcategory":"Accounting & Tax Preparation",
            "type":"Services"
        }
    ],
    "sg:phone":"+1 920 748 6247",
    "sg:postcode":"54941",
    "sg:province":"WI",
    "wof:name":"Ken Koffarnus",
    "wof:placetype":"venue"
},
  "geometry": {"coordinates":[-88.913773,43.854499],"type":"Point"}
}