{
  "type": "Feature",
  "properties": {
    "iso:country":"US",
    "sg:address":"507 S 8th St",
    "sg:city":"Sheboygan",
    "sg:classifiers":[
        {
            "category":"Professional",
            "subcategory":"Accounting & Tax Preparation",
            "type":"Services"
        }
    ],
    "sg:phone":"+1 920 458 3500",
    "sg:postcode":"53081",
    "sg:province":"WI",
    "sg:tags":[
        "accountant"
    ],
    "wof:name":"Wilford W Elliott LTD",
    "wof:placetype":"venue"
},
  "geometry": {"coordinates":[-87.712862,43.749044],"type":"Point"}
}