{
  "type": "Feature",
  "properties": {
    "iso:country":"US",
    "sg:address":"217 E Wisconsin Ave",
    "sg:city":"Appleton",
    "sg:classifiers":[
        {
            "category":"Food & Beverages",
            "subcategory":"Candy",
            "type":"Retail Goods"
        }
    ],
    "sg:phone":"+1 920 733 6182",
    "sg:postcode":"54911",
    "sg:province":"WI",
    "sg:tags":[
        "confectionery"
    ],
    "sg:website":"www.wilmarchocolates.com",
    "wof:name":"Wilmar Chocolates",
    "wof:placetype":"venue"
},
  "geometry": {"coordinates":[-88.402939,44.272859],"type":"Point"}
}