{
  "type": "Feature",
  "properties": {
    "addr:full":"7535 Island Lake Rd Spooner WI 54801",
    "addr:housenumber":"7535",
    "addr:postcode":"54801",
    "addr:street":"Island Lake Rd",
    "iso:country":"US",
    "sg:address":"7535 Island Lake Rd",
    "sg:city":"Spooner",
    "sg:classifiers":[
        {
            "category":"Building & Trades",
            "subcategory":"Plumbing",
            "type":"Services"
        }
    ],
    "sg:phone":"+1 715 635 7243",
    "sg:postcode":"54801",
    "sg:province":"WI",
    "sg:tags":[
        "septic"
    ],
    "wof:name":"Badger Septic Svc",
    "wof:placetype":"venue"
},
  "geometry": {"coordinates":[-91.930919,45.900262],"type":"Point"}
}