{
  "type": "Feature",
  "properties": {
    "addr:full":"6982 US Hwy 45 Three Lakes WI 54562",
    "addr:housenumber":"6982",
    "addr:postcode":"54562",
    "addr:street":"Us Hwy 45",
    "iso:country":"US",
    "sg:address":"6982 US Hwy 45",
    "sg:city":"Three Lakes",
    "sg:classifiers":[
        {
            "category":"Travel",
            "subcategory":"Hotels & Motels",
            "type":"Entertainment"
        }
    ],
    "sg:phone":"+1 715 546 2443",
    "sg:postcode":"54562",
    "sg:province":"WI",
    "sg:tags":[
        "operation"
    ],
    "wof:name":"Triangle Motel",
    "wof:placetype":"venue"
},
  "geometry": {"coordinates":[-89.153423,45.796188],"type":"Point"}
}