{
  "type": "Feature",
  "properties": {
    "iso:country":"US",
    "sg:address":"1018 Oregon St",
    "sg:city":"Oshkosh",
    "sg:classifiers":[
        {
            "category":"Personal",
            "subcategory":"Beauty Salon",
            "type":"Services"
        }
    ],
    "sg:phone":"+1 920 303 9730",
    "sg:postcode":"54902",
    "sg:province":"WI",
    "sg:tags":[
        "shop"
    ],
    "wof:name":"Shannon Helf",
    "wof:placetype":"venue"
},
  "geometry": {"coordinates":[-88.542433,44.008934],"type":"Point"}
}