{
  "type": "Feature",
  "properties": {
    "iso:country":"US",
    "sg:address":"275 W Wisconsin Ave",
    "sg:city":"Milwaukee",
    "sg:classifiers":[
        {
            "category":"Utilities",
            "subcategory":"Mobile Phone",
            "type":"Services"
        },
        {
            "category":"Shopping",
            "subcategory":"Mobile Phones",
            "type":"Retail Goods"
        },
        {
            "category":"Utilities",
            "subcategory":"Telephone",
            "type":"Services"
        },
        {
            "category":"Manufacturing",
            "subcategory":"Electronics",
            "type":"Manufacturing & Wholesale Goods"
        }
    ],
    "sg:phone":"+1 414 347 0479",
    "sg:postcode":"53203",
    "sg:province":"WI",
    "sg:tags":[
        "telecommunications-equipment",
        "supply",
        "communication",
        "system",
        "equipment",
        "cellular"
    ],
    "sg:website":"http://www.uscellular.com",
    "wof:name":"US Cellular-WPI-Grand Avenue Mall",
    "wof:placetype":"venue"
},
  "geometry": {"coordinates":[-87.914169,43.038795],"type":"Point"}
}