{
  "type": "Feature",
  "properties": {
    "iso:country":"US",
    "sg:address":"738 Hickory Point Ln",
    "sg:city":"Amery",
    "sg:classifiers":[
        {
            "category":"Travel",
            "subcategory":"Campground",
            "type":"Entertainment"
        }
    ],
    "sg:phone":"+1 715 268 8434",
    "sg:postcode":"54001",
    "sg:province":"WI",
    "sg:tags":[
        "camp"
    ],
    "sg:website":"www.campwapo.org",
    "wof:name":"Lake Wapogasset Lutheran Bible",
    "wof:placetype":"venue"
},
  "geometry": {"coordinates":[-92.412894,45.319927],"type":"Point"}
}