{
  "type": "Feature",
  "properties": {
    "iso:country":"US",
    "sg:address":"1346 State Hwy 73",
    "sg:city":"Edgerton",
    "sg:phone":"+1 608 884 4055",
    "sg:postcode":"53534",
    "sg:province":"WI",
    "sg:tags":[
        "farm",
        "soybean"
    ],
    "wof:name":"Kenneth Williams",
    "wof:placetype":"venue"
},
  "geometry": {"coordinates":[-89.060793,42.923554],"type":"Point"}
}