{
  "type": "Feature",
  "properties": {
    "iso:country":"US",
    "sg:address":"1731 N Central Ave",
    "sg:city":"Marshfield",
    "sg:classifiers":[
        {
            "category":"Insurance",
            "subcategory":"Hazard Insurance",
            "type":"Services"
        }
    ],
    "sg:phone":"+1 715 387 1736",
    "sg:postcode":"54449",
    "sg:province":"WI",
    "sg:tags":[
        "commercial",
        "business"
    ],
    "sg:website":"http://www.nikolaiins.com",
    "wof:name":"Nikolai Insurance",
    "wof:placetype":"venue"
},
  "geometry": {"coordinates":[-90.18437400000001,44.651514],"type":"Point"}
}