{
  "type": "Feature",
  "properties": {
    "addr:full":"120 Martin Ave Turtle Lake WI 54889",
    "addr:housenumber":"120",
    "addr:postcode":"54889",
    "addr:street":"Martin Ave",
    "iso:country":"US",
    "sg:address":"120 Martin Ave",
    "sg:city":"Turtle Lake",
    "sg:classifiers":[
        {
            "category":"Home & Garden",
            "subcategory":"Home Furnishings",
            "type":"Retail Goods"
        }
    ],
    "sg:phone":"+1 715 986 4030",
    "sg:postcode":"54889",
    "sg:province":"WI",
    "sg:tags":[
        "beveled",
        "glass",
        "ornamental"
    ],
    "sg:website":"www.glockesglass.com",
    "wof:name":"Glocke's Glass",
    "wof:placetype":"venue"
},
  "geometry": {"coordinates":[-92.140788,45.39535],"type":"Point"}
}