{
  "type": "Feature",
  "properties": {
    "iso:country":"US",
    "sg:address":"626 Ondossagon Way",
    "sg:city":"Madison",
    "sg:classifiers":[
        {
            "category":"Health Services",
            "subcategory":"Doctor",
            "type":"Services"
        }
    ],
    "sg:phone":"+1 608 232 1616",
    "sg:postcode":"53719",
    "sg:province":"WI",
    "sg:tags":[
        "physician",
        "surgeon",
        "medical"
    ],
    "sg:website":"www.aestheticskin.com",
    "wof:name":"Parfitt Facial Plastic Surgery",
    "wof:placetype":"venue"
},
  "geometry": {"coordinates":[-89.514319,43.048737],"type":"Point"}
}