{
  "type": "Feature",
  "properties": {
    "iso:country":"US",
    "sg:address":"8240 Mineral Point Rd",
    "sg:city":"Madison",
    "sg:classifiers":[
        {
            "category":"Bars & Pubs",
            "type":"Food & Drink"
        }
    ],
    "sg:phone":"+1 608 833 7033",
    "sg:postcode":"53719",
    "sg:province":"WI",
    "sg:tags":[
        "tavern"
    ],
    "wof:name":"Pauls Speedway Bar",
    "wof:placetype":"venue"
},
  "geometry": {"coordinates":[-89.523093,43.060477],"type":"Point"}
}