{
  "type": "Feature",
  "properties": {
    "addr:full":"2803 N 55th St Milwaukee WI 53210",
    "addr:housenumber":"2803",
    "addr:postcode":"53210",
    "addr:street":"N 55Th St",
    "iso:country":"US",
    "sg:address":"2803 N 55th St",
    "sg:city":"Milwaukee",
    "sg:classifiers":[
        {
            "category":"Wholesale",
            "subcategory":"Apparel",
            "type":"Manufacturing & Wholesale Goods"
        },
        {
            "category":"Shopping",
            "subcategory":"Shoes",
            "type":"Retail Goods"
        }
    ],
    "sg:phone":"+1 414 445 6515",
    "sg:postcode":"53210",
    "sg:province":"WI",
    "sg:tags":[
        "shoes-wholesale",
        "store",
        "manufacturer"
    ],
    "wof:name":"The Shoe Closet",
    "wof:placetype":"venue"
},
  "geometry": {"coordinates":[-87.98209300000001,43.069839],"type":"Point"}
}