{
  "type": "Feature",
  "properties": {
    "iso:country":"US",
    "sg:address":"126 E Division St",
    "sg:city":"Shawano",
    "sg:classifiers":[
        {
            "category":"Personal",
            "subcategory":"Tanning Parlor",
            "type":"Services"
        }
    ],
    "sg:phone":"+1 715 526 3266",
    "sg:postcode":"54166",
    "sg:province":"WI",
    "sg:tags":[
        "salon"
    ],
    "wof:name":"Island Tropics & Hair Design",
    "wof:placetype":"venue"
},
  "geometry": {"coordinates":[-88.60886499999999,44.780085],"type":"Point"}
}