{
  "type": "Feature",
  "properties": {
    "iso:country":"US",
    "sg:address":"1689 N Humboldt Ave",
    "sg:city":"Milwaukee",
    "sg:classifiers":[
        {
            "category":"Restaurant",
            "type":"Food & Drink"
        }
    ],
    "sg:phone":"+1 414 277 8447",
    "sg:postcode":"53202",
    "sg:province":"WI",
    "sg:tags":[
        "eating"
    ],
    "wof:name":"Italian Carretto",
    "wof:placetype":"venue"
},
  "geometry": {"coordinates":[-87.898217,43.051986],"type":"Point"}
}