{
  "type": "Feature",
  "properties": {
    "iso:country":"US",
    "sg:address":"1200 State Hwy 69",
    "sg:city":"New Glarus",
    "sg:classifiers":[
        {
            "category":"Travel",
            "subcategory":"Hotels & Motels",
            "type":"Entertainment"
        }
    ],
    "sg:phone":"+1 608 527 2138",
    "sg:postcode":"53574",
    "sg:province":"WI",
    "wof:name":"Swiss-Aire Motel",
    "wof:placetype":"venue"
},
  "geometry": {"coordinates":[-89.631226,42.808908],"type":"Point"}
}