{
  "type": "Feature",
  "properties": {
    "iso:country":"US",
    "sg:address":"3950 County Line Rd",
    "sg:city":"Rudolph",
    "sg:classifiers":[
        {
            "category":"Farming",
            "subcategory":"Dairy Farm",
            "type":"Manufacturing & Wholesale Goods"
        }
    ],
    "sg:phone":"+1 715 435 3462",
    "sg:postcode":"54475",
    "sg:province":"WI",
    "wof:name":"Eron Harold or Carol",
    "wof:placetype":"venue"
},
  "geometry": {"coordinates":[-89.757345,44.511543],"type":"Point"}
}