{
  "type": "Feature",
  "properties": {
    "addr:full":"735 S Cleveland St Shawano WI 54166",
    "addr:housenumber":"735",
    "addr:postcode":"54166",
    "addr:street":"S Cleveland St",
    "iso:country":"US",
    "sg:address":"735 S Cleveland St",
    "sg:city":"Shawano",
    "sg:classifiers":[
        {
            "category":"Building & Trades",
            "subcategory":"Construction",
            "type":"Services"
        }
    ],
    "sg:phone":"+1 715 524 3887",
    "sg:postcode":"54166",
    "sg:province":"WI",
    "sg:tags":[
        "house"
    ],
    "wof:name":"Quality Construction",
    "wof:placetype":"venue"
},
  "geometry": {"coordinates":[-88.597252,44.774832],"type":"Point"}
}