{
  "type": "Feature",
  "properties": {
    "addr:full":"6676 Lone Pine Rd Merrill WI 54452",
    "addr:housenumber":"6676",
    "addr:postcode":"54452",
    "addr:street":"Lone Pine Rd",
    "iso:country":"US",
    "sg:address":"6676 Lone Pine Rd",
    "sg:city":"Merrill",
    "sg:classifiers":[
        {
            "category":"Farming",
            "subcategory":"Dairy Farm",
            "type":"Manufacturing & Wholesale Goods"
        }
    ],
    "sg:phone":"+1 715 536 3494",
    "sg:postcode":"54452",
    "sg:province":"WI",
    "wof:name":"John Fehlberg",
    "wof:placetype":"venue"
},
  "geometry": {"coordinates":[-89.76528999999999,45.216999],"type":"Point"}
}