{
  "type": "Feature",
  "properties": {
    "iso:country":"US",
    "sg:address":"3675 S 16th St",
    "sg:city":"Milwaukee",
    "sg:classifiers":[
        {
            "category":"Professional",
            "subcategory":"Employment Agencies",
            "type":"Services"
        }
    ],
    "sg:phone":"+1 414 643 8123",
    "sg:postcode":"53221",
    "sg:province":"WI",
    "sg:tags":[
        "truck",
        "driver"
    ],
    "wof:name":"Galaxy Inc",
    "wof:placetype":"venue"
},
  "geometry": {"coordinates":[-87.933976,42.980651],"type":"Point"}
}