{
  "type": "Feature",
  "properties": {
    "addr:full":"10463 S Leisure Dr Hazelhurst WI 54531",
    "addr:housenumber":"10463",
    "addr:postcode":"54531",
    "addr:street":"S Leisure Dr",
    "iso:country":"US",
    "sg:address":"10463 S Leisure Dr",
    "sg:city":"Hazelhurst",
    "sg:classifiers":[
        {
            "category":"Professional",
            "type":"Services"
        }
    ],
    "sg:phone":"+1 715 358 6722",
    "sg:postcode":"54531",
    "sg:province":"WI",
    "sg:tags":[
        "establishment"
    ],
    "wof:name":"Crites & Assoc",
    "wof:placetype":"venue"
},
  "geometry": {"coordinates":[-89.767493,45.736517],"type":"Point"}
}