{
  "type": "Feature",
  "properties": {
    "iso:country":"US",
    "sg:address":"515 N Glenview Ave",
    "sg:city":"Milwaukee",
    "sg:classifiers":[
        {
            "category":"Wholesale",
            "subcategory":"Machinery & Supplies",
            "type":"Manufacturing & Wholesale Goods"
        }
    ],
    "sg:phone":"+1 414 607 1786",
    "sg:postcode":"53213",
    "sg:province":"WI",
    "sg:tags":[
        "pump"
    ],
    "wof:name":"Roto-Jet Pumps",
    "wof:placetype":"venue"
},
  "geometry": {"coordinates":[-88.015934,43.0368],"type":"Point"}
}