{
  "type": "Feature",
  "properties": {
    "iso:country":"US",
    "sg:address":"1593 10th St",
    "sg:city":"Plum City",
    "sg:classifiers":[
        {
            "category":"Farming",
            "subcategory":"Dairy Farm",
            "type":"Manufacturing & Wholesale Goods"
        }
    ],
    "sg:phone":"+1 715 647 3119",
    "sg:postcode":"54761",
    "sg:province":"WI",
    "sg:tags":[
        "beef",
        "feedlot",
        "cattle"
    ],
    "wof:name":"Steven Abel",
    "wof:placetype":"venue"
},
  "geometry": {"coordinates":[-92.134907,44.586565],"type":"Point"}
}