{
  "type": "Feature",
  "properties": {
    "iso:country":"US",
    "sg:address":"2 Stanton St",
    "sg:city":"Marinette",
    "sg:classifiers":[
        {
            "category":"Manufacturing",
            "subcategory":"Chemicals & Compounds",
            "type":"Manufacturing & Wholesale Goods"
        }
    ],
    "sg:phone":"+1 715 735 8266",
    "sg:postcode":"54143",
    "sg:province":"WI",
    "sg:tags":[
        "mfg"
    ],
    "wof:name":"Chemdesign Corporation",
    "wof:placetype":"venue"
},
  "geometry": {"coordinates":[-87.615432,45.098122],"type":"Point"}
}