{
  "type": "Feature",
  "properties": {
    "iso:country":"US",
    "sg:address":"340 E Washington St",
    "sg:city":"Slinger",
    "sg:classifiers":[
        {
            "category":"Health Services",
            "subcategory":"Doctor",
            "type":"Services"
        }
    ],
    "sg:phone":"+1 262 644 6921",
    "sg:postcode":"53086",
    "sg:province":"WI",
    "sg:tags":[
        "dentist"
    ],
    "wof:name":"Donald F Crego Jr DDS",
    "wof:placetype":"venue"
},
  "geometry": {"coordinates":[-88.280906,43.331609],"type":"Point"}
}