{
  "type": "Feature",
  "properties": {
    "iso:country":"US",
    "sg:address":"2363 S 102nd St",
    "sg:city":"Milwaukee",
    "sg:classifiers":[
        {
            "category":"Professional",
            "subcategory":"Employment Agencies",
            "type":"Services"
        }
    ],
    "sg:phone":"+1 414 431 0702",
    "sg:postcode":"53227",
    "sg:province":"WI",
    "sg:tags":[
        "opportunity"
    ],
    "wof:name":"Premiere Medical Staffing Svc",
    "wof:placetype":"venue"
},
  "geometry": {"coordinates":[-88.04075400000001,43.001696],"type":"Point"}
}