{
  "type": "Feature",
  "properties": {
    "addr:full":"7426 Co Rd H Fremont WI 54940",
    "addr:housenumber":"7426",
    "addr:postcode":"54940",
    "addr:street":"Co Rd H",
    "iso:country":"US",
    "sg:address":"7426 Co Rd H",
    "sg:city":"Fremont",
    "sg:classifiers":[
        {
            "category":"Travel",
            "subcategory":"Hotels & Motels",
            "type":"Entertainment"
        },
        {
            "category":"Bars & Pubs",
            "type":"Food & Drink"
        }
    ],
    "sg:phone":"+1 920 446 3295",
    "sg:postcode":"54940",
    "sg:province":"WI",
    "sg:tags":[
        "resort",
        "drinking"
    ],
    "wof:name":"Brefeld's Pine Grove Resort",
    "wof:placetype":"venue"
},
  "geometry": {"coordinates":[-88.87530700000001,44.160627],"type":"Point"}
}