{
  "type": "Feature",
  "properties": {
    "iso:country":"US",
    "sg:address":"1044 9th St",
    "sg:city":"Green Bay",
    "sg:classifiers":[
        {
            "category":"Professional",
            "subcategory":"Art Services",
            "type":"Services"
        }
    ],
    "sg:phone":"+1 920 491 1108",
    "sg:postcode":"54304",
    "sg:province":"WI",
    "sg:tags":[
        "artist"
    ],
    "wof:name":"Unique Shoppe",
    "wof:placetype":"venue"
},
  "geometry": {"coordinates":[-88.046899,44.508276],"type":"Point"}
}