{
  "type": "Feature",
  "properties": {
    "addr:full":"8428 W Silver Spring Dr Milwaukee WI 53225",
    "addr:housenumber":"8428",
    "addr:postcode":"53225",
    "addr:street":"W Silver Spring Dr",
    "iso:country":"US",
    "sg:address":"8428 W Silver Spring Dr",
    "sg:city":"Milwaukee",
    "sg:classifiers":[
        {
            "category":"Shopping",
            "subcategory":"Pharmacy",
            "type":"Retail Goods"
        }
    ],
    "sg:phone":"+1 414 463 5600",
    "sg:postcode":"53225",
    "sg:province":"WI",
    "sg:website":"www.healthcare.org",
    "wof:name":"Aurora Pharmacy",
    "wof:placetype":"venue"
},
  "geometry": {"coordinates":[-88.014043,43.119562],"type":"Point"}
}