{
  "type": "Feature",
  "properties": {
    "iso:country":"US",
    "sg:address":"281 Commerce St",
    "sg:city":"Belgium",
    "sg:classifiers":[
        {
            "category":"Manufacturing",
            "subcategory":"Food",
            "type":"Manufacturing & Wholesale Goods"
        }
    ],
    "sg:phone":"+1 262 285 4800",
    "sg:postcode":"53050",
    "sg:province":"WI",
    "sg:tags":[
        "popcorn",
        "supply"
    ],
    "sg:website":"www.popcornlovers.com",
    "wof:name":"Fireworks Popcorn Co",
    "wof:placetype":"venue"
},
  "geometry": {"coordinates":[-88.551964,43.492602],"type":"Point"}
}