{
  "type": "Feature",
  "properties": {
    "iso:country":"US",
    "sg:address":"4131 W Martin Dr",
    "sg:city":"Milwaukee",
    "sg:classifiers":[
        {
            "category":"Shopping",
            "subcategory":"Computers & Home Electronics",
            "type":"Retail Goods"
        }
    ],
    "sg:phone":"+1 414 345 9779",
    "sg:postcode":"53208",
    "sg:province":"WI",
    "sg:tags":[
        "equipment",
        "dealer"
    ],
    "wof:name":"Greater Milwaukee Computer",
    "wof:placetype":"venue"
},
  "geometry": {"coordinates":[-87.96784100000001,43.044978],"type":"Point"}
}