{
  "type": "Feature",
  "properties": {
    "iso:country":"US",
    "sg:address":"3950 Highland Shore Ln",
    "sg:city":"Oshkosh",
    "sg:classifiers":[
        {
            "category":"Professional",
            "subcategory":"Secretarial Services",
            "type":"Services"
        }
    ],
    "sg:phone":"+1 920 303 1055",
    "sg:postcode":"54904",
    "sg:province":"WI",
    "sg:tags":[
        "reporting",
        "court"
    ],
    "wof:name":"Larson Secretarial Services",
    "wof:placetype":"venue"
},
  "geometry": {"coordinates":[-88.628547,44.04895],"type":"Point"}
}