{
  "type": "Feature",
  "properties": {
    "iso:country":"US",
    "sg:address":"722 State St",
    "sg:city":"Ripon",
    "sg:classifiers":[
        {
            "category":"Building & Trades",
            "subcategory":"Landscaping Services",
            "type":"Services"
        }
    ],
    "sg:phone":"+1 920 748 3421",
    "sg:postcode":"54971",
    "sg:province":"WI",
    "wof:name":"J H Landscaping",
    "wof:placetype":"venue"
},
  "geometry": {"coordinates":[-88.85023,43.845758],"type":"Point"}
}