{
  "type": "Feature",
  "properties": {
    "iso:country":"US",
    "sg:address":"2834 Agriculture Dr",
    "sg:city":"Madison",
    "sg:classifiers":[
        {
            "category":"Retail",
            "subcategory":"Laundry & Dry Cleaning",
            "type":"Services"
        }
    ],
    "sg:phone":"+1 608 222 3731",
    "sg:postcode":"53718",
    "sg:province":"WI",
    "sg:tags":[
        "cleaners",
        "rug",
        "carpet"
    ],
    "wof:name":"Stanley Steemer Carpet Cleaner",
    "wof:placetype":"venue"
},
  "geometry": {"coordinates":[-89.292489,43.057998],"type":"Point"}
}