{
  "type": "Feature",
  "properties": {
    "addr:full":"10344 Horseshoe Rd Tomahawk WI 54487",
    "addr:housenumber":"10344",
    "addr:postcode":"54487",
    "addr:street":"Horseshoe Rd",
    "iso:country":"US",
    "sg:address":"10344 Horseshoe Rd",
    "sg:city":"Tomahawk",
    "sg:classifiers":[
        {
            "category":"Travel",
            "subcategory":"Hotels & Motels",
            "type":"Entertainment"
        },
        {
            "category":"Travel",
            "subcategory":"Campground",
            "type":"Entertainment"
        }
    ],
    "sg:phone":"+1 715 453 5444",
    "sg:postcode":"54487",
    "sg:province":"WI",
    "sg:tags":[
        "resort",
        "camp"
    ],
    "wof:name":"Tom & Sallys Hide A Way Resort",
    "wof:placetype":"venue"
},
  "geometry": {"coordinates":[-89.620749,45.491423],"type":"Point"}
}