{
  "type": "Feature",
  "properties": {
    "iso:country":"US",
    "sg:address":"3540 N 126th St",
    "sg:city":"Brookfield",
    "sg:classifiers":[
        {
            "category":"Professional",
            "subcategory":"Engineering",
            "type":"Services"
        }
    ],
    "sg:phone":"+1 262 373 0653",
    "sg:postcode":"53005",
    "sg:province":"WI",
    "sg:tags":[
        "engineer"
    ],
    "wof:name":"Nel Pretech Corp",
    "wof:placetype":"venue"
},
  "geometry": {"coordinates":[-88.068979,43.083819],"type":"Point"}
}