{
  "type": "Feature",
  "properties": {
    "iso:country":"US",
    "sg:address":"431 Main St",
    "sg:city":"Montello",
    "sg:classifiers":[
        {
            "category":"Retail",
            "subcategory":"Veterinary Services",
            "type":"Services"
        }
    ],
    "sg:phone":"+1 608 297 7995",
    "sg:postcode":"53949",
    "sg:province":"WI",
    "wof:name":"River Valley Veterinary Svc",
    "wof:placetype":"venue"
},
  "geometry": {"coordinates":[-89.325945,43.783077],"type":"Point"}
}