{
  "type": "Feature",
  "properties": {
    "iso:country":"US",
    "sg:address":"1039 W Historic Mitchell St",
    "sg:city":"Milwaukee",
    "sg:classifiers":[
        {
            "category":"Banks & Credit Unions",
            "subcategory":"Bank",
            "type":"Services"
        },
        {
            "category":"Banks & Credit Unions",
            "subcategory":"Financial Services",
            "type":"Services"
        }
    ],
    "sg:phone":"+1 414 645 0600",
    "sg:postcode":"53204",
    "sg:province":"WI",
    "sg:tags":[
        "saving",
        "mortgage",
        "cashing",
        "money",
        "loan",
        "commercial",
        "transfer",
        "check"
    ],
    "sg:website":"http://www.mitchellbank.com",
    "wof:name":"Mitchell Bank",
    "wof:placetype":"venue"
},
  "geometry": {"coordinates":[-87.92464200000001,43.012344],"type":"Point"}
}