{
  "type": "Feature",
  "properties": {
    "iso:country":"US",
    "sg:address":"2127 E Springs Dr",
    "sg:city":"Madison",
    "sg:classifiers":[
        {
            "category":"Shopping",
            "subcategory":"Used Merchandise",
            "type":"Retail Goods"
        }
    ],
    "sg:phone":"+1 608 246 3147",
    "sg:postcode":"53704",
    "sg:province":"WI",
    "sg:tags":[
        "shop",
        "thrift"
    ],
    "wof:name":"Goodwill Industries",
    "wof:placetype":"venue"
},
  "geometry": {"coordinates":[-89.29661900000001,43.125813],"type":"Point"}
}