{
  "type": "Feature",
  "properties": {
    "addr:full":"4502 Verona Rd Madison WI 53711",
    "addr:housenumber":"4502",
    "addr:postcode":"53711",
    "addr:street":"Verona Rd",
    "iso:country":"US",
    "sg:address":"4502 Verona Rd",
    "sg:city":"Madison",
    "sg:classifiers":[
        {
            "category":"Restaurant",
            "type":"Food & Drink"
        }
    ],
    "sg:menulink":"http://www.allmenus.com/wi/madison/181477-kfc---kentucky-fried-chicken/menu/",
    "sg:phone":"+1 608 271 1355",
    "sg:postcode":"53711",
    "sg:province":"WI",
    "sg:tags":[
        "american",
        "chicken"
    ],
    "wof:name":"KFC - Kentucky Fried Chicken",
    "wof:placetype":"venue"
},
  "geometry": {"coordinates":[-89.45389299999999,43.03672],"type":"Point"}
}