{
  "type": "Feature",
  "properties": {
    "iso:country":"US",
    "sg:address":"8956 Curve Inn Rd",
    "sg:city":"Tomahawk",
    "sg:classifiers":[
        {
            "category":"Bars & Pubs",
            "type":"Food & Drink"
        }
    ],
    "sg:phone":"+1 715 453 9701",
    "sg:postcode":"54487",
    "sg:province":"WI",
    "sg:tags":[
        "drinking"
    ],
    "wof:name":"A & J Sports Bar",
    "wof:placetype":"venue"
},
  "geometry": {"coordinates":[-89.704147,45.441233],"type":"Point"}
}