{
  "type": "Feature",
  "properties": {
    "iso:country":"US",
    "sg:address":"527 E Co Rd M",
    "sg:city":"Edgerton",
    "sg:classifiers":[
        {
            "category":"Building & Trades",
            "subcategory":"Landscaping Services",
            "type":"Services"
        }
    ],
    "sg:phone":"+1 608 868 2384",
    "sg:postcode":"53534",
    "sg:province":"WI",
    "wof:name":"Custom Tree Service-Rock Vly",
    "wof:placetype":"venue"
},
  "geometry": {"coordinates":[-89.045761,42.793052],"type":"Point"}
}