{
  "type": "Feature",
  "properties": {
    "iso:country":"US",
    "sg:address":"2161 250th St",
    "sg:city":"Deer Park",
    "sg:classifiers":[
        {
            "category":"Building & Trades",
            "subcategory":"Construction",
            "type":"Services"
        }
    ],
    "sg:phone":"+1 715 269 5146",
    "sg:postcode":"54007",
    "sg:province":"WI",
    "sg:tags":[
        "contractor"
    ],
    "wof:name":"Rick Waldschmidt",
    "wof:placetype":"venue"
},
  "geometry": {"coordinates":[-92.303122,45.171589],"type":"Point"}
}