{
  "type": "Feature",
  "properties": {
    "iso:country":"US",
    "sg:address":"5300 N 76th St",
    "sg:city":"Milwaukee",
    "sg:classifiers":[
        {
            "category":"Food & Beverages",
            "subcategory":"Candy",
            "type":"Retail Goods"
        }
    ],
    "sg:phone":"+1 414 421 2095",
    "sg:postcode":"53218",
    "sg:province":"WI",
    "wof:name":"Quality Candy/Buddy",
    "wof:placetype":"venue"
},
  "geometry": {"coordinates":[-88.005954,43.115206],"type":"Point"}
}