{
  "type": "Feature",
  "properties": {
    "iso:country":"US",
    "sg:address":"7433 State Hwy 188",
    "sg:city":"Sauk City",
    "sg:classifiers":[
        {
            "category":"Travel",
            "subcategory":"Hotels & Motels",
            "type":"Entertainment"
        }
    ],
    "sg:phone":"+1 608 643 8551",
    "sg:postcode":"53583",
    "sg:province":"WI",
    "sg:tags":[
        "operation"
    ],
    "wof:name":"Ganser's Motel",
    "wof:placetype":"venue"
},
  "geometry": {"coordinates":[-89.709962,43.263508],"type":"Point"}
}