{
  "type": "Feature",
  "properties": {
    "addr:full":"250 Stam St Williams Bay WI 53191",
    "addr:housenumber":"250",
    "addr:postcode":"53191",
    "addr:street":"Stam St",
    "iso:country":"US",
    "sg:address":"250 Stam St",
    "sg:city":"Williams Bay",
    "sg:classifiers":[
        {
            "category":"Travel",
            "subcategory":"Campground",
            "type":"Entertainment"
        }
    ],
    "sg:phone":"+1 262 245 6631",
    "sg:postcode":"53191",
    "sg:province":"WI",
    "sg:tags":[
        "camp"
    ],
    "wof:name":"Wesley Woods Conference Center",
    "wof:placetype":"venue"
},
  "geometry": {"coordinates":[-88.549042,42.569275],"type":"Point"}
}