{
  "type": "Feature",
  "properties": {
    "addr:full":"2311 Industrial St Wisconsin Rapids WI 54495",
    "addr:housenumber":"2311",
    "addr:postcode":"54495",
    "addr:street":"Industrial St",
    "iso:country":"US",
    "sg:address":"2311 Industrial St",
    "sg:city":"Wisconsin Rapids",
    "sg:classifiers":[
        {
            "category":"Wholesale",
            "subcategory":"Electrical",
            "type":"Manufacturing & Wholesale Goods"
        }
    ],
    "sg:phone":"+1 715 421 2355",
    "sg:postcode":"54495",
    "sg:province":"WI",
    "sg:tags":[
        "equipment",
        "electric",
        "supply"
    ],
    "wof:name":"Crescent Electric Supply Co",
    "wof:placetype":"venue"
},
  "geometry": {"coordinates":[-89.85255600000001,44.401922],"type":"Point"}
}