{
  "type": "Feature",
  "properties": {
    "iso:country":"US",
    "sg:address":"526 Louisiana St",
    "sg:city":"Sturgeon Bay",
    "sg:classifiers":[
        {
            "category":"Organizations",
            "subcategory":"Religious Organization",
            "type":"Services"
        }
    ],
    "sg:phone":"+1 920 743 2062",
    "sg:postcode":"54235",
    "sg:province":"WI",
    "sg:tags":[
        "church"
    ],
    "wof:name":"St Joseph's Catholic Church",
    "wof:placetype":"venue"
},
  "geometry": {"coordinates":[-87.373211,44.836868],"type":"Point"}
}