{
  "type": "Feature",
  "properties": {
    "addr:full":"2020 Radisson St Green Bay WI 54302",
    "addr:housenumber":"2020",
    "addr:postcode":"54302",
    "addr:street":"Radisson St",
    "iso:country":"US",
    "sg:address":"2020 Radisson St",
    "sg:city":"Green Bay",
    "sg:classifiers":[
        {
            "category":"Building & Trades",
            "subcategory":"Plumbing",
            "type":"Services"
        }
    ],
    "sg:phone":"+1 920 468 4671",
    "sg:postcode":"54302",
    "sg:province":"WI",
    "sg:tags":[
        "heating",
        "contractor"
    ],
    "sg:website":"www.bayheatingservice.com",
    "wof:name":"Bay Heating Svc Co Inc",
    "wof:placetype":"venue"
},
  "geometry": {"coordinates":[-87.97753,44.523112],"type":"Point"}
}