{
  "type": "Feature",
  "properties": {
    "addr:full":"1033 25th St Clayton WI 54004",
    "addr:housenumber":"1033",
    "addr:postcode":"54004",
    "addr:street":"25Th St",
    "iso:country":"US",
    "sg:address":"1033 25th St",
    "sg:city":"Clayton",
    "sg:classifiers":[
        {
            "category":"Professional",
            "subcategory":"Management & Consulting",
            "type":"Services"
        }
    ],
    "sg:phone":"+1 715 948 2503",
    "sg:postcode":"54004",
    "sg:province":"WI",
    "wof:name":"Wilshire Management LLC",
    "wof:placetype":"venue"
},
  "geometry": {"coordinates":[-92.20844700000001,45.353204],"type":"Point"}
}