{
  "type": "Feature",
  "properties": {
    "iso:country":"US",
    "sg:address":"2907 Ravine Dr",
    "sg:city":"Middleton",
    "sg:classifiers":[
        {
            "category":"Building & Trades",
            "subcategory":"Construction",
            "type":"Services"
        }
    ],
    "sg:phone":"+1 608 831 4993",
    "sg:postcode":"53562",
    "sg:province":"WI",
    "sg:tags":[
        "repair",
        "handyman",
        "maintenance",
        "home"
    ],
    "wof:name":"C-Youth",
    "wof:placetype":"venue"
},
  "geometry": {"coordinates":[-89.50569,43.106143],"type":"Point"}
}