{
  "type": "Feature",
  "properties": {
    "iso:country":"US",
    "sg:address":"4922 42nd Ave",
    "sg:city":"Kenosha",
    "sg:classifiers":[
        {
            "category":"Home & Garden",
            "subcategory":"Building Materials",
            "type":"Retail Goods"
        },
        {
            "category":"Building & Trades",
            "subcategory":"Construction",
            "type":"Services"
        }
    ],
    "sg:phone":"+1 262 770 8174",
    "sg:postcode":"53144",
    "sg:province":"WI",
    "sg:tags":[
        "improvement",
        "drywall",
        "contractor"
    ],
    "sg:website":"http://www.familydrywall.net",
    "wof:name":"Family Drywall",
    "wof:placetype":"venue"
},
  "geometry": {"coordinates":[-87.859996,42.592405],"type":"Point"}
}