{
  "type": "Feature",
  "properties": {
    "iso:country":"US",
    "sg:address":"1738 Main St",
    "sg:city":"Marinette",
    "sg:classifiers":[
        {
            "category":"Home & Garden",
            "subcategory":"Carpets & Floor Coverings",
            "type":"Retail Goods"
        }
    ],
    "sg:phone":"+1 715 732 6061",
    "sg:postcode":"54143",
    "sg:province":"WI",
    "sg:tags":[
        "material"
    ],
    "wof:name":"Quality Floor & Installations",
    "wof:placetype":"venue"
},
  "geometry": {"coordinates":[-87.628286,45.098637],"type":"Point"}
}