{
  "type": "Feature",
  "properties": {
    "iso:country":"US",
    "sg:address":"1219 Grove Ave",
    "sg:city":"Racine",
    "sg:classifiers":[
        {
            "category":"Professional",
            "type":"Services"
        }
    ],
    "sg:phone":"+1 262 619 3116",
    "sg:postcode":"53405",
    "sg:province":"WI",
    "sg:tags":[
        "establishment"
    ],
    "wof:name":"Racine Kenosha Comm Action",
    "wof:placetype":"venue"
},
  "geometry": {"coordinates":[-87.817285,42.717276],"type":"Point"}
}