{
  "type": "Feature",
  "properties": {
    "iso:country":"US",
    "sg:address":"1458 S 92nd St",
    "sg:city":"Milwaukee",
    "sg:classifiers":[
        {
            "category":"Building & Trades",
            "subcategory":"Construction",
            "type":"Services"
        }
    ],
    "sg:phone":"+1 414 527 9138",
    "sg:postcode":"53214",
    "sg:province":"WI",
    "sg:tags":[
        "general",
        "contractor"
    ],
    "wof:name":"C & C Contractors",
    "wof:placetype":"venue"
},
  "geometry": {"coordinates":[-88.027017,43.015493],"type":"Point"}
}