{
  "type": "Feature",
  "properties": {
    "iso:country":"US",
    "sg:address":"9308 W National Ave",
    "sg:city":"Milwaukee",
    "sg:classifiers":[
        {
            "category":"Shopping",
            "subcategory":"Pets & Pet Supplies",
            "type":"Retail Goods"
        }
    ],
    "sg:phone":"+1 414 541 6000",
    "sg:postcode":"53227",
    "sg:province":"WI",
    "sg:tags":[
        "food",
        "furnishing",
        "dog",
        "store",
        "cat"
    ],
    "wof:name":"Al-Mar Pet Shoppe",
    "wof:placetype":"venue"
},
  "geometry": {"coordinates":[-88.028452,43.004223],"type":"Point"}
}