{
  "type": "Feature",
  "properties": {
    "iso:country":"US",
    "sg:address":"9300 W Manor Ct",
    "sg:city":"Milwaukee",
    "sg:classifiers":[
        {
            "category":"Organizations",
            "subcategory":"Membership Organization",
            "type":"Services"
        }
    ],
    "sg:phone":"+1 414 355 1793",
    "sg:postcode":"53224",
    "sg:province":"WI",
    "sg:tags":[
        "military",
        "veteran"
    ],
    "wof:name":"Disabled Veterans Helping Veterans Inc.",
    "wof:placetype":"venue"
},
  "geometry": {"coordinates":[-88.02557400000001,43.18446],"type":"Point"}
}