{
  "type": "Feature",
  "properties": {
    "iso:country":"US",
    "sg:address":"1135 Regent St",
    "sg:city":"Madison",
    "sg:classifiers":[
        {
            "category":"Shopping",
            "subcategory":"Florist",
            "type":"Retail Goods"
        }
    ],
    "sg:phone":"+1 608 256 7016",
    "sg:postcode":"53715",
    "sg:province":"WI",
    "sg:tags":[
        "fresh",
        "flower"
    ],
    "wof:name":"Choles Campus Floral",
    "wof:placetype":"venue"
},
  "geometry": {"coordinates":[-89.405295,43.067634],"type":"Point"}
}