{
  "type": "Feature",
  "properties": {
    "iso:country":"US",
    "sg:address":"500 Industrial Dr",
    "sg:city":"Horicon",
    "sg:classifiers":[
        {
            "category":"Manufacturing",
            "subcategory":"Wood Products",
            "type":"Manufacturing & Wholesale Goods"
        }
    ],
    "sg:phone":"+1 920 485 4108",
    "sg:postcode":"53032",
    "sg:province":"WI",
    "sg:tags":[
        "pallet",
        "skid",
        "mfg"
    ],
    "wof:name":"Pufahl Pallet Co Inc",
    "wof:placetype":"venue"
},
  "geometry": {"coordinates":[-88.653972,43.456151],"type":"Point"}
}