{
  "type": "Feature",
  "properties": {
    "iso:country":"US",
    "sg:address":"21052 W Good Hope Rd",
    "sg:city":"Lannon",
    "sg:classifiers":[
        {
            "category":"Utilities",
            "subcategory":"Fuel Oil & Lpg",
            "type":"Services"
        }
    ],
    "sg:phone":"+1 262 251 8855",
    "sg:postcode":"53046",
    "sg:province":"WI",
    "sg:tags":[
        "firewood"
    ],
    "wof:name":"Woodland Contractors",
    "wof:placetype":"venue"
},
  "geometry": {"coordinates":[-88.170864,43.148305],"type":"Point"}
}