{
  "type": "Feature",
  "properties": {
    "iso:country":"US",
    "sg:address":"215 E Washington St",
    "sg:city":"Appleton",
    "sg:classifiers":[
        {
            "category":"Cinema",
            "subcategory":"Movie Theater",
            "type":"Entertainment"
        }
    ],
    "sg:phone":"+1 920 731 7700",
    "sg:postcode":"54911",
    "sg:province":"WI",
    "wof:name":"Big Picture",
    "wof:placetype":"venue"
},
  "geometry": {"coordinates":[-88.402911,44.262866],"type":"Point"}
}