{
  "type": "Feature",
  "properties": {
    "iso:country":"US",
    "sg:address":"1501 Main St",
    "sg:city":"Luxemburg",
    "sg:classifiers":[
        {
            "category":"Utilities",
            "subcategory":"Fuel Oil & Lpg",
            "type":"Services"
        }
    ],
    "sg:phone":"+1 920 845 2992",
    "sg:postcode":"54217",
    "sg:province":"WI",
    "sg:tags":[
        "liquefied",
        "petroleum",
        "household",
        "gas",
        "re",
        "appliance"
    ],
    "wof:name":"Rockys Propane Inc",
    "wof:placetype":"venue"
},
  "geometry": {"coordinates":[-87.703858,44.530702],"type":"Point"}
}