{
  "type": "Feature",
  "properties": {
    "addr:full":"5303 N 90th St Milwaukee WI 53225",
    "addr:housenumber":"5303",
    "addr:postcode":"53225",
    "addr:street":"N 90Th St",
    "iso:country":"US",
    "sg:address":"5303 N 90th St",
    "sg:city":"Milwaukee",
    "sg:classifiers":[
        {
            "category":"Building & Trades",
            "subcategory":"Landscaping Services",
            "type":"Services"
        }
    ],
    "sg:phone":"+1 414 463 0671",
    "sg:postcode":"53225",
    "sg:province":"WI",
    "sg:tags":[
        "lawn"
    ],
    "wof:name":"Larry Green Lawn Service",
    "wof:placetype":"venue"
},
  "geometry": {"coordinates":[-88.024563,43.11456],"type":"Point"}
}