{
  "type": "Feature",
  "properties": {
    "iso:country":"US",
    "sg:address":"1400 Packerland Dr",
    "sg:city":"Green Bay",
    "sg:classifiers":[
        {
            "category":"Building & Trades",
            "subcategory":"Cleaning & Sanitation",
            "type":"Services"
        }
    ],
    "sg:phone":"+1 920 497 1751",
    "sg:postcode":"54304",
    "sg:province":"WI",
    "sg:tags":[
        "janitor"
    ],
    "wof:name":"Total Maintenance",
    "wof:placetype":"venue"
},
  "geometry": {"coordinates":[-88.099467,44.51991],"type":"Point"}
}