{
  "type": "Feature",
  "properties": {
    "iso:country":"US",
    "sg:address":"304 S 4th St",
    "sg:city":"Stoughton",
    "sg:classifiers":[
        {
            "category":"Education",
            "subcategory":"Library",
            "type":"Public Place"
        }
    ],
    "sg:phone":"+1 608 873 6281",
    "sg:postcode":"53589",
    "sg:province":"WI",
    "sg:tags":[
        "executive"
    ],
    "wof:name":"Stoughton Public Library",
    "wof:placetype":"venue"
},
  "geometry": {"coordinates":[-89.217971,42.916699],"type":"Point"}
}