{
  "type": "Feature",
  "properties": {
    "iso:country":"US",
    "sg:address":"2323 Deer Trl",
    "sg:city":"Green Bay",
    "sg:classifiers":[
        {
            "category":"Social Services",
            "subcategory":"Adult Care",
            "type":"Services"
        }
    ],
    "sg:phone":"+1 920 465 8478",
    "sg:postcode":"54302",
    "sg:province":"WI",
    "wof:name":"Deer Trail Home",
    "wof:placetype":"venue"
},
  "geometry": {"coordinates":[-87.965161,44.504165],"type":"Point"}
}