{
  "type": "Feature",
  "properties": {
    "iso:country":"US",
    "sg:address":"2347 N 45th St",
    "sg:city":"Milwaukee",
    "sg:classifiers":[
        {
            "category":"Social Services",
            "subcategory":"Child Care",
            "type":"Services"
        }
    ],
    "sg:phone":"+1 414 873 0663",
    "sg:postcode":"53210",
    "sg:province":"WI",
    "wof:name":"Powells House Of Love",
    "wof:placetype":"venue"
},
  "geometry": {"coordinates":[-87.970122,43.061594],"type":"Point"}
}