{
  "type": "Feature",
  "properties": {
    "iso:country":"US",
    "sg:address":"210 S Barstow St",
    "sg:city":"Eau Claire",
    "sg:classifiers":[
        {
            "category":"Shopping",
            "type":"Retail Goods"
        }
    ],
    "sg:phone":"+1 715 836 7331",
    "sg:postcode":"54701",
    "sg:province":"WI",
    "sg:tags":[
        "art",
        "gallery",
        "dealer"
    ],
    "sg:website":"www.destiniartworks.com",
    "wof:name":"Destini Artworks Inc",
    "wof:placetype":"venue"
},
  "geometry": {"coordinates":[-91.499516,44.810918],"type":"Point"}
}