{
  "type": "Feature",
  "properties": {
    "iso:country":"US",
    "sg:address":"615 Milwaukee Ave",
    "sg:city":"South Milwaukee",
    "sg:classifiers":[
        {
            "category":"Building & Trades",
            "subcategory":"Construction",
            "type":"Services"
        }
    ],
    "sg:phone":"+1 414 762 9284",
    "sg:postcode":"53172",
    "sg:province":"WI",
    "sg:tags":[
        "hanging",
        "contractor"
    ],
    "wof:name":"Luedtke Painting Co",
    "wof:placetype":"venue"
},
  "geometry": {"coordinates":[-87.85471,42.910472],"type":"Point"}
}