{
  "type": "Feature",
  "properties": {
    "iso:country":"US",
    "sg:address":"4505 Terminal Dr",
    "sg:city":"Mc Farland",
    "sg:classifiers":[
        {
            "category":"Utilities",
            "subcategory":"Fuel Oil & Lpg",
            "type":"Services"
        }
    ],
    "sg:phone":"+1 608 838 3370",
    "sg:postcode":"53558",
    "sg:province":"WI",
    "sg:tags":[
        "product",
        "petroleum",
        "dealer"
    ],
    "wof:name":"Flint Hills Resources LP",
    "wof:placetype":"venue"
},
  "geometry": {"coordinates":[-89.302699,43.027459],"type":"Point"}
}