{
  "type": "Feature",
  "properties": {
    "iso:country":"US",
    "sg:address":"2031 Red Oak Dr",
    "sg:city":"Plover",
    "sg:classifiers":[
        {
            "category":"Shopping",
            "subcategory":"Bicycles & Sporting Goods",
            "type":"Retail Goods"
        }
    ],
    "sg:phone":"+1 715 341 1595",
    "sg:postcode":"54467",
    "sg:province":"WI",
    "wof:name":"Edge Pro Shop",
    "wof:placetype":"venue"
},
  "geometry": {"coordinates":[-89.527426,44.467658],"type":"Point"}
}