{
  "type": "Feature",
  "properties": {
    "iso:country":"US",
    "sg:address":"11403 Co Hwy M",
    "sg:city":"New Auburn",
    "sg:classifiers":[
        {
            "category":"Retail",
            "subcategory":"Repair Shop",
            "type":"Services"
        }
    ],
    "sg:phone":"+1 715 967 4075",
    "sg:postcode":"54757",
    "sg:province":"WI",
    "wof:name":"McGills Septic Service",
    "wof:placetype":"venue"
},
  "geometry": {"coordinates":[-91.453,45.220546],"type":"Point"}
}