{
  "type": "Feature",
  "properties": {
    "iso:country":"US",
    "sg:address":"525 Franklin Ct",
    "sg:city":"Madison",
    "sg:classifiers":[
        {
            "category":"Professional",
            "subcategory":"Management & Consulting",
            "type":"Services"
        }
    ],
    "sg:phone":"+1 608 238 7053",
    "sg:postcode":"53705",
    "sg:province":"WI",
    "wof:name":"Mad City Services",
    "wof:placetype":"venue"
},
  "geometry": {"coordinates":[-89.437281,43.073804],"type":"Point"}
}