{
  "type": "Feature",
  "properties": {
    "iso:country":"US",
    "sg:address":"1020 21st Ave S",
    "sg:city":"Wisconsin Rapids",
    "sg:classifiers":[
        {
            "category":"Wholesale",
            "subcategory":"Durable Goods & Equipment",
            "type":"Manufacturing & Wholesale Goods"
        }
    ],
    "sg:phone":"+1 715 421 2579",
    "sg:postcode":"54495",
    "sg:province":"WI",
    "wof:name":"Wunrow Enterprises",
    "wof:placetype":"venue"
},
  "geometry": {"coordinates":[-89.84959,44.386477],"type":"Point"}
}