{
  "type": "Feature",
  "properties": {
    "iso:country":"US",
    "sg:address":"15908 Bufton Hollow Rd",
    "sg:city":"Viola",
    "sg:classifiers":[
        {
            "category":"Manufacturing",
            "subcategory":"Wood Products",
            "type":"Manufacturing & Wholesale Goods"
        }
    ],
    "sg:phone":"+1 608 627 2029",
    "sg:postcode":"54664",
    "sg:province":"WI",
    "sg:tags":[
        "mfg"
    ],
    "wof:name":"Hamann Stake Mill",
    "wof:placetype":"venue"
},
  "geometry": {"coordinates":[-90.551023,43.517952],"type":"Point"}
}