{
  "type": "Feature",
  "properties": {
    "iso:country":"US",
    "sg:address":"4575 Anston Rd",
    "sg:city":"Green Bay",
    "sg:classifiers":[
        {
            "category":"Manufacturing",
            "subcategory":"Motor Vehicles & Parts",
            "type":"Manufacturing & Wholesale Goods"
        }
    ],
    "sg:phone":"+1 920 865 4266",
    "sg:postcode":"54313",
    "sg:province":"WI",
    "sg:tags":[
        "manufacture",
        "transmission",
        "drive",
        "equipment",
        "test",
        "line"
    ],
    "wof:name":"Hicklin Engineering Lc",
    "wof:placetype":"venue"
},
  "geometry": {"coordinates":[-88.159842,44.61725],"type":"Point"}
}