{
  "type": "Feature",
  "properties": {
    "iso:country":"US",
    "sg:address":"2625 S Kernan Ave",
    "sg:city":"Appleton",
    "sg:classifiers":[
        {
            "category":"Building & Trades",
            "subcategory":"Cleaning & Sanitation",
            "type":"Services"
        }
    ],
    "sg:phone":"+1 920 954 0068",
    "sg:postcode":"54915",
    "sg:province":"WI",
    "sg:tags":[
        "maintenance"
    ],
    "wof:name":"Valley Cleaning LLC",
    "wof:placetype":"venue"
},
  "geometry": {"coordinates":[-88.383392,44.238611],"type":"Point"}
}