{
  "type": "Feature",
  "properties": {
    "iso:country":"US",
    "sg:address":"20365 Independence Dr",
    "sg:city":"Brookfield",
    "sg:classifiers":[
        {
            "category":"Wholesale",
            "subcategory":"Medical Equipment & Supplies",
            "type":"Manufacturing & Wholesale Goods"
        }
    ],
    "sg:phone":"+1 262 641 5765",
    "sg:postcode":"53045",
    "sg:province":"WI",
    "sg:tags":[
        "hospital"
    ],
    "wof:name":"Medtronic Physio-Control Inc",
    "wof:placetype":"venue"
},
  "geometry": {"coordinates":[-88.159446,43.047769],"type":"Point"}
}