{
  "type": "Feature",
  "properties": {
    "iso:country":"US",
    "sg:address":"347 Misere Rd",
    "sg:city":"Forestville",
    "sg:phone":"+1 920 825 7004",
    "sg:postcode":"54213",
    "sg:province":"WI",
    "sg:tags":[
        "farm",
        "field",
        "crop"
    ],
    "wof:name":"Patricia Leclous",
    "wof:placetype":"venue"
},
  "geometry": {"coordinates":[-87.60039,44.685447],"type":"Point"}
}