{
  "type": "Feature",
  "properties": {
    "iso:country":"US",
    "sg:address":"2426 N Rapids Rd",
    "sg:city":"Manitowoc",
    "sg:classifiers":[
        {
            "category":"Organizations",
            "subcategory":"Religious Organization",
            "type":"Services"
        }
    ],
    "sg:phone":"+1 920 682 7377",
    "sg:postcode":"54220",
    "sg:province":"WI",
    "sg:tags":[
        "church"
    ],
    "sg:website":"www.gracelutheran-church.com",
    "wof:name":"Grace Evangelical Lutheran Chr",
    "wof:placetype":"venue"
},
  "geometry": {"coordinates":[-87.709685,44.128343],"type":"Point"}
}