{
  "type": "Feature",
  "properties": {
    "iso:country":"US",
    "sg:address":"6524 S Lovers Lane Rd",
    "sg:city":"Franklin",
    "sg:classifiers":[
        {
            "category":"Personal",
            "subcategory":"Beauty Salon",
            "type":"Services"
        }
    ],
    "sg:phone":"+1 414 529 5340",
    "sg:postcode":"53132",
    "sg:province":"WI",
    "wof:name":"Hair Xperience",
    "wof:placetype":"venue"
},
  "geometry": {"coordinates":[-88.048418,42.928333],"type":"Point"}
}