{
  "type": "Feature",
  "properties": {
    "iso:country":"US",
    "sg:address":"7937 Elm Rd",
    "sg:city":"Sturgeon Bay",
    "sg:classifiers":[
        {
            "category":"Retail",
            "subcategory":"Car Wash",
            "type":"Services"
        }
    ],
    "sg:phone":"+1 920 743 6822",
    "sg:postcode":"54235",
    "sg:province":"WI",
    "sg:tags":[
        "carwash"
    ],
    "wof:name":"Detail Center",
    "wof:placetype":"venue"
},
  "geometry": {"coordinates":[-87.499678,44.733291],"type":"Point"}
}