{
  "type": "Feature",
  "properties": {
    "iso:country":"US",
    "sg:address":"1500 S West Ln",
    "sg:city":"New Berlin",
    "sg:classifiers":[
        {
            "category":"Organizations",
            "subcategory":"Religious Organization",
            "type":"Services"
        }
    ],
    "sg:phone":"+1 262 754 1122",
    "sg:postcode":"53146",
    "sg:province":"WI",
    "sg:tags":[
        "church"
    ],
    "wof:name":"World Harvest Church",
    "wof:placetype":"venue"
},
  "geometry": {"coordinates":[-88.131896,43.016372],"type":"Point"}
}