{
  "type": "Feature",
  "properties": {
    "iso:country":"US",
    "sg:address":"1402 Mount Vernon St",
    "sg:city":"Oshkosh",
    "sg:classifiers":[
        {
            "category":"Local Transit",
            "type":"Transportation"
        }
    ],
    "sg:phone":"+1 920 426 3900",
    "sg:postcode":"54901",
    "sg:province":"WI",
    "sg:tags":[
        "passenger"
    ],
    "wof:name":"Cabulance Inc",
    "wof:placetype":"venue"
},
  "geometry": {"coordinates":[-88.535079,44.03579],"type":"Point"}
}