{
  "type": "Feature",
  "properties": {
    "addr:full":"2277 Edgewood Dr Grafton WI 53024",
    "addr:housenumber":"2277",
    "addr:postcode":"53024",
    "addr:street":"Edgewood Dr",
    "iso:country":"US",
    "sg:address":"2277 Edgewood Dr",
    "sg:city":"Grafton",
    "sg:classifiers":[
        {
            "category":"Manufacturing",
            "subcategory":"Apparel",
            "type":"Manufacturing & Wholesale Goods"
        }
    ],
    "sg:phone":"+1 262 677 3552",
    "sg:postcode":"53024",
    "sg:province":"WI",
    "sg:tags":[
        "household",
        "furnishing",
        "mfg"
    ],
    "wof:name":"Raspberry Hill Patchwork",
    "wof:placetype":"venue"
},
  "geometry": {"coordinates":[-87.952105,43.35804],"type":"Point"}
}