{
  "type": "Feature",
  "properties": {
    "iso:country":"US",
    "sg:address":"1094 Golden Oaks Rd",
    "sg:city":"Hudson",
    "sg:classifiers":[
        {
            "category":"Professional",
            "subcategory":"Management & Consulting",
            "type":"Services"
        }
    ],
    "sg:phone":"+1 715 381 5701",
    "sg:postcode":"54016",
    "sg:province":"WI",
    "sg:tags":[
        "business"
    ],
    "wof:name":"St Croix Environmental Inc",
    "wof:placetype":"venue"
},
  "geometry": {"coordinates":[-92.733445,45.019135],"type":"Point"}
}