{
  "type": "Feature",
  "properties": {
    "iso:country":"US",
    "sg:address":"165 E Chestnut St",
    "sg:city":"Burlington",
    "sg:classifiers":[
        {
            "category":"Food & Beverages",
            "subcategory":"Specialty",
            "type":"Retail Goods"
        }
    ],
    "sg:phone":"+1 262 763 7709",
    "sg:postcode":"53105",
    "sg:province":"WI",
    "sg:tags":[
        "health",
        "market"
    ],
    "wof:name":"Burlington Health Foods",
    "wof:placetype":"venue"
},
  "geometry": {"coordinates":[-88.276901,42.68],"type":"Point"}
}