{
  "type": "Feature",
  "properties": {
    "iso:country":"US",
    "sg:address":"1581 E Racine Ave",
    "sg:city":"Waukesha",
    "sg:classifiers":[
        {
            "category":"Insurance",
            "subcategory":"Insurance Agent",
            "type":"Services"
        }
    ],
    "sg:phone":"+1 262 953 7171",
    "sg:postcode":"53186",
    "sg:province":"WI",
    "sg:website":"www.rrins.com",
    "wof:name":"R & R Insurance Svc Inc",
    "wof:placetype":"venue"
},
  "geometry": {"coordinates":[-88.201544,42.9964],"type":"Point"}
}