{
  "type": "Feature",
  "properties": {
    "iso:country":"US",
    "sg:address":"1610 N 48th St",
    "sg:city":"Milwaukee",
    "sg:classifiers":[
        {
            "category":"Food & Beverages",
            "subcategory":"Farmers Market",
            "type":"Retail Goods"
        },
        {
            "category":"Utilities",
            "type":"Services"
        }
    ],
    "sg:phone":"+1 414 771 8883",
    "sg:postcode":"53208",
    "sg:province":"WI",
    "sg:tags":[
        "equipment",
        "beer",
        "cooling",
        "dispensing",
        "supply"
    ],
    "wof:name":"Cream City Beer Pipe Cleaning Inc",
    "wof:placetype":"venue"
},
  "geometry": {"coordinates":[-87.973547,43.051651],"type":"Point"}
}