{
  "type": "Feature",
  "properties": {
    "addr:full":"400 Pine St Viroqua WI 54665",
    "addr:housenumber":"400",
    "addr:postcode":"54665",
    "addr:street":"Pine St",
    "iso:country":"US",
    "sg:address":"400 Pine St",
    "sg:city":"Viroqua",
    "sg:classifiers":[
        {
            "category":"Organizations",
            "subcategory":"Community Association",
            "type":"Services"
        }
    ],
    "sg:phone":"+1 608 637 7371",
    "sg:postcode":"54665",
    "sg:province":"WI",
    "wof:name":"Lions International Inter",
    "wof:placetype":"venue"
},
  "geometry": {"coordinates":[-90.89308699999999,43.548724],"type":"Point"}
}