{
  "type": "Feature",
  "properties": {
    "iso:country":"US",
    "sg:address":"1325 Boundary Rd",
    "sg:city":"Middleton",
    "sg:classifiers":[
        {
            "category":"Farming",
            "subcategory":"Farm",
            "type":"Manufacturing & Wholesale Goods"
        }
    ],
    "sg:phone":"+1 608 831 3707",
    "sg:postcode":"53562",
    "sg:province":"WI",
    "sg:tags":[
        "crop",
        "general"
    ],
    "wof:name":"Frostwood Farm LLC",
    "wof:placetype":"venue"
},
  "geometry": {"coordinates":[-89.496155,43.084491],"type":"Point"}
}