{
  "type": "Feature",
  "properties": {
    "addr:full":"233 4th Ave Baraboo WI 53913",
    "addr:housenumber":"233",
    "addr:postcode":"53913",
    "addr:street":"4Th Ave",
    "iso:country":"US",
    "sg:address":"233 4th Ave",
    "sg:city":"Baraboo",
    "sg:classifiers":[
        {
            "category":"Personal",
            "subcategory":"Beauty Salon",
            "type":"Services"
        }
    ],
    "sg:phone":"+1 608 356 4233",
    "sg:postcode":"53913",
    "sg:province":"WI",
    "sg:tags":[
        "shop"
    ],
    "wof:name":"Cinder Fellas Hair Salon",
    "wof:placetype":"venue"
},
  "geometry": {"coordinates":[-89.744238,43.470897],"type":"Point"}
}