{
  "type": "Feature",
  "properties": {
    "addr:full":"125 Serenity Oaks Ter Watertown WI 53098",
    "addr:housenumber":"125",
    "addr:postcode":"53098",
    "addr:street":"Serenity Oaks Ter",
    "iso:country":"US",
    "sg:address":"125 Serenity Oaks Ter",
    "sg:city":"Watertown",
    "sg:classifiers":[
        {
            "category":"Building & Trades",
            "subcategory":"Construction",
            "type":"Services"
        }
    ],
    "sg:phone":"+1 920 206 1945",
    "sg:postcode":"53098",
    "sg:province":"WI",
    "sg:tags":[
        "floor",
        "laying",
        "contractor"
    ],
    "wof:name":"J & M Flooring",
    "wof:placetype":"venue"
},
  "geometry": {"coordinates":[-88.613527,43.204366],"type":"Point"}
}