{
  "type": "Feature",
  "properties": {
    "iso:country":"US",
    "sg:address":"8057 W Appleton Ave",
    "sg:city":"Milwaukee",
    "sg:classifiers":[
        {
            "category":"Organizations",
            "subcategory":"Religious Organization",
            "type":"Services"
        }
    ],
    "sg:phone":"+1 414 462 6706",
    "sg:postcode":"53218",
    "sg:province":"WI",
    "sg:tags":[
        "church"
    ],
    "wof:name":"Ark Of The New Covenant Church",
    "wof:placetype":"venue"
},
  "geometry": {"coordinates":[-88.013701,43.10172],"type":"Point"}
}