{
  "type": "Feature",
  "properties": {
    "iso:country":"US",
    "sg:address":"8100 W Greenfield Ave",
    "sg:city":"West Allis",
    "sg:classifiers":[
        {
            "category":"Home & Garden",
            "subcategory":"Home Furnishings",
            "type":"Retail Goods"
        }
    ],
    "sg:phone":"+1 414 302 1702",
    "sg:postcode":"53214",
    "sg:province":"WI",
    "sg:tags":[
        "pottery"
    ],
    "wof:name":"Plantation Pottery",
    "wof:placetype":"venue"
},
  "geometry": {"coordinates":[-88.012412,43.016668],"type":"Point"}
}