{
  "type": "Feature",
  "properties": {
    "iso:country":"US",
    "sg:address":"366 60th Ave",
    "sg:city":"Clear Lake",
    "sg:classifiers":[
        {
            "category":"Freight",
            "type":"Transportation"
        }
    ],
    "sg:phone":"+1 715 263 3179",
    "sg:postcode":"54005",
    "sg:province":"WI",
    "sg:tags":[
        "trucking"
    ],
    "wof:name":"Benware Trucking",
    "wof:placetype":"venue"
},
  "geometry": {"coordinates":[-92.249078,45.295478],"type":"Point"}
}