{
  "type": "Feature",
  "properties": {
    "iso:country":"US",
    "sg:address":"2500 W Layton Ave",
    "sg:city":"Milwaukee",
    "sg:classifiers":[
        {
            "category":"Health Services",
            "subcategory":"Doctor",
            "type":"Services"
        }
    ],
    "sg:phone":"+1 414 281 3444",
    "sg:postcode":"53221",
    "sg:province":"WI",
    "sg:tags":[
        "physician",
        "surgeon"
    ],
    "wof:name":"Cardiac Diagnostic Clinic LTD",
    "wof:placetype":"venue"
},
  "geometry": {"coordinates":[-87.947369,42.959395],"type":"Point"}
}