{
  "type": "Feature",
  "properties": {
    "iso:country":"US",
    "sg:address":"707 Shepherds Dr",
    "sg:city":"West Bend",
    "sg:classifiers":[
        {
            "category":"Arts & Performance",
            "subcategory":"Theater",
            "type":"Entertainment"
        }
    ],
    "sg:phone":"+1 262 334 8111",
    "sg:postcode":"53090",
    "sg:province":"WI",
    "sg:tags":[
        "group"
    ],
    "wof:name":"Caricatures By Rex",
    "wof:placetype":"venue"
},
  "geometry": {"coordinates":[-88.233033,43.431317],"type":"Point"}
}