{
  "type": "Feature",
  "properties": {
    "iso:country":"US",
    "sg:address":"11135 Cottonwood Rd",
    "sg:city":"Waupun",
    "sg:classifiers":[
        {
            "category":"Farming",
            "subcategory":"Farm",
            "type":"Manufacturing & Wholesale Goods"
        },
        {
            "category":"Farming",
            "subcategory":"Farm & Veterinary Services",
            "type":"Manufacturing & Wholesale Goods"
        }
    ],
    "sg:phone":"+1 920 324 9931",
    "sg:postcode":"53963",
    "sg:province":"WI",
    "sg:tags":[
        "crop",
        "harvesting"
    ],
    "wof:name":"Lemmenes Custom Farms LLC",
    "wof:placetype":"venue"
},
  "geometry": {"coordinates":[-88.78049799999999,43.6215],"type":"Point"}
}