{
  "type": "Feature",
  "properties": {
    "addr:full":"1781 21st Ave Rice Lake WI 54868",
    "addr:housenumber":"1781",
    "addr:postcode":"54868",
    "addr:street":"21St Ave",
    "iso:country":"US",
    "sg:address":"1781 21st Ave",
    "sg:city":"Rice Lake",
    "sg:classifiers":[
        {
            "category":"Building & Trades",
            "subcategory":"Construction",
            "type":"Services"
        }
    ],
    "sg:phone":"+1 715 234 7878",
    "sg:postcode":"54868",
    "sg:province":"WI",
    "sg:tags":[
        "clearing",
        "land",
        "grading",
        "contractor"
    ],
    "wof:name":"Earthmovers Inc",
    "wof:placetype":"venue"
},
  "geometry": {"coordinates":[-91.79152499999999,45.509838],"type":"Point"}
}