{
  "type": "Feature",
  "properties": {
    "iso:country":"US",
    "sg:address":"129 N Madison St",
    "sg:city":"Waupun",
    "sg:classifiers":[
        {
            "category":"Health Services",
            "subcategory":"Doctor",
            "type":"Services"
        }
    ],
    "sg:phone":"+1 920 324 2561",
    "sg:postcode":"53963",
    "sg:province":"WI",
    "wof:name":"Jeffrey L Champion",
    "wof:placetype":"venue"
},
  "geometry": {"coordinates":[-88.729738,43.634955],"type":"Point"}
}