{
  "type": "Feature",
  "properties": {
    "iso:country":"US",
    "sg:address":"559 State St",
    "sg:city":"Racine",
    "sg:classifiers":[
        {
            "category":"Recreation",
            "type":"Entertainment"
        },
        {
            "category":"Organizations",
            "subcategory":"Community Association",
            "type":"Services"
        }
    ],
    "sg:phone":"+1 262 634 9280",
    "sg:postcode":"53404",
    "sg:province":"WI",
    "sg:tags":[
        "club",
        "membership"
    ],
    "wof:name":"Harbor Lite Yacht Club Inc",
    "wof:placetype":"venue"
},
  "geometry": {"coordinates":[-87.786289,42.731565],"type":"Point"}
}