{
  "type": "Feature",
  "properties": {
    "iso:country":"US",
    "sg:address":"2323 Aviation Dr",
    "sg:city":"Waukesha",
    "sg:classifiers":[
        {
            "category":"Professional",
            "type":"Services"
        }
    ],
    "sg:phone":"+1 262 896 1655",
    "sg:postcode":"53188",
    "sg:province":"WI",
    "wof:name":"Stbc LLC",
    "wof:placetype":"venue"
},
  "geometry": {"coordinates":[-88.237125,43.032976],"type":"Point"}
}