{
  "type": "Feature",
  "properties": {
    "addr:full":"21201 9th St Kansasville WI 53139",
    "addr:housenumber":"21201",
    "addr:postcode":"53139",
    "addr:street":"9Th St",
    "iso:country":"US",
    "sg:address":"21201 9th St",
    "sg:city":"Kansasville",
    "sg:classifiers":[
        {
            "category":"Building & Trades",
            "subcategory":"Construction",
            "type":"Services"
        }
    ],
    "sg:phone":"+1 262 657 5508",
    "sg:postcode":"53139",
    "sg:province":"WI",
    "sg:tags":[
        "concrete",
        "contractor"
    ],
    "wof:name":"Jim Zimmermann Construction",
    "wof:placetype":"venue"
},
  "geometry": {"coordinates":[-88.06515400000001,42.648042],"type":"Point"}
}