{
  "type": "Feature",
  "properties": {
    "addr:full":"7617 Co Rd J Cuba City WI 53807",
    "addr:housenumber":"7617",
    "addr:postcode":"53807",
    "addr:street":"Co Rd",
    "iso:country":"US",
    "sg:address":"7617 Co Rd J",
    "sg:city":"Cuba City",
    "sg:classifiers":[
        {
            "category":"Sports & Exercise",
            "subcategory":"Golf",
            "type":"Entertainment"
        }
    ],
    "sg:phone":"+1 608 744 2476",
    "sg:postcode":"53807",
    "sg:province":"WI",
    "sg:tags":[
        "course"
    ],
    "wof:name":"Cole Acres Golf Course",
    "wof:placetype":"venue"
},
  "geometry": {"coordinates":[-90.406767,42.599883],"type":"Point"}
}