{
  "type": "Feature",
  "properties": {
    "addr:full":"375 Monroe St Platteville WI 53818",
    "addr:housenumber":"375",
    "addr:postcode":"53818",
    "addr:street":"Monroe St",
    "iso:country":"US",
    "sg:address":"375 Monroe St",
    "sg:city":"Platteville",
    "sg:classifiers":[
        {
            "category":"Real Estate",
            "subcategory":"Real Estate Operator",
            "type":"Services"
        }
    ],
    "sg:phone":"+1 608 348 7172",
    "sg:postcode":"53818",
    "sg:province":"WI",
    "sg:tags":[
        "property",
        "lessor"
    ],
    "wof:name":"Walter Edge",
    "wof:placetype":"venue"
},
  "geometry": {"coordinates":[-90.48086600000001,42.744763],"type":"Point"}
}