{
  "type": "Feature",
  "properties": {
    "iso:country":"US",
    "sg:address":"2130 Co Rd Pp",
    "sg:city":"Stevens Point",
    "sg:classifiers":[
        {
            "category":"Building & Trades",
            "subcategory":"Construction",
            "type":"Services"
        }
    ],
    "sg:phone":"+1 715 345 9811",
    "sg:postcode":"54481",
    "sg:province":"WI",
    "sg:tags":[
        "masonry",
        "contractor"
    ],
    "wof:name":"S K Masonry",
    "wof:placetype":"venue"
},
  "geometry": {"coordinates":[-89.664135,44.475897],"type":"Point"}
}