{
  "type": "Feature",
  "properties": {
    "addr:full":"819 S Gibson St Medford WI 54451",
    "addr:housenumber":"819",
    "addr:postcode":"54451",
    "addr:street":"S Gibson St",
    "iso:country":"US",
    "sg:address":"819 S Gibson St",
    "sg:city":"Medford",
    "sg:classifiers":[
        {
            "category":"Retail",
            "subcategory":"Animal Services",
            "type":"Services"
        }
    ],
    "sg:phone":"+1 715 748 9699",
    "sg:postcode":"54451",
    "sg:province":"WI",
    "sg:tags":[
        "pet",
        "boarding",
        "sitting"
    ],
    "wof:name":"Gentle Hearts Boarding Kennel",
    "wof:placetype":"venue"
},
  "geometry": {"coordinates":[-90.351997,45.126241],"type":"Point"}
}