{
  "type": "Feature",
  "properties": {
    "iso:country":"US",
    "sg:address":"1101 Red Wing Trl",
    "sg:city":"De Pere",
    "sg:classifiers":[
        {
            "category":"Real Estate",
            "subcategory":"Developer",
            "type":"Services"
        }
    ],
    "sg:phone":"+1 920 336 3868",
    "sg:postcode":"54115",
    "sg:province":"WI",
    "sg:tags":[
        "development",
        "residential",
        "land",
        "contracting"
    ],
    "wof:name":"Sunny Side Builders & Realty",
    "wof:placetype":"venue"
},
  "geometry": {"coordinates":[-88.04934299999999,44.433527],"type":"Point"}
}