{
  "type": "Feature",
  "properties": {
    "iso:country":"US",
    "sg:address":"8340 Co Rd Cp",
    "sg:city":"Beaver Dam",
    "sg:classifiers":[
        {
            "category":"Wholesale",
            "subcategory":"Farm Supplies",
            "type":"Manufacturing & Wholesale Goods"
        }
    ],
    "sg:phone":"+1 920 887 0691",
    "sg:postcode":"53916",
    "sg:province":"WI",
    "wof:name":"Custom Formulated Premixes",
    "wof:placetype":"venue"
},
  "geometry": {"coordinates":[-88.880549,43.499457],"type":"Point"}
}