{
  "type": "Feature",
  "properties": {
    "addr:full":"5734 Halle Ave Neillsville WI 54456",
    "addr:housenumber":"5734",
    "addr:postcode":"54456",
    "addr:street":"Halle Ave",
    "iso:country":"US",
    "sg:address":"5734 Halle Ave",
    "sg:city":"Neillsville",
    "sg:classifiers":[
        {
            "category":"Shopping",
            "subcategory":"Bicycles & Sporting Goods",
            "type":"Retail Goods"
        }
    ],
    "sg:phone":"+1 715 743 6819",
    "sg:postcode":"54456",
    "sg:province":"WI",
    "wof:name":"Larrys Tack",
    "wof:placetype":"venue"
},
  "geometry": {"coordinates":[-90.547815,44.630452],"type":"Point"}
}