{
  "type": "Feature",
  "properties": {
    "iso:country":"US",
    "sg:address":"8170 N Granville Woods Rd",
    "sg:city":"Milwaukee",
    "sg:classifiers":[
        {
            "category":"Home & Garden",
            "subcategory":"Garden Supply",
            "type":"Retail Goods"
        }
    ],
    "sg:phone":"+1 262 242 9100",
    "sg:postcode":"53223",
    "sg:province":"WI",
    "sg:tags":[
        "landscaping",
        "equipment"
    ],
    "wof:name":"Progreen Plus Inc",
    "wof:placetype":"venue"
},
  "geometry": {"coordinates":[-87.996323,43.166084],"type":"Point"}
}