{
  "type": "Feature",
  "properties": {
    "addr:full":"855 S Main St West Bend WI 53095",
    "addr:housenumber":"855",
    "addr:postcode":"53095",
    "addr:street":"S Main St",
    "iso:country":"US",
    "sg:address":"855 S Main St",
    "sg:city":"West Bend",
    "sg:classifiers":[
        {
            "category":"Restaurant",
            "type":"Food & Drink"
        }
    ],
    "sg:phone":"+1 262 306 1199",
    "sg:postcode":"53095",
    "sg:province":"WI",
    "sg:tags":[
        "shop",
        "coffee"
    ],
    "wof:name":"Filling Station Cafe",
    "wof:placetype":"venue"
},
  "geometry": {"coordinates":[-88.180983,43.410414],"type":"Point"}
}