{
  "type": "Feature",
  "properties": {
    "iso:country":"US",
    "sg:address":"1401 Tower Ave",
    "sg:city":"Superior",
    "sg:classifiers":[
        {
            "category":"Banks & Credit Unions",
            "subcategory":"Bank",
            "type":"Services"
        }
    ],
    "sg:phone":"+1 715 395 3199",
    "sg:postcode":"54880",
    "sg:province":"WI",
    "sg:tags":[
        "loan",
        "real estate"
    ],
    "wof:name":"Precision Mortgage",
    "wof:placetype":"venue"
},
  "geometry": {"coordinates":[-92.10390599999999,46.720686],"type":"Point"}
}