{
  "type": "Feature",
  "properties": {
    "addr:full":"3315 W College Ave Appleton WI 54914",
    "addr:housenumber":"3315",
    "addr:postcode":"54914",
    "addr:street":"W College Ave",
    "iso:country":"US",
    "sg:address":"3315 W College Ave",
    "sg:city":"Appleton",
    "sg:classifiers":[
        {
            "category":"Recreation",
            "type":"Entertainment"
        }
    ],
    "sg:phone":"+1 920 830 6567",
    "sg:postcode":"54914",
    "sg:province":"WI",
    "sg:tags":[
        "employee",
        "martial",
        "arts",
        "instruction",
        "security"
    ],
    "wof:name":"Original Martial Systems",
    "wof:placetype":"venue"
},
  "geometry": {"coordinates":[-88.45308199999999,44.261674],"type":"Point"}
}