{
  "type": "Feature",
  "properties": {
    "iso:country":"US",
    "sg:address":"2983 Co Rd F",
    "sg:city":"Montello",
    "sg:classifiers":[
        {
            "category":"Social Services",
            "subcategory":"Adult Care",
            "type":"Services"
        }
    ],
    "sg:phone":"+1 608 297 9088",
    "sg:postcode":"53949",
    "sg:province":"WI",
    "sg:tags":[
        "residential"
    ],
    "wof:name":"Ann Salzwedel Adult Home",
    "wof:placetype":"venue"
},
  "geometry": {"coordinates":[-89.357131,43.74495],"type":"Point"}
}