{
  "type": "Feature",
  "properties": {
    "iso:country":"US",
    "sg:address":"2985 Division Rd",
    "sg:city":"Jackson",
    "sg:classifiers":[
        {
            "category":"Shopping",
            "subcategory":"Clothing, Apparel, & Fashions",
            "type":"Retail Goods"
        }
    ],
    "sg:phone":"+1 262 677 3752",
    "sg:postcode":"53037",
    "sg:province":"WI",
    "sg:tags":[
        "miscellaneous",
        "store",
        "accessory"
    ],
    "wof:name":"Champion Three",
    "wof:placetype":"venue"
},
  "geometry": {"coordinates":[-88.12242500000001,43.294912],"type":"Point"}
}