{
  "type": "Feature",
  "properties": {
    "iso:country":"US",
    "sg:address":"1316 Honeysuckle Ln",
    "sg:city":"Neenah",
    "sg:classifiers":[
        {
            "category":"Real Estate",
            "subcategory":"Real Estate Operator",
            "type":"Services"
        }
    ],
    "sg:phone":"+1 920 725 5754",
    "sg:postcode":"54956",
    "sg:province":"WI",
    "sg:tags":[
        "apartment"
    ],
    "wof:name":"Appleblossom Apartments",
    "wof:placetype":"venue"
},
  "geometry": {"coordinates":[-88.491518,44.157957],"type":"Point"}
}