{
  "type": "Feature",
  "properties": {
    "iso:country":"US",
    "sg:address":"2730 Fell Rd",
    "sg:city":"Madison",
    "sg:classifiers":[
        {
            "category":"Professional",
            "subcategory":"Computer Services",
            "type":"Services"
        }
    ],
    "sg:phone":"+1 608 274 2672",
    "sg:postcode":"53713",
    "sg:province":"WI",
    "sg:tags":[
        "credit",
        "card"
    ],
    "wof:name":"Fifth Third Processing Sltns",
    "wof:placetype":"venue"
},
  "geometry": {"coordinates":[-89.371246,43.03447],"type":"Point"}
}