{
  "type": "Feature",
  "properties": {
    "iso:country":"US",
    "sg:address":"238 W Pulaski St",
    "sg:city":"Pulaski",
    "sg:classifiers":[
        {
            "category":"Restaurant",
            "type":"Food & Drink"
        }
    ],
    "sg:phone":"+1 920 822 1655",
    "sg:postcode":"54162",
    "sg:province":"WI",
    "sg:tags":[
        "eating"
    ],
    "wof:name":"Toozaks Subs & Mexican",
    "wof:placetype":"venue"
},
  "geometry": {"coordinates":[-88.243025,44.672338],"type":"Point"}
}