{
  "type": "Feature",
  "properties": {
    "iso:country":"US",
    "sg:address":"1315 S Hastings Way",
    "sg:city":"Eau Claire",
    "sg:classifiers":[
        {
            "category":"Shopping",
            "subcategory":"Bicycles & Sporting Goods",
            "type":"Retail Goods"
        }
    ],
    "sg:phone":"+1 715 836 6840",
    "sg:postcode":"54701",
    "sg:province":"WI",
    "sg:website":"www.cv-sports.com",
    "wof:name":"Chippewa Valley Sporting Goods",
    "wof:placetype":"venue"
},
  "geometry": {"coordinates":[-91.470177,44.803986],"type":"Point"}
}