{
  "type": "Feature",
  "properties": {
    "addr:full":"1319 Timber Rd Eau Claire WI 54701",
    "addr:housenumber":"1319",
    "addr:postcode":"54701",
    "addr:street":"Timber Rd",
    "iso:country":"US",
    "sg:address":"1319 Timber Rd",
    "sg:city":"Eau Claire",
    "sg:classifiers":[
        {
            "category":"Professional",
            "type":"Services"
        }
    ],
    "sg:phone":"+1 715 833 9968",
    "sg:postcode":"54701",
    "sg:province":"WI",
    "wof:name":"Dutchman 1 LLC",
    "wof:placetype":"venue"
},
  "geometry": {"coordinates":[-91.48120400000001,44.77515],"type":"Point"}
}