{
  "type": "Feature",
  "properties": {
    "addr:full":"2187 21st Ave Rice Lake WI 54868",
    "addr:housenumber":"2187",
    "addr:postcode":"54868",
    "addr:street":"21St Ave",
    "iso:country":"US",
    "sg:address":"2187 21st Ave",
    "sg:city":"Rice Lake",
    "sg:phone":"+1 715 234 8741",
    "sg:postcode":"54868",
    "sg:province":"WI",
    "sg:tags":[
        "farm",
        "field",
        "corn",
        "crop"
    ],
    "wof:name":"Dennis Gonyer",
    "wof:placetype":"venue"
},
  "geometry": {"coordinates":[-91.70801400000001,45.508767],"type":"Point"}
}