{
  "type": "Feature",
  "properties": {
    "iso:country":"US",
    "sg:address":"808 S Worthington St",
    "sg:city":"Oconomowoc",
    "sg:classifiers":[
        {
            "category":"Utilities",
            "subcategory":"Electric",
            "type":"Services"
        },
        {
            "category":"Government",
            "subcategory":"Office",
            "type":"Public Place"
        }
    ],
    "sg:phone":"+1 262 569 3198",
    "sg:postcode":"53066",
    "sg:province":"WI",
    "sg:tags":[
        "govt",
        "city",
        "company"
    ],
    "wof:name":"Oconomowoc Utilities Director",
    "wof:placetype":"venue"
},
  "geometry": {"coordinates":[-88.503183,43.100769],"type":"Point"}
}