{
  "type": "Feature",
  "properties": {
    "iso:country":"US",
    "sg:address":"262 W Main St",
    "sg:city":"Campbellsport",
    "sg:classifiers":[
        {
            "category":"Professional",
            "type":"Services"
        }
    ],
    "sg:phone":"+1 920 533 5839",
    "sg:postcode":"53010",
    "sg:province":"WI",
    "wof:name":"Mystic Wolf",
    "wof:placetype":"venue"
},
  "geometry": {"coordinates":[-88.289034,43.598185],"type":"Point"}
}