{
  "type": "Feature",
  "properties": {
    "iso:country":"US",
    "sg:address":"413 Maple Dr",
    "sg:city":"Sister Bay",
    "sg:classifiers":[
        {
            "category":"Real Estate",
            "subcategory":"Real Estate Agent",
            "type":"Services"
        }
    ],
    "sg:phone":"+1 920 854 4699",
    "sg:postcode":"54234",
    "sg:province":"WI",
    "sg:tags":[
        "inspection"
    ],
    "wof:name":"Second Opinion",
    "wof:placetype":"venue"
},
  "geometry": {"coordinates":[-87.12451799999999,45.188066],"type":"Point"}
}