{
  "type": "Feature",
  "properties": {
    "addr:full":"7393 Spring Valley Dr Greenville WI 54942",
    "addr:housenumber":"7393",
    "addr:postcode":"54942",
    "addr:street":"Spring Valley Dr",
    "iso:country":"US",
    "sg:address":"7393 Spring Valley Dr",
    "sg:city":"Greenville",
    "sg:classifiers":[
        {
            "category":"Banks & Credit Unions",
            "subcategory":"Financial Services",
            "type":"Services"
        }
    ],
    "sg:phone":"+1 920 757 7733",
    "sg:postcode":"54942",
    "sg:province":"WI",
    "sg:tags":[
        "trust",
        "investment",
        "real estate"
    ],
    "wof:name":"Csw Investments Inc",
    "wof:placetype":"venue"
},
  "geometry": {"coordinates":[-88.57161499999999,44.277469],"type":"Point"}
}