{
  "type": "Feature",
  "properties": {
    "iso:country":"US",
    "sg:address":"2555 7th St S",
    "sg:city":"La Crosse",
    "sg:classifiers":[
        {
            "category":"Social Services",
            "subcategory":"Adult Care",
            "type":"Services"
        }
    ],
    "sg:phone":"+1 608 775 8280",
    "sg:postcode":"54601",
    "sg:province":"WI",
    "sg:tags":[
        "home",
        "residential"
    ],
    "wof:name":"Willows Assisted Living",
    "wof:placetype":"venue"
},
  "geometry": {"coordinates":[-91.247002,43.786313],"type":"Point"}
}