{
  "type": "Feature",
  "properties": {
    "iso:country":"US",
    "sg:address":"612 1st St S",
    "sg:city":"Ladysmith",
    "sg:classifiers":[
        {
            "category":"Shopping",
            "subcategory":"Clothing, Apparel, & Fashions",
            "type":"Retail Goods"
        }
    ],
    "sg:phone":"+1 715 532 5786",
    "sg:postcode":"54848",
    "sg:province":"WI",
    "sg:tags":[
        "tailor"
    ],
    "wof:name":"Three Mice Tailoring Shoppe",
    "wof:placetype":"venue"
},
  "geometry": {"coordinates":[-91.101103,45.459362],"type":"Point"}
}