{
  "type": "Feature",
  "properties": {
    "iso:country":"US",
    "sg:address":"5500 W Morgan Ave",
    "sg:city":"Milwaukee",
    "sg:classifiers":[
        {
            "category":"Autos & Motor Vehicles",
            "subcategory":"Automobile Sales",
            "type":"Retail Goods"
        }
    ],
    "sg:phone":"+1 414 543 5604",
    "sg:postcode":"53220",
    "sg:province":"WI",
    "sg:tags":[
        "equipment",
        "aircraft",
        "parts",
        "supply"
    ],
    "wof:name":"Arcom Enterprises Inc",
    "wof:placetype":"venue"
},
  "geometry": {"coordinates":[-87.984174,42.981154],"type":"Point"}
}