{
  "type": "Feature",
  "properties": {
    "iso:country":"US",
    "sg:address":"540 College St",
    "sg:city":"Medford",
    "sg:classifiers":[
        {
            "category":"Government",
            "subcategory":"Office",
            "type":"Public Place"
        }
    ],
    "sg:phone":"+1 715 748 1491",
    "sg:postcode":"54451",
    "sg:province":"WI",
    "sg:tags":[
        "county",
        "resource"
    ],
    "wof:name":"Commission On Aging",
    "wof:placetype":"venue"
},
  "geometry": {"coordinates":[-90.336995,45.129873],"type":"Point"}
}