{
  "type": "Feature",
  "properties": {
    "addr:full":"635 S Bay Shore Dr Sister Bay WI 54234",
    "addr:housenumber":"635",
    "addr:postcode":"54234",
    "addr:street":"S Bay Shore Dr",
    "iso:country":"US",
    "sg:address":"635 S Bay Shore Dr",
    "sg:city":"Sister Bay",
    "sg:classifiers":[
        {
            "category":"Retail",
            "subcategory":"Auto Repair",
            "type":"Services"
        }
    ],
    "sg:phone":"+1 920 854 4016",
    "sg:postcode":"54234",
    "sg:province":"WI",
    "sg:tags":[
        "repairing",
        "automobile"
    ],
    "wof:name":"Voight Automotive",
    "wof:placetype":"venue"
},
  "geometry": {"coordinates":[-87.126144,45.185483],"type":"Point"}
}