{
  "type": "Feature",
  "properties": {
    "iso:country":"US",
    "sg:address":"1569 Co Hwy A",
    "sg:city":"West Bend",
    "sg:classifiers":[
        {
            "category":"Building & Trades",
            "subcategory":"Construction",
            "type":"Services"
        }
    ],
    "sg:phone":"+1 262 692 2548",
    "sg:postcode":"53090",
    "sg:province":"WI",
    "sg:tags":[
        "insulation",
        "heat",
        "contractor"
    ],
    "wof:name":"Quality Insulation",
    "wof:placetype":"venue"
},
  "geometry": {"coordinates":[-88.119986,43.468878],"type":"Point"}
}