{
  "type": "Feature",
  "properties": {
    "addr:full":"146 E Towne Mall Madison WI 53704",
    "addr:housenumber":"146",
    "addr:postcode":"53704",
    "addr:street":"E Towne Mall",
    "iso:country":"US",
    "sg:address":"146 E Towne Mall",
    "sg:city":"Madison",
    "sg:classifiers":[
        {
            "category":"Shopping",
            "subcategory":"Clothing, Apparel, & Fashions",
            "type":"Retail Goods"
        }
    ],
    "sg:phone":"+1 608 241 1127",
    "sg:postcode":"53704",
    "sg:province":"WI",
    "wof:name":"Maurice's",
    "wof:placetype":"venue"
},
  "geometry": {"coordinates":[-89.3044,43.12818],"type":"Point"}
}