{
  "type": "Feature",
  "properties": {
    "iso:country":"US",
    "sg:address":"1003 S Hillcrest Pkwy",
    "sg:city":"Altoona",
    "sg:classifiers":[
        {
            "category":"Insurance",
            "subcategory":"Insurance Agent",
            "type":"Services"
        }
    ],
    "sg:phone":"+1 715 855 0206",
    "sg:postcode":"54720",
    "sg:province":"WI",
    "wof:name":"Catholic Knights",
    "wof:placetype":"venue"
},
  "geometry": {"coordinates":[-91.427292,44.793181],"type":"Point"}
}