{
  "type": "Feature",
  "properties": {
    "iso:country":"US",
    "sg:address":"259 Sky Lane Dr",
    "sg:city":"Lake Geneva",
    "sg:classifiers":[
        {
            "category":"Utilities",
            "subcategory":"Telephone",
            "type":"Services"
        }
    ],
    "sg:phone":"+1 262 348 9193",
    "sg:postcode":"53147",
    "sg:province":"WI",
    "sg:tags":[
        "communications"
    ],
    "wof:name":"Smithlewis Inc",
    "wof:placetype":"venue"
},
  "geometry": {"coordinates":[-88.449195,42.591411],"type":"Point"}
}