{
  "type": "Feature",
  "properties": {
    "addr:full":"1223 S 92nd St Milwaukee WI 53214",
    "addr:housenumber":"1223",
    "addr:postcode":"53214",
    "addr:street":"S 92Nd St",
    "iso:country":"US",
    "sg:address":"1223 S 92nd St",
    "sg:city":"Milwaukee",
    "sg:classifiers":[
        {
            "category":"Real Estate",
            "subcategory":"Real Estate Agent",
            "type":"Services"
        }
    ],
    "sg:phone":"+1 414 258 0393",
    "sg:postcode":"53214",
    "sg:province":"WI",
    "wof:name":"Reese & Odya Properties",
    "wof:placetype":"venue"
},
  "geometry": {"coordinates":[-88.02730099999999,43.016706],"type":"Point"}
}