{
  "type": "Feature",
  "properties": {
    "addr:full":"11 N 7th St Madison WI 53704",
    "addr:housenumber":"11",
    "addr:postcode":"53704",
    "addr:street":"N 7Th St",
    "iso:country":"US",
    "sg:address":"11 N 7th St",
    "sg:city":"Madison",
    "sg:classifiers":[
        {
            "category":"Organizations",
            "subcategory":"Religious Organization",
            "type":"Services"
        }
    ],
    "sg:phone":"+1 608 244 1001",
    "sg:postcode":"53704",
    "sg:province":"WI",
    "wof:name":"Greek Orthodox Church",
    "wof:placetype":"venue"
},
  "geometry": {"coordinates":[-89.350573,43.100333],"type":"Point"}
}