{
  "type": "Feature",
  "properties": {
    "iso:country":"US",
    "sg:address":"807 5th Ave",
    "sg:city":"Antigo",
    "sg:classifiers":[
        {
            "category":"Government",
            "subcategory":"Office",
            "type":"Public Place"
        }
    ],
    "sg:phone":"+1 715 623 3930",
    "sg:postcode":"54409",
    "sg:province":"WI",
    "sg:tags":[
        "state",
        "program"
    ],
    "wof:name":"Agriculture-Fruit & Vegetable",
    "wof:placetype":"venue"
},
  "geometry": {"coordinates":[-89.15613999999999,45.140497],"type":"Point"}
}