{
  "type": "Feature",
  "properties": {
    "iso:country":"US",
    "sg:address":"1433 Paines Pt Rd",
    "sg:city":"Neenah",
    "sg:classifiers":[
        {
            "category":"Retail",
            "subcategory":"Repair Shop",
            "type":"Services"
        }
    ],
    "sg:phone":"+1 920 725 0479",
    "sg:postcode":"54956",
    "sg:province":"WI",
    "sg:tags":[
        "repairing",
        "lawn",
        "mower"
    ],
    "wof:name":"Inda Small Engine & Equipment",
    "wof:placetype":"venue"
},
  "geometry": {"coordinates":[-88.46937800000001,44.123849],"type":"Point"}
}