{
  "type": "Feature",
  "properties": {
    "addr:full":"1908 Grand Ave Wausau WI 54403",
    "addr:housenumber":"1908",
    "addr:postcode":"54403",
    "addr:street":"Grand Ave",
    "iso:country":"US",
    "sg:address":"1908 Grand Ave",
    "sg:city":"Wausau",
    "sg:classifiers":[
        {
            "category":"Professional",
            "type":"Services"
        }
    ],
    "sg:phone":"+1 715 848 0111",
    "sg:postcode":"54403",
    "sg:province":"WI",
    "sg:tags":[
        "weather",
        "consulting",
        "management",
        "forecast"
    ],
    "sg:website":"www.greatlakesweatherserv.com",
    "wof:name":"Great Lakes Weather Service",
    "wof:placetype":"venue"
},
  "geometry": {"coordinates":[-89.617214,44.936251],"type":"Point"}
}