{
  "type": "Feature",
  "properties": {
    "iso:country":"US",
    "sg:address":"1959 S 124th St",
    "sg:city":"New Berlin",
    "sg:classifiers":[
        {
            "category":"Bars & Pubs",
            "type":"Food & Drink"
        }
    ],
    "sg:phone":"+1 262 782 8960",
    "sg:postcode":"53151",
    "sg:province":"WI",
    "wof:name":"Pendulum Pub",
    "wof:placetype":"venue"
},
  "geometry": {"coordinates":[-88.067568,43.007878],"type":"Point"}
}