{
  "type": "Feature",
  "properties": {
    "iso:country":"US",
    "sg:address":"1197 Co Rd B",
    "sg:city":"Mosinee",
    "sg:classifiers":[
        {
            "category":"Manufacturing",
            "subcategory":"Retail Goods",
            "type":"Manufacturing & Wholesale Goods"
        }
    ],
    "sg:phone":"+1 715 693 0909",
    "sg:postcode":"54455",
    "sg:province":"WI",
    "sg:tags":[
        "manufacturer"
    ],
    "wof:name":"R D Industries",
    "wof:placetype":"venue"
},
  "geometry": {"coordinates":[-89.709113,44.797157],"type":"Point"}
}