{
  "type": "Feature",
  "properties": {
    "iso:country":"US",
    "sg:address":"3633 N 124th St",
    "sg:city":"Brookfield",
    "sg:classifiers":[
        {
            "category":"Banks & Credit Unions",
            "subcategory":"Bank",
            "type":"Services"
        }
    ],
    "sg:phone":"+1 262 781 1904",
    "sg:postcode":"53222",
    "sg:province":"WI",
    "sg:tags":[
        "correspondent",
        "banker",
        "mortgage"
    ],
    "wof:name":"Sunset Mortgage Company Limit",
    "wof:placetype":"venue"
},
  "geometry": {"coordinates":[-88.066301,43.085685],"type":"Point"}
}