{
  "type": "Feature",
  "properties": {
    "iso:country":"US",
    "sg:address":"611 N Lynndale Dr",
    "sg:city":"Neenah",
    "sg:classifiers":[
        {
            "category":"Professional",
            "subcategory":"Management & Consulting",
            "type":"Services"
        }
    ],
    "sg:phone":"+1 920 725 5161",
    "sg:postcode":"54914",
    "sg:province":"WI",
    "sg:tags":[
        "consultant",
        "agency",
        "advertising",
        "business"
    ],
    "wof:name":"Bilotta Communications",
    "wof:placetype":"venue"
},
  "geometry": {"coordinates":[-88.445971,44.26247],"type":"Point"}
}