{
  "type": "Feature",
  "properties": {
    "iso:country":"US",
    "sg:address":"6787 Sunset Meadow Dr",
    "sg:city":"Windsor",
    "sg:classifiers":[
        {
            "category":"Home & Garden",
            "subcategory":"Home Furnishings",
            "type":"Retail Goods"
        }
    ],
    "sg:phone":"+1 608 334 6739",
    "sg:postcode":"53598",
    "sg:province":"WI",
    "sg:tags":[
        "curtain",
        "made",
        "drapery"
    ],
    "wof:name":"Sew-N-Go",
    "wof:placetype":"venue"
},
  "geometry": {"coordinates":[-89.337254,43.219446],"type":"Point"}
}