{
  "type": "Feature",
  "properties": {
    "iso:country":"US",
    "sg:address":"5979 Loghouse Rd",
    "sg:city":"Hartford",
    "sg:classifiers":[
        {
            "category":"Professional",
            "subcategory":"Computer Services",
            "type":"Services"
        }
    ],
    "sg:phone":"+1 262 670 0439",
    "sg:postcode":"53027",
    "sg:province":"WI",
    "sg:tags":[
        "consultant",
        "designer"
    ],
    "wof:name":"162 Solutions Group",
    "wof:placetype":"venue"
},
  "geometry": {"coordinates":[-88.336659,43.274751],"type":"Point"}
}