{
  "type": "Feature",
  "properties": {
    "iso:country":"US",
    "sg:address":"2757 220th Ave",
    "sg:city":"Deer Park",
    "sg:classifiers":[
        {
            "category":"Farming",
            "subcategory":"Farm",
            "type":"Manufacturing & Wholesale Goods"
        }
    ],
    "sg:phone":"+1 715 263 3140",
    "sg:postcode":"54007",
    "sg:province":"WI",
    "sg:tags":[
        "crop",
        "general"
    ],
    "wof:name":"Sally Sanftner Farm",
    "wof:placetype":"venue"
},
  "geometry": {"coordinates":[-92.249184,45.18003],"type":"Point"}
}