{
  "type": "Feature",
  "properties": {
    "iso:country":"US",
    "sg:address":"11010 W Hampton Ave",
    "sg:city":"Milwaukee",
    "sg:classifiers":[
        {
            "category":"Education",
            "subcategory":"College",
            "type":"Public Place"
        },
        {
            "category":"Education",
            "subcategory":"Vocational School",
            "type":"Public Place"
        },
        {
            "category":"Education",
            "subcategory":"School",
            "type":"Public Place"
        },
        {
            "category":"Education",
            "subcategory":"University",
            "type":"Public Place"
        }
    ],
    "sg:phone":"+1 414 967 2000",
    "sg:postcode":"53225",
    "sg:province":"WI",
    "sg:tags":[
        "business",
        "beauty"
    ],
    "sg:website":"http://www.vicicapilli.com",
    "wof:name":"Vici Beauty School",
    "wof:placetype":"venue"
},
  "geometry": {"coordinates":[-88.049488,43.104897],"type":"Point"}
}