{
  "type": "Feature",
  "properties": {
    "addr:full":"1209 S 41st St Manitowoc WI 54220",
    "addr:housenumber":"1209",
    "addr:postcode":"54220",
    "addr:street":"S 41St St",
    "iso:country":"US",
    "sg:address":"1209 S 41st St",
    "sg:city":"Manitowoc",
    "sg:classifiers":[
        {
            "category":"Wholesale",
            "subcategory":"Machinery & Supplies",
            "type":"Manufacturing & Wholesale Goods"
        }
    ],
    "sg:phone":"+1 920 684 4911",
    "sg:postcode":"54220",
    "sg:province":"WI",
    "sg:tags":[
        "construction",
        "fastener",
        "industrial",
        "suppl",
        "threaded"
    ],
    "wof:name":"Fastenal Company",
    "wof:placetype":"venue"
},
  "geometry": {"coordinates":[-87.69904200000001,44.080614],"type":"Point"}
}