{
  "type": "Feature",
  "properties": {
    "iso:country":"US",
    "sg:address":"11817 Highland Rd",
    "sg:city":"Antigo",
    "sg:classifiers":[
        {
            "category":"Sports & Exercise",
            "subcategory":"Golf",
            "type":"Entertainment"
        }
    ],
    "sg:phone":"+1 715 623 2663",
    "sg:postcode":"54409",
    "sg:province":"WI",
    "sg:tags":[
        "course"
    ],
    "wof:name":"Riverview Golf /Course",
    "wof:placetype":"venue"
},
  "geometry": {"coordinates":[-89.249916,45.14035],"type":"Point"}
}