{
  "type": "Feature",
  "properties": {
    "iso:country":"US",
    "sg:address":"3447 S 93rd St",
    "sg:city":"Milwaukee",
    "sg:classifiers":[
        {
            "category":"Building & Trades",
            "subcategory":"Electrical",
            "type":"Services"
        }
    ],
    "sg:phone":"+1 414 546 2998",
    "sg:postcode":"53227",
    "sg:province":"WI",
    "sg:tags":[
        "electric",
        "industrial",
        "contractors-commercial",
        "contractor"
    ],
    "wof:name":"Mrotek Electric",
    "wof:placetype":"venue"
},
  "geometry": {"coordinates":[-88.029121,42.984811],"type":"Point"}
}