{
  "type": "Feature",
  "properties": {
    "iso:country":"US",
    "sg:address":"221 Camp Rd",
    "sg:city":"Fairchild",
    "sg:classifiers":[
        {
            "category":"Building & Trades",
            "subcategory":"Construction",
            "type":"Services"
        }
    ],
    "sg:phone":"+1 715 334 2907",
    "sg:postcode":"54741",
    "sg:province":"WI",
    "wof:name":"D JS Construction",
    "wof:placetype":"venue"
},
  "geometry": {"coordinates":[-90.947445,44.607054],"type":"Point"}
}