{
  "type": "Feature",
  "properties": {
    "iso:country":"US",
    "sg:address":"2997 Stamford Pl",
    "sg:city":"Fitchburg",
    "sg:classifiers":[
        {
            "category":"Home & Garden",
            "subcategory":"Building Materials",
            "type":"Retail Goods"
        }
    ],
    "sg:phone":"+1 608 270 0053",
    "sg:postcode":"53711",
    "sg:province":"WI",
    "sg:tags":[
        "roofing"
    ],
    "wof:name":"Sarnafil",
    "wof:placetype":"venue"
},
  "geometry": {"coordinates":[-89.433803,43.016946],"type":"Point"}
}