{
  "type": "Feature",
  "properties": {
    "iso:country":"US",
    "sg:address":"731 Amy Belle Lake Rd",
    "sg:city":"Hubertus",
    "sg:classifiers":[
        {
            "category":"Wholesale",
            "subcategory":"Machinery & Supplies",
            "type":"Manufacturing & Wholesale Goods"
        }
    ],
    "sg:phone":"+1 262 628 4360",
    "sg:postcode":"53033",
    "sg:province":"WI",
    "sg:tags":[
        "equipment",
        "industry",
        "ma",
        "mfg"
    ],
    "wof:name":"Badger State Equipment Co",
    "wof:placetype":"venue"
},
  "geometry": {"coordinates":[-88.189311,43.214941],"type":"Point"}
}