{
  "type": "Feature",
  "properties": {
    "addr:full":"430 Gulch Ave Wisconsin Dells WI 53965",
    "addr:housenumber":"430",
    "addr:postcode":"53965",
    "addr:street":"Gulch Ave",
    "iso:country":"US",
    "sg:address":"430 Gulch Ave",
    "sg:city":"Wisconsin Dells",
    "sg:classifiers":[
        {
            "category":"Building & Trades",
            "subcategory":"Construction",
            "type":"Services"
        }
    ],
    "sg:phone":"+1 608 254 7654",
    "sg:postcode":"53965",
    "sg:province":"WI",
    "sg:tags":[
        "house"
    ],
    "wof:name":"Hoege & Son Const",
    "wof:placetype":"venue"
},
  "geometry": {"coordinates":[-89.668623,43.643043],"type":"Point"}
}