{
  "type": "Feature",
  "properties": {
    "iso:country":"US",
    "sg:address":"1358 Timber Trl",
    "sg:city":"Suamico",
    "sg:classifiers":[
        {
            "category":"Building & Trades",
            "subcategory":"Construction",
            "type":"Services"
        }
    ],
    "sg:phone":"+1 920 434 1725",
    "sg:postcode":"54173",
    "sg:province":"WI",
    "sg:tags":[
        "contractor"
    ],
    "wof:name":"Mathena Roofing",
    "wof:placetype":"venue"
},
  "geometry": {"coordinates":[-88.039393,44.644608],"type":"Point"}
}