{
  "type": "Feature",
  "properties": {
    "iso:country":"US",
    "sg:address":"3214 US Hwy 12",
    "sg:city":"Baraboo",
    "sg:classifiers":[
        {
            "category":"Professional",
            "type":"Services"
        }
    ],
    "sg:phone":"+1 608 355 2338",
    "sg:postcode":"53913",
    "sg:province":"WI",
    "sg:tags":[
        "establishment"
    ],
    "wof:name":"Cost Inc Of Wisconsin",
    "wof:placetype":"venue"
},
  "geometry": {"coordinates":[-89.77782999999999,43.528504],"type":"Point"}
}