{
  "type": "Feature",
  "properties": {
    "iso:country":"US",
    "sg:address":"5148 Holcomb Ln",
    "sg:city":"Monticello",
    "sg:classifiers":[
        {
            "category":"Farming",
            "subcategory":"Dairy Farm",
            "type":"Manufacturing & Wholesale Goods"
        }
    ],
    "sg:phone":"+1 608 938 4725",
    "sg:postcode":"53570",
    "sg:province":"WI",
    "wof:name":"Ronald Holcomb",
    "wof:placetype":"venue"
},
  "geometry": {"coordinates":[-89.61315399999999,42.72728],"type":"Point"}
}