{
  "type": "Feature",
  "properties": {
    "addr:full":"312 W Columbia St Chippewa Falls WI 54729",
    "addr:housenumber":"312",
    "addr:postcode":"54729",
    "addr:street":"W Columbia St",
    "iso:country":"US",
    "sg:address":"312 W Columbia St",
    "sg:city":"Chippewa Falls",
    "sg:classifiers":[
        {
            "category":"Travel",
            "subcategory":"Hotels & Motels",
            "type":"Entertainment"
        }
    ],
    "sg:phone":"+1 715 720 1600",
    "sg:postcode":"54729",
    "sg:province":"WI",
    "sg:tags":[
        "breakfast",
        "accommodation",
        "bed"
    ],
    "sg:website":"www.mcgilvraysbb.com",
    "wof:name":"Mc Gilvray's Victorian B & B",
    "wof:placetype":"venue"
},
  "geometry": {"coordinates":[-91.399384,44.934584],"type":"Point"}
}