{
  "type": "Feature",
  "properties": {
    "iso:country":"US",
    "sg:address":"12634 40th Ave",
    "sg:city":"Chippewa Falls",
    "sg:classifiers":[
        {
            "category":"Shopping",
            "subcategory":"Used Merchandise",
            "type":"Retail Goods"
        }
    ],
    "sg:phone":"+1 715 723 7916",
    "sg:postcode":"54729",
    "sg:province":"WI",
    "sg:tags":[
        "shop",
        "consignment"
    ],
    "wof:name":"Bearly Worn",
    "wof:placetype":"venue"
},
  "geometry": {"coordinates":[-91.415422,44.900833],"type":"Point"}
}