{
  "type": "Feature",
  "properties": {
    "iso:country":"US",
    "sg:address":"503 Mill St",
    "sg:city":"Green Lake",
    "sg:classifiers":[
        {
            "category":"Real Estate",
            "subcategory":"Real Estate Services",
            "type":"Services"
        }
    ],
    "sg:phone":"+1 920 294 6056",
    "sg:postcode":"54941",
    "sg:province":"WI",
    "sg:tags":[
        "company",
        "title"
    ],
    "wof:name":"Mid State Abstract & Title",
    "wof:placetype":"venue"
},
  "geometry": {"coordinates":[-88.96016400000001,43.845015],"type":"Point"}
}