{
  "type": "Feature",
  "properties": {
    "iso:country":"US",
    "sg:address":"5660 Pioneer Rd",
    "sg:city":"Cedarburg",
    "sg:classifiers":[
        {
            "category":"Wholesale",
            "subcategory":"Non-durable Goods",
            "type":"Manufacturing & Wholesale Goods"
        }
    ],
    "sg:phone":"+1 262 375 4806",
    "sg:postcode":"53012",
    "sg:province":"WI",
    "wof:name":"Lh Inter Pacific Trade",
    "wof:placetype":"venue"
},
  "geometry": {"coordinates":[-87.979811,43.279543],"type":"Point"}
}