{
  "type": "Feature",
  "properties": {
    "iso:country":"US",
    "sg:address":"14259 Tower Ct",
    "sg:city":"Mountain",
    "sg:classifiers":[
        {
            "category":"Retail",
            "subcategory":"Repair Shop",
            "type":"Services"
        }
    ],
    "sg:phone":"+1 715 276 7812",
    "sg:postcode":"54149",
    "sg:province":"WI",
    "sg:tags":[
        "pump"
    ],
    "wof:name":"Lloyd's Mountain Pump Svc",
    "wof:placetype":"venue"
},
  "geometry": {"coordinates":[-88.47224799999999,45.208262],"type":"Point"}
}