{
  "type": "Feature",
  "properties": {
    "iso:country":"US",
    "sg:address":"4177 Lake Dr",
    "sg:city":"Brodhead",
    "sg:classifiers":[
        {
            "category":"Banks & Credit Unions",
            "subcategory":"Financial Services",
            "type":"Services"
        }
    ],
    "sg:phone":"+1 608 862 7777",
    "sg:postcode":"53520",
    "sg:province":"WI",
    "sg:tags":[
        "investor"
    ],
    "wof:name":"Rcs Properties LLC",
    "wof:placetype":"venue"
},
  "geometry": {"coordinates":[-89.414599,42.655131],"type":"Point"}
}