{
  "type": "Feature",
  "properties": {
    "addr:full":"5729 Forsythia Pl Madison WI 53705",
    "addr:housenumber":"5729",
    "addr:postcode":"53705",
    "addr:street":"Forsythia Pl",
    "iso:country":"US",
    "sg:address":"5729 Forsythia Pl",
    "sg:city":"Madison",
    "sg:classifiers":[
        {
            "category":"Professional",
            "subcategory":"Business Services",
            "type":"Services"
        }
    ],
    "sg:phone":"+1 608 238 6092",
    "sg:postcode":"53705",
    "sg:province":"WI",
    "wof:name":"Light & Shadow Inc",
    "wof:placetype":"venue"
},
  "geometry": {"coordinates":[-89.48156,43.069671],"type":"Point"}
}