{
  "type": "Feature",
  "properties": {
    "iso:country":"US",
    "sg:address":"1348 Spaight St",
    "sg:city":"Madison",
    "sg:classifiers":[
        {
            "category":"Professional",
            "type":"Services"
        }
    ],
    "sg:phone":"+1 608 256 8934",
    "sg:postcode":"53703",
    "sg:province":"WI",
    "sg:tags":[
        "magnetic",
        "datum",
        "mfg"
    ],
    "wof:name":"Longhair Mp3com",
    "wof:placetype":"venue"
},
  "geometry": {"coordinates":[-89.35989600000001,43.0839],"type":"Point"}
}