{
  "type": "Feature",
  "properties": {
    "iso:country":"US",
    "sg:address":"1922 Wisconsin Ave",
    "sg:city":"New Holstein",
    "sg:classifiers":[
        {
            "category":"Organizations",
            "subcategory":"Community Association",
            "type":"Services"
        }
    ],
    "sg:phone":"+1 920 898 5135",
    "sg:postcode":"53061",
    "sg:province":"WI",
    "sg:tags":[
        "military"
    ],
    "wof:name":"American Legion",
    "wof:placetype":"venue"
},
  "geometry": {"coordinates":[-88.090946,43.949841],"type":"Point"}
}