{
  "type": "Feature",
  "properties": {
    "iso:country":"US",
    "sg:address":"1300 Capitol Dr",
    "sg:city":"Pewaukee",
    "sg:classifiers":[
        {
            "category":"Shopping",
            "subcategory":"Clothing, Apparel, & Fashions",
            "type":"Retail Goods"
        }
    ],
    "sg:phone":"+1 262 695 2266",
    "sg:postcode":"53072",
    "sg:province":"WI",
    "wof:name":"Divna",
    "wof:placetype":"venue"
},
  "geometry": {"coordinates":[-88.23077000000001,43.083242],"type":"Point"}
}