{
  "type": "Feature",
  "properties": {
    "iso:country":"US",
    "sg:address":"203 W Grant St",
    "sg:city":"Montfort",
    "sg:classifiers":[
        {
            "category":"Retail",
            "subcategory":"Funeral Services",
            "type":"Services"
        }
    ],
    "sg:phone":"+1 608 943 6906",
    "sg:postcode":"53569",
    "sg:province":"WI",
    "sg:tags":[
        "director"
    ],
    "wof:name":"Soman-Larson Funeral Home",
    "wof:placetype":"venue"
},
  "geometry": {"coordinates":[-90.434611,42.968496],"type":"Point"}
}