{
  "type": "Feature",
  "properties": {
    "addr:full":"2125 S Schaefer St Appleton WI 54915",
    "addr:housenumber":"2125",
    "addr:postcode":"54915",
    "addr:street":"S Schaefer St",
    "iso:country":"US",
    "sg:address":"2125 S Schaefer St",
    "sg:city":"Appleton",
    "sg:classifiers":[
        {
            "category":"Recreation",
            "type":"Entertainment"
        }
    ],
    "sg:phone":"+1 920 733 3444",
    "sg:postcode":"54915",
    "sg:province":"WI",
    "sg:tags":[
        "martial",
        "arts",
        "instruction"
    ],
    "sg:website":"www.kaaeast.com",
    "wof:name":"Karate America",
    "wof:placetype":"venue"
},
  "geometry": {"coordinates":[-88.375293,44.24294],"type":"Point"}
}