{
  "type": "Feature",
  "properties": {
    "iso:country":"US",
    "sg:address":"101 Division St",
    "sg:city":"Stevens Point",
    "sg:classifiers":[
        {
            "category":"Personal",
            "subcategory":"Tanning Parlor",
            "type":"Services"
        },
        {
            "category":"Personal",
            "type":"Services"
        }
    ],
    "sg:phone":"+1 715 342 1722",
    "sg:postcode":"54481",
    "sg:province":"WI",
    "sg:tags":[
        "salon"
    ],
    "wof:name":"Hawaiian Tanning Studios",
    "wof:placetype":"venue"
},
  "geometry": {"coordinates":[-89.574974,44.535491],"type":"Point"}
}