{
  "type": "Feature",
  "properties": {
    "iso:country":"US",
    "sg:address":"600 Lac la Belle Dr",
    "sg:city":"Oconomowoc",
    "sg:classifiers":[
        {
            "category":"Travel",
            "subcategory":"Campground",
            "type":"Entertainment"
        }
    ],
    "sg:phone":"+1 262 567 6277",
    "sg:postcode":"53066",
    "sg:province":"WI",
    "sg:tags":[
        "camp"
    ],
    "wof:name":"Union Institute UAHC",
    "wof:placetype":"venue"
},
  "geometry": {"coordinates":[-88.532417,43.143505],"type":"Point"}
}