{
  "type": "Feature",
  "properties": {
    "iso:country":"US",
    "sg:address":"37460 US Hwy 18",
    "sg:city":"Prairie Du Chien",
    "sg:classifiers":[
        {
            "category":"Retail",
            "subcategory":"Veterinary Services",
            "type":"Services"
        }
    ],
    "sg:phone":"+1 608 326 6464",
    "sg:postcode":"53821",
    "sg:province":"WI",
    "sg:tags":[
        "veterinarian"
    ],
    "wof:name":"Southwest Veterinary Svc",
    "wof:placetype":"venue"
},
  "geometry": {"coordinates":[-91.12421999999999,43.026133],"type":"Point"}
}