{
  "type": "Feature",
  "properties": {
    "iso:country":"US",
    "sg:address":"71 E Albert Dr",
    "sg:city":"Manitowoc",
    "sg:classifiers":[
        {
            "category":"Freight",
            "type":"Transportation"
        }
    ],
    "sg:phone":"+1 920 682 8820",
    "sg:postcode":"54220",
    "sg:province":"WI",
    "wof:name":"Assist To Transport",
    "wof:placetype":"venue"
},
  "geometry": {"coordinates":[-87.648933,44.124505],"type":"Point"}
}