{
  "type": "Feature",
  "properties": {
    "iso:country":"US",
    "sg:address":"7628 W Florist Ave",
    "sg:city":"Milwaukee",
    "sg:classifiers":[
        {
            "category":"Manufacturing",
            "subcategory":"Tools & Machinery",
            "type":"Manufacturing & Wholesale Goods"
        }
    ],
    "sg:phone":"+1 414 466 5200",
    "sg:postcode":"53218",
    "sg:province":"WI",
    "sg:tags":[
        "filter",
        "pump",
        "industrial",
        "mfg"
    ],
    "wof:name":"Sepermatic Fluid Systems",
    "wof:placetype":"venue"
},
  "geometry": {"coordinates":[-88.00688599999999,43.126939],"type":"Point"}
}