{
  "type": "Feature",
  "properties": {
    "iso:country":"US",
    "sg:address":"120 Bishop Ave",
    "sg:city":"Plymouth",
    "sg:classifiers":[
        {
            "category":"Wholesale",
            "subcategory":"Metals & Minerals",
            "type":"Manufacturing & Wholesale Goods"
        }
    ],
    "sg:phone":"+1 920 892 2229",
    "sg:postcode":"53073",
    "sg:province":"WI",
    "sg:tags":[
        "center"
    ],
    "wof:name":"Iron Lily Forge LLC",
    "wof:placetype":"venue"
},
  "geometry": {"coordinates":[-87.965721,43.748083],"type":"Point"}
}