{
  "type": "Feature",
  "properties": {
    "addr:full":"128 Elm St Dousman WI 53118",
    "addr:housenumber":"128",
    "addr:postcode":"53118",
    "addr:street":"Elm St",
    "iso:country":"US",
    "sg:address":"128 Elm St",
    "sg:city":"Dousman",
    "sg:classifiers":[
        {
            "category":"Wholesale",
            "subcategory":"Hardware",
            "type":"Manufacturing & Wholesale Goods"
        },
        {
            "category":"Professional",
            "subcategory":"Research",
            "type":"Services"
        }
    ],
    "sg:phone":"+1 262 965 4366",
    "sg:postcode":"53118",
    "sg:province":"WI",
    "sg:tags":[
        "environmental",
        "ecological"
    ],
    "wof:name":"Clean Air & Water Systems LLC",
    "wof:placetype":"venue"
},
  "geometry": {"coordinates":[-88.472009,43.014176],"type":"Point"}
}