{
  "type": "Feature",
  "properties": {
    "iso:country":"US",
    "sg:address":"2159 N 73rd St",
    "sg:city":"Milwaukee",
    "sg:classifiers":[
        {
            "category":"Personal",
            "subcategory":"Beauty Salon",
            "type":"Services"
        }
    ],
    "sg:phone":"+1 414 771 5838",
    "sg:postcode":"53213",
    "sg:province":"WI",
    "sg:tags":[
        "shop"
    ],
    "wof:name":"Cullens Hair Design Inc",
    "wof:placetype":"venue"
},
  "geometry": {"coordinates":[-88.003518,43.057801],"type":"Point"}
}