{
  "type": "Feature",
  "properties": {
    "addr:full":"23 W 5th Ave Shell Lake WI 54871",
    "addr:housenumber":"23",
    "addr:postcode":"54871",
    "addr:street":"W 5Th Ave",
    "iso:country":"US",
    "sg:address":"23 W 5th Ave",
    "sg:city":"Shell Lake",
    "sg:classifiers":[
        {
            "category":"Building & Trades",
            "subcategory":"Construction",
            "type":"Services"
        }
    ],
    "sg:phone":"+1 715 468 4151",
    "sg:postcode":"54871",
    "sg:province":"WI",
    "sg:tags":[
        "general",
        "contractor"
    ],
    "wof:name":"Construction JMK",
    "wof:placetype":"venue"
},
  "geometry": {"coordinates":[-91.92538500000001,45.743119],"type":"Point"}
}