{
  "type": "Feature",
  "properties": {
    "iso:country":"US",
    "sg:address":"1210 Shields Rd",
    "sg:city":"Saint Germain",
    "sg:classifiers":[
        {
            "category":"Professional",
            "subcategory":"Management & Consulting",
            "type":"Services"
        }
    ],
    "sg:phone":"+1 715 479 4714",
    "sg:postcode":"54558",
    "sg:province":"WI",
    "wof:name":"Entrena Inc",
    "wof:placetype":"venue"
},
  "geometry": {"coordinates":[-89.42876699999999,45.905659],"type":"Point"}
}