{
  "type": "Feature",
  "properties": {
    "iso:country":"US",
    "sg:address":"140 Warren St",
    "sg:city":"Beaver Dam",
    "sg:classifiers":[
        {
            "category":"Organizations",
            "subcategory":"Religious Organization",
            "type":"Services"
        }
    ],
    "sg:phone":"+1 920 887 9660",
    "sg:postcode":"53916",
    "sg:province":"WI",
    "sg:tags":[
        "church"
    ],
    "wof:name":"Church Of Jesus Christ Of Lds",
    "wof:placetype":"venue"
},
  "geometry": {"coordinates":[-88.824991,43.448418],"type":"Point"}
}