{
  "type": "Feature",
  "properties": {
    "iso:country":"US",
    "sg:address":"1024 Nunn Ave",
    "sg:city":"Rice Lake",
    "sg:classifiers":[
        {
            "category":"Organizations",
            "subcategory":"Membership Organization",
            "type":"Services"
        }
    ],
    "sg:phone":"+1 715 234 6843",
    "sg:postcode":"54868",
    "sg:province":"WI",
    "wof:name":"Barrens Group LLC",
    "wof:placetype":"venue"
},
  "geometry": {"coordinates":[-91.742948,45.515721],"type":"Point"}
}