{
  "type": "Feature",
  "properties": {
    "addr:full":"8700 N Servite Dr Milwaukee WI 53223",
    "addr:housenumber":"8700",
    "addr:postcode":"53223",
    "addr:street":"N Servite Dr",
    "iso:country":"US",
    "sg:address":"8700 N Servite Dr",
    "sg:city":"Milwaukee",
    "sg:classifiers":[
        {
            "category":"Personal",
            "subcategory":"Beauty Salon",
            "type":"Services"
        }
    ],
    "sg:phone":"+1 414 371 0946",
    "sg:postcode":"53223",
    "sg:province":"WI",
    "sg:tags":[
        "shop"
    ],
    "wof:name":"Regal Nails",
    "wof:placetype":"venue"
},
  "geometry": {"coordinates":[-88.009968,43.176636],"type":"Point"}
}