{
  "type": "Feature",
  "properties": {
    "addr:full":"751 40th Ave Plum City WI 54761",
    "addr:housenumber":"751",
    "addr:postcode":"54761",
    "addr:street":"40Th Ave",
    "iso:country":"US",
    "sg:address":"751 40th Ave",
    "sg:city":"Plum City",
    "sg:classifiers":[
        {
            "category":"Farming",
            "subcategory":"Livestock Farm",
            "type":"Manufacturing & Wholesale Goods"
        }
    ],
    "sg:phone":"+1 715 448 2286",
    "sg:postcode":"54761",
    "sg:province":"WI",
    "sg:tags":[
        "hog",
        "or",
        "feedlot"
    ],
    "wof:name":"Eugene Gullickson",
    "wof:placetype":"venue"
},
  "geometry": {"coordinates":[-92.168499,44.550298],"type":"Point"}
}