{
  "type": "Feature",
  "properties": {
    "iso:country":"US",
    "sg:address":"2342 Drinkwater Rd",
    "sg:city":"Montfort",
    "sg:classifiers":[
        {
            "category":"Farming",
            "subcategory":"Farm",
            "type":"Manufacturing & Wholesale Goods"
        }
    ],
    "sg:phone":"+1 608 623 2537",
    "sg:postcode":"53569",
    "sg:province":"WI",
    "sg:tags":[
        "crop",
        "general"
    ],
    "wof:name":"Welshs Farm LLC",
    "wof:placetype":"venue"
},
  "geometry": {"coordinates":[-90.359542,42.92838],"type":"Point"}
}