{
  "type": "Feature",
  "properties": {
    "iso:country":"US",
    "sg:address":"18205 W Bluemound Rd",
    "sg:city":"Brookfield",
    "sg:classifiers":[
        {
            "category":"Social Services",
            "subcategory":"Child Care",
            "type":"Services"
        },
        {
            "category":"Education",
            "subcategory":"Preschool",
            "type":"Public Place"
        }
    ],
    "sg:phone":"+1 262 792 1112",
    "sg:postcode":"53045",
    "sg:province":"WI",
    "sg:tags":[
        "kindergarten",
        "nursery",
        "day"
    ],
    "sg:website":"http://www.kindercare.com/our-centers/center-details/301356/?cid=YP_KC301356",
    "wof:name":"Bluemound Road KinderCare",
    "wof:placetype":"venue"
},
  "geometry": {"coordinates":[-88.140625,43.036479],"type":"Point"}
}