{
  "type": "Feature",
  "properties": {
    "iso:country":"US",
    "sg:address":"130 Meyer Ave",
    "sg:city":"Fredonia",
    "sg:classifiers":[
        {
            "category":"Health Services",
            "subcategory":"Optometrist",
            "type":"Services"
        }
    ],
    "sg:phone":"+1 262 692 9000",
    "sg:postcode":"53021",
    "sg:province":"WI",
    "wof:name":"Fredonia Vision Ctr",
    "wof:placetype":"venue"
},
  "geometry": {"coordinates":[-87.956547,43.468773],"type":"Point"}
}