{
  "type": "Feature",
  "properties": {
    "iso:country":"US",
    "sg:address":"9167 Golf Club Rd",
    "sg:city":"Clintonville",
    "sg:classifiers":[
        {
            "category":"Building & Trades",
            "subcategory":"Construction",
            "type":"Services"
        }
    ],
    "sg:phone":"+1 715 823 5577",
    "sg:postcode":"54929",
    "sg:province":"WI",
    "sg:tags":[
        "contractor"
    ],
    "wof:name":"Town & Country Drywall",
    "wof:placetype":"venue"
},
  "geometry": {"coordinates":[-88.764781,44.637729],"type":"Point"}
}