{
  "type": "Feature",
  "properties": {
    "iso:country":"US",
    "sg:address":"2727 Co Rd K N",
    "sg:city":"Custer",
    "sg:classifiers":[
        {
            "category":"Wholesale",
            "subcategory":"Hardware",
            "type":"Manufacturing & Wholesale Goods"
        }
    ],
    "sg:phone":"+1 715 344 9556",
    "sg:postcode":"54423",
    "sg:province":"WI",
    "wof:name":"Total Comfort Heating & Coolg",
    "wof:placetype":"venue"
},
  "geometry": {"coordinates":[-89.45724800000001,44.603407],"type":"Point"}
}