{
  "type": "Feature",
  "properties": {
    "iso:country":"US",
    "sg:address":"2510 S Howell Ave",
    "sg:city":"Milwaukee",
    "sg:classifiers":[
        {
            "category":"Wholesale",
            "subcategory":"Non-durable Goods",
            "type":"Manufacturing & Wholesale Goods"
        }
    ],
    "sg:phone":"+1 414 482 4002",
    "sg:postcode":"53207",
    "sg:province":"WI",
    "sg:tags":[
        "marketing",
        "broker"
    ],
    "wof:name":"Edi Marketing Inc",
    "wof:placetype":"venue"
},
  "geometry": {"coordinates":[-87.904746,42.999242],"type":"Point"}
}