{
  "type": "Feature",
  "properties": {
    "iso:country":"US",
    "sg:address":"2405 20th St",
    "sg:city":"Racine",
    "sg:classifiers":[
        {
            "category":"Freight",
            "type":"Transportation"
        }
    ],
    "sg:phone":"+1 262 633 3409",
    "sg:postcode":"53403",
    "sg:province":"WI",
    "sg:tags":[
        "operator",
        "local",
        "trucking"
    ],
    "wof:name":"R & 3 JS Inc",
    "wof:placetype":"venue"
},
  "geometry": {"coordinates":[-87.808597,42.705951],"type":"Point"}
}