{
  "type": "Feature",
  "properties": {
    "iso:country":"US",
    "sg:address":"615 N Military Ave",
    "sg:city":"Green Bay",
    "sg:classifiers":[
        {
            "category":"Shopping",
            "subcategory":"Florist",
            "type":"Retail Goods"
        }
    ],
    "sg:phone":"+1 920 965 0044",
    "sg:postcode":"54303",
    "sg:province":"WI",
    "wof:name":"Flowerama",
    "wof:placetype":"venue"
},
  "geometry": {"coordinates":[-88.053115,44.539876],"type":"Point"}
}