{
  "type": "Feature",
  "properties": {
    "iso:country":"US",
    "sg:address":"174 N Broadway",
    "sg:city":"Milwaukee",
    "sg:classifiers":[
        {
            "category":"Home & Garden",
            "subcategory":"Home Furnishings",
            "type":"Retail Goods"
        },
        {
            "category":"Manufacturing",
            "subcategory":"Furniture",
            "type":"Manufacturing & Wholesale Goods"
        }
    ],
    "sg:phone":"+1 414 271 1234",
    "sg:postcode":"53202",
    "sg:province":"WI",
    "sg:tags":[
        "house",
        "builder",
        "designer",
        "custom"
    ],
    "wof:name":"Jamie Wilke Interiors",
    "wof:placetype":"venue"
},
  "geometry": {"coordinates":[-87.90695599999999,43.032353],"type":"Point"}
}