{
  "type": "Feature",
  "properties": {
    "iso:country":"US",
    "sg:address":"33541 Washington Ave",
    "sg:city":"Burlington",
    "sg:classifiers":[
        {
            "category":"Building & Trades",
            "subcategory":"Construction",
            "type":"Services"
        }
    ],
    "sg:phone":"+1 262 534 2802",
    "sg:postcode":"53105",
    "sg:province":"WI",
    "sg:tags":[
        "contractor"
    ],
    "wof:name":"Chart Drywall Inc",
    "wof:placetype":"venue"
},
  "geometry": {"coordinates":[-88.26807100000001,42.744031],"type":"Point"}
}