{
  "type": "Feature",
  "properties": {
    "iso:country":"US",
    "sg:address":"630 W Pine St",
    "sg:city":"Baraboo",
    "sg:classifiers":[
        {
            "category":"Restaurant",
            "type":"Food & Drink"
        }
    ],
    "sg:phone":"+1 608 356 4869",
    "sg:postcode":"53913",
    "sg:province":"WI",
    "sg:website":"www.glacierrock.com",
    "wof:name":"Glacier Rock",
    "wof:placetype":"venue"
},
  "geometry": {"coordinates":[-89.768745,43.477081],"type":"Point"}
}