{
  "type": "Feature",
  "properties": {
    "iso:country":"US",
    "sg:address":"310 Muirfield Cir",
    "sg:city":"North Prairie",
    "sg:classifiers":[
        {
            "category":"Real Estate",
            "subcategory":"Real Estate Agent",
            "type":"Services"
        }
    ],
    "sg:phone":"+1 262 392 5571",
    "sg:postcode":"53153",
    "sg:province":"WI",
    "wof:name":"Green C D & Associates LLC",
    "wof:placetype":"venue"
},
  "geometry": {"coordinates":[-88.422902,42.937033],"type":"Point"}
}