{
  "type": "Feature",
  "properties": {
    "iso:country":"US",
    "sg:address":"7841 Smith St",
    "sg:city":"Shiocton",
    "sg:classifiers":[
        {
            "category":"Manufacturing",
            "subcategory":"Food",
            "type":"Manufacturing & Wholesale Goods"
        }
    ],
    "sg:phone":"+1 920 986 3816",
    "sg:postcode":"54170",
    "sg:province":"WI",
    "sg:tags":[
        "canning"
    ],
    "wof:name":"Great Lakes Kraut Co",
    "wof:placetype":"venue"
},
  "geometry": {"coordinates":[-88.580399,44.440121],"type":"Point"}
}