{
  "type": "Feature",
  "properties": {
    "addr:full":"307 Maple St Woodville WI 54028",
    "addr:housenumber":"307",
    "addr:postcode":"54028",
    "addr:street":"Maple St",
    "iso:country":"US",
    "sg:address":"307 Maple St",
    "sg:city":"Woodville",
    "sg:classifiers":[
        {
            "category":"Organizations",
            "subcategory":"Religious Organization",
            "type":"Services"
        }
    ],
    "sg:phone":"+1 715 698 2623",
    "sg:postcode":"54028",
    "sg:province":"WI",
    "sg:tags":[
        "parsonage"
    ],
    "wof:name":"First Baptist Church Parsonage",
    "wof:placetype":"venue"
},
  "geometry": {"coordinates":[-92.287036,44.951951],"type":"Point"}
}