{
  "type": "Feature",
  "properties": {
    "iso:country":"US",
    "sg:address":"422 3rd St W",
    "sg:city":"Ashland",
    "sg:classifiers":[
        {
            "category":"Manufacturing",
            "subcategory":"Tools & Machinery",
            "type":"Manufacturing & Wholesale Goods"
        }
    ],
    "sg:phone":"+1 715 682 8370",
    "sg:postcode":"54806",
    "sg:province":"WI",
    "sg:tags":[
        "machine",
        "shop"
    ],
    "wof:name":"Horizon Industries Inc",
    "wof:placetype":"venue"
},
  "geometry": {"coordinates":[-90.886425,46.58881],"type":"Point"}
}