{
  "type": "Feature",
  "properties": {
    "iso:country":"US",
    "sg:address":"3601 Main St",
    "sg:city":"Stevens Point",
    "sg:classifiers":[
        {
            "category":"Banks & Credit Unions",
            "subcategory":"Bank",
            "type":"Services"
        }
    ],
    "sg:phone":"+1 715 341 5600",
    "sg:postcode":"54481",
    "sg:province":"WI",
    "sg:tags":[
        "commercial"
    ],
    "wof:name":"Pineries Bank Inc",
    "wof:placetype":"venue"
},
  "geometry": {"coordinates":[-89.54942200000001,44.523182],"type":"Point"}
}