{
  "type": "Feature",
  "properties": {
    "iso:country":"US",
    "sg:address":"10072 Kinsey Bay Ln",
    "sg:city":"Sister Bay",
    "sg:classifiers":[
        {
            "category":"Building & Trades",
            "subcategory":"Construction",
            "type":"Services"
        }
    ],
    "sg:phone":"+1 920 854 4705",
    "sg:postcode":"54234",
    "sg:province":"WI",
    "sg:tags":[
        "house"
    ],
    "wof:name":"A Flying Construction Inc",
    "wof:placetype":"venue"
},
  "geometry": {"coordinates":[-87.047764,45.164085],"type":"Point"}
}