{
  "type": "Feature",
  "properties": {
    "iso:country":"US",
    "sg:address":"210 Martin Luther King Jr Blvd",
    "sg:city":"Madison",
    "sg:classifiers":[
        {
            "category":"Wholesale",
            "subcategory":"Dairy",
            "type":"Manufacturing & Wholesale Goods"
        }
    ],
    "sg:phone":"+1 608 271 6455",
    "sg:postcode":"53709",
    "sg:province":"WI",
    "sg:tags":[
        "product"
    ],
    "wof:name":"Dane County Dairy Inc",
    "wof:placetype":"venue"
},
  "geometry": {"coordinates":[-89.381456,43.072555],"type":"Point"}
}