{
  "type": "Feature",
  "properties": {
    "iso:country":"US",
    "sg:address":"340 Broad St",
    "sg:city":"Menasha",
    "sg:classifiers":[
        {
            "category":"Professional",
            "subcategory":"Accounting & Tax Preparation",
            "type":"Services"
        }
    ],
    "sg:phone":"+1 920 725 8991",
    "sg:postcode":"54952",
    "sg:province":"WI",
    "sg:tags":[
        "return",
        "filing"
    ],
    "wof:name":"Les Account Tax Svc",
    "wof:placetype":"venue"
},
  "geometry": {"coordinates":[-88.450339,44.202114],"type":"Point"}
}