{
  "type": "Feature",
  "properties": {
    "iso:country":"US",
    "sg:address":"14100 W Capitol Dr",
    "sg:city":"Brookfield",
    "sg:classifiers":[
        {
            "category":"Autos & Motor Vehicles",
            "subcategory":"Fuel & Gas Station",
            "type":"Retail Goods"
        }
    ],
    "sg:phone":"+1 262 781 1827",
    "sg:postcode":"53005",
    "sg:province":"WI",
    "sg:tags":[
        "oil"
    ],
    "sg:website":"www.brookfieldcarwash.com",
    "wof:name":"Plaza Service Inc",
    "wof:placetype":"venue"
},
  "geometry": {"coordinates":[-88.090223,43.089814],"type":"Point"}
}