{
  "type": "Feature",
  "properties": {
    "iso:country":"US",
    "sg:address":"19 15th St",
    "sg:city":"Clintonville",
    "sg:classifiers":[
        {
            "category":"Organizations",
            "subcategory":"Religious Organization",
            "type":"Services"
        }
    ],
    "sg:phone":"+1 715 823 4514",
    "sg:postcode":"54929",
    "sg:province":"WI",
    "sg:tags":[
        "clergy"
    ],
    "wof:name":"Willard Hager",
    "wof:placetype":"venue"
},
  "geometry": {"coordinates":[-88.755483,44.626478],"type":"Point"}
}