{
  "type": "Feature",
  "properties": {
    "iso:country":"US",
    "sg:address":"3936 Circle Dr",
    "sg:city":"Holmen",
    "sg:classifiers":[
        {
            "category":"Manufacturing",
            "subcategory":"Tools & Machinery",
            "type":"Manufacturing & Wholesale Goods"
        }
    ],
    "sg:phone":"+1 608 781 1606",
    "sg:postcode":"54636",
    "sg:province":"WI",
    "sg:tags":[
        "equipment",
        "printing",
        "photographic",
        "mfg"
    ],
    "wof:name":"Laser Products Technologies",
    "wof:placetype":"venue"
},
  "geometry": {"coordinates":[-91.24574,43.925184],"type":"Point"}
}