{
  "type": "Feature",
  "properties": {
    "iso:country":"US",
    "sg:address":"325 Luedtke Ave",
    "sg:city":"Racine",
    "sg:classifiers":[
        {
            "category":"Social Services",
            "subcategory":"Child Care",
            "type":"Services"
        }
    ],
    "sg:phone":"+1 262 638 6038",
    "sg:postcode":"53405",
    "sg:province":"WI",
    "wof:name":"Mary Had A Little Lamb",
    "wof:placetype":"venue"
},
  "geometry": {"coordinates":[-87.806414,42.727425],"type":"Point"}
}