{
  "type": "Feature",
  "properties": {
    "iso:country":"US",
    "sg:address":"3593 US Hwy 18",
    "sg:city":"Fennimore",
    "sg:classifiers":[
        {
            "category":"Manufacturing",
            "subcategory":"Printing",
            "type":"Manufacturing & Wholesale Goods"
        }
    ],
    "sg:phone":"+1 608 822 7168",
    "sg:postcode":"53809",
    "sg:province":"WI",
    "sg:tags":[
        "book"
    ],
    "wof:name":"Yellow Book USA Gary Winkers",
    "wof:placetype":"venue"
},
  "geometry": {"coordinates":[-90.585987,42.973698],"type":"Point"}
}