{
  "type": "Feature",
  "properties": {
    "iso:country":"US",
    "sg:address":"1810 12th Ave",
    "sg:city":"Monroe",
    "sg:classifiers":[
        {
            "category":"Retail",
            "subcategory":"Repair Shop",
            "type":"Services"
        }
    ],
    "sg:phone":"+1 608 328 4109",
    "sg:postcode":"53566",
    "sg:province":"WI",
    "sg:tags":[
        "welding"
    ],
    "wof:name":"Steinmann Stainless Fbrctn",
    "wof:placetype":"venue"
},
  "geometry": {"coordinates":[-89.64449500000001,42.594634],"type":"Point"}
}