{
  "type": "Feature",
  "properties": {
    "iso:country":"US",
    "sg:address":"949 W Ravine Dr",
    "sg:city":"Beloit",
    "sg:classifiers":[
        {
            "category":"Professional",
            "type":"Services"
        }
    ],
    "sg:phone":"+1 608 364 0040",
    "sg:postcode":"53511",
    "sg:province":"IL",
    "wof:name":"Tekrite",
    "wof:placetype":"venue"
},
  "geometry": {"coordinates":[-89.045356,42.541808],"type":"Point"}
}