{
  "type": "Feature",
  "properties": {
    "addr:full":"2730 Woleske Rd Marinette WI 54143",
    "addr:housenumber":"2730",
    "addr:postcode":"54143",
    "addr:street":"Woleske Rd",
    "iso:country":"US",
    "sg:address":"2730 Woleske Rd",
    "sg:city":"Marinette",
    "sg:classifiers":[
        {
            "category":"Wholesale",
            "subcategory":"Machinery & Supplies",
            "type":"Manufacturing & Wholesale Goods"
        }
    ],
    "sg:phone":"+1 715 732 1714",
    "sg:postcode":"54143",
    "sg:province":"WI",
    "sg:tags":[
        "industrial"
    ],
    "wof:name":"Motion Industries Inc",
    "wof:placetype":"venue"
},
  "geometry": {"coordinates":[-87.64729800000001,45.082084],"type":"Point"}
}