{
  "type": "Feature",
  "properties": {
    "iso:country":"US",
    "sg:address":"7721 Mill Ave",
    "sg:city":"Wisconsin Rapids",
    "sg:classifiers":[
        {
            "category":"Building & Trades",
            "subcategory":"Landscaping Services",
            "type":"Services"
        }
    ],
    "sg:phone":"+1 715 325 3456",
    "sg:postcode":"54494",
    "sg:province":"WI",
    "wof:name":"Fae Heller",
    "wof:placetype":"venue"
},
  "geometry": {"coordinates":[-89.728207,44.305686],"type":"Point"}
}