{
  "type": "Feature",
  "properties": {
    "iso:country":"US",
    "sg:address":"6163 Colby Factory Rd",
    "sg:city":"Owen",
    "sg:classifiers":[
        {
            "category":"Farming",
            "subcategory":"Dairy Farm",
            "type":"Manufacturing & Wholesale Goods"
        }
    ],
    "sg:phone":"+1 715 229 4614",
    "sg:postcode":"54460",
    "sg:province":"WI",
    "wof:name":"Mark Hoover",
    "wof:placetype":"venue"
},
  "geometry": {"coordinates":[-90.621899,44.88608],"type":"Point"}
}