{
  "type": "Feature",
  "properties": {
    "iso:country":"US",
    "sg:address":"1678 Co Rd K",
    "sg:city":"Fort Atkinson",
    "sg:classifiers":[
        {
            "category":"Retail",
            "subcategory":"Repair Shop",
            "type":"Services"
        }
    ],
    "sg:phone":"+1 920 563 5892",
    "sg:postcode":"53538",
    "sg:province":"WI",
    "sg:tags":[
        "lock",
        "locksmith"
    ],
    "wof:name":"Jim's Key Shop",
    "wof:placetype":"venue"
},
  "geometry": {"coordinates":[-88.827146,42.904633],"type":"Point"}
}