{
  "type": "Feature",
  "properties": {
    "iso:country":"US",
    "sg:address":"404 Walworth St",
    "sg:city":"Lake Geneva",
    "sg:classifiers":[
        {
            "category":"Building & Trades",
            "subcategory":"Construction",
            "type":"Services"
        }
    ],
    "sg:phone":"+1 262 248 1810",
    "sg:postcode":"53147",
    "sg:province":"WI",
    "sg:tags":[
        "hanging",
        "contractor"
    ],
    "wof:name":"Marks Paint & Painting",
    "wof:placetype":"venue"
},
  "geometry": {"coordinates":[-88.430302,42.598929],"type":"Point"}
}