{
  "type": "Feature",
  "properties": {
    "iso:country":"US",
    "sg:address":"207 S 18th St",
    "sg:city":"Barron",
    "sg:classifiers":[
        {
            "category":"Manufacturing",
            "subcategory":"Food",
            "type":"Manufacturing & Wholesale Goods"
        },
        {
            "category":"Manufacturing",
            "subcategory":"Pet Food",
            "type":"Manufacturing & Wholesale Goods"
        }
    ],
    "sg:phone":"+1 715 537 3050",
    "sg:postcode":"54812",
    "sg:province":"WI",
    "sg:tags":[
        "mfg",
        "dog",
        "cat"
    ],
    "wof:name":"Indianhead Stock Removal Inc",
    "wof:placetype":"venue"
},
  "geometry": {"coordinates":[-91.827667,45.398221],"type":"Point"}
}