{
  "type": "Feature",
  "properties": {
    "iso:country":"US",
    "sg:address":"3349 Paine Ave",
    "sg:city":"Sheboygan",
    "sg:classifiers":[
        {
            "category":"Retail",
            "subcategory":"Auto Rental",
            "type":"Services"
        }
    ],
    "sg:phone":"+1 920 451 8965",
    "sg:postcode":"53081",
    "sg:province":"WI",
    "sg:tags":[
        "renting",
        "truck",
        "leasing"
    ],
    "wof:name":"Valley Truck Leasing Inc",
    "wof:placetype":"venue"
},
  "geometry": {"coordinates":[-87.749596,43.72465],"type":"Point"}
}