{
  "type": "Feature",
  "properties": {
    "addr:full":"384 Oak St Berlin WI 54923",
    "addr:housenumber":"384",
    "addr:postcode":"54923",
    "addr:street":"Oak St",
    "iso:country":"US",
    "sg:address":"384 Oak St",
    "sg:city":"Berlin",
    "sg:classifiers":[
        {
            "category":"Social Services",
            "type":"Services"
        }
    ],
    "sg:phone":"+1 920 361 1820",
    "sg:postcode":"54923",
    "sg:province":"WI",
    "wof:name":"Berlin Emergency Food Pantry",
    "wof:placetype":"venue"
},
  "geometry": {"coordinates":[-88.94418400000001,43.977398],"type":"Point"}
}