{
  "type": "Feature",
  "properties": {
    "iso:country":"US",
    "sg:address":"2690 18th St",
    "sg:city":"Rice Lake",
    "sg:classifiers":[
        {
            "category":"Professional",
            "subcategory":"Business Services",
            "type":"Services"
        }
    ],
    "sg:phone":"+1 715 234 1383",
    "sg:postcode":"54868",
    "sg:province":"WI",
    "wof:name":"Pattimacs Storage & Auction",
    "wof:placetype":"venue"
},
  "geometry": {"coordinates":[-91.78631900000001,45.589153],"type":"Point"}
}