{
  "type": "Feature",
  "properties": {
    "iso:country":"US",
    "sg:address":"3369 W Mequon Rd",
    "sg:city":"Mequon",
    "sg:classifiers":[
        {
            "category":"Organizations",
            "subcategory":"Membership Organization",
            "type":"Services"
        },
        {
            "category":"Retail",
            "subcategory":"Animal Services",
            "type":"Services"
        }
    ],
    "sg:phone":"+1 262 242 9232",
    "sg:postcode":"53092",
    "sg:province":"WI",
    "sg:tags":[
        "shelter"
    ],
    "wof:name":"Christine M Kiedrowicz",
    "wof:placetype":"venue"
},
  "geometry": {"coordinates":[-87.957292,43.221478],"type":"Point"}
}