{
  "type": "Feature",
  "properties": {
    "iso:country":"US",
    "sg:address":"2502 Shopko Dr",
    "sg:city":"Madison",
    "sg:classifiers":[
        {
            "category":"Shopping",
            "subcategory":"Pharmacy",
            "type":"Retail Goods"
        }
    ],
    "sg:phone":"+1 608 243 7788",
    "sg:postcode":"53704",
    "sg:province":"WI",
    "wof:name":"Aurora Pharmacy",
    "wof:placetype":"venue"
},
  "geometry": {"coordinates":[-89.347108,43.11149],"type":"Point"}
}