{
  "type": "Feature",
  "properties": {
    "iso:country":"US",
    "sg:address":"8218 State Hwy 57",
    "sg:city":"Elkhart Lake",
    "sg:classifiers":[
        {
            "category":"Shopping",
            "subcategory":"Crafts & Fabrics",
            "type":"Retail Goods"
        }
    ],
    "sg:phone":"+1 920 876 2258",
    "sg:postcode":"53020",
    "sg:province":"WI",
    "sg:tags":[
        "sewing"
    ],
    "wof:name":"Hares To Ewe Wools",
    "wof:placetype":"venue"
},
  "geometry": {"coordinates":[-87.94155600000001,43.834302],"type":"Point"}
}