{
  "type": "Feature",
  "properties": {
    "iso:country":"US",
    "sg:address":"337 Main St",
    "sg:city":"Racine",
    "sg:classifiers":[
        {
            "category":"Real Estate",
            "subcategory":"Real Estate Services",
            "type":"Services"
        }
    ],
    "sg:phone":"+1 262 638 7441",
    "sg:postcode":"53403",
    "sg:province":"WI",
    "sg:tags":[
        "company",
        "title"
    ],
    "wof:name":"Excell Closing Svc",
    "wof:placetype":"venue"
},
  "geometry": {"coordinates":[-87.78326300000001,42.729826],"type":"Point"}
}