{
  "type": "Feature",
  "properties": {
    "iso:country":"US",
    "sg:address":"3714 Skyhigh Rd",
    "sg:city":"Cottage Grove",
    "sg:classifiers":[
        {
            "category":"Retail",
            "subcategory":"Repair Shop",
            "type":"Services"
        }
    ],
    "sg:phone":"+1 608 839 4790",
    "sg:postcode":"53527",
    "sg:province":"WI",
    "sg:tags":[
        "television"
    ],
    "wof:name":"Dmkwood",
    "wof:placetype":"venue"
},
  "geometry": {"coordinates":[-89.207167,43.053086],"type":"Point"}
}