{
  "type": "Feature",
  "properties": {
    "iso:country":"US",
    "sg:address":"3701 Kadow St",
    "sg:city":"Manitowoc",
    "sg:classifiers":[
        {
            "category":"Social Services",
            "type":"Services"
        }
    ],
    "sg:phone":"+1 920 682 9211",
    "sg:postcode":"54220",
    "sg:province":"WI",
    "sg:tags":[
        "clinic",
        "agency",
        "adoption",
        "specialty",
        "outpatient"
    ],
    "wof:name":"Community Adoption Center Inc",
    "wof:placetype":"venue"
},
  "geometry": {"coordinates":[-87.695079,44.082708],"type":"Point"}
}