{
  "type": "Feature",
  "properties": {
    "addr:full":"111 N Dodge St Burlington WI 53105",
    "addr:housenumber":"111",
    "addr:postcode":"53105",
    "addr:street":"N Dodge St",
    "iso:country":"US",
    "sg:address":"111 N Dodge St",
    "sg:city":"Burlington",
    "sg:classifiers":[
        {
            "category":"Recreation",
            "type":"Entertainment"
        }
    ],
    "sg:phone":"+1 262 763 4880",
    "sg:postcode":"53105",
    "sg:province":"WI",
    "sg:tags":[
        "instruction",
        "yoga"
    ],
    "wof:name":"Synchronicity Learning Ctr",
    "wof:placetype":"venue"
},
  "geometry": {"coordinates":[-88.273787,42.677928],"type":"Point"}
}