{
  "type": "Feature",
  "properties": {
    "addr:full":"919 Shamrock Ct Kaukauna WI 54130",
    "addr:housenumber":"919",
    "addr:postcode":"54130",
    "addr:street":"Shamrock Ct",
    "iso:country":"US",
    "sg:address":"919 Shamrock Ct",
    "sg:city":"Kaukauna",
    "sg:classifiers":[
        {
            "category":"Building & Trades",
            "subcategory":"Construction",
            "type":"Services"
        }
    ],
    "sg:phone":"+1 920 766 2923",
    "sg:postcode":"54130",
    "sg:province":"WI",
    "sg:tags":[
        "house"
    ],
    "wof:name":"Pvh Construction",
    "wof:placetype":"venue"
},
  "geometry": {"coordinates":[-88.288861,44.272985],"type":"Point"}
}