{
  "type": "Feature",
  "properties": {
    "addr:full":"3318 Darryl Ln Eau Claire WI 54703",
    "addr:housenumber":"3318",
    "addr:postcode":"54703",
    "addr:street":"Darryl Ln",
    "iso:country":"US",
    "sg:address":"3318 Darryl Ln",
    "sg:city":"Eau Claire",
    "sg:classifiers":[
        {
            "category":"Shopping",
            "subcategory":"Jewelry",
            "type":"Retail Goods"
        }
    ],
    "sg:phone":"+1 715 831 0048",
    "sg:postcode":"54703",
    "sg:province":"WI",
    "sg:tags":[
        "jeweler"
    ],
    "wof:name":"Master Jewelers Repair & Dsgn",
    "wof:placetype":"venue"
},
  "geometry": {"coordinates":[-91.45621199999999,44.852489],"type":"Point"}
}