{
  "type": "Feature",
  "properties": {
    "iso:country":"US",
    "sg:address":"1220 W Burleigh St",
    "sg:city":"Milwaukee",
    "sg:classifiers":[
        {
            "category":"Social Services",
            "type":"Services"
        }
    ],
    "sg:phone":"+1 414 372 5530",
    "sg:postcode":"53206",
    "sg:province":"WI",
    "wof:name":"Evelonia Sweet Angel Day Care",
    "wof:placetype":"venue"
},
  "geometry": {"coordinates":[-87.92741700000001,43.074993],"type":"Point"}
}