{
  "type": "Feature",
  "properties": {
    "iso:country":"US",
    "sg:address":"743 Woodcrest Dr N",
    "sg:city":"Hudson",
    "sg:classifiers":[
        {
            "category":"Insurance",
            "subcategory":"Insurance Agent",
            "type":"Services"
        }
    ],
    "sg:phone":"+1 715 386 2203",
    "sg:postcode":"54016",
    "sg:province":"WI",
    "wof:name":"Pete Keskey",
    "wof:placetype":"venue"
},
  "geometry": {"coordinates":[-92.748182,45.002396],"type":"Point"}
}