{
  "type": "Feature",
  "properties": {
    "addr:full":"1117 E Brady St Milwaukee WI 53202",
    "addr:housenumber":"1117",
    "addr:postcode":"53202",
    "addr:street":"E Brady St",
    "iso:country":"US",
    "sg:address":"1117 E Brady St",
    "sg:city":"Milwaukee",
    "sg:classifiers":[
        {
            "category":"Shopping",
            "subcategory":"Gifts & Souvenirs",
            "type":"Retail Goods"
        }
    ],
    "sg:phone":"+1 414 271 1244",
    "sg:postcode":"53202",
    "sg:province":"WI",
    "sg:tags":[
        "shop"
    ],
    "wof:name":"Dragonfly Vintage Goods Gifts",
    "wof:placetype":"venue"
},
  "geometry": {"coordinates":[-87.896984,43.052877],"type":"Point"}
}