{
  "type": "Feature",
  "properties": {
    "iso:country":"US",
    "sg:address":"2601 N Union St",
    "sg:city":"Appleton",
    "sg:classifiers":[
        {
            "category":"Shopping",
            "subcategory":"Books",
            "type":"Retail Goods"
        }
    ],
    "sg:phone":"+1 920 731 5364",
    "sg:postcode":"54911",
    "sg:province":"WI",
    "wof:name":"Roop Books",
    "wof:placetype":"venue"
},
  "geometry": {"coordinates":[-88.39840700000001,44.285624],"type":"Point"}
}