{
  "type": "Feature",
  "properties": {
    "iso:country":"US",
    "sg:address":"801 Highland Ave",
    "sg:city":"Watertown",
    "sg:classifiers":[
        {
            "category":"Retail",
            "subcategory":"Repair Shop",
            "type":"Services"
        }
    ],
    "sg:phone":"+1 920 261 2527",
    "sg:postcode":"53098",
    "sg:province":"WI",
    "sg:tags":[
        "related"
    ],
    "wof:name":"Ragdoll's Repair",
    "wof:placetype":"venue"
},
  "geometry": {"coordinates":[-88.70856999999999,43.20023],"type":"Point"}
}