{
  "type": "Feature",
  "properties": {
    "iso:country":"US",
    "sg:address":"306 S Foster St",
    "sg:city":"Merrill",
    "sg:classifiers":[
        {
            "category":"Local Transit",
            "type":"Transportation"
        }
    ],
    "sg:phone":"+1 715 355 2609",
    "sg:postcode":"54452",
    "sg:province":"WI",
    "sg:tags":[
        "limousine"
    ],
    "wof:name":"Antique Limousine Svc",
    "wof:placetype":"venue"
},
  "geometry": {"coordinates":[-89.71911799999999,45.176819],"type":"Point"}
}