{
  "type": "Feature",
  "properties": {
    "iso:country":"US",
    "sg:address":"1103 Hall Rd",
    "sg:city":"Columbus",
    "sg:classifiers":[
        {
            "category":"Professional",
            "subcategory":"Business Services",
            "type":"Services"
        }
    ],
    "sg:phone":"+1 920 623 4303",
    "sg:postcode":"53925",
    "sg:province":"WI",
    "wof:name":"Johnson Johnny O & Shirley",
    "wof:placetype":"venue"
},
  "geometry": {"coordinates":[-89.052778,43.356853],"type":"Point"}
}