{
  "type": "Feature",
  "properties": {
    "addr:full":"2103 Hall Ave Marinette WI 54143",
    "addr:housenumber":"2103",
    "addr:postcode":"54143",
    "addr:street":"Hall Ave",
    "iso:country":"US",
    "sg:address":"2103 Hall Ave",
    "sg:city":"Marinette",
    "sg:classifiers":[
        {
            "category":"Wholesale",
            "subcategory":"Vending Machines",
            "type":"Manufacturing & Wholesale Goods"
        }
    ],
    "sg:phone":"+1 715 735 3904",
    "sg:postcode":"54143",
    "sg:province":"WI",
    "wof:name":"Be's Coffee & Vending Svc",
    "wof:placetype":"venue"
},
  "geometry": {"coordinates":[-87.635234,45.099654],"type":"Point"}
}