{
  "type": "Feature",
  "properties": {
    "iso:country":"US",
    "sg:address":"1548 Oak Ridge Ln",
    "sg:city":"Hudson",
    "sg:classifiers":[
        {
            "category":"Home & Garden",
            "subcategory":"Furniture",
            "type":"Retail Goods"
        }
    ],
    "sg:phone":"+1 715 549 5501",
    "sg:postcode":"54082",
    "sg:province":"WI",
    "wof:name":"Stone Goose",
    "wof:placetype":"venue"
},
  "geometry": {"coordinates":[-92.76552100000001,45.078931],"type":"Point"}
}