{
  "type": "Feature",
  "properties": {
    "iso:country":"US",
    "sg:address":"9241 N 76th St",
    "sg:city":"Milwaukee",
    "sg:classifiers":[
        {
            "category":"Local Transit",
            "type":"Transportation"
        }
    ],
    "sg:phone":"+1 414 403 1015",
    "sg:postcode":"53223",
    "sg:province":"WI",
    "sg:tags":[
        "airport"
    ],
    "wof:name":"Airport Sedan Svc",
    "wof:placetype":"venue"
},
  "geometry": {"coordinates":[-88.004227,43.188852],"type":"Point"}
}