{
  "type": "Feature",
  "properties": {
    "iso:country":"US",
    "sg:address":"7371 Wilburn Rd",
    "sg:city":"Sun Prairie",
    "sg:classifiers":[
        {
            "category":"Professional",
            "type":"Services"
        }
    ],
    "sg:phone":"+1 608 834 9238",
    "sg:postcode":"53590",
    "sg:province":"WI",
    "wof:name":"J & C Transfer LLC",
    "wof:placetype":"venue"
},
  "geometry": {"coordinates":[-89.191786,43.253248],"type":"Point"}
}