{
  "type": "Feature",
  "properties": {
    "iso:country":"US",
    "sg:address":"8134 Sandy Ridge Rd",
    "sg:city":"Kewaskum",
    "sg:classifiers":[
        {
            "category":"Farming",
            "subcategory":"Dairy Farm",
            "type":"Manufacturing & Wholesale Goods"
        }
    ],
    "sg:phone":"+1 262 334 2722",
    "sg:postcode":"53040",
    "sg:province":"WI",
    "wof:name":"Al Staehler",
    "wof:placetype":"venue"
},
  "geometry": {"coordinates":[-88.20475399999999,43.4872],"type":"Point"}
}