{
  "type": "Feature",
  "properties": {
    "iso:country":"US",
    "sg:address":"1169 Lowell Dr",
    "sg:city":"Oconomowoc",
    "sg:classifiers":[
        {
            "category":"Building & Trades",
            "subcategory":"Cleaning & Sanitation",
            "type":"Services"
        }
    ],
    "sg:phone":"+1 262 560 1172",
    "sg:postcode":"53066",
    "sg:province":"WI",
    "sg:tags":[
        "maintenance"
    ],
    "wof:name":"Starich Property Maintenance",
    "wof:placetype":"venue"
},
  "geometry": {"coordinates":[-88.48115799999999,43.092921],"type":"Point"}
}