{
  "type": "Feature",
  "properties": {
    "iso:country":"US",
    "sg:address":"9896 Lakeside Rd",
    "sg:city":"Trego",
    "sg:classifiers":[
        {
            "category":"Bars & Pubs",
            "type":"Food & Drink"
        }
    ],
    "sg:phone":"+1 715 466 2908",
    "sg:postcode":"54888",
    "sg:province":"WI",
    "sg:tags":[
        "drinking"
    ],
    "wof:name":"Doug's Silver Lake Saloon",
    "wof:placetype":"venue"
},
  "geometry": {"coordinates":[-91.81585099999999,46.020417],"type":"Point"}
}