{
  "type": "Feature",
  "properties": {
    "iso:country":"US",
    "sg:address":"332 E Wausau Ave",
    "sg:city":"Wausau",
    "sg:classifiers":[
        {
            "category":"Shopping",
            "subcategory":"Jewelry",
            "type":"Retail Goods"
        }
    ],
    "sg:phone":"+1 715 842 5757",
    "sg:postcode":"54403",
    "sg:province":"WI",
    "wof:name":"Fred Meyer Jewelers",
    "wof:placetype":"venue"
},
  "geometry": {"coordinates":[-89.625796,44.973883],"type":"Point"}
}