{
  "type": "Feature",
  "properties": {
    "addr:full":"1673 Co Rd K Columbus WI 53925",
    "addr:housenumber":"1673",
    "addr:postcode":"53925",
    "addr:street":"Co Rd",
    "iso:country":"US",
    "sg:address":"1673 Co Rd K",
    "sg:city":"Columbus",
    "sg:classifiers":[
        {
            "category":"Building & Trades",
            "subcategory":"Construction",
            "type":"Services"
        }
    ],
    "sg:phone":"+1 920 623 2171",
    "sg:postcode":"53925",
    "sg:province":"WI",
    "sg:tags":[
        "contractor"
    ],
    "wof:name":"R & R Construction",
    "wof:placetype":"venue"
},
  "geometry": {"coordinates":[-89.08204499999999,43.319266],"type":"Point"}
}