{
  "type": "Feature",
  "properties": {
    "iso:country":"US",
    "sg:address":"620 W Kemp St",
    "sg:city":"Rhinelander",
    "sg:classifiers":[
        {
            "category":"Ice Cream",
            "type":"Food & Drink"
        }
    ],
    "sg:menulink":"http://www.allmenus.com/wi/rhinelander/182984-culvers/menu/",
    "sg:phone":"+1 715 369 1800",
    "sg:postcode":"54501",
    "sg:province":"WI",
    "sg:tags":[
        "burger",
        "american"
    ],
    "wof:name":"Culver's",
    "wof:placetype":"venue"
},
  "geometry": {"coordinates":[-89.421902,45.631838],"type":"Point"}
}