{
  "type": "Feature",
  "properties": {
    "addr:full":"455 Smythe Dr Williams Bay WI 53191",
    "addr:housenumber":"455",
    "addr:postcode":"53191",
    "addr:street":"Smythe Dr",
    "iso:country":"US",
    "sg:address":"455 Smythe Dr",
    "sg:city":"Williams Bay",
    "sg:classifiers":[
        {
            "category":"Professional",
            "subcategory":"Art Services",
            "type":"Services"
        }
    ],
    "sg:phone":"+1 262 245 6425",
    "sg:postcode":"53191",
    "sg:province":"WI",
    "sg:tags":[
        "commercial",
        "design"
    ],
    "wof:name":"Bay Graphics LLC",
    "wof:placetype":"venue"
},
  "geometry": {"coordinates":[-88.55959799999999,42.577751],"type":"Point"}
}