{
  "type": "Feature",
  "properties": {
    "addr:full":"2201 Carrie Ave Rice Lake WI 54868",
    "addr:housenumber":"2201",
    "addr:postcode":"54868",
    "addr:street":"Carrie Ave",
    "iso:country":"US",
    "sg:address":"2201 Carrie Ave",
    "sg:city":"Rice Lake",
    "sg:classifiers":[
        {
            "category":"Education",
            "subcategory":"School",
            "type":"Public Place"
        }
    ],
    "sg:phone":"+1 715 234 8065",
    "sg:postcode":"54868",
    "sg:province":"WI",
    "wof:name":"Tainter Elementary School",
    "wof:placetype":"venue"
},
  "geometry": {"coordinates":[-91.728369,45.480679],"type":"Point"}
}