{
  "type": "Feature",
  "properties": {
    "iso:country":"US",
    "sg:address":"23630 Co Hwy U",
    "sg:city":"Norwalk",
    "sg:classifiers":[
        {
            "category":"Social Services",
            "subcategory":"Child Care",
            "type":"Services"
        }
    ],
    "sg:phone":"+1 608 435 6842",
    "sg:postcode":"54648",
    "sg:province":"WI",
    "sg:tags":[
        "day"
    ],
    "wof:name":"Sonja Childcare",
    "wof:placetype":"venue"
},
  "geometry": {"coordinates":[-90.615614,43.836956],"type":"Point"}
}