{
  "type": "Feature",
  "properties": {
    "iso:country":"US",
    "sg:address":"1151 State Hwy 13",
    "sg:city":"Park Falls",
    "sg:classifiers":[
        {
            "category":"Real Estate",
            "subcategory":"Real Estate Agent",
            "type":"Services"
        }
    ],
    "sg:phone":"+1 715 339 6300",
    "sg:postcode":"54552",
    "sg:province":"WI",
    "wof:name":"Larson Realty",
    "wof:placetype":"venue"
},
  "geometry": {"coordinates":[-90.461809,45.945915],"type":"Point"}
}