{
  "type": "Feature",
  "properties": {
    "iso:country":"US",
    "sg:address":"5409 W Center St",
    "sg:city":"Milwaukee",
    "sg:classifiers":[
        {
            "category":"Banks & Credit Unions",
            "subcategory":"Bank",
            "type":"Services"
        }
    ],
    "sg:phone":"+1 414 442 8660",
    "sg:postcode":"53210",
    "sg:province":"WI",
    "sg:tags":[
        "mortgage",
        "loan",
        "broker",
        "real estate"
    ],
    "wof:name":"Abate Mortgage Services Inc",
    "wof:placetype":"venue"
},
  "geometry": {"coordinates":[-87.982074,43.067925],"type":"Point"}
}