{
  "type": "Feature",
  "properties": {
    "iso:country":"US",
    "sg:address":"6133 S 27th St",
    "sg:city":"Milwaukee",
    "sg:classifiers":[
        {
            "category":"Autos & Motor Vehicles",
            "subcategory":"Automobile Sales",
            "type":"Retail Goods"
        }
    ],
    "sg:phone":"+1 414 281 1234",
    "sg:postcode":"53221",
    "sg:province":"WI",
    "sg:website":"www.cherek.com",
    "wof:name":"Cherek Lincoln-Mercury Inc",
    "wof:placetype":"venue"
},
  "geometry": {"coordinates":[-87.949404,42.933091],"type":"Point"}
}