{
  "type": "Feature",
  "properties": {
    "addr:full":"708 Superior Ave Tomah WI 54660",
    "addr:housenumber":"708",
    "addr:postcode":"54660",
    "addr:street":"Superior Ave",
    "iso:country":"US",
    "sg:address":"708 Superior Ave",
    "sg:city":"Tomah",
    "sg:classifiers":[
        {
            "category":"Personal",
            "subcategory":"Beauty Salon",
            "type":"Services"
        }
    ],
    "sg:phone":"+1 608 372 9632",
    "sg:postcode":"54660",
    "sg:province":"WI",
    "sg:tags":[
        "shop"
    ],
    "wof:name":"Shear Designs",
    "wof:placetype":"venue"
},
  "geometry": {"coordinates":[-90.504689,43.980451],"type":"Point"}
}