{
  "type": "Feature",
  "properties": {
    "iso:country":"US",
    "sg:address":"4215 Green Bay Rd",
    "sg:city":"Kenosha",
    "sg:classifiers":[
        {
            "category":"Banks & Credit Unions",
            "subcategory":"Bank",
            "type":"Services"
        }
    ],
    "sg:phone":"+1 262 657 5626",
    "sg:postcode":"53144",
    "sg:province":"WI",
    "sg:tags":[
        "federal"
    ],
    "wof:name":"Educators Credit Union",
    "wof:placetype":"venue"
},
  "geometry": {"coordinates":[-87.879739,42.599715],"type":"Point"}
}