{
  "type": "Feature",
  "properties": {
    "iso:country":"US",
    "sg:address":"4438 Just Ct",
    "sg:city":"Manitowoc",
    "sg:classifiers":[
        {
            "category":"Arts & Performance",
            "subcategory":"Theater",
            "type":"Entertainment"
        }
    ],
    "sg:phone":"+1 920 682 7456",
    "sg:postcode":"54220",
    "sg:province":"WI",
    "sg:tags":[
        "group"
    ],
    "wof:name":"D R D JS Services",
    "wof:placetype":"venue"
},
  "geometry": {"coordinates":[-87.703796,44.117641],"type":"Point"}
}