{
  "type": "Feature",
  "properties": {
    "iso:country":"US",
    "sg:address":"515 S Lake Ave",
    "sg:city":"Phillips",
    "sg:classifiers":[
        {
            "category":"Autos & Motor Vehicles",
            "subcategory":"Fuel & Gas Station",
            "type":"Retail Goods"
        }
    ],
    "sg:phone":"+1 715 339 3655",
    "sg:postcode":"54555",
    "sg:province":"WI",
    "sg:tags":[
        "oil"
    ],
    "wof:name":"Phillips Service Ctr",
    "wof:placetype":"venue"
},
  "geometry": {"coordinates":[-90.39102099999999,45.684991],"type":"Point"}
}