{
  "type": "Feature",
  "properties": {
    "addr:full":"3973 Redwood Dr Pulaski WI 54162",
    "addr:housenumber":"3973",
    "addr:postcode":"54162",
    "addr:street":"Redwood Dr",
    "iso:country":"US",
    "sg:address":"3973 Redwood Dr",
    "sg:city":"Pulaski",
    "sg:classifiers":[
        {
            "category":"Real Estate",
            "subcategory":"Developer",
            "type":"Services"
        }
    ],
    "sg:phone":"+1 920 865 4066",
    "sg:postcode":"54162",
    "sg:province":"WI",
    "wof:name":"White Pine Realty Inc",
    "wof:placetype":"venue"
},
  "geometry": {"coordinates":[-88.141085,44.664773],"type":"Point"}
}