{
  "type": "Feature",
  "properties": {
    "iso:country":"US",
    "sg:address":"801 W Stout St",
    "sg:city":"Chetek",
    "sg:classifiers":[
        {
            "category":"Real Estate",
            "subcategory":"Real Estate Agent",
            "type":"Services"
        }
    ],
    "sg:phone":"+1 715 924 3300",
    "sg:postcode":"54728",
    "sg:province":"WI",
    "sg:tags":[
        "authorities",
        "housing"
    ],
    "wof:name":"Chetek Housing Authority",
    "wof:placetype":"venue"
},
  "geometry": {"coordinates":[-91.66107599999999,45.315844],"type":"Point"}
}