{
  "type": "Feature",
  "properties": {
    "iso:country":"US",
    "sg:address":"3525 Terra Ct",
    "sg:city":"Sun Prairie",
    "sg:classifiers":[
        {
            "category":"Personal",
            "subcategory":"Barber",
            "type":"Services"
        }
    ],
    "sg:phone":"+1 608 243 1503",
    "sg:postcode":"53590",
    "sg:province":"WI",
    "sg:tags":[
        "shop"
    ],
    "wof:name":"Cutting Edge Metal Fab Inc",
    "wof:placetype":"venue"
},
  "geometry": {"coordinates":[-89.272148,43.155579],"type":"Point"}
}