{
  "type": "Feature",
  "properties": {
    "iso:country":"US",
    "sg:address":"4091 Beaver Dam Rd",
    "sg:city":"West Bend",
    "sg:classifiers":[
        {
            "category":"Professional",
            "subcategory":"Management & Consulting",
            "type":"Services"
        }
    ],
    "sg:phone":"+1 262 338 0411",
    "sg:postcode":"53090",
    "sg:province":"WI",
    "wof:name":"Stars In Stripes",
    "wof:placetype":"venue"
},
  "geometry": {"coordinates":[-88.240241,43.449212],"type":"Point"}
}