{
  "type": "Feature",
  "properties": {
    "iso:country":"US",
    "sg:address":"140 Poplar St",
    "sg:city":"Turtle Lake",
    "sg:classifiers":[
        {
            "category":"Retail",
            "subcategory":"Repair Shop",
            "type":"Services"
        }
    ],
    "sg:phone":"+1 715 986 2451",
    "sg:postcode":"54889",
    "sg:province":"WI",
    "wof:name":"Selles Engine Repair",
    "wof:placetype":"venue"
},
  "geometry": {"coordinates":[-92.133961,45.396937],"type":"Point"}
}