{
  "type": "Feature",
  "properties": {
    "iso:country":"US",
    "sg:address":"583 Eagle Rd",
    "sg:city":"Neshkoro",
    "sg:classifiers":[
        {
            "category":"Retail",
            "subcategory":"Veterinary Services",
            "type":"Services"
        }
    ],
    "sg:phone":"+1 920 295 3007",
    "sg:postcode":"54960",
    "sg:province":"WI",
    "wof:name":"Animal Entertainments Inc",
    "wof:placetype":"venue"
},
  "geometry": {"coordinates":[-89.179806,43.894674],"type":"Point"}
}