{
  "type": "Feature",
  "properties": {
    "iso:country":"US",
    "sg:address":"3009 88th Pl",
    "sg:city":"Kenosha",
    "sg:classifiers":[
        {
            "category":"Professional",
            "subcategory":"Business Services",
            "type":"Services"
        }
    ],
    "sg:phone":"+1 262 694 0574",
    "sg:postcode":"53142",
    "sg:province":"IL",
    "wof:name":"Ladine Ltd Partnership",
    "wof:placetype":"venue"
},
  "geometry": {"coordinates":[-87.845911,42.544925],"type":"Point"}
}