{
  "type": "Feature",
  "properties": {
    "iso:country":"US",
    "sg:address":"312 S Tomahawk Ave",
    "sg:city":"Tomahawk",
    "sg:classifiers":[
        {
            "category":"Autos & Motor Vehicles",
            "subcategory":"Fuel & Gas Station",
            "type":"Retail Goods"
        }
    ],
    "sg:phone":"+1 715 453 4807",
    "sg:postcode":"54487",
    "sg:province":"WI",
    "sg:tags":[
        "station"
    ],
    "wof:name":"Remington Oil",
    "wof:placetype":"venue"
},
  "geometry": {"coordinates":[-89.73368000000001,45.467865],"type":"Point"}
}