{
  "type": "Feature",
  "properties": {
    "iso:country":"US",
    "sg:address":"8540 W Brown Deer Rd",
    "sg:city":"Milwaukee",
    "sg:classifiers":[
        {
            "category":"Personal",
            "subcategory":"Beauty Salon",
            "type":"Services"
        }
    ],
    "sg:phone":"+1 414 354 4522",
    "sg:postcode":"53224",
    "sg:province":"WI",
    "sg:tags":[
        "shop"
    ],
    "wof:name":"Supercuts",
    "wof:placetype":"venue"
},
  "geometry": {"coordinates":[-88.02392500000001,43.177791],"type":"Point"}
}