{
  "type": "Feature",
  "properties": {
    "iso:country":"US",
    "sg:address":"2535 S Kinnickinnic Ave",
    "sg:city":"Milwaukee",
    "sg:classifiers":[
        {
            "category":"Restaurant",
            "type":"Food & Drink"
        }
    ],
    "sg:phone":"+1 414 481 8060",
    "sg:postcode":"53207",
    "sg:province":"WI",
    "sg:tags":[
        "ballroom",
        "facility",
        "banquet",
        "reception",
        "caterer",
        "halls",
        "hall",
        "auditorium"
    ],
    "wof:name":"Bay View Banquets & Casino",
    "wof:placetype":"venue"
},
  "geometry": {"coordinates":[-87.900626,42.99862],"type":"Point"}
}