{
  "type": "Feature",
  "properties": {
    "iso:country":"US",
    "sg:address":"55 W Hosmer St",
    "sg:city":"Marinette",
    "sg:classifiers":[
        {
            "category":"Retail",
            "subcategory":"Auto Repair",
            "type":"Services"
        }
    ],
    "sg:phone":"+1 715 732 5444",
    "sg:postcode":"54143",
    "sg:province":"WI",
    "sg:tags":[
        "repairing",
        "automobile"
    ],
    "wof:name":"Auto Plus Inc",
    "wof:placetype":"venue"
},
  "geometry": {"coordinates":[-87.6003,45.089992],"type":"Point"}
}