{
  "type": "Feature",
  "properties": {
    "addr:full":"501 Progress Dr Hartland WI 53029",
    "addr:housenumber":"501",
    "addr:postcode":"53029",
    "addr:street":"Progress Dr",
    "iso:country":"US",
    "sg:address":"501 Progress Dr",
    "sg:city":"Hartland",
    "sg:classifiers":[
        {
            "category":"Manufacturing",
            "subcategory":"Tools & Machinery",
            "type":"Manufacturing & Wholesale Goods"
        }
    ],
    "sg:phone":"+1 262 367 1060",
    "sg:postcode":"53029",
    "sg:province":"WI",
    "sg:tags":[
        "machine",
        "shop",
        "job",
        "welding"
    ],
    "wof:name":"Kapco Machine of Hartland",
    "wof:placetype":"venue"
},
  "geometry": {"coordinates":[-88.355943,43.096246],"type":"Point"}
}