{
  "type": "Feature",
  "properties": {
    "iso:country":"US",
    "sg:address":"12020 W Feerick St",
    "sg:city":"Milwaukee",
    "sg:classifiers":[
        {
            "category":"Professional",
            "subcategory":"Detective & Security Services",
            "type":"Services"
        }
    ],
    "sg:phone":"+1 414 536 3000",
    "sg:postcode":"53222",
    "sg:province":"WI",
    "sg:tags":[
        "system"
    ],
    "wof:name":"Brinks Home Security Inc",
    "wof:placetype":"venue"
},
  "geometry": {"coordinates":[-88.066177,43.086086],"type":"Point"}
}