{
  "type": "Feature",
  "properties": {
    "iso:country":"US",
    "sg:address":"255 W Lincoln Ave",
    "sg:city":"Hartford",
    "sg:classifiers":[
        {
            "category":"Social Services",
            "subcategory":"Child Care",
            "type":"Services"
        }
    ],
    "sg:phone":"+1 262 673 0161",
    "sg:postcode":"53027",
    "sg:province":"WI",
    "sg:tags":[
        "day"
    ],
    "wof:name":"Sycamore Tree Day Care",
    "wof:placetype":"venue"
},
  "geometry": {"coordinates":[-88.382449,43.311013],"type":"Point"}
}