{
  "type": "Feature",
  "properties": {
    "iso:country":"US",
    "sg:address":"1200 Joseph St",
    "sg:city":"Dodgeville",
    "sg:classifiers":[
        {
            "category":"Retail",
            "subcategory":"Car Wash",
            "type":"Services"
        }
    ],
    "sg:phone":"+1 608 935 5735",
    "sg:postcode":"53533",
    "sg:province":"WI",
    "sg:tags":[
        "polishing",
        "washing"
    ],
    "wof:name":"Dodgeville Wonder Wash",
    "wof:placetype":"venue"
},
  "geometry": {"coordinates":[-90.13684600000001,42.972691],"type":"Point"}
}