{
  "type": "Feature",
  "properties": {
    "iso:country":"US",
    "sg:address":"710 S 14th St",
    "sg:city":"Sheboygan",
    "sg:classifiers":[
        {
            "category":"Retail",
            "subcategory":"Auto Repair",
            "type":"Services"
        },
        {
            "category":"Wholesale",
            "subcategory":"Auto Parts",
            "type":"Manufacturing & Wholesale Goods"
        }
    ],
    "sg:phone":"+1 920 452 9872",
    "sg:postcode":"53081",
    "sg:province":"WI",
    "sg:tags":[
        "repairing",
        "exhaust",
        "system",
        "tire",
        "automobile"
    ],
    "wof:name":"Wittrock's Tire & Muffler Inc",
    "wof:placetype":"venue"
},
  "geometry": {"coordinates":[-87.723026,43.746609],"type":"Point"}
}