{
  "type": "Feature",
  "properties": {
    "addr:full":"4137 Peterson Rd Sturgeon Bay WI 54235",
    "addr:housenumber":"4137",
    "addr:postcode":"54235",
    "addr:street":"Peterson Rd",
    "iso:country":"US",
    "sg:address":"4137 Peterson Rd",
    "sg:city":"Sturgeon Bay",
    "sg:classifiers":[
        {
            "category":"Building & Trades",
            "subcategory":"Plumbing",
            "type":"Services"
        }
    ],
    "sg:phone":"+1 920 743 7009",
    "sg:postcode":"54235",
    "sg:province":"WI",
    "sg:tags":[
        "tank",
        "septic"
    ],
    "wof:name":"Fellner Soil Analysis & Conslt",
    "wof:placetype":"venue"
},
  "geometry": {"coordinates":[-87.361707,44.867186],"type":"Point"}
}