{
  "type": "Feature",
  "properties": {
    "iso:country":"US",
    "sg:address":"876 Iroquois Cir",
    "sg:city":"Baraboo",
    "sg:classifiers":[
        {
            "category":"Real Estate",
            "subcategory":"Real Estate Operator",
            "type":"Services"
        }
    ],
    "sg:phone":"+1 608 356 2880",
    "sg:postcode":"53913",
    "sg:province":"WI",
    "sg:tags":[
        "building",
        "apartment"
    ],
    "wof:name":"B & B Rentals",
    "wof:placetype":"venue"
},
  "geometry": {"coordinates":[-89.756912,43.482012],"type":"Point"}
}