{
  "type": "Feature",
  "properties": {
    "addr:full":"9200 Wyndham Hills Ct Franklin WI 53132",
    "addr:housenumber":"9200",
    "addr:postcode":"53132",
    "addr:street":"Wyndham Hills Ct",
    "iso:country":"US",
    "sg:address":"9200 Wyndham Hills Ct",
    "sg:city":"Franklin",
    "sg:classifiers":[
        {
            "category":"Recreation",
            "type":"Entertainment"
        }
    ],
    "sg:phone":"+1 414 427 0030",
    "sg:postcode":"53132",
    "sg:province":"WI",
    "sg:tags":[
        "rental",
        "event",
        "supply"
    ],
    "wof:name":"Event Source LLC",
    "wof:placetype":"venue"
},
  "geometry": {"coordinates":[-88.029979,42.904565],"type":"Point"}
}