{
  "type": "Feature",
  "properties": {
    "iso:country":"US",
    "sg:address":"1205 W Wolf River Ave",
    "sg:city":"New London",
    "sg:classifiers":[
        {
            "category":"Shopping",
            "subcategory":"Bicycles & Sporting Goods",
            "type":"Retail Goods"
        }
    ],
    "sg:phone":"+1 920 982 4802",
    "sg:postcode":"54961",
    "sg:province":"WI",
    "sg:tags":[
        "bait",
        "fishing"
    ],
    "wof:name":"Cash's Little Shoppe Of Bait",
    "wof:placetype":"venue"
},
  "geometry": {"coordinates":[-88.75341,44.390619],"type":"Point"}
}