{
  "type": "Feature",
  "properties": {
    "iso:country":"US",
    "sg:address":"222 Stewart Ave",
    "sg:city":"Wausau",
    "sg:classifiers":[
        {
            "category":"Restaurant",
            "type":"Food & Drink"
        }
    ],
    "sg:menulink":"http://www.allmenus.com/wi/wausau/181529-kfc---kentucky-fried-chicken/menu/",
    "sg:phone":"+1 715 842 3667",
    "sg:postcode":"54401",
    "sg:province":"WI",
    "sg:tags":[
        "american",
        "chicken"
    ],
    "wof:name":"KFC - Kentucky Fried Chicken",
    "wof:placetype":"venue"
},
  "geometry": {"coordinates":[-89.63837599999999,44.959432],"type":"Point"}
}