{
  "type": "Feature",
  "properties": {
    "iso:country":"US",
    "sg:address":"5798 Star Neva Rd",
    "sg:city":"Deerbrook",
    "sg:phone":"+1 715 623 6963",
    "sg:postcode":"54424",
    "sg:province":"WI",
    "sg:tags":[
        "farm",
        "field",
        "irish",
        "crop",
        "potato"
    ],
    "wof:name":"J W Mattek & Sons Inc",
    "wof:placetype":"venue"
},
  "geometry": {"coordinates":[-89.113247,45.237947],"type":"Point"}
}