{
  "type": "Feature",
  "properties": {
    "iso:country":"US",
    "sg:address":"4833 Sheldon Ave",
    "sg:city":"Oconomowoc",
    "sg:classifiers":[
        {
            "category":"Retail",
            "subcategory":"Auto Repair",
            "type":"Services"
        }
    ],
    "sg:phone":"+1 262 567 6830",
    "sg:postcode":"53066",
    "sg:province":"WI",
    "sg:tags":[
        "repairing",
        "automobile"
    ],
    "wof:name":"J & J Auto Electric",
    "wof:placetype":"venue"
},
  "geometry": {"coordinates":[-88.484889,43.108182],"type":"Point"}
}