{
  "type": "Feature",
  "properties": {
    "addr:full":"2548 Lake Shore Dr La Crosse WI 54603",
    "addr:housenumber":"2548",
    "addr:postcode":"54603",
    "addr:street":"Lake Shore Dr",
    "iso:country":"US",
    "sg:address":"2548 Lake Shore Dr",
    "sg:city":"La Crosse",
    "sg:classifiers":[
        {
            "category":"Organizations",
            "subcategory":"Religious Organization",
            "type":"Services"
        }
    ],
    "sg:phone":"+1 608 783 1272",
    "sg:postcode":"54603",
    "sg:province":"WI",
    "sg:tags":[
        "church"
    ],
    "wof:name":"Island Park Baptist CHURCH",
    "wof:placetype":"venue"
},
  "geometry": {"coordinates":[-91.26971899999999,43.863877],"type":"Point"}
}