{
  "type": "Feature",
  "properties": {
    "addr:full":"3630 Riverside Dr Green Bay WI 54301",
    "addr:housenumber":"3630",
    "addr:postcode":"54301",
    "addr:street":"Riverside Dr",
    "iso:country":"US",
    "sg:address":"3630 Riverside Dr",
    "sg:city":"Green Bay",
    "sg:classifiers":[
        {
            "category":"Autos & Motor Vehicles",
            "subcategory":"Fuel & Gas Station",
            "type":"Retail Goods"
        }
    ],
    "sg:phone":"+1 920 336 8262",
    "sg:postcode":"54301",
    "sg:province":"WI",
    "sg:tags":[
        "automotive",
        "general",
        "gasoline",
        "repair"
    ],
    "wof:name":"Peters Service Center Inc",
    "wof:placetype":"venue"
},
  "geometry": {"coordinates":[-88.050225,44.463941],"type":"Point"}
}