{
  "type": "Feature",
  "properties": {
    "iso:country":"US",
    "sg:address":"6575 95th St",
    "sg:city":"Chippewa Falls",
    "sg:classifiers":[
        {
            "category":"Building & Trades",
            "subcategory":"Electrical",
            "type":"Services"
        }
    ],
    "sg:phone":"+1 715 723 7046",
    "sg:postcode":"54729",
    "sg:province":"WI",
    "sg:tags":[
        "electrical",
        "contractor"
    ],
    "wof:name":"Double M Service",
    "wof:placetype":"venue"
},
  "geometry": {"coordinates":[-91.478977,44.942174],"type":"Point"}
}