{
  "type": "Feature",
  "properties": {
    "iso:country":"US",
    "sg:address":"928 Freeman St",
    "sg:city":"Genoa City",
    "sg:classifiers":[
        {
            "category":"Building & Trades",
            "subcategory":"Construction",
            "type":"Services"
        }
    ],
    "sg:phone":"+1 262 279 2880",
    "sg:postcode":"53128",
    "sg:province":"WI",
    "sg:tags":[
        "contractor"
    ],
    "wof:name":"Fix-A-Closet & More Inc",
    "wof:placetype":"venue"
},
  "geometry": {"coordinates":[-88.329872,42.505257],"type":"Point"}
}