{
  "type": "Feature",
  "properties": {
    "iso:country":"US",
    "sg:address":"205 South St",
    "sg:city":"Bonduel",
    "sg:classifiers":[
        {
            "category":"Farming",
            "subcategory":"Farm & Veterinary Services",
            "type":"Manufacturing & Wholesale Goods"
        }
    ],
    "sg:phone":"+1 715 758 7990",
    "sg:postcode":"54107",
    "sg:province":"WI",
    "wof:name":"Stuart Sorenson Feed & Grain",
    "wof:placetype":"venue"
},
  "geometry": {"coordinates":[-88.450838,44.734782],"type":"Point"}
}