{
  "type": "Feature",
  "properties": {
    "iso:country":"US",
    "sg:address":"152 Park St",
    "sg:city":"Redgranite",
    "sg:classifiers":[
        {
            "category":"Retail",
            "subcategory":"Repair Shop",
            "type":"Services"
        }
    ],
    "sg:phone":"+1 920 566 4573",
    "sg:postcode":"54970",
    "sg:province":"WI",
    "wof:name":"S Gunderson Repair",
    "wof:placetype":"venue"
},
  "geometry": {"coordinates":[-89.106796,44.043476],"type":"Point"}
}