{
  "type": "Feature",
  "properties": {
    "iso:country":"US",
    "sg:address":"1288 Rudy St",
    "sg:city":"Onalaska",
    "sg:classifiers":[
        {
            "category":"Manufacturing",
            "subcategory":"Tools & Machinery",
            "type":"Manufacturing & Wholesale Goods"
        }
    ],
    "sg:phone":"+1 608 781 7180",
    "sg:postcode":"54650",
    "sg:province":"WI",
    "sg:tags":[
        "equipment",
        "electric"
    ],
    "wof:name":"Rockwell Automation",
    "wof:placetype":"venue"
},
  "geometry": {"coordinates":[-91.19774200000001,43.875854],"type":"Point"}
}