{
  "type": "Feature",
  "properties": {
    "iso:country":"US",
    "sg:address":"1030 Ontario Ave",
    "sg:city":"Sheboygan",
    "sg:classifiers":[
        {
            "category":"Building & Trades",
            "subcategory":"Construction",
            "type":"Services"
        }
    ],
    "sg:phone":"+1 920 457 6602",
    "sg:postcode":"53081",
    "sg:province":"WI",
    "sg:tags":[
        "auto",
        "contractor",
        "specialty",
        "special",
        "mfg"
    ],
    "wof:name":"Rlo Sign Inc",
    "wof:placetype":"venue"
},
  "geometry": {"coordinates":[-87.717572,43.75534],"type":"Point"}
}