{
  "type": "Feature",
  "properties": {
    "iso:country":"US",
    "sg:address":"3435 690th St",
    "sg:city":"Menomonie",
    "sg:phone":"+1 715 235 7117",
    "sg:postcode":"54751",
    "sg:province":"WI",
    "sg:tags":[
        "farm",
        "field",
        "corn",
        "crop"
    ],
    "wof:name":"Daniel Skillings",
    "wof:placetype":"venue"
},
  "geometry": {"coordinates":[-91.81207000000001,44.788405],"type":"Point"}
}