{
  "type": "Feature",
  "properties": {
    "iso:country":"US",
    "sg:address":"2294 State Hwy 60",
    "sg:city":"Neosho",
    "sg:phone":"+1 920 625 3783",
    "sg:postcode":"53059",
    "sg:province":"WI",
    "sg:tags":[
        "farm",
        "corn",
        "soybean"
    ],
    "wof:name":"Ruth Hintz",
    "wof:placetype":"venue"
},
  "geometry": {"coordinates":[-88.52645,43.326697],"type":"Point"}
}