{
  "type": "Feature",
  "properties": {
    "addr:full":"17 W Main St Madison WI 53703",
    "addr:housenumber":"17",
    "addr:postcode":"53703",
    "addr:street":"W Main St",
    "iso:country":"US",
    "sg:address":"17 W Main St",
    "sg:city":"Madison",
    "sg:classifiers":[
        {
            "category":"Social Services",
            "type":"Services"
        }
    ],
    "sg:phone":"+1 608 264 9497",
    "sg:postcode":"53703",
    "sg:province":"WI",
    "sg:tags":[
        "victim",
        "crime"
    ],
    "wof:name":"Crime Victim Compensation",
    "wof:placetype":"venue"
},
  "geometry": {"coordinates":[-89.38392899999999,43.073225],"type":"Point"}
}