{
  "type": "Feature",
  "properties": {
    "iso:country":"US",
    "sg:address":"2778 N 24th St",
    "sg:city":"Milwaukee",
    "sg:classifiers":[
        {
            "category":"Bars & Pubs",
            "type":"Food & Drink"
        }
    ],
    "sg:phone":"+1 414 265 4015",
    "sg:postcode":"53206",
    "sg:province":"WI",
    "wof:name":"Place",
    "wof:placetype":"venue"
},
  "geometry": {"coordinates":[-87.94237,43.068225],"type":"Point"}
}