{
  "type": "Feature",
  "properties": {
    "iso:country":"US",
    "sg:address":"5582 Co Rd G",
    "sg:city":"West Bend",
    "sg:classifiers":[
        {
            "category":"Professional",
            "subcategory":"Business Services",
            "type":"Services"
        }
    ],
    "sg:phone":"+1 262 335 0195",
    "sg:postcode":"53095",
    "sg:province":"WI",
    "wof:name":"Robert Vogt",
    "wof:placetype":"venue"
},
  "geometry": {"coordinates":[-88.16091,43.384266],"type":"Point"}
}