{
  "type": "Feature",
  "properties": {
    "addr:full":"2614 E Milwaukee St Janesville WI 53545",
    "addr:housenumber":"2614",
    "addr:postcode":"53545",
    "addr:street":"E Milwaukee St",
    "iso:country":"US",
    "sg:address":"2614 E Milwaukee St",
    "sg:city":"Janesville",
    "sg:classifiers":[
        {
            "category":"Restaurant",
            "type":"Food & Drink"
        }
    ],
    "sg:phone":"+1 608 756 5638",
    "sg:postcode":"53545",
    "sg:province":"WI",
    "sg:tags":[
        "delicatessen"
    ],
    "wof:name":"European American Deli",
    "wof:placetype":"venue"
},
  "geometry": {"coordinates":[-88.98988199999999,42.694591],"type":"Point"}
}