{
  "type": "Feature",
  "properties": {
    "addr:full":"375 Buffalo St Sheboygan Falls WI 53085",
    "addr:housenumber":"375",
    "addr:postcode":"53085",
    "addr:street":"Buffalo St",
    "iso:country":"US",
    "sg:address":"375 Buffalo St",
    "sg:city":"Sheboygan Falls",
    "sg:classifiers":[
        {
            "category":"Government",
            "subcategory":"Office",
            "type":"Public Place"
        }
    ],
    "sg:phone":"+1 920 467 2770",
    "sg:postcode":"53085",
    "sg:province":"WI",
    "sg:tags":[
        "village"
    ],
    "wof:name":"Sheboygan Falls Senior Citizen",
    "wof:placetype":"venue"
},
  "geometry": {"coordinates":[-87.81265500000001,43.728738],"type":"Point"}
}