{
  "type": "Feature",
  "properties": {
    "iso:country":"US",
    "sg:address":"3249 Fawn Rd",
    "sg:city":"Wausau",
    "sg:classifiers":[
        {
            "category":"Retail",
            "subcategory":"Repair Shop",
            "type":"Services"
        }
    ],
    "sg:phone":"+1 715 675 6955",
    "sg:postcode":"54403",
    "sg:province":"WI",
    "wof:name":"Back 80 Taxidermy",
    "wof:placetype":"venue"
},
  "geometry": {"coordinates":[-89.577057,45.082833],"type":"Point"}
}