{
  "type": "Feature",
  "properties": {
    "addr:full":"3326 Peterson St Eau Claire WI 54703",
    "addr:housenumber":"3326",
    "addr:postcode":"54703",
    "addr:street":"Peterson St",
    "iso:country":"US",
    "sg:address":"3326 Peterson St",
    "sg:city":"Eau Claire",
    "sg:classifiers":[
        {
            "category":"Utilities",
            "subcategory":"Refuse",
            "type":"Services"
        }
    ],
    "sg:phone":"+1 715 831 8325",
    "sg:postcode":"54703",
    "sg:province":"WI",
    "sg:tags":[
        "system"
    ],
    "wof:name":"Northern Recycling Eqp Co",
    "wof:placetype":"venue"
},
  "geometry": {"coordinates":[-91.458735,44.866633],"type":"Point"}
}