{
  "type": "Feature",
  "properties": {
    "addr:full":"6385 Division Rd Glenbeulah WI 53023",
    "addr:housenumber":"6385",
    "addr:postcode":"53023",
    "addr:street":"Division Rd",
    "iso:country":"US",
    "sg:address":"6385 Division Rd",
    "sg:city":"Glenbeulah",
    "sg:classifiers":[
        {
            "category":"Professional",
            "subcategory":"Business Services",
            "type":"Services"
        }
    ],
    "sg:phone":"+1 920 999 5502",
    "sg:postcode":"53023",
    "sg:province":"WI",
    "wof:name":"Farm Country Gospel Music",
    "wof:placetype":"venue"
},
  "geometry": {"coordinates":[-88.160597,43.765285],"type":"Point"}
}