{
  "type": "Feature",
  "properties": {
    "iso:country":"US",
    "sg:address":"7602 S Logan Ave",
    "sg:city":"Oak Creek",
    "sg:classifiers":[
        {
            "category":"Education",
            "subcategory":"Special Training",
            "type":"Public Place"
        }
    ],
    "sg:phone":"+1 414 762 5881",
    "sg:postcode":"53154",
    "sg:province":"WI",
    "wof:name":"Education Training & Comm LLC",
    "wof:placetype":"venue"
},
  "geometry": {"coordinates":[-87.89798999999999,42.904789],"type":"Point"}
}