{
  "type": "Feature",
  "properties": {
    "addr:full":"7240 Sycamore Dr Cedarburg WI 53012",
    "addr:housenumber":"7240",
    "addr:postcode":"53012",
    "addr:street":"Sycamore Dr",
    "iso:country":"US",
    "sg:address":"7240 Sycamore Dr",
    "sg:city":"Cedarburg",
    "sg:classifiers":[
        {
            "category":"Government",
            "subcategory":"Office",
            "type":"Public Place"
        }
    ],
    "sg:phone":"+1 262 377 6477",
    "sg:postcode":"53012",
    "sg:province":"WI",
    "sg:tags":[
        "test",
        "station"
    ],
    "wof:name":"Test Station",
    "wof:placetype":"venue"
},
  "geometry": {"coordinates":[-88.000331,43.320772],"type":"Point"}
}