{
  "type": "Feature",
  "properties": {
    "iso:country":"US",
    "sg:address":"645 Wells St",
    "sg:city":"Delafield",
    "sg:classifiers":[
        {
            "category":"Banks & Credit Unions",
            "subcategory":"Investment Brokerage",
            "type":"Services"
        }
    ],
    "sg:phone":"+1 262 646 5073",
    "sg:postcode":"53018",
    "sg:province":"WI",
    "sg:tags":[
        "security"
    ],
    "wof:name":"Edward Jones Co",
    "wof:placetype":"venue"
},
  "geometry": {"coordinates":[-88.40315099999999,43.060029],"type":"Point"}
}