{
  "type": "Feature",
  "properties": {
    "iso:country":"US",
    "sg:address":"4299 S Helenville Rd",
    "sg:city":"Helenville",
    "sg:classifiers":[
        {
            "category":"Farming",
            "subcategory":"Farm & Veterinary Services",
            "type":"Manufacturing & Wholesale Goods"
        }
    ],
    "sg:phone":"+1 920 674 2378",
    "sg:postcode":"53137",
    "sg:province":"WI",
    "sg:tags":[
        "sample",
        "soil",
        "groundwater",
        "drilling"
    ],
    "wof:name":"Kitson Environmental Services",
    "wof:placetype":"venue"
},
  "geometry": {"coordinates":[-88.708111,42.99537],"type":"Point"}
}