{
  "type": "Feature",
  "properties": {
    "iso:country":"US",
    "sg:address":"4605 Bunker Hill Ln",
    "sg:city":"Madison",
    "sg:classifiers":[
        {
            "category":"Shopping",
            "subcategory":"Computers & Home Electronics",
            "type":"Retail Goods"
        }
    ],
    "sg:phone":"+1 608 246 8630",
    "sg:postcode":"53704",
    "sg:province":"WI",
    "sg:tags":[
        "software"
    ],
    "wof:name":"Reynolds & Reynolds Co",
    "wof:placetype":"venue"
},
  "geometry": {"coordinates":[-89.305125,43.133366],"type":"Point"}
}