{
  "type": "Feature",
  "properties": {
    "iso:country":"US",
    "sg:address":"7714 N Chadwick Rd",
    "sg:city":"Milwaukee",
    "sg:classifiers":[
        {
            "category":"Building & Trades",
            "subcategory":"Cleaning & Sanitation",
            "type":"Services"
        },
        {
            "category":"Retail",
            "subcategory":"Repair Shop",
            "type":"Services"
        }
    ],
    "sg:phone":"+1 414 352 1484",
    "sg:postcode":"53217",
    "sg:province":"WI",
    "sg:tags":[
        "real",
        "venetian",
        "blind",
        "esta",
        "maintenance"
    ],
    "wof:name":"Structure Valet Services Co",
    "wof:placetype":"venue"
},
  "geometry": {"coordinates":[-87.91400899999999,43.158334],"type":"Point"}
}