{
  "type": "Feature",
  "properties": {
    "addr:full":"410 Packerland Dr Green Bay WI 54303",
    "addr:housenumber":"410",
    "addr:postcode":"54303",
    "addr:street":"Packerland Dr",
    "iso:country":"US",
    "sg:address":"410 Packerland Dr",
    "sg:city":"Green Bay",
    "sg:classifiers":[
        {
            "category":"Retail",
            "subcategory":"Auto Repair",
            "type":"Services"
        }
    ],
    "sg:phone":"+1 920 499 1475",
    "sg:postcode":"54303",
    "sg:province":"WI",
    "sg:tags":[
        "engine"
    ],
    "wof:name":"Diesel Specialists-Green Bay",
    "wof:placetype":"venue"
},
  "geometry": {"coordinates":[-88.094504,44.531535],"type":"Point"}
}