{
  "type": "Feature",
  "properties": {
    "iso:country":"US",
    "sg:address":"4430 N 127th St",
    "sg:city":"Brookfield",
    "sg:classifiers":[
        {
            "category":"Professional",
            "subcategory":"Lawyer & Legal Services",
            "type":"Services"
        }
    ],
    "sg:phone":"+1 262 781 2425",
    "sg:postcode":"53005",
    "sg:province":"WI",
    "sg:tags":[
        "attorney"
    ],
    "wof:name":"Melvin E Beyer",
    "wof:placetype":"venue"
},
  "geometry": {"coordinates":[-88.069577,43.097271],"type":"Point"}
}