{
  "type": "Feature",
  "properties": {
    "addr:full":"5859 S 13th St Milwaukee WI 53221",
    "addr:housenumber":"5859",
    "addr:postcode":"53221",
    "addr:street":"S 13Th St",
    "iso:country":"US",
    "sg:address":"5859 S 13th St",
    "sg:city":"Milwaukee",
    "sg:classifiers":[
        {
            "category":"Local Transit",
            "type":"Transportation"
        }
    ],
    "sg:phone":"+1 414 281 6666",
    "sg:postcode":"53221",
    "sg:province":"WI",
    "sg:tags":[
        "limousine"
    ],
    "wof:name":"Crystal Limousine & Coach Inc",
    "wof:placetype":"venue"
},
  "geometry": {"coordinates":[-87.929582,42.938591],"type":"Point"}
}