{
  "type": "Feature",
  "properties": {
    "iso:country":"US",
    "sg:address":"4231 Argosy Ct Ste E",
    "sg:city":"Madison",
    "sg:classifiers":[
        {
            "category":"Manufacturing",
            "subcategory":"Wood Products",
            "type":"Manufacturing & Wholesale Goods"
        },
        {
            "category":"Home & Garden",
            "subcategory":"Building Materials",
            "type":"Retail Goods"
        },
        {
            "category":"Building & Trades",
            "subcategory":"Construction",
            "type":"Services"
        },
        {
            "category":"Home & Garden",
            "subcategory":"Furniture",
            "type":"Retail Goods"
        }
    ],
    "sg:phone":"+1 608 222 8111",
    "sg:postcode":"53714",
    "sg:province":"WI",
    "sg:tags":[
        "cabinet",
        "cabinets-wholesale",
        "altering",
        "improvement",
        "contractor",
        "remodeling",
        "manufacturer"
    ],
    "wof:name":"A & R Closet Creations Inc",
    "wof:placetype":"venue"
},
  "geometry": {"coordinates":[-89.309467,43.08836],"type":"Point"}
}