{
  "type": "Feature",
  "properties": {
    "iso:country":"US",
    "sg:address":"115 Watson St",
    "sg:city":"Ripon",
    "sg:classifiers":[
        {
            "category":"Shopping",
            "subcategory":"Clothing, Apparel, & Fashions",
            "type":"Retail Goods"
        }
    ],
    "sg:phone":"+1 920 748 6367",
    "sg:postcode":"54971",
    "sg:province":"WI",
    "sg:tags":[
        "woman",
        "accessory"
    ],
    "wof:name":"Watson Streetwear",
    "wof:placetype":"venue"
},
  "geometry": {"coordinates":[-88.838847,43.846126],"type":"Point"}
}