{
  "type": "Feature",
  "properties": {
    "iso:country":"US",
    "sg:address":"800 Clinton St",
    "sg:city":"Waukesha",
    "sg:classifiers":[
        {
            "category":"Restaurant",
            "type":"Food & Drink"
        }
    ],
    "sg:phone":"+1 262 547 6503",
    "sg:postcode":"53186",
    "sg:province":"WI",
    "sg:tags":[
        "tavern"
    ],
    "wof:name":"Mama Mia Restaurant",
    "wof:placetype":"venue"
},
  "geometry": {"coordinates":[-88.23287500000001,43.011212],"type":"Point"}
}