{
  "type": "Feature",
  "properties": {
    "addr:full":"4705 Lilac Ave Wausau WI 54401",
    "addr:housenumber":"4705",
    "addr:postcode":"54401",
    "addr:street":"Lilac Ave",
    "iso:country":"US",
    "sg:address":"4705 Lilac Ave",
    "sg:city":"Wausau",
    "sg:classifiers":[
        {
            "category":"Retail",
            "subcategory":"Auto Rental",
            "type":"Services"
        }
    ],
    "sg:phone":"+1 715 359 4291",
    "sg:postcode":"54401",
    "sg:province":"WI",
    "sg:tags":[
        "renting",
        "truck",
        "leasing"
    ],
    "wof:name":"Budget Truck Rental",
    "wof:placetype":"venue"
},
  "geometry": {"coordinates":[-89.64760800000001,44.9126],"type":"Point"}
}