{
  "type": "Feature",
  "properties": {
    "iso:country":"US",
    "sg:address":"910 E Silver Spring Dr",
    "sg:city":"Milwaukee",
    "sg:classifiers":[
        {
            "category":"Wholesale",
            "subcategory":"Machinery & Supplies",
            "type":"Manufacturing & Wholesale Goods"
        }
    ],
    "sg:phone":"+1 414 332 7851",
    "sg:postcode":"53217",
    "sg:province":"WI",
    "sg:tags":[
        "machine",
        "tool",
        "mfr",
        "rep"
    ],
    "wof:name":"Machine Tool Associates Inc",
    "wof:placetype":"venue"
},
  "geometry": {"coordinates":[-87.89907700000001,43.118484],"type":"Point"}
}