{
  "type": "Feature",
  "properties": {
    "iso:country":"US",
    "sg:address":"416 Co Rd D",
    "sg:city":"Eau Galle",
    "sg:classifiers":[
        {
            "category":"Personal",
            "type":"Services"
        }
    ],
    "sg:phone":"+1 715 283 4303",
    "sg:postcode":"54737",
    "sg:province":"WI",
    "sg:tags":[
        "wedding",
        "chapel"
    ],
    "wof:name":"Lakeside Wedding Chapel",
    "wof:placetype":"venue"
},
  "geometry": {"coordinates":[-92.020602,44.696758],"type":"Point"}
}