{
  "type": "Feature",
  "properties": {
    "iso:country":"US",
    "sg:address":"91 Courtney St",
    "sg:city":"Rhinelander",
    "sg:classifiers":[
        {
            "category":"Professional",
            "subcategory":"Computer Services",
            "type":"Services"
        }
    ],
    "sg:phone":"+1 715 362 4712",
    "sg:postcode":"54501",
    "sg:province":"WI",
    "wof:name":"ABC Computers Inc",
    "wof:placetype":"venue"
},
  "geometry": {"coordinates":[-89.41203,45.634799],"type":"Point"}
}