{
  "type": "Feature",
  "properties": {
    "iso:country":"US",
    "sg:address":"1945 Progress St",
    "sg:city":"Green Bay",
    "sg:classifiers":[
        {
            "category":"Wholesale",
            "subcategory":"Machinery & Supplies",
            "type":"Manufacturing & Wholesale Goods"
        }
    ],
    "sg:phone":"+1 920 494 8778",
    "sg:postcode":"54304",
    "sg:province":"WI",
    "sg:tags":[
        "equipment",
        "welding"
    ],
    "sg:website":"www.aga.com",
    "wof:name":"AGA Gas Inc",
    "wof:placetype":"venue"
},
  "geometry": {"coordinates":[-88.048818,44.497207],"type":"Point"}
}