{
  "type": "Feature",
  "properties": {
    "iso:country":"US",
    "sg:address":"5596 Sand Hill Rd",
    "sg:city":"Reedsburg",
    "sg:classifiers":[
        {
            "category":"Farming",
            "subcategory":"Dairy Farm",
            "type":"Manufacturing & Wholesale Goods"
        }
    ],
    "sg:phone":"+1 608 727 2807",
    "sg:postcode":"53959",
    "sg:province":"WI",
    "wof:name":"Darrell Myers",
    "wof:placetype":"venue"
},
  "geometry": {"coordinates":[-90.038539,43.460343],"type":"Point"}
}