{
  "type": "Feature",
  "properties": {
    "addr:full":"111 Division St Stevens Point WI 54481",
    "addr:housenumber":"111",
    "addr:postcode":"54481",
    "addr:street":"Division St",
    "iso:country":"US",
    "sg:address":"111 Division St",
    "sg:city":"Stevens Point",
    "sg:classifiers":[
        {
            "category":"Shopping",
            "subcategory":"Department Store",
            "type":"Retail Goods"
        }
    ],
    "sg:phone":"+1 715 341 6060",
    "sg:postcode":"54481",
    "sg:province":"WI",
    "wof:name":"Kmart",
    "wof:placetype":"venue"
},
  "geometry": {"coordinates":[-89.57488600000001,44.535222],"type":"Point"}
}