{
  "type": "Feature",
  "properties": {
    "iso:country":"US",
    "sg:address":"1400 Ellis St",
    "sg:city":"Waukesha",
    "sg:classifiers":[
        {
            "category":"Retail",
            "subcategory":"Auto Repair",
            "type":"Services"
        }
    ],
    "sg:phone":"+1 262 650 1951",
    "sg:postcode":"53186",
    "sg:province":"WI",
    "sg:tags":[
        "truck"
    ],
    "wof:name":"R & B Truck Repair",
    "wof:placetype":"venue"
},
  "geometry": {"coordinates":[-88.2042,43.006475],"type":"Point"}
}