{
  "type": "Feature",
  "properties": {
    "iso:country":"US",
    "sg:address":"305 W Wisconsin St",
    "sg:city":"Chippewa Falls",
    "sg:classifiers":[
        {
            "category":"Freight",
            "type":"Transportation"
        }
    ],
    "sg:phone":"+1 715 720 9015",
    "sg:postcode":"54729",
    "sg:province":"WI",
    "sg:tags":[
        "arrangement"
    ],
    "wof:name":"Wincek",
    "wof:placetype":"venue"
},
  "geometry": {"coordinates":[-91.394942,44.918588],"type":"Point"}
}