{
  "type": "Feature",
  "properties": {
    "iso:country":"US",
    "sg:address":"4805 Winnequah Rd",
    "sg:city":"Madison",
    "sg:classifiers":[
        {
            "category":"Building & Trades",
            "subcategory":"Construction",
            "type":"Services"
        }
    ],
    "sg:phone":"+1 608 222 2630",
    "sg:postcode":"53716",
    "sg:province":"WI",
    "sg:tags":[
        "floor",
        "laying",
        "contractor"
    ],
    "wof:name":"Gallagher Twoie Flr Refinishes",
    "wof:placetype":"venue"
},
  "geometry": {"coordinates":[-89.342148,43.06699],"type":"Point"}
}