{
  "type": "Feature",
  "properties": {
    "addr:full":"10485 State Hwy 29 Chippewa Falls WI 54729",
    "addr:housenumber":"10485",
    "addr:postcode":"54729",
    "addr:street":"State Hwy 29",
    "iso:country":"US",
    "sg:address":"10485 State Hwy 29",
    "sg:city":"Chippewa Falls",
    "sg:classifiers":[
        {
            "category":"Shopping",
            "type":"Retail Goods"
        },
        {
            "category":"Professional",
            "subcategory":"Research",
            "type":"Services"
        }
    ],
    "sg:phone":"+1 715 723 0093",
    "sg:postcode":"54729",
    "sg:province":"WI",
    "sg:tags":[
        "organization",
        "noncommercial",
        "monument"
    ],
    "wof:name":"Chippewa Monument Company",
    "wof:placetype":"venue"
},
  "geometry": {"coordinates":[-91.457255,44.922715],"type":"Point"}
}