{
  "type": "Feature",
  "properties": {
    "addr:full":"5610 Co Rd Ot Onalaska WI 54650",
    "addr:housenumber":"5610",
    "addr:postcode":"54650",
    "addr:street":"Co Rd",
    "iso:country":"US",
    "sg:address":"5610 Co Rd Ot",
    "sg:city":"Onalaska",
    "sg:classifiers":[
        {
            "category":"Building & Trades",
            "subcategory":"Equipment Rental",
            "type":"Services"
        }
    ],
    "sg:phone":"+1 608 781 7755",
    "sg:postcode":"54650",
    "sg:province":"WI",
    "sg:tags":[
        "yard"
    ],
    "wof:name":"Topps Elite Tent Rentals",
    "wof:placetype":"venue"
},
  "geometry": {"coordinates":[-91.252134,43.923454],"type":"Point"}
}