{
  "type": "Feature",
  "properties": {
    "iso:country":"US",
    "sg:address":"26625 Roosevelt Ln",
    "sg:city":"Waterford",
    "sg:classifiers":[
        {
            "category":"Building & Trades",
            "subcategory":"Plumbing",
            "type":"Services"
        }
    ],
    "sg:phone":"+1 262 895 2722",
    "sg:postcode":"53185",
    "sg:province":"WI",
    "sg:tags":[
        "contractor"
    ],
    "wof:name":"Milwaukee Stove & Furnace",
    "wof:placetype":"venue"
},
  "geometry": {"coordinates":[-88.163405,42.819414],"type":"Point"}
}