{
  "type": "Feature",
  "properties": {
    "iso:country":"US",
    "sg:address":"2330 Pamperin Rd",
    "sg:city":"Green Bay",
    "sg:classifiers":[
        {
            "category":"Manufacturing",
            "subcategory":"Tools & Machinery",
            "type":"Manufacturing & Wholesale Goods"
        }
    ],
    "sg:phone":"+1 920 662 2100",
    "sg:postcode":"54313",
    "sg:province":"WI",
    "sg:tags":[
        "industry",
        "pa",
        "engineering",
        "mfg"
    ],
    "wof:name":"Vision Packaging Systems",
    "wof:placetype":"venue"
},
  "geometry": {"coordinates":[-88.07382800000001,44.58507],"type":"Point"}
}