{
  "type": "Feature",
  "properties": {
    "iso:country":"US",
    "sg:address":"24784 W Sunset Dr",
    "sg:city":"Waukesha",
    "sg:classifiers":[
        {
            "category":"Banks & Credit Unions",
            "subcategory":"Bank",
            "type":"Services"
        }
    ],
    "sg:phone":"+1 262 522 9400",
    "sg:postcode":"53189",
    "sg:province":"WI",
    "sg:tags":[
        "mortgage"
    ],
    "wof:name":"Americas Mortgage Profes",
    "wof:placetype":"venue"
},
  "geometry": {"coordinates":[-88.24090099999999,42.988328],"type":"Point"}
}