{
  "type": "Feature",
  "properties": {
    "iso:country":"US",
    "sg:address":"1403 Superior St",
    "sg:city":"Racine",
    "sg:classifiers":[
        {
            "category":"Bars & Pubs",
            "type":"Food & Drink"
        }
    ],
    "sg:phone":"+1 262 638 0656",
    "sg:postcode":"53402",
    "sg:province":"WI",
    "wof:name":"Winner's Circle",
    "wof:placetype":"venue"
},
  "geometry": {"coordinates":[-87.790376,42.737956],"type":"Point"}
}