{
  "type": "Feature",
  "properties": {
    "iso:country":"US",
    "sg:address":"5602 W Forest Home Ave",
    "sg:city":"Milwaukee",
    "sg:classifiers":[
        {
            "category":"Retail",
            "subcategory":"Repair Shop",
            "type":"Services"
        }
    ],
    "sg:phone":"+1 414 327 4303",
    "sg:postcode":"53220",
    "sg:province":"WI",
    "sg:tags":[
        "equipment",
        "electronic",
        "supply"
    ],
    "wof:name":"City Wide Electronics",
    "wof:placetype":"venue"
},
  "geometry": {"coordinates":[-87.984399,42.979039],"type":"Point"}
}