{
  "type": "Feature",
  "properties": {
    "iso:country":"US",
    "sg:address":"209 Quinton St",
    "sg:city":"Green Bay",
    "sg:classifiers":[
        {
            "category":"Arts & Performance",
            "subcategory":"Theater",
            "type":"Entertainment"
        }
    ],
    "sg:phone":"+1 920 468 9953",
    "sg:postcode":"54302",
    "sg:province":"WI",
    "sg:tags":[
        "group"
    ],
    "wof:name":"On The Wildside Djs",
    "wof:placetype":"venue"
},
  "geometry": {"coordinates":[-87.986361,44.500512],"type":"Point"}
}