{
  "type": "Feature",
  "properties": {
    "addr:full":"611 Belshire Dr Hartland WI 53029",
    "addr:housenumber":"611",
    "addr:postcode":"53029",
    "addr:street":"Belshire Dr",
    "iso:country":"US",
    "sg:address":"611 Belshire Dr",
    "sg:city":"Hartland",
    "sg:classifiers":[
        {
            "category":"Manufacturing",
            "subcategory":"Tools & Machinery",
            "type":"Manufacturing & Wholesale Goods"
        }
    ],
    "sg:phone":"+1 262 367 2115",
    "sg:postcode":"53029",
    "sg:province":"WI",
    "sg:tags":[
        "control"
    ],
    "wof:name":"KRB Systems Design",
    "wof:placetype":"venue"
},
  "geometry": {"coordinates":[-88.334784,43.108686],"type":"Point"}
}