{
  "type": "Feature",
  "properties": {
    "iso:country":"US",
    "sg:address":"1465 Russell St",
    "sg:city":"Green Bay",
    "sg:classifiers":[
        {
            "category":"Real Estate",
            "subcategory":"Surveying",
            "type":"Services"
        }
    ],
    "sg:phone":"+1 920 499 9775",
    "sg:postcode":"54304",
    "sg:province":"WI",
    "wof:name":"Robert Strassburger",
    "wof:placetype":"venue"
},
  "geometry": {"coordinates":[-88.06298200000001,44.512446],"type":"Point"}
}