{
  "type": "Feature",
  "properties": {
    "iso:country":"US",
    "sg:address":"7611 Harwood Ave",
    "sg:city":"Milwaukee",
    "sg:classifiers":[
        {
            "category":"Real Estate",
            "subcategory":"Architect",
            "type":"Services"
        }
    ],
    "sg:phone":"+1 414 777 0428",
    "sg:postcode":"53213",
    "sg:province":"WI",
    "wof:name":"Envision Consultant",
    "wof:placetype":"venue"
},
  "geometry": {"coordinates":[-88.00811,43.049522],"type":"Point"}
}