{
  "type": "Feature",
  "properties": {
    "addr:full":"8440 Shady Rest Rd Rhinelander WI 54501",
    "addr:housenumber":"8440",
    "addr:postcode":"54501",
    "addr:street":"Shady Rest Rd",
    "iso:country":"US",
    "sg:address":"8440 Shady Rest Rd",
    "sg:city":"Rhinelander",
    "sg:classifiers":[
        {
            "category":"Travel",
            "subcategory":"Hotels & Motels",
            "type":"Entertainment"
        }
    ],
    "sg:phone":"+1 715 282 5231",
    "sg:postcode":"54501",
    "sg:province":"WI",
    "sg:tags":[
        "resort"
    ],
    "sg:website":"www.feases.com",
    "wof:name":"Feases Shady Rest Lodge Inc",
    "wof:placetype":"venue"
},
  "geometry": {"coordinates":[-89.62306,45.566306],"type":"Point"}
}