{
  "type": "Feature",
  "properties": {
    "iso:country":"US",
    "sg:address":"222 E Broadway Ave",
    "sg:city":"Grantsburg",
    "sg:classifiers":[
        {
            "category":"Manufacturing",
            "subcategory":"Buildings",
            "type":"Manufacturing & Wholesale Goods"
        }
    ],
    "sg:phone":"+1 715 463 5896",
    "sg:postcode":"54840",
    "sg:province":"WI",
    "sg:tags":[
        "prefabricated",
        "wood",
        "mfg"
    ],
    "wof:name":"Johnson Construction",
    "wof:placetype":"venue"
},
  "geometry": {"coordinates":[-92.679437,45.777591],"type":"Point"}
}