{
  "type": "Feature",
  "properties": {
    "addr:full":"16665 Eldorado Dr Brookfield WI 53005",
    "addr:housenumber":"16665",
    "addr:postcode":"53005",
    "addr:street":"Eldorado Dr",
    "iso:country":"US",
    "sg:address":"16665 Eldorado Dr",
    "sg:city":"Brookfield",
    "sg:classifiers":[
        {
            "category":"Transit Center",
            "subcategory":"Freight",
            "type":"Transportation"
        },
        {
            "category":"Freight",
            "type":"Transportation"
        },
        {
            "category":"Building & Trades",
            "subcategory":"Construction",
            "type":"Services"
        }
    ],
    "sg:phone":"+1 262 781 9279",
    "sg:postcode":"53005",
    "sg:province":"WI",
    "sg:tags":[
        "excavation",
        "trucking",
        "local",
        "trucking-motor",
        "contractor"
    ],
    "wof:name":"I T S Inc",
    "wof:placetype":"venue"
},
  "geometry": {"coordinates":[-88.118439,43.092974],"type":"Point"}
}