{
  "type": "Feature",
  "properties": {
    "iso:country":"US",
    "sg:address":"10437 W Innovation Dr",
    "sg:city":"Milwaukee",
    "sg:classifiers":[
        {
            "category":"Professional",
            "subcategory":"Research",
            "type":"Services"
        }
    ],
    "sg:phone":"+1 414 771 7469",
    "sg:postcode":"53226",
    "sg:province":"WI",
    "sg:tags":[
        "development",
        "laboratory"
    ],
    "wof:name":"Physiogenix Inc",
    "wof:placetype":"venue"
},
  "geometry": {"coordinates":[-88.037644,43.041894],"type":"Point"}
}