{
  "type": "Feature",
  "properties": {
    "iso:country":"US",
    "sg:address":"5310 Desert Rd",
    "sg:city":"Fennimore",
    "sg:classifiers":[
        {
            "category":"Farming",
            "subcategory":"Dairy Farm",
            "type":"Manufacturing & Wholesale Goods"
        }
    ],
    "sg:phone":"+1 608 822 6078",
    "sg:postcode":"53809",
    "sg:province":"WI",
    "wof:name":"Thomas & Alice Shea",
    "wof:placetype":"venue"
},
  "geometry": {"coordinates":[-90.692358,42.955638],"type":"Point"}
}