{
  "type": "Feature",
  "properties": {
    "iso:country":"US",
    "sg:address":"6531 N Sidney Pl",
    "sg:city":"Milwaukee",
    "sg:classifiers":[
        {
            "category":"Shopping",
            "subcategory":"Computers & Home Electronics",
            "type":"Retail Goods"
        }
    ],
    "sg:phone":"+1 414 352 4465",
    "sg:postcode":"53209",
    "sg:province":"WI",
    "wof:name":"Centrak",
    "wof:placetype":"venue"
},
  "geometry": {"coordinates":[-87.948423,43.134777],"type":"Point"}
}