{
  "type": "Feature",
  "properties": {
    "iso:country":"US",
    "sg:address":"1317 N 25th St",
    "sg:city":"Sheboygan",
    "sg:classifiers":[
        {
            "category":"Banks & Credit Unions",
            "subcategory":"Bank",
            "type":"Services"
        }
    ],
    "sg:phone":"+1 920 451 4110",
    "sg:postcode":"53081",
    "sg:province":"WI",
    "wof:name":"Associated Bank",
    "wof:placetype":"venue"
},
  "geometry": {"coordinates":[-87.739546,43.759021],"type":"Point"}
}