{
  "type": "Feature",
  "properties": {
    "iso:country":"US",
    "sg:address":"10406 N Reedsburg Rd",
    "sg:city":"Baraboo",
    "sg:classifiers":[
        {
            "category":"Professional",
            "subcategory":"Computer Services",
            "type":"Services"
        }
    ],
    "sg:phone":"+1 608 356 3571",
    "sg:postcode":"53913",
    "sg:province":"WI",
    "sg:tags":[
        "datum"
    ],
    "wof:name":"Micro Refurb",
    "wof:placetype":"venue"
},
  "geometry": {"coordinates":[-89.80285600000001,43.532754],"type":"Point"}
}