{
  "type": "Feature",
  "properties": {
    "iso:country":"US",
    "sg:address":"1408 Pearl St",
    "sg:city":"Prescott",
    "sg:classifiers":[
        {
            "category":"Professional",
            "type":"Services"
        },
        {
            "category":"Taxi",
            "type":"Transportation"
        },
        {
            "category":"Freight",
            "type":"Transportation"
        }
    ],
    "sg:phone":"+1 715 262 4663",
    "sg:postcode":"54021",
    "sg:province":"WI",
    "sg:tags":[
        "trucking"
    ],
    "wof:name":"Riverfront Transportation",
    "wof:placetype":"venue"
},
  "geometry": {"coordinates":[-92.800191,44.76459],"type":"Point"}
}