{
  "type": "Feature",
  "properties": {
    "iso:country":"US",
    "sg:address":"1501 Jenifer St",
    "sg:city":"Madison",
    "sg:classifiers":[
        {
            "category":"Social Services",
            "subcategory":"Child Care",
            "type":"Services"
        }
    ],
    "sg:phone":"+1 608 251 5432",
    "sg:postcode":"53703",
    "sg:province":"WI",
    "sg:tags":[
        "day"
    ],
    "wof:name":"Red Caboose School Age Program",
    "wof:placetype":"venue"
},
  "geometry": {"coordinates":[-89.357529,43.086766],"type":"Point"}
}