{
  "type": "Feature",
  "properties": {
    "addr:full":"1919 E Calumet St Appleton WI 54915",
    "addr:housenumber":"1919",
    "addr:postcode":"54915",
    "addr:street":"E Calumet St",
    "iso:country":"US",
    "sg:address":"1919 E Calumet St",
    "sg:city":"Appleton",
    "sg:classifiers":[
        {
            "category":"Shopping",
            "subcategory":"Florist",
            "type":"Retail Goods"
        }
    ],
    "sg:phone":"+1 920 734 5091",
    "sg:postcode":"54915",
    "sg:province":"WI",
    "wof:name":"Rose Petals",
    "wof:placetype":"venue"
},
  "geometry": {"coordinates":[-88.378249,44.243957],"type":"Point"}
}