{
  "type": "Feature",
  "properties": {
    "iso:country":"US",
    "sg:address":"306 S Barstow St",
    "sg:city":"Eau Claire",
    "sg:classifiers":[
        {
            "category":"Shopping",
            "subcategory":"Hobbies, Toys, & Games",
            "type":"Retail Goods"
        }
    ],
    "sg:phone":"+1 715 838 8858",
    "sg:postcode":"54701",
    "sg:province":"WI",
    "sg:tags":[
        "model",
        "supply"
    ],
    "sg:website":"www.modeltrainclassics.com",
    "wof:name":"Model Train Classics Plus",
    "wof:placetype":"venue"
},
  "geometry": {"coordinates":[-91.49879900000001,44.810133],"type":"Point"}
}