{
  "type": "Feature",
  "properties": {
    "addr:full":"3939 Ridgevue Rd Ridgeway WI 53582",
    "addr:housenumber":"3939",
    "addr:postcode":"53582",
    "addr:street":"Ridgevue Rd",
    "iso:country":"US",
    "sg:address":"3939 Ridgevue Rd",
    "sg:city":"Ridgeway",
    "sg:classifiers":[
        {
            "category":"Museum",
            "type":"Entertainment"
        }
    ],
    "sg:phone":"+1 608 924 3569",
    "sg:postcode":"53582",
    "sg:province":"WI",
    "sg:tags":[
        "gallery"
    ],
    "wof:name":"Hyde Historical Territory Inc",
    "wof:placetype":"venue"
},
  "geometry": {"coordinates":[-90.03255,43.013899],"type":"Point"}
}