{
  "type": "Feature",
  "properties": {
    "iso:country":"US",
    "sg:address":"5301 S 76th St",
    "sg:city":"Greendale",
    "sg:classifiers":[
        {
            "category":"Organizations",
            "subcategory":"Professional Association",
            "type":"Services"
        }
    ],
    "sg:phone":"+1 414 421 9008",
    "sg:postcode":"53129",
    "sg:province":"WI",
    "sg:website":"www.bowl.com",
    "wof:name":"BOWLING Inc",
    "wof:placetype":"venue"
},
  "geometry": {"coordinates":[-88.00862600000001,42.94684],"type":"Point"}
}