{
  "type": "Feature",
  "properties": {
    "iso:country":"US",
    "sg:address":"450 Main St",
    "sg:city":"Green Valley",
    "sg:classifiers":[
        {
            "category":"Bars & Pubs",
            "type":"Food & Drink"
        }
    ],
    "sg:phone":"+1 715 745 6510",
    "sg:postcode":"54154",
    "sg:province":"WI",
    "wof:name":"Railway Street Bar & Grill",
    "wof:placetype":"venue"
},
  "geometry": {"coordinates":[-88.268413,44.796827],"type":"Point"}
}