{
  "type": "Feature",
  "properties": {
    "addr:full":"404 E Main St Watertown WI 53094",
    "addr:housenumber":"404",
    "addr:postcode":"53094",
    "addr:street":"E Main St",
    "iso:country":"US",
    "sg:address":"404 E Main St",
    "sg:city":"Watertown",
    "sg:classifiers":[
        {
            "category":"Wholesale",
            "subcategory":"Home Furnishings",
            "type":"Manufacturing & Wholesale Goods"
        },
        {
            "category":"Shopping",
            "subcategory":"Clothing, Apparel, & Fashions",
            "type":"Retail Goods"
        }
    ],
    "sg:phone":"+1 920 261 5224",
    "sg:postcode":"53094",
    "sg:province":"WI",
    "sg:tags":[
        "closet",
        "family",
        "accessory"
    ],
    "wof:name":"Mandy's Closet",
    "wof:placetype":"venue"
},
  "geometry": {"coordinates":[-88.721166,43.194037],"type":"Point"}
}