{
  "type": "Feature",
  "properties": {
    "iso:country":"US",
    "sg:address":"8105 Sandy Hook Rd",
    "sg:city":"Brooklyn",
    "sg:classifiers":[
        {
            "category":"Real Estate",
            "subcategory":"Real Estate Operator",
            "type":"Services"
        }
    ],
    "sg:phone":"+1 608 455 6892",
    "sg:postcode":"53521",
    "sg:province":"WI",
    "sg:tags":[
        "property",
        "lessor"
    ],
    "wof:name":"Sugar Brook Berry Inc",
    "wof:placetype":"venue"
},
  "geometry": {"coordinates":[-89.467188,42.791658],"type":"Point"}
}