{
  "type": "Feature",
  "properties": {
    "addr:full":"6014 Range Line Rd Manitowoc WI 54220",
    "addr:housenumber":"6014",
    "addr:postcode":"54220",
    "addr:street":"Range Line Rd",
    "iso:country":"US",
    "sg:address":"6014 Range Line Rd",
    "sg:city":"Manitowoc",
    "sg:classifiers":[
        {
            "category":"Building & Trades",
            "subcategory":"Plumbing",
            "type":"Services"
        }
    ],
    "sg:phone":"+1 920 758 3700",
    "sg:postcode":"54220",
    "sg:province":"WI",
    "sg:tags":[
        "contractor"
    ],
    "wof:name":"Range Line Plumbing Inc",
    "wof:placetype":"venue"
},
  "geometry": {"coordinates":[-87.801658,44.026094],"type":"Point"}
}