{
  "type": "Feature",
  "properties": {
    "iso:country":"US",
    "sg:address":"1120 Radisson St",
    "sg:city":"Green Bay",
    "sg:classifiers":[
        {
            "category":"Restaurant",
            "type":"Food & Drink"
        }
    ],
    "sg:phone":"+1 920 438 8646",
    "sg:postcode":"54302",
    "sg:province":"WI",
    "sg:tags":[
        "shop",
        "coffee"
    ],
    "sg:website":"www.jotogo.com",
    "wof:name":"Jo To Go",
    "wof:placetype":"venue"
},
  "geometry": {"coordinates":[-87.991973,44.524861],"type":"Point"}
}