{
  "type": "Feature",
  "properties": {
    "iso:country":"US",
    "sg:address":"1334 Benjamin Ct",
    "sg:city":"Green Bay",
    "sg:classifiers":[
        {
            "category":"Professional",
            "subcategory":"Business Services",
            "type":"Services"
        }
    ],
    "sg:phone":"+1 920 469 1311",
    "sg:postcode":"54311",
    "sg:province":"WI",
    "wof:name":"Interior Wall Dsgns Faux Fnish",
    "wof:placetype":"venue"
},
  "geometry": {"coordinates":[-87.950019,44.476287],"type":"Point"}
}