{
  "type": "Feature",
  "properties": {
    "iso:country":"US",
    "sg:address":"510 Co Rd D",
    "sg:city":"Cashton",
    "sg:classifiers":[
        {
            "category":"Food & Beverages",
            "subcategory":"Dairy",
            "type":"Retail Goods"
        }
    ],
    "sg:phone":"+1 608 654 5580",
    "sg:postcode":"54619",
    "sg:province":"WI",
    "sg:tags":[
        "cheese"
    ],
    "wof:name":"K & K Cheese LLC",
    "wof:placetype":"venue"
},
  "geometry": {"coordinates":[-90.723067,43.716408],"type":"Point"}
}