{
  "type": "Feature",
  "properties": {
    "addr:full":"2105 Tori Ln Marinette WI 54143",
    "addr:housenumber":"2105",
    "addr:postcode":"54143",
    "addr:street":"Tori Ln",
    "iso:country":"US",
    "sg:address":"2105 Tori Ln",
    "sg:city":"Marinette",
    "sg:classifiers":[
        {
            "category":"Building & Trades",
            "subcategory":"Electrical",
            "type":"Services"
        }
    ],
    "sg:phone":"+1 715 732 4167",
    "sg:postcode":"54143",
    "sg:province":"WI",
    "sg:tags":[
        "electric",
        "contractor"
    ],
    "wof:name":"Pudg Soderberg Electric Inc",
    "wof:placetype":"venue"
},
  "geometry": {"coordinates":[-87.620943,45.081845],"type":"Point"}
}