{
  "type": "Feature",
  "properties": {
    "iso:country":"US",
    "sg:address":"1000 Tesch Ct",
    "sg:city":"Waukesha",
    "sg:classifiers":[
        {
            "category":"Freight",
            "type":"Transportation"
        }
    ],
    "sg:phone":"+1 262 549 6229",
    "sg:postcode":"53186",
    "sg:province":"WI",
    "sg:tags":[
        "cartage",
        "trucking"
    ],
    "wof:name":"Whirl Wind Express Inc",
    "wof:placetype":"venue"
},
  "geometry": {"coordinates":[-88.205135,43.014945],"type":"Point"}
}