{
  "type": "Feature",
  "properties": {
    "addr:full":"2108 Kohler Memorial Dr Sheboygan WI 53081",
    "addr:housenumber":"2108",
    "addr:postcode":"53081",
    "addr:street":"Memorial Dr",
    "iso:country":"US",
    "sg:address":"2108 Kohler Memorial Dr",
    "sg:city":"Sheboygan",
    "sg:classifiers":[
        {
            "category":"Social Services",
            "type":"Services"
        }
    ],
    "sg:phone":"+1 920 458 9401",
    "sg:postcode":"53081",
    "sg:province":"WI",
    "sg:tags":[
        "information",
        "planning",
        "center",
        "family"
    ],
    "wof:name":"Planned Parenthood",
    "wof:placetype":"venue"
},
  "geometry": {"coordinates":[-87.736923,43.756494],"type":"Point"}
}