{
  "type": "Feature",
  "properties": {
    "iso:country":"US",
    "sg:address":"203 W Main St",
    "sg:city":"Rochester",
    "sg:classifiers":[
        {
            "category":"Government",
            "subcategory":"Office",
            "type":"Public Place"
        }
    ],
    "sg:phone":"+1 262 534 2431",
    "sg:postcode":"53167",
    "sg:province":"WI",
    "sg:tags":[
        "village"
    ],
    "wof:name":"Rochester Town Municipal Hall",
    "wof:placetype":"venue"
},
  "geometry": {"coordinates":[-88.225325,42.741193],"type":"Point"}
}