{
  "type": "Feature",
  "properties": {
    "addr:full":"1564 N 116th St Milwaukee WI 53226",
    "addr:housenumber":"1564",
    "addr:postcode":"53226",
    "addr:street":"N 116Th St",
    "iso:country":"US",
    "sg:address":"1564 N 116th St",
    "sg:city":"Milwaukee",
    "sg:classifiers":[
        {
            "category":"Place Of Worship",
            "subcategory":"Monastery",
            "type":"Public Place"
        }
    ],
    "sg:phone":"+1 414 453 1334",
    "sg:postcode":"53226",
    "sg:province":"WI",
    "sg:tags":[
        "convent"
    ],
    "wof:name":"Notre Dame School Sisters of",
    "wof:placetype":"venue"
},
  "geometry": {"coordinates":[-88.057394,43.050536],"type":"Point"}
}