{
  "type": "Feature",
  "properties": {
    "addr:full":"20726 Co Hwy F Bloomer WI 54724",
    "addr:housenumber":"20726",
    "addr:postcode":"54724",
    "addr:street":"Co Hwy F",
    "iso:country":"US",
    "sg:address":"20726 Co Hwy F",
    "sg:city":"Bloomer",
    "sg:classifiers":[
        {
            "category":"Personal",
            "type":"Services"
        }
    ],
    "sg:phone":"+1 715 568 2457",
    "sg:postcode":"54724",
    "sg:province":"WI",
    "sg:tags":[
        "therapist",
        "massage"
    ],
    "wof:name":"MBSE Integrated",
    "wof:placetype":"venue"
},
  "geometry": {"coordinates":[-91.491409,45.138839],"type":"Point"}
}