{
  "type": "Feature",
  "properties": {
    "iso:country":"US",
    "sg:address":"1126 Frisch Rd",
    "sg:city":"Madison",
    "sg:classifiers":[
        {
            "category":"Professional",
            "subcategory":"Business Services",
            "type":"Services"
        },
        {
            "category":"Professional",
            "subcategory":"Management & Consulting",
            "type":"Services"
        }
    ],
    "sg:phone":"+1 608 273 0263",
    "sg:postcode":"53711",
    "sg:province":"WI",
    "sg:tags":[
        "interior",
        "consultant",
        "design",
        "decorator"
    ],
    "wof:name":"Deb Corning Interiors",
    "wof:placetype":"venue"
},
  "geometry": {"coordinates":[-89.49290000000001,43.041464],"type":"Point"}
}