{
  "type": "Feature",
  "properties": {
    "iso:country":"US",
    "sg:address":"211 S Spring St",
    "sg:city":"Beaver Dam",
    "sg:classifiers":[
        {
            "category":"Real Estate",
            "subcategory":"Real Estate Agent",
            "type":"Services"
        }
    ],
    "sg:phone":"+1 920 887 7909",
    "sg:postcode":"53916",
    "sg:province":"WI",
    "wof:name":"Dodge County Board Of Realtors",
    "wof:placetype":"venue"
},
  "geometry": {"coordinates":[-88.836831,43.455115],"type":"Point"}
}