{
  "type": "Feature",
  "properties": {
    "iso:country":"US",
    "sg:address":"5592 590th St",
    "sg:city":"Ellsworth",
    "sg:classifiers":[
        {
            "category":"Farming",
            "subcategory":"Dairy Farm",
            "type":"Manufacturing & Wholesale Goods"
        }
    ],
    "sg:phone":"+1 715 273 3582",
    "sg:postcode":"54011",
    "sg:province":"WI",
    "wof:name":"Don Jakes",
    "wof:placetype":"venue"
},
  "geometry": {"coordinates":[-92.426308,44.744989],"type":"Point"}
}