{
  "type": "Feature",
  "properties": {
    "iso:country":"US",
    "sg:address":"116 W Knapp St",
    "sg:city":"Rice Lake",
    "sg:classifiers":[
        {
            "category":"Autos & Motor Vehicles",
            "subcategory":"Automobile Sales",
            "type":"Retail Goods"
        }
    ],
    "sg:phone":"+1 715 234 6511",
    "sg:postcode":"54868",
    "sg:province":"WI",
    "sg:tags":[
        "car",
        "used",
        "dealer"
    ],
    "wof:name":"J R Auto Sales",
    "wof:placetype":"venue"
},
  "geometry": {"coordinates":[-91.737949,45.50878],"type":"Point"}
}