{
  "type": "Feature",
  "properties": {
    "iso:country":"US",
    "sg:address":"20518 Co Rd G",
    "sg:city":"Dodge",
    "sg:classifiers":[
        {
            "category":"Bars & Pubs",
            "type":"Food & Drink"
        }
    ],
    "sg:phone":"+1 608 539 3269",
    "sg:postcode":"54612",
    "sg:province":"WI",
    "wof:name":"Village Inn Tavern",
    "wof:placetype":"venue"
},
  "geometry": {"coordinates":[-91.521428,44.134502],"type":"Point"}
}