{
  "type": "Feature",
  "properties": {
    "iso:country":"US",
    "sg:address":"3135 Liberty Bell Rd",
    "sg:city":"Green Bay",
    "sg:classifiers":[
        {
            "category":"Autos & Motor Vehicles",
            "subcategory":"Automobile Sales",
            "type":"Retail Goods"
        }
    ],
    "sg:phone":"+1 920 434 6679",
    "sg:postcode":"54313",
    "sg:province":"WI",
    "wof:name":"Neuville Lon J",
    "wof:placetype":"venue"
},
  "geometry": {"coordinates":[-88.102448,44.564365],"type":"Point"}
}