{
  "type": "Feature",
  "properties": {
    "iso:country":"US",
    "sg:address":"1505 W Mequon Rd",
    "sg:city":"Thiensville",
    "sg:classifiers":[
        {
            "category":"Shopping",
            "subcategory":"Gifts & Souvenirs",
            "type":"Retail Goods"
        }
    ],
    "sg:phone":"+1 262 241 9292",
    "sg:postcode":"53092",
    "sg:province":"WI",
    "sg:tags":[
        "item",
        "fashion",
        "accessory"
    ],
    "wof:name":"Accentrics Ltd",
    "wof:placetype":"venue"
},
  "geometry": {"coordinates":[-87.926484,43.221091],"type":"Point"}
}