{
  "type": "Feature",
  "properties": {
    "iso:country":"US",
    "sg:address":"1402 Washington Ave",
    "sg:city":"Racine",
    "sg:classifiers":[
        {
            "category":"Shopping",
            "subcategory":"Used Merchandise",
            "type":"Retail Goods"
        }
    ],
    "sg:phone":"+1 262 632 6520",
    "sg:postcode":"53403",
    "sg:province":"WI",
    "sg:tags":[
        "furniture"
    ],
    "wof:name":"Needful Things Antique & Used",
    "wof:placetype":"venue"
},
  "geometry": {"coordinates":[-87.797626,42.715273],"type":"Point"}
}