{
  "type": "Feature",
  "properties": {
    "iso:country":"US",
    "sg:address":"206 2nd Ave E",
    "sg:city":"Luck",
    "sg:classifiers":[
        {
            "category":"Retail",
            "subcategory":"Funeral Services",
            "type":"Services"
        }
    ],
    "sg:phone":"+1 715 472 2444",
    "sg:postcode":"54853",
    "sg:province":"WI",
    "sg:tags":[
        "director"
    ],
    "wof:name":"Edling-Rowe Funeral Home",
    "wof:placetype":"venue"
},
  "geometry": {"coordinates":[-92.480284,45.574709],"type":"Point"}
}