{
  "type": "Feature",
  "properties": {
    "iso:country":"US",
    "sg:address":"396 E 1st St",
    "sg:city":"Fond Du Lac",
    "sg:classifiers":[
        {
            "category":"Professional",
            "type":"Services"
        }
    ],
    "sg:phone":"+1 920 923 9240",
    "sg:postcode":"54935",
    "sg:province":"WI",
    "wof:name":"Dream Scents",
    "wof:placetype":"venue"
},
  "geometry": {"coordinates":[-88.432525,43.775804],"type":"Point"}
}