{
  "type": "Feature",
  "properties": {
    "iso:country":"US",
    "sg:address":"1439 Utah St",
    "sg:city":"Sturgeon Bay",
    "sg:classifiers":[
        {
            "category":"Banks & Credit Unions",
            "subcategory":"Bank",
            "type":"Services"
        }
    ],
    "sg:phone":"+1 920 746 0537",
    "sg:postcode":"54235",
    "sg:province":"WI",
    "sg:tags":[
        "national",
        "commercial"
    ],
    "wof:name":"Embroidery By Nat",
    "wof:placetype":"venue"
},
  "geometry": {"coordinates":[-87.360615,44.827768],"type":"Point"}
}