{
  "type": "Feature",
  "properties": {
    "iso:country":"US",
    "sg:address":"1306 Deer Lake Park",
    "sg:city":"Saint Croix Falls",
    "sg:classifiers":[
        {
            "category":"Banks & Credit Unions",
            "subcategory":"Financial Services",
            "type":"Services"
        }
    ],
    "sg:phone":"+1 715 483 3066",
    "sg:postcode":"54024",
    "sg:province":"WI",
    "sg:tags":[
        "trust",
        "management"
    ],
    "wof:name":"Blanding Trust",
    "wof:placetype":"venue"
},
  "geometry": {"coordinates":[-92.543795,45.400057],"type":"Point"}
}