{
  "type": "Feature",
  "properties": {
    "iso:country":"US",
    "sg:address":"28759 Crabtree Rd",
    "sg:city":"Cuba City",
    "sg:classifiers":[
        {
            "category":"Organizations",
            "subcategory":"Religious Organization",
            "type":"Services"
        }
    ],
    "sg:phone":"+1 608 348 5232",
    "sg:postcode":"53807",
    "sg:province":"WI",
    "sg:tags":[
        "church"
    ],
    "wof:name":"Church Of Jesus Christ Of Lds",
    "wof:placetype":"venue"
},
  "geometry": {"coordinates":[-90.388362,42.609178],"type":"Point"}
}