{
  "type": "Feature",
  "properties": {
    "iso:country":"US",
    "sg:address":"8757 N Port Washington Rd",
    "sg:city":"Milwaukee",
    "sg:classifiers":[
        {
            "category":"Shopping",
            "subcategory":"Used Merchandise",
            "type":"Retail Goods"
        }
    ],
    "sg:phone":"+1 414 228 0291",
    "sg:postcode":"53217",
    "sg:province":"WI",
    "sg:tags":[
        "clothing"
    ],
    "wof:name":"Garage Clothing Co",
    "wof:placetype":"venue"
},
  "geometry": {"coordinates":[-87.912593,43.173685],"type":"Point"}
}