{
  "type": "Feature",
  "properties": {
    "addr:full":"202 N Henry St Madison WI 53703",
    "addr:housenumber":"202",
    "addr:postcode":"53703",
    "addr:street":"N Henry St",
    "iso:country":"US",
    "sg:address":"202 N Henry St",
    "sg:city":"Madison",
    "sg:classifiers":[
        {
            "category":"Restaurant",
            "type":"Food & Drink"
        }
    ],
    "sg:phone":"+1 608 255 9933",
    "sg:postcode":"53703",
    "sg:province":"WI",
    "sg:website":"www.thewhitehorseinn.com",
    "wof:name":"White Horse Inn",
    "wof:placetype":"venue"
},
  "geometry": {"coordinates":[-89.389968,43.074692],"type":"Point"}
}