{
  "type": "Feature",
  "properties": {
    "iso:country":"US",
    "sg:address":"17395 W Bluemound Rd",
    "sg:city":"Brookfield",
    "sg:classifiers":[
        {
            "category":"Food & Beverages",
            "subcategory":"Bakery",
            "type":"Retail Goods"
        }
    ],
    "sg:phone":"+1 262 784 0778",
    "sg:postcode":"53045",
    "sg:province":"WI",
    "sg:tags":[
        "baker"
    ],
    "wof:name":"Brownberry Thrift Store",
    "wof:placetype":"venue"
},
  "geometry": {"coordinates":[-88.127098,43.036273],"type":"Point"}
}