{
  "type": "Feature",
  "properties": {
    "iso:country":"US",
    "sg:address":"1156 Schauer Ln",
    "sg:city":"Green Bay",
    "sg:classifiers":[
        {
            "category":"Professional",
            "type":"Services"
        }
    ],
    "sg:phone":"+1 920 497 0764",
    "sg:postcode":"54304",
    "sg:province":"WI",
    "wof:name":"Marina Martirosyan",
    "wof:placetype":"venue"
},
  "geometry": {"coordinates":[-88.077081,44.493013],"type":"Point"}
}