{
  "type": "Feature",
  "properties": {
    "addr:full":"929 N Water St Milwaukee WI 53202",
    "addr:housenumber":"929",
    "addr:postcode":"53202",
    "addr:street":"N Water St",
    "iso:country":"US",
    "sg:address":"929 N Water St",
    "sg:city":"Milwaukee",
    "sg:classifiers":[
        {
            "category":"Education",
            "subcategory":"Special Training",
            "type":"Public Place"
        }
    ],
    "sg:phone":"+1 414 272 8540",
    "sg:postcode":"53202",
    "sg:province":"WI",
    "wof:name":"Milwauke Yuth Symphony Orcstra",
    "wof:placetype":"venue"
},
  "geometry": {"coordinates":[-87.910769,43.043022],"type":"Point"}
}