{
  "type": "Feature",
  "properties": {
    "iso:country":"US",
    "sg:address":"2541 8th St S",
    "sg:city":"Wisconsin Rapids",
    "sg:classifiers":[
        {
            "category":"Professional",
            "subcategory":"Business Services",
            "type":"Services"
        }
    ],
    "sg:phone":"+1 715 424 1717",
    "sg:postcode":"54494",
    "sg:province":"WI",
    "wof:name":"Fantasy Dreams",
    "wof:placetype":"venue"
},
  "geometry": {"coordinates":[-89.816862,44.371802],"type":"Point"}
}