{
  "type": "Feature",
  "properties": {
    "iso:country":"US",
    "sg:address":"526 Baird Creek Rd",
    "sg:city":"Green Bay",
    "sg:classifiers":[
        {
            "category":"Personal",
            "subcategory":"Barber",
            "type":"Services"
        }
    ],
    "sg:phone":"+1 920 465 3263",
    "sg:postcode":"54311",
    "sg:province":"WI",
    "sg:tags":[
        "shop"
    ],
    "wof:name":"C C",
    "wof:placetype":"venue"
},
  "geometry": {"coordinates":[-87.945201,44.508032],"type":"Point"}
}