{
  "type": "Feature",
  "properties": {
    "addr:full":"8203 Dumke Rd Portage WI 53901",
    "addr:postcode":"8203;53901",
    "addr:street":"Dumke Rd",
    "iso:country":"US",
    "sg:address":"8203 Dumke Rd",
    "sg:city":"Portage",
    "sg:classifiers":[
        {
            "category":"Manufacturing",
            "subcategory":"Printing",
            "type":"Manufacturing & Wholesale Goods"
        }
    ],
    "sg:phone":"+1 608 742 5652",
    "sg:postcode":"53901",
    "sg:province":"WI",
    "sg:tags":[
        "stamping",
        "supply",
        "scrap",
        "retailer",
        "rubber",
        "book"
    ],
    "wof:name":"Scrapsite",
    "wof:placetype":"venue"
},
  "geometry": {"coordinates":[-89.399981,43.590454],"type":"Point"}
}