{
  "type": "Feature",
  "properties": {
    "iso:country":"US",
    "sg:address":"308 Grant St",
    "sg:city":"Waunakee",
    "sg:classifiers":[
        {
            "category":"Professional",
            "subcategory":"Management & Consulting",
            "type":"Services"
        }
    ],
    "sg:phone":"+1 608 850 5170",
    "sg:postcode":"53597",
    "sg:province":"WI",
    "sg:tags":[
        "consultant",
        "business"
    ],
    "wof:name":"Windward Consulting LLC",
    "wof:placetype":"venue"
},
  "geometry": {"coordinates":[-89.450299,43.190798],"type":"Point"}
}