{
  "type": "Feature",
  "properties": {
    "iso:country":"US",
    "sg:address":"424 W Center Ave",
    "sg:city":"Dorchester",
    "sg:classifiers":[
        {
            "category":"Health Services",
            "subcategory":"Doctor",
            "type":"Services"
        }
    ],
    "sg:phone":"+1 715 654 5911",
    "sg:postcode":"54425",
    "sg:province":"WI",
    "sg:tags":[
        "medical"
    ],
    "wof:name":"M D Gibson DDS",
    "wof:placetype":"venue"
},
  "geometry": {"coordinates":[-90.336122,45.00307],"type":"Point"}
}