{
  "type": "Feature",
  "properties": {
    "iso:country":"US",
    "sg:address":"1370 Fairhaven Blvd",
    "sg:city":"Elm Grove",
    "sg:classifiers":[
        {
            "category":"Professional",
            "subcategory":"Business Services",
            "type":"Services"
        }
    ],
    "sg:phone":"+1 262 782 8729",
    "sg:postcode":"53122",
    "sg:province":"WI",
    "sg:tags":[
        "house",
        "construction"
    ],
    "wof:name":"Kitchens By Designs Inc",
    "wof:placetype":"venue"
},
  "geometry": {"coordinates":[-88.071083,43.0498],"type":"Point"}
}