{
  "type": "Feature",
  "properties": {
    "iso:country":"US",
    "sg:address":"3770 S Pennsylvania Ave",
    "sg:city":"Milwaukee",
    "sg:classifiers":[
        {
            "category":"Wholesale",
            "subcategory":"Machinery & Supplies",
            "type":"Manufacturing & Wholesale Goods"
        }
    ],
    "sg:phone":"+1 414 483 2525",
    "sg:postcode":"53235",
    "sg:province":"WI",
    "sg:tags":[
        "equipment",
        "industrial"
    ],
    "wof:name":"B & H Supply Inc",
    "wof:placetype":"venue"
},
  "geometry": {"coordinates":[-87.879621,42.976132],"type":"Point"}
}