{
  "type": "Feature",
  "properties": {
    "addr:full":"3743 N 42nd St Milwaukee WI 53216",
    "addr:housenumber":"3743",
    "addr:postcode":"53216",
    "addr:street":"N 42Nd St",
    "iso:country":"US",
    "sg:address":"3743 N 42nd St",
    "sg:city":"Milwaukee",
    "sg:classifiers":[
        {
            "category":"Insurance",
            "subcategory":"Insurance Agent",
            "type":"Services"
        }
    ],
    "sg:phone":"+1 414 871 5794",
    "sg:postcode":"53216",
    "sg:province":"WI",
    "wof:name":"George H Rankin Insurance",
    "wof:placetype":"venue"
},
  "geometry": {"coordinates":[-87.965502,43.085526],"type":"Point"}
}