{
  "type": "Feature",
  "properties": {
    "addr:full":"5034 Co Rd F Fond Du Lac WI 54935",
    "addr:housenumber":"5034",
    "addr:postcode":"54935",
    "addr:street":"Co Rd",
    "iso:country":"US",
    "sg:address":"5034 Co Rd F",
    "sg:city":"Fond Du Lac",
    "sg:classifiers":[
        {
            "category":"Freight",
            "type":"Transportation"
        }
    ],
    "sg:phone":"+1 920 921 5513",
    "sg:postcode":"54935",
    "sg:province":"WI",
    "sg:tags":[
        "operator",
        "local",
        "trucking"
    ],
    "wof:name":"S & R Trucking LLC",
    "wof:placetype":"venue"
},
  "geometry": {"coordinates":[-88.404449,43.66007],"type":"Point"}
}