{
  "type": "Feature",
  "properties": {
    "iso:country":"US",
    "sg:address":"116 S Adams St",
    "sg:city":"Green Bay",
    "sg:classifiers":[
        {
            "category":"Bars & Pubs",
            "type":"Food & Drink"
        }
    ],
    "sg:phone":"+1 920 431 1180",
    "sg:postcode":"54301",
    "sg:province":"WI",
    "wof:name":"Hip Cats",
    "wof:placetype":"venue"
},
  "geometry": {"coordinates":[-88.015529,44.512811],"type":"Point"}
}