{
  "type": "Feature",
  "properties": {
    "addr:full":"25 Brodhead St Mazomanie WI 53560",
    "addr:postcode":"53560",
    "addr:street":"25 Brodhead St",
    "iso:country":"US",
    "sg:address":"25 Brodhead St",
    "sg:city":"Mazomanie",
    "sg:classifiers":[
        {
            "category":"Personal",
            "subcategory":"Beauty Salon",
            "type":"Services"
        }
    ],
    "sg:phone":"+1 608 795 2333",
    "sg:postcode":"53560",
    "sg:province":"WI",
    "sg:tags":[
        "shop"
    ],
    "wof:name":"Cutter",
    "wof:placetype":"venue"
},
  "geometry": {"coordinates":[-89.79418200000001,43.17621],"type":"Point"}
}