{
  "type": "Feature",
  "properties": {
    "iso:country":"US",
    "sg:address":"202 E Grand Ave",
    "sg:city":"Wittenberg",
    "sg:classifiers":[
        {
            "category":"Banks & Credit Unions",
            "subcategory":"Bank",
            "type":"Services"
        }
    ],
    "sg:phone":"+1 715 253 2999",
    "sg:postcode":"54499",
    "sg:province":"WI",
    "wof:name":"Banner Bank",
    "wof:placetype":"venue"
},
  "geometry": {"coordinates":[-89.168741,44.826813],"type":"Point"}
}