{
  "type": "Feature",
  "properties": {
    "iso:country":"US",
    "sg:address":"4408 State Hwy 49",
    "sg:city":"Rosholt",
    "sg:classifiers":[
        {
            "category":"Social Services",
            "subcategory":"Child Care",
            "type":"Services"
        }
    ],
    "sg:phone":"+1 715 677 4778",
    "sg:postcode":"54473",
    "sg:province":"WI",
    "sg:tags":[
        "day"
    ],
    "wof:name":"Nanas Daycare",
    "wof:placetype":"venue"
},
  "geometry": {"coordinates":[-89.26473799999999,44.662166],"type":"Point"}
}