{
  "type": "Feature",
  "properties": {
    "iso:country":"US",
    "sg:address":"612 Meade St",
    "sg:city":"Kaukauna",
    "sg:classifiers":[
        {
            "category":"Arts & Performance",
            "subcategory":"Theater",
            "type":"Entertainment"
        }
    ],
    "sg:phone":"+1 920 759 9372",
    "sg:postcode":"54130",
    "sg:province":"WI",
    "sg:tags":[
        "live",
        "music"
    ],
    "wof:name":"Brian's DS Dj's",
    "wof:placetype":"venue"
},
  "geometry": {"coordinates":[-88.271497,44.289449],"type":"Point"}
}