{
  "type": "Feature",
  "properties": {
    "addr:full":"4016 Terminal Dr Mc Farland WI 53558",
    "addr:housenumber":"4016",
    "addr:postcode":"53558",
    "addr:street":"Terminal Dr",
    "iso:country":"US",
    "sg:address":"4016 Terminal Dr",
    "sg:city":"Mc Farland",
    "sg:classifiers":[
        {
            "category":"Local Transit",
            "type":"Transportation"
        }
    ],
    "sg:phone":"+1 608 838 9644",
    "sg:postcode":"53558",
    "sg:province":"WI",
    "sg:tags":[
        "limousine"
    ],
    "wof:name":"Elegance In Motion",
    "wof:placetype":"venue"
},
  "geometry": {"coordinates":[-89.302178,43.040009],"type":"Point"}
}