{
  "type": "Feature",
  "properties": {
    "iso:country":"US",
    "sg:address":"6401 Odana Rd",
    "sg:city":"Madison",
    "sg:classifiers":[
        {
            "category":"Real Estate",
            "subcategory":"Real Estate Agent",
            "type":"Services"
        }
    ],
    "sg:phone":"+1 608 770 2650",
    "sg:postcode":"53719",
    "sg:province":"WI",
    "wof:name":"Menards Real Estate",
    "wof:placetype":"venue"
},
  "geometry": {"coordinates":[-89.490184,43.054911],"type":"Point"}
}