{
  "type": "Feature",
  "properties": {
    "iso:country":"US",
    "sg:address":"908 E Main St",
    "sg:city":"Winneconne",
    "sg:classifiers":[
        {
            "category":"Insurance",
            "subcategory":"Insurance Agent",
            "type":"Services"
        }
    ],
    "sg:phone":"+1 920 582 4880",
    "sg:postcode":"54986",
    "sg:province":"WI",
    "wof:name":"John Tillema Agency",
    "wof:placetype":"venue"
},
  "geometry": {"coordinates":[-88.694219,44.112481],"type":"Point"}
}