{
  "type": "Feature",
  "properties": {
    "iso:country":"US",
    "sg:address":"1616 S Main St",
    "sg:city":"West Bend",
    "sg:classifiers":[
        {
            "category":"Manufacturing",
            "subcategory":"Tools & Machinery",
            "type":"Manufacturing & Wholesale Goods"
        }
    ],
    "sg:phone":"+1 262 306 7328",
    "sg:postcode":"53095",
    "sg:province":"WI",
    "sg:tags":[
        "terminal",
        "computer",
        "mfg"
    ],
    "wof:name":"Mpc West Bend",
    "wof:placetype":"venue"
},
  "geometry": {"coordinates":[-88.181152,43.401119],"type":"Point"}
}