{
  "type": "Feature",
  "properties": {
    "iso:country":"US",
    "sg:address":"3919 Co Hwy H",
    "sg:city":"Fredonia",
    "sg:classifiers":[
        {
            "category":"Retail",
            "subcategory":"Veterinary Services",
            "type":"Services"
        }
    ],
    "sg:phone":"+1 262 692 2439",
    "sg:postcode":"53021",
    "sg:province":"WI",
    "wof:name":"Fredonia Veterinary Clinic",
    "wof:placetype":"venue"
},
  "geometry": {"coordinates":[-87.98129900000001,43.469589],"type":"Point"}
}