{
  "type": "Feature",
  "properties": {
    "addr:full":"1945 Dordona Dr Neenah WI 54956",
    "addr:housenumber":"1945",
    "addr:postcode":"54956",
    "addr:street":"Dordona Dr",
    "iso:country":"US",
    "sg:address":"1945 Dordona Dr",
    "sg:city":"Neenah",
    "sg:classifiers":[
        {
            "category":"Manufacturing",
            "subcategory":"Metals",
            "type":"Manufacturing & Wholesale Goods"
        }
    ],
    "sg:phone":"+1 920 727 4531",
    "sg:postcode":"54956",
    "sg:province":"WI",
    "sg:tags":[
        "tool",
        "mfg"
    ],
    "wof:name":"Snap-On Incorporated",
    "wof:placetype":"venue"
},
  "geometry": {"coordinates":[-88.48916199999999,44.227074],"type":"Point"}
}