{
  "type": "Feature",
  "properties": {
    "iso:country":"US",
    "sg:address":"4905 Knox Ln",
    "sg:city":"Madison",
    "sg:classifiers":[
        {
            "category":"Social Services",
            "subcategory":"Child Care",
            "type":"Services"
        }
    ],
    "sg:phone":"+1 608 274 4493",
    "sg:postcode":"53711",
    "sg:province":"WI",
    "sg:tags":[
        "day"
    ],
    "wof:name":"Cookie Crumbs Day Care",
    "wof:placetype":"venue"
},
  "geometry": {"coordinates":[-89.463855,43.035505],"type":"Point"}
}