{
  "type": "Feature",
  "properties": {
    "addr:full":"167 N Arch Ave New Richmond WI 54017",
    "addr:housenumber":"167",
    "addr:postcode":"54017",
    "addr:street":"N Arch Ave",
    "iso:country":"US",
    "sg:address":"167 N Arch Ave",
    "sg:city":"New Richmond",
    "sg:classifiers":[
        {
            "category":"Personal",
            "type":"Services"
        }
    ],
    "sg:phone":"+1 715 246 6777",
    "sg:postcode":"54017",
    "sg:province":"WI",
    "sg:tags":[
        "therapist",
        "massage"
    ],
    "wof:name":"Comfort Massage",
    "wof:placetype":"venue"
},
  "geometry": {"coordinates":[-92.536027,45.12443],"type":"Point"}
}