{
  "type": "Feature",
  "properties": {
    "addr:full":"601 Cummings Rd Wautoma WI 54982",
    "addr:housenumber":"601",
    "addr:postcode":"54982",
    "addr:street":"Cummings Rd",
    "iso:country":"US",
    "sg:address":"601 Cummings Rd",
    "sg:city":"Wautoma",
    "sg:classifiers":[
        {
            "category":"Professional",
            "subcategory":"Lawyer & Legal Services",
            "type":"Services"
        }
    ],
    "sg:phone":"+1 920 787 3396",
    "sg:postcode":"54982",
    "sg:province":"WI",
    "sg:tags":[
        "attorney"
    ],
    "wof:name":"Dutcher Law Office",
    "wof:placetype":"venue"
},
  "geometry": {"coordinates":[-89.298226,44.074712],"type":"Point"}
}