{
  "type": "Feature",
  "properties": {
    "iso:country":"US",
    "sg:address":"428 Walton Rd",
    "sg:city":"Plymouth",
    "sg:classifiers":[
        {
            "category":"Personal",
            "subcategory":"Beauty Salon",
            "type":"Services"
        }
    ],
    "sg:phone":"+1 920 893 8655",
    "sg:postcode":"53098",
    "sg:province":"WI",
    "sg:website":"www.wi.costcutters.com",
    "wof:name":"Cost Cutters Family Hair Care",
    "wof:placetype":"venue"
},
  "geometry": {"coordinates":[-88.797088,43.200606],"type":"Point"}
}