{
  "type": "Feature",
  "properties": {
    "addr:full":"5839 San-Dell Way Racine WI 53402",
    "addr:housenumber":"5839",
    "addr:postcode":"53402",
    "addr:street":"San-Dell Way",
    "iso:country":"US",
    "sg:address":"5839 San-Dell Way",
    "sg:city":"Racine",
    "sg:classifiers":[
        {
            "category":"Real Estate",
            "subcategory":"Real Estate Agent",
            "type":"Services"
        }
    ],
    "sg:phone":"+1 262 752 0555",
    "sg:postcode":"53402",
    "sg:province":"WI",
    "sg:tags":[
        "management"
    ],
    "wof:name":"MNR Enterprise Inc",
    "wof:placetype":"venue"
},
  "geometry": {"coordinates":[-87.806997,42.794928],"type":"Point"}
}