{
  "type": "Feature",
  "properties": {
    "iso:country":"US",
    "sg:address":"375 N Hickory St",
    "sg:city":"Fond Du Lac",
    "sg:classifiers":[
        {
            "category":"Retail",
            "subcategory":"Auto Repair",
            "type":"Services"
        }
    ],
    "sg:phone":"+1 920 923 6551",
    "sg:postcode":"54935",
    "sg:province":"WI",
    "sg:tags":[
        "automotive",
        "towing"
    ],
    "wof:name":"Whealons Towing & Service",
    "wof:placetype":"venue"
},
  "geometry": {"coordinates":[-88.462769,43.786998],"type":"Point"}
}