{
  "type": "Feature",
  "properties": {
    "iso:country":"US",
    "sg:address":"7211 W Greenfield Ave",
    "sg:city":"Milwaukee",
    "sg:classifiers":[
        {
            "category":"Bars & Pubs",
            "type":"Food & Drink"
        },
        {
            "category":"Bars & Pubs",
            "subcategory":"Lounge",
            "type":"Food & Drink"
        }
    ],
    "sg:phone":"+1 414 257 9490",
    "sg:postcode":"53214",
    "sg:province":"WI",
    "sg:tags":[
        "tavern",
        "cocktail"
    ],
    "wof:name":"88 Keys Piano Martini Lounge",
    "wof:placetype":"venue"
},
  "geometry": {"coordinates":[-88.002554,43.016689],"type":"Point"}
}