{
  "type": "Feature",
  "properties": {
    "addr:full":"15375 W Bluemound Rd Brookfield WI 53005",
    "addr:housenumber":"15375",
    "addr:postcode":"53005",
    "addr:street":"W Bluemound Rd",
    "iso:country":"US",
    "sg:address":"15375 W Bluemound Rd",
    "sg:city":"Brookfield",
    "sg:classifiers":[
        {
            "category":"Restaurant",
            "type":"Food & Drink"
        }
    ],
    "sg:menulink":"http://www.allmenus.com/wi/brookfield/63443-chipotle/menu/",
    "sg:phone":"+1 262 796 0463",
    "sg:postcode":"53005",
    "sg:province":"WI",
    "sg:tags":[
        "american",
        "mexican",
        "southwestern"
    ],
    "wof:name":"Chipotle",
    "wof:placetype":"venue"
},
  "geometry": {"coordinates":[-88.103796,43.03576],"type":"Point"}
}