{
  "type": "Feature",
  "properties": {
    "iso:country":"US",
    "sg:address":"2445 S Afton Rd",
    "sg:city":"Beloit",
    "sg:classifiers":[
        {
            "category":"Government",
            "subcategory":"Fire Station",
            "type":"Public Place"
        }
    ],
    "sg:phone":"+1 608 364 2997",
    "sg:postcode":"53511",
    "sg:province":"IL",
    "sg:tags":[
        "protection"
    ],
    "wof:name":"Town of Beloit Fire Dept",
    "wof:placetype":"venue"
},
  "geometry": {"coordinates":[-89.0517,42.539277],"type":"Point"}
}