{
  "type": "Feature",
  "properties": {
    "iso:country":"US",
    "sg:address":"281 S Main St",
    "sg:city":"Fond Du Lac",
    "sg:classifiers":[
        {
            "category":"Autos & Motor Vehicles",
            "subcategory":"Fuel & Gas Station",
            "type":"Retail Goods"
        }
    ],
    "sg:phone":"+1 920 922 1687",
    "sg:postcode":"54935",
    "sg:province":"WI",
    "sg:tags":[
        "oil"
    ],
    "wof:name":"Metro Quick Mart",
    "wof:placetype":"venue"
},
  "geometry": {"coordinates":[-88.447121,43.770354],"type":"Point"}
}