{
  "type": "Feature",
  "properties": {
    "iso:country":"US",
    "sg:address":"725 N 8th St",
    "sg:city":"Black River Fls",
    "sg:classifiers":[
        {
            "category":"Organizations",
            "subcategory":"Non-profit Organization",
            "type":"Services"
        },
        {
            "category":"Social Services",
            "subcategory":"Child Care",
            "type":"Services"
        }
    ],
    "sg:phone":"+1 715 284 2238",
    "sg:postcode":"54615",
    "sg:province":"WI",
    "sg:tags":[
        "day"
    ],
    "wof:name":"Black River Child Care Center",
    "wof:placetype":"venue"
},
  "geometry": {"coordinates":[-90.856937,44.302774],"type":"Point"}
}