{
  "type": "Feature",
  "properties": {
    "iso:country":"US",
    "sg:address":"2585 S 33rd St",
    "sg:city":"Milwaukee",
    "sg:classifiers":[
        {
            "category":"Manufacturing",
            "subcategory":"Metals",
            "type":"Manufacturing & Wholesale Goods"
        }
    ],
    "sg:phone":"+1 414 383 0043",
    "sg:postcode":"53215",
    "sg:province":"WI",
    "sg:tags":[
        "sheet",
        "metalwork",
        "installation",
        "provides",
        "mfg"
    ],
    "wof:name":"Old Sheet Metal Shop Inc",
    "wof:placetype":"venue"
},
  "geometry": {"coordinates":[-87.955653,42.997968],"type":"Point"}
}