{
  "type": "Feature",
  "properties": {
    "iso:country":"US",
    "sg:address":"9436 Coon Creek Rd",
    "sg:city":"Browntown",
    "sg:classifiers":[
        {
            "category":"Farming",
            "subcategory":"Dairy Farm",
            "type":"Manufacturing & Wholesale Goods"
        }
    ],
    "sg:phone":"+1 608 966 1574",
    "sg:postcode":"53522",
    "sg:province":"WI",
    "wof:name":"Jim Notter",
    "wof:placetype":"venue"
},
  "geometry": {"coordinates":[-89.833107,42.618059],"type":"Point"}
}