{
  "type": "Feature",
  "properties": {
    "iso:country":"US",
    "sg:address":"6246 N Port Washington Rd",
    "sg:city":"Milwaukee",
    "sg:classifiers":[
        {
            "category":"Shopping",
            "subcategory":"Florist",
            "type":"Retail Goods"
        }
    ],
    "sg:phone":"+1 414 962 9822",
    "sg:postcode":"53217",
    "sg:province":"WI",
    "wof:name":"Bay Floral",
    "wof:placetype":"venue"
},
  "geometry": {"coordinates":[-87.912975,43.131616],"type":"Point"}
}