{
  "type": "Feature",
  "properties": {
    "iso:country":"US",
    "sg:address":"3351 Sandy Hook Rd",
    "sg:city":"Hazel Green",
    "sg:classifiers":[
        {
            "category":"Professional",
            "subcategory":"Business Services",
            "type":"Services"
        }
    ],
    "sg:phone":"+1 608 748 4292",
    "sg:postcode":"53811",
    "sg:province":"WI",
    "wof:name":"Lins Originals",
    "wof:placetype":"venue"
},
  "geometry": {"coordinates":[-90.586687,42.544438],"type":"Point"}
}