{
  "type": "Feature",
  "properties": {
    "iso:country":"US",
    "sg:address":"105 E Main St",
    "sg:city":"Gillett",
    "sg:classifiers":[
        {
            "category":"Bars & Pubs",
            "type":"Food & Drink"
        }
    ],
    "sg:phone":"+1 920 855 2177",
    "sg:postcode":"54124",
    "sg:province":"WI",
    "wof:name":"Legion Arcade",
    "wof:placetype":"venue"
},
  "geometry": {"coordinates":[-88.30549600000001,44.890538],"type":"Point"}
}