{
  "type": "Feature",
  "properties": {
    "iso:country":"US",
    "sg:address":"1849 Hobbs Dr",
    "sg:city":"Delavan",
    "sg:classifiers":[
        {
            "category":"Home & Garden",
            "subcategory":"Building Materials",
            "type":"Retail Goods"
        }
    ],
    "sg:phone":"+1 262 728 0110",
    "sg:postcode":"53115",
    "sg:province":"WI",
    "sg:tags":[
        "lumber"
    ],
    "wof:name":"Stock Building Supply Inc",
    "wof:placetype":"venue"
},
  "geometry": {"coordinates":[-88.6095,42.639553],"type":"Point"}
}