{
  "type": "Feature",
  "properties": {
    "iso:country":"US",
    "sg:address":"3595 Joanne St",
    "sg:city":"Appleton",
    "sg:classifiers":[
        {
            "category":"Autos & Motor Vehicles",
            "subcategory":"Motorcycle Sales",
            "type":"Retail Goods"
        }
    ],
    "sg:phone":"+1 920 730 8190",
    "sg:postcode":"54913",
    "sg:province":"WI",
    "sg:tags":[
        "scooter"
    ],
    "wof:name":"ITR Enterprise",
    "wof:placetype":"venue"
},
  "geometry": {"coordinates":[-88.367769,44.384311],"type":"Point"}
}