{
  "type": "Feature",
  "properties": {
    "iso:country":"US",
    "sg:address":"3139 S 84th St",
    "sg:city":"Milwaukee",
    "sg:classifiers":[
        {
            "category":"Building & Trades",
            "subcategory":"Construction",
            "type":"Services"
        }
    ],
    "sg:phone":"+1 414 321 9389",
    "sg:postcode":"53227",
    "sg:province":"WI",
    "sg:tags":[
        "repairing",
        "housing",
        "remodeling",
        "contractor"
    ],
    "wof:name":"J Daniel Remodeling Co LLC",
    "wof:placetype":"venue"
},
  "geometry": {"coordinates":[-88.01765399999999,42.98713],"type":"Point"}
}