{
  "type": "Feature",
  "properties": {
    "iso:country":"US",
    "sg:address":"117 E 5th St",
    "sg:city":"Washburn",
    "sg:classifiers":[
        {
            "category":"Manufacturing",
            "subcategory":"Lumber",
            "type":"Manufacturing & Wholesale Goods"
        }
    ],
    "sg:phone":"+1 715 373 6114",
    "sg:postcode":"54891",
    "sg:province":"WI",
    "sg:tags":[
        "government"
    ],
    "wof:name":"Bayfield County Forestry Dept",
    "wof:placetype":"venue"
},
  "geometry": {"coordinates":[-90.891639,46.676963],"type":"Point"}
}