{
  "type": "Feature",
  "properties": {
    "iso:country":"US",
    "sg:address":"131 S Main St",
    "sg:city":"Shawano",
    "sg:classifiers":[
        {
            "category":"Shopping",
            "subcategory":"Gifts & Souvenirs",
            "type":"Retail Goods"
        }
    ],
    "sg:phone":"+1 715 524 3333",
    "sg:postcode":"54166",
    "sg:province":"WI",
    "sg:tags":[
        "shop"
    ],
    "wof:name":"Spirit Of The Northwoods",
    "wof:placetype":"venue"
},
  "geometry": {"coordinates":[-88.60942900000001,44.781457],"type":"Point"}
}