{
  "type": "Feature",
  "properties": {
    "iso:country":"US",
    "sg:address":"529 S Midvale Blvd",
    "sg:city":"Madison",
    "sg:classifiers":[
        {
            "category":"Cinema",
            "subcategory":"Movie Rental",
            "type":"Entertainment"
        }
    ],
    "sg:phone":"+1 608 238 9993",
    "sg:postcode":"53711",
    "sg:province":"WI",
    "sg:tags":[
        "video",
        "tape"
    ],
    "wof:name":"Movie Gallery",
    "wof:placetype":"venue"
},
  "geometry": {"coordinates":[-89.45104000000001,43.054287],"type":"Point"}
}