{
  "type": "Feature",
  "properties": {
    "addr:full":"308 W Stout St Rice Lake WI 54868",
    "addr:housenumber":"308",
    "addr:postcode":"54868",
    "addr:street":"W Stout St",
    "iso:country":"US",
    "sg:address":"308 W Stout St",
    "sg:city":"Rice Lake",
    "sg:classifiers":[
        {
            "category":"Professional",
            "subcategory":"Business Services",
            "type":"Services"
        }
    ],
    "sg:phone":"+1 715 234 4677",
    "sg:postcode":"54868",
    "sg:province":"WI",
    "wof:name":"Classic Enterprises",
    "wof:placetype":"venue"
},
  "geometry": {"coordinates":[-91.74131199999999,45.507827],"type":"Point"}
}