{
  "type": "Feature",
  "properties": {
    "addr:full":"308 S Sprague Ave Prairie Farm WI 54762",
    "addr:housenumber":"308",
    "addr:postcode":"54762",
    "addr:street":"S Sprague Ave Prairie",
    "iso:country":"US",
    "sg:address":"308 S Sprague Ave",
    "sg:city":"Prairie Farm",
    "sg:classifiers":[
        {
            "category":"Wholesale",
            "subcategory":"Meat",
            "type":"Manufacturing & Wholesale Goods"
        }
    ],
    "sg:phone":"+1 715 455 1431",
    "sg:postcode":"54762",
    "sg:province":"WI",
    "sg:tags":[
        "product"
    ],
    "wof:name":"B & R Sausage",
    "wof:placetype":"venue"
},
  "geometry": {"coordinates":[-91.980448,45.236828],"type":"Point"}
}