{
  "type": "Feature",
  "properties": {
    "iso:country":"US",
    "sg:address":"8478 Stetzer Rd",
    "sg:city":"Mindoro",
    "sg:phone":"+1 608 857 3196",
    "sg:postcode":"54644",
    "sg:province":"WI",
    "sg:tags":[
        "farm",
        "corn"
    ],
    "wof:name":"Donald Craig",
    "wof:placetype":"venue"
},
  "geometry": {"coordinates":[-90.98515399999999,44.021907],"type":"Point"}
}