{
  "type": "Feature",
  "properties": {
    "addr:full":"3251 Huebscher Rd Abrams WI 54101",
    "addr:housenumber":"3251",
    "addr:postcode":"54101",
    "addr:street":"Huebscher Rd",
    "iso:country":"US",
    "sg:address":"3251 Huebscher Rd",
    "sg:city":"Abrams",
    "sg:classifiers":[
        {
            "category":"Airline",
            "type":"Transportation"
        }
    ],
    "sg:phone":"+1 920 826 7745",
    "sg:postcode":"54101",
    "sg:province":"WI",
    "sg:tags":[
        "helicopter",
        "maintenance"
    ],
    "wof:name":"Chemair Helicopters Inc",
    "wof:placetype":"venue"
},
  "geometry": {"coordinates":[-87.977818,44.790473],"type":"Point"}
}