{
  "type": "Feature",
  "properties": {
    "iso:country":"US",
    "sg:address":"410 12th St",
    "sg:city":"Racine",
    "sg:classifiers":[
        {
            "category":"Professional",
            "subcategory":"Business Services",
            "type":"Services"
        }
    ],
    "sg:phone":"+1 262 632 5224",
    "sg:postcode":"53403",
    "sg:province":"WI",
    "wof:name":"Tract Enterprises Inc",
    "wof:placetype":"venue"
},
  "geometry": {"coordinates":[-87.78585200000001,42.718592],"type":"Point"}
}