{
  "type": "Feature",
  "properties": {
    "addr:full":"203 S Main St Potosi WI 53820",
    "addr:housenumber":"203",
    "addr:postcode":"53820",
    "addr:street":"S Main St",
    "iso:country":"US",
    "sg:address":"203 S Main St",
    "sg:city":"Potosi",
    "sg:classifiers":[
        {
            "category":"Professional",
            "subcategory":"Business Services",
            "type":"Services"
        },
        {
            "category":"Building & Trades",
            "subcategory":"Construction",
            "type":"Services"
        }
    ],
    "sg:phone":"+1 608 763 2968",
    "sg:postcode":"53820",
    "sg:province":"WI",
    "sg:tags":[
        "hanging",
        "painter",
        "contractor"
    ],
    "wof:name":"Droessler Interior Services",
    "wof:placetype":"venue"
},
  "geometry": {"coordinates":[-90.727227,42.671644],"type":"Point"}
}