{
  "type": "Feature",
  "properties": {
    "addr:full":"4505 State Hwy 55 White Lake WI 54491",
    "addr:housenumber":"4505",
    "addr:postcode":"54491",
    "addr:street":"State Hwy 55",
    "iso:country":"US",
    "sg:address":"4505 State Hwy 55",
    "sg:city":"White Lake",
    "sg:classifiers":[
        {
            "category":"Autos & Motor Vehicles",
            "subcategory":"Fuel & Gas Station",
            "type":"Retail Goods"
        }
    ],
    "sg:phone":"+1 715 882 8901",
    "sg:postcode":"54491",
    "sg:province":"WI",
    "sg:tags":[
        "station",
        "gasoline"
    ],
    "wof:name":"Mobil",
    "wof:placetype":"venue"
},
  "geometry": {"coordinates":[-88.736704,45.193538],"type":"Point"}
}