{
  "type": "Feature",
  "properties": {
    "addr:full":"1421 Fremont Rd Granton WI 54436",
    "addr:housenumber":"1421",
    "addr:postcode":"54436",
    "addr:street":"Fremont Rd",
    "iso:country":"US",
    "sg:address":"1421 Fremont Rd",
    "sg:city":"Granton",
    "sg:classifiers":[
        {
            "category":"Farming",
            "subcategory":"Dairy Farm",
            "type":"Manufacturing & Wholesale Goods"
        }
    ],
    "sg:phone":"+1 715 683 2429",
    "sg:postcode":"54436",
    "sg:province":"WI",
    "wof:name":"Schmitz Farms LLC",
    "wof:placetype":"venue"
},
  "geometry": {"coordinates":[-90.379696,44.597566],"type":"Point"}
}