{
  "type": "Feature",
  "properties": {
    "iso:country":"US",
    "sg:address":"530 W Chickadee Ln",
    "sg:city":"Green Bay",
    "sg:classifiers":[
        {
            "category":"Wholesale",
            "subcategory":"Machinery & Supplies",
            "type":"Manufacturing & Wholesale Goods"
        }
    ],
    "sg:phone":"+1 920 497 9435",
    "sg:postcode":"54313",
    "sg:province":"WI",
    "wof:name":"Landscape Equipment Suppliers",
    "wof:placetype":"venue"
},
  "geometry": {"coordinates":[-88.11209700000001,44.530746],"type":"Point"}
}