{
  "type": "Feature",
  "properties": {
    "iso:country":"US",
    "sg:address":"6141 Co Rd A",
    "sg:city":"Webster",
    "sg:classifiers":[
        {
            "category":"Manufacturing",
            "subcategory":"Wood Products",
            "type":"Manufacturing & Wholesale Goods"
        }
    ],
    "sg:phone":"+1 715 866 7312",
    "sg:postcode":"54893",
    "sg:province":"WI",
    "sg:tags":[
        "mfg"
    ],
    "wof:name":"Orange Enterprise Inc",
    "wof:placetype":"venue"
},
  "geometry": {"coordinates":[-92.293081,45.901937],"type":"Point"}
}