{
  "type": "Feature",
  "properties": {
    "iso:country":"US",
    "sg:address":"4869 Fairgrounds Rd",
    "sg:city":"Spooner",
    "sg:classifiers":[
        {
            "category":"Retail",
            "subcategory":"Auto Repair",
            "type":"Services"
        }
    ],
    "sg:phone":"+1 715 635 9699",
    "sg:postcode":"54801",
    "sg:province":"WI",
    "sg:tags":[
        "repairing",
        "automobile"
    ],
    "wof:name":"Jock's Auto & Truck Repair",
    "wof:placetype":"venue"
},
  "geometry": {"coordinates":[-91.900842,45.812142],"type":"Point"}
}