{
  "type": "Feature",
  "properties": {
    "addr:full":"1234 State St Green Bay WI 54304",
    "addr:housenumber":"1234",
    "addr:postcode":"54304",
    "addr:street":"State St",
    "iso:country":"US",
    "sg:address":"1234 State St",
    "sg:city":"Green Bay",
    "sg:classifiers":[
        {
            "category":"Bars & Pubs",
            "type":"Food & Drink"
        }
    ],
    "sg:phone":"+1 920 432 6701",
    "sg:postcode":"54304",
    "sg:province":"WI",
    "sg:tags":[
        "drinking"
    ],
    "wof:name":"Thirsty's",
    "wof:placetype":"venue"
},
  "geometry": {"coordinates":[-88.029428,44.502711],"type":"Point"}
}