{
  "type": "Feature",
  "properties": {
    "iso:country":"US",
    "sg:address":"8139 Franklin Rd",
    "sg:city":"Plymouth",
    "sg:classifiers":[
        {
            "category":"Government",
            "subcategory":"Office",
            "type":"Public Place"
        }
    ],
    "sg:phone":"+1 920 565 2934",
    "sg:postcode":"53073",
    "sg:province":"WI",
    "sg:tags":[
        "city"
    ],
    "wof:name":"Hermann Town Hall",
    "wof:placetype":"venue"
},
  "geometry": {"coordinates":[-87.904314,43.834449],"type":"Point"}
}