{
  "type": "Feature",
  "properties": {
    "iso:country":"US",
    "sg:address":"1700 Tower Dr",
    "sg:city":"Kaukauna",
    "sg:classifiers":[
        {
            "category":"Freight",
            "type":"Transportation"
        }
    ],
    "sg:phone":"+1 920 766 9510",
    "sg:postcode":"54130",
    "sg:province":"WI",
    "sg:tags":[
        "distance",
        "long",
        "trucking"
    ],
    "wof:name":"Central Freight Lines",
    "wof:placetype":"venue"
},
  "geometry": {"coordinates":[-88.258521,44.30268],"type":"Point"}
}