{
  "type": "Feature",
  "properties": {
    "iso:country":"US",
    "sg:address":"1658 Morrow St",
    "sg:city":"Green Bay",
    "sg:classifiers":[
        {
            "category":"Retail",
            "subcategory":"Repair Shop",
            "type":"Services"
        }
    ],
    "sg:phone":"+1 920 497 8324",
    "sg:postcode":"54302",
    "sg:province":"WI",
    "sg:tags":[
        "electronics",
        "consumer"
    ],
    "sg:website":"www.techdiff.com",
    "wof:name":"Technical Difficulties",
    "wof:placetype":"venue"
},
  "geometry": {"coordinates":[-87.981641,44.508344],"type":"Point"}
}