{
  "type": "Feature",
  "properties": {
    "iso:country":"US",
    "sg:address":"1409 Hammond Ave",
    "sg:city":"Superior",
    "sg:classifiers":[
        {
            "category":"Government",
            "subcategory":"Police Station",
            "type":"Public Place"
        }
    ],
    "sg:phone":"+1 715 394 0435",
    "sg:postcode":"54880",
    "sg:province":"WI",
    "sg:tags":[
        "department"
    ],
    "wof:name":"Superior Police-Traffic Bureau",
    "wof:placetype":"venue"
},
  "geometry": {"coordinates":[-92.097972,46.72077],"type":"Point"}
}