{
  "type": "Feature",
  "properties": {
    "iso:country":"US",
    "sg:address":"305 Reid St",
    "sg:city":"De Pere",
    "sg:classifiers":[
        {
            "category":"Health Services",
            "subcategory":"Medical Lab",
            "type":"Services"
        }
    ],
    "sg:phone":"+1 920 347 3498",
    "sg:postcode":"54115",
    "sg:province":"WI",
    "sg:tags":[
        "laboratory",
        "dental"
    ],
    "wof:name":"Siebrick Dental Studio",
    "wof:placetype":"venue"
},
  "geometry": {"coordinates":[-88.069687,44.446324],"type":"Point"}
}