{
  "type": "Feature",
  "properties": {
    "iso:country":"US",
    "sg:address":"11350 1st Ct",
    "sg:city":"Pleasant Prairie",
    "sg:classifiers":[
        {
            "category":"Professional",
            "subcategory":"Management & Consulting",
            "type":"Services"
        }
    ],
    "sg:phone":"+1 262 694 0444",
    "sg:postcode":"53158",
    "sg:province":"WI",
    "sg:tags":[
        "sanitary"
    ],
    "wof:name":"Pro Grasscaping",
    "wof:placetype":"venue"
},
  "geometry": {"coordinates":[-87.811197,42.512005],"type":"Point"}
}