{
  "type": "Feature",
  "properties": {
    "iso:country":"US",
    "sg:address":"6302 N Brockway Rd",
    "sg:city":"Black River Fls",
    "sg:classifiers":[
        {
            "category":"Travel",
            "subcategory":"Campground",
            "type":"Entertainment"
        }
    ],
    "sg:phone":"+1 715 284 3171",
    "sg:postcode":"54615",
    "sg:province":"WI",
    "wof:name":"Wazee County Park",
    "wof:placetype":"venue"
},
  "geometry": {"coordinates":[-90.741486,44.293567],"type":"Point"}
}