{
  "type": "Feature",
  "properties": {
    "iso:country":"US",
    "sg:address":"2269 Old Peshtigo Rd",
    "sg:city":"Marinette",
    "sg:classifiers":[
        {
            "category":"Professional",
            "type":"Services"
        }
    ],
    "sg:phone":"+1 715 735 5509",
    "sg:postcode":"54143",
    "sg:province":"WI",
    "wof:name":"Charlene Staudenmaie",
    "wof:placetype":"venue"
},
  "geometry": {"coordinates":[-87.71021500000001,45.058074],"type":"Point"}
}