{
  "type": "Feature",
  "properties": {
    "addr:full":"6339 W Beloit Rd Milwaukee WI 53219",
    "addr:housenumber":"6339",
    "addr:postcode":"53219",
    "addr:street":"W Beloit Rd",
    "iso:country":"US",
    "sg:address":"6339 W Beloit Rd",
    "sg:city":"Milwaukee",
    "sg:classifiers":[
        {
            "category":"Home & Garden",
            "subcategory":"Building Materials",
            "type":"Retail Goods"
        },
        {
            "category":"Building & Trades",
            "subcategory":"Construction",
            "type":"Services"
        },
        {
            "category":"Manufacturing",
            "subcategory":"Building Materials",
            "type":"Manufacturing & Wholesale Goods"
        }
    ],
    "sg:phone":"+1 414 541 0444",
    "sg:postcode":"53219",
    "sg:province":"WI",
    "sg:tags":[
        "roofing",
        "installation",
        "windows-repair",
        "siding",
        "improvement",
        "window",
        "doors",
        "frames",
        "contractor",
        "accessory",
        "replacement"
    ],
    "sg:website":"http://www.allaboutwindowsandsiding.net",
    "wof:name":"All About Windows And Siding",
    "wof:placetype":"venue"
},
  "geometry": {"coordinates":[-87.991545,43.00616],"type":"Point"}
}