{
  "type": "Feature",
  "properties": {
    "iso:country":"US",
    "sg:address":"3701 S Iowa Ave",
    "sg:city":"Milwaukee",
    "sg:classifiers":[
        {
            "category":"Bars & Pubs",
            "type":"Food & Drink"
        }
    ],
    "sg:phone":"+1 414 481 4150",
    "sg:postcode":"53235",
    "sg:province":"WI",
    "sg:tags":[
        "bar"
    ],
    "wof:name":"Kaz's Pub",
    "wof:placetype":"venue"
},
  "geometry": {"coordinates":[-87.884694,42.977534],"type":"Point"}
}