{
  "type": "Feature",
  "properties": {
    "iso:country":"US",
    "sg:address":"225 Stoney Brook Rd",
    "sg:city":"Appleton",
    "sg:classifiers":[
        {
            "category":"Bars & Pubs",
            "type":"Food & Drink"
        }
    ],
    "sg:phone":"+1 920 830 2510",
    "sg:postcode":"54915",
    "sg:province":"WI",
    "sg:website":"www.tcfsportsbar.com",
    "wof:name":"Checkered Flag Sportsbar",
    "wof:placetype":"venue"
},
  "geometry": {"coordinates":[-88.35197700000001,44.252849],"type":"Point"}
}