{
  "type": "Feature",
  "properties": {
    "addr:full":"2808 Krueger Rd Lake Geneva WI 53147",
    "addr:housenumber":"2808",
    "addr:postcode":"53147",
    "addr:street":"Krueger Rd",
    "iso:country":"US",
    "sg:address":"2808 Krueger Rd",
    "sg:city":"Lake Geneva",
    "sg:classifiers":[
        {
            "category":"Wholesale",
            "subcategory":"Non-durable Goods",
            "type":"Manufacturing & Wholesale Goods"
        }
    ],
    "sg:phone":"+1 262 248 2440",
    "sg:postcode":"53147",
    "sg:province":"WI",
    "wof:name":"Mc Distributors LLC",
    "wof:placetype":"venue"
},
  "geometry": {"coordinates":[-88.438559,42.620588],"type":"Point"}
}