{
  "type": "Feature",
  "properties": {
    "addr:full":"2000 Stonepine Bay Hudson WI 54016",
    "addr:housenumber":"2000",
    "addr:postcode":"54016",
    "addr:street":"Stonepine Bay",
    "iso:country":"US",
    "sg:address":"2000 Stonepine Bay",
    "sg:city":"Hudson",
    "sg:classifiers":[
        {
            "category":"Professional",
            "subcategory":"Computer Services",
            "type":"Services"
        }
    ],
    "sg:phone":"+1 715 381 6565",
    "sg:postcode":"54016",
    "sg:province":"WI",
    "sg:tags":[
        "related"
    ],
    "wof:name":"J&B Consulting",
    "wof:placetype":"venue"
},
  "geometry": {"coordinates":[-92.73311,44.971373],"type":"Point"}
}