{
  "type": "Feature",
  "properties": {
    "iso:country":"US",
    "sg:address":"8401 57th Ave",
    "sg:city":"Kenosha",
    "sg:classifiers":[
        {
            "category":"Professional",
            "subcategory":"Employment Agencies",
            "type":"Services"
        }
    ],
    "sg:phone":"+1 262 694 2952",
    "sg:postcode":"53142",
    "sg:province":"IL",
    "sg:tags":[
        "opportunity"
    ],
    "wof:name":"Professional Manpower Svc",
    "wof:placetype":"venue"
},
  "geometry": {"coordinates":[-87.875336,42.553617],"type":"Point"}
}