{
  "type": "Feature",
  "properties": {
    "iso:country":"US",
    "sg:address":"1101 Northland Terrace Ln",
    "sg:city":"Marinette",
    "sg:classifiers":[
        {
            "category":"Health Services",
            "subcategory":"Nursing And Care Facility",
            "type":"Services"
        }
    ],
    "sg:phone":"+1 715 735 7447",
    "sg:postcode":"54143",
    "sg:province":"WI",
    "wof:name":"Edgewood Manor Inc",
    "wof:placetype":"venue"
},
  "geometry": {"coordinates":[-87.621398,45.074923],"type":"Point"}
}