{
  "type": "Feature",
  "properties": {
    "iso:country":"US",
    "sg:address":"1710 Harding Ave",
    "sg:city":"Eau Claire",
    "sg:classifiers":[
        {
            "category":"Personal",
            "subcategory":"Tattoo Parlor",
            "type":"Services"
        }
    ],
    "sg:phone":"+1 715 833 9522",
    "sg:postcode":"54701",
    "sg:province":"WI",
    "sg:tags":[
        "tattooing"
    ],
    "wof:name":"Bodyparts Tattoo & Piercing",
    "wof:placetype":"venue"
},
  "geometry": {"coordinates":[-91.47704,44.800262],"type":"Point"}
}