{
  "type": "Feature",
  "properties": {
    "iso:country":"US",
    "sg:address":"1560 Margaret Lake Rd",
    "sg:city":"Mercer",
    "sg:classifiers":[
        {
            "category":"Travel",
            "subcategory":"Hotels & Motels",
            "type":"Entertainment"
        }
    ],
    "sg:phone":"+1 715 476 2143",
    "sg:postcode":"54547",
    "sg:province":"WI",
    "wof:name":"Horns Margret Lake Resort",
    "wof:placetype":"venue"
},
  "geometry": {"coordinates":[-89.99782500000001,46.191158],"type":"Point"}
}