{
  "type": "Feature",
  "properties": {
    "iso:country":"US",
    "sg:address":"806 N Edge Trl",
    "sg:city":"Verona",
    "sg:classifiers":[
        {
            "category":"Professional",
            "subcategory":"Business Services",
            "type":"Services"
        },
        {
            "category":"Wholesale",
            "subcategory":"Groceries",
            "type":"Manufacturing & Wholesale Goods"
        }
    ],
    "sg:phone":"+1 608 848 8778",
    "sg:postcode":"53593",
    "sg:province":"WI",
    "sg:tags":[
        "food",
        "product"
    ],
    "wof:name":"Family Fresch Foods",
    "wof:placetype":"venue"
},
  "geometry": {"coordinates":[-89.532279,42.999315],"type":"Point"}
}