{
  "type": "Feature",
  "properties": {
    "addr:full":"2917 Latham Dr Madison WI 53713",
    "addr:housenumber":"2917",
    "addr:postcode":"53713",
    "addr:street":"Latham Dr",
    "iso:country":"US",
    "sg:address":"2917 Latham Dr",
    "sg:city":"Madison",
    "sg:classifiers":[
        {
            "category":"Manufacturing",
            "subcategory":"Furniture",
            "type":"Manufacturing & Wholesale Goods"
        }
    ],
    "sg:phone":"+1 608 271 2777",
    "sg:postcode":"53713",
    "sg:province":"WI",
    "sg:tags":[
        "mfg",
        "household",
        "sp",
        "metal",
        "bench",
        "wood",
        "furn"
    ],
    "wof:name":"Gerber Manufacturing Ltd",
    "wof:placetype":"venue"
},
  "geometry": {"coordinates":[-89.402749,43.030768],"type":"Point"}
}