{
  "type": "Feature",
  "properties": {
    "iso:country":"US",
    "sg:address":"717 US Hwy 45",
    "sg:city":"Pelican Lake",
    "sg:classifiers":[
        {
            "category":"Travel",
            "subcategory":"Hotels & Motels",
            "type":"Entertainment"
        }
    ],
    "sg:phone":"+1 715 487 5280",
    "sg:postcode":"54463",
    "sg:province":"WI",
    "wof:name":"Trail-Inn Tavern & Motel",
    "wof:placetype":"venue"
},
  "geometry": {"coordinates":[-89.167959,45.497669],"type":"Point"}
}