{
  "type": "Feature",
  "properties": {
    "addr:full":"117 Wisconsin Ave Denmark WI 54208",
    "addr:housenumber":"117",
    "addr:postcode":"54208",
    "addr:street":"Wisconsin Ave",
    "iso:country":"US",
    "sg:address":"117 Wisconsin Ave",
    "sg:city":"Denmark",
    "sg:classifiers":[
        {
            "category":"Bars & Pubs",
            "type":"Food & Drink"
        }
    ],
    "sg:phone":"+1 920 863 6168",
    "sg:postcode":"54208",
    "sg:province":"WI",
    "wof:name":"Planet Magic",
    "wof:placetype":"venue"
},
  "geometry": {"coordinates":[-87.825531,44.346901],"type":"Point"}
}