{
  "type": "Feature",
  "properties": {
    "iso:country":"US",
    "sg:address":"198 Westbridge Ave",
    "sg:city":"Burlington",
    "sg:classifiers":[
        {
            "category":"Education",
            "subcategory":"Preschool",
            "type":"Public Place"
        },
        {
            "category":"Education",
            "subcategory":"School",
            "type":"Public Place"
        }
    ],
    "sg:phone":"+1 262 763 8229",
    "sg:postcode":"53105",
    "sg:province":"WI",
    "sg:tags":[
        "high",
        "middle",
        "elementary"
    ],
    "sg:website":"www.stjohnsburlington.org",
    "wof:name":"St John's Lutheran Church & School",
    "wof:placetype":"venue"
},
  "geometry": {"coordinates":[-88.271947,42.678129],"type":"Point"}
}