{
  "type": "Feature",
  "properties": {
    "iso:country":"US",
    "sg:address":"610 N Badger Ave",
    "sg:city":"Appleton",
    "sg:classifiers":[
        {
            "category":"Banks & Credit Unions",
            "subcategory":"Bank",
            "type":"Services"
        }
    ],
    "sg:phone":"+1 920 968 1300",
    "sg:postcode":"54914",
    "sg:province":"WI",
    "wof:name":"Community First Credit Union",
    "wof:placetype":"venue"
},
  "geometry": {"coordinates":[-88.428133,44.267204],"type":"Point"}
}