{
  "type": "Feature",
  "properties": {
    "iso:country":"US",
    "sg:address":"5201 Washington Ave",
    "sg:city":"Racine",
    "sg:classifiers":[
        {
            "category":"Banks & Credit Unions",
            "subcategory":"Bank",
            "type":"Services"
        }
    ],
    "sg:phone":"+1 262 634 2410",
    "sg:postcode":"53406",
    "sg:province":"WI",
    "wof:name":"Guaranty Bank",
    "wof:placetype":"venue"
},
  "geometry": {"coordinates":[-87.842973,42.71873],"type":"Point"}
}