{
  "type": "Feature",
  "properties": {
    "iso:country":"US",
    "sg:address":"3636 Jeffers Rd",
    "sg:city":"Eau Claire",
    "sg:classifiers":[
        {
            "category":"Utilities",
            "subcategory":"Refuse",
            "type":"Services"
        }
    ],
    "sg:phone":"+1 715 834 3508",
    "sg:postcode":"54703",
    "sg:province":"WI",
    "sg:tags":[
        "system"
    ],
    "wof:name":"Olson Disposal & Recycling",
    "wof:placetype":"venue"
},
  "geometry": {"coordinates":[-91.52459399999999,44.83575],"type":"Point"}
}