{
  "type": "Feature",
  "properties": {
    "iso:country":"US",
    "sg:address":"3425 N Summit Ave",
    "sg:city":"Milwaukee",
    "sg:classifiers":[
        {
            "category":"Health Services",
            "subcategory":"Doctor",
            "type":"Services"
        }
    ],
    "sg:phone":"+1 414 967 7054",
    "sg:postcode":"53211",
    "sg:province":"WI",
    "sg:tags":[
        "technician",
        "x"
    ],
    "wof:name":"Locher Charles J Md SC",
    "wof:placetype":"venue"
},
  "geometry": {"coordinates":[-87.87554299999999,43.081315],"type":"Point"}
}