{
  "type": "Feature",
  "properties": {
    "iso:country":"US",
    "sg:address":"555 State St",
    "sg:city":"Madison",
    "sg:classifiers":[
        {
            "category":"Professional",
            "subcategory":"Printing & Photocopies",
            "type":"Services"
        }
    ],
    "sg:phone":"+1 608 251 3401",
    "sg:postcode":"53703",
    "sg:province":"WI",
    "sg:tags":[
        "duplicating",
        "copying"
    ],
    "wof:name":"Campus Copy Services",
    "wof:placetype":"venue"
},
  "geometry": {"coordinates":[-89.395758,43.074791],"type":"Point"}
}