{
  "type": "Feature",
  "properties": {
    "addr:full":"5225 Co Rd K Hartford WI 53027",
    "addr:housenumber":"5225",
    "addr:postcode":"53027",
    "addr:street":"Co Rd",
    "iso:country":"US",
    "sg:address":"5225 Co Rd K",
    "sg:city":"Hartford",
    "sg:classifiers":[
        {
            "category":"Manufacturing",
            "subcategory":"Signs",
            "type":"Manufacturing & Wholesale Goods"
        }
    ],
    "sg:phone":"+1 262 644 1439",
    "sg:postcode":"53027",
    "sg:province":"WI",
    "sg:tags":[
        "specialty",
        "mfg"
    ],
    "wof:name":"Tezzies Sign Shop",
    "wof:placetype":"venue"
},
  "geometry": {"coordinates":[-88.294106,43.369399],"type":"Point"}
}