{
  "type": "Feature",
  "properties": {
    "iso:country":"US",
    "sg:address":"5860 Advance Rd",
    "sg:city":"Monroe",
    "sg:classifiers":[
        {
            "category":"Health Services",
            "subcategory":"Nursing And Care Facility",
            "type":"Services"
        }
    ],
    "sg:phone":"+1 608 325 4686",
    "sg:postcode":"53566",
    "sg:province":"WI",
    "sg:tags":[
        "skilled"
    ],
    "wof:name":"Country Care Adult Family Home",
    "wof:placetype":"venue"
},
  "geometry": {"coordinates":[-89.649614,42.53383],"type":"Point"}
}