{
  "type": "Feature",
  "properties": {
    "iso:country":"US",
    "sg:address":"6009 US Hwy 51",
    "sg:city":"Mc Farland",
    "sg:classifiers":[
        {
            "category":"Restaurant",
            "type":"Food & Drink"
        }
    ],
    "sg:phone":"+1 608 838 4048",
    "sg:postcode":"53558",
    "sg:province":"WI",
    "sg:tags":[
        "caterer"
    ],
    "wof:name":"Cousins Subs",
    "wof:placetype":"venue"
},
  "geometry": {"coordinates":[-89.303262,43.012228],"type":"Point"}
}