{
  "type": "Feature",
  "properties": {
    "iso:country":"US",
    "sg:address":"923 Eisenhower Ave",
    "sg:city":"Janesville",
    "sg:classifiers":[
        {
            "category":"Building & Trades",
            "subcategory":"Construction",
            "type":"Services"
        }
    ],
    "sg:phone":"+1 608 758 4258",
    "sg:postcode":"53545",
    "sg:province":"WI",
    "sg:tags":[
        "contractor"
    ],
    "wof:name":"Dutcher Construction",
    "wof:placetype":"venue"
},
  "geometry": {"coordinates":[-89.01894,42.69697],"type":"Point"}
}