{
  "type": "Feature",
  "properties": {
    "iso:country":"US",
    "sg:address":"4101 Schofield Ave",
    "sg:city":"Schofield",
    "sg:classifiers":[
        {
            "category":"Autos & Motor Vehicles",
            "subcategory":"Fuel & Gas Station",
            "type":"Retail Goods"
        }
    ],
    "sg:phone":"+1 715 355 4544",
    "sg:postcode":"54476",
    "sg:province":"WI",
    "sg:tags":[
        "oil"
    ],
    "wof:name":"IMR Mobil Mart",
    "wof:placetype":"venue"
},
  "geometry": {"coordinates":[-89.57150300000001,44.904978],"type":"Point"}
}