{
  "type": "Feature",
  "properties": {
    "iso:country":"US",
    "sg:address":"750 Tropicana Blvd",
    "sg:city":"Chippewa Falls",
    "sg:classifiers":[
        {
            "category":"Education",
            "subcategory":"School",
            "type":"Public Place"
        }
    ],
    "sg:phone":"+1 715 726 2400",
    "sg:postcode":"54729",
    "sg:province":"WI",
    "wof:name":"Chippewa Falls Middle School",
    "wof:placetype":"venue"
},
  "geometry": {"coordinates":[-91.421953,44.938685],"type":"Point"}
}