{
  "type": "Feature",
  "properties": {
    "iso:country":"US",
    "sg:address":"10 Waywood Cir",
    "sg:city":"Madison",
    "sg:classifiers":[
        {
            "category":"Restaurant",
            "type":"Food & Drink"
        }
    ],
    "sg:phone":"+1 608 243 9103",
    "sg:postcode":"53704",
    "sg:province":"WI",
    "wof:name":"Worldwide Ventures",
    "wof:placetype":"venue"
},
  "geometry": {"coordinates":[-89.297105,43.119354],"type":"Point"}
}