{
  "type": "Feature",
  "properties": {
    "iso:country":"US",
    "sg:address":"919 N River Rd",
    "sg:city":"West Bend",
    "sg:classifiers":[
        {
            "category":"Professional",
            "subcategory":"Management & Consulting",
            "type":"Services"
        }
    ],
    "sg:phone":"+1 262 306 7977",
    "sg:postcode":"53090",
    "sg:province":"WI",
    "sg:tags":[
        "business"
    ],
    "wof:name":"Compunch Ltd",
    "wof:placetype":"venue"
},
  "geometry": {"coordinates":[-88.161377,43.431549],"type":"Point"}
}