{
  "type": "Feature",
  "properties": {
    "iso:country":"US",
    "sg:address":"703 26th St",
    "sg:city":"Chetek",
    "sg:classifiers":[
        {
            "category":"Wholesale",
            "subcategory":"Office Equipment",
            "type":"Manufacturing & Wholesale Goods"
        }
    ],
    "sg:phone":"+1 715 924 3000",
    "sg:postcode":"54728",
    "sg:province":"WI",
    "wof:name":"Unibind of Wisconsin",
    "wof:placetype":"venue"
},
  "geometry": {"coordinates":[-91.621427,45.307884],"type":"Point"}
}