{
  "type": "Feature",
  "properties": {
    "iso:country":"US",
    "sg:address":"580 S Elizabeth St",
    "sg:city":"Whitewater",
    "sg:classifiers":[
        {
            "category":"Health Services",
            "subcategory":"Doctor",
            "type":"Services"
        }
    ],
    "sg:phone":"+1 262 473 4900",
    "sg:postcode":"53190",
    "sg:province":"WI",
    "sg:tags":[
        "physician",
        "surgeon"
    ],
    "wof:name":"Mercy Fitness & Whitewater Ctr",
    "wof:placetype":"venue"
},
  "geometry": {"coordinates":[-88.75317,42.827745],"type":"Point"}
}