{
  "type": "Feature",
  "properties": {
    "addr:full":"1648 County Rd N Stoughton WI 53589",
    "addr:housenumber":"1648",
    "addr:postcode":"53589",
    "addr:street":"County Rd N",
    "iso:country":"US",
    "sg:address":"1648 County Rd N",
    "sg:city":"Stoughton",
    "sg:classifiers":[
        {
            "category":"Travel",
            "subcategory":"Hotels & Motels",
            "type":"Entertainment"
        },
        {
            "category":"Recreation",
            "subcategory":"Campground",
            "type":"Entertainment"
        }
    ],
    "sg:phone":"+1 608 873 6601",
    "sg:postcode":"53589",
    "sg:province":"WI",
    "sg:tags":[
        "lodging",
        "recreational",
        "park",
        "vehicle"
    ],
    "wof:name":"Viking Village Campground",
    "wof:placetype":"venue"
},
  "geometry": {"coordinates":[-89.201176,42.93982],"type":"Point"}
}