{
  "type": "Feature",
  "properties": {
    "iso:country":"US",
    "sg:address":"1200 Christopher Ct",
    "sg:city":"Oconomowoc",
    "sg:classifiers":[
        {
            "category":"Professional",
            "subcategory":"Management & Consulting",
            "type":"Services"
        }
    ],
    "sg:phone":"+1 262 567 8858",
    "sg:postcode":"53066",
    "sg:province":"WI",
    "sg:tags":[
        "public",
        "relations"
    ],
    "wof:name":"Image One Promotions",
    "wof:placetype":"venue"
},
  "geometry": {"coordinates":[-88.486661,43.125478],"type":"Point"}
}