{
  "type": "Feature",
  "properties": {
    "iso:country":"US",
    "sg:address":"299 Linnerud Dr",
    "sg:city":"Sun Prairie",
    "sg:classifiers":[
        {
            "category":"Retail",
            "subcategory":"Repair Shop",
            "type":"Services"
        }
    ],
    "sg:phone":"+1 608 837 7434",
    "sg:postcode":"53590",
    "sg:province":"WI",
    "wof:name":"Bills Shrpning Svc Small Engi",
    "wof:placetype":"venue"
},
  "geometry": {"coordinates":[-89.213961,43.179404],"type":"Point"}
}