{
  "type": "Feature",
  "properties": {
    "iso:country":"US",
    "sg:address":"1134 Winston Dr",
    "sg:city":"Madison",
    "sg:classifiers":[
        {
            "category":"Professional",
            "subcategory":"Management & Consulting",
            "type":"Services"
        }
    ],
    "sg:phone":"+1 608 274 4482",
    "sg:postcode":"53711",
    "sg:province":"WI",
    "wof:name":"Russell Consulting Inc",
    "wof:placetype":"venue"
},
  "geometry": {"coordinates":[-89.491714,43.041108],"type":"Point"}
}