{
  "type": "Feature",
  "properties": {
    "iso:country":"US",
    "sg:address":"3394 Bonnie Ln",
    "sg:city":"Slinger",
    "sg:classifiers":[
        {
            "category":"Shopping",
            "subcategory":"Bicycles & Sporting Goods",
            "type":"Retail Goods"
        }
    ],
    "sg:phone":"+1 262 644 6328",
    "sg:postcode":"53086",
    "sg:province":"WI",
    "sg:tags":[
        "repair"
    ],
    "wof:name":"Powderhorn Taxidermy",
    "wof:placetype":"venue"
},
  "geometry": {"coordinates":[-88.290317,43.310466],"type":"Point"}
}