{
  "type": "Feature",
  "properties": {
    "iso:country":"US",
    "sg:address":"2396 State Hwy 13",
    "sg:city":"Adams",
    "sg:classifiers":[
        {
            "category":"Building & Trades",
            "subcategory":"Construction",
            "type":"Services"
        }
    ],
    "sg:phone":"+1 608 339 9109",
    "sg:postcode":"53910",
    "sg:province":"WI",
    "sg:tags":[
        "steel",
        "erectors"
    ],
    "wof:name":"Rhinehart Metal Buildings Inc",
    "wof:placetype":"venue"
},
  "geometry": {"coordinates":[-89.817242,43.909541],"type":"Point"}
}