{
  "type": "Feature",
  "properties": {
    "iso:country":"US",
    "sg:address":"1102 S Center Ave",
    "sg:city":"Merrill",
    "sg:classifiers":[
        {
            "category":"Social Services",
            "subcategory":"Adult Care",
            "type":"Services"
        }
    ],
    "sg:phone":"+1 715 536 3399",
    "sg:postcode":"54452",
    "sg:province":"WI",
    "sg:tags":[
        "home",
        "residential"
    ],
    "wof:name":"Woodland Court Elder Svc Unit",
    "wof:placetype":"venue"
},
  "geometry": {"coordinates":[-89.68966500000001,45.167668],"type":"Point"}
}