{
  "type": "Feature",
  "properties": {
    "addr:full":"506 East Ave Hartford WI 53027",
    "addr:housenumber":"506",
    "addr:postcode":"53027",
    "addr:street":"East Ave",
    "iso:country":"US",
    "sg:address":"506 East Ave",
    "sg:city":"Hartford",
    "sg:classifiers":[
        {
            "category":"Shopping",
            "subcategory":"Hobbies, Toys, & Games",
            "type":"Retail Goods"
        }
    ],
    "sg:phone":"+1 262 670 6923",
    "sg:postcode":"53027",
    "sg:province":"WI",
    "sg:tags":[
        "craft"
    ],
    "wof:name":"Impressive Reflections",
    "wof:placetype":"venue"
},
  "geometry": {"coordinates":[-88.369766,43.313868],"type":"Point"}
}