{
  "type": "Feature",
  "properties": {
    "iso:country":"US",
    "sg:address":"1797 Rowe Rd",
    "sg:city":"Sheboygan",
    "sg:classifiers":[
        {
            "category":"Real Estate",
            "subcategory":"Real Estate Operator",
            "type":"Services"
        }
    ],
    "sg:phone":"+1 920 565 2382",
    "sg:postcode":"53083",
    "sg:province":"WI",
    "sg:tags":[
        "property",
        "lessor"
    ],
    "wof:name":"Thomas Frane",
    "wof:placetype":"venue"
},
  "geometry": {"coordinates":[-87.785473,43.833885],"type":"Point"}
}