{
  "type": "Feature",
  "properties": {
    "iso:country":"US",
    "sg:address":"6996 Co Rd K",
    "sg:city":"Wausau",
    "sg:classifiers":[
        {
            "category":"Building & Trades",
            "subcategory":"Construction",
            "type":"Services"
        }
    ],
    "sg:phone":"+1 715 675 6558",
    "sg:postcode":"54452",
    "sg:province":"WI",
    "sg:tags":[
        "water",
        "well",
        "drilling"
    ],
    "wof:name":"Gordie & Debra Mathwich",
    "wof:placetype":"venue"
},
  "geometry": {"coordinates":[-89.692178,45.032236],"type":"Point"}
}