{
  "type": "Feature",
  "properties": {
    "addr:full":"705 N Hamilton St St Croix Falls WI 54024",
    "addr:housenumber":"705",
    "addr:postcode":"54024",
    "addr:street":"N Hamilton St St",
    "iso:country":"US",
    "sg:address":"705 N Hamilton St",
    "sg:city":"St Croix Falls",
    "sg:classifiers":[
        {
            "category":"Real Estate",
            "subcategory":"Real Estate Agent",
            "type":"Services"
        }
    ],
    "sg:phone":"+1 715 483 3211",
    "sg:postcode":"54024",
    "sg:province":"WI",
    "wof:name":"Westlunde Real Estate",
    "wof:placetype":"venue"
},
  "geometry": {"coordinates":[-92.646197,45.419312],"type":"Point"}
}