{
  "type": "Feature",
  "properties": {
    "iso:country":"US",
    "sg:address":"1080 E Hiawatha Dr",
    "sg:city":"Wisconsin Dells",
    "sg:classifiers":[
        {
            "category":"Travel",
            "subcategory":"Hotels & Motels",
            "type":"Entertainment"
        }
    ],
    "sg:phone":"+1 608 253 4411",
    "sg:postcode":"53965",
    "sg:province":"WI",
    "wof:name":"Sandrift Resort",
    "wof:placetype":"venue"
},
  "geometry": {"coordinates":[-89.78346000000001,43.606805],"type":"Point"}
}