{
  "type": "Feature",
  "properties": {
    "iso:country":"US",
    "sg:address":"5944 Quaker Hill Rd",
    "sg:city":"Racine",
    "sg:classifiers":[
        {
            "category":"Manufacturing",
            "subcategory":"Paper Products",
            "type":"Manufacturing & Wholesale Goods"
        }
    ],
    "sg:phone":"+1 262 886 4424",
    "sg:postcode":"53406",
    "sg:province":"WI",
    "sg:tags":[
        "box",
        "fiber",
        "mfg"
    ],
    "wof:name":"Inland Paperboard and Packg",
    "wof:placetype":"venue"
},
  "geometry": {"coordinates":[-87.852175,42.743117],"type":"Point"}
}