{
  "type": "Feature",
  "properties": {
    "iso:country":"US",
    "sg:address":"5828 Pleasant Hill Rd",
    "sg:city":"Auburndale",
    "sg:classifiers":[
        {
            "category":"Farming",
            "subcategory":"Livestock Farm",
            "type":"Manufacturing & Wholesale Goods"
        }
    ],
    "sg:phone":"+1 715 652 3547",
    "sg:postcode":"54412",
    "sg:province":"WI",
    "sg:tags":[
        "beef",
        "feedlot",
        "cattle"
    ],
    "wof:name":"Scott Breu",
    "wof:placetype":"venue"
},
  "geometry": {"coordinates":[-90.01639,44.67752],"type":"Point"}
}