{
  "type": "Feature",
  "properties": {
    "iso:country":"US",
    "sg:address":"214 Main St",
    "sg:city":"Darlington",
    "sg:classifiers":[
        {
            "category":"Home & Garden",
            "subcategory":"Carpets & Floor Coverings",
            "type":"Retail Goods"
        }
    ],
    "sg:phone":"+1 608 776 2446",
    "sg:postcode":"53530",
    "sg:province":"WI",
    "sg:tags":[
        "dealer",
        "laying",
        "rug",
        "contractor"
    ],
    "wof:name":"Black's Floor Covering",
    "wof:placetype":"venue"
},
  "geometry": {"coordinates":[-90.117862,42.678548],"type":"Point"}
}