{
  "type": "Feature",
  "properties": {
    "iso:country":"US",
    "sg:address":"206 Cambridge Ave",
    "sg:city":"Waukesha",
    "sg:classifiers":[
        {
            "category":"Personal",
            "type":"Services"
        }
    ],
    "sg:phone":"+1 262 549 3269",
    "sg:postcode":"53188",
    "sg:province":"WI",
    "sg:tags":[
        "consultant",
        "program",
        "health",
        "fitness"
    ],
    "wof:name":"Piranio Fitness Systems",
    "wof:placetype":"venue"
},
  "geometry": {"coordinates":[-88.260119,43.007022],"type":"Point"}
}