{
  "type": "Feature",
  "properties": {
    "iso:country":"US",
    "sg:address":"2903 Timber Ln",
    "sg:city":"Janesville",
    "sg:classifiers":[
        {
            "category":"Professional",
            "subcategory":"Business Services",
            "type":"Services"
        }
    ],
    "sg:phone":"+1 608 314 0781",
    "sg:postcode":"53545",
    "sg:province":"WI",
    "wof:name":"Decorating Den Interiors",
    "wof:placetype":"venue"
},
  "geometry": {"coordinates":[-89.05806,42.700407],"type":"Point"}
}