{
  "type": "Feature",
  "properties": {
    "iso:country":"US",
    "sg:address":"1305 S Commercial St",
    "sg:city":"Neenah",
    "sg:classifiers":[
        {
            "category":"Autos & Motor Vehicles",
            "subcategory":"Fuel & Gas Station",
            "type":"Retail Goods"
        }
    ],
    "sg:phone":"+1 920 722 3048",
    "sg:postcode":"54956",
    "sg:province":"WI",
    "sg:tags":[
        "oil"
    ],
    "wof:name":"Citgo",
    "wof:placetype":"venue"
},
  "geometry": {"coordinates":[-88.46496500000001,44.164064],"type":"Point"}
}