{
  "type": "Feature",
  "properties": {
    "iso:country":"US",
    "sg:address":"14417 Fixit Ln",
    "sg:city":"Ferryville",
    "sg:classifiers":[
        {
            "category":"Retail",
            "subcategory":"Auto Repair",
            "type":"Services"
        }
    ],
    "sg:phone":"+1 608 734 3514",
    "sg:postcode":"54628",
    "sg:province":"WI",
    "sg:tags":[
        "general"
    ],
    "wof:name":"Rogers Repair Shop",
    "wof:placetype":"venue"
},
  "geometry": {"coordinates":[-91.120452,43.360894],"type":"Point"}
}