{
  "type": "Feature",
  "properties": {
    "iso:country":"US",
    "sg:address":"435 Frost Dr",
    "sg:city":"Williams Bay",
    "sg:classifiers":[
        {
            "category":"Real Estate",
            "subcategory":"Real Estate Operator",
            "type":"Services"
        }
    ],
    "sg:phone":"+1 262 245 5683",
    "sg:postcode":"53191",
    "sg:province":"WI",
    "sg:tags":[
        "building",
        "apartment"
    ],
    "wof:name":"P D H Management Services",
    "wof:placetype":"venue"
},
  "geometry": {"coordinates":[-88.559101,42.575669],"type":"Point"}
}