{
  "type": "Feature",
  "properties": {
    "iso:country":"US",
    "sg:address":"5405 Big Bow Rd",
    "sg:city":"Fitchburg",
    "sg:classifiers":[
        {
            "category":"Professional",
            "subcategory":"Research",
            "type":"Services"
        }
    ],
    "sg:phone":"+1 608 848 9411",
    "sg:postcode":"53711",
    "sg:province":"WI",
    "sg:tags":[
        "environmental",
        "ecological"
    ],
    "wof:name":"Prizim Inc",
    "wof:placetype":"venue"
},
  "geometry": {"coordinates":[-89.472822,43.025847],"type":"Point"}
}