{
  "type": "Feature",
  "properties": {
    "iso:country":"US",
    "sg:address":"6332 State Hwy 57",
    "sg:city":"Sturgeon Bay",
    "sg:classifiers":[
        {
            "category":"Travel",
            "subcategory":"Hotels & Motels",
            "type":"Entertainment"
        }
    ],
    "sg:phone":"+1 920 823 2404",
    "sg:postcode":"54235",
    "sg:province":"WI",
    "sg:tags":[
        "operation",
        "eating"
    ],
    "wof:name":"Square Rigger Lodge",
    "wof:placetype":"venue"
},
  "geometry": {"coordinates":[-87.183986,44.980318],"type":"Point"}
}