{
  "type": "Feature",
  "properties": {
    "iso:country":"US",
    "sg:address":"983 Parkview Dr",
    "sg:city":"Hudson",
    "sg:classifiers":[
        {
            "category":"Building & Trades",
            "subcategory":"Construction",
            "type":"Services"
        }
    ],
    "sg:phone":"+1 651 755 4590",
    "sg:postcode":"54017",
    "sg:province":"WI",
    "sg:tags":[
        "floor",
        "laying",
        "contractor"
    ],
    "wof:name":"Newbauer Custom Wood Floors",
    "wof:placetype":"venue"
},
  "geometry": {"coordinates":[-92.527808,45.109887],"type":"Point"}
}