{
  "type": "Feature",
  "properties": {
    "iso:country":"US",
    "sg:address":"403 E Front St",
    "sg:city":"Peshtigo",
    "sg:classifiers":[
        {
            "category":"Government",
            "subcategory":"Office",
            "type":"Public Place"
        }
    ],
    "sg:phone":"+1 715 582 0545",
    "sg:postcode":"54157",
    "sg:province":"WI",
    "sg:tags":[
        "village"
    ],
    "wof:name":"Peshtigo City Engineer",
    "wof:placetype":"venue"
},
  "geometry": {"coordinates":[-87.741837,45.048213],"type":"Point"}
}