{
  "type": "Feature",
  "properties": {
    "iso:country":"US",
    "sg:address":"307 Main St",
    "sg:city":"Casco",
    "sg:classifiers":[
        {
            "category":"Government",
            "subcategory":"Post Office",
            "type":"Public Place"
        }
    ],
    "sg:phone":"+1 920 837 7551",
    "sg:postcode":"54205",
    "sg:province":"WI",
    "wof:name":"US Post Office",
    "wof:placetype":"venue"
},
  "geometry": {"coordinates":[-87.618337,44.557664],"type":"Point"}
}