{
  "type": "Feature",
  "properties": {
    "iso:country":"US",
    "sg:address":"12509 Stettin Dr",
    "sg:city":"Marathon",
    "sg:classifiers":[
        {
            "category":"Professional",
            "subcategory":"Advertising",
            "type":"Services"
        }
    ],
    "sg:phone":"+1 715 843 6647",
    "sg:postcode":"54448",
    "sg:province":"WI",
    "sg:tags":[
        "mailing",
        "shipping"
    ],
    "wof:name":"Heart Felt Creations",
    "wof:placetype":"venue"
},
  "geometry": {"coordinates":[-89.798019,44.973127],"type":"Point"}
}