{
  "type": "Feature",
  "properties": {
    "addr:full":"19290 Co Rd Z Darlington WI 53530",
    "addr:housenumber":"19290",
    "addr:postcode":"53530",
    "addr:street":"Co Rd",
    "iso:country":"US",
    "sg:address":"19290 Co Rd Z",
    "sg:city":"Darlington",
    "sg:classifiers":[
        {
            "category":"Farming",
            "subcategory":"Dairy Farm",
            "type":"Manufacturing & Wholesale Goods"
        }
    ],
    "sg:phone":"+1 608 762 5549",
    "sg:postcode":"53530",
    "sg:province":"WI",
    "wof:name":"Ray McDonald",
    "wof:placetype":"venue"
},
  "geometry": {"coordinates":[-90.198981,42.719417],"type":"Point"}
}