{
  "type": "Feature",
  "properties": {
    "addr:full":"5882 Poplar Rd Hawkins WI 54530",
    "addr:housenumber":"5882",
    "addr:postcode":"54530",
    "addr:street":"Poplar Rd",
    "iso:country":"US",
    "sg:address":"5882 Poplar Rd",
    "sg:city":"Hawkins",
    "sg:classifiers":[
        {
            "category":"Farming",
            "subcategory":"Dairy Farm",
            "type":"Manufacturing & Wholesale Goods"
        }
    ],
    "sg:phone":"+1 715 585 6601",
    "sg:postcode":"54530",
    "sg:province":"WI",
    "wof:name":"Dennis Severson Farm",
    "wof:placetype":"venue"
},
  "geometry": {"coordinates":[-90.740129,45.505162],"type":"Point"}
}