{
  "type": "Feature",
  "properties": {
    "iso:country":"US",
    "sg:address":"501 S Yellowstone Dr",
    "sg:city":"Madison",
    "sg:classifiers":[
        {
            "category":"Manufacturing",
            "subcategory":"Printing",
            "type":"Manufacturing & Wholesale Goods"
        }
    ],
    "sg:phone":"+1 608 833 5020",
    "sg:postcode":"53719",
    "sg:province":"WI",
    "sg:tags":[
        "printer"
    ],
    "wof:name":"Econo-Print Inc",
    "wof:placetype":"venue"
},
  "geometry": {"coordinates":[-89.492982,43.055968],"type":"Point"}
}