{
  "type": "Feature",
  "properties": {
    "iso:country":"US",
    "sg:address":"3943 Vruwink Rd",
    "sg:city":"Milladore",
    "sg:classifiers":[
        {
            "category":"Freight",
            "type":"Transportation"
        }
    ],
    "sg:phone":"+1 715 652 3242",
    "sg:postcode":"54454",
    "sg:province":"WI",
    "sg:tags":[
        "trucking"
    ],
    "wof:name":"G & P Trucking",
    "wof:placetype":"venue"
},
  "geometry": {"coordinates":[-89.91209,44.576934],"type":"Point"}
}