{
  "type": "Feature",
  "properties": {
    "iso:country":"US",
    "sg:address":"417 Diving Hawk Trl",
    "sg:city":"Madison",
    "sg:classifiers":[
        {
            "category":"Building & Trades",
            "subcategory":"Construction",
            "type":"Services"
        }
    ],
    "sg:phone":"+1 608 276 9517",
    "sg:postcode":"53713",
    "sg:province":"WI",
    "sg:tags":[
        "house"
    ],
    "wof:name":"Ew Home Improvements",
    "wof:placetype":"venue"
},
  "geometry": {"coordinates":[-89.376724,43.031485],"type":"Point"}
}