{
  "type": "Feature",
  "properties": {
    "iso:country":"US",
    "sg:address":"227 Water St",
    "sg:city":"Sauk City",
    "sg:classifiers":[
        {
            "category":"Food & Beverages",
            "subcategory":"Liquor & Beverages",
            "type":"Retail Goods"
        }
    ],
    "sg:phone":"+1 608 643 8340",
    "sg:postcode":"53583",
    "sg:province":"WI",
    "sg:tags":[
        "store"
    ],
    "wof:name":"Sauk Prairie Liquor Store",
    "wof:placetype":"venue"
},
  "geometry": {"coordinates":[-89.726884,43.295898],"type":"Point"}
}