{
  "type": "Feature",
  "properties": {
    "iso:country":"US",
    "sg:address":"2160 Kraus Ln",
    "sg:city":"Mount Calvary",
    "sg:classifiers":[
        {
            "category":"Farming",
            "subcategory":"Dairy Farm",
            "type":"Manufacturing & Wholesale Goods"
        }
    ],
    "sg:phone":"+1 920 922 7462",
    "sg:postcode":"53057",
    "sg:province":"WI",
    "wof:name":"Bros Bros Farm",
    "wof:placetype":"venue"
},
  "geometry": {"coordinates":[-88.26237999999999,43.79225],"type":"Point"}
}