{
  "type": "Feature",
  "properties": {
    "iso:country":"US",
    "sg:address":"514 E Murray St",
    "sg:city":"Boyd",
    "sg:classifiers":[
        {
            "category":"Shopping",
            "subcategory":"Gifts & Souvenirs",
            "type":"Retail Goods"
        }
    ],
    "sg:phone":"+1 715 667 3861",
    "sg:postcode":"54726",
    "sg:province":"WI",
    "sg:tags":[
        "shop"
    ],
    "wof:name":"Ribbons & Rosebuds",
    "wof:placetype":"venue"
},
  "geometry": {"coordinates":[-91.03952700000001,44.951556],"type":"Point"}
}