{
  "type": "Feature",
  "properties": {
    "addr:full":"375 Williamstowne Delafield WI 53018",
    "addr:housenumber":"375",
    "addr:postcode":"53018",
    "addr:street":"Williamstowne",
    "iso:country":"US",
    "sg:address":"375 Williamstowne",
    "sg:city":"Delafield",
    "sg:classifiers":[
        {
            "category":"Banks & Credit Unions",
            "subcategory":"Bank",
            "type":"Services"
        }
    ],
    "sg:phone":"+1 262 646 8400",
    "sg:postcode":"53018",
    "sg:province":"WI",
    "wof:name":"Canvasback Lending LLC",
    "wof:placetype":"venue"
},
  "geometry": {"coordinates":[-88.377376,43.050055],"type":"Point"}
}