{
  "type": "Feature",
  "properties": {
    "addr:full":"4427 Moody Ln Two Rivers WI 54241",
    "addr:housenumber":"4427",
    "addr:postcode":"54241",
    "addr:street":"Moody Ln",
    "iso:country":"US",
    "sg:address":"4427 Moody Ln",
    "sg:city":"Two Rivers",
    "sg:classifiers":[
        {
            "category":"Building & Trades",
            "subcategory":"Landscaping Services",
            "type":"Services"
        }
    ],
    "sg:phone":"+1 920 755 2007",
    "sg:postcode":"54241",
    "sg:province":"WI",
    "sg:tags":[
        "landscape",
        "contractor"
    ],
    "wof:name":"Scenic Landscape Co",
    "wof:placetype":"venue"
},
  "geometry": {"coordinates":[-87.70375199999999,44.2333],"type":"Point"}
}