{
  "type": "Feature",
  "properties": {
    "addr:full":"2339 E Rockdale Rd Cambridge WI 53523",
    "addr:housenumber":"2339",
    "addr:postcode":"53523",
    "addr:street":"E Rockdale Rd",
    "iso:country":"US",
    "sg:address":"2339 E Rockdale Rd",
    "sg:city":"Cambridge",
    "sg:classifiers":[
        {
            "category":"Farming",
            "subcategory":"Farm",
            "type":"Manufacturing & Wholesale Goods"
        }
    ],
    "sg:phone":"+1 608 423 3191",
    "sg:postcode":"53523",
    "sg:province":"WI",
    "sg:tags":[
        "crop",
        "general"
    ],
    "wof:name":"Ray Dalby",
    "wof:placetype":"venue"
},
  "geometry": {"coordinates":[-89.003693,42.928771],"type":"Point"}
}