{
  "type": "Feature",
  "properties": {
    "iso:country":"US",
    "sg:address":"2312 N Shore Dr",
    "sg:city":"Delavan",
    "sg:classifiers":[
        {
            "category":"Professional",
            "subcategory":"Business Services",
            "type":"Services"
        }
    ],
    "sg:phone":"+1 262 728 3779",
    "sg:postcode":"53115",
    "sg:province":"WI",
    "wof:name":"Legend Enterprises",
    "wof:placetype":"venue"
},
  "geometry": {"coordinates":[-88.614603,42.606914],"type":"Point"}
}