{
  "type": "Feature",
  "properties": {
    "iso:country":"US",
    "sg:address":"2657 University Ave",
    "sg:city":"Green Bay",
    "sg:classifiers":[
        {
            "category":"Bars & Pubs",
            "type":"Food & Drink"
        }
    ],
    "sg:phone":"+1 920 468 9455",
    "sg:postcode":"54311",
    "sg:province":"WI",
    "sg:tags":[
        "drinking"
    ],
    "wof:name":"Escapades",
    "wof:placetype":"venue"
},
  "geometry": {"coordinates":[-87.948336,44.515865],"type":"Point"}
}