{
  "type": "Feature",
  "properties": {
    "iso:country":"US",
    "sg:address":"138 Buntrock Ave",
    "sg:city":"Thiensville",
    "sg:classifiers":[
        {
            "category":"Organizations",
            "subcategory":"Religious Organization",
            "type":"Services"
        }
    ],
    "sg:phone":"+1 262 796 3950",
    "sg:postcode":"53092",
    "sg:province":"WI",
    "wof:name":"Dennis M Andrews Rev",
    "wof:placetype":"venue"
},
  "geometry": {"coordinates":[-87.987044,43.230429],"type":"Point"}
}