{
  "type": "Feature",
  "properties": {
    "addr:full":"8327 US Hwy 10 Marshfield WI 54449",
    "addr:housenumber":"8327",
    "addr:postcode":"54449",
    "addr:street":"Us Hwy 10",
    "iso:country":"US",
    "sg:address":"8327 US Hwy 10",
    "sg:city":"Marshfield",
    "sg:classifiers":[
        {
            "category":"Retail",
            "subcategory":"Auto Repair",
            "type":"Services"
        }
    ],
    "sg:phone":"+1 715 591 3139",
    "sg:postcode":"54449",
    "sg:province":"WI",
    "sg:tags":[
        "general"
    ],
    "wof:name":"Kevs Auto Repair",
    "wof:placetype":"venue"
},
  "geometry": {"coordinates":[-90.13466099999999,44.626342],"type":"Point"}
}