{
  "type": "Feature",
  "properties": {
    "iso:country":"US",
    "sg:address":"403 N High St",
    "sg:city":"Chippewa Falls",
    "sg:classifiers":[
        {
            "category":"Education",
            "subcategory":"Special Training",
            "type":"Public Place"
        },
        {
            "category":"Social Services",
            "type":"Services"
        }
    ],
    "sg:phone":"+1 715 720 1841",
    "sg:postcode":"54729",
    "sg:province":"WI",
    "sg:tags":[
        "development",
        "child"
    ],
    "wof:name":"River Source Family Center",
    "wof:placetype":"venue"
},
  "geometry": {"coordinates":[-91.392671,44.939746],"type":"Point"}
}