{
  "type": "Feature",
  "properties": {
    "iso:country":"US",
    "sg:address":"141 S Main St",
    "sg:city":"West Bend",
    "sg:classifiers":[
        {
            "category":"Real Estate",
            "subcategory":"Real Estate Operator",
            "type":"Services"
        }
    ],
    "sg:phone":"+1 262 338 3909",
    "sg:postcode":"53095",
    "sg:province":"WI",
    "sg:tags":[
        "building",
        "m",
        "association",
        "business",
        "nonresidential"
    ],
    "wof:name":"City Centro",
    "wof:placetype":"venue"
},
  "geometry": {"coordinates":[-88.18225700000001,43.423184],"type":"Point"}
}