{
  "type": "Feature",
  "properties": {
    "iso:country":"US",
    "sg:address":"5 Round Hill Cir",
    "sg:city":"Madison",
    "sg:classifiers":[
        {
            "category":"Professional",
            "subcategory":"Management & Consulting",
            "type":"Services"
        }
    ],
    "sg:phone":"+1 608 833 9697",
    "sg:postcode":"53717",
    "sg:province":"WI",
    "sg:tags":[
        "business"
    ],
    "wof:name":"Stephen R Carpenter",
    "wof:placetype":"venue"
},
  "geometry": {"coordinates":[-89.503844,43.071018],"type":"Point"}
}