{
  "type": "Feature",
  "properties": {
    "iso:country":"US",
    "sg:address":"630 S Madison St",
    "sg:city":"Waupun",
    "sg:classifiers":[
        {
            "category":"Shopping",
            "subcategory":"Computers & Home Electronics",
            "type":"Retail Goods"
        }
    ],
    "sg:phone":"+1 920 324 9224",
    "sg:postcode":"53963",
    "sg:province":"WI",
    "sg:tags":[
        "equipment",
        "dealer"
    ],
    "wof:name":"Home Office Technology",
    "wof:placetype":"venue"
},
  "geometry": {"coordinates":[-88.729859,43.624102],"type":"Point"}
}