{
  "type": "Feature",
  "properties": {
    "iso:country":"US",
    "sg:address":"7944 S 13th St",
    "sg:city":"Oak Creek",
    "sg:classifiers":[
        {
            "category":"Freight",
            "type":"Transportation"
        }
    ],
    "sg:phone":"+1 414 764 3889",
    "sg:postcode":"53154",
    "sg:province":"WI",
    "sg:tags":[
        "operator",
        "trucking"
    ],
    "wof:name":"Turinski Trucking",
    "wof:placetype":"venue"
},
  "geometry": {"coordinates":[-87.93129,42.899204],"type":"Point"}
}