{
  "type": "Feature",
  "properties": {
    "iso:country":"US",
    "sg:address":"1340 Hubble Dr",
    "sg:city":"Green Bay",
    "sg:classifiers":[
        {
            "category":"Health Services",
            "subcategory":"Hospital",
            "type":"Services"
        }
    ],
    "sg:phone":"+1 920 468 9100",
    "sg:postcode":"54311",
    "sg:province":"WI",
    "wof:name":"Aurora-Baycare Surgery Ctr",
    "wof:placetype":"venue"
},
  "geometry": {"coordinates":[-87.938771,44.477672],"type":"Point"}
}