{
  "type": "Feature",
  "properties": {
    "iso:country":"US",
    "sg:address":"3853 Shawano Ave",
    "sg:city":"Green Bay",
    "sg:classifiers":[
        {
            "category":"Building & Trades",
            "subcategory":"Construction",
            "type":"Services"
        }
    ],
    "sg:phone":"+1 920 434 1092",
    "sg:postcode":"54313",
    "sg:province":"WI",
    "sg:tags":[
        "house"
    ],
    "wof:name":"Ronald Rentmeester Cnstr",
    "wof:placetype":"venue"
},
  "geometry": {"coordinates":[-88.130666,44.56712],"type":"Point"}
}