{
  "type": "Feature",
  "properties": {
    "iso:country":"US",
    "sg:address":"13855 W North Ave",
    "sg:city":"Brookfield",
    "sg:classifiers":[
        {
            "category":"Home & Garden",
            "subcategory":"Home Furnishings",
            "type":"Retail Goods"
        }
    ],
    "sg:phone":"+1 262 641 1600",
    "sg:postcode":"53005",
    "sg:province":"WI",
    "sg:tags":[
        "shop",
        "lamp",
        "shade"
    ],
    "wof:name":"Lighting Accessories",
    "wof:placetype":"venue"
},
  "geometry": {"coordinates":[-88.085847,43.060397],"type":"Point"}
}