{
  "type": "Feature",
  "properties": {
    "iso:country":"US",
    "sg:address":"448 Highview Rd",
    "sg:city":"Ixonia",
    "sg:classifiers":[
        {
            "category":"Freight",
            "type":"Transportation"
        }
    ],
    "sg:phone":"+1 262 569 7718",
    "sg:postcode":"53036",
    "sg:province":"WI",
    "sg:tags":[
        "hauling",
        "trucking"
    ],
    "wof:name":"Spoerl Trucking Inc",
    "wof:placetype":"venue"
},
  "geometry": {"coordinates":[-88.551407,43.207862],"type":"Point"}
}