{
  "type": "Feature",
  "properties": {
    "iso:country":"US",
    "sg:address":"2671 Circle Dr",
    "sg:city":"Stoughton",
    "sg:classifiers":[
        {
            "category":"Travel",
            "subcategory":"Campground",
            "type":"Entertainment"
        }
    ],
    "sg:phone":"+1 608 873 5800",
    "sg:postcode":"53589",
    "sg:province":"WI",
    "sg:tags":[
        "trailer"
    ],
    "wof:name":"Kamp Kegonsa Inc",
    "wof:placetype":"venue"
},
  "geometry": {"coordinates":[-89.21298400000001,42.97472],"type":"Point"}
}