{
  "type": "Feature",
  "properties": {
    "addr:full":"215 Banks Ave Superior WI 54880",
    "addr:housenumber":"215",
    "addr:postcode":"54880",
    "addr:street":"Banks Ave",
    "iso:country":"US",
    "sg:address":"215 Banks Ave",
    "sg:city":"Superior",
    "sg:classifiers":[
        {
            "category":"Manufacturing",
            "subcategory":"Tools & Machinery",
            "type":"Manufacturing & Wholesale Goods"
        }
    ],
    "sg:phone":"+1 715 392 8402",
    "sg:postcode":"54880",
    "sg:province":"WI",
    "sg:tags":[
        "steel",
        "fabricator",
        "construction",
        "cab",
        "mfg"
    ],
    "wof:name":"Northland Welding & Mfg Inc",
    "wof:placetype":"venue"
},
  "geometry": {"coordinates":[-92.105429,46.736103],"type":"Point"}
}