{
  "type": "Feature",
  "properties": {
    "iso:country":"US",
    "sg:address":"19039 Co Rd F",
    "sg:city":"Darlington",
    "sg:classifiers":[
        {
            "category":"Manufacturing",
            "subcategory":"Printing",
            "type":"Manufacturing & Wholesale Goods"
        }
    ],
    "sg:phone":"+1 608 776 8501",
    "sg:postcode":"53530",
    "sg:province":"WI",
    "sg:tags":[
        "screen"
    ],
    "wof:name":"Lobdell & Lobdell",
    "wof:placetype":"venue"
},
  "geometry": {"coordinates":[-90.191956,42.675395],"type":"Point"}
}