{
  "type": "Feature",
  "properties": {
    "addr:full":"121 N Main St Fort Atkinson WI 53538",
    "addr:housenumber":"121",
    "addr:postcode":"53538",
    "addr:street":"N Main St",
    "iso:country":"US",
    "sg:address":"121 N Main St",
    "sg:city":"Fort Atkinson",
    "sg:classifiers":[
        {
            "category":"Sports & Exercise",
            "subcategory":"Gym",
            "type":"Entertainment"
        }
    ],
    "sg:phone":"+1 920 563 8013",
    "sg:postcode":"53538",
    "sg:province":"WI",
    "sg:tags":[
        "fitness",
        "physical",
        "facility"
    ],
    "wof:name":"Curves For Women",
    "wof:placetype":"venue"
},
  "geometry": {"coordinates":[-88.837097,42.929473],"type":"Point"}
}