{
  "type": "Feature",
  "properties": {
    "addr:full":"8092 Edgewood Ave E Ladysmith WI 54848",
    "addr:housenumber":"8092",
    "addr:postcode":"54848",
    "addr:street":"Edgewood Ave E",
    "iso:country":"US",
    "sg:address":"8092 Edgewood Ave E",
    "sg:city":"Ladysmith",
    "sg:classifiers":[
        {
            "category":"Restaurant",
            "type":"Food & Drink"
        }
    ],
    "sg:phone":"+1 715 532 3239",
    "sg:postcode":"54848",
    "sg:province":"WI",
    "wof:name":"Tinker Tot Drive-In",
    "wof:placetype":"venue"
},
  "geometry": {"coordinates":[-91.08134099999999,45.473497],"type":"Point"}
}