{
  "type": "Feature",
  "properties": {
    "addr:full":"151 Virginia St Antigo WI 54409",
    "addr:housenumber":"151",
    "addr:postcode":"54409",
    "addr:street":"Virginia St",
    "iso:country":"US",
    "sg:address":"151 Virginia St",
    "sg:city":"Antigo",
    "sg:classifiers":[
        {
            "category":"Building & Trades",
            "subcategory":"Construction",
            "type":"Services"
        }
    ],
    "sg:phone":"+1 715 623 5938",
    "sg:postcode":"54409",
    "sg:province":"WI",
    "sg:tags":[
        "contractor"
    ],
    "wof:name":"Double J Construction",
    "wof:placetype":"venue"
},
  "geometry": {"coordinates":[-89.144507,45.133405],"type":"Point"}
}