{
  "type": "Feature",
  "properties": {
    "iso:country":"US",
    "sg:address":"6024 Overlook Dr",
    "sg:city":"Mc Farland",
    "sg:classifiers":[
        {
            "category":"Manufacturing",
            "subcategory":"Printing",
            "type":"Manufacturing & Wholesale Goods"
        }
    ],
    "sg:phone":"+1 608 838 7070",
    "sg:postcode":"53558",
    "sg:province":"WI",
    "sg:tags":[
        "typesetting"
    ],
    "wof:name":"Goddard & Daughters Inc",
    "wof:placetype":"venue"
},
  "geometry": {"coordinates":[-89.30705,43.010712],"type":"Point"}
}