{
  "type": "Feature",
  "properties": {
    "iso:country":"US",
    "sg:address":"2168 S Memorial Dr",
    "sg:city":"Appleton",
    "sg:classifiers":[
        {
            "category":"Retail",
            "subcategory":"Auto Repair",
            "type":"Services"
        }
    ],
    "sg:phone":"+1 920 734 7486",
    "sg:postcode":"54915",
    "sg:province":"WI",
    "sg:tags":[
        "repairing",
        "automobile",
        "general",
        "automation"
    ],
    "wof:name":"Mark's Auto Repair",
    "wof:placetype":"venue"
},
  "geometry": {"coordinates":[-88.417969,44.241692],"type":"Point"}
}