{
  "type": "Feature",
  "properties": {
    "addr:full":"4041 Co Hwy A Bloomer WI 54724",
    "addr:housenumber":"4041",
    "addr:postcode":"54724",
    "addr:street":"Co Hwy A",
    "iso:country":"US",
    "sg:address":"4041 Co Hwy A",
    "sg:city":"Bloomer",
    "sg:classifiers":[
        {
            "category":"Freight",
            "type":"Transportation"
        }
    ],
    "sg:phone":"+1 715 568 3299",
    "sg:postcode":"54724",
    "sg:province":"WI",
    "sg:tags":[
        "operator",
        "local",
        "trucking"
    ],
    "wof:name":"D & B Trucking",
    "wof:placetype":"venue"
},
  "geometry": {"coordinates":[-91.578636,45.088189],"type":"Point"}
}