{
  "type": "Feature",
  "properties": {
    "addr:full":"210 Haylett St Neenah WI 54956",
    "addr:housenumber":"210",
    "addr:postcode":"54956",
    "addr:street":"Haylett St",
    "iso:country":"US",
    "sg:address":"210 Haylett St",
    "sg:city":"Neenah",
    "sg:classifiers":[
        {
            "category":"Health Services",
            "subcategory":"Nursing And Care Facility",
            "type":"Services"
        },
        {
            "category":"Real Estate",
            "subcategory":"Real Estate Operator",
            "type":"Services"
        }
    ],
    "sg:phone":"+1 920 725 8816",
    "sg:postcode":"54956",
    "sg:province":"WI",
    "sg:tags":[
        "building",
        "home",
        "apartment",
        "rest"
    ],
    "wof:name":"Hearthside Apartments",
    "wof:placetype":"venue"
},
  "geometry": {"coordinates":[-88.462495,44.169645],"type":"Point"}
}