{
  "type": "Feature",
  "properties": {
    "iso:country":"US",
    "sg:address":"1805 Kern Ave",
    "sg:city":"Rice Lake",
    "sg:classifiers":[
        {
            "category":"Personal",
            "subcategory":"Beauty Salon",
            "type":"Services"
        }
    ],
    "sg:phone":"+1 715 736 0177",
    "sg:postcode":"54868",
    "sg:province":"WI",
    "sg:tags":[
        "shop"
    ],
    "wof:name":"Seasons Change Salon & Day Spa",
    "wof:placetype":"venue"
},
  "geometry": {"coordinates":[-91.725088,45.483253],"type":"Point"}
}