{
  "type": "Feature",
  "properties": {
    "iso:country":"US",
    "sg:address":"1280 S Van Dyke Rd",
    "sg:city":"Appleton",
    "sg:classifiers":[
        {
            "category":"Manufacturing",
            "subcategory":"Food",
            "type":"Manufacturing & Wholesale Goods"
        }
    ],
    "sg:phone":"+1 920 739 5732",
    "sg:postcode":"54914",
    "sg:province":"WI",
    "sg:tags":[
        "brewer"
    ],
    "wof:name":"Steep & Brew",
    "wof:placetype":"venue"
},
  "geometry": {"coordinates":[-88.468042,44.246069],"type":"Point"}
}