{
  "type": "Feature",
  "properties": {
    "iso:country":"US",
    "sg:address":"1344 Arthur St",
    "sg:city":"Darlington",
    "sg:classifiers":[
        {
            "category":"Building & Trades",
            "subcategory":"Construction",
            "type":"Services"
        }
    ],
    "sg:phone":"+1 608 776 3670",
    "sg:postcode":"53530",
    "sg:province":"WI",
    "sg:tags":[
        "floor",
        "laying",
        "contractor"
    ],
    "wof:name":"Haesler Flooring",
    "wof:placetype":"venue"
},
  "geometry": {"coordinates":[-90.108114,42.689271],"type":"Point"}
}