{
  "type": "Feature",
  "properties": {
    "iso:country":"US",
    "sg:address":"296 Spring Prairie Rd",
    "sg:city":"Burlington",
    "sg:classifiers":[
        {
            "category":"Building & Trades",
            "subcategory":"Landscaping Services",
            "type":"Services"
        }
    ],
    "sg:phone":"+1 262 763 4645",
    "sg:postcode":"53105",
    "sg:province":"WI",
    "sg:tags":[
        "trim",
        "tree"
    ],
    "wof:name":"Arbor Images",
    "wof:placetype":"venue"
},
  "geometry": {"coordinates":[-88.32164,42.697872],"type":"Point"}
}