{
  "type": "Feature",
  "properties": {
    "iso:country":"US",
    "sg:address":"11723 W Brown Deer Rd",
    "sg:city":"Milwaukee",
    "sg:classifiers":[
        {
            "category":"Professional",
            "subcategory":"Accounting & Tax Preparation",
            "type":"Services"
        }
    ],
    "sg:phone":"+1 414 578 1606",
    "sg:postcode":"53224",
    "sg:province":"WI",
    "sg:tags":[
        "return",
        "filing"
    ],
    "wof:name":"Jackson Hewitt Tax Svc",
    "wof:placetype":"venue"
},
  "geometry": {"coordinates":[-88.055421,43.177106],"type":"Point"}
}