{
  "type": "Feature",
  "properties": {
    "iso:country":"US",
    "sg:address":"9000 W Burleigh St",
    "sg:city":"Milwaukee",
    "sg:classifiers":[
        {
            "category":"Shopping",
            "subcategory":"Pharmacy",
            "type":"Retail Goods"
        }
    ],
    "sg:phone":"+1 414 442 4400",
    "sg:postcode":"53222",
    "sg:province":"WI",
    "sg:tags":[
        "drug"
    ],
    "wof:name":"Wilke's Village Pharmacy",
    "wof:placetype":"venue"
},
  "geometry": {"coordinates":[-88.026297,43.075074],"type":"Point"}
}