{
  "type": "Feature",
  "properties": {
    "iso:country":"US",
    "sg:address":"14617 W Highland Rd",
    "sg:city":"Hayward",
    "sg:classifiers":[
        {
            "category":"Wholesale",
            "subcategory":"Electrical",
            "type":"Manufacturing & Wholesale Goods"
        }
    ],
    "sg:phone":"+1 715 634 3060",
    "sg:postcode":"54843",
    "sg:province":"WI",
    "sg:tags":[
        "control",
        "security",
        "system"
    ],
    "wof:name":"Protective Systems",
    "wof:placetype":"venue"
},
  "geometry": {"coordinates":[-91.427014,45.903674],"type":"Point"}
}