{
  "type": "Feature",
  "properties": {
    "iso:country":"US",
    "sg:address":"3384 Maple Ln",
    "sg:city":"Fond Du Lac",
    "sg:classifiers":[
        {
            "category":"Farming",
            "subcategory":"Dairy Farm",
            "type":"Manufacturing & Wholesale Goods"
        }
    ],
    "sg:phone":"+1 920 923 0761",
    "sg:postcode":"54935",
    "sg:province":"WI",
    "wof:name":"Oak View Farms",
    "wof:placetype":"venue"
},
  "geometry": {"coordinates":[-88.411036,43.664],"type":"Point"}
}