{
  "type": "Feature",
  "properties": {
    "iso:country":"US",
    "sg:address":"6606 Forest Rd",
    "sg:city":"Beaver Dam",
    "sg:classifiers":[
        {
            "category":"Farming",
            "subcategory":"Farm",
            "type":"Manufacturing & Wholesale Goods"
        }
    ],
    "sg:phone":"+1 920 356 9051",
    "sg:postcode":"53916",
    "sg:province":"WI",
    "sg:tags":[
        "crop",
        "general"
    ],
    "wof:name":"Kraus John",
    "wof:placetype":"venue"
},
  "geometry": {"coordinates":[-88.90475000000001,43.433751],"type":"Point"}
}