{
  "type": "Feature",
  "properties": {
    "iso:country":"US",
    "sg:address":"3436 W Kiehnau Ave",
    "sg:city":"Milwaukee",
    "sg:classifiers":[
        {
            "category":"Retail",
            "subcategory":"Repair Shop",
            "type":"Services"
        }
    ],
    "sg:phone":"+1 414 931 0201",
    "sg:postcode":"53209",
    "sg:province":"WI",
    "sg:tags":[
        "operator",
        "device",
        "vending",
        "broker",
        "amusement"
    ],
    "wof:name":"A-One Vending & Amusement Inc",
    "wof:placetype":"venue"
},
  "geometry": {"coordinates":[-87.955794,43.1372],"type":"Point"}
}