{
  "type": "Feature",
  "properties": {
    "iso:country":"US",
    "sg:address":"1330 S Main St",
    "sg:city":"Rice Lake",
    "sg:classifiers":[
        {
            "category":"Autos & Motor Vehicles",
            "subcategory":"Automobile Sales",
            "type":"Retail Goods"
        }
    ],
    "sg:phone":"+1 715 234 8222",
    "sg:postcode":"54868",
    "sg:province":"WI",
    "sg:tags":[
        "car",
        "dealer"
    ],
    "wof:name":"Skar's Auto Svc",
    "wof:placetype":"venue"
},
  "geometry": {"coordinates":[-91.73344299999999,45.487098],"type":"Point"}
}