{
  "type": "Feature",
  "properties": {
    "addr:full":"2608 Madison Ln Barronett WI 54813",
    "addr:housenumber":"2608",
    "addr:postcode":"54813",
    "addr:street":"Madison Ln",
    "iso:country":"US",
    "sg:address":"2608 Madison Ln",
    "sg:city":"Barronett",
    "sg:classifiers":[
        {
            "category":"Building & Trades",
            "subcategory":"Construction",
            "type":"Services"
        }
    ],
    "sg:phone":"+1 715 468 2327",
    "sg:postcode":"54813",
    "sg:province":"WI",
    "sg:tags":[
        "concrete",
        "contractor"
    ],
    "wof:name":"Ricks Concrete",
    "wof:placetype":"venue"
},
  "geometry": {"coordinates":[-92.113444,45.654502],"type":"Point"}
}