{
  "type": "Feature",
  "properties": {
    "iso:country":"US",
    "sg:address":"731 Pennsylvania Ave",
    "sg:city":"Sheboygan",
    "sg:classifiers":[
        {
            "category":"Insurance",
            "subcategory":"Insurance Agent",
            "type":"Services"
        }
    ],
    "sg:phone":"+1 920 457 6669",
    "sg:postcode":"53081",
    "sg:province":"WI",
    "wof:name":"Mony Life Insurance Co",
    "wof:placetype":"venue"
},
  "geometry": {"coordinates":[-87.712664,43.749714],"type":"Point"}
}