{
  "type": "Feature",
  "properties": {
    "addr:full":"1815 Kohler Rd Neosho WI 53059",
    "addr:housenumber":"1815",
    "addr:postcode":"53059",
    "addr:street":"Kohler Rd",
    "iso:country":"US",
    "sg:address":"1815 Kohler Rd",
    "sg:city":"Neosho",
    "sg:classifiers":[
        {
            "category":"Real Estate",
            "subcategory":"Real Estate Operator",
            "type":"Services"
        }
    ],
    "sg:phone":"+1 920 474 4325",
    "sg:postcode":"53059",
    "sg:province":"WI",
    "sg:tags":[
        "property",
        "lessor"
    ],
    "wof:name":"Hilbert Grulke",
    "wof:placetype":"venue"
},
  "geometry": {"coordinates":[-88.536969,43.266067],"type":"Point"}
}