{
  "type": "Feature",
  "properties": {
    "iso:country":"US",
    "sg:address":"615 Flight Rd",
    "sg:city":"Antigo",
    "sg:classifiers":[
        {
            "category":"Professional",
            "type":"Services"
        }
    ],
    "sg:phone":"+1 715 623 3212",
    "sg:postcode":"54409",
    "sg:province":"WI",
    "wof:name":"Joseph Kessler",
    "wof:placetype":"venue"
},
  "geometry": {"coordinates":[-89.13206099999999,45.14736],"type":"Point"}
}