{
  "type": "Feature",
  "properties": {
    "iso:country":"US",
    "sg:address":"102 N Van Rensselaer St",
    "sg:city":"Merrill",
    "sg:classifiers":[
        {
            "category":"Real Estate",
            "subcategory":"Real Estate Operator",
            "type":"Services"
        }
    ],
    "sg:phone":"+1 715 536 9323",
    "sg:postcode":"54452",
    "sg:province":"WI",
    "sg:tags":[
        "building",
        "nonresidential"
    ],
    "wof:name":"M1 Properties LLC",
    "wof:placetype":"venue"
},
  "geometry": {"coordinates":[-89.678951,45.182679],"type":"Point"}
}