{
  "type": "Feature",
  "properties": {
    "iso:country":"US",
    "sg:address":"361 Pickett Ct",
    "sg:city":"Burlington",
    "sg:classifiers":[
        {
            "category":"Professional",
            "subcategory":"Management & Consulting",
            "type":"Services"
        }
    ],
    "sg:phone":"+1 262 763 5230",
    "sg:postcode":"53105",
    "sg:province":"WI",
    "sg:tags":[
        "business"
    ],
    "wof:name":"Spitzer Robert R & Assoc",
    "wof:placetype":"venue"
},
  "geometry": {"coordinates":[-88.29785800000001,42.680977],"type":"Point"}
}