{
  "type": "Feature",
  "properties": {
    "iso:country":"US",
    "sg:address":"2575 Telluride Trl",
    "sg:city":"Green Bay",
    "sg:classifiers":[
        {
            "category":"Professional",
            "type":"Services"
        }
    ],
    "sg:phone":"+1 920 434 8416",
    "sg:postcode":"54313",
    "sg:province":"WI",
    "wof:name":"Dimitri Veliotis",
    "wof:placetype":"venue"
},
  "geometry": {"coordinates":[-88.083545,44.579958],"type":"Point"}
}