{
  "type": "Feature",
  "properties": {
    "iso:country":"US",
    "sg:address":"1614 Henry Johns Blvd",
    "sg:city":"Bangor",
    "sg:classifiers":[
        {
            "category":"Social Services",
            "subcategory":"Adult Care",
            "type":"Services"
        }
    ],
    "sg:phone":"+1 608 486 4210",
    "sg:postcode":"54614",
    "sg:province":"WI",
    "sg:tags":[
        "residential"
    ],
    "wof:name":"Helen House LLC",
    "wof:placetype":"venue"
},
  "geometry": {"coordinates":[-90.994377,43.895322],"type":"Point"}
}