{
  "type": "Feature",
  "properties": {
    "iso:country":"US",
    "sg:address":"2 E Mifflin St",
    "sg:city":"Madison",
    "sg:classifiers":[
        {
            "category":"Banks & Credit Unions",
            "subcategory":"Investment Brokerage",
            "type":"Services"
        },
        {
            "category":"Real Estate",
            "subcategory":"Real Estate Operator",
            "type":"Services"
        }
    ],
    "sg:phone":"+1 608 255 4070",
    "sg:postcode":"53703",
    "sg:province":"WI",
    "sg:tags":[
        "building",
        "security",
        "commercial"
    ],
    "wof:name":"Inland Investment Co",
    "wof:placetype":"venue"
},
  "geometry": {"coordinates":[-89.38412599999999,43.076195],"type":"Point"}
}