{
  "type": "Feature",
  "properties": {
    "iso:country":"US",
    "sg:address":"230 S Main St",
    "sg:city":"Jefferson",
    "sg:classifiers":[
        {
            "category":"Real Estate",
            "subcategory":"Surveying",
            "type":"Services"
        }
    ],
    "sg:phone":"+1 920 674 4884",
    "sg:postcode":"53549",
    "sg:province":"WI",
    "sg:tags":[
        "surveyor"
    ],
    "wof:name":"Southwest Surveying & Assoc",
    "wof:placetype":"venue"
},
  "geometry": {"coordinates":[-88.807241,43.003632],"type":"Point"}
}