{
  "type": "Feature",
  "properties": {
    "iso:country":"US",
    "sg:address":"605 W Commercial St",
    "sg:city":"Mazomanie",
    "sg:classifiers":[
        {
            "category":"Building & Trades",
            "subcategory":"Plumbing",
            "type":"Services"
        }
    ],
    "sg:phone":"+1 608 795 0015",
    "sg:postcode":"53560",
    "sg:province":"WI",
    "sg:tags":[
        "management",
        "contractor"
    ],
    "wof:name":"Unified Building Systems",
    "wof:placetype":"venue"
},
  "geometry": {"coordinates":[-89.799323,43.171735],"type":"Point"}
}