{
  "type": "Feature",
  "properties": {
    "iso:country":"US",
    "sg:address":"206 Kirby St",
    "sg:city":"Ridgeway",
    "sg:classifiers":[
        {
            "category":"Government",
            "subcategory":"Office",
            "type":"Public Place"
        }
    ],
    "sg:phone":"+1 608 924 1520",
    "sg:postcode":"53582",
    "sg:province":"WI",
    "sg:tags":[
        "village"
    ],
    "wof:name":"Village Of Rdigeway",
    "wof:placetype":"venue"
},
  "geometry": {"coordinates":[-89.98974,43.000309],"type":"Point"}
}