{
  "type": "Feature",
  "properties": {
    "iso:country":"US",
    "sg:address":"12625 State Hwy 42",
    "sg:city":"Ellison Bay",
    "sg:classifiers":[
        {
            "category":"Museum",
            "type":"Entertainment"
        }
    ],
    "sg:phone":"+1 920 854 9907",
    "sg:postcode":"54210",
    "sg:province":"WI",
    "sg:tags":[
        "gallery"
    ],
    "wof:name":"Charlenes Gallery Ten Ltd",
    "wof:placetype":"venue"
},
  "geometry": {"coordinates":[-87.021851,45.287416],"type":"Point"}
}