{
  "type": "Feature",
  "properties": {
    "addr:full":"417 W Lincoln St Augusta WI 54722",
    "addr:housenumber":"417",
    "addr:postcode":"54722",
    "addr:street":"W Lincoln St",
    "iso:country":"US",
    "sg:address":"417 W Lincoln St",
    "sg:city":"Augusta",
    "sg:classifiers":[
        {
            "category":"Organizations",
            "subcategory":"Religious Organization",
            "type":"Services"
        }
    ],
    "sg:phone":"+1 715 286 2205",
    "sg:postcode":"54722",
    "sg:province":"WI",
    "sg:tags":[
        "church"
    ],
    "wof:name":"St Paul Lutheran Church",
    "wof:placetype":"venue"
},
  "geometry": {"coordinates":[-91.12311699999999,44.680113],"type":"Point"}
}