{
  "type": "Feature",
  "properties": {
    "iso:country":"US",
    "sg:address":"927 Sheridan Rd",
    "sg:city":"Kenosha",
    "sg:classifiers":[
        {
            "category":"Education",
            "subcategory":"Dance Studio",
            "type":"Public Place"
        }
    ],
    "sg:phone":"+1 262 552 8278",
    "sg:postcode":"53140",
    "sg:province":"WI",
    "wof:name":"E-Z Dance Studio",
    "wof:placetype":"venue"
},
  "geometry": {"coordinates":[-87.816467,42.644186],"type":"Point"}
}