{
  "type": "Feature",
  "properties": {
    "iso:country":"US",
    "sg:address":"2688 N Korth Ln",
    "sg:city":"Clintonville",
    "sg:classifiers":[
        {
            "category":"Real Estate",
            "subcategory":"Real Estate Operator",
            "type":"Services"
        }
    ],
    "sg:phone":"+1 715 823 2533",
    "sg:postcode":"54929",
    "sg:province":"WI",
    "sg:tags":[
        "mobile",
        "home",
        "community"
    ],
    "wof:name":"Cloverleaf Mobile Home Park",
    "wof:placetype":"venue"
},
  "geometry": {"coordinates":[-88.67739,44.684242],"type":"Point"}
}