{
  "type": "Feature",
  "properties": {
    "iso:country":"US",
    "sg:address":"2417 Hansen Ave",
    "sg:city":"Racine",
    "sg:classifiers":[
        {
            "category":"Professional",
            "subcategory":"Management & Consulting",
            "type":"Services"
        }
    ],
    "sg:phone":"+1 262 637 4475",
    "sg:postcode":"53405",
    "sg:province":"WI",
    "sg:tags":[
        "consultant",
        "business"
    ],
    "wof:name":"Health Care Receivables",
    "wof:placetype":"venue"
},
  "geometry": {"coordinates":[-87.81355600000001,42.723366],"type":"Point"}
}