{
  "type": "Feature",
  "properties": {
    "iso:country":"US",
    "sg:address":"6646 Anthony Dr",
    "sg:city":"Sobieski",
    "sg:classifiers":[
        {
            "category":"Banks & Credit Unions",
            "subcategory":"Financial Services",
            "type":"Services"
        }
    ],
    "sg:phone":"+1 920 822 8708",
    "sg:postcode":"54171",
    "sg:province":"WI",
    "sg:tags":[
        "investor"
    ],
    "wof:name":"Jobe Investment LLC",
    "wof:placetype":"venue"
},
  "geometry": {"coordinates":[-88.101601,44.682256],"type":"Point"}
}