{
  "type": "Feature",
  "properties": {
    "iso:country":"US",
    "sg:address":"6744 Blackhawk Rd",
    "sg:city":"Portage",
    "sg:classifiers":[
        {
            "category":"Building & Trades",
            "subcategory":"Landscaping Services",
            "type":"Services"
        }
    ],
    "sg:phone":"+1 608 742 5657",
    "sg:postcode":"53901",
    "sg:province":"WI",
    "sg:tags":[
        "landscape",
        "contractor"
    ],
    "wof:name":"Dixon Shoreline Landscaping",
    "wof:placetype":"venue"
},
  "geometry": {"coordinates":[-89.454213,43.520133],"type":"Point"}
}