{
  "type": "Feature",
  "properties": {
    "iso:country":"US",
    "sg:address":"4806 E Broadway",
    "sg:city":"Madison",
    "sg:classifiers":[
        {
            "category":"Retail",
            "subcategory":"Repair Shop",
            "type":"Services"
        }
    ],
    "sg:phone":"+1 608 221 1361",
    "sg:postcode":"53716",
    "sg:province":"WI",
    "wof:name":"Badger Upholstery By Delarosa",
    "wof:placetype":"venue"
},
  "geometry": {"coordinates":[-89.29773299999999,43.048089],"type":"Point"}
}