{
  "type": "Feature",
  "properties": {
    "iso:country":"US",
    "sg:address":"1625 57th St",
    "sg:city":"Kenosha",
    "sg:classifiers":[
        {
            "category":"Food & Beverages",
            "subcategory":"Groceries & Convenience Stores",
            "type":"Retail Goods"
        }
    ],
    "sg:phone":"+1 262 605 0525",
    "sg:postcode":"53140",
    "sg:province":"WI",
    "wof:name":"Fast & Friendly Market",
    "wof:placetype":"venue"
},
  "geometry": {"coordinates":[-87.82961,42.582687],"type":"Point"}
}