{
  "type": "Feature",
  "properties": {
    "iso:country":"US",
    "sg:address":"3022 6th Ct",
    "sg:city":"Grand Marsh",
    "sg:classifiers":[
        {
            "category":"Organizations",
            "subcategory":"Religious Organization",
            "type":"Services"
        }
    ],
    "sg:phone":"+1 608 584 4634",
    "sg:postcode":"53936",
    "sg:province":"WI",
    "sg:tags":[
        "church"
    ],
    "wof:name":"Freewill Missionary Baptist",
    "wof:placetype":"venue"
},
  "geometry": {"coordinates":[-89.700063,43.815429],"type":"Point"}
}