{
  "type": "Feature",
  "properties": {
    "addr:full":"151 S Adams Ave Berlin WI 54923",
    "addr:housenumber":"151",
    "addr:postcode":"54923",
    "addr:street":"S Adams Ave",
    "iso:country":"US",
    "sg:address":"151 S Adams Ave",
    "sg:city":"Berlin",
    "sg:classifiers":[
        {
            "category":"Retail",
            "subcategory":"Portrait Studio",
            "type":"Services"
        }
    ],
    "sg:phone":"+1 920 361 4270",
    "sg:postcode":"54923",
    "sg:province":"WI",
    "sg:tags":[
        "photo"
    ],
    "wof:name":"Sponholtz Photography",
    "wof:placetype":"venue"
},
  "geometry": {"coordinates":[-88.945519,43.966627],"type":"Point"}
}