{
  "type": "Feature",
  "properties": {
    "iso:country":"US",
    "sg:address":"4128 27th St",
    "sg:city":"Kenosha",
    "sg:classifiers":[
        {
            "category":"Professional",
            "type":"Services"
        }
    ],
    "sg:phone":"+1 262 551 8654",
    "sg:postcode":"53144",
    "sg:province":"WI",
    "wof:name":"First Step Kitchen & Bath LLC",
    "wof:placetype":"venue"
},
  "geometry": {"coordinates":[-87.858509,42.614028],"type":"Point"}
}