{
  "type": "Feature",
  "properties": {
    "iso:country":"US",
    "sg:address":"636 Oak Lodge Rd",
    "sg:city":"Waterford",
    "sg:classifiers":[
        {
            "category":"Professional",
            "subcategory":"Computer Services",
            "type":"Services"
        }
    ],
    "sg:phone":"+1 262 534 7963",
    "sg:postcode":"53185",
    "sg:province":"WI",
    "sg:tags":[
        "programing",
        "custom"
    ],
    "wof:name":"Logic Computing Corp",
    "wof:placetype":"venue"
},
  "geometry": {"coordinates":[-88.208697,42.771017],"type":"Point"}
}