{
  "type": "Feature",
  "properties": {
    "iso:country":"US",
    "sg:address":"2201 Main St",
    "sg:city":"Green Bay",
    "sg:classifiers":[
        {
            "category":"Shopping",
            "subcategory":"Department Store",
            "type":"Retail Goods"
        }
    ],
    "sg:phone":"+1 262 468 6215",
    "sg:postcode":"54302",
    "sg:province":"WI",
    "wof:name":"Kmart",
    "wof:placetype":"venue"
},
  "geometry": {"coordinates":[-87.970405,44.483152],"type":"Point"}
}