{
  "type": "Feature",
  "properties": {
    "iso:country":"US",
    "sg:address":"621A Westover St",
    "sg:city":"Oconomowoc",
    "sg:classifiers":[
        {
            "category":"Manufacturing",
            "subcategory":"Electronics",
            "type":"Manufacturing & Wholesale Goods"
        }
    ],
    "sg:phone":"+1 414 449 6000",
    "sg:postcode":"53066",
    "sg:province":"WI",
    "sg:tags":[
        "electronic",
        "controls-manufacturers"
    ],
    "sg:website":"http://www.panelmate.com",
    "wof:name":"Eaton Corporation",
    "wof:placetype":"venue"
},
  "geometry": {"coordinates":[-88.49445299999999,43.104819],"type":"Point"}
}