{
  "type": "Feature",
  "properties": {
    "iso:country":"US",
    "sg:address":"6640 State Hwy 13 S",
    "sg:city":"Wisconsin Rapids",
    "sg:classifiers":[
        {
            "category":"Building & Trades",
            "subcategory":"Construction",
            "type":"Services"
        }
    ],
    "sg:phone":"+1 715 325 2340",
    "sg:postcode":"54494",
    "sg:province":"WI",
    "sg:tags":[
        "home",
        "contractor",
        "general",
        "new"
    ],
    "wof:name":"Ramsden Construction Ltd",
    "wof:placetype":"venue"
},
  "geometry": {"coordinates":[-89.81460199999999,44.33463],"type":"Point"}
}