{
  "type": "Feature",
  "properties": {
    "addr:full":"619 Broadway St S Menomonie WI 54751",
    "addr:housenumber":"619",
    "addr:postcode":"54751",
    "addr:street":"Broadway St S",
    "iso:country":"US",
    "sg:address":"619 Broadway St S",
    "sg:city":"Menomonie",
    "sg:classifiers":[
        {
            "category":"Bars & Pubs",
            "type":"Food & Drink"
        }
    ],
    "sg:phone":"+1 715 235 9993",
    "sg:postcode":"54751",
    "sg:province":"WI",
    "sg:tags":[
        "drinking",
        "eating"
    ],
    "wof:name":"Flame Lounge",
    "wof:placetype":"venue"
},
  "geometry": {"coordinates":[-91.92980300000001,44.877215],"type":"Point"}
}