{
  "type": "Feature",
  "properties": {
    "iso:country":"US",
    "sg:address":"135 S 84th St",
    "sg:city":"Milwaukee",
    "sg:classifiers":[
        {
            "category":"Wholesale",
            "subcategory":"Office Equipment",
            "type":"Manufacturing & Wholesale Goods"
        }
    ],
    "sg:phone":"+1 414 773 7000",
    "sg:postcode":"53214",
    "sg:province":"WI",
    "wof:name":"IKON Office Solutions",
    "wof:placetype":"venue"
},
  "geometry": {"coordinates":[-88.017329,43.03107],"type":"Point"}
}