{
  "type": "Feature",
  "properties": {
    "iso:country":"US",
    "sg:address":"8807 W Grantosa Dr",
    "sg:city":"Milwaukee",
    "sg:classifiers":[
        {
            "category":"Professional",
            "subcategory":"Printing & Photocopies",
            "type":"Services"
        }
    ],
    "sg:phone":"+1 414 466 8964",
    "sg:postcode":"53225",
    "sg:province":"WI",
    "sg:tags":[
        "lithographer"
    ],
    "wof:name":"Resource Printing",
    "wof:placetype":"venue"
},
  "geometry": {"coordinates":[-88.023017,43.101377],"type":"Point"}
}