{
  "type": "Feature",
  "properties": {
    "iso:country":"US",
    "sg:address":"314 160th St",
    "sg:city":"Milltown",
    "sg:classifiers":[
        {
            "category":"Building & Trades",
            "subcategory":"Construction",
            "type":"Services"
        }
    ],
    "sg:phone":"+1 715 825 4340",
    "sg:postcode":"54858",
    "sg:province":"WI",
    "sg:tags":[
        "contractor"
    ],
    "wof:name":"Baillargeon Drywall",
    "wof:placetype":"venue"
},
  "geometry": {"coordinates":[-92.488485,45.526606],"type":"Point"}
}