{
  "type": "Feature",
  "properties": {
    "iso:country":"US",
    "sg:address":"3971 Village Rd",
    "sg:city":"Argonne",
    "sg:classifiers":[
        {
            "category":"Freight",
            "type":"Transportation"
        }
    ],
    "sg:phone":"+1 715 674 4773",
    "sg:postcode":"54511",
    "sg:province":"WI",
    "sg:tags":[
        "distance",
        "long",
        "trucker"
    ],
    "wof:name":"Falat Trucking Inc",
    "wof:placetype":"venue"
},
  "geometry": {"coordinates":[-88.630187,45.651555],"type":"Point"}
}