{
  "type": "Feature",
  "properties": {
    "iso:country":"US",
    "sg:address":"2243 N Dr Martin Luther King Dr",
    "sg:city":"Milwaukee",
    "sg:classifiers":[
        {
            "category":"Shopping",
            "subcategory":"Shoes",
            "type":"Retail Goods"
        }
    ],
    "sg:phone":"+1 414 263 5743",
    "sg:postcode":"53212",
    "sg:province":"WI",
    "wof:name":"Payless Shoe Source",
    "wof:placetype":"venue"
},
  "geometry": {"coordinates":[-87.914232,43.059774],"type":"Point"}
}