{
  "type": "Feature",
  "properties": {
    "addr:full":"320 S Erie St De Pere WI 54115",
    "addr:housenumber":"320",
    "addr:postcode":"54115",
    "addr:street":"S Erie St",
    "iso:country":"US",
    "sg:address":"320 S Erie St",
    "sg:city":"De Pere",
    "sg:classifiers":[
        {
            "category":"Building & Trades",
            "subcategory":"Landscaping Services",
            "type":"Services"
        }
    ],
    "sg:phone":"+1 920 336 0539",
    "sg:postcode":"54115",
    "sg:province":"WI",
    "wof:name":"Summer Star Landscape",
    "wof:placetype":"venue"
},
  "geometry": {"coordinates":[-88.054542,44.44552],"type":"Point"}
}