{
  "type": "Feature",
  "properties": {
    "iso:country":"US",
    "sg:address":"1127 Division St",
    "sg:city":"Withee",
    "sg:classifiers":[
        {
            "category":"Organizations",
            "subcategory":"Religious Organization",
            "type":"Services"
        }
    ],
    "sg:phone":"+1 715 229 2051",
    "sg:postcode":"54498",
    "sg:province":"WI",
    "sg:tags":[
        "church"
    ],
    "wof:name":"Nazareth Lutheran Church",
    "wof:placetype":"venue"
},
  "geometry": {"coordinates":[-90.597985,44.963236],"type":"Point"}
}