{
  "type": "Feature",
  "properties": {
    "addr:full":"4900 Nature Trl Racine WI 53403",
    "addr:housenumber":"4900",
    "addr:postcode":"53403",
    "addr:street":"Nature Trl",
    "iso:country":"US",
    "sg:address":"4900 Nature Trl",
    "sg:city":"Racine",
    "sg:classifiers":[
        {
            "category":"Wholesale",
            "subcategory":"Construction Materials",
            "type":"Manufacturing & Wholesale Goods"
        }
    ],
    "sg:phone":"+1 262 554 2381",
    "sg:postcode":"53403",
    "sg:province":"WI",
    "wof:name":"Software Supply Company Inc",
    "wof:placetype":"venue"
},
  "geometry": {"coordinates":[-87.839406,42.680162],"type":"Point"}
}