{
  "type": "Feature",
  "properties": {
    "addr:full":"7182 State Hwy 113 Dane WI 53529",
    "addr:housenumber":"7182",
    "addr:postcode":"53529",
    "addr:street":"State Hwy 113",
    "iso:country":"US",
    "sg:address":"7182 State Hwy 113",
    "sg:city":"Dane",
    "sg:classifiers":[
        {
            "category":"Farming",
            "subcategory":"Dairy Farm",
            "type":"Manufacturing & Wholesale Goods"
        }
    ],
    "sg:phone":"+1 608 592 4089",
    "sg:postcode":"53529",
    "sg:province":"WI",
    "sg:tags":[
        "corn"
    ],
    "wof:name":"Bill Quam",
    "wof:placetype":"venue"
},
  "geometry": {"coordinates":[-89.51016300000001,43.250528],"type":"Point"}
}