{
  "type": "Feature",
  "properties": {
    "addr:full":"2412 N Mountain Rd Wausau WI 54401",
    "addr:housenumber":"2412",
    "addr:postcode":"54401",
    "addr:street":"N Mountain Rd",
    "iso:country":"US",
    "sg:address":"2412 N Mountain Rd",
    "sg:city":"Wausau",
    "sg:classifiers":[
        {
            "category":"Autos & Motor Vehicles",
            "subcategory":"Fuel & Gas Station",
            "type":"Retail Goods"
        }
    ],
    "sg:phone":"+1 715 845 1149",
    "sg:postcode":"54401",
    "sg:province":"WI",
    "sg:tags":[
        "oil"
    ],
    "wof:name":"Mount View Mobil",
    "wof:placetype":"venue"
},
  "geometry": {"coordinates":[-89.669206,44.933744],"type":"Point"}
}