{
  "type": "Feature",
  "properties": {
    "iso:country":"US",
    "sg:address":"10835 W Pine Lake Rd",
    "sg:city":"Argonne",
    "sg:classifiers":[
        {
            "category":"Freight",
            "type":"Transportation"
        }
    ],
    "sg:phone":"+1 715 649 3335",
    "sg:postcode":"54511",
    "sg:province":"WI",
    "sg:tags":[
        "commercial",
        "storage"
    ],
    "wof:name":"Pine Lake Storage",
    "wof:placetype":"venue"
},
  "geometry": {"coordinates":[-88.99046,45.691537],"type":"Point"}
}