{
  "type": "Feature",
  "properties": {
    "iso:country":"US",
    "sg:address":"3711 Co Rd K",
    "sg:city":"Omro",
    "sg:phone":"+1 920 685 5879",
    "sg:postcode":"54963",
    "sg:province":"WI",
    "sg:tags":[
        "farm",
        "corn",
        "soybean"
    ],
    "wof:name":"Albright Brothers",
    "wof:placetype":"venue"
},
  "geometry": {"coordinates":[-88.84525600000001,44.033433],"type":"Point"}
}