{
  "type": "Feature",
  "properties": {
    "addr:full":"225 S Main St Rice Lake WI 54868",
    "addr:housenumber":"225",
    "addr:postcode":"54868",
    "addr:street":"S Main St",
    "iso:country":"US",
    "sg:address":"225 S Main St",
    "sg:city":"Rice Lake",
    "sg:classifiers":[
        {
            "category":"Real Estate",
            "subcategory":"Real Estate Agent",
            "type":"Services"
        }
    ],
    "sg:phone":"+1 715 736 1330",
    "sg:postcode":"54868",
    "sg:province":"WI",
    "sg:tags":[
        "inspection"
    ],
    "wof:name":"J & J Inspections",
    "wof:placetype":"venue"
},
  "geometry": {"coordinates":[-91.733306,45.498444],"type":"Point"}
}