{
  "type": "Feature",
  "properties": {
    "iso:country":"US",
    "sg:address":"925 W Lincoln Ave",
    "sg:city":"Milwaukee",
    "sg:classifiers":[
        {
            "category":"Shopping",
            "subcategory":"Bicycles & Sporting Goods",
            "type":"Retail Goods"
        }
    ],
    "sg:phone":"+1 414 384 3368",
    "sg:postcode":"53215",
    "sg:province":"WI",
    "sg:tags":[
        "bait",
        "fishing"
    ],
    "wof:name":"Joe's Bait Shop",
    "wof:placetype":"venue"
},
  "geometry": {"coordinates":[-87.923117,43.00276],"type":"Point"}
}