{
  "type": "Feature",
  "properties": {
    "addr:full":"4924 S 13th St Milwaukee WI 53221",
    "addr:housenumber":"4924",
    "addr:postcode":"53221",
    "addr:street":"S 13Th St",
    "iso:country":"US",
    "sg:address":"4924 S 13th St",
    "sg:city":"Milwaukee",
    "sg:classifiers":[
        {
            "category":"Freight",
            "type":"Transportation"
        }
    ],
    "sg:phone":"+1 414 281 3883",
    "sg:postcode":"53221",
    "sg:province":"WI",
    "sg:tags":[
        "operator",
        "trucking"
    ],
    "sg:website":"www.overnighttransportation.com",
    "wof:name":"Overnite Transportation Co",
    "wof:placetype":"venue"
},
  "geometry": {"coordinates":[-87.92918299999999,42.956127],"type":"Point"}
}