{
  "type": "Feature",
  "properties": {
    "iso:country":"US",
    "sg:address":"1259 Milton Ave",
    "sg:city":"Janesville",
    "sg:classifiers":[
        {
            "category":"Shopping",
            "subcategory":"Music",
            "type":"Retail Goods"
        }
    ],
    "sg:phone":"+1 608 743 0786",
    "sg:postcode":"53545",
    "sg:province":"WI",
    "sg:tags":[
        "compact",
        "record",
        "disc",
        "tape"
    ],
    "wof:name":"Exclusive Co",
    "wof:placetype":"venue"
},
  "geometry": {"coordinates":[-89.009433,42.700224],"type":"Point"}
}