{
  "type": "Feature",
  "properties": {
    "iso:country":"US",
    "sg:address":"17325 W Capitol Dr",
    "sg:city":"Brookfield",
    "sg:classifiers":[
        {
            "category":"Retail",
            "subcategory":"Laundry & Dry Cleaning",
            "type":"Services"
        }
    ],
    "sg:phone":"+1 262 790 6911",
    "sg:postcode":"53045",
    "sg:province":"WI",
    "sg:tags":[
        "garment",
        "agent",
        "cleaners"
    ],
    "wof:name":"Choice Cleaners",
    "wof:placetype":"venue"
},
  "geometry": {"coordinates":[-88.129542,43.090012],"type":"Point"}
}