{
  "type": "Feature",
  "properties": {
    "iso:country":"US",
    "sg:address":"8000 109th Ave",
    "sg:city":"Pleasant Prairie",
    "sg:classifiers":[
        {
            "category":"Building & Trades",
            "subcategory":"Landscaping Services",
            "type":"Services"
        }
    ],
    "sg:phone":"+1 262 697 0882",
    "sg:postcode":"53158",
    "sg:province":"WI",
    "sg:tags":[
        "tree"
    ],
    "wof:name":"Oly's Stump Removal",
    "wof:placetype":"venue"
},
  "geometry": {"coordinates":[-87.93920799999999,42.557725],"type":"Point"}
}