{
  "type": "Feature",
  "properties": {
    "addr:full":"2199 Lineville Rd Green Bay WI 54313",
    "addr:housenumber":"2199",
    "addr:postcode":"54313",
    "addr:street":"Lineville Rd",
    "iso:country":"US",
    "sg:address":"2199 Lineville Rd",
    "sg:city":"Green Bay",
    "sg:classifiers":[
        {
            "category":"Professional",
            "subcategory":"Accounting & Tax Preparation",
            "type":"Services"
        }
    ],
    "sg:phone":"+1 920 434 2192",
    "sg:postcode":"54313",
    "sg:province":"WI",
    "sg:tags":[
        "accountant"
    ],
    "wof:name":"C & S Accounting & Tax Svc LLC",
    "wof:placetype":"venue"
},
  "geometry": {"coordinates":[-88.067685,44.591017],"type":"Point"}
}