{
  "type": "Feature",
  "properties": {
    "iso:country":"US",
    "sg:address":"6407 Kathleen St",
    "sg:city":"Schofield",
    "sg:classifiers":[
        {
            "category":"Manufacturing",
            "subcategory":"Metals",
            "type":"Manufacturing & Wholesale Goods"
        }
    ],
    "sg:phone":"+1 715 849 4809",
    "sg:postcode":"54476",
    "sg:province":"WI",
    "sg:tags":[
        "mfg",
        "purchase",
        "wire",
        "display",
        "point"
    ],
    "wof:name":"Photo Max Mfg LLC",
    "wof:placetype":"venue"
},
  "geometry": {"coordinates":[-89.57432799999999,44.899179],"type":"Point"}
}