{
  "type": "Feature",
  "properties": {
    "iso:country":"US",
    "sg:address":"124 Co Hwy Bb",
    "sg:city":"Marshall",
    "sg:classifiers":[
        {
            "category":"Banks & Credit Unions",
            "subcategory":"Bank",
            "type":"Services"
        }
    ],
    "sg:phone":"+1 608 764 8748",
    "sg:postcode":"53559",
    "sg:province":"WI",
    "sg:tags":[
        "financing"
    ],
    "wof:name":"CITI Capital Fleet",
    "wof:placetype":"venue"
},
  "geometry": {"coordinates":[-89.01533,43.08301],"type":"Point"}
}