{
  "type": "Feature",
  "properties": {
    "iso:country":"US",
    "sg:address":"835 Valley Rd",
    "sg:city":"Menasha",
    "sg:classifiers":[
        {
            "category":"Wholesale",
            "subcategory":"Machinery & Supplies",
            "type":"Manufacturing & Wholesale Goods"
        }
    ],
    "sg:phone":"+1 920 996 0423",
    "sg:postcode":"54952",
    "sg:province":"WI",
    "sg:tags":[
        "packaging",
        "wrap",
        "distributes",
        "shrink"
    ],
    "wof:name":"First American Supply LLC",
    "wof:placetype":"venue"
},
  "geometry": {"coordinates":[-88.434198,44.237062],"type":"Point"}
}