{
  "type": "Feature",
  "properties": {
    "addr:full":"1611 W Hopkins St Milwaukee WI 53206",
    "addr:housenumber":"1611",
    "addr:postcode":"53206",
    "addr:street":"W Hopkins St",
    "iso:country":"US",
    "sg:address":"1611 W Hopkins St",
    "sg:city":"Milwaukee",
    "sg:classifiers":[
        {
            "category":"Shopping",
            "subcategory":"Music",
            "type":"Retail Goods"
        }
    ],
    "sg:phone":"+1 414 372 5171",
    "sg:postcode":"53206",
    "sg:province":"WI",
    "sg:tags":[
        "compact",
        "record",
        "disc",
        "tape"
    ],
    "wof:name":"Big 4",
    "wof:placetype":"venue"
},
  "geometry": {"coordinates":[-87.933988,43.073002],"type":"Point"}
}