{
  "type": "Feature",
  "properties": {
    "iso:country":"US",
    "sg:address":"307 W Grove St",
    "sg:city":"South Wayne",
    "sg:classifiers":[
        {
            "category":"Retail",
            "subcategory":"Auto Repair",
            "type":"Services"
        }
    ],
    "sg:phone":"+1 608 439 3385",
    "sg:postcode":"53587",
    "sg:province":"WI",
    "sg:tags":[
        "repairing",
        "automobile"
    ],
    "wof:name":"Mark's Automotive",
    "wof:placetype":"venue"
},
  "geometry": {"coordinates":[-89.880901,42.565255],"type":"Point"}
}