{
  "type": "Feature",
  "properties": {
    "iso:country":"US",
    "sg:address":"438 W Main St",
    "sg:city":"Lena",
    "sg:classifiers":[
        {
            "category":"Retail",
            "subcategory":"Funeral Services",
            "type":"Services"
        }
    ],
    "sg:phone":"+1 920 829 6100",
    "sg:postcode":"54139",
    "sg:province":"WI",
    "wof:name":"Rhodes Charapata Funeral Home",
    "wof:placetype":"venue"
},
  "geometry": {"coordinates":[-88.053259,44.951042],"type":"Point"}
}