{
  "type": "Feature",
  "properties": {
    "iso:country":"US",
    "sg:address":"8008 W Capitol Dr",
    "sg:city":"Milwaukee",
    "sg:classifiers":[
        {
            "category":"Social Services",
            "type":"Services"
        },
        {
            "category":"Social Services",
            "subcategory":"Child Care",
            "type":"Services"
        }
    ],
    "sg:phone":"+1 414 464 1805",
    "sg:postcode":"53222",
    "sg:province":"WI",
    "sg:tags":[
        "homes-children"
    ],
    "wof:name":"Unity House",
    "wof:placetype":"venue"
},
  "geometry": {"coordinates":[-88.012446,43.089938],"type":"Point"}
}