{
  "type": "Feature",
  "properties": {
    "iso:country":"US",
    "sg:address":"3859 State Hwy 42",
    "sg:city":"Fish Creek",
    "sg:classifiers":[
        {
            "category":"Recreation",
            "subcategory":"Marina",
            "type":"Entertainment"
        }
    ],
    "sg:phone":"+1 920 868 3909",
    "sg:postcode":"54212",
    "sg:province":"WI",
    "sg:tags":[
        "repairing",
        "boat"
    ],
    "wof:name":"Fish Creek Marine & Supply",
    "wof:placetype":"venue"
},
  "geometry": {"coordinates":[-87.225254,45.12811],"type":"Point"}
}