{
  "type": "Feature",
  "properties": {
    "addr:full":"420 Wallace St Combined Locks WI 54113",
    "addr:housenumber":"420",
    "addr:postcode":"54113",
    "addr:street":"Wallace St",
    "iso:country":"US",
    "sg:address":"420 Wallace St",
    "sg:city":"Combined Locks",
    "sg:classifiers":[
        {
            "category":"Education",
            "subcategory":"School",
            "type":"Public Place"
        }
    ],
    "sg:phone":"+1 920 788 7915",
    "sg:postcode":"54113",
    "sg:province":"WI",
    "wof:name":"Janssen Elementary School",
    "wof:placetype":"venue"
},
  "geometry": {"coordinates":[-88.306378,44.266533],"type":"Point"}
}