{
  "type": "Feature",
  "properties": {
    "addr:full":"1103 Grossman Dr. Schofield WI 54476",
    "addr:housenumber":"1103",
    "addr:postcode":"54476",
    "addr:street":"Grossman Dr.",
    "iso:country":"US",
    "sg:address":"1103 Grossman Dr.",
    "sg:city":"Schofield",
    "sg:classifiers":[
        {
            "category":"Professional",
            "subcategory":"Computer Services",
            "type":"Services"
        }
    ],
    "sg:postcode":"54476",
    "sg:province":"WI",
    "sg:tags":[
        "wipes",
        "wet-wipes",
        "cleaning",
        "baby-wipes",
        "household",
        "lens-wipes",
        "antibacterial",
        "hand-wipes",
        "auto-wipes",
        "personal-care",
        "pet-wipes",
        "shoe-wipes",
        "electronic-wipes"
    ],
    "sg:website":"http://www.wipemart.com",
    "wof:name":"Wipemart.com",
    "wof:placetype":"venue"
},
  "geometry": {"coordinates":[-89.602289,44.914524],"type":"Point"}
}