{
  "type": "Feature",
  "properties": {
    "iso:country":"US",
    "sg:address":"6547 Elm Ave",
    "sg:city":"Dorchester",
    "sg:phone":"+1 715 678 2149",
    "sg:postcode":"54425",
    "sg:province":"WI",
    "sg:tags":[
        "farm",
        "field",
        "corn",
        "crop"
    ],
    "wof:name":"Bruce Lewondowski",
    "wof:placetype":"venue"
},
  "geometry": {"coordinates":[-90.383504,45.046533],"type":"Point"}
}