{
  "type": "Feature",
  "properties": {
    "iso:country":"US",
    "sg:address":"24107 State Rd 35",
    "sg:city":"Siren",
    "sg:classifiers":[
        {
            "category":"Building & Trades",
            "subcategory":"Plumbing",
            "type":"Services"
        }
    ],
    "sg:phone":"+1 715 349 2888",
    "sg:postcode":"54872",
    "sg:province":"WI",
    "sg:tags":[
        "heating",
        "contractor"
    ],
    "wof:name":"Joel's Heating",
    "wof:placetype":"venue"
},
  "geometry": {"coordinates":[-92.381061,45.789576],"type":"Point"}
}