{
  "type": "Feature",
  "properties": {
    "iso:country":"US",
    "sg:address":"8753 N 72nd St",
    "sg:city":"Milwaukee",
    "sg:classifiers":[
        {
            "category":"Wholesale",
            "subcategory":"Computers",
            "type":"Manufacturing & Wholesale Goods"
        }
    ],
    "sg:phone":"+1 414 899 8368",
    "sg:postcode":"53223",
    "sg:province":"WI",
    "sg:tags":[
        "equipment"
    ],
    "wof:name":"Computers R Us",
    "wof:placetype":"venue"
},
  "geometry": {"coordinates":[-87.99959,43.176772],"type":"Point"}
}