{
  "type": "Feature",
  "properties": {
    "iso:country":"US",
    "sg:address":"1672 State Hwy 37",
    "sg:city":"Alma",
    "sg:classifiers":[
        {
            "category":"Government",
            "subcategory":"Office",
            "type":"Public Place"
        }
    ],
    "sg:phone":"+1 608 685 3541",
    "sg:postcode":"54610",
    "sg:province":"WI",
    "wof:name":"Highway Shop",
    "wof:placetype":"venue"
},
  "geometry": {"coordinates":[-91.912954,44.352942],"type":"Point"}
}