{
  "type": "Feature",
  "properties": {
    "iso:country":"US",
    "sg:address":"131 N Adams St",
    "sg:city":"Bonduel",
    "sg:classifiers":[
        {
            "category":"Restaurant",
            "type":"Food & Drink"
        }
    ],
    "sg:phone":"+1 715 758 2164",
    "sg:postcode":"54107",
    "sg:province":"WI",
    "wof:name":"Club 117",
    "wof:placetype":"venue"
},
  "geometry": {"coordinates":[-88.43917399999999,44.741172],"type":"Point"}
}