{
  "type": "Feature",
  "properties": {
    "addr:full":"891 Co Rd K Wisconsin Dells WI 53965",
    "addr:housenumber":"891",
    "addr:postcode":"53965",
    "addr:street":"Co Rd",
    "iso:country":"US",
    "sg:address":"891 Co Rd K",
    "sg:city":"Wisconsin Dells",
    "sg:classifiers":[
        {
            "category":"Real Estate",
            "subcategory":"Real Estate Operator",
            "type":"Services"
        }
    ],
    "sg:phone":"+1 608 254 2142",
    "sg:postcode":"53965",
    "sg:province":"WI",
    "sg:tags":[
        "mobile",
        "home",
        "community"
    ],
    "wof:name":"White Pine Ridge Estates",
    "wof:placetype":"venue"
},
  "geometry": {"coordinates":[-89.753975,43.707],"type":"Point"}
}