{
  "type": "Feature",
  "properties": {
    "iso:country":"US",
    "sg:address":"121 Watson St",
    "sg:city":"Ripon",
    "sg:classifiers":[
        {
            "category":"Banks & Credit Unions",
            "subcategory":"Investment Brokerage",
            "type":"Services"
        }
    ],
    "sg:phone":"+1 920 748 5118",
    "sg:postcode":"54971",
    "sg:province":"WI",
    "sg:tags":[
        "stock",
        "bond"
    ],
    "wof:name":"Edward Jones Co",
    "wof:placetype":"venue"
},
  "geometry": {"coordinates":[-88.838847,43.846074],"type":"Point"}
}