{
  "type": "Feature",
  "properties": {
    "iso:country":"US",
    "sg:address":"8207 W Villard Ave",
    "sg:city":"Milwaukee",
    "sg:classifiers":[
        {
            "category":"Health Services",
            "subcategory":"Clinic",
            "type":"Services"
        }
    ],
    "sg:phone":"+1 414 462 6414",
    "sg:postcode":"53218",
    "sg:province":"WI",
    "sg:tags":[
        "specialty",
        "outpatient"
    ],
    "wof:name":"Bellwood Villard",
    "wof:placetype":"venue"
},
  "geometry": {"coordinates":[-88.013351,43.112173],"type":"Point"}
}