{
  "type": "Feature",
  "properties": {
    "iso:country":"US",
    "sg:address":"130 W Maple St",
    "sg:city":"Lancaster",
    "sg:classifiers":[
        {
            "category":"Government",
            "subcategory":"Office",
            "type":"Public Place"
        }
    ],
    "sg:phone":"+1 608 723 6576",
    "sg:postcode":"53813",
    "sg:province":"WI",
    "wof:name":"George Curry",
    "wof:placetype":"venue"
},
  "geometry": {"coordinates":[-90.71050200000001,42.847884],"type":"Point"}
}