{
  "type": "Feature",
  "properties": {
    "iso:country":"US",
    "sg:address":"19550 Pinewood Dr",
    "sg:city":"New Berlin",
    "sg:classifiers":[
        {
            "category":"Professional",
            "subcategory":"Accounting & Tax Preparation",
            "type":"Services"
        }
    ],
    "sg:phone":"+1 262 679 8449",
    "sg:postcode":"53146",
    "sg:province":"WI",
    "sg:tags":[
        "accountant"
    ],
    "wof:name":"Dennis W Novak CPA",
    "wof:placetype":"venue"
},
  "geometry": {"coordinates":[-88.157219,42.953143],"type":"Point"}
}