{
  "type": "Feature",
  "properties": {
    "iso:country":"US",
    "sg:address":"2186 Co Rd Y",
    "sg:city":"Knowles",
    "sg:classifiers":[
        {
            "category":"Banks & Credit Unions",
            "subcategory":"Bank",
            "type":"Services"
        }
    ],
    "sg:phone":"+1 920 583 3626",
    "sg:postcode":"53048",
    "sg:province":"WI",
    "sg:tags":[
        "state",
        "commercial"
    ],
    "wof:name":"American Bank",
    "wof:placetype":"venue"
},
  "geometry": {"coordinates":[-88.504812,43.573031],"type":"Point"}
}