{
  "type": "Feature",
  "properties": {
    "iso:country":"US",
    "sg:address":"4308 Springbrook Ln",
    "sg:city":"Omro",
    "sg:classifiers":[
        {
            "category":"Building & Trades",
            "subcategory":"Construction",
            "type":"Services"
        }
    ],
    "sg:phone":"+1 920 685 6902",
    "sg:postcode":"54963",
    "sg:province":"WI",
    "sg:tags":[
        "contractor"
    ],
    "wof:name":"Zms LLC",
    "wof:placetype":"venue"
},
  "geometry": {"coordinates":[-88.69014,44.048823],"type":"Point"}
}