{
  "type": "Feature",
  "properties": {
    "iso:country":"US",
    "sg:address":"10506 Berberg Rd",
    "sg:city":"Amherst",
    "sg:classifiers":[
        {
            "category":"Professional",
            "subcategory":"Employment Agencies",
            "type":"Services"
        }
    ],
    "sg:phone":"+1 715 824 2255",
    "sg:postcode":"54406",
    "sg:province":"WI",
    "sg:tags":[
        "consultant",
        "search",
        "executive"
    ],
    "wof:name":"Cook & Assoc",
    "wof:placetype":"venue"
},
  "geometry": {"coordinates":[-89.258967,44.468814],"type":"Point"}
}