{
  "type": "Feature",
  "properties": {
    "addr:full":"327 Broadway St Berlin WI 54923",
    "addr:housenumber":"327",
    "addr:postcode":"54923",
    "addr:street":"Broadway St",
    "iso:country":"US",
    "sg:address":"327 Broadway St",
    "sg:city":"Berlin",
    "sg:classifiers":[
        {
            "category":"Autos & Motor Vehicles",
            "subcategory":"Fuel & Gas Station",
            "type":"Retail Goods"
        }
    ],
    "sg:phone":"+1 920 361 2818",
    "sg:postcode":"54923",
    "sg:province":"WI",
    "sg:tags":[
        "oil"
    ],
    "wof:name":"Krause's Mobil",
    "wof:placetype":"venue"
},
  "geometry": {"coordinates":[-88.95570600000001,43.968419],"type":"Point"}
}