{
  "type": "Feature",
  "properties": {
    "addr:full":"1565 Milrod Ln Brookfield WI 53005",
    "addr:housenumber":"1565",
    "addr:postcode":"53005",
    "addr:street":"Milrod Ln",
    "iso:country":"US",
    "sg:address":"1565 Milrod Ln",
    "sg:city":"Brookfield",
    "sg:classifiers":[
        {
            "category":"Real Estate",
            "subcategory":"Real Estate Agent",
            "type":"Services"
        }
    ],
    "sg:phone":"+1 262 860 1121",
    "sg:postcode":"53005",
    "sg:province":"WI",
    "sg:tags":[
        "inspection"
    ],
    "wof:name":"R J R Inspections/Appraisal",
    "wof:placetype":"venue"
},
  "geometry": {"coordinates":[-88.122327,43.052655],"type":"Point"}
}