{
  "type": "Feature",
  "properties": {
    "iso:country":"US",
    "sg:address":"108 E South St",
    "sg:city":"Browntown",
    "sg:classifiers":[
        {
            "category":"Bars & Pubs",
            "type":"Food & Drink"
        }
    ],
    "sg:phone":"+1 608 966 3447",
    "sg:postcode":"53522",
    "sg:province":"WI",
    "sg:tags":[
        "drinking"
    ],
    "wof:name":"Goebels Inn Inc",
    "wof:placetype":"venue"
},
  "geometry": {"coordinates":[-89.794377,42.576951],"type":"Point"}
}