{
  "type": "Feature",
  "properties": {
    "addr:full":"1070 Yarwood Rd Brooklyn WI 53521",
    "addr:postcode":"1070;53521",
    "addr:street":"Yarwood Rd",
    "iso:country":"US",
    "sg:address":"1070 Yarwood Rd",
    "sg:city":"Brooklyn",
    "sg:classifiers":[
        {
            "category":"Building & Trades",
            "subcategory":"Construction",
            "type":"Services"
        }
    ],
    "sg:phone":"+1 608 455 4311",
    "sg:postcode":"53521",
    "sg:province":"WI",
    "sg:tags":[
        "house"
    ],
    "wof:name":"Raineys Residental & Cnstr Clg",
    "wof:placetype":"venue"
},
  "geometry": {"coordinates":[-89.416472,42.813609],"type":"Point"}
}