{
  "type": "Feature",
  "properties": {
    "iso:country":"US",
    "sg:address":"464 S Hickory St",
    "sg:city":"Fond Du Lac",
    "sg:classifiers":[
        {
            "category":"Banks & Credit Unions",
            "subcategory":"Bank",
            "type":"Services"
        }
    ],
    "sg:phone":"+1 920 922 7705",
    "sg:postcode":"54935",
    "sg:province":"WI",
    "sg:tags":[
        "loan"
    ],
    "wof:name":"Assured Mortgage Inc",
    "wof:placetype":"venue"
},
  "geometry": {"coordinates":[-88.462084,43.766471],"type":"Point"}
}