{
  "type": "Feature",
  "properties": {
    "iso:country":"US",
    "sg:address":"726 Sauk Ridge Trl",
    "sg:city":"Madison",
    "sg:classifiers":[
        {
            "category":"Retail",
            "subcategory":"Laundry & Dry Cleaning",
            "type":"Services"
        }
    ],
    "sg:phone":"+1 608 831 1293",
    "sg:postcode":"53705",
    "sg:province":"WI",
    "sg:tags":[
        "cleaners",
        "rug",
        "carpet"
    ],
    "wof:name":"Complete Carpets",
    "wof:placetype":"venue"
},
  "geometry": {"coordinates":[-89.493747,43.076347],"type":"Point"}
}