{
  "type": "Feature",
  "properties": {
    "iso:country":"US",
    "sg:address":"1181 Wauwatosa Rd",
    "sg:city":"Cedarburg",
    "sg:classifiers":[
        {
            "category":"Autos & Motor Vehicles",
            "subcategory":"Automobile Sales",
            "type":"Retail Goods"
        },
        {
            "category":"Retail",
            "subcategory":"Auto Repair",
            "type":"Services"
        }
    ],
    "sg:phone":"+1 262 377 3020",
    "sg:postcode":"53012",
    "sg:province":"WI",
    "sg:tags":[
        "body",
        "shop",
        "car"
    ],
    "wof:name":"Newman Chevrolet-Oldsmoble & Geo",
    "wof:placetype":"venue"
},
  "geometry": {"coordinates":[-88.004898,43.316799],"type":"Point"}
}