{
  "type": "Feature",
  "properties": {
    "iso:country":"US",
    "sg:address":"8243 Jackson St",
    "sg:city":"Pittsville",
    "sg:classifiers":[
        {
            "category":"Health Services",
            "subcategory":"Doctor",
            "type":"Services"
        }
    ],
    "sg:phone":"+1 715 884 6584",
    "sg:postcode":"54466",
    "sg:province":"WI",
    "wof:name":"John N Casey",
    "wof:placetype":"venue"
},
  "geometry": {"coordinates":[-90.127087,44.442477],"type":"Point"}
}