{
  "type": "Feature",
  "properties": {
    "iso:country":"US",
    "sg:address":"2472 S Main St",
    "sg:city":"Rice Lake",
    "sg:classifiers":[
        {
            "category":"Restaurant",
            "type":"Food & Drink"
        }
    ],
    "sg:phone":"+1 715 236 2220",
    "sg:postcode":"54868",
    "sg:province":"WI",
    "sg:tags":[
        "eating"
    ],
    "wof:name":"China Buffet",
    "wof:placetype":"venue"
},
  "geometry": {"coordinates":[-91.735313,45.47552],"type":"Point"}
}