{
  "type": "Feature",
  "properties": {
    "addr:full":"8501 W Lincoln Ave Milwaukee WI 53227",
    "addr:housenumber":"8501",
    "addr:postcode":"53227",
    "addr:street":"W Lincoln Ave",
    "iso:country":"US",
    "sg:address":"8501 W Lincoln Ave",
    "sg:city":"Milwaukee",
    "sg:classifiers":[
        {
            "category":"Health Services",
            "subcategory":"Health Practitioner",
            "type":"Services"
        }
    ],
    "sg:phone":"+1 414 328 8650",
    "sg:postcode":"53227",
    "sg:province":"WI",
    "sg:tags":[
        "midwife"
    ],
    "wof:name":"Cheryl A Jaeger",
    "wof:placetype":"venue"
},
  "geometry": {"coordinates":[-88.01983799999999,43.002728],"type":"Point"}
}