{
  "type": "Feature",
  "properties": {
    "iso:country":"US",
    "sg:address":"101 E Main St",
    "sg:city":"Port Washington",
    "sg:classifiers":[
        {
            "category":"Restaurant",
            "type":"Food & Drink"
        }
    ],
    "sg:phone":"+1 262 377 6195",
    "sg:postcode":"53074",
    "sg:province":"WI",
    "wof:name":"Port Hotel Restaurant & Lounge",
    "wof:placetype":"venue"
},
  "geometry": {"coordinates":[-87.870899,43.388495],"type":"Point"}
}