{
  "type": "Feature",
  "properties": {
    "iso:country":"US",
    "sg:address":"3565 Belgium-Kohler Rd",
    "sg:city":"Fredonia",
    "sg:classifiers":[
        {
            "category":"Building & Trades",
            "subcategory":"Construction",
            "type":"Services"
        }
    ],
    "sg:phone":"+1 262 692 6057",
    "sg:postcode":"53021",
    "sg:province":"WI",
    "sg:tags":[
        "house",
        "improvement",
        "home"
    ],
    "wof:name":"Roy's Home Improvement",
    "wof:placetype":"venue"
},
  "geometry": {"coordinates":[-87.961209,43.491657],"type":"Point"}
}