{
  "type": "Feature",
  "properties": {
    "iso:country":"US",
    "sg:address":"412 W Kinne St",
    "sg:city":"Ellsworth",
    "sg:classifiers":[
        {
            "category":"Government",
            "subcategory":"Office",
            "type":"Public Place"
        }
    ],
    "sg:phone":"+1 715 273 6770",
    "sg:postcode":"54011",
    "sg:province":"WI",
    "sg:tags":[
        "county",
        "program",
        "health"
    ],
    "sg:website":"www.co.pierce.wi.us",
    "wof:name":"Pierce County Mental Health",
    "wof:placetype":"venue"
},
  "geometry": {"coordinates":[-92.485191,44.732988],"type":"Point"}
}