{
  "type": "Feature",
  "properties": {
    "iso:country":"US",
    "sg:address":"128 State St",
    "sg:city":"Oshkosh",
    "sg:classifiers":[
        {
            "category":"Travel",
            "subcategory":"Hotels & Motels",
            "type":"Entertainment"
        }
    ],
    "sg:phone":"+1 920 233 5252",
    "sg:postcode":"54901",
    "sg:province":"WI",
    "wof:name":"State Street Suites",
    "wof:placetype":"venue"
},
  "geometry": {"coordinates":[-88.536452,44.015632],"type":"Point"}
}