{
  "type": "Feature",
  "properties": {
    "iso:country":"US",
    "sg:address":"1621 E Division Ave",
    "sg:city":"Barron",
    "sg:classifiers":[
        {
            "category":"Manufacturing",
            "subcategory":"Tools & Machinery",
            "type":"Manufacturing & Wholesale Goods"
        }
    ],
    "sg:phone":"+1 715 537 9505",
    "sg:postcode":"54812",
    "sg:province":"WI",
    "sg:tags":[
        "farm",
        "equipment"
    ],
    "sg:website":"www.barronsupply.com",
    "wof:name":"Barron Supply Co",
    "wof:placetype":"venue"
},
  "geometry": {"coordinates":[-91.823914,45.401203],"type":"Point"}
}