{
  "type": "Feature",
  "properties": {
    "iso:country":"US",
    "sg:address":"2565 Milton Ave",
    "sg:city":"Janesville",
    "sg:classifiers":[
        {
            "category":"Wholesale",
            "subcategory":"Machinery & Supplies",
            "type":"Manufacturing & Wholesale Goods"
        }
    ],
    "sg:phone":"+1 608 754 1023",
    "sg:postcode":"53545",
    "sg:province":"WI",
    "sg:tags":[
        "salon",
        "beauty"
    ],
    "wof:name":"Victory Beauty Systems",
    "wof:placetype":"venue"
},
  "geometry": {"coordinates":[-89.001857,42.711997],"type":"Point"}
}