{
  "type": "Feature",
  "properties": {
    "iso:country":"US",
    "sg:address":"1413 Mahler Blvd",
    "sg:city":"Neenah",
    "sg:classifiers":[
        {
            "category":"Health Services",
            "subcategory":"Clinic",
            "type":"Services"
        }
    ],
    "sg:phone":"+1 920 886 3615",
    "sg:postcode":"54956",
    "sg:province":"WI",
    "sg:tags":[
        "agency",
        "welfare"
    ],
    "wof:name":"Easter Seals Wisconsin Inc",
    "wof:placetype":"venue"
},
  "geometry": {"coordinates":[-88.45813099999999,44.158699],"type":"Point"}
}