{
  "type": "Feature",
  "properties": {
    "iso:country":"US",
    "sg:address":"1850 N Silverspring Dr",
    "sg:city":"Appleton",
    "sg:classifiers":[
        {
            "category":"Professional",
            "subcategory":"Business Services",
            "type":"Services"
        }
    ],
    "sg:phone":"+1 920 380 1170",
    "sg:postcode":"54913",
    "sg:province":"WI",
    "sg:tags":[
        "establishment"
    ],
    "wof:name":"Bobcat of Appelton",
    "wof:placetype":"venue"
},
  "geometry": {"coordinates":[-88.48233399999999,44.277183],"type":"Point"}
}