{
  "type": "Feature",
  "properties": {
    "iso:country":"US",
    "sg:address":"828 Cherry St",
    "sg:city":"Green Bay",
    "sg:classifiers":[
        {
            "category":"Professional",
            "subcategory":"Accounting & Tax Preparation",
            "type":"Services"
        }
    ],
    "sg:phone":"+1 920 469 9301",
    "sg:postcode":"54301",
    "sg:province":"WI",
    "wof:name":"Allcox & Associates",
    "wof:placetype":"venue"
},
  "geometry": {"coordinates":[-88.00588999999999,44.511856],"type":"Point"}
}