{
  "type": "Feature",
  "properties": {
    "iso:country":"US",
    "sg:address":"652 Commerce Dr",
    "sg:city":"Hudson",
    "sg:classifiers":[
        {
            "category":"Building & Trades",
            "subcategory":"Construction",
            "type":"Services"
        }
    ],
    "sg:phone":"+1 715 386 1200",
    "sg:postcode":"54016",
    "sg:province":"WI",
    "sg:tags":[
        "contractor"
    ],
    "wof:name":"Stcroix Insulation",
    "wof:placetype":"venue"
},
  "geometry": {"coordinates":[-92.670152,44.966407],"type":"Point"}
}