{
  "type": "Feature",
  "properties": {
    "iso:country":"US",
    "sg:address":"2355 US Hwy 18",
    "sg:city":"Helenville",
    "sg:classifiers":[
        {
            "category":"Freight",
            "type":"Transportation"
        }
    ],
    "sg:phone":"+1 262 593 8074",
    "sg:postcode":"53137",
    "sg:province":"WI",
    "sg:tags":[
        "commercial",
        "storage"
    ],
    "wof:name":"Easy Stor",
    "wof:placetype":"venue"
},
  "geometry": {"coordinates":[-88.642161,43.011433],"type":"Point"}
}