{
  "type": "Feature",
  "properties": {
    "iso:country":"US",
    "sg:address":"410 N 4th Ave",
    "sg:city":"Sturgeon Bay",
    "sg:classifiers":[
        {
            "category":"Travel",
            "subcategory":"Hotels & Motels",
            "type":"Entertainment"
        }
    ],
    "sg:phone":"+1 920 746 9776",
    "sg:postcode":"54235",
    "sg:province":"WI",
    "sg:tags":[
        "breakfast",
        "accommodation",
        "bed"
    ],
    "wof:name":"Pembrooke Inn",
    "wof:placetype":"venue"
},
  "geometry": {"coordinates":[-87.378875,44.841435],"type":"Point"}
}