{
  "type": "Feature",
  "properties": {
    "iso:country":"US",
    "sg:address":"1801 State Hwy 59",
    "sg:city":"Middleton",
    "sg:classifiers":[
        {
            "category":"Travel",
            "subcategory":"Hotels & Motels",
            "type":"Entertainment"
        }
    ],
    "sg:phone":"+1 608 868 7833",
    "sg:postcode":"53502",
    "sg:province":"WI",
    "sg:tags":[
        "inn"
    ],
    "wof:name":"Tx4 Country Side Inn",
    "wof:placetype":"venue"
},
  "geometry": {"coordinates":[-89.45124,42.697375],"type":"Point"}
}