{
  "type": "Feature",
  "properties": {
    "addr:full":"491 Flambeau Ave Phillips WI 54555",
    "addr:housenumber":"491",
    "addr:postcode":"54555",
    "addr:street":"Flambeau Ave",
    "iso:country":"US",
    "sg:address":"491 Flambeau Ave",
    "sg:city":"Phillips",
    "sg:classifiers":[
        {
            "category":"Shopping",
            "subcategory":"Used Merchandise",
            "type":"Retail Goods"
        }
    ],
    "sg:phone":"+1 715 339 4373",
    "sg:postcode":"54555",
    "sg:province":"WI",
    "sg:tags":[
        "second",
        "store",
        "hand"
    ],
    "wof:name":"Second Time Around",
    "wof:placetype":"venue"
},
  "geometry": {"coordinates":[-90.406156,45.691915],"type":"Point"}
}