{
  "type": "Feature",
  "properties": {
    "addr:full":"2520 Todd Dr Madison WI 53713",
    "addr:housenumber":"2520",
    "addr:postcode":"53713",
    "addr:street":"Todd Dr",
    "iso:country":"US",
    "sg:address":"2520 Todd Dr",
    "sg:city":"Madison",
    "sg:classifiers":[
        {
            "category":"Utilities",
            "subcategory":"Cable",
            "type":"Services"
        }
    ],
    "sg:phone":"+1 608 271 6999",
    "sg:postcode":"53713",
    "sg:province":"WI",
    "sg:tags":[
        "wireless",
        "satellite",
        "including"
    ],
    "wof:name":"Sky Cable T V",
    "wof:placetype":"venue"
},
  "geometry": {"coordinates":[-89.42268900000001,43.036843],"type":"Point"}
}