{
  "type": "Feature",
  "properties": {
    "iso:country":"US",
    "sg:address":"1297 Badger Rd",
    "sg:city":"Kaukauna",
    "sg:classifiers":[
        {
            "category":"Building & Trades",
            "subcategory":"Equipment Rental",
            "type":"Services"
        }
    ],
    "sg:phone":"+1 920 766 9199",
    "sg:postcode":"54130",
    "sg:province":"WI",
    "sg:tags":[
        "medical"
    ],
    "wof:name":"Kinetic Concepts Inc",
    "wof:placetype":"venue"
},
  "geometry": {"coordinates":[-88.265125,44.295067],"type":"Point"}
}