{
  "type": "Feature",
  "properties": {
    "iso:country":"US",
    "sg:address":"6210 Mineral Point Rd",
    "sg:city":"Madison",
    "sg:classifiers":[
        {
            "category":"Real Estate",
            "subcategory":"Real Estate Operator",
            "type":"Services"
        }
    ],
    "sg:phone":"+1 608 233 7403",
    "sg:postcode":"53705",
    "sg:province":"WI",
    "sg:tags":[
        "building",
        "apartment"
    ],
    "wof:name":"Isle of View Apts",
    "wof:placetype":"venue"
},
  "geometry": {"coordinates":[-89.48853,43.060885],"type":"Point"}
}