{
  "type": "Feature",
  "properties": {
    "addr:full":"72 W Waukau Ave Oshkosh WI 54902",
    "addr:housenumber":"72",
    "addr:postcode":"54902",
    "addr:street":"W Waukau Ave",
    "iso:country":"US",
    "sg:address":"72 W Waukau Ave",
    "sg:city":"Oshkosh",
    "sg:classifiers":[
        {
            "category":"Farming",
            "subcategory":"Nursery",
            "type":"Manufacturing & Wholesale Goods"
        }
    ],
    "sg:phone":"+1 920 235 3630",
    "sg:postcode":"54902",
    "sg:province":"WI",
    "sg:tags":[
        "ornamental",
        "landscape"
    ],
    "wof:name":"Roe Nurseries Inc",
    "wof:placetype":"venue"
},
  "geometry": {"coordinates":[-88.533253,43.981091],"type":"Point"}
}