{
  "type": "Feature",
  "properties": {
    "iso:country":"US",
    "sg:address":"155 Griffith St",
    "sg:city":"Fond Du Lac",
    "sg:classifiers":[
        {
            "category":"Building & Trades",
            "subcategory":"Landscaping Services",
            "type":"Services"
        }
    ],
    "sg:phone":"+1 920 921 4353",
    "sg:postcode":"54935",
    "sg:province":"WI",
    "sg:tags":[
        "lawn",
        "maintenance",
        "grounds"
    ],
    "wof:name":"Kohnke's Lawn Care",
    "wof:placetype":"venue"
},
  "geometry": {"coordinates":[-88.452946,43.764556],"type":"Point"}
}