{
  "type": "Feature",
  "properties": {
    "addr:full":"1962 N Prospect Ave Milwaukee WI 53202",
    "addr:housenumber":"1962",
    "addr:postcode":"53202",
    "addr:street":"N Prospect Ave",
    "iso:country":"US",
    "sg:address":"1962 N Prospect Ave",
    "sg:city":"Milwaukee",
    "sg:classifiers":[
        {
            "category":"Health Services",
            "subcategory":"Doctor",
            "type":"Services"
        }
    ],
    "sg:phone":"+1 414 803 2721",
    "sg:postcode":"53202",
    "sg:province":"WI",
    "sg:tags":[
        "physician",
        "surgeon",
        "kidneys",
        "surgeons",
        "nephrology"
    ],
    "wof:name":"Wisconsin Vascular Access And Nephrology",
    "wof:placetype":"venue"
},
  "geometry": {"coordinates":[-87.88799899999999,43.055783],"type":"Point"}
}