{
  "type": "Feature",
  "properties": {
    "iso:country":"US",
    "sg:address":"1 N Bridge St",
    "sg:city":"Chippewa Falls",
    "sg:classifiers":[
        {
            "category":"Professional",
            "subcategory":"Engineering",
            "type":"Services"
        }
    ],
    "sg:phone":"+1 715 723 6777",
    "sg:postcode":"54729",
    "sg:province":"WI",
    "sg:tags":[
        "engineer"
    ],
    "sg:website":"www.tiryengineering.com",
    "wof:name":"Tiry Engineering Inc",
    "wof:placetype":"venue"
},
  "geometry": {"coordinates":[-91.391525,44.935679],"type":"Point"}
}