{
  "type": "Feature",
  "properties": {
    "addr:full":"5215 N Ironwood Ln Milwaukee WI 53217",
    "addr:housenumber":"5215",
    "addr:postcode":"53217",
    "addr:street":"N Ironwood Ln",
    "iso:country":"US",
    "sg:address":"5215 N Ironwood Ln",
    "sg:city":"Milwaukee",
    "sg:classifiers":[
        {
            "category":"Professional",
            "type":"Services"
        }
    ],
    "sg:phone":"+1 414 906 9282",
    "sg:postcode":"53217",
    "sg:province":"WI",
    "sg:tags":[
        "technical",
        "preparation",
        "manual"
    ],
    "wof:name":"Vital Wave Technologies",
    "wof:placetype":"venue"
},
  "geometry": {"coordinates":[-87.91767,43.143319],"type":"Point"}
}