{
  "type": "Feature",
  "properties": {
    "iso:country":"US",
    "sg:address":"12358 Co Hwy Q",
    "sg:city":"Bloomer",
    "sg:phone":"+1 715 288 6279",
    "sg:postcode":"54724",
    "sg:province":"WI",
    "sg:tags":[
        "farm",
        "grain",
        "cash",
        "animal",
        "general"
    ],
    "wof:name":"William Pickerign",
    "wof:placetype":"venue"
},
  "geometry": {"coordinates":[-91.44841599999999,45.025318],"type":"Point"}
}