{
  "type": "Feature",
  "properties": {
    "iso:country":"US",
    "sg:address":"5050 Lake Rd",
    "sg:city":"Oshkosh",
    "sg:classifiers":[
        {
            "category":"Real Estate",
            "subcategory":"Real Estate Agent",
            "type":"Services"
        }
    ],
    "sg:phone":"+1 920 233 3732",
    "sg:postcode":"54902",
    "sg:province":"WI",
    "wof:name":"Vette Properties Management LL",
    "wof:placetype":"venue"
},
  "geometry": {"coordinates":[-88.482254,43.943441],"type":"Point"}
}