{
  "type": "Feature",
  "properties": {
    "addr:full":"1751 Center St Racine WI 53403",
    "addr:housenumber":"1751",
    "addr:postcode":"53403",
    "addr:street":"Center St",
    "iso:country":"US",
    "sg:address":"1751 Center St",
    "sg:city":"Racine",
    "sg:classifiers":[
        {
            "category":"Organizations",
            "subcategory":"Professional Association",
            "type":"Services"
        }
    ],
    "sg:phone":"+1 262 636 9285",
    "sg:postcode":"53403",
    "sg:province":"WI",
    "wof:name":"Racine Symphony Orchestra Assn",
    "wof:placetype":"venue"
},
  "geometry": {"coordinates":[-87.789152,42.710012],"type":"Point"}
}