{
  "type": "Feature",
  "properties": {
    "iso:country":"US",
    "sg:address":"6012 248th Ave",
    "sg:city":"Salem",
    "sg:classifiers":[
        {
            "category":"Health Services",
            "subcategory":"Clinic",
            "type":"Services"
        }
    ],
    "sg:phone":"+1 262 553 1836",
    "sg:postcode":"53168",
    "sg:province":"WI",
    "wof:name":"Corporate Health Concepts",
    "wof:placetype":"venue"
},
  "geometry": {"coordinates":[-88.109116,42.582381],"type":"Point"}
}