{
  "type": "Feature",
  "properties": {
    "iso:country":"US",
    "sg:address":"1114 Hubbard Ct",
    "sg:city":"Oconomowoc",
    "sg:classifiers":[
        {
            "category":"Building & Trades",
            "subcategory":"Construction",
            "type":"Services"
        }
    ],
    "sg:phone":"+1 262 569 2963",
    "sg:postcode":"53066",
    "sg:province":"WI",
    "sg:tags":[
        "house"
    ],
    "wof:name":"Gregg Laffin Builders LLC",
    "wof:placetype":"venue"
},
  "geometry": {"coordinates":[-88.517725,43.116329],"type":"Point"}
}