{
  "type": "Feature",
  "properties": {
    "iso:country":"US",
    "sg:address":"6111 Co Rd A",
    "sg:city":"New Lisbon",
    "sg:classifiers":[
        {
            "category":"Autos & Motor Vehicles",
            "subcategory":"Boat Sales",
            "type":"Retail Goods"
        }
    ],
    "sg:phone":"+1 608 562 5977",
    "sg:postcode":"53950",
    "sg:province":"WI",
    "sg:tags":[
        "dealer",
        "sales"
    ],
    "wof:name":"Smith's II Marine",
    "wof:placetype":"venue"
},
  "geometry": {"coordinates":[-90.073089,43.9085],"type":"Point"}
}