{
  "type": "Feature",
  "properties": {
    "iso:country":"US",
    "sg:address":"308 S Shawano St",
    "sg:city":"New London",
    "sg:classifiers":[
        {
            "category":"Food & Beverages",
            "subcategory":"Groceries & Convenience Stores",
            "type":"Retail Goods"
        }
    ],
    "sg:phone":"+1 920 982 9835",
    "sg:postcode":"54961",
    "sg:province":"WI",
    "sg:tags":[
        "independent",
        "supermarket"
    ],
    "wof:name":"Festival Foods",
    "wof:placetype":"venue"
},
  "geometry": {"coordinates":[-88.745312,44.390718],"type":"Point"}
}