{
  "type": "Feature",
  "properties": {
    "iso:country":"US",
    "sg:address":"2723 Martin Dr",
    "sg:city":"Medford",
    "sg:classifiers":[
        {
            "category":"Banks & Credit Unions",
            "subcategory":"Investment Brokerage",
            "type":"Services"
        }
    ],
    "sg:phone":"+1 715 748 3283",
    "sg:postcode":"54451",
    "sg:province":"WI",
    "sg:tags":[
        "advisory",
        "financial"
    ],
    "wof:name":"Peche Agency Financial West",
    "wof:placetype":"venue"
},
  "geometry": {"coordinates":[-90.12600500000001,45.124813],"type":"Point"}
}