{
  "type": "Feature",
  "properties": {
    "iso:country":"US",
    "sg:address":"340 Black Bridge Rd",
    "sg:city":"Janesville",
    "sg:classifiers":[
        {
            "category":"Utilities",
            "subcategory":"Refuse",
            "type":"Services"
        },
        {
            "category":"Wholesale",
            "subcategory":"Scrap",
            "type":"Manufacturing & Wholesale Goods"
        }
    ],
    "sg:phone":"+1 608 756 0001",
    "sg:postcode":"53545",
    "sg:province":"WI",
    "sg:tags":[
        "recycling",
        "material",
        "center",
        "system"
    ],
    "wof:name":"Janesville Recycling Center",
    "wof:placetype":"venue"
},
  "geometry": {"coordinates":[-89.02748,42.704605],"type":"Point"}
}