{
  "type": "Feature",
  "properties": {
    "iso:country":"US",
    "sg:address":"330 N Mall Dr",
    "sg:city":"Appleton",
    "sg:classifiers":[
        {
            "category":"Shopping",
            "subcategory":"Jewelry",
            "type":"Retail Goods"
        }
    ],
    "sg:phone":"+1 920 734 8747",
    "sg:postcode":"54913",
    "sg:province":"WI",
    "wof:name":"Uffenbeck Diamonds Ltd",
    "wof:placetype":"venue"
},
  "geometry": {"coordinates":[-88.473277,44.264742],"type":"Point"}
}