{
  "type": "Feature",
  "properties": {
    "iso:country":"US",
    "sg:address":"10701 W Lincoln Ave",
    "sg:city":"Milwaukee",
    "sg:classifiers":[
        {
            "category":"Health Services",
            "subcategory":"Doctor",
            "type":"Services"
        }
    ],
    "sg:phone":"+1 414 545 9090",
    "sg:postcode":"53227",
    "sg:province":"WI",
    "wof:name":"Dennis R Anderson DDS",
    "wof:placetype":"venue"
},
  "geometry": {"coordinates":[-88.046927,43.002577],"type":"Point"}
}