{
  "type": "Feature",
  "properties": {
    "addr:full":"2215 State Hwy 83 Hartland WI 53029",
    "addr:housenumber":"2215",
    "addr:postcode":"53029",
    "addr:street":"State Hwy 83",
    "iso:country":"US",
    "sg:address":"2215 State Hwy 83",
    "sg:city":"Hartland",
    "sg:classifiers":[
        {
            "category":"Education",
            "subcategory":"Special Training",
            "type":"Public Place"
        }
    ],
    "sg:phone":"+1 262 369 9490",
    "sg:postcode":"53029",
    "sg:province":"WI",
    "sg:tags":[
        "merchandise"
    ],
    "wof:name":"Art DAngel",
    "wof:placetype":"venue"
},
  "geometry": {"coordinates":[-88.36336300000001,43.081131],"type":"Point"}
}