{
  "type": "Feature",
  "properties": {
    "iso:country":"US",
    "sg:address":"506 Riverview Ct",
    "sg:city":"De Forest",
    "sg:classifiers":[
        {
            "category":"Restaurant",
            "type":"Food & Drink"
        }
    ],
    "sg:phone":"+1 608 846 9159",
    "sg:postcode":"53532",
    "sg:province":"WI",
    "sg:tags":[
        "eating"
    ],
    "wof:name":"Tonys",
    "wof:placetype":"venue"
},
  "geometry": {"coordinates":[-89.353885,43.240407],"type":"Point"}
}