{
  "type": "Feature",
  "properties": {
    "iso:country":"US",
    "sg:address":"11541 N Laguna Dr",
    "sg:city":"Thiensville",
    "sg:classifiers":[
        {
            "category":"Retail",
            "subcategory":"Repair Shop",
            "type":"Services"
        }
    ],
    "sg:phone":"+1 262 242 0977",
    "sg:postcode":"53092",
    "sg:province":"WI",
    "wof:name":"Showtime Shoeing LLC",
    "wof:placetype":"venue"
},
  "geometry": {"coordinates":[-87.93678300000001,43.227965],"type":"Point"}
}