{
  "type": "Feature",
  "properties": {
    "iso:country":"US",
    "sg:address":"1003 Pleasant St",
    "sg:city":"Beloit",
    "sg:classifiers":[
        {
            "category":"Organizations",
            "subcategory":"Membership Organization",
            "type":"Services"
        }
    ],
    "sg:phone":"+1 608 362 0964",
    "sg:postcode":"53511",
    "sg:province":"WI",
    "wof:name":"Friends Of Riverfront",
    "wof:placetype":"venue"
},
  "geometry": {"coordinates":[-89.031844,42.505426],"type":"Point"}
}