{
  "type": "Feature",
  "properties": {
    "iso:country":"US",
    "sg:address":"1025 S 3rd Ave",
    "sg:city":"Wausau",
    "sg:classifiers":[
        {
            "category":"Bars & Pubs",
            "type":"Food & Drink"
        }
    ],
    "sg:phone":"+1 715 849 8696",
    "sg:postcode":"54401",
    "sg:province":"WI",
    "sg:tags":[
        "drinking"
    ],
    "wof:name":"Bar & Grill",
    "wof:placetype":"venue"
},
  "geometry": {"coordinates":[-89.639279,44.948812],"type":"Point"}
}