{
  "type": "Feature",
  "properties": {
    "iso:country":"US",
    "sg:address":"6208 Tatro Rd",
    "sg:city":"Bruce",
    "sg:classifiers":[
        {
            "category":"Wholesale",
            "subcategory":"Machinery & Supplies",
            "type":"Manufacturing & Wholesale Goods"
        }
    ],
    "sg:phone":"+1 715 868 5211",
    "sg:postcode":"54819",
    "sg:province":"WI",
    "sg:tags":[
        "equipment",
        "industrial"
    ],
    "wof:name":"LP Scientific",
    "wof:placetype":"venue"
},
  "geometry": {"coordinates":[-91.297471,45.513753],"type":"Point"}
}