{
  "type": "Feature",
  "properties": {
    "iso:country":"US",
    "sg:address":"12885 Elmhurst Pkwy",
    "sg:city":"Elm Grove",
    "sg:classifiers":[
        {
            "category":"Home & Garden",
            "subcategory":"Furniture",
            "type":"Retail Goods"
        }
    ],
    "sg:phone":"+1 262 782 4253",
    "sg:postcode":"53122",
    "sg:province":"WI",
    "wof:name":"Electropedic Adjustable Beds",
    "wof:placetype":"venue"
},
  "geometry": {"coordinates":[-88.071119,43.050546],"type":"Point"}
}