{
  "type": "Feature",
  "properties": {
    "iso:country":"US",
    "sg:address":"6745 Co Rd A",
    "sg:city":"Amherst",
    "sg:classifiers":[
        {
            "category":"Building & Trades",
            "subcategory":"Construction",
            "type":"Services"
        }
    ],
    "sg:phone":"+1 715 824 6285",
    "sg:postcode":"54406",
    "sg:province":"WI",
    "sg:tags":[
        "contractor"
    ],
    "wof:name":"Lanark Contracting LLC",
    "wof:placetype":"venue"
},
  "geometry": {"coordinates":[-89.324684,44.369483],"type":"Point"}
}