{
  "type": "Feature",
  "properties": {
    "iso:country":"US",
    "sg:address":"1040 Indianhead Dr",
    "sg:city":"Mosinee",
    "sg:classifiers":[
        {
            "category":"Utilities",
            "subcategory":"Refuse",
            "type":"Services"
        }
    ],
    "sg:phone":"+1 715 693 7123",
    "sg:postcode":"54455",
    "sg:province":"WI",
    "sg:tags":[
        "stationery",
        "garbage",
        "collection",
        "system"
    ],
    "wof:name":"Industrial Recyclers Of Wi",
    "wof:placetype":"venue"
},
  "geometry": {"coordinates":[-89.66921600000001,44.793205],"type":"Point"}
}