{
  "type": "Feature",
  "properties": {
    "iso:country":"US",
    "sg:address":"1000 3rd St",
    "sg:city":"Menasha",
    "sg:classifiers":[
        {
            "category":"Autos & Motor Vehicles",
            "subcategory":"Motorcycle Sales",
            "type":"Retail Goods"
        }
    ],
    "sg:phone":"+1 920 725 2416",
    "sg:postcode":"54952",
    "sg:province":"WI",
    "wof:name":"Metro Motorcycles Inc",
    "wof:placetype":"venue"
},
  "geometry": {"coordinates":[-88.423489,44.205593],"type":"Point"}
}