{
  "type": "Feature",
  "properties": {
    "addr:full":"9007 State Hwy 91 Berlin WI 54923",
    "addr:housenumber":"9007",
    "addr:postcode":"54923",
    "addr:street":"State Hwy 91",
    "iso:country":"US",
    "sg:address":"9007 State Hwy 91",
    "sg:city":"Berlin",
    "sg:classifiers":[
        {
            "category":"Retail",
            "subcategory":"Auto Repair",
            "type":"Services"
        }
    ],
    "sg:phone":"+1 920 361 3200",
    "sg:postcode":"54923",
    "sg:province":"WI",
    "sg:tags":[
        "body",
        "automobile",
        "painting"
    ],
    "wof:name":"Le Dioyt Enterprises",
    "wof:placetype":"venue"
},
  "geometry": {"coordinates":[-88.84992200000001,43.967712],"type":"Point"}
}