{
  "type": "Feature",
  "properties": {
    "addr:full":"5225 Johnson Rd Superior WI 54880",
    "addr:housenumber":"5225",
    "addr:postcode":"54880",
    "addr:street":"Johnson Rd",
    "iso:country":"US",
    "sg:address":"5225 Johnson Rd",
    "sg:city":"Superior",
    "sg:classifiers":[
        {
            "category":"Restaurant",
            "type":"Food & Drink"
        }
    ],
    "sg:phone":"+1 715 398 6850",
    "sg:postcode":"54880",
    "sg:province":"WI",
    "sg:tags":[
        "eating"
    ],
    "wof:name":"Betty S Country Catering",
    "wof:placetype":"venue"
},
  "geometry": {"coordinates":[-92.02923,46.575904],"type":"Point"}
}