{
  "type": "Feature",
  "properties": {
    "addr:full":"424 3rd St Walworth WI 53184",
    "addr:housenumber":"424",
    "addr:postcode":"53184",
    "addr:street":"3Rd St",
    "iso:country":"US",
    "sg:address":"424 3rd St",
    "sg:city":"Walworth",
    "sg:classifiers":[
        {
            "category":"Personal",
            "subcategory":"Beauty Salon",
            "type":"Services"
        }
    ],
    "sg:phone":"+1 262 275 5543",
    "sg:postcode":"53184",
    "sg:province":"WI",
    "sg:tags":[
        "shop"
    ],
    "wof:name":"A Cut Above",
    "wof:placetype":"venue"
},
  "geometry": {"coordinates":[-88.59252499999999,42.528969],"type":"Point"}
}