{
  "type": "Feature",
  "properties": {
    "iso:country":"US",
    "sg:address":"1192 Washington Rd",
    "sg:city":"Stoughton",
    "sg:classifiers":[
        {
            "category":"Building & Trades",
            "subcategory":"Construction",
            "type":"Services"
        }
    ],
    "sg:phone":"+1 608 873 5865",
    "sg:postcode":"53589",
    "sg:province":"WI",
    "sg:tags":[
        "house"
    ],
    "wof:name":"Cornell Construction",
    "wof:placetype":"venue"
},
  "geometry": {"coordinates":[-89.13181,42.912389],"type":"Point"}
}