{
  "type": "Feature",
  "properties": {
    "iso:country":"US",
    "sg:address":"622 N Water St",
    "sg:city":"Milwaukee",
    "sg:classifiers":[
        {
            "category":"Professional",
            "subcategory":"Lawyer & Legal Services",
            "type":"Services"
        }
    ],
    "sg:phone":"+1 414 273 3939",
    "sg:postcode":"53202",
    "sg:province":"WI",
    "sg:tags":[
        "attorney"
    ],
    "wof:name":"Fox ONeill & Shannon SC",
    "wof:placetype":"venue"
},
  "geometry": {"coordinates":[-87.909018,43.038304],"type":"Point"}
}