{
  "type": "Feature",
  "properties": {
    "iso:country":"US",
    "sg:address":"4715 King Rd",
    "sg:city":"Rio",
    "sg:phone":"+1 920 992 3462",
    "sg:postcode":"53960",
    "sg:province":"WI",
    "sg:tags":[
        "farm",
        "grain",
        "cash",
        "soybean"
    ],
    "wof:name":"Reierson Farm",
    "wof:placetype":"venue"
},
  "geometry": {"coordinates":[-89.23417600000001,43.398358],"type":"Point"}
}