{
  "type": "Feature",
  "properties": {
    "iso:country":"US",
    "sg:address":"100 W Division St",
    "sg:city":"Fond Du Lac",
    "sg:classifiers":[
        {
            "category":"Retail",
            "subcategory":"Repair Shop",
            "type":"Services"
        }
    ],
    "sg:phone":"+1 920 922 4810",
    "sg:postcode":"54935",
    "sg:province":"WI",
    "wof:name":"Bob Voskuil Antenna Service",
    "wof:placetype":"venue"
},
  "geometry": {"coordinates":[-88.451946,43.778878],"type":"Point"}
}