{
  "type": "Feature",
  "properties": {
    "iso:country":"US",
    "sg:address":"6835 30th Ave",
    "sg:city":"Kenosha",
    "sg:classifiers":[
        {
            "category":"Professional",
            "type":"Services"
        }
    ],
    "sg:phone":"+1 262 654 2480",
    "sg:postcode":"53142",
    "sg:province":"IL",
    "sg:tags":[
        "establishment"
    ],
    "wof:name":"Kenosha Frame",
    "wof:placetype":"venue"
},
  "geometry": {"coordinates":[-87.845247,42.570231],"type":"Point"}
}