{
  "type": "Feature",
  "properties": {
    "iso:country":"US",
    "sg:address":"3998 Lincoln Dr",
    "sg:city":"Lake Geneva",
    "sg:classifiers":[
        {
            "category":"Building & Trades",
            "subcategory":"Cleaning & Sanitation",
            "type":"Services"
        }
    ],
    "sg:phone":"+1 262 248 1986",
    "sg:postcode":"53147",
    "sg:province":"WI",
    "sg:tags":[
        "maintenance"
    ],
    "wof:name":"Offiserve Cleaning",
    "wof:placetype":"venue"
},
  "geometry": {"coordinates":[-88.496668,42.608359],"type":"Point"}
}