{
  "type": "Feature",
  "properties": {
    "iso:country":"US",
    "sg:address":"1534 Sylmar Rd",
    "sg:city":"Cedarburg",
    "sg:classifiers":[
        {
            "category":"Communications",
            "subcategory":"Film & Video Production",
            "type":"Services"
        }
    ],
    "sg:phone":"+1 262 373 0376",
    "sg:postcode":"53012",
    "sg:province":"WI",
    "sg:tags":[
        "taping"
    ],
    "wof:name":"Wessel Productions",
    "wof:placetype":"venue"
},
  "geometry": {"coordinates":[-87.998484,43.331201],"type":"Point"}
}