{
  "type": "Feature",
  "properties": {
    "addr:full":"429 E Co Rd A Stetsonville WI 54480",
    "addr:housenumber":"429",
    "addr:postcode":"54480",
    "addr:street":"E Co Rd A Stetsonville",
    "iso:country":"US",
    "sg:address":"429 E Co Rd A",
    "sg:city":"Stetsonville",
    "sg:classifiers":[
        {
            "category":"Retail",
            "subcategory":"Repair Shop",
            "type":"Services"
        }
    ],
    "sg:phone":"+1 715 678 2315",
    "sg:postcode":"54480",
    "sg:province":"WI",
    "sg:tags":[
        "snowplowing",
        "welding"
    ],
    "wof:name":"Henrichs Welding & Snowplowing",
    "wof:placetype":"venue"
},
  "geometry": {"coordinates":[-90.310056,45.076841],"type":"Point"}
}