{
  "type": "Feature",
  "properties": {
    "iso:country":"US",
    "sg:address":"5205 N Lydell Ave",
    "sg:city":"Milwaukee",
    "sg:classifiers":[
        {
            "category":"Government",
            "subcategory":"Office",
            "type":"Public Place"
        }
    ],
    "sg:phone":"+1 414 963 3947",
    "sg:postcode":"53217",
    "sg:province":"WI",
    "sg:tags":[
        "village"
    ],
    "wof:name":"Whitefish Bay Schls Rcrtn Dept",
    "wof:placetype":"venue"
},
  "geometry": {"coordinates":[-87.911919,43.112646],"type":"Point"}
}