{
  "type": "Feature",
  "properties": {
    "addr:full":"103 Franklin St Walworth WI 53184",
    "addr:housenumber":"103",
    "addr:postcode":"53184",
    "addr:street":"Franklin St",
    "iso:country":"US",
    "sg:address":"103 Franklin St",
    "sg:city":"Walworth",
    "sg:classifiers":[
        {
            "category":"Wholesale",
            "subcategory":"Metals & Minerals",
            "type":"Manufacturing & Wholesale Goods"
        }
    ],
    "sg:phone":"+1 262 275 0888",
    "sg:postcode":"53184",
    "sg:province":"WI",
    "wof:name":"White Swan Fine Pewter",
    "wof:placetype":"venue"
},
  "geometry": {"coordinates":[-88.597605,42.535283],"type":"Point"}
}