{
  "type": "Feature",
  "properties": {
    "iso:country":"US",
    "sg:address":"2028 Maryland Ave",
    "sg:city":"Sheboygan",
    "sg:classifiers":[
        {
            "category":"Wholesale",
            "subcategory":"Machinery & Supplies",
            "type":"Manufacturing & Wholesale Goods"
        }
    ],
    "sg:phone":"+1 920 208 7090",
    "sg:postcode":"53081",
    "sg:province":"WI",
    "sg:tags":[
        "equipment",
        "industrial"
    ],
    "wof:name":"Castle Controls & Automation",
    "wof:placetype":"venue"
},
  "geometry": {"coordinates":[-87.734233,43.745496],"type":"Point"}
}