{
  "type": "Feature",
  "properties": {
    "iso:country":"US",
    "sg:address":"2765 Country View Rd",
    "sg:city":"Verona",
    "sg:classifiers":[
        {
            "category":"Retail",
            "subcategory":"Auto Repair",
            "type":"Services"
        }
    ],
    "sg:phone":"+1 608 845 9403",
    "sg:postcode":"53593",
    "sg:province":"WI",
    "sg:tags":[
        "truck",
        "general"
    ],
    "wof:name":"Drz Enterprises LLC",
    "wof:placetype":"venue"
},
  "geometry": {"coordinates":[-89.574252,42.993845],"type":"Point"}
}