{
  "type": "Feature",
  "properties": {
    "iso:country":"US",
    "sg:address":"210 N Henry St",
    "sg:city":"Madison",
    "sg:classifiers":[
        {
            "category":"Professional",
            "type":"Services"
        },
        {
            "category":"Shopping",
            "type":"Retail Goods"
        }
    ],
    "sg:phone":"+1 608 255 3422",
    "sg:postcode":"53703",
    "sg:province":"WI",
    "sg:tags":[
        "amber",
        "art",
        "gallery",
        "production",
        "import",
        "dealer"
    ],
    "wof:name":"Art Saint Ann Gallery",
    "wof:placetype":"venue"
},
  "geometry": {"coordinates":[-89.38991799999999,43.074641],"type":"Point"}
}