{
  "type": "Feature",
  "properties": {
    "addr:full":"2211 E Clairemont Ave Eau Claire WI 54701",
    "addr:housenumber":"2211",
    "addr:postcode":"54701",
    "addr:street":"E Clairemont Ave",
    "iso:country":"US",
    "sg:address":"2211 E Clairemont Ave",
    "sg:city":"Eau Claire",
    "sg:classifiers":[
        {
            "category":"Professional",
            "subcategory":"Accounting & Tax Preparation",
            "type":"Services"
        }
    ],
    "sg:phone":"+1 715 836 0907",
    "sg:postcode":"54701",
    "sg:province":"WI",
    "sg:tags":[
        "accountant"
    ],
    "wof:name":"K M Flesher LLC",
    "wof:placetype":"venue"
},
  "geometry": {"coordinates":[-91.471661,44.794253],"type":"Point"}
}