{
  "type": "Feature",
  "properties": {
    "iso:country":"US",
    "sg:address":"107 N Milwaukee St",
    "sg:city":"Waterford",
    "sg:classifiers":[
        {
            "category":"Building & Trades",
            "subcategory":"Plumbing",
            "type":"Services"
        }
    ],
    "sg:phone":"+1 262 534 5568",
    "sg:postcode":"53185",
    "sg:province":"WI",
    "sg:tags":[
        "heating",
        "contractor"
    ],
    "wof:name":"Roth Heating Co",
    "wof:placetype":"venue"
},
  "geometry": {"coordinates":[-88.20933,42.762974],"type":"Point"}
}