{
  "type": "Feature",
  "properties": {
    "iso:country":"US",
    "sg:address":"15082 Homer Rd",
    "sg:city":"Fennimore",
    "sg:classifiers":[
        {
            "category":"Farming",
            "subcategory":"Dairy Farm",
            "type":"Manufacturing & Wholesale Goods"
        }
    ],
    "sg:phone":"+1 608 822 6964",
    "sg:postcode":"53809",
    "sg:province":"WI",
    "wof:name":"Earl Schaefer Farms",
    "wof:placetype":"venue"
},
  "geometry": {"coordinates":[-90.567387,43.050421],"type":"Point"}
}