{
  "type": "Feature",
  "properties": {
    "iso:country":"US",
    "sg:address":"12910 N Tews Rd",
    "sg:city":"Hayward",
    "sg:classifiers":[
        {
            "category":"Professional",
            "type":"Services"
        }
    ],
    "sg:phone":"+1 715 462 3374",
    "sg:postcode":"54843",
    "sg:province":"WI",
    "sg:tags":[
        "establishment"
    ],
    "wof:name":"Deer Trail Camp/Linda Bratteig",
    "wof:placetype":"venue"
},
  "geometry": {"coordinates":[-91.12825599999999,46.097339],"type":"Point"}
}