{
  "type": "Feature",
  "properties": {
    "iso:country":"US",
    "sg:address":"1422 Geneva St",
    "sg:city":"Racine",
    "sg:classifiers":[
        {
            "category":"Social Services",
            "subcategory":"Child Care",
            "type":"Services"
        }
    ],
    "sg:phone":"+1 262 619 1966",
    "sg:postcode":"53404",
    "sg:province":"WI",
    "wof:name":"Rhonda's Day Care",
    "wof:placetype":"venue"
},
  "geometry": {"coordinates":[-87.79432199999999,42.738949],"type":"Point"}
}