{
  "type": "Feature",
  "properties": {
    "addr:full":"900 N Parkview St Cottage Grove WI 53527",
    "addr:housenumber":"900",
    "addr:postcode":"53527",
    "addr:street":"N Parkview St",
    "iso:country":"US",
    "sg:address":"900 N Parkview St",
    "sg:city":"Cottage Grove",
    "sg:classifiers":[
        {
            "category":"Education",
            "subcategory":"School",
            "type":"Public Place"
        }
    ],
    "sg:phone":"+1 608 221 7692",
    "sg:postcode":"53527",
    "sg:province":"WI",
    "wof:name":"Taylor Prairie Elem School",
    "wof:placetype":"venue"
},
  "geometry": {"coordinates":[-89.20726999999999,43.097505],"type":"Point"}
}