{
  "type": "Feature",
  "properties": {
    "iso:country":"US",
    "sg:address":"1641 Gohres St",
    "sg:city":"La Crosse",
    "sg:classifiers":[
        {
            "category":"Retail",
            "subcategory":"Self-service Laundry",
            "type":"Services"
        }
    ],
    "sg:phone":"+1 608 782 9006",
    "sg:postcode":"54603",
    "sg:province":"WI",
    "wof:name":"French Island Laundromat",
    "wof:placetype":"venue"
},
  "geometry": {"coordinates":[-91.233464,43.849312],"type":"Point"}
}