{
  "type": "Feature",
  "properties": {
    "iso:country":"US",
    "sg:address":"5001 W Fond du Lac Ave",
    "sg:city":"Milwaukee",
    "sg:classifiers":[
        {
            "category":"Utilities",
            "subcategory":"Mobile Phone",
            "type":"Services"
        }
    ],
    "sg:phone":"+1 414 265 9663",
    "sg:postcode":"53216",
    "sg:province":"WI",
    "sg:tags":[
        "telephone",
        "cellular"
    ],
    "wof:name":"Perfect Pagers",
    "wof:placetype":"venue"
},
  "geometry": {"coordinates":[-87.97502299999999,43.088772],"type":"Point"}
}