{
  "type": "Feature",
  "properties": {
    "iso:country":"US",
    "sg:address":"8710 Evergreen Rd",
    "sg:city":"Shawano",
    "sg:classifiers":[
        {
            "category":"Retail",
            "subcategory":"Auto Repair",
            "type":"Services"
        }
    ],
    "sg:phone":"+1 715 526 9072",
    "sg:postcode":"54166",
    "sg:province":"WI",
    "sg:tags":[
        "repairing",
        "automobile"
    ],
    "wof:name":"Jerry's Automotive",
    "wof:placetype":"venue"
},
  "geometry": {"coordinates":[-88.69646,44.708068],"type":"Point"}
}