{
  "type": "Feature",
  "properties": {
    "iso:country":"US",
    "sg:address":"521 Main St",
    "sg:city":"La Crosse",
    "sg:classifiers":[
        {
            "category":"Organizations",
            "subcategory":"Religious Organization",
            "type":"Services"
        }
    ],
    "sg:phone":"+1 608 784 9968",
    "sg:postcode":"54601",
    "sg:province":"WI",
    "sg:tags":[
        "church"
    ],
    "wof:name":"First Ch Of Christ Scientist",
    "wof:placetype":"venue"
},
  "geometry": {"coordinates":[-91.248541,43.811712],"type":"Point"}
}