{
  "type": "Feature",
  "properties": {
    "iso:country":"US",
    "sg:address":"4208 W Parkway Blvd",
    "sg:city":"Appleton",
    "sg:classifiers":[
        {
            "category":"Manufacturing",
            "subcategory":"Glass & Minerals",
            "type":"Manufacturing & Wholesale Goods"
        }
    ],
    "sg:phone":"+1 920 731 2671",
    "sg:postcode":"54913",
    "sg:province":"WI",
    "sg:tags":[
        "product",
        "wool",
        "mfg"
    ],
    "wof:name":"Midwest Perlite Inc",
    "wof:placetype":"venue"
},
  "geometry": {"coordinates":[-88.47598499999999,44.280263],"type":"Point"}
}