{
  "type": "Feature",
  "properties": {
    "iso:country":"US",
    "sg:address":"7404 Ogden Ave",
    "sg:city":"Superior",
    "sg:classifiers":[
        {
            "category":"Building & Trades",
            "subcategory":"Plumbing",
            "type":"Services"
        }
    ],
    "sg:phone":"+1 715 392 2574",
    "sg:postcode":"54880",
    "sg:province":"WI",
    "sg:tags":[
        "me",
        "sheet",
        "doe",
        "heating",
        "air",
        "conditioning",
        "contractor"
    ],
    "wof:name":"Aire Care",
    "wof:placetype":"venue"
},
  "geometry": {"coordinates":[-92.102969,46.651226],"type":"Point"}
}