{
  "type": "Feature",
  "properties": {
    "iso:country":"US",
    "sg:address":"2824 130th St",
    "sg:city":"Frederic",
    "sg:classifiers":[
        {
            "category":"Organizations",
            "subcategory":"Religious Organization",
            "type":"Services"
        }
    ],
    "sg:phone":"+1 715 327 4500",
    "sg:postcode":"54837",
    "sg:province":"WI",
    "wof:name":"Oak Forest Ctr",
    "wof:placetype":"venue"
},
  "geometry": {"coordinates":[-92.427245,45.615486],"type":"Point"}
}