{
  "type": "Feature",
  "properties": {
    "iso:country":"US",
    "sg:address":"720 2nd Ave",
    "sg:city":"Eau Claire",
    "sg:classifiers":[
        {
            "category":"Government",
            "subcategory":"Office",
            "type":"Public Place"
        }
    ],
    "sg:phone":"+1 715 839 4718",
    "sg:postcode":"54703",
    "sg:province":"WI",
    "sg:tags":[
        "city",
        "program",
        "health"
    ],
    "wof:name":"Eau Claire County Health Dept",
    "wof:placetype":"venue"
},
  "geometry": {"coordinates":[-91.50420699999999,44.809053],"type":"Point"}
}