{
  "type": "Feature",
  "properties": {
    "addr:full":"1990 80th St Somerset WI 54025",
    "addr:housenumber":"1990",
    "addr:postcode":"54025",
    "addr:street":"80Th St",
    "iso:country":"US",
    "sg:address":"1990 80th St",
    "sg:city":"Somerset",
    "sg:classifiers":[
        {
            "category":"Professional",
            "type":"Services"
        }
    ],
    "sg:phone":"+1 715 248 1990",
    "sg:postcode":"54025",
    "sg:province":"WI",
    "wof:name":"Dean M Everson",
    "wof:placetype":"venue"
},
  "geometry": {"coordinates":[-92.652089,45.15059],"type":"Point"}
}