{
  "type": "Feature",
  "properties": {
    "iso:country":"US",
    "sg:address":"9922 W Cleveland Ave",
    "sg:city":"Milwaukee",
    "sg:classifiers":[
        {
            "category":"Shopping",
            "subcategory":"Florist",
            "type":"Retail Goods"
        }
    ],
    "sg:phone":"+1 414 327 6953",
    "sg:postcode":"53227",
    "sg:province":"WI",
    "wof:name":"Everflora",
    "wof:placetype":"venue"
},
  "geometry": {"coordinates":[-88.037488,42.995448],"type":"Point"}
}