{
  "type": "Feature",
  "properties": {
    "addr:full":"5626 N 91st St Milwaukee WI 53225",
    "addr:housenumber":"5626",
    "addr:postcode":"53225",
    "addr:street":"N 91St St",
    "iso:country":"US",
    "sg:address":"5626 N 91st St",
    "sg:city":"Milwaukee",
    "sg:classifiers":[
        {
            "category":"Education",
            "subcategory":"Dance Studio",
            "type":"Public Place"
        }
    ],
    "sg:phone":"+1 414 463 8530",
    "sg:postcode":"53225",
    "sg:province":"WI",
    "sg:tags":[
        "instruction",
        "dancing"
    ],
    "sg:website":"http://www.gaylesdancestudio.com",
    "wof:name":"Gayle's Dance Studio Ltd",
    "wof:placetype":"venue"
},
  "geometry": {"coordinates":[-88.02579,43.120056],"type":"Point"}
}