{
  "type": "Feature",
  "properties": {
    "iso:country":"US",
    "sg:address":"6250 Woodland Dr",
    "sg:city":"Waunakee",
    "sg:classifiers":[
        {
            "category":"Building & Trades",
            "subcategory":"Construction",
            "type":"Services"
        }
    ],
    "sg:phone":"+1 608 850 5846",
    "sg:postcode":"53597",
    "sg:province":"WI",
    "sg:tags":[
        "house"
    ],
    "wof:name":"Hoffman Construciton Co",
    "wof:placetype":"venue"
},
  "geometry": {"coordinates":[-89.470135,43.177515],"type":"Point"}
}