{
  "type": "Feature",
  "properties": {
    "iso:country":"US",
    "sg:address":"627 E Erie St",
    "sg:city":"Milwaukee",
    "sg:classifiers":[
        {
            "category":"Insurance",
            "subcategory":"Hazard Insurance",
            "type":"Services"
        },
        {
            "category":"Insurance",
            "subcategory":"Insurance Agent",
            "type":"Services"
        },
        {
            "category":"Insurance",
            "subcategory":"Life Insurance",
            "type":"Services"
        },
        {
            "category":"Insurance",
            "subcategory":"Title Insurance",
            "type":"Services"
        }
    ],
    "sg:phone":"+1 414 769 1455",
    "sg:postcode":"53202",
    "sg:province":"WI",
    "sg:tags":[
        "auto",
        "commercial",
        "business",
        "homeowner"
    ],
    "sg:website":"http://www.farmersagent.com/jsusedik/",
    "wof:name":"James Susedik - Farmers Insurance",
    "wof:placetype":"venue"
},
  "geometry": {"coordinates":[-87.902415,43.02682],"type":"Point"}
}