{
  "type": "Feature",
  "properties": {
    "iso:country":"US",
    "sg:address":"934 Sauk Ridge Trl",
    "sg:city":"Madison",
    "sg:classifiers":[
        {
            "category":"Professional",
            "subcategory":"Computer Services",
            "type":"Services"
        }
    ],
    "sg:phone":"+1 608 824 0793",
    "sg:postcode":"53717",
    "sg:province":"WI",
    "sg:tags":[
        "datum"
    ],
    "wof:name":"Swe Selwyn",
    "wof:placetype":"venue"
},
  "geometry": {"coordinates":[-89.493876,43.081117],"type":"Point"}
}