{
  "type": "Feature",
  "properties": {
    "iso:country":"US",
    "sg:address":"1224 Rangeline Rd",
    "sg:city":"Auburndale",
    "sg:classifiers":[
        {
            "category":"Retail",
            "subcategory":"Veterinary Services",
            "type":"Services"
        }
    ],
    "sg:phone":"+1 715 389 8365",
    "sg:postcode":"54412",
    "sg:province":"WI",
    "sg:tags":[
        "veterinarian"
    ],
    "wof:name":"Boviczech Veterinary Svc",
    "wof:placetype":"venue"
},
  "geometry": {"coordinates":[-89.963989,44.731921],"type":"Point"}
}