{
  "type": "Feature",
  "properties": {
    "addr:full":"5570 Frontage Rd Onalaska WI 54650",
    "addr:housenumber":"5570",
    "addr:postcode":"54650",
    "addr:street":"Frontage Rd",
    "iso:country":"US",
    "sg:address":"5570 Frontage Rd",
    "sg:city":"Onalaska",
    "sg:classifiers":[
        {
            "category":"Home & Garden",
            "subcategory":"Carpets & Floor Coverings",
            "type":"Retail Goods"
        }
    ],
    "sg:phone":"+1 608 783 1088",
    "sg:postcode":"54650",
    "sg:province":"WI",
    "sg:website":"www.floorcraftersinc.com",
    "wof:name":"Floorcrafters",
    "wof:placetype":"venue"
},
  "geometry": {"coordinates":[-91.249612,43.922711],"type":"Point"}
}