{
  "type": "Feature",
  "properties": {
    "iso:country":"US",
    "sg:address":"218 N 14th Ave",
    "sg:city":"Sturgeon Bay",
    "sg:classifiers":[
        {
            "category":"Real Estate",
            "subcategory":"Developer",
            "type":"Services"
        },
        {
            "category":"Professional",
            "subcategory":"Lawyer & Legal Services",
            "type":"Services"
        }
    ],
    "sg:phone":"+1 920 743 7427",
    "sg:postcode":"54235",
    "sg:province":"WI",
    "sg:tags":[
        "shared",
        "attorney",
        "hospitality"
    ],
    "wof:name":"Hedeen International Inc",
    "wof:placetype":"venue"
},
  "geometry": {"coordinates":[-87.36102,44.837003],"type":"Point"}
}