{
  "type": "Feature",
  "properties": {
    "iso:country":"US",
    "sg:address":"511 Colfax St",
    "sg:city":"Augusta",
    "sg:classifiers":[
        {
            "category":"Banks & Credit Unions",
            "subcategory":"Financial Services",
            "type":"Services"
        }
    ],
    "sg:phone":"+1 715 286 2639",
    "sg:postcode":"54722",
    "sg:province":"WI",
    "sg:tags":[
        "trust",
        "investment",
        "real estate"
    ],
    "wof:name":"Basic Holdings LLC",
    "wof:placetype":"venue"
},
  "geometry": {"coordinates":[-91.127027,44.678436],"type":"Point"}
}