{
  "type": "Feature",
  "properties": {
    "iso:country":"US",
    "sg:address":"1112 Spruce St",
    "sg:city":"Wausau",
    "sg:classifiers":[
        {
            "category":"Building & Trades",
            "subcategory":"Landscaping Services",
            "type":"Services"
        }
    ],
    "sg:phone":"+1 715 845 6769",
    "sg:postcode":"54401",
    "sg:province":"WI",
    "wof:name":"Kreft Contracting Services",
    "wof:placetype":"venue"
},
  "geometry": {"coordinates":[-89.64877300000001,44.966472],"type":"Point"}
}