{
  "type": "Feature",
  "properties": {
    "iso:country":"US",
    "sg:address":"1921 Wegner St",
    "sg:city":"Wausau",
    "sg:classifiers":[
        {
            "category":"Social Services",
            "subcategory":"Child Care",
            "type":"Services"
        }
    ],
    "sg:phone":"+1 715 842 7917",
    "sg:postcode":"54401",
    "sg:province":"WI",
    "wof:name":"Montessori School Of Wausau",
    "wof:placetype":"venue"
},
  "geometry": {"coordinates":[-89.660539,44.957208],"type":"Point"}
}