{
  "type": "Feature",
  "properties": {
    "iso:country":"US",
    "sg:address":"3000 Orchard Rd",
    "sg:city":"Antigo",
    "sg:classifiers":[
        {
            "category":"Food & Beverages",
            "subcategory":"Fruits & Vegetables",
            "type":"Retail Goods"
        }
    ],
    "sg:phone":"+1 715 627 2628",
    "sg:postcode":"54409",
    "sg:province":"WI",
    "sg:tags":[
        "sales"
    ],
    "wof:name":"Canopy Gardens Country Store",
    "wof:placetype":"venue"
},
  "geometry": {"coordinates":[-89.053697,45.132577],"type":"Point"}
}