{
  "type": "Feature",
  "properties": {
    "iso:country":"US",
    "sg:address":"2417 Cleveland Ave",
    "sg:city":"Marinette",
    "sg:classifiers":[
        {
            "category":"Manufacturing",
            "subcategory":"Tools & Machinery",
            "type":"Manufacturing & Wholesale Goods"
        }
    ],
    "sg:phone":"+1 715 732 0504",
    "sg:postcode":"54143",
    "sg:province":"WI",
    "sg:tags":[
        "machine",
        "shop"
    ],
    "sg:website":"www.dsmold.com",
    "wof:name":"D & S Mold & Tool Co",
    "wof:placetype":"venue"
},
  "geometry": {"coordinates":[-87.63621,45.084769],"type":"Point"}
}