{
  "type": "Feature",
  "properties": {
    "iso:country":"US",
    "sg:address":"3019 W College Ave",
    "sg:city":"Milwaukee",
    "sg:classifiers":[
        {
            "category":"Shopping",
            "type":"Retail Goods"
        }
    ],
    "sg:phone":"+1 414 325 8080",
    "sg:postcode":"53221",
    "sg:province":"WI",
    "sg:tags":[
        "cards",
        "payphones",
        "calling"
    ],
    "wof:name":"Payphones Unlimited Inc",
    "wof:placetype":"venue"
},
  "geometry": {"coordinates":[-87.95018399999999,42.930299],"type":"Point"}
}