{
  "type": "Feature",
  "properties": {
    "addr:full":"903 Morning Glory Ln Wausau WI 54401",
    "addr:housenumber":"903",
    "addr:postcode":"54401",
    "addr:street":"Morning Glory Ln",
    "iso:country":"US",
    "sg:address":"903 Morning Glory Ln",
    "sg:city":"Wausau",
    "sg:classifiers":[
        {
            "category":"Freight",
            "type":"Transportation"
        }
    ],
    "sg:phone":"+1 715 355 4595",
    "sg:postcode":"54401",
    "sg:province":"WI",
    "sg:tags":[
        "delivery",
        "operator",
        "local",
        "trucking"
    ],
    "wof:name":"All Hours Transportation",
    "wof:placetype":"venue"
},
  "geometry": {"coordinates":[-89.64716799999999,44.916089],"type":"Point"}
}