{
  "type": "Feature",
  "properties": {
    "iso:country":"US",
    "sg:address":"3962 Hillside Rd",
    "sg:city":"Egg Harbor",
    "sg:classifiers":[
        {
            "category":"Professional",
            "subcategory":"Management & Consulting",
            "type":"Services"
        }
    ],
    "sg:phone":"+1 920 823 2478",
    "sg:postcode":"54209",
    "sg:province":"WI",
    "sg:tags":[
        "business"
    ],
    "wof:name":"Nature Wise",
    "wof:placetype":"venue"
},
  "geometry": {"coordinates":[-87.231649,45.025325],"type":"Point"}
}