{
  "type": "Feature",
  "properties": {
    "iso:country":"US",
    "sg:address":"1815 Tall Grass Cir",
    "sg:city":"Waukesha",
    "sg:classifiers":[
        {
            "category":"Real Estate",
            "subcategory":"Real Estate Operator",
            "type":"Services"
        }
    ],
    "sg:phone":"+1 262 542 2494",
    "sg:postcode":"53188",
    "sg:province":"WI",
    "sg:tags":[
        "building",
        "nonresidential"
    ],
    "wof:name":"Jaykay Properties LLC",
    "wof:placetype":"venue"
},
  "geometry": {"coordinates":[-88.273488,43.029796],"type":"Point"}
}