{
  "type": "Feature",
  "properties": {
    "iso:country":"US",
    "sg:address":"2400 Eastern Ave",
    "sg:city":"Plymouth",
    "sg:classifiers":[
        {
            "category":"Retail",
            "subcategory":"Veterinary Services",
            "type":"Services"
        }
    ],
    "sg:phone":"+1 920 892 6878",
    "sg:postcode":"53073",
    "sg:province":"WI",
    "sg:tags":[
        "veterinarian"
    ],
    "wof:name":"Emquest",
    "wof:placetype":"venue"
},
  "geometry": {"coordinates":[-87.95156,43.747196],"type":"Point"}
}