{
  "type": "Feature",
  "properties": {
    "iso:country":"US",
    "sg:address":"5912 S 116th St",
    "sg:city":"Hales Corners",
    "sg:classifiers":[
        {
            "category":"Professional",
            "type":"Services"
        }
    ],
    "sg:phone":"+1 414 427 3880",
    "sg:postcode":"53130",
    "sg:province":"WI",
    "wof:name":"Joseph F Fix",
    "wof:placetype":"venue"
},
  "geometry": {"coordinates":[-88.058288,42.936702],"type":"Point"}
}