{
  "type": "Feature",
  "properties": {
    "iso:country":"US",
    "sg:address":"9825 S 13th St",
    "sg:city":"Oak Creek",
    "sg:classifiers":[
        {
            "category":"Home & Garden",
            "subcategory":"Carpets & Floor Coverings",
            "type":"Retail Goods"
        }
    ],
    "sg:phone":"+1 414 571 6309",
    "sg:postcode":"53154",
    "sg:province":"WI",
    "wof:name":"Finish Line Floors Milw Fax",
    "wof:placetype":"venue"
},
  "geometry": {"coordinates":[-87.93265,42.866106],"type":"Point"}
}