{
  "type": "Feature",
  "properties": {
    "addr:full":"2096 Helena St Madison WI 53704",
    "addr:housenumber":"2096",
    "addr:postcode":"53704",
    "addr:street":"Helena St",
    "iso:country":"US",
    "sg:address":"2096 Helena St",
    "sg:city":"Madison",
    "sg:classifiers":[
        {
            "category":"Manufacturing",
            "subcategory":"Tools & Machinery",
            "type":"Manufacturing & Wholesale Goods"
        }
    ],
    "sg:phone":"+1 608 241 1511",
    "sg:postcode":"53704",
    "sg:province":"WI",
    "sg:tags":[
        "softener",
        "water",
        "mfg",
        "household",
        "filter",
        "p"
    ],
    "wof:name":"Capital Water Softener Inc",
    "wof:placetype":"venue"
},
  "geometry": {"coordinates":[-89.353365,43.090534],"type":"Point"}
}