{
  "type": "Feature",
  "properties": {
    "iso:country":"US",
    "sg:address":"8110 W Brown Deer Rd",
    "sg:city":"Milwaukee",
    "sg:classifiers":[
        {
            "category":"Home & Garden",
            "subcategory":"Hardware",
            "type":"Retail Goods"
        },
        {
            "category":"Manufacturing",
            "subcategory":"Wood Products",
            "type":"Manufacturing & Wholesale Goods"
        },
        {
            "category":"Wholesale",
            "subcategory":"Construction Materials",
            "type":"Manufacturing & Wholesale Goods"
        },
        {
            "category":"Home & Garden",
            "subcategory":"Building Materials",
            "type":"Retail Goods"
        }
    ],
    "sg:phone":"+1 414 355 5666",
    "sg:postcode":"53223",
    "sg:province":"WI",
    "sg:tags":[
        "supply",
        "lumber",
        "lumber-used",
        "improvement",
        "part",
        "plumbing",
        "fixtures",
        "store"
    ],
    "sg:website":"http://www.menards.com/",
    "wof:name":"Menards",
    "wof:placetype":"venue"
},
  "geometry": {"coordinates":[-88.01036999999999,43.177949],"type":"Point"}
}