{
  "type": "Feature",
  "properties": {
    "iso:country":"US",
    "sg:address":"2500 W Vliet St",
    "sg:city":"Milwaukee",
    "sg:classifiers":[
        {
            "category":"Wholesale",
            "subcategory":"Machinery & Supplies",
            "type":"Manufacturing & Wholesale Goods"
        }
    ],
    "sg:phone":"+1 414 342 1604",
    "sg:postcode":"53205",
    "sg:province":"WI",
    "sg:tags":[
        "janitor"
    ],
    "wof:name":"Vacuum Cleaner Shop Inc",
    "wof:placetype":"venue"
},
  "geometry": {"coordinates":[-87.946274,43.048641],"type":"Point"}
}