{
  "type": "Feature",
  "properties": {
    "iso:country":"US",
    "sg:address":"610 Herda Ave",
    "sg:city":"Twin Lakes",
    "sg:classifiers":[
        {
            "category":"Freight",
            "type":"Transportation"
        }
    ],
    "sg:phone":"+1 262 877 2344",
    "sg:postcode":"53181",
    "sg:province":"WI",
    "sg:tags":[
        "courier"
    ],
    "wof:name":"Livingston Management",
    "wof:placetype":"venue"
},
  "geometry": {"coordinates":[-88.254398,42.53797],"type":"Point"}
}