{
  "type": "Feature",
  "properties": {
    "iso:country":"US",
    "sg:address":"915 2nd St",
    "sg:city":"Kewaunee",
    "sg:classifiers":[
        {
            "category":"Education",
            "subcategory":"School",
            "type":"Public Place"
        }
    ],
    "sg:phone":"+1 920 388 2951",
    "sg:postcode":"54216",
    "sg:province":"WI",
    "wof:name":"Kewaunee High School",
    "wof:placetype":"venue"
},
  "geometry": {"coordinates":[-87.513091,44.454053],"type":"Point"}
}