{
  "type": "Feature",
  "properties": {
    "addr:full":"403 Division St Cobb WI 53526",
    "addr:housenumber":"403",
    "addr:postcode":"53526",
    "addr:street":"Division St",
    "iso:country":"US",
    "sg:address":"403 Division St",
    "sg:city":"Cobb",
    "sg:classifiers":[
        {
            "category":"Retail",
            "subcategory":"Repair Shop",
            "type":"Services"
        }
    ],
    "sg:phone":"+1 608 623 3323",
    "sg:postcode":"53526",
    "sg:province":"WI",
    "sg:tags":[
        "related"
    ],
    "wof:name":"Tri Star Repair",
    "wof:placetype":"venue"
},
  "geometry": {"coordinates":[-90.329803,42.969231],"type":"Point"}
}