{
  "type": "Feature",
  "properties": {
    "iso:country":"US",
    "sg:address":"7 Albion St",
    "sg:city":"Edgerton",
    "sg:classifiers":[
        {
            "category":"Health Services",
            "subcategory":"Health Practitioner",
            "type":"Services"
        }
    ],
    "sg:phone":"+1 608 884 2197",
    "sg:postcode":"53534",
    "sg:province":"WI",
    "wof:name":"Herban Home",
    "wof:placetype":"venue"
},
  "geometry": {"coordinates":[-89.071898,42.8373],"type":"Point"}
}