{
  "type": "Feature",
  "properties": {
    "iso:country":"US",
    "sg:address":"4650 N Port Washington Rd",
    "sg:city":"Milwaukee",
    "sg:classifiers":[
        {
            "category":"Education",
            "subcategory":"Special Training",
            "type":"Public Place"
        }
    ],
    "sg:phone":"+1 414 374 5433",
    "sg:postcode":"53212",
    "sg:province":"WI",
    "sg:tags":[
        "self",
        "motivational",
        "improvement"
    ],
    "wof:name":"Center For Creative Learning",
    "wof:placetype":"venue"
},
  "geometry": {"coordinates":[-87.916848,43.101194],"type":"Point"}
}