{
  "type": "Feature",
  "properties": {
    "iso:country":"US",
    "sg:address":"3034 W Elberg Ave",
    "sg:city":"Appleton",
    "sg:classifiers":[
        {
            "category":"Professional",
            "subcategory":"Computer Services",
            "type":"Services"
        }
    ],
    "sg:phone":"+1 920 832 8406",
    "sg:postcode":"54914",
    "sg:province":"WI",
    "sg:tags":[
        "design",
        "support",
        "installation",
        "network"
    ],
    "sg:website":"www.cnetsol.com",
    "wof:name":"Corporate Network Solutions",
    "wof:placetype":"venue"
},
  "geometry": {"coordinates":[-88.452832,44.271262],"type":"Point"}
}