{
  "type": "Feature",
  "properties": {
    "iso:country":"US",
    "sg:address":"1759 Co Rd Uu",
    "sg:city":"Kaukauna",
    "sg:classifiers":[
        {
            "category":"Recreation",
            "type":"Entertainment"
        }
    ],
    "sg:phone":"+1 920 766 0697",
    "sg:postcode":"54130",
    "sg:province":"WI",
    "sg:tags":[
        "course",
        "golf"
    ],
    "wof:name":"Fox Valley Golf Club",
    "wof:placetype":"venue"
},
  "geometry": {"coordinates":[-88.275938,44.357333],"type":"Point"}
}