{
  "type": "Feature",
  "properties": {
    "iso:country":"US",
    "sg:address":"624 US Hwy 12",
    "sg:city":"Baraboo",
    "sg:classifiers":[
        {
            "category":"Professional",
            "subcategory":"Employment Agencies",
            "type":"Services"
        }
    ],
    "sg:phone":"+1 608 356 5757",
    "sg:postcode":"53913",
    "sg:province":"WI",
    "sg:tags":[
        "temporary",
        "help"
    ],
    "wof:name":"Life Style Staffing",
    "wof:placetype":"venue"
},
  "geometry": {"coordinates":[-89.768661,43.476589],"type":"Point"}
}