{
  "type": "Feature",
  "properties": {
    "iso:country":"US",
    "sg:address":"2969 Co Rd T",
    "sg:city":"Sun Prairie",
    "sg:classifiers":[
        {
            "category":"Wholesale",
            "subcategory":"Chemicals & Plastics",
            "type":"Manufacturing & Wholesale Goods"
        }
    ],
    "sg:phone":"+1 608 825 8298",
    "sg:postcode":"53590",
    "sg:province":"WI",
    "sg:tags":[
        "product",
        "allied"
    ],
    "wof:name":"C C T L L C",
    "wof:placetype":"venue"
},
  "geometry": {"coordinates":[-89.235467,43.125073],"type":"Point"}
}