{
  "type": "Feature",
  "properties": {
    "iso:country":"US",
    "sg:address":"774 N Lake Ave",
    "sg:city":"Phillips",
    "sg:classifiers":[
        {
            "category":"Restaurant",
            "type":"Food & Drink"
        }
    ],
    "sg:menulink":"http://www.allmenus.com/wi/phillips/151851-aw-restaurant/menu/",
    "sg:phone":"+1 715 339 3104",
    "sg:postcode":"54555",
    "sg:province":"WI",
    "sg:tags":[
        "burger",
        "american",
        "dog",
        "pub",
        "hot"
    ],
    "wof:name":"A&W Restaurant",
    "wof:placetype":"venue"
},
  "geometry": {"coordinates":[-90.4081,45.696235],"type":"Point"}
}