{
  "type": "Feature",
  "properties": {
    "iso:country":"US",
    "sg:address":"10206 Standing Oak Dr",
    "sg:city":"Schofield",
    "sg:classifiers":[
        {
            "category":"Building & Trades",
            "subcategory":"Construction",
            "type":"Services"
        }
    ],
    "sg:phone":"+1 715 355 9600",
    "sg:postcode":"54476",
    "sg:province":"WI",
    "sg:tags":[
        "house"
    ],
    "wof:name":"Rainbow Builders",
    "wof:placetype":"venue"
},
  "geometry": {"coordinates":[-89.584606,44.863402],"type":"Point"}
}