{
  "type": "Feature",
  "properties": {
    "addr:full":"715 S Pearl St Janesville WI 53548",
    "addr:housenumber":"715",
    "addr:postcode":"53548",
    "addr:street":"S Pearl St",
    "iso:country":"US",
    "sg:address":"715 S Pearl St",
    "sg:city":"Janesville",
    "sg:classifiers":[
        {
            "category":"Local Transit",
            "type":"Transportation"
        }
    ],
    "sg:phone":"+1 608 752 5407",
    "sg:postcode":"53548",
    "sg:province":"WI",
    "sg:tags":[
        "bus",
        "line"
    ],
    "sg:website":"www.vangalderbus.com",
    "wof:name":"Van Galder Bus Co",
    "wof:placetype":"venue"
},
  "geometry": {"coordinates":[-89.035295,42.671354],"type":"Point"}
}