{
  "type": "Feature",
  "properties": {
    "iso:country":"US",
    "sg:address":"4236 N Meade St",
    "sg:city":"Appleton",
    "sg:phone":"+1 920 730 4038",
    "sg:postcode":"54911",
    "sg:province":"WI",
    "sg:tags":[
        "farm",
        "field",
        "crop"
    ],
    "wof:name":"Randy Schmidt",
    "wof:placetype":"venue"
},
  "geometry": {"coordinates":[-88.39536099999999,44.304325],"type":"Point"}
}