{
  "type": "Feature",
  "properties": {
    "iso:country":"US",
    "sg:address":"513 4th St",
    "sg:city":"Baraboo",
    "sg:classifiers":[
        {
            "category":"Professional",
            "subcategory":"Accounting & Tax Preparation",
            "type":"Services"
        }
    ],
    "sg:phone":"+1 608 356 4603",
    "sg:postcode":"53913",
    "sg:province":"WI",
    "wof:name":"Karen Ducharme",
    "wof:placetype":"venue"
},
  "geometry": {"coordinates":[-89.733983,43.470856],"type":"Point"}
}