{
  "type": "Feature",
  "properties": {
    "iso:country":"US",
    "sg:address":"86 16th St",
    "sg:city":"Clintonville",
    "sg:classifiers":[
        {
            "category":"Banks & Credit Unions",
            "subcategory":"Bank",
            "type":"Services"
        }
    ],
    "sg:phone":"+1 715 823 6455",
    "sg:postcode":"54929",
    "sg:province":"WI",
    "sg:tags":[
        "loan",
        "real estate"
    ],
    "wof:name":"Titletown Mortgage",
    "wof:placetype":"venue"
},
  "geometry": {"coordinates":[-88.751744,44.627238],"type":"Point"}
}