{
  "type": "Feature",
  "properties": {
    "iso:country":"US",
    "sg:address":"8832 N Port Washington Rd # 1",
    "sg:city":"Milwaukee",
    "sg:classifiers":[
        {
            "category":"Banks & Credit Unions",
            "subcategory":"Investment Brokerage",
            "type":"Services"
        }
    ],
    "sg:phone":"+1 414 379 7185",
    "sg:postcode":"53217",
    "sg:province":"WI",
    "sg:tags":[
        "tape",
        "video",
        "sale",
        "dvds-rental"
    ],
    "wof:name":"Tld Photo & Video",
    "wof:placetype":"venue"
},
  "geometry": {"coordinates":[-87.912937,43.176982],"type":"Point"}
}