{
  "type": "Feature",
  "properties": {
    "iso:country":"US",
    "sg:address":"1986 Kettle Creek Ln",
    "sg:city":"De Pere",
    "sg:classifiers":[
        {
            "category":"Building & Trades",
            "subcategory":"Construction",
            "type":"Services"
        }
    ],
    "sg:phone":"+1 920 339 0202",
    "sg:postcode":"54115",
    "sg:province":"WI",
    "sg:tags":[
        "house"
    ],
    "wof:name":"Marty Brice Construction",
    "wof:placetype":"venue"
},
  "geometry": {"coordinates":[-87.980904,44.438318],"type":"Point"}
}