{
  "type": "Feature",
  "properties": {
    "iso:country":"US",
    "sg:address":"1674 E Deerfield Ave",
    "sg:city":"Green Bay",
    "sg:classifiers":[
        {
            "category":"Home & Garden",
            "subcategory":"Garden Supply",
            "type":"Retail Goods"
        }
    ],
    "sg:phone":"+1 920 434 7200",
    "sg:postcode":"54313",
    "sg:province":"WI",
    "sg:tags":[
        "lawn",
        "mower"
    ],
    "wof:name":"West Side Small Engine LLC",
    "wof:placetype":"venue"
},
  "geometry": {"coordinates":[-88.048017,44.581777],"type":"Point"}
}