{
  "type": "Feature",
  "properties": {
    "addr:full":"712 Pine St Athens WI 54451",
    "addr:housenumber":"712",
    "addr:postcode":"54451",
    "addr:street":"Pine St",
    "iso:country":"US",
    "sg:address":"712 Pine St",
    "sg:city":"Athens",
    "sg:classifiers":[
        {
            "category":"Organizations",
            "subcategory":"Religious Organization",
            "type":"Services"
        }
    ],
    "sg:phone":"+1 715 257 7777",
    "sg:postcode":"54451",
    "sg:province":"WI",
    "wof:name":"Christ United Church",
    "wof:placetype":"venue"
},
  "geometry": {"coordinates":[-90.078749,45.029968],"type":"Point"}
}