{
  "type": "Feature",
  "properties": {
    "iso:country":"US",
    "sg:address":"6822 550th St",
    "sg:city":"Menomonie",
    "sg:classifiers":[
        {
            "category":"Professional",
            "subcategory":"Computer Services",
            "type":"Services"
        }
    ],
    "sg:phone":"+1 715 497 2809",
    "sg:postcode":"54751",
    "sg:province":"WI",
    "sg:tags":[
        "related"
    ],
    "wof:name":"Advanced Automation Engineers",
    "wof:placetype":"venue"
},
  "geometry": {"coordinates":[-91.885442,44.927989],"type":"Point"}
}