{
  "type": "Feature",
  "properties": {
    "iso:country":"US",
    "sg:address":"435 Broadway",
    "sg:city":"Wisconsin Dells",
    "sg:classifiers":[
        {
            "category":"Restaurant",
            "type":"Food & Drink"
        }
    ],
    "sg:menulink":"http://www.allmenus.com/wi/wisconsin-dells/10115-famous-daves/menu/",
    "sg:phone":"+1 608 253 6683",
    "sg:postcode":"53965",
    "sg:province":"WI",
    "sg:tags":[
        "barbecue",
        "american"
    ],
    "wof:name":"Famous Dave's",
    "wof:placetype":"venue"
},
  "geometry": {"coordinates":[-89.773467,43.627367],"type":"Point"}
}