{
  "type": "Feature",
  "properties": {
    "iso:country":"US",
    "sg:address":"1457 N Farwell Ave",
    "sg:city":"Milwaukee",
    "sg:classifiers":[
        {
            "category":"Professional",
            "subcategory":"Management & Consulting",
            "type":"Services"
        }
    ],
    "sg:phone":"+1 414 276 7144",
    "sg:postcode":"53202",
    "sg:province":"WI",
    "wof:name":"Yes Men Corporation",
    "wof:placetype":"venue"
},
  "geometry": {"coordinates":[-87.896185,43.048826],"type":"Point"}
}