{
  "type": "Feature",
  "properties": {
    "addr:full":"1124 Colby St Madison WI 53715",
    "addr:housenumber":"1124",
    "addr:postcode":"53715",
    "addr:street":"Colby St",
    "iso:country":"US",
    "sg:address":"1124 Colby St",
    "sg:city":"Madison",
    "sg:classifiers":[
        {
            "category":"Social Services",
            "subcategory":"Child Care",
            "type":"Services"
        }
    ],
    "sg:phone":"+1 608 256 8076",
    "sg:postcode":"53715",
    "sg:province":"WI",
    "sg:tags":[
        "school",
        "day"
    ],
    "wof:name":"Woodland Montessori School",
    "wof:placetype":"venue"
},
  "geometry": {"coordinates":[-89.38403099999999,43.055348],"type":"Point"}
}