{
  "type": "Feature",
  "properties": {
    "addr:full":"300 N Van Buren St Milwaukee WI 53202",
    "addr:housenumber":"300",
    "addr:postcode":"53202",
    "addr:street":"N Van Buren St",
    "iso:country":"US",
    "sg:address":"300 N Van Buren St",
    "sg:city":"Milwaukee",
    "sg:classifiers":[
        {
            "category":"Wholesale",
            "subcategory":"Fruits & Vegetables",
            "type":"Manufacturing & Wholesale Goods"
        }
    ],
    "sg:phone":"+1 414 271 4318",
    "sg:postcode":"53202",
    "sg:province":"WI",
    "sg:tags":[
        "produce"
    ],
    "sg:website":"www.tropicbanana.com",
    "wof:name":"Tropic Banana Company",
    "wof:placetype":"venue"
},
  "geometry": {"coordinates":[-87.902326,43.03536],"type":"Point"}
}