{
  "type": "Feature",
  "properties": {
    "iso:country":"US",
    "sg:address":"4410 86th Pl",
    "sg:city":"Kenosha",
    "sg:classifiers":[
        {
            "category":"Professional",
            "type":"Services"
        }
    ],
    "sg:phone":"+1 262 694 6695",
    "sg:postcode":"53142",
    "sg:province":"WI",
    "wof:name":"Richard A Selsberg",
    "wof:placetype":"venue"
},
  "geometry": {"coordinates":[-87.861501,42.548686],"type":"Point"}
}