{
  "type": "Feature",
  "properties": {
    "iso:country":"US",
    "sg:address":"1949 Center St",
    "sg:city":"East Troy",
    "sg:classifiers":[
        {
            "category":"Retail",
            "subcategory":"Repair Shop",
            "type":"Services"
        }
    ],
    "sg:phone":"+1 262 642 5986",
    "sg:postcode":"53120",
    "sg:province":"WI",
    "wof:name":"C C Randolph III",
    "wof:placetype":"venue"
},
  "geometry": {"coordinates":[-88.407988,42.791156],"type":"Point"}
}