{
  "type": "Feature",
  "properties": {
    "iso:country":"US",
    "sg:address":"842 Sky Ridge Dr",
    "sg:city":"Madison",
    "sg:classifiers":[
        {
            "category":"Building & Trades",
            "subcategory":"Construction",
            "type":"Services"
        }
    ],
    "sg:phone":"+1 608 277 1885",
    "sg:postcode":"53719",
    "sg:province":"WI",
    "sg:tags":[
        "concrete",
        "contractor"
    ],
    "wof:name":"Ainsworth Concrete Constr",
    "wof:placetype":"venue"
},
  "geometry": {"coordinates":[-89.510284,43.049916],"type":"Point"}
}