{
  "type": "Feature",
  "properties": {
    "iso:country":"US",
    "sg:address":"9739 Co Rd Tt",
    "sg:city":"Hortonville",
    "sg:phone":"+1 920 779 6630",
    "sg:postcode":"54944",
    "sg:province":"WI",
    "sg:tags":[
        "farm",
        "corn",
        "soybean"
    ],
    "wof:name":"Gruetzmacher Eldor",
    "wof:placetype":"venue"
},
  "geometry": {"coordinates":[-88.67722000000001,44.331127],"type":"Point"}
}