{
  "type": "Feature",
  "properties": {
    "addr:full":"939 Merritt Ave Oshkosh WI 54901",
    "addr:housenumber":"939",
    "addr:postcode":"54901",
    "addr:street":"Merritt Ave",
    "iso:country":"US",
    "sg:address":"939 Merritt Ave",
    "sg:city":"Oshkosh",
    "sg:classifiers":[
        {
            "category":"Communications",
            "subcategory":"Film & Video Production",
            "type":"Services"
        }
    ],
    "sg:phone":"+1 920 203 2888",
    "sg:postcode":"54901",
    "sg:province":"WI",
    "sg:tags":[
        "editing",
        "graphics"
    ],
    "wof:name":"I Shoot TV Productions",
    "wof:placetype":"venue"
},
  "geometry": {"coordinates":[-88.525615,44.019589],"type":"Point"}
}