{
  "type": "Feature",
  "properties": {
    "addr:full":"3848 Keith Siding Rd Crandon WI 54520",
    "addr:housenumber":"3848",
    "addr:postcode":"54520",
    "addr:street":"Keith Siding Rd",
    "iso:country":"US",
    "sg:address":"3848 Keith Siding Rd",
    "sg:city":"Crandon",
    "sg:classifiers":[
        {
            "category":"Professional",
            "subcategory":"Accounting & Tax Preparation",
            "type":"Services"
        }
    ],
    "sg:phone":"+1 715 478 5460",
    "sg:postcode":"54520",
    "sg:province":"WI",
    "sg:tags":[
        "bookkeeping",
        "general"
    ],
    "wof:name":"Wabick Inc",
    "wof:placetype":"venue"
},
  "geometry": {"coordinates":[-88.91268700000001,45.517461],"type":"Point"}
}