{
  "type": "Feature",
  "properties": {
    "addr:full":"640 Main St Montello WI 53949",
    "addr:housenumber":"640",
    "addr:postcode":"53949",
    "addr:street":"Main St",
    "iso:country":"US",
    "sg:address":"640 Main St",
    "sg:city":"Montello",
    "sg:classifiers":[
        {
            "category":"Retail",
            "subcategory":"Self-service Laundry",
            "type":"Services"
        }
    ],
    "sg:phone":"+1 608 297 8093",
    "sg:postcode":"53949",
    "sg:province":"WI",
    "wof:name":"Soap Box",
    "wof:placetype":"venue"
},
  "geometry": {"coordinates":[-89.325535,43.780038],"type":"Point"}
}