{
  "type": "Feature",
  "properties": {
    "iso:country":"US",
    "sg:address":"1 Barker St",
    "sg:city":"Racine",
    "sg:classifiers":[
        {
            "category":"Recreation",
            "type":"Entertainment"
        }
    ],
    "sg:phone":"+1 262 634 8585",
    "sg:postcode":"53402",
    "sg:province":"WI",
    "sg:tags":[
        "club",
        "membership",
        "drinking"
    ],
    "wof:name":"Racine Yacht Club Inc",
    "wof:placetype":"venue"
},
  "geometry": {"coordinates":[-87.782764,42.738102],"type":"Point"}
}