{
  "type": "Feature",
  "properties": {
    "iso:country":"US",
    "sg:address":"2855 Castle Hill Ln",
    "sg:city":"Green Bay",
    "sg:classifiers":[
        {
            "category":"Real Estate",
            "subcategory":"Surveying",
            "type":"Services"
        }
    ],
    "sg:phone":"+1 920 465 9477",
    "sg:postcode":"54302",
    "sg:province":"WI",
    "sg:tags":[
        "consulting",
        "management"
    ],
    "wof:name":"Tilly Raymond D",
    "wof:placetype":"venue"
},
  "geometry": {"coordinates":[-87.939977,44.49812],"type":"Point"}
}