{
  "type": "Feature",
  "properties": {
    "addr:full":"740 W Wisconsin Ave Milwaukee WI 53233",
    "addr:housenumber":"740",
    "addr:postcode":"53233",
    "addr:street":"W Wisconsin Ave",
    "iso:country":"US",
    "sg:address":"740 W Wisconsin Ave",
    "sg:city":"Milwaukee",
    "sg:classifiers":[
        {
            "category":"Shopping",
            "type":"Retail Goods"
        }
    ],
    "sg:phone":"+1 414 287 9812",
    "sg:postcode":"53233",
    "sg:province":"WI",
    "sg:tags":[
        "equipment",
        "care",
        "health",
        "home"
    ],
    "wof:name":"Almost Home",
    "wof:placetype":"venue"
},
  "geometry": {"coordinates":[-87.921226,43.038887],"type":"Point"}
}