{
  "type": "Feature",
  "properties": {
    "iso:country":"US",
    "sg:address":"517 Half Mile Rd",
    "sg:city":"Verona",
    "sg:classifiers":[
        {
            "category":"Shopping",
            "subcategory":"Bicycles & Sporting Goods",
            "type":"Retail Goods"
        }
    ],
    "sg:phone":"+1 608 845 6644",
    "sg:postcode":"53593",
    "sg:province":"WI",
    "sg:tags":[
        "repair"
    ],
    "wof:name":"Atkins Verona Bicycle Shoppe",
    "wof:placetype":"venue"
},
  "geometry": {"coordinates":[-89.548033,42.987278],"type":"Point"}
}