{
  "type": "Feature",
  "properties": {
    "iso:country":"US",
    "sg:address":"3741 W Greenfield Ave",
    "sg:city":"Milwaukee",
    "sg:classifiers":[
        {
            "category":"Shopping",
            "subcategory":"Florist",
            "type":"Retail Goods"
        }
    ],
    "sg:phone":"+1 414 384 1235",
    "sg:postcode":"53215",
    "sg:province":"WI",
    "wof:name":"House of Flowers",
    "wof:placetype":"venue"
},
  "geometry": {"coordinates":[-87.961279,43.016808],"type":"Point"}
}