{
  "type": "Feature",
  "properties": {
    "iso:country":"US",
    "sg:address":"1313 Milton Ave",
    "sg:city":"Janesville",
    "sg:classifiers":[
        {
            "category":"Restaurant",
            "type":"Food & Drink"
        }
    ],
    "sg:phone":"+1 608 757 1999",
    "sg:postcode":"53545",
    "sg:province":"WI",
    "sg:tags":[
        "eating"
    ],
    "wof:name":"Sams Pizza Inc",
    "wof:placetype":"venue"
},
  "geometry": {"coordinates":[-89.00858700000001,42.701638],"type":"Point"}
}