{
  "type": "Feature",
  "properties": {
    "iso:country":"US",
    "sg:address":"3 E Main St",
    "sg:city":"Evansville",
    "sg:classifiers":[
        {
            "category":"Building & Trades",
            "subcategory":"Construction",
            "type":"Services"
        }
    ],
    "sg:phone":"+1 608 289 2116",
    "sg:postcode":"53536",
    "sg:province":"WI",
    "sg:tags":[
        "house"
    ],
    "wof:name":"Tory Construction",
    "wof:placetype":"venue"
},
  "geometry": {"coordinates":[-89.298166,42.780225],"type":"Point"}
}