{
  "type": "Feature",
  "properties": {
    "iso:country":"US",
    "sg:address":"8980 Prairie Grove Rd",
    "sg:city":"Barneveld",
    "sg:classifiers":[
        {
            "category":"Freight",
            "type":"Transportation"
        }
    ],
    "sg:phone":"+1 608 437 7483",
    "sg:postcode":"53516",
    "sg:province":"WI",
    "sg:tags":[
        "operator",
        "local",
        "trucking"
    ],
    "wof:name":"Markhardt Transit Inc",
    "wof:placetype":"venue"
},
  "geometry": {"coordinates":[-89.843303,42.973767],"type":"Point"}
}