{
  "type": "Feature",
  "properties": {
    "addr:full":"4441 Woodgate Dr Janesville WI 53546",
    "addr:housenumber":"4441",
    "addr:postcode":"53546",
    "addr:street":"Woodgate Dr",
    "iso:country":"US",
    "sg:address":"4441 Woodgate Dr",
    "sg:city":"Janesville",
    "sg:classifiers":[
        {
            "category":"Professional",
            "subcategory":"Lawyer & Legal Services",
            "type":"Services"
        }
    ],
    "sg:phone":"+1 608 743 8201",
    "sg:postcode":"53546",
    "sg:province":"WI",
    "sg:tags":[
        "attorney"
    ],
    "wof:name":"Trish Arreazola Atty At Law",
    "wof:placetype":"venue"
},
  "geometry": {"coordinates":[-88.98096099999999,42.735739],"type":"Point"}
}