{
  "type": "Feature",
  "properties": {
    "iso:country":"US",
    "sg:address":"1223 Gohres St",
    "sg:city":"La Crosse",
    "sg:classifiers":[
        {
            "category":"Recreation",
            "type":"Entertainment"
        }
    ],
    "sg:phone":"+1 608 796 9553",
    "sg:postcode":"54603",
    "sg:province":"WI",
    "sg:tags":[
        "club",
        "membership",
        "baseball"
    ],
    "wof:name":"La Crosse Loggers Baseball CLU",
    "wof:placetype":"venue"
},
  "geometry": {"coordinates":[-91.238659,43.849288],"type":"Point"}
}