{
  "type": "Feature",
  "properties": {
    "iso:country":"US",
    "sg:address":"2324 Western Ave",
    "sg:city":"Eau Claire",
    "sg:classifiers":[
        {
            "category":"Retail",
            "subcategory":"Auto Repair",
            "type":"Services"
        }
    ],
    "sg:phone":"+1 715 832 6666",
    "sg:postcode":"54703",
    "sg:province":"WI",
    "sg:tags":[
        "wrecker"
    ],
    "wof:name":"Amazon Heavy Duty Towing",
    "wof:placetype":"venue"
},
  "geometry": {"coordinates":[-91.478076,44.842052],"type":"Point"}
}