{
  "type": "Feature",
  "properties": {
    "addr:full":"17601 W Greenfield Ave New Berlin WI 53146",
    "addr:housenumber":"17601",
    "addr:postcode":"53146",
    "addr:street":"W Greenfield Ave",
    "iso:country":"US",
    "sg:address":"17601 W Greenfield Ave",
    "sg:city":"New Berlin",
    "sg:classifiers":[
        {
            "category":"Building & Trades",
            "subcategory":"Construction",
            "type":"Services"
        }
    ],
    "sg:phone":"+1 262 782 1564",
    "sg:postcode":"53146",
    "sg:province":"WI",
    "sg:tags":[
        "house"
    ],
    "wof:name":"Ervs Remodeling & Repair",
    "wof:placetype":"venue"
},
  "geometry": {"coordinates":[-88.13319,43.016905],"type":"Point"}
}