{
  "type": "Feature",
  "properties": {
    "iso:country":"US",
    "sg:address":"7415 Devonshire Dr",
    "sg:city":"Cedarburg",
    "sg:classifiers":[
        {
            "category":"Professional",
            "subcategory":"Management & Consulting",
            "type":"Services"
        }
    ],
    "sg:phone":"+1 262 375 9704",
    "sg:postcode":"53012",
    "sg:province":"WI",
    "sg:tags":[
        "fuel"
    ],
    "wof:name":"DHDS Management Group",
    "wof:placetype":"venue"
},
  "geometry": {"coordinates":[-87.99686,43.333832],"type":"Point"}
}