{
  "type": "Feature",
  "properties": {
    "addr:full":"3871 State Hwy 42 Fish Creek WI 54212",
    "addr:housenumber":"3871",
    "addr:postcode":"54212",
    "addr:street":"State Hwy 42",
    "iso:country":"US",
    "sg:address":"3871 State Hwy 42",
    "sg:city":"Fish Creek",
    "sg:classifiers":[
        {
            "category":"Autos & Motor Vehicles",
            "subcategory":"Fuel & Gas Station",
            "type":"Retail Goods"
        }
    ],
    "sg:phone":"+1 920 868 2858",
    "sg:postcode":"54212",
    "sg:province":"WI",
    "sg:tags":[
        "oil"
    ],
    "wof:name":"Fish Creek Amoco",
    "wof:placetype":"venue"
},
  "geometry": {"coordinates":[-87.226782,45.127765],"type":"Point"}
}