{
  "type": "Feature",
  "properties": {
    "addr:full":"5229 Roberts Dr Greendale WI 53129",
    "addr:housenumber":"5229",
    "addr:postcode":"53129",
    "addr:street":"Roberts Dr",
    "iso:country":"US",
    "sg:address":"5229 Roberts Dr",
    "sg:city":"Greendale",
    "sg:classifiers":[
        {
            "category":"Organizations",
            "subcategory":"Community Association",
            "type":"Services"
        }
    ],
    "sg:phone":"+1 414 423 0126",
    "sg:postcode":"53129",
    "sg:province":"WI",
    "wof:name":"American Legion Post 0388",
    "wof:placetype":"venue"
},
  "geometry": {"coordinates":[-87.979983,42.927865],"type":"Point"}
}