{
  "type": "Feature",
  "properties": {
    "addr:full":"2213 Woodale Ave Green Bay WI 54313",
    "addr:housenumber":"2213",
    "addr:postcode":"54313",
    "addr:street":"Woodale Ave",
    "iso:country":"US",
    "sg:address":"2213 Woodale Ave",
    "sg:city":"Green Bay",
    "sg:classifiers":[
        {
            "category":"Building & Trades",
            "subcategory":"Electrical",
            "type":"Services"
        }
    ],
    "sg:phone":"+1 920 434 9556",
    "sg:postcode":"54313",
    "sg:province":"WI",
    "sg:tags":[
        "electric",
        "contractor"
    ],
    "wof:name":"Master Electric Inc",
    "wof:placetype":"venue"
},
  "geometry": {"coordinates":[-88.07320300000001,44.572926],"type":"Point"}
}