{
  "type": "Feature",
  "properties": {
    "addr:full":"3005 Siggelkow Rd Mc Farland WI 53558",
    "addr:postcode":"3005;53558",
    "addr:street":"Siggelkow Rd",
    "iso:country":"US",
    "sg:address":"3005 Siggelkow Rd",
    "sg:city":"Mc Farland",
    "sg:classifiers":[
        {
            "category":"Farming",
            "subcategory":"Farm & Veterinary Services",
            "type":"Manufacturing & Wholesale Goods"
        }
    ],
    "sg:phone":"+1 608 838 3328",
    "sg:postcode":"53558",
    "sg:province":"WI",
    "sg:tags":[
        "crop"
    ],
    "wof:name":"Jones Orchard",
    "wof:placetype":"venue"
},
  "geometry": {"coordinates":[-89.234532,43.02856],"type":"Point"}
}