{
  "type": "Feature",
  "properties": {
    "iso:country":"US",
    "sg:address":"1470 Gruber Rd",
    "sg:city":"Green Bay",
    "sg:classifiers":[
        {
            "category":"Manufacturing",
            "subcategory":"Printing",
            "type":"Manufacturing & Wholesale Goods"
        }
    ],
    "sg:phone":"+1 920 662 1654",
    "sg:postcode":"54313",
    "sg:province":"WI",
    "sg:tags":[
        "commercial"
    ],
    "wof:name":"Bay Promotions Inc",
    "wof:placetype":"venue"
},
  "geometry": {"coordinates":[-88.07263399999999,44.584006],"type":"Point"}
}