{
  "type": "Feature",
  "properties": {
    "iso:country":"US",
    "sg:address":"10508 Co Rd D",
    "sg:city":"Tomahawk",
    "sg:classifiers":[
        {
            "category":"Bars & Pubs",
            "type":"Food & Drink"
        }
    ],
    "sg:phone":"+1 715 453 3298",
    "sg:postcode":"54487",
    "sg:province":"WI",
    "sg:tags":[
        "drinking"
    ],
    "wof:name":"Herbs Country Tap",
    "wof:placetype":"venue"
},
  "geometry": {"coordinates":[-89.50743,45.48891],"type":"Point"}
}