{
  "type": "Feature",
  "properties": {
    "iso:country":"US",
    "sg:address":"3680 N 126th St",
    "sg:city":"Brookfield",
    "sg:classifiers":[
        {
            "category":"Home & Garden",
            "subcategory":"Furniture",
            "type":"Retail Goods"
        }
    ],
    "sg:phone":"+1 262 781 9906",
    "sg:postcode":"53005",
    "sg:province":"WI",
    "wof:name":"Stately Seating",
    "wof:placetype":"venue"
},
  "geometry": {"coordinates":[-88.06887999999999,43.085342],"type":"Point"}
}