{
  "type": "Feature",
  "properties": {
    "iso:country":"US",
    "sg:address":"688 Rader Rd",
    "sg:city":"Marinette",
    "sg:classifiers":[
        {
            "category":"Professional",
            "type":"Services"
        }
    ],
    "sg:phone":"+1 715 732 0400",
    "sg:postcode":"54143",
    "sg:province":"WI",
    "wof:name":"Debnmark Inc",
    "wof:placetype":"venue"
},
  "geometry": {"coordinates":[-87.628576,45.05642],"type":"Point"}
}