{
  "type": "Feature",
  "properties": {
    "iso:country":"US",
    "sg:address":"228 Paperjack Dr",
    "sg:city":"New Richmond",
    "sg:classifiers":[
        {
            "category":"Professional",
            "subcategory":"Employment Agencies",
            "type":"Services"
        }
    ],
    "sg:phone":"+1 715 246 6555",
    "sg:postcode":"54017",
    "sg:province":"WI",
    "sg:tags":[
        "help",
        "contractor"
    ],
    "wof:name":"Moffat Personnel Svc",
    "wof:placetype":"venue"
},
  "geometry": {"coordinates":[-92.53565,45.104353],"type":"Point"}
}