{
  "type": "Feature",
  "properties": {
    "iso:country":"US",
    "sg:address":"501 Orchard Ridge Rd",
    "sg:city":"Dodgeville",
    "sg:classifiers":[
        {
            "category":"Restaurant",
            "type":"Food & Drink"
        }
    ],
    "sg:phone":"+1 608 935 7107",
    "sg:postcode":"53533",
    "sg:province":"WI",
    "sg:tags":[
        "eating"
    ],
    "wof:name":"Julias Cafe LLC",
    "wof:placetype":"venue"
},
  "geometry": {"coordinates":[-90.120469,42.954232],"type":"Point"}
}