{
  "type": "Feature",
  "properties": {
    "iso:country":"US",
    "sg:address":"2464 S Oneida St",
    "sg:city":"Green Bay",
    "sg:classifiers":[
        {
            "category":"Home & Garden",
            "subcategory":"Building Materials",
            "type":"Retail Goods"
        }
    ],
    "sg:phone":"+1 920 498 3400",
    "sg:postcode":"54304",
    "sg:province":"WI",
    "sg:tags":[
        "paint",
        "floor",
        "covering"
    ],
    "wof:name":"Sherwin-Williams Paints",
    "wof:placetype":"venue"
},
  "geometry": {"coordinates":[-88.06949899999999,44.483455],"type":"Point"}
}