{
  "type": "Feature",
  "properties": {
    "iso:country":"US",
    "sg:address":"2710 Syene Rd",
    "sg:city":"Madison",
    "sg:classifiers":[
        {
            "category":"Manufacturing",
            "subcategory":"Toys & Sporting Goods",
            "type":"Manufacturing & Wholesale Goods"
        }
    ],
    "sg:phone":"+1 608 271 5155",
    "sg:postcode":"53713",
    "sg:province":"WI",
    "sg:tags":[
        "cue",
        "billiard",
        "mfg"
    ],
    "wof:name":"Viking Cue Mfg Inc",
    "wof:placetype":"venue"
},
  "geometry": {"coordinates":[-89.394085,43.033078],"type":"Point"}
}