{
  "type": "Feature",
  "properties": {
    "addr:full":"10536 State Hwy 70 E Woodruff WI 54568",
    "addr:housenumber":"10536",
    "addr:postcode":"54568",
    "addr:street":"State Hwy 70 E",
    "iso:country":"US",
    "sg:address":"10536 State Hwy 70 E",
    "sg:city":"Woodruff",
    "sg:classifiers":[
        {
            "category":"Retail",
            "subcategory":"Repair Shop",
            "type":"Services"
        }
    ],
    "sg:phone":"+1 715 356 9990",
    "sg:postcode":"54568",
    "sg:province":"WI",
    "sg:tags":[
        "snowmobile",
        "maintenance"
    ],
    "wof:name":"Welch's Service Ctr",
    "wof:placetype":"venue"
},
  "geometry": {"coordinates":[-89.654938,45.913041],"type":"Point"}
}