{
  "type": "Feature",
  "properties": {
    "iso:country":"US",
    "sg:address":"9330 41st Ave",
    "sg:city":"Pleasant Prairie",
    "sg:classifiers":[
        {
            "category":"Professional",
            "subcategory":"Advertising",
            "type":"Services"
        }
    ],
    "sg:phone":"+1 262 942 1758",
    "sg:postcode":"53158",
    "sg:province":"WI",
    "sg:tags":[
        "agency"
    ],
    "wof:name":"Kibar Asscts Adv Art",
    "wof:placetype":"venue"
},
  "geometry": {"coordinates":[-87.857078,42.536325],"type":"Point"}
}