{
  "type": "Feature",
  "properties": {
    "addr:full":"164 W 28th Ave Oshkosh WI 54902",
    "addr:housenumber":"164",
    "addr:postcode":"54902",
    "addr:street":"W 28Th Ave",
    "iso:country":"US",
    "sg:address":"164 W 28th Ave",
    "sg:city":"Oshkosh",
    "sg:classifiers":[
        {
            "category":"Manufacturing",
            "subcategory":"Metals",
            "type":"Manufacturing & Wholesale Goods"
        }
    ],
    "sg:phone":"+1 920 235 2124",
    "sg:postcode":"54902",
    "sg:province":"WI",
    "sg:tags":[
        "coating"
    ],
    "wof:name":"CRT",
    "wof:placetype":"venue"
},
  "geometry": {"coordinates":[-88.54220100000001,43.986557],"type":"Point"}
}