{
  "type": "Feature",
  "properties": {
    "iso:country":"US",
    "sg:address":"4012 Martin Ln",
    "sg:city":"Two Rivers",
    "sg:classifiers":[
        {
            "category":"Building & Trades",
            "subcategory":"Landscaping Services",
            "type":"Services"
        }
    ],
    "sg:phone":"+1 920 794 7163",
    "sg:postcode":"54241",
    "sg:province":"WI",
    "sg:tags":[
        "landscape"
    ],
    "wof:name":"Scriver Landscaping",
    "wof:placetype":"venue"
},
  "geometry": {"coordinates":[-87.59427700000001,44.171424],"type":"Point"}
}