{
  "type": "Feature",
  "properties": {
    "addr:full":"836 Park Ave Beloit WI 53511",
    "addr:housenumber":"836",
    "addr:postcode":"53511",
    "addr:street":"Park Ave",
    "iso:country":"US",
    "sg:address":"836 Park Ave",
    "sg:city":"Beloit",
    "sg:classifiers":[
        {
            "category":"Professional",
            "subcategory":"Testing Lab",
            "type":"Services"
        }
    ],
    "sg:phone":"+1 608 313 8741",
    "sg:postcode":"53511",
    "sg:province":"WI",
    "sg:tags":[
        "laboratory"
    ],
    "wof:name":"Compliance Testing Services",
    "wof:placetype":"venue"
},
  "geometry": {"coordinates":[-89.026881,42.505746],"type":"Point"}
}