{
  "type": "Feature",
  "properties": {
    "addr:full":"803 Knollwood Ct Waukesha WI 53188",
    "addr:housenumber":"803",
    "addr:postcode":"53188",
    "addr:street":"Knollwood Ct",
    "iso:country":"US",
    "sg:address":"803 Knollwood Ct",
    "sg:city":"Waukesha",
    "sg:classifiers":[
        {
            "category":"Shopping",
            "subcategory":"Crafts & Fabrics",
            "type":"Retail Goods"
        }
    ],
    "sg:phone":"+1 262 513 9920",
    "sg:postcode":"53188",
    "sg:province":"WI",
    "sg:tags":[
        "material",
        "needlework"
    ],
    "wof:name":"Paula's Canvas & Cross-Stitch",
    "wof:placetype":"venue"
},
  "geometry": {"coordinates":[-88.284502,43.004223],"type":"Point"}
}