{
  "type": "Feature",
  "properties": {
    "iso:country":"US",
    "sg:address":"12116 W Hadley St",
    "sg:city":"Wauwatosa",
    "sg:classifiers":[
        {
            "category":"Insurance",
            "subcategory":"Hazard Insurance",
            "type":"Services"
        }
    ],
    "sg:phone":"+1 414 453 1970",
    "sg:postcode":"53222",
    "sg:province":"WI",
    "sg:tags":[
        "casualty"
    ],
    "wof:name":"Hartford Personal Insurance",
    "wof:placetype":"venue"
},
  "geometry": {"coordinates":[-88.064291,43.069459],"type":"Point"}
}