{
  "type": "Feature",
  "properties": {
    "addr:full":"303 Butternut Dr Delavan WI 53115",
    "addr:housenumber":"303",
    "addr:postcode":"53115",
    "addr:street":"Butternut Dr",
    "iso:country":"US",
    "sg:address":"303 Butternut Dr",
    "sg:city":"Delavan",
    "sg:classifiers":[
        {
            "category":"Arts & Performance",
            "subcategory":"Theater",
            "type":"Entertainment"
        }
    ],
    "sg:phone":"+1 262 728 1950",
    "sg:postcode":"53115",
    "sg:province":"WI",
    "sg:tags":[
        "group"
    ],
    "wof:name":"Whistles T Clown",
    "wof:placetype":"venue"
},
  "geometry": {"coordinates":[-88.669392,42.629732],"type":"Point"}
}