{
  "type": "Feature",
  "properties": {
    "iso:country":"US",
    "sg:address":"2350 W Pershing St",
    "sg:city":"Appleton",
    "sg:classifiers":[
        {
            "category":"Wholesale",
            "subcategory":"Electrical",
            "type":"Manufacturing & Wholesale Goods"
        }
    ],
    "sg:phone":"+1 920 380 2400",
    "sg:postcode":"54914",
    "sg:province":"WI",
    "sg:tags":[
        "equipment",
        "electric",
        "supply"
    ],
    "wof:name":"Eaton Corp",
    "wof:placetype":"venue"
},
  "geometry": {"coordinates":[-88.443659,44.28414],"type":"Point"}
}