{
  "type": "Feature",
  "properties": {
    "addr:full":"5110 Washington Ave Racine WI 53406",
    "addr:housenumber":"5110",
    "addr:postcode":"53406",
    "addr:street":"Washington Ave",
    "iso:country":"US",
    "sg:address":"5110 Washington Ave",
    "sg:city":"Racine",
    "sg:classifiers":[
        {
            "category":"Banks & Credit Unions",
            "subcategory":"Bank",
            "type":"Services"
        }
    ],
    "sg:phone":"+1 262 635 8179",
    "sg:postcode":"53406",
    "sg:province":"WI",
    "sg:tags":[
        "cashing",
        "check"
    ],
    "wof:name":"Advance America",
    "wof:placetype":"venue"
},
  "geometry": {"coordinates":[-87.841948,42.718849],"type":"Point"}
}