{
  "type": "Feature",
  "properties": {
    "iso:country":"US",
    "sg:address":"7071 S 13th St",
    "sg:city":"Oak Creek",
    "sg:classifiers":[
        {
            "category":"Freight",
            "type":"Transportation"
        }
    ],
    "sg:phone":"+1 414 571 9335",
    "sg:postcode":"53154",
    "sg:province":"WI",
    "sg:tags":[
        "arrangement"
    ],
    "wof:name":"Glaus Trucking",
    "wof:placetype":"venue"
},
  "geometry": {"coordinates":[-87.930794,42.91747],"type":"Point"}
}