{
  "type": "Feature",
  "properties": {
    "iso:country":"US",
    "sg:address":"10611 State Hwy 13 S",
    "sg:city":"Wisconsin Rapids",
    "sg:classifiers":[
        {
            "category":"Organizations",
            "subcategory":"Religious Organization",
            "type":"Services"
        }
    ],
    "sg:phone":"+1 715 325 3355",
    "sg:postcode":"54494",
    "sg:province":"WI",
    "wof:name":"Good Shepherd Lutheran Church",
    "wof:placetype":"venue"
},
  "geometry": {"coordinates":[-89.810174,44.297906],"type":"Point"}
}