{
  "type": "Feature",
  "properties": {
    "iso:country":"US",
    "sg:address":"6616 W Council Hill Rd",
    "sg:city":"Scales Mound",
    "sg:classifiers":[
        {
            "category":"Professional",
            "type":"Services"
        }
    ],
    "sg:phone":"+1 815 777 3505",
    "sg:postcode":"61075",
    "sg:province":"WI",
    "wof:name":"Wilbur Wills",
    "wof:placetype":"venue"
},
  "geometry": {"coordinates":[-90.35399700000001,42.487897],"type":"Point"}
}