{
  "type": "Feature",
  "properties": {
    "addr:full":"130 W Ryan Rd Oak Creek WI 53154",
    "addr:housenumber":"130",
    "addr:postcode":"53154",
    "addr:street":"W Ryan Rd",
    "iso:country":"US",
    "sg:address":"130 W Ryan Rd",
    "sg:city":"Oak Creek",
    "sg:classifiers":[
        {
            "category":"Restaurant",
            "type":"Food & Drink"
        }
    ],
    "sg:phone":"+1 414 762 5010",
    "sg:postcode":"53154",
    "sg:province":"WI",
    "sg:website":"www.ervsmug.com",
    "wof:name":"Erv's Mug",
    "wof:placetype":"venue"
},
  "geometry": {"coordinates":[-87.91439800000001,42.872299],"type":"Point"}
}