{
  "type": "Feature",
  "properties": {
    "iso:country":"US",
    "sg:address":"7526 State Hwy 33",
    "sg:city":"Cashton",
    "sg:classifiers":[
        {
            "category":"Organizations",
            "subcategory":"Religious Organization",
            "type":"Services"
        }
    ],
    "sg:phone":"+1 608 654 7977",
    "sg:postcode":"54619",
    "sg:province":"WI",
    "sg:tags":[
        "church"
    ],
    "wof:name":"Portland Lutheran Church",
    "wof:placetype":"venue"
},
  "geometry": {"coordinates":[-90.856691,43.767691],"type":"Point"}
}