{
  "type": "Feature",
  "properties": {
    "iso:country":"US",
    "sg:address":"6890 Lakeview Rd",
    "sg:city":"Crivitz",
    "sg:classifiers":[
        {
            "category":"Building & Trades",
            "subcategory":"Construction",
            "type":"Services"
        }
    ],
    "sg:phone":"+1 715 854 2441",
    "sg:postcode":"54114",
    "sg:province":"WI",
    "sg:tags":[
        "house"
    ],
    "wof:name":"Baranek Enterprises",
    "wof:placetype":"venue"
},
  "geometry": {"coordinates":[-87.938667,45.258184],"type":"Point"}
}