{
  "type": "Feature",
  "properties": {
    "iso:country":"US",
    "sg:address":"102 Lothe Rd",
    "sg:city":"Marshall",
    "sg:classifiers":[
        {
            "category":"Social Services",
            "subcategory":"Child Care",
            "type":"Services"
        }
    ],
    "sg:phone":"+1 608 655 3653",
    "sg:postcode":"53559",
    "sg:province":"WI",
    "sg:tags":[
        "day"
    ],
    "wof:name":"Little Fmly Daycare Preschool",
    "wof:placetype":"venue"
},
  "geometry": {"coordinates":[-89.070638,43.170436],"type":"Point"}
}