{
  "type": "Feature",
  "properties": {
    "iso:country":"US",
    "sg:address":"2005 Highland Ave",
    "sg:city":"Eau Claire",
    "sg:classifiers":[
        {
            "category":"Insurance",
            "subcategory":"Insurance Agent",
            "type":"Services"
        }
    ],
    "sg:phone":"+1 715 835 5113",
    "sg:postcode":"54701",
    "sg:province":"WI",
    "wof:name":"Principal Financial Group",
    "wof:placetype":"venue"
},
  "geometry": {"coordinates":[-91.47346899999999,44.807306],"type":"Point"}
}