{
  "type": "Feature",
  "properties": {
    "iso:country":"US",
    "sg:address":"500 E Jefferson St",
    "sg:city":"Viroqua",
    "sg:classifiers":[
        {
            "category":"Health Services",
            "subcategory":"Chiropractor",
            "type":"Services"
        }
    ],
    "sg:phone":"+1 608 637 7516",
    "sg:postcode":"54665",
    "sg:province":"WI",
    "wof:name":"Bright Life Ctr",
    "wof:placetype":"venue"
},
  "geometry": {"coordinates":[-90.88029299999999,43.55542],"type":"Point"}
}