{
  "type": "Feature",
  "properties": {
    "iso:country":"US",
    "sg:address":"820 West St",
    "sg:city":"Watertown",
    "sg:classifiers":[
        {
            "category":"Manufacturing",
            "subcategory":"Tools & Machinery",
            "type":"Manufacturing & Wholesale Goods"
        }
    ],
    "sg:phone":"+1 920 261 4112",
    "sg:postcode":"53094",
    "sg:province":"WI",
    "sg:tags":[
        "food",
        "product"
    ],
    "sg:website":"www.kuselequipment.com",
    "wof:name":"Kusel Equipment Co",
    "wof:placetype":"venue"
},
  "geometry": {"coordinates":[-88.74165600000001,43.189741],"type":"Point"}
}