{
  "type": "Feature",
  "properties": {
    "addr:full":"4661 S 27th St Milwaukee WI 53221",
    "addr:housenumber":"4661",
    "addr:postcode":"53221",
    "addr:street":"S 27Th St",
    "iso:country":"US",
    "sg:address":"4661 S 27th St",
    "sg:city":"Milwaukee",
    "sg:classifiers":[
        {
            "category":"Banks & Credit Unions",
            "subcategory":"Bank",
            "type":"Services"
        }
    ],
    "sg:phone":"+1 414 282 4661",
    "sg:postcode":"53221",
    "sg:province":"WI",
    "sg:website":"http://www.guarantybank.com",
    "wof:name":"Guaranty Bank",
    "wof:placetype":"venue"
},
  "geometry": {"coordinates":[-87.94886,42.96022],"type":"Point"}
}