{
  "type": "Feature",
  "properties": {
    "iso:country":"US",
    "sg:address":"1646 US Hwy 51",
    "sg:city":"Mercer",
    "sg:classifiers":[
        {
            "category":"Building & Trades",
            "subcategory":"Construction",
            "type":"Services"
        }
    ],
    "sg:phone":"+1 715 476 2966",
    "sg:postcode":"54547",
    "sg:province":"WI",
    "sg:tags":[
        "industrial"
    ],
    "wof:name":"Snowbabies Inc",
    "wof:placetype":"venue"
},
  "geometry": {"coordinates":[-90.011556,46.132128],"type":"Point"}
}