{
  "type": "Feature",
  "properties": {
    "iso:country":"US",
    "sg:address":"815 S Ithaca Pl",
    "sg:city":"Sturgeon Bay",
    "sg:classifiers":[
        {
            "category":"Social Services",
            "subcategory":"Child Care",
            "type":"Services"
        }
    ],
    "sg:phone":"+1 920 743 0200",
    "sg:postcode":"54235",
    "sg:province":"WI",
    "sg:tags":[
        "day",
        "family"
    ],
    "wof:name":"Karens Day Care Center",
    "wof:placetype":"venue"
},
  "geometry": {"coordinates":[-87.391175,44.820158],"type":"Point"}
}