{
  "type": "Feature",
  "properties": {
    "addr:full":"503 S Center Ave Merrill WI 54452",
    "addr:housenumber":"503",
    "addr:postcode":"54452",
    "addr:street":"S Center Ave",
    "iso:country":"US",
    "sg:address":"503 S Center Ave",
    "sg:city":"Merrill",
    "sg:classifiers":[
        {
            "category":"Health Services",
            "subcategory":"Doctor",
            "type":"Services"
        }
    ],
    "sg:phone":"+1 715 539 2346",
    "sg:postcode":"54452",
    "sg:province":"WI",
    "sg:tags":[
        "clinic"
    ],
    "wof:name":"Cardiac Clinic",
    "wof:placetype":"venue"
},
  "geometry": {"coordinates":[-89.682743,45.176984],"type":"Point"}
}