{
  "type": "Feature",
  "properties": {
    "iso:country":"US",
    "sg:address":"5170 Co Rd Mm",
    "sg:city":"Shawano",
    "sg:classifiers":[
        {
            "category":"Government",
            "subcategory":"Office",
            "type":"Public Place"
        }
    ],
    "sg:phone":"+1 715 526 6527",
    "sg:postcode":"54166",
    "sg:province":"WI",
    "sg:tags":[
        "executive"
    ],
    "wof:name":"Richmond Town Hall",
    "wof:placetype":"venue"
},
  "geometry": {"coordinates":[-88.624487,44.781041],"type":"Point"}
}