{
  "type": "Feature",
  "properties": {
    "iso:country":"US",
    "sg:address":"14404 Fulmar Dr",
    "sg:city":"South Beloit",
    "sg:classifiers":[
        {
            "category":"Building & Trades",
            "subcategory":"Construction",
            "type":"Services"
        }
    ],
    "sg:phone":"+1 815 389 2566",
    "sg:postcode":"61080",
    "sg:province":"WI",
    "sg:tags":[
        "concrete",
        "contractor"
    ],
    "wof:name":"Hale Concrete Construction",
    "wof:placetype":"venue"
},
  "geometry": {"coordinates":[-89.03625,42.468402],"type":"Point"}
}