{
  "type": "Feature",
  "properties": {
    "addr:full":"522 Co Rd M River Falls WI 54022",
    "addr:housenumber":"522",
    "addr:postcode":"54022",
    "addr:street":"Co Rd M",
    "iso:country":"US",
    "sg:address":"522 Co Rd M",
    "sg:city":"River Falls",
    "sg:classifiers":[
        {
            "category":"Building & Trades",
            "subcategory":"Cleaning & Sanitation",
            "type":"Services"
        }
    ],
    "sg:phone":"+1 715 425 6594",
    "sg:postcode":"54022",
    "sg:province":"WI",
    "sg:tags":[
        "janitor"
    ],
    "wof:name":"Langlois Building Maintenance",
    "wof:placetype":"venue"
},
  "geometry": {"coordinates":[-92.696063,44.862458],"type":"Point"}
}