{
  "type": "Feature",
  "properties": {
    "iso:country":"US",
    "sg:address":"2574 Oakbrook Ct",
    "sg:city":"Appleton",
    "sg:classifiers":[
        {
            "category":"Building & Trades",
            "subcategory":"Construction",
            "type":"Services"
        }
    ],
    "sg:phone":"+1 920 687 0404",
    "sg:postcode":"54915",
    "sg:province":"WI",
    "sg:tags":[
        "paving",
        "asphalt",
        "contractor"
    ],
    "wof:name":"Ace Black Asphalt Seal Coating",
    "wof:placetype":"venue"
},
  "geometry": {"coordinates":[-88.316901,44.250367],"type":"Point"}
}