{
  "type": "Feature",
  "properties": {
    "iso:country":"US",
    "sg:address":"4162 Ridge Rd",
    "sg:city":"Kewaskum",
    "sg:classifiers":[
        {
            "category":"Farming",
            "subcategory":"Dairy Farm",
            "type":"Manufacturing & Wholesale Goods"
        }
    ],
    "sg:phone":"+1 262 626 2205",
    "sg:postcode":"53040",
    "sg:province":"WI",
    "wof:name":"Michael Lettow",
    "wof:placetype":"venue"
},
  "geometry": {"coordinates":[-88.244367,43.484929],"type":"Point"}
}