{
  "type": "Feature",
  "properties": {
    "iso:country":"US",
    "sg:address":"1260 Co Rd Xx",
    "sg:city":"Berlin",
    "sg:classifiers":[
        {
            "category":"Farming",
            "subcategory":"Farm",
            "type":"Manufacturing & Wholesale Goods"
        }
    ],
    "sg:phone":"+1 920 361 4519",
    "sg:postcode":"54923",
    "sg:province":"WI",
    "sg:tags":[
        "crop",
        "general"
    ],
    "wof:name":"Gordon Przybyl",
    "wof:placetype":"venue"
},
  "geometry": {"coordinates":[-88.916588,44.022023],"type":"Point"}
}