{
  "type": "Feature",
  "properties": {
    "iso:country":"US",
    "sg:address":"8133 N Granville Woods Rd",
    "sg:city":"Milwaukee",
    "sg:classifiers":[
        {
            "category":"Wholesale",
            "subcategory":"Stationery",
            "type":"Manufacturing & Wholesale Goods"
        }
    ],
    "sg:phone":"+1 414 771 4300",
    "sg:postcode":"53223",
    "sg:province":"WI",
    "sg:tags":[
        "mill",
        "paper",
        "broker",
        "representative"
    ],
    "wof:name":"A D Schinner Co",
    "wof:placetype":"venue"
},
  "geometry": {"coordinates":[-87.996481,43.16544],"type":"Point"}
}