{
  "type": "Feature",
  "properties": {
    "iso:country":"US",
    "sg:address":"205 Dodge St",
    "sg:city":"Kaukauna",
    "sg:classifiers":[
        {
            "category":"Professional",
            "subcategory":"Business Services",
            "type":"Services"
        }
    ],
    "sg:phone":"+1 920 766 0424",
    "sg:postcode":"54130",
    "sg:province":"WI",
    "sg:tags":[
        "water",
        "treatment"
    ],
    "wof:name":"Griesbach Diamond Water",
    "wof:placetype":"venue"
},
  "geometry": {"coordinates":[-88.27166699999999,44.276366],"type":"Point"}
}