{
  "type": "Feature",
  "properties": {
    "addr:full":"900 N Main St Oshkosh WI 54901",
    "addr:housenumber":"900",
    "addr:postcode":"54901",
    "addr:street":"N Main St",
    "iso:country":"US",
    "sg:address":"900 N Main St",
    "sg:city":"Oshkosh",
    "sg:classifiers":[
        {
            "category":"Restaurant",
            "type":"Food & Drink"
        }
    ],
    "sg:phone":"+1 920 235 8778",
    "sg:postcode":"54901",
    "sg:province":"WI",
    "wof:name":"Doctor Benzie's Pizza",
    "wof:placetype":"venue"
},
  "geometry": {"coordinates":[-88.53758500000001,44.028541],"type":"Point"}
}