{
  "type": "Feature",
  "properties": {
    "iso:country":"US",
    "sg:address":"4185 Co Rd Ab",
    "sg:city":"Madison",
    "sg:classifiers":[
        {
            "category":"Autos & Motor Vehicles",
            "subcategory":"Automobile Sales",
            "type":"Retail Goods"
        }
    ],
    "sg:phone":"+1 608 224 2142",
    "sg:postcode":"53718",
    "sg:province":"WI",
    "sg:tags":[
        "car",
        "dealer"
    ],
    "wof:name":"D C's Auto & Truck",
    "wof:placetype":"venue"
},
  "geometry": {"coordinates":[-89.262338,43.073669],"type":"Point"}
}