{
  "type": "Feature",
  "properties": {
    "addr:full":"8804 State Hwy 56 Viroqua WI 54665",
    "addr:housenumber":"8804",
    "addr:postcode":"54665",
    "addr:street":"State Hwy 56",
    "iso:country":"US",
    "sg:address":"8804 State Hwy 56",
    "sg:city":"Viroqua",
    "sg:classifiers":[
        {
            "category":"Wholesale",
            "subcategory":"Auto Parts",
            "type":"Manufacturing & Wholesale Goods"
        }
    ],
    "sg:phone":"+1 608 637 2230",
    "sg:postcode":"54665",
    "sg:province":"WI",
    "sg:tags":[
        "automobile",
        "wrecking"
    ],
    "wof:name":"Sheldon's Auto Wrecking Co",
    "wof:placetype":"venue"
},
  "geometry": {"coordinates":[-90.81962300000001,43.54861],"type":"Point"}
}