{
  "type": "Feature",
  "properties": {
    "addr:full":"433 Kalb Ave Green Bay WI 54301",
    "addr:housenumber":"433",
    "addr:postcode":"54301",
    "addr:street":"Kalb Ave",
    "iso:country":"US",
    "sg:address":"433 Kalb Ave",
    "sg:city":"Green Bay",
    "sg:classifiers":[
        {
            "category":"Building & Trades",
            "subcategory":"Construction",
            "type":"Services"
        }
    ],
    "sg:phone":"+1 920 435 5839",
    "sg:postcode":"54301",
    "sg:province":"WI",
    "sg:tags":[
        "floor",
        "laying",
        "contractor"
    ],
    "wof:name":"Flagstad Hardwood Floors LLC",
    "wof:placetype":"venue"
},
  "geometry": {"coordinates":[-88.01131100000001,44.488758],"type":"Point"}
}