{
  "type": "Feature",
  "properties": {
    "iso:country":"US",
    "sg:address":"3350 Evergreen Ave",
    "sg:city":"Wisconsin Rapids",
    "sg:classifiers":[
        {
            "category":"Organizations",
            "subcategory":"Religious Organization",
            "type":"Services"
        }
    ],
    "sg:phone":"+1 715 325 5405",
    "sg:postcode":"54494",
    "sg:province":"WI",
    "sg:tags":[
        "church"
    ],
    "wof:name":"Restoration Church",
    "wof:placetype":"venue"
},
  "geometry": {"coordinates":[-89.783844,44.291874],"type":"Point"}
}