{
  "type": "Feature",
  "properties": {
    "iso:country":"US",
    "sg:address":"416 Meadow Oak Trl",
    "sg:city":"De Forest",
    "sg:classifiers":[
        {
            "category":"Social Services",
            "subcategory":"Child Care",
            "type":"Services"
        }
    ],
    "sg:phone":"+1 608 846 1563",
    "sg:postcode":"53532",
    "sg:province":"WI",
    "sg:tags":[
        "day"
    ],
    "wof:name":"Daycare",
    "wof:placetype":"venue"
},
  "geometry": {"coordinates":[-89.359241,43.249571],"type":"Point"}
}