{
  "type": "Feature",
  "properties": {
    "iso:country":"US",
    "sg:address":"6406 Odana Rd",
    "sg:city":"Madison",
    "sg:classifiers":[
        {
            "category":"Wholesale",
            "subcategory":"Machinery & Supplies",
            "type":"Manufacturing & Wholesale Goods"
        }
    ],
    "sg:phone":"+1 608 276 6414",
    "sg:postcode":"53719",
    "sg:province":"WI",
    "sg:tags":[
        "equipment",
        "management",
        "establishment",
        "consult"
    ],
    "wof:name":"Quility",
    "wof:placetype":"venue"
},
  "geometry": {"coordinates":[-89.490048,43.054933],"type":"Point"}
}