{
  "type": "Feature",
  "properties": {
    "iso:country":"US",
    "sg:address":"710 N Main St",
    "sg:city":"River Falls",
    "sg:classifiers":[
        {
            "category":"Insurance",
            "subcategory":"Insurance Agent",
            "type":"Services"
        }
    ],
    "sg:phone":"+1 715 426 6300",
    "sg:postcode":"54022",
    "sg:province":"WI",
    "wof:name":"State Farm Insurance",
    "wof:placetype":"venue"
},
  "geometry": {"coordinates":[-92.621815,44.867166],"type":"Point"}
}