{
  "type": "Feature",
  "properties": {
    "iso:country":"US",
    "sg:address":"7845 State Hwy 144",
    "sg:city":"West Bend",
    "sg:classifiers":[
        {
            "category":"Personal",
            "subcategory":"Beauty Salon",
            "type":"Services"
        }
    ],
    "sg:phone":"+1 262 334 9117",
    "sg:postcode":"53090",
    "sg:province":"WI",
    "sg:tags":[
        "shop"
    ],
    "wof:name":"Hair Designs By Judy",
    "wof:placetype":"venue"
},
  "geometry": {"coordinates":[-88.14648,43.471219],"type":"Point"}
}