{
  "type": "Feature",
  "properties": {
    "iso:country":"US",
    "sg:address":"200 N Main St",
    "sg:city":"Loyal",
    "sg:classifiers":[
        {
            "category":"Home & Garden",
            "subcategory":"Furniture",
            "type":"Retail Goods"
        }
    ],
    "sg:phone":"+1 715 255 8244",
    "sg:postcode":"54446",
    "sg:province":"WI",
    "wof:name":"Zepplin's Furniture & Carpet",
    "wof:placetype":"venue"
},
  "geometry": {"coordinates":[-90.495966,44.738094],"type":"Point"}
}