{
  "type": "Feature",
  "properties": {
    "iso:country":"US",
    "sg:address":"110 E 2nd St",
    "sg:city":"Superior",
    "sg:classifiers":[
        {
            "category":"Travel",
            "subcategory":"Hotels & Motels",
            "type":"Entertainment"
        }
    ],
    "sg:phone":"+1 715 392 9434",
    "sg:postcode":"54880",
    "sg:province":"WI",
    "sg:tags":[
        "lodging"
    ],
    "sg:website":"http://www.daysinn.com",
    "wof:name":"Days Inn",
    "wof:placetype":"venue"
},
  "geometry": {"coordinates":[-92.071147,46.723996],"type":"Point"}
}