{
  "type": "Feature",
  "properties": {
    "iso:country":"US",
    "sg:address":"4755 Hilldale Dr",
    "sg:city":"Edgar",
    "sg:classifiers":[
        {
            "category":"Building & Trades",
            "subcategory":"Landscaping Services",
            "type":"Services"
        }
    ],
    "sg:phone":"+1 715 352 2672",
    "sg:postcode":"54426",
    "sg:province":"WI",
    "sg:tags":[
        "landscape"
    ],
    "wof:name":"Pilgrim Enterprises",
    "wof:placetype":"venue"
},
  "geometry": {"coordinates":[-90.004613,44.931637],"type":"Point"}
}