{
  "type": "Feature",
  "properties": {
    "iso:country":"US",
    "sg:address":"6179 State Hwy 35",
    "sg:city":"Superior",
    "sg:classifiers":[
        {
            "category":"Building & Trades",
            "subcategory":"Construction",
            "type":"Services"
        }
    ],
    "sg:phone":"+1 715 399 2300",
    "sg:postcode":"54880",
    "sg:province":"WI",
    "sg:tags":[
        "house"
    ],
    "wof:name":"1st Quality Builders",
    "wof:placetype":"venue"
},
  "geometry": {"coordinates":[-92.104389,46.664952],"type":"Point"}
}