{
  "type": "Feature",
  "properties": {
    "iso:country":"US",
    "sg:address":"4430 Trump Lake Rd",
    "sg:city":"Wabeno",
    "sg:classifiers":[
        {
            "category":"Manufacturing",
            "subcategory":"Wood Products",
            "type":"Manufacturing & Wholesale Goods"
        }
    ],
    "sg:phone":"+1 715 473 3807",
    "sg:postcode":"54566",
    "sg:province":"WI",
    "sg:tags":[
        "mfg"
    ],
    "wof:name":"Dobbratz Skidding Inc",
    "wof:placetype":"venue"
},
  "geometry": {"coordinates":[-88.674663,45.464443],"type":"Point"}
}