{
  "type": "Feature",
  "properties": {
    "iso:country":"US",
    "sg:address":"7106 S Chase Rd",
    "sg:city":"Sobieski",
    "sg:classifiers":[
        {
            "category":"Professional",
            "type":"Services"
        }
    ],
    "sg:phone":"+1 920 822 5366",
    "sg:postcode":"54171",
    "sg:province":"WI",
    "wof:name":"Franklin L Hoffmann",
    "wof:placetype":"venue"
},
  "geometry": {"coordinates":[-88.116549,44.691731],"type":"Point"}
}