{
  "type": "Feature",
  "properties": {
    "iso:country":"US",
    "sg:address":"1480 Cross Country Rd",
    "sg:city":"Verona",
    "sg:classifiers":[
        {
            "category":"Building & Trades",
            "subcategory":"Construction",
            "type":"Services"
        }
    ],
    "sg:phone":"+1 608 848 0210",
    "sg:postcode":"53593",
    "sg:province":"WI",
    "sg:tags":[
        "general",
        "contractor"
    ],
    "wof:name":"J P Cullen & Sons Gen Constr",
    "wof:placetype":"venue"
},
  "geometry": {"coordinates":[-89.511985,43.001326],"type":"Point"}
}