{
  "type": "Feature",
  "properties": {
    "iso:country":"US",
    "sg:address":"7712 W Mineral Point Rd",
    "sg:city":"Janesville",
    "sg:classifiers":[
        {
            "category":"Shopping",
            "subcategory":"Florist",
            "type":"Retail Goods"
        }
    ],
    "sg:phone":"+1 608 876 4224",
    "sg:postcode":"53548",
    "sg:province":"WI",
    "wof:name":"Apple Acres Ranch",
    "wof:placetype":"venue"
},
  "geometry": {"coordinates":[-89.170031,42.686844],"type":"Point"}
}