{
  "type": "Feature",
  "properties": {
    "iso:country":"US",
    "sg:address":"50256 Co Rd K",
    "sg:city":"Osseo",
    "sg:classifiers":[
        {
            "category":"Building & Trades",
            "subcategory":"Construction",
            "type":"Services"
        }
    ],
    "sg:phone":"+1 715 597 2037",
    "sg:postcode":"54758",
    "sg:province":"WI",
    "sg:tags":[
        "contractor"
    ],
    "wof:name":"Stensen Construction Contr",
    "wof:placetype":"venue"
},
  "geometry": {"coordinates":[-91.24238,44.592243],"type":"Point"}
}