{
  "type": "Feature",
  "properties": {
    "iso:country":"US",
    "sg:address":"115 W Hill St",
    "sg:city":"Blanchardville",
    "sg:classifiers":[
        {
            "category":"Freight",
            "type":"Transportation"
        }
    ],
    "sg:phone":"+1 608 523 2314",
    "sg:postcode":"53516",
    "sg:province":"WI",
    "sg:tags":[
        "operator",
        "local",
        "trucking"
    ],
    "wof:name":"Rindy Trucking LLC",
    "wof:placetype":"venue"
},
  "geometry": {"coordinates":[-89.86253600000001,42.813412],"type":"Point"}
}