{
  "type": "Feature",
  "properties": {
    "addr:full":"3714 S Dutch Mill Rd Madison WI 53718",
    "addr:housenumber":"3714",
    "addr:postcode":"53718",
    "addr:street":"S Dutch Mill Rd",
    "iso:country":"US",
    "sg:address":"3714 S Dutch Mill Rd",
    "sg:city":"Madison",
    "sg:classifiers":[
        {
            "category":"Retail",
            "subcategory":"Auto Rental",
            "type":"Services"
        }
    ],
    "sg:phone":"+1 608 221 1818",
    "sg:postcode":"53718",
    "sg:province":"WI",
    "sg:tags":[
        "passenger",
        "car"
    ],
    "wof:name":"Tom & Jerry Transit LLC",
    "wof:placetype":"venue"
},
  "geometry": {"coordinates":[-89.30376099999999,43.045252],"type":"Point"}
}