{
  "type": "Feature",
  "properties": {
    "iso:country":"US",
    "sg:address":"41 S Park Ave",
    "sg:city":"Fond Du Lac",
    "sg:classifiers":[
        {
            "category":"Freight",
            "type":"Transportation"
        }
    ],
    "sg:phone":"+1 920 929 9709",
    "sg:postcode":"54935",
    "sg:province":"WI",
    "sg:tags":[
        "commercial",
        "storage"
    ],
    "wof:name":"A-Ok Mini Storage",
    "wof:placetype":"venue"
},
  "geometry": {"coordinates":[-88.438871,43.777272],"type":"Point"}
}