{
  "type": "Feature",
  "properties": {
    "iso:country":"US",
    "sg:address":"301 E Cook St",
    "sg:city":"Portage",
    "sg:classifiers":[
        {
            "category":"Communications",
            "subcategory":"Television Station",
            "type":"Services"
        }
    ],
    "sg:phone":"+1 608 742 7796",
    "sg:postcode":"53901",
    "sg:province":"WI",
    "sg:tags":[
        "broadcasting",
        "co"
    ],
    "wof:name":"WKOW TV Ing",
    "wof:placetype":"venue"
},
  "geometry": {"coordinates":[-89.45549699999999,43.541709],"type":"Point"}
}