{
  "type": "Feature",
  "properties": {
    "iso:country":"US",
    "sg:address":"133 N Oneida Ave",
    "sg:city":"Rhinelander",
    "sg:classifiers":[
        {
            "category":"Wholesale",
            "subcategory":"Machinery & Supplies",
            "type":"Manufacturing & Wholesale Goods"
        }
    ],
    "sg:phone":"+1 715 362 3817",
    "sg:postcode":"54501",
    "sg:province":"WI",
    "sg:tags":[
        "brush"
    ],
    "wof:name":"Fuller Brush Co",
    "wof:placetype":"venue"
},
  "geometry": {"coordinates":[-89.408577,45.63904],"type":"Point"}
}