{
  "type": "Feature",
  "properties": {
    "iso:country":"US",
    "sg:address":"6028 County Line Rd",
    "sg:city":"Delavan",
    "sg:classifiers":[
        {
            "category":"Building & Trades",
            "subcategory":"Construction",
            "type":"Services"
        }
    ],
    "sg:phone":"+1 262 473 7169",
    "sg:postcode":"53115",
    "sg:province":"WI",
    "sg:tags":[
        "house"
    ],
    "wof:name":"Streib Construction",
    "wof:placetype":"venue"
},
  "geometry": {"coordinates":[-88.77783599999999,42.710847],"type":"Point"}
}