{
  "type": "Feature",
  "properties": {
    "iso:country":"US",
    "sg:address":"622 Fremont St",
    "sg:city":"Kiel",
    "sg:classifiers":[
        {
            "category":"Banks & Credit Unions",
            "subcategory":"Bank",
            "type":"Services"
        }
    ],
    "sg:phone":"+1 920 894 2278",
    "sg:postcode":"53042",
    "sg:province":"WI",
    "wof:name":"Bank Mutual",
    "wof:placetype":"venue"
},
  "geometry": {"coordinates":[-88.03940900000001,43.912636],"type":"Point"}
}