{
  "type": "Feature",
  "properties": {
    "addr:full":"8214 W Cleveland Ave Milwaukee WI 53227",
    "addr:housenumber":"8214",
    "addr:postcode":"53227",
    "addr:street":"W Cleveland Ave",
    "iso:country":"US",
    "sg:address":"8214 W Cleveland Ave",
    "sg:city":"Milwaukee",
    "sg:classifiers":[
        {
            "category":"Government",
            "subcategory":"Office",
            "type":"Public Place"
        }
    ],
    "sg:phone":"+1 414 543 5578",
    "sg:postcode":"53227",
    "sg:province":"WI",
    "sg:tags":[
        "county",
        "park"
    ],
    "wof:name":"Parks-Mccarty Park",
    "wof:placetype":"venue"
},
  "geometry": {"coordinates":[-88.015503,42.995563],"type":"Point"}
}