{
  "type": "Feature",
  "properties": {
    "addr:full":"21975 Kerry Ave Wilton WI 54670",
    "addr:housenumber":"21975",
    "addr:postcode":"54670",
    "addr:street":"Kerry Ave",
    "iso:country":"US",
    "sg:address":"21975 Kerry Ave",
    "sg:city":"Wilton",
    "sg:classifiers":[
        {
            "category":"Shopping",
            "subcategory":"Computers & Home Electronics",
            "type":"Retail Goods"
        }
    ],
    "sg:phone":"+1 608 435 6424",
    "sg:postcode":"54670",
    "sg:province":"WI",
    "wof:name":"Zumco Inc",
    "wof:placetype":"venue"
},
  "geometry": {"coordinates":[-90.552086,43.851057],"type":"Point"}
}