{
  "type": "Feature",
  "properties": {
    "addr:full":"1802 Stout Rd Menomonie WI 54751",
    "addr:housenumber":"1802",
    "addr:postcode":"54751",
    "addr:street":"Stout Rd",
    "iso:country":"US",
    "sg:address":"1802 Stout Rd",
    "sg:city":"Menomonie",
    "sg:classifiers":[
        {
            "category":"Shopping",
            "subcategory":"Florist",
            "type":"Retail Goods"
        },
        {
            "category":"Farming",
            "subcategory":"Nursery",
            "type":"Manufacturing & Wholesale Goods"
        }
    ],
    "sg:phone":"+1 715 235 0902",
    "sg:postcode":"54751",
    "sg:province":"WI",
    "sg:tags":[
        "ornamental"
    ],
    "wof:name":"Lakeview Floral Inc",
    "wof:placetype":"venue"
},
  "geometry": {"coordinates":[-91.90616300000001,44.880833],"type":"Point"}
}