{
  "type": "Feature",
  "properties": {
    "addr:full":"7217 Saint James St Milwaukee WI 53213",
    "addr:housenumber":"7217",
    "addr:postcode":"53213",
    "addr:street":"Saint James St",
    "iso:country":"US",
    "sg:address":"7217 Saint James St",
    "sg:city":"Milwaukee",
    "sg:phone":"+1 414 698 8414",
    "sg:postcode":"53213",
    "sg:province":"WI",
    "wof:name":"Built To Last",
    "wof:placetype":"venue"
},
  "geometry": {"coordinates":[-88.00233299999999,43.049185],"type":"Point"}
}