{
  "type": "Feature",
  "properties": {
    "addr:full":"7859 E Clark Rd Oakfield WI 53065",
    "addr:housenumber":"7859",
    "addr:postcode":"53065",
    "addr:street":"E Clark Rd",
    "iso:country":"US",
    "sg:address":"7859 E Clark Rd",
    "sg:city":"Oakfield",
    "sg:classifiers":[
        {
            "category":"Sports & Exercise",
            "subcategory":"Bowling",
            "type":"Entertainment"
        }
    ],
    "sg:phone":"+1 920 458 3476",
    "sg:postcode":"53065",
    "sg:province":"WI",
    "sg:tags":[
        "center"
    ],
    "wof:name":"North Bowl Of Sheboygan Inc",
    "wof:placetype":"venue"
},
  "geometry": {"coordinates":[-88.552661,43.726627],"type":"Point"}
}