{
  "type": "Feature",
  "properties": {
    "iso:country":"US",
    "sg:address":"8503 Red River Lincoln T L Rd",
    "sg:city":"Casco",
    "sg:classifiers":[
        {
            "category":"Farming",
            "subcategory":"Dairy Farm",
            "type":"Manufacturing & Wholesale Goods"
        }
    ],
    "sg:phone":"+1 920 837 7262",
    "sg:postcode":"54205",
    "sg:province":"WI",
    "wof:name":"Corner Site Dairy",
    "wof:placetype":"venue"
},
  "geometry": {"coordinates":[-87.641912,44.63943],"type":"Point"}
}