{
  "type": "Feature",
  "properties": {
    "addr:full":"2273 S Howell Ave Milwaukee WI 53207",
    "addr:housenumber":"2273",
    "addr:postcode":"53207",
    "addr:street":"S Howell Ave",
    "iso:country":"US",
    "sg:address":"2273 S Howell Ave",
    "sg:city":"Milwaukee",
    "sg:classifiers":[
        {
            "category":"Shopping",
            "subcategory":"Computers & Home Electronics",
            "type":"Retail Goods"
        }
    ],
    "sg:phone":"+1 414 744 0782",
    "sg:postcode":"53207",
    "sg:province":"WI",
    "sg:tags":[
        "system",
        "high",
        "equipment",
        "stereophonic",
        "lighting",
        "fidelity"
    ],
    "wof:name":"Custom Designed Lighting",
    "wof:placetype":"venue"
},
  "geometry": {"coordinates":[-87.90473900000001,43.002977],"type":"Point"}
}