{
  "type": "Feature",
  "properties": {
    "iso:country":"US",
    "sg:address":"126 E Washington St",
    "sg:city":"Stoughton",
    "sg:classifiers":[
        {
            "category":"Travel",
            "subcategory":"Hotels & Motels",
            "type":"Entertainment"
        }
    ],
    "sg:phone":"+1 608 877 4150",
    "sg:postcode":"53589",
    "sg:province":"WI",
    "sg:tags":[
        "breakfast",
        "operation",
        "bed",
        "accommodation"
    ],
    "sg:website":"www.naesetroe.com",
    "wof:name":"Naeset Roe Bed & Breakfast",
    "wof:placetype":"venue"
},
  "geometry": {"coordinates":[-89.21943400000001,42.917747],"type":"Point"}
}