{
  "type": "Feature",
  "properties": {
    "iso:country":"US",
    "sg:address":"31 N Park St",
    "sg:city":"Clintonville",
    "sg:classifiers":[
        {
            "category":"Social Services",
            "subcategory":"Child Care",
            "type":"Services"
        }
    ],
    "sg:phone":"+1 715 823 3078",
    "sg:postcode":"54929",
    "sg:province":"WI",
    "wof:name":"Tiny Treasures Preschool",
    "wof:placetype":"venue"
},
  "geometry": {"coordinates":[-88.753277,44.631564],"type":"Point"}
}