{
  "type": "Feature",
  "properties": {
    "iso:country":"US",
    "sg:address":"1840 N Farwell Ave # 404",
    "sg:city":"Milwaukee",
    "sg:classifiers":[
        {
            "category":"Real Estate",
            "subcategory":"Real Estate Services",
            "type":"Services"
        },
        {
            "category":"Banks & Credit Unions",
            "subcategory":"Financial Services",
            "type":"Services"
        }
    ],
    "sg:phone":"+1 414 461 9759",
    "sg:postcode":"53202",
    "sg:province":"WI",
    "sg:tags":[
        "loan"
    ],
    "wof:name":"Assurance Financial & Mortgage Svcs",
    "wof:placetype":"venue"
},
  "geometry": {"coordinates":[-87.890872,43.05452],"type":"Point"}
}