{
  "type": "Feature",
  "properties": {
    "iso:country":"US",
    "sg:address":"4681 Vine Rd",
    "sg:city":"Kaukauna",
    "sg:classifiers":[
        {
            "category":"Building & Trades",
            "subcategory":"Construction",
            "type":"Services"
        }
    ],
    "sg:phone":"+1 920 788 4951",
    "sg:postcode":"54130",
    "sg:province":"WI",
    "sg:tags":[
        "boring",
        "drilling",
        "contractor"
    ],
    "wof:name":"Unlimited Enterprise",
    "wof:placetype":"venue"
},
  "geometry": {"coordinates":[-88.311785,44.405524],"type":"Point"}
}