{
  "type": "Feature",
  "properties": {
    "iso:country":"US",
    "sg:address":"5968 Lambie Rd",
    "sg:city":"De Pere",
    "sg:classifiers":[
        {
            "category":"Wholesale",
            "subcategory":"Plants",
            "type":"Manufacturing & Wholesale Goods"
        }
    ],
    "sg:phone":"+1 920 869 2488",
    "sg:postcode":"54115",
    "sg:province":"WI",
    "sg:tags":[
        "supply"
    ],
    "wof:name":"Bonsai Art By Mertz",
    "wof:placetype":"venue"
},
  "geometry": {"coordinates":[-88.22894,44.453779],"type":"Point"}
}