{
  "type": "Feature",
  "properties": {
    "iso:country":"US",
    "sg:address":"7698 210th Ave",
    "sg:city":"Hager City",
    "sg:phone":"+1 715 792 2551",
    "sg:postcode":"54014",
    "sg:province":"WI",
    "sg:tags":[
        "farm",
        "field",
        "corn",
        "crop"
    ],
    "wof:name":"Happ E Hill",
    "wof:placetype":"venue"
},
  "geometry": {"coordinates":[-92.519617,44.615778],"type":"Point"}
}