{
  "type": "Feature",
  "properties": {
    "iso:country":"US",
    "sg:address":"2 S Mills St",
    "sg:city":"Madison",
    "sg:classifiers":[
        {
            "category":"Restaurant",
            "type":"Food & Drink"
        }
    ],
    "sg:phone":"+1 608 259 1668",
    "sg:postcode":"53715",
    "sg:province":"WI",
    "sg:tags":[
        "eating"
    ],
    "wof:name":"Hong Kong Cafe",
    "wof:placetype":"venue"
},
  "geometry": {"coordinates":[-89.404056,43.06708],"type":"Point"}
}