{
  "type": "Feature",
  "properties": {
    "iso:country":"US",
    "sg:address":"2447 16th Rd",
    "sg:city":"Montello",
    "sg:classifiers":[
        {
            "category":"Building & Trades",
            "subcategory":"Plumbing",
            "type":"Services"
        }
    ],
    "sg:phone":"+1 608 297 7470",
    "sg:postcode":"53949",
    "sg:province":"WI",
    "sg:tags":[
        "plumbing",
        "contractor"
    ],
    "wof:name":"Oakes Plumbing",
    "wof:placetype":"venue"
},
  "geometry": {"coordinates":[-89.288201,43.820197],"type":"Point"}
}