{
  "type": "Feature",
  "properties": {
    "addr:full":"449 8th St Monroe WI 53566",
    "addr:housenumber":"449",
    "addr:postcode":"53566",
    "addr:street":"8Th St",
    "iso:country":"US",
    "sg:address":"449 8th St",
    "sg:city":"Monroe",
    "sg:classifiers":[
        {
            "category":"Restaurant",
            "type":"Food & Drink"
        }
    ],
    "sg:menulink":"http://www.allmenus.com/wi/monroe/145653-subway/menu/",
    "sg:phone":"+1 608 328 2500",
    "sg:postcode":"53566",
    "sg:province":"WI",
    "sg:tags":[
        "american",
        "sandwich"
    ],
    "wof:name":"Subway",
    "wof:placetype":"venue"
},
  "geometry": {"coordinates":[-89.654169,42.603485],"type":"Point"}
}