{
  "type": "Feature",
  "properties": {
    "iso:country":"US",
    "sg:address":"2751 Riveridge Ln",
    "sg:city":"Green Bay",
    "sg:classifiers":[
        {
            "category":"Professional",
            "subcategory":"Management & Consulting",
            "type":"Services"
        }
    ],
    "sg:phone":"+1 920 662 2718",
    "sg:postcode":"54313",
    "sg:province":"WI",
    "wof:name":"Maintnance Professionals L L C",
    "wof:placetype":"venue"
},
  "geometry": {"coordinates":[-88.091002,44.554027],"type":"Point"}
}