{
  "type": "Feature",
  "properties": {
    "iso:country":"US",
    "sg:address":"8898 Forest Lane Rd",
    "sg:city":"Ripon",
    "sg:classifiers":[
        {
            "category":"Freight",
            "type":"Transportation"
        }
    ],
    "sg:phone":"+1 920 589 4038",
    "sg:postcode":"54971",
    "sg:province":"WI",
    "wof:name":"Pickett Transport LLC",
    "wof:placetype":"venue"
},
  "geometry": {"coordinates":[-88.735407,43.86591],"type":"Point"}
}