{
  "type": "Feature",
  "properties": {
    "iso:country":"US",
    "sg:address":"20150 Greens Landing Rd",
    "sg:city":"Augusta",
    "sg:classifiers":[
        {
            "category":"Restaurant",
            "type":"Food & Drink"
        }
    ],
    "sg:phone":"+1 715 286 2687",
    "sg:postcode":"54722",
    "sg:province":"WI",
    "sg:tags":[
        "personal",
        "eating"
    ],
    "wof:name":"Black Bear Supper Club",
    "wof:placetype":"venue"
},
  "geometry": {"coordinates":[-91.120908,44.755085],"type":"Point"}
}