{
  "type": "Feature",
  "properties": {
    "addr:full":"2525 Milton Ave Janesville WI 53545",
    "addr:housenumber":"2525",
    "addr:postcode":"53545",
    "addr:street":"Milton Ave",
    "iso:country":"US",
    "sg:address":"2525 Milton Ave",
    "sg:city":"Janesville",
    "sg:classifiers":[
        {
            "category":"Banks & Credit Unions",
            "subcategory":"Investment Brokerage",
            "type":"Services"
        }
    ],
    "sg:phone":"+1 608 756 2002",
    "sg:postcode":"53545",
    "sg:province":"WI",
    "sg:tags":[
        "advisory",
        "financial"
    ],
    "wof:name":"Met Life",
    "wof:placetype":"venue"
},
  "geometry": {"coordinates":[-89.001648,42.712447],"type":"Point"}
}