{
  "type": "Feature",
  "properties": {
    "iso:country":"US",
    "sg:address":"Hwy C",
    "sg:city":"Wilmot",
    "sg:classifiers":[
        {
            "category":"Restaurant",
            "type":"Food & Drink"
        }
    ],
    "sg:phone":"+1 262 862 9377",
    "sg:postcode":"53192",
    "sg:province":"WI",
    "wof:name":"Twin Oaks Country Inn Restaurant",
    "wof:placetype":"venue"
},
  "geometry": {"coordinates":[-88.187682,42.511314],"type":"Point"}
}