{
  "type": "Feature",
  "properties": {
    "iso:country":"US",
    "sg:address":"4080 Cloverland Dr",
    "sg:city":"Campbellsport",
    "sg:classifiers":[
        {
            "category":"Building & Trades",
            "subcategory":"Construction",
            "type":"Services"
        }
    ],
    "sg:phone":"+1 920 533 4689",
    "sg:postcode":"53010",
    "sg:province":"WI",
    "sg:tags":[
        "excavation",
        "contractor"
    ],
    "wof:name":"Weiland Excavating LLC",
    "wof:placetype":"venue"
},
  "geometry": {"coordinates":[-88.357371,43.56511],"type":"Point"}
}