{
  "type": "Feature",
  "properties": {
    "iso:country":"US",
    "sg:address":"3260 Janke Rd",
    "sg:city":"Black River Falls",
    "sg:classifiers":[
        {
            "category":"Farming",
            "subcategory":"Berry Farm",
            "type":"Manufacturing & Wholesale Goods"
        }
    ],
    "sg:phone":"+1 715 284 5622",
    "sg:postcode":"54615",
    "sg:province":"WI",
    "sg:tags":[
        "crop"
    ],
    "wof:name":"Brockway Cranberry Inc",
    "wof:placetype":"venue"
},
  "geometry": {"coordinates":[-90.734084,44.183798],"type":"Point"}
}