{
  "type": "Feature",
  "properties": {
    "iso:country":"US",
    "sg:address":"1061 Blue River Rd",
    "sg:city":"Muscoda",
    "sg:classifiers":[
        {
            "category":"Education",
            "subcategory":"School",
            "type":"Public Place"
        }
    ],
    "sg:phone":"+1 608 739 3369",
    "sg:postcode":"53573",
    "sg:province":"WI",
    "wof:name":"Christian Day School",
    "wof:placetype":"venue"
},
  "geometry": {"coordinates":[-90.470358,43.175849],"type":"Point"}
}