{
  "type": "Feature",
  "properties": {
    "iso:country":"US",
    "sg:address":"2646 Pheasant Valley Ct",
    "sg:city":"Waldo",
    "sg:classifiers":[
        {
            "category":"Manufacturing",
            "subcategory":"Toys & Sporting Goods",
            "type":"Manufacturing & Wholesale Goods"
        }
    ],
    "sg:phone":"+1 920 528 7127",
    "sg:postcode":"53093",
    "sg:province":"WI",
    "sg:tags":[
        "porcelain",
        "mfg",
        "doll"
    ],
    "wof:name":"Oldenburg Originals",
    "wof:placetype":"venue"
},
  "geometry": {"coordinates":[-87.949023,43.6364],"type":"Point"}
}