{
  "type": "Feature",
  "properties": {
    "iso:country":"US",
    "sg:address":"15204 Co Rd G",
    "sg:city":"Nekoosa",
    "sg:classifiers":[
        {
            "category":"Farming",
            "subcategory":"Farm",
            "type":"Manufacturing & Wholesale Goods"
        }
    ],
    "sg:phone":"+1 715 886 4029",
    "sg:postcode":"54457",
    "sg:province":"WI",
    "sg:tags":[
        "crop",
        "general"
    ],
    "wof:name":"Anthony Farms Inc",
    "wof:placetype":"venue"
},
  "geometry": {"coordinates":[-89.955514,44.193172],"type":"Point"}
}