{
  "type": "Feature",
  "properties": {
    "addr:full":"3830 N Holton St Milwaukee WI 53212",
    "addr:housenumber":"3830",
    "addr:postcode":"53212",
    "addr:street":"N Holton St",
    "iso:country":"US",
    "sg:address":"3830 N Holton St",
    "sg:city":"Milwaukee",
    "sg:classifiers":[
        {
            "category":"Personal",
            "subcategory":"Shoe Repair & Shine",
            "type":"Services"
        }
    ],
    "sg:phone":"+1 414 962 6287",
    "sg:postcode":"53212",
    "sg:province":"WI",
    "sg:tags":[
        "repairing",
        "boot"
    ],
    "wof:name":"Village Shoe Repair",
    "wof:placetype":"venue"
},
  "geometry": {"coordinates":[-87.90475000000001,43.088718],"type":"Point"}
}