{
  "type": "Feature",
  "properties": {
    "iso:country":"US",
    "sg:address":"6714 W Mequon Rd",
    "sg:city":"Mequon",
    "sg:classifiers":[
        {
            "category":"Shopping",
            "subcategory":"Antiques",
            "type":"Retail Goods"
        }
    ],
    "sg:phone":"+1 262 242 6823",
    "sg:postcode":"53092",
    "sg:province":"WI",
    "wof:name":"Wood Shelter Furniture Refinishing",
    "wof:placetype":"venue"
},
  "geometry": {"coordinates":[-87.992897,43.221802],"type":"Point"}
}