{
  "type": "Feature",
  "properties": {
    "iso:country":"US",
    "sg:address":"1109 Williamson St",
    "sg:city":"Madison",
    "sg:classifiers":[
        {
            "category":"Organizations",
            "subcategory":"Professional Association",
            "type":"Services"
        }
    ],
    "sg:phone":"+1 608 256 8500",
    "sg:postcode":"53703",
    "sg:province":"WI",
    "wof:name":"Madison Association-Deaf",
    "wof:placetype":"venue"
},
  "geometry": {"coordinates":[-89.364364,43.083107],"type":"Point"}
}