{
  "type": "Feature",
  "properties": {
    "iso:country":"US",
    "sg:address":"1164 S Lansing Ave",
    "sg:city":"Sturgeon Bay",
    "sg:classifiers":[
        {
            "category":"Restaurant",
            "type":"Food & Drink"
        },
        {
            "category":"Bars & Pubs",
            "type":"Food & Drink"
        }
    ],
    "sg:phone":"+1 920 743 9576",
    "sg:postcode":"54235",
    "sg:province":"WI",
    "sg:tags":[
        "eating"
    ],
    "wof:name":"County Line Bar & Grill Corp",
    "wof:placetype":"venue"
},
  "geometry": {"coordinates":[-87.387143,44.814007],"type":"Point"}
}