{
  "type": "Feature",
  "properties": {
    "iso:country":"US",
    "sg:address":"7010 Woodsmoke Rd",
    "sg:city":"Wausau",
    "sg:classifiers":[
        {
            "category":"Building & Trades",
            "subcategory":"Construction",
            "type":"Services"
        }
    ],
    "sg:phone":"+1 715 359 9272",
    "sg:postcode":"54401",
    "sg:province":"WI",
    "sg:tags":[
        "house"
    ],
    "wof:name":"Bauer Builders",
    "wof:placetype":"venue"
},
  "geometry": {"coordinates":[-89.69459500000001,44.892153],"type":"Point"}
}