{
  "type": "Feature",
  "properties": {
    "iso:country":"US",
    "sg:address":"1356 118th St",
    "sg:city":"Chippewa Falls",
    "sg:classifiers":[
        {
            "category":"Utilities",
            "subcategory":"Refuse",
            "type":"Services"
        }
    ],
    "sg:phone":"+1 715 286 4777",
    "sg:postcode":"54729",
    "sg:province":"WI",
    "sg:tags":[
        "pet",
        "waste",
        "removal"
    ],
    "wof:name":"Dr Doo-Litter",
    "wof:placetype":"venue"
},
  "geometry": {"coordinates":[-91.43276899999999,44.86124],"type":"Point"}
}