{
  "type": "Feature",
  "properties": {
    "iso:country":"US",
    "sg:address":"1820 Westmoor Ter",
    "sg:city":"Elm Grove",
    "sg:classifiers":[
        {
            "category":"Social Services",
            "subcategory":"Adult Care",
            "type":"Services"
        }
    ],
    "sg:phone":"+1 262 796 0123",
    "sg:postcode":"53122",
    "sg:province":"WI",
    "sg:tags":[
        "residential"
    ],
    "wof:name":"Hearthside Care LLP Offices",
    "wof:placetype":"venue"
},
  "geometry": {"coordinates":[-88.101865,43.056091],"type":"Point"}
}