{
  "type": "Feature",
  "properties": {
    "iso:country":"US",
    "sg:address":"1865 Pine Rd",
    "sg:city":"Mosinee",
    "sg:classifiers":[
        {
            "category":"Professional",
            "subcategory":"Business Services",
            "type":"Services"
        }
    ],
    "sg:phone":"+1 715 359 9700",
    "sg:postcode":"54455",
    "sg:province":"WI",
    "wof:name":"Oakwood Enterprises of Wausau",
    "wof:placetype":"venue"
},
  "geometry": {"coordinates":[-89.622846,44.851003],"type":"Point"}
}