{
  "type": "Feature",
  "properties": {
    "iso:country":"US",
    "sg:address":"2145 Fox Ridge Ln",
    "sg:city":"New London",
    "sg:classifiers":[
        {
            "category":"Professional",
            "subcategory":"Lawyer & Legal Services",
            "type":"Services"
        }
    ],
    "sg:phone":"+1 920 982 6669",
    "sg:postcode":"54961",
    "sg:province":"WI",
    "wof:name":"Attorney At Law",
    "wof:placetype":"venue"
},
  "geometry": {"coordinates":[-88.764381,44.318518],"type":"Point"}
}