{
  "type": "Feature",
  "properties": {
    "iso:country":"US",
    "sg:address":"2506 S 84th St",
    "sg:city":"Milwaukee",
    "sg:classifiers":[
        {
            "category":"Shopping",
            "subcategory":"Gifts & Souvenirs",
            "type":"Retail Goods"
        }
    ],
    "sg:phone":"+1 414 543 2373",
    "sg:postcode":"53227",
    "sg:province":"WI",
    "wof:name":"Suzies Foral & Affaires",
    "wof:placetype":"venue"
},
  "geometry": {"coordinates":[-88.017337,42.997256],"type":"Point"}
}