{
  "type": "Feature",
  "properties": {
    "iso:country":"US",
    "sg:address":"11630 Center Hill Rd",
    "sg:city":"Darlington",
    "sg:classifiers":[
        {
            "category":"Education",
            "subcategory":"School",
            "type":"Public Place"
        }
    ],
    "sg:phone":"+1 608 776 4021",
    "sg:postcode":"53530",
    "sg:province":"WI",
    "wof:name":"Darlington Elementary-Middle",
    "wof:placetype":"venue"
},
  "geometry": {"coordinates":[-90.126058,42.664305],"type":"Point"}
}