{
  "type": "Feature",
  "properties": {
    "iso:country":"US",
    "sg:address":"908 W Main St",
    "sg:city":"Cameron",
    "sg:classifiers":[
        {
            "category":"Restaurant",
            "type":"Food & Drink"
        }
    ],
    "sg:phone":"+1 715 458 0500",
    "sg:postcode":"54822",
    "sg:province":"WI",
    "sg:tags":[
        "eating"
    ],
    "wof:name":"Jimmys Pizza",
    "wof:placetype":"venue"
},
  "geometry": {"coordinates":[-91.745711,45.408528],"type":"Point"}
}