{
  "type": "Feature",
  "properties": {
    "iso:country":"US",
    "sg:address":"15212 Co Rd Z",
    "sg:city":"Ringle",
    "sg:classifiers":[
        {
            "category":"Retail",
            "subcategory":"Auto Repair",
            "type":"Services"
        }
    ],
    "sg:phone":"+1 715 446 3400",
    "sg:postcode":"54471",
    "sg:province":"WI",
    "sg:tags":[
        "general"
    ],
    "wof:name":"Easton Town Garage",
    "wof:placetype":"venue"
},
  "geometry": {"coordinates":[-89.430108,44.98763],"type":"Point"}
}