{
  "type": "Feature",
  "properties": {
    "iso:country":"US",
    "sg:address":"131 River St",
    "sg:city":"Woodville",
    "sg:classifiers":[
        {
            "category":"Building & Trades",
            "subcategory":"Plumbing",
            "type":"Services"
        }
    ],
    "sg:phone":"+1 715 698 2407",
    "sg:postcode":"54028",
    "sg:province":"WI",
    "sg:tags":[
        "conditioning",
        "air",
        "system",
        "contractor"
    ],
    "wof:name":"Gunderson's Heating & Electric",
    "wof:placetype":"venue"
},
  "geometry": {"coordinates":[-92.289909,44.952517],"type":"Point"}
}