{
  "type": "Feature",
  "properties": {
    "addr:full":"9693 US Hwy 2 Poplar WI 54864",
    "addr:housenumber":"9693",
    "addr:postcode":"54864",
    "addr:street":"Us Hwy 2",
    "iso:country":"US",
    "sg:address":"9693 US Hwy 2",
    "sg:city":"Poplar",
    "sg:classifiers":[
        {
            "category":"Home & Garden",
            "subcategory":"Hardware",
            "type":"Retail Goods"
        }
    ],
    "sg:phone":"+1 715 364 2238",
    "sg:postcode":"54864",
    "sg:province":"WI",
    "wof:name":"Poplar Hardware",
    "wof:placetype":"venue"
},
  "geometry": {"coordinates":[-91.80462900000001,46.586616],"type":"Point"}
}