{
  "type": "Feature",
  "properties": {
    "addr:full":"11065 Point Rd W Mayville WI 53050",
    "addr:housenumber":"11065",
    "addr:postcode":"53050",
    "addr:street":"Point Rd W",
    "iso:country":"US",
    "sg:address":"11065 Point Rd W",
    "sg:city":"Mayville",
    "sg:phone":"+1 920 583 3315",
    "sg:postcode":"53050",
    "sg:province":"WI",
    "sg:tags":[
        "farm",
        "corn",
        "dairy"
    ],
    "wof:name":"Jesse Farm",
    "wof:placetype":"venue"
},
  "geometry": {"coordinates":[-88.626046,43.589456],"type":"Point"}
}