{
  "type": "Feature",
  "properties": {
    "iso:country":"US",
    "sg:address":"851 Bearskin Cir",
    "sg:city":"Lac Du Flambeau",
    "sg:classifiers":[
        {
            "category":"Professional",
            "type":"Services"
        }
    ],
    "sg:phone":"+1 715 588 7676",
    "sg:postcode":"54538",
    "sg:province":"WI",
    "wof:name":"Great Lakes Fish & Wildlife",
    "wof:placetype":"venue"
},
  "geometry": {"coordinates":[-89.903451,45.969168],"type":"Point"}
}