{
  "type": "Feature",
  "properties": {
    "addr:full":"811 N 3rd Ave Wausau WI 54401",
    "addr:housenumber":"811",
    "addr:postcode":"54401",
    "addr:street":"N 3Rd Ave",
    "iso:country":"US",
    "sg:address":"811 N 3rd Ave",
    "sg:city":"Wausau",
    "sg:classifiers":[
        {
            "category":"Shopping",
            "subcategory":"Books",
            "type":"Retail Goods"
        }
    ],
    "sg:phone":"+1 715 675 7789",
    "sg:postcode":"54401",
    "sg:province":"WI",
    "sg:tags":[
        "bookstore",
        "christian"
    ],
    "sg:website":"www.christianbkstr.com",
    "wof:name":"Christian Bookstore",
    "wof:placetype":"venue"
},
  "geometry": {"coordinates":[-89.639234,44.973561],"type":"Point"}
}