{
  "type": "Feature",
  "properties": {
    "iso:country":"US",
    "sg:address":"1319 S Layton Blvd",
    "sg:city":"Milwaukee",
    "sg:classifiers":[
        {
            "category":"Education",
            "subcategory":"School",
            "type":"Public Place"
        }
    ],
    "sg:phone":"+1 414 389 1586",
    "sg:postcode":"53215",
    "sg:province":"WI",
    "wof:name":"School Sisters Of St Francis",
    "wof:placetype":"venue"
},
  "geometry": {"coordinates":[-87.947868,43.018242],"type":"Point"}
}