{
  "type": "Feature",
  "properties": {
    "iso:country":"US",
    "sg:address":"1822 N Hi Mount Blvd",
    "sg:city":"Milwaukee",
    "sg:classifiers":[
        {
            "category":"Building & Trades",
            "subcategory":"Electrical",
            "type":"Services"
        },
        {
            "category":"Wholesale",
            "subcategory":"Electrical",
            "type":"Manufacturing & Wholesale Goods"
        }
    ],
    "sg:phone":"+1 414 964 6463",
    "sg:postcode":"53208",
    "sg:province":"WI",
    "sg:tags":[
        "lighting",
        "landscape",
        "supply"
    ],
    "wof:name":"Luminoptics Lighting Inc",
    "wof:placetype":"venue"
},
  "geometry": {"coordinates":[-87.975932,43.053816],"type":"Point"}
}