{
  "type": "Feature",
  "properties": {
    "iso:country":"US",
    "sg:address":"1844 State Hwy 13",
    "sg:city":"Friendship",
    "sg:classifiers":[
        {
            "category":"Travel",
            "subcategory":"Hotels & Motels",
            "type":"Entertainment"
        }
    ],
    "sg:phone":"+1 608 339 7295",
    "sg:postcode":"53934",
    "sg:province":"WI",
    "wof:name":"Akorn Inn",
    "wof:placetype":"venue"
},
  "geometry": {"coordinates":[-89.812444,43.989848],"type":"Point"}
}