{
  "type": "Feature",
  "properties": {
    "iso:country":"US",
    "sg:address":"600 Union St",
    "sg:city":"Watertown",
    "sg:classifiers":[
        {
            "category":"Retail",
            "subcategory":"Auto Repair",
            "type":"Services"
        }
    ],
    "sg:phone":"+1 920 206 1066",
    "sg:postcode":"53098",
    "sg:province":"WI",
    "sg:tags":[
        "transmission"
    ],
    "wof:name":"Transmasters",
    "wof:placetype":"venue"
},
  "geometry": {"coordinates":[-88.733573,43.20336],"type":"Point"}
}