{
  "type": "Feature",
  "properties": {
    "iso:country":"US",
    "sg:address":"3607 Washington Ave",
    "sg:city":"Racine",
    "sg:classifiers":[
        {
            "category":"Real Estate",
            "subcategory":"Real Estate Agent",
            "type":"Services"
        }
    ],
    "sg:phone":"+1 262 634 1629",
    "sg:postcode":"53405",
    "sg:province":"WI",
    "wof:name":"Taurus LLC",
    "wof:placetype":"venue"
},
  "geometry": {"coordinates":[-87.823562,42.718599],"type":"Point"}
}