{
  "type": "Feature",
  "properties": {
    "iso:country":"US",
    "sg:address":"422 Westgate Mall",
    "sg:city":"Madison",
    "sg:classifiers":[
        {
            "category":"Shopping",
            "subcategory":"Shoes",
            "type":"Retail Goods"
        }
    ],
    "sg:phone":"+1 608 271 1271",
    "sg:postcode":"53711",
    "sg:province":"WI",
    "wof:name":"Good Feets Store",
    "wof:placetype":"venue"
},
  "geometry": {"coordinates":[-89.472226,43.051962],"type":"Point"}
}