{
  "type": "Feature",
  "properties": {
    "iso:country":"US",
    "sg:address":"10565 Mayflower Rd",
    "sg:city":"Milladore",
    "sg:classifiers":[
        {
            "category":"Farming",
            "subcategory":"Dairy Farm",
            "type":"Manufacturing & Wholesale Goods"
        }
    ],
    "sg:phone":"+1 715 652 2951",
    "sg:postcode":"54454",
    "sg:province":"WI",
    "wof:name":"Nine Pines Dairy Farm",
    "wof:placetype":"venue"
},
  "geometry": {"coordinates":[-89.906271,44.63005],"type":"Point"}
}