{
  "type": "Feature",
  "properties": {
    "iso:country":"US",
    "sg:address":"11803 Ringle Ave",
    "sg:city":"Ringle",
    "sg:phone":"+1 715 359 4951",
    "sg:postcode":"54471",
    "sg:province":"WI",
    "sg:tags":[
        "farm"
    ],
    "wof:name":"Herman Benaszeski",
    "wof:placetype":"venue"
},
  "geometry": {"coordinates":[-89.473815,44.896837],"type":"Point"}
}