{
  "type": "Feature",
  "properties": {
    "iso:country":"US",
    "sg:address":"3210 Hogarth St",
    "sg:city":"Eau Claire",
    "sg:classifiers":[
        {
            "category":"Manufacturing",
            "subcategory":"Tools & Machinery",
            "type":"Manufacturing & Wholesale Goods"
        }
    ],
    "sg:phone":"+1 715 832 1717",
    "sg:postcode":"54703",
    "sg:province":"WI",
    "sg:tags":[
        "industrial",
        "mfg"
    ],
    "sg:website":"www.mightymount.com",
    "wof:name":"Envirotech",
    "wof:placetype":"venue"
},
  "geometry": {"coordinates":[-91.463267,44.868547],"type":"Point"}
}