{
  "type": "Feature",
  "properties": {
    "iso:country":"US",
    "sg:address":"805 E Lake St",
    "sg:city":"Lake Mills",
    "sg:classifiers":[
        {
            "category":"Freight",
            "type":"Transportation"
        }
    ],
    "sg:phone":"+1 920 648 2025",
    "sg:postcode":"53551",
    "sg:province":"WI",
    "sg:tags":[
        "commercial",
        "storage"
    ],
    "wof:name":"East Lake Storage",
    "wof:placetype":"venue"
},
  "geometry": {"coordinates":[-88.893806,43.077635],"type":"Point"}
}