{
  "type": "Feature",
  "properties": {
    "iso:country":"US",
    "sg:address":"14633 Clover Ln",
    "sg:city":"Blue River",
    "sg:classifiers":[
        {
            "category":"Farming",
            "subcategory":"Dairy Farm",
            "type":"Manufacturing & Wholesale Goods"
        }
    ],
    "sg:phone":"+1 608 537 2900",
    "sg:postcode":"53518",
    "sg:province":"WI",
    "wof:name":"Schauf Enterprises Inc",
    "wof:placetype":"venue"
},
  "geometry": {"coordinates":[-90.573395,43.222478],"type":"Point"}
}