{
  "type": "Feature",
  "properties": {
    "iso:country":"US",
    "sg:address":"1311 13th Ave",
    "sg:city":"Monroe",
    "sg:classifiers":[
        {
            "category":"Wholesale",
            "subcategory":"Farm Supplies",
            "type":"Manufacturing & Wholesale Goods"
        }
    ],
    "sg:phone":"+1 608 325 3495",
    "sg:postcode":"53566",
    "sg:province":"WI",
    "sg:tags":[
        "feed",
        "fertilizer",
        "seed"
    ],
    "wof:name":"Kens Agri-Services Inc",
    "wof:placetype":"venue"
},
  "geometry": {"coordinates":[-89.64337999999999,42.599395],"type":"Point"}
}