{
  "type": "Feature",
  "properties": {
    "addr:full":"5501 W National Ave Milwaukee WI 53214",
    "addr:housenumber":"5501",
    "addr:postcode":"53214",
    "addr:street":"W National Ave",
    "iso:country":"US",
    "sg:address":"5501 W National Ave",
    "sg:city":"Milwaukee",
    "sg:classifiers":[
        {
            "category":"Restaurant",
            "type":"Food & Drink"
        }
    ],
    "sg:menulink":"http://www.allmenus.com/wi/milwaukee/141445-the-new-colony-restaurant/menu/",
    "sg:phone":"+1 414 671 6400",
    "sg:postcode":"53214",
    "sg:province":"WI",
    "sg:tags":[
        "american"
    ],
    "wof:name":"The New Colony Restaurant",
    "wof:placetype":"venue"
},
  "geometry": {"coordinates":[-87.98206399999999,43.018475],"type":"Point"}
}