{
  "type": "Feature",
  "properties": {
    "addr:full":"503 Kekoskee St Mayville WI 53050",
    "addr:housenumber":"503",
    "addr:postcode":"53050",
    "addr:street":"Kekoskee St",
    "iso:country":"US",
    "sg:address":"503 Kekoskee St",
    "sg:city":"Mayville",
    "sg:classifiers":[
        {
            "category":"Shopping",
            "type":"Retail Goods"
        }
    ],
    "sg:phone":"+1 920 387 4892",
    "sg:postcode":"53050",
    "sg:province":"WI",
    "sg:tags":[
        "space"
    ],
    "wof:name":"Wwwartistryllccom",
    "wof:placetype":"venue"
},
  "geometry": {"coordinates":[-88.550434,43.504241],"type":"Point"}
}