{
  "type": "Feature",
  "properties": {
    "iso:country":"US",
    "sg:address":"200 N Water St",
    "sg:city":"Watertown",
    "sg:classifiers":[
        {
            "category":"Professional",
            "type":"Services"
        }
    ],
    "sg:phone":"+1 920 206 0794",
    "sg:postcode":"53094",
    "sg:province":"WI",
    "wof:name":"Chances R Good Inc",
    "wof:placetype":"venue"
},
  "geometry": {"coordinates":[-88.725811,43.196781],"type":"Point"}
}