{
  "type": "Feature",
  "properties": {
    "iso:country":"US",
    "sg:address":"2255 Co Rd J",
    "sg:city":"Kaukauna",
    "sg:classifiers":[
        {
            "category":"Professional",
            "subcategory":"Business Services",
            "type":"Services"
        }
    ],
    "sg:phone":"+1 920 766 4279",
    "sg:postcode":"54130",
    "sg:province":"WI",
    "sg:tags":[
        "auctioneer"
    ],
    "wof:name":"Major Auction Sales",
    "wof:placetype":"venue"
},
  "geometry": {"coordinates":[-88.302546,44.414817],"type":"Point"}
}