{
  "type": "Feature",
  "properties": {
    "addr:full":"7322 Pittman Ln Arkansaw WI 54721",
    "addr:housenumber":"7322",
    "addr:postcode":"54721",
    "addr:street":"Pittman Ln",
    "iso:country":"US",
    "sg:address":"7322 Pittman Ln",
    "sg:city":"Arkansaw",
    "sg:classifiers":[
        {
            "category":"Farming",
            "subcategory":"Dairy Farm",
            "type":"Manufacturing & Wholesale Goods"
        }
    ],
    "sg:phone":"+1 715 285 5103",
    "sg:postcode":"54721",
    "sg:province":"WI",
    "wof:name":"Dan Pittman",
    "wof:placetype":"venue"
},
  "geometry": {"coordinates":[-92.067341,44.672444],"type":"Point"}
}