{
  "type": "Feature",
  "properties": {
    "addr:full":"406 N Lake Ave Twin Lakes WI 53181",
    "addr:housenumber":"406",
    "addr:postcode":"53181",
    "addr:street":"N Lake Ave",
    "iso:country":"US",
    "sg:address":"406 N Lake Ave",
    "sg:city":"Twin Lakes",
    "sg:classifiers":[
        {
            "category":"Shopping",
            "subcategory":"Department Store",
            "type":"Retail Goods"
        }
    ],
    "sg:phone":"+1 262 877 2655",
    "sg:postcode":"53181",
    "sg:province":"WI",
    "sg:tags":[
        "shop"
    ],
    "wof:name":"Dollar Depot",
    "wof:placetype":"venue"
},
  "geometry": {"coordinates":[-88.247159,42.53505],"type":"Point"}
}