{
  "type": "Feature",
  "properties": {
    "iso:country":"US",
    "sg:address":"3754 E Grange Ave",
    "sg:city":"Cudahy",
    "sg:classifiers":[
        {
            "category":"Freight",
            "type":"Transportation"
        }
    ],
    "sg:phone":"+1 414 481 5390",
    "sg:postcode":"53110",
    "sg:province":"WI",
    "sg:tags":[
        "operator",
        "local",
        "trucking"
    ],
    "wof:name":"Tek Trucking LLC",
    "wof:placetype":"venue"
},
  "geometry": {"coordinates":[-87.85508900000001,42.944693],"type":"Point"}
}