{
  "type": "Feature",
  "properties": {
    "iso:country":"US",
    "sg:address":"507 N Railroad St",
    "sg:city":"Eagle River",
    "sg:classifiers":[
        {
            "category":"Autos & Motor Vehicles",
            "subcategory":"Automobile Sales",
            "type":"Retail Goods"
        }
    ],
    "sg:phone":"+1 715 479 7405",
    "sg:postcode":"54521",
    "sg:province":"WI",
    "sg:tags":[
        "car",
        "dealer"
    ],
    "wof:name":"Ron's Auto Sales",
    "wof:placetype":"venue"
},
  "geometry": {"coordinates":[-89.255016,45.922652],"type":"Point"}
}