{
  "type": "Feature",
  "properties": {
    "iso:country":"US",
    "sg:address":"228 Reuter Ave",
    "sg:city":"Rice Lake",
    "sg:classifiers":[
        {
            "category":"Building & Trades",
            "subcategory":"Construction",
            "type":"Services"
        }
    ],
    "sg:phone":"+1 715 234 5440",
    "sg:postcode":"54868",
    "sg:province":"WI",
    "sg:tags":[
        "contractor"
    ],
    "wof:name":"Solar Eclipse Window Tinting",
    "wof:placetype":"venue"
},
  "geometry": {"coordinates":[-91.740285,45.498096],"type":"Point"}
}