{
  "type": "Feature",
  "properties": {
    "iso:country":"US",
    "sg:address":"5990 US Hwy 51",
    "sg:city":"Mc Farland",
    "sg:classifiers":[
        {
            "category":"Banks & Credit Unions",
            "subcategory":"Investment Brokerage",
            "type":"Services"
        }
    ],
    "sg:phone":"+1 608 838 2265",
    "sg:postcode":"53558",
    "sg:province":"WI",
    "wof:name":"Mcfarland Investment Corp",
    "wof:placetype":"venue"
},
  "geometry": {"coordinates":[-89.302931,43.01358],"type":"Point"}
}