{
  "type": "Feature",
  "properties": {
    "iso:country":"US",
    "sg:address":"610 Depere Rd",
    "sg:city":"Denmark",
    "sg:classifiers":[
        {
            "category":"Restaurant",
            "type":"Food & Drink"
        }
    ],
    "sg:phone":"+1 920 863 3922",
    "sg:postcode":"54208",
    "sg:province":"WI",
    "wof:name":"Mc Donald's",
    "wof:placetype":"venue"
},
  "geometry": {"coordinates":[-87.837216,44.347235],"type":"Point"}
}