{
  "type": "Feature",
  "properties": {
    "iso:country":"US",
    "sg:address":"3827 W Clarke St",
    "sg:city":"Milwaukee",
    "sg:classifiers":[
        {
            "category":"Shopping",
            "subcategory":"Gifts & Souvenirs",
            "type":"Retail Goods"
        }
    ],
    "sg:phone":"+1 414 342 1837",
    "sg:postcode":"53210",
    "sg:province":"WI",
    "sg:tags":[
        "shop"
    ],
    "wof:name":"B & L Nationwide Gift Shop",
    "wof:placetype":"venue"
},
  "geometry": {"coordinates":[-87.96192,43.065992],"type":"Point"}
}