{
  "type": "Feature",
  "properties": {
    "iso:country":"US",
    "sg:address":"5210 Odana Rd",
    "sg:city":"Madison",
    "sg:classifiers":[
        {
            "category":"Organizations",
            "subcategory":"Religious Organization",
            "type":"Services"
        }
    ],
    "sg:phone":"+1 608 274 0266",
    "sg:postcode":"53711",
    "sg:province":"WI",
    "sg:tags":[
        "church"
    ],
    "sg:website":"www.westwoodchristian.com",
    "wof:name":"Christian Westwood Church",
    "wof:placetype":"venue"
},
  "geometry": {"coordinates":[-89.471073,43.050099],"type":"Point"}
}