{
  "type": "Feature",
  "properties": {
    "iso:country":"US",
    "sg:address":"8432 Flambeau Ave",
    "sg:city":"Ladysmith",
    "sg:classifiers":[
        {
            "category":"Professional",
            "subcategory":"Management & Consulting",
            "type":"Services"
        }
    ],
    "sg:phone":"+1 715 532 7356",
    "sg:postcode":"54848",
    "sg:province":"WI",
    "wof:name":"Senior Financial Resource",
    "wof:placetype":"venue"
},
  "geometry": {"coordinates":[-91.107093,45.479841],"type":"Point"}
}