{
  "type": "Feature",
  "properties": {
    "iso:country":"US",
    "sg:address":"506 Main St",
    "sg:city":"La Crosse",
    "sg:classifiers":[
        {
            "category":"Home & Garden",
            "subcategory":"Furniture",
            "type":"Retail Goods"
        }
    ],
    "sg:phone":"+1 608 781 8558",
    "sg:postcode":"54601",
    "sg:province":"WI",
    "wof:name":"Onalaska Furniture",
    "wof:placetype":"venue"
},
  "geometry": {"coordinates":[-91.248255,43.81156],"type":"Point"}
}