{
  "type": "Feature",
  "properties": {
    "iso:country":"US",
    "sg:address":"1541 Bellevue St",
    "sg:city":"Green Bay",
    "sg:classifiers":[
        {
            "category":"Sports & Exercise",
            "subcategory":"Gym",
            "type":"Entertainment"
        }
    ],
    "sg:phone":"+1 920 469 3850",
    "sg:postcode":"54311",
    "sg:province":"WI",
    "sg:tags":[
        "club",
        "health",
        "studio",
        "gymnasium"
    ],
    "wof:name":"Curves For Women",
    "wof:placetype":"venue"
},
  "geometry": {"coordinates":[-87.99955199999999,44.474868],"type":"Point"}
}