{
  "type": "Feature",
  "properties": {
    "iso:country":"US",
    "sg:address":"5715 W Appleton Ave",
    "sg:city":"Milwaukee",
    "sg:classifiers":[
        {
            "category":"Retail",
            "subcategory":"Auto Repair",
            "type":"Services"
        }
    ],
    "sg:phone":"+1 414 445 8000",
    "sg:postcode":"53210",
    "sg:province":"WI",
    "sg:tags":[
        "body",
        "automobile",
        "used"
    ],
    "wof:name":"Roberts Auto Mart Inc",
    "wof:placetype":"venue"
},
  "geometry": {"coordinates":[-87.984516,43.066864],"type":"Point"}
}