{
  "type": "Feature",
  "properties": {
    "iso:country":"US",
    "sg:address":"6250 Norwegian Rd",
    "sg:city":"Bruce",
    "sg:classifiers":[
        {
            "category":"Farming",
            "subcategory":"Livestock Farm",
            "type":"Manufacturing & Wholesale Goods"
        }
    ],
    "sg:phone":"+1 715 868 6250",
    "sg:postcode":"54819",
    "sg:province":"WI",
    "sg:tags":[
        "beef",
        "feedlot",
        "cattle"
    ],
    "wof:name":"Joel Borta",
    "wof:placetype":"venue"
},
  "geometry": {"coordinates":[-91.39949799999999,45.512172],"type":"Point"}
}