{
  "type": "Feature",
  "properties": {
    "iso:country":"US",
    "sg:address":"3312 River Bend Rd",
    "sg:city":"Peshtigo",
    "sg:classifiers":[
        {
            "category":"Manufacturing",
            "subcategory":"Lumber",
            "type":"Manufacturing & Wholesale Goods"
        }
    ],
    "sg:phone":"+1 715 582 4340",
    "sg:postcode":"54157",
    "sg:province":"WI",
    "sg:tags":[
        "forestry"
    ],
    "wof:name":"Trees & Trails Forestry Conslt",
    "wof:placetype":"venue"
},
  "geometry": {"coordinates":[-87.97811799999999,45.204],"type":"Point"}
}