{
  "type": "Feature",
  "properties": {
    "addr:full":"337 S Main St West Bend WI 53095",
    "addr:housenumber":"337",
    "addr:postcode":"53095",
    "addr:street":"S Main St",
    "iso:country":"US",
    "sg:address":"337 S Main St",
    "sg:city":"West Bend",
    "sg:classifiers":[
        {
            "category":"Professional",
            "subcategory":"Business Services",
            "type":"Services"
        }
    ],
    "sg:phone":"+1 262 334 5402",
    "sg:postcode":"53095",
    "sg:province":"WI",
    "sg:tags":[
        "transportation",
        "freight",
        "arrangement"
    ],
    "wof:name":"Mail Drop",
    "wof:placetype":"venue"
},
  "geometry": {"coordinates":[-88.180999,43.420406],"type":"Point"}
}