{
  "type": "Feature",
  "properties": {
    "addr:full":"621 Twelve Oak Ln Hudson WI 54016",
    "addr:housenumber":"621",
    "addr:postcode":"54016",
    "addr:street":"Twelve Oak Ln",
    "iso:country":"US",
    "sg:address":"621 Twelve Oak Ln",
    "sg:city":"Hudson",
    "sg:classifiers":[
        {
            "category":"Professional",
            "type":"Services"
        }
    ],
    "sg:phone":"+1 715 381 3076",
    "sg:postcode":"54016",
    "sg:province":"WI",
    "wof:name":"Integrated Network Tech",
    "wof:placetype":"venue"
},
  "geometry": {"coordinates":[-92.740595,44.977678],"type":"Point"}
}