{
  "type": "Feature",
  "properties": {
    "iso:country":"US",
    "sg:address":"404 W Main St",
    "sg:city":"Merrill",
    "sg:classifiers":[
        {
            "category":"Banks & Credit Unions",
            "subcategory":"Bank",
            "type":"Services"
        }
    ],
    "sg:phone":"+1 715 536 5202",
    "sg:postcode":"54452",
    "sg:province":"WI",
    "sg:tags":[
        "loan",
        "real estate"
    ],
    "wof:name":"CLA Mortgage",
    "wof:placetype":"venue"
},
  "geometry": {"coordinates":[-89.706648,45.179033],"type":"Point"}
}