{
  "type": "Feature",
  "properties": {
    "iso:country":"US",
    "sg:address":"2338 N 7th St",
    "sg:city":"Milwaukee",
    "sg:classifiers":[
        {
            "category":"Personal",
            "subcategory":"Beauty Salon",
            "type":"Services"
        }
    ],
    "sg:phone":"+1 414 264 1755",
    "sg:postcode":"53212",
    "sg:province":"WI",
    "sg:tags":[
        "shop"
    ],
    "wof:name":"Mario House of Beauty",
    "wof:placetype":"venue"
},
  "geometry": {"coordinates":[-87.91989599999999,43.062129],"type":"Point"}
}