{
  "type": "Feature",
  "properties": {
    "iso:country":"US",
    "sg:address":"9250 W Watertown Plank Rd",
    "sg:city":"Milwaukee",
    "sg:classifiers":[
        {
            "category":"Utilities",
            "subcategory":"Electric",
            "type":"Services"
        }
    ],
    "sg:phone":"+1 414 221 4447",
    "sg:postcode":"53226",
    "sg:province":"WI",
    "sg:website":"http://www.powerthefuture.com",
    "wof:name":"Wisconsin Electric Power Company",
    "wof:placetype":"venue"
},
  "geometry": {"coordinates":[-88.027687,43.045078],"type":"Point"}
}