{
  "type": "Feature",
  "properties": {
    "iso:country":"US",
    "sg:address":"2734 N Stowell Ave",
    "sg:city":"Milwaukee",
    "sg:classifiers":[
        {
            "category":"Professional",
            "type":"Services"
        }
    ],
    "sg:phone":"+1 414 961 0199",
    "sg:postcode":"53211",
    "sg:province":"WI",
    "wof:name":"Sarah Erdmann",
    "wof:placetype":"venue"
},
  "geometry": {"coordinates":[-87.879215,43.068618],"type":"Point"}
}