{
  "type": "Feature",
  "properties": {
    "iso:country":"US",
    "sg:address":"18201 115th Ave",
    "sg:city":"Chippewa Falls",
    "sg:phone":"+1 715 382 4771",
    "sg:postcode":"54729",
    "sg:province":"WI",
    "sg:tags":[
        "farm",
        "corn"
    ],
    "wof:name":"Loren Lueck Farm",
    "wof:placetype":"venue"
},
  "geometry": {"coordinates":[-91.3034,45.009515],"type":"Point"}
}