{
  "type": "Feature",
  "properties": {
    "iso:country":"US",
    "sg:address":"759 N Milwaukee St",
    "sg:city":"Milwaukee",
    "sg:classifiers":[
        {
            "category":"Professional",
            "subcategory":"Advertising",
            "type":"Services"
        }
    ],
    "sg:phone":"+1 414 272 8700",
    "sg:postcode":"53202",
    "sg:province":"WI",
    "sg:tags":[
        "counselor"
    ],
    "wof:name":"Marge Meyer Assoc Inc",
    "wof:placetype":"venue"
},
  "geometry": {"coordinates":[-87.906841,43.040977],"type":"Point"}
}