{
  "type": "Feature",
  "properties": {
    "addr:full":"120 Nashotah Rd Nashotah WI 53058",
    "addr:housenumber":"120",
    "addr:postcode":"53058",
    "addr:street":"Nashotah Rd",
    "iso:country":"US",
    "sg:address":"120 Nashotah Rd",
    "sg:city":"Nashotah",
    "sg:classifiers":[
        {
            "category":"Organizations",
            "subcategory":"Religious Organization",
            "type":"Services"
        }
    ],
    "sg:phone":"+1 262 646 8078",
    "sg:postcode":"53058",
    "sg:province":"WI",
    "wof:name":"Stjoan of ARC",
    "wof:placetype":"venue"
},
  "geometry": {"coordinates":[-88.41824,43.093463],"type":"Point"}
}