{
  "type": "Feature",
  "properties": {
    "iso:country":"US",
    "sg:address":"8226 Big Bend Rd",
    "sg:city":"Waterford",
    "sg:classifiers":[
        {
            "category":"Food & Beverages",
            "subcategory":"Liquor & Beverages",
            "type":"Retail Goods"
        }
    ],
    "sg:phone":"+1 262 895 6707",
    "sg:postcode":"53185",
    "sg:province":"WI",
    "wof:name":"Tichigan Beer Depot",
    "wof:placetype":"venue"
},
  "geometry": {"coordinates":[-88.19815,42.831349],"type":"Point"}
}