{
  "type": "Feature",
  "properties": {
    "iso:country":"US",
    "sg:address":"3250 S Stonegate Cir",
    "sg:city":"New Berlin",
    "sg:classifiers":[
        {
            "category":"Professional",
            "subcategory":"Art Services",
            "type":"Services"
        }
    ],
    "sg:phone":"+1 262 784 1034",
    "sg:postcode":"53151",
    "sg:province":"WI",
    "sg:tags":[
        "commercial",
        "design"
    ],
    "wof:name":"Sheldon Printing & Publishing",
    "wof:placetype":"venue"
},
  "geometry": {"coordinates":[-88.08113899999999,42.985682],"type":"Point"}
}