{
  "type": "Feature",
  "properties": {
    "iso:country":"US",
    "sg:address":"7733 N 80th St",
    "sg:city":"Milwaukee",
    "sg:classifiers":[
        {
            "category":"Professional",
            "type":"Services"
        }
    ],
    "sg:phone":"+1 414 355 9340",
    "sg:postcode":"53223",
    "sg:province":"WI",
    "sg:tags":[
        "establishment"
    ],
    "wof:name":"Muhhammad Abdurrahim",
    "wof:placetype":"venue"
},
  "geometry": {"coordinates":[-88.0093,43.158764],"type":"Point"}
}