{
  "type": "Feature",
  "properties": {
    "iso:country":"US",
    "sg:address":"8995 Pine St",
    "sg:city":"Nichols",
    "sg:classifiers":[
        {
            "category":"Manufacturing",
            "subcategory":"Paper Products",
            "type":"Manufacturing & Wholesale Goods"
        }
    ],
    "sg:phone":"+1 920 833 6895",
    "sg:postcode":"54152",
    "sg:province":"WI",
    "sg:website":"www.nicholspaper.com",
    "wof:name":"Nichols Paper Products Co",
    "wof:placetype":"venue"
},
  "geometry": {"coordinates":[-88.46347,44.562051],"type":"Point"}
}