{
  "type": "Feature",
  "properties": {
    "iso:country":"US",
    "sg:address":"8129 Larson Rd",
    "sg:city":"Cambria",
    "sg:classifiers":[
        {
            "category":"Travel",
            "subcategory":"Campground",
            "type":"Entertainment"
        }
    ],
    "sg:phone":"+1 920 348 6413",
    "sg:postcode":"53923",
    "sg:province":"WI",
    "sg:tags":[
        "trailer"
    ],
    "wof:name":"Deer Creek Campground LLC",
    "wof:placetype":"venue"
},
  "geometry": {"coordinates":[-89.187549,43.57072],"type":"Point"}
}