{
  "type": "Feature",
  "properties": {
    "iso:country":"US",
    "sg:address":"1131 Main St",
    "sg:city":"Oconto",
    "sg:classifiers":[
        {
            "category":"Sports & Exercise",
            "subcategory":"Gym",
            "type":"Entertainment"
        }
    ],
    "sg:phone":"+1 920 835 1188",
    "sg:postcode":"54153",
    "sg:province":"WI",
    "sg:tags":[
        "fitness",
        "physical",
        "facility"
    ],
    "wof:name":"Curves of Oconto",
    "wof:placetype":"venue"
},
  "geometry": {"coordinates":[-87.867133,44.887614],"type":"Point"}
}