{
  "type": "Feature",
  "properties": {
    "iso:country":"US",
    "sg:address":"8478 Cloverleaf Lake Rd",
    "sg:city":"Clintonville",
    "sg:classifiers":[
        {
            "category":"Building & Trades",
            "subcategory":"Landscaping Services",
            "type":"Services"
        }
    ],
    "sg:phone":"+1 715 823 3886",
    "sg:postcode":"54929",
    "sg:province":"WI",
    "sg:tags":[
        "lawn",
        "maintenance",
        "grounds"
    ],
    "wof:name":"Tony's Lawn Care",
    "wof:placetype":"venue"
},
  "geometry": {"coordinates":[-88.663303,44.693204],"type":"Point"}
}