{
  "type": "Feature",
  "properties": {
    "iso:country":"US",
    "sg:address":"1215 N Bequette St",
    "sg:city":"Dodgeville",
    "sg:classifiers":[
        {
            "category":"Government",
            "subcategory":"Office",
            "type":"Public Place"
        }
    ],
    "sg:phone":"+1 608 935 3381",
    "sg:postcode":"53533",
    "sg:province":"WI",
    "wof:name":"Iowa County Highway Cmmssnr",
    "wof:placetype":"venue"
},
  "geometry": {"coordinates":[-90.132732,42.974181],"type":"Point"}
}