{
  "type": "Feature",
  "properties": {
    "addr:full":"216 S 3rd St Watertown WI 53094",
    "addr:housenumber":"216",
    "addr:postcode":"53094",
    "addr:street":"S 3Rd St",
    "iso:country":"US",
    "sg:address":"216 S 3rd St",
    "sg:city":"Watertown",
    "sg:classifiers":[
        {
            "category":"Health Services",
            "subcategory":"Medical Lab",
            "type":"Services"
        }
    ],
    "sg:phone":"+1 920 261 8080",
    "sg:postcode":"53094",
    "sg:province":"WI",
    "sg:tags":[
        "laboratory",
        "dental"
    ],
    "wof:name":"D & S Dental Laboratory Inc",
    "wof:placetype":"venue"
},
  "geometry": {"coordinates":[-88.72243400000001,43.19321],"type":"Point"}
}