{
  "type": "Feature",
  "properties": {
    "addr:full":"6636 L B White Rd Onalaska WI 54650",
    "addr:housenumber":"6636",
    "addr:postcode":"54650",
    "addr:street":"L B White Rd",
    "iso:country":"US",
    "sg:address":"6636 L B White Rd",
    "sg:city":"Onalaska",
    "sg:classifiers":[
        {
            "category":"Manufacturing",
            "subcategory":"Metals",
            "type":"Manufacturing & Wholesale Goods"
        }
    ],
    "sg:phone":"+1 608 783 5691",
    "sg:postcode":"54650",
    "sg:province":"WI",
    "sg:tags":[
        "steel",
        "mfg",
        "stainless",
        "heating",
        "equipment",
        "s"
    ],
    "wof:name":"PSI",
    "wof:placetype":"venue"
},
  "geometry": {"coordinates":[-91.236525,43.910322],"type":"Point"}
}