{
  "type": "Feature",
  "properties": {
    "iso:country":"US",
    "sg:address":"177 Division St",
    "sg:city":"Park Falls",
    "sg:classifiers":[
        {
            "category":"Restaurant",
            "type":"Food & Drink"
        }
    ],
    "sg:phone":"+1 715 762 1668",
    "sg:postcode":"54552",
    "sg:province":"WI",
    "wof:name":"Frontier",
    "wof:placetype":"venue"
},
  "geometry": {"coordinates":[-90.448853,45.93504],"type":"Point"}
}