{
  "type": "Feature",
  "properties": {
    "iso:country":"US",
    "sg:address":"204 E Pier St",
    "sg:city":"Port Washington",
    "sg:classifiers":[
        {
            "category":"Professional",
            "subcategory":"Management & Consulting",
            "type":"Services"
        }
    ],
    "sg:phone":"+1 262 284 6700",
    "sg:postcode":"53074",
    "sg:province":"WI",
    "sg:tags":[
        "business"
    ],
    "wof:name":"Port Enviromental LLC",
    "wof:placetype":"venue"
},
  "geometry": {"coordinates":[-87.867728,43.389972],"type":"Point"}
}