{
  "type": "Feature",
  "properties": {
    "addr:full":"3027 W Lincoln Ave Milwaukee WI 53215",
    "addr:housenumber":"3027",
    "addr:postcode":"53215",
    "addr:street":"W Lincoln Ave",
    "iso:country":"US",
    "sg:address":"3027 W Lincoln Ave",
    "sg:city":"Milwaukee",
    "sg:classifiers":[
        {
            "category":"Banks & Credit Unions",
            "subcategory":"Bank",
            "type":"Services"
        }
    ],
    "sg:phone":"+1 414 645 0280",
    "sg:postcode":"53215",
    "sg:province":"WI",
    "sg:tags":[
        "state"
    ],
    "wof:name":"Associated Bank",
    "wof:placetype":"venue"
},
  "geometry": {"coordinates":[-87.952659,43.00303],"type":"Point"}
}