{
  "type": "Feature",
  "properties": {
    "iso:country":"US",
    "sg:address":"8191 S Pole Grove Rd",
    "sg:city":"Hixton",
    "sg:classifiers":[
        {
            "category":"Building & Trades",
            "subcategory":"Construction",
            "type":"Services"
        }
    ],
    "sg:phone":"+1 715 963 2947",
    "sg:postcode":"54635",
    "sg:province":"WI",
    "sg:tags":[
        "roofing",
        "contractor"
    ],
    "wof:name":"Knutson Roofing",
    "wof:placetype":"venue"
},
  "geometry": {"coordinates":[-90.969369,44.375497],"type":"Point"}
}