{
  "type": "Feature",
  "properties": {
    "addr:full":"737 W Glendale Ave Milwaukee WI 53209",
    "addr:housenumber":"737",
    "addr:postcode":"53209",
    "addr:street":"W Glendale Ave",
    "iso:country":"US",
    "sg:address":"737 W Glendale Ave",
    "sg:city":"Milwaukee",
    "sg:classifiers":[
        {
            "category":"Real Estate",
            "subcategory":"Developer",
            "type":"Services"
        }
    ],
    "sg:phone":"+1 414 332 5370",
    "sg:postcode":"53209",
    "sg:province":"WI",
    "wof:name":"Fratrick & Finnessy Inc",
    "wof:placetype":"venue"
},
  "geometry": {"coordinates":[-87.918744,43.100033],"type":"Point"}
}