{
  "type": "Feature",
  "properties": {
    "iso:country":"US",
    "sg:address":"680 Steele Rd",
    "sg:city":"Fall River",
    "sg:classifiers":[
        {
            "category":"Building & Trades",
            "subcategory":"Plumbing",
            "type":"Services"
        }
    ],
    "sg:phone":"+1 920 484 6522",
    "sg:postcode":"53932",
    "sg:province":"WI",
    "sg:tags":[
        "contractor"
    ],
    "wof:name":"Number One Plumbing Inc",
    "wof:placetype":"venue"
},
  "geometry": {"coordinates":[-89.062924,43.379828],"type":"Point"}
}