{
  "type": "Feature",
  "properties": {
    "iso:country":"US",
    "sg:address":"253 Center St",
    "sg:city":"Lake Geneva",
    "sg:classifiers":[
        {
            "category":"Banks & Credit Unions",
            "subcategory":"Bank",
            "type":"Services"
        }
    ],
    "sg:phone":"+1 262 249 0980",
    "sg:postcode":"53147",
    "sg:province":"WI",
    "sg:tags":[
        "federal",
        "savings",
        "institution",
        "mortgage"
    ],
    "wof:name":"Washington Mutual Bank",
    "wof:placetype":"venue"
},
  "geometry": {"coordinates":[-88.433566,42.59294],"type":"Point"}
}