{
  "type": "Feature",
  "properties": {
    "iso:country":"US",
    "sg:address":"1823 S Park St",
    "sg:city":"Madison",
    "sg:classifiers":[
        {
            "category":"Autos & Motor Vehicles",
            "subcategory":"Auto Supplies",
            "type":"Retail Goods"
        }
    ],
    "sg:phone":"+1 608 255 1668",
    "sg:postcode":"53713",
    "sg:province":"WI",
    "sg:tags":[
        "automobile",
        "parts"
    ],
    "wof:name":"GTC Auto Parts",
    "wof:placetype":"venue"
},
  "geometry": {"coordinates":[-89.393978,43.046777],"type":"Point"}
}