{
  "type": "Feature",
  "properties": {
    "iso:country":"US",
    "sg:address":"411 Washington St",
    "sg:city":"Wausau",
    "sg:classifiers":[
        {
            "category":"Retail",
            "subcategory":"Portrait Studio",
            "type":"Services"
        }
    ],
    "sg:phone":"+1 715 845 6261",
    "sg:postcode":"54403",
    "sg:province":"WI",
    "sg:tags":[
        "photographer",
        "photo"
    ],
    "wof:name":"Sears Portrait Studio M63",
    "wof:placetype":"venue"
},
  "geometry": {"coordinates":[-89.625795,44.95876],"type":"Point"}
}