{
  "type": "Feature",
  "properties": {
    "iso:country":"US",
    "sg:address":"2040 Jefferson St",
    "sg:city":"Stevens Point",
    "sg:classifiers":[
        {
            "category":"Health Services",
            "subcategory":"Clinic",
            "type":"Services"
        }
    ],
    "sg:phone":"+1 715 341 2540",
    "sg:postcode":"54481",
    "sg:province":"WI",
    "sg:tags":[
        "home",
        "care"
    ],
    "sg:website":"www.auroraservices.com",
    "wof:name":"Jefferson House",
    "wof:placetype":"venue"
},
  "geometry": {"coordinates":[-89.570082,44.519446],"type":"Point"}
}