{
  "type": "Feature",
  "properties": {
    "iso:country":"US",
    "sg:address":"644 S 7th Ave",
    "sg:city":"West Bend",
    "sg:classifiers":[
        {
            "category":"Professional",
            "subcategory":"Business Services",
            "type":"Services"
        }
    ],
    "sg:phone":"+1 262 338 2185",
    "sg:postcode":"53095",
    "sg:province":"WI",
    "wof:name":"Stonebridge LLC",
    "wof:placetype":"venue"
},
  "geometry": {"coordinates":[-88.18493100000001,43.415396],"type":"Point"}
}