{
  "type": "Feature",
  "properties": {
    "iso:country":"US",
    "sg:address":"1126 Grant St",
    "sg:city":"Lake Geneva",
    "sg:classifiers":[
        {
            "category":"Recreation",
            "type":"Entertainment"
        }
    ],
    "sg:phone":"+1 262 723 1815",
    "sg:postcode":"53147",
    "sg:province":"WI",
    "wof:name":"Meadow Creek Stables",
    "wof:placetype":"venue"
},
  "geometry": {"coordinates":[-88.44045300000001,42.60312],"type":"Point"}
}