{
  "type": "Feature",
  "properties": {
    "iso:country":"US",
    "sg:address":"203 S Paterson St",
    "sg:city":"Madison",
    "sg:classifiers":[
        {
            "category":"Professional",
            "type":"Services"
        }
    ],
    "sg:phone":"+1 608 663 3750",
    "sg:postcode":"53703",
    "sg:province":"WI",
    "wof:name":"Envise LLC",
    "wof:placetype":"venue"
},
  "geometry": {"coordinates":[-89.370679,43.080251],"type":"Point"}
}