{
  "type": "Feature",
  "properties": {
    "addr:full":"1530 Troy Dr Madison WI 53704",
    "addr:housenumber":"1530",
    "addr:postcode":"53704",
    "addr:street":"Troy Dr",
    "iso:country":"US",
    "sg:address":"1530 Troy Dr",
    "sg:city":"Madison",
    "sg:classifiers":[
        {
            "category":"Social Services",
            "subcategory":"Child Care",
            "type":"Services"
        },
        {
            "category":"Social Services",
            "type":"Services"
        }
    ],
    "sg:phone":"+1 608 241 4722",
    "sg:postcode":"53704",
    "sg:province":"WI",
    "wof:name":"Jovana's Daycare",
    "wof:placetype":"venue"
},
  "geometry": {"coordinates":[-89.369112,43.133267],"type":"Point"}
}