{
  "type": "Feature",
  "properties": {
    "iso:country":"US",
    "sg:address":"107 E Lincoln Ave",
    "sg:city":"Milwaukee",
    "sg:classifiers":[
        {
            "category":"Wholesale",
            "subcategory":"Fruits & Vegetables",
            "type":"Manufacturing & Wholesale Goods"
        }
    ],
    "sg:phone":"+1 414 483 8942",
    "sg:postcode":"53207",
    "sg:province":"WI",
    "sg:tags":[
        "fresh"
    ],
    "wof:name":"Pre Pac Food Co",
    "wof:placetype":"venue"
},
  "geometry": {"coordinates":[-87.91055,43.002796],"type":"Point"}
}