{
  "type": "Feature",
  "properties": {
    "iso:country":"US",
    "sg:address":"504 Hogan St",
    "sg:city":"Antigo",
    "sg:classifiers":[
        {
            "category":"Building & Trades",
            "subcategory":"Construction",
            "type":"Services"
        }
    ],
    "sg:phone":"+1 715 623 2212",
    "sg:postcode":"54409",
    "sg:province":"WI",
    "wof:name":"Sewer Tech LLC",
    "wof:placetype":"venue"
},
  "geometry": {"coordinates":[-89.167445,45.138236],"type":"Point"}
}