{
  "type": "Feature",
  "properties": {
    "iso:country":"US",
    "sg:address":"1111 20th Pl",
    "sg:city":"Wisconsin Rapids",
    "sg:classifiers":[
        {
            "category":"Building & Trades",
            "subcategory":"Landscaping Services",
            "type":"Services"
        }
    ],
    "sg:phone":"+1 715 423 4455",
    "sg:postcode":"54494",
    "sg:province":"WI",
    "sg:tags":[
        "landscape",
        "contractor"
    ],
    "wof:name":"Grounds Detail Svc",
    "wof:placetype":"venue"
},
  "geometry": {"coordinates":[-89.80234,44.380998],"type":"Point"}
}