{
  "type": "Feature",
  "properties": {
    "addr:full":"2066 Lawrence Dr De Pere WI 54115",
    "addr:housenumber":"2066",
    "addr:postcode":"54115",
    "addr:street":"Lawrence Dr",
    "iso:country":"US",
    "sg:address":"2066 Lawrence Dr",
    "sg:city":"De Pere",
    "sg:classifiers":[
        {
            "category":"Social Services",
            "type":"Services"
        }
    ],
    "sg:phone":"+1 920 338 8699",
    "sg:postcode":"54115",
    "sg:province":"WI",
    "sg:tags":[
        "counseling"
    ],
    "wof:name":"Living Hope Christian Cnslng",
    "wof:placetype":"venue"
},
  "geometry": {"coordinates":[-88.11323299999999,44.419481],"type":"Point"}
}