{
  "type": "Feature",
  "properties": {
    "iso:country":"US",
    "sg:address":"11400 W Burleigh St",
    "sg:city":"Milwaukee",
    "sg:classifiers":[
        {
            "category":"Freight",
            "type":"Transportation"
        }
    ],
    "sg:phone":"+1 414 778 0100",
    "sg:postcode":"53222",
    "sg:province":"WI",
    "sg:tags":[
        "refrigeration",
        "general"
    ],
    "wof:name":"Milwaukee Ligistics",
    "wof:placetype":"venue"
},
  "geometry": {"coordinates":[-88.057491,43.074593],"type":"Point"}
}