{
  "type": "Feature",
  "properties": {
    "iso:country":"US",
    "sg:address":"94 Lawson St",
    "sg:city":"Menasha",
    "sg:classifiers":[
        {
            "category":"Manufacturing",
            "subcategory":"Metals",
            "type":"Manufacturing & Wholesale Goods"
        }
    ],
    "sg:phone":"+1 920 725 8617",
    "sg:postcode":"54952",
    "sg:province":"WI",
    "wof:name":"Elite Custom Metal Finishing",
    "wof:placetype":"venue"
},
  "geometry": {"coordinates":[-88.460359,44.198233],"type":"Point"}
}