{
  "type": "Feature",
  "properties": {
    "iso:country":"US",
    "sg:address":"15310 Dutch Hill Rd",
    "sg:city":"Woodman",
    "sg:classifiers":[
        {
            "category":"Farming",
            "subcategory":"Livestock Farm",
            "type":"Manufacturing & Wholesale Goods"
        }
    ],
    "sg:phone":"+1 608 533 2416",
    "sg:postcode":"53827",
    "sg:province":"WI",
    "sg:tags":[
        "feedlot",
        "field",
        "crop",
        "beef",
        "cattle"
    ],
    "wof:name":"Christoph L Gebhard",
    "wof:placetype":"venue"
},
  "geometry": {"coordinates":[-90.789811,43.073572],"type":"Point"}
}