{
  "type": "Feature",
  "properties": {
    "iso:country":"US",
    "sg:address":"4776 Co Rd Tt",
    "sg:city":"Cottage Grove",
    "sg:classifiers":[
        {
            "category":"Real Estate",
            "subcategory":"Real Estate Operator",
            "type":"Services"
        }
    ],
    "sg:phone":"+1 608 246 4142",
    "sg:postcode":"53527",
    "sg:province":"WI",
    "sg:tags":[
        "building",
        "nonresidential"
    ],
    "wof:name":"Business Park Development LLC",
    "wof:placetype":"venue"
},
  "geometry": {"coordinates":[-89.194867,43.111451],"type":"Point"}
}