{
  "type": "Feature",
  "properties": {
    "iso:country":"US",
    "sg:address":"12044 State Hwy 78",
    "sg:city":"Argyle",
    "sg:classifiers":[
        {
            "category":"Farming",
            "subcategory":"Farm & Veterinary Services",
            "type":"Manufacturing & Wholesale Goods"
        }
    ],
    "sg:phone":"+1 608 543 3778",
    "sg:postcode":"53504",
    "sg:province":"WI",
    "sg:tags":[
        "livestock"
    ],
    "wof:name":"Owego Stock Farm",
    "wof:placetype":"venue"
},
  "geometry": {"coordinates":[-89.896036,42.668561],"type":"Point"}
}