{
  "type": "Feature",
  "properties": {
    "iso:country":"US",
    "sg:address":"1412 Crystal Lake Dr",
    "sg:city":"Oconomowoc",
    "sg:classifiers":[
        {
            "category":"Professional",
            "subcategory":"Computer Services",
            "type":"Services"
        }
    ],
    "sg:phone":"+1 262 569 9787",
    "sg:postcode":"53066",
    "sg:province":"WI",
    "sg:tags":[
        "datum"
    ],
    "wof:name":"SF Sports LLC",
    "wof:placetype":"venue"
},
  "geometry": {"coordinates":[-88.489906,43.132025],"type":"Point"}
}