{
  "type": "Feature",
  "properties": {
    "iso:country":"US",
    "sg:address":"455 Springbrook Ct",
    "sg:city":"Mayville",
    "sg:classifiers":[
        {
            "category":"Professional",
            "subcategory":"Computer Services",
            "type":"Services"
        }
    ],
    "sg:phone":"+1 920 387 4797",
    "sg:postcode":"53050",
    "sg:province":"WI",
    "sg:tags":[
        "related"
    ],
    "wof:name":"Ronald A Carpenter & Assoc LLC",
    "wof:placetype":"venue"
},
  "geometry": {"coordinates":[-88.55035,43.502066],"type":"Point"}
}