{
  "type": "Feature",
  "properties": {
    "addr:full":"1973 117th Ave Dresser WI 54009",
    "addr:housenumber":"1973",
    "addr:postcode":"54009",
    "addr:street":"117Th Ave",
    "iso:country":"US",
    "sg:address":"1973 117th Ave",
    "sg:city":"Dresser",
    "sg:classifiers":[
        {
            "category":"Building & Trades",
            "subcategory":"Construction",
            "type":"Services"
        }
    ],
    "sg:phone":"+1 715 483 5776",
    "sg:postcode":"54009",
    "sg:province":"WI",
    "sg:tags":[
        "contractor"
    ],
    "wof:name":"Siding & Roofing Guys",
    "wof:placetype":"venue"
},
  "geometry": {"coordinates":[-92.565417,45.377321],"type":"Point"}
}