{
  "type": "Feature",
  "properties": {
    "addr:full":"2572 Kitzinger Ln Fort Atkinson WI 53538",
    "addr:housenumber":"2572",
    "addr:postcode":"53538",
    "addr:street":"Kitzinger Ln",
    "iso:country":"US",
    "sg:address":"2572 Kitzinger Ln",
    "sg:city":"Fort Atkinson",
    "sg:classifiers":[
        {
            "category":"Professional",
            "subcategory":"Management & Consulting",
            "type":"Services"
        }
    ],
    "sg:phone":"+1 920 563 7002",
    "sg:postcode":"53538",
    "sg:province":"WI",
    "sg:tags":[
        "business"
    ],
    "wof:name":"Terry W Schwalenberg Consultin",
    "wof:placetype":"venue"
},
  "geometry": {"coordinates":[-88.714268,42.933666],"type":"Point"}
}