{
  "type": "Feature",
  "properties": {
    "iso:country":"US",
    "sg:address":"2421 E Main St",
    "sg:city":"Merrill",
    "sg:classifiers":[
        {
            "category":"Retail",
            "subcategory":"Auto Repair",
            "type":"Services"
        }
    ],
    "sg:phone":"+1 715 539 3344",
    "sg:postcode":"54452",
    "sg:province":"WI",
    "sg:tags":[
        "body",
        "automobile",
        "painting"
    ],
    "wof:name":"R P M Body & Custom",
    "wof:placetype":"venue"
},
  "geometry": {"coordinates":[-89.666469,45.180565],"type":"Point"}
}