{
  "type": "Feature",
  "properties": {
    "addr:full":"5117 N Bay Ridge Ave Milwaukee WI 53217",
    "addr:housenumber":"5117",
    "addr:postcode":"53217",
    "addr:street":"N Bay Ridge Ave",
    "iso:country":"US",
    "sg:address":"5117 N Bay Ridge Ave",
    "sg:city":"Milwaukee",
    "sg:classifiers":[
        {
            "category":"Professional",
            "subcategory":"Computer Services",
            "type":"Services"
        }
    ],
    "sg:phone":"+1 414 964 8647",
    "sg:postcode":"53217",
    "sg:province":"WI",
    "sg:tags":[
        "datum"
    ],
    "wof:name":"G T Design Inc",
    "wof:placetype":"venue"
},
  "geometry": {"coordinates":[-87.910725,43.111019],"type":"Point"}
}