{
  "type": "Feature",
  "properties": {
    "addr:full":"209 Bay Park Sq Green Bay WI 54304",
    "addr:housenumber":"209",
    "addr:postcode":"54304",
    "addr:street":"Bay Park Sq",
    "iso:country":"US",
    "sg:address":"209 Bay Park Sq",
    "sg:city":"Green Bay",
    "sg:classifiers":[
        {
            "category":"Food & Beverages",
            "subcategory":"Bakery",
            "type":"Retail Goods"
        }
    ],
    "sg:phone":"+1 920 499 9494",
    "sg:postcode":"54304",
    "sg:province":"WI",
    "wof:name":"Mrs Powells Cinnamon Rolls",
    "wof:placetype":"venue"
},
  "geometry": {"coordinates":[-88.067539,44.48448],"type":"Point"}
}