{
  "type": "Feature",
  "properties": {
    "iso:country":"US",
    "sg:address":"1017 Tower Ave",
    "sg:city":"Superior",
    "sg:classifiers":[
        {
            "category":"Retail",
            "subcategory":"Repair Shop",
            "type":"Services"
        }
    ],
    "sg:phone":"+1 715 392 5625",
    "sg:postcode":"54880",
    "sg:province":"WI",
    "wof:name":"Northern Lock & Key",
    "wof:placetype":"venue"
},
  "geometry": {"coordinates":[-92.10397,46.725616],"type":"Point"}
}