{
  "type": "Feature",
  "properties": {
    "iso:country":"US",
    "sg:address":"309 Ridge St",
    "sg:city":"Mineral Point",
    "sg:phone":"+1 608 987 1403",
    "sg:postcode":"53565",
    "sg:province":"WI",
    "sg:tags":[
        "farm",
        "field",
        "crop"
    ],
    "wof:name":"Karl Anderson",
    "wof:placetype":"venue"
},
  "geometry": {"coordinates":[-90.187972,42.861396],"type":"Point"}
}