{
  "type": "Feature",
  "properties": {
    "iso:country":"US",
    "sg:address":"2996 Beechwood Industrial Ct",
    "sg:city":"Hubertus",
    "sg:classifiers":[
        {
            "category":"Professional",
            "subcategory":"Accounting & Tax Preparation",
            "type":"Services"
        }
    ],
    "sg:phone":"+1 262 628 3196",
    "sg:postcode":"53033",
    "sg:province":"WI",
    "sg:tags":[
        "accountant",
        "public",
        "certified"
    ],
    "wof:name":"Erling K Christensen CPA",
    "wof:placetype":"venue"
},
  "geometry": {"coordinates":[-88.187974,43.233657],"type":"Point"}
}