{
  "type": "Feature",
  "properties": {
    "addr:full":"3906 S Whitnall Ave Milwaukee WI 53207",
    "addr:housenumber":"3906",
    "addr:postcode":"53207",
    "addr:street":"S Whitnall Ave",
    "iso:country":"US",
    "sg:address":"3906 S Whitnall Ave",
    "sg:city":"Milwaukee",
    "sg:classifiers":[
        {
            "category":"Wholesale",
            "subcategory":"Stationery",
            "type":"Manufacturing & Wholesale Goods"
        }
    ],
    "sg:phone":"+1 414 483 1093",
    "sg:postcode":"53207",
    "sg:province":"WI",
    "sg:tags":[
        "paper",
        "real estate"
    ],
    "wof:name":"Ideal Tape Products",
    "wof:placetype":"venue"
},
  "geometry": {"coordinates":[-87.905259,42.972948],"type":"Point"}
}