{
  "type": "Feature",
  "properties": {
    "iso:country":"US",
    "sg:address":"111 Maple St E",
    "sg:city":"Amery",
    "sg:classifiers":[
        {
            "category":"Utilities",
            "subcategory":"Fuel Oil & Lpg",
            "type":"Services"
        }
    ],
    "sg:phone":"+1 715 268 8335",
    "sg:postcode":"54001",
    "sg:province":"WI",
    "sg:tags":[
        "liquefied",
        "gas",
        "petroleum"
    ],
    "wof:name":"Ferrellgas",
    "wof:placetype":"venue"
},
  "geometry": {"coordinates":[-92.361546,45.313805],"type":"Point"}
}