{
  "type": "Feature",
  "properties": {
    "iso:country":"US",
    "sg:address":"2040 Rock Rd",
    "sg:city":"Stratford",
    "sg:classifiers":[
        {
            "category":"Retail",
            "subcategory":"Auto Repair",
            "type":"Services"
        }
    ],
    "sg:phone":"+1 715 687 2170",
    "sg:postcode":"54484",
    "sg:province":"WI",
    "sg:tags":[
        "general"
    ],
    "wof:name":"Kralls Auto Repair & Wrckr Svc",
    "wof:placetype":"venue"
},
  "geometry": {"coordinates":[-90.010653,44.829958],"type":"Point"}
}