{
  "type": "Feature",
  "properties": {
    "iso:country":"US",
    "sg:address":"26503 Musky Ave N",
    "sg:city":"Webster",
    "sg:classifiers":[
        {
            "category":"Organizations",
            "subcategory":"Religious Organization",
            "type":"Services"
        }
    ],
    "sg:phone":"+1 715 866 8646",
    "sg:postcode":"54893",
    "sg:province":"WI",
    "sg:tags":[
        "church"
    ],
    "wof:name":"Grace United Methodist Church",
    "wof:placetype":"venue"
},
  "geometry": {"coordinates":[-92.365686,45.878353],"type":"Point"}
}