{
  "type": "Feature",
  "properties": {
    "iso:country":"US",
    "sg:address":"310 Main St W",
    "sg:city":"Milltown",
    "sg:classifiers":[
        {
            "category":"Professional",
            "type":"Services"
        }
    ],
    "sg:phone":"+1 715 825 4654",
    "sg:postcode":"54858",
    "sg:province":"WI",
    "wof:name":"David & Rhonda J Hansch",
    "wof:placetype":"venue"
},
  "geometry": {"coordinates":[-92.51215000000001,45.526853],"type":"Point"}
}