{
  "type": "Feature",
  "properties": {
    "iso:country":"US",
    "sg:address":"1100 Nassau St",
    "sg:city":"New London",
    "sg:classifiers":[
        {
            "category":"Organizations",
            "subcategory":"Community Association",
            "type":"Services"
        }
    ],
    "sg:phone":"+1 920 982 6866",
    "sg:postcode":"54961",
    "sg:province":"WI",
    "wof:name":"Amvets",
    "wof:placetype":"venue"
},
  "geometry": {"coordinates":[-88.741915,44.383869],"type":"Point"}
}