{
  "type": "Feature",
  "properties": {
    "iso:country":"US",
    "sg:address":"1026 Co Rd M",
    "sg:city":"Adams",
    "sg:classifiers":[
        {
            "category":"Freight",
            "type":"Transportation"
        }
    ],
    "sg:phone":"+1 608 339 7606",
    "sg:postcode":"53910",
    "sg:province":"WI",
    "sg:tags":[
        "operator",
        "trucking"
    ],
    "wof:name":"Sutherland Trucking",
    "wof:placetype":"venue"
},
  "geometry": {"coordinates":[-89.77978,43.952257],"type":"Point"}
}