{
  "type": "Feature",
  "properties": {
    "addr:full":"4720 Golf Rd Eau Claire WI 54701",
    "addr:housenumber":"4720",
    "addr:postcode":"54701",
    "addr:street":"Golf Rd",
    "iso:country":"US",
    "sg:address":"4720 Golf Rd",
    "sg:city":"Eau Claire",
    "sg:classifiers":[
        {
            "category":"Shopping",
            "subcategory":"Optical Goods",
            "type":"Retail Goods"
        }
    ],
    "sg:phone":"+1 715 830 0916",
    "sg:postcode":"54701",
    "sg:province":"WI",
    "wof:name":"Sears Optical",
    "wof:placetype":"venue"
},
  "geometry": {"coordinates":[-91.448609,44.770517],"type":"Point"}
}