{
  "type": "Feature",
  "properties": {
    "iso:country":"US",
    "sg:address":"2821 N 4th St",
    "sg:city":"Milwaukee",
    "sg:classifiers":[
        {
            "category":"Professional",
            "subcategory":"Management & Consulting",
            "type":"Services"
        }
    ],
    "sg:phone":"+1 414 562 3030",
    "sg:postcode":"53212",
    "sg:province":"WI",
    "sg:tags":[
        "business",
        "association"
    ],
    "wof:name":"ACM of Milwaukee Inc",
    "wof:placetype":"venue"
},
  "geometry": {"coordinates":[-87.915575,43.070779],"type":"Point"}
}