{
  "type": "Feature",
  "properties": {
    "iso:country":"US",
    "sg:address":"511 N Madison St",
    "sg:city":"Chilton",
    "sg:classifiers":[
        {
            "category":"Food & Beverages",
            "subcategory":"Groceries & Convenience Stores",
            "type":"Retail Goods"
        }
    ],
    "sg:phone":"+1 920 849 8300",
    "sg:postcode":"53014",
    "sg:province":"WI",
    "sg:tags":[
        "supermarket"
    ],
    "wof:name":"Sav A Lot",
    "wof:placetype":"venue"
},
  "geometry": {"coordinates":[-88.163006,44.038989],"type":"Point"}
}