{
  "type": "Feature",
  "properties": {
    "iso:country":"US",
    "sg:address":"1209 Spruce Ct",
    "sg:city":"New Richmond",
    "sg:classifiers":[
        {
            "category":"Building & Trades",
            "subcategory":"Construction",
            "type":"Services"
        }
    ],
    "sg:phone":"+1 715 246 8930",
    "sg:postcode":"54017",
    "sg:province":"WI",
    "sg:tags":[
        "house"
    ],
    "wof:name":"Stones Homes",
    "wof:placetype":"venue"
},
  "geometry": {"coordinates":[-92.519567,45.11394],"type":"Point"}
}