{
  "type": "Feature",
  "properties": {
    "iso:country":"US",
    "sg:address":"600 E Rawson Ave",
    "sg:city":"Oak Creek",
    "sg:classifiers":[
        {
            "category":"Social Services",
            "subcategory":"Child Care",
            "type":"Services"
        }
    ],
    "sg:phone":"+1 414 764 6540",
    "sg:postcode":"53154",
    "sg:province":"WI",
    "sg:tags":[
        "day"
    ],
    "wof:name":"Pre School Plus",
    "wof:placetype":"venue"
},
  "geometry": {"coordinates":[-87.90931500000001,42.915656],"type":"Point"}
}