{
  "type": "Feature",
  "properties": {
    "iso:country":"US",
    "sg:address":"4147 US Hwy 45",
    "sg:city":"Oshkosh",
    "sg:classifiers":[
        {
            "category":"Insurance",
            "subcategory":"Insurance Agent",
            "type":"Services"
        }
    ],
    "sg:phone":"+1 920 426 2803",
    "sg:postcode":"54902",
    "sg:province":"WI",
    "wof:name":"All Star Insurance Service LLC",
    "wof:placetype":"venue"
},
  "geometry": {"coordinates":[-88.518576,43.956051],"type":"Point"}
}