{
  "type": "Feature",
  "properties": {
    "iso:country":"US",
    "sg:address":"700 S 1st St",
    "sg:city":"Cameron",
    "sg:classifiers":[
        {
            "category":"Education",
            "subcategory":"School",
            "type":"Public Place"
        }
    ],
    "sg:phone":"+1 715 458 4563",
    "sg:postcode":"54822",
    "sg:province":"WI",
    "sg:website":"www.cameron.k12.wi.us",
    "wof:name":"Cameron Middle School",
    "wof:placetype":"venue"
},
  "geometry": {"coordinates":[-91.73542500000001,45.404917],"type":"Point"}
}