{
  "type": "Feature",
  "properties": {
    "iso:country":"US",
    "sg:address":"4661 Michaels Dr",
    "sg:city":"Appleton",
    "sg:classifiers":[
        {
            "category":"Personal",
            "type":"Services"
        }
    ],
    "sg:phone":"+1 920 738 0166",
    "sg:postcode":"54913",
    "sg:province":"WI",
    "sg:tags":[
        "wear",
        "formal"
    ],
    "wof:name":"Du Bois Formal Wear",
    "wof:placetype":"venue"
},
  "geometry": {"coordinates":[-88.47686400000001,44.26755],"type":"Point"}
}