{
  "type": "Feature",
  "properties": {
    "iso:country":"US",
    "sg:address":"2040 Radisson St",
    "sg:city":"Green Bay",
    "sg:classifiers":[
        {
            "category":"Building & Trades",
            "subcategory":"Equipment Rental",
            "type":"Services"
        }
    ],
    "sg:phone":"+1 920 468 7373",
    "sg:postcode":"54302",
    "sg:province":"WI",
    "sg:tags":[
        "radio",
        "lease"
    ],
    "wof:name":"E T Communications",
    "wof:placetype":"venue"
},
  "geometry": {"coordinates":[-87.97785,44.523269],"type":"Point"}
}