{
  "type": "Feature",
  "properties": {
    "iso:country":"US",
    "sg:address":"6128 Dell Dr",
    "sg:city":"Madison",
    "sg:classifiers":[
        {
            "category":"Professional",
            "subcategory":"Business Services",
            "type":"Services"
        }
    ],
    "sg:phone":"+1 608 223 9799",
    "sg:postcode":"53718",
    "sg:province":"WI",
    "wof:name":"Smith Enterprises",
    "wof:placetype":"venue"
},
  "geometry": {"coordinates":[-89.27499400000001,43.075633],"type":"Point"}
}