{
  "type": "Feature",
  "properties": {
    "iso:country":"US",
    "sg:address":"3119 Golf Rd",
    "sg:city":"Eau Claire",
    "sg:classifiers":[
        {
            "category":"Personal",
            "subcategory":"Adult",
            "type":"Services"
        }
    ],
    "sg:phone":"+1 715 836 7714",
    "sg:postcode":"54701",
    "sg:province":"WI",
    "wof:name":"Renaissance For Singles",
    "wof:placetype":"venue"
},
  "geometry": {"coordinates":[-91.45730500000001,44.770603],"type":"Point"}
}