{
  "type": "Feature",
  "properties": {
    "iso:country":"US",
    "sg:address":"1362 Martha Washington Dr",
    "sg:city":"Milwaukee",
    "sg:classifiers":[
        {
            "category":"Social Services",
            "type":"Services"
        },
        {
            "category":"Professional",
            "subcategory":"Employment Agencies",
            "type":"Services"
        }
    ],
    "sg:phone":"+1 262 853 1500",
    "sg:postcode":"53213",
    "sg:province":"WI",
    "sg:tags":[
        "workers'",
        "placement",
        "volunteer"
    ],
    "wof:name":"Brewgate",
    "wof:placetype":"venue"
},
  "geometry": {"coordinates":[-87.989734,43.049381],"type":"Point"}
}