{
  "type": "Feature",
  "properties": {
    "iso:country":"US",
    "sg:address":"2181 Shady Ln",
    "sg:city":"Green Bay",
    "sg:classifiers":[
        {
            "category":"Real Estate",
            "subcategory":"Real Estate Operator",
            "type":"Services"
        }
    ],
    "sg:phone":"+1 920 494 8318",
    "sg:postcode":"54313",
    "sg:province":"WI",
    "sg:tags":[
        "building",
        "nonresidential"
    ],
    "wof:name":"Rockstroh Properties LLC",
    "wof:placetype":"venue"
},
  "geometry": {"coordinates":[-88.09069,44.503467],"type":"Point"}
}