{
  "type": "Feature",
  "properties": {
    "addr:full":"622 W Main St Sun Prairie WI 53590",
    "addr:housenumber":"622",
    "addr:postcode":"53590",
    "addr:street":"W Main St",
    "iso:country":"US",
    "sg:address":"622 W Main St",
    "sg:city":"Sun Prairie",
    "sg:classifiers":[
        {
            "category":"Shopping",
            "type":"Retail Goods"
        }
    ],
    "sg:phone":"+1 608 825 6200",
    "sg:postcode":"53590",
    "sg:province":"WI",
    "sg:tags":[
        "spa",
        "hot",
        "tub"
    ],
    "sg:website":"www.patio-pleasures.com",
    "wof:name":"Patio Pleasure & Spa's-Sun Prr",
    "wof:placetype":"venue"
},
  "geometry": {"coordinates":[-89.224535,43.1825],"type":"Point"}
}