{
  "type": "Feature",
  "properties": {
    "addr:full":"8855 W Schlinger Ave Milwaukee WI 53214",
    "addr:housenumber":"8855",
    "addr:postcode":"53214",
    "addr:street":"W Schlinger Ave",
    "iso:country":"US",
    "sg:address":"8855 W Schlinger Ave",
    "sg:city":"Milwaukee",
    "sg:classifiers":[
        {
            "category":"Wholesale",
            "subcategory":"Office Equipment",
            "type":"Manufacturing & Wholesale Goods"
        }
    ],
    "sg:phone":"+1 414 475 0522",
    "sg:postcode":"53214",
    "sg:province":"WI",
    "sg:tags":[
        "equipment-wholesale",
        "manufacturer",
        "furniture"
    ],
    "wof:name":"A M S",
    "wof:placetype":"venue"
},
  "geometry": {"coordinates":[-88.023236,43.023834],"type":"Point"}
}