{
  "type": "Feature",
  "properties": {
    "iso:country":"US",
    "sg:address":"2804 N Tuttle Rd",
    "sg:city":"Evansville",
    "sg:phone":"+1 608 876 6896",
    "sg:postcode":"53536",
    "sg:province":"WI",
    "sg:tags":[
        "farm",
        "corn",
        "beef",
        "feedlot",
        "cattle"
    ],
    "wof:name":"Donald Senn",
    "wof:placetype":"venue"
},
  "geometry": {"coordinates":[-89.22012700000001,42.722966],"type":"Point"}
}