{
  "type": "Feature",
  "properties": {
    "iso:country":"US",
    "sg:address":"1851 Co Rd Xx",
    "sg:city":"Mosinee",
    "sg:classifiers":[
        {
            "category":"Health Services",
            "subcategory":"Doctor",
            "type":"Services"
        }
    ],
    "sg:phone":"+1 715 359 0550",
    "sg:postcode":"54455",
    "sg:province":"WI",
    "sg:tags":[
        "dentist"
    ],
    "wof:name":"Dental Associates Cedar Creek",
    "wof:placetype":"venue"
},
  "geometry": {"coordinates":[-89.620331,44.858247],"type":"Point"}
}