{
  "type": "Feature",
  "properties": {
    "iso:country":"US",
    "sg:address":"362 Juniper Ct",
    "sg:city":"Delafield",
    "sg:classifiers":[
        {
            "category":"Professional",
            "type":"Services"
        }
    ],
    "sg:phone":"+1 262 646 2122",
    "sg:postcode":"53018",
    "sg:province":"WI",
    "wof:name":"Joel & Lisa Frank",
    "wof:placetype":"venue"
},
  "geometry": {"coordinates":[-88.421713,43.072698],"type":"Point"}
}