{
  "type": "Feature",
  "properties": {
    "iso:country":"US",
    "sg:address":"113 Hillside Dr",
    "sg:city":"Twin Lakes",
    "sg:classifiers":[
        {
            "category":"Professional",
            "subcategory":"Management & Consulting",
            "type":"Services"
        }
    ],
    "sg:phone":"+1 262 877 9042",
    "sg:postcode":"53181",
    "sg:province":"WI",
    "wof:name":"Mandinos",
    "wof:placetype":"venue"
},
  "geometry": {"coordinates":[-88.26067500000001,42.533048],"type":"Point"}
}