{
  "type": "Feature",
  "properties": {
    "iso:country":"US",
    "sg:address":"15350 W National Ave",
    "sg:city":"New Berlin",
    "sg:classifiers":[
        {
            "category":"Building & Trades",
            "subcategory":"Electrical",
            "type":"Services"
        }
    ],
    "sg:phone":"+1 262 641 8817",
    "sg:postcode":"53151",
    "sg:province":"WI",
    "sg:tags":[
        "electric",
        "contractor"
    ],
    "wof:name":"Electric Power Research Inst",
    "wof:placetype":"venue"
},
  "geometry": {"coordinates":[-88.104852,42.979036],"type":"Point"}
}