{
  "type": "Feature",
  "properties": {
    "iso:country":"US",
    "sg:address":"1253 S Irwin Ave",
    "sg:city":"Green Bay",
    "sg:classifiers":[
        {
            "category":"Real Estate",
            "subcategory":"Developer",
            "type":"Services"
        }
    ],
    "sg:phone":"+1 920 965 6565",
    "sg:postcode":"54301",
    "sg:province":"WI",
    "wof:name":"W S Enterprises",
    "wof:placetype":"venue"
},
  "geometry": {"coordinates":[-88.00834500000001,44.492455],"type":"Point"}
}