{
  "type": "Feature",
  "properties": {
    "iso:country":"US",
    "sg:address":"439 Main St",
    "sg:city":"Darlington",
    "sg:classifiers":[
        {
            "category":"Organizations",
            "subcategory":"Professional Association",
            "type":"Services"
        }
    ],
    "sg:phone":"+1 608 776 3067",
    "sg:postcode":"53530",
    "sg:province":"WI",
    "sg:tags":[
        "chambers",
        "commerce"
    ],
    "wof:name":"Darlington Main Street Program",
    "wof:placetype":"venue"
},
  "geometry": {"coordinates":[-90.117677,42.68069],"type":"Point"}
}