{
  "type": "Feature",
  "properties": {
    "iso:country":"US",
    "sg:address":"1820 Hanley Rd",
    "sg:city":"Hudson",
    "sg:classifiers":[
        {
            "category":"Shopping",
            "subcategory":"Bicycles & Sporting Goods",
            "type":"Retail Goods"
        }
    ],
    "sg:phone":"+1 715 377 0582",
    "sg:postcode":"54016",
    "sg:province":"WI",
    "wof:name":"Arena Sport",
    "wof:placetype":"venue"
},
  "geometry": {"coordinates":[-92.73128199999999,44.952649],"type":"Point"}
}