{
  "type": "Feature",
  "properties": {
    "addr:full":"7340 Benson Rd Trego WI 54840",
    "addr:housenumber":"7340",
    "addr:postcode":"54840",
    "addr:street":"Benson Rd",
    "iso:country":"US",
    "sg:address":"7340 Benson Rd",
    "sg:city":"Trego",
    "sg:classifiers":[
        {
            "category":"Autos & Motor Vehicles",
            "subcategory":"Recreational Vehicle Sales",
            "type":"Retail Goods"
        }
    ],
    "sg:phone":"+1 715 635 7171",
    "sg:postcode":"54840",
    "sg:province":"WI",
    "wof:name":"Higgins Camper Rentals & Sales",
    "wof:placetype":"venue"
},
  "geometry": {"coordinates":[-92.67420300000001,45.787434],"type":"Point"}
}