{
  "type": "Feature",
  "properties": {
    "iso:country":"US",
    "sg:address":"2027 Dakota Ave",
    "sg:city":"Berlin",
    "sg:classifiers":[
        {
            "category":"Building & Trades",
            "subcategory":"Construction",
            "type":"Services"
        }
    ],
    "sg:phone":"+1 920 361 0603",
    "sg:postcode":"54923",
    "sg:province":"WI",
    "sg:tags":[
        "general",
        "contractor"
    ],
    "wof:name":"C Keller Construction",
    "wof:placetype":"venue"
},
  "geometry": {"coordinates":[-88.988058,43.983323],"type":"Point"}
}