{
  "type": "Feature",
  "properties": {
    "iso:country":"US",
    "sg:address":"845 Leslie Ln",
    "sg:city":"Green Lake",
    "sg:classifiers":[
        {
            "category":"Building & Trades",
            "subcategory":"Construction",
            "type":"Services"
        }
    ],
    "sg:phone":"+1 920 748 9311",
    "sg:postcode":"54941",
    "sg:province":"WI",
    "sg:tags":[
        "house"
    ],
    "wof:name":"Taylor Aj Construction LLC",
    "wof:placetype":"venue"
},
  "geometry": {"coordinates":[-88.924256,43.850081],"type":"Point"}
}