{
  "type": "Feature",
  "properties": {
    "iso:country":"US",
    "sg:address":"2218 N 117th St",
    "sg:city":"Wauwatosa",
    "sg:classifiers":[
        {
            "category":"Local Transit",
            "type":"Transportation"
        }
    ],
    "sg:phone":"+1 414 614 5466",
    "sg:postcode":"53226",
    "sg:province":"WI",
    "sg:tags":[
        "limousine"
    ],
    "wof:name":"Great Italian Limousines",
    "wof:placetype":"venue"
},
  "geometry": {"coordinates":[-88.05884399999999,43.059705],"type":"Point"}
}