{
  "type": "Feature",
  "properties": {
    "iso:country":"US",
    "sg:address":"400 2nd Ave",
    "sg:city":"New Glarus",
    "sg:classifiers":[
        {
            "category":"Manufacturing",
            "subcategory":"Printing",
            "type":"Manufacturing & Wholesale Goods"
        }
    ],
    "sg:phone":"+1 608 527 8120",
    "sg:postcode":"53574",
    "sg:province":"WI",
    "sg:tags":[
        "publisher"
    ],
    "wof:name":"Daehn Publications",
    "wof:placetype":"venue"
},
  "geometry": {"coordinates":[-89.637351,42.818175],"type":"Point"}
}