{
  "type": "Feature",
  "properties": {
    "iso:country":"US",
    "sg:address":"300 Clark St",
    "sg:city":"Brandon",
    "sg:classifiers":[
        {
            "category":"Professional",
            "subcategory":"Engineering",
            "type":"Services"
        }
    ],
    "sg:phone":"+1 920 346 5241",
    "sg:postcode":"53959",
    "sg:province":"WI",
    "sg:tags":[
        "project",
        "management",
        "provides"
    ],
    "wof:name":"Sharpe Engineering & Equipment",
    "wof:placetype":"venue"
},
  "geometry": {"coordinates":[-90.018559,43.531465],"type":"Point"}
}