{
  "type": "Feature",
  "properties": {
    "iso:country":"US",
    "sg:address":"320 Main St",
    "sg:city":"Fall River",
    "sg:classifiers":[
        {
            "category":"Retail",
            "subcategory":"Auto Repair",
            "type":"Services"
        }
    ],
    "sg:phone":"+1 920 484 3137",
    "sg:postcode":"53932",
    "sg:province":"WI",
    "sg:tags":[
        "body"
    ],
    "wof:name":"Little Detroit Auto Body Shop",
    "wof:placetype":"venue"
},
  "geometry": {"coordinates":[-89.044169,43.387316],"type":"Point"}
}