{
  "type": "Feature",
  "properties": {
    "iso:country":"US",
    "sg:address":"2300 S Ridge Rd",
    "sg:city":"Green Bay",
    "sg:classifiers":[
        {
            "category":"Retail",
            "subcategory":"Auto Repair",
            "type":"Services"
        }
    ],
    "sg:phone":"+1 920 494 2860",
    "sg:postcode":"54304",
    "sg:province":"WI",
    "sg:tags":[
        "general"
    ],
    "wof:name":"Dells Service Center",
    "wof:placetype":"venue"
},
  "geometry": {"coordinates":[-88.072829,44.491315],"type":"Point"}
}