{
  "type": "Feature",
  "properties": {
    "iso:country":"US",
    "sg:address":"4829 US Hwy 14",
    "sg:city":"Spring Green",
    "sg:classifiers":[
        {
            "category":"Autos & Motor Vehicles",
            "subcategory":"Automobile Sales",
            "type":"Retail Goods"
        }
    ],
    "sg:phone":"+1 608 588 7399",
    "sg:postcode":"53588",
    "sg:province":"WI",
    "sg:tags":[
        "car",
        "dealer"
    ],
    "wof:name":"Apple Automotive Used Cars",
    "wof:placetype":"venue"
},
  "geometry": {"coordinates":[-90.07769399999999,43.189661],"type":"Point"}
}