{
  "type": "Feature",
  "properties": {
    "addr:full":"9910 W Layton Ave Milwaukee WI 53228",
    "addr:housenumber":"9910",
    "addr:postcode":"53228",
    "addr:street":"W Layton Ave",
    "iso:country":"US",
    "sg:address":"9910 W Layton Ave",
    "sg:city":"Milwaukee",
    "sg:classifiers":[
        {
            "category":"Organizations",
            "subcategory":"Professional Association",
            "type":"Services"
        }
    ],
    "sg:phone":"+1 414 529 4705",
    "sg:postcode":"53228",
    "sg:province":"WI",
    "sg:website":"www.wislf.org",
    "wof:name":"Wisconsin Landscape Federation",
    "wof:placetype":"venue"
},
  "geometry": {"coordinates":[-88.039692,42.959235],"type":"Point"}
}