{
  "type": "Feature",
  "properties": {
    "iso:country":"US",
    "sg:address":"502 Krueger Ave",
    "sg:city":"Cameron",
    "sg:classifiers":[
        {
            "category":"Real Estate",
            "subcategory":"Real Estate Operator",
            "type":"Services"
        }
    ],
    "sg:phone":"+1 715 357 3334",
    "sg:postcode":"54822",
    "sg:province":"WI",
    "sg:tags":[
        "apartment"
    ],
    "wof:name":"James Banks Manor",
    "wof:placetype":"venue"
},
  "geometry": {"coordinates":[-91.74041099999999,45.415641],"type":"Point"}
}