{
  "type": "Feature",
  "properties": {
    "iso:country":"US",
    "sg:address":"2497 Meadow Park Dr",
    "sg:city":"Green Bay",
    "sg:classifiers":[
        {
            "category":"Professional",
            "subcategory":"Lawyer & Legal Services",
            "type":"Services"
        }
    ],
    "sg:phone":"+1 920 468 9515",
    "sg:postcode":"54311",
    "sg:province":"WI",
    "wof:name":"Andres Law Office LLC",
    "wof:placetype":"venue"
},
  "geometry": {"coordinates":[-87.952943,44.455044],"type":"Point"}
}