{
  "type": "Feature",
  "properties": {
    "iso:country":"US",
    "sg:address":"517 Beaser Ave",
    "sg:city":"Ashland",
    "sg:classifiers":[
        {
            "category":"Social Services",
            "subcategory":"Adult Care",
            "type":"Services"
        }
    ],
    "sg:phone":"+1 715 682 1160",
    "sg:postcode":"54806",
    "sg:province":"WI",
    "sg:tags":[
        "foster"
    ],
    "wof:name":"Prentice House",
    "wof:placetype":"venue"
},
  "geometry": {"coordinates":[-90.89570000000001,46.582266],"type":"Point"}
}