{
  "type": "Feature",
  "properties": {
    "iso:country":"US",
    "sg:address":"301 Chestnut St",
    "sg:city":"Boscobel",
    "sg:classifiers":[
        {
            "category":"Organizations",
            "subcategory":"Religious Organization",
            "type":"Services"
        }
    ],
    "sg:phone":"+1 608 375 5088",
    "sg:postcode":"53805",
    "sg:province":"WI",
    "sg:tags":[
        "church"
    ],
    "wof:name":"Boscobel Assembly Of God Chrch",
    "wof:placetype":"venue"
},
  "geometry": {"coordinates":[-90.70078,43.141137],"type":"Point"}
}