{
  "type": "Feature",
  "properties": {
    "addr:full":"503 Shay St Somerset WI 54025",
    "addr:housenumber":"503",
    "addr:postcode":"54025",
    "addr:street":"Shay St",
    "iso:country":"US",
    "sg:address":"503 Shay St",
    "sg:city":"Somerset",
    "sg:classifiers":[
        {
            "category":"Professional",
            "subcategory":"Printing & Photocopies",
            "type":"Services"
        }
    ],
    "sg:phone":"+1 715 247 2750",
    "sg:postcode":"54025",
    "sg:province":"WI",
    "sg:tags":[
        "equipment-repairing"
    ],
    "sg:website":"http://www.a2ninc.com",
    "wof:name":"A2n, Inc",
    "wof:placetype":"venue"
},
  "geometry": {"coordinates":[-92.66978400000001,45.133946],"type":"Point"}
}