{
  "type": "Feature",
  "properties": {
    "iso:country":"US",
    "sg:address":"443 3rd St",
    "sg:city":"Hartford",
    "sg:classifiers":[
        {
            "category":"Professional",
            "type":"Services"
        }
    ],
    "sg:phone":"+1 262 670 9115",
    "sg:postcode":"53027",
    "sg:province":"WI",
    "sg:tags":[
        "establishment"
    ],
    "wof:name":"E Ci",
    "wof:placetype":"venue"
},
  "geometry": {"coordinates":[-88.374835,43.323054],"type":"Point"}
}