{
  "type": "Feature",
  "properties": {
    "iso:country":"US",
    "sg:address":"522 Mill St",
    "sg:city":"Green Lake",
    "sg:classifiers":[
        {
            "category":"Personal",
            "subcategory":"Beauty Salon",
            "type":"Services"
        }
    ],
    "sg:phone":"+1 920 294 6642",
    "sg:postcode":"54941",
    "sg:province":"WI",
    "wof:name":"Hairitage Barber & Beauty Sln",
    "wof:placetype":"venue"
},
  "geometry": {"coordinates":[-88.960013,43.84565],"type":"Point"}
}