{
  "type": "Feature",
  "properties": {
    "addr:full":"608 Oak St Sauk City WI 53583",
    "addr:housenumber":"608",
    "addr:postcode":"53583",
    "addr:street":"Oak St",
    "iso:country":"US",
    "sg:address":"608 Oak St",
    "sg:city":"Sauk City",
    "sg:classifiers":[
        {
            "category":"Education",
            "subcategory":"School",
            "type":"Public Place"
        }
    ],
    "sg:phone":"+1 608 643 6868",
    "sg:postcode":"53583",
    "sg:province":"WI",
    "wof:name":"St Aloysius Catholic School",
    "wof:placetype":"venue"
},
  "geometry": {"coordinates":[-89.726376,43.281912],"type":"Point"}
}