{
  "type": "Feature",
  "properties": {
    "iso:country":"US",
    "sg:address":"4692 Clear View Ln",
    "sg:city":"Oneida",
    "sg:classifiers":[
        {
            "category":"Banks & Credit Unions",
            "subcategory":"Financial Services",
            "type":"Services"
        }
    ],
    "sg:phone":"+1 920 434 6931",
    "sg:postcode":"54155",
    "sg:province":"WI",
    "sg:tags":[
        "company",
        "bank",
        "holding"
    ],
    "wof:name":"Pyco Inc",
    "wof:placetype":"venue"
},
  "geometry": {"coordinates":[-88.157797,44.563734],"type":"Point"}
}