{
  "type": "Feature",
  "properties": {
    "iso:country":"US",
    "sg:address":"2402 Co Rd A",
    "sg:city":"Markesan",
    "sg:classifiers":[
        {
            "category":"Wholesale",
            "subcategory":"Construction Materials",
            "type":"Manufacturing & Wholesale Goods"
        }
    ],
    "sg:phone":"+1 920 398 1700",
    "sg:postcode":"53946",
    "sg:province":"WI",
    "sg:tags":[
        "sand",
        "gravel"
    ],
    "wof:name":"Nor Rock Aggregate Inc",
    "wof:placetype":"venue"
},
  "geometry": {"coordinates":[-88.937894,43.716937],"type":"Point"}
}