{
  "type": "Feature",
  "properties": {
    "iso:country":"US",
    "sg:address":"9361 Wilderness Dr",
    "sg:city":"Tomahawk",
    "sg:classifiers":[
        {
            "category":"Building & Trades",
            "subcategory":"Landscaping Services",
            "type":"Services"
        }
    ],
    "sg:phone":"+1 715 453 4723",
    "sg:postcode":"54487",
    "sg:province":"WI",
    "sg:tags":[
        "landscape",
        "contractor"
    ],
    "wof:name":"Spirit View Landscpg & Design",
    "wof:placetype":"venue"
},
  "geometry": {"coordinates":[-89.834019,45.458627],"type":"Point"}
}