{
  "type": "Feature",
  "properties": {
    "addr:full":"740 E Saint Mary St Milton WI 53563",
    "addr:housenumber":"740",
    "addr:postcode":"53563",
    "addr:street":"E Saint Mary St",
    "iso:country":"US",
    "sg:address":"740 E Saint Mary St",
    "sg:city":"Milton",
    "sg:classifiers":[
        {
            "category":"Restaurant",
            "type":"Food & Drink"
        }
    ],
    "sg:menulink":"http://www.allmenus.com/wi/milton/218321-burger-king/menu/",
    "sg:phone":"+1 608 868 6342",
    "sg:postcode":"53563",
    "sg:province":"WI",
    "sg:tags":[
        "american"
    ],
    "wof:name":"Burger King",
    "wof:placetype":"venue"
},
  "geometry": {"coordinates":[-88.937686,42.76909],"type":"Point"}
}