{
  "type": "Feature",
  "properties": {
    "addr:full":"3335 Calumet Ave Manitowoc WI 54220",
    "addr:housenumber":"3335",
    "addr:postcode":"54220",
    "addr:street":"Calumet Ave",
    "iso:country":"US",
    "sg:address":"3335 Calumet Ave",
    "sg:city":"Manitowoc",
    "sg:classifiers":[
        {
            "category":"Building & Trades",
            "subcategory":"Construction",
            "type":"Services"
        }
    ],
    "sg:phone":"+1 920 686 9511",
    "sg:postcode":"54220",
    "sg:province":"WI",
    "sg:tags":[
        "contractor"
    ],
    "wof:name":"Innovative Nationwide Builders",
    "wof:placetype":"venue"
},
  "geometry": {"coordinates":[-87.69055,44.083815],"type":"Point"}
}