{
  "type": "Feature",
  "properties": {
    "iso:country":"US",
    "sg:address":"29013 Co Rd I",
    "sg:city":"Blair",
    "sg:classifiers":[
        {
            "category":"Farming",
            "subcategory":"Dairy Farm",
            "type":"Manufacturing & Wholesale Goods"
        }
    ],
    "sg:phone":"+1 608 989 2963",
    "sg:postcode":"54616",
    "sg:province":"WI",
    "wof:name":"Oldendorf Art",
    "wof:placetype":"venue"
},
  "geometry": {"coordinates":[-91.252498,44.265468],"type":"Point"}
}