{
  "type": "Feature",
  "properties": {
    "iso:country":"US",
    "sg:address":"2701 Monroe St",
    "sg:city":"Madison",
    "sg:classifiers":[
        {
            "category":"Shopping",
            "subcategory":"Gifts & Souvenirs",
            "type":"Retail Goods"
        }
    ],
    "sg:phone":"+1 608 233 4438",
    "sg:postcode":"53711",
    "sg:province":"WI",
    "wof:name":"A Greater Gift",
    "wof:placetype":"venue"
},
  "geometry": {"coordinates":[-89.429639,43.056684],"type":"Point"}
}