{
  "type": "Feature",
  "properties": {
    "addr:full":"2455 Anita Dr Brookfield WI 53045",
    "addr:housenumber":"2455",
    "addr:postcode":"53045",
    "addr:street":"Anita Dr",
    "iso:country":"US",
    "sg:address":"2455 Anita Dr",
    "sg:city":"Brookfield",
    "sg:classifiers":[
        {
            "category":"Building & Trades",
            "subcategory":"Construction",
            "type":"Services"
        }
    ],
    "sg:phone":"+1 262 786 0783",
    "sg:postcode":"53045",
    "sg:province":"WI",
    "sg:tags":[
        "residential",
        "condominium"
    ],
    "sg:website":"http://www.dixenterprises.net",
    "wof:name":"Dix Enterprises",
    "wof:placetype":"venue"
},
  "geometry": {"coordinates":[-88.14309799999999,43.064181],"type":"Point"}
}