{
  "type": "Feature",
  "properties": {
    "iso:country":"US",
    "sg:address":"902 Taft Ave",
    "sg:city":"Oshkosh",
    "sg:classifiers":[
        {
            "category":"Recreation",
            "subcategory":"Marina",
            "type":"Entertainment"
        }
    ],
    "sg:phone":"+1 920 432 2400",
    "sg:postcode":"54902",
    "sg:province":"WI",
    "sg:tags":[
        "sale",
        "boat"
    ],
    "sg:website":"www.lakesidemarina.com",
    "wof:name":"Lakeside Marina",
    "wof:placetype":"venue"
},
  "geometry": {"coordinates":[-88.5622,44.025626],"type":"Point"}
}