{
  "type": "Feature",
  "properties": {
    "iso:country":"US",
    "sg:address":"2040 Jay Mar Rd",
    "sg:city":"Plover",
    "sg:classifiers":[
        {
            "category":"Insurance",
            "subcategory":"Insurance Agent",
            "type":"Services"
        }
    ],
    "sg:phone":"+1 715 341 8899",
    "sg:postcode":"54467",
    "sg:province":"WI",
    "wof:name":"Principal Life Insurance Co",
    "wof:placetype":"venue"
},
  "geometry": {"coordinates":[-89.528716,44.454495],"type":"Point"}
}