{
  "type": "Feature",
  "properties": {
    "iso:country":"US",
    "sg:address":"215 Elmwood Ave",
    "sg:city":"South Beloit",
    "sg:classifiers":[
        {
            "category":"Manufacturing",
            "subcategory":"Tools & Machinery",
            "type":"Manufacturing & Wholesale Goods"
        }
    ],
    "sg:phone":"+1 815 389 2300",
    "sg:postcode":"61080",
    "sg:province":"WI",
    "sg:tags":[
        "cutting"
    ],
    "sg:website":"www.groupunited.com",
    "wof:name":"North American Tool Corp",
    "wof:placetype":"venue"
},
  "geometry": {"coordinates":[-89.040768,42.489506],"type":"Point"}
}