{
  "type": "Feature",
  "properties": {
    "iso:country":"US",
    "sg:address":"4221 Co Rd W",
    "sg:city":"De Pere",
    "sg:classifiers":[
        {
            "category":"Farming",
            "subcategory":"Dairy Farm",
            "type":"Manufacturing & Wholesale Goods"
        }
    ],
    "sg:phone":"+1 920 339 0518",
    "sg:postcode":"54115",
    "sg:province":"WI",
    "wof:name":"Genesis Dairy",
    "wof:placetype":"venue"
},
  "geometry": {"coordinates":[-87.96169500000001,44.422121],"type":"Point"}
}