{
  "type": "Feature",
  "properties": {
    "addr:full":"1643 Careful Dr Green Bay WI 54304",
    "addr:housenumber":"1643",
    "addr:postcode":"54304",
    "addr:street":"Careful Dr",
    "iso:country":"US",
    "sg:address":"1643 Careful Dr",
    "sg:city":"Green Bay",
    "sg:classifiers":[
        {
            "category":"Professional",
            "type":"Services"
        }
    ],
    "sg:phone":"+1 920 497 8046",
    "sg:postcode":"54304",
    "sg:province":"WI",
    "wof:name":"Dan Hasenjager",
    "wof:placetype":"venue"
},
  "geometry": {"coordinates":[-88.076514,44.510482],"type":"Point"}
}