{
  "type": "Feature",
  "properties": {
    "iso:country":"US",
    "sg:address":"1100 Broad St",
    "sg:city":"Beloit",
    "sg:classifiers":[
        {
            "category":"Autos & Motor Vehicles",
            "subcategory":"Automobile Sales",
            "type":"Retail Goods"
        }
    ],
    "sg:phone":"+1 608 363 8784",
    "sg:postcode":"53511",
    "sg:province":"IL",
    "sg:tags":[
        "car",
        "dealer"
    ],
    "wof:name":"Crocker's Motors",
    "wof:placetype":"venue"
},
  "geometry": {"coordinates":[-89.024075,42.498622],"type":"Point"}
}