{
  "type": "Feature",
  "properties": {
    "addr:full":"12657 Dyke Rd Spring Green WI 53588",
    "addr:housenumber":"12657",
    "addr:postcode":"53588",
    "addr:street":"Dyke Rd",
    "iso:country":"US",
    "sg:address":"12657 Dyke Rd",
    "sg:city":"Spring Green",
    "sg:classifiers":[
        {
            "category":"Manufacturing",
            "subcategory":"Tools & Machinery",
            "type":"Manufacturing & Wholesale Goods"
        }
    ],
    "sg:phone":"+1 608 588 7710",
    "sg:postcode":"53588",
    "sg:province":"WI",
    "sg:tags":[
        "die",
        "maker"
    ],
    "wof:name":"Kline Tool & Engineering",
    "wof:placetype":"venue"
},
  "geometry": {"coordinates":[-90.133382,43.186995],"type":"Point"}
}