{
  "type": "Feature",
  "properties": {
    "addr:full":"3490 Kohn Rd Conover WI 54519",
    "addr:postcode":"3490;54519",
    "addr:street":"Kohn Rd",
    "iso:country":"US",
    "sg:address":"3490 Kohn Rd",
    "sg:city":"Conover",
    "sg:classifiers":[
        {
            "category":"Professional",
            "subcategory":"Business Services",
            "type":"Services"
        }
    ],
    "sg:phone":"+1 715 479 8371",
    "sg:postcode":"54519",
    "sg:province":"WI",
    "wof:name":"Walls Corporation",
    "wof:placetype":"venue"
},
  "geometry": {"coordinates":[-89.3605,46.013646],"type":"Point"}
}