{
  "type": "Feature",
  "properties": {
    "iso:country":"US",
    "sg:address":"265 Knox St",
    "sg:city":"Lowell",
    "sg:classifiers":[
        {
            "category":"Building & Trades",
            "subcategory":"Construction",
            "type":"Services"
        }
    ],
    "sg:phone":"+1 920 927 3322",
    "sg:postcode":"53557",
    "sg:province":"WI",
    "sg:tags":[
        "repairing",
        "remodeling",
        "contractor"
    ],
    "wof:name":"Milestone Construction",
    "wof:placetype":"venue"
},
  "geometry": {"coordinates":[-88.813227,43.340168],"type":"Point"}
}