{
  "type": "Feature",
  "properties": {
    "iso:country":"US",
    "sg:address":"909 Schloemer Dr",
    "sg:city":"West Bend",
    "sg:classifiers":[
        {
            "category":"Professional",
            "type":"Services"
        }
    ],
    "sg:phone":"+1 262 334 3202",
    "sg:postcode":"53095",
    "sg:province":"WI",
    "wof:name":"Saveon U S Acom",
    "wof:placetype":"venue"
},
  "geometry": {"coordinates":[-88.18892099999999,43.403399],"type":"Point"}
}