{
  "type": "Feature",
  "properties": {
    "iso:country":"US",
    "sg:address":"414 W Carroll St",
    "sg:city":"Portage",
    "sg:classifiers":[
        {
            "category":"Building & Trades",
            "subcategory":"Construction",
            "type":"Services"
        }
    ],
    "sg:phone":"+1 608 742 2306",
    "sg:postcode":"53901",
    "sg:province":"WI",
    "sg:tags":[
        "builder",
        "operative"
    ],
    "wof:name":"W A Schultz LLC",
    "wof:placetype":"venue"
},
  "geometry": {"coordinates":[-89.469565,43.541921],"type":"Point"}
}