{
  "type": "Feature",
  "properties": {
    "addr:full":"116 Lance Dr Twin Lakes WI 53181",
    "addr:housenumber":"116",
    "addr:postcode":"53181",
    "addr:street":"Lance Dr",
    "iso:country":"US",
    "sg:address":"116 Lance Dr",
    "sg:city":"Twin Lakes",
    "sg:classifiers":[
        {
            "category":"Restaurant",
            "type":"Food & Drink"
        }
    ],
    "sg:phone":"+1 262 877 9597",
    "sg:postcode":"53181",
    "sg:province":"WI",
    "wof:name":"Lancelot Pizza",
    "wof:placetype":"venue"
},
  "geometry": {"coordinates":[-88.255037,42.530623],"type":"Point"}
}