{
  "type": "Feature",
  "properties": {
    "iso:country":"US",
    "sg:address":"3903 N Morris Blvd",
    "sg:city":"Milwaukee",
    "sg:classifiers":[
        {
            "category":"Communications",
            "subcategory":"Film & Video Production",
            "type":"Services"
        }
    ],
    "sg:phone":"+1 414 962 8020",
    "sg:postcode":"53211",
    "sg:province":"WI",
    "sg:tags":[
        "recording",
        "service-sound"
    ],
    "wof:name":"DV Productions",
    "wof:placetype":"venue"
},
  "geometry": {"coordinates":[-87.892348,43.0882],"type":"Point"}
}