{
  "type": "Feature",
  "properties": {
    "addr:full":"827 16th Ave Monroe WI 53566",
    "addr:housenumber":"827",
    "addr:postcode":"53566",
    "addr:street":"16Th Ave",
    "iso:country":"US",
    "sg:address":"827 16th Ave",
    "sg:city":"Monroe",
    "sg:classifiers":[
        {
            "category":"Utilities",
            "subcategory":"Telephone",
            "type":"Services"
        }
    ],
    "sg:phone":"+1 608 328 5298",
    "sg:postcode":"53566",
    "sg:province":"WI",
    "sg:tags":[
        "communications"
    ],
    "wof:name":"Jeri Cook",
    "wof:placetype":"venue"
},
  "geometry": {"coordinates":[-89.63995199999999,42.603724],"type":"Point"}
}