{
  "type": "Feature",
  "properties": {
    "iso:country":"US",
    "sg:address":"3501 W Greenfield Ave",
    "sg:city":"Milwaukee",
    "sg:classifiers":[
        {
            "category":"Health Services",
            "subcategory":"Doctor",
            "type":"Services"
        }
    ],
    "sg:phone":"+1 414 645 4263",
    "sg:postcode":"53215",
    "sg:province":"WI",
    "sg:tags":[
        "medical"
    ],
    "wof:name":"Greenfield Medical Clinic",
    "wof:placetype":"venue"
},
  "geometry": {"coordinates":[-87.957887,43.016898],"type":"Point"}
}