{
  "type": "Feature",
  "properties": {
    "iso:country":"US",
    "sg:address":"3474 S Pennsylvania Ave",
    "sg:city":"Milwaukee",
    "sg:classifiers":[
        {
            "category":"Professional",
            "subcategory":"Business Services",
            "type":"Services"
        }
    ],
    "sg:phone":"+1 414 483 7917",
    "sg:postcode":"53207",
    "sg:province":"WI",
    "wof:name":"St Joseph Partners LLC",
    "wof:placetype":"venue"
},
  "geometry": {"coordinates":[-87.87952,42.9823],"type":"Point"}
}