{
  "type": "Feature",
  "properties": {
    "iso:country":"US",
    "sg:address":"9716 Pioneer Rd",
    "sg:city":"Cedarburg",
    "sg:classifiers":[
        {
            "category":"Real Estate",
            "subcategory":"Architect",
            "type":"Services"
        }
    ],
    "sg:phone":"+1 262 375 9700",
    "sg:postcode":"53012",
    "sg:province":"WI",
    "sg:tags":[
        "architectural"
    ],
    "wof:name":"Advanced Wood Design Inc",
    "wof:placetype":"venue"
},
  "geometry": {"coordinates":[-88.037536,43.278848],"type":"Point"}
}