{
  "type": "Feature",
  "properties": {
    "iso:country":"US",
    "sg:address":"9695 Wilcox Rd",
    "sg:city":"Portage",
    "sg:phone":"+1 608 742 3624",
    "sg:postcode":"53901",
    "sg:province":"WI",
    "sg:tags":[
        "farm",
        "corn",
        "soybean"
    ],
    "wof:name":"Frank Vomdersump",
    "wof:placetype":"venue"
},
  "geometry": {"coordinates":[-89.375286,43.617466],"type":"Point"}
}