{
  "type": "Feature",
  "properties": {
    "iso:country":"US",
    "sg:address":"5089 Tank Rd",
    "sg:city":"New London",
    "sg:classifiers":[
        {
            "category":"Building & Trades",
            "subcategory":"Construction",
            "type":"Services"
        }
    ],
    "sg:phone":"+1 920 359 0027",
    "sg:postcode":"54961",
    "sg:province":"WI",
    "sg:tags":[
        "paving",
        "asphalt",
        "contractor"
    ],
    "wof:name":"Solid Black Sealcoating",
    "wof:placetype":"venue"
},
  "geometry": {"coordinates":[-88.798025,44.41707],"type":"Point"}
}