{
  "type": "Feature",
  "properties": {
    "iso:country":"US",
    "sg:address":"41 Park Heights Ct",
    "sg:city":"Madison",
    "sg:classifiers":[
        {
            "category":"Retail",
            "subcategory":"Auto Repair",
            "type":"Services"
        }
    ],
    "sg:phone":"+1 608 274 6401",
    "sg:postcode":"53711",
    "sg:province":"WI",
    "sg:tags":[
        "repairing",
        "automobile"
    ],
    "wof:name":"Scudder Automotive",
    "wof:placetype":"venue"
},
  "geometry": {"coordinates":[-89.496422,43.036546],"type":"Point"}
}