{
  "type": "Feature",
  "properties": {
    "iso:country":"US",
    "sg:address":"5822 W Forest Home Ave",
    "sg:city":"Milwaukee",
    "sg:classifiers":[
        {
            "category":"Shopping",
            "subcategory":"Hobbies, Toys, & Games",
            "type":"Retail Goods"
        }
    ],
    "sg:phone":"+1 414 327 4003",
    "sg:postcode":"53220",
    "sg:province":"WI",
    "wof:name":"Lucky Bobs Raceway",
    "wof:placetype":"venue"
},
  "geometry": {"coordinates":[-87.987886,42.977038],"type":"Point"}
}