{
  "type": "Feature",
  "properties": {
    "iso:country":"US",
    "sg:address":"101 S Tyler St",
    "sg:city":"Sparta",
    "sg:classifiers":[
        {
            "category":"Real Estate",
            "subcategory":"Real Estate Operator",
            "type":"Services"
        }
    ],
    "sg:phone":"+1 608 269 5813",
    "sg:postcode":"54656",
    "sg:province":"WI",
    "sg:tags":[
        "property",
        "lessor"
    ],
    "wof:name":"Yahnke Estates",
    "wof:placetype":"venue"
},
  "geometry": {"coordinates":[-90.805094,43.944379],"type":"Point"}
}