{
  "type": "Feature",
  "properties": {
    "iso:country":"US",
    "sg:address":"1550 Johnston Dr",
    "sg:city":"Manitowoc",
    "sg:classifiers":[
        {
            "category":"Restaurant",
            "type":"Food & Drink"
        }
    ],
    "sg:phone":"+1 920 684 8820",
    "sg:postcode":"54220",
    "sg:province":"WI",
    "wof:name":"Galley",
    "wof:placetype":"venue"
},
  "geometry": {"coordinates":[-87.640418,44.118585],"type":"Point"}
}