{
  "type": "Feature",
  "properties": {
    "iso:country":"US",
    "sg:address":"11310 Buckeye Ridge Rd",
    "sg:city":"La Farge",
    "sg:classifiers":[
        {
            "category":"Farming",
            "subcategory":"Dairy Farm",
            "type":"Manufacturing & Wholesale Goods"
        }
    ],
    "sg:phone":"+1 608 625 4296",
    "sg:postcode":"54639",
    "sg:province":"WI",
    "wof:name":"Rose Wild Dairy LLC",
    "wof:placetype":"venue"
},
  "geometry": {"coordinates":[-90.676593,43.613858],"type":"Point"}
}