{
  "type": "Feature",
  "properties": {
    "addr:full":"1221 S 26th St Manitowoc WI 54220",
    "addr:housenumber":"1221",
    "addr:postcode":"54220",
    "addr:street":"S 26Th St",
    "iso:country":"US",
    "sg:address":"1221 S 26th St",
    "sg:city":"Manitowoc",
    "sg:classifiers":[
        {
            "category":"Organizations",
            "subcategory":"Labor Organization",
            "type":"Services"
        }
    ],
    "sg:phone":"+1 920 682 8692",
    "sg:postcode":"54220",
    "sg:province":"WI",
    "wof:name":"Uswa",
    "wof:placetype":"venue"
},
  "geometry": {"coordinates":[-87.68021299999999,44.084832],"type":"Point"}
}