{
  "type": "Feature",
  "properties": {
    "iso:country":"US",
    "sg:address":"2275 Castle Dr",
    "sg:city":"Medford",
    "sg:classifiers":[
        {
            "category":"Professional",
            "type":"Services"
        }
    ],
    "sg:phone":"+1 715 748 6612",
    "sg:postcode":"54451",
    "sg:province":"WI",
    "wof:name":"Tracy L Hraby",
    "wof:placetype":"venue"
},
  "geometry": {"coordinates":[-90.396308,45.108717],"type":"Point"}
}