{
  "type": "Feature",
  "properties": {
    "iso:country":"US",
    "sg:address":"14165 Hampton Rd",
    "sg:city":"Brookfield",
    "sg:classifiers":[
        {
            "category":"Building & Trades",
            "subcategory":"Construction",
            "type":"Services"
        }
    ],
    "sg:phone":"+1 262 781 1786",
    "sg:postcode":"53005",
    "sg:province":"WI",
    "sg:tags":[
        "wallpaper",
        "painting",
        "hanging"
    ],
    "wof:name":"John H Schmidt Painting Co",
    "wof:placetype":"venue"
},
  "geometry": {"coordinates":[-88.090059,43.104611],"type":"Point"}
}