{
  "type": "Feature",
  "properties": {
    "addr:full":"512 2nd St Hudson WI 54016",
    "addr:housenumber":"512",
    "addr:postcode":"54016",
    "addr:street":"2Nd St",
    "iso:country":"US",
    "sg:address":"512 2nd St",
    "sg:city":"Hudson",
    "sg:classifiers":[
        {
            "category":"Banks & Credit Unions",
            "subcategory":"Bank",
            "type":"Services"
        }
    ],
    "sg:phone":"+1 715 531 1108",
    "sg:postcode":"54016",
    "sg:province":"WI",
    "sg:tags":[
        "loan"
    ],
    "wof:name":"Countrywide Home Loans",
    "wof:placetype":"venue"
},
  "geometry": {"coordinates":[-92.75682399999999,44.974946],"type":"Point"}
}