{
  "type": "Feature",
  "properties": {
    "iso:country":"US",
    "sg:address":"21140 W Capitol Dr",
    "sg:city":"Pewaukee",
    "sg:classifiers":[
        {
            "category":"Insurance",
            "subcategory":"Insurance Agent",
            "type":"Services"
        }
    ],
    "sg:phone":"+1 262 790 1099",
    "sg:postcode":"53072",
    "sg:province":"WI",
    "wof:name":"AFLAC",
    "wof:placetype":"venue"
},
  "geometry": {"coordinates":[-88.177195,43.083246],"type":"Point"}
}