{
  "type": "Feature",
  "properties": {
    "iso:country":"US",
    "sg:address":"2402 Rose St",
    "sg:city":"La Crosse",
    "sg:classifiers":[
        {
            "category":"Banks & Credit Unions",
            "subcategory":"Bank",
            "type":"Services"
        }
    ],
    "sg:phone":"+1 608 781 1500",
    "sg:postcode":"54603",
    "sg:province":"WI",
    "sg:website":"www.firstfed.com",
    "wof:name":"First Federal Savings Bank",
    "wof:placetype":"venue"
},
  "geometry": {"coordinates":[-91.243302,43.857386],"type":"Point"}
}