{
  "type": "Feature",
  "properties": {
    "iso:country":"US",
    "sg:address":"213 N Black River St",
    "sg:city":"Sparta",
    "sg:classifiers":[
        {
            "category":"Freight",
            "type":"Transportation"
        }
    ],
    "sg:phone":"+1 608 269 1603",
    "sg:postcode":"54656",
    "sg:province":"WI",
    "sg:tags":[
        "local",
        "mover",
        "storage",
        "trucking"
    ],
    "wof:name":"Innovative Movers Inc",
    "wof:placetype":"venue"
},
  "geometry": {"coordinates":[-90.82069799999999,43.946098],"type":"Point"}
}