{
  "type": "Feature",
  "properties": {
    "iso:country":"US",
    "sg:address":"3633 W College Ave",
    "sg:city":"Appleton",
    "sg:classifiers":[
        {
            "category":"Restaurant",
            "type":"Food & Drink"
        }
    ],
    "sg:menulink":"http://www.allmenus.com/wi/grand-chute/79993-pizza-hut/menu/",
    "sg:phone":"+1 920 734 2558",
    "sg:postcode":"54914",
    "sg:province":"WI",
    "sg:tags":[
        "american",
        "pizza"
    ],
    "wof:name":"Pizza Hut",
    "wof:placetype":"venue"
},
  "geometry": {"coordinates":[-88.45935799999999,44.261514],"type":"Point"}
}