{
  "type": "Feature",
  "properties": {
    "addr:full":"2200 Woodale Ave Green Bay WI 54313",
    "addr:housenumber":"2200",
    "addr:postcode":"54313",
    "addr:street":"Woodale Ave",
    "iso:country":"US",
    "sg:address":"2200 Woodale Ave",
    "sg:city":"Green Bay",
    "sg:classifiers":[
        {
            "category":"Building & Trades",
            "subcategory":"Construction",
            "type":"Services"
        }
    ],
    "sg:phone":"+1 920 434 0230",
    "sg:postcode":"54313",
    "sg:province":"WI",
    "sg:tags":[
        "general",
        "contractor"
    ],
    "sg:website":"www.theselmerco.com",
    "wof:name":"Selmer Co",
    "wof:placetype":"venue"
},
  "geometry": {"coordinates":[-88.07369,44.572995],"type":"Point"}
}