{
  "type": "Feature",
  "properties": {
    "iso:country":"US",
    "sg:address":"885 Badger Cir",
    "sg:city":"Grafton",
    "sg:classifiers":[
        {
            "category":"Social Services",
            "type":"Services"
        }
    ],
    "sg:phone":"+1 262 375 4683",
    "sg:postcode":"53024",
    "sg:province":"WI",
    "sg:tags":[
        "youth"
    ],
    "wof:name":"Youth and Family Project",
    "wof:placetype":"venue"
},
  "geometry": {"coordinates":[-87.932192,43.32602],"type":"Point"}
}