{
  "type": "Feature",
  "properties": {
    "iso:country":"US",
    "sg:address":"4909 N 119th St",
    "sg:city":"Milwaukee",
    "sg:classifiers":[
        {
            "category":"Manufacturing",
            "subcategory":"Metals",
            "type":"Manufacturing & Wholesale Goods"
        },
        {
            "category":"Manufacturing",
            "subcategory":"Building Materials",
            "type":"Manufacturing & Wholesale Goods"
        }
    ],
    "sg:phone":"+1 414 461 5500",
    "sg:postcode":"53225",
    "sg:province":"WI",
    "sg:tags":[
        "tubing",
        "pipe-wholesale",
        "manufacturer"
    ],
    "wof:name":"A.F. Seideman Co., Inc.",
    "wof:placetype":"venue"
},
  "geometry": {"coordinates":[-88.060947,43.106858],"type":"Point"}
}