{
  "type": "Feature",
  "properties": {
    "iso:country":"US",
    "sg:address":"85 E Main St",
    "sg:city":"Platteville",
    "sg:classifiers":[
        {
            "category":"Shopping",
            "subcategory":"Used Merchandise",
            "type":"Retail Goods"
        }
    ],
    "sg:phone":"+1 608 348 7356",
    "sg:postcode":"53818",
    "sg:province":"WI",
    "wof:name":"Change Of Seasons",
    "wof:placetype":"venue"
},
  "geometry": {"coordinates":[-90.477406,42.73382],"type":"Point"}
}