{
  "type": "Feature",
  "properties": {
    "iso:country":"US",
    "sg:address":"6240 S 92nd St",
    "sg:city":"Hales Corners",
    "sg:classifiers":[
        {
            "category":"Insurance",
            "subcategory":"Insurance Agent",
            "type":"Services"
        }
    ],
    "sg:phone":"+1 414 423 8885",
    "sg:postcode":"53130",
    "sg:province":"WI",
    "wof:name":"E Wenzel Insurance Assoc Inc",
    "wof:placetype":"venue"
},
  "geometry": {"coordinates":[-88.028476,42.931772],"type":"Point"}
}