{
  "type": "Feature",
  "properties": {
    "iso:country":"US",
    "sg:address":"801 Water St",
    "sg:city":"Sauk City",
    "sg:classifiers":[
        {
            "category":"Manufacturing",
            "subcategory":"Printing",
            "type":"Manufacturing & Wholesale Goods"
        }
    ],
    "sg:phone":"+1 608 643 3444",
    "sg:postcode":"53583",
    "sg:province":"WI",
    "sg:tags":[
        "newspaper"
    ],
    "wof:name":"Sauk-Prairie Star & Satellite",
    "wof:placetype":"venue"
},
  "geometry": {"coordinates":[-89.72134699999999,43.272064],"type":"Point"}
}