{
  "type": "Feature",
  "properties": {
    "iso:country":"US",
    "sg:address":"2501 N 5th St",
    "sg:city":"Milwaukee",
    "sg:classifiers":[
        {
            "category":"Shopping",
            "subcategory":"Clothing, Apparel, & Fashions",
            "type":"Retail Goods"
        }
    ],
    "sg:phone":"+1 414 263 9171",
    "sg:postcode":"53212",
    "sg:province":"WI",
    "sg:tags":[
        "tailor"
    ],
    "wof:name":"Fit-Rite Tailors",
    "wof:placetype":"venue"
},
  "geometry": {"coordinates":[-87.917026,43.065757],"type":"Point"}
}