{
  "type": "Feature",
  "properties": {
    "addr:full":"3380 S 108th St Milwaukee WI 53227",
    "addr:housenumber":"3380",
    "addr:postcode":"53227",
    "addr:street":"S 108Th St",
    "iso:country":"US",
    "sg:address":"3380 S 108th St",
    "sg:city":"Milwaukee",
    "sg:classifiers":[
        {
            "category":"Health Services",
            "subcategory":"Chiropractor",
            "type":"Services"
        }
    ],
    "sg:phone":"+1 414 541 6444",
    "sg:postcode":"53227",
    "sg:province":"WI",
    "wof:name":"Jacober Ray & Assoc",
    "wof:placetype":"venue"
},
  "geometry": {"coordinates":[-88.04738999999999,42.980827],"type":"Point"}
}