{
  "type": "Feature",
  "properties": {
    "addr:full":"4626 University Ave Madison WI 53705",
    "addr:housenumber":"4626",
    "addr:postcode":"53705",
    "addr:street":"University Ave",
    "iso:country":"US",
    "sg:address":"4626 University Ave",
    "sg:city":"Madison",
    "sg:classifiers":[
        {
            "category":"Government",
            "subcategory":"Office",
            "type":"Public Place"
        }
    ],
    "sg:phone":"+1 608 266 2031",
    "sg:postcode":"53705",
    "sg:province":"WI",
    "wof:name":"Crime Laboratory",
    "wof:placetype":"venue"
},
  "geometry": {"coordinates":[-89.456929,43.075303],"type":"Point"}
}