{
  "type": "Feature",
  "properties": {
    "iso:country":"US",
    "sg:address":"7112 270th Ave",
    "sg:city":"Menomonie",
    "sg:classifiers":[
        {
            "category":"Organizations",
            "subcategory":"Religious Organization",
            "type":"Services"
        }
    ],
    "sg:phone":"+1 715 664 8436",
    "sg:postcode":"54751",
    "sg:province":"WI",
    "sg:tags":[
        "church"
    ],
    "wof:name":"Forest Ctr Chr Of The Nazarene",
    "wof:placetype":"venue"
},
  "geometry": {"coordinates":[-91.801488,44.778154],"type":"Point"}
}