{
  "type": "Feature",
  "properties": {
    "iso:country":"US",
    "sg:address":"400 Park Hill Dr",
    "sg:city":"Pewaukee",
    "sg:classifiers":[
        {
            "category":"Real Estate",
            "subcategory":"Real Estate Agent",
            "type":"Services"
        },
        {
            "category":"Real Estate",
            "subcategory":"Real Estate Operator",
            "type":"Services"
        }
    ],
    "sg:phone":"+1 262 695 9836",
    "sg:postcode":"53072",
    "sg:province":"WI",
    "sg:tags":[
        "condominium"
    ],
    "wof:name":"Pewaukee Hlls Condo Homes Assn",
    "wof:placetype":"venue"
},
  "geometry": {"coordinates":[-88.262559,43.089024],"type":"Point"}
}