{
  "type": "Feature",
  "properties": {
    "iso:country":"US",
    "sg:address":"895 Pleasent View Ct",
    "sg:city":"Mount Calvary",
    "sg:classifiers":[
        {
            "category":"Organizations",
            "subcategory":"Religious Organization",
            "type":"Services"
        }
    ],
    "sg:phone":"+1 920 753 2221",
    "sg:postcode":"53057",
    "sg:province":"WI",
    "wof:name":"Covenant Construction",
    "wof:placetype":"venue"
},
  "geometry": {"coordinates":[-88.200743,43.789957],"type":"Point"}
}