{
  "type": "Feature",
  "properties": {
    "iso:country":"US",
    "sg:address":"1114 S 10th St",
    "sg:city":"Manitowoc",
    "sg:classifiers":[
        {
            "category":"Home & Garden",
            "subcategory":"Furniture",
            "type":"Retail Goods"
        }
    ],
    "sg:phone":"+1 920 682 8400",
    "sg:postcode":"54220",
    "sg:province":"WI",
    "sg:tags":[
        "used",
        "merchandise"
    ],
    "wof:name":"Medley Resale & Antiques",
    "wof:placetype":"venue"
},
  "geometry": {"coordinates":[-87.660672,44.085695],"type":"Point"}
}