{
  "type": "Feature",
  "properties": {
    "iso:country":"US",
    "sg:address":"360 W Little Sister Rd",
    "sg:city":"Sister Bay",
    "sg:classifiers":[
        {
            "category":"Restaurant",
            "type":"Food & Drink"
        }
    ],
    "sg:phone":"+1 920 854 6699",
    "sg:postcode":"54234",
    "sg:province":"WI",
    "sg:tags":[
        "eating"
    ],
    "wof:name":"Fred & Fuzzys Bar & Grill",
    "wof:placetype":"venue"
},
  "geometry": {"coordinates":[-87.147739,45.186611],"type":"Point"}
}