{
  "type": "Feature",
  "properties": {
    "iso:country":"US",
    "sg:address":"1930 Co Rd Xx",
    "sg:city":"Mosinee",
    "sg:classifiers":[
        {
            "category":"Organizations",
            "subcategory":"Religious Organization",
            "type":"Services"
        }
    ],
    "sg:phone":"+1 715 355 9900",
    "sg:postcode":"54474",
    "sg:province":"WI",
    "sg:tags":[
        "pentecostal",
        "church"
    ],
    "wof:name":"Crossroads Assembly Of God",
    "wof:placetype":"venue"
},
  "geometry": {"coordinates":[-89.615939,44.858309],"type":"Point"}
}