{
  "type": "Feature",
  "properties": {
    "iso:country":"US",
    "sg:address":"5803 52nd St",
    "sg:city":"Kenosha",
    "sg:classifiers":[
        {
            "category":"Real Estate",
            "subcategory":"Real Estate Agent",
            "type":"Services"
        }
    ],
    "sg:phone":"+1 262 658 8190",
    "sg:postcode":"53144",
    "sg:province":"WI",
    "sg:tags":[
        "broker",
        "mortgage"
    ],
    "sg:website":"www.providence-realty.com",
    "wof:name":"Providence Realty",
    "wof:placetype":"venue"
},
  "geometry": {"coordinates":[-87.882171,42.588737],"type":"Point"}
}