{
  "type": "Feature",
  "properties": {
    "iso:country":"US",
    "sg:address":"17294 Thielke Rd",
    "sg:city":"Lakewood",
    "sg:classifiers":[
        {
            "category":"Freight",
            "type":"Transportation"
        }
    ],
    "sg:phone":"+1 715 276 6622",
    "sg:postcode":"54138",
    "sg:province":"WI",
    "sg:tags":[
        "operator",
        "local",
        "trucking"
    ],
    "wof:name":"John Eichinger Inc",
    "wof:placetype":"venue"
},
  "geometry": {"coordinates":[-88.475999,45.304547],"type":"Point"}
}