{
  "type": "Feature",
  "properties": {
    "iso:country":"US",
    "sg:address":"18900 W Bluemound Rd",
    "sg:city":"Brookfield",
    "sg:classifiers":[
        {
            "category":"Shopping",
            "subcategory":"Stationery & Office Supplies",
            "type":"Retail Goods"
        },
        {
            "category":"Professional",
            "subcategory":"Management & Consulting",
            "type":"Services"
        }
    ],
    "sg:phone":"+1 262 787 0007",
    "sg:postcode":"53045",
    "sg:province":"WI",
    "sg:tags":[
        "album",
        "scrapbook",
        "business"
    ],
    "wof:name":"Creative Pals Inc",
    "wof:placetype":"venue"
},
  "geometry": {"coordinates":[-88.15030299999999,43.035978],"type":"Point"}
}