{
  "type": "Feature",
  "properties": {
    "iso:country":"US",
    "sg:address":"821 Park Ave",
    "sg:city":"Beaver Dam",
    "sg:classifiers":[
        {
            "category":"Retail",
            "subcategory":"Car Wash",
            "type":"Services"
        }
    ],
    "sg:phone":"+1 920 356 9744",
    "sg:postcode":"53916",
    "sg:province":"WI",
    "sg:tags":[
        "automobile",
        "detail",
        "clean"
    ],
    "wof:name":"Einstein Auto Detailers",
    "wof:placetype":"venue"
},
  "geometry": {"coordinates":[-88.821533,43.456249],"type":"Point"}
}