{
  "type": "Feature",
  "properties": {
    "iso:country":"US",
    "sg:address":"2552 Co Rd F",
    "sg:city":"Baileys Harbor",
    "sg:classifiers":[
        {
            "category":"Travel",
            "subcategory":"Campground",
            "type":"Entertainment"
        }
    ],
    "sg:phone":"+1 920 839 2559",
    "sg:postcode":"54202",
    "sg:province":"WI",
    "wof:name":"Bailey's Grove",
    "wof:placetype":"venue"
},
  "geometry": {"coordinates":[-87.13877100000001,45.072529],"type":"Point"}
}