{
  "type": "Feature",
  "properties": {
    "iso:country":"US",
    "sg:address":"540 E Thomas St",
    "sg:city":"Wausau",
    "sg:classifiers":[
        {
            "category":"Social Services",
            "type":"Services"
        }
    ],
    "sg:phone":"+1 715 849 1749",
    "sg:postcode":"54403",
    "sg:province":"WI",
    "sg:tags":[
        "counseling",
        "senior",
        "citizen"
    ],
    "wof:name":"Senior Citizens Assn Inc",
    "wof:placetype":"venue"
},
  "geometry": {"coordinates":[-89.626044,44.950089],"type":"Point"}
}