{
  "type": "Feature",
  "properties": {
    "iso:country":"US",
    "sg:address":"706 Prairie Rd",
    "sg:city":"Fond Du Lac",
    "sg:classifiers":[
        {
            "category":"Education",
            "subcategory":"School",
            "type":"Public Place"
        }
    ],
    "sg:phone":"+1 920 929 2901",
    "sg:postcode":"54935",
    "sg:province":"WI",
    "sg:tags":[
        "elementary"
    ],
    "wof:name":"Lakeshore Elementary School",
    "wof:placetype":"venue"
},
  "geometry": {"coordinates":[-88.412086,43.794284],"type":"Point"}
}