{
  "type": "Feature",
  "properties": {
    "iso:country":"US",
    "sg:address":"519 Chad Ct",
    "sg:city":"North Prairie",
    "sg:classifiers":[
        {
            "category":"Professional",
            "subcategory":"Management & Consulting",
            "type":"Services"
        }
    ],
    "sg:phone":"+1 262 392 2269",
    "sg:postcode":"53153",
    "sg:province":"WI",
    "wof:name":"Tri Products",
    "wof:placetype":"venue"
},
  "geometry": {"coordinates":[-88.390336,42.936943],"type":"Point"}
}