{
  "type": "Feature",
  "properties": {
    "iso:country":"US",
    "sg:address":"3333 County Road H",
    "sg:city":"Franksville",
    "sg:classifiers":[
        {
            "category":"Autos & Motor Vehicles",
            "subcategory":"Auto Supplies",
            "type":"Retail Goods"
        },
        {
            "category":"Retail",
            "subcategory":"Auto Repair",
            "type":"Services"
        }
    ],
    "sg:phone":"+1 262 886 3011",
    "sg:postcode":"53126",
    "sg:province":"WI",
    "sg:tags":[
        "tire"
    ],
    "sg:website":"www.franksvilleauto.net",
    "wof:name":"Franksville Tire and Auto Service",
    "wof:placetype":"venue"
},
  "geometry": {"coordinates":[-87.91480300000001,42.7612],"type":"Point"}
}