{
  "type": "Feature",
  "properties": {
    "iso:country":"US",
    "sg:address":"19 W Main St",
    "sg:city":"Cambridge",
    "sg:classifiers":[
        {
            "category":"Building & Trades",
            "subcategory":"Plumbing",
            "type":"Services"
        }
    ],
    "sg:phone":"+1 608 423 4109",
    "sg:postcode":"53523",
    "sg:province":"WI",
    "sg:tags":[
        "air",
        "heating",
        "conditioning",
        "contractor"
    ],
    "wof:name":"Bittner Heating & Cooling Inc",
    "wof:placetype":"venue"
},
  "geometry": {"coordinates":[-89.02027099999999,43.0042],"type":"Point"}
}