{
  "type": "Feature",
  "properties": {
    "iso:country":"US",
    "sg:address":"951 W Broadway Dr",
    "sg:city":"Appleton",
    "sg:classifiers":[
        {
            "category":"Manufacturing",
            "subcategory":"Printing",
            "type":"Manufacturing & Wholesale Goods"
        }
    ],
    "sg:phone":"+1 920 733 0542",
    "sg:postcode":"54913",
    "sg:province":"WI",
    "sg:tags":[
        "screen",
        "commercial"
    ],
    "wof:name":"Valley Screenprint Inc",
    "wof:placetype":"venue"
},
  "geometry": {"coordinates":[-88.424502,44.329179],"type":"Point"}
}