{
  "type": "Feature",
  "properties": {
    "iso:country":"US",
    "sg:address":"1182 State Hwy 21",
    "sg:city":"Friendship",
    "sg:classifiers":[
        {
            "category":"Shopping",
            "type":"Retail Goods"
        },
        {
            "category":"Shopping",
            "subcategory":"Gifts & Souvenirs",
            "type":"Retail Goods"
        }
    ],
    "sg:phone":"+1 608 339 2113",
    "sg:postcode":"53934",
    "sg:province":"WI",
    "sg:tags":[
        "craft",
        "gallery",
        "dealer"
    ],
    "wof:name":"God's Country Crafts Gifts",
    "wof:placetype":"venue"
},
  "geometry": {"coordinates":[-89.810509,44.024847],"type":"Point"}
}