{
  "type": "Feature",
  "properties": {
    "addr:full":"4303 Co Hwy M S Elk Mound WI 54739",
    "addr:housenumber":"4303",
    "addr:postcode":"54739",
    "addr:street":"Co Hwy M",
    "iso:country":"US",
    "sg:address":"4303 Co Hwy M S",
    "sg:city":"Elk Mound",
    "sg:classifiers":[
        {
            "category":"Manufacturing",
            "subcategory":"Printing",
            "type":"Manufacturing & Wholesale Goods"
        }
    ],
    "sg:phone":"+1 715 874 5149",
    "sg:postcode":"54739",
    "sg:province":"WI",
    "sg:tags":[
        "commercial"
    ],
    "wof:name":"Badgerland Printing",
    "wof:placetype":"venue"
},
  "geometry": {"coordinates":[-91.610544,44.910707],"type":"Point"}
}