{
  "type": "Feature",
  "properties": {
    "iso:country":"US",
    "sg:address":"565 Co Rd J",
    "sg:city":"Hatley",
    "sg:classifiers":[
        {
            "category":"Farming",
            "subcategory":"Livestock Farm",
            "type":"Manufacturing & Wholesale Goods"
        }
    ],
    "sg:phone":"+1 715 446 3870",
    "sg:postcode":"54440",
    "sg:province":"WI",
    "sg:tags":[
        "beef",
        "feedlot",
        "cattle"
    ],
    "wof:name":"Dan Zogata",
    "wof:placetype":"venue"
},
  "geometry": {"coordinates":[-89.447706,44.791112],"type":"Point"}
}