{
  "type": "Feature",
  "properties": {
    "iso:country":"US",
    "sg:address":"4833 State Hwy 58",
    "sg:city":"Mauston",
    "sg:classifiers":[
        {
            "category":"Autos & Motor Vehicles",
            "subcategory":"Motorcycle Sales",
            "type":"Retail Goods"
        }
    ],
    "sg:phone":"+1 608 847 7702",
    "sg:postcode":"53948",
    "sg:province":"WI",
    "sg:tags":[
        "scooter"
    ],
    "sg:website":"www.balas-hd.com",
    "wof:name":"Bala's Harley-Davidson",
    "wof:placetype":"venue"
},
  "geometry": {"coordinates":[-90.07679400000001,43.7891],"type":"Point"}
}