{
  "type": "Feature",
  "properties": {
    "iso:country":"US",
    "sg:address":"4439 N Frederick Ave",
    "sg:city":"Shorewood",
    "sg:classifiers":[
        {
            "category":"Professional",
            "subcategory":"Business Services",
            "type":"Services"
        }
    ],
    "sg:phone":"+1 414 964 8141",
    "sg:postcode":"53211",
    "sg:province":"WI",
    "sg:tags":[
        "translator",
        "interpreter"
    ],
    "wof:name":"Barbara Collignon",
    "wof:placetype":"venue"
},
  "geometry": {"coordinates":[-87.883578,43.097212],"type":"Point"}
}