{
  "type": "Feature",
  "properties": {
    "addr:full":"9286 Iron Rd Beaver Dam WI 53916",
    "addr:housenumber":"9286",
    "addr:postcode":"53916",
    "addr:street":"Iron Rd",
    "iso:country":"US",
    "sg:address":"9286 Iron Rd",
    "sg:city":"Beaver Dam",
    "sg:classifiers":[
        {
            "category":"Manufacturing",
            "subcategory":"Metals",
            "type":"Manufacturing & Wholesale Goods"
        }
    ],
    "sg:phone":"+1 920 887 3320",
    "sg:postcode":"53916",
    "sg:province":"WI",
    "sg:tags":[
        "equipment",
        "heating",
        "mfg"
    ],
    "wof:name":"Propst Pellets & Stoves LLC",
    "wof:placetype":"venue"
},
  "geometry": {"coordinates":[-88.865832,43.43603],"type":"Point"}
}