{
  "type": "Feature",
  "properties": {
    "iso:country":"US",
    "sg:address":"2910 E Washington Ave",
    "sg:city":"Madison",
    "sg:classifiers":[
        {
            "category":"Restaurant",
            "type":"Food & Drink"
        }
    ],
    "sg:phone":"+1 608 204 9955",
    "sg:postcode":"53704",
    "sg:province":"WI",
    "sg:tags":[
        "shop",
        "coffee"
    ],
    "wof:name":"Java Detour",
    "wof:placetype":"venue"
},
  "geometry": {"coordinates":[-89.343256,43.103691],"type":"Point"}
}