{
  "type": "Feature",
  "properties": {
    "addr:full":"4757 S Packard Ave Cudahy WI 53110",
    "addr:housenumber":"4757",
    "addr:postcode":"53110",
    "addr:street":"S Packard Ave",
    "iso:country":"US",
    "sg:address":"4757 S Packard Ave",
    "sg:city":"Cudahy",
    "sg:classifiers":[
        {
            "category":"Professional",
            "subcategory":"Lawyer & Legal Services",
            "type":"Services"
        }
    ],
    "sg:phone":"+1 414 744 6822",
    "sg:postcode":"53110",
    "sg:province":"WI",
    "sg:tags":[
        "attorney",
        "law",
        "divorce",
        "wills",
        "planning",
        "real estate",
        "trust",
        "bankruptcy"
    ],
    "sg:website":"http://www.cudahylawyer.com",
    "wof:name":"Maranan Paul",
    "wof:placetype":"venue"
},
  "geometry": {"coordinates":[-87.860056,42.95785],"type":"Point"}
}