{
  "type": "Feature",
  "properties": {
    "iso:country":"US",
    "sg:address":"8211 W River Rd",
    "sg:city":"Manawa",
    "sg:classifiers":[
        {
            "category":"Farming",
            "subcategory":"Farm",
            "type":"Manufacturing & Wholesale Goods"
        }
    ],
    "sg:phone":"+1 920 596 2348",
    "sg:postcode":"54949",
    "sg:province":"WI",
    "sg:tags":[
        "crop",
        "animal",
        "general"
    ],
    "wof:name":"D Dale",
    "wof:placetype":"venue"
},
  "geometry": {"coordinates":[-88.91060299999999,44.532063],"type":"Point"}
}