{
  "type": "Feature",
  "properties": {
    "iso:country":"US",
    "sg:address":"1097 Manke Hesselberg Rd",
    "sg:city":"Bangor",
    "sg:classifiers":[
        {
            "category":"Farming",
            "subcategory":"Livestock Farm",
            "type":"Manufacturing & Wholesale Goods"
        }
    ],
    "sg:phone":"+1 608 486 2680",
    "sg:postcode":"54614",
    "sg:province":"WI",
    "sg:tags":[
        "hog",
        "dairy",
        "or",
        "feedlot"
    ],
    "wof:name":"I View Farm",
    "wof:placetype":"venue"
},
  "geometry": {"coordinates":[-90.96541499999999,43.892713],"type":"Point"}
}