{
  "type": "Feature",
  "properties": {
    "iso:country":"US",
    "sg:address":"102 E Cook St",
    "sg:city":"New London",
    "sg:classifiers":[
        {
            "category":"Freight",
            "type":"Transportation"
        },
        {
            "category":"Retail",
            "subcategory":"Laundry & Dry Cleaning",
            "type":"Services"
        }
    ],
    "sg:phone":"+1 920 982 3212",
    "sg:postcode":"54961",
    "sg:province":"WI",
    "sg:tags":[
        "cleaners",
        "courier"
    ],
    "wof:name":"Dry Cleaners Etc",
    "wof:placetype":"venue"
},
  "geometry": {"coordinates":[-88.739633,44.389065],"type":"Point"}
}