{
  "type": "Feature",
  "properties": {
    "iso:country":"US",
    "sg:address":"16640 Ridgeview Dr",
    "sg:city":"Brookfield",
    "sg:classifiers":[
        {
            "category":"Real Estate",
            "subcategory":"Real Estate Agent",
            "type":"Services"
        }
    ],
    "sg:phone":"+1 262 790 0156",
    "sg:postcode":"53005",
    "sg:province":"WI",
    "sg:tags":[
        "property",
        "management"
    ],
    "wof:name":"Scott Johnson Realty Inc",
    "wof:placetype":"venue"
},
  "geometry": {"coordinates":[-88.124313,43.096599],"type":"Point"}
}