{
  "type": "Feature",
  "properties": {
    "addr:full":"601 E Silver Spring Dr Milwaukee WI 53217",
    "addr:housenumber":"601",
    "addr:postcode":"53217",
    "addr:street":"E Silver Spring Dr",
    "iso:country":"US",
    "sg:address":"601 E Silver Spring Dr",
    "sg:city":"Milwaukee",
    "sg:classifiers":[
        {
            "category":"Food Court",
            "type":"Food & Drink"
        },
        {
            "category":"Restaurant",
            "type":"Food & Drink"
        },
        {
            "category":"Bagels",
            "subcategory":"None",
            "type":"Food & Drink"
        },
        {
            "category":"Coffee & Tea",
            "type":"Food & Drink"
        },
        {
            "category":"Bakery",
            "type":"Food & Drink"
        },
        {
            "category":"Food & Beverages",
            "subcategory":"Groceries & Convenience Stores",
            "type":"Retail Goods"
        }
    ],
    "sg:phone":"+1 414 964 4600",
    "sg:postcode":"53217",
    "sg:province":"WI",
    "sg:tags":[
        "shop",
        "sandwich",
        "espresso",
        "box",
        "lunch",
        "brunch",
        "breakfast"
    ],
    "sg:website":"http://www.brueggers.com",
    "wof:name":"Bruegger's",
    "wof:placetype":"venue"
},
  "geometry": {"coordinates":[-87.90300000000001,43.1185],"type":"Point"}
}