{
  "type": "Feature",
  "properties": {
    "iso:country":"US",
    "sg:address":"13264 Bachelors Ave",
    "sg:city":"Thorp",
    "sg:phone":"+1 715 669 7209",
    "sg:postcode":"54771",
    "sg:province":"WI",
    "sg:tags":[
        "farm",
        "corn"
    ],
    "wof:name":"Martin Zieset",
    "wof:placetype":"venue"
},
  "geometry": {"coordinates":[-90.739985,44.895502],"type":"Point"}
}