{
  "type": "Feature",
  "properties": {
    "iso:country":"US",
    "sg:address":"1840 N Prospect Ave",
    "sg:city":"Milwaukee",
    "sg:classifiers":[
        {
            "category":"Banks & Credit Unions",
            "subcategory":"Bank",
            "type":"Services"
        }
    ],
    "sg:phone":"+1 414 272 2022",
    "sg:postcode":"53202",
    "sg:province":"WI",
    "sg:tags":[
        "state"
    ],
    "wof:name":"M & I Marshall & Ilsley Bank",
    "wof:placetype":"venue"
},
  "geometry": {"coordinates":[-87.889374,43.05405],"type":"Point"}
}