{
  "type": "Feature",
  "properties": {
    "addr:full":"2826 Brandon Rd Madison WI 53719",
    "addr:housenumber":"2826",
    "addr:postcode":"53719",
    "addr:street":"Brandon Rd",
    "iso:country":"US",
    "sg:address":"2826 Brandon Rd",
    "sg:city":"Madison",
    "sg:classifiers":[
        {
            "category":"Real Estate",
            "subcategory":"Real Estate Agent",
            "type":"Services"
        }
    ],
    "sg:phone":"+1 608 274 0872",
    "sg:postcode":"53719",
    "sg:province":"WI",
    "wof:name":"Alliance Real Estate Service",
    "wof:placetype":"venue"
},
  "geometry": {"coordinates":[-89.492099,43.022055],"type":"Point"}
}