{
  "type": "Feature",
  "properties": {
    "iso:country":"US",
    "sg:address":"12901 Scholze Rd",
    "sg:city":"Humbird",
    "sg:classifiers":[
        {
            "category":"Building & Trades",
            "subcategory":"Plumbing",
            "type":"Services"
        }
    ],
    "sg:phone":"+1 715 964 7864",
    "sg:postcode":"54746",
    "sg:province":"WI",
    "sg:tags":[
        "conditioning",
        "contractor",
        "system",
        "air"
    ],
    "wof:name":"Scholze Heating & Air Cond",
    "wof:placetype":"venue"
},
  "geometry": {"coordinates":[-90.948376,44.524343],"type":"Point"}
}