{
  "type": "Feature",
  "properties": {
    "iso:country":"US",
    "sg:address":"1808 S Elm Grove Rd",
    "sg:city":"New Berlin",
    "sg:classifiers":[
        {
            "category":"Professional",
            "subcategory":"Accounting & Tax Preparation",
            "type":"Services"
        }
    ],
    "sg:phone":"+1 262 797 8027",
    "sg:postcode":"53151",
    "sg:province":"WI",
    "sg:tags":[
        "accountant"
    ],
    "wof:name":"Tax-Xperts",
    "wof:placetype":"venue"
},
  "geometry": {"coordinates":[-88.077522,43.011762],"type":"Point"}
}