{
  "type": "Feature",
  "properties": {
    "addr:full":"10599 Big Arbor Vitae Dr Woodruff WI 54568",
    "addr:housenumber":"10599",
    "addr:postcode":"54568",
    "addr:street":"Big Arbor Vitae Dr",
    "iso:country":"US",
    "sg:address":"10599 Big Arbor Vitae Dr",
    "sg:city":"Woodruff",
    "sg:classifiers":[
        {
            "category":"Bars & Pubs",
            "type":"Food & Drink"
        }
    ],
    "sg:phone":"+1 715 358 3006",
    "sg:postcode":"54568",
    "sg:province":"WI",
    "wof:name":"Slo's Pub",
    "wof:placetype":"venue"
},
  "geometry": {"coordinates":[-89.656987,45.91769],"type":"Point"}
}