{
  "type": "Feature",
  "properties": {
    "iso:country":"US",
    "sg:address":"150 East St",
    "sg:city":"Potosi",
    "sg:classifiers":[
        {
            "category":"Freight",
            "type":"Transportation"
        }
    ],
    "sg:phone":"+1 608 763 2913",
    "sg:postcode":"53820",
    "sg:province":"WI",
    "sg:tags":[
        "trucking"
    ],
    "wof:name":"B X Trucking Inc",
    "wof:placetype":"venue"
},
  "geometry": {"coordinates":[-90.704185,42.688795],"type":"Point"}
}