{
  "type": "Feature",
  "properties": {
    "iso:country":"US",
    "sg:address":"1330 S Lutz St",
    "sg:city":"Shawano",
    "sg:classifiers":[
        {
            "category":"Personal",
            "subcategory":"Beauty Salon",
            "type":"Services"
        }
    ],
    "sg:phone":"+1 715 524 5828",
    "sg:postcode":"54166",
    "sg:province":"WI",
    "sg:tags":[
        "manicuring"
    ],
    "wof:name":"Loving Hands 2",
    "wof:placetype":"venue"
},
  "geometry": {"coordinates":[-88.606146,44.766147],"type":"Point"}
}