{
  "type": "Feature",
  "properties": {
    "iso:country":"US",
    "sg:address":"828 Perkins Dr",
    "sg:city":"Mukwonago",
    "sg:classifiers":[
        {
            "category":"Retail",
            "subcategory":"Animal Services",
            "type":"Services"
        }
    ],
    "sg:phone":"+1 262 363 4529",
    "sg:postcode":"53149",
    "sg:province":"WI",
    "sg:tags":[
        "pet",
        "training",
        "dog"
    ],
    "wof:name":"For Pet's Sake",
    "wof:placetype":"venue"
},
  "geometry": {"coordinates":[-88.317972,42.865188],"type":"Point"}
}