{
  "type": "Feature",
  "properties": {
    "iso:country":"US",
    "sg:address":"3500 S 13th St",
    "sg:city":"Milwaukee",
    "sg:classifiers":[
        {
            "category":"Autos & Motor Vehicles",
            "subcategory":"Fuel & Gas Station",
            "type":"Retail Goods"
        },
        {
            "category":"Wholesale",
            "subcategory":"Petroleum",
            "type":"Manufacturing & Wholesale Goods"
        },
        {
            "category":"Manufacturing",
            "subcategory":"Petroleum Products",
            "type":"Manufacturing & Wholesale Goods"
        },
        {
            "category":"Utilities",
            "subcategory":"Fuel Oil & Lpg",
            "type":"Services"
        }
    ],
    "sg:phone":"+1 414 486 7691",
    "sg:postcode":"53221",
    "sg:province":"WI",
    "sg:tags":[
        "oils-fuel",
        "gasoline-wholesale",
        "marketer",
        "oils-petroleum"
    ],
    "wof:name":"Himalyan Oil Company",
    "wof:placetype":"venue"
},
  "geometry": {"coordinates":[-87.92894699999999,42.981079],"type":"Point"}
}