{
  "type": "Feature",
  "properties": {
    "iso:country":"US",
    "sg:address":"1460 Iris Dr",
    "sg:city":"Manitowoc",
    "sg:classifiers":[
        {
            "category":"Food & Beverages",
            "subcategory":"Specialty",
            "type":"Retail Goods"
        }
    ],
    "sg:phone":"+1 920 682 1647",
    "sg:postcode":"54220",
    "sg:province":"WI",
    "sg:tags":[
        "vitamin"
    ],
    "wof:name":"Herbalife Distributor",
    "wof:placetype":"venue"
},
  "geometry": {"coordinates":[-87.635138,44.116139],"type":"Point"}
}