{
  "type": "Feature",
  "properties": {
    "addr:full":"2920 Fairmont St Manitowoc WI 54220",
    "addr:housenumber":"2920",
    "addr:postcode":"54220",
    "addr:street":"Fairmont St",
    "iso:country":"US",
    "sg:address":"2920 Fairmont St",
    "sg:city":"Manitowoc",
    "sg:classifiers":[
        {
            "category":"Manufacturing",
            "subcategory":"Motor Vehicles & Parts",
            "type":"Manufacturing & Wholesale Goods"
        }
    ],
    "sg:phone":"+1 920 684 6662",
    "sg:postcode":"54220",
    "sg:province":"WI",
    "sg:tags":[
        "automobile",
        "supply"
    ],
    "wof:name":"Federal Mogul Powertrain Syst",
    "wof:placetype":"venue"
},
  "geometry": {"coordinates":[-87.684038,44.110112],"type":"Point"}
}