{
  "type": "Feature",
  "properties": {
    "iso:country":"US",
    "sg:address":"18680 Abbey Ln",
    "sg:city":"Brookfield",
    "sg:classifiers":[
        {
            "category":"Wholesale",
            "subcategory":"Medical Equipment & Supplies",
            "type":"Manufacturing & Wholesale Goods"
        }
    ],
    "sg:phone":"+1 262 783 9803",
    "sg:postcode":"53045",
    "sg:province":"WI",
    "wof:name":"Ingel Biomedix",
    "wof:placetype":"venue"
},
  "geometry": {"coordinates":[-88.142905,43.087833],"type":"Point"}
}