{
  "type": "Feature",
  "properties": {
    "addr:full":"1202 Williamson St Madison WI 53703",
    "addr:housenumber":"1202",
    "addr:postcode":"53703",
    "addr:street":"Williamson St",
    "iso:country":"US",
    "sg:address":"1202 Williamson St",
    "sg:city":"Madison",
    "sg:classifiers":[
        {
            "category":"Organizations",
            "subcategory":"Non-profit Organization",
            "type":"Services"
        }
    ],
    "sg:phone":"+1 608 251 6834",
    "sg:postcode":"53703",
    "sg:province":"WI",
    "sg:tags":[
        "noncommercial"
    ],
    "wof:name":"Wisconsin Community Fund Inc",
    "wof:placetype":"venue"
},
  "geometry": {"coordinates":[-89.36262499999999,43.084535],"type":"Point"}
}