{
  "type": "Feature",
  "properties": {
    "iso:country":"US",
    "sg:address":"2104 N Swan Blvd",
    "sg:city":"Milwaukee",
    "sg:classifiers":[
        {
            "category":"Home & Garden",
            "subcategory":"Home Furnishings",
            "type":"Retail Goods"
        }
    ],
    "sg:phone":"+1 414 476 6536",
    "sg:postcode":"53226",
    "sg:province":"WI",
    "wof:name":"B&C Draperies",
    "wof:placetype":"venue"
},
  "geometry": {"coordinates":[-88.027401,43.057479],"type":"Point"}
}