{
  "type": "Feature",
  "properties": {
    "iso:country":"US",
    "sg:address":"6421 W Port Ave",
    "sg:city":"Milwaukee",
    "sg:classifiers":[
        {
            "category":"Real Estate",
            "subcategory":"Real Estate Services",
            "type":"Services"
        },
        {
            "category":"Real Estate",
            "subcategory":"Real Estate Operator",
            "type":"Services"
        }
    ],
    "sg:phone":"+1 414 357 8215",
    "sg:postcode":"53223",
    "sg:province":"WI",
    "sg:tags":[
        "vacancy",
        "apartment",
        "rental",
        "finder",
        "listing"
    ],
    "wof:name":"Abundant Life Apartments Inc",
    "wof:placetype":"venue"
},
  "geometry": {"coordinates":[-87.988461,43.158452],"type":"Point"}
}