{
  "type": "Feature",
  "properties": {
    "iso:country":"US",
    "sg:address":"1395 Broderick Rd",
    "sg:city":"Omro",
    "sg:classifiers":[
        {
            "category":"Wholesale",
            "subcategory":"Motor Vehicles",
            "type":"Manufacturing & Wholesale Goods"
        }
    ],
    "sg:phone":"+1 920 685 0165",
    "sg:postcode":"54963",
    "sg:province":"WI",
    "wof:name":"Hillhaven Enterprises LLC",
    "wof:placetype":"venue"
},
  "geometry": {"coordinates":[-88.758289,44.043441],"type":"Point"}
}