{
  "type": "Feature",
  "properties": {
    "iso:country":"US",
    "sg:address":"2202 School Ln",
    "sg:city":"Sturgeon Bay",
    "sg:classifiers":[
        {
            "category":"Farming",
            "subcategory":"Dairy Farm",
            "type":"Manufacturing & Wholesale Goods"
        }
    ],
    "sg:phone":"+1 920 825 7673",
    "sg:postcode":"54235",
    "sg:province":"WI",
    "wof:name":"Leon Vogel",
    "wof:placetype":"venue"
},
  "geometry": {"coordinates":[-87.519433,44.771837],"type":"Point"}
}