{
  "type": "Feature",
  "properties": {
    "addr:full":"6605 Mineral Point Rd Madison WI 53705",
    "addr:housenumber":"6605",
    "addr:postcode":"53705",
    "addr:street":"Mineral Point Rd",
    "iso:country":"US",
    "sg:address":"6605 Mineral Point Rd",
    "sg:city":"Madison",
    "sg:classifiers":[
        {
            "category":"Banks & Credit Unions",
            "subcategory":"Investment Brokerage",
            "type":"Services"
        }
    ],
    "sg:phone":"+1 608 829 8200",
    "sg:postcode":"53705",
    "sg:province":"WI",
    "sg:tags":[
        "stockbroker"
    ],
    "wof:name":"H & R Block Financial Advisors",
    "wof:placetype":"venue"
},
  "geometry": {"coordinates":[-89.49704800000001,43.060676],"type":"Point"}
}