{
  "type": "Feature",
  "properties": {
    "addr:full":"6993 Forest St Three Lakes WI 54562",
    "addr:housenumber":"6993",
    "addr:postcode":"54562",
    "addr:street":"Forest St",
    "iso:country":"US",
    "sg:address":"6993 Forest St",
    "sg:city":"Three Lakes",
    "sg:classifiers":[
        {
            "category":"Organizations",
            "subcategory":"Religious Organization",
            "type":"Services"
        }
    ],
    "sg:phone":"+1 715 546 2169",
    "sg:postcode":"54562",
    "sg:province":"WI",
    "sg:tags":[
        "church"
    ],
    "wof:name":"Union Congregational Church",
    "wof:placetype":"venue"
},
  "geometry": {"coordinates":[-89.165491,45.79647],"type":"Point"}
}