{
  "type": "Feature",
  "properties": {
    "iso:country":"US",
    "sg:address":"1216 North Rd",
    "sg:city":"Burlington",
    "sg:classifiers":[
        {
            "category":"Autos & Motor Vehicles",
            "subcategory":"Automobile Sales",
            "type":"Retail Goods"
        }
    ],
    "sg:phone":"+1 262 763 3145",
    "sg:postcode":"53105",
    "sg:province":"WI",
    "sg:tags":[
        "equipment",
        "aircraft",
        "parts",
        "supply"
    ],
    "wof:name":"Aero Fabricators Inc",
    "wof:placetype":"venue"
},
  "geometry": {"coordinates":[-88.357614,42.661041],"type":"Point"}
}