{
  "type": "Feature",
  "properties": {
    "addr:full":"190 Robinhood Ct Sherwood WI 54169",
    "addr:housenumber":"190",
    "addr:postcode":"54169",
    "addr:street":"Robinhood Ct",
    "iso:country":"US",
    "sg:address":"190 Robinhood Ct",
    "sg:city":"Sherwood",
    "sg:classifiers":[
        {
            "category":"Professional",
            "subcategory":"Management & Consulting",
            "type":"Services"
        }
    ],
    "sg:phone":"+1 920 989 2267",
    "sg:postcode":"54169",
    "sg:province":"WI",
    "sg:tags":[
        "trade",
        "contractor"
    ],
    "wof:name":"Godschalx Construction",
    "wof:placetype":"venue"
},
  "geometry": {"coordinates":[-88.24942,44.173946],"type":"Point"}
}