{
  "type": "Feature",
  "properties": {
    "iso:country":"US",
    "sg:address":"9317 Benson Rd",
    "sg:city":"Brooklyn",
    "sg:classifiers":[
        {
            "category":"Building & Trades",
            "subcategory":"Construction",
            "type":"Services"
        }
    ],
    "sg:phone":"+1 608 455 3307",
    "sg:postcode":"53521",
    "sg:province":"WI",
    "sg:tags":[
        "house"
    ],
    "wof:name":"KLAY Construction",
    "wof:placetype":"venue"
},
  "geometry": {"coordinates":[-89.389418,42.848621],"type":"Point"}
}