{
  "type": "Feature",
  "properties": {
    "iso:country":"US",
    "sg:address":"7316 Co Rd F W",
    "sg:city":"Randolph",
    "sg:classifiers":[
        {
            "category":"Farming",
            "subcategory":"Livestock Farm",
            "type":"Manufacturing & Wholesale Goods"
        }
    ],
    "sg:phone":"+1 920 326 3834",
    "sg:postcode":"53956",
    "sg:province":"WI",
    "sg:tags":[
        "beef",
        "feedlot",
        "cattle"
    ],
    "wof:name":"Stan Steinhorst",
    "wof:placetype":"venue"
},
  "geometry": {"coordinates":[-88.96646800000001,43.45918],"type":"Point"}
}