{
  "type": "Feature",
  "properties": {
    "iso:country":"US",
    "sg:address":"10231 Penny Lake Rd",
    "sg:city":"Rosholt",
    "sg:classifiers":[
        {
            "category":"Travel",
            "subcategory":"Hotels & Motels",
            "type":"Entertainment"
        }
    ],
    "sg:phone":"+1 715 677 4625",
    "sg:postcode":"54473",
    "sg:province":"WI",
    "sg:tags":[
        "operation"
    ],
    "wof:name":"Golden Sands Respiratory Care",
    "wof:placetype":"venue"
},
  "geometry": {"coordinates":[-89.270832,44.66809],"type":"Point"}
}