{
  "type": "Feature",
  "properties": {
    "iso:country":"US",
    "sg:address":"19 Green Bay Rd",
    "sg:city":"Sturgeon Bay",
    "sg:classifiers":[
        {
            "category":"Restaurant",
            "type":"Food & Drink"
        }
    ],
    "sg:phone":"+1 920 746 8727",
    "sg:postcode":"54235",
    "sg:province":"WI",
    "sg:tags":[
        "eating"
    ],
    "wof:name":"Scaturo's Baking Co & Cafe",
    "wof:placetype":"venue"
},
  "geometry": {"coordinates":[-87.384456,44.825007],"type":"Point"}
}