{
  "type": "Feature",
  "properties": {
    "iso:country":"US",
    "sg:address":"7922 US Hwy 12",
    "sg:city":"Elkhorn",
    "sg:classifiers":[
        {
            "category":"Real Estate",
            "subcategory":"Real Estate Operator",
            "type":"Services"
        }
    ],
    "sg:phone":"+1 262 742 3580",
    "sg:postcode":"53121",
    "sg:province":"WI",
    "sg:tags":[
        "property",
        "lessor"
    ],
    "wof:name":"Gordon Smith",
    "wof:placetype":"venue"
},
  "geometry": {"coordinates":[-88.554794,42.780237],"type":"Point"}
}