{
  "type": "Feature",
  "properties": {
    "iso:country":"US",
    "sg:address":"515 W Thorne St",
    "sg:city":"Ripon",
    "sg:classifiers":[
        {
            "category":"Restaurant",
            "type":"Food & Drink"
        }
    ],
    "sg:phone":"+1 920 748 7726",
    "sg:postcode":"54971",
    "sg:province":"WI",
    "sg:tags":[
        "eating"
    ],
    "wof:name":"C JS Catering",
    "wof:placetype":"venue"
},
  "geometry": {"coordinates":[-88.844938,43.841596],"type":"Point"}
}