{
  "type": "Feature",
  "properties": {
    "iso:country":"US",
    "sg:address":"9871 Image Ave",
    "sg:city":"Sparta",
    "sg:classifiers":[
        {
            "category":"Manufacturing",
            "subcategory":"Wood Products",
            "type":"Manufacturing & Wholesale Goods"
        }
    ],
    "sg:phone":"+1 608 366 1890",
    "sg:postcode":"54656",
    "sg:province":"WI",
    "wof:name":"Crook Stake Products",
    "wof:placetype":"venue"
},
  "geometry": {"coordinates":[-90.794779,43.919874],"type":"Point"}
}