{
  "type": "Feature",
  "properties": {
    "iso:country":"US",
    "sg:address":"904 3rd St",
    "sg:city":"Hudson",
    "sg:classifiers":[
        {
            "category":"Wholesale",
            "subcategory":"Durable Goods & Equipment",
            "type":"Manufacturing & Wholesale Goods"
        }
    ],
    "sg:phone":"+1 715 381 6500",
    "sg:postcode":"54016",
    "sg:province":"WI",
    "sg:tags":[
        "representative",
        "manufacturer"
    ],
    "wof:name":"St Croix Trading & Cllctbls Co",
    "wof:placetype":"venue"
},
  "geometry": {"coordinates":[-92.7555,44.979297],"type":"Point"}
}