{
  "type": "Feature",
  "properties": {
    "iso:country":"US",
    "sg:address":"235 N Casaloma Dr",
    "sg:city":"Appleton",
    "sg:classifiers":[
        {
            "category":"Home & Garden",
            "subcategory":"Household Appliances",
            "type":"Retail Goods"
        }
    ],
    "sg:phone":"+1 920 730 8787",
    "sg:postcode":"54913",
    "sg:province":"WI",
    "sg:tags":[
        "repair",
        "electrical"
    ],
    "wof:name":"Aerus Electrolux",
    "wof:placetype":"venue"
},
  "geometry": {"coordinates":[-88.476283,44.267397],"type":"Point"}
}