{
  "type": "Feature",
  "properties": {
    "addr:full":"1492 Russell St Green Bay WI 54304",
    "addr:housenumber":"1492",
    "addr:postcode":"54304",
    "addr:street":"Russell St",
    "iso:country":"US",
    "sg:address":"1492 Russell St",
    "sg:city":"Green Bay",
    "sg:classifiers":[
        {
            "category":"Professional",
            "subcategory":"Business Services",
            "type":"Services"
        }
    ],
    "sg:phone":"+1 920 498 0613",
    "sg:postcode":"54304",
    "sg:province":"WI",
    "wof:name":"Onsite Business Services",
    "wof:placetype":"venue"
},
  "geometry": {"coordinates":[-88.068333,44.514747],"type":"Point"}
}