{
  "type": "Feature",
  "properties": {
    "iso:country":"US",
    "sg:address":"2536 N 81st St",
    "sg:city":"Milwaukee",
    "sg:classifiers":[
        {
            "category":"Professional",
            "subcategory":"Business Services",
            "type":"Services"
        }
    ],
    "sg:phone":"+1 414 453 2014",
    "sg:postcode":"53213",
    "sg:province":"WI",
    "wof:name":"Titan Energy Solutions Inc",
    "wof:placetype":"venue"
},
  "geometry": {"coordinates":[-88.013643,43.065459],"type":"Point"}
}