{
  "type": "Feature",
  "properties": {
    "iso:country":"US",
    "sg:address":"2317 N Dr Martin Luther King Dr",
    "sg:city":"Milwaukee",
    "sg:classifiers":[
        {
            "category":"Manufacturing",
            "subcategory":"Printing",
            "type":"Manufacturing & Wholesale Goods"
        }
    ],
    "sg:phone":"+1 414 263 2679",
    "sg:postcode":"53212",
    "sg:province":"WI",
    "sg:tags":[
        "printer"
    ],
    "wof:name":"Shekinah Printing",
    "wof:placetype":"venue"
},
  "geometry": {"coordinates":[-87.914204,43.061814],"type":"Point"}
}