{
  "type": "Feature",
  "properties": {
    "addr:full":"8155 Apollo Ct Neenah WI 54956",
    "addr:housenumber":"8155",
    "addr:postcode":"54956",
    "addr:street":"Apollo Ct",
    "iso:country":"US",
    "sg:address":"8155 Apollo Ct",
    "sg:city":"Neenah",
    "sg:classifiers":[
        {
            "category":"Professional",
            "subcategory":"Business Services",
            "type":"Services"
        }
    ],
    "sg:phone":"+1 920 836 3973",
    "sg:postcode":"54956",
    "sg:province":"WI",
    "wof:name":"Krotje Enterprises",
    "wof:placetype":"venue"
},
  "geometry": {"coordinates":[-88.570654,44.187508],"type":"Point"}
}