{
  "type": "Feature",
  "properties": {
    "addr:full":"5639 W Peninsula Rd Waterford WI 53185",
    "addr:housenumber":"5639",
    "addr:postcode":"53185",
    "addr:street":"W Peninsula Rd",
    "iso:country":"US",
    "sg:address":"5639 W Peninsula Rd",
    "sg:city":"Waterford",
    "sg:classifiers":[
        {
            "category":"Bars & Pubs",
            "type":"Food & Drink"
        }
    ],
    "sg:phone":"+1 262 534 6053",
    "sg:postcode":"53185",
    "sg:province":"WI",
    "sg:tags":[
        "tavern"
    ],
    "wof:name":"Jask-Ziora Ltd",
    "wof:placetype":"venue"
},
  "geometry": {"coordinates":[-88.216629,42.789546],"type":"Point"}
}