{
  "type": "Feature",
  "properties": {
    "iso:country":"US",
    "sg:address":"4753 Paradise Rd",
    "sg:city":"Helenville",
    "sg:classifiers":[
        {
            "category":"Wholesale",
            "subcategory":"Machinery & Supplies",
            "type":"Manufacturing & Wholesale Goods"
        }
    ],
    "sg:phone":"+1 920 674 3083",
    "sg:postcode":"53137",
    "sg:province":"WI",
    "sg:tags":[
        "crane",
        "industrial"
    ],
    "wof:name":"Superior Lakefront Crane Svc",
    "wof:placetype":"venue"
},
  "geometry": {"coordinates":[-88.724727,43.014077],"type":"Point"}
}