{
  "type": "Feature",
  "properties": {
    "addr:full":"797 50th Ave Clear Lake WI 54005",
    "addr:housenumber":"797",
    "addr:postcode":"54005",
    "addr:street":"50Th Ave",
    "iso:country":"US",
    "sg:address":"797 50th Ave",
    "sg:city":"Clear Lake",
    "sg:classifiers":[
        {
            "category":"Building & Trades",
            "subcategory":"Construction",
            "type":"Services"
        }
    ],
    "sg:phone":"+1 715 263 2177",
    "sg:postcode":"54005",
    "sg:province":"WI",
    "sg:tags":[
        "contractor"
    ],
    "wof:name":"Barney Barns",
    "wof:placetype":"venue"
},
  "geometry": {"coordinates":[-92.325726,45.282246],"type":"Point"}
}