{
  "type": "Feature",
  "properties": {
    "addr:full":"2114 E Edgewood Ave Milwaukee WI 53211",
    "addr:housenumber":"2114",
    "addr:postcode":"53211",
    "addr:street":"E Edgewood Ave",
    "iso:country":"US",
    "sg:address":"2114 E Edgewood Ave",
    "sg:city":"Milwaukee",
    "sg:classifiers":[
        {
            "category":"Professional",
            "subcategory":"Management & Consulting",
            "type":"Services"
        }
    ],
    "sg:phone":"+1 414 977 1099",
    "sg:postcode":"53211",
    "sg:province":"WI",
    "sg:tags":[
        "business"
    ],
    "wof:name":"Benjamin Consulting Svcs LLC",
    "wof:placetype":"venue"
},
  "geometry": {"coordinates":[-87.88288300000001,43.082003],"type":"Point"}
}