{
  "type": "Feature",
  "properties": {
    "iso:country":"US",
    "sg:address":"11620 Lax Chapel Rd",
    "sg:city":"Kiel",
    "sg:classifiers":[
        {
            "category":"Building & Trades",
            "subcategory":"Cleaning & Sanitation",
            "type":"Services"
        }
    ],
    "sg:phone":"+1 920 894 2690",
    "sg:postcode":"53042",
    "sg:province":"WI",
    "wof:name":"Cleaning Solutions",
    "wof:placetype":"venue"
},
  "geometry": {"coordinates":[-87.982633,43.960934],"type":"Point"}
}