{
  "type": "Feature",
  "properties": {
    "iso:country":"US",
    "sg:address":"205 S Lincoln St",
    "sg:city":"Antigo",
    "sg:classifiers":[
        {
            "category":"Building & Trades",
            "subcategory":"Construction",
            "type":"Services"
        }
    ],
    "sg:phone":"+1 715 627 0646",
    "sg:postcode":"54409",
    "sg:province":"WI",
    "sg:tags":[
        "carpentry",
        "contractor"
    ],
    "wof:name":"H C Bzzmor Strpping Rfinishing",
    "wof:placetype":"venue"
},
  "geometry": {"coordinates":[-89.16021000000001,45.135998],"type":"Point"}
}