{
  "type": "Feature",
  "properties": {
    "iso:country":"US",
    "sg:address":"520 Coventry Dr",
    "sg:city":"Plover",
    "sg:classifiers":[
        {
            "category":"Building & Trades",
            "subcategory":"Construction",
            "type":"Services"
        }
    ],
    "sg:phone":"+1 715 342 0709",
    "sg:postcode":"54467",
    "sg:province":"WI",
    "sg:tags":[
        "house"
    ],
    "wof:name":"Lindstrom Remodeling",
    "wof:placetype":"venue"
},
  "geometry": {"coordinates":[-89.52932699999999,44.489711],"type":"Point"}
}