{
  "type": "Feature",
  "properties": {
    "addr:full":"1103 Sycamore St Delavan WI 53115",
    "addr:housenumber":"1103",
    "addr:postcode":"53115",
    "addr:street":"Sycamore St",
    "iso:country":"US",
    "sg:address":"1103 Sycamore St",
    "sg:city":"Delavan",
    "sg:classifiers":[
        {
            "category":"Shopping",
            "subcategory":"Gifts & Souvenirs",
            "type":"Retail Goods"
        }
    ],
    "sg:phone":"+1 262 728 8552",
    "sg:postcode":"53115",
    "sg:province":"WI",
    "wof:name":"Country Friends Gift Shop",
    "wof:placetype":"venue"
},
  "geometry": {"coordinates":[-88.666613,42.626979],"type":"Point"}
}