{
  "type": "Feature",
  "properties": {
    "iso:country":"US",
    "sg:address":"1516 Church St",
    "sg:city":"Stevens Point",
    "sg:classifiers":[
        {
            "category":"Government",
            "subcategory":"Office",
            "type":"Public Place"
        }
    ],
    "sg:phone":"+1 715 346 1350",
    "sg:postcode":"54481",
    "sg:province":"WI",
    "wof:name":"County Services Information",
    "wof:placetype":"venue"
},
  "geometry": {"coordinates":[-89.580196,44.520858],"type":"Point"}
}