{
  "type": "Feature",
  "properties": {
    "iso:country":"US",
    "sg:address":"1252 Fatima St",
    "sg:city":"Menasha",
    "sg:classifiers":[
        {
            "category":"Professional",
            "type":"Services"
        }
    ],
    "sg:phone":"+1 920 720 9124",
    "sg:postcode":"54952",
    "sg:province":"WI",
    "wof:name":"American Communications N",
    "wof:placetype":"venue"
},
  "geometry": {"coordinates":[-88.43481,44.227421],"type":"Point"}
}