{
  "type": "Feature",
  "properties": {
    "iso:country":"US",
    "sg:address":"604 Eagle Crest Ct",
    "sg:city":"Prairie Du Sac",
    "sg:classifiers":[
        {
            "category":"Manufacturing",
            "subcategory":"Textiles",
            "type":"Manufacturing & Wholesale Goods"
        },
        {
            "category":"Professional",
            "type":"Services"
        }
    ],
    "sg:phone":"+1 608 643 6899",
    "sg:postcode":"53578",
    "sg:province":"WI",
    "sg:tags":[
        "cotton"
    ],
    "wof:name":"Bauer Maintainance",
    "wof:placetype":"venue"
},
  "geometry": {"coordinates":[-89.730683,43.292127],"type":"Point"}
}