{
  "type": "Feature",
  "properties": {
    "addr:full":"4353 Galilee Rd Weyauwega WI 54983",
    "addr:housenumber":"4353",
    "addr:postcode":"54983",
    "addr:street":"Galilee Rd",
    "iso:country":"US",
    "sg:address":"4353 Galilee Rd",
    "sg:city":"Weyauwega",
    "sg:classifiers":[
        {
            "category":"Farming",
            "subcategory":"Dairy Farm",
            "type":"Manufacturing & Wholesale Goods"
        }
    ],
    "sg:phone":"+1 920 867 3915",
    "sg:postcode":"54983",
    "sg:province":"WI",
    "wof:name":"Stearn Farms",
    "wof:placetype":"venue"
},
  "geometry": {"coordinates":[-89.008854,44.313717],"type":"Point"}
}