{
  "type": "Feature",
  "properties": {
    "iso:country":"US",
    "sg:address":"880 Main St",
    "sg:city":"Baldwin",
    "sg:classifiers":[
        {
            "category":"Insurance",
            "subcategory":"Insurance Agent",
            "type":"Services"
        }
    ],
    "sg:phone":"+1 715 684 2400",
    "sg:postcode":"54002",
    "sg:province":"WI",
    "wof:name":"Baldwin Insurance",
    "wof:placetype":"venue"
},
  "geometry": {"coordinates":[-92.372896,44.966836],"type":"Point"}
}