{
  "type": "Feature",
  "properties": {
    "addr:full":"8086 N 76th St Milwaukee WI 53223",
    "addr:housenumber":"8086",
    "addr:postcode":"53223",
    "addr:street":"N 76Th St",
    "iso:country":"US",
    "sg:address":"8086 N 76th St",
    "sg:city":"Milwaukee",
    "sg:classifiers":[
        {
            "category":"Retail",
            "subcategory":"Auto Repair",
            "type":"Services"
        }
    ],
    "sg:phone":"+1 414 357 0900",
    "sg:postcode":"53223",
    "sg:province":"WI",
    "sg:tags":[
        "body",
        "automobile",
        "painting"
    ],
    "wof:name":"Russ Darrow Chrysler Jeep",
    "wof:placetype":"venue"
},
  "geometry": {"coordinates":[-88.004589,43.163525],"type":"Point"}
}