{
  "type": "Feature",
  "properties": {
    "iso:country":"US",
    "sg:address":"14 E Eau Claire St",
    "sg:city":"Rice Lake",
    "sg:classifiers":[
        {
            "category":"Government",
            "subcategory":"Post Office",
            "type":"Public Place"
        }
    ],
    "sg:phone":"+1 715 234 3555",
    "sg:postcode":"54868",
    "sg:province":"WI",
    "sg:tags":[
        "postal",
        "us"
    ],
    "sg:website":"www.usps.com",
    "wof:name":"US Post Office",
    "wof:placetype":"venue"
},
  "geometry": {"coordinates":[-91.732693,45.503415],"type":"Point"}
}