{
  "type": "Feature",
  "properties": {
    "iso:country":"US",
    "sg:address":"81 Bel-Aire Dr",
    "sg:city":"Madison",
    "sg:classifiers":[
        {
            "category":"Building & Trades",
            "subcategory":"Construction",
            "type":"Services"
        }
    ],
    "sg:phone":"+1 608 251 6320",
    "sg:postcode":"53713",
    "sg:province":"WI",
    "sg:tags":[
        "roofing",
        "contractor"
    ],
    "wof:name":"Quality Roofing",
    "wof:placetype":"venue"
},
  "geometry": {"coordinates":[-89.35747600000001,43.030424],"type":"Point"}
}