{
  "type": "Feature",
  "properties": {
    "iso:country":"US",
    "sg:address":"1406 Belknap St",
    "sg:city":"Superior",
    "sg:classifiers":[
        {
            "category":"Banks & Credit Unions",
            "subcategory":"Bank",
            "type":"Services"
        }
    ],
    "sg:phone":"+1 715 392 3399",
    "sg:postcode":"54880",
    "sg:province":"WI",
    "sg:tags":[
        "loan",
        "real estate"
    ],
    "wof:name":"Heritage Financial Svc",
    "wof:placetype":"venue"
},
  "geometry": {"coordinates":[-92.099378,46.720587],"type":"Point"}
}