{
  "type": "Feature",
  "properties": {
    "iso:country":"US",
    "sg:address":"5373 State Hwy 153",
    "sg:city":"Hatley",
    "sg:phone":"+1 715 446 3923",
    "sg:postcode":"54440",
    "sg:province":"WI",
    "sg:tags":[
        "beef",
        "farm",
        "corn",
        "crop",
        "field",
        "cattle",
        "feedlot"
    ],
    "wof:name":"Norman Ciszewski",
    "wof:placetype":"venue"
},
  "geometry": {"coordinates":[-89.444543,44.771633],"type":"Point"}
}