{
  "type": "Feature",
  "properties": {
    "iso:country":"US",
    "sg:address":"15465 W Howard Ave",
    "sg:city":"New Berlin",
    "sg:classifiers":[
        {
            "category":"Retail",
            "subcategory":"Laundry & Dry Cleaning",
            "type":"Services"
        }
    ],
    "sg:phone":"+1 262 814 0057",
    "sg:postcode":"53151",
    "sg:province":"WI",
    "sg:tags":[
        "cleaners"
    ],
    "wof:name":"Park Cleaners",
    "wof:placetype":"venue"
},
  "geometry": {"coordinates":[-88.094059,42.973431],"type":"Point"}
}