{
  "type": "Feature",
  "properties": {
    "addr:full":"10908 W Co Rd B Hayward WI 54843",
    "addr:housenumber":"10908",
    "addr:postcode":"54843",
    "addr:street":"W Co Rd",
    "iso:country":"US",
    "sg:address":"10908 W Co Rd B",
    "sg:city":"Hayward",
    "sg:classifiers":[
        {
            "category":"Autos & Motor Vehicles",
            "subcategory":"Boat Sales",
            "type":"Retail Goods"
        },
        {
            "category":"Home & Garden",
            "subcategory":"Garden Supply",
            "type":"Retail Goods"
        }
    ],
    "sg:phone":"+1 715 462 3124",
    "sg:postcode":"54843",
    "sg:province":"WI",
    "sg:tags":[
        "outboard"
    ],
    "wof:name":"Mel's Outdoor Power",
    "wof:placetype":"venue"
},
  "geometry": {"coordinates":[-91.21277000000001,45.982125],"type":"Point"}
}