{
  "type": "Feature",
  "properties": {
    "addr:full":"2500 W Wending Dr Milwaukee WI 53209",
    "addr:housenumber":"2500",
    "addr:postcode":"53209",
    "addr:street":"W Wending Dr",
    "iso:country":"US",
    "sg:address":"2500 W Wending Dr",
    "sg:city":"Milwaukee",
    "sg:classifiers":[
        {
            "category":"Professional",
            "subcategory":"Business Services",
            "type":"Services"
        }
    ],
    "sg:phone":"+1 414 352 2788",
    "sg:postcode":"53209",
    "sg:province":"WI",
    "wof:name":"Juhua Technology Liability",
    "wof:placetype":"venue"
},
  "geometry": {"coordinates":[-87.94382299999999,43.154852],"type":"Point"}
}