{
  "type": "Feature",
  "properties": {
    "addr:full":"104 W Wisconsin Ave Pewaukee WI 53072",
    "addr:housenumber":"104",
    "addr:postcode":"53072",
    "addr:street":"W Wisconsin Ave",
    "iso:country":"US",
    "sg:address":"104 W Wisconsin Ave",
    "sg:city":"Pewaukee",
    "sg:classifiers":[
        {
            "category":"Real Estate",
            "subcategory":"Real Estate Agent",
            "type":"Services"
        }
    ],
    "sg:phone":"+1 262 691 2700",
    "sg:postcode":"53072",
    "sg:province":"WI",
    "sg:website":"http://www.c21koepp.com",
    "wof:name":"Century 21-Koepp Realty",
    "wof:placetype":"venue"
},
  "geometry": {"coordinates":[-88.26283599999999,43.082384],"type":"Point"}
}