{
  "type": "Feature",
  "properties": {
    "iso:country":"US",
    "sg:address":"421 Lynn Ave",
    "sg:city":"Baraboo",
    "sg:classifiers":[
        {
            "category":"Professional",
            "type":"Services"
        }
    ],
    "sg:phone":"+1 608 393 8793",
    "sg:postcode":"53913",
    "sg:province":"WI",
    "wof:name":"Sporetec Environmental Service",
    "wof:placetype":"venue"
},
  "geometry": {"coordinates":[-89.749365,43.465084],"type":"Point"}
}