{
  "type": "Feature",
  "properties": {
    "iso:country":"US",
    "sg:address":"11070 Bellwood Dr",
    "sg:city":"Minocqua",
    "sg:classifiers":[
        {
            "category":"Real Estate",
            "subcategory":"Real Estate Operator",
            "type":"Services"
        }
    ],
    "sg:phone":"+1 715 356 6368",
    "sg:postcode":"54548",
    "sg:province":"WI",
    "sg:tags":[
        "mobile",
        "home",
        "site"
    ],
    "sg:website":"www.lakelandvillage.com",
    "wof:name":"Lakeland Village",
    "wof:placetype":"venue"
},
  "geometry": {"coordinates":[-89.808007,45.889185],"type":"Point"}
}