{
  "type": "Feature",
  "properties": {
    "addr:full":"18228 Co Rd R Denmark WI 54208",
    "addr:housenumber":"18228",
    "addr:postcode":"54208",
    "addr:street":"Co Rd",
    "iso:country":"US",
    "sg:address":"18228 Co Rd R",
    "sg:city":"Denmark",
    "sg:classifiers":[
        {
            "category":"Organizations",
            "subcategory":"Religious Organization",
            "type":"Services"
        }
    ],
    "sg:phone":"+1 920 863 2585",
    "sg:postcode":"54208",
    "sg:province":"WI",
    "sg:tags":[
        "church"
    ],
    "wof:name":"St James Church",
    "wof:placetype":"venue"
},
  "geometry": {"coordinates":[-87.77454899999999,44.312862],"type":"Point"}
}