{
  "type": "Feature",
  "properties": {
    "addr:full":"1221 Bellevue St Green Bay WI 54302",
    "addr:housenumber":"1221",
    "addr:postcode":"54302",
    "addr:street":"Bellevue St",
    "iso:country":"US",
    "sg:address":"1221 Bellevue St",
    "sg:city":"Green Bay",
    "sg:classifiers":[
        {
            "category":"Building & Trades",
            "subcategory":"Construction",
            "type":"Services"
        }
    ],
    "sg:phone":"+1 920 406 0849",
    "sg:postcode":"54302",
    "sg:province":"WI",
    "sg:tags":[
        "contractor"
    ],
    "wof:name":"Swan Corp On E",
    "wof:placetype":"venue"
},
  "geometry": {"coordinates":[-87.994821,44.487758],"type":"Point"}
}