{
  "type": "Feature",
  "properties": {
    "iso:country":"US",
    "sg:address":"5111 Deer Rd",
    "sg:city":"Hartford",
    "sg:classifiers":[
        {
            "category":"Farming",
            "subcategory":"Dairy Farm",
            "type":"Manufacturing & Wholesale Goods"
        }
    ],
    "sg:phone":"+1 262 644 9547",
    "sg:postcode":"53027",
    "sg:province":"WI",
    "wof:name":"Melvin Oelhafen",
    "wof:placetype":"venue"
},
  "geometry": {"coordinates":[-88.287244,43.383829],"type":"Point"}
}