{
  "type": "Feature",
  "properties": {
    "addr:full":"2963 Co Hwy C Weyerhaeuser WI 54868",
    "addr:housenumber":"2963",
    "addr:postcode":"54868",
    "addr:street":"Co Hwy C",
    "iso:country":"US",
    "sg:address":"2963 Co Hwy C",
    "sg:city":"Weyerhaeuser",
    "sg:classifiers":[
        {
            "category":"Building & Trades",
            "subcategory":"Plumbing",
            "type":"Services"
        }
    ],
    "sg:phone":"+1 715 353 2270",
    "sg:postcode":"54868",
    "sg:province":"WI",
    "sg:tags":[
        "contractor"
    ],
    "wof:name":"Zahorski Heating",
    "wof:placetype":"venue"
},
  "geometry": {"coordinates":[-91.54477199999999,45.493923],"type":"Point"}
}