{
  "type": "Feature",
  "properties": {
    "iso:country":"US",
    "sg:address":"8716 Spring Rd",
    "sg:city":"Hortonville",
    "sg:classifiers":[
        {
            "category":"Building & Trades",
            "subcategory":"Plumbing",
            "type":"Services"
        }
    ],
    "sg:phone":"+1 920 779 0351",
    "sg:postcode":"54944",
    "sg:province":"WI",
    "sg:tags":[
        "plumbing",
        "contractor"
    ],
    "wof:name":"Plaski Plumbing Inc",
    "wof:placetype":"venue"
},
  "geometry": {"coordinates":[-88.628497,44.301513],"type":"Point"}
}