{
  "type": "Feature",
  "properties": {
    "iso:country":"US",
    "sg:address":"785 Hawthorne Ln",
    "sg:city":"Hartford",
    "sg:classifiers":[
        {
            "category":"Professional",
            "type":"Services"
        }
    ],
    "sg:phone":"+1 262 670 0442",
    "sg:postcode":"53027",
    "sg:province":"WI",
    "wof:name":"Mr JS Music Machine",
    "wof:placetype":"venue"
},
  "geometry": {"coordinates":[-88.36071699999999,43.306094],"type":"Point"}
}