{
  "type": "Feature",
  "properties": {
    "iso:country":"US",
    "sg:address":"531 Columbus Ave",
    "sg:city":"Brillion",
    "sg:classifiers":[
        {
            "category":"Building & Trades",
            "subcategory":"Construction",
            "type":"Services"
        }
    ],
    "sg:phone":"+1 920 756 2635",
    "sg:postcode":"54110",
    "sg:province":"WI",
    "sg:tags":[
        "carpentry",
        "contractor"
    ],
    "wof:name":"Precision Trim & Woodwork",
    "wof:placetype":"venue"
},
  "geometry": {"coordinates":[-88.06744500000001,44.182257],"type":"Point"}
}