{
  "type": "Feature",
  "properties": {
    "iso:country":"US",
    "sg:address":"131 E 1st Ave",
    "sg:city":"Stanley",
    "sg:classifiers":[
        {
            "category":"Manufacturing",
            "subcategory":"Printing",
            "type":"Manufacturing & Wholesale Goods"
        }
    ],
    "sg:phone":"+1 715 644 3319",
    "sg:postcode":"54768",
    "sg:province":"WI",
    "sg:tags":[
        "newspaper",
        "publishing"
    ],
    "wof:name":"Stanley Republican",
    "wof:placetype":"venue"
},
  "geometry": {"coordinates":[-90.937197,44.959992],"type":"Point"}
}