{
  "type": "Feature",
  "properties": {
    "addr:full":"1451 Clay Banks Rd Sturgeon Bay WI 54235",
    "addr:housenumber":"1451",
    "addr:postcode":"54235",
    "addr:street":"Clay Banks Rd",
    "iso:country":"US",
    "sg:address":"1451 Clay Banks Rd",
    "sg:city":"Sturgeon Bay",
    "sg:classifiers":[
        {
            "category":"Building & Trades",
            "subcategory":"Construction",
            "type":"Services"
        }
    ],
    "sg:phone":"+1 920 743 5833",
    "sg:postcode":"54235",
    "sg:province":"WI",
    "sg:tags":[
        "excavation",
        "excavating",
        "contractor"
    ],
    "wof:name":"Soil Specialists Tld",
    "wof:placetype":"venue"
},
  "geometry": {"coordinates":[-87.363806,44.812237],"type":"Point"}
}