{
  "type": "Feature",
  "properties": {
    "iso:country":"US",
    "sg:address":"2042 9th St",
    "sg:city":"Green Bay",
    "sg:classifiers":[
        {
            "category":"Professional",
            "subcategory":"Business Services",
            "type":"Services"
        }
    ],
    "sg:phone":"+1 920 491 9090",
    "sg:postcode":"54304",
    "sg:province":"WI",
    "wof:name":"Geisheker Group Inc",
    "wof:placetype":"venue"
},
  "geometry": {"coordinates":[-88.08466300000001,44.519058],"type":"Point"}
}