{
  "type": "Feature",
  "properties": {
    "iso:country":"US",
    "sg:address":"320 S Main St",
    "sg:city":"Jefferson",
    "sg:classifiers":[
        {
            "category":"Recreation",
            "type":"Entertainment"
        }
    ],
    "sg:phone":"+1 920 674 7260",
    "sg:postcode":"53549",
    "sg:province":"WI",
    "sg:tags":[
        "parks"
    ],
    "wof:name":"Jefferson County Parks Dept",
    "wof:placetype":"venue"
},
  "geometry": {"coordinates":[-88.807267,43.003257],"type":"Point"}
}