{
  "type": "Feature",
  "properties": {
    "iso:country":"US",
    "sg:address":"816 E Dayton St",
    "sg:city":"Madison",
    "sg:classifiers":[
        {
            "category":"Professional",
            "type":"Services"
        }
    ],
    "sg:phone":"+1 608 257 4248",
    "sg:postcode":"53703",
    "sg:province":"WI",
    "wof:name":"Karens Creations",
    "wof:placetype":"venue"
},
  "geometry": {"coordinates":[-89.37559400000001,43.083659],"type":"Point"}
}