{
  "type": "Feature",
  "properties": {
    "iso:country":"US",
    "sg:address":"7525 Carstens Lake Rd",
    "sg:city":"Manitowoc",
    "sg:classifiers":[
        {
            "category":"Building & Trades",
            "subcategory":"Construction",
            "type":"Services"
        }
    ],
    "sg:phone":"+1 920 758 4755",
    "sg:postcode":"54220",
    "sg:province":"WI",
    "sg:tags":[
        "contractor"
    ],
    "wof:name":"Herzfeldt Contractors",
    "wof:placetype":"venue"
},
  "geometry": {"coordinates":[-87.75569900000001,44.022705],"type":"Point"}
}