{
  "type": "Feature",
  "properties": {
    "iso:country":"US",
    "sg:address":"442 Shervin Dr",
    "sg:city":"Burlington",
    "sg:classifiers":[
        {
            "category":"Building & Trades",
            "subcategory":"Plumbing",
            "type":"Services"
        }
    ],
    "sg:phone":"+1 262 514 3838",
    "sg:postcode":"53105",
    "sg:province":"WI",
    "sg:tags":[
        "contractor"
    ],
    "wof:name":"McCann Heating & Cooling",
    "wof:placetype":"venue"
},
  "geometry": {"coordinates":[-88.304262,42.718684],"type":"Point"}
}