{
  "type": "Feature",
  "properties": {
    "iso:country":"US",
    "sg:address":"1563 E Racine Ave",
    "sg:city":"Waukesha",
    "sg:classifiers":[
        {
            "category":"Personal",
            "type":"Services"
        }
    ],
    "sg:phone":"+1 262 524 2435",
    "sg:postcode":"53186",
    "sg:province":"WI",
    "wof:name":"Martina Schmidt",
    "wof:placetype":"venue"
},
  "geometry": {"coordinates":[-88.20305399999999,42.996909],"type":"Point"}
}