{
  "type": "Feature",
  "properties": {
    "iso:country":"US",
    "sg:address":"1302 Tower Ave",
    "sg:city":"Superior",
    "sg:classifiers":[
        {
            "category":"Professional",
            "subcategory":"Advertising",
            "type":"Services"
        }
    ],
    "sg:phone":"+1 715 394 3979",
    "sg:postcode":"54880",
    "sg:province":"WI",
    "sg:tags":[
        "counselor",
        "agency"
    ],
    "wof:name":"P S Advertising & Marketing",
    "wof:placetype":"venue"
},
  "geometry": {"coordinates":[-92.103848,46.721995],"type":"Point"}
}