{
  "type": "Feature",
  "properties": {
    "iso:country":"US",
    "sg:address":"470 N Oak Crest Dr",
    "sg:city":"Wales",
    "sg:classifiers":[
        {
            "category":"Social Services",
            "subcategory":"Child Care",
            "type":"Services"
        }
    ],
    "sg:phone":"+1 262 968 2194",
    "sg:postcode":"53183",
    "sg:province":"WI",
    "sg:tags":[
        "kindergarten",
        "academic",
        "school"
    ],
    "wof:name":"Bethlehem Lutheran Chr Preschl",
    "wof:placetype":"venue"
},
  "geometry": {"coordinates":[-88.377314,43.012812],"type":"Point"}
}