{
  "type": "Feature",
  "properties": {
    "iso:country":"US",
    "sg:address":"11563 Back Bay Rd",
    "sg:city":"Minocqua",
    "sg:classifiers":[
        {
            "category":"Health Services",
            "subcategory":"Doctor",
            "type":"Services"
        }
    ],
    "sg:phone":"+1 715 356 8207",
    "sg:postcode":"54548",
    "sg:province":"WI",
    "sg:tags":[
        "medical"
    ],
    "wof:name":"Dawn Baker MD",
    "wof:placetype":"venue"
},
  "geometry": {"coordinates":[-89.840023,45.895835],"type":"Point"}
}