{
  "type": "Feature",
  "properties": {
    "iso:country":"US",
    "sg:address":"1603 Monroe St",
    "sg:city":"Madison",
    "sg:classifiers":[
        {
            "category":"Health Services",
            "subcategory":"Doctor",
            "type":"Services"
        }
    ],
    "sg:phone":"+1 608 257 2626",
    "sg:postcode":"53711",
    "sg:province":"WI",
    "wof:name":"K R Sachtgen DDS",
    "wof:placetype":"venue"
},
  "geometry": {"coordinates":[-89.413769,43.067065],"type":"Point"}
}