{
  "type": "Feature",
  "properties": {
    "iso:country":"US",
    "sg:address":"11601 W Brown Deer Rd",
    "sg:city":"Milwaukee",
    "sg:classifiers":[
        {
            "category":"Professional",
            "subcategory":"Computer Services",
            "type":"Services"
        }
    ],
    "sg:phone":"+1 414 355 1000",
    "sg:postcode":"53224",
    "sg:province":"WI",
    "sg:tags":[
        "repair",
        "consulting"
    ],
    "wof:name":"Tom Slapo LLC",
    "wof:placetype":"venue"
},
  "geometry": {"coordinates":[-88.057139,43.177042],"type":"Point"}
}