{
  "type": "Feature",
  "properties": {
    "iso:country":"US",
    "sg:address":"716 Co Rd B",
    "sg:city":"Scandinavia",
    "sg:classifiers":[
        {
            "category":"Farming",
            "subcategory":"Livestock Farm",
            "type":"Manufacturing & Wholesale Goods"
        }
    ],
    "sg:phone":"+1 715 467 2224",
    "sg:postcode":"54977",
    "sg:province":"WI",
    "sg:tags":[
        "feedlot",
        "field",
        "crop",
        "beef",
        "cattle"
    ],
    "wof:name":"Charles & Mary Barden",
    "wof:placetype":"venue"
},
  "geometry": {"coordinates":[-89.14546199999999,44.464523],"type":"Point"}
}