{
  "type": "Feature",
  "properties": {
    "iso:country":"US",
    "sg:address":"839 62nd St",
    "sg:city":"Kenosha",
    "sg:classifiers":[
        {
            "category":"Education",
            "subcategory":"School",
            "type":"Public Place"
        }
    ],
    "sg:phone":"+1 262 653 6307",
    "sg:postcode":"53143",
    "sg:province":"WI",
    "wof:name":"Durkee Elementary School",
    "wof:placetype":"venue"
},
  "geometry": {"coordinates":[-87.82076000000001,42.578671],"type":"Point"}
}