{
  "type": "Feature",
  "properties": {
    "iso:country":"US",
    "sg:address":"544 Acme St",
    "sg:city":"Green Bay",
    "sg:classifiers":[
        {
            "category":"Wholesale",
            "subcategory":"Meat",
            "type":"Manufacturing & Wholesale Goods"
        }
    ],
    "sg:phone":"+1 920 437 6330",
    "sg:postcode":"54302",
    "sg:province":"WI",
    "sg:tags":[
        "packer"
    ],
    "wof:name":"Dakota Pork Industries",
    "wof:placetype":"venue"
},
  "geometry": {"coordinates":[-87.980554,44.511984],"type":"Point"}
}