{
  "type": "Feature",
  "properties": {
    "iso:country":"US",
    "sg:address":"7736 State Hwy 70 E",
    "sg:city":"Saint Germain",
    "sg:classifiers":[
        {
            "category":"Building & Trades",
            "subcategory":"Landscaping Services",
            "type":"Services"
        }
    ],
    "sg:phone":"+1 715 479 8733",
    "sg:postcode":"54558",
    "sg:province":"WI",
    "wof:name":"Lumber Jacks Service",
    "wof:placetype":"venue"
},
  "geometry": {"coordinates":[-89.459722,45.898493],"type":"Point"}
}