{
  "type": "Feature",
  "properties": {
    "iso:country":"US",
    "sg:address":"123 E State St",
    "sg:city":"Mauston",
    "sg:classifiers":[
        {
            "category":"Shopping",
            "subcategory":"Pharmacy",
            "type":"Retail Goods"
        }
    ],
    "sg:phone":"+1 608 847 5949",
    "sg:postcode":"53948",
    "sg:province":"WI",
    "sg:website":"www.phillipsrx.com",
    "wof:name":"Phillips Pharmacies",
    "wof:placetype":"venue"
},
  "geometry": {"coordinates":[-90.07568999999999,43.79692],"type":"Point"}
}