{
  "type": "Feature",
  "properties": {
    "iso:country":"US",
    "sg:address":"3146 Mercier Rd",
    "sg:city":"New Franken",
    "sg:classifiers":[
        {
            "category":"Retail",
            "subcategory":"Auto Repair",
            "type":"Services"
        }
    ],
    "sg:phone":"+1 920 866 3337",
    "sg:postcode":"54229",
    "sg:province":"WI",
    "sg:tags":[
        "repairing",
        "automobile"
    ],
    "wof:name":"Neighborhood Auto & Repair",
    "wof:placetype":"venue"
},
  "geometry": {"coordinates":[-87.805514,44.554802],"type":"Point"}
}