{
  "type": "Feature",
  "properties": {
    "addr:full":"4799 90th St Chippewa Falls WI 54729",
    "addr:housenumber":"4799",
    "addr:postcode":"54729",
    "addr:street":"90Th St",
    "iso:country":"US",
    "sg:address":"4799 90th St",
    "sg:city":"Chippewa Falls",
    "sg:classifiers":[
        {
            "category":"Manufacturing",
            "subcategory":"Tools & Machinery",
            "type":"Manufacturing & Wholesale Goods"
        }
    ],
    "sg:phone":"+1 715 723 9234",
    "sg:postcode":"54729",
    "sg:province":"WI",
    "sg:tags":[
        "machine",
        "shop",
        "job"
    ],
    "wof:name":"Chippewa Stnless Stl Wldg Fabg",
    "wof:placetype":"venue"
},
  "geometry": {"coordinates":[-91.488924,44.912422],"type":"Point"}
}