{
  "type": "Feature",
  "properties": {
    "iso:country":"US",
    "sg:address":"6728 Parkedge Cir",
    "sg:city":"Franklin",
    "sg:classifiers":[
        {
            "category":"Professional",
            "type":"Services"
        }
    ],
    "sg:phone":"+1 414 525 4545",
    "sg:postcode":"53132",
    "sg:province":"WI",
    "sg:tags":[
        "establishment"
    ],
    "wof:name":"Jbu",
    "wof:placetype":"venue"
},
  "geometry": {"coordinates":[-88.040818,42.924574],"type":"Point"}
}