{
  "type": "Feature",
  "properties": {
    "addr:full":"6520 Canary Ln Allenton WI 53002",
    "addr:housenumber":"6520",
    "addr:postcode":"53002",
    "addr:street":"Canary Ln",
    "iso:country":"US",
    "sg:address":"6520 Canary Ln",
    "sg:city":"Allenton",
    "sg:classifiers":[
        {
            "category":"Building & Trades",
            "subcategory":"Construction",
            "type":"Services"
        }
    ],
    "sg:phone":"+1 262 629 1148",
    "sg:postcode":"53002",
    "sg:province":"WI",
    "sg:tags":[
        "carpentry",
        "contractor"
    ],
    "wof:name":"Wood Worker",
    "wof:placetype":"venue"
},
  "geometry": {"coordinates":[-88.36494,43.493311],"type":"Point"}
}