{
  "type": "Feature",
  "properties": {
    "iso:country":"US",
    "sg:address":"6536 Scenic View Dr",
    "sg:city":"Glenbeulah",
    "sg:classifiers":[
        {
            "category":"Building & Trades",
            "subcategory":"Electrical",
            "type":"Services"
        }
    ],
    "sg:phone":"+1 920 526 3223",
    "sg:postcode":"53023",
    "sg:province":"WI",
    "sg:tags":[
        "electric",
        "contractor"
    ],
    "wof:name":"Hau Electric",
    "wof:placetype":"venue"
},
  "geometry": {"coordinates":[-88.11104,43.784589],"type":"Point"}
}