{
  "type": "Feature",
  "properties": {
    "iso:country":"US",
    "sg:address":"801 W Fond du Lac St",
    "sg:city":"Ripon",
    "sg:classifiers":[
        {
            "category":"Home & Garden",
            "subcategory":"Building Materials",
            "type":"Retail Goods"
        },
        {
            "category":"Building & Trades",
            "subcategory":"Construction",
            "type":"Services"
        }
    ],
    "sg:phone":"+1 920 748 3149",
    "sg:postcode":"54971",
    "sg:province":"WI",
    "sg:tags":[
        "glass",
        "window",
        "contractor",
        "plate"
    ],
    "wof:name":"Jackson Glass Ripon Inc",
    "wof:placetype":"venue"
},
  "geometry": {"coordinates":[-88.853148,43.850981],"type":"Point"}
}