{
  "type": "Feature",
  "properties": {
    "iso:country":"US",
    "sg:address":"103 E Green Bay St",
    "sg:city":"Bonduel",
    "sg:classifiers":[
        {
            "category":"Insurance",
            "subcategory":"Insurance Agent",
            "type":"Services"
        }
    ],
    "sg:phone":"+1 715 758 2159",
    "sg:postcode":"54107",
    "sg:province":"WI",
    "wof:name":"State Farm Insurance",
    "wof:placetype":"venue"
},
  "geometry": {"coordinates":[-88.44606400000001,44.739764],"type":"Point"}
}