{
  "type": "Feature",
  "properties": {
    "iso:country":"US",
    "sg:address":"561 Co Rd M",
    "sg:city":"River Falls",
    "sg:classifiers":[
        {
            "category":"Professional",
            "subcategory":"Business Services",
            "type":"Services"
        }
    ],
    "sg:phone":"+1 715 426 9670",
    "sg:postcode":"54022",
    "sg:province":"WI",
    "wof:name":"Xponential Technology LLC",
    "wof:placetype":"venue"
},
  "geometry": {"coordinates":[-92.69820300000001,44.862541],"type":"Point"}
}