{
  "type": "Feature",
  "properties": {
    "addr:full":"524 Water St Sauk City WI 53583",
    "addr:housenumber":"524",
    "addr:postcode":"53583",
    "addr:street":"Water St",
    "iso:country":"US",
    "sg:address":"524 Water St",
    "sg:city":"Sauk City",
    "sg:classifiers":[
        {
            "category":"Manufacturing",
            "subcategory":"Lumber",
            "type":"Manufacturing & Wholesale Goods"
        }
    ],
    "sg:phone":"+1 608 643 4140",
    "sg:postcode":"53583",
    "sg:province":"WI",
    "sg:tags":[
        "forester"
    ],
    "wof:name":"Oakwood Forestry Consulting",
    "wof:placetype":"venue"
},
  "geometry": {"coordinates":[-89.72000199999999,43.290181],"type":"Point"}
}