{
  "type": "Feature",
  "properties": {
    "addr:full":"4943 Hickory Ct Elkhorn WI 53121",
    "addr:housenumber":"4943",
    "addr:postcode":"53121",
    "addr:street":"Hickory Ct",
    "iso:country":"US",
    "sg:address":"4943 Hickory Ct",
    "sg:city":"Elkhorn",
    "sg:classifiers":[
        {
            "category":"Building & Trades",
            "subcategory":"Electrical",
            "type":"Services"
        }
    ],
    "sg:phone":"+1 262 723 5587",
    "sg:postcode":"53121",
    "sg:province":"WI",
    "sg:tags":[
        "electrical",
        "electric",
        "contractor"
    ],
    "wof:name":"Schoultz Electric Inc",
    "wof:placetype":"venue"
},
  "geometry": {"coordinates":[-88.543521,42.638644],"type":"Point"}
}