{
  "type": "Feature",
  "properties": {
    "addr:full":"506 Flambeau St Minocqua WI 54548",
    "addr:housenumber":"506",
    "addr:postcode":"54548",
    "addr:street":"Flambeau St",
    "iso:country":"US",
    "sg:address":"506 Flambeau St",
    "sg:city":"Minocqua",
    "sg:classifiers":[
        {
            "category":"Personal",
            "subcategory":"Barber",
            "type":"Services"
        }
    ],
    "sg:phone":"+1 715 356 7020",
    "sg:postcode":"54548",
    "sg:province":"WI",
    "wof:name":"Mane Design",
    "wof:placetype":"venue"
},
  "geometry": {"coordinates":[-89.711365,45.870992],"type":"Point"}
}