{
  "type": "Feature",
  "properties": {
    "iso:country":"US",
    "sg:address":"3767 E Underwood Ave",
    "sg:city":"Cudahy",
    "sg:classifiers":[
        {
            "category":"Organizations",
            "subcategory":"Religious Organization",
            "type":"Services"
        }
    ],
    "sg:phone":"+1 414 744 6892",
    "sg:postcode":"53110",
    "sg:province":"WI",
    "sg:tags":[
        "church"
    ],
    "wof:name":"Holy Family Congregation",
    "wof:placetype":"venue"
},
  "geometry": {"coordinates":[-87.85638400000001,42.950036],"type":"Point"}
}