{
  "type": "Feature",
  "properties": {
    "addr:full":"747 Cleveland St Neenah WI 54956",
    "addr:housenumber":"747",
    "addr:postcode":"54956",
    "addr:street":"Cleveland St",
    "iso:country":"US",
    "sg:address":"747 Cleveland St",
    "sg:city":"Neenah",
    "sg:classifiers":[
        {
            "category":"Building & Trades",
            "subcategory":"Electrical",
            "type":"Services"
        }
    ],
    "sg:phone":"+1 920 751 8978",
    "sg:postcode":"54956",
    "sg:province":"WI",
    "sg:tags":[
        "electrical",
        "contractor"
    ],
    "wof:name":"Premier Cabling Inc",
    "wof:placetype":"venue"
},
  "geometry": {"coordinates":[-88.477576,44.174725],"type":"Point"}
}