{
  "type": "Feature",
  "properties": {
    "iso:country":"US",
    "sg:address":"3301 Roche Rd",
    "sg:city":"Columbus",
    "sg:classifiers":[
        {
            "category":"Professional",
            "type":"Services"
        }
    ],
    "sg:phone":"+1 920 623 4339",
    "sg:postcode":"53925",
    "sg:province":"WI",
    "wof:name":"Amy S Roche",
    "wof:placetype":"venue"
},
  "geometry": {"coordinates":[-88.927666,43.315107],"type":"Point"}
}