{
  "type": "Feature",
  "properties": {
    "iso:country":"US",
    "sg:address":"720 Pilgrim Trl",
    "sg:city":"Sun Prairie",
    "sg:classifiers":[
        {
            "category":"Building & Trades",
            "subcategory":"Construction",
            "type":"Services"
        }
    ],
    "sg:phone":"+1 608 825 9227",
    "sg:postcode":"53590",
    "sg:province":"WI",
    "sg:tags":[
        "nonresidential"
    ],
    "sg:website":"www.bigdinos.com",
    "wof:name":"Building Components",
    "wof:placetype":"venue"
},
  "geometry": {"coordinates":[-89.193431,43.189453],"type":"Point"}
}