{
  "type": "Feature",
  "properties": {
    "iso:country":"US",
    "sg:address":"3824 Millwood Dr",
    "sg:city":"Appleton",
    "sg:classifiers":[
        {
            "category":"Real Estate",
            "subcategory":"Real Estate Agent",
            "type":"Services"
        }
    ],
    "sg:phone":"+1 920 830 8814",
    "sg:postcode":"54913",
    "sg:province":"WI",
    "wof:name":"Kriewaldt & Assoc",
    "wof:placetype":"venue"
},
  "geometry": {"coordinates":[-88.396411,44.29981],"type":"Point"}
}