{
  "type": "Feature",
  "properties": {
    "iso:country":"US",
    "sg:address":"2749 N 69th St",
    "sg:city":"Milwaukee",
    "sg:classifiers":[
        {
            "category":"Arts & Performance",
            "subcategory":"Theater",
            "type":"Entertainment"
        }
    ],
    "sg:phone":"+1 414 774 2202",
    "sg:postcode":"53210",
    "sg:province":"WI",
    "sg:tags":[
        "band",
        "orchestra"
    ],
    "wof:name":"Gerard Entertainment Group",
    "wof:placetype":"venue"
},
  "geometry": {"coordinates":[-87.998627,43.07103],"type":"Point"}
}