{
  "type": "Feature",
  "properties": {
    "addr:full":"5341 W Woolworth Ave Milwaukee WI 53218",
    "addr:housenumber":"5341",
    "addr:postcode":"53218",
    "addr:street":"W Woolworth Ave",
    "iso:country":"US",
    "sg:address":"5341 W Woolworth Ave",
    "sg:city":"Milwaukee",
    "sg:classifiers":[
        {
            "category":"Shopping",
            "subcategory":"Shoes",
            "type":"Retail Goods"
        }
    ],
    "sg:phone":"+1 414 353 4768",
    "sg:postcode":"53218",
    "sg:province":"WI",
    "wof:name":"Foot Locker",
    "wof:placetype":"venue"
},
  "geometry": {"coordinates":[-87.981521,43.133013],"type":"Point"}
}