{
  "type": "Feature",
  "properties": {
    "addr:full":"631 E Hadley St Milwaukee WI 53212",
    "addr:housenumber":"631",
    "addr:postcode":"53212",
    "addr:street":"E Hadley St",
    "iso:country":"US",
    "sg:address":"631 E Hadley St",
    "sg:city":"Milwaukee",
    "sg:classifiers":[
        {
            "category":"Shopping",
            "subcategory":"Florist",
            "type":"Retail Goods"
        }
    ],
    "sg:phone":"+1 414 263 2393",
    "sg:postcode":"53212",
    "sg:province":"WI",
    "wof:name":"Purple Flower Films Inc",
    "wof:placetype":"venue"
},
  "geometry": {"coordinates":[-87.90312299999999,43.069238],"type":"Point"}
}