{
  "type": "Feature",
  "properties": {
    "iso:country":"US",
    "sg:address":"9140 N Green Bay Rd",
    "sg:city":"Milwaukee",
    "sg:classifiers":[
        {
            "category":"Shopping",
            "subcategory":"Department Store",
            "type":"Retail Goods"
        }
    ],
    "sg:phone":"+1 414 354 4775",
    "sg:postcode":"53209",
    "sg:province":"WI",
    "wof:name":"Marshalls",
    "wof:placetype":"venue"
},
  "geometry": {"coordinates":[-87.964242,43.185232],"type":"Point"}
}