{
  "type": "Feature",
  "properties": {
    "iso:country":"US",
    "sg:address":"222 N Adams St",
    "sg:city":"Green Bay",
    "sg:classifiers":[
        {
            "category":"Shopping",
            "subcategory":"Shoes",
            "type":"Retail Goods"
        }
    ],
    "sg:phone":"+1 920 432 3640",
    "sg:postcode":"54301",
    "sg:province":"WI",
    "wof:name":"Lou s Bootery Inc",
    "wof:placetype":"venue"
},
  "geometry": {"coordinates":[-88.013408,44.515489],"type":"Point"}
}