{
  "type": "Feature",
  "properties": {
    "iso:country":"US",
    "sg:address":"7110 Co Rd C",
    "sg:city":"Fort Atkinson",
    "sg:classifiers":[
        {
            "category":"Building & Trades",
            "subcategory":"Landscaping Services",
            "type":"Services"
        }
    ],
    "sg:phone":"+1 920 563 6970",
    "sg:postcode":"53538",
    "sg:province":"WI",
    "wof:name":"Kochs D&P Lawn Care LLC",
    "wof:placetype":"venue"
},
  "geometry": {"coordinates":[-88.888312,42.947706],"type":"Point"}
}