{
  "type": "Feature",
  "properties": {
    "iso:country":"US",
    "sg:address":"148 Maple St",
    "sg:city":"Rhinelander",
    "sg:classifiers":[
        {
            "category":"Local Transit",
            "type":"Transportation"
        }
    ],
    "sg:phone":"+1 715 362 1277",
    "sg:postcode":"54501",
    "sg:province":"WI",
    "sg:tags":[
        "bus",
        "line"
    ],
    "wof:name":"Lucky Seven's Shuttle",
    "wof:placetype":"venue"
},
  "geometry": {"coordinates":[-89.424297,45.639208],"type":"Point"}
}