{
  "type": "Feature",
  "properties": {
    "iso:country":"US",
    "sg:address":"1324 E Fremont St",
    "sg:city":"Appleton",
    "sg:classifiers":[
        {
            "category":"Personal",
            "subcategory":"Beauty Salon",
            "type":"Services"
        }
    ],
    "sg:phone":"+1 920 731 6587",
    "sg:postcode":"54915",
    "sg:province":"WI",
    "sg:tags":[
        "shop"
    ],
    "wof:name":"Rose Garden Salon",
    "wof:placetype":"venue"
},
  "geometry": {"coordinates":[-88.387381,44.249978],"type":"Point"}
}