{
  "type": "Feature",
  "properties": {
    "iso:country":"US",
    "sg:address":"4404 Rib Mountain Dr",
    "sg:city":"Wausau",
    "sg:classifiers":[
        {
            "category":"Wholesale",
            "subcategory":"Machinery & Supplies",
            "type":"Manufacturing & Wholesale Goods"
        }
    ],
    "sg:phone":"+1 715 355 1670",
    "sg:postcode":"54401",
    "sg:province":"WI",
    "sg:tags":[
        "shop",
        "equipment",
        "barber",
        "beauty"
    ],
    "wof:name":"Aerial Company Inc",
    "wof:placetype":"venue"
},
  "geometry": {"coordinates":[-89.650487,44.918778],"type":"Point"}
}