{
  "type": "Feature",
  "properties": {
    "iso:country":"US",
    "sg:address":"824 Sylvan St",
    "sg:city":"Cumberland",
    "sg:classifiers":[
        {
            "category":"Real Estate",
            "subcategory":"Real Estate Agent",
            "type":"Services"
        }
    ],
    "sg:phone":"+1 715 822 2877",
    "sg:postcode":"54829",
    "sg:province":"WI",
    "wof:name":"Joco Inc",
    "wof:placetype":"venue"
},
  "geometry": {"coordinates":[-92.013406,45.547679],"type":"Point"}
}