{
  "type": "Feature",
  "properties": {
    "addr:full":"9634 Holly Rd St Cloud WI 53079",
    "addr:housenumber":"9634",
    "addr:postcode":"53079",
    "addr:street":"Holly Rd",
    "iso:country":"US",
    "sg:address":"9634 Holly Rd",
    "sg:city":"St Cloud",
    "sg:classifiers":[
        {
            "category":"Building & Trades",
            "subcategory":"Construction",
            "type":"Services"
        }
    ],
    "sg:phone":"+1 920 898 4154",
    "sg:postcode":"53079",
    "sg:province":"WI",
    "sg:tags":[
        "excavation",
        "excavating",
        "contractor"
    ],
    "wof:name":"Halbach Excavating",
    "wof:placetype":"venue"
},
  "geometry": {"coordinates":[-88.219084,43.884089],"type":"Point"}
}