{
  "type": "Feature",
  "properties": {
    "iso:country":"US",
    "sg:address":"8495 Yellowstone Dr",
    "sg:city":"Marshfield",
    "sg:classifiers":[
        {
            "category":"Building & Trades",
            "subcategory":"Construction",
            "type":"Services"
        }
    ],
    "sg:phone":"+1 715 384 2608",
    "sg:postcode":"54449",
    "sg:province":"WI",
    "sg:tags":[
        "concrete",
        "contractor"
    ],
    "wof:name":"Gust Construction Inc",
    "wof:placetype":"venue"
},
  "geometry": {"coordinates":[-90.133115,44.640817],"type":"Point"}
}