{
  "type": "Feature",
  "properties": {
    "iso:country":"US",
    "sg:address":"6613 County Line Rd",
    "sg:city":"Elkhart Lake",
    "sg:classifiers":[
        {
            "category":"Building & Trades",
            "subcategory":"Construction",
            "type":"Services"
        }
    ],
    "sg:phone":"+1 920 894 4351",
    "sg:postcode":"53020",
    "sg:province":"WI",
    "sg:tags":[
        "carpentry",
        "contractor"
    ],
    "wof:name":"Charles Carpentry LLC",
    "wof:placetype":"venue"
},
  "geometry": {"coordinates":[-88.027496,43.891771],"type":"Point"}
}