{
  "type": "Feature",
  "properties": {
    "iso:country":"US",
    "sg:address":"2103 E Kenwood Blvd",
    "sg:city":"Milwaukee",
    "sg:classifiers":[
        {
            "category":"Real Estate",
            "subcategory":"Real Estate Operator",
            "type":"Services"
        }
    ],
    "sg:phone":"+1 414 962 5964",
    "sg:postcode":"53211",
    "sg:province":"WI",
    "sg:tags":[
        "building",
        "apartment"
    ],
    "wof:name":"Castle The",
    "wof:placetype":"venue"
},
  "geometry": {"coordinates":[-87.882924,43.074567],"type":"Point"}
}