{
  "type": "Feature",
  "properties": {
    "iso:country":"US",
    "sg:address":"10442 W Fisher Pkwy",
    "sg:city":"Wauwatosa",
    "sg:classifiers":[
        {
            "category":"Freight",
            "type":"Transportation"
        }
    ],
    "sg:phone":"+1 414 774 3646",
    "sg:postcode":"53226",
    "sg:province":"WI",
    "sg:tags":[
        "consultant",
        "trucking"
    ],
    "wof:name":"Specialized Truck Svc Inc",
    "wof:placetype":"venue"
},
  "geometry": {"coordinates":[-88.043702,43.057734],"type":"Point"}
}