{
  "type": "Feature",
  "properties": {
    "addr:full":"300 N Mall Dr Appleton WI 54913",
    "addr:housenumber":"300",
    "addr:postcode":"54913",
    "addr:street":"N Mall Dr",
    "iso:country":"US",
    "sg:address":"300 N Mall Dr",
    "sg:city":"Appleton",
    "sg:classifiers":[
        {
            "category":"Travel",
            "subcategory":"Hotels & Motels",
            "type":"Entertainment"
        }
    ],
    "sg:phone":"+1 920 993 1200",
    "sg:postcode":"54913",
    "sg:province":"WI",
    "sg:tags":[
        "operation"
    ],
    "wof:name":"Wingate Inn",
    "wof:placetype":"venue"
},
  "geometry": {"coordinates":[-88.47052600000001,44.263632],"type":"Point"}
}