{
  "type": "Feature",
  "properties": {
    "iso:country":"US",
    "sg:address":"37720 US Hwy 18",
    "sg:city":"Prairie Du Chien",
    "sg:classifiers":[
        {
            "category":"Autos & Motor Vehicles",
            "subcategory":"Auto Supplies",
            "type":"Retail Goods"
        }
    ],
    "sg:phone":"+1 608 326 4766",
    "sg:postcode":"53821",
    "sg:province":"WI",
    "wof:name":"D & J Toppers & Truck ACC",
    "wof:placetype":"venue"
},
  "geometry": {"coordinates":[-91.124216,43.026129],"type":"Point"}
}