{
  "type": "Feature",
  "properties": {
    "addr:full":"5350 N Richmond St Appleton WI 54913",
    "addr:housenumber":"5350",
    "addr:postcode":"54913",
    "addr:street":"N Richmond St",
    "iso:country":"US",
    "sg:address":"5350 N Richmond St",
    "sg:city":"Appleton",
    "sg:classifiers":[
        {
            "category":"Wholesale",
            "subcategory":"Hardware",
            "type":"Manufacturing & Wholesale Goods"
        }
    ],
    "sg:phone":"+1 920 731 3252",
    "sg:postcode":"54913",
    "sg:province":"WI",
    "sg:tags":[
        "water",
        "work",
        "system"
    ],
    "wof:name":"Davies Wtr Eqp Wisconsin Inc",
    "wof:placetype":"venue"
},
  "geometry": {"coordinates":[-88.414704,44.317878],"type":"Point"}
}