{
  "type": "Feature",
  "properties": {
    "iso:country":"US",
    "sg:address":"11414 Spruce Rd",
    "sg:city":"Woodruff",
    "sg:classifiers":[
        {
            "category":"Banks & Credit Unions",
            "subcategory":"Financial Services",
            "type":"Services"
        }
    ],
    "sg:phone":"+1 715 356 3157",
    "sg:postcode":"54568",
    "sg:province":"WI",
    "sg:tags":[
        "trust",
        "management"
    ],
    "wof:name":"Griswold Family Trust",
    "wof:placetype":"venue"
},
  "geometry": {"coordinates":[-89.716909,45.968076],"type":"Point"}
}