{
  "type": "Feature",
  "properties": {
    "iso:country":"US",
    "sg:address":"5226 Monument Point Rd",
    "sg:city":"Egg Harbor",
    "sg:classifiers":[
        {
            "category":"Farming",
            "subcategory":"Dairy Farm",
            "type":"Manufacturing & Wholesale Goods"
        }
    ],
    "sg:phone":"+1 920 743 4671",
    "sg:postcode":"54209",
    "sg:province":"WI",
    "wof:name":"Kuehn Acres Farm",
    "wof:placetype":"venue"
},
  "geometry": {"coordinates":[-87.317865,44.96607],"type":"Point"}
}