{
  "type": "Feature",
  "properties": {
    "iso:country":"US",
    "sg:address":"1593 S Moorland Rd",
    "sg:city":"New Berlin",
    "sg:classifiers":[
        {
            "category":"Banks & Credit Unions",
            "subcategory":"Investment Brokerage",
            "type":"Services"
        }
    ],
    "sg:phone":"+1 262 821 1887",
    "sg:postcode":"53151",
    "sg:province":"WI",
    "sg:tags":[
        "security"
    ],
    "wof:name":"Janacek Investments Inc",
    "wof:placetype":"venue"
},
  "geometry": {"coordinates":[-88.107345,43.015697],"type":"Point"}
}