{
  "type": "Feature",
  "properties": {
    "iso:country":"US",
    "sg:address":"329 102nd St",
    "sg:city":"Pleasant Prairie",
    "sg:classifiers":[
        {
            "category":"Building & Trades",
            "subcategory":"Electrical",
            "type":"Services"
        }
    ],
    "sg:phone":"+1 262 697 4419",
    "sg:postcode":"53158",
    "sg:province":"WI",
    "sg:tags":[
        "electrical",
        "contractor"
    ],
    "wof:name":"Comfort Security",
    "wof:placetype":"venue"
},
  "geometry": {"coordinates":[-87.815595,42.523521],"type":"Point"}
}