{
  "type": "Feature",
  "properties": {
    "iso:country":"US",
    "sg:address":"316 W Redwood St",
    "sg:city":"Edgar",
    "sg:classifiers":[
        {
            "category":"Wholesale",
            "subcategory":"Farm Supplies",
            "type":"Manufacturing & Wholesale Goods"
        }
    ],
    "sg:phone":"+1 715 443 2241",
    "sg:postcode":"54426",
    "sg:province":"WI",
    "wof:name":"Customer One",
    "wof:placetype":"venue"
},
  "geometry": {"coordinates":[-89.96709199999999,44.921501],"type":"Point"}
}