{
  "type": "Feature",
  "properties": {
    "iso:country":"US",
    "sg:address":"4313 N 71st St",
    "sg:city":"Milwaukee",
    "sg:classifiers":[
        {
            "category":"Social Services",
            "subcategory":"Job Training",
            "type":"Services"
        }
    ],
    "sg:phone":"+1 414 364 8997",
    "sg:postcode":"53216",
    "sg:province":"WI",
    "sg:tags":[
        "career",
        "counseling",
        "vocational"
    ],
    "wof:name":"Helping Hands Career Dev Inc",
    "wof:placetype":"venue"
},
  "geometry": {"coordinates":[-88.000748,43.097017],"type":"Point"}
}