{
  "type": "Feature",
  "properties": {
    "iso:country":"US",
    "sg:address":"6520 Monona Dr",
    "sg:city":"Madison",
    "sg:classifiers":[
        {
            "category":"Restaurant",
            "type":"Food & Drink"
        }
    ],
    "sg:menulink":"http://www.allmenus.com/wi/monona/104754-noodles--company/menu/",
    "sg:phone":"+1 608 226 9500",
    "sg:postcode":"53716",
    "sg:province":"WI",
    "sg:tags":[
        "noodle",
        "bar",
        "salad",
        "chinese",
        "japanese",
        "soup",
        "american",
        "asian",
        "thai",
        "italian"
    ],
    "wof:name":"Noodles & Company",
    "wof:placetype":"venue"
},
  "geometry": {"coordinates":[-89.324434,43.046834],"type":"Point"}
}