{
  "type": "Feature",
  "properties": {
    "addr:full":"302 S Pine St Grantsburg WI 54840",
    "addr:housenumber":"302",
    "addr:postcode":"54840",
    "addr:street":"S Pine St",
    "iso:country":"US",
    "sg:address":"302 S Pine St",
    "sg:city":"Grantsburg",
    "sg:classifiers":[
        {
            "category":"Health Services",
            "subcategory":"Doctor",
            "type":"Services"
        }
    ],
    "sg:phone":"+1 715 463 2882",
    "sg:postcode":"54840",
    "sg:province":"WI",
    "sg:tags":[
        "dentist"
    ],
    "wof:name":"Kaefer Dental Clinic",
    "wof:placetype":"venue"
},
  "geometry": {"coordinates":[-92.681951,45.777509],"type":"Point"}
}