{
  "type": "Feature",
  "properties": {
    "iso:country":"US",
    "sg:address":"228 N Milwaukee St",
    "sg:city":"Waterford",
    "sg:classifiers":[
        {
            "category":"Insurance",
            "subcategory":"Insurance Agent",
            "type":"Services"
        }
    ],
    "sg:phone":"+1 262 514 4840",
    "sg:postcode":"53185",
    "sg:province":"WI",
    "wof:name":"Allstate Insurance",
    "wof:placetype":"venue"
},
  "geometry": {"coordinates":[-88.209395,42.76581],"type":"Point"}
}