{
  "type": "Feature",
  "properties": {
    "iso:country":"US",
    "sg:address":"2085 Co Hwy G",
    "sg:city":"East Troy",
    "sg:classifiers":[
        {
            "category":"Airport",
            "type":"Transportation"
        }
    ],
    "sg:phone":"+1 262 642 5008",
    "sg:postcode":"53120",
    "sg:province":"WI",
    "sg:tags":[
        "aircraft",
        "maintenance"
    ],
    "wof:name":"Over Land Aviation",
    "wof:placetype":"venue"
},
  "geometry": {"coordinates":[-88.40503099999999,42.784992],"type":"Point"}
}