{
  "type": "Feature",
  "properties": {
    "addr:full":"2905 S Wentworth Ave Milwaukee WI 53207",
    "addr:housenumber":"2905",
    "addr:postcode":"53207",
    "addr:street":"S Wentworth Ave",
    "iso:country":"US",
    "sg:address":"2905 S Wentworth Ave",
    "sg:city":"Milwaukee",
    "sg:classifiers":[
        {
            "category":"Building & Trades",
            "subcategory":"Construction",
            "type":"Services"
        }
    ],
    "sg:phone":"+1 414 483 9336",
    "sg:postcode":"53207",
    "sg:province":"WI",
    "sg:tags":[
        "house",
        "general",
        "contractor"
    ],
    "wof:name":"Timber Builders LLC",
    "wof:placetype":"venue"
},
  "geometry": {"coordinates":[-87.880197,42.990689],"type":"Point"}
}