{
  "type": "Feature",
  "properties": {
    "addr:full":"2434 State Rd La Crosse WI 54601",
    "addr:housenumber":"2434",
    "addr:postcode":"54601",
    "addr:street":"State Rd",
    "iso:country":"US",
    "sg:address":"2434 State Rd",
    "sg:city":"La Crosse",
    "sg:classifiers":[
        {
            "category":"Shopping",
            "subcategory":"Discount & Variety Stores",
            "type":"Retail Goods"
        }
    ],
    "sg:phone":"+1 608 787 0232",
    "sg:postcode":"54601",
    "sg:province":"WI",
    "wof:name":"Village Dollar Store",
    "wof:placetype":"venue"
},
  "geometry": {"coordinates":[-91.217558,43.795662],"type":"Point"}
}