{
  "type": "Feature",
  "properties": {
    "iso:country":"US",
    "sg:address":"8367 N 107th St",
    "sg:city":"Milwaukee",
    "sg:classifiers":[
        {
            "category":"Freight",
            "type":"Transportation"
        }
    ],
    "sg:phone":"+1 414 357 7327",
    "sg:postcode":"53224",
    "sg:province":"WI",
    "sg:tags":[
        "trucking"
    ],
    "wof:name":"Dawes Transport Inc",
    "wof:placetype":"venue"
},
  "geometry": {"coordinates":[-88.044393,43.170008],"type":"Point"}
}