{
  "type": "Feature",
  "properties": {
    "iso:country":"US",
    "sg:address":"2577 N Downer Ave",
    "sg:city":"Milwaukee",
    "sg:classifiers":[
        {
            "category":"Health Services",
            "subcategory":"Clinic",
            "type":"Services"
        },
        {
            "category":"Health Services",
            "subcategory":"Doctor",
            "type":"Services"
        }
    ],
    "sg:phone":"+1 414 964 9201",
    "sg:postcode":"53211",
    "sg:province":"WI",
    "sg:tags":[
        "physician",
        "surgeon",
        "specialty",
        "outpatient"
    ],
    "wof:name":"Mary Alice Houghton Dr",
    "wof:placetype":"venue"
},
  "geometry": {"coordinates":[-87.878164,43.065514],"type":"Point"}
}