{
  "type": "Feature",
  "properties": {
    "iso:country":"US",
    "sg:address":"3522 Evan Acres Rd",
    "sg:city":"Madison",
    "sg:classifiers":[
        {
            "category":"Real Estate",
            "subcategory":"Real Estate Operator",
            "type":"Services"
        }
    ],
    "sg:phone":"+1 608 224 2138",
    "sg:postcode":"53718",
    "sg:province":"WI",
    "sg:tags":[
        "building",
        "apartment"
    ],
    "wof:name":"Lincoln Borgrud",
    "wof:placetype":"venue"
},
  "geometry": {"coordinates":[-89.272228,43.040954],"type":"Point"}
}