{
  "type": "Feature",
  "properties": {
    "iso:country":"US",
    "sg:address":"10936 N Port Washington Rd",
    "sg:city":"Thiensville",
    "sg:classifiers":[
        {
            "category":"Banks & Credit Unions",
            "subcategory":"Financial Services",
            "type":"Services"
        }
    ],
    "sg:phone":"+1 262 243 9243",
    "sg:postcode":"53092",
    "sg:province":"WI",
    "sg:tags":[
        "company",
        "investment",
        "holding"
    ],
    "wof:name":"Chowning 2 Ltd",
    "wof:placetype":"venue"
},
  "geometry": {"coordinates":[-87.92392599999999,43.215237],"type":"Point"}
}