{
  "type": "Feature",
  "properties": {
    "iso:country":"US",
    "sg:address":"150 Jefferson Pl",
    "sg:city":"Kimberly",
    "sg:classifiers":[
        {
            "category":"Wholesale",
            "subcategory":"Groceries",
            "type":"Manufacturing & Wholesale Goods"
        }
    ],
    "sg:phone":"+1 920 687 1963",
    "sg:postcode":"54136",
    "sg:province":"WI",
    "wof:name":"Watkins Products",
    "wof:placetype":"venue"
},
  "geometry": {"coordinates":[-88.323277,44.270926],"type":"Point"}
}