{
  "type": "Feature",
  "properties": {
    "addr:full":"8064 State Hwy 57 Baileys Harbor WI 54202",
    "addr:housenumber":"8064",
    "addr:postcode":"54202",
    "addr:street":"State Hwy 57",
    "iso:country":"US",
    "sg:address":"8064 State Hwy 57",
    "sg:city":"Baileys Harbor",
    "sg:classifiers":[
        {
            "category":"Shopping",
            "subcategory":"Clothing, Apparel, & Fashions",
            "type":"Retail Goods"
        }
    ],
    "sg:phone":"+1 920 839 2600",
    "sg:postcode":"54202",
    "sg:province":"WI",
    "wof:name":"Hjertehjem",
    "wof:placetype":"venue"
},
  "geometry": {"coordinates":[-87.123614,45.063776],"type":"Point"}
}