{
  "type": "Feature",
  "properties": {
    "addr:full":"10945 N Port Washington Rd Mequon WI 53092",
    "addr:housenumber":"10945",
    "addr:postcode":"53092",
    "addr:street":"N Port Washington Rd",
    "iso:country":"US",
    "sg:address":"10945 N Port Washington Rd",
    "sg:city":"Mequon",
    "sg:classifiers":[
        {
            "category":"Health Services",
            "subcategory":"Doctor",
            "type":"Services"
        }
    ],
    "sg:phone":"+1 262 240 0300",
    "sg:postcode":"53092",
    "sg:province":"WI",
    "sg:tags":[
        "dentist"
    ],
    "wof:name":"Wisconsin Orthodontic Spec",
    "wof:placetype":"venue"
},
  "geometry": {"coordinates":[-87.92407799999999,43.213854],"type":"Point"}
}