{
  "type": "Feature",
  "properties": {
    "addr:full":"301 de Witt St Portage WI 53901",
    "addr:housenumber":"301",
    "addr:postcode":"53901",
    "addr:street":"De Witt St",
    "iso:country":"US",
    "sg:address":"301 de Witt St",
    "sg:city":"Portage",
    "sg:classifiers":[
        {
            "category":"Real Estate",
            "subcategory":"Architect",
            "type":"Services"
        }
    ],
    "sg:phone":"+1 608 742 9995",
    "sg:postcode":"53901",
    "sg:province":"WI",
    "sg:tags":[
        "home",
        "planning",
        "design"
    ],
    "wof:name":"Design Solutions",
    "wof:placetype":"venue"
},
  "geometry": {"coordinates":[-89.46020799999999,43.54065],"type":"Point"}
}