{
  "type": "Feature",
  "properties": {
    "iso:country":"US",
    "sg:address":"910 Velp Ave",
    "sg:city":"Green Bay",
    "sg:classifiers":[
        {
            "category":"Recreation",
            "subcategory":"Arcade",
            "type":"Entertainment"
        }
    ],
    "sg:phone":"+1 920 497 7272",
    "sg:postcode":"54303",
    "sg:province":"WI",
    "sg:tags":[
        "operated",
        "machine",
        "coin",
        "amusement"
    ],
    "wof:name":"Mellen Sales & Service",
    "wof:placetype":"venue"
},
  "geometry": {"coordinates":[-88.025364,44.528967],"type":"Point"}
}