{
  "type": "Feature",
  "properties": {
    "iso:country":"US",
    "sg:address":"901 N 57th St",
    "sg:city":"Wausau",
    "sg:classifiers":[
        {
            "category":"Food & Beverages",
            "subcategory":"Specialty",
            "type":"Retail Goods"
        },
        {
            "category":"Manufacturing",
            "subcategory":"Lumber",
            "type":"Manufacturing & Wholesale Goods"
        }
    ],
    "sg:phone":"+1 715 848 2420",
    "sg:postcode":"54403",
    "sg:province":"WI",
    "sg:tags":[
        "ginseng",
        "business"
    ],
    "wof:name":"Sing Hing Lung Wisconsin Inc",
    "wof:placetype":"venue"
},
  "geometry": {"coordinates":[-89.552996,44.961734],"type":"Point"}
}