{
  "type": "Feature",
  "properties": {
    "iso:country":"US",
    "sg:address":"16489 State Hwy 13",
    "sg:city":"Dorchester",
    "sg:classifiers":[
        {
            "category":"Professional",
            "subcategory":"Business Services",
            "type":"Services"
        }
    ],
    "sg:phone":"+1 715 654 5946",
    "sg:postcode":"54425",
    "sg:province":"WI",
    "sg:website":"www.seubertinc.com",
    "wof:name":"Seubert Inc",
    "wof:placetype":"venue"
},
  "geometry": {"coordinates":[-90.315331,45.01381],"type":"Point"}
}