{
  "type": "Feature",
  "properties": {
    "addr:full":"2646 S Kinnickinnic Ave Milwaukee WI 53207",
    "addr:housenumber":"2646",
    "addr:postcode":"53207",
    "addr:street":"S Kinnickinnic Ave",
    "iso:country":"US",
    "sg:address":"2646 S Kinnickinnic Ave",
    "sg:city":"Milwaukee",
    "sg:classifiers":[
        {
            "category":"Professional",
            "subcategory":"Business Services",
            "type":"Services"
        }
    ],
    "sg:phone":"+1 414 744 0220",
    "sg:postcode":"53207",
    "sg:province":"WI",
    "wof:name":"Graphic Sign Co",
    "wof:placetype":"venue"
},
  "geometry": {"coordinates":[-87.898011,42.996776],"type":"Point"}
}