{
  "type": "Feature",
  "properties": {
    "addr:full":"795 N Jefferson St Milwaukee WI 53202",
    "addr:housenumber":"795",
    "addr:postcode":"53202",
    "addr:street":"N Jefferson St",
    "iso:country":"US",
    "sg:address":"795 N Jefferson St",
    "sg:city":"Milwaukee",
    "sg:classifiers":[
        {
            "category":"Bars & Pubs",
            "type":"Food & Drink"
        },
        {
            "category":"Bars & Pubs",
            "subcategory":"Nightclub",
            "type":"Food & Drink"
        },
        {
            "category":"Bars & Pubs",
            "subcategory":"Lounge",
            "type":"Food & Drink"
        }
    ],
    "sg:phone":"+1 414 271 2855",
    "sg:postcode":"53202",
    "sg:province":"WI",
    "sg:tags":[
        "club",
        "cocktail",
        "night"
    ],
    "sg:website":"http://www.taylorsmilwaukee.com",
    "wof:name":"Taylor's",
    "wof:placetype":"venue"
},
  "geometry": {"coordinates":[-87.905506,43.041186],"type":"Point"}
}