{
  "type": "Feature",
  "properties": {
    "iso:country":"US",
    "sg:address":"1401 Lime Kiln Rd",
    "sg:city":"Green Bay",
    "sg:classifiers":[
        {
            "category":"Retail",
            "subcategory":"Repair Shop",
            "type":"Services"
        }
    ],
    "sg:phone":"+1 920 469 8980",
    "sg:postcode":"54311",
    "sg:province":"WI",
    "wof:name":"Kummels Locksmiths",
    "wof:placetype":"venue"
},
  "geometry": {"coordinates":[-87.982524,44.474613],"type":"Point"}
}