{
  "type": "Feature",
  "properties": {
    "iso:country":"US",
    "sg:address":"1806 E Main St",
    "sg:city":"Merrill",
    "sg:classifiers":[
        {
            "category":"Shopping",
            "subcategory":"Used Merchandise",
            "type":"Retail Goods"
        }
    ],
    "sg:phone":"+1 715 536 7258",
    "sg:postcode":"54452",
    "sg:province":"WI",
    "wof:name":"Grannys Antiques",
    "wof:placetype":"venue"
},
  "geometry": {"coordinates":[-89.675123,45.180818],"type":"Point"}
}