{
  "type": "Feature",
  "properties": {
    "addr:full":"6694 Dogtail Rd Potosi WI 53820",
    "addr:housenumber":"6694",
    "addr:postcode":"53820",
    "addr:street":"Dogtail Rd",
    "iso:country":"US",
    "sg:address":"6694 Dogtail Rd",
    "sg:city":"Potosi",
    "sg:phone":"+1 608 763 2808",
    "sg:postcode":"53820",
    "sg:province":"WI",
    "sg:tags":[
        "farm",
        "field",
        "corn",
        "crop"
    ],
    "wof:name":"Kenneth Timmerman",
    "wof:placetype":"venue"
},
  "geometry": {"coordinates":[-90.749881,42.67656],"type":"Point"}
}