{
  "type": "Feature",
  "properties": {
    "iso:country":"US",
    "sg:address":"2528 15th St",
    "sg:city":"Rice Lake",
    "sg:classifiers":[
        {
            "category":"Professional",
            "type":"Services"
        }
    ],
    "sg:phone":"+1 715 234 3994",
    "sg:postcode":"54868",
    "sg:province":"WI",
    "wof:name":"Walter Kolba",
    "wof:placetype":"venue"
},
  "geometry": {"coordinates":[-91.847494,45.577831],"type":"Point"}
}