{
  "type": "Feature",
  "properties": {
    "iso:country":"US",
    "sg:address":"1601 Alexander Ct",
    "sg:city":"Sheboygan",
    "sg:classifiers":[
        {
            "category":"Building & Trades",
            "subcategory":"Construction",
            "type":"Services"
        }
    ],
    "sg:phone":"+1 920 451 7161",
    "sg:postcode":"53081",
    "sg:province":"WI",
    "sg:tags":[
        "hanging",
        "contractor"
    ],
    "wof:name":"Exterior Dimensions",
    "wof:placetype":"venue"
},
  "geometry": {"coordinates":[-87.726912,43.76596],"type":"Point"}
}