{
  "type": "Feature",
  "properties": {
    "iso:country":"US",
    "sg:address":"1657 Pine Ln",
    "sg:city":"Waupaca",
    "sg:classifiers":[
        {
            "category":"Building & Trades",
            "subcategory":"Landscaping Services",
            "type":"Services"
        }
    ],
    "sg:phone":"+1 715 258 7977",
    "sg:postcode":"54981",
    "sg:province":"WI",
    "sg:tags":[
        "contractor"
    ],
    "wof:name":"Wolflake Landscaping",
    "wof:placetype":"venue"
},
  "geometry": {"coordinates":[-89.142371,44.24721],"type":"Point"}
}