{
  "type": "Feature",
  "properties": {
    "iso:country":"US",
    "sg:address":"387 Streamside Ct",
    "sg:city":"Grafton",
    "sg:classifiers":[
        {
            "category":"Freight",
            "type":"Transportation"
        }
    ],
    "sg:phone":"+1 262 376 9800",
    "sg:postcode":"53024",
    "sg:province":"WI",
    "sg:tags":[
        "mover",
        "moving"
    ],
    "sg:website":"www.mrmover.com",
    "wof:name":"Mr Mover Inc",
    "wof:placetype":"venue"
},
  "geometry": {"coordinates":[-87.961899,43.3382],"type":"Point"}
}