{
  "type": "Feature",
  "properties": {
    "iso:country":"US",
    "sg:address":"3505 S 76th St",
    "sg:city":"Milwaukee",
    "sg:classifiers":[
        {
            "category":"Autos & Motor Vehicles",
            "subcategory":"Automobile Sales",
            "type":"Retail Goods"
        }
    ],
    "sg:phone":"+1 414 546 0905",
    "sg:postcode":"53220",
    "sg:province":"WI",
    "sg:tags":[
        "used"
    ],
    "wof:name":"Economy Auto Mart Inc",
    "wof:placetype":"venue"
},
  "geometry": {"coordinates":[-88.007926,42.979284],"type":"Point"}
}