{
  "type": "Feature",
  "properties": {
    "addr:full":"17431 W Milbrant Rd Evansville WI 53536",
    "addr:housenumber":"17431",
    "addr:postcode":"53536",
    "addr:street":"W Milbrant Rd",
    "iso:country":"US",
    "sg:address":"17431 W Milbrant Rd",
    "sg:city":"Evansville",
    "sg:classifiers":[
        {
            "category":"Real Estate",
            "subcategory":"Real Estate Services",
            "type":"Services"
        },
        {
            "category":"Building & Trades",
            "subcategory":"Cleaning & Sanitation",
            "type":"Services"
        }
    ],
    "sg:phone":"+1 608 882 4203",
    "sg:postcode":"53536",
    "sg:province":"WI",
    "sg:tags":[
        "maintenance",
        "cleaners-interior"
    ],
    "wof:name":"Meg",
    "wof:placetype":"venue"
},
  "geometry": {"coordinates":[-89.352189,42.758349],"type":"Point"}
}