{
  "type": "Feature",
  "properties": {
    "iso:country":"US",
    "sg:address":"200 Eagle Bluff Ct",
    "sg:city":"Onalaska",
    "sg:classifiers":[
        {
            "category":"Education",
            "subcategory":"School",
            "type":"Public Place"
        }
    ],
    "sg:phone":"+1 608 783 2453",
    "sg:postcode":"54650",
    "sg:province":"WI",
    "wof:name":"Eagle Bluff Schools",
    "wof:placetype":"venue"
},
  "geometry": {"coordinates":[-91.198907,43.881201],"type":"Point"}
}