{
  "type": "Feature",
  "properties": {
    "iso:country":"US",
    "sg:address":"721 Park St",
    "sg:city":"Manitowoc",
    "sg:classifiers":[
        {
            "category":"Social Services",
            "type":"Services"
        }
    ],
    "sg:phone":"+1 920 682 2816",
    "sg:postcode":"54220",
    "sg:province":"WI",
    "wof:name":"Project Youth",
    "wof:placetype":"venue"
},
  "geometry": {"coordinates":[-87.657493,44.09875],"type":"Point"}
}