{
  "type": "Feature",
  "properties": {
    "iso:country":"US",
    "sg:address":"3865 S 76th St",
    "sg:city":"Milwaukee",
    "sg:classifiers":[
        {
            "category":"Autos & Motor Vehicles",
            "subcategory":"Fuel & Gas Station",
            "type":"Retail Goods"
        }
    ],
    "sg:phone":"+1 414 329 9115",
    "sg:postcode":"53220",
    "sg:province":"WI",
    "sg:tags":[
        "oil"
    ],
    "wof:name":"LAL Mobil Svc",
    "wof:placetype":"venue"
},
  "geometry": {"coordinates":[-88.00798399999999,42.976768],"type":"Point"}
}