{
  "type": "Feature",
  "properties": {
    "iso:country":"US",
    "sg:address":"1747 Shawano Ave",
    "sg:city":"Green Bay",
    "sg:classifiers":[
        {
            "category":"Health Services",
            "subcategory":"Doctor",
            "type":"Services"
        }
    ],
    "sg:phone":"+1 920 497 5716",
    "sg:postcode":"54303",
    "sg:province":"WI",
    "sg:tags":[
        "clinic"
    ],
    "sg:website":"www.foxriverhealthcenter.com",
    "wof:name":"Fox River Health Ctr",
    "wof:placetype":"venue"
},
  "geometry": {"coordinates":[-88.066592,44.532087],"type":"Point"}
}