{
  "type": "Feature",
  "properties": {
    "addr:full":"7898 Ski Slide Rd Oconomowoc WI 53066",
    "addr:postcode":"7898;53066",
    "addr:street":"Slide Rd",
    "iso:country":"US",
    "sg:address":"7898 Ski Slide Rd",
    "sg:city":"Oconomowoc",
    "sg:classifiers":[
        {
            "category":"Building & Trades",
            "subcategory":"Electrical",
            "type":"Services"
        }
    ],
    "sg:phone":"+1 262 569 7614",
    "sg:postcode":"53066",
    "sg:province":"WI",
    "sg:tags":[
        "installation"
    ],
    "wof:name":"M & M Designs",
    "wof:placetype":"venue"
},
  "geometry": {"coordinates":[-88.548765,43.129034],"type":"Point"}
}