{
  "type": "Feature",
  "properties": {
    "iso:country":"US",
    "sg:address":"1601 Lincoln St",
    "sg:city":"Wisconsin Rapids",
    "sg:classifiers":[
        {
            "category":"Banks & Credit Unions",
            "subcategory":"Bank",
            "type":"Services"
        }
    ],
    "sg:phone":"+1 715 422 1100",
    "sg:postcode":"54494",
    "sg:province":"WI",
    "sg:website":"www.rivercitiesbank.com",
    "wof:name":"River Cities Bank",
    "wof:placetype":"venue"
},
  "geometry": {"coordinates":[-89.822296,44.379072],"type":"Point"}
}