{
  "type": "Feature",
  "properties": {
    "iso:country":"US",
    "sg:address":"500 Walton Ave",
    "sg:city":"Racine",
    "sg:classifiers":[
        {
            "category":"Banks & Credit Unions",
            "subcategory":"Investment Brokerage",
            "type":"Services"
        }
    ],
    "sg:phone":"+1 262 637 7825",
    "sg:postcode":"53402",
    "sg:province":"WI",
    "sg:tags":[
        "security"
    ],
    "wof:name":"Mortgage Services",
    "wof:placetype":"venue"
},
  "geometry": {"coordinates":[-87.78710599999999,42.749558],"type":"Point"}
}