{
  "type": "Feature",
  "properties": {
    "iso:country":"US",
    "sg:address":"2062 930th Ave",
    "sg:city":"Boyceville",
    "sg:classifiers":[
        {
            "category":"Shopping",
            "type":"Retail Goods"
        }
    ],
    "sg:phone":"+1 715 643 7313",
    "sg:postcode":"54725",
    "sg:province":"WI",
    "sg:tags":[
        "merchandise",
        "animal"
    ],
    "wof:name":"Tealwood Kennel",
    "wof:placetype":"venue"
},
  "geometry": {"coordinates":[-92.058798,45.01704],"type":"Point"}
}