{
  "type": "Feature",
  "properties": {
    "addr:full":"3837 Cosgrove Dr Madison WI 53719",
    "addr:housenumber":"3837",
    "addr:postcode":"53719",
    "addr:street":"Cosgrove Dr",
    "iso:country":"US",
    "sg:address":"3837 Cosgrove Dr",
    "sg:city":"Madison",
    "sg:classifiers":[
        {
            "category":"Building & Trades",
            "subcategory":"Construction",
            "type":"Services"
        }
    ],
    "sg:phone":"+1 608 848 2737",
    "sg:postcode":"53719",
    "sg:province":"WI",
    "sg:tags":[
        "house",
        "builder",
        "operative",
        "res"
    ],
    "wof:name":"Cosgrove Construction Inc",
    "wof:placetype":"venue"
},
  "geometry": {"coordinates":[-89.489537,43.008507],"type":"Point"}
}