{
  "type": "Feature",
  "properties": {
    "addr:full":"123 N Main St Shawano WI 54166",
    "addr:housenumber":"123",
    "addr:postcode":"54166",
    "addr:street":"N Main St",
    "iso:country":"US",
    "sg:address":"123 N Main St",
    "sg:city":"Shawano",
    "sg:classifiers":[
        {
            "category":"Restaurant",
            "type":"Food & Drink"
        }
    ],
    "sg:phone":"+1 715 524 4916",
    "sg:postcode":"54166",
    "sg:province":"WI",
    "wof:name":"Main Street Diner",
    "wof:placetype":"venue"
},
  "geometry": {"coordinates":[-88.609482,44.782976],"type":"Point"}
}