{
  "type": "Feature",
  "properties": {
    "iso:country":"US",
    "sg:address":"366 W Grove St",
    "sg:city":"Alma Center",
    "sg:classifiers":[
        {
            "category":"Organizations",
            "subcategory":"Religious Organization",
            "type":"Services"
        }
    ],
    "sg:phone":"+1 715 964 2213",
    "sg:postcode":"54611",
    "sg:province":"WI",
    "sg:tags":[
        "church"
    ],
    "wof:name":"Village Christian Church",
    "wof:placetype":"venue"
},
  "geometry": {"coordinates":[-90.914985,44.435028],"type":"Point"}
}