{
  "type": "Feature",
  "properties": {
    "addr:full":"2146 E Johnson St Madison WI 53704",
    "addr:housenumber":"2146",
    "addr:postcode":"53704",
    "addr:street":"E Johnson St",
    "iso:country":"US",
    "sg:address":"2146 E Johnson St",
    "sg:city":"Madison",
    "sg:classifiers":[
        {
            "category":"Organizations",
            "subcategory":"Religious Organization",
            "type":"Services"
        }
    ],
    "sg:phone":"+1 608 242 8887",
    "sg:postcode":"53704",
    "sg:province":"WI",
    "wof:name":"James Reeb Unitarn Universlst",
    "wof:placetype":"venue"
},
  "geometry": {"coordinates":[-89.357876,43.097641],"type":"Point"}
}