{
  "type": "Feature",
  "properties": {
    "iso:country":"US",
    "sg:address":"7199 20th Ave",
    "sg:city":"Wild Rose",
    "sg:classifiers":[
        {
            "category":"Home & Garden",
            "subcategory":"Furniture",
            "type":"Retail Goods"
        }
    ],
    "sg:phone":"+1 715 256 9652",
    "sg:postcode":"54984",
    "sg:province":"WI",
    "sg:tags":[
        "equipment",
        "kitchen",
        "cabinet"
    ],
    "wof:name":"Kitchen Solvers",
    "wof:placetype":"venue"
},
  "geometry": {"coordinates":[-89.22910899999999,44.234113],"type":"Point"}
}