{
  "type": "Feature",
  "properties": {
    "iso:country":"US",
    "sg:address":"3415 N Richmond St",
    "sg:city":"Appleton",
    "sg:classifiers":[
        {
            "category":"Retail",
            "subcategory":"Car Wash",
            "type":"Services"
        }
    ],
    "sg:phone":"+1 920 731 1280",
    "sg:postcode":"54911",
    "sg:province":"WI",
    "sg:tags":[
        "polishing",
        "washing"
    ],
    "wof:name":"Washworld LLP",
    "wof:placetype":"venue"
},
  "geometry": {"coordinates":[-88.415616,44.295097],"type":"Point"}
}