{
  "type": "Feature",
  "properties": {
    "iso:country":"US",
    "sg:address":"410 Co Rd D",
    "sg:city":"Eau Galle",
    "sg:classifiers":[
        {
            "category":"Farming",
            "subcategory":"Dairy Farm",
            "type":"Manufacturing & Wholesale Goods"
        }
    ],
    "sg:phone":"+1 715 283 4339",
    "sg:postcode":"54737",
    "sg:province":"WI",
    "wof:name":"Val-O-Mo Farm",
    "wof:placetype":"venue"
},
  "geometry": {"coordinates":[-92.01445200000001,44.694741],"type":"Point"}
}