{
  "type": "Feature",
  "properties": {
    "iso:country":"US",
    "sg:address":"721 W Kemp St",
    "sg:city":"Rhinelander",
    "sg:classifiers":[
        {
            "category":"Restaurant",
            "type":"Food & Drink"
        }
    ],
    "sg:phone":"+1 715 362 2686",
    "sg:postcode":"54501",
    "sg:province":"WI",
    "sg:tags":[
        "eating"
    ],
    "wof:name":"Wolff's Log Cabin Restaurant",
    "wof:placetype":"venue"
},
  "geometry": {"coordinates":[-89.42297,45.63195],"type":"Point"}
}