{
  "type": "Feature",
  "properties": {
    "addr:full":"3500 N Newville Rd Janesville WI 53545",
    "addr:housenumber":"3500",
    "addr:postcode":"53545",
    "addr:street":"N Newville Rd",
    "iso:country":"US",
    "sg:address":"3500 N Newville Rd",
    "sg:city":"Janesville",
    "sg:classifiers":[
        {
            "category":"Professional",
            "subcategory":"Advertising",
            "type":"Services"
        },
        {
            "category":"Manufacturing",
            "subcategory":"Signs",
            "type":"Manufacturing & Wholesale Goods"
        }
    ],
    "sg:phone":"+1 608 743 0077",
    "sg:postcode":"53545",
    "sg:province":"WI",
    "sg:tags":[
        "specialty"
    ],
    "wof:name":"Rock Graphics & Signs Inc",
    "wof:placetype":"venue"
},
  "geometry": {"coordinates":[-89.013283,42.724918],"type":"Point"}
}