{
  "type": "Feature",
  "properties": {
    "iso:country":"US",
    "sg:address":"8551 S Chicago Rd",
    "sg:city":"Oak Creek",
    "sg:classifiers":[
        {
            "category":"Real Estate",
            "subcategory":"Real Estate Operator",
            "type":"Services"
        }
    ],
    "sg:phone":"+1 414 764 7244",
    "sg:postcode":"53154",
    "sg:province":"WI",
    "sg:tags":[
        "apartment"
    ],
    "wof:name":"Metropolitan Association",
    "wof:placetype":"venue"
},
  "geometry": {"coordinates":[-87.86274400000001,42.8913],"type":"Point"}
}