{
  "type": "Feature",
  "properties": {
    "iso:country":"US",
    "sg:address":"2204 N Hillcrest Pkwy",
    "sg:city":"Altoona",
    "sg:classifiers":[
        {
            "category":"Health Services",
            "subcategory":"Doctor",
            "type":"Services"
        }
    ],
    "sg:phone":"+1 715 834 8288",
    "sg:postcode":"54720",
    "sg:province":"WI",
    "sg:tags":[
        "clinic"
    ],
    "wof:name":"Altoona Family Chiropractic",
    "wof:placetype":"venue"
},
  "geometry": {"coordinates":[-91.447586,44.796781],"type":"Point"}
}