{
  "type": "Feature",
  "properties": {
    "iso:country":"US",
    "sg:address":"303 E Washington St",
    "sg:city":"Delavan",
    "sg:classifiers":[
        {
            "category":"Professional",
            "subcategory":"Detective & Security Services",
            "type":"Services"
        }
    ],
    "sg:phone":"+1 262 740 1445",
    "sg:postcode":"53115",
    "sg:province":"WI",
    "sg:tags":[
        "investigator"
    ],
    "wof:name":"K C Investigations",
    "wof:placetype":"venue"
},
  "geometry": {"coordinates":[-88.645277,42.631264],"type":"Point"}
}