{
  "type": "Feature",
  "properties": {
    "iso:country":"US",
    "sg:address":"1521 E Division Ave",
    "sg:city":"Barron",
    "sg:classifiers":[
        {
            "category":"Travel",
            "subcategory":"Hotels & Motels",
            "type":"Entertainment"
        }
    ],
    "sg:phone":"+1 715 637 3154",
    "sg:postcode":"54812",
    "sg:province":"WI",
    "sg:tags":[
        "operation"
    ],
    "wof:name":"Barron Motel and Rv Campground",
    "wof:placetype":"venue"
},
  "geometry": {"coordinates":[-91.834512,45.401343],"type":"Point"}
}