{
  "type": "Feature",
  "properties": {
    "iso:country":"US",
    "sg:address":"29 Amory St",
    "sg:city":"Fond Du Lac",
    "sg:classifiers":[
        {
            "category":"Building & Trades",
            "subcategory":"Electrical",
            "type":"Services"
        }
    ],
    "sg:phone":"+1 920 926 0559",
    "sg:postcode":"54935",
    "sg:province":"WI",
    "sg:tags":[
        "electric",
        "contractor"
    ],
    "wof:name":"Pat Schommer Electric",
    "wof:placetype":"venue"
},
  "geometry": {"coordinates":[-88.443395,43.780249],"type":"Point"}
}