{
  "type": "Feature",
  "properties": {
    "iso:country":"US",
    "sg:address":"19941 Co Hwy X",
    "sg:city":"Chippewa Falls",
    "sg:classifiers":[
        {
            "category":"Freight",
            "type":"Transportation"
        }
    ],
    "sg:phone":"+1 715 723 0043",
    "sg:postcode":"54729",
    "sg:province":"WI",
    "sg:tags":[
        "trucking"
    ],
    "wof:name":"Center Line Trucking LLC",
    "wof:placetype":"venue"
},
  "geometry": {"coordinates":[-91.26933,44.929576],"type":"Point"}
}