{
  "type": "Feature",
  "properties": {
    "iso:country":"US",
    "sg:address":"405 N Washington St",
    "sg:city":"Thorp",
    "sg:classifiers":[
        {
            "category":"Utilities",
            "subcategory":"Cable",
            "type":"Services"
        }
    ],
    "sg:phone":"+1 715 669 5304",
    "sg:postcode":"54771",
    "sg:province":"WI",
    "sg:tags":[
        "television"
    ],
    "wof:name":"Century Tel",
    "wof:placetype":"venue"
},
  "geometry": {"coordinates":[-90.80037,44.962739],"type":"Point"}
}