{
  "type": "Feature",
  "properties": {
    "iso:country":"US",
    "sg:address":"16572 W Company Lake Rd",
    "sg:city":"Hayward",
    "sg:classifiers":[
        {
            "category":"Manufacturing",
            "subcategory":"Paper Products",
            "type":"Manufacturing & Wholesale Goods"
        }
    ],
    "sg:phone":"+1 715 634 2901",
    "sg:postcode":"54843",
    "sg:province":"WI",
    "sg:tags":[
        "stationery"
    ],
    "wof:name":"Hometown Prints",
    "wof:placetype":"venue"
},
  "geometry": {"coordinates":[-91.529228,46.041257],"type":"Point"}
}