{
  "type": "Feature",
  "properties": {
    "addr:full":"706 E Lyon St Milwaukee WI 53202",
    "addr:housenumber":"706",
    "addr:postcode":"53202",
    "addr:street":"E Lyon St",
    "iso:country":"US",
    "sg:address":"706 E Lyon St",
    "sg:city":"Milwaukee",
    "sg:classifiers":[
        {
            "category":"Bars & Pubs",
            "type":"Food & Drink"
        }
    ],
    "sg:phone":"+1 414 347 9972",
    "sg:postcode":"53202",
    "sg:province":"WI",
    "wof:name":"Y-Not II",
    "wof:placetype":"venue"
},
  "geometry": {"coordinates":[-87.902254,43.049419],"type":"Point"}
}