{
  "type": "Feature",
  "properties": {
    "iso:country":"US",
    "sg:address":"1500 W National Ave",
    "sg:city":"Milwaukee",
    "sg:classifiers":[
        {
            "category":"Professional",
            "subcategory":"Advertising",
            "type":"Services"
        },
        {
            "category":"Professional",
            "subcategory":"Art Services",
            "type":"Services"
        },
        {
            "category":"Manufacturing",
            "subcategory":"Signs",
            "type":"Manufacturing & Wholesale Goods"
        }
    ],
    "sg:phone":"+1 414 383 0424",
    "sg:postcode":"53204",
    "sg:province":"WI",
    "sg:tags":[
        "designer",
        "specialty",
        "producer",
        "display"
    ],
    "sg:website":"http://www.avilesplastics.com",
    "wof:name":"A & A",
    "wof:placetype":"venue"
},
  "geometry": {"coordinates":[-87.93055,43.02314],"type":"Point"}
}