{
  "type": "Feature",
  "properties": {
    "iso:country":"US",
    "sg:address":"12277 US Hwy 61",
    "sg:city":"Soldiers Grove",
    "sg:classifiers":[
        {
            "category":"Autos & Motor Vehicles",
            "subcategory":"Fuel & Gas Station",
            "type":"Retail Goods"
        }
    ],
    "sg:phone":"+1 608 624 5710",
    "sg:postcode":"54655",
    "sg:province":"WI",
    "sg:tags":[
        "oil"
    ],
    "wof:name":"P & D Repair",
    "wof:placetype":"venue"
},
  "geometry": {"coordinates":[-90.767753,43.392742],"type":"Point"}
}