{
  "type": "Feature",
  "properties": {
    "addr:full":"6812 W Calumet Rd Milwaukee WI 53223",
    "addr:housenumber":"6812",
    "addr:postcode":"53223",
    "addr:street":"W Calumet Rd",
    "iso:country":"US",
    "sg:address":"6812 W Calumet Rd",
    "sg:city":"Milwaukee",
    "sg:classifiers":[
        {
            "category":"Communications",
            "subcategory":"Film & Video Production",
            "type":"Services"
        }
    ],
    "sg:phone":"+1 414 355 5114",
    "sg:postcode":"53223",
    "sg:province":"WI",
    "sg:tags":[
        "movie",
        "television",
        "produce",
        "commercial"
    ],
    "wof:name":"Pyramid Pictures Inc",
    "wof:placetype":"venue"
},
  "geometry": {"coordinates":[-88.000756,43.15611],"type":"Point"}
}