{
  "type": "Feature",
  "properties": {
    "iso:country":"US",
    "sg:address":"6300 W Douglas Ave",
    "sg:city":"Milwaukee",
    "sg:classifiers":[
        {
            "category":"Building & Trades",
            "subcategory":"Equipment Rental",
            "type":"Services"
        }
    ],
    "sg:phone":"+1 414 616 0194",
    "sg:postcode":"53218",
    "sg:province":"WI",
    "sg:tags":[
        "contractor"
    ],
    "wof:name":"Hertz Equipment Rental",
    "wof:placetype":"venue"
},
  "geometry": {"coordinates":[-87.98792400000001,43.129567],"type":"Point"}
}