{
  "type": "Feature",
  "properties": {
    "iso:country":"US",
    "sg:address":"102 N Main St",
    "sg:city":"Viroqua",
    "sg:classifiers":[
        {
            "category":"Travel",
            "subcategory":"Hotels & Motels",
            "type":"Entertainment"
        }
    ],
    "sg:phone":"+1 608 637 8466",
    "sg:postcode":"54665",
    "sg:province":"WI",
    "wof:name":"Fortney Residence Hotel",
    "wof:placetype":"venue"
},
  "geometry": {"coordinates":[-90.889388,43.557114],"type":"Point"}
}