{
  "type": "Feature",
  "properties": {
    "iso:country":"US",
    "sg:address":"2159 Brackett Ave",
    "sg:city":"Eau Claire",
    "sg:classifiers":[
        {
            "category":"Bars & Pubs",
            "type":"Food & Drink"
        }
    ],
    "sg:menulink":"http://www.allmenus.com/wi/eau-claire/293298-wagners-bar-n-grill/menu/",
    "sg:phone":"+1 715 833 6700",
    "sg:postcode":"54701",
    "sg:province":"WI",
    "wof:name":"Wagner's Bar-N-Grill",
    "wof:placetype":"venue"
},
  "geometry": {"coordinates":[-91.47058699999999,44.799963],"type":"Point"}
}