{
  "type": "Feature",
  "properties": {
    "iso:country":"US",
    "sg:address":"4622 E Washington Ave",
    "sg:city":"Madison",
    "sg:classifiers":[
        {
            "category":"Restaurant",
            "type":"Food & Drink"
        }
    ],
    "sg:phone":"+1 608 241 0902",
    "sg:postcode":"53704",
    "sg:province":"WI",
    "sg:tags":[
        "family"
    ],
    "wof:name":"Ponderosa Steakhouse",
    "wof:placetype":"venue"
},
  "geometry": {"coordinates":[-89.307253,43.128733],"type":"Point"}
}