{
  "type": "Feature",
  "properties": {
    "iso:country":"US",
    "sg:address":"1837 Co Rd Mm",
    "sg:city":"Oregon",
    "sg:classifiers":[
        {
            "category":"Building & Trades",
            "subcategory":"Plumbing",
            "type":"Services"
        }
    ],
    "sg:phone":"+1 608 835 7319",
    "sg:postcode":"53575",
    "sg:province":"WI",
    "sg:tags":[
        "d",
        "heating",
        "air",
        "ventilation",
        "warm",
        "conditioning"
    ],
    "wof:name":"Tarkenton Bros Htg & Shtmtl",
    "wof:placetype":"venue"
},
  "geometry": {"coordinates":[-89.376961,42.954015],"type":"Point"}
}