{
  "type": "Feature",
  "properties": {
    "iso:country":"US",
    "sg:address":"334 Main Ave",
    "sg:city":"De Pere",
    "sg:classifiers":[
        {
            "category":"Bars & Pubs",
            "type":"Food & Drink"
        }
    ],
    "sg:phone":"+1 920 336 5013",
    "sg:postcode":"54115",
    "sg:province":"WI",
    "sg:tags":[
        "drinking"
    ],
    "wof:name":"Saloon Long Branch",
    "wof:placetype":"venue"
},
  "geometry": {"coordinates":[-88.07003400000001,44.447572],"type":"Point"}
}