{
  "type": "Feature",
  "properties": {
    "iso:country":"US",
    "sg:address":"179 W Co Rd W",
    "sg:city":"Pewaukee",
    "sg:classifiers":[
        {
            "category":"Professional",
            "type":"Services"
        }
    ],
    "sg:phone":"+1 262 691 0200",
    "sg:postcode":"53057",
    "sg:province":"WI",
    "wof:name":"Piano Blu",
    "wof:placetype":"venue"
},
  "geometry": {"coordinates":[-88.432609,43.034065],"type":"Point"}
}