{
  "type": "Feature",
  "properties": {
    "addr:full":"431 E Evandale Dr Oak Creek WI 53154",
    "addr:housenumber":"431",
    "addr:postcode":"53154",
    "addr:street":"E Evandale Dr",
    "iso:country":"US",
    "sg:address":"431 E Evandale Dr",
    "sg:city":"Oak Creek",
    "sg:classifiers":[
        {
            "category":"Personal",
            "subcategory":"Beauty Salon",
            "type":"Services"
        }
    ],
    "sg:phone":"+1 414 762 4713",
    "sg:postcode":"53154",
    "sg:province":"WI",
    "sg:tags":[
        "shop"
    ],
    "wof:name":"Lloyd Salon Management Inc",
    "wof:placetype":"venue"
},
  "geometry": {"coordinates":[-87.904748,42.900302],"type":"Point"}
}