{
  "type": "Feature",
  "properties": {
    "addr:full":"7121 Lincoln Rd Pittsville WI 54466",
    "addr:housenumber":"7121",
    "addr:postcode":"54466",
    "addr:street":"Lincoln Rd",
    "iso:country":"US",
    "sg:address":"7121 Lincoln Rd",
    "sg:city":"Pittsville",
    "sg:classifiers":[
        {
            "category":"Farming",
            "subcategory":"Farm",
            "type":"Manufacturing & Wholesale Goods"
        }
    ],
    "sg:phone":"+1 715 884 2259",
    "sg:postcode":"54466",
    "sg:province":"WI",
    "wof:name":"Pleasant Valley Cranberry",
    "wof:placetype":"venue"
},
  "geometry": {"coordinates":[-90.071383,44.438791],"type":"Point"}
}