{
  "type": "Feature",
  "properties": {
    "iso:country":"US",
    "sg:address":"807 Allouez Ter",
    "sg:city":"Green Bay",
    "sg:classifiers":[
        {
            "category":"Insurance",
            "subcategory":"Insurance Agent",
            "type":"Services"
        }
    ],
    "sg:phone":"+1 920 435 1487",
    "sg:postcode":"54301",
    "sg:province":"WI",
    "wof:name":"Prudential Insurance Co",
    "wof:placetype":"venue"
},
  "geometry": {"coordinates":[-88.018721,44.49297],"type":"Point"}
}