{
  "type": "Feature",
  "properties": {
    "iso:country":"US",
    "sg:address":"3909 N Sherburn Pl",
    "sg:city":"Milwaukee",
    "sg:classifiers":[
        {
            "category":"Home & Garden",
            "subcategory":"Carpets & Floor Coverings",
            "type":"Retail Goods"
        }
    ],
    "sg:phone":"+1 414 325 8368",
    "sg:postcode":"53211",
    "sg:province":"WI",
    "wof:name":"Quailty Carpet Services",
    "wof:placetype":"venue"
},
  "geometry": {"coordinates":[-87.896075,43.08911],"type":"Point"}
}