{
  "type": "Feature",
  "properties": {
    "iso:country":"US",
    "sg:address":"3421 Gaynor Ave",
    "sg:city":"Wisconsin Rapids",
    "sg:classifiers":[
        {
            "category":"Retail",
            "subcategory":"Auto Repair",
            "type":"Services"
        }
    ],
    "sg:phone":"+1 715 423 7275",
    "sg:postcode":"54495",
    "sg:province":"WI",
    "sg:tags":[
        "body",
        "automobile",
        "painting"
    ],
    "wof:name":"J & D Auto Body",
    "wof:placetype":"venue"
},
  "geometry": {"coordinates":[-89.868152,44.380239],"type":"Point"}
}