{
  "type": "Feature",
  "properties": {
    "iso:country":"US",
    "sg:address":"220 Cottage Grove Rd",
    "sg:city":"Madison",
    "sg:classifiers":[
        {
            "category":"Retail",
            "subcategory":"Auto Repair",
            "type":"Services"
        }
    ],
    "sg:phone":"+1 608 221 1438",
    "sg:postcode":"53716",
    "sg:province":"WI",
    "sg:tags":[
        "repairing",
        "automobile"
    ],
    "wof:name":"Wayne's Automotive",
    "wof:placetype":"venue"
},
  "geometry": {"coordinates":[-89.321874,43.083804],"type":"Point"}
}