{
  "type": "Feature",
  "properties": {
    "addr:full":"200 S Church St Berlin WI 54923",
    "addr:housenumber":"200",
    "addr:postcode":"54923",
    "addr:street":"S Church St",
    "iso:country":"US",
    "sg:address":"200 S Church St",
    "sg:city":"Berlin",
    "sg:classifiers":[
        {
            "category":"Organizations",
            "subcategory":"Religious Organization",
            "type":"Services"
        }
    ],
    "sg:phone":"+1 920 361 3758",
    "sg:postcode":"54923",
    "sg:province":"WI",
    "sg:tags":[
        "clergy"
    ],
    "wof:name":"Faith Community Church",
    "wof:placetype":"venue"
},
  "geometry": {"coordinates":[-88.94163399999999,43.965488],"type":"Point"}
}