{
  "type": "Feature",
  "properties": {
    "iso:country":"US",
    "sg:address":"1861 Northport Dr",
    "sg:city":"Madison",
    "sg:classifiers":[
        {
            "category":"Insurance",
            "subcategory":"Insurance Agent",
            "type":"Services"
        }
    ],
    "sg:phone":"+1 608 661 5700",
    "sg:postcode":"53704",
    "sg:province":"WI",
    "wof:name":"State Farm Insurance",
    "wof:placetype":"venue"
},
  "geometry": {"coordinates":[-89.361694,43.130234],"type":"Point"}
}