{
  "type": "Feature",
  "properties": {
    "iso:country":"US",
    "sg:address":"110 W 5th Ave",
    "sg:city":"Shell Lake",
    "sg:classifiers":[
        {
            "category":"Government",
            "subcategory":"Post Office",
            "type":"Public Place"
        }
    ],
    "sg:phone":"+1 715 468 2111",
    "sg:postcode":"54871",
    "sg:province":"WI",
    "wof:name":"US Post Office",
    "wof:placetype":"venue"
},
  "geometry": {"coordinates":[-91.927252,45.742968],"type":"Point"}
}