{
  "type": "Feature",
  "properties": {
    "iso:country":"US",
    "sg:address":"270 E Marquette St",
    "sg:city":"Berlin",
    "sg:classifiers":[
        {
            "category":"Health Services",
            "subcategory":"Clinic",
            "type":"Services"
        }
    ],
    "sg:phone":"+1 920 361 5727",
    "sg:postcode":"54923",
    "sg:province":"WI",
    "wof:name":"Womens Health Resource Center",
    "wof:placetype":"venue"
},
  "geometry": {"coordinates":[-88.94072799999999,43.973847],"type":"Point"}
}