{
  "type": "Feature",
  "properties": {
    "iso:country":"US",
    "sg:address":"30810 State Rd 27",
    "sg:city":"Holcombe",
    "sg:classifiers":[
        {
            "category":"Building & Trades",
            "subcategory":"Construction",
            "type":"Services"
        }
    ],
    "sg:phone":"+1 715 595 4160",
    "sg:postcode":"54745",
    "sg:province":"WI",
    "sg:tags":[
        "riding",
        "housing",
        "stable"
    ],
    "wof:name":"Blue Ox Riding Stables",
    "wof:placetype":"venue"
},
  "geometry": {"coordinates":[-91.110289,45.39508],"type":"Point"}
}