{
  "type": "Feature",
  "properties": {
    "addr:full":"811 W Lexington Pkwy De Forest WI 53532",
    "addr:housenumber":"811",
    "addr:postcode":"53532",
    "addr:street":"W Lexington Pkwy",
    "iso:country":"US",
    "sg:address":"811 W Lexington Pkwy",
    "sg:city":"De Forest",
    "sg:classifiers":[
        {
            "category":"Banks & Credit Unions",
            "subcategory":"Financial Services",
            "type":"Services"
        }
    ],
    "sg:phone":"+1 608 846 8868",
    "sg:postcode":"53532",
    "sg:province":"WI",
    "sg:tags":[
        "investor"
    ],
    "wof:name":"Northwoods Investment Property",
    "wof:placetype":"venue"
},
  "geometry": {"coordinates":[-89.36114999999999,43.247401],"type":"Point"}
}