{
  "type": "Feature",
  "properties": {
    "iso:country":"US",
    "sg:address":"740 Melanie Dr",
    "sg:city":"Oneida",
    "sg:classifiers":[
        {
            "category":"Professional",
            "subcategory":"Business Services",
            "type":"Services"
        }
    ],
    "sg:phone":"+1 920 869 1290",
    "sg:postcode":"54155",
    "sg:province":"WI",
    "wof:name":"Connell Industrial Design",
    "wof:placetype":"venue"
},
  "geometry": {"coordinates":[-88.156568,44.545313],"type":"Point"}
}