{
  "type": "Feature",
  "properties": {
    "addr:full":"31638 State Hwy 27 Prairie Du Chien WI 53821",
    "addr:housenumber":"31638",
    "addr:postcode":"53821",
    "addr:street":"State Hwy 27",
    "iso:country":"US",
    "sg:address":"31638 State Hwy 27",
    "sg:city":"Prairie Du Chien",
    "sg:classifiers":[
        {
            "category":"Farming",
            "subcategory":"Livestock Farm",
            "type":"Manufacturing & Wholesale Goods"
        }
    ],
    "sg:phone":"+1 608 326 6810",
    "sg:postcode":"53821",
    "sg:province":"WI",
    "sg:tags":[
        "beef",
        "feedlot",
        "cattle"
    ],
    "wof:name":"Robert Check",
    "wof:placetype":"venue"
},
  "geometry": {"coordinates":[-91.057143,43.107862],"type":"Point"}
}