{
  "type": "Feature",
  "properties": {
    "iso:country":"US",
    "sg:address":"2944 Jackson St",
    "sg:city":"Oshkosh",
    "sg:classifiers":[
        {
            "category":"Autos & Motor Vehicles",
            "subcategory":"Automobile Sales",
            "type":"Retail Goods"
        }
    ],
    "sg:phone":"+1 920 426 5010",
    "sg:postcode":"54901",
    "sg:province":"WI",
    "sg:tags":[
        "car",
        "dealer"
    ],
    "wof:name":"West Side Garage Of Oshkosh",
    "wof:placetype":"venue"
},
  "geometry": {"coordinates":[-88.542935,44.05596],"type":"Point"}
}