{
  "type": "Feature",
  "properties": {
    "addr:full":"5618 Independence Rd Racine WI 53406",
    "addr:housenumber":"5618",
    "addr:postcode":"53406",
    "addr:street":"Independence Rd",
    "iso:country":"US",
    "sg:address":"5618 Independence Rd",
    "sg:city":"Racine",
    "sg:classifiers":[
        {
            "category":"Professional",
            "subcategory":"Management & Consulting",
            "type":"Services"
        }
    ],
    "sg:phone":"+1 262 886 0237",
    "sg:postcode":"53406",
    "sg:province":"WI",
    "wof:name":"Tran Financial Ntwk",
    "wof:placetype":"venue"
},
  "geometry": {"coordinates":[-87.847082,42.742843],"type":"Point"}
}