{
  "type": "Feature",
  "properties": {
    "addr:full":"637 Main St Delafield WI 53018",
    "addr:housenumber":"637",
    "addr:postcode":"53018",
    "addr:street":"Main St",
    "iso:country":"US",
    "sg:address":"637 Main St",
    "sg:city":"Delafield",
    "sg:classifiers":[
        {
            "category":"Restaurant",
            "type":"Food & Drink"
        }
    ],
    "sg:phone":"+1 262 646 2555",
    "sg:postcode":"53018",
    "sg:province":"WI",
    "sg:tags":[
        "eating"
    ],
    "sg:website":"www.whollycow.net",
    "wof:name":"Wholly Cow Frozen Custard",
    "wof:placetype":"venue"
},
  "geometry": {"coordinates":[-88.402962,43.060948],"type":"Point"}
}