{
  "type": "Feature",
  "properties": {
    "addr:full":"219 W Main St Mt Horeb WI 53572",
    "addr:housenumber":"219",
    "addr:postcode":"53572",
    "addr:street":"W Main St",
    "iso:country":"US",
    "sg:address":"219 W Main St",
    "sg:city":"Mt Horeb",
    "sg:classifiers":[
        {
            "category":"Shopping",
            "type":"Retail Goods"
        }
    ],
    "sg:phone":"+1 608 437 7185",
    "sg:postcode":"53572",
    "sg:province":"WI",
    "sg:tags":[
        "art",
        "gallery",
        "dealer"
    ],
    "sg:website":"www.mounthorebtrollway.com",
    "wof:name":"Wooden Chicken",
    "wof:placetype":"venue"
},
  "geometry": {"coordinates":[-89.740622,43.008581],"type":"Point"}
}