{
  "type": "Feature",
  "properties": {
    "iso:country":"US",
    "sg:address":"121 N Main St",
    "sg:city":"Eagle River",
    "sg:classifiers":[
        {
            "category":"Personal",
            "subcategory":"Beauty Salon",
            "type":"Services"
        }
    ],
    "sg:phone":"+1 715 479 8482",
    "sg:postcode":"54521",
    "sg:province":"WI",
    "sg:tags":[
        "shop"
    ],
    "wof:name":"MI Ladys Beauty Salon",
    "wof:placetype":"venue"
},
  "geometry": {"coordinates":[-89.250581,45.917331],"type":"Point"}
}