{
  "type": "Feature",
  "properties": {
    "iso:country":"US",
    "sg:address":"6525 Odana Rd",
    "sg:city":"Madison",
    "sg:classifiers":[
        {
            "category":"Autos & Motor Vehicles",
            "subcategory":"Auto Supplies",
            "type":"Retail Goods"
        }
    ],
    "sg:phone":"+1 608 275 7711",
    "sg:postcode":"53719",
    "sg:province":"WI",
    "sg:tags":[
        "automobile",
        "parts"
    ],
    "wof:name":"Russ Darrow Parts Dept",
    "wof:placetype":"venue"
},
  "geometry": {"coordinates":[-89.49490299999999,43.055565],"type":"Point"}
}