{
  "type": "Feature",
  "properties": {
    "iso:country":"US",
    "sg:address":"831 26th St N",
    "sg:city":"Wisconsin Rapids",
    "sg:classifiers":[
        {
            "category":"Retail",
            "subcategory":"Repair Shop",
            "type":"Services"
        }
    ],
    "sg:phone":"+1 715 423 7325",
    "sg:postcode":"54494",
    "sg:province":"WI",
    "sg:tags":[
        "appliance"
    ],
    "wof:name":"Hager's Appliance Svc",
    "wof:placetype":"venue"
},
  "geometry": {"coordinates":[-89.794371,44.39537],"type":"Point"}
}