{
  "type": "Feature",
  "properties": {
    "iso:country":"US",
    "sg:address":"170 S 1st St",
    "sg:city":"Milwaukee",
    "sg:classifiers":[
        {
            "category":"Restaurant",
            "type":"Food & Drink"
        }
    ],
    "sg:menulink":"http://www.allmenus.com/wi/milwaukee/272711-the-social/menu/",
    "sg:phone":"+1 414 270 0438",
    "sg:postcode":"53204",
    "sg:province":"WI",
    "sg:tags":[
        "sandwich",
        "salad",
        "seafood",
        "soup",
        "american",
        "pasta",
        "new",
        "chicken"
    ],
    "wof:name":"The Social",
    "wof:placetype":"venue"
},
  "geometry": {"coordinates":[-87.910966,43.029697],"type":"Point"}
}