{
  "type": "Feature",
  "properties": {
    "iso:country":"US",
    "sg:address":"4808 W Converters Dr",
    "sg:city":"Appleton",
    "sg:classifiers":[
        {
            "category":"Wholesale",
            "subcategory":"Stationery",
            "type":"Manufacturing & Wholesale Goods"
        }
    ],
    "sg:phone":"+1 920 733 3576",
    "sg:postcode":"54913",
    "sg:province":"WI",
    "sg:tags":[
        "product",
        "paper"
    ],
    "wof:name":"Camelot Distributing",
    "wof:placetype":"venue"
},
  "geometry": {"coordinates":[-88.47672900000001,44.289343],"type":"Point"}
}