{
  "type": "Feature",
  "properties": {
    "iso:country":"US",
    "sg:address":"725 W Glendale Ave",
    "sg:city":"Milwaukee",
    "sg:classifiers":[
        {
            "category":"Building & Trades",
            "subcategory":"Construction",
            "type":"Services"
        }
    ],
    "sg:phone":"+1 414 961 9159",
    "sg:postcode":"53209",
    "sg:province":"WI",
    "sg:tags":[
        "contractor"
    ],
    "wof:name":"Jonas Builders Inc",
    "wof:placetype":"venue"
},
  "geometry": {"coordinates":[-87.91879400000001,43.100035],"type":"Point"}
}