{
  "type": "Feature",
  "properties": {
    "addr:full":"9977 W McMillan St Marshfield WI 54449",
    "addr:housenumber":"9977",
    "addr:postcode":"54449",
    "addr:street":"W Mcmillan St",
    "iso:country":"US",
    "sg:address":"9977 W McMillan St",
    "sg:city":"Marshfield",
    "sg:classifiers":[
        {
            "category":"Professional",
            "subcategory":"Business Services",
            "type":"Services"
        }
    ],
    "sg:phone":"+1 715 387 6105",
    "sg:postcode":"54449",
    "sg:province":"WI",
    "wof:name":"Beyond Conflict",
    "wof:placetype":"venue"
},
  "geometry": {"coordinates":[-90.209957,44.685216],"type":"Point"}
}