{
  "type": "Feature",
  "properties": {
    "iso:country":"US",
    "sg:address":"20961 Co Hwy Aa",
    "sg:city":"Bloomer",
    "sg:classifiers":[
        {
            "category":"Shopping",
            "subcategory":"Gifts & Souvenirs",
            "type":"Retail Goods"
        }
    ],
    "sg:phone":"+1 715 568 1253",
    "sg:postcode":"54724",
    "sg:province":"WI",
    "sg:tags":[
        "shop"
    ],
    "wof:name":"Masae's Country Cor Gift Btq",
    "wof:placetype":"venue"
},
  "geometry": {"coordinates":[-91.408326,45.137949],"type":"Point"}
}