{
  "type": "Feature",
  "properties": {
    "iso:country":"US",
    "sg:address":"1521 Williamson St",
    "sg:city":"Madison",
    "sg:classifiers":[
        {
            "category":"Shopping",
            "subcategory":"Crafts & Fabrics",
            "type":"Retail Goods"
        }
    ],
    "sg:phone":"+1 608 294 7436",
    "sg:postcode":"53703",
    "sg:province":"WI",
    "sg:tags":[
        "sewing"
    ],
    "sg:website":"www.gayfeatherfabrics.com",
    "wof:name":"Gayfeather Fabrics",
    "wof:placetype":"venue"
},
  "geometry": {"coordinates":[-89.358365,43.087897],"type":"Point"}
}