{
  "type": "Feature",
  "properties": {
    "addr:full":"2491 Co Rd A Fort Atkinson WI 53538",
    "addr:housenumber":"2491",
    "addr:postcode":"53538",
    "addr:street":"Co Rd",
    "iso:country":"US",
    "sg:address":"2491 Co Rd A",
    "sg:city":"Fort Atkinson",
    "sg:phone":"+1 920 563 6142",
    "sg:postcode":"53538",
    "sg:province":"WI",
    "sg:tags":[
        "farm",
        "corn"
    ],
    "wof:name":"Hope Future Farm",
    "wof:placetype":"venue"
},
  "geometry": {"coordinates":[-88.96419,42.93646],"type":"Point"}
}