{
  "type": "Feature",
  "properties": {
    "addr:full":"951 N James Lovell St Milwaukee WI 53233",
    "addr:housenumber":"951",
    "addr:postcode":"53233",
    "addr:street":"N James Lovell St",
    "iso:country":"US",
    "sg:address":"951 N James Lovell St",
    "sg:city":"Milwaukee",
    "sg:classifiers":[
        {
            "category":"Government",
            "subcategory":"Police Station",
            "type":"Public Place"
        }
    ],
    "sg:phone":"+1 414 935 3510",
    "sg:postcode":"53233",
    "sg:province":"WI",
    "sg:tags":[
        "department"
    ],
    "wof:name":"Milwaukee Background",
    "wof:placetype":"venue"
},
  "geometry": {"coordinates":[-87.920329,43.042585],"type":"Point"}
}