{
  "type": "Feature",
  "properties": {
    "iso:country":"US",
    "sg:address":"7574 Sommers St",
    "sg:city":"Shiocton",
    "sg:classifiers":[
        {
            "category":"Wholesale",
            "subcategory":"Construction Materials",
            "type":"Manufacturing & Wholesale Goods"
        },
        {
            "category":"Building & Trades",
            "subcategory":"Construction",
            "type":"Services"
        }
    ],
    "sg:phone":"+1 920 986 3301",
    "sg:postcode":"54170",
    "sg:province":"WI",
    "sg:tags":[
        "concrete",
        "form"
    ],
    "wof:name":"Sommers Construction Co Inc",
    "wof:placetype":"venue"
},
  "geometry": {"coordinates":[-88.56895799999999,44.452198],"type":"Point"}
}