{
  "type": "Feature",
  "properties": {
    "iso:country":"US",
    "sg:address":"6578 State Hwy 180",
    "sg:city":"Marinette",
    "sg:classifiers":[
        {
            "category":"Professional",
            "subcategory":"Business Services",
            "type":"Services"
        }
    ],
    "sg:phone":"+1 715 732 4327",
    "sg:postcode":"54143",
    "sg:province":"WI",
    "wof:name":"Shadetree Farms",
    "wof:placetype":"venue"
},
  "geometry": {"coordinates":[-87.742368,45.18955],"type":"Point"}
}