{
  "type": "Feature",
  "properties": {
    "iso:country":"US",
    "sg:address":"2216 Evergreen Rd",
    "sg:city":"Middleton",
    "sg:classifiers":[
        {
            "category":"Freight",
            "type":"Transportation"
        }
    ],
    "sg:phone":"+1 608 831 9137",
    "sg:postcode":"53562",
    "sg:province":"WI",
    "sg:tags":[
        "commercial",
        "storage"
    ],
    "wof:name":"Evergreen Mini-Storage",
    "wof:placetype":"venue"
},
  "geometry": {"coordinates":[-89.535862,43.097623],"type":"Point"}
}