{
  "type": "Feature",
  "properties": {
    "iso:country":"US",
    "sg:address":"5610 W Wisconsin Ave",
    "sg:city":"Milwaukee",
    "sg:classifiers":[
        {
            "category":"Education",
            "subcategory":"School",
            "type":"Public Place"
        }
    ],
    "sg:phone":"+1 414 256 8500",
    "sg:postcode":"53213",
    "sg:province":"WI",
    "wof:name":"Hawley Public School",
    "wof:placetype":"venue"
},
  "geometry": {"coordinates":[-87.98196299999999,43.038795],"type":"Point"}
}