{
  "type": "Feature",
  "properties": {
    "iso:country":"US",
    "sg:address":"3401 W Lincoln Ave",
    "sg:city":"Milwaukee",
    "sg:classifiers":[
        {
            "category":"Building & Trades",
            "subcategory":"Plumbing",
            "type":"Services"
        }
    ],
    "sg:phone":"+1 414 645 4845",
    "sg:postcode":"53215",
    "sg:province":"WI",
    "sg:tags":[
        "plumbing",
        "heating",
        "contractor"
    ],
    "wof:name":"Borkenhagen Plumbing & Htg Co",
    "wof:placetype":"venue"
},
  "geometry": {"coordinates":[-87.957932,43.003029],"type":"Point"}
}