{
  "type": "Feature",
  "properties": {
    "iso:country":"US",
    "sg:address":"800 Clermont St",
    "sg:city":"Antigo",
    "sg:classifiers":[
        {
            "category":"Government",
            "subcategory":"Office",
            "type":"Public Place"
        }
    ],
    "sg:phone":"+1 715 627 6200",
    "sg:postcode":"54409",
    "sg:province":"WI",
    "sg:tags":[
        "county"
    ],
    "wof:name":"Langlade County Clerk",
    "wof:placetype":"venue"
},
  "geometry": {"coordinates":[-89.15412499999999,45.144729],"type":"Point"}
}