{
  "type": "Feature",
  "properties": {
    "iso:country":"US",
    "sg:address":"547 1st St",
    "sg:city":"Menasha",
    "sg:classifiers":[
        {
            "category":"Professional",
            "type":"Services"
        }
    ],
    "sg:phone":"+1 920 727 9196",
    "sg:postcode":"54952",
    "sg:province":"WI",
    "wof:name":"Drapery Installation Services",
    "wof:placetype":"venue"
},
  "geometry": {"coordinates":[-88.444157,44.202848],"type":"Point"}
}