{
  "type": "Feature",
  "properties": {
    "iso:country":"US",
    "sg:address":"754 N 27th St",
    "sg:city":"Milwaukee",
    "sg:classifiers":[
        {
            "category":"Shopping",
            "subcategory":"Clothing, Apparel, & Fashions",
            "type":"Retail Goods"
        }
    ],
    "sg:phone":"+1 414 342 9282",
    "sg:postcode":"53208",
    "sg:province":"WI",
    "wof:name":"Vera Meneese",
    "wof:placetype":"venue"
},
  "geometry": {"coordinates":[-87.947641,43.038783],"type":"Point"}
}