{
  "type": "Feature",
  "properties": {
    "iso:country":"US",
    "sg:address":"1915 Neva Rd",
    "sg:city":"Antigo",
    "sg:classifiers":[
        {
            "category":"Shopping",
            "subcategory":"Bicycles & Sporting Goods",
            "type":"Retail Goods"
        }
    ],
    "sg:phone":"+1 715 623 3051",
    "sg:postcode":"54409",
    "sg:province":"WI",
    "wof:name":"R & R Live Bait Shop",
    "wof:placetype":"venue"
},
  "geometry": {"coordinates":[-89.147715,45.158383],"type":"Point"}
}