{
  "type": "Feature",
  "properties": {
    "addr:full":"805 S 108th St West Allis WI 53214",
    "addr:housenumber":"805",
    "addr:postcode":"53214",
    "addr:street":"S 108Th St",
    "iso:country":"US",
    "sg:address":"805 S 108th St",
    "sg:city":"West Allis",
    "sg:classifiers":[
        {
            "category":"Personal",
            "subcategory":"Beauty Salon",
            "type":"Services"
        }
    ],
    "sg:phone":"+1 414 916 2930",
    "sg:postcode":"53214",
    "sg:province":"WI",
    "wof:name":"Hair With My Friends",
    "wof:placetype":"venue"
},
  "geometry": {"coordinates":[-88.04719900000001,43.022851],"type":"Point"}
}