{
  "type": "Feature",
  "properties": {
    "iso:country":"US",
    "sg:address":"12020 128th St",
    "sg:city":"Kenosha",
    "sg:classifiers":[
        {
            "category":"Local Transit",
            "type":"Transportation"
        }
    ],
    "sg:phone":"+1 262 857 9292",
    "sg:postcode":"53142",
    "sg:province":"WI",
    "wof:name":"Far Side Trucking Inc",
    "wof:placetype":"venue"
},
  "geometry": {"coordinates":[-87.951725,42.494692],"type":"Point"}
}