{
  "type": "Feature",
  "properties": {
    "addr:full":"5606 S Packard Ave Cudahy WI 53110",
    "addr:housenumber":"5606",
    "addr:postcode":"53110",
    "addr:street":"S Packard Ave",
    "iso:country":"US",
    "sg:address":"5606 S Packard Ave",
    "sg:city":"Cudahy",
    "sg:classifiers":[
        {
            "category":"Autos & Motor Vehicles",
            "subcategory":"Fuel & Gas Station",
            "type":"Retail Goods"
        }
    ],
    "sg:phone":"+1 414 481 4428",
    "sg:postcode":"53110",
    "sg:province":"WI",
    "sg:tags":[
        "oil"
    ],
    "wof:name":"Shell Mart",
    "wof:placetype":"venue"
},
  "geometry": {"coordinates":[-87.859882,42.939893],"type":"Point"}
}