{
  "type": "Feature",
  "properties": {
    "addr:full":"11 Lance Dr Twin Lakes WI 53181",
    "addr:housenumber":"11",
    "addr:postcode":"53181",
    "addr:street":"Lance Dr",
    "iso:country":"US",
    "sg:address":"11 Lance Dr",
    "sg:city":"Twin Lakes",
    "sg:classifiers":[
        {
            "category":"Shopping",
            "subcategory":"Catalog Store",
            "type":"Retail Goods"
        }
    ],
    "sg:phone":"+1 262 877 4201",
    "sg:postcode":"53181",
    "sg:province":"WI",
    "sg:tags":[
        "mail",
        "order"
    ],
    "wof:name":"Wiredmax Corp",
    "wof:placetype":"venue"
},
  "geometry": {"coordinates":[-88.25291199999999,42.531117],"type":"Point"}
}