{
  "type": "Feature",
  "properties": {
    "iso:country":"US",
    "sg:address":"316 W Main St",
    "sg:city":"Forestville",
    "sg:classifiers":[
        {
            "category":"Organizations",
            "subcategory":"Religious Organization",
            "type":"Services"
        }
    ],
    "sg:phone":"+1 920 856 6420",
    "sg:postcode":"54213",
    "sg:province":"WI",
    "sg:tags":[
        "church"
    ],
    "wof:name":"St Peters Lutheran Church",
    "wof:placetype":"venue"
},
  "geometry": {"coordinates":[-87.48414,44.690036],"type":"Point"}
}