{
  "type": "Feature",
  "properties": {
    "iso:country":"US",
    "sg:address":"6 Streeter Ct",
    "sg:city":"Fond Du Lac",
    "sg:classifiers":[
        {
            "category":"Professional",
            "subcategory":"Accounting & Tax Preparation",
            "type":"Services"
        }
    ],
    "sg:phone":"+1 920 923 2820",
    "sg:postcode":"54935",
    "sg:province":"WI",
    "sg:tags":[
        "firm"
    ],
    "wof:name":"David C Shaw CPA",
    "wof:placetype":"venue"
},
  "geometry": {"coordinates":[-88.476677,43.770655],"type":"Point"}
}