{
  "type": "Feature",
  "properties": {
    "iso:country":"US",
    "sg:address":"466 Collette Ave",
    "sg:city":"Green Bay",
    "sg:classifiers":[
        {
            "category":"Social Services",
            "subcategory":"Child Care",
            "type":"Services"
        }
    ],
    "sg:phone":"+1 920 431 0838",
    "sg:postcode":"54304",
    "sg:province":"WI",
    "sg:website":"www.steppingstones.4t.com",
    "wof:name":"Stepping Stones Child Care Inc",
    "wof:placetype":"venue"
},
  "geometry": {"coordinates":[-88.04537500000001,44.485353],"type":"Point"}
}