{
  "type": "Feature",
  "properties": {
    "addr:full":"2945 Monroe St Madison WI 53711",
    "addr:housenumber":"2945",
    "addr:postcode":"53711",
    "addr:street":"Monroe St",
    "iso:country":"US",
    "sg:address":"2945 Monroe St",
    "sg:city":"Madison",
    "sg:classifiers":[
        {
            "category":"Real Estate",
            "subcategory":"Real Estate Agent",
            "type":"Services"
        }
    ],
    "sg:phone":"+1 608 232 7777",
    "sg:postcode":"53711",
    "sg:province":"WI",
    "sg:website":"www.tommeyer.com",
    "wof:name":"Restaino Bunbury & Assoc",
    "wof:placetype":"venue"
},
  "geometry": {"coordinates":[-89.431915,43.055112],"type":"Point"}
}