{
  "type": "Feature",
  "properties": {
    "iso:country":"US",
    "sg:address":"7524 Grandview Ave",
    "sg:city":"Merrimac",
    "sg:classifiers":[
        {
            "category":"Freight",
            "type":"Transportation"
        }
    ],
    "sg:phone":"+1 608 493 2628",
    "sg:postcode":"53561",
    "sg:province":"WI",
    "sg:tags":[
        "commercial",
        "storage"
    ],
    "wof:name":"Four Seasons Storage LLC",
    "wof:placetype":"venue"
},
  "geometry": {"coordinates":[-89.66359,43.372293],"type":"Point"}
}