{
  "type": "Feature",
  "properties": {
    "iso:country":"US",
    "sg:address":"3 S Pinckney St",
    "sg:city":"Madison",
    "sg:classifiers":[
        {
            "category":"Building & Trades",
            "subcategory":"Landscaping Services",
            "type":"Services"
        }
    ],
    "sg:phone":"+1 608 258 1813",
    "sg:postcode":"53703",
    "sg:province":"WI",
    "sg:tags":[
        "designer",
        "landscape"
    ],
    "wof:name":"Blue Hills Gardens & Designs",
    "wof:placetype":"venue"
},
  "geometry": {"coordinates":[-89.382062,43.074693],"type":"Point"}
}