{
  "type": "Feature",
  "properties": {
    "addr:full":"1641 Commanche Ave Green Bay WI 54313",
    "addr:housenumber":"1641",
    "addr:postcode":"54313",
    "addr:street":"Commanche Ave",
    "iso:country":"US",
    "sg:address":"1641 Commanche Ave",
    "sg:city":"Green Bay",
    "sg:classifiers":[
        {
            "category":"Personal",
            "subcategory":"Beauty Salon",
            "type":"Services"
        }
    ],
    "sg:phone":"+1 920 496 6040",
    "sg:postcode":"54313",
    "sg:province":"WI",
    "sg:tags":[
        "shop"
    ],
    "wof:name":"Exsalonce LLC",
    "wof:placetype":"venue"
},
  "geometry": {"coordinates":[-88.10499299999999,44.492516],"type":"Point"}
}