{
  "type": "Feature",
  "properties": {
    "addr:full":"4951 Midway Ln Marshall WI 53559",
    "addr:housenumber":"4951",
    "addr:postcode":"53559",
    "addr:street":"Midway Ln",
    "iso:country":"US",
    "sg:address":"4951 Midway Ln",
    "sg:city":"Marshall",
    "sg:classifiers":[
        {
            "category":"Professional",
            "subcategory":"Management & Consulting",
            "type":"Services"
        }
    ],
    "sg:phone":"+1 608 655 4504",
    "sg:postcode":"53559",
    "sg:province":"WI",
    "sg:tags":[
        "business"
    ],
    "wof:name":"Schweizer Aj Consulting",
    "wof:placetype":"venue"
},
  "geometry": {"coordinates":[-89.08147099999999,43.120997],"type":"Point"}
}