{
  "type": "Feature",
  "properties": {
    "iso:country":"US",
    "sg:address":"2680 N 130th St",
    "sg:city":"Brookfield",
    "sg:classifiers":[
        {
            "category":"Real Estate",
            "subcategory":"Real Estate Agent",
            "type":"Services"
        }
    ],
    "sg:phone":"+1 262 785 0692",
    "sg:postcode":"53005",
    "sg:province":"WI",
    "sg:tags":[
        "appraiser"
    ],
    "wof:name":"Richard Spiegel & Barnum",
    "wof:placetype":"venue"
},
  "geometry": {"coordinates":[-88.075121,43.066012],"type":"Point"}
}