{
  "type": "Feature",
  "properties": {
    "iso:country":"US",
    "sg:address":"7712 Lowe Creek Rd",
    "sg:city":"Hixton",
    "sg:classifiers":[
        {
            "category":"Building & Trades",
            "subcategory":"Electrical",
            "type":"Services"
        }
    ],
    "sg:phone":"+1 715 963 2313",
    "sg:postcode":"54635",
    "sg:province":"WI",
    "sg:tags":[
        "electric",
        "contractor"
    ],
    "wof:name":"Hickrod & Hickrod",
    "wof:placetype":"venue"
},
  "geometry": {"coordinates":[-91.004538,44.349739],"type":"Point"}
}