{
  "type": "Feature",
  "properties": {
    "iso:country":"US",
    "sg:address":"1901 Crooks Ave",
    "sg:city":"Kaukauna",
    "sg:classifiers":[
        {
            "category":"Health Services",
            "subcategory":"Doctor",
            "type":"Services"
        }
    ],
    "sg:phone":"+1 920 766 1122",
    "sg:postcode":"54130",
    "sg:province":"WI",
    "sg:tags":[
        "dentist"
    ],
    "wof:name":"John N Krupka DDS",
    "wof:placetype":"venue"
},
  "geometry": {"coordinates":[-88.273889,44.263339],"type":"Point"}
}