{
  "type": "Feature",
  "properties": {
    "iso:country":"US",
    "sg:address":"762 Brookview Ave",
    "sg:city":"Burlington",
    "sg:classifiers":[
        {
            "category":"Manufacturing",
            "subcategory":"Tools & Machinery",
            "type":"Manufacturing & Wholesale Goods"
        }
    ],
    "sg:phone":"+1 262 763 6220",
    "sg:postcode":"53105",
    "sg:province":"WI",
    "sg:tags":[
        "fire",
        "department",
        "equipment"
    ],
    "sg:website":"www.ustanker.com",
    "wof:name":"U S Tank Sales & Svc Inc",
    "wof:placetype":"venue"
},
  "geometry": {"coordinates":[-88.274924,42.663918],"type":"Point"}
}