{
  "type": "Feature",
  "properties": {
    "addr:full":"801 Oakwood Dr Waukesha WI 53186",
    "addr:housenumber":"801",
    "addr:postcode":"53186",
    "addr:street":"Oakwood Dr",
    "iso:country":"US",
    "sg:address":"801 Oakwood Dr",
    "sg:city":"Waukesha",
    "sg:classifiers":[
        {
            "category":"Shopping",
            "subcategory":"Discount & Variety Stores",
            "type":"Retail Goods"
        }
    ],
    "sg:phone":"+1 262 544 1898",
    "sg:postcode":"53186",
    "sg:province":"WI",
    "sg:tags":[
        "merchandise",
        "general"
    ],
    "wof:name":"Spring City Sales",
    "wof:placetype":"venue"
},
  "geometry": {"coordinates":[-88.21905099999999,42.995371],"type":"Point"}
}