{
  "type": "Feature",
  "properties": {
    "iso:country":"US",
    "sg:address":"1153 Foundry St",
    "sg:city":"Schofield",
    "sg:classifiers":[
        {
            "category":"Utilities",
            "subcategory":"Fuel Oil & Lpg",
            "type":"Services"
        }
    ],
    "sg:phone":"+1 715 359 1075",
    "sg:postcode":"54476",
    "sg:province":"WI",
    "sg:tags":[
        "liquefied",
        "gas",
        "petroleum"
    ],
    "wof:name":"France Propane Service Inc",
    "wof:placetype":"venue"
},
  "geometry": {"coordinates":[-89.605802,44.914727],"type":"Point"}
}