{
  "type": "Feature",
  "properties": {
    "iso:country":"US",
    "sg:address":"3509 Willow Ln",
    "sg:city":"South Milwaukee",
    "sg:classifiers":[
        {
            "category":"Professional",
            "subcategory":"Research",
            "type":"Services"
        }
    ],
    "sg:phone":"+1 414 764 8270",
    "sg:postcode":"53172",
    "sg:province":"WI",
    "sg:tags":[
        "commercial",
        "physical"
    ],
    "wof:name":"Bassett Air Quality Inc",
    "wof:placetype":"venue"
},
  "geometry": {"coordinates":[-87.881105,42.895245],"type":"Point"}
}