{
  "type": "Feature",
  "properties": {
    "iso:country":"US",
    "sg:address":"2300 W Highland Ave",
    "sg:city":"Milwaukee",
    "sg:classifiers":[
        {
            "category":"Education",
            "subcategory":"School",
            "type":"Public Place"
        }
    ],
    "sg:phone":"+1 414 934 7000",
    "sg:postcode":"53233",
    "sg:province":"WI",
    "wof:name":"Milwaukee High School of Arts",
    "wof:placetype":"venue"
},
  "geometry": {"coordinates":[-87.942858,43.044337],"type":"Point"}
}