{
  "type": "Feature",
  "properties": {
    "iso:country":"US",
    "sg:address":"1416 N Woodale Rd",
    "sg:city":"Birchwood",
    "sg:classifiers":[
        {
            "category":"Manufacturing",
            "subcategory":"Metals",
            "type":"Manufacturing & Wholesale Goods"
        }
    ],
    "sg:phone":"+1 715 354 3889",
    "sg:postcode":"54817",
    "sg:province":"WI",
    "sg:tags":[
        "steel",
        "mfg"
    ],
    "wof:name":"Discount Steel & Service",
    "wof:placetype":"venue"
},
  "geometry": {"coordinates":[-91.460964,45.682729],"type":"Point"}
}