{
  "type": "Feature",
  "properties": {
    "iso:country":"US",
    "sg:address":"331 26th Pl N",
    "sg:city":"La Crosse",
    "sg:classifiers":[
        {
            "category":"Retail",
            "subcategory":"Laundry & Dry Cleaning",
            "type":"Services"
        }
    ],
    "sg:phone":"+1 608 784 2434",
    "sg:postcode":"54601",
    "sg:province":"WI",
    "wof:name":"First Class Cleaning Service",
    "wof:placetype":"venue"
},
  "geometry": {"coordinates":[-91.218177,43.814432],"type":"Point"}
}