{
  "type": "Feature",
  "properties": {
    "iso:country":"US",
    "sg:address":"W5498 Hazel Ridge Rd",
    "sg:city":"Elkhorn",
    "sg:classifiers":[
        {
            "category":"Recreation",
            "subcategory":"Picnic Area",
            "type":"Entertainment"
        },
        {
            "category":"Community Center",
            "type":"Public Place"
        }
    ],
    "sg:phone":"+1 262 723 4982",
    "sg:postcode":"53121",
    "sg:province":"WI",
    "sg:tags":[
        "amusement",
        "arcade"
    ],
    "sg:website":"http://www.mcandalusians.com",
    "wof:name":"Music City Andalusians",
    "wof:placetype":"venue"
},
  "geometry": {"coordinates":[-88.5634,42.679686],"type":"Point"}
}