{
  "type": "Feature",
  "properties": {
    "addr:full":"308 Blue View Dr Mount Horeb WI 53572",
    "addr:housenumber":"308",
    "addr:postcode":"53572",
    "addr:street":"Blue View Dr",
    "iso:country":"US",
    "sg:address":"308 Blue View Dr",
    "sg:city":"Mount Horeb",
    "sg:classifiers":[
        {
            "category":"Building & Trades",
            "subcategory":"Construction",
            "type":"Services"
        }
    ],
    "sg:phone":"+1 608 437 5025",
    "sg:postcode":"53572",
    "sg:province":"WI",
    "sg:tags":[
        "concrete",
        "contractor"
    ],
    "wof:name":"Concrete Innovations Inc",
    "wof:placetype":"venue"
},
  "geometry": {"coordinates":[-89.732996,43.017285],"type":"Point"}
}