{
  "type": "Feature",
  "properties": {
    "addr:full":"1504 Davis St Watertown WI 53098",
    "addr:housenumber":"1504",
    "addr:postcode":"53098",
    "addr:street":"Davis St",
    "iso:country":"US",
    "sg:address":"1504 Davis St",
    "sg:city":"Watertown",
    "sg:classifiers":[
        {
            "category":"Building & Trades",
            "subcategory":"Construction",
            "type":"Services"
        }
    ],
    "sg:phone":"+1 920 261 0243",
    "sg:postcode":"53098",
    "sg:province":"WI",
    "sg:tags":[
        "house"
    ],
    "wof:name":"Brom Remodeling",
    "wof:placetype":"venue"
},
  "geometry": {"coordinates":[-88.719695,43.211672],"type":"Point"}
}