{
  "type": "Feature",
  "properties": {
    "iso:country":"US",
    "sg:address":"445 E Oklahoma Ave",
    "sg:city":"Milwaukee",
    "sg:classifiers":[
        {
            "category":"Professional",
            "subcategory":"Business Services",
            "type":"Services"
        }
    ],
    "sg:phone":"+1 414 747 7256",
    "sg:postcode":"53207",
    "sg:province":"WI",
    "wof:name":"Heartland Wisconsin Corp",
    "wof:placetype":"venue"
},
  "geometry": {"coordinates":[-87.903189,42.988226],"type":"Point"}
}