{
  "type": "Feature",
  "properties": {
    "iso:country":"US",
    "sg:address":"1502 Bellinger St",
    "sg:city":"Eau Claire",
    "sg:classifiers":[
        {
            "category":"Restaurant",
            "type":"Food & Drink"
        }
    ],
    "sg:phone":"+1 715 830 9303",
    "sg:postcode":"54703",
    "sg:province":"WI",
    "sg:tags":[
        "eating"
    ],
    "wof:name":"Ricky DS Family Cafe",
    "wof:placetype":"venue"
},
  "geometry": {"coordinates":[-91.511444,44.815515],"type":"Point"}
}