{
  "type": "Feature",
  "properties": {
    "iso:country":"US",
    "sg:address":"8430 W Howard Ave",
    "sg:city":"Milwaukee",
    "sg:classifiers":[
        {
            "category":"Building & Trades",
            "subcategory":"Construction",
            "type":"Services"
        }
    ],
    "sg:phone":"+1 414 327 7898",
    "sg:postcode":"53228",
    "sg:province":"WI",
    "sg:tags":[
        "contractor"
    ],
    "wof:name":"Potter Roofing",
    "wof:placetype":"venue"
},
  "geometry": {"coordinates":[-88.01875800000001,42.973801],"type":"Point"}
}