{
  "type": "Feature",
  "properties": {
    "iso:country":"US",
    "sg:address":"2401 S Oneida St",
    "sg:city":"Green Bay",
    "sg:classifiers":[
        {
            "category":"Shopping",
            "subcategory":"Gifts & Souvenirs",
            "type":"Retail Goods"
        }
    ],
    "sg:phone":"+1 920 494 9640",
    "sg:postcode":"54304",
    "sg:province":"WI",
    "sg:tags":[
        "shop"
    ],
    "sg:website":"www.coachhousegifts.com",
    "wof:name":"Coach House",
    "wof:placetype":"venue"
},
  "geometry": {"coordinates":[-88.067645,44.485974],"type":"Point"}
}