{
  "type": "Feature",
  "properties": {
    "addr:full":"633 S Main St De Forest WI 53532",
    "addr:housenumber":"633",
    "addr:postcode":"53532",
    "addr:street":"S Main St",
    "iso:country":"US",
    "sg:address":"633 S Main St",
    "sg:city":"De Forest",
    "sg:classifiers":[
        {
            "category":"Restaurant",
            "type":"Food & Drink"
        }
    ],
    "sg:menulink":"http://www.allmenus.com/wi/deforest/80021-pizza-hut/menu/",
    "sg:phone":"+1 608 846 8484",
    "sg:postcode":"53532",
    "sg:province":"WI",
    "sg:tags":[
        "american",
        "pizza"
    ],
    "wof:name":"Pizza Hut",
    "wof:placetype":"venue"
},
  "geometry": {"coordinates":[-89.34369700000001,43.24058],"type":"Point"}
}