{
  "type": "Feature",
  "properties": {
    "iso:country":"US",
    "sg:address":"11461 Co Rd F",
    "sg:city":"Darlington",
    "sg:classifiers":[
        {
            "category":"Building & Trades",
            "subcategory":"Construction",
            "type":"Services"
        }
    ],
    "sg:phone":"+1 608 776 2960",
    "sg:postcode":"53530",
    "sg:province":"WI",
    "sg:tags":[
        "house"
    ],
    "wof:name":"Bruce Geissbuhler Bldg Design",
    "wof:placetype":"venue"
},
  "geometry": {"coordinates":[-90.045095,42.75496],"type":"Point"}
}