{
  "type": "Feature",
  "properties": {
    "iso:country":"US",
    "sg:address":"2623 Douglas Ave",
    "sg:city":"Racine",
    "sg:classifiers":[
        {
            "category":"Insurance",
            "subcategory":"Insurance Agent",
            "type":"Services"
        }
    ],
    "sg:phone":"+1 262 681 5577",
    "sg:postcode":"53402",
    "sg:province":"WI",
    "wof:name":"Annette Varnes Agency",
    "wof:placetype":"venue"
},
  "geometry": {"coordinates":[-87.798293,42.752819],"type":"Point"}
}