{
  "type": "Feature",
  "properties": {
    "addr:full":"105 N Main St Dousman WI 53118",
    "addr:housenumber":"105",
    "addr:postcode":"53118",
    "addr:street":"N Main St",
    "iso:country":"US",
    "sg:address":"105 N Main St",
    "sg:city":"Dousman",
    "sg:classifiers":[
        {
            "category":"Education",
            "subcategory":"Special Training",
            "type":"Public Place"
        }
    ],
    "sg:phone":"+1 262 965 5763",
    "sg:postcode":"53118",
    "sg:province":"WI",
    "wof:name":"Main Stage Academy Of Dance",
    "wof:placetype":"venue"
},
  "geometry": {"coordinates":[-88.47291300000001,43.013962],"type":"Point"}
}