{
  "type": "Feature",
  "properties": {
    "addr:full":"4838 Douglas Ave Racine WI 53402",
    "addr:housenumber":"4838",
    "addr:postcode":"53402",
    "addr:street":"Douglas Ave",
    "iso:country":"US",
    "sg:address":"4838 Douglas Ave",
    "sg:city":"Racine",
    "sg:classifiers":[
        {
            "category":"Farming",
            "subcategory":"Nursery",
            "type":"Manufacturing & Wholesale Goods"
        },
        {
            "category":"Home & Garden",
            "subcategory":"Garden Supply",
            "type":"Retail Goods"
        }
    ],
    "sg:phone":"+1 262 639 2040",
    "sg:postcode":"53402",
    "sg:province":"WI",
    "sg:tags":[
        "tree",
        "christmas",
        "nurseries-plants"
    ],
    "sg:website":"http://www.milaegers.com",
    "wof:name":"Milaeger's",
    "wof:placetype":"venue"
},
  "geometry": {"coordinates":[-87.80776899999999,42.781957],"type":"Point"}
}