{
  "type": "Feature",
  "properties": {
    "iso:country":"US",
    "sg:address":"206 Water St",
    "sg:city":"Eau Claire",
    "sg:classifiers":[
        {
            "category":"Organizations",
            "subcategory":"Professional Association",
            "type":"Services"
        },
        {
            "category":"Social Services",
            "type":"Services"
        }
    ],
    "sg:phone":"+1 715 832 1782",
    "sg:postcode":"54703",
    "sg:province":"WI",
    "wof:name":"United Cerebral Palsy of West",
    "wof:placetype":"venue"
},
  "geometry": {"coordinates":[-91.505571,44.802242],"type":"Point"}
}