{
  "type": "Feature",
  "properties": {
    "iso:country":"US",
    "sg:address":"1049 13th Ave",
    "sg:city":"Deer Park",
    "sg:classifiers":[
        {
            "category":"Shopping",
            "subcategory":"Hobbies, Toys, & Games",
            "type":"Retail Goods"
        }
    ],
    "sg:phone":"+1 715 269 5539",
    "sg:postcode":"54007",
    "sg:province":"WI",
    "wof:name":"Equis Inc",
    "wof:placetype":"venue"
},
  "geometry": {"coordinates":[-92.37494599999999,45.227812],"type":"Point"}
}