{
  "type": "Feature",
  "properties": {
    "addr:full":"3525 Patch St Stevens Point WI 54481",
    "addr:housenumber":"3525",
    "addr:postcode":"54481",
    "addr:street":"Patch St",
    "iso:country":"US",
    "sg:address":"3525 Patch St",
    "sg:city":"Stevens Point",
    "sg:classifiers":[
        {
            "category":"Building & Trades",
            "subcategory":"Construction",
            "type":"Services"
        }
    ],
    "sg:phone":"+1 715 344 6777",
    "sg:postcode":"54481",
    "sg:province":"WI",
    "sg:tags":[
        "general",
        "contractor"
    ],
    "wof:name":"Guzman Corp",
    "wof:placetype":"venue"
},
  "geometry": {"coordinates":[-89.55131,44.512079],"type":"Point"}
}