{
  "type": "Feature",
  "properties": {
    "iso:country":"US",
    "sg:address":"2427 W Nash St",
    "sg:city":"Milwaukee",
    "sg:classifiers":[
        {
            "category":"Building & Trades",
            "subcategory":"Cleaning & Sanitation",
            "type":"Services"
        }
    ],
    "sg:phone":"+1 414 873 8771",
    "sg:postcode":"53206",
    "sg:province":"WI",
    "sg:tags":[
        "snow",
        "removal"
    ],
    "wof:name":"Freeman Snow Plowing Svc",
    "wof:placetype":"venue"
},
  "geometry": {"coordinates":[-87.94278300000001,43.08458],"type":"Point"}
}