{
  "type": "Feature",
  "properties": {
    "iso:country":"US",
    "sg:address":"8 Mechanic St",
    "sg:city":"Edgerton",
    "sg:classifiers":[
        {
            "category":"Farming",
            "subcategory":"Farm",
            "type":"Manufacturing & Wholesale Goods"
        }
    ],
    "sg:phone":"+1 608 884 9630",
    "sg:postcode":"53534",
    "sg:province":"WI",
    "sg:tags":[
        "crop",
        "general"
    ],
    "wof:name":"Daniel Schaff",
    "wof:placetype":"venue"
},
  "geometry": {"coordinates":[-89.073842,42.837306],"type":"Point"}
}