{
  "type": "Feature",
  "properties": {
    "addr:full":"6946 Von Besser Dr Merrill WI 54452",
    "addr:housenumber":"6946",
    "addr:postcode":"54452",
    "addr:street":"Von Besser Dr",
    "iso:country":"US",
    "sg:address":"6946 Von Besser Dr",
    "sg:city":"Merrill",
    "sg:classifiers":[
        {
            "category":"Building & Trades",
            "subcategory":"Construction",
            "type":"Services"
        }
    ],
    "sg:phone":"+1 715 536 5505",
    "sg:postcode":"54452",
    "sg:province":"WI",
    "sg:tags":[
        "general",
        "contractor"
    ],
    "wof:name":"Duerr Construction",
    "wof:placetype":"venue"
},
  "geometry": {"coordinates":[-89.78697200000001,45.211998],"type":"Point"}
}