{
  "type": "Feature",
  "properties": {
    "addr:full":"3512 S Maple Ave Marshfield WI 54449",
    "addr:housenumber":"3512",
    "addr:postcode":"54449",
    "addr:street":"S Maple Ave",
    "iso:country":"US",
    "sg:address":"3512 S Maple Ave",
    "sg:city":"Marshfield",
    "sg:classifiers":[
        {
            "category":"Professional",
            "type":"Services"
        }
    ],
    "sg:phone":"+1 715 387 1980",
    "sg:postcode":"54449",
    "sg:province":"WI",
    "sg:tags":[
        "establishment"
    ],
    "wof:name":"Hesch Of Wisconsin Inc",
    "wof:placetype":"venue"
},
  "geometry": {"coordinates":[-90.180046,44.638878],"type":"Point"}
}