{
  "type": "Feature",
  "properties": {
    "iso:country":"US",
    "sg:address":"5475 Crossman Rd",
    "sg:city":"Lake Mills",
    "sg:classifiers":[
        {
            "category":"Manufacturing",
            "subcategory":"Pet Food",
            "type":"Manufacturing & Wholesale Goods"
        }
    ],
    "sg:phone":"+1 920 648 3003",
    "sg:postcode":"53551",
    "sg:province":"WI",
    "sg:tags":[
        "animal",
        "mfg"
    ],
    "wof:name":"Nutrition First Processing",
    "wof:placetype":"venue"
},
  "geometry": {"coordinates":[-88.94369500000001,43.03329],"type":"Point"}
}