{
  "type": "Feature",
  "properties": {
    "iso:country":"US",
    "sg:address":"571 Marcella St",
    "sg:city":"Kimberly",
    "sg:classifiers":[
        {
            "category":"Personal",
            "subcategory":"Beauty Salon",
            "type":"Services"
        }
    ],
    "sg:phone":"+1 920 738 5300",
    "sg:postcode":"54136",
    "sg:province":"WI",
    "sg:tags":[
        "shop"
    ],
    "wof:name":"Cost Cutters",
    "wof:placetype":"venue"
},
  "geometry": {"coordinates":[-88.35494,44.264219],"type":"Point"}
}