{
  "type": "Feature",
  "properties": {
    "addr:full":"236 Nancy Ln Pulaski WI 54162",
    "addr:housenumber":"236",
    "addr:postcode":"54162",
    "addr:street":"Nancy Ln",
    "iso:country":"US",
    "sg:address":"236 Nancy Ln",
    "sg:city":"Pulaski",
    "sg:classifiers":[
        {
            "category":"Building & Trades",
            "subcategory":"Construction",
            "type":"Services"
        }
    ],
    "sg:phone":"+1 920 822 5086",
    "sg:postcode":"54162",
    "sg:province":"WI",
    "sg:tags":[
        "installs",
        "tiling",
        "drainage",
        "contractor"
    ],
    "sg:website":"www.angelicatile.com",
    "wof:name":"Angelica Tile Inc",
    "wof:placetype":"venue"
},
  "geometry": {"coordinates":[-88.239338,44.665146],"type":"Point"}
}