{
  "type": "Feature",
  "properties": {
    "iso:country":"US",
    "sg:address":"8409 Lakeshore Dr",
    "sg:city":"Fond Du Lac",
    "sg:classifiers":[
        {
            "category":"Wholesale",
            "subcategory":"Durable Goods & Equipment",
            "type":"Manufacturing & Wholesale Goods"
        }
    ],
    "sg:phone":"+1 920 923 2454",
    "sg:postcode":"54937",
    "sg:province":"WI",
    "wof:name":"Amway Products Distributor",
    "wof:placetype":"venue"
},
  "geometry": {"coordinates":[-88.46380600000001,43.845812],"type":"Point"}
}