{
  "type": "Feature",
  "properties": {
    "iso:country":"US",
    "sg:address":"3114 Sievert Rd",
    "sg:city":"Seymour",
    "sg:classifiers":[
        {
            "category":"Professional",
            "subcategory":"Business Services",
            "type":"Services"
        }
    ],
    "sg:phone":"+1 920 749 9097",
    "sg:postcode":"54165",
    "sg:province":"WI",
    "wof:name":"Transport Design LLC",
    "wof:placetype":"venue"
},
  "geometry": {"coordinates":[-88.334869,44.429165],"type":"Point"}
}