{
  "type": "Feature",
  "properties": {
    "iso:country":"US",
    "sg:address":"13055 Dunwoody Dr",
    "sg:city":"Elm Grove",
    "sg:classifiers":[
        {
            "category":"Wholesale",
            "subcategory":"Electrical",
            "type":"Manufacturing & Wholesale Goods"
        }
    ],
    "sg:phone":"+1 262 821 0111",
    "sg:postcode":"53122",
    "sg:province":"WI",
    "sg:tags":[
        "substation",
        "equipment",
        "distribution"
    ],
    "wof:name":"Paresources Inc",
    "wof:placetype":"venue"
},
  "geometry": {"coordinates":[-88.07401,43.055578],"type":"Point"}
}