{
  "type": "Feature",
  "properties": {
    "iso:country":"US",
    "sg:address":"2680 Comings Rd",
    "sg:city":"Eau Claire",
    "sg:classifiers":[
        {
            "category":"Building & Trades",
            "subcategory":"Construction",
            "type":"Services"
        }
    ],
    "sg:phone":"+1 715 835 6155",
    "sg:postcode":"54701",
    "sg:province":"WI",
    "sg:tags":[
        "dry wall",
        "contractor"
    ],
    "wof:name":"ROBINSON'S Construction & Rpr",
    "wof:placetype":"venue"
},
  "geometry": {"coordinates":[-91.539005,44.769776],"type":"Point"}
}