{
  "type": "Feature",
  "properties": {
    "iso:country":"US",
    "sg:address":"8230 W Lincoln Ave",
    "sg:city":"Milwaukee",
    "sg:classifiers":[
        {
            "category":"Wholesale",
            "subcategory":"Medical Equipment & Supplies",
            "type":"Manufacturing & Wholesale Goods"
        },
        {
            "category":"Health Services",
            "subcategory":"Hospital",
            "type":"Services"
        },
        {
            "category":"Shopping",
            "subcategory":"Pharmacy",
            "type":"Retail Goods"
        }
    ],
    "sg:phone":"+1 414 321 3500",
    "sg:postcode":"53219",
    "sg:province":"WI",
    "sg:tags":[
        "mobility",
        "wheelchair",
        "disabled",
        "person",
        "aid",
        "home",
        "scooter",
        "care"
    ],
    "wof:name":"Discount Mobility",
    "wof:placetype":"venue"
},
  "geometry": {"coordinates":[-88.01541,43.002747],"type":"Point"}
}