{
  "type": "Feature",
  "properties": {
    "addr:full":"2547 3rd Ave Chetek WI 54757",
    "addr:housenumber":"2547",
    "addr:postcode":"54757",
    "addr:street":"3Rd Ave",
    "iso:country":"US",
    "sg:address":"2547 3rd Ave",
    "sg:city":"Chetek",
    "sg:classifiers":[
        {
            "category":"Organizations",
            "subcategory":"Religious Organization",
            "type":"Services"
        }
    ],
    "sg:phone":"+1 715 868 2761",
    "sg:postcode":"54757",
    "sg:province":"WI",
    "sg:tags":[
        "church"
    ],
    "wof:name":"Grace Bible Church",
    "wof:placetype":"venue"
},
  "geometry": {"coordinates":[-91.64627900000001,45.250793],"type":"Point"}
}