{
  "type": "Feature",
  "properties": {
    "iso:country":"US",
    "sg:address":"1932 George St",
    "sg:city":"La Crosse",
    "sg:classifiers":[
        {
            "category":"Personal",
            "type":"Services"
        }
    ],
    "sg:phone":"+1 608 781 4644",
    "sg:postcode":"54603",
    "sg:province":"WI",
    "wof:name":"Hire-A-Hubby Handyman Services",
    "wof:placetype":"venue"
},
  "geometry": {"coordinates":[-91.2397,43.850398],"type":"Point"}
}