{
  "type": "Feature",
  "properties": {
    "iso:country":"US",
    "sg:address":"2115 S 162nd St",
    "sg:city":"New Berlin",
    "sg:classifiers":[
        {
            "category":"Building & Trades",
            "subcategory":"Cleaning & Sanitation",
            "type":"Services"
        }
    ],
    "sg:phone":"+1 262 785 1126",
    "sg:postcode":"53151",
    "sg:province":"WI",
    "sg:tags":[
        "janitor"
    ],
    "wof:name":"Programmed Cleaning Inc",
    "wof:placetype":"venue"
},
  "geometry": {"coordinates":[-88.113759,43.004294],"type":"Point"}
}