{
  "type": "Feature",
  "properties": {
    "iso:country":"US",
    "sg:address":"925 S 12th St",
    "sg:city":"Watertown",
    "sg:classifiers":[
        {
            "category":"Recreation",
            "type":"Entertainment"
        }
    ],
    "sg:phone":"+1 920 206 8883",
    "sg:postcode":"53094",
    "sg:province":"WI",
    "wof:name":"Star Karate Inc",
    "wof:placetype":"venue"
},
  "geometry": {"coordinates":[-88.713574,43.174707],"type":"Point"}
}