{
  "type": "Feature",
  "properties": {
    "addr:full":"2205 Forest Ave Two Rivers WI 54241",
    "addr:housenumber":"2205",
    "addr:postcode":"54241",
    "addr:street":"Forest Ave",
    "iso:country":"US",
    "sg:address":"2205 Forest Ave",
    "sg:city":"Two Rivers",
    "sg:classifiers":[
        {
            "category":"Shopping",
            "type":"Retail Goods"
        }
    ],
    "sg:phone":"+1 920 553 2211",
    "sg:postcode":"54241",
    "sg:province":"WI",
    "sg:tags":[
        "merchandise"
    ],
    "wof:name":"Lakefield Telecom Inc",
    "wof:placetype":"venue"
},
  "geometry": {"coordinates":[-87.572732,44.154623],"type":"Point"}
}