{
  "type": "Feature",
  "properties": {
    "iso:country":"US",
    "sg:address":"4051 Karen Ln",
    "sg:city":"Stratford",
    "sg:classifiers":[
        {
            "category":"Freight",
            "type":"Transportation"
        }
    ],
    "sg:phone":"+1 715 687 2110",
    "sg:postcode":"54484",
    "sg:province":"WI",
    "sg:tags":[
        "operator",
        "local",
        "trucking"
    ],
    "wof:name":"Dale Heil Trucking LLC",
    "wof:placetype":"venue"
},
  "geometry": {"coordinates":[-90.045141,44.79773],"type":"Point"}
}