{
  "type": "Feature",
  "properties": {
    "iso:country":"US",
    "sg:address":"209 Church St",
    "sg:city":"Lake Mills",
    "sg:classifiers":[
        {
            "category":"Education",
            "subcategory":"School",
            "type":"Public Place"
        }
    ],
    "sg:phone":"+1 920 648 2215",
    "sg:postcode":"53551",
    "sg:province":"WI",
    "sg:tags":[
        "independent",
        "district"
    ],
    "wof:name":"Lake Mills School District",
    "wof:placetype":"venue"
},
  "geometry": {"coordinates":[-88.91291699999999,43.08224],"type":"Point"}
}