{
  "type": "Feature",
  "properties": {
    "addr:full":"6630 Co Rd Hh Stevens Point WI 54481",
    "addr:housenumber":"6630",
    "addr:postcode":"54481",
    "addr:street":"Co Rd",
    "iso:country":"US",
    "sg:address":"6630 Co Rd Hh",
    "sg:city":"Stevens Point",
    "sg:classifiers":[
        {
            "category":"Building & Trades",
            "subcategory":"Landscaping Services",
            "type":"Services"
        }
    ],
    "sg:phone":"+1 715 342 3924",
    "sg:postcode":"54481",
    "sg:province":"WI",
    "sg:tags":[
        "lawn",
        "maintenance",
        "grounds"
    ],
    "wof:name":"Scott's Lawn Care",
    "wof:placetype":"venue"
},
  "geometry": {"coordinates":[-89.456479,44.496248],"type":"Point"}
}