{
  "type": "Feature",
  "properties": {
    "addr:full":"7277 Garden Prairie Rd Cassville WI 53806",
    "addr:housenumber":"7277",
    "addr:postcode":"53806",
    "addr:street":"Garden Prairie Rd",
    "iso:country":"US",
    "sg:address":"7277 Garden Prairie Rd",
    "sg:city":"Cassville",
    "sg:classifiers":[
        {
            "category":"Retail",
            "subcategory":"Auto Repair",
            "type":"Services"
        }
    ],
    "sg:phone":"+1 608 725 5928",
    "sg:postcode":"53806",
    "sg:province":"WI",
    "sg:tags":[
        "automotive"
    ],
    "wof:name":"Randy Express",
    "wof:placetype":"venue"
},
  "geometry": {"coordinates":[-90.93368100000001,42.77065],"type":"Point"}
}