{
  "type": "Feature",
  "properties": {
    "iso:country":"US",
    "sg:address":"5825 W Capitol Dr",
    "sg:city":"Milwaukee",
    "sg:classifiers":[
        {
            "category":"Social Services",
            "subcategory":"Child Care",
            "type":"Services"
        }
    ],
    "sg:phone":"+1 414 449 8470",
    "sg:postcode":"53216",
    "sg:province":"WI",
    "wof:name":"Wee Care Wic",
    "wof:placetype":"venue"
},
  "geometry": {"coordinates":[-87.986811,43.089896],"type":"Point"}
}