{
  "type": "Feature",
  "properties": {
    "iso:country":"US",
    "sg:address":"27610 113th",
    "sg:city":"Camp Lake",
    "sg:classifiers":[
        {
            "category":"Restaurant",
            "type":"Food & Drink"
        }
    ],
    "sg:phone":"+1 262 862 6667",
    "sg:postcode":"53109",
    "sg:province":"WI",
    "wof:name":"Last Resort Tavern",
    "wof:placetype":"venue"
},
  "geometry": {"coordinates":[-88.14450100000001,42.535099],"type":"Point"}
}