{
  "type": "Feature",
  "properties": {
    "iso:country":"US",
    "sg:address":"14258 State Hwy 70",
    "sg:city":"Lac Du Flambeau",
    "sg:classifiers":[
        {
            "category":"Professional",
            "subcategory":"Business Services",
            "type":"Services"
        }
    ],
    "sg:phone":"+1 715 588 3790",
    "sg:postcode":"54538",
    "sg:province":"WI",
    "wof:name":"Ojibwe Plastics",
    "wof:placetype":"venue"
},
  "geometry": {"coordinates":[-89.913523,45.914389],"type":"Point"}
}