{
  "type": "Feature",
  "properties": {
    "iso:country":"US",
    "sg:address":"11912 N 16th Ave",
    "sg:city":"Chippewa Falls",
    "sg:classifiers":[
        {
            "category":"Building & Trades",
            "subcategory":"Electrical",
            "type":"Services"
        }
    ],
    "sg:phone":"+1 715 864 9092",
    "sg:postcode":"54729",
    "sg:province":"WI",
    "sg:tags":[
        "electrical",
        "contractor"
    ],
    "wof:name":"Powerpro",
    "wof:placetype":"venue"
},
  "geometry": {"coordinates":[-91.427818,44.867356],"type":"Point"}
}