{
  "type": "Feature",
  "properties": {
    "iso:country":"US",
    "sg:address":"3522 S 18th St",
    "sg:city":"Sheboygan",
    "sg:classifiers":[
        {
            "category":"Professional",
            "subcategory":"Business Services",
            "type":"Services"
        }
    ],
    "sg:phone":"+1 920 452 8837",
    "sg:postcode":"53081",
    "sg:province":"WI",
    "sg:tags":[
        "painter",
        "sign"
    ],
    "wof:name":"Bob's Sign Svc",
    "wof:placetype":"venue"
},
  "geometry": {"coordinates":[-87.72950899999999,43.717251],"type":"Point"}
}