{
  "type": "Feature",
  "properties": {
    "iso:country":"US",
    "sg:address":"6051 N Lake Dr",
    "sg:city":"Milwaukee",
    "sg:classifiers":[
        {
            "category":"Shopping",
            "type":"Retail Goods"
        }
    ],
    "sg:phone":"+1 414 964 8666",
    "sg:postcode":"53217",
    "sg:province":"WI",
    "sg:tags":[
        "merchandise"
    ],
    "wof:name":"Corporate Flag Services Inc",
    "wof:placetype":"venue"
},
  "geometry": {"coordinates":[-87.90419900000001,43.126969],"type":"Point"}
}