{
  "type": "Feature",
  "properties": {
    "iso:country":"US",
    "sg:address":"8912 Co Rd B",
    "sg:city":"Pittsville",
    "sg:classifiers":[
        {
            "category":"Farming",
            "subcategory":"Farm",
            "type":"Manufacturing & Wholesale Goods"
        }
    ],
    "sg:phone":"+1 715 884 2700",
    "sg:postcode":"54466",
    "sg:province":"WI",
    "sg:tags":[
        "dairy",
        "crop",
        "general"
    ],
    "wof:name":"Harvey Petersen",
    "wof:placetype":"venue"
},
  "geometry": {"coordinates":[-90.17061200000001,44.43911],"type":"Point"}
}