{
  "type": "Feature",
  "properties": {
    "addr:full":"702 Wexford Way Hartland WI 53029",
    "addr:housenumber":"702",
    "addr:postcode":"53029",
    "addr:street":"Wexford Way",
    "iso:country":"US",
    "sg:address":"702 Wexford Way",
    "sg:city":"Hartland",
    "sg:classifiers":[
        {
            "category":"Social Services",
            "subcategory":"Child Care",
            "type":"Services"
        }
    ],
    "sg:phone":"+1 262 367 4688",
    "sg:postcode":"53029",
    "sg:province":"WI",
    "sg:tags":[
        "day"
    ],
    "wof:name":"Special Needs Daycare",
    "wof:placetype":"venue"
},
  "geometry": {"coordinates":[-88.33108799999999,43.094704],"type":"Point"}
}