{
  "type": "Feature",
  "properties": {
    "addr:full":"13116 W Stark St Butler WI 53007",
    "addr:housenumber":"13116",
    "addr:postcode":"53007",
    "addr:street":"W Stark St",
    "iso:country":"US",
    "sg:address":"13116 W Stark St",
    "sg:city":"Butler",
    "sg:classifiers":[
        {
            "category":"Building & Trades",
            "subcategory":"Construction",
            "type":"Services"
        }
    ],
    "sg:phone":"+1 262 781 9441",
    "sg:postcode":"53007",
    "sg:province":"WI",
    "sg:tags":[
        "excavation",
        "grading",
        "contractor"
    ],
    "wof:name":"Britches Excavating",
    "wof:placetype":"venue"
},
  "geometry": {"coordinates":[-88.07580400000001,43.105805],"type":"Point"}
}