{
  "type": "Feature",
  "properties": {
    "iso:country":"US",
    "sg:address":"124 W Wisconsin Ave",
    "sg:city":"Neenah",
    "sg:classifiers":[
        {
            "category":"Retail",
            "subcategory":"Portrait Studio",
            "type":"Services"
        }
    ],
    "sg:phone":"+1 920 733 4500",
    "sg:postcode":"54956",
    "sg:province":"WI",
    "sg:tags":[
        "photographer",
        "photo"
    ],
    "wof:name":"Geris Photography and Video",
    "wof:placetype":"venue"
},
  "geometry": {"coordinates":[-88.463031,44.186993],"type":"Point"}
}