{
  "type": "Feature",
  "properties": {
    "addr:full":"3023 N 15th St Sheboygan WI 53083",
    "addr:housenumber":"3023",
    "addr:postcode":"53083",
    "addr:street":"N 15Th St",
    "iso:country":"US",
    "sg:address":"3023 N 15th St",
    "sg:city":"Sheboygan",
    "sg:classifiers":[
        {
            "category":"Bars & Pubs",
            "type":"Food & Drink"
        }
    ],
    "sg:phone":"+1 920 457 9946",
    "sg:postcode":"53083",
    "sg:province":"WI",
    "wof:name":"Smolic's Tavern",
    "wof:placetype":"venue"
},
  "geometry": {"coordinates":[-87.72479300000001,43.77718],"type":"Point"}
}