{
  "type": "Feature",
  "properties": {
    "iso:country":"US",
    "sg:address":"5055 N 28th St",
    "sg:city":"Milwaukee",
    "sg:classifiers":[
        {
            "category":"Arts & Performance",
            "subcategory":"Theater",
            "type":"Entertainment"
        }
    ],
    "sg:phone":"+1 414 873 5462",
    "sg:postcode":"53209",
    "sg:province":"WI",
    "sg:tags":[
        "entertainer",
        "business"
    ],
    "wof:name":"Lucky 7 Entertainment",
    "wof:placetype":"venue"
},
  "geometry": {"coordinates":[-87.947873,43.10887],"type":"Point"}
}