{
  "type": "Feature",
  "properties": {
    "iso:country":"US",
    "sg:address":"15350 W National Ave",
    "sg:city":"New Berlin",
    "sg:classifiers":[
        {
            "category":"Insurance",
            "subcategory":"Insurance Agent",
            "type":"Services"
        }
    ],
    "sg:phone":"+1 262 780 1179",
    "sg:postcode":"53151",
    "sg:province":"WI",
    "wof:name":"Craig R Murphy Agency",
    "wof:placetype":"venue"
},
  "geometry": {"coordinates":[-88.104852,42.979036],"type":"Point"}
}