{
  "type": "Feature",
  "properties": {
    "iso:country":"US",
    "sg:address":"14450 W Lilly Heights Dr",
    "sg:city":"Brookfield",
    "sg:classifiers":[
        {
            "category":"Professional",
            "subcategory":"Management & Consulting",
            "type":"Services"
        }
    ],
    "sg:phone":"+1 262 781 3371",
    "sg:postcode":"53005",
    "sg:province":"WI",
    "wof:name":"Christensen Environmental Svcs",
    "wof:placetype":"venue"
},
  "geometry": {"coordinates":[-88.089643,43.094452],"type":"Point"}
}