{
  "type": "Feature",
  "properties": {
    "iso:country":"US",
    "sg:address":"5201 N 84th Ave",
    "sg:city":"Wausau",
    "sg:phone":"+1 715 675 7425",
    "sg:postcode":"54401",
    "sg:province":"WI",
    "sg:tags":[
        "farm",
        "corn"
    ],
    "wof:name":"Harold Hintz",
    "wof:placetype":"venue"
},
  "geometry": {"coordinates":[-89.742237,45.024567],"type":"Point"}
}