{
  "type": "Feature",
  "properties": {
    "iso:country":"US",
    "sg:address":"7461 State Rd 21 and 73",
    "sg:city":"Wautoma",
    "sg:classifiers":[
        {
            "category":"Shopping",
            "subcategory":"Gifts & Souvenirs",
            "type":"Retail Goods"
        }
    ],
    "sg:phone":"+1 920 787 2303",
    "sg:postcode":"54982",
    "sg:province":"WI",
    "sg:tags":[
        "shop"
    ],
    "wof:name":"Vintage Shoppes Genuine Amish",
    "wof:placetype":"venue"
},
  "geometry": {"coordinates":[-89.268064,44.068833],"type":"Point"}
}