{
  "type": "Feature",
  "properties": {
    "iso:country":"US",
    "sg:address":"426 N Front St",
    "sg:city":"Spooner",
    "sg:classifiers":[
        {
            "category":"Building & Trades",
            "subcategory":"Construction",
            "type":"Services"
        }
    ],
    "sg:phone":"+1 715 635 3200",
    "sg:postcode":"54801",
    "sg:province":"WI",
    "sg:tags":[
        "railroad",
        "contractor"
    ],
    "wof:name":"Wisconsin Great Northern Rlrd",
    "wof:placetype":"venue"
},
  "geometry": {"coordinates":[-91.886978,45.825993],"type":"Point"}
}