{
  "type": "Feature",
  "properties": {
    "addr:full":"27754 20th Ave Cadott WI 54727",
    "addr:housenumber":"27754",
    "addr:postcode":"54727",
    "addr:street":"20Th Ave",
    "iso:country":"US",
    "sg:address":"27754 20th Ave",
    "sg:city":"Cadott",
    "sg:classifiers":[
        {
            "category":"Freight",
            "type":"Transportation"
        }
    ],
    "sg:phone":"+1 715 289 4580",
    "sg:postcode":"54727",
    "sg:province":"WI",
    "sg:tags":[
        "transport"
    ],
    "wof:name":"Pechas Auto Transport",
    "wof:placetype":"venue"
},
  "geometry": {"coordinates":[-91.111002,44.87098],"type":"Point"}
}