{
  "type": "Feature",
  "properties": {
    "iso:country":"US",
    "sg:address":"234 W Johnson St",
    "sg:city":"Fond Du Lac",
    "sg:classifiers":[
        {
            "category":"Retail",
            "subcategory":"Auto Rental",
            "type":"Services"
        }
    ],
    "sg:phone":"+1 920 922 6512",
    "sg:postcode":"54935",
    "sg:province":"WI",
    "sg:tags":[
        "trailer",
        "utility"
    ],
    "wof:name":"C C & K Hamberger LLC",
    "wof:placetype":"venue"
},
  "geometry": {"coordinates":[-88.454355,43.783625],"type":"Point"}
}