{
  "type": "Feature",
  "properties": {
    "iso:country":"US",
    "sg:address":"4222 Milwaukee St",
    "sg:city":"Madison",
    "sg:classifiers":[
        {
            "category":"Personal",
            "subcategory":"Beauty Salon",
            "type":"Services"
        }
    ],
    "sg:phone":"+1 608 241 2557",
    "sg:postcode":"53714",
    "sg:province":"WI",
    "wof:name":"Richard's Family Hair Design",
    "wof:placetype":"venue"
},
  "geometry": {"coordinates":[-89.310762,43.098651],"type":"Point"}
}