{
  "type": "Feature",
  "properties": {
    "iso:country":"US",
    "sg:address":"101 Main St W",
    "sg:city":"Ashland",
    "sg:classifiers":[
        {
            "category":"Health Services",
            "subcategory":"Clinic",
            "type":"Services"
        }
    ],
    "sg:phone":"+1 715 682 6892",
    "sg:postcode":"54806",
    "sg:province":"WI",
    "sg:tags":[
        "home",
        "care"
    ],
    "wof:name":"C H R Home Health",
    "wof:placetype":"venue"
},
  "geometry": {"coordinates":[-90.8832,46.59149],"type":"Point"}
}