{
  "type": "Feature",
  "properties": {
    "iso:country":"US",
    "sg:address":"1314 11th St E",
    "sg:city":"Menomonie",
    "sg:classifiers":[
        {
            "category":"Building & Trades",
            "subcategory":"Construction",
            "type":"Services"
        }
    ],
    "sg:phone":"+1 715 552 0968",
    "sg:postcode":"54751",
    "sg:province":"WI",
    "sg:tags":[
        "house"
    ],
    "wof:name":"Innovative Home Improvements",
    "wof:placetype":"venue"
},
  "geometry": {"coordinates":[-91.917022,44.870862],"type":"Point"}
}