{
  "type": "Feature",
  "properties": {
    "addr:full":"741 Abrams St Green Bay WI 54302",
    "addr:housenumber":"741",
    "addr:postcode":"54302",
    "addr:street":"Abrams St",
    "iso:country":"US",
    "sg:address":"741 Abrams St",
    "sg:city":"Green Bay",
    "sg:classifiers":[
        {
            "category":"Food & Beverages",
            "subcategory":"Groceries & Convenience Stores",
            "type":"Retail Goods"
        }
    ],
    "sg:phone":"+1 920 468 9722",
    "sg:postcode":"54302",
    "sg:province":"WI",
    "wof:name":"LA Piedad Mexican Mini Mart",
    "wof:placetype":"venue"
},
  "geometry": {"coordinates":[-87.98503700000001,44.492707],"type":"Point"}
}