{
  "type": "Feature",
  "properties": {
    "addr:full":"1400 Spring Grove Rd Ripon WI 54971",
    "addr:housenumber":"1400",
    "addr:postcode":"54971",
    "addr:street":"Spring Grove Rd",
    "iso:country":"US",
    "sg:address":"1400 Spring Grove Rd",
    "sg:city":"Ripon",
    "sg:classifiers":[
        {
            "category":"Real Estate",
            "subcategory":"Real Estate Agent",
            "type":"Services"
        },
        {
            "category":"Real Estate",
            "subcategory":"Real Estate Operator",
            "type":"Services"
        }
    ],
    "sg:phone":"+1 920 745 2766",
    "sg:postcode":"54971",
    "sg:province":"WI",
    "sg:tags":[
        "condominium"
    ],
    "wof:name":"Sunrise Point Condo Clubhouse",
    "wof:placetype":"venue"
},
  "geometry": {"coordinates":[-88.95620599999999,43.815523],"type":"Point"}
}