{
  "type": "Feature",
  "properties": {
    "iso:country":"US",
    "sg:address":"4732 Red Fox Ct",
    "sg:city":"West Bend",
    "sg:classifiers":[
        {
            "category":"Professional",
            "subcategory":"Business Services",
            "type":"Services"
        }
    ],
    "sg:phone":"+1 262 675 0669",
    "sg:postcode":"53095",
    "sg:province":"WI",
    "wof:name":"A&D Net Enterprises",
    "wof:placetype":"venue"
},
  "geometry": {"coordinates":[-88.095294,43.36029],"type":"Point"}
}