{
  "type": "Feature",
  "properties": {
    "addr:full":"5728 W Oklahoma Ave Milwaukee WI 53219",
    "addr:housenumber":"5728",
    "addr:postcode":"53219",
    "addr:street":"W Oklahoma Ave",
    "iso:country":"US",
    "sg:address":"5728 W Oklahoma Ave",
    "sg:city":"Milwaukee",
    "sg:classifiers":[
        {
            "category":"Shopping",
            "type":"Retail Goods"
        },
        {
            "category":"Shopping",
            "subcategory":"Gifts & Souvenirs",
            "type":"Retail Goods"
        }
    ],
    "sg:phone":"+1 414 546 6290",
    "sg:postcode":"53219",
    "sg:province":"WI",
    "sg:tags":[
        "cards",
        "memorabilia",
        "baseball",
        "sport",
        "mfg"
    ],
    "wof:name":"Prime Time Sports Card & Gifts",
    "wof:placetype":"venue"
},
  "geometry": {"coordinates":[-87.98774400000001,42.988489],"type":"Point"}
}