{
  "type": "Feature",
  "properties": {
    "iso:country":"US",
    "sg:address":"2800 Pioneer Ave",
    "sg:city":"Rice Lake",
    "sg:classifiers":[
        {
            "category":"Shopping",
            "subcategory":"Department Store",
            "type":"Retail Goods"
        }
    ],
    "sg:phone":"+1 715 234 6990",
    "sg:postcode":"54868",
    "sg:province":"WI",
    "sg:tags":[
        "discount"
    ],
    "wof:name":"Wal-Mart",
    "wof:placetype":"venue"
},
  "geometry": {"coordinates":[-91.741283,45.468165],"type":"Point"}
}