{
  "type": "Feature",
  "properties": {
    "iso:country":"US",
    "sg:address":"202 S Level St",
    "sg:city":"Dodgeville",
    "sg:classifiers":[
        {
            "category":"Real Estate",
            "subcategory":"Real Estate Operator",
            "type":"Services"
        }
    ],
    "sg:phone":"+1 608 935 5305",
    "sg:postcode":"53533",
    "sg:province":"WI",
    "sg:tags":[
        "property",
        "lessor"
    ],
    "wof:name":"Everett Olsen",
    "wof:placetype":"venue"
},
  "geometry": {"coordinates":[-90.133472,42.958997],"type":"Point"}
}