{
  "type": "Feature",
  "properties": {
    "iso:country":"US",
    "sg:address":"142 South St W",
    "sg:city":"Amery",
    "sg:classifiers":[
        {
            "category":"Freight",
            "type":"Transportation"
        }
    ],
    "sg:phone":"+1 715 268 2474",
    "sg:postcode":"54001",
    "sg:province":"WI",
    "sg:tags":[
        "operator",
        "local",
        "trucking"
    ],
    "wof:name":"Utgard Trucking",
    "wof:placetype":"venue"
},
  "geometry": {"coordinates":[-92.362866,45.305179],"type":"Point"}
}