{
  "type": "Feature",
  "properties": {
    "iso:country":"US",
    "sg:address":"11 S 2nd St",
    "sg:city":"Tomahawk",
    "sg:classifiers":[
        {
            "category":"Shopping",
            "type":"Retail Goods"
        }
    ],
    "sg:phone":"+1 715 453 3141",
    "sg:postcode":"54487",
    "sg:province":"WI",
    "sg:tags":[
        "merchandise"
    ],
    "wof:name":"Augies Collectibles",
    "wof:placetype":"venue"
},
  "geometry": {"coordinates":[-89.732041,45.470902],"type":"Point"}
}