{
  "type": "Feature",
  "properties": {
    "iso:country":"US",
    "sg:address":"424 Arrowhead Dr",
    "sg:city":"Green Bay",
    "sg:classifiers":[
        {
            "category":"Banks & Credit Unions",
            "subcategory":"Financial Services",
            "type":"Services"
        }
    ],
    "sg:phone":"+1 920 339 9535",
    "sg:postcode":"54301",
    "sg:province":"WI",
    "sg:tags":[
        "investor"
    ],
    "wof:name":"Pinnacle Uk Investment Co LLC",
    "wof:placetype":"venue"
},
  "geometry": {"coordinates":[-88.04559500000001,44.465016],"type":"Point"}
}