{
  "type": "Feature",
  "properties": {
    "iso:country":"US",
    "sg:address":"6702 Ryan St",
    "sg:city":"Schofield",
    "sg:classifiers":[
        {
            "category":"Wholesale",
            "subcategory":"Auto Parts",
            "type":"Manufacturing & Wholesale Goods"
        }
    ],
    "sg:phone":"+1 715 359 9419",
    "sg:postcode":"54476",
    "sg:province":"WI",
    "sg:tags":[
        "used"
    ],
    "sg:website":"www.cousineauauto.com",
    "wof:name":"Cousineau Auto Inc",
    "wof:placetype":"venue"
},
  "geometry": {"coordinates":[-89.536879,44.896598],"type":"Point"}
}