{
  "type": "Feature",
  "properties": {
    "iso:country":"US",
    "sg:address":"1674 160th Ave",
    "sg:city":"New Richmond",
    "sg:classifiers":[
        {
            "category":"Retail",
            "subcategory":"Repair Shop",
            "type":"Services"
        }
    ],
    "sg:phone":"+1 715 246 6389",
    "sg:postcode":"54017",
    "sg:province":"WI",
    "wof:name":"Rineck Repair & Service",
    "wof:placetype":"venue"
},
  "geometry": {"coordinates":[-92.47823699999999,45.093904],"type":"Point"}
}