{
  "type": "Feature",
  "properties": {
    "addr:full":"8468 State Rd 82 Oxford WI 53952",
    "addr:housenumber":"8468;82",
    "addr:postcode":"53952",
    "addr:street":"State Rd",
    "iso:country":"US",
    "sg:address":"8468 State Rd 82",
    "sg:city":"Oxford",
    "sg:classifiers":[
        {
            "category":"Restaurant",
            "type":"Food & Drink"
        }
    ],
    "sg:phone":"+1 608 586 4881",
    "sg:postcode":"53952",
    "sg:province":"WI",
    "wof:name":"Maggie Mae's Cafe",
    "wof:placetype":"venue"
},
  "geometry": {"coordinates":[-89.586342,43.781194],"type":"Point"}
}