{
  "type": "Feature",
  "properties": {
    "iso:country":"US",
    "sg:address":"212 E Capitol Dr",
    "sg:city":"Hartland",
    "sg:classifiers":[
        {
            "category":"Recreation",
            "type":"Entertainment"
        }
    ],
    "sg:phone":"+1 262 369 3893",
    "sg:postcode":"53029",
    "sg:province":"WI",
    "sg:tags":[
        "martial",
        "arts",
        "instruction"
    ],
    "wof:name":"Elite's Olympic Taekwondo",
    "wof:placetype":"venue"
},
  "geometry": {"coordinates":[-88.34515399999999,43.104708],"type":"Point"}
}