{
  "type": "Feature",
  "properties": {
    "addr:full":"10535 N Port Washington Rd Thiensville WI 53092",
    "addr:housenumber":"10535",
    "addr:postcode":"53092",
    "addr:street":"N Port Washington Rd",
    "iso:country":"US",
    "sg:address":"10535 N Port Washington Rd",
    "sg:city":"Thiensville",
    "sg:classifiers":[
        {
            "category":"Insurance",
            "subcategory":"Insurance Agent",
            "type":"Services"
        }
    ],
    "sg:phone":"+1 262 241 1800",
    "sg:postcode":"53092",
    "sg:province":"WI",
    "wof:name":"AFLAC",
    "wof:placetype":"venue"
},
  "geometry": {"coordinates":[-87.924335,43.207582],"type":"Point"}
}