{
  "type": "Feature",
  "properties": {
    "iso:country":"US",
    "sg:address":"416 Scott Ct",
    "sg:city":"Hartford",
    "sg:classifiers":[
        {
            "category":"Insurance",
            "subcategory":"Insurance Agent",
            "type":"Services"
        }
    ],
    "sg:phone":"+1 262 673 2804",
    "sg:postcode":"53027",
    "sg:province":"WI",
    "wof:name":"Zurich Small Business",
    "wof:placetype":"venue"
},
  "geometry": {"coordinates":[-88.373572,43.302892],"type":"Point"}
}