{
  "type": "Feature",
  "properties": {
    "iso:country":"US",
    "sg:address":"2011 Spring St",
    "sg:city":"Stockholm",
    "sg:classifiers":[
        {
            "category":"Building & Trades",
            "subcategory":"Construction",
            "type":"Services"
        }
    ],
    "sg:phone":"+1 715 442 9038",
    "sg:postcode":"54769",
    "sg:province":"WI",
    "sg:tags":[
        "contractor"
    ],
    "wof:name":"Wallin Roofing & Construction",
    "wof:placetype":"venue"
},
  "geometry": {"coordinates":[-92.262281,44.48291],"type":"Point"}
}