{
  "type": "Feature",
  "properties": {
    "iso:country":"US",
    "sg:address":"1131 County Line Rd",
    "sg:city":"Deer Park",
    "sg:classifiers":[
        {
            "category":"Retail",
            "subcategory":"Repair Shop",
            "type":"Services"
        }
    ],
    "sg:phone":"+1 715 269 5271",
    "sg:postcode":"54007",
    "sg:province":"WI",
    "sg:tags":[
        "water",
        "well",
        "drilling"
    ],
    "wof:name":"Bills Pump Service",
    "wof:placetype":"venue"
},
  "geometry": {"coordinates":[-92.400138,45.726376],"type":"Point"}
}