{
  "type": "Feature",
  "properties": {
    "addr:full":"14016 W Avon North Townline Rd Brodhead WI 53520",
    "addr:housenumber":"14016",
    "addr:postcode":"53520",
    "addr:street":"W Avon North Townline Rd",
    "iso:country":"US",
    "sg:address":"14016 W Avon North Townline Rd",
    "sg:city":"Brodhead",
    "sg:phone":"+1 608 879 2883",
    "sg:postcode":"53520",
    "sg:province":"WI",
    "sg:tags":[
        "farm"
    ],
    "wof:name":"Davey Lee",
    "wof:placetype":"venue"
},
  "geometry": {"coordinates":[-89.279387,42.585648],"type":"Point"}
}