{
  "type": "Feature",
  "properties": {
    "addr:full":"6150 W Fond du Lac Ave Milwaukee WI 53218",
    "addr:housenumber":"6150",
    "addr:postcode":"53218",
    "addr:street":"W Fond Du Lac Ave",
    "iso:country":"US",
    "sg:address":"6150 W Fond du Lac Ave",
    "sg:city":"Milwaukee",
    "sg:classifiers":[
        {
            "category":"Education",
            "subcategory":"Special Training",
            "type":"Public Place"
        }
    ],
    "sg:phone":"+1 414 463 4252",
    "sg:postcode":"53218",
    "sg:province":"WI",
    "sg:tags":[
        "county",
        "evaluation",
        "for",
        "doe"
    ],
    "wof:name":"Better Living Academy Inc",
    "wof:placetype":"venue"
},
  "geometry": {"coordinates":[-87.98766500000001,43.098658],"type":"Point"}
}