{
  "type": "Feature",
  "properties": {
    "iso:country":"US",
    "sg:address":"16004 US Hwy 63 S",
    "sg:city":"Hayward",
    "sg:classifiers":[
        {
            "category":"Insurance",
            "subcategory":"Insurance Agent",
            "type":"Services"
        }
    ],
    "sg:phone":"+1 715 634 9238",
    "sg:postcode":"54843",
    "sg:province":"WI",
    "wof:name":"Thrivent Financial-Lutherans",
    "wof:placetype":"venue"
},
  "geometry": {"coordinates":[-91.49248900000001,46.007412],"type":"Point"}
}