{
  "type": "Feature",
  "properties": {
    "addr:full":"2005 Co Rd Zz Sister Bay WI 54234",
    "addr:housenumber":"2005",
    "addr:postcode":"54234",
    "addr:street":"Co Rd",
    "iso:country":"US",
    "sg:address":"2005 Co Rd Zz",
    "sg:city":"Sister Bay",
    "sg:classifiers":[
        {
            "category":"Retail",
            "subcategory":"Auto Repair",
            "type":"Services"
        }
    ],
    "sg:phone":"+1 920 854 2019",
    "sg:postcode":"54234",
    "sg:province":"WI",
    "sg:tags":[
        "body",
        "automobile",
        "painting"
    ],
    "wof:name":"Mark Sunstrom's Auto Body",
    "wof:placetype":"venue"
},
  "geometry": {"coordinates":[-87.09791800000001,45.185542],"type":"Point"}
}