{
  "type": "Feature",
  "properties": {
    "iso:country":"US",
    "sg:address":"3224 E Hampshire St",
    "sg:city":"Milwaukee",
    "sg:classifiers":[
        {
            "category":"Manufacturing",
            "subcategory":"Jewelry",
            "type":"Manufacturing & Wholesale Goods"
        }
    ],
    "sg:phone":"+1 414 964 9444",
    "sg:postcode":"53211",
    "sg:province":"WI",
    "sg:tags":[
        "mfg",
        "material",
        "business",
        "furniture"
    ],
    "wof:name":"Checota Ellen Designs",
    "wof:placetype":"venue"
},
  "geometry": {"coordinates":[-87.870245,43.07553],"type":"Point"}
}