{
  "type": "Feature",
  "properties": {
    "iso:country":"US",
    "sg:address":"8430 Co Rd I",
    "sg:city":"Oxford",
    "sg:classifiers":[
        {
            "category":"Building & Trades",
            "subcategory":"Construction",
            "type":"Services"
        }
    ],
    "sg:phone":"+1 608 586 5226",
    "sg:postcode":"53952",
    "sg:province":"WI",
    "sg:tags":[
        "excavation",
        "contractor"
    ],
    "wof:name":"Steve Polzin Excavating",
    "wof:placetype":"venue"
},
  "geometry": {"coordinates":[-89.580128,43.779479],"type":"Point"}
}