{
  "type": "Feature",
  "properties": {
    "iso:country":"US",
    "sg:address":"3118 N Teutonia Ave",
    "sg:city":"Milwaukee",
    "sg:classifiers":[
        {
            "category":"Professional",
            "type":"Services"
        }
    ],
    "sg:phone":"+1 414 264 6155",
    "sg:postcode":"53206",
    "sg:province":"WI",
    "wof:name":"Dir Of Continuation Svc",
    "wof:placetype":"venue"
},
  "geometry": {"coordinates":[-87.93259,43.077617],"type":"Point"}
}