{
  "type": "Feature",
  "properties": {
    "addr:full":"519 N Main St Oshkosh WI 54901",
    "addr:housenumber":"519",
    "addr:postcode":"54901",
    "addr:street":"N Main St",
    "iso:country":"US",
    "sg:address":"519 N Main St",
    "sg:city":"Oshkosh",
    "sg:classifiers":[
        {
            "category":"Recreation",
            "type":"Entertainment"
        },
        {
            "category":"Bars & Pubs",
            "type":"Food & Drink"
        }
    ],
    "sg:phone":"+1 920 235 4880",
    "sg:postcode":"54901",
    "sg:province":"WI",
    "sg:tags":[
        "parlor",
        "billiard",
        "drinking",
        "sporting"
    ],
    "wof:name":"Magnet Billiards",
    "wof:placetype":"venue"
},
  "geometry": {"coordinates":[-88.537627,44.021696],"type":"Point"}
}