{
  "type": "Feature",
  "properties": {
    "iso:country":"US",
    "sg:address":"12845 W Weatherstone Blvd",
    "sg:city":"New Berlin",
    "sg:classifiers":[
        {
            "category":"Building & Trades",
            "subcategory":"Plumbing",
            "type":"Services"
        }
    ],
    "sg:phone":"+1 262 785 1502",
    "sg:postcode":"53151",
    "sg:province":"WI",
    "sg:tags":[
        "contractor"
    ],
    "wof:name":"Andersen Plumbing Inc",
    "wof:placetype":"venue"
},
  "geometry": {"coordinates":[-88.075357,42.967876],"type":"Point"}
}