{
  "type": "Feature",
  "properties": {
    "addr:full":"504 Lakeland Rd Shawano WI 54166",
    "addr:housenumber":"504",
    "addr:postcode":"54166",
    "addr:street":"Lakeland Rd",
    "iso:country":"US",
    "sg:address":"504 Lakeland Rd",
    "sg:city":"Shawano",
    "sg:classifiers":[
        {
            "category":"Government",
            "subcategory":"Office",
            "type":"Public Place"
        }
    ],
    "sg:phone":"+1 715 526 3240",
    "sg:postcode":"54166",
    "sg:province":"WI",
    "wof:name":"Crisis Line",
    "wof:placetype":"venue"
},
  "geometry": {"coordinates":[-88.583685,44.779843],"type":"Point"}
}