{
  "type": "Feature",
  "properties": {
    "iso:country":"US",
    "sg:address":"10602 N Port Washington Rd",
    "sg:city":"Thiensville",
    "sg:classifiers":[
        {
            "category":"Professional",
            "subcategory":"Advertising",
            "type":"Services"
        }
    ],
    "sg:phone":"+1 262 241 0235",
    "sg:postcode":"53092",
    "sg:province":"WI",
    "sg:tags":[
        "agency"
    ],
    "wof:name":"Creative Advertising Services",
    "wof:placetype":"venue"
},
  "geometry": {"coordinates":[-87.924092,43.211318],"type":"Point"}
}