{
  "type": "Feature",
  "properties": {
    "addr:full":"10329 Richolson Dr Sauk City WI 53583",
    "addr:housenumber":"10329",
    "addr:postcode":"53583",
    "addr:street":"Richolson Dr",
    "iso:country":"US",
    "sg:address":"10329 Richolson Dr",
    "sg:city":"Sauk City",
    "sg:classifiers":[
        {
            "category":"Retail",
            "subcategory":"Auto Repair",
            "type":"Services"
        }
    ],
    "sg:phone":"+1 608 643 0769",
    "sg:postcode":"53583",
    "sg:province":"WI",
    "sg:tags":[
        "general"
    ],
    "wof:name":"Richolson Repair",
    "wof:placetype":"venue"
},
  "geometry": {"coordinates":[-89.754408,43.268835],"type":"Point"}
}