{
  "type": "Feature",
  "properties": {
    "iso:country":"US",
    "sg:address":"409 S Webb St",
    "sg:city":"Wittenberg",
    "sg:classifiers":[
        {
            "category":"Home & Garden",
            "subcategory":"Hardware",
            "type":"Retail Goods"
        }
    ],
    "sg:phone":"+1 715 253 2733",
    "sg:postcode":"54499",
    "sg:province":"WI",
    "wof:name":"Jerry's Hardware",
    "wof:placetype":"venue"
},
  "geometry": {"coordinates":[-89.170406,44.823856],"type":"Point"}
}