{
  "type": "Feature",
  "properties": {
    "iso:country":"US",
    "sg:address":"6829 Stone Lake Rd",
    "sg:city":"Stone Lake",
    "sg:classifiers":[
        {
            "category":"Farming",
            "subcategory":"Dairy Farm",
            "type":"Manufacturing & Wholesale Goods"
        }
    ],
    "sg:phone":"+1 715 865 2405",
    "sg:postcode":"54876",
    "sg:province":"WI",
    "wof:name":"Michael J Jarvis",
    "wof:placetype":"venue"
},
  "geometry": {"coordinates":[-91.541201,45.870554],"type":"Point"}
}