{
  "type": "Feature",
  "properties": {
    "iso:country":"US",
    "sg:address":"8825 N Lake Dr",
    "sg:city":"Milwaukee",
    "sg:classifiers":[
        {
            "category":"Restaurant",
            "type":"Food & Drink"
        }
    ],
    "sg:menulink":"http://www.allmenus.com/wi/bayside/8095-pandis-in-bayside/menu/",
    "sg:phone":"+1 414 352 7300",
    "sg:postcode":"53217",
    "sg:province":"WI",
    "sg:tags":[
        "american"
    ],
    "wof:name":"Pandi's In Bayside",
    "wof:placetype":"venue"
},
  "geometry": {"coordinates":[-87.89613199999999,43.177144],"type":"Point"}
}