{
  "type": "Feature",
  "properties": {
    "addr:full":"221 N Louis Ave Coleman WI 54112",
    "addr:housenumber":"221",
    "addr:postcode":"54112",
    "addr:street":"N Louis Ave",
    "iso:country":"US",
    "sg:address":"221 N Louis Ave",
    "sg:city":"Coleman",
    "sg:classifiers":[
        {
            "category":"Organizations",
            "subcategory":"Religious Organization",
            "type":"Services"
        }
    ],
    "sg:phone":"+1 920 897 3422",
    "sg:postcode":"54112",
    "sg:province":"WI",
    "wof:name":"Trinity Ev Ltheran Church Wels",
    "wof:placetype":"venue"
},
  "geometry": {"coordinates":[-88.03192799999999,45.068966],"type":"Point"}
}