{
  "type": "Feature",
  "properties": {
    "addr:full":"4676 Co Hwy P West Bend WI 53095",
    "addr:housenumber":"4676",
    "addr:postcode":"53095",
    "addr:street":"Co Hwy P West",
    "iso:country":"US",
    "sg:address":"4676 Co Hwy P",
    "sg:city":"West Bend",
    "sg:classifiers":[
        {
            "category":"Freight",
            "type":"Transportation"
        }
    ],
    "sg:phone":"+1 262 677 2051",
    "sg:postcode":"53095",
    "sg:province":"WI",
    "sg:tags":[
        "operator",
        "local",
        "trucking"
    ],
    "wof:name":"J & R Trckg of W Bend Wsconsin",
    "wof:placetype":"venue"
},
  "geometry": {"coordinates":[-88.18163300000001,43.362462],"type":"Point"}
}