{
  "type": "Feature",
  "properties": {
    "iso:country":"US",
    "sg:address":"124 N Main St",
    "sg:city":"Neillsville",
    "sg:classifiers":[
        {
            "category":"Utilities",
            "subcategory":"Electric",
            "type":"Services"
        }
    ],
    "sg:phone":"+1 715 267 4705",
    "sg:postcode":"54436",
    "sg:province":"WI",
    "sg:tags":[
        "company"
    ],
    "wof:name":"Clark Electric Cooperative",
    "wof:placetype":"venue"
},
  "geometry": {"coordinates":[-90.46146299999999,44.59037],"type":"Point"}
}