{
  "type": "Feature",
  "properties": {
    "iso:country":"US",
    "sg:address":"1279 Woodsview Cir",
    "sg:city":"Stoughton",
    "sg:classifiers":[
        {
            "category":"Building & Trades",
            "subcategory":"Construction",
            "type":"Services"
        }
    ],
    "sg:phone":"+1 608 873 8016",
    "sg:postcode":"53589",
    "sg:province":"WI",
    "sg:tags":[
        "house"
    ],
    "wof:name":"A&O Builders",
    "wof:placetype":"venue"
},
  "geometry": {"coordinates":[-89.283363,42.915974],"type":"Point"}
}