{
  "type": "Feature",
  "properties": {
    "iso:country":"US",
    "sg:address":"5912 75th St",
    "sg:city":"Kenosha",
    "sg:classifiers":[
        {
            "category":"Banks & Credit Unions",
            "subcategory":"Bank",
            "type":"Services"
        }
    ],
    "sg:phone":"+1 262 697 7773",
    "sg:postcode":"53142",
    "sg:province":"WI",
    "sg:tags":[
        "correspondent",
        "banker",
        "mortgage"
    ],
    "wof:name":"Platinum Home Mortgage Corp",
    "wof:placetype":"venue"
},
  "geometry": {"coordinates":[-87.87764900000001,42.566638],"type":"Point"}
}