{
  "type": "Feature",
  "properties": {
    "iso:country":"US",
    "sg:address":"8980 Fish Hatchery Rd",
    "sg:city":"Burlington",
    "sg:classifiers":[
        {
            "category":"Personal",
            "type":"Services"
        }
    ],
    "sg:phone":"+1 262 539 2798",
    "sg:postcode":"53105",
    "sg:province":"WI",
    "wof:name":"Lovell Licensing Service",
    "wof:placetype":"venue"
},
  "geometry": {"coordinates":[-88.267218,42.611281],"type":"Point"}
}