{
  "type": "Feature",
  "properties": {
    "iso:country":"US",
    "sg:address":"101 Bay Beach Rd",
    "sg:city":"Green Bay",
    "sg:classifiers":[
        {
            "category":"Recreation",
            "subcategory":"Marina",
            "type":"Entertainment"
        }
    ],
    "sg:phone":"+1 920 884 1464",
    "sg:postcode":"54302",
    "sg:province":"WI",
    "wof:name":"South Bay Marina Gas Dock",
    "wof:placetype":"venue"
},
  "geometry": {"coordinates":[-87.995813,44.535869],"type":"Point"}
}