{
  "type": "Feature",
  "properties": {
    "iso:country":"US",
    "sg:address":"5572 Sunset Ter",
    "sg:city":"Pardeeville",
    "sg:phone":"+1 608 429 2815",
    "sg:postcode":"53954",
    "sg:province":"WI",
    "sg:tags":[
        "farm",
        "corn",
        "crop",
        "general"
    ],
    "wof:name":"Sanderson Prairie Farms Inc",
    "wof:placetype":"venue"
},
  "geometry": {"coordinates":[-89.28134300000001,43.541639],"type":"Point"}
}