{
  "type": "Feature",
  "properties": {
    "iso:country":"US",
    "sg:address":"11612 N Crestwood Dr",
    "sg:city":"Edgerton",
    "sg:classifiers":[
        {
            "category":"Professional",
            "subcategory":"Accounting & Tax Preparation",
            "type":"Services"
        }
    ],
    "sg:phone":"+1 608 884 7576",
    "sg:postcode":"53534",
    "sg:province":"WI",
    "wof:name":"All Enterprises",
    "wof:placetype":"venue"
},
  "geometry": {"coordinates":[-89.012605,42.842331],"type":"Point"}
}