{
  "type": "Feature",
  "properties": {
    "iso:country":"US",
    "sg:address":"150 N Sunnyslope Rd",
    "sg:city":"Brookfield",
    "sg:classifiers":[
        {
            "category":"Professional",
            "subcategory":"Management & Consulting",
            "type":"Services"
        },
        {
            "category":"Health Services",
            "subcategory":"Clinic",
            "type":"Services"
        }
    ],
    "sg:phone":"+1 262 796 8007",
    "sg:postcode":"53005",
    "sg:province":"WI",
    "sg:tags":[
        "consultant",
        "medical",
        "legal"
    ],
    "wof:name":"Medical Impressions LLC",
    "wof:placetype":"venue"
},
  "geometry": {"coordinates":[-88.086781,43.035053],"type":"Point"}
}