{
  "type": "Feature",
  "properties": {
    "iso:country":"US",
    "sg:address":"417 Kittiver Ct",
    "sg:city":"Neenah",
    "sg:classifiers":[
        {
            "category":"Shopping",
            "subcategory":"Gifts & Souvenirs",
            "type":"Retail Goods"
        }
    ],
    "sg:phone":"+1 920 725 5422",
    "sg:postcode":"54956",
    "sg:province":"WI",
    "wof:name":"Different Drummer",
    "wof:placetype":"venue"
},
  "geometry": {"coordinates":[-88.438034,44.193146],"type":"Point"}
}