{
  "type": "Feature",
  "properties": {
    "iso:country":"US",
    "sg:address":"2305 Atwood Ave",
    "sg:city":"Madison",
    "sg:classifiers":[
        {
            "category":"Retail",
            "subcategory":"Auto Repair",
            "type":"Services"
        }
    ],
    "sg:phone":"+1 608 249 7957",
    "sg:postcode":"53704",
    "sg:province":"WI",
    "sg:tags":[
        "body"
    ],
    "wof:name":"Lynch Auto Body Inc",
    "wof:placetype":"venue"
},
  "geometry": {"coordinates":[-89.347143,43.093608],"type":"Point"}
}