{
  "type": "Feature",
  "properties": {
    "iso:country":"US",
    "sg:address":"5718 52nd St",
    "sg:city":"Kenosha",
    "sg:classifiers":[
        {
            "category":"Manufacturing",
            "subcategory":"Furniture",
            "type":"Manufacturing & Wholesale Goods"
        }
    ],
    "sg:phone":"+1 262 658 4114",
    "sg:postcode":"53144",
    "sg:province":"WI",
    "sg:tags":[
        "top",
        "counter"
    ],
    "wof:name":"Laminated Products Inc",
    "wof:placetype":"venue"
},
  "geometry": {"coordinates":[-87.876457,42.588761],"type":"Point"}
}