{
  "type": "Feature",
  "properties": {
    "iso:country":"US",
    "sg:address":"200 Industrial Dr",
    "sg:city":"Beaver Dam",
    "sg:classifiers":[
        {
            "category":"Manufacturing",
            "subcategory":"Motor Vehicles & Parts",
            "type":"Manufacturing & Wholesale Goods"
        }
    ],
    "sg:phone":"+1 920 887 3721",
    "sg:postcode":"53916",
    "sg:province":"WI",
    "sg:tags":[
        "tank",
        "component"
    ],
    "sg:website":"www.apachestainless.com",
    "wof:name":"Apache Stainless Equipment",
    "wof:placetype":"venue"
},
  "geometry": {"coordinates":[-88.827478,43.477245],"type":"Point"}
}