{
  "type": "Feature",
  "properties": {
    "iso:country":"US",
    "sg:address":"1840 Sycamore Ave",
    "sg:city":"Racine",
    "sg:classifiers":[
        {
            "category":"Social Services",
            "subcategory":"Job Training",
            "type":"Services"
        },
        {
            "category":"Education",
            "subcategory":"Vocational School",
            "type":"Public Place"
        }
    ],
    "sg:phone":"+1 262 632 7005",
    "sg:postcode":"53406",
    "sg:province":"WI",
    "sg:tags":[
        "apprenticeship",
        "program"
    ],
    "wof:name":"Southeastern Sheet Metal Joint",
    "wof:placetype":"venue"
},
  "geometry": {"coordinates":[-87.84254900000001,42.709127],"type":"Point"}
}