{
  "type": "Feature",
  "properties": {
    "iso:country":"US",
    "sg:address":"1626 S Harbor Dr",
    "sg:city":"Milwaukee",
    "sg:classifiers":[
        {
            "category":"Freight",
            "type":"Transportation"
        }
    ],
    "sg:phone":"+1 414 271 8700",
    "sg:postcode":"53207",
    "sg:province":"WI",
    "sg:tags":[
        "bulk",
        "storage"
    ],
    "wof:name":"S T Svc",
    "wof:placetype":"venue"
},
  "geometry": {"coordinates":[-87.894977,43.00799],"type":"Point"}
}