{
  "type": "Feature",
  "properties": {
    "addr:full":"2709 Great Forest Dr West Bend WI 53090",
    "addr:housenumber":"2709",
    "addr:postcode":"53090",
    "addr:street":"Great Forest Dr",
    "iso:country":"US",
    "sg:address":"2709 Great Forest Dr",
    "sg:city":"West Bend",
    "sg:classifiers":[
        {
            "category":"Building & Trades",
            "subcategory":"Construction",
            "type":"Services"
        }
    ],
    "sg:phone":"+1 262 338 9400",
    "sg:postcode":"53090",
    "sg:province":"WI",
    "sg:tags":[
        "contractor"
    ],
    "sg:website":"www.brookstonemortgageservices.com",
    "wof:name":"Brookstone Homes",
    "wof:placetype":"venue"
},
  "geometry": {"coordinates":[-88.221039,43.44166],"type":"Point"}
}