{
  "type": "Feature",
  "properties": {
    "iso:country":"US",
    "sg:address":"6175 E Metra Dr",
    "sg:city":"De Forest",
    "sg:classifiers":[
        {
            "category":"Real Estate",
            "subcategory":"Real Estate Agent",
            "type":"Services"
        }
    ],
    "sg:phone":"+1 608 242 1383",
    "sg:postcode":"53532",
    "sg:province":"WI",
    "wof:name":"Welton Properties LLC",
    "wof:placetype":"venue"
},
  "geometry": {"coordinates":[-89.324337,43.186279],"type":"Point"}
}