{
  "type": "Feature",
  "properties": {
    "iso:country":"US",
    "sg:address":"5061 Co Rd U",
    "sg:city":"Shawano",
    "sg:classifiers":[
        {
            "category":"Professional",
            "type":"Services"
        }
    ],
    "sg:phone":"+1 715 526 6881",
    "sg:postcode":"54166",
    "sg:province":"WI",
    "sg:tags":[
        "establishment"
    ],
    "wof:name":"Northwest Forest Products",
    "wof:placetype":"venue"
},
  "geometry": {"coordinates":[-88.766693,44.776678],"type":"Point"}
}