{
  "type": "Feature",
  "properties": {
    "iso:country":"US",
    "sg:address":"401 Bernard St",
    "sg:city":"Watertown",
    "sg:classifiers":[
        {
            "category":"Building & Trades",
            "subcategory":"Equipment Rental",
            "type":"Services"
        }
    ],
    "sg:phone":"+1 920 261 2284",
    "sg:postcode":"53094",
    "sg:province":"WI",
    "sg:tags":[
        "yard"
    ],
    "wof:name":"Ace Rental Ctr",
    "wof:placetype":"venue"
},
  "geometry": {"coordinates":[-88.730828,43.186564],"type":"Point"}
}