{
  "type": "Feature",
  "properties": {
    "iso:country":"US",
    "sg:address":"650 Pearl St",
    "sg:city":"Rib Lake",
    "sg:classifiers":[
        {
            "category":"Health Services",
            "subcategory":"Nursing And Care Facility",
            "type":"Services"
        }
    ],
    "sg:phone":"+1 715 427 5291",
    "sg:postcode":"54470",
    "sg:province":"WI",
    "sg:tags":[
        "home",
        "convalescent"
    ],
    "wof:name":"Rib Lake Health Care Ctr",
    "wof:placetype":"venue"
},
  "geometry": {"coordinates":[-90.20530599999999,45.317117],"type":"Point"}
}