{
  "type": "Feature",
  "properties": {
    "iso:country":"US",
    "sg:address":"21795 Doral Rd",
    "sg:city":"Waukesha",
    "sg:classifiers":[
        {
            "category":"Manufacturing",
            "subcategory":"Tools & Machinery",
            "type":"Manufacturing & Wholesale Goods"
        }
    ],
    "sg:phone":"+1 262 798 9777",
    "sg:postcode":"53186",
    "sg:province":"WI",
    "sg:tags":[
        "concrete",
        "designed",
        "production",
        "built",
        "equipment"
    ],
    "sg:website":"www.elematic.com",
    "wof:name":"Elematic Inc",
    "wof:placetype":"venue"
},
  "geometry": {"coordinates":[-88.180463,43.041929],"type":"Point"}
}