{
  "type": "Feature",
  "properties": {
    "iso:country":"US",
    "sg:address":"1601 Industrial St",
    "sg:city":"Hudson",
    "sg:classifiers":[
        {
            "category":"Professional",
            "subcategory":"Employment Agencies",
            "type":"Services"
        }
    ],
    "sg:phone":"+1 715 386 7676",
    "sg:postcode":"54016",
    "sg:province":"WI",
    "sg:tags":[
        "help",
        "contractor"
    ],
    "wof:name":"St Croix Valley Staffing",
    "wof:placetype":"venue"
},
  "geometry": {"coordinates":[-92.73413499999999,44.952609],"type":"Point"}
}