{
  "type": "Feature",
  "properties": {
    "addr:full":"431 E Albert St Portage WI 53901",
    "addr:housenumber":"431",
    "addr:postcode":"53901",
    "addr:street":"E Albert St",
    "iso:country":"US",
    "sg:address":"431 E Albert St",
    "sg:city":"Portage",
    "sg:classifiers":[
        {
            "category":"Shopping",
            "type":"Retail Goods"
        }
    ],
    "sg:phone":"+1 608 742 3678",
    "sg:postcode":"53901",
    "sg:province":"WI",
    "sg:tags":[
        "merchandise"
    ],
    "wof:name":"Kept In Stitches",
    "wof:placetype":"venue"
},
  "geometry": {"coordinates":[-89.443566,43.549851],"type":"Point"}
}