{
  "type": "Feature",
  "properties": {
    "addr:full":"6435 W North Ave Milwaukee WI 53213",
    "addr:housenumber":"6435",
    "addr:postcode":"53213",
    "addr:street":"W North Ave",
    "iso:country":"US",
    "sg:address":"6435 W North Ave",
    "sg:city":"Milwaukee",
    "sg:classifiers":[
        {
            "category":"Personal",
            "subcategory":"Beauty Salon",
            "type":"Services"
        }
    ],
    "sg:phone":"+1 414 774 5211",
    "sg:postcode":"53213",
    "sg:province":"WI",
    "sg:tags":[
        "shop"
    ],
    "wof:name":"Eastowne Hair Care Inc",
    "wof:placetype":"venue"
},
  "geometry": {"coordinates":[-87.99315,43.060647],"type":"Point"}
}