{
  "type": "Feature",
  "properties": {
    "iso:country":"US",
    "sg:address":"137 Grove St",
    "sg:city":"Waterloo",
    "sg:classifiers":[
        {
            "category":"Manufacturing",
            "subcategory":"Lumber",
            "type":"Manufacturing & Wholesale Goods"
        }
    ],
    "sg:phone":"+1 920 478 2342",
    "sg:postcode":"53594",
    "sg:province":"WI",
    "sg:tags":[
        "farm",
        "tree"
    ],
    "wof:name":"Mikes Tree Service Waterloo",
    "wof:placetype":"venue"
},
  "geometry": {"coordinates":[-88.980519,43.184627],"type":"Point"}
}