{
  "type": "Feature",
  "properties": {
    "addr:full":"356 145th Ave Hudson WI 54082",
    "addr:housenumber":"356",
    "addr:postcode":"54082",
    "addr:street":"145Th Ave",
    "iso:country":"US",
    "sg:address":"356 145th Ave",
    "sg:city":"Hudson",
    "sg:classifiers":[
        {
            "category":"Building & Trades",
            "subcategory":"Construction",
            "type":"Services"
        }
    ],
    "sg:phone":"+1 715 549 6158",
    "sg:postcode":"54082",
    "sg:province":"WI",
    "sg:tags":[
        "hanging",
        "contractor"
    ],
    "wof:name":"N C Painting",
    "wof:placetype":"venue"
},
  "geometry": {"coordinates":[-92.734065,45.071912],"type":"Point"}
}