{
  "type": "Feature",
  "properties": {
    "iso:country":"US",
    "sg:address":"156 S Main St",
    "sg:city":"Iron Ridge",
    "sg:classifiers":[
        {
            "category":"Banks & Credit Unions",
            "subcategory":"Bank",
            "type":"Services"
        }
    ],
    "sg:phone":"+1 920 387 3640",
    "sg:postcode":"53035",
    "sg:province":"WI",
    "wof:name":"Horicon State Bank",
    "wof:placetype":"venue"
},
  "geometry": {"coordinates":[-88.531335,43.397669],"type":"Point"}
}