{
  "type": "Feature",
  "properties": {
    "iso:country":"US",
    "sg:address":"864 Country Club Ln",
    "sg:city":"Fond Du Lac",
    "sg:classifiers":[
        {
            "category":"Arts & Performance",
            "subcategory":"Theater",
            "type":"Entertainment"
        }
    ],
    "sg:phone":"+1 920 929 9999",
    "sg:postcode":"54935",
    "sg:province":"WI",
    "sg:tags":[
        "theatrical"
    ],
    "wof:name":"Bravo Productions Inc",
    "wof:placetype":"venue"
},
  "geometry": {"coordinates":[-88.405326,43.757261],"type":"Point"}
}