{
  "type": "Feature",
  "properties": {
    "iso:country":"US",
    "sg:address":"3718 Country Grove Dr",
    "sg:city":"Madison",
    "sg:classifiers":[
        {
            "category":"Real Estate",
            "subcategory":"Real Estate Agent",
            "type":"Services"
        }
    ],
    "sg:phone":"+1 608 663 1778",
    "sg:postcode":"53719",
    "sg:province":"WI",
    "sg:tags":[
        "investment"
    ],
    "wof:name":"Corcoran Doty Properties",
    "wof:placetype":"venue"
},
  "geometry": {"coordinates":[-89.513253,43.010472],"type":"Point"}
}