{
  "type": "Feature",
  "properties": {
    "addr:full":"930 Crawford St Lake Geneva WI 53147",
    "addr:housenumber":"930",
    "addr:postcode":"53147",
    "addr:street":"Crawford St",
    "iso:country":"US",
    "sg:address":"930 Crawford St",
    "sg:city":"Lake Geneva",
    "sg:classifiers":[
        {
            "category":"Building & Trades",
            "subcategory":"Construction",
            "type":"Services"
        }
    ],
    "sg:phone":"+1 262 249 0700",
    "sg:postcode":"53147",
    "sg:province":"WI",
    "sg:tags":[
        "new",
        "remodeling",
        "contractor"
    ],
    "wof:name":"Fine Line Construction",
    "wof:placetype":"venue"
},
  "geometry": {"coordinates":[-88.430407,42.600384],"type":"Point"}
}