{
  "type": "Feature",
  "properties": {
    "addr:full":"607 S 24th Ave Wausau WI 54401",
    "addr:housenumber":"607",
    "addr:postcode":"54401",
    "addr:street":"S 24Th Ave",
    "iso:country":"US",
    "sg:address":"607 S 24th Ave",
    "sg:city":"Wausau",
    "sg:classifiers":[
        {
            "category":"Retail",
            "subcategory":"Portrait Studio",
            "type":"Services"
        }
    ],
    "sg:phone":"+1 715 843 0707",
    "sg:postcode":"54401",
    "sg:province":"WI",
    "sg:tags":[
        "photo"
    ],
    "wof:name":"UPS Store",
    "wof:placetype":"venue"
},
  "geometry": {"coordinates":[-89.66574,44.956115],"type":"Point"}
}