{
  "type": "Feature",
  "properties": {
    "iso:country":"US",
    "sg:address":"2213 250th St",
    "sg:city":"Deer Park",
    "sg:classifiers":[
        {
            "category":"Professional",
            "type":"Services"
        }
    ],
    "sg:phone":"+1 715 269 5363",
    "sg:postcode":"54007",
    "sg:province":"WI",
    "wof:name":"Tripple Birch",
    "wof:placetype":"venue"
},
  "geometry": {"coordinates":[-92.303603,45.185734],"type":"Point"}
}