{
  "type": "Feature",
  "properties": {
    "iso:country":"US",
    "sg:address":"7137 Trainor Rd",
    "sg:city":"Dodgeville",
    "sg:classifiers":[
        {
            "category":"Farming",
            "subcategory":"Dairy Farm",
            "type":"Manufacturing & Wholesale Goods"
        }
    ],
    "sg:phone":"+1 608 924 3205",
    "sg:postcode":"53533",
    "sg:province":"WI",
    "wof:name":"Thomas McGraw",
    "wof:placetype":"venue"
},
  "geometry": {"coordinates":[-89.964176,42.943856],"type":"Point"}
}