{
  "type": "Feature",
  "properties": {
    "iso:country":"US",
    "sg:address":"7325 30th Ave",
    "sg:city":"Kenosha",
    "sg:classifiers":[
        {
            "category":"Manufacturing",
            "subcategory":"Printing",
            "type":"Manufacturing & Wholesale Goods"
        }
    ],
    "sg:phone":"+1 262 658 1628",
    "sg:postcode":"53142",
    "sg:province":"IL",
    "sg:tags":[
        "commercial"
    ],
    "sg:website":"www.badgerprinting.com",
    "wof:name":"Badger Press-Photographics Inc",
    "wof:placetype":"venue"
},
  "geometry": {"coordinates":[-87.845176,42.56733],"type":"Point"}
}