{
  "type": "Feature",
  "properties": {
    "addr:full":"4330 W Fond du Lac Ave Milwaukee WI 53216",
    "addr:housenumber":"4330",
    "addr:postcode":"53216",
    "addr:street":"W Fond Du Lac Ave",
    "iso:country":"US",
    "sg:address":"4330 W Fond du Lac Ave",
    "sg:city":"Milwaukee",
    "sg:classifiers":[
        {
            "category":"Personal",
            "subcategory":"Beauty Salon",
            "type":"Services"
        }
    ],
    "sg:phone":"+1 414 871 0841",
    "sg:postcode":"53216",
    "sg:province":"WI",
    "sg:tags":[
        "shop"
    ],
    "wof:name":"Wendy's Hair Studio",
    "wof:placetype":"venue"
},
  "geometry": {"coordinates":[-87.969263,43.084395],"type":"Point"}
}