{
  "type": "Feature",
  "properties": {
    "iso:country":"US",
    "sg:address":"6281 Reynolds Ridge Rd",
    "sg:city":"Potosi",
    "sg:classifiers":[
        {
            "category":"Professional",
            "type":"Services"
        }
    ],
    "sg:phone":"+1 608 763 4251",
    "sg:postcode":"53820",
    "sg:province":"WI",
    "wof:name":"Hodges Production",
    "wof:placetype":"venue"
},
  "geometry": {"coordinates":[-90.780773,42.726607],"type":"Point"}
}