{
  "type": "Feature",
  "properties": {
    "iso:country":"US",
    "sg:address":"7240 W Good Hope Rd",
    "sg:city":"Milwaukee",
    "sg:classifiers":[
        {
            "category":"Autos & Motor Vehicles",
            "subcategory":"Automobile Sales",
            "type":"Retail Goods"
        }
    ],
    "sg:phone":"+1 414 358 0600",
    "sg:postcode":"53223",
    "sg:province":"WI",
    "sg:tags":[
        "used"
    ],
    "wof:name":"A Car Lot",
    "wof:placetype":"venue"
},
  "geometry": {"coordinates":[-87.991394,43.148643],"type":"Point"}
}