{
  "type": "Feature",
  "properties": {
    "iso:country":"US",
    "sg:address":"6222 W Fond du Lac Ave",
    "sg:city":"Milwaukee",
    "sg:classifiers":[
        {
            "category":"Travel",
            "subcategory":"Hotels & Motels",
            "type":"Entertainment"
        }
    ],
    "sg:phone":"+1 414 463 9000",
    "sg:postcode":"53218",
    "sg:province":"WI",
    "wof:name":"Diamond Inn Motel",
    "wof:placetype":"venue"
},
  "geometry": {"coordinates":[-87.991268,43.101804],"type":"Point"}
}