{
  "type": "Feature",
  "properties": {
    "iso:country":"US",
    "sg:address":"127 S Garfield Ave",
    "sg:city":"Janesville",
    "sg:classifiers":[
        {
            "category":"Real Estate",
            "subcategory":"Real Estate Operator",
            "type":"Services"
        }
    ],
    "sg:phone":"+1 608 754 8569",
    "sg:postcode":"53545",
    "sg:province":"WI",
    "sg:tags":[
        "building",
        "commercial"
    ],
    "wof:name":"Southern Wisconsin Pharmacies",
    "wof:placetype":"venue"
},
  "geometry": {"coordinates":[-89.012255,42.685188],"type":"Point"}
}