{
  "type": "Feature",
  "properties": {
    "iso:country":"US",
    "sg:address":"9445 1st St",
    "sg:city":"Sturtevant",
    "sg:classifiers":[
        {
            "category":"Government",
            "subcategory":"Office",
            "type":"Public Place"
        }
    ],
    "sg:phone":"+1 262 886 6057",
    "sg:postcode":"53177",
    "sg:province":"WI",
    "sg:tags":[
        "sector",
        "operator",
        "regulation",
        "commercial",
        "trucking"
    ],
    "wof:name":"Antique Sales",
    "wof:placetype":"venue"
},
  "geometry": {"coordinates":[-87.92313900000001,42.669199],"type":"Point"}
}