{
  "type": "Feature",
  "properties": {
    "iso:country":"US",
    "sg:address":"4501 S Hearthside Dr",
    "sg:city":"New Berlin",
    "sg:classifiers":[
        {
            "category":"Shopping",
            "subcategory":"Catalog Store",
            "type":"Retail Goods"
        }
    ],
    "sg:phone":"+1 262 860 6269",
    "sg:postcode":"53151",
    "sg:province":"WI",
    "sg:tags":[
        "mail",
        "house"
    ],
    "wof:name":"Products 4 Him LLC",
    "wof:placetype":"venue"
},
  "geometry": {"coordinates":[-88.12531199999999,42.961888],"type":"Point"}
}