{
  "type": "Feature",
  "properties": {
    "iso:country":"US",
    "sg:address":"413 N Casaloma Dr",
    "sg:city":"Appleton",
    "sg:classifiers":[
        {
            "category":"Professional",
            "subcategory":"Accounting & Tax Preparation",
            "type":"Services"
        }
    ],
    "sg:phone":"+1 920 731 6789",
    "sg:postcode":"54913",
    "sg:province":"WI",
    "sg:tags":[
        "return"
    ],
    "wof:name":"H & R Block",
    "wof:placetype":"venue"
},
  "geometry": {"coordinates":[-88.476338,44.270802],"type":"Point"}
}