{
  "type": "Feature",
  "properties": {
    "iso:country":"US",
    "sg:address":"461 N Main St",
    "sg:city":"Oshkosh",
    "sg:classifiers":[
        {
            "category":"Shopping",
            "subcategory":"Used Merchandise",
            "type":"Retail Goods"
        }
    ],
    "sg:phone":"+1 920 231 7757",
    "sg:postcode":"54901",
    "sg:province":"WI",
    "sg:tags":[
        "shop",
        "consignment"
    ],
    "wof:name":"P J's Patch",
    "wof:placetype":"venue"
},
  "geometry": {"coordinates":[-88.53759599999999,44.019075],"type":"Point"}
}