{
  "type": "Feature",
  "properties": {
    "iso:country":"US",
    "sg:address":"600 Paradise Dr",
    "sg:city":"Stoughton",
    "sg:classifiers":[
        {
            "category":"Building & Trades",
            "subcategory":"Construction",
            "type":"Services"
        }
    ],
    "sg:phone":"+1 608 877 1235",
    "sg:postcode":"53589",
    "sg:province":"WI",
    "sg:tags":[
        "hanging",
        "contractor"
    ],
    "wof:name":"First Choice Painters LLC",
    "wof:placetype":"venue"
},
  "geometry": {"coordinates":[-89.247908,42.92331],"type":"Point"}
}