{
  "type": "Feature",
  "properties": {
    "iso:country":"US",
    "sg:address":"7667 Power Line Ln",
    "sg:city":"Phillips",
    "sg:classifiers":[
        {
            "category":"Education",
            "subcategory":"Special Training",
            "type":"Public Place"
        }
    ],
    "sg:phone":"+1 715 339 4468",
    "sg:postcode":"54555",
    "sg:province":"WI",
    "sg:tags":[
        "instruction",
        "driving"
    ],
    "wof:name":"North Country Driving School",
    "wof:placetype":"venue"
},
  "geometry": {"coordinates":[-90.349861,45.653245],"type":"Point"}
}