{
  "type": "Feature",
  "properties": {
    "addr:full":"1921 Brunkow Rd Juda WI 53550",
    "addr:housenumber":"1921",
    "addr:postcode":"53550",
    "addr:street":"Brunkow Rd",
    "iso:country":"US",
    "sg:address":"1921 Brunkow Rd",
    "sg:city":"Juda",
    "sg:classifiers":[
        {
            "category":"Freight",
            "type":"Transportation"
        }
    ],
    "sg:phone":"+1 608 934 1177",
    "sg:postcode":"53550",
    "sg:province":"WI",
    "sg:tags":[
        "trucking"
    ],
    "wof:name":"SBF Trucking Inc",
    "wof:placetype":"venue"
},
  "geometry": {"coordinates":[-89.523762,42.563034],"type":"Point"}
}