{
  "type": "Feature",
  "properties": {
    "addr:full":"200 Duke St Marinette WI 54143",
    "addr:housenumber":"200",
    "addr:postcode":"54143",
    "addr:street":"Duke St",
    "iso:country":"US",
    "sg:address":"200 Duke St",
    "sg:city":"Marinette",
    "sg:classifiers":[
        {
            "category":"Building & Trades",
            "subcategory":"Construction",
            "type":"Services"
        }
    ],
    "sg:phone":"+1 715 732 3974",
    "sg:postcode":"54143",
    "sg:province":"WI",
    "sg:tags":[
        "carpentry",
        "contractor"
    ],
    "wof:name":"Rl Construction",
    "wof:placetype":"venue"
},
  "geometry": {"coordinates":[-87.599948,45.088127],"type":"Point"}
}