{
  "type": "Feature",
  "properties": {
    "addr:full":"4104 7th Ave Kenosha WI 53140",
    "addr:housenumber":"4104",
    "addr:postcode":"53140",
    "addr:street":"7Th Ave",
    "iso:country":"US",
    "sg:address":"4104 7th Ave",
    "sg:city":"Kenosha",
    "sg:classifiers":[
        {
            "category":"Personal",
            "subcategory":"Beauty Salon",
            "type":"Services"
        }
    ],
    "sg:phone":"+1 262 605 0825",
    "sg:postcode":"53140",
    "sg:province":"WI",
    "sg:tags":[
        "shop"
    ],
    "wof:name":"Theodore's Hair Design",
    "wof:placetype":"venue"
},
  "geometry": {"coordinates":[-87.820607,42.59803],"type":"Point"}
}