{
  "type": "Feature",
  "properties": {
    "iso:country":"US",
    "sg:address":"799 Maple Ave",
    "sg:city":"Columbus",
    "sg:classifiers":[
        {
            "category":"Organizations",
            "subcategory":"Religious Organization",
            "type":"Services"
        }
    ],
    "sg:phone":"+1 920 623 2977",
    "sg:postcode":"53925",
    "sg:province":"WI",
    "sg:tags":[
        "church"
    ],
    "wof:name":"Columbus Christian Fellowship",
    "wof:placetype":"venue"
},
  "geometry": {"coordinates":[-89.035744,43.342057],"type":"Point"}
}