{
  "type": "Feature",
  "properties": {
    "addr:full":"8775 Hunters Rd Hortonville WI 54944",
    "addr:housenumber":"8775",
    "addr:postcode":"54944",
    "addr:street":"Hunters Rd",
    "iso:country":"US",
    "sg:address":"8775 Hunters Rd",
    "sg:city":"Hortonville",
    "sg:classifiers":[
        {
            "category":"Farming",
            "subcategory":"Dairy Farm",
            "type":"Manufacturing & Wholesale Goods"
        }
    ],
    "sg:phone":"+1 920 779 6120",
    "sg:postcode":"54944",
    "sg:province":"WI",
    "wof:name":"Benton & Beechy LLC",
    "wof:placetype":"venue"
},
  "geometry": {"coordinates":[-88.630624,44.258288],"type":"Point"}
}