{
  "type": "Feature",
  "properties": {
    "iso:country":"US",
    "sg:address":"4506 Larson Beach Rd",
    "sg:city":"Mc Farland",
    "sg:classifiers":[
        {
            "category":"Restaurant",
            "type":"Food & Drink"
        }
    ],
    "sg:phone":"+1 608 838 7248",
    "sg:postcode":"53558",
    "sg:province":"WI",
    "wof:name":"Beach House Restaurant",
    "wof:placetype":"venue"
},
  "geometry": {"coordinates":[-89.302807,43.017522],"type":"Point"}
}