{
  "type": "Feature",
  "properties": {
    "iso:country":"US",
    "sg:address":"2029 Trestik Rd",
    "sg:city":"Junction City",
    "sg:classifiers":[
        {
            "category":"Farming",
            "subcategory":"Livestock Farm",
            "type":"Manufacturing & Wholesale Goods"
        }
    ],
    "sg:phone":"+1 715 457 6659",
    "sg:postcode":"54443",
    "sg:province":"WI",
    "sg:tags":[
        "animal",
        "general"
    ],
    "wof:name":"Mark Totten",
    "wof:placetype":"venue"
},
  "geometry": {"coordinates":[-89.828031,44.582898],"type":"Point"}
}