{
  "type": "Feature",
  "properties": {
    "iso:country":"US",
    "sg:address":"1101 Perry St",
    "sg:city":"Algoma",
    "sg:classifiers":[
        {
            "category":"Manufacturing",
            "subcategory":"Retail Goods",
            "type":"Manufacturing & Wholesale Goods"
        }
    ],
    "sg:phone":"+1 920 487 7250",
    "sg:postcode":"54201",
    "sg:province":"WI",
    "sg:tags":[
        "assembly",
        "fabricating"
    ],
    "wof:name":"Olson Fabrication Inc",
    "wof:placetype":"venue"
},
  "geometry": {"coordinates":[-87.44810699999999,44.613815],"type":"Point"}
}