{
  "type": "Feature",
  "properties": {
    "iso:country":"US",
    "sg:address":"9175 N Mill Rd",
    "sg:city":"Kewaskum",
    "sg:classifiers":[
        {
            "category":"Building & Trades",
            "subcategory":"Plumbing",
            "type":"Services"
        }
    ],
    "sg:phone":"+1 262 626 2424",
    "sg:postcode":"53040",
    "sg:province":"WI",
    "sg:tags":[
        "contractor"
    ],
    "wof:name":"Ramthum H & Sons",
    "wof:placetype":"venue"
},
  "geometry": {"coordinates":[-88.200788,43.523595],"type":"Point"}
}