{
  "type": "Feature",
  "properties": {
    "iso:country":"US",
    "sg:address":"3570 Co Rd K",
    "sg:city":"Montello",
    "sg:classifiers":[
        {
            "category":"Autos & Motor Vehicles",
            "subcategory":"Fuel & Gas Station",
            "type":"Retail Goods"
        }
    ],
    "sg:phone":"+1 608 297 8127",
    "sg:postcode":"53949",
    "sg:province":"WI",
    "sg:tags":[
        "station",
        "gasoline"
    ],
    "wof:name":"Picadilly Circus Pizza",
    "wof:placetype":"venue"
},
  "geometry": {"coordinates":[-89.347853,43.777537],"type":"Point"}
}