{
  "type": "Feature",
  "properties": {
    "iso:country":"US",
    "sg:address":"1625 Chatham St",
    "sg:city":"Racine",
    "sg:classifiers":[
        {
            "category":"Professional",
            "subcategory":"Business Services",
            "type":"Services"
        }
    ],
    "sg:phone":"+1 262 619 9636",
    "sg:postcode":"53402",
    "sg:province":"WI",
    "wof:name":"Delotell Enterprises LLC",
    "wof:placetype":"venue"
},
  "geometry": {"coordinates":[-87.783657,42.7419],"type":"Point"}
}