{
  "type": "Feature",
  "properties": {
    "addr:full":"802 W Main St Waunakee WI 53597",
    "addr:housenumber":"802",
    "addr:postcode":"53597",
    "addr:street":"W Main St",
    "iso:country":"US",
    "sg:address":"802 W Main St",
    "sg:city":"Waunakee",
    "sg:classifiers":[
        {
            "category":"Real Estate",
            "subcategory":"Real Estate Operator",
            "type":"Services"
        }
    ],
    "sg:phone":"+1 608 849 6895",
    "sg:postcode":"53597",
    "sg:province":"WI",
    "sg:tags":[
        "building",
        "apartment"
    ],
    "wof:name":"Nelson Apts",
    "wof:placetype":"venue"
},
  "geometry": {"coordinates":[-89.46895000000001,43.191999],"type":"Point"}
}