{
  "type": "Feature",
  "properties": {
    "iso:country":"US",
    "sg:address":"10179 S 57 St",
    "sg:city":"Franklin",
    "sg:classifiers":[
        {
            "category":"Manufacturing",
            "subcategory":"Tools & Machinery",
            "type":"Manufacturing & Wholesale Goods"
        }
    ],
    "sg:phone":"+1 414 421 2333",
    "sg:postcode":"53132",
    "sg:province":"WI",
    "sg:tags":[
        "machine",
        "die",
        "mold",
        "special",
        "mfg"
    ],
    "wof:name":"TTI",
    "wof:placetype":"venue"
},
  "geometry": {"coordinates":[-87.988438,42.863501],"type":"Point"}
}