{
  "type": "Feature",
  "properties": {
    "iso:country":"US",
    "sg:address":"2920 99th St",
    "sg:city":"Sturtevant",
    "sg:classifiers":[
        {
            "category":"Building & Trades",
            "subcategory":"Construction",
            "type":"Services"
        }
    ],
    "sg:phone":"+1 262 884 9295",
    "sg:postcode":"53177",
    "sg:province":"WI",
    "sg:tags":[
        "brick",
        "laying",
        "contractor"
    ],
    "wof:name":"Gift Bricks",
    "wof:placetype":"venue"
},
  "geometry": {"coordinates":[-87.906783,42.698456],"type":"Point"}
}