{
  "type": "Feature",
  "properties": {
    "iso:country":"US",
    "sg:address":"2528 75th St",
    "sg:city":"Kenosha",
    "sg:classifiers":[
        {
            "category":"Food & Beverages",
            "subcategory":"Groceries & Convenience Stores",
            "type":"Retail Goods"
        }
    ],
    "sg:phone":"+1 262 656 0887",
    "sg:postcode":"53143",
    "sg:province":"WI",
    "sg:tags":[
        "grocer"
    ],
    "wof:name":"Andy's Petro Pantry",
    "wof:placetype":"venue"
},
  "geometry": {"coordinates":[-87.839775,42.566048],"type":"Point"}
}