{
  "type": "Feature",
  "properties": {
    "iso:country":"US",
    "sg:address":"2242 Edgewood Dr",
    "sg:city":"Grafton",
    "sg:classifiers":[
        {
            "category":"Professional",
            "subcategory":"Management & Consulting",
            "type":"Services"
        }
    ],
    "sg:phone":"+1 262 376 1010",
    "sg:postcode":"53024",
    "sg:province":"WI",
    "sg:tags":[
        "business",
        "real estate"
    ],
    "wof:name":"Real Futures",
    "wof:placetype":"venue"
},
  "geometry": {"coordinates":[-87.952508,43.359134],"type":"Point"}
}