{
  "type": "Feature",
  "properties": {
    "iso:country":"US",
    "sg:address":"10220 Harrison Rd",
    "sg:city":"Readstown",
    "sg:phone":"+1 608 629 5798",
    "sg:postcode":"54652",
    "sg:province":"WI",
    "sg:tags":[
        "farm",
        "soybean"
    ],
    "wof:name":"Morton Reser",
    "wof:placetype":"venue"
},
  "geometry": {"coordinates":[-90.76294,43.487778],"type":"Point"}
}