{
  "type": "Feature",
  "properties": {
    "addr:full":"425 Ridge St Mineral Point WI 53565",
    "addr:housenumber":"425",
    "addr:postcode":"53565",
    "addr:street":"Ridge St",
    "iso:country":"US",
    "sg:address":"425 Ridge St",
    "sg:city":"Mineral Point",
    "sg:classifiers":[
        {
            "category":"Shopping",
            "subcategory":"Gifts & Souvenirs",
            "type":"Retail Goods"
        }
    ],
    "sg:phone":"+1 608 987 2742",
    "sg:postcode":"53565",
    "sg:province":"WI",
    "wof:name":"Snow House Gift Collectibles",
    "wof:placetype":"venue"
},
  "geometry": {"coordinates":[-90.1883,42.859854],"type":"Point"}
}