{
  "type": "Feature",
  "properties": {
    "iso:country":"US",
    "sg:address":"7259 W North Ave",
    "sg:city":"Milwaukee",
    "sg:classifiers":[
        {
            "category":"Shopping",
            "subcategory":"Florist",
            "type":"Retail Goods"
        }
    ],
    "sg:phone":"+1 414 771 7186",
    "sg:postcode":"53213",
    "sg:province":"WI",
    "wof:name":"Bud's & Blossoms",
    "wof:placetype":"venue"
},
  "geometry": {"coordinates":[-88.003687,43.060668],"type":"Point"}
}