{
  "type": "Feature",
  "properties": {
    "iso:country":"US",
    "sg:address":"1262 Gavin Rd",
    "sg:city":"Neenah",
    "sg:classifiers":[
        {
            "category":"Building & Trades",
            "subcategory":"Construction",
            "type":"Services"
        }
    ],
    "sg:phone":"+1 920 722 9977",
    "sg:postcode":"54956",
    "sg:province":"WI",
    "sg:tags":[
        "house"
    ],
    "wof:name":"HI Class Home Imp",
    "wof:placetype":"venue"
},
  "geometry": {"coordinates":[-88.511786,44.214105],"type":"Point"}
}