{
  "type": "Feature",
  "properties": {
    "iso:country":"US",
    "sg:address":"956 165th Ave",
    "sg:city":"Balsam Lake",
    "sg:classifiers":[
        {
            "category":"Travel",
            "subcategory":"Campground",
            "type":"Entertainment"
        }
    ],
    "sg:phone":"+1 715 268 8980",
    "sg:postcode":"54810",
    "sg:province":"WI",
    "sg:tags":[
        "trailer"
    ],
    "wof:name":"Dn Campground LLC",
    "wof:placetype":"venue"
},
  "geometry": {"coordinates":[-92.35716499999999,45.44638],"type":"Point"}
}