{
  "type": "Feature",
  "properties": {
    "iso:country":"US",
    "sg:address":"2014 Spring Valley Rd",
    "sg:city":"Jackson",
    "sg:classifiers":[
        {
            "category":"Sports & Exercise",
            "subcategory":"Race Track",
            "type":"Entertainment"
        }
    ],
    "sg:phone":"+1 262 677 2442",
    "sg:postcode":"53037",
    "sg:province":"WI",
    "sg:tags":[
        "operation",
        "racing",
        "or"
    ],
    "wof:name":"Tumbleweed Ranch",
    "wof:placetype":"venue"
},
  "geometry": {"coordinates":[-88.138141,43.287453],"type":"Point"}
}