{
  "type": "Feature",
  "properties": {
    "iso:country":"US",
    "sg:address":"2500 Deerfield Ln E",
    "sg:city":"Suamico",
    "sg:classifiers":[
        {
            "category":"Building & Trades",
            "subcategory":"Electrical",
            "type":"Services"
        }
    ],
    "sg:phone":"+1 920 662 9207",
    "sg:postcode":"54173",
    "sg:province":"WI",
    "sg:tags":[
        "electric",
        "contractor"
    ],
    "wof:name":"Monty Young Electric",
    "wof:placetype":"venue"
},
  "geometry": {"coordinates":[-88.049402,44.611497],"type":"Point"}
}