{
  "type": "Feature",
  "properties": {
    "iso:country":"US",
    "sg:address":"8085 Miller Ave",
    "sg:city":"Loyal",
    "sg:classifiers":[
        {
            "category":"Farming",
            "subcategory":"Dairy Farm",
            "type":"Manufacturing & Wholesale Goods"
        }
    ],
    "sg:phone":"+1 715 255 8973",
    "sg:postcode":"54446",
    "sg:province":"WI",
    "wof:name":"Roehl Acres",
    "wof:placetype":"venue"
},
  "geometry": {"coordinates":[-90.516582,44.68842],"type":"Point"}
}