{
  "type": "Feature",
  "properties": {
    "iso:country":"US",
    "sg:address":"449 Hyland Dr",
    "sg:city":"Stoughton",
    "sg:classifiers":[
        {
            "category":"Wholesale",
            "subcategory":"Groceries",
            "type":"Manufacturing & Wholesale Goods"
        }
    ],
    "sg:phone":"+1 608 873 2033",
    "sg:postcode":"53589",
    "sg:province":"WI",
    "wof:name":"Quantum Enterprises",
    "wof:placetype":"venue"
},
  "geometry": {"coordinates":[-89.225291,42.929891],"type":"Point"}
}