{
  "type": "Feature",
  "properties": {
    "iso:country":"US",
    "sg:address":"414 Main St",
    "sg:city":"Mukwonago",
    "sg:classifiers":[
        {
            "category":"Professional",
            "subcategory":"Accounting & Tax Preparation",
            "type":"Services"
        }
    ],
    "sg:phone":"+1 262 363 4873",
    "sg:postcode":"53149",
    "sg:province":"WI",
    "wof:name":"David H Gilliland CPA",
    "wof:placetype":"venue"
},
  "geometry": {"coordinates":[-88.332183,42.860738],"type":"Point"}
}