{
  "type": "Feature",
  "properties": {
    "iso:country":"US",
    "sg:address":"1091 State Hwy 73 S",
    "sg:city":"Wisconsin Rapids",
    "sg:classifiers":[
        {
            "category":"Freight",
            "type":"Transportation"
        }
    ],
    "sg:phone":"+1 715 325 2298",
    "sg:postcode":"54494",
    "sg:province":"WI",
    "sg:tags":[
        "local",
        "trucking"
    ],
    "wof:name":"R C Trucking",
    "wof:placetype":"venue"
},
  "geometry": {"coordinates":[-89.812548,44.307185],"type":"Point"}
}