{
  "type": "Feature",
  "properties": {
    "iso:country":"US",
    "sg:address":"7601 118th Ave",
    "sg:city":"Pleasant Prairie",
    "sg:classifiers":[
        {
            "category":"Travel",
            "subcategory":"Hotels & Motels",
            "type":"Entertainment"
        }
    ],
    "sg:phone":"+1 262 857 7963",
    "sg:postcode":"53158",
    "sg:province":"WI",
    "wof:name":"Super 8 Motel",
    "wof:placetype":"venue"
},
  "geometry": {"coordinates":[-87.94977299999999,42.564574],"type":"Point"}
}