{
  "type": "Feature",
  "properties": {
    "addr:full":"2078 90th St Somerset WI 54025",
    "addr:housenumber":"2078",
    "addr:postcode":"54025",
    "addr:street":"90Th St",
    "iso:country":"US",
    "sg:address":"2078 90th St",
    "sg:city":"Somerset",
    "sg:classifiers":[
        {
            "category":"Shopping",
            "subcategory":"Stationery & Office Supplies",
            "type":"Retail Goods"
        }
    ],
    "sg:phone":"+1 715 247 2202",
    "sg:postcode":"54025",
    "sg:province":"WI",
    "sg:tags":[
        "album",
        "scrapbook"
    ],
    "wof:name":"Home Made Card & Scrapbook Shp",
    "wof:placetype":"venue"
},
  "geometry": {"coordinates":[-92.630922,45.161979],"type":"Point"}
}