{
  "type": "Feature",
  "properties": {
    "iso:country":"US",
    "sg:address":"19100 Baythorn Way",
    "sg:city":"Brookfield",
    "sg:classifiers":[
        {
            "category":"Professional",
            "subcategory":"Business Services",
            "type":"Services"
        }
    ],
    "sg:phone":"+1 262 792 9579",
    "sg:postcode":"53045",
    "sg:province":"WI",
    "sg:tags":[
        "technical",
        "preparation",
        "manual"
    ],
    "wof:name":"Ronald R Hofer",
    "wof:placetype":"venue"
},
  "geometry": {"coordinates":[-88.152404,43.020691],"type":"Point"}
}