{
  "type": "Feature",
  "properties": {
    "addr:full":"5808 E Open Meadow Mc Farland WI 53558",
    "addr:housenumber":"5808 e",
    "addr:postcode":"53558",
    "addr:street":"Open Meadow Mc Farland",
    "iso:country":"US",
    "sg:address":"5808 E Open Meadow",
    "sg:city":"Mc Farland",
    "sg:classifiers":[
        {
            "category":"Recreation",
            "type":"Entertainment"
        }
    ],
    "sg:phone":"+1 608 838 0991",
    "sg:postcode":"53558",
    "sg:province":"WI",
    "wof:name":"Academy of Huarangdo",
    "wof:placetype":"venue"
},
  "geometry": {"coordinates":[-89.279831,43.005845],"type":"Point"}
}