{
  "type": "Feature",
  "properties": {
    "addr:full":"7900 N Mohawk Rd Milwaukee WI 53217",
    "addr:housenumber":"7900",
    "addr:postcode":"53217",
    "addr:street":"N Mohawk Rd",
    "iso:country":"US",
    "sg:address":"7900 N Mohawk Rd",
    "sg:city":"Milwaukee",
    "sg:classifiers":[
        {
            "category":"Banks & Credit Unions",
            "subcategory":"Bank",
            "type":"Services"
        }
    ],
    "sg:phone":"+1 414 352 6557",
    "sg:postcode":"53217",
    "sg:province":"WI",
    "sg:tags":[
        "federal",
        "agency"
    ],
    "wof:name":"General Trading Office",
    "wof:placetype":"venue"
},
  "geometry": {"coordinates":[-87.910325,43.159186],"type":"Point"}
}