{
  "type": "Feature",
  "properties": {
    "iso:country":"US",
    "sg:address":"3083 State Hwy 13 N",
    "sg:city":"Wisconsin Rapids",
    "sg:classifiers":[
        {
            "category":"Retail",
            "subcategory":"Repair Shop",
            "type":"Services"
        }
    ],
    "sg:phone":"+1 715 424 5837",
    "sg:postcode":"54495",
    "sg:province":"WI",
    "wof:name":"Cranbrry Creek Furn Rstoration",
    "wof:placetype":"venue"
},
  "geometry": {"coordinates":[-89.871308,44.405425],"type":"Point"}
}