{
  "type": "Feature",
  "properties": {
    "addr:full":"108 Packerland Dr Green Bay WI 54303",
    "addr:housenumber":"108",
    "addr:postcode":"54303",
    "addr:street":"Packerland Dr",
    "iso:country":"US",
    "sg:address":"108 Packerland Dr",
    "sg:city":"Green Bay",
    "sg:classifiers":[
        {
            "category":"Banks & Credit Unions",
            "subcategory":"Bank",
            "type":"Services"
        }
    ],
    "sg:phone":"+1 920 499 6330",
    "sg:postcode":"54303",
    "sg:province":"WI",
    "sg:tags":[
        "loan",
        "broker",
        "mortgage"
    ],
    "sg:website":"www.premiermortgageteam.com",
    "wof:name":"Premier Mortgage Llc",
    "wof:placetype":"venue"
},
  "geometry": {"coordinates":[-88.094534,44.534315],"type":"Point"}
}