{
  "type": "Feature",
  "properties": {
    "addr:full":"9555 S Howell Ave Oak Creek WI 53154",
    "addr:housenumber":"9555",
    "addr:postcode":"53154",
    "addr:street":"S Howell Ave",
    "iso:country":"US",
    "sg:address":"9555 S Howell Ave",
    "sg:city":"Oak Creek",
    "sg:classifiers":[
        {
            "category":"Wholesale",
            "subcategory":"Computers",
            "type":"Manufacturing & Wholesale Goods"
        }
    ],
    "sg:phone":"+1 414 764 4465",
    "sg:postcode":"53154",
    "sg:province":"WI",
    "wof:name":"Dk Systems",
    "wof:placetype":"venue"
},
  "geometry": {"coordinates":[-87.91300200000001,42.870998],"type":"Point"}
}