{
  "type": "Feature",
  "properties": {
    "iso:country":"US",
    "sg:address":"920 Kilbourn Ave",
    "sg:city":"Tomah",
    "sg:classifiers":[
        {
            "category":"Retail",
            "subcategory":"Portrait Studio",
            "type":"Services"
        }
    ],
    "sg:phone":"+1 608 372 5136",
    "sg:postcode":"54660",
    "sg:province":"WI",
    "sg:tags":[
        "photographer"
    ],
    "wof:name":"Schreiner's Studio-Photography",
    "wof:placetype":"venue"
},
  "geometry": {"coordinates":[-90.503061,43.978477],"type":"Point"}
}