{
  "type": "Feature",
  "properties": {
    "iso:country":"US",
    "sg:address":"4796 Donovan Dr",
    "sg:city":"Irma",
    "sg:classifiers":[
        {
            "category":"Manufacturing",
            "subcategory":"Wood Products",
            "type":"Manufacturing & Wholesale Goods"
        }
    ],
    "sg:phone":"+1 715 536 5003",
    "sg:postcode":"54442",
    "sg:province":"WI",
    "sg:tags":[
        "mfg"
    ],
    "wof:name":"Allen Wood Products",
    "wof:placetype":"venue"
},
  "geometry": {"coordinates":[-89.6652,45.329968],"type":"Point"}
}