{
  "type": "Feature",
  "properties": {
    "addr:full":"7525 W Florist Ave Milwaukee WI 53218",
    "addr:housenumber":"7525",
    "addr:postcode":"53218",
    "addr:street":"W Florist Ave",
    "iso:country":"US",
    "sg:address":"7525 W Florist Ave",
    "sg:city":"Milwaukee",
    "sg:classifiers":[
        {
            "category":"Retail",
            "subcategory":"Auto Repair",
            "type":"Services"
        }
    ],
    "sg:phone":"+1 414 463 4890",
    "sg:postcode":"53218",
    "sg:province":"WI",
    "sg:tags":[
        "repairing",
        "automobile"
    ],
    "wof:name":"Berger's Hitch Ctr",
    "wof:placetype":"venue"
},
  "geometry": {"coordinates":[-88.005651,43.126788],"type":"Point"}
}