{
  "type": "Feature",
  "properties": {
    "iso:country":"US",
    "sg:address":"3155 S 77th St Apt 106",
    "sg:city":"Milwaukee",
    "sg:classifiers":[
        {
            "category":"Professional",
            "subcategory":"Detective & Security Services",
            "type":"Services"
        }
    ],
    "sg:phone":"+1 414 543 8123",
    "sg:postcode":"53219",
    "sg:province":"WI",
    "sg:tags":[
        "information",
        "bureau"
    ],
    "wof:name":"Phil Wrobbel Service Corp",
    "wof:placetype":"venue"
},
  "geometry": {"coordinates":[-88.009176,42.987185],"type":"Point"}
}