{
  "type": "Feature",
  "properties": {
    "iso:country":"US",
    "sg:address":"4465 Ashberry Dr",
    "sg:city":"Milton",
    "sg:classifiers":[
        {
            "category":"Building & Trades",
            "subcategory":"Construction",
            "type":"Services"
        }
    ],
    "sg:phone":"+1 608 741 6659",
    "sg:postcode":"53563",
    "sg:province":"WI",
    "sg:tags":[
        "house"
    ],
    "wof:name":"Only Way Remodeling",
    "wof:placetype":"venue"
},
  "geometry": {"coordinates":[-88.989673,42.736594],"type":"Point"}
}