{
  "type": "Feature",
  "properties": {
    "iso:country":"US",
    "sg:address":"315 State St",
    "sg:city":"Beloit",
    "sg:classifiers":[
        {
            "category":"Restaurant",
            "type":"Food & Drink"
        }
    ],
    "sg:phone":"+1 608 362 2990",
    "sg:postcode":"53511",
    "sg:province":"WI",
    "wof:name":"Hometown Diner",
    "wof:placetype":"venue"
},
  "geometry": {"coordinates":[-89.035556,42.499537],"type":"Point"}
}