{
  "type": "Feature",
  "properties": {
    "iso:country":"US",
    "sg:address":"4117 N Green Bay Ave",
    "sg:city":"Milwaukee",
    "sg:classifiers":[
        {
            "category":"Professional",
            "subcategory":"Research",
            "type":"Services"
        }
    ],
    "sg:phone":"+1 414 265 5885",
    "sg:postcode":"53209",
    "sg:province":"WI",
    "sg:tags":[
        "commercial",
        "physical"
    ],
    "wof:name":"Tech Line Technologies",
    "wof:placetype":"venue"
},
  "geometry": {"coordinates":[-87.924643,43.092451],"type":"Point"}
}