{
  "type": "Feature",
  "properties": {
    "addr:full":"335 N Ashland Ave Green Bay WI 54303",
    "addr:housenumber":"335",
    "addr:postcode":"54303",
    "addr:street":"N Ashland Ave",
    "iso:country":"US",
    "sg:address":"335 N Ashland Ave",
    "sg:city":"Green Bay",
    "sg:classifiers":[
        {
            "category":"Building & Trades",
            "subcategory":"Construction",
            "type":"Services"
        }
    ],
    "sg:phone":"+1 920 432 2145",
    "sg:postcode":"54303",
    "sg:province":"WI",
    "sg:tags":[
        "contractor"
    ],
    "wof:name":"D&D Glass",
    "wof:placetype":"venue"
},
  "geometry": {"coordinates":[-88.022713,44.521658],"type":"Point"}
}