{
  "type": "Feature",
  "properties": {
    "iso:country":"US",
    "sg:address":"4370 N 29th St",
    "sg:city":"Milwaukee",
    "sg:classifiers":[
        {
            "category":"Organizations",
            "subcategory":"Religious Organization",
            "type":"Services"
        }
    ],
    "sg:phone":"+1 414 294 1463",
    "sg:postcode":"53216",
    "sg:province":"WI",
    "sg:tags":[
        "clergy"
    ],
    "wof:name":"William Rogers",
    "wof:placetype":"venue"
},
  "geometry": {"coordinates":[-87.949241,43.095261],"type":"Point"}
}