{
  "type": "Feature",
  "properties": {
    "iso:country":"US",
    "sg:address":"3519 Gregory St",
    "sg:city":"Madison",
    "sg:classifiers":[
        {
            "category":"Communications",
            "subcategory":"Film & Video Production",
            "type":"Services"
        }
    ],
    "sg:phone":"+1 608 238 7302",
    "sg:postcode":"53711",
    "sg:province":"WI",
    "sg:tags":[
        "motion",
        "picture"
    ],
    "wof:name":"Emerald City Productions",
    "wof:placetype":"venue"
},
  "geometry": {"coordinates":[-89.439635,43.053274],"type":"Point"}
}