{
  "type": "Feature",
  "properties": {
    "addr:full":"5340 County Line Rd Dorchester WI 54425",
    "addr:housenumber":"5340",
    "addr:postcode":"54425",
    "addr:street":"County Line Rd",
    "iso:country":"US",
    "sg:address":"5340 County Line Rd",
    "sg:city":"Dorchester",
    "sg:classifiers":[
        {
            "category":"Professional",
            "subcategory":"Business Services",
            "type":"Services"
        }
    ],
    "sg:phone":"+1 715 654 5162",
    "sg:postcode":"54425",
    "sg:province":"WI",
    "wof:name":"Stockwell R J",
    "wof:placetype":"venue"
},
  "geometry": {"coordinates":[-90.319575,45.033775],"type":"Point"}
}