{
  "type": "Feature",
  "properties": {
    "iso:country":"US",
    "sg:address":"1953 US Hwy 8",
    "sg:city":"St Croix Falls",
    "sg:classifiers":[
        {
            "category":"Bars & Pubs",
            "type":"Food & Drink"
        }
    ],
    "sg:phone":"+1 715 483 1911",
    "sg:postcode":"54024",
    "sg:province":"WI",
    "wof:name":"Polk County Tavern League",
    "wof:placetype":"venue"
},
  "geometry": {"coordinates":[-92.55828,45.397584],"type":"Point"}
}