{
  "type": "Feature",
  "properties": {
    "iso:country":"US",
    "sg:address":"6004 Tower Ave",
    "sg:city":"Superior",
    "sg:classifiers":[
        {
            "category":"Wholesale",
            "subcategory":"Office Equipment",
            "type":"Manufacturing & Wholesale Goods"
        }
    ],
    "sg:phone":"+1 715 395 7938",
    "sg:postcode":"54880",
    "sg:province":"WI",
    "wof:name":"Bkrh Inc",
    "wof:placetype":"venue"
},
  "geometry": {"coordinates":[-92.104214,46.665823],"type":"Point"}
}