{
  "type": "Feature",
  "properties": {
    "iso:country":"US",
    "sg:address":"1704 Madison St",
    "sg:city":"Manitowoc",
    "sg:classifiers":[
        {
            "category":"Real Estate",
            "subcategory":"Real Estate Operator",
            "type":"Services"
        }
    ],
    "sg:phone":"+1 920 682 9492",
    "sg:postcode":"54220",
    "sg:province":"WI",
    "sg:tags":[
        "apartment"
    ],
    "wof:name":"Maritime Apartment Rentals",
    "wof:placetype":"venue"
},
  "geometry": {"coordinates":[-87.67146700000001,44.083896],"type":"Point"}
}