{
  "type": "Feature",
  "properties": {
    "iso:country":"US",
    "sg:address":"777 E Jonquil Ct",
    "sg:city":"Beloit",
    "sg:classifiers":[
        {
            "category":"Manufacturing",
            "subcategory":"Buildings",
            "type":"Manufacturing & Wholesale Goods"
        }
    ],
    "sg:phone":"+1 608 365 6833",
    "sg:postcode":"53511",
    "sg:province":"IL",
    "sg:tags":[
        "home",
        "log",
        "cabin"
    ],
    "sg:website":"www.beaverloghomes.net",
    "wof:name":"Moose Log Homes",
    "wof:placetype":"venue"
},
  "geometry": {"coordinates":[-89.033213,42.561026],"type":"Point"}
}