{
  "type": "Feature",
  "properties": {
    "addr:full":"125 S Lake Ave Phillips WI 54555",
    "addr:housenumber":"125",
    "addr:postcode":"54555",
    "addr:street":"S Lake Ave",
    "iso:country":"US",
    "sg:address":"125 S Lake Ave",
    "sg:city":"Phillips",
    "sg:classifiers":[
        {
            "category":"Shopping",
            "subcategory":"Bicycles & Sporting Goods",
            "type":"Retail Goods"
        }
    ],
    "sg:phone":"+1 715 339 6254",
    "sg:postcode":"54555",
    "sg:province":"WI",
    "wof:name":"Crazy Loon",
    "wof:placetype":"venue"
},
  "geometry": {"coordinates":[-90.395938,45.689172],"type":"Point"}
}