{
  "type": "Feature",
  "properties": {
    "iso:country":"US",
    "sg:address":"1400 Vernon St",
    "sg:city":"Stoughton",
    "sg:classifiers":[
        {
            "category":"Education",
            "subcategory":"School",
            "type":"Public Place"
        }
    ],
    "sg:phone":"+1 608 877 5200",
    "sg:postcode":"53589",
    "sg:province":"WI",
    "wof:name":"Kegonsa Elementary School",
    "wof:placetype":"venue"
},
  "geometry": {"coordinates":[-89.204947,42.916807],"type":"Point"}
}