{
  "type": "Feature",
  "properties": {
    "iso:country":"US",
    "sg:address":"755 Zeh Ave",
    "sg:city":"Neenah",
    "sg:classifiers":[
        {
            "category":"Building & Trades",
            "subcategory":"Construction",
            "type":"Services"
        }
    ],
    "sg:phone":"+1 920 722 8425",
    "sg:postcode":"54956",
    "sg:province":"WI",
    "sg:tags":[
        "hanging",
        "contractor"
    ],
    "wof:name":"Barbs Wallpapering",
    "wof:placetype":"venue"
},
  "geometry": {"coordinates":[-88.490737,44.202281],"type":"Point"}
}