{
  "type": "Feature",
  "properties": {
    "addr:full":"2736 Hillside Dr Delafield WI 53018",
    "addr:housenumber":"2736",
    "addr:postcode":"53018",
    "addr:street":"Hillside Dr",
    "iso:country":"US",
    "sg:address":"2736 Hillside Dr",
    "sg:city":"Delafield",
    "sg:classifiers":[
        {
            "category":"Restaurant",
            "type":"Food & Drink"
        }
    ],
    "sg:menulink":"http://www.allmenus.com/wi/delafield/63542-pizza-hut/menu/",
    "sg:phone":"+1 262 646 2375",
    "sg:postcode":"53018",
    "sg:province":"WI",
    "sg:tags":[
        "american",
        "pizza"
    ],
    "wof:name":"Pizza Hut",
    "wof:placetype":"venue"
},
  "geometry": {"coordinates":[-88.372187,43.047454],"type":"Point"}
}