{
  "type": "Feature",
  "properties": {
    "iso:country":"US",
    "sg:address":"7442 Meadowrue Cir",
    "sg:city":"Middleton",
    "sg:classifiers":[
        {
            "category":"Professional",
            "type":"Services"
        }
    ],
    "sg:phone":"+1 608 288 3000",
    "sg:postcode":"53562",
    "sg:province":"WI",
    "wof:name":"Berbee",
    "wof:placetype":"venue"
},
  "geometry": {"coordinates":[-89.563509,43.11579],"type":"Point"}
}