{
  "type": "Feature",
  "properties": {
    "iso:country":"US",
    "sg:address":"1234 S Cesar E Chavez Dr",
    "sg:city":"Milwaukee",
    "sg:classifiers":[
        {
            "category":"Restaurant",
            "type":"Food & Drink"
        }
    ],
    "sg:phone":"+1 414 671 5360",
    "sg:postcode":"53204",
    "sg:province":"WI",
    "wof:name":"Arteaga's Restaurant",
    "wof:placetype":"venue"
},
  "geometry": {"coordinates":[-87.933064,43.017313],"type":"Point"}
}