{
  "type": "Feature",
  "properties": {
    "iso:country":"US",
    "sg:address":"518 S 4th St",
    "sg:city":"Stoughton",
    "sg:classifiers":[
        {
            "category":"Government",
            "subcategory":"Office",
            "type":"Public Place"
        }
    ],
    "sg:phone":"+1 608 873 3880",
    "sg:postcode":"53589",
    "sg:province":"WI",
    "sg:tags":[
        "village"
    ],
    "wof:name":"City Of Stoughton",
    "wof:placetype":"venue"
},
  "geometry": {"coordinates":[-89.218009,42.914725],"type":"Point"}
}