{
  "type": "Feature",
  "properties": {
    "addr:full":"11023 Blackhawk Trl Fox Lake WI 53933",
    "addr:housenumber":"11023",
    "addr:postcode":"53933",
    "addr:street":"Blackhawk Trl",
    "iso:country":"US",
    "sg:address":"11023 Blackhawk Trl",
    "sg:city":"Fox Lake",
    "sg:classifiers":[
        {
            "category":"Professional",
            "type":"Services"
        }
    ],
    "sg:phone":"+1 920 928 3308",
    "sg:postcode":"53933",
    "sg:province":"WI",
    "sg:tags":[
        "establishment"
    ],
    "wof:name":"Bentley's Acre",
    "wof:placetype":"venue"
},
  "geometry": {"coordinates":[-88.952589,43.588701],"type":"Point"}
}