{
  "type": "Feature",
  "properties": {
    "iso:country":"US",
    "sg:address":"216 S Rock Ave",
    "sg:city":"Viroqua",
    "sg:classifiers":[
        {
            "category":"Education",
            "subcategory":"Dance Studio",
            "type":"Public Place"
        }
    ],
    "sg:phone":"+1 608 637 6750",
    "sg:postcode":"54665",
    "sg:province":"WI",
    "sg:tags":[
        "instruction",
        "dancing"
    ],
    "wof:name":"Julie's School Of Dance",
    "wof:placetype":"venue"
},
  "geometry": {"coordinates":[-90.89064,43.555105],"type":"Point"}
}