{
  "type": "Feature",
  "properties": {
    "iso:country":"US",
    "sg:address":"4126 Lien Rd",
    "sg:city":"Madison",
    "sg:classifiers":[
        {
            "category":"Health Services",
            "subcategory":"Chiropractor",
            "type":"Services"
        }
    ],
    "sg:phone":"+1 608 241 4500",
    "sg:postcode":"53704",
    "sg:province":"WI",
    "wof:name":"Utschig Group Chiro Clnc",
    "wof:placetype":"venue"
},
  "geometry": {"coordinates":[-89.312584,43.121083],"type":"Point"}
}