{
  "type": "Feature",
  "properties": {
    "iso:country":"US",
    "sg:address":"7 W Eau Claire St",
    "sg:city":"Rice Lake",
    "sg:classifiers":[
        {
            "category":"Professional",
            "subcategory":"Business Services",
            "type":"Services"
        }
    ],
    "sg:phone":"+1 715 736 4333",
    "sg:postcode":"54868",
    "sg:province":"WI",
    "wof:name":"Wealth Management Group",
    "wof:placetype":"venue"
},
  "geometry": {"coordinates":[-91.733593,45.503551],"type":"Point"}
}