{
  "type": "Feature",
  "properties": {
    "addr:full":"108 Highland Ct Neenah WI 54956",
    "addr:housenumber":"108",
    "addr:postcode":"54956",
    "addr:street":"Highland Ct",
    "iso:country":"US",
    "sg:address":"108 Highland Ct",
    "sg:city":"Neenah",
    "sg:classifiers":[
        {
            "category":"Restaurant",
            "type":"Food & Drink"
        }
    ],
    "sg:menulink":"http://www.allmenus.com/wi/neenah/206445-mcdonalds/menu/",
    "sg:postcode":"54956",
    "sg:province":"WI",
    "sg:tags":[
        "burger",
        "american"
    ],
    "wof:name":"McDonald's",
    "wof:placetype":"venue"
},
  "geometry": {"coordinates":[-88.520979,44.142044],"type":"Point"}
}