{
  "type": "Feature",
  "properties": {
    "iso:country":"US",
    "sg:address":"3280 Oak Center Rd",
    "sg:city":"Oakfield",
    "sg:classifiers":[
        {
            "category":"Home & Garden",
            "subcategory":"Building Materials",
            "type":"Retail Goods"
        }
    ],
    "sg:phone":"+1 920 583 4546",
    "sg:postcode":"53065",
    "sg:province":"WI",
    "sg:tags":[
        "lumber",
        "yard"
    ],
    "wof:name":"Faber Building Center Inc",
    "wof:placetype":"venue"
},
  "geometry": {"coordinates":[-88.601832,43.6652],"type":"Point"}
}