{
  "type": "Feature",
  "properties": {
    "iso:country":"US",
    "sg:address":"209 Washington St",
    "sg:city":"Waterford",
    "sg:classifiers":[
        {
            "category":"Building & Trades",
            "subcategory":"Construction",
            "type":"Services"
        }
    ],
    "sg:phone":"+1 262 534 6305",
    "sg:postcode":"53185",
    "sg:province":"WI",
    "sg:tags":[
        "laying"
    ],
    "wof:name":"Art Wood Floors",
    "wof:placetype":"venue"
},
  "geometry": {"coordinates":[-88.21509,42.761556],"type":"Point"}
}