{
  "type": "Feature",
  "properties": {
    "iso:country":"US",
    "sg:address":"105 N Sawyer St",
    "sg:city":"Oshkosh",
    "sg:classifiers":[
        {
            "category":"Restaurant",
            "type":"Food & Drink"
        }
    ],
    "sg:menulink":"http://www.allmenus.com/wi/oshkosh/96458-taco-johns/menu/",
    "sg:phone":"+1 920 230 8226",
    "sg:postcode":"54902",
    "sg:province":"WI",
    "sg:tags":[
        "american",
        "mexican"
    ],
    "wof:name":"Taco John's",
    "wof:placetype":"venue"
},
  "geometry": {"coordinates":[-88.56739399999999,44.018077],"type":"Point"}
}