{
  "type": "Feature",
  "properties": {
    "iso:country":"US",
    "sg:address":"409 E Buffalo St",
    "sg:city":"Milwaukee",
    "sg:classifiers":[
        {
            "category":"Shopping",
            "type":"Retail Goods"
        }
    ],
    "sg:phone":"+1 414 431 5050",
    "sg:postcode":"53202",
    "sg:province":"WI",
    "sg:tags":[
        "merchandise"
    ],
    "wof:name":"Eye Level Framing",
    "wof:placetype":"venue"
},
  "geometry": {"coordinates":[-87.904774,43.033912],"type":"Point"}
}