{
  "type": "Feature",
  "properties": {
    "iso:country":"US",
    "sg:address":"2200 S 114th St",
    "sg:city":"Milwaukee",
    "sg:classifiers":[
        {
            "category":"Food & Beverages",
            "subcategory":"Liquor & Beverages",
            "type":"Retail Goods"
        },
        {
            "category":"Wholesale",
            "subcategory":"Wine & Distilled Alcoholic Beverages",
            "type":"Manufacturing & Wholesale Goods"
        }
    ],
    "sg:phone":"+1 414 546 2060",
    "sg:postcode":"53227",
    "sg:province":"WI",
    "sg:tags":[
        "liquors-wholesale",
        "store"
    ],
    "wof:name":"Badger Liquor",
    "wof:placetype":"venue"
},
  "geometry": {"coordinates":[-88.054333,43.003126],"type":"Point"}
}