{
  "type": "Feature",
  "properties": {
    "iso:country":"US",
    "sg:address":"1621 140th St",
    "sg:city":"New Richmond",
    "sg:classifiers":[
        {
            "category":"Building & Trades",
            "subcategory":"Electrical",
            "type":"Services"
        }
    ],
    "sg:phone":"+1 715 246 4423",
    "sg:postcode":"54017",
    "sg:province":"WI",
    "sg:tags":[
        "electrical",
        "contractor"
    ],
    "wof:name":"Hopkins Electric",
    "wof:placetype":"venue"
},
  "geometry": {"coordinates":[-92.51702899999999,45.098737],"type":"Point"}
}