{
  "type": "Feature",
  "properties": {
    "addr:full":"2135 Co Rd Z Eau Galle WI 54737",
    "addr:housenumber":"2135",
    "addr:postcode":"54737",
    "addr:street":"Co Rd",
    "iso:country":"US",
    "sg:address":"2135 Co Rd Z",
    "sg:city":"Eau Galle",
    "sg:classifiers":[
        {
            "category":"Farming",
            "subcategory":"Dairy Farm",
            "type":"Manufacturing & Wholesale Goods"
        }
    ],
    "sg:phone":"+1 715 283 4313",
    "sg:postcode":"54737",
    "sg:province":"WI",
    "wof:name":"Jack Weber Farm",
    "wof:placetype":"venue"
},
  "geometry": {"coordinates":[-91.984369,44.752581],"type":"Point"}
}