{
  "type": "Feature",
  "properties": {
    "iso:country":"US",
    "sg:address":"17125 W Greenfield Ave",
    "sg:city":"New Berlin",
    "sg:classifiers":[
        {
            "category":"Retail",
            "subcategory":"Auto Repair",
            "type":"Services"
        }
    ],
    "sg:phone":"+1 262 782 1740",
    "sg:postcode":"53151",
    "sg:province":"WI",
    "sg:tags":[
        "repairing",
        "automobile",
        "general"
    ],
    "wof:name":"K K Auto Engine Inc",
    "wof:placetype":"venue"
},
  "geometry": {"coordinates":[-88.12610599999999,43.016807],"type":"Point"}
}