{
  "type": "Feature",
  "properties": {
    "iso:country":"US",
    "sg:address":"2999 S Delaware Ave",
    "sg:city":"Milwaukee",
    "sg:classifiers":[
        {
            "category":"Personal",
            "subcategory":"Beauty Salon",
            "type":"Services"
        }
    ],
    "sg:phone":"+1 414 744 8871",
    "sg:postcode":"53207",
    "sg:province":"WI",
    "wof:name":"Sweeney Todd Salon",
    "wof:placetype":"venue"
},
  "geometry": {"coordinates":[-87.879284,42.989132],"type":"Point"}
}