{
  "type": "Feature",
  "properties": {
    "iso:country":"US",
    "sg:address":"12028 Day Rd",
    "sg:city":"Marshfield",
    "sg:classifiers":[
        {
            "category":"Farming",
            "subcategory":"Dairy Farm",
            "type":"Manufacturing & Wholesale Goods"
        }
    ],
    "sg:phone":"+1 715 384 5765",
    "sg:postcode":"54449",
    "sg:province":"WI",
    "wof:name":"Joseph Fuchs",
    "wof:placetype":"venue"
},
  "geometry": {"coordinates":[-90.079329,44.675153],"type":"Point"}
}