{
  "type": "Feature",
  "properties": {
    "iso:country":"US",
    "sg:address":"114 Church St",
    "sg:city":"Potosi",
    "sg:classifiers":[
        {
            "category":"Farming",
            "subcategory":"Livestock Farm",
            "type":"Manufacturing & Wholesale Goods"
        }
    ],
    "sg:phone":"+1 608 763 2645",
    "sg:postcode":"53820",
    "sg:province":"WI",
    "sg:tags":[
        "hog",
        "or",
        "feedlot"
    ],
    "wof:name":"Danny Schaefer",
    "wof:placetype":"venue"
},
  "geometry": {"coordinates":[-90.681967,42.690436],"type":"Point"}
}