{
  "type": "Feature",
  "properties": {
    "addr:full":"1844 Shalom Dr West Bend WI 53090",
    "addr:housenumber":"1844",
    "addr:postcode":"53090",
    "addr:street":"Shalom Dr",
    "iso:country":"US",
    "sg:address":"1844 Shalom Dr",
    "sg:city":"West Bend",
    "sg:classifiers":[
        {
            "category":"Real Estate",
            "subcategory":"Real Estate Agent",
            "type":"Services"
        }
    ],
    "sg:phone":"+1 262 335 6358",
    "sg:postcode":"53090",
    "sg:province":"WI",
    "wof:name":"Warneckes Properties",
    "wof:placetype":"venue"
},
  "geometry": {"coordinates":[-88.131091,43.483674],"type":"Point"}
}