{
  "type": "Feature",
  "properties": {
    "iso:country":"US",
    "sg:address":"12557 Breezy Hill Rd",
    "sg:city":"Mt Hope",
    "sg:classifiers":[
        {
            "category":"Social Services",
            "type":"Services"
        }
    ],
    "sg:phone":"+1 608 988 4234",
    "sg:postcode":"53816",
    "sg:province":"WI",
    "sg:tags":[
        "organization",
        "welfare"
    ],
    "wof:name":"Thursday's Child",
    "wof:placetype":"venue"
},
  "geometry": {"coordinates":[-90.83910400000001,42.954773],"type":"Point"}
}