{
  "type": "Feature",
  "properties": {
    "iso:country":"US",
    "sg:address":"940 Lincoln Ave",
    "sg:city":"Fennimore",
    "sg:classifiers":[
        {
            "category":"Restaurant",
            "type":"Food & Drink"
        }
    ],
    "sg:phone":"+1 608 822 6331",
    "sg:postcode":"53809",
    "sg:province":"WI",
    "wof:name":"Our Little Restaurant & Bakery",
    "wof:placetype":"venue"
},
  "geometry": {"coordinates":[-90.655661,42.98339],"type":"Point"}
}