{
  "type": "Feature",
  "properties": {
    "iso:country":"US",
    "sg:address":"7900 W Tower Ave",
    "sg:city":"Milwaukee",
    "sg:classifiers":[
        {
            "category":"Manufacturing",
            "subcategory":"Metals",
            "type":"Manufacturing & Wholesale Goods"
        }
    ],
    "sg:phone":"+1 414 355 4801",
    "sg:postcode":"53223",
    "sg:province":"WI",
    "sg:tags":[
        "steel"
    ],
    "sg:website":"www.supersteel.com",
    "wof:name":"Super Steel Products Corp",
    "wof:placetype":"venue"
},
  "geometry": {"coordinates":[-88.006601,43.165248],"type":"Point"}
}