{
  "type": "Feature",
  "properties": {
    "iso:country":"US",
    "sg:address":"612 Cass St",
    "sg:city":"La Crosse",
    "sg:classifiers":[
        {
            "category":"Autos & Motor Vehicles",
            "subcategory":"Auto Supplies",
            "type":"Retail Goods"
        }
    ],
    "sg:phone":"+1 608 784 5687",
    "sg:postcode":"54601",
    "sg:province":"WI",
    "sg:tags":[
        "sales",
        "tire"
    ],
    "wof:name":"Goodyear",
    "wof:placetype":"venue"
},
  "geometry": {"coordinates":[-91.248313,43.808648],"type":"Point"}
}