{
  "type": "Feature",
  "properties": {
    "iso:country":"US",
    "sg:address":"511 N 8th St",
    "sg:city":"Sheboygan",
    "sg:classifiers":[
        {
            "category":"Shopping",
            "subcategory":"Clothing, Apparel, & Fashions",
            "type":"Retail Goods"
        }
    ],
    "sg:phone":"+1 920 803 6241",
    "sg:postcode":"53081",
    "sg:province":"WI",
    "wof:name":"Mark J Rieger",
    "wof:placetype":"venue"
},
  "geometry": {"coordinates":[-87.712858,43.750768],"type":"Point"}
}