{
  "type": "Feature",
  "properties": {
    "addr:full":"9999 W North Ave Milwaukee WI 53226",
    "addr:housenumber":"9999",
    "addr:postcode":"53226",
    "addr:street":"W North Ave",
    "iso:country":"US",
    "sg:address":"9999 W North Ave",
    "sg:city":"Milwaukee",
    "sg:classifiers":[
        {
            "category":"Shopping",
            "subcategory":"Stationery & Office Supplies",
            "type":"Retail Goods"
        }
    ],
    "sg:phone":"+1 414 771 4224",
    "sg:postcode":"53226",
    "sg:province":"WI",
    "sg:tags":[
        "equipment",
        "bookbinder"
    ],
    "wof:name":"Vanguard Industries",
    "wof:placetype":"venue"
},
  "geometry": {"coordinates":[-88.037491,43.060291],"type":"Point"}
}