{
  "type": "Feature",
  "properties": {
    "addr:full":"200 Oak St Mauston WI 53948",
    "addr:housenumber":"200",
    "addr:postcode":"53948",
    "addr:street":"Oak St",
    "iso:country":"US",
    "sg:address":"200 Oak St",
    "sg:city":"Mauston",
    "sg:classifiers":[
        {
            "category":"Government",
            "subcategory":"Office",
            "type":"Public Place"
        }
    ],
    "sg:phone":"+1 608 847 9361",
    "sg:postcode":"53948",
    "sg:province":"WI",
    "wof:name":"Juneau County Traffic Ct Clerk",
    "wof:placetype":"venue"
},
  "geometry": {"coordinates":[-90.07611,43.796186],"type":"Point"}
}