{
  "type": "Feature",
  "properties": {
    "iso:country":"US",
    "sg:address":"19482 105th Ave",
    "sg:city":"Cadott",
    "sg:classifiers":[
        {
            "category":"Manufacturing",
            "subcategory":"Tools & Machinery",
            "type":"Manufacturing & Wholesale Goods"
        }
    ],
    "sg:phone":"+1 715 382 4623",
    "sg:postcode":"54727",
    "sg:province":"WI",
    "sg:tags":[
        "welder"
    ],
    "wof:name":"Lane Mikes Repair",
    "wof:placetype":"venue"
},
  "geometry": {"coordinates":[-91.282574,44.995046],"type":"Point"}
}