{
  "type": "Feature",
  "properties": {
    "iso:country":"US",
    "sg:address":"7833 Marsh Ln",
    "sg:city":"Horicon",
    "sg:classifiers":[
        {
            "category":"Real Estate",
            "subcategory":"Real Estate Agent",
            "type":"Services"
        }
    ],
    "sg:phone":"+1 920 387 3575",
    "sg:postcode":"53032",
    "sg:province":"WI",
    "wof:name":"Luedtke Group LLC",
    "wof:placetype":"venue"
},
  "geometry": {"coordinates":[-88.595279,43.475956],"type":"Point"}
}