{
  "type": "Feature",
  "properties": {
    "iso:country":"US",
    "sg:address":"901 Walsh Rd",
    "sg:city":"Madison",
    "sg:classifiers":[
        {
            "category":"Wholesale",
            "subcategory":"Machinery & Supplies",
            "type":"Manufacturing & Wholesale Goods"
        }
    ],
    "sg:phone":"+1 608 249 6476",
    "sg:postcode":"53714",
    "sg:province":"WI",
    "sg:tags":[
        "equipment"
    ],
    "sg:website":"www.lincolncontrsup.com",
    "wof:name":"Lincoln Contractors Supply",
    "wof:placetype":"venue"
},
  "geometry": {"coordinates":[-89.309384,43.113751],"type":"Point"}
}