{
  "type": "Feature",
  "properties": {
    "iso:country":"US",
    "sg:address":"505 Chaplin Ct",
    "sg:city":"Plymouth",
    "sg:classifiers":[
        {
            "category":"Home & Garden",
            "subcategory":"Household Appliances",
            "type":"Retail Goods"
        }
    ],
    "sg:phone":"+1 920 892 6851",
    "sg:postcode":"53073",
    "sg:province":"WI",
    "wof:name":"Chaplins Inc",
    "wof:placetype":"venue"
},
  "geometry": {"coordinates":[-87.989624,43.75585],"type":"Point"}
}