{
  "type": "Feature",
  "properties": {
    "iso:country":"US",
    "sg:address":"212 W Chestnut St",
    "sg:city":"Pardeeville",
    "sg:classifiers":[
        {
            "category":"Retail",
            "subcategory":"Auto Repair",
            "type":"Services"
        }
    ],
    "sg:phone":"+1 608 429 3136",
    "sg:postcode":"53954",
    "sg:province":"WI",
    "wof:name":"L & D Auto Services & Salvage",
    "wof:placetype":"venue"
},
  "geometry": {"coordinates":[-89.304357,43.535602],"type":"Point"}
}