{
  "type": "Feature",
  "properties": {
    "iso:country":"US",
    "sg:address":"1710 S 108th St",
    "sg:city":"Milwaukee",
    "sg:classifiers":[
        {
            "category":"Food & Beverages",
            "subcategory":"Groceries & Convenience Stores",
            "type":"Retail Goods"
        }
    ],
    "sg:phone":"+1 414 453 4790",
    "sg:postcode":"53214",
    "sg:province":"WI",
    "sg:tags":[
        "pr",
        "mfg"
    ],
    "wof:name":"Crestwood Bakery",
    "wof:placetype":"venue"
},
  "geometry": {"coordinates":[-88.046757,43.012122],"type":"Point"}
}