{
  "type": "Feature",
  "properties": {
    "iso:country":"US",
    "sg:address":"1467 Co Hwy C",
    "sg:city":"Sobieski",
    "sg:classifiers":[
        {
            "category":"Building & Trades",
            "subcategory":"Construction",
            "type":"Services"
        }
    ],
    "sg:phone":"+1 920 822 5359",
    "sg:postcode":"54171",
    "sg:province":"WI",
    "sg:tags":[
        "house"
    ],
    "wof:name":"Ostrowski Construction",
    "wof:placetype":"venue"
},
  "geometry": {"coordinates":[-88.156426,44.728065],"type":"Point"}
}