{
  "type": "Feature",
  "properties": {
    "iso:country":"US",
    "sg:address":"1350 State Hwy 175",
    "sg:city":"Hubertus",
    "sg:classifiers":[
        {
            "category":"Organizations",
            "subcategory":"Religious Organization",
            "type":"Services"
        }
    ],
    "sg:phone":"+1 262 628 2633",
    "sg:postcode":"53033",
    "sg:province":"WI",
    "sg:tags":[
        "church"
    ],
    "sg:website":"www.shepherd-hills.com",
    "wof:name":"Shepherd Of The Hills Church",
    "wof:placetype":"venue"
},
  "geometry": {"coordinates":[-88.188801,43.242008],"type":"Point"}
}