{
  "type": "Feature",
  "properties": {
    "addr:full":"6609 Manchester Dr Greendale WI 53129",
    "addr:housenumber":"6609",
    "addr:postcode":"53129",
    "addr:street":"Manchester Dr",
    "iso:country":"US",
    "sg:address":"6609 Manchester Dr",
    "sg:city":"Greendale",
    "sg:classifiers":[
        {
            "category":"Building & Trades",
            "subcategory":"Construction",
            "type":"Services"
        }
    ],
    "sg:phone":"+1 414 421 3211",
    "sg:postcode":"53129",
    "sg:province":"WI",
    "sg:tags":[
        "house"
    ],
    "wof:name":"Multi Home Skills Inc",
    "wof:placetype":"venue"
},
  "geometry": {"coordinates":[-87.997545,42.950551],"type":"Point"}
}