{
  "type": "Feature",
  "properties": {
    "iso:country":"US",
    "sg:address":"808 Co Rd K",
    "sg:city":"Wisconsin Dells",
    "sg:classifiers":[
        {
            "category":"Manufacturing",
            "subcategory":"Retail Goods",
            "type":"Manufacturing & Wholesale Goods"
        }
    ],
    "sg:phone":"+1 608 254 4726",
    "sg:postcode":"53965",
    "sg:province":"WI",
    "sg:tags":[
        "product",
        "mfg"
    ],
    "wof:name":"Cadys Candle Creations",
    "wof:placetype":"venue"
},
  "geometry": {"coordinates":[-89.73918500000001,43.707566],"type":"Point"}
}