{
  "type": "Feature",
  "properties": {
    "iso:country":"US",
    "sg:address":"2810 Eagle Rd",
    "sg:city":"Wisconsin Rapids",
    "sg:classifiers":[
        {
            "category":"Bars & Pubs",
            "type":"Food & Drink"
        }
    ],
    "sg:phone":"+1 715 424 4062",
    "sg:postcode":"54494",
    "sg:province":"WI",
    "sg:tags":[
        "drinking"
    ],
    "wof:name":"Jammers",
    "wof:placetype":"venue"
},
  "geometry": {"coordinates":[-89.77506,44.413519],"type":"Point"}
}