{
  "type": "Feature",
  "properties": {
    "iso:country":"US",
    "sg:address":"22 Hatten Ave",
    "sg:city":"Rice Lake",
    "sg:classifiers":[
        {
            "category":"Professional",
            "subcategory":"Business Services",
            "type":"Services"
        }
    ],
    "sg:phone":"+1 715 234 4496",
    "sg:postcode":"54868",
    "sg:province":"WI",
    "wof:name":"Phones & More Inc",
    "wof:placetype":"venue"
},
  "geometry": {"coordinates":[-91.741505,45.501185],"type":"Point"}
}