{
  "type": "Feature",
  "properties": {
    "addr:full":"2607 Riverside Ave Marinette WI 54143",
    "addr:housenumber":"2607",
    "addr:postcode":"54143",
    "addr:street":"Riverside Ave",
    "iso:country":"US",
    "sg:address":"2607 Riverside Ave",
    "sg:city":"Marinette",
    "sg:classifiers":[
        {
            "category":"Wholesale",
            "subcategory":"Electrical",
            "type":"Manufacturing & Wholesale Goods"
        }
    ],
    "sg:phone":"+1 715 735 3838",
    "sg:postcode":"54143",
    "sg:province":"WI",
    "sg:tags":[
        "equipment",
        "electric",
        "supply"
    ],
    "wof:name":"Wire Works Inc",
    "wof:placetype":"venue"
},
  "geometry": {"coordinates":[-87.641451,45.104096],"type":"Point"}
}