{
  "type": "Feature",
  "properties": {
    "iso:country":"US",
    "sg:address":"1523 Rose St",
    "sg:city":"La Crosse",
    "sg:classifiers":[
        {
            "category":"Health Services",
            "subcategory":"Health Practitioner",
            "type":"Services"
        }
    ],
    "sg:phone":"+1 608 784 4580",
    "sg:postcode":"54603",
    "sg:province":"WI",
    "wof:name":"Wellness Zone",
    "wof:placetype":"venue"
},
  "geometry": {"coordinates":[-91.248223,43.846037],"type":"Point"}
}