{
  "type": "Feature",
  "properties": {
    "addr:full":"405 Arcadian Ave Waukesha WI 53186",
    "addr:housenumber":"405",
    "addr:postcode":"53186",
    "addr:street":"Arcadian Ave",
    "iso:country":"US",
    "sg:address":"405 Arcadian Ave",
    "sg:city":"Waukesha",
    "sg:classifiers":[
        {
            "category":"Social Services",
            "type":"Services"
        }
    ],
    "sg:phone":"+1 262 970 0539",
    "sg:postcode":"53186",
    "sg:province":"WI",
    "sg:tags":[
        "organization",
        "welfare"
    ],
    "wof:name":"LA Casa De Espernaza",
    "wof:placetype":"venue"
},
  "geometry": {"coordinates":[-88.222751,43.011808],"type":"Point"}
}