{
  "type": "Feature",
  "properties": {
    "iso:country":"US",
    "sg:address":"123 Talon Pl",
    "sg:city":"Sun Prairie",
    "sg:classifiers":[
        {
            "category":"Real Estate",
            "subcategory":"Real Estate Agent",
            "type":"Services"
        }
    ],
    "sg:phone":"+1 608 834 8804",
    "sg:postcode":"53590",
    "sg:province":"WI",
    "wof:name":"Spanos Co",
    "wof:placetype":"venue"
},
  "geometry": {"coordinates":[-89.225577,43.178449],"type":"Point"}
}