{
  "type": "Feature",
  "properties": {
    "iso:country":"US",
    "sg:address":"13255 W Bluemound Rd",
    "sg:city":"Brookfield",
    "sg:classifiers":[
        {
            "category":"Professional",
            "subcategory":"Business Services",
            "type":"Services"
        }
    ],
    "sg:phone":"+1 262 786 7800",
    "sg:postcode":"53005",
    "sg:province":"WI",
    "sg:tags":[
        "credit",
        "processor",
        "card"
    ],
    "sg:website":"http://www.mseft.com",
    "wof:name":"Merchant Services",
    "wof:placetype":"venue"
},
  "geometry": {"coordinates":[-88.078114,43.035839],"type":"Point"}
}