{
  "type": "Feature",
  "properties": {
    "iso:country":"US",
    "sg:address":"1920 Libal St",
    "sg:city":"Green Bay",
    "sg:classifiers":[
        {
            "category":"Manufacturing",
            "subcategory":"Printing",
            "type":"Manufacturing & Wholesale Goods"
        }
    ],
    "sg:phone":"+1 920 437 7593",
    "sg:postcode":"54301",
    "sg:province":"WI",
    "sg:tags":[
        "commercial"
    ],
    "wof:name":"J M C Animation & Graphics",
    "wof:placetype":"venue"
},
  "geometry": {"coordinates":[-88.012378,44.483434],"type":"Point"}
}