{
  "type": "Feature",
  "properties": {
    "iso:country":"US",
    "sg:address":"34510 Geneva Rd",
    "sg:city":"New Munster",
    "sg:classifiers":[
        {
            "category":"Personal",
            "subcategory":"Barber",
            "type":"Services"
        }
    ],
    "sg:phone":"+1 262 537 2669",
    "sg:postcode":"53152",
    "sg:province":"WI",
    "wof:name":"Larry's Barber Shop",
    "wof:placetype":"venue"
},
  "geometry": {"coordinates":[-88.235298,42.5821],"type":"Point"}
}