{
  "type": "Feature",
  "properties": {
    "iso:country":"US",
    "sg:address":"122 N 16th St",
    "sg:city":"Milwaukee",
    "sg:classifiers":[
        {
            "category":"Organizations",
            "subcategory":"Religious Organization",
            "type":"Services"
        }
    ],
    "sg:phone":"+1 414 672 9226",
    "sg:postcode":"53233",
    "sg:province":"WI",
    "wof:name":"Milwaukee Victory Church",
    "wof:placetype":"venue"
},
  "geometry": {"coordinates":[-87.932911,43.030863],"type":"Point"}
}