{
  "type": "Feature",
  "properties": {
    "addr:full":"28840 Beach Dr Waterford WI 53185",
    "addr:housenumber":"28840",
    "addr:postcode":"53185",
    "addr:street":"Beach Dr",
    "iso:country":"US",
    "sg:address":"28840 Beach Dr",
    "sg:city":"Waterford",
    "sg:classifiers":[
        {
            "category":"Manufacturing",
            "subcategory":"Rubber & Plastics",
            "type":"Manufacturing & Wholesale Goods"
        }
    ],
    "sg:phone":"+1 262 895 2061",
    "sg:postcode":"53185",
    "sg:province":"WI",
    "sg:tags":[
        "product",
        "mfg"
    ],
    "wof:name":"Seegers Environmental LLC",
    "wof:placetype":"venue"
},
  "geometry": {"coordinates":[-88.209495,42.809636],"type":"Point"}
}