{
  "type": "Feature",
  "properties": {
    "iso:country":"US",
    "sg:address":"1221 Clary St",
    "sg:city":"Beloit",
    "sg:classifiers":[
        {
            "category":"Real Estate",
            "subcategory":"Developer",
            "type":"Services"
        }
    ],
    "sg:phone":"+1 608 364 2874",
    "sg:postcode":"53511",
    "sg:province":"WI",
    "sg:tags":[
        "cemetery"
    ],
    "wof:name":"Oakwood Cemetery",
    "wof:placetype":"venue"
},
  "geometry": {"coordinates":[-89.020328,42.506478],"type":"Point"}
}