{
  "type": "Feature",
  "properties": {
    "addr:full":"2249 Amsterdam Rd Cedar Grove WI 53013",
    "addr:housenumber":"2249",
    "addr:postcode":"53013",
    "addr:street":"Amsterdam Rd",
    "iso:country":"US",
    "sg:address":"2249 Amsterdam Rd",
    "sg:city":"Cedar Grove",
    "sg:classifiers":[
        {
            "category":"Farming",
            "subcategory":"Dairy Farm",
            "type":"Manufacturing & Wholesale Goods"
        }
    ],
    "sg:phone":"+1 920 668 6349",
    "sg:postcode":"53013",
    "sg:province":"WI",
    "wof:name":"Lake Breeze Farms",
    "wof:placetype":"venue"
},
  "geometry": {"coordinates":[-87.80743,43.557485],"type":"Point"}
}