{
  "type": "Feature",
  "properties": {
    "iso:country":"US",
    "sg:address":"3408 N Port Washington Rd",
    "sg:city":"Milwaukee",
    "sg:classifiers":[
        {
            "category":"Bars & Pubs",
            "type":"Food & Drink"
        }
    ],
    "sg:phone":"+1 414 265 6040",
    "sg:postcode":"53212",
    "sg:province":"WI",
    "sg:tags":[
        "drinking"
    ],
    "wof:name":"Promises",
    "wof:placetype":"venue"
},
  "geometry": {"coordinates":[-87.917329,43.081975],"type":"Point"}
}