{
  "type": "Feature",
  "properties": {
    "iso:country":"US",
    "sg:address":"2745 Fox River Shores W",
    "sg:city":"Berlin",
    "sg:classifiers":[
        {
            "category":"Professional",
            "type":"Services"
        }
    ],
    "sg:phone":"+1 920 748 7198",
    "sg:postcode":"54923",
    "sg:province":"WI",
    "wof:name":"Just Pleasures",
    "wof:placetype":"venue"
},
  "geometry": {"coordinates":[-89.018003,43.943125],"type":"Point"}
}