{
  "type": "Feature",
  "properties": {
    "addr:full":"3680 Co Rd Ww Wausau WI 54403",
    "addr:housenumber":"3680",
    "addr:postcode":"54403",
    "addr:street":"Co Rd",
    "iso:country":"US",
    "sg:address":"3680 Co Rd Ww",
    "sg:city":"Wausau",
    "sg:classifiers":[
        {
            "category":"Manufacturing",
            "subcategory":"Metals",
            "type":"Manufacturing & Wholesale Goods"
        }
    ],
    "sg:phone":"+1 715 675 3669",
    "sg:postcode":"54403",
    "sg:province":"WI",
    "sg:tags":[
        "steel"
    ],
    "wof:name":"Wausau Hardware & Machine Co",
    "wof:placetype":"venue"
},
  "geometry": {"coordinates":[-89.574684,45.043159],"type":"Point"}
}