{
  "type": "Feature",
  "properties": {
    "iso:country":"US",
    "sg:address":"2 Cherbourg Ct",
    "sg:city":"Madison",
    "sg:classifiers":[
        {
            "category":"Real Estate",
            "subcategory":"Real Estate Agent",
            "type":"Services"
        }
    ],
    "sg:phone":"+1 608 274 9533",
    "sg:postcode":"53711",
    "sg:province":"WI",
    "sg:tags":[
        "broker",
        "appraiser"
    ],
    "wof:name":"Mueller Real Estate Service",
    "wof:placetype":"venue"
},
  "geometry": {"coordinates":[-89.494717,43.033668],"type":"Point"}
}