{
  "type": "Feature",
  "properties": {
    "addr:full":"1267 W Mason St Green Bay WI 54303",
    "addr:housenumber":"1267",
    "addr:postcode":"54303",
    "addr:street":"W Mason St",
    "iso:country":"US",
    "sg:address":"1267 W Mason St",
    "sg:city":"Green Bay",
    "sg:classifiers":[
        {
            "category":"Retail",
            "subcategory":"Self-service Laundry",
            "type":"Services"
        }
    ],
    "sg:phone":"+1 920 496 2260",
    "sg:postcode":"54303",
    "sg:province":"WI",
    "sg:tags":[
        "coin"
    ],
    "wof:name":"Laundry Center West",
    "wof:placetype":"venue"
},
  "geometry": {"coordinates":[-88.04971,44.518353],"type":"Point"}
}