{
  "type": "Feature",
  "properties": {
    "iso:country":"US",
    "sg:address":"403 Mallard Dr",
    "sg:city":"Holmen",
    "sg:classifiers":[
        {
            "category":"Building & Trades",
            "subcategory":"Construction",
            "type":"Services"
        }
    ],
    "sg:phone":"+1 608 526 2213",
    "sg:postcode":"54636",
    "sg:province":"WI",
    "sg:tags":[
        "house"
    ],
    "wof:name":"Gunderson Custom Homes",
    "wof:placetype":"venue"
},
  "geometry": {"coordinates":[-91.27489300000001,43.96611],"type":"Point"}
}