{
  "type": "Feature",
  "properties": {
    "addr:full":"304 W Main St Waterford WI 53185",
    "addr:housenumber":"304",
    "addr:postcode":"53185",
    "addr:street":"W Main St",
    "iso:country":"US",
    "sg:address":"304 W Main St",
    "sg:city":"Waterford",
    "sg:classifiers":[
        {
            "category":"Retail",
            "subcategory":"Portrait Studio",
            "type":"Services"
        }
    ],
    "sg:phone":"+1 262 534 5569",
    "sg:postcode":"53185",
    "sg:province":"WI",
    "sg:tags":[
        "photo"
    ],
    "wof:name":"C & M Photography",
    "wof:placetype":"venue"
},
  "geometry": {"coordinates":[-88.215879,42.763709],"type":"Point"}
}