{
  "type": "Feature",
  "properties": {
    "addr:full":"10368 Center Rd Tomahawk WI 54487",
    "addr:housenumber":"10368",
    "addr:postcode":"54487",
    "addr:street":"Center Rd",
    "iso:country":"US",
    "sg:address":"10368 Center Rd",
    "sg:city":"Tomahawk",
    "sg:classifiers":[
        {
            "category":"Manufacturing",
            "subcategory":"Toys & Sporting Goods",
            "type":"Manufacturing & Wholesale Goods"
        }
    ],
    "sg:phone":"+1 715 453 4249",
    "sg:postcode":"54487",
    "sg:province":"WI",
    "sg:tags":[
        "mfg"
    ],
    "wof:name":"Serendipity",
    "wof:placetype":"venue"
},
  "geometry": {"coordinates":[-89.76470399999999,45.575693],"type":"Point"}
}