{
  "type": "Feature",
  "properties": {
    "iso:country":"US",
    "sg:address":"2025 Highland Ave",
    "sg:city":"Eau Claire",
    "sg:classifiers":[
        {
            "category":"Bakery",
            "type":"Food & Drink"
        }
    ],
    "sg:menulink":"http://www.allmenus.com/wi/eau-claire/102348-perkins-restaurant--bakery/menu/",
    "sg:phone":"+1 715 834 9911",
    "sg:postcode":"54701",
    "sg:province":"WI",
    "sg:tags":[
        "sandwich",
        "salad",
        "soup",
        "american",
        "pastry",
        "wrap"
    ],
    "wof:name":"Perkins Restaurant & Bakery",
    "wof:placetype":"venue"
},
  "geometry": {"coordinates":[-91.47248999999999,44.807323],"type":"Point"}
}