{
  "type": "Feature",
  "properties": {
    "iso:country":"US",
    "sg:address":"860 Fox Point Plz",
    "sg:city":"Neenah",
    "sg:classifiers":[
        {
            "category":"Shopping",
            "subcategory":"Gifts & Souvenirs",
            "type":"Retail Goods"
        }
    ],
    "sg:phone":"+1 920 722 0267",
    "sg:postcode":"54956",
    "sg:province":"WI",
    "sg:tags":[
        "shop"
    ],
    "wof:name":"Winslow's Hallmark",
    "wof:placetype":"venue"
},
  "geometry": {"coordinates":[-88.482634,44.175791],"type":"Point"}
}