{
  "type": "Feature",
  "properties": {
    "addr:full":"705 4th St Mattoon WI 54450",
    "addr:housenumber":"705",
    "addr:postcode":"54450",
    "addr:street":"4Th St",
    "iso:country":"US",
    "sg:address":"705 4th St",
    "sg:city":"Mattoon",
    "sg:classifiers":[
        {
            "category":"Government",
            "subcategory":"Post Office",
            "type":"Public Place"
        }
    ],
    "sg:phone":"+1 715 000 1111",
    "sg:postcode":"54450",
    "sg:province":"WI",
    "wof:name":"US Post Office",
    "wof:placetype":"venue"
},
  "geometry": {"coordinates":[-89.041951,45.004915],"type":"Point"}
}