{
  "type": "Feature",
  "properties": {
    "iso:country":"US",
    "sg:address":"231 N Main St",
    "sg:city":"Kewaunee",
    "sg:classifiers":[
        {
            "category":"Professional",
            "type":"Services"
        }
    ],
    "sg:phone":"+1 920 388 0229",
    "sg:postcode":"54216",
    "sg:province":"WI",
    "wof:name":"Krohn Sports",
    "wof:placetype":"venue"
},
  "geometry": {"coordinates":[-87.501476,44.463926],"type":"Point"}
}