{
  "type": "Feature",
  "properties": {
    "iso:country":"US",
    "sg:address":"135 W Wisconsin Ave",
    "sg:city":"Neenah",
    "sg:classifiers":[
        {
            "category":"Organizations",
            "subcategory":"Non-profit Organization",
            "type":"Services"
        }
    ],
    "sg:phone":"+1 920 722 1920",
    "sg:postcode":"54956",
    "sg:province":"WI",
    "sg:tags":[
        "fund",
        "counselor",
        "raising"
    ],
    "sg:website":"www.neenahtrails.com",
    "wof:name":"Future Neenah Inc",
    "wof:placetype":"venue"
},
  "geometry": {"coordinates":[-88.462824,44.187037],"type":"Point"}
}