{
  "type": "Feature",
  "properties": {
    "addr:full":"2032 S Oneida St Green Bay WI 54304",
    "addr:housenumber":"2032",
    "addr:postcode":"54304",
    "addr:street":"S Oneida St",
    "iso:country":"US",
    "sg:address":"2032 S Oneida St",
    "sg:city":"Green Bay",
    "sg:classifiers":[
        {
            "category":"Building & Trades",
            "subcategory":"Construction",
            "type":"Services"
        }
    ],
    "sg:phone":"+1 920 497 3084",
    "sg:postcode":"54304",
    "sg:province":"WI",
    "sg:tags":[
        "house"
    ],
    "wof:name":"All County Construction",
    "wof:placetype":"venue"
},
  "geometry": {"coordinates":[-88.06026,44.49672],"type":"Point"}
}