{
  "type": "Feature",
  "properties": {
    "iso:country":"US",
    "sg:address":"4062 Sunset Hill Rd",
    "sg:city":"Hubertus",
    "sg:classifiers":[
        {
            "category":"Professional",
            "type":"Services"
        }
    ],
    "sg:phone":"+1 262 628 3990",
    "sg:postcode":"53033",
    "sg:province":"WI",
    "wof:name":"Wendy Ruhland",
    "wof:placetype":"venue"
},
  "geometry": {"coordinates":[-88.24015199999999,43.22882],"type":"Point"}
}