{
  "type": "Feature",
  "properties": {
    "iso:country":"US",
    "sg:address":"657 Chestnut St",
    "sg:city":"Neenah",
    "sg:classifiers":[
        {
            "category":"Building & Trades",
            "subcategory":"Construction",
            "type":"Services"
        }
    ],
    "sg:phone":"+1 920 729 1831",
    "sg:postcode":"54956",
    "sg:province":"WI",
    "sg:tags":[
        "hanging",
        "contractor"
    ],
    "wof:name":"Parker Painting & Remodeling",
    "wof:placetype":"venue"
},
  "geometry": {"coordinates":[-88.458773,44.176897],"type":"Point"}
}