{
  "type": "Feature",
  "properties": {
    "iso:country":"US",
    "sg:address":"601 Lake Ave",
    "sg:city":"Racine",
    "sg:classifiers":[
        {
            "category":"Building & Trades",
            "subcategory":"Cleaning & Sanitation",
            "type":"Services"
        }
    ],
    "sg:phone":"+1 262 634 9000",
    "sg:postcode":"53403",
    "sg:province":"WI",
    "sg:tags":[
        "maintenance"
    ],
    "wof:name":"Cleanpower",
    "wof:placetype":"venue"
},
  "geometry": {"coordinates":[-87.78142699999999,42.725969],"type":"Point"}
}