{
  "type": "Feature",
  "properties": {
    "iso:country":"US",
    "sg:address":"122 Main St",
    "sg:city":"Almond",
    "sg:classifiers":[
        {
            "category":"Government",
            "subcategory":"Office",
            "type":"Public Place"
        }
    ],
    "sg:phone":"+1 715 366 8171",
    "sg:postcode":"54909",
    "sg:province":"WI",
    "sg:tags":[
        "village"
    ],
    "wof:name":"Almond Village Clerk",
    "wof:placetype":"venue"
},
  "geometry": {"coordinates":[-89.408113,44.26106],"type":"Point"}
}