{
  "type": "Feature",
  "properties": {
    "iso:country":"US",
    "sg:address":"1290 Russett Ct",
    "sg:city":"Green Bay",
    "sg:classifiers":[
        {
            "category":"Retail",
            "subcategory":"Car Wash",
            "type":"Services"
        }
    ],
    "sg:phone":"+1 920 819 4001",
    "sg:postcode":"54313",
    "sg:province":"WI",
    "sg:tags":[
        "automobile",
        "detail",
        "clean"
    ],
    "wof:name":"Checkered Flag Auto Wash",
    "wof:placetype":"venue"
},
  "geometry": {"coordinates":[-88.075638,44.578922],"type":"Point"}
}