{
  "type": "Feature",
  "properties": {
    "iso:country":"US",
    "sg:address":"1224 Crestview Dr",
    "sg:city":"Baraboo",
    "sg:classifiers":[
        {
            "category":"Professional",
            "subcategory":"Business Services",
            "type":"Services"
        }
    ],
    "sg:phone":"+1 608 356 2377",
    "sg:postcode":"53913",
    "sg:province":"WI",
    "wof:name":"Granite Express LLC",
    "wof:placetype":"venue"
},
  "geometry": {"coordinates":[-89.72057599999999,43.468763],"type":"Point"}
}