{
  "type": "Feature",
  "properties": {
    "iso:country":"US",
    "sg:address":"5085 Thorson Rd",
    "sg:city":"Sun Prairie",
    "sg:classifiers":[
        {
            "category":"Building & Trades",
            "subcategory":"Construction",
            "type":"Services"
        }
    ],
    "sg:phone":"+1 608 244 6053",
    "sg:postcode":"53590",
    "sg:province":"WI",
    "sg:tags":[
        "resurfacing",
        "laying",
        "refinishing",
        "floor"
    ],
    "wof:name":"Larson Floor Svc",
    "wof:placetype":"venue"
},
  "geometry": {"coordinates":[-89.246865,43.121766],"type":"Point"}
}