{
  "type": "Feature",
  "properties": {
    "iso:country":"US",
    "sg:address":"1982 Rader Rd",
    "sg:city":"Marinette",
    "sg:classifiers":[
        {
            "category":"Shopping",
            "type":"Retail Goods"
        }
    ],
    "sg:phone":"+1 715 732 8981",
    "sg:postcode":"54143",
    "sg:province":"WI",
    "sg:tags":[
        "merchandise"
    ],
    "wof:name":"A New You",
    "wof:placetype":"venue"
},
  "geometry": {"coordinates":[-87.68517300000001,45.056635],"type":"Point"}
}