{
  "type": "Feature",
  "properties": {
    "iso:country":"US",
    "sg:address":"18185 Lamplighter Ln",
    "sg:city":"Brookfield",
    "sg:classifiers":[
        {
            "category":"Health Services",
            "subcategory":"Clinic",
            "type":"Services"
        }
    ],
    "sg:phone":"+1 262 782 1976",
    "sg:postcode":"53045",
    "sg:province":"WI",
    "sg:tags":[
        "counseling",
        "specialty",
        "outpatient"
    ],
    "wof:name":"Post Abortion Helpline Inc",
    "wof:placetype":"venue"
},
  "geometry": {"coordinates":[-88.13861900000001,43.066102],"type":"Point"}
}