{
  "type": "Feature",
  "properties": {
    "iso:country":"US",
    "sg:address":"1180 Mid Valley Dr",
    "sg:city":"De Pere",
    "sg:classifiers":[
        {
            "category":"Home & Garden",
            "subcategory":"Furniture",
            "type":"Retail Goods"
        }
    ],
    "sg:phone":"+1 920 339 0670",
    "sg:postcode":"54115",
    "sg:province":"WI",
    "sg:tags":[
        "bedding"
    ],
    "wof:name":"Mc Crory's Furniture Gallery",
    "wof:placetype":"venue"
},
  "geometry": {"coordinates":[-88.092091,44.450766],"type":"Point"}
}