{
  "type": "Feature",
  "properties": {
    "addr:full":"124 W Chestnut St Burlington WI 53105",
    "addr:housenumber":"124",
    "addr:postcode":"53105",
    "addr:street":"W Chestnut St",
    "iso:country":"US",
    "sg:address":"124 W Chestnut St",
    "sg:city":"Burlington",
    "sg:classifiers":[
        {
            "category":"Health Services",
            "subcategory":"Optometrist",
            "type":"Services"
        }
    ],
    "sg:phone":"+1 262 767 1266",
    "sg:postcode":"53105",
    "sg:province":"WI",
    "wof:name":"Neighborhood Optometry Llc",
    "wof:placetype":"venue"
},
  "geometry": {"coordinates":[-88.277885,42.680531],"type":"Point"}
}