{
  "type": "Feature",
  "properties": {
    "iso:country":"US",
    "sg:address":"8124 Windancer Dr",
    "sg:city":"Pulaski",
    "sg:classifiers":[
        {
            "category":"Real Estate",
            "subcategory":"Real Estate Operator",
            "type":"Services"
        }
    ],
    "sg:phone":"+1 920 822 5774",
    "sg:postcode":"54162",
    "sg:province":"WI",
    "sg:tags":[
        "building",
        "nonresidential"
    ],
    "wof:name":"Zimms Properties LLC",
    "wof:placetype":"venue"
},
  "geometry": {"coordinates":[-88.174683,44.692952],"type":"Point"}
}