{
  "type": "Feature",
  "properties": {
    "iso:country":"US",
    "sg:address":"2830 Crystal Rd",
    "sg:city":"Waupaca",
    "sg:classifiers":[
        {
            "category":"Freight",
            "type":"Transportation"
        }
    ],
    "sg:phone":"+1 715 256 1955",
    "sg:postcode":"54981",
    "sg:province":"WI",
    "sg:tags":[
        "hauling",
        "trucking"
    ],
    "wof:name":"Cross Roads Transit",
    "wof:placetype":"venue"
},
  "geometry": {"coordinates":[-89.083062,44.31565],"type":"Point"}
}