{
  "type": "Feature",
  "properties": {
    "iso:country":"US",
    "sg:address":"248 Wausau Center",
    "sg:city":"Wausau",
    "sg:classifiers":[
        {
            "category":"Shopping",
            "subcategory":"Pharmacy",
            "type":"Retail Goods"
        }
    ],
    "sg:phone":"+1 715 845 8278",
    "sg:postcode":"54403",
    "sg:province":"WI",
    "sg:tags":[
        "photofinishing",
        "laboratory"
    ],
    "wof:name":"Walgreens",
    "wof:placetype":"venue"
},
  "geometry": {"coordinates":[-89.628719,44.958748],"type":"Point"}
}