{
  "type": "Feature",
  "properties": {
    "iso:country":"US",
    "sg:address":"9636 W Flagg Ave",
    "sg:city":"Milwaukee",
    "sg:classifiers":[
        {
            "category":"Building & Trades",
            "subcategory":"Construction",
            "type":"Services"
        }
    ],
    "sg:phone":"+1 414 536 0287",
    "sg:postcode":"53225",
    "sg:province":"WI",
    "sg:tags":[
        "contractor"
    ],
    "wof:name":"K & J Builders Inc",
    "wof:placetype":"venue"
},
  "geometry": {"coordinates":[-88.03281200000001,43.124326],"type":"Point"}
}