{
  "type": "Feature",
  "properties": {
    "iso:country":"US",
    "sg:address":"23 Taylor St",
    "sg:city":"Winneconne",
    "sg:classifiers":[
        {
            "category":"Real Estate",
            "subcategory":"Real Estate Agent",
            "type":"Services"
        }
    ],
    "sg:phone":"+1 920 410 3766",
    "sg:postcode":"54986",
    "sg:province":"WI",
    "wof:name":"Coldwell Banker Group",
    "wof:placetype":"venue"
},
  "geometry": {"coordinates":[-88.714847,44.105207],"type":"Point"}
}