{
  "type": "Feature",
  "properties": {
    "iso:country":"US",
    "sg:address":"416 W Geneva St",
    "sg:city":"Delavan",
    "sg:classifiers":[
        {
            "category":"Organizations",
            "subcategory":"Religious Organization",
            "type":"Services"
        }
    ],
    "sg:phone":"+1 262 728 6589",
    "sg:postcode":"53115",
    "sg:province":"WI",
    "sg:tags":[
        "school",
        "church"
    ],
    "wof:name":"Angelcal Lthern Chrch Redeemer",
    "wof:placetype":"venue"
},
  "geometry": {"coordinates":[-88.657481,42.627746],"type":"Point"}
}