{
  "type": "Feature",
  "properties": {
    "iso:country":"US",
    "sg:address":"1216 W Walnut St",
    "sg:city":"Milwaukee",
    "sg:classifiers":[
        {
            "category":"Professional",
            "subcategory":"Business Services",
            "type":"Services"
        }
    ],
    "sg:phone":"+1 414 264 2326",
    "sg:postcode":"53205",
    "sg:province":"WI",
    "wof:name":"Walnut Way Conservation Core",
    "wof:placetype":"venue"
},
  "geometry": {"coordinates":[-87.927461,43.052692],"type":"Point"}
}