{
  "type": "Feature",
  "properties": {
    "iso:country":"US",
    "sg:address":"5541 N Co Rd Kk",
    "sg:city":"Milton",
    "sg:classifiers":[
        {
            "category":"Insurance",
            "subcategory":"Insurance Agent",
            "type":"Services"
        }
    ],
    "sg:phone":"+1 608 868 3746",
    "sg:postcode":"53563",
    "sg:province":"WI",
    "wof:name":"Sugar Creek Mutual Insurance",
    "wof:placetype":"venue"
},
  "geometry": {"coordinates":[-88.85747499999999,42.748746],"type":"Point"}
}