{
  "type": "Feature",
  "properties": {
    "iso:country":"US",
    "sg:address":"1206 Dartmouth Rd",
    "sg:city":"Madison",
    "sg:classifiers":[
        {
            "category":"Food & Beverages",
            "subcategory":"Groceries & Convenience Stores",
            "type":"Retail Goods"
        }
    ],
    "sg:phone":"+1 608 236 4565",
    "sg:postcode":"53705",
    "sg:province":"WI",
    "sg:tags":[
        "eat",
        "mfg"
    ],
    "wof:name":"Atlas Delicatessen",
    "wof:placetype":"venue"
},
  "geometry": {"coordinates":[-89.439666,43.079564],"type":"Point"}
}