{
  "type": "Feature",
  "properties": {
    "addr:full":"6254 Co Rd Bb Appleton WI 54914",
    "addr:housenumber":"6254",
    "addr:postcode":"54914",
    "addr:street":"Co Rd",
    "iso:country":"US",
    "sg:address":"6254 Co Rd Bb",
    "sg:city":"Appleton",
    "sg:classifiers":[
        {
            "category":"Manufacturing",
            "subcategory":"Building Materials",
            "type":"Manufacturing & Wholesale Goods"
        }
    ],
    "sg:phone":"+1 920 739 8199",
    "sg:postcode":"54914",
    "sg:province":"WI",
    "sg:tags":[
        "wooden",
        "mfg",
        "truss",
        "roof",
        "floor"
    ],
    "wof:name":"Trussco",
    "wof:placetype":"venue"
},
  "geometry": {"coordinates":[-88.499467,44.244178],"type":"Point"}
}