{
  "type": "Feature",
  "properties": {
    "iso:country":"US",
    "sg:address":"6054 N Railroad St",
    "sg:city":"Lyons",
    "sg:classifiers":[
        {
            "category":"Food & Beverages",
            "subcategory":"Groceries & Convenience Stores",
            "type":"Retail Goods"
        }
    ],
    "sg:phone":"+1 262 763 9499",
    "sg:postcode":"53148",
    "sg:province":"WI",
    "wof:name":"Jeannie's Little Store",
    "wof:placetype":"venue"
},
  "geometry": {"coordinates":[-88.35746399999999,42.651849],"type":"Point"}
}