{
  "type": "Feature",
  "properties": {
    "addr:full":"308 E 4th St Marshfield WI 54449",
    "addr:housenumber":"308",
    "addr:postcode":"54449",
    "addr:street":"E 4Th St",
    "iso:country":"US",
    "sg:address":"308 E 4th St",
    "sg:city":"Marshfield",
    "sg:classifiers":[
        {
            "category":"Professional",
            "subcategory":"Lawyer & Legal Services",
            "type":"Services"
        }
    ],
    "sg:phone":"+1 715 387 3611",
    "sg:postcode":"54449",
    "sg:province":"WI",
    "sg:tags":[
        "attorney"
    ],
    "wof:name":"Gorst Law Offices",
    "wof:placetype":"venue"
},
  "geometry": {"coordinates":[-90.172653,44.66301],"type":"Point"}
}