{
  "type": "Feature",
  "properties": {
    "iso:country":"US",
    "sg:address":"3704 Platt View Ct",
    "sg:city":"Manitowoc",
    "sg:classifiers":[
        {
            "category":"Banks & Credit Unions",
            "subcategory":"Bank",
            "type":"Services"
        }
    ],
    "sg:phone":"+1 920 652 9047",
    "sg:postcode":"54220",
    "sg:province":"WI",
    "sg:tags":[
        "commercial"
    ],
    "wof:name":"Wismarq",
    "wof:placetype":"venue"
},
  "geometry": {"coordinates":[-87.695025,44.120508],"type":"Point"}
}