{
  "type": "Feature",
  "properties": {
    "addr:full":"4460 N Lake Dr Shorewood WI 53211",
    "addr:housenumber":"4460",
    "addr:postcode":"53211",
    "addr:street":"N Lake Dr",
    "iso:country":"US",
    "sg:address":"4460 N Lake Dr",
    "sg:city":"Shorewood",
    "sg:classifiers":[
        {
            "category":"Health Services",
            "subcategory":"Doctor",
            "type":"Services"
        }
    ],
    "sg:phone":"+1 414 332 5184",
    "sg:postcode":"53211",
    "sg:province":"WI",
    "sg:tags":[
        "physician",
        "surgeon"
    ],
    "wof:name":"James H Langenkamp MD",
    "wof:placetype":"venue"
},
  "geometry": {"coordinates":[-87.87728799999999,43.096483],"type":"Point"}
}