{
  "type": "Feature",
  "properties": {
    "addr:full":"2641 W Mason St Green Bay WI 54303",
    "addr:housenumber":"2641",
    "addr:postcode":"54303",
    "addr:street":"W Mason St",
    "iso:country":"US",
    "sg:address":"2641 W Mason St",
    "sg:city":"Green Bay",
    "sg:classifiers":[
        {
            "category":"Shopping",
            "subcategory":"Department Store",
            "type":"Retail Goods"
        }
    ],
    "sg:phone":"+1 920 494 2990",
    "sg:postcode":"54303",
    "sg:province":"WI",
    "sg:tags":[
        "shop"
    ],
    "wof:name":"Ben Franklin",
    "wof:placetype":"venue"
},
  "geometry": {"coordinates":[-88.10952899999999,44.523944],"type":"Point"}
}