{
  "type": "Feature",
  "properties": {
    "addr:full":"1227 N 8th St Sheboygan WI 53081",
    "addr:housenumber":"1227",
    "addr:postcode":"53081",
    "addr:street":"N 8Th St",
    "iso:country":"US",
    "sg:address":"1227 N 8th St",
    "sg:city":"Sheboygan",
    "sg:classifiers":[
        {
            "category":"Personal",
            "subcategory":"Beauty Salon",
            "type":"Services"
        }
    ],
    "sg:phone":"+1 920 457 4247",
    "sg:postcode":"53081",
    "sg:province":"WI",
    "sg:website":"www.groovesalon.net",
    "wof:name":"Groove Salon LTD",
    "wof:placetype":"venue"
},
  "geometry": {"coordinates":[-87.712862,43.75824],"type":"Point"}
}