{
  "type": "Feature",
  "properties": {
    "iso:country":"US",
    "sg:address":"1361 Elmwood Ave",
    "sg:city":"Ixonia",
    "sg:classifiers":[
        {
            "category":"Building & Trades",
            "subcategory":"Equipment Rental",
            "type":"Services"
        }
    ],
    "sg:phone":"+1 920 261 8404",
    "sg:postcode":"53036",
    "sg:province":"WI",
    "sg:tags":[
        "earth",
        "moving",
        "rent",
        "lease"
    ],
    "wof:name":"American Midwest Equipment Co",
    "wof:placetype":"venue"
},
  "geometry": {"coordinates":[-88.594321,43.140576],"type":"Point"}
}