{
  "type": "Feature",
  "properties": {
    "iso:country":"US",
    "sg:address":"309 Superior St",
    "sg:city":"Antigo",
    "sg:classifiers":[
        {
            "category":"Wholesale",
            "subcategory":"Machinery & Supplies",
            "type":"Manufacturing & Wholesale Goods"
        }
    ],
    "sg:phone":"+1 715 627 0077",
    "sg:postcode":"54409",
    "sg:province":"WI",
    "sg:tags":[
        "industrial"
    ],
    "wof:name":"Fastenal Company",
    "wof:placetype":"venue"
},
  "geometry": {"coordinates":[-89.15227299999999,45.137556],"type":"Point"}
}