{
  "type": "Feature",
  "properties": {
    "addr:full":"1040 Crestview Cir Baraboo WI 53913",
    "addr:housenumber":"1040",
    "addr:postcode":"53913",
    "addr:street":"Crestview Cir",
    "iso:country":"US",
    "sg:address":"1040 Crestview Cir",
    "sg:city":"Baraboo",
    "sg:classifiers":[
        {
            "category":"Wholesale",
            "subcategory":"Machinery & Supplies",
            "type":"Manufacturing & Wholesale Goods"
        }
    ],
    "sg:phone":"+1 608 356 3498",
    "sg:postcode":"53913",
    "sg:province":"WI",
    "sg:tags":[
        "equipment",
        "industrial"
    ],
    "wof:name":"Factory Supplies Co",
    "wof:placetype":"venue"
},
  "geometry": {"coordinates":[-89.768112,43.481338],"type":"Point"}
}