{
  "type": "Feature",
  "properties": {
    "iso:country":"US",
    "sg:address":"8145 N Highline Rd",
    "sg:city":"Hayward",
    "sg:classifiers":[
        {
            "category":"Travel",
            "subcategory":"Hotels & Motels",
            "type":"Entertainment"
        }
    ],
    "sg:phone":"+1 715 634 3766",
    "sg:postcode":"54843",
    "sg:province":"WI",
    "sg:tags":[
        "operation"
    ],
    "wof:name":"Pine Hill LLC",
    "wof:placetype":"venue"
},
  "geometry": {"coordinates":[-91.459625,45.914846],"type":"Point"}
}