{
  "type": "Feature",
  "properties": {
    "iso:country":"US",
    "sg:address":"110 N Main St",
    "sg:city":"Poynette",
    "sg:classifiers":[
        {
            "category":"Health Services",
            "subcategory":"Chiropractor",
            "type":"Services"
        }
    ],
    "sg:phone":"+1 608 635 8915",
    "sg:postcode":"53955",
    "sg:province":"WI",
    "wof:name":"Anunson Family Chiropractic",
    "wof:placetype":"venue"
},
  "geometry": {"coordinates":[-89.402689,43.391551],"type":"Point"}
}