{
  "type": "Feature",
  "properties": {
    "iso:country":"US",
    "sg:address":"1861 W Puetz Rd",
    "sg:city":"Oak Creek",
    "sg:classifiers":[
        {
            "category":"Building & Trades",
            "subcategory":"Plumbing",
            "type":"Services"
        }
    ],
    "sg:phone":"+1 414 761 3839",
    "sg:postcode":"53154",
    "sg:province":"WI",
    "sg:tags":[
        "contractor"
    ],
    "wof:name":"Five Star Heating and Cooling",
    "wof:placetype":"venue"
},
  "geometry": {"coordinates":[-87.940887,42.887078],"type":"Point"}
}