{
  "type": "Feature",
  "properties": {
    "iso:country":"US",
    "sg:address":"16601 W Cleveland Ave",
    "sg:city":"New Berlin",
    "sg:classifiers":[
        {
            "category":"Home & Garden",
            "subcategory":"Building Materials",
            "type":"Retail Goods"
        }
    ],
    "sg:phone":"+1 262 782 0500",
    "sg:postcode":"53151",
    "sg:province":"WI",
    "sg:tags":[
        "overhead",
        "product",
        "door",
        "improvement"
    ],
    "sg:website":"www.joewilde.com",
    "wof:name":"Joe Wilde Company Inc",
    "wof:placetype":"venue"
},
  "geometry": {"coordinates":[-88.12101,42.995228],"type":"Point"}
}