{
  "type": "Feature",
  "properties": {
    "iso:country":"US",
    "sg:address":"204 W Ravine Baye Rd",
    "sg:city":"Milwaukee",
    "sg:classifiers":[
        {
            "category":"Real Estate",
            "subcategory":"Architect",
            "type":"Services"
        }
    ],
    "sg:phone":"+1 414 351 6424",
    "sg:postcode":"53217",
    "sg:province":"WI",
    "sg:tags":[
        "architects'",
        "specification",
        "construction",
        "builders'",
        "architectural"
    ],
    "wof:name":"Sandy Volk Design Service",
    "wof:placetype":"venue"
},
  "geometry": {"coordinates":[-87.91002400000001,43.1917],"type":"Point"}
}