{
  "type": "Feature",
  "properties": {
    "iso:country":"US",
    "sg:address":"9200 W Wisconsin Ave",
    "sg:city":"Milwaukee",
    "sg:classifiers":[
        {
            "category":"Education",
            "subcategory":"Vocational School",
            "type":"Public Place"
        }
    ],
    "sg:phone":"+1 414 805 2071",
    "sg:postcode":"53226",
    "sg:province":"WI",
    "sg:tags":[
        "medical"
    ],
    "wof:name":"Nuclear Medicin Tech Program",
    "wof:placetype":"venue"
},
  "geometry": {"coordinates":[-88.03243399999999,43.038357],"type":"Point"}
}