{
  "type": "Feature",
  "properties": {
    "iso:country":"US",
    "sg:address":"860 Briar Ridge Dr E",
    "sg:city":"Brookfield",
    "sg:classifiers":[
        {
            "category":"Real Estate",
            "subcategory":"Real Estate Operator",
            "type":"Services"
        }
    ],
    "sg:phone":"+1 262 784 0068",
    "sg:postcode":"53045",
    "sg:province":"WI",
    "sg:tags":[
        "building",
        "nonresidential"
    ],
    "wof:name":"Agnos Enterprises",
    "wof:placetype":"venue"
},
  "geometry": {"coordinates":[-88.155388,43.039801],"type":"Point"}
}