{
  "type": "Feature",
  "properties": {
    "iso:country":"US",
    "sg:address":"110 E Hancock St",
    "sg:city":"New London",
    "sg:classifiers":[
        {
            "category":"Social Services",
            "type":"Services"
        }
    ],
    "sg:phone":"+1 920 982 7863",
    "sg:postcode":"54961",
    "sg:province":"WI",
    "sg:tags":[
        "counselor",
        "marriage",
        "family"
    ],
    "wof:name":"Fox Valley Pastoral Counseling",
    "wof:placetype":"venue"
},
  "geometry": {"coordinates":[-88.739613,44.387418],"type":"Point"}
}