{
  "type": "Feature",
  "properties": {
    "iso:country":"US",
    "sg:address":"421 E Jefferson St",
    "sg:city":"Waupun",
    "sg:classifiers":[
        {
            "category":"Real Estate",
            "subcategory":"Real Estate Operator",
            "type":"Services"
        }
    ],
    "sg:phone":"+1 920 743 5253",
    "sg:postcode":"53963",
    "sg:province":"WI",
    "sg:tags":[
        "property",
        "lessor"
    ],
    "wof:name":"Oscar Wagner",
    "wof:placetype":"venue"
},
  "geometry": {"coordinates":[-88.729541,43.632033],"type":"Point"}
}