{
  "type": "Feature",
  "properties": {
    "addr:full":"102 10th St Racine WI 53403",
    "addr:housenumber":"102",
    "addr:postcode":"53403",
    "addr:street":"10Th St",
    "iso:country":"US",
    "sg:address":"102 10th St",
    "sg:city":"Racine",
    "sg:classifiers":[
        {
            "category":"Organizations",
            "subcategory":"Community Association",
            "type":"Services"
        }
    ],
    "sg:phone":"+1 262 634 5748",
    "sg:postcode":"53403",
    "sg:province":"WI",
    "wof:name":"Preservation-Racine",
    "wof:placetype":"venue"
},
  "geometry": {"coordinates":[-87.782529,42.721573],"type":"Point"}
}