{
  "type": "Feature",
  "properties": {
    "iso:country":"US",
    "sg:address":"3920 S Adell Ave",
    "sg:city":"New Berlin",
    "sg:classifiers":[
        {
            "category":"Real Estate",
            "subcategory":"Real Estate Operator",
            "type":"Services"
        }
    ],
    "sg:phone":"+1 262 789 0308",
    "sg:postcode":"53151",
    "sg:province":"WI",
    "sg:tags":[
        "building",
        "apartment"
    ],
    "wof:name":"Maron I LLC",
    "wof:placetype":"venue"
},
  "geometry": {"coordinates":[-88.107615,42.972588],"type":"Point"}
}