{
  "type": "Feature",
  "properties": {
    "iso:country":"US",
    "sg:address":"5008 Green Bay Rd",
    "sg:city":"Kenosha",
    "sg:classifiers":[
        {
            "category":"Health Services",
            "subcategory":"Doctor",
            "type":"Services"
        }
    ],
    "sg:phone":"+1 262 657 1660",
    "sg:postcode":"53144",
    "sg:province":"WI",
    "sg:tags":[
        "physician",
        "surgeon"
    ],
    "wof:name":"Neurology Associates-Wi",
    "wof:placetype":"venue"
},
  "geometry": {"coordinates":[-87.881986,42.590516],"type":"Point"}
}