{
  "type": "Feature",
  "properties": {
    "iso:country":"US",
    "sg:address":"60 Water St",
    "sg:city":"Marinette",
    "sg:classifiers":[
        {
            "category":"Food & Beverages",
            "subcategory":"Groceries & Convenience Stores",
            "type":"Retail Goods"
        }
    ],
    "sg:phone":"+1 715 732 8991",
    "sg:postcode":"54143",
    "sg:province":"WI",
    "wof:name":"Waterfront Store",
    "wof:placetype":"venue"
},
  "geometry": {"coordinates":[-87.598243,45.091455],"type":"Point"}
}