{
  "type": "Feature",
  "properties": {
    "addr:full":"2225 W Sycamore Ave Oak Creek WI 53154",
    "addr:housenumber":"2225",
    "addr:postcode":"53154",
    "addr:street":"W Sycamore Ave",
    "iso:country":"US",
    "sg:address":"2225 W Sycamore Ave",
    "sg:city":"Oak Creek",
    "sg:classifiers":[
        {
            "category":"Education",
            "subcategory":"School",
            "type":"Public Place"
        }
    ],
    "sg:phone":"+1 414 761 3020",
    "sg:postcode":"53154",
    "sg:province":"WI",
    "sg:tags":[
        "elementary"
    ],
    "wof:name":"Oak Creek Franklin School Dst",
    "wof:placetype":"venue"
},
  "geometry": {"coordinates":[-87.944046,42.924157],"type":"Point"}
}