{
  "type": "Feature",
  "properties": {
    "iso:country":"US",
    "sg:address":"4076 N 100th St",
    "sg:city":"Milwaukee",
    "sg:classifiers":[
        {
            "category":"Insurance",
            "subcategory":"Insurance Agent",
            "type":"Services"
        }
    ],
    "sg:phone":"+1 414 466 2390",
    "sg:postcode":"53222",
    "sg:province":"WI",
    "wof:name":"Alfred A Erdmann Agent",
    "wof:placetype":"venue"
},
  "geometry": {"coordinates":[-88.037629,43.090919],"type":"Point"}
}