{
  "type": "Feature",
  "properties": {
    "iso:country":"US",
    "sg:address":"107 N Main St",
    "sg:city":"Oconomowoc",
    "sg:classifiers":[
        {
            "category":"Shopping",
            "subcategory":"Shoes",
            "type":"Retail Goods"
        }
    ],
    "sg:phone":"+1 262 567 6042",
    "sg:postcode":"53066",
    "sg:province":"WI",
    "wof:name":"Boelter's Shoes",
    "wof:placetype":"venue"
},
  "geometry": {"coordinates":[-88.499526,43.113851],"type":"Point"}
}