{
  "type": "Feature",
  "properties": {
    "iso:country":"US",
    "sg:address":"282 E Marquette St",
    "sg:city":"Berlin",
    "sg:classifiers":[
        {
            "category":"Retail",
            "subcategory":"Funeral Services",
            "type":"Services"
        }
    ],
    "sg:phone":"+1 920 361 2755",
    "sg:postcode":"54923",
    "sg:province":"WI",
    "sg:tags":[
        "director"
    ],
    "wof:name":"Barbola Funeral Chapel",
    "wof:placetype":"venue"
},
  "geometry": {"coordinates":[-88.939212,43.973778],"type":"Point"}
}