{
  "type": "Feature",
  "properties": {
    "iso:country":"US",
    "sg:address":"820 Madison St",
    "sg:city":"Little Chute",
    "sg:classifiers":[
        {
            "category":"Shopping",
            "subcategory":"Clothing, Apparel, & Fashions",
            "type":"Retail Goods"
        }
    ],
    "sg:phone":"+1 920 788 4544",
    "sg:postcode":"54140",
    "sg:province":"WI",
    "sg:tags":[
        "alteration"
    ],
    "sg:website":"www.stitchs.com",
    "wof:name":"Stitch's Alterations & Repairs",
    "wof:placetype":"venue"
},
  "geometry": {"coordinates":[-88.31826100000001,44.281783],"type":"Point"}
}