{
  "type": "Feature",
  "properties": {
    "addr:full":"201 US Hwy 141 Crivitz WI 54114",
    "addr:housenumber":"201",
    "addr:postcode":"54114",
    "addr:street":"Us Hwy 141",
    "iso:country":"US",
    "sg:address":"201 US Hwy 141",
    "sg:city":"Crivitz",
    "sg:classifiers":[
        {
            "category":"Shopping",
            "type":"Retail Goods"
        }
    ],
    "sg:phone":"+1 715 854 2482",
    "sg:postcode":"54114",
    "sg:province":"WI",
    "sg:tags":[
        "hearing",
        "equipment",
        "supply",
        "impaired"
    ],
    "wof:name":"Miracle-Ear",
    "wof:placetype":"venue"
},
  "geometry": {"coordinates":[-87.996787,45.227348],"type":"Point"}
}