{
  "type": "Feature",
  "properties": {
    "iso:country":"US",
    "sg:address":"1007 N 19th St",
    "sg:city":"Superior",
    "sg:classifiers":[
        {
            "category":"Professional",
            "subcategory":"Business Services",
            "type":"Services"
        }
    ],
    "sg:phone":"+1 715 395 9490",
    "sg:postcode":"54880",
    "sg:province":"WI",
    "wof:name":"Interior Barricade Systems LLC",
    "wof:placetype":"venue"
},
  "geometry": {"coordinates":[-92.093404,46.716145],"type":"Point"}
}