{
  "type": "Feature",
  "properties": {
    "iso:country":"US",
    "sg:address":"1105 Co Rd Z",
    "sg:city":"Arkdale",
    "sg:classifiers":[
        {
            "category":"Utilities",
            "type":"Services"
        }
    ],
    "sg:phone":"+1 608 564 7674",
    "sg:postcode":"54613",
    "sg:province":"WI",
    "sg:tags":[
        "sanitary"
    ],
    "wof:name":"Y&B Enterprise Inc",
    "wof:placetype":"venue"
},
  "geometry": {"coordinates":[-89.939285,44.096704],"type":"Point"}
}