{
  "type": "Feature",
  "properties": {
    "addr:full":"917 Thrush St Green Bay WI 54303",
    "addr:housenumber":"917",
    "addr:postcode":"54303",
    "addr:street":"Thrush St",
    "iso:country":"US",
    "sg:address":"917 Thrush St",
    "sg:city":"Green Bay",
    "sg:classifiers":[
        {
            "category":"Professional",
            "subcategory":"Advertising",
            "type":"Services"
        }
    ],
    "sg:phone":"+1 920 499 5575",
    "sg:postcode":"54303",
    "sg:province":"WI",
    "sg:tags":[
        "counselor"
    ],
    "wof:name":"Adds",
    "wof:placetype":"venue"
},
  "geometry": {"coordinates":[-88.043181,44.536074],"type":"Point"}
}