{
  "type": "Feature",
  "properties": {
    "iso:country":"US",
    "sg:address":"2478 N 73rd St",
    "sg:city":"Milwaukee",
    "sg:classifiers":[
        {
            "category":"Home & Garden",
            "subcategory":"Furniture",
            "type":"Retail Goods"
        }
    ],
    "sg:phone":"+1 414 672 3331",
    "sg:postcode":"53213",
    "sg:province":"WI",
    "wof:name":"Lincoln Furniture Inc",
    "wof:placetype":"venue"
},
  "geometry": {"coordinates":[-88.003923,43.062938],"type":"Point"}
}