{
  "type": "Feature",
  "properties": {
    "addr:full":"1799 Co Rd Pp De Pere WI 54115",
    "addr:housenumber":"1799",
    "addr:postcode":"54115",
    "addr:street":"Co Rd Pp",
    "iso:country":"US",
    "sg:address":"1799 Co Rd Pp",
    "sg:city":"De Pere",
    "sg:classifiers":[
        {
            "category":"Wholesale",
            "subcategory":"Scrap",
            "type":"Manufacturing & Wholesale Goods"
        }
    ],
    "sg:phone":"+1 920 983 3341",
    "sg:postcode":"54115",
    "sg:province":"WI",
    "sg:tags":[
        "waste"
    ],
    "sg:website":"www.onyxna.net",
    "wof:name":"Onyx Waste Svc Inc",
    "wof:placetype":"venue"
},
  "geometry": {"coordinates":[-88.056832,44.423026],"type":"Point"}
}