{
  "type": "Feature",
  "properties": {
    "iso:country":"US",
    "sg:address":"828 190th St",
    "sg:city":"Dresser",
    "sg:classifiers":[
        {
            "category":"Retail",
            "subcategory":"Repair Shop",
            "type":"Services"
        }
    ],
    "sg:phone":"+1 715 294 2085",
    "sg:postcode":"54009",
    "sg:province":"WI",
    "wof:name":"Wet Creation Taxidermy",
    "wof:placetype":"venue"
},
  "geometry": {"coordinates":[-92.550003,45.329139],"type":"Point"}
}