{
  "type": "Feature",
  "properties": {
    "addr:full":"5005 US Hwy 53 Eau Claire WI 54701",
    "addr:housenumber":"5005",
    "addr:postcode":"54701",
    "addr:street":"Us Hwy 53",
    "iso:country":"US",
    "sg:address":"5005 US Hwy 53",
    "sg:city":"Eau Claire",
    "sg:classifiers":[
        {
            "category":"Government",
            "subcategory":"Office",
            "type":"Public Place"
        }
    ],
    "sg:phone":"+1 715 839 3825",
    "sg:postcode":"54701",
    "sg:province":"WI",
    "sg:tags":[
        "state",
        "safety",
        "order"
    ],
    "wof:name":"Emergency Management",
    "wof:placetype":"venue"
},
  "geometry": {"coordinates":[-91.412666,44.759467],"type":"Point"}
}