{
  "type": "Feature",
  "properties": {
    "iso:country":"US",
    "sg:address":"209 Broadway St",
    "sg:city":"Berlin",
    "sg:classifiers":[
        {
            "category":"Bars & Pubs",
            "type":"Food & Drink"
        }
    ],
    "sg:phone":"+1 920 361 4347",
    "sg:postcode":"54923",
    "sg:province":"WI",
    "sg:tags":[
        "drinking"
    ],
    "wof:name":"Driftwood On Broadway Inc",
    "wof:placetype":"venue"
},
  "geometry": {"coordinates":[-88.95097699999999,43.968354],"type":"Point"}
}