{
  "type": "Feature",
  "properties": {
    "iso:country":"US",
    "sg:address":"930 Goddard Way",
    "sg:city":"Green Bay",
    "sg:classifiers":[
        {
            "category":"Manufacturing",
            "subcategory":"Food",
            "type":"Manufacturing & Wholesale Goods"
        }
    ],
    "sg:phone":"+1 920 468 1020",
    "sg:postcode":"54311",
    "sg:province":"WI",
    "sg:tags":[
        "mfg",
        "frozen",
        "ice",
        "operates",
        "dairy",
        "cream",
        "store",
        "pizza"
    ],
    "wof:name":"Hansen Dairy & Deli",
    "wof:placetype":"venue"
},
  "geometry": {"coordinates":[-87.930369,44.483654],"type":"Point"}
}