{
  "type": "Feature",
  "properties": {
    "addr:full":"5772 S 108th St Hales Corners WI 53130",
    "addr:housenumber":"5772",
    "addr:postcode":"53130",
    "addr:street":"S 108Th St",
    "iso:country":"US",
    "sg:address":"5772 S 108th St",
    "sg:city":"Hales Corners",
    "sg:classifiers":[
        {
            "category":"Shopping",
            "subcategory":"Gifts & Souvenirs",
            "type":"Retail Goods"
        }
    ],
    "sg:phone":"+1 414 427 9310",
    "sg:postcode":"53130",
    "sg:province":"WI",
    "sg:tags":[
        "shop",
        "cards"
    ],
    "wof:name":"Linda's Hallmark",
    "wof:placetype":"venue"
},
  "geometry": {"coordinates":[-88.04832399999999,42.939399],"type":"Point"}
}