{
  "type": "Feature",
  "properties": {
    "addr:full":"7828 State Hwy 42 Egg Harbor WI 54209",
    "addr:housenumber":"7828",
    "addr:postcode":"54209",
    "addr:street":"State Hwy 42",
    "iso:country":"US",
    "sg:address":"7828 State Hwy 42",
    "sg:city":"Egg Harbor",
    "sg:classifiers":[
        {
            "category":"Shopping",
            "subcategory":"Gifts & Souvenirs",
            "type":"Retail Goods"
        }
    ],
    "sg:phone":"+1 920 868 1134",
    "sg:postcode":"54209",
    "sg:province":"WI",
    "wof:name":"Antiques Etc Etc",
    "wof:placetype":"venue"
},
  "geometry": {"coordinates":[-87.28053800000001,45.051919],"type":"Point"}
}