{
  "type": "Feature",
  "properties": {
    "iso:country":"US",
    "sg:address":"2320 N 69th St",
    "sg:city":"Milwaukee",
    "sg:classifiers":[
        {
            "category":"Professional",
            "subcategory":"Lawyer & Legal Services",
            "type":"Services"
        }
    ],
    "sg:phone":"+1 414 476 6669",
    "sg:postcode":"53213",
    "sg:province":"WI",
    "wof:name":"Curt M Weber",
    "wof:placetype":"venue"
},
  "geometry": {"coordinates":[-87.998543,43.062188],"type":"Point"}
}