{
  "type": "Feature",
  "properties": {
    "iso:country":"US",
    "sg:address":"301 W Grand Ave",
    "sg:city":"Chippewa Falls",
    "sg:classifiers":[
        {
            "category":"Organizations",
            "subcategory":"Religious Organization",
            "type":"Services"
        }
    ],
    "sg:phone":"+1 715 723 8534",
    "sg:postcode":"54729",
    "sg:province":"WI",
    "sg:website":"www.grace2day.com",
    "wof:name":"Berean Bible Church",
    "wof:placetype":"venue"
},
  "geometry": {"coordinates":[-91.398624,44.933744],"type":"Point"}
}