{
  "type": "Feature",
  "properties": {
    "iso:country":"US",
    "sg:address":"210 Martin Luther King Jr Blvd",
    "sg:city":"Madison",
    "sg:classifiers":[
        {
            "category":"Banks & Credit Unions",
            "subcategory":"Bank",
            "type":"Services"
        }
    ],
    "sg:phone":"+1 608 266 4615",
    "sg:postcode":"53709",
    "sg:province":"WI",
    "sg:tags":[
        "federal",
        "agency"
    ],
    "wof:name":"Human Resource Department",
    "wof:placetype":"venue"
},
  "geometry": {"coordinates":[-89.381456,43.072555],"type":"Point"}
}