{
  "type": "Feature",
  "properties": {
    "addr:full":"250 N Sunnyslope Rd Brookfield WI 53005",
    "addr:housenumber":"250",
    "addr:postcode":"53005",
    "addr:street":"N Sunnyslope Rd",
    "iso:country":"US",
    "sg:address":"250 N Sunnyslope Rd",
    "sg:city":"Brookfield",
    "sg:classifiers":[
        {
            "category":"Manufacturing",
            "subcategory":"Food",
            "type":"Manufacturing & Wholesale Goods"
        }
    ],
    "sg:phone":"+1 414 259 1288",
    "sg:postcode":"53005",
    "sg:province":"WI",
    "sg:tags":[
        "brewer"
    ],
    "wof:name":"Miller Brewing Co",
    "wof:placetype":"venue"
},
  "geometry": {"coordinates":[-88.086804,43.033939],"type":"Point"}
}