{
  "type": "Feature",
  "properties": {
    "addr:full":"119 E 16th Rd Coleman WI 54112",
    "addr:housenumber":"119",
    "addr:postcode":"54112",
    "addr:street":"E 16Th Rd",
    "iso:country":"US",
    "sg:address":"119 E 16th Rd",
    "sg:city":"Coleman",
    "sg:classifiers":[
        {
            "category":"Government",
            "subcategory":"Fire Station",
            "type":"Public Place"
        }
    ],
    "sg:phone":"+1 920 897 4514",
    "sg:postcode":"54112",
    "sg:province":"WI",
    "sg:tags":[
        "department"
    ],
    "wof:name":"Coleman Rescue Squad Garage",
    "wof:placetype":"venue"
},
  "geometry": {"coordinates":[-88.02334999999999,45.079533],"type":"Point"}
}