{
  "type": "Feature",
  "properties": {
    "iso:country":"US",
    "sg:address":"233 Taylor St",
    "sg:city":"Little Chute",
    "sg:classifiers":[
        {
            "category":"Organizations",
            "subcategory":"Professional Association",
            "type":"Services"
        }
    ],
    "sg:phone":"+1 920 687 1642",
    "sg:postcode":"54140",
    "sg:province":"WI",
    "sg:tags":[
        "business"
    ],
    "wof:name":"Chamber Entertainment LLC",
    "wof:placetype":"venue"
},
  "geometry": {"coordinates":[-88.308248,44.277564],"type":"Point"}
}