{
  "type": "Feature",
  "properties": {
    "addr:full":"1610 E Newton Ave Milwaukee WI 53211",
    "addr:housenumber":"1610",
    "addr:postcode":"53211",
    "addr:street":"E Newton Ave",
    "iso:country":"US",
    "sg:address":"1610 E Newton Ave",
    "sg:city":"Milwaukee",
    "sg:classifiers":[
        {
            "category":"Professional",
            "type":"Services"
        }
    ],
    "sg:phone":"+1 414 964 7781",
    "sg:postcode":"53211",
    "sg:province":"WI",
    "sg:tags":[
        "establishment"
    ],
    "wof:name":"EDS",
    "wof:placetype":"venue"
},
  "geometry": {"coordinates":[-87.88770700000001,43.085119],"type":"Point"}
}