{
  "type": "Feature",
  "properties": {
    "addr:full":"660 W Sunset Dr Waukesha WI 53186",
    "addr:housenumber":"660",
    "addr:postcode":"53186",
    "addr:street":"W Sunset Dr",
    "iso:country":"US",
    "sg:address":"660 W Sunset Dr",
    "sg:city":"Waukesha",
    "sg:classifiers":[
        {
            "category":"Manufacturing",
            "subcategory":"Metals",
            "type":"Manufacturing & Wholesale Goods"
        }
    ],
    "sg:phone":"+1 262 542 4856",
    "sg:postcode":"53186",
    "sg:province":"WI",
    "sg:tags":[
        "apparel",
        "award"
    ],
    "wof:name":"Geiger Inc",
    "wof:placetype":"venue"
},
  "geometry": {"coordinates":[-88.24228599999999,42.988172],"type":"Point"}
}