{
  "type": "Feature",
  "properties": {
    "iso:country":"US",
    "sg:address":"407 N Main St",
    "sg:city":"Edgerton",
    "sg:classifiers":[
        {
            "category":"Professional",
            "subcategory":"Advertising",
            "type":"Services"
        }
    ],
    "sg:phone":"+1 608 884 9455",
    "sg:postcode":"53534",
    "sg:province":"WI",
    "wof:name":"Gardner Sales",
    "wof:placetype":"venue"
},
  "geometry": {"coordinates":[-89.06588600000001,42.836931],"type":"Point"}
}