{
  "type": "Feature",
  "properties": {
    "addr:full":"709 W Main St Lake Geneva WI 53147",
    "addr:housenumber":"709",
    "addr:postcode":"53147",
    "addr:street":"W Main St",
    "iso:country":"US",
    "sg:address":"709 W Main St",
    "sg:city":"Lake Geneva",
    "sg:classifiers":[
        {
            "category":"Utilities",
            "subcategory":"Mobile Phone",
            "type":"Services"
        }
    ],
    "sg:phone":"+1 262 348 0199",
    "sg:postcode":"53147",
    "sg:province":"WI",
    "sg:tags":[
        "telephone",
        "cellular"
    ],
    "wof:name":"National Cellular Safetalk",
    "wof:placetype":"venue"
},
  "geometry": {"coordinates":[-88.43523,42.591807],"type":"Point"}
}