{
  "type": "Feature",
  "properties": {
    "iso:country":"US",
    "sg:address":"2501 E Newton Ave",
    "sg:city":"Milwaukee",
    "sg:classifiers":[
        {
            "category":"Banks & Credit Unions",
            "subcategory":"Financial Services",
            "type":"Services"
        }
    ],
    "sg:phone":"+1 414 305 6918",
    "sg:postcode":"53211",
    "sg:province":"WI",
    "sg:tags":[
        "advisory",
        "management",
        "open",
        "investment"
    ],
    "wof:name":"Tower View Inv MGT & RES LLC",
    "wof:placetype":"venue"
},
  "geometry": {"coordinates":[-87.878708,43.084963],"type":"Point"}
}