{
  "type": "Feature",
  "properties": {
    "addr:full":"3400 S 13th St Milwaukee WI 53215",
    "addr:housenumber":"3400",
    "addr:postcode":"53215",
    "addr:street":"S 13Th St",
    "iso:country":"US",
    "sg:address":"3400 S 13th St",
    "sg:city":"Milwaukee",
    "sg:classifiers":[
        {
            "category":"Real Estate",
            "subcategory":"Real Estate Agent",
            "type":"Services"
        }
    ],
    "sg:phone":"+1 414 481 9044",
    "sg:postcode":"53215",
    "sg:province":"WI",
    "wof:name":"Whitten Realty",
    "wof:placetype":"venue"
},
  "geometry": {"coordinates":[-87.92894699999999,42.981055],"type":"Point"}
}