{
  "type": "Feature",
  "properties": {
    "iso:country":"US",
    "sg:address":"5071 Co Rd B",
    "sg:city":"Rio",
    "sg:classifiers":[
        {
            "category":"Building & Trades",
            "subcategory":"Construction",
            "type":"Services"
        }
    ],
    "sg:phone":"+1 920 992 5538",
    "sg:postcode":"53960",
    "sg:province":"WI",
    "sg:tags":[
        "house"
    ],
    "wof:name":"Q C Construction",
    "wof:placetype":"venue"
},
  "geometry": {"coordinates":[-89.146282,43.45768],"type":"Point"}
}