{
  "type": "Feature",
  "properties": {
    "iso:country":"US",
    "sg:address":"2160 Sleepy Hollow Dr",
    "sg:city":"Kaukauna",
    "sg:classifiers":[
        {
            "category":"Shopping",
            "subcategory":"Bicycles & Sporting Goods",
            "type":"Retail Goods"
        }
    ],
    "sg:phone":"+1 920 788 2562",
    "sg:postcode":"54130",
    "sg:province":"WI",
    "wof:name":"Go Video",
    "wof:placetype":"venue"
},
  "geometry": {"coordinates":[-88.284486,44.317531],"type":"Point"}
}