{
  "type": "Feature",
  "properties": {
    "iso:country":"US",
    "sg:address":"447 S 72nd St",
    "sg:city":"Milwaukee",
    "sg:classifiers":[
        {
            "category":"Banks & Credit Unions",
            "subcategory":"Investment Brokerage",
            "type":"Services"
        }
    ],
    "sg:phone":"+1 414 771 1851",
    "sg:postcode":"53214",
    "sg:province":"WI",
    "sg:tags":[
        "security"
    ],
    "wof:name":"First Investors Corporation",
    "wof:placetype":"venue"
},
  "geometry": {"coordinates":[-88.002481,43.026682],"type":"Point"}
}