{
  "type": "Feature",
  "properties": {
    "iso:country":"US",
    "sg:address":"14297 Broadway Rd",
    "sg:city":"Wisconsin Dells",
    "sg:classifiers":[
        {
            "category":"Farming",
            "subcategory":"Dairy Farm",
            "type":"Manufacturing & Wholesale Goods"
        }
    ],
    "sg:phone":"+1 608 254 2864",
    "sg:postcode":"53965",
    "sg:province":"WI",
    "wof:name":"Neldell Farms",
    "wof:placetype":"venue"
},
  "geometry": {"coordinates":[-89.707724,43.626407],"type":"Point"}
}