{
  "type": "Feature",
  "properties": {
    "iso:country":"US",
    "sg:address":"2779 S 34th St",
    "sg:city":"Milwaukee",
    "sg:classifiers":[
        {
            "category":"Manufacturing",
            "subcategory":"Tools & Machinery",
            "type":"Manufacturing & Wholesale Goods"
        }
    ],
    "sg:phone":"+1 414 645 0109",
    "sg:postcode":"53215",
    "sg:province":"WI",
    "sg:tags":[
        "photographic",
        "supply"
    ],
    "sg:website":"www.doranent.com",
    "wof:name":"Doran Enterprises Inc",
    "wof:placetype":"venue"
},
  "geometry": {"coordinates":[-87.956839,42.995321],"type":"Point"}
}