{
  "type": "Feature",
  "properties": {
    "iso:country":"US",
    "sg:address":"301 N Walnut St",
    "sg:city":"Mayville",
    "sg:classifiers":[
        {
            "category":"Retail",
            "subcategory":"Funeral Services",
            "type":"Services"
        }
    ],
    "sg:phone":"+1 920 387 4440",
    "sg:postcode":"53050",
    "sg:province":"WI",
    "sg:tags":[
        "director"
    ],
    "wof:name":"Koepsell Funeral Home Inc",
    "wof:placetype":"venue"
},
  "geometry": {"coordinates":[-88.548556,43.499494],"type":"Point"}
}