{
  "type": "Feature",
  "properties": {
    "iso:country":"US",
    "sg:address":"721 E Beacon Ave",
    "sg:city":"New London",
    "sg:classifiers":[
        {
            "category":"Retail",
            "subcategory":"Repair Shop",
            "type":"Services"
        }
    ],
    "sg:phone":"+1 920 982 2560",
    "sg:postcode":"54961",
    "sg:province":"WI",
    "sg:tags":[
        "equipment",
        "industrial",
        "machinery"
    ],
    "wof:name":"Ace Industrial Tech Inc",
    "wof:placetype":"venue"
},
  "geometry": {"coordinates":[-88.727201,44.388402],"type":"Point"}
}