{
  "type": "Feature",
  "properties": {
    "addr:full":"4701 State Hwy 26 Janesville WI 53546",
    "addr:housenumber":"4701",
    "addr:postcode":"53546",
    "addr:street":"State Hwy 26",
    "iso:country":"US",
    "sg:address":"4701 State Hwy 26",
    "sg:city":"Janesville",
    "sg:classifiers":[
        {
            "category":"Manufacturing",
            "subcategory":"Building Materials",
            "type":"Manufacturing & Wholesale Goods"
        }
    ],
    "sg:phone":"+1 608 868 9880",
    "sg:postcode":"53546",
    "sg:province":"WI",
    "sg:tags":[
        "cabinet"
    ],
    "wof:name":"Fassl's Fourmost Kitchens",
    "wof:placetype":"venue"
},
  "geometry": {"coordinates":[-88.976394,42.739542],"type":"Point"}
}