{
  "type": "Feature",
  "properties": {
    "iso:country":"US",
    "sg:address":"5720 State Hwy 60",
    "sg:city":"Hartford",
    "sg:classifiers":[
        {
            "category":"Food & Beverages",
            "subcategory":"Groceries & Convenience Stores",
            "type":"Retail Goods"
        }
    ],
    "sg:phone":"+1 262 673 6079",
    "sg:postcode":"53027",
    "sg:province":"WI",
    "wof:name":"Rapid Mart",
    "wof:placetype":"venue"
},
  "geometry": {"coordinates":[-88.320147,43.320766],"type":"Point"}
}