{
  "type": "Feature",
  "properties": {
    "iso:country":"US",
    "sg:address":"1632 Douglas Ave",
    "sg:city":"Racine",
    "sg:classifiers":[
        {
            "category":"Organizations",
            "subcategory":"Community Association",
            "type":"Services"
        }
    ],
    "sg:phone":"+1 262 619 0544",
    "sg:postcode":"53404",
    "sg:province":"WI",
    "sg:tags":[
        "club"
    ],
    "wof:name":"Shockers Club",
    "wof:placetype":"venue"
},
  "geometry": {"coordinates":[-87.794425,42.741667],"type":"Point"}
}