{
  "type": "Feature",
  "properties": {
    "iso:country":"US",
    "sg:address":"2641 20th Ave",
    "sg:city":"Monroe",
    "sg:classifiers":[
        {
            "category":"Professional",
            "subcategory":"Advertising",
            "type":"Services"
        }
    ],
    "sg:phone":"+1 608 325 4929",
    "sg:postcode":"53566",
    "sg:province":"WI",
    "sg:tags":[
        "agency"
    ],
    "wof:name":"Hayes Advertising & Marketing",
    "wof:placetype":"venue"
},
  "geometry": {"coordinates":[-89.634684,42.587649],"type":"Point"}
}