{
  "type": "Feature",
  "properties": {
    "iso:country":"US",
    "sg:address":"18630 W Cleveland Ave",
    "sg:city":"New Berlin",
    "sg:classifiers":[
        {
            "category":"Building & Trades",
            "subcategory":"Plumbing",
            "type":"Services"
        }
    ],
    "sg:phone":"+1 262 786 4969",
    "sg:postcode":"53146",
    "sg:province":"WI",
    "sg:tags":[
        "contractor"
    ],
    "wof:name":"Statewide Heating & Cooling",
    "wof:placetype":"venue"
},
  "geometry": {"coordinates":[-88.14742,42.990872],"type":"Point"}
}