{
  "type": "Feature",
  "properties": {
    "iso:country":"US",
    "sg:address":"208 S West St",
    "sg:city":"Waupun",
    "sg:classifiers":[
        {
            "category":"Manufacturing",
            "subcategory":"Tools & Machinery",
            "type":"Manufacturing & Wholesale Goods"
        }
    ],
    "sg:phone":"+1 920 324 3511",
    "sg:postcode":"53963",
    "sg:province":"WI",
    "sg:tags":[
        "electrical",
        "mfg"
    ],
    "wof:name":"Tyco International (us) Inc",
    "wof:placetype":"venue"
},
  "geometry": {"coordinates":[-88.75135400000001,43.630864],"type":"Point"}
}