{
  "type": "Feature",
  "properties": {
    "iso:country":"US",
    "sg:address":"301 Bridge St",
    "sg:city":"Green Bay",
    "sg:classifiers":[
        {
            "category":"Manufacturing",
            "subcategory":"Chemicals & Compounds",
            "type":"Manufacturing & Wholesale Goods"
        }
    ],
    "sg:phone":"+1 920 437 8658",
    "sg:postcode":"54303",
    "sg:province":"WI",
    "sg:tags":[
        "manufacture",
        "cleaning",
        "sanitation"
    ],
    "wof:name":"Pro Chemicals LLC",
    "wof:placetype":"venue"
},
  "geometry": {"coordinates":[-88.02363099999999,44.513535],"type":"Point"}
}