{
  "type": "Feature",
  "properties": {
    "iso:country":"US",
    "sg:address":"202 N East St",
    "sg:city":"Blue River",
    "sg:classifiers":[
        {
            "category":"Utilities",
            "subcategory":"Telephone",
            "type":"Services"
        }
    ],
    "sg:phone":"+1 608 537 2461",
    "sg:postcode":"53518",
    "sg:province":"WI",
    "sg:tags":[
        "company"
    ],
    "sg:website":"www.rgtc.coop",
    "wof:name":"Richland-Grant Telephone Co-Op",
    "wof:placetype":"venue"
},
  "geometry": {"coordinates":[-90.567176,43.187431],"type":"Point"}
}