{
  "type": "Feature",
  "properties": {
    "iso:country":"US",
    "sg:address":"2313 Sugar River Rd",
    "sg:city":"Verona",
    "sg:classifiers":[
        {
            "category":"Shopping",
            "subcategory":"Hobbies, Toys, & Games",
            "type":"Retail Goods"
        }
    ],
    "sg:phone":"+1 608 848 1617",
    "sg:postcode":"53593",
    "sg:province":"WI",
    "sg:tags":[
        "supply"
    ],
    "sg:website":"www.brainshake.com",
    "wof:name":"Games Networknet",
    "wof:placetype":"venue"
},
  "geometry": {"coordinates":[-89.577451,42.980092],"type":"Point"}
}