{
  "type": "Feature",
  "properties": {
    "addr:full":"210 N Grand Ave Waukesha WI 53186",
    "addr:housenumber":"210",
    "addr:postcode":"53186",
    "addr:street":"N Grand Ave",
    "iso:country":"US",
    "sg:address":"210 N Grand Ave",
    "sg:city":"Waukesha",
    "sg:classifiers":[
        {
            "category":"Social Services",
            "type":"Services"
        }
    ],
    "sg:phone":"+1 262 521 2501",
    "sg:postcode":"53186",
    "sg:province":"WI",
    "sg:tags":[
        "youth",
        "organization",
        "center"
    ],
    "wof:name":"One 2 One Waukesha Teen Ctr",
    "wof:placetype":"venue"
},
  "geometry": {"coordinates":[-88.231846,43.004811],"type":"Point"}
}