{
  "type": "Feature",
  "properties": {
    "iso:country":"US",
    "sg:address":"914 Moorland Rd",
    "sg:city":"Madison",
    "sg:classifiers":[
        {
            "category":"Personal",
            "subcategory":"Beauty Salon",
            "type":"Services"
        }
    ],
    "sg:phone":"+1 608 255 6854",
    "sg:postcode":"53713",
    "sg:province":"WI",
    "sg:tags":[
        "shop"
    ],
    "wof:name":"Images Salon",
    "wof:placetype":"venue"
},
  "geometry": {"coordinates":[-89.35892800000001,43.032814],"type":"Point"}
}