{
  "type": "Feature",
  "properties": {
    "iso:country":"US",
    "sg:address":"6081 W River Rd",
    "sg:city":"Hilbert",
    "sg:classifiers":[
        {
            "category":"Education",
            "subcategory":"School",
            "type":"Public Place"
        }
    ],
    "sg:phone":"+1 920 853 3134",
    "sg:postcode":"54129",
    "sg:province":"WI",
    "wof:name":"Trinity Lutheran School",
    "wof:placetype":"venue"
},
  "geometry": {"coordinates":[-88.093821,44.109585],"type":"Point"}
}