{
  "type": "Feature",
  "properties": {
    "addr:full":"1223 Partridge Ave Beloit WI 53511",
    "addr:housenumber":"1223",
    "addr:postcode":"53511",
    "addr:street":"Partridge Ave",
    "iso:country":"US",
    "sg:address":"1223 Partridge Ave",
    "sg:city":"Beloit",
    "sg:classifiers":[
        {
            "category":"Personal",
            "type":"Services"
        }
    ],
    "sg:phone":"+1 608 365 3606",
    "sg:postcode":"53511",
    "sg:province":"WI",
    "wof:name":"City Center LLC",
    "wof:placetype":"venue"
},
  "geometry": {"coordinates":[-89.017109,42.512277],"type":"Point"}
}