{
  "type": "Feature",
  "properties": {
    "addr:full":"3217 S 49th St Milwaukee WI 53219",
    "addr:housenumber":"3217",
    "addr:postcode":"53219",
    "addr:street":"S 49Th St",
    "iso:country":"US",
    "sg:address":"3217 S 49th St",
    "sg:city":"Milwaukee",
    "sg:classifiers":[
        {
            "category":"Freight",
            "type":"Transportation"
        }
    ],
    "sg:phone":"+1 414 545 6648",
    "sg:postcode":"53219",
    "sg:province":"WI",
    "sg:tags":[
        "local",
        "trucking"
    ],
    "wof:name":"Dean Gonzalez Trucking Inc",
    "wof:placetype":"venue"
},
  "geometry": {"coordinates":[-87.97551300000001,42.984841],"type":"Point"}
}