{
  "type": "Feature",
  "properties": {
    "addr:full":"1605 Post Rd Plover WI 54467",
    "addr:housenumber":"1605",
    "addr:postcode":"54467",
    "addr:street":"Post Rd",
    "iso:country":"US",
    "sg:address":"1605 Post Rd",
    "sg:city":"Plover",
    "sg:classifiers":[
        {
            "category":"Health Services",
            "subcategory":"Doctor",
            "type":"Services"
        }
    ],
    "sg:phone":"+1 715 341 7665",
    "sg:postcode":"54467",
    "sg:province":"WI",
    "sg:tags":[
        "dentist"
    ],
    "wof:name":"Plover Family Dental Care",
    "wof:placetype":"venue"
},
  "geometry": {"coordinates":[-89.547782,44.475453],"type":"Point"}
}