{
  "type": "Feature",
  "properties": {
    "addr:full":"207 S 4th Ave Sturgeon Bay WI 54235",
    "addr:housenumber":"207",
    "addr:postcode":"54235",
    "addr:street":"S 4Th Ave",
    "iso:country":"US",
    "sg:address":"207 S 4th Ave",
    "sg:city":"Sturgeon Bay",
    "sg:classifiers":[
        {
            "category":"Professional",
            "subcategory":"Lawyer & Legal Services",
            "type":"Services"
        }
    ],
    "sg:phone":"+1 920 743 6336",
    "sg:postcode":"54235",
    "sg:province":"WI",
    "sg:tags":[
        "attorney"
    ],
    "wof:name":"Reynolds Law Offices",
    "wof:placetype":"venue"
},
  "geometry": {"coordinates":[-87.373617,44.833074],"type":"Point"}
}