{
  "type": "Feature",
  "properties": {
    "iso:country":"US",
    "sg:address":"1375 W Main Ave",
    "sg:city":"De Pere",
    "sg:classifiers":[
        {
            "category":"Wholesale",
            "subcategory":"Computers",
            "type":"Manufacturing & Wholesale Goods"
        }
    ],
    "sg:phone":"+1 920 336 1387",
    "sg:postcode":"54115",
    "sg:province":"WI",
    "sg:tags":[
        "compute",
        "provides",
        "software"
    ],
    "sg:website":"www.computechresources.com",
    "wof:name":"Computech Resources Inc",
    "wof:placetype":"venue"
},
  "geometry": {"coordinates":[-88.104142,44.45804],"type":"Point"}
}