{
  "type": "Feature",
  "properties": {
    "iso:country":"US",
    "sg:address":"928 Lakeview Dr",
    "sg:city":"Green Bay",
    "sg:classifiers":[
        {
            "category":"Building & Trades",
            "subcategory":"Cleaning & Sanitation",
            "type":"Services"
        }
    ],
    "sg:phone":"+1 920 434 9775",
    "sg:postcode":"54313",
    "sg:province":"WI",
    "sg:tags":[
        "window",
        "maintenance"
    ],
    "wof:name":"Packerland Window Cleaning",
    "wof:placetype":"venue"
},
  "geometry": {"coordinates":[-88.064605,44.566924],"type":"Point"}
}