{
  "type": "Feature",
  "properties": {
    "iso:country":"US",
    "sg:address":"301 E Lakeview Ave",
    "sg:city":"Madison",
    "sg:classifiers":[
        {
            "category":"Professional",
            "type":"Services"
        }
    ],
    "sg:phone":"+1 608 223 0967",
    "sg:postcode":"53716",
    "sg:province":"WI",
    "sg:tags":[
        "establishment"
    ],
    "wof:name":"Thomas & Thomas",
    "wof:placetype":"venue"
},
  "geometry": {"coordinates":[-89.314787,43.077194],"type":"Point"}
}