{
  "type": "Feature",
  "properties": {
    "iso:country":"US",
    "sg:address":"2009 N Elco Rd",
    "sg:city":"Fall Creek",
    "sg:classifiers":[
        {
            "category":"Building & Trades",
            "subcategory":"Construction",
            "type":"Services"
        }
    ],
    "sg:phone":"+1 715 835 8431",
    "sg:postcode":"54742",
    "sg:province":"WI",
    "sg:tags":[
        "house"
    ],
    "wof:name":"Northwood Builders",
    "wof:placetype":"venue"
},
  "geometry": {"coordinates":[-91.372609,44.798915],"type":"Point"}
}