{
  "type": "Feature",
  "properties": {
    "iso:country":"US",
    "sg:address":"5329 Century Ave",
    "sg:city":"Middleton",
    "sg:classifiers":[
        {
            "category":"Shopping",
            "subcategory":"Catalog Store",
            "type":"Retail Goods"
        }
    ],
    "sg:phone":"+1 608 232 0130",
    "sg:postcode":"53562",
    "sg:province":"WI",
    "sg:tags":[
        "mail",
        "order"
    ],
    "wof:name":"End Connection",
    "wof:placetype":"venue"
},
  "geometry": {"coordinates":[-89.472545,43.111455],"type":"Point"}
}