{
  "type": "Feature",
  "properties": {
    "iso:country":"US",
    "sg:address":"14870 W Signet Ln",
    "sg:city":"New Berlin",
    "sg:classifiers":[
        {
            "category":"Manufacturing",
            "subcategory":"Metals",
            "type":"Manufacturing & Wholesale Goods"
        }
    ],
    "sg:phone":"+1 262 784 4442",
    "sg:postcode":"53151",
    "sg:province":"WI",
    "sg:tags":[
        "coating"
    ],
    "wof:name":"W K Products Inc",
    "wof:placetype":"venue"
},
  "geometry": {"coordinates":[-88.102059,42.970129],"type":"Point"}
}