{
  "type": "Feature",
  "properties": {
    "iso:country":"US",
    "sg:address":"819 Thomas Dr",
    "sg:city":"Sun Prairie",
    "sg:classifiers":[
        {
            "category":"Real Estate",
            "subcategory":"Real Estate Operator",
            "type":"Services"
        }
    ],
    "sg:phone":"+1 608 825 7759",
    "sg:postcode":"53590",
    "sg:province":"WI",
    "sg:tags":[
        "building",
        "apartment"
    ],
    "wof:name":"6607 31st Ave Kenosha WI LLC",
    "wof:placetype":"venue"
},
  "geometry": {"coordinates":[-89.19921100000001,43.185067],"type":"Point"}
}