{
  "type": "Feature",
  "properties": {
    "iso:country":"US",
    "sg:address":"137 N Main St",
    "sg:city":"Rice Lake",
    "sg:classifiers":[
        {
            "category":"Building & Trades",
            "subcategory":"Plumbing",
            "type":"Services"
        }
    ],
    "sg:phone":"+1 715 234 3310",
    "sg:postcode":"54868",
    "sg:province":"WI",
    "sg:tags":[
        "heating",
        "contractor"
    ],
    "wof:name":"Northern Heating & Mobile Hm",
    "wof:placetype":"venue"
},
  "geometry": {"coordinates":[-91.733391,45.503148],"type":"Point"}
}