{
  "type": "Feature",
  "properties": {
    "addr:full":"1639 State Hwy 164 Hubertus WI 53033",
    "addr:housenumber":"1639",
    "addr:postcode":"53033",
    "addr:street":"State Hwy 164",
    "iso:country":"US",
    "sg:address":"1639 State Hwy 164",
    "sg:city":"Hubertus",
    "sg:classifiers":[
        {
            "category":"Professional",
            "type":"Services"
        }
    ],
    "sg:phone":"+1 262 628 0969",
    "sg:postcode":"53033",
    "sg:province":"WI",
    "wof:name":"Jnj Elec",
    "wof:placetype":"venue"
},
  "geometry": {"coordinates":[-88.261788,43.250666],"type":"Point"}
}