{
  "type": "Feature",
  "properties": {
    "iso:country":"US",
    "sg:address":"115 S Main St",
    "sg:city":"Verona",
    "sg:classifiers":[
        {
            "category":"Insurance",
            "subcategory":"Insurance Agent",
            "type":"Services"
        }
    ],
    "sg:phone":"+1 608 848 8515",
    "sg:postcode":"53593",
    "sg:province":"WI",
    "wof:name":"Aid Assoc For Lutherans/Luther",
    "wof:placetype":"venue"
},
  "geometry": {"coordinates":[-89.533386,42.990236],"type":"Point"}
}