{
  "type": "Feature",
  "properties": {
    "iso:country":"US",
    "sg:address":"1640 Co Rd K N",
    "sg:city":"Custer",
    "sg:classifiers":[
        {
            "category":"Farming",
            "subcategory":"Dairy Farm",
            "type":"Manufacturing & Wholesale Goods"
        }
    ],
    "sg:phone":"+1 715 592 4285",
    "sg:postcode":"54423",
    "sg:province":"WI",
    "wof:name":"Jerry Studzinski",
    "wof:placetype":"venue"
},
  "geometry": {"coordinates":[-89.415662,44.568136],"type":"Point"}
}