{
  "type": "Feature",
  "properties": {
    "addr:full":"816 Washington St Manitowoc WI 54220",
    "addr:housenumber":"816",
    "addr:postcode":"54220",
    "addr:street":"Washington St",
    "iso:country":"US",
    "sg:address":"816 Washington St",
    "sg:city":"Manitowoc",
    "sg:classifiers":[
        {
            "category":"Professional",
            "subcategory":"Business Services",
            "type":"Services"
        }
    ],
    "sg:phone":"+1 920 683 3944",
    "sg:postcode":"54220",
    "sg:province":"WI",
    "sg:tags":[
        "interior",
        "decorating"
    ],
    "wof:name":"Shoreline Interiors",
    "wof:placetype":"venue"
},
  "geometry": {"coordinates":[-87.65901599999999,44.088944],"type":"Point"}
}