{
  "type": "Feature",
  "properties": {
    "iso:country":"US",
    "sg:address":"605 N 3rd Ave",
    "sg:city":"Sturgeon Bay",
    "sg:classifiers":[
        {
            "category":"Manufacturing",
            "subcategory":"Watercraft",
            "type":"Manufacturing & Wholesale Goods"
        }
    ],
    "sg:phone":"+1 920 743 5524",
    "sg:postcode":"54235",
    "sg:province":"WI",
    "sg:tags":[
        "builder",
        "ship",
        "repairer"
    ],
    "wof:name":"Bay Shipbuilding Co",
    "wof:placetype":"venue"
},
  "geometry": {"coordinates":[-87.381198,44.842931],"type":"Point"}
}