{
  "type": "Feature",
  "properties": {
    "iso:country":"US",
    "sg:address":"11818 560th Ave",
    "sg:city":"Prescott",
    "sg:classifiers":[
        {
            "category":"Real Estate",
            "subcategory":"Real Estate Operator",
            "type":"Services"
        }
    ],
    "sg:phone":"+1 715 262 5722",
    "sg:postcode":"54021",
    "sg:province":"WI",
    "sg:tags":[
        "property",
        "lessor"
    ],
    "wof:name":"Raymond Henry",
    "wof:placetype":"venue"
},
  "geometry": {"coordinates":[-92.729606,44.742995],"type":"Point"}
}