{
  "type": "Feature",
  "properties": {
    "addr:full":"7 W Main St Evansville WI 53536",
    "addr:housenumber":"7",
    "addr:postcode":"53536",
    "addr:street":"W Main St",
    "iso:country":"US",
    "sg:address":"7 W Main St",
    "sg:city":"Evansville",
    "sg:classifiers":[
        {
            "category":"Real Estate",
            "subcategory":"Real Estate Agent",
            "type":"Services"
        }
    ],
    "sg:phone":"+1 608 882 5216",
    "sg:postcode":"53536",
    "sg:province":"WI",
    "wof:name":"First United Realty Coldwell",
    "wof:placetype":"venue"
},
  "geometry": {"coordinates":[-89.301165,42.780236],"type":"Point"}
}