{
  "type": "Feature",
  "properties": {
    "iso:country":"US",
    "sg:address":"3913 W Prospect Ave",
    "sg:city":"Appleton",
    "sg:classifiers":[
        {
            "category":"Travel",
            "subcategory":"Hotels & Motels",
            "type":"Entertainment"
        }
    ],
    "sg:phone":"+1 920 730 8447",
    "sg:postcode":"54914",
    "sg:province":"WI",
    "wof:name":"Colonial Inn",
    "wof:placetype":"venue"
},
  "geometry": {"coordinates":[-88.46509,44.243726],"type":"Point"}
}