{
  "type": "Feature",
  "properties": {
    "iso:country":"US",
    "sg:address":"781 Potts Ave",
    "sg:city":"Green Bay",
    "sg:classifiers":[
        {
            "category":"Recreation",
            "type":"Entertainment"
        }
    ],
    "sg:phone":"+1 920 494 9931",
    "sg:postcode":"54304",
    "sg:province":"WI",
    "sg:tags":[
        "club",
        "membership"
    ],
    "wof:name":"Green Bay Curling Club",
    "wof:placetype":"venue"
},
  "geometry": {"coordinates":[-88.058941,44.497242],"type":"Point"}
}