{
  "type": "Feature",
  "properties": {
    "iso:country":"US",
    "sg:address":"1101 Superior Ave",
    "sg:city":"Tomah",
    "sg:classifiers":[
        {
            "category":"Shopping",
            "subcategory":"Bicycles & Sporting Goods",
            "type":"Retail Goods"
        }
    ],
    "sg:phone":"+1 608 372 4877",
    "sg:postcode":"54660",
    "sg:province":"WI",
    "wof:name":"City Center Sports",
    "wof:placetype":"venue"
},
  "geometry": {"coordinates":[-90.50477600000001,43.976811],"type":"Point"}
}