{
  "type": "Feature",
  "properties": {
    "iso:country":"US",
    "sg:address":"3077 State Hwy 60",
    "sg:city":"Columbus",
    "sg:classifiers":[
        {
            "category":"Real Estate",
            "subcategory":"Real Estate Operator",
            "type":"Services"
        }
    ],
    "sg:phone":"+1 920 623 2807",
    "sg:postcode":"53925",
    "sg:province":"WI",
    "sg:tags":[
        "property",
        "lessor"
    ],
    "wof:name":"Keip John",
    "wof:placetype":"venue"
},
  "geometry": {"coordinates":[-89.15467,43.340273],"type":"Point"}
}