{
  "type": "Feature",
  "properties": {
    "iso:country":"US",
    "sg:address":"441 Highland Vw",
    "sg:city":"Hudson",
    "sg:classifiers":[
        {
            "category":"Professional",
            "subcategory":"Management & Consulting",
            "type":"Services"
        }
    ],
    "sg:phone":"+1 715 549 6329",
    "sg:postcode":"54082",
    "sg:province":"WI",
    "sg:tags":[
        "business"
    ],
    "wof:name":"L K Fire & Safety Consulting",
    "wof:placetype":"venue"
},
  "geometry": {"coordinates":[-92.715499,45.051351],"type":"Point"}
}