{
  "type": "Feature",
  "properties": {
    "addr:full":"709 Howard St Green Bay WI 54303",
    "addr:housenumber":"709",
    "addr:postcode":"54303",
    "addr:street":"Howard St",
    "iso:country":"US",
    "sg:address":"709 Howard St",
    "sg:city":"Green Bay",
    "sg:classifiers":[
        {
            "category":"Education",
            "subcategory":"Special Training",
            "type":"Public Place"
        }
    ],
    "sg:phone":"+1 920 432 5816",
    "sg:postcode":"54303",
    "sg:province":"WI",
    "sg:tags":[
        "school",
        "language"
    ],
    "wof:name":"ESLNWTC Outreach",
    "wof:placetype":"venue"
},
  "geometry": {"coordinates":[-88.027362,44.516778],"type":"Point"}
}