{
  "type": "Feature",
  "properties": {
    "iso:country":"US",
    "sg:address":"2750 Agriculture Dr",
    "sg:city":"Madison",
    "sg:classifiers":[
        {
            "category":"Wholesale",
            "subcategory":"Electrical",
            "type":"Manufacturing & Wholesale Goods"
        }
    ],
    "sg:phone":"+1 608 224 0999",
    "sg:postcode":"53718",
    "sg:province":"WI",
    "sg:tags":[
        "supply"
    ],
    "wof:name":"Standard Electric Supply Co",
    "wof:placetype":"venue"
},
  "geometry": {"coordinates":[-89.29356199999999,43.058826],"type":"Point"}
}