{
  "type": "Feature",
  "properties": {
    "addr:full":"7562 Co Rd C Clintonville WI 54929",
    "addr:housenumber":"7562",
    "addr:postcode":"54929",
    "addr:street":"Co Rd",
    "iso:country":"US",
    "sg:address":"7562 Co Rd C",
    "sg:city":"Clintonville",
    "sg:classifiers":[
        {
            "category":"Real Estate",
            "subcategory":"Real Estate Operator",
            "type":"Services"
        }
    ],
    "sg:phone":"+1 715 823 3860",
    "sg:postcode":"54929",
    "sg:province":"WI",
    "sg:tags":[
        "property",
        "lessor"
    ],
    "wof:name":"Norman Hitzk",
    "wof:placetype":"venue"
},
  "geometry": {"coordinates":[-88.850354,44.619707],"type":"Point"}
}