{
  "type": "Feature",
  "properties": {
    "addr:full":"1434 Post Rd Plover WI 54467",
    "addr:housenumber":"1434",
    "addr:postcode":"54467",
    "addr:street":"Post Rd",
    "iso:country":"US",
    "sg:address":"1434 Post Rd",
    "sg:city":"Plover",
    "sg:classifiers":[
        {
            "category":"Manufacturing",
            "subcategory":"Food",
            "type":"Manufacturing & Wholesale Goods"
        }
    ],
    "sg:phone":"+1 715 341 3191",
    "sg:postcode":"54467",
    "sg:province":"WI",
    "sg:tags":[
        "product",
        "potato"
    ],
    "sg:website":"www.goldencountyfoods.com",
    "wof:name":"Golden County Foods Inc",
    "wof:placetype":"venue"
},
  "geometry": {"coordinates":[-89.54803099999999,44.476957],"type":"Point"}
}