{
  "type": "Feature",
  "properties": {
    "iso:country":"US",
    "sg:address":"2458 Cumberland Way",
    "sg:city":"Green Bay",
    "sg:classifiers":[
        {
            "category":"Banks & Credit Unions",
            "subcategory":"Financial Services",
            "type":"Services"
        }
    ],
    "sg:phone":"+1 920 468 3414",
    "sg:postcode":"54311",
    "sg:province":"WI",
    "sg:tags":[
        "investor"
    ],
    "wof:name":"G & A Investments LLC",
    "wof:placetype":"venue"
},
  "geometry": {"coordinates":[-87.97903100000001,44.456487],"type":"Point"}
}