{
  "type": "Feature",
  "properties": {
    "addr:full":"3530 Richland Hills Dr Wisconsin Rapids WI 54494",
    "addr:housenumber":"3530",
    "addr:postcode":"54494",
    "addr:street":"Richland Hills Dr",
    "iso:country":"US",
    "sg:address":"3530 Richland Hills Dr",
    "sg:city":"Wisconsin Rapids",
    "sg:classifiers":[
        {
            "category":"Building & Trades",
            "subcategory":"Construction",
            "type":"Services"
        }
    ],
    "sg:phone":"+1 715 423 3203",
    "sg:postcode":"54494",
    "sg:province":"WI",
    "sg:tags":[
        "contractor"
    ],
    "wof:name":"Board Foam Insulation",
    "wof:placetype":"venue"
},
  "geometry": {"coordinates":[-89.75771,44.363206],"type":"Point"}
}