{
  "type": "Feature",
  "properties": {
    "iso:country":"US",
    "sg:address":"204 Lac la Belle Dr",
    "sg:city":"Oconomowoc",
    "sg:classifiers":[
        {
            "category":"Building & Trades",
            "subcategory":"Construction",
            "type":"Services"
        }
    ],
    "sg:phone":"+1 262 567 2313",
    "sg:postcode":"53066",
    "sg:province":"WI",
    "sg:tags":[
        "residential",
        "contractor"
    ],
    "wof:name":"Griesemer Premier Builders Inc",
    "wof:placetype":"venue"
},
  "geometry": {"coordinates":[-88.509324,43.136451],"type":"Point"}
}