{
  "type": "Feature",
  "properties": {
    "iso:country":"US",
    "sg:address":"125 S Adams St",
    "sg:city":"Green Bay",
    "sg:classifiers":[
        {
            "category":"Government",
            "subcategory":"Police Station",
            "type":"Public Place"
        }
    ],
    "sg:phone":"+1 920 448 4260",
    "sg:postcode":"54301",
    "sg:province":"WI",
    "sg:tags":[
        "sheriff"
    ],
    "wof:name":"Sheriff's Dept-Huber Law Lt",
    "wof:placetype":"venue"
},
  "geometry": {"coordinates":[-88.015345,44.512845],"type":"Point"}
}