{
  "type": "Feature",
  "properties": {
    "iso:country":"US",
    "sg:address":"206 Schnitzler Dr",
    "sg:city":"Theresa",
    "sg:classifiers":[
        {
            "category":"Building & Trades",
            "subcategory":"Construction",
            "type":"Services"
        }
    ],
    "sg:phone":"+1 920 488 1101",
    "sg:postcode":"53091",
    "sg:province":"WI",
    "sg:tags":[
        "house"
    ],
    "wof:name":"Emco Of Wisconsin Inc",
    "wof:placetype":"venue"
},
  "geometry": {"coordinates":[-88.457623,43.512539],"type":"Point"}
}