{
  "type": "Feature",
  "properties": {
    "addr:full":"4475 N 124th St Brookfield WI 53005",
    "addr:housenumber":"4475",
    "addr:postcode":"53005",
    "addr:street":"N 124Th St",
    "iso:country":"US",
    "sg:address":"4475 N 124th St",
    "sg:city":"Brookfield",
    "sg:classifiers":[
        {
            "category":"Home & Garden",
            "subcategory":"Building Materials",
            "type":"Retail Goods"
        }
    ],
    "sg:phone":"+1 262 790 4916",
    "sg:postcode":"53005",
    "sg:province":"WI",
    "sg:tags":[
        "windows"
    ],
    "wof:name":"Us Aluminum",
    "wof:placetype":"venue"
},
  "geometry": {"coordinates":[-88.066237,43.096752],"type":"Point"}
}