{
  "type": "Feature",
  "properties": {
    "addr:full":"13022 Wilmot Rd Kenosha WI 53142",
    "addr:housenumber":"13022",
    "addr:postcode":"53142",
    "addr:street":"Wilmot Rd",
    "iso:country":"US",
    "sg:address":"13022 Wilmot Rd",
    "sg:city":"Kenosha",
    "sg:classifiers":[
        {
            "category":"Organizations",
            "subcategory":"Religious Organization",
            "type":"Services"
        }
    ],
    "sg:phone":"+1 262 857 4743",
    "sg:postcode":"53142",
    "sg:province":"WI",
    "sg:tags":[
        "church"
    ],
    "sg:website":"www.kenoshafcc.com",
    "wof:name":"First Christian Church",
    "wof:placetype":"venue"
},
  "geometry": {"coordinates":[-87.96393999999999,42.540864],"type":"Point"}
}