{
  "type": "Feature",
  "properties": {
    "addr:full":"3432 Sunset Dr Madison WI 53705",
    "addr:housenumber":"3432",
    "addr:postcode":"53705",
    "addr:street":"Sunset Dr",
    "iso:country":"US",
    "sg:address":"3432 Sunset Dr",
    "sg:city":"Madison",
    "sg:classifiers":[
        {
            "category":"Professional",
            "subcategory":"Management & Consulting",
            "type":"Services"
        }
    ],
    "sg:phone":"+1 608 233 8519",
    "sg:postcode":"53705",
    "sg:province":"WI",
    "wof:name":"Plantes Co",
    "wof:placetype":"venue"
},
  "geometry": {"coordinates":[-89.45058,43.081325],"type":"Point"}
}