{
  "type": "Feature",
  "properties": {
    "addr:full":"5266 Williamsburg Way Fitchburg WI 53719",
    "addr:housenumber":"5266",
    "addr:postcode":"53719",
    "addr:street":"Williamsburg Way",
    "iso:country":"US",
    "sg:address":"5266 Williamsburg Way",
    "sg:city":"Fitchburg",
    "sg:classifiers":[
        {
            "category":"Restaurant",
            "type":"Food & Drink"
        }
    ],
    "sg:menulink":"http://www.allmenus.com/wi/fitchburg/261417-picassos-pizza/menu/",
    "sg:phone":"+1 608 271 8440",
    "sg:postcode":"53719",
    "sg:province":"WI",
    "wof:name":"Picasso's Pizza",
    "wof:placetype":"venue"
},
  "geometry": {"coordinates":[-89.46973199999999,43.024333],"type":"Point"}
}