{
  "type": "Feature",
  "properties": {
    "iso:country":"US",
    "sg:address":"2334 State Hwy 78",
    "sg:city":"Mount Horeb",
    "sg:classifiers":[
        {
            "category":"Farming",
            "subcategory":"Dairy Farm",
            "type":"Manufacturing & Wholesale Goods"
        }
    ],
    "sg:phone":"+1 608 437 3967",
    "sg:postcode":"53572",
    "sg:province":"WI",
    "sg:tags":[
        "crop",
        "general"
    ],
    "wof:name":"Dennis Dreger Farm",
    "wof:placetype":"venue"
},
  "geometry": {"coordinates":[-89.760171,42.987109],"type":"Point"}
}