{
  "type": "Feature",
  "properties": {
    "iso:country":"US",
    "sg:address":"8070 N 76th St",
    "sg:city":"Milwaukee",
    "sg:classifiers":[
        {
            "category":"Shopping",
            "subcategory":"Used Merchandise",
            "type":"Retail Goods"
        },
        {
            "category":"Professional",
            "subcategory":"Computer Services",
            "type":"Services"
        },
        {
            "category":"Utilities",
            "subcategory":"Recycling",
            "type":"Services"
        },
        {
            "category":"Wholesale",
            "subcategory":"Computers",
            "type":"Manufacturing & Wholesale Goods"
        }
    ],
    "sg:phone":"+1 414 362 0560",
    "sg:postcode":"53223",
    "sg:province":"WI",
    "sg:tags":[
        "repair",
        "technical",
        "assistance",
        "equipment",
        "computer-wholesale",
        "equipment-service",
        "electronics",
        "support",
        "manufacturer"
    ],
    "sg:website":"http://computergeeksmilwaukee.com",
    "wof:name":"Computer Geeks",
    "wof:placetype":"venue"
},
  "geometry": {"coordinates":[-88.004531,43.164638],"type":"Point"}
}