{
  "type": "Feature",
  "properties": {
    "iso:country":"US",
    "sg:address":"18410 South St",
    "sg:city":"Whitehall",
    "sg:classifiers":[
        {
            "category":"Real Estate",
            "subcategory":"Real Estate Operator",
            "type":"Services"
        }
    ],
    "sg:phone":"+1 715 538 4165",
    "sg:postcode":"54773",
    "sg:province":"WI",
    "sg:tags":[
        "apartment"
    ],
    "wof:name":"Creekside Apartments",
    "wof:placetype":"venue"
},
  "geometry": {"coordinates":[-91.315736,44.362939],"type":"Point"}
}