{
  "type": "Feature",
  "properties": {
    "addr:full":"6881 S 10th St Oak Creek WI 53154",
    "addr:housenumber":"6881",
    "addr:postcode":"53154",
    "addr:street":"S 10Th St",
    "iso:country":"US",
    "sg:address":"6881 S 10th St",
    "sg:city":"Oak Creek",
    "sg:classifiers":[
        {
            "category":"Manufacturing",
            "subcategory":"Tools & Machinery",
            "type":"Manufacturing & Wholesale Goods"
        },
        {
            "category":"Wholesale",
            "subcategory":"Auto Parts",
            "type":"Manufacturing & Wholesale Goods"
        }
    ],
    "sg:phone":"+1 414 764 4211",
    "sg:postcode":"53154",
    "sg:province":"WI",
    "sg:tags":[
        "control",
        "mfg",
        "equipment",
        "truck",
        "motor",
        "vehicle"
    ],
    "wof:name":"Neo Brake Systems Inc",
    "wof:placetype":"venue"
},
  "geometry": {"coordinates":[-87.9267,42.92024],"type":"Point"}
}