{
  "type": "Feature",
  "properties": {
    "iso:country":"US",
    "sg:address":"20133 Co Hwy Q",
    "sg:city":"Bloomer",
    "sg:classifiers":[
        {
            "category":"Farming",
            "subcategory":"Livestock Farm",
            "type":"Manufacturing & Wholesale Goods"
        }
    ],
    "sg:phone":"+1 715 288 6583",
    "sg:postcode":"54724",
    "sg:province":"WI",
    "sg:tags":[
        "beef",
        "feedlot",
        "cattle"
    ],
    "wof:name":"Neil Rasmussen",
    "wof:placetype":"venue"
},
  "geometry": {"coordinates":[-91.562501,45.147411],"type":"Point"}
}