{
  "type": "Feature",
  "properties": {
    "iso:country":"US",
    "sg:address":"1717 N 47th St",
    "sg:city":"Milwaukee",
    "sg:classifiers":[
        {
            "category":"Professional",
            "subcategory":"Computer Services",
            "type":"Services"
        }
    ],
    "sg:phone":"+1 414 453 0933",
    "sg:postcode":"53208",
    "sg:province":"WI",
    "sg:tags":[
        "programing",
        "custom"
    ],
    "wof:name":"Kraus Energy Systems",
    "wof:placetype":"venue"
},
  "geometry": {"coordinates":[-87.97252,43.054498],"type":"Point"}
}