{
  "type": "Feature",
  "properties": {
    "addr:full":"330 Country Walk Ln Sister Bay WI 54234",
    "addr:housenumber":"330",
    "addr:postcode":"54234",
    "addr:street":"Country Walk Ln",
    "iso:country":"US",
    "sg:address":"330 Country Walk Ln",
    "sg:city":"Sister Bay",
    "sg:classifiers":[
        {
            "category":"Shopping",
            "subcategory":"Gifts & Souvenirs",
            "type":"Retail Goods"
        }
    ],
    "sg:phone":"+1 920 854 4665",
    "sg:postcode":"54234",
    "sg:province":"WI",
    "sg:tags":[
        "shop"
    ],
    "wof:name":"Busha's",
    "wof:placetype":"venue"
},
  "geometry": {"coordinates":[-87.12732800000001,45.183421],"type":"Point"}
}