{
  "type": "Feature",
  "properties": {
    "iso:country":"US",
    "sg:address":"1112 Alva St",
    "sg:city":"Menasha",
    "sg:classifiers":[
        {
            "category":"Building & Trades",
            "subcategory":"Construction",
            "type":"Services"
        }
    ],
    "sg:phone":"+1 920 205 8505",
    "sg:postcode":"54952",
    "sg:province":"WI",
    "sg:tags":[
        "painter"
    ],
    "wof:name":"M & J Renovating",
    "wof:placetype":"venue"
},
  "geometry": {"coordinates":[-88.421997,44.221981],"type":"Point"}
}