{
  "type": "Feature",
  "properties": {
    "addr:full":"705 W Lincoln Ave Milwaukee WI 53215",
    "addr:housenumber":"705",
    "addr:postcode":"53215",
    "addr:street":"W Lincoln Ave",
    "iso:country":"US",
    "sg:address":"705 W Lincoln Ave",
    "sg:city":"Milwaukee",
    "sg:classifiers":[
        {
            "category":"Museum",
            "type":"Entertainment"
        }
    ],
    "sg:phone":"+1 414 643 4758",
    "sg:postcode":"53215",
    "sg:province":"WI",
    "wof:name":"Urban Anthropology Inc",
    "wof:placetype":"venue"
},
  "geometry": {"coordinates":[-87.920063,43.002862],"type":"Point"}
}