{
  "type": "Feature",
  "properties": {
    "iso:country":"US",
    "sg:address":"400 Sunnyslope Dr",
    "sg:city":"Hartland",
    "sg:classifiers":[
        {
            "category":"Government",
            "subcategory":"Office",
            "type":"Public Place"
        }
    ],
    "sg:phone":"+1 262 367 5689",
    "sg:postcode":"53029",
    "sg:province":"WI",
    "wof:name":"Hartland Nutrition Site",
    "wof:placetype":"venue"
},
  "geometry": {"coordinates":[-88.337628,43.11125],"type":"Point"}
}