{
  "type": "Feature",
  "properties": {
    "iso:country":"US",
    "sg:address":"9130 W Loomis Rd",
    "sg:city":"Franklin",
    "sg:classifiers":[
        {
            "category":"Health Services",
            "subcategory":"Doctor",
            "type":"Services"
        }
    ],
    "sg:phone":"+1 414 427 1210",
    "sg:postcode":"53132",
    "sg:province":"WI",
    "sg:tags":[
        "dentist"
    ],
    "sg:website":"www.drbubon.com",
    "wof:name":"Michael Bubon & Assoc",
    "wof:placetype":"venue"
},
  "geometry": {"coordinates":[-88.020734,42.910564],"type":"Point"}
}