{
  "type": "Feature",
  "properties": {
    "iso:country":"US",
    "sg:address":"3525 W Oklahoma Ave",
    "sg:city":"Milwaukee",
    "sg:classifiers":[
        {
            "category":"Personal",
            "subcategory":"Beauty Salon",
            "type":"Services"
        }
    ],
    "sg:phone":"+1 414 671 1222",
    "sg:postcode":"53215",
    "sg:province":"WI",
    "sg:tags":[
        "shop"
    ],
    "wof:name":"Oak Park Beauty Salon",
    "wof:placetype":"venue"
},
  "geometry": {"coordinates":[-87.959022,42.988371],"type":"Point"}
}