{
  "type": "Feature",
  "properties": {
    "addr:full":"4756 Vine Rd Kaukauna WI 54130",
    "addr:housenumber":"4756",
    "addr:postcode":"54130",
    "addr:street":"Vine Rd",
    "iso:country":"US",
    "sg:address":"4756 Vine Rd",
    "sg:city":"Kaukauna",
    "sg:classifiers":[
        {
            "category":"Building & Trades",
            "subcategory":"Construction",
            "type":"Services"
        }
    ],
    "sg:phone":"+1 920 788 4150",
    "sg:postcode":"54130",
    "sg:province":"WI",
    "sg:tags":[
        "interior",
        "new",
        "hanging",
        "home",
        "contractor"
    ],
    "wof:name":"Larry Daul Painting LLC",
    "wof:placetype":"venue"
},
  "geometry": {"coordinates":[-88.31161299999999,44.402931],"type":"Point"}
}