{
  "type": "Feature",
  "properties": {
    "iso:country":"US",
    "sg:address":"4482 Cook Rd",
    "sg:city":"Oconto",
    "sg:classifiers":[
        {
            "category":"Professional",
            "type":"Services"
        }
    ],
    "sg:phone":"+1 920 834 5607",
    "sg:postcode":"54153",
    "sg:province":"WI",
    "wof:name":"Francis T Cook",
    "wof:placetype":"venue"
},
  "geometry": {"coordinates":[-88.00484400000001,44.878455],"type":"Point"}
}