{
  "type": "Feature",
  "properties": {
    "iso:country":"US",
    "sg:address":"8546 North Rd",
    "sg:city":"Arpin",
    "sg:classifiers":[
        {
            "category":"Farming",
            "subcategory":"Dairy Farm",
            "type":"Manufacturing & Wholesale Goods"
        }
    ],
    "sg:phone":"+1 715 652 3394",
    "sg:postcode":"54410",
    "sg:province":"WI",
    "wof:name":"Thomas Farm",
    "wof:placetype":"venue"
},
  "geometry": {"coordinates":[-90.004749,44.567188],"type":"Point"}
}