{
  "type": "Feature",
  "properties": {
    "addr:full":"100 S Mill St Merrill WI 54452",
    "addr:housenumber":"100",
    "addr:postcode":"54452",
    "addr:street":"S Mill St",
    "iso:country":"US",
    "sg:address":"100 S Mill St",
    "sg:city":"Merrill",
    "sg:classifiers":[
        {
            "category":"Shopping",
            "subcategory":"Pharmacy",
            "type":"Retail Goods"
        }
    ],
    "sg:phone":"+1 715 536 8391",
    "sg:postcode":"54452",
    "sg:province":"WI",
    "wof:name":"Snyders Drug Store 47",
    "wof:placetype":"venue"
},
  "geometry": {"coordinates":[-89.687505,45.180717],"type":"Point"}
}