{
  "type": "Feature",
  "properties": {
    "iso:country":"US",
    "sg:address":"518 Elm Ave",
    "sg:city":"South Milwaukee",
    "sg:classifiers":[
        {
            "category":"Building & Trades",
            "subcategory":"Construction",
            "type":"Services"
        }
    ],
    "sg:phone":"+1 414 762 9333",
    "sg:postcode":"53172",
    "sg:province":"WI",
    "sg:tags":[
        "carpentry",
        "contractor"
    ],
    "wof:name":"Thompson Knneth H Carptr Contr",
    "wof:placetype":"venue"
},
  "geometry": {"coordinates":[-87.85324900000001,42.923248],"type":"Point"}
}