{
  "type": "Feature",
  "properties": {
    "iso:country":"US",
    "sg:address":"551 Dru Dr",
    "sg:city":"Hudson",
    "sg:classifiers":[
        {
            "category":"Building & Trades",
            "subcategory":"Landscaping Services",
            "type":"Services"
        },
        {
            "category":"Building & Trades",
            "subcategory":"Construction",
            "type":"Services"
        }
    ],
    "sg:phone":"+1 715 386 6265",
    "sg:postcode":"54016",
    "sg:province":"WI",
    "sg:tags":[
        "clearing",
        "contractor",
        "land",
        "leveling",
        "grading"
    ],
    "wof:name":"Bluemels Tree & Landscape Inc",
    "wof:placetype":"venue"
},
  "geometry": {"coordinates":[-92.69008700000001,44.974134],"type":"Point"}
}