{
  "type": "Feature",
  "properties": {
    "addr:full":"560 4th St Prairie Du Sac WI 53578",
    "addr:housenumber":"560",
    "addr:postcode":"53578",
    "addr:street":"4Th St",
    "iso:country":"US",
    "sg:address":"560 4th St",
    "sg:city":"Prairie Du Sac",
    "sg:classifiers":[
        {
            "category":"Health Services",
            "subcategory":"Hospital",
            "type":"Services"
        }
    ],
    "sg:phone":"+1 608 643 3663",
    "sg:postcode":"53578",
    "sg:province":"WI",
    "sg:tags":[
        "mental"
    ],
    "wof:name":"Pathway Clinic",
    "wof:placetype":"venue"
},
  "geometry": {"coordinates":[-89.72384599999999,43.291097],"type":"Point"}
}