{
  "type": "Feature",
  "properties": {
    "iso:country":"US",
    "sg:address":"4502 Muncie Rd",
    "sg:city":"Hillsboro",
    "sg:classifiers":[
        {
            "category":"Farming",
            "subcategory":"Dairy Farm",
            "type":"Manufacturing & Wholesale Goods"
        }
    ],
    "sg:phone":"+1 608 528 4531",
    "sg:postcode":"54634",
    "sg:province":"WI",
    "wof:name":"Brown Earl R or Connie K",
    "wof:placetype":"venue"
},
  "geometry": {"coordinates":[-90.471538,43.568484],"type":"Point"}
}