{
  "type": "Feature",
  "properties": {
    "iso:country":"US",
    "sg:address":"501 E Division St",
    "sg:city":"Neillsville",
    "sg:classifiers":[
        {
            "category":"Restaurant",
            "type":"Food & Drink"
        }
    ],
    "sg:phone":"+1 715 743 7900",
    "sg:postcode":"54456",
    "sg:province":"WI",
    "sg:tags":[
        "eating"
    ],
    "wof:name":"A&W Restaurant",
    "wof:placetype":"venue"
},
  "geometry": {"coordinates":[-90.590443,44.552702],"type":"Point"}
}