{
  "type": "Feature",
  "properties": {
    "addr:full":"9740 S 58th St Franklin WI 53132",
    "addr:housenumber":"9740",
    "addr:postcode":"53132",
    "addr:street":"S 58Th St",
    "iso:country":"US",
    "sg:address":"9740 S 58th St",
    "sg:city":"Franklin",
    "sg:classifiers":[
        {
            "category":"Food & Beverages",
            "subcategory":"Meat & Fish",
            "type":"Retail Goods"
        }
    ],
    "sg:phone":"+1 414 421 9234",
    "sg:postcode":"53132",
    "sg:province":"WI",
    "sg:tags":[
        "frozen"
    ],
    "wof:name":"Schwan's Ice Cream & Fine Food",
    "wof:placetype":"venue"
},
  "geometry": {"coordinates":[-87.98842399999999,42.870598],"type":"Point"}
}