{
  "type": "Feature",
  "properties": {
    "iso:country":"US",
    "sg:address":"2224 E Main St",
    "sg:city":"Omro",
    "sg:classifiers":[
        {
            "category":"Autos & Motor Vehicles",
            "subcategory":"Automobile Sales",
            "type":"Retail Goods"
        }
    ],
    "sg:phone":"+1 920 685 6099",
    "sg:postcode":"54963",
    "sg:province":"WI",
    "sg:tags":[
        "used"
    ],
    "wof:name":"Park Place Auto Sales",
    "wof:placetype":"venue"
},
  "geometry": {"coordinates":[-88.715602,44.040417],"type":"Point"}
}