{
  "type": "Feature",
  "properties": {
    "iso:country":"US",
    "sg:address":"700 S Main St",
    "sg:city":"Fountain City",
    "sg:classifiers":[
        {
            "category":"Recreation",
            "type":"Entertainment"
        }
    ],
    "sg:phone":"+1 608 687 4103",
    "sg:postcode":"54629",
    "sg:province":"WI",
    "wof:name":"Fountain City Pool",
    "wof:placetype":"venue"
},
  "geometry": {"coordinates":[-91.680256,44.09948],"type":"Point"}
}