{
  "type": "Feature",
  "properties": {
    "iso:country":"US",
    "sg:address":"3228 Robin Rd",
    "sg:city":"Lake Geneva",
    "sg:classifiers":[
        {
            "category":"Building & Trades",
            "subcategory":"Construction",
            "type":"Services"
        }
    ],
    "sg:phone":"+1 262 249 8667",
    "sg:postcode":"53147",
    "sg:province":"WI",
    "sg:tags":[
        "contractor"
    ],
    "wof:name":"Volbrecht Masonry",
    "wof:placetype":"venue"
},
  "geometry": {"coordinates":[-88.498348,42.609466],"type":"Point"}
}