{
  "type": "Feature",
  "properties": {
    "addr:full":"1213 Menomonie St Eau Claire WI 54703",
    "addr:housenumber":"1213",
    "addr:postcode":"54703",
    "addr:street":"Menomonie St",
    "iso:country":"US",
    "sg:address":"1213 Menomonie St",
    "sg:city":"Eau Claire",
    "sg:classifiers":[
        {
            "category":"Manufacturing",
            "subcategory":"Printing",
            "type":"Manufacturing & Wholesale Goods"
        }
    ],
    "sg:phone":"+1 715 836 0049",
    "sg:postcode":"54703",
    "sg:province":"WI",
    "sg:tags":[
        "lithographic",
        "c",
        "commercial",
        "typesetting"
    ],
    "wof:name":"Quality Quick Print",
    "wof:placetype":"venue"
},
  "geometry": {"coordinates":[-91.52881499999999,44.799915],"type":"Point"}
}