{
  "type": "Feature",
  "properties": {
    "iso:country":"US",
    "sg:address":"244 W Pioneer Rd",
    "sg:city":"Fond Du Lac",
    "sg:classifiers":[
        {
            "category":"Professional",
            "subcategory":"Engineering",
            "type":"Services"
        }
    ],
    "sg:phone":"+1 920 923 1034",
    "sg:postcode":"54935",
    "sg:province":"WI",
    "sg:tags":[
        "work",
        "design",
        "telecommunication"
    ],
    "sg:website":"www.techplanners.com",
    "wof:name":"Technology Planners",
    "wof:placetype":"venue"
},
  "geometry": {"coordinates":[-88.457112,43.754169],"type":"Point"}
}