{
  "type": "Feature",
  "properties": {
    "iso:country":"US",
    "sg:address":"4054 N Broadway Rd",
    "sg:city":"Bonduel",
    "sg:classifiers":[
        {
            "category":"Farming",
            "subcategory":"Dairy Farm",
            "type":"Manufacturing & Wholesale Goods"
        }
    ],
    "sg:phone":"+1 715 758 2612",
    "sg:postcode":"54107",
    "sg:province":"WI",
    "wof:name":"Robert & Terry Rehn",
    "wof:placetype":"venue"
},
  "geometry": {"coordinates":[-88.384053,44.730679],"type":"Point"}
}