{
  "type": "Feature",
  "properties": {
    "iso:country":"US",
    "sg:address":"2143 Cater Rd",
    "sg:city":"Eau Claire",
    "sg:classifiers":[
        {
            "category":"Professional",
            "subcategory":"Management & Consulting",
            "type":"Services"
        }
    ],
    "sg:phone":"+1 715 834 8500",
    "sg:postcode":"54701",
    "sg:province":"WI",
    "wof:name":"Consumer Credit Counseling Svc",
    "wof:placetype":"venue"
},
  "geometry": {"coordinates":[-91.49884900000001,44.748671],"type":"Point"}
}