{
  "type": "Feature",
  "properties": {
    "iso:country":"US",
    "sg:address":"10652 Lakeshore Rd",
    "sg:city":"Clintonville",
    "sg:classifiers":[
        {
            "category":"Real Estate",
            "subcategory":"Real Estate Operator",
            "type":"Services"
        }
    ],
    "sg:phone":"+1 715 823 9021",
    "sg:postcode":"54929",
    "sg:province":"WI",
    "sg:tags":[
        "building",
        "operation",
        "apartment"
    ],
    "wof:name":"Lake Shore Motel & Apartments",
    "wof:placetype":"venue"
},
  "geometry": {"coordinates":[-88.773169,44.62188],"type":"Point"}
}