{
  "type": "Feature",
  "properties": {
    "iso:country":"US",
    "sg:address":"9075 State Hwy 85",
    "sg:city":"Mondovi",
    "sg:classifiers":[
        {
            "category":"Wholesale",
            "subcategory":"Farm Supplies",
            "type":"Manufacturing & Wholesale Goods"
        }
    ],
    "sg:phone":"+1 715 875 4215",
    "sg:postcode":"54755",
    "sg:province":"WI",
    "wof:name":"Countryside Cooperative",
    "wof:placetype":"venue"
},
  "geometry": {"coordinates":[-91.708521,44.713708],"type":"Point"}
}