{
  "type": "Feature",
  "properties": {
    "iso:country":"US",
    "sg:address":"513 Isle Royal Dr",
    "sg:city":"Madison",
    "sg:classifiers":[
        {
            "category":"Professional",
            "subcategory":"Research",
            "type":"Services"
        }
    ],
    "sg:phone":"+1 608 833 1791",
    "sg:postcode":"53705",
    "sg:province":"WI",
    "sg:tags":[
        "development",
        "area"
    ],
    "wof:name":"Ants",
    "wof:placetype":"venue"
},
  "geometry": {"coordinates":[-89.497265,43.074104],"type":"Point"}
}