{
  "type": "Feature",
  "properties": {
    "addr:full":"2270 US Hwy 10 Granton WI 54436",
    "addr:housenumber":"2270",
    "addr:postcode":"54436",
    "addr:street":"Us Hwy 10",
    "iso:country":"US",
    "sg:address":"2270 US Hwy 10",
    "sg:city":"Granton",
    "sg:classifiers":[
        {
            "category":"Organizations",
            "subcategory":"Membership Organization",
            "type":"Services"
        }
    ],
    "sg:phone":"+1 715 238 7291",
    "sg:postcode":"54436",
    "sg:province":"WI",
    "wof:name":"American Pheasant Wtr Foul Soc",
    "wof:placetype":"venue"
},
  "geometry": {"coordinates":[-90.42484899999999,44.582135],"type":"Point"}
}