{
  "type": "Feature",
  "properties": {
    "iso:country":"US",
    "sg:address":"30 N 18th Ave",
    "sg:city":"Sturgeon Bay",
    "sg:classifiers":[
        {
            "category":"Health Services",
            "subcategory":"Nursing And Care Facility",
            "type":"Services"
        }
    ],
    "sg:phone":"+1 920 743 6440",
    "sg:postcode":"54235",
    "sg:province":"WI",
    "sg:tags":[
        "skilled"
    ],
    "wof:name":"Green Bay Office",
    "wof:placetype":"venue"
},
  "geometry": {"coordinates":[-87.351389,44.835989],"type":"Point"}
}