{
  "type": "Feature",
  "properties": {
    "iso:country":"US",
    "sg:address":"1717 E Kensington Blvd",
    "sg:city":"Milwaukee",
    "sg:classifiers":[
        {
            "category":"Professional",
            "type":"Services"
        }
    ],
    "sg:phone":"+1 414 906 1853",
    "sg:postcode":"53211",
    "sg:province":"WI",
    "wof:name":"Metropolitan",
    "wof:placetype":"venue"
},
  "geometry": {"coordinates":[-87.887563,43.098196],"type":"Point"}
}