{
  "type": "Feature",
  "properties": {
    "iso:country":"US",
    "sg:address":"2007 N 57th St",
    "sg:city":"Milwaukee",
    "sg:classifiers":[
        {
            "category":"Professional",
            "subcategory":"Management & Consulting",
            "type":"Services"
        }
    ],
    "sg:phone":"+1 414 453 9003",
    "sg:postcode":"53208",
    "sg:province":"WI",
    "sg:tags":[
        "consultant",
        "resource",
        "human"
    ],
    "wof:name":"Be The Change Inc",
    "wof:placetype":"venue"
},
  "geometry": {"coordinates":[-87.984257,43.056215],"type":"Point"}
}