{
  "type": "Feature",
  "properties": {
    "iso:country":"US",
    "sg:address":"4370 Tenpas Rd",
    "sg:city":"Vesper",
    "sg:classifiers":[
        {
            "category":"Farming",
            "subcategory":"Farm",
            "type":"Manufacturing & Wholesale Goods"
        }
    ],
    "sg:phone":"+1 715 569 3956",
    "sg:postcode":"54489",
    "sg:province":"WI",
    "sg:tags":[
        "crop",
        "general"
    ],
    "wof:name":"Roger Greeneway",
    "wof:placetype":"venue"
},
  "geometry": {"coordinates":[-89.94231499999999,44.511843],"type":"Point"}
}