{
  "type": "Feature",
  "properties": {
    "iso:country":"US",
    "sg:address":"324 Water St",
    "sg:city":"Cambridge",
    "sg:classifiers":[
        {
            "category":"Retail",
            "subcategory":"Auto Repair",
            "type":"Services"
        }
    ],
    "sg:phone":"+1 608 423 4200",
    "sg:postcode":"53523",
    "sg:province":"WI",
    "sg:tags":[
        "body"
    ],
    "wof:name":"Rockdale Body Shop",
    "wof:placetype":"venue"
},
  "geometry": {"coordinates":[-89.030567,42.973293],"type":"Point"}
}