{
  "type": "Feature",
  "properties": {
    "iso:country":"US",
    "sg:address":"701 Lake Shore Dr E",
    "sg:city":"Ashland",
    "sg:classifiers":[
        {
            "category":"Organizations",
            "subcategory":"Labor Organization",
            "type":"Services"
        }
    ],
    "sg:phone":"+1 715 682 4196",
    "sg:postcode":"54806",
    "sg:province":"WI",
    "wof:name":"United Transportation Union",
    "wof:placetype":"venue"
},
  "geometry": {"coordinates":[-90.87566,46.59605],"type":"Point"}
}