{
  "type": "Feature",
  "properties": {
    "addr:full":"6605 Stenulson Rd Black River Falls WI 54615",
    "addr:housenumber":"6605",
    "addr:postcode":"54615",
    "addr:street":"Stenulson Rd",
    "iso:country":"US",
    "sg:address":"6605 Stenulson Rd",
    "sg:city":"Black River Falls",
    "sg:classifiers":[
        {
            "category":"Shopping",
            "subcategory":"Hobbies, Toys, & Games",
            "type":"Retail Goods"
        }
    ],
    "sg:phone":"+1 715 284 5644",
    "sg:postcode":"54615",
    "sg:province":"WI",
    "wof:name":"Jessys Originals",
    "wof:placetype":"venue"
},
  "geometry": {"coordinates":[-90.925361,44.313276],"type":"Point"}
}