{
  "type": "Feature",
  "properties": {
    "addr:full":"465 Henry Mall Madison WI 53706",
    "addr:housenumber":"465",
    "addr:postcode":"53706",
    "addr:street":"Henry Mall",
    "iso:country":"US",
    "sg:address":"465 Henry Mall",
    "sg:city":"Madison",
    "sg:classifiers":[
        {
            "category":"Health Services",
            "subcategory":"Medical Lab",
            "type":"Services"
        }
    ],
    "sg:phone":"+1 608 265 1100",
    "sg:postcode":"53706",
    "sg:province":"WI",
    "sg:tags":[
        "state",
        "public"
    ],
    "wof:name":"Profiency Testing",
    "wof:placetype":"venue"
},
  "geometry": {"coordinates":[-89.41006400000001,43.074475],"type":"Point"}
}