{
  "type": "Feature",
  "properties": {
    "iso:country":"US",
    "sg:address":"520 S Shawano St",
    "sg:city":"New London",
    "sg:classifiers":[
        {
            "category":"Professional",
            "subcategory":"Accounting & Tax Preparation",
            "type":"Services"
        }
    ],
    "sg:phone":"+1 920 982 3937",
    "sg:postcode":"54961",
    "sg:province":"WI",
    "sg:tags":[
        "return",
        "filing"
    ],
    "wof:name":"New London Tax Svc",
    "wof:placetype":"venue"
},
  "geometry": {"coordinates":[-88.745312,44.388973],"type":"Point"}
}