{
  "type": "Feature",
  "properties": {
    "iso:country":"US",
    "sg:address":"2822 Michigan Blvd",
    "sg:city":"Racine",
    "sg:classifiers":[
        {
            "category":"Shopping",
            "subcategory":"Pharmacy",
            "type":"Retail Goods"
        }
    ],
    "sg:phone":"+1 262 639 7733",
    "sg:postcode":"53402",
    "sg:province":"WI",
    "sg:tags":[
        "aid",
        "first",
        "supply"
    ],
    "wof:name":"Respond First Aid Systems",
    "wof:placetype":"venue"
},
  "geometry": {"coordinates":[-87.780939,42.755371],"type":"Point"}
}