{
  "type": "Feature",
  "properties": {
    "addr:full":"133 E Main St Marshall WI 53529",
    "addr:housenumber":"133",
    "addr:postcode":"53529",
    "addr:street":"E Main St",
    "iso:country":"US",
    "sg:address":"133 E Main St",
    "sg:city":"Marshall",
    "sg:classifiers":[
        {
            "category":"Sports & Exercise",
            "subcategory":"Gym",
            "type":"Entertainment"
        }
    ],
    "sg:phone":"+1 608 655 3488",
    "sg:postcode":"53529",
    "sg:province":"WI",
    "sg:tags":[
        "fitness",
        "physical",
        "facility"
    ],
    "wof:name":"Fitness Plus",
    "wof:placetype":"venue"
},
  "geometry": {"coordinates":[-89.06397200000001,43.167367],"type":"Point"}
}