{
  "type": "Feature",
  "properties": {
    "iso:country":"US",
    "sg:address":"3120 E Norwich Ave",
    "sg:city":"Milwaukee",
    "sg:classifiers":[
        {
            "category":"Real Estate",
            "subcategory":"Real Estate Operator",
            "type":"Services"
        }
    ],
    "sg:phone":"+1 414 769 9240",
    "sg:postcode":"53235",
    "sg:province":"WI",
    "sg:tags":[
        "building",
        "apartment"
    ],
    "wof:name":"Thompson Meadows Apartments",
    "wof:placetype":"venue"
},
  "geometry": {"coordinates":[-87.872272,42.971909],"type":"Point"}
}