{
  "type": "Feature",
  "properties": {
    "iso:country":"US",
    "sg:address":"990 E Green Bay St",
    "sg:city":"Shawano",
    "sg:classifiers":[
        {
            "category":"Recreation",
            "type":"Entertainment"
        }
    ],
    "sg:phone":"+1 715 526 5419",
    "sg:postcode":"54166",
    "sg:province":"WI",
    "sg:tags":[
        "fairground"
    ],
    "wof:name":"Shawano County Fairgrounds 4-H",
    "wof:placetype":"venue"
},
  "geometry": {"coordinates":[-88.596719,44.782048],"type":"Point"}
}