{
  "type": "Feature",
  "properties": {
    "iso:country":"US",
    "sg:address":"2407 Cherokee Rd",
    "sg:city":"Janesville",
    "sg:classifiers":[
        {
            "category":"Banks & Credit Unions",
            "subcategory":"Financial Services",
            "type":"Services"
        }
    ],
    "sg:phone":"+1 608 755 5717",
    "sg:postcode":"53545",
    "sg:province":"WI",
    "sg:tags":[
        "investor"
    ],
    "wof:name":"3 Cs Investments LLC",
    "wof:placetype":"venue"
},
  "geometry": {"coordinates":[-88.992714,42.684365],"type":"Point"}
}