{
  "type": "Feature",
  "properties": {
    "iso:country":"US",
    "sg:address":"27339 Meadowlark Ct",
    "sg:city":"Waterford",
    "sg:classifiers":[
        {
            "category":"Building & Trades",
            "subcategory":"Construction",
            "type":"Services"
        }
    ],
    "sg:phone":"+1 262 895 2016",
    "sg:postcode":"53185",
    "sg:province":"WI",
    "sg:tags":[
        "house"
    ],
    "wof:name":"Borchardt Builders",
    "wof:placetype":"venue"
},
  "geometry": {"coordinates":[-88.174151,42.820457],"type":"Point"}
}