{
  "type": "Feature",
  "properties": {
    "addr:full":"8501 Co Rd D Forestville WI 54213",
    "addr:housenumber":"8501",
    "addr:postcode":"54213",
    "addr:street":"Co Rd D",
    "iso:country":"US",
    "sg:address":"8501 Co Rd D",
    "sg:city":"Forestville",
    "sg:classifiers":[
        {
            "category":"Utilities",
            "subcategory":"Telephone",
            "type":"Services"
        }
    ],
    "sg:phone":"+1 920 825 7372",
    "sg:postcode":"54213",
    "sg:province":"WI",
    "sg:tags":[
        "communications"
    ],
    "wof:name":"Mac Helper",
    "wof:placetype":"venue"
},
  "geometry": {"coordinates":[-87.549847,44.718964],"type":"Point"}
}