{
  "type": "Feature",
  "properties": {
    "iso:country":"US",
    "sg:address":"769 Leeward Ln",
    "sg:city":"Oregon",
    "sg:classifiers":[
        {
            "category":"Banks & Credit Unions",
            "subcategory":"Financial Services",
            "type":"Services"
        }
    ],
    "sg:phone":"+1 608 835 8123",
    "sg:postcode":"53575",
    "sg:province":"WI",
    "sg:tags":[
        "investor"
    ],
    "wof:name":"Deits Investments",
    "wof:placetype":"venue"
},
  "geometry": {"coordinates":[-89.391418,42.915184],"type":"Point"}
}