{
  "type": "Feature",
  "properties": {
    "iso:country":"US",
    "sg:address":"6490 US Hwy 63",
    "sg:city":"Beldenville",
    "sg:classifiers":[
        {
            "category":"Building & Trades",
            "subcategory":"Plumbing",
            "type":"Services"
        }
    ],
    "sg:phone":"+1 715 273 6360",
    "sg:postcode":"54003",
    "sg:province":"WI",
    "sg:tags":[
        "tank",
        "septic"
    ],
    "wof:name":"St Croix Septic Systems",
    "wof:placetype":"venue"
},
  "geometry": {"coordinates":[-92.416213,44.765808],"type":"Point"}
}