{
  "type": "Feature",
  "properties": {
    "addr:full":"4078 Castle Rd Medford WI 54451",
    "addr:housenumber":"4078",
    "addr:postcode":"54451",
    "addr:street":"Castle Rd",
    "iso:country":"US",
    "sg:address":"4078 Castle Rd",
    "sg:city":"Medford",
    "sg:classifiers":[
        {
            "category":"Wholesale",
            "subcategory":"Non-durable Goods",
            "type":"Manufacturing & Wholesale Goods"
        }
    ],
    "sg:phone":"+1 715 748 6805",
    "sg:postcode":"54451",
    "sg:province":"WI",
    "wof:name":"Castle Tree Farm",
    "wof:placetype":"venue"
},
  "geometry": {"coordinates":[-90.394209,45.188413],"type":"Point"}
}