{
  "type": "Feature",
  "properties": {
    "iso:country":"US",
    "sg:address":"55 S Pontiac Dr",
    "sg:city":"Janesville",
    "sg:classifiers":[
        {
            "category":"Education",
            "subcategory":"School",
            "type":"Public Place"
        }
    ],
    "sg:phone":"+1 608 743 6900",
    "sg:postcode":"53545",
    "sg:province":"WI",
    "wof:name":"Monroe Elementary School",
    "wof:placetype":"venue"
},
  "geometry": {"coordinates":[-88.987718,42.695385],"type":"Point"}
}