{
  "type": "Feature",
  "properties": {
    "iso:country":"US",
    "sg:address":"1027 Stanley St",
    "sg:city":"Chippewa Falls",
    "sg:classifiers":[
        {
            "category":"Organizations",
            "subcategory":"Community Association",
            "type":"Services"
        }
    ],
    "sg:phone":"+1 715 723 6924",
    "sg:postcode":"54729",
    "sg:province":"WI",
    "wof:name":"Order of Amaranth Inc",
    "wof:placetype":"venue"
},
  "geometry": {"coordinates":[-91.414326,44.93776],"type":"Point"}
}