{
  "type": "Feature",
  "properties": {
    "iso:country":"US",
    "sg:address":"110 Spruce St",
    "sg:city":"Argyle",
    "sg:classifiers":[
        {
            "category":"Banks & Credit Unions",
            "subcategory":"Bank",
            "type":"Services"
        }
    ],
    "sg:phone":"+1 608 543 9117",
    "sg:postcode":"53504",
    "sg:province":"WI",
    "wof:name":"Woodford State Bank",
    "wof:placetype":"venue"
},
  "geometry": {"coordinates":[-89.87571199999999,42.698569],"type":"Point"}
}