{
  "type": "Feature",
  "properties": {
    "addr:full":"2053 State Rd 17 Merrill WI 54452",
    "addr:housenumber":"2053;17",
    "addr:postcode":"54452",
    "addr:street":"State Rd",
    "iso:country":"US",
    "sg:address":"2053 State Rd 17",
    "sg:city":"Merrill",
    "sg:classifiers":[
        {
            "category":"Building & Trades",
            "subcategory":"Construction",
            "type":"Services"
        }
    ],
    "sg:phone":"+1 715 536 4412",
    "sg:postcode":"54452",
    "sg:province":"WI",
    "sg:tags":[
        "house",
        "residential"
    ],
    "wof:name":"Hagedorn Construction",
    "wof:placetype":"venue"
},
  "geometry": {"coordinates":[-89.64162,45.18511],"type":"Point"}
}