{
  "type": "Feature",
  "properties": {
    "iso:country":"US",
    "sg:address":"3104 Schiller Dr",
    "sg:city":"Merrill",
    "sg:classifiers":[
        {
            "category":"Building & Trades",
            "subcategory":"Construction",
            "type":"Services"
        }
    ],
    "sg:phone":"+1 715 536 9321",
    "sg:postcode":"54452",
    "sg:province":"WI",
    "sg:tags":[
        "industrial"
    ],
    "wof:name":"S & V Builders of Merrill Inc",
    "wof:placetype":"venue"
},
  "geometry": {"coordinates":[-89.579052,45.213818],"type":"Point"}
}