{
  "type": "Feature",
  "properties": {
    "addr:full":"3159 Shady Oak Ln Verona WI 53593",
    "addr:housenumber":"3159",
    "addr:postcode":"53593",
    "addr:street":"Shady Oak Ln",
    "iso:country":"US",
    "sg:address":"3159 Shady Oak Ln",
    "sg:city":"Verona",
    "sg:classifiers":[
        {
            "category":"Health Services",
            "subcategory":"Doctor",
            "type":"Services"
        }
    ],
    "sg:phone":"+1 608 845 8035",
    "sg:postcode":"53593",
    "sg:province":"WI",
    "sg:tags":[
        "medical"
    ],
    "wof:name":"Paul M Jacobsen Dr",
    "wof:placetype":"venue"
},
  "geometry": {"coordinates":[-89.57201000000001,43.024355],"type":"Point"}
}