{
  "type": "Feature",
  "properties": {
    "iso:country":"US",
    "sg:address":"28824 Co Hwy B",
    "sg:city":"Sextonville",
    "sg:classifiers":[
        {
            "category":"Organizations",
            "subcategory":"Religious Organization",
            "type":"Services"
        }
    ],
    "sg:phone":"+1 608 647 7302",
    "sg:postcode":"53556",
    "sg:province":"WI",
    "wof:name":"Willow Valley United Methodist",
    "wof:placetype":"venue"
},
  "geometry": {"coordinates":[-90.29136800000001,43.280336],"type":"Point"}
}