{
  "type": "Feature",
  "properties": {
    "iso:country":"US",
    "sg:address":"4379 S Howell Ave",
    "sg:city":"Milwaukee",
    "sg:classifiers":[
        {
            "category":"Freight",
            "type":"Transportation"
        }
    ],
    "sg:phone":"+1 414 482 4888",
    "sg:postcode":"53207",
    "sg:province":"WI",
    "sg:tags":[
        "delivery"
    ],
    "wof:name":"Speedy Delivery Svc",
    "wof:placetype":"venue"
},
  "geometry": {"coordinates":[-87.90971999999999,42.964956],"type":"Point"}
}