{
  "type": "Feature",
  "properties": {
    "iso:country":"US",
    "sg:address":"121 W Park Ave",
    "sg:city":"Berlin",
    "sg:classifiers":[
        {
            "category":"Education",
            "subcategory":"Library",
            "type":"Public Place"
        }
    ],
    "sg:phone":"+1 920 361 1916",
    "sg:postcode":"54923",
    "sg:province":"WI",
    "wof:name":"Winnefox Co-Op Tech Service",
    "wof:placetype":"venue"
},
  "geometry": {"coordinates":[-88.946929,43.969344],"type":"Point"}
}