{
  "type": "Feature",
  "properties": {
    "iso:country":"US",
    "sg:address":"3007 Nick Ave",
    "sg:city":"Mosinee",
    "sg:classifiers":[
        {
            "category":"Professional",
            "type":"Services"
        }
    ],
    "sg:phone":"+1 715 359 1750",
    "sg:postcode":"54455",
    "sg:province":"WI",
    "sg:tags":[
        "establishment"
    ],
    "wof:name":"ISC Inc",
    "wof:placetype":"venue"
},
  "geometry": {"coordinates":[-89.561818,44.858283],"type":"Point"}
}