{
  "type": "Feature",
  "properties": {
    "iso:country":"US",
    "sg:address":"1230 S 32nd St",
    "sg:city":"Manitowoc",
    "sg:classifiers":[
        {
            "category":"Restaurant",
            "type":"Food & Drink"
        }
    ],
    "sg:phone":"+1 920 684 8471",
    "sg:postcode":"54220",
    "sg:province":"WI",
    "sg:tags":[
        "eating"
    ],
    "wof:name":"Q Country Crafts and Supplies",
    "wof:placetype":"venue"
},
  "geometry": {"coordinates":[-87.68745699999999,44.081474],"type":"Point"}
}