{
  "type": "Feature",
  "properties": {
    "iso:country":"US",
    "sg:address":"794 Winneconne Ave",
    "sg:city":"Neenah",
    "sg:classifiers":[
        {
            "category":"Real Estate",
            "subcategory":"Real Estate Agent",
            "type":"Services"
        }
    ],
    "sg:phone":"+1 920 727 2121",
    "sg:postcode":"54956",
    "sg:province":"WI",
    "wof:name":"Century 21",
    "wof:placetype":"venue"
},
  "geometry": {"coordinates":[-88.480275,44.177298],"type":"Point"}
}