{
  "type": "Feature",
  "properties": {
    "iso:country":"US",
    "sg:address":"1539 N Main St",
    "sg:city":"West Bend",
    "sg:classifiers":[
        {
            "category":"Bars & Pubs",
            "type":"Food & Drink"
        }
    ],
    "sg:phone":"+1 262 334 7828",
    "sg:postcode":"53090",
    "sg:province":"WI",
    "sg:tags":[
        "drinking"
    ],
    "wof:name":"M & R Bar",
    "wof:placetype":"venue"
},
  "geometry": {"coordinates":[-88.186445,43.441062],"type":"Point"}
}