{
  "type": "Feature",
  "properties": {
    "addr:full":"826 22nd St Two Rivers WI 54241",
    "addr:housenumber":"826",
    "addr:postcode":"54241",
    "addr:street":"22Nd St",
    "iso:country":"US",
    "sg:address":"826 22nd St",
    "sg:city":"Two Rivers",
    "sg:classifiers":[
        {
            "category":"Restaurant",
            "type":"Food & Drink"
        }
    ],
    "sg:menulink":"http://www.allmenus.com/wi/two-rivers/101346-cousins-subs/menu/",
    "sg:phone":"+1 920 553 5001",
    "sg:postcode":"54241",
    "sg:province":"WI",
    "sg:tags":[
        "wrap",
        "american",
        "sandwich"
    ],
    "wof:name":"Cousin's Subs",
    "wof:placetype":"venue"
},
  "geometry": {"coordinates":[-87.558341,44.153667],"type":"Point"}
}