{
  "type": "Feature",
  "properties": {
    "iso:country":"US",
    "sg:address":"600 W College Ave",
    "sg:city":"Appleton",
    "sg:classifiers":[
        {
            "category":"Restaurant",
            "type":"Food & Drink"
        }
    ],
    "sg:phone":"+1 920 749 1111",
    "sg:postcode":"54911",
    "sg:province":"WI",
    "sg:tags":[
        "eating"
    ],
    "wof:name":"Muncheez Pizza LLC",
    "wof:placetype":"venue"
},
  "geometry": {"coordinates":[-88.41498799999999,44.26182],"type":"Point"}
}