{
  "type": "Feature",
  "properties": {
    "iso:country":"US",
    "sg:address":"730 Red Iron Rd",
    "sg:city":"Black River Fls",
    "sg:classifiers":[
        {
            "category":"Manufacturing",
            "subcategory":"Printing",
            "type":"Manufacturing & Wholesale Goods"
        }
    ],
    "sg:phone":"+1 715 284 9250",
    "sg:postcode":"54615",
    "sg:province":"WI",
    "sg:tags":[
        "label"
    ],
    "sg:website":"www.flash4.com",
    "wof:name":"Flash 4",
    "wof:placetype":"venue"
},
  "geometry": {"coordinates":[-90.807108,44.300884],"type":"Point"}
}