{
  "type": "Feature",
  "properties": {
    "iso:country":"US",
    "sg:address":"748 Bow Bells Rd",
    "sg:city":"Oneida",
    "sg:classifiers":[
        {
            "category":"Real Estate",
            "subcategory":"Developer",
            "type":"Services"
        }
    ],
    "sg:phone":"+1 920 869 1383",
    "sg:postcode":"54155",
    "sg:province":"WI",
    "wof:name":"Mountain Bay Development",
    "wof:placetype":"venue"
},
  "geometry": {"coordinates":[-88.162521,44.504395],"type":"Point"}
}