{
  "type": "Feature",
  "properties": {
    "iso:country":"US",
    "sg:address":"3023 Weyers Rd",
    "sg:city":"Kaukauna",
    "sg:classifiers":[
        {
            "category":"Manufacturing",
            "subcategory":"Food",
            "type":"Manufacturing & Wholesale Goods"
        }
    ],
    "sg:phone":"+1 920 766 0550",
    "sg:postcode":"54130",
    "sg:province":"WI",
    "sg:tags":[
        "extract",
        "syrup",
        "flavoring"
    ],
    "wof:name":"Mels Seasoning",
    "wof:placetype":"venue"
},
  "geometry": {"coordinates":[-88.271799,44.348823],"type":"Point"}
}