{
  "type": "Feature",
  "properties": {
    "iso:country":"US",
    "sg:address":"4722 E Washington Ave",
    "sg:city":"Madison",
    "sg:classifiers":[
        {
            "category":"Home & Garden",
            "subcategory":"Furniture",
            "type":"Retail Goods"
        }
    ],
    "sg:phone":"+1 608 249 1128",
    "sg:postcode":"53704",
    "sg:province":"WI",
    "wof:name":"Bedroom Expressions",
    "wof:placetype":"venue"
},
  "geometry": {"coordinates":[-89.30360400000001,43.131299],"type":"Point"}
}