{
  "type": "Feature",
  "properties": {
    "iso:country":"US",
    "sg:address":"1351 Williamson St",
    "sg:city":"Madison",
    "sg:classifiers":[
        {
            "category":"Restaurant",
            "type":"Food & Drink"
        }
    ],
    "sg:phone":"+1 608 256 6088",
    "sg:postcode":"53703",
    "sg:province":"WI",
    "sg:tags":[
        "eating"
    ],
    "wof:name":"Willalby's Cafe",
    "wof:placetype":"venue"
},
  "geometry": {"coordinates":[-89.361377,43.085069],"type":"Point"}
}