{
  "type": "Feature",
  "properties": {
    "addr:full":"2922 Syene Rd Madison WI 53713",
    "addr:housenumber":"2922",
    "addr:postcode":"53713",
    "addr:street":"Syene Rd",
    "iso:country":"US",
    "sg:address":"2922 Syene Rd",
    "sg:city":"Madison",
    "sg:classifiers":[
        {
            "category":"Wholesale",
            "subcategory":"Construction Materials",
            "type":"Manufacturing & Wholesale Goods"
        }
    ],
    "sg:phone":"+1 608 273 4614",
    "sg:postcode":"53713",
    "sg:province":"WI",
    "sg:tags":[
        "windows",
        "roofing",
        "siding",
        "door"
    ],
    "wof:name":"Allside Supply Center 172",
    "wof:placetype":"venue"
},
  "geometry": {"coordinates":[-89.39457,43.030351],"type":"Point"}
}