{
  "type": "Feature",
  "properties": {
    "addr:full":"3270 N 126th St Brookfield WI 53005",
    "addr:housenumber":"3270",
    "addr:postcode":"53005",
    "addr:street":"N 126Th St",
    "iso:country":"US",
    "sg:address":"3270 N 126th St",
    "sg:city":"Brookfield",
    "sg:classifiers":[
        {
            "category":"Building & Trades",
            "subcategory":"Plumbing",
            "type":"Services"
        },
        {
            "category":"Home & Garden",
            "subcategory":"Building Materials",
            "type":"Retail Goods"
        },
        {
            "category":"Building & Trades",
            "subcategory":"Construction",
            "type":"Services"
        }
    ],
    "sg:phone":"+1 262 781 6466",
    "sg:postcode":"53005",
    "sg:province":"WI",
    "sg:tags":[
        "bathroom",
        "industrial",
        "system",
        "specialty",
        "altering",
        "contractors-commercial",
        "plumber",
        "contractor",
        "heating",
        "cleaning",
        "plumbing-drain",
        "improvement",
        "remodeling",
        "air conditioning",
        "sewer"
    ],
    "sg:website":"http://www.borthwilson.com",
    "wof:name":"Borth-Wilson Plumbing",
    "wof:placetype":"venue"
},
  "geometry": {"coordinates":[-88.06900899999999,43.077151],"type":"Point"}
}