{
  "type": "Feature",
  "properties": {
    "iso:country":"US",
    "sg:address":"1049 Lombardi Access Rd",
    "sg:city":"Green Bay",
    "sg:classifiers":[
        {
            "category":"Restaurant",
            "type":"Food & Drink"
        }
    ],
    "sg:phone":"+1 920 496 5857",
    "sg:postcode":"54304",
    "sg:province":"WI",
    "sg:tags":[
        "eating"
    ],
    "wof:name":"Side Line",
    "wof:placetype":"venue"
},
  "geometry": {"coordinates":[-88.070235,44.505579],"type":"Point"}
}