{
  "type": "Feature",
  "properties": {
    "iso:country":"US",
    "sg:address":"10021 Sunnyside Rd",
    "sg:city":"Antigo",
    "sg:classifiers":[
        {
            "category":"Building & Trades",
            "subcategory":"Construction",
            "type":"Services"
        }
    ],
    "sg:phone":"+1 715 627 4125",
    "sg:postcode":"54409",
    "sg:province":"WI",
    "sg:tags":[
        "masonry",
        "contractor"
    ],
    "wof:name":"G & B Masonry of Wisconcin",
    "wof:placetype":"venue"
},
  "geometry": {"coordinates":[-89.150385,45.101766],"type":"Point"}
}