{
  "type": "Feature",
  "properties": {
    "iso:country":"US",
    "sg:address":"203 Cherry Ave",
    "sg:city":"Oconto Falls",
    "sg:classifiers":[
        {
            "category":"Professional",
            "subcategory":"Management & Consulting",
            "type":"Services"
        }
    ],
    "sg:phone":"+1 920 848 7684",
    "sg:postcode":"54154",
    "sg:province":"WI",
    "sg:tags":[
        "retail",
        "direct",
        "sales"
    ],
    "wof:name":"Parties With Pizzazz",
    "wof:placetype":"venue"
},
  "geometry": {"coordinates":[-88.14559199999999,44.877103],"type":"Point"}
}