{
  "type": "Feature",
  "properties": {
    "addr:full":"1700 George St La Crosse WI 54603",
    "addr:housenumber":"1700",
    "addr:postcode":"54603",
    "addr:street":"George St",
    "iso:country":"US",
    "sg:address":"1700 George St",
    "sg:city":"La Crosse",
    "sg:classifiers":[
        {
            "category":"Building & Trades",
            "subcategory":"Construction",
            "type":"Services"
        }
    ],
    "sg:phone":"+1 608 779 9535",
    "sg:postcode":"54603",
    "sg:province":"WI",
    "sg:tags":[
        "contractor"
    ],
    "wof:name":"Thompsons Drywall & Plasterin",
    "wof:placetype":"venue"
},
  "geometry": {"coordinates":[-91.239763,43.849201],"type":"Point"}
}