{
  "type": "Feature",
  "properties": {
    "addr:full":"12244 N River Rd Thiensville WI 53092",
    "addr:housenumber":"12244",
    "addr:postcode":"53092",
    "addr:street":"N River Rd",
    "iso:country":"US",
    "sg:address":"12244 N River Rd",
    "sg:city":"Thiensville",
    "sg:classifiers":[
        {
            "category":"Banks & Credit Unions",
            "subcategory":"Financial Services",
            "type":"Services"
        }
    ],
    "sg:phone":"+1 262 242 1635",
    "sg:postcode":"53092",
    "sg:province":"WI",
    "sg:tags":[
        "trust",
        "management"
    ],
    "wof:name":"H Grassin Revocable Livin",
    "wof:placetype":"venue"
},
  "geometry": {"coordinates":[-87.963757,43.240763],"type":"Point"}
}