{
  "type": "Feature",
  "properties": {
    "iso:country":"US",
    "sg:address":"1910 Co Rd Kk",
    "sg:city":"Kaukauna",
    "sg:classifiers":[
        {
            "category":"Wholesale",
            "subcategory":"Meat",
            "type":"Manufacturing & Wholesale Goods"
        }
    ],
    "sg:phone":"+1 920 766 3239",
    "sg:postcode":"54130",
    "sg:province":"WI",
    "sg:tags":[
        "plant",
        "mfg",
        "packer",
        "prepared",
        "personal",
        "packing"
    ],
    "sg:website":"www.haenmeats.com",
    "wof:name":"Haen Meat Packing Inc",
    "wof:placetype":"venue"
},
  "geometry": {"coordinates":[-88.28395399999999,44.243198],"type":"Point"}
}