{
  "type": "Feature",
  "properties": {
    "addr:full":"5051 Willow Rd Owen WI 54460",
    "addr:housenumber":"5051",
    "addr:postcode":"54460",
    "addr:street":"Willow Rd",
    "iso:country":"US",
    "sg:address":"5051 Willow Rd",
    "sg:city":"Owen",
    "sg:classifiers":[
        {
            "category":"Freight",
            "type":"Transportation"
        }
    ],
    "sg:phone":"+1 715 229 9000",
    "sg:postcode":"54460",
    "sg:province":"WI",
    "sg:tags":[
        "commercial",
        "storage"
    ],
    "wof:name":"Gardner Cold Storage",
    "wof:placetype":"venue"
},
  "geometry": {"coordinates":[-90.56406200000001,44.958573],"type":"Point"}
}