{
  "type": "Feature",
  "properties": {
    "iso:country":"US",
    "sg:address":"4543 State Hwy 22",
    "sg:city":"Shawano",
    "sg:classifiers":[
        {
            "category":"Restaurant",
            "type":"Food & Drink"
        }
    ],
    "sg:phone":"+1 715 526 8072",
    "sg:postcode":"54166",
    "sg:province":"WI",
    "sg:website":"www.arbys.com",
    "wof:name":"Arby's",
    "wof:placetype":"venue"
},
  "geometry": {"coordinates":[-88.61409500000001,44.752865],"type":"Point"}
}