{
  "type": "Feature",
  "properties": {
    "addr:full":"450 Overland Trl Grafton WI 53024",
    "addr:housenumber":"450",
    "addr:postcode":"53024",
    "addr:street":"Overland Trl",
    "iso:country":"US",
    "sg:address":"450 Overland Trl",
    "sg:city":"Grafton",
    "sg:classifiers":[
        {
            "category":"Manufacturing",
            "subcategory":"Tools & Machinery",
            "type":"Manufacturing & Wholesale Goods"
        }
    ],
    "sg:phone":"+1 262 377 3100",
    "sg:postcode":"53024",
    "sg:province":"WI",
    "sg:tags":[
        "industrial",
        "mfg"
    ],
    "wof:name":"Oetlinger Tool Engineering Co",
    "wof:placetype":"venue"
},
  "geometry": {"coordinates":[-87.961912,43.336779],"type":"Point"}
}