{
  "type": "Feature",
  "properties": {
    "addr:full":"360 S Tower St Saukville WI 53080",
    "addr:housenumber":"360",
    "addr:postcode":"53080",
    "addr:street":"S Tower St",
    "iso:country":"US",
    "sg:address":"360 S Tower St",
    "sg:city":"Saukville",
    "sg:classifiers":[
        {
            "category":"Manufacturing",
            "subcategory":"Metals",
            "type":"Manufacturing & Wholesale Goods"
        }
    ],
    "sg:phone":"+1 262 377 3991",
    "sg:postcode":"53080",
    "sg:province":"WI",
    "wof:name":"Logamann Bros Co",
    "wof:placetype":"venue"
},
  "geometry": {"coordinates":[-87.94780900000001,43.380014],"type":"Point"}
}