{
  "type": "Feature",
  "properties": {
    "iso:country":"US",
    "sg:address":"126 Langdon St",
    "sg:city":"Madison",
    "sg:classifiers":[
        {
            "category":"Real Estate",
            "subcategory":"Real Estate Operator",
            "type":"Services"
        }
    ],
    "sg:phone":"+1 608 257 8841",
    "sg:postcode":"53703",
    "sg:province":"WI",
    "sg:tags":[
        "apartment"
    ],
    "sg:website":"www.privatereshalls.com",
    "wof:name":"Langdon Private Residence Hall",
    "wof:placetype":"venue"
},
  "geometry": {"coordinates":[-89.39102200000001,43.077873],"type":"Point"}
}