{
  "type": "Feature",
  "properties": {
    "iso:country":"US",
    "sg:address":"385 S Main St",
    "sg:city":"Iola",
    "sg:classifiers":[
        {
            "category":"Travel",
            "subcategory":"Hotels & Motels",
            "type":"Entertainment"
        }
    ],
    "sg:phone":"+1 715 445 4080",
    "sg:postcode":"54945",
    "sg:province":"WI",
    "sg:tags":[
        "breakfast",
        "accommodation",
        "bed"
    ],
    "wof:name":"Iris Inn Bed & Breakfast",
    "wof:placetype":"venue"
},
  "geometry": {"coordinates":[-89.130904,44.503404],"type":"Point"}
}