{
  "type": "Feature",
  "properties": {
    "iso:country":"US",
    "sg:address":"9410 Wilson Blvd",
    "sg:city":"Milwaukee",
    "sg:classifiers":[
        {
            "category":"Real Estate",
            "subcategory":"Real Estate Operator",
            "type":"Services"
        }
    ],
    "sg:phone":"+1 414 258 5789",
    "sg:postcode":"53226",
    "sg:province":"WI",
    "sg:tags":[
        "building",
        "nonresidential"
    ],
    "wof:name":"Wood Property Mgmnt LLC",
    "wof:placetype":"venue"
},
  "geometry": {"coordinates":[-88.030618,43.064283],"type":"Point"}
}