{
  "type": "Feature",
  "properties": {
    "addr:full":"3151 Saemann Ave Sheboygan WI 53081",
    "addr:housenumber":"3151",
    "addr:postcode":"53081",
    "addr:street":"Saemann Ave",
    "iso:country":"US",
    "sg:address":"3151 Saemann Ave",
    "sg:city":"Sheboygan",
    "sg:classifiers":[
        {
            "category":"Social Services",
            "type":"Services"
        }
    ],
    "sg:phone":"+1 920 458 5557",
    "sg:postcode":"53081",
    "sg:province":"WI",
    "sg:tags":[
        "professional",
        "counselor"
    ],
    "sg:website":"www.lakeshorementalhealth.com",
    "wof:name":"Lakeshore Mental Health Inc",
    "wof:placetype":"venue"
},
  "geometry": {"coordinates":[-87.746589,43.764675],"type":"Point"}
}