{
  "type": "Feature",
  "properties": {
    "iso:country":"US",
    "sg:address":"204 W Main St",
    "sg:city":"Hortonville",
    "sg:classifiers":[
        {
            "category":"Restaurant",
            "type":"Food & Drink"
        }
    ],
    "sg:phone":"+1 920 779 6500",
    "sg:postcode":"54944",
    "sg:province":"WI",
    "sg:tags":[
        "eating"
    ],
    "wof:name":"Dickies Pizza",
    "wof:placetype":"venue"
},
  "geometry": {"coordinates":[-88.640472,44.335203],"type":"Point"}
}