{
  "type": "Feature",
  "properties": {
    "iso:country":"US",
    "sg:address":"3390 W Loomis Rd",
    "sg:city":"Milwaukee",
    "sg:classifiers":[
        {
            "category":"Food & Beverages",
            "subcategory":"Groceries & Convenience Stores",
            "type":"Retail Goods"
        }
    ],
    "sg:phone":"+1 414 281 0205",
    "sg:postcode":"53221",
    "sg:province":"WI",
    "wof:name":"Speedway 4154",
    "wof:placetype":"venue"
},
  "geometry": {"coordinates":[-87.956374,42.974795],"type":"Point"}
}