{
  "type": "Feature",
  "properties": {
    "addr:full":"8736 W North Ave Wauwatosa WI 53226",
    "addr:housenumber":"8736",
    "addr:postcode":"53226",
    "addr:street":"W North Ave",
    "iso:country":"US",
    "sg:address":"8736 W North Ave",
    "sg:city":"Wauwatosa",
    "sg:classifiers":[
        {
            "category":"Health Services",
            "subcategory":"Health Practitioner",
            "type":"Services"
        }
    ],
    "sg:phone":"+1 414 431 5010",
    "sg:postcode":"53226",
    "sg:province":"WI",
    "sg:tags":[
        "acupuncture"
    ],
    "wof:name":"Acupuncture & Oriental Mdcn",
    "wof:placetype":"venue"
},
  "geometry": {"coordinates":[-88.022035,43.0606],"type":"Point"}
}