{
  "type": "Feature",
  "properties": {
    "iso:country":"US",
    "sg:address":"550 Martin Ave",
    "sg:city":"Turtle Lake",
    "sg:classifiers":[
        {
            "category":"Health Services",
            "subcategory":"Doctor",
            "type":"Services"
        }
    ],
    "sg:phone":"+1 715 986 4101",
    "sg:postcode":"54889",
    "sg:province":"WI",
    "sg:tags":[
        "clinic",
        "medical"
    ],
    "wof:name":"Turtle Lake Medical Clinic",
    "wof:placetype":"venue"
},
  "geometry": {"coordinates":[-92.15078699999999,45.395277],"type":"Point"}
}