{
  "type": "Feature",
  "properties": {
    "addr:full":"1136 Madison St Beaver Dam WI 53916",
    "addr:housenumber":"1136",
    "addr:postcode":"53916",
    "addr:street":"Madison St",
    "iso:country":"US",
    "sg:address":"1136 Madison St",
    "sg:city":"Beaver Dam",
    "sg:classifiers":[
        {
            "category":"Home & Garden",
            "subcategory":"Building Materials",
            "type":"Retail Goods"
        }
    ],
    "sg:phone":"+1 920 887 7177",
    "sg:postcode":"53916",
    "sg:province":"WI",
    "sg:tags":[
        "contractor"
    ],
    "wof:name":"Lake Unit Step By Foxx Fence",
    "wof:placetype":"venue"
},
  "geometry": {"coordinates":[-88.854725,43.443264],"type":"Point"}
}